{"id":"2014-00355","title":"Atap Palms","source":"Bumblebee","path":"./Data/json/","content":"accession_no_csv:2014-00355\nImage:\nobject_work_type:black-and-white photographs\ntitle_text:Atap Palms\npreference:main\ntitle_language:\ncreator_2:G.R. Lambert \\u0026 Company\ncreator_1:G.R. Lambert \\u0026 Co.\ncreator_role:photography studios (organizations)\ncreation_date:1900\ncreation_place_original_location:Singapore\ninscriptions:\ninscription_language:\nshape:rectangular\nmaterials_name:paper (fiber product)\ntechniques_name:printing (process) photographic processes\nobject_colour:grey (colour) monochrome\nphysical_appearance:\\The image shows a photograph that is in black-and-white. It is rectangular and it features a forested landscape. There are tall trees as well as dense shrubs. A body of water can be seen in the foreground of the photograph. Shrouded amidst the greenery to the right of the photograph\n a roofed building can be discerned. \\\\Atap Palms 108\\\\ is stated in white at the lower right hand side of the photograph. \\\nsubject_terms_1:Arecaceae (family) bungalows bodies of water (natural) natural landscapes\nsubject_terms_2:Black-and-white photography Nypa palm Bungalows Architecture\n Colonial Bodies of water Landscape photography Landscapes\nsubject_terms_3:Landscape photography G. R. Lambert \\u0026 Co. Waterways\nsgcool_label_text:The photograph from G. R. Lambert shows atap palms (also known as nipah palms) growing beside a river or pool with a European bungalow in the background.","createdDate":"20201018182635","version":0,"latest":false,"roles":[],"metadata":{"accession_no_csv":"2014-00355","Image":"","object_work_type":"black-and-white photographs","title_text":"Atap Palms","preference":"main","title_language":"","creator_2":"G.R. Lambert \u0026 Company","creator_1":"G.R. Lambert \u0026 Co.","creator_role":"photography studios (organizations)","creation_date":"1900","creation_place_original_location":"Singapore","inscriptions":"","inscription_language":"","shape":"rectangular","materials_name":"paper (fiber product)","techniques_name":"printing (process) photographic processes","object_colour":"grey (colour) monochrome","physical_appearance":"\"The image shows a photograph that is in black-and-white. It is rectangular and it features a forested landscape. There are tall trees as well as dense shrubs. A body of water can be seen in the foreground of the photograph. Shrouded amidst the greenery to the right of the photograph, a roofed building can be discerned. \"\"Atap Palms 108\"\" is stated in white at the lower right hand side of the photograph. \"","subject_terms_1":"Arecaceae (family) bungalows bodies of water (natural) natural landscapes","subject_terms_2":"Black-and-white photography Nypa palm Bungalows Architecture, Colonial Bodies of water Landscape photography Landscapes","subject_terms_3":"Landscape photography G. R. Lambert \u0026 Co. Waterways","sgcool_label_text":"The photograph from G. R. Lambert shows atap palms (also known as nipah palms) growing beside a river or pool with a European bungalow in the background."},"nlpDate":"20201018182635","connectorId":0,"tags":{}}