{"id":"2014-00358","title":"Map of China Sea - Singapore Strait","source":"Bumblebee","path":"./Data/json/","content":"accession_no_csv:2014-00358\nImage:\nobject_work_type:nautical charts\ntitle_text:Map of China Sea - Singapore Strait\npreference:main\ntitle_language:\ncreator_2:Not indicated\ncreator_1:Not indicated\ncreation_date:1923\ncreation_place_original_location:Singapore Malaysia\ninscriptions:\ninscription_language:\nscale_type:Not indicated\nshape:rectangular\nmaterials_name:paper (fiber product)\ntechniques_name:mapmaking (process) printing (process)\nobject_colour:grey (colour)\nphysical_appearance:\\The map is rectangular in shape and there is a black boundary separating it from the frame. The words \\\\Malay Peninsula\\\\ and four Kanji characters are displayed at the top centre of the chart. The map is separated into a larger part and a smaller one. For the larger part\nsubject_terms_1:\\\\Singapore Strait\\\\ can be seen at the top left hand corner of the chart. The outline of \\\\Singapore Island\\\\ can be seen. There are several archipelagoes that are southeast from Singapore. \\\\Selat Sinki\\\\ can be seen at the top left hand corner of the smaller part of the chart at the bottom right hand side. There are little round yellow dots on several points on the map.  \\ archipelagoes trade routes seas peninsulas\nsubject_terms_2:straits Straits Singapore Kepulauan Riau (Indonesia : Province) Trade routes China Sea Malay Peninsula\nsubject_terms_3:Nautical charts Straits Islands\nsubject_terms_4:Malay archipelago","createdDate":"20201018182635","version":0,"latest":false,"roles":[],"metadata":{"accession_no_csv":"2014-00358","Image":"","object_work_type":"nautical charts","title_text":"Map of China Sea - Singapore Strait","preference":"main","title_language":"","creator_2":"Not indicated","creator_1":"Not indicated","creation_date":"1923","creation_place_original_location":"Singapore Malaysia","inscriptions":"","inscription_language":"","scale_type":"Not indicated","shape":"rectangular","materials_name":"paper (fiber product)","techniques_name":"mapmaking (process) printing (process)","object_colour":"grey (colour)","physical_appearance":"\"The map is rectangular in shape and there is a black boundary separating it from the frame. The words \"\"Malay Peninsula\"\" and four Kanji characters are displayed at the top centre of the chart. The map is separated into a larger part and a smaller one. For the larger part","subject_terms_1":"\"\"Singapore Strait\"\" can be seen at the top left hand corner of the chart. The outline of \"\"Singapore Island\"\" can be seen. There are several archipelagoes that are southeast from Singapore. \"\"Selat Sinki\"\" can be seen at the top left hand corner of the smaller part of the chart at the bottom right hand side. There are little round yellow dots on several points on the map.  \" archipelagoes trade routes seas peninsulas","subject_terms_2":"straits Straits Singapore Kepulauan Riau (Indonesia : Province) Trade routes China Sea Malay Peninsula","subject_terms_3":"Nautical charts Straits Islands","subject_terms_4":"Malay archipelago"},"nlpDate":"20201018182635","connectorId":0,"tags":{}}