{"id":"2014-00906","title":"Affordable Art Fair (2) Invite cards for Affordable Art Fair (2)","source":"Bumblebee","path":"./Data/json/","content":"accession_no_csv:2014-00906\nImage:\nobject_work_type:invitations\ntitle_text:Affordable Art Fair (2) Invite cards for Affordable Art Fair (2)\npreference:main alternate\ntitle_language:\ncreator_2:Not indicated\ncreator_1:Not indicated\ncreation_date:5-Mar\ncreation_place_original_location:Singapore\ninscriptions:\ninscription_language:\nshape:rectangular\nmaterials_name:paper (fiber product)\ntechniques_name:printing (process)\nobject_colour:multicoloured\nphysical_appearance:\\The image features 2 rectangular sets of invitation cards \\\\Affordable Art Fair\\\\ is printed on the left hand side of both invitation cards. The phrase\nsubject_terms_1:\\\\I am an Art Collector\\\\ fairs collectors Contemporary (style of art)\nsubject_terms_2:and the dates Art fairs Art Collectors and collecting Art\n Modern 21st century\nsubject_terms_3:\\\\15 - 18 November 2012\\\\\nsubject_terms_4:are displayed on both of the invitation cards. The image of an man in a trishaw is displayed on both the invitation cards as well.\\\ncontext_1:cards (information artifacts)\ncontext_2:Invitation cards\ncontext_3:Arts events\ncontext_5:Affordable Art Fair\ncontext_6:fairs\ncontext_7:15th - 17th Nov 2012\ncontext_8:20171115\ncontext_9:20171117\ncontext_10:F1 Pit Building\ncontext_11:Will Ramsay\ncontext_12:creators","createdDate":"20201119143405","version":0,"latest":false,"roles":[],"metadata":{"accession_no_csv":"2014-00906","Image":"","object_work_type":"invitations","title_text":"Affordable Art Fair (2) Invite cards for Affordable Art Fair (2)","preference":"main alternate","title_language":"","creator_2":"Not indicated","creator_1":"Not indicated","creation_date":"5-Mar","creation_place_original_location":"Singapore","inscriptions":"","inscription_language":"","shape":"rectangular","materials_name":"paper (fiber product)","techniques_name":"printing (process)","object_colour":"multicoloured","physical_appearance":"\"The image features 2 rectangular sets of invitation cards \"\"Affordable Art Fair\"\" is printed on the left hand side of both invitation cards. The phrase","subject_terms_1":"\"\"I am an Art Collector\"\" fairs collectors Contemporary (style of art)","subject_terms_2":"and the dates Art fairs Art Collectors and collecting Art, Modern 21st century","subject_terms_3":"\"\"15 - 18 November 2012\"\"","subject_terms_4":"are displayed on both of the invitation cards. The image of an man in a trishaw is displayed on both the invitation cards as well.\"","context_1":"cards (information artifacts)","context_2":"Invitation cards","context_3":"Arts events","context_5":"Affordable Art Fair","context_6":"fairs","context_7":"15th - 17th Nov 2012","context_8":"20171115","context_9":"20171117","context_10":"F1 Pit Building","context_11":"Will Ramsay","context_12":"creators"},"nlpDate":"20201119143405","connectorId":0,"tags":{}}