{
  "id": "2014-00909-015",
  "title": "72-13 (06) Brochures and cards for performances by Theatreworks (20) - 72-13 (6/9)",
  "source": "Bumblebee",
  "path": "./Data/json/",
  "content": "\n  accession_no_csv: 2014-00909-015\n\n  Image: \n\n  object_work_type: brochures\n\n  title_text: 72-13 (06) Brochures and cards for performances by Theatreworks (20) - 72-13 (6/9)\n\n  preference: main alternate\n\n  title_language: \n\n  creator_2: Not indicated\n\n  creator_1: Not indicated\n\n  creator_role: Not indicated\n\n  creation_date: Not indicated\n\n  creation_place_original_location: Singapore\n\n  inscriptions: \n\n  inscription_language: \n\n  shape: square (shape)\n\n  materials_name: paper (fiber product)\n\n  techniques_name: printing (process)\n\n  object_colour: multicoloured\n\n  physical_appearance: \\The image shows a square brochure. \\\\72-13\\\\ is displayed at the centre of the brochure in pink font. \\\\06\\\\ is stated at the lower left hand corner of the brochure. \\\\Image by Torrance Goh\\\\ is stated at the bottom left hand corner of the brochure. The image at the background shows several human heads which are faceless\n\n  subject_terms_1: numerous arms of different sizes\n\n  subject_terms_2: and palms. The outline of blue and green planets can be seen as well.\\ Theatres\n\n  subject_terms_3: theatres (buildings)\n\n  subject_terms_4: Brochures\n\n  context_1: Theatre organisations\n\n  context_22: 72-13 was an old rice warehouse\n\n  context_23: 72-13 Mohammed Sultan Road\n Singapore 239007\n\n  context_24: 2005\n\n  sgcool_label_text: 5-Sep\n",
  "createdDate": "20201125084544",
  "version": 0,
  "latest": false,
  "roles": [],
  "metadata": {
    "accession_no_csv": "2014-00909-015",
    "Image": "",
    "object_work_type": "brochures",
    "title_text": "72-13 (06) Brochures and cards for performances by Theatreworks (20) - 72-13 (6/9)",
    "preference": "main alternate",
    "title_language": "",
    "creator_2": "Not indicated",
    "creator_1": "Not indicated",
    "creator_role": "Not indicated",
    "creation_date": "Not indicated",
    "creation_place_original_location": "Singapore",
    "inscriptions": "",
    "inscription_language": "",
    "shape": "square (shape)",
    "materials_name": "paper (fiber product)",
    "techniques_name": "printing (process)",
    "object_colour": "multicoloured",
    "physical_appearance": "\"The image shows a square brochure. \"\"72-13\"\" is displayed at the centre of the brochure in pink font. \"\"06\"\" is stated at the lower left hand corner of the brochure. \"\"Image by Torrance Goh\"\" is stated at the bottom left hand corner of the brochure. The image at the background shows several human heads which are faceless",
    "subject_terms_1": "numerous arms of different sizes",
    "subject_terms_2": "and palms. The outline of blue and green planets can be seen as well.\" Theatres",
    "subject_terms_3": "theatres (buildings)",
    "subject_terms_4": "Brochures",
    "context_1": "Theatre organisations",
    "context_22": "72-13 was an old rice warehouse",
    "context_23": "72-13 Mohammed Sultan Road, Singapore 239007",
    "context_24": "2005",
    "sgcool_label_text": "5-Sep"
  },
  "nlpDate": "20201125084544",
  "connectorId": 0,
  "tags": {}
}