{
  "id": "2014-00503-002",
  "title": "The Orient India Celebrates Her Independence Day",
  "source": "Bumblebee",
  "path": "./Data/json/",
  "content": "\n  accession_no_csv: 2014-00503-002\n\n  Image: \n\n  object_work_type: clippings (information artifacts) pages (components)\n\n  title_text: The Orient India Celebrates Her Independence Day\n\n  preference: alternate main\n\n  title_language: \n\n  creation_date: August\n 1947\n\n  creation_place_original_location: Singapore Malaya India\n\n  inscriptions: \n\n  inscription_language: \n\n  shape: rectangular\n\n  materials_name: paper (fiber product)\n\n  techniques_name: printing processes\n\n  object_colour: black-and-white prints (prints on paper)\n\n  physical_appearance: This clipping is a page from the publication \\u0027The Orient Illustrated Weekly\\u0027. The title is printed at the top of the page. The page features seven black-and-white photographs depicting scenes of India on India\\u0027s independence day. There are captions at the bottom of the page. The edges of the page is slightly torn\n especially at the bottom.\n\n  subject_terms_1: nationalism Indian (South Asian) political events Independence Day parades celebrations periodicals\n\n  subject_terms_2: self-determination\n national Nationalism anti-imperialist movements Provisional Government of Free India Delhi (India) Independence Day (India) Periodicals\n\n  subject_terms_3: Indian National Army (Singapore) Indian National Army Monument Site periodicals\n\n  context_1: India Independence Day\n\n  context_2: Independence Day\n\n  context_3: 15/8/57\n\n  context_4: 15/8/57\n\n  context_5: 15/8/57\n\n  context_6: Delhi (India)\n\n  sgcool_label_text: \\Prior to the World War II period\n Indians in Singapore and Malaya retained strong political\n sentimental and economic ties with their home country. Anti-colonial thoughts and actions\n inspired by the \\\\call for freedom\\\\ in India\n",
  "createdDate": "20201120223706",
  "version": 0,
  "latest": false,
  "roles": [],
  "metadata": {
    "accession_no_csv": "2014-00503-002",
    "Image": "",
    "object_work_type": "clippings (information artifacts) pages (components)",
    "title_text": "The Orient India Celebrates Her Independence Day",
    "preference": "alternate main",
    "title_language": "",
    "creation_date": "August, 1947",
    "creation_place_original_location": "Singapore Malaya India",
    "inscriptions": "",
    "inscription_language": "",
    "shape": "rectangular",
    "materials_name": "paper (fiber product)",
    "techniques_name": "printing processes",
    "object_colour": "black-and-white prints (prints on paper)",
    "physical_appearance": "This clipping is a page from the publication \u0027The Orient Illustrated Weekly\u0027. The title is printed at the top of the page. The page features seven black-and-white photographs depicting scenes of India on India\u0027s independence day. There are captions at the bottom of the page. The edges of the page is slightly torn, especially at the bottom.",
    "subject_terms_1": "nationalism Indian (South Asian) political events Independence Day parades celebrations periodicals",
    "subject_terms_2": "self-determination, national Nationalism anti-imperialist movements Provisional Government of Free India Delhi (India) Independence Day (India) Periodicals",
    "subject_terms_3": "Indian National Army (Singapore) Indian National Army Monument Site periodicals",
    "context_1": "India Independence Day",
    "context_2": "Independence Day",
    "context_3": "15/8/57",
    "context_4": "15/8/57",
    "context_5": "15/8/57",
    "context_6": "Delhi (India)",
    "sgcool_label_text": "\"Prior to the World War II period, Indians in Singapore and Malaya retained strong political, sentimental and economic ties with their home country. Anti-colonial thoughts and actions, inspired by the \"\"call for freedom\"\" in India"
  },
  "nlpDate": "20201120223706",
  "connectorId": 0,
  "tags": {}
}