{
  "id": "2014-00285-063",
  "title": "Band for a Chinese Funeral (Keep Evil Spirits Away) Photography Album (donation from Anthony Robert Saint Claire)",
  "source": "Bumblebee",
  "path": "./Data/json/",
  "content": "\n  accession_no_csv: 2014-00285-063\n\n  Image: \n\n  object_work_type: black-and-white photographs\n\n  title_text: Band for a Chinese Funeral (Keep Evil Spirits Away) Photography Album (donation from Anthony Robert Saint Claire)\n\n  preference: main alternate\n\n  title_language: \n\n  creator_2: Robert Arthur Polglaze\n\n  creator_1: Not indicated\n\n  creator_role: photographers\n\n  creation_date: 1940s\n\n  creation_place_original_location: Singapore\n\n  inscriptions: \n\n  inscription_language: \n\n  shape: rectangular\n\n  materials_name: paper (fiber product)\n\n  techniques_name: printing (process) photographic processes\n\n  object_colour: grey monochrome\n\n  physical_appearance: The image shows a black-and-white photograph. It is rectangular and it features a group of people in front of a building at the ground floor. There are a couple of children and toddlers as well. Several people are wearing uniforms that are white in colour. Some of these people are accompanied with drums. The right hand side of the photograph displays a wreath\n\n  subject_terms_1: funerals bands (ensembles) folklore\n\n  subject_terms_2: Black-and-white photography Funeral rites and ceremonies Bands (Music) Superstition\n\n  subject_terms_3: Photography Bands\n\n  sgcool_label_text: Not indicated\n",
  "createdDate": "20201120223706",
  "version": 0,
  "latest": false,
  "roles": [],
  "metadata": {
    "accession_no_csv": "2014-00285-063",
    "Image": "",
    "object_work_type": "black-and-white photographs",
    "title_text": "Band for a Chinese Funeral (Keep Evil Spirits Away) Photography Album (donation from Anthony Robert Saint Claire)",
    "preference": "main alternate",
    "title_language": "",
    "creator_2": "Robert Arthur Polglaze",
    "creator_1": "Not indicated",
    "creator_role": "photographers",
    "creation_date": "1940s",
    "creation_place_original_location": "Singapore",
    "inscriptions": "",
    "inscription_language": "",
    "shape": "rectangular",
    "materials_name": "paper (fiber product)",
    "techniques_name": "printing (process) photographic processes",
    "object_colour": "grey monochrome",
    "physical_appearance": "The image shows a black-and-white photograph. It is rectangular and it features a group of people in front of a building at the ground floor. There are a couple of children and toddlers as well. Several people are wearing uniforms that are white in colour. Some of these people are accompanied with drums. The right hand side of the photograph displays a wreath",
    "subject_terms_1": "funerals bands (ensembles) folklore",
    "subject_terms_2": "Black-and-white photography Funeral rites and ceremonies Bands (Music) Superstition",
    "subject_terms_3": "Photography Bands",
    "sgcool_label_text": "Not indicated"
  },
  "nlpDate": "20201120223706",
  "connectorId": 0,
  "tags": {}
}