{"id":"2014-00285-030","title":"Japanese prisoners of war guarded by an Indian sepoy Photography Album (donation from Anthony Robert Saint Claire)","source":"Bumblebee","path":"./Data/json/","content":"accession_no_csv:2014-00285-030\nImage:\nobject_work_type:black-and-white photographs\ntitle_text:Japanese prisoners of war guarded by an Indian sepoy Photography Album (donation from Anthony Robert Saint Claire)\npreference:main alternate\ntitle_language:\ncreator_2:Robert Arthur Polglaze\ncreator_1:Not indicated\ncreator_role:photographers\ncreation_date:1940s\ncreation_place_original_location:Singapore\ninscriptions:\ninscription_language:\nshape:rectangular\nmaterials_name:paper (fiber product)\ntechniques_name:printing (process) photographic processes\nobject_colour:grey monochrome\nphysical_appearance:The image shows a black-and-white photograph. It is rectangular and it features a military personnel\n together with numerous prisoners of war. These prisoners of war are lined up in three rows and some of them are not wearing shirts. To the extreme left of the photograph\n a soldier with a rifle slung on his right arm faces the prisoners of war. There is a roofed building at the background of the photograph\n towards the left.\nsubject_terms_1:world wars military personnel prisoners of war\nsubject_terms_2:Black-and-white photography World War\n 1939 - 1945 Japan. Rikugun Prisoner of war Great Britain Army\n British Indian Army\nsubject_terms_3:Photography Surrender of Japan\n 1945 Wars\ncontext_1:World War\n 1939 - 1945\ncontext_2:world wars\ncontext_3:1939 - 1945\ncontext_4:1939\ncontext_5:1945\ncontext_6:Southeast Asia\nsgcool_label_text:Not indicated","createdDate":"20201018182635","version":0,"latest":false,"roles":[],"metadata":{"accession_no_csv":"2014-00285-030","Image":"","object_work_type":"black-and-white photographs","title_text":"Japanese prisoners of war guarded by an Indian sepoy Photography Album (donation from Anthony Robert Saint Claire)","preference":"main alternate","title_language":"","creator_2":"Robert Arthur Polglaze","creator_1":"Not indicated","creator_role":"photographers","creation_date":"1940s","creation_place_original_location":"Singapore","inscriptions":"","inscription_language":"","shape":"rectangular","materials_name":"paper (fiber product)","techniques_name":"printing (process) photographic processes","object_colour":"grey monochrome","physical_appearance":"The image shows a black-and-white photograph. It is rectangular and it features a military personnel, together with numerous prisoners of war. These prisoners of war are lined up in three rows and some of them are not wearing shirts. To the extreme left of the photograph, a soldier with a rifle slung on his right arm faces the prisoners of war. There is a roofed building at the background of the photograph, towards the left.","subject_terms_1":"world wars military personnel prisoners of war","subject_terms_2":"Black-and-white photography World War, 1939 - 1945 Japan. Rikugun Prisoner of war Great Britain Army, British Indian Army","subject_terms_3":"Photography Surrender of Japan, 1945 Wars","context_1":"World War, 1939 - 1945","context_2":"world wars","context_3":"1939 - 1945","context_4":"1939","context_5":"1945","context_6":"Southeast Asia","sgcool_label_text":"Not indicated"},"nlpDate":"20201018182635","connectorId":0,"tags":{}}