{"id":"2014-00206-010","title":"Doris Geddes, The Little Shop, Raffles Hotel, Singapore Items Related to Doris Geddes","source":"Bumblebee","path":"./Data/json/","content":"accession_no_csv:2014-00206-010\nImage:\nobject_work_type:advertising cards\ntitle_text:Doris Geddes\n The Little Shop\n Raffles Hotel\n Singapore Items Related to Doris Geddes\npreference:main alternate\ntitle_language:\ncreation_date:Not indicated\ncreation_place_original_location:Singapore\ninscriptions:\ninscription_language:\nshape:irregular\nmaterials_name:paper (fiber product) printing paper\ntechniques_name:printing processes\nobject_colour:multicoloured\nphysical_appearance:\\The image displays an advertising card. It is rectangular in shape. \\\\Greetings from Doris Geddes\nsubject_terms_1:The Little Shop hotels (public accommodations) advertisements retail stores\nsubject_terms_2:Raffles Hotel Raffles Hotel advertising Stores\n Retail Figurines\nsubject_terms_3:Singapore\\\\ is displayed below the image on the advertising card. The image on the card depicts several items in the interior of a building. A figurine of a male figure holding a torch can be seen standing on a round stool. There are other smaller figurines of humans and animals on the floor as well. A small decorated tree can be seen in the corner as well.\\ Retail\nsubject_terms_4:figurines\ncontext_1:Advertising cards\ncontext_2:Media and advertising","createdDate":"20201018182635","version":0,"latest":false,"roles":[],"metadata":{"accession_no_csv":"2014-00206-010","Image":"","object_work_type":"advertising cards","title_text":"Doris Geddes, The Little Shop, Raffles Hotel, Singapore Items Related to Doris Geddes","preference":"main alternate","title_language":"","creation_date":"Not indicated","creation_place_original_location":"Singapore","inscriptions":"","inscription_language":"","shape":"irregular","materials_name":"paper (fiber product) printing paper","techniques_name":"printing processes","object_colour":"multicoloured","physical_appearance":"\"The image displays an advertising card. It is rectangular in shape. \"\"Greetings from Doris Geddes","subject_terms_1":"The Little Shop hotels (public accommodations) advertisements retail stores","subject_terms_2":"Raffles Hotel Raffles Hotel advertising Stores, Retail Figurines","subject_terms_3":"Singapore\"\" is displayed below the image on the advertising card. The image on the card depicts several items in the interior of a building. A figurine of a male figure holding a torch can be seen standing on a round stool. There are other smaller figurines of humans and animals on the floor as well. A small decorated tree can be seen in the corner as well.\" Retail","subject_terms_4":"figurines","context_1":"Advertising cards","context_2":"Media and advertising"},"nlpDate":"20201018182635","connectorId":0,"tags":{}}