{
  "id": "2014-00502-001",
  "title": "The Orient The Orient Illustrated Weekly",
  "source": "Bumblebee",
  "path": "./Data/json/",
  "content": "\n  accession_no_csv: 2014-00502-001\n\n  Image: \n\n  object_work_type: clippings (information artifacts) pages (components) articles\n\n  title_text: The Orient The Orient Illustrated Weekly\n\n  preference: alternate main\n\n  title_language: \n\n  creation_date: 2/3/46\n\n  creation_place_original_location: Singapore Malaya India\n\n  inscriptions: \n\n  inscription_language: \n\n  shape: rectangular\n\n  materials_name: paper (fiber product)\n\n  techniques_name: printing processes\n\n  object_colour: black-and-white prints (prints on paper)\n\n  physical_appearance: This clipping is page 23 from the periodical \\u0027The Orient Illustrated Weekly\\u0027 published on 3 February 1946. The left side of the page comprises of three articles. A photograph at the bottom left of the page shows two cadet officers from the Indian National Army posing with a group of women. The right column of the page features two advertisements. The edges are slightly torn\n especially at the bottom.\n\n  subject_terms_1: nationalism Indian (South Asian) soldiers periodicals\n\n  subject_terms_2: self-determination\n national Nationalism anti-imperialist movements independence movements Indian National Army Periodicals\n\n  subject_terms_3: Indian National Army (Singapore) Indian National Army Monument Site periodicals\n\n  sgcool_label_text: \\Prior to the World War II period\n Indians in Singapore and Malaya retained strong political\n sentimental and economic ties with their home country. Anti-colonial thoughts and actions\n inspired by the \\\\call for freedom\\\\ in India\n",
  "createdDate": "20201120223706",
  "version": 0,
  "latest": false,
  "roles": [],
  "metadata": {
    "accession_no_csv": "2014-00502-001",
    "Image": "",
    "object_work_type": "clippings (information artifacts) pages (components) articles",
    "title_text": "The Orient The Orient Illustrated Weekly",
    "preference": "alternate main",
    "title_language": "",
    "creation_date": "2/3/46",
    "creation_place_original_location": "Singapore Malaya India",
    "inscriptions": "",
    "inscription_language": "",
    "shape": "rectangular",
    "materials_name": "paper (fiber product)",
    "techniques_name": "printing processes",
    "object_colour": "black-and-white prints (prints on paper)",
    "physical_appearance": "This clipping is page 23 from the periodical \u0027The Orient Illustrated Weekly\u0027 published on 3 February 1946. The left side of the page comprises of three articles. A photograph at the bottom left of the page shows two cadet officers from the Indian National Army posing with a group of women. The right column of the page features two advertisements. The edges are slightly torn, especially at the bottom.",
    "subject_terms_1": "nationalism Indian (South Asian) soldiers periodicals",
    "subject_terms_2": "self-determination, national Nationalism anti-imperialist movements independence movements Indian National Army Periodicals",
    "subject_terms_3": "Indian National Army (Singapore) Indian National Army Monument Site periodicals",
    "sgcool_label_text": "\"Prior to the World War II period, Indians in Singapore and Malaya retained strong political, sentimental and economic ties with their home country. Anti-colonial thoughts and actions, inspired by the \"\"call for freedom\"\" in India"
  },
  "nlpDate": "20201120223706",
  "connectorId": 0,
  "tags": {}
}