{
  "id": "2014-00500-003",
  "title": "The Orient Weekly Jawaharlal in Ipoh",
  "source": "Bumblebee",
  "path": "./Data/json/",
  "content": "\n  accession_no_csv: 2014-00500-003\n\n  Image: \n\n  object_work_type: clippings (information artifacts) pages (components)\n\n  title_text: The Orient Weekly Jawaharlal in Ipoh\n\n  preference: alternate main\n\n  title_language: \n\n  creation_date: 27/1/46\n\n  creation_place_original_location: Singapore Malaya India\n\n  inscriptions: \n\n  inscription_language: \n\n  shape: rectangular\n\n  materials_name: paper (fiber product)\n\n  techniques_name: printing processes\n\n  object_colour: black-and-white prints (prints on paper)\n\n  physical_appearance: This clipping is a page from the periodical \\u0027The Orient Illustrated Weekly\\u0027\n titled \\u0027Jawaharlal in Ipoh\\u0027. The title is printed at the top of the page. The clipping includes six black-and-white photographs\n taken in the town of Ipoh Malaya\n during Pandit Jawaharlal Nehru\\u0027s visit in March 1946. The edges of the page are slightly torn\n especially on the right.\n\n  subject_terms_1: nationalism Indian (South Asian) political events rallies periodicals\n\n  subject_terms_2: self-determination\n national Nationalism anti-imperialist movements independence movements Indian National Army Nehru\n Jawaharlal\n 1889-1964 Ipoh (Perak\n Malaysia) Periodicals\n\n  subject_terms_3: Indian National Army (Singapore) Indian National Army Monument Site periodicals\n",
  "createdDate": "20201120223706",
  "version": 0,
  "latest": false,
  "roles": [],
  "metadata": {
    "accession_no_csv": "2014-00500-003",
    "Image": "",
    "object_work_type": "clippings (information artifacts) pages (components)",
    "title_text": "The Orient Weekly Jawaharlal in Ipoh",
    "preference": "alternate main",
    "title_language": "",
    "creation_date": "27/1/46",
    "creation_place_original_location": "Singapore Malaya India",
    "inscriptions": "",
    "inscription_language": "",
    "shape": "rectangular",
    "materials_name": "paper (fiber product)",
    "techniques_name": "printing processes",
    "object_colour": "black-and-white prints (prints on paper)",
    "physical_appearance": "This clipping is a page from the periodical \u0027The Orient Illustrated Weekly\u0027, titled \u0027Jawaharlal in Ipoh\u0027. The title is printed at the top of the page. The clipping includes six black-and-white photographs, taken in the town of Ipoh Malaya, during Pandit Jawaharlal Nehru\u0027s visit in March 1946. The edges of the page are slightly torn, especially on the right.",
    "subject_terms_1": "nationalism Indian (South Asian) political events rallies periodicals",
    "subject_terms_2": "self-determination, national Nationalism anti-imperialist movements independence movements Indian National Army Nehru, Jawaharlal, 1889-1964 Ipoh (Perak, Malaysia) Periodicals",
    "subject_terms_3": "Indian National Army (Singapore) Indian National Army Monument Site periodicals"
  },
  "nlpDate": "20201120223706",
  "connectorId": 0,
  "tags": {}
}