{"id":"2014-00285-035","title":"Outram Road Jail Photography Album (donation from Anthony Robert Saint Claire)","source":"Bumblebee","path":"./Data/json/","content":"accession_no_csv:2014-00285-035\nImage:\nobject_work_type:colour photographs\ntitle_text:Outram Road Jail Photography Album (donation from Anthony Robert Saint Claire)\npreference:main alternate\ntitle_language:\ncreator_2:Robert Arthur Polglaze\ncreator_1:Not indicated\ncreator_role:photographers\ncreation_date:1940s\ncreation_place_original_location:Singapore\ninscriptions:\ninscription_language:\nshape:rectangular\nmaterials_name:paper (fiber product)\ntechniques_name:printing (process) photographic processes\nobject_colour:grey monochrome\nphysical_appearance:The image shows a colour photograph. It is rectangular and it features a building that is light pink in colour. It has two roofed segments and numerous windows. There are a couple of people standing at the entrance of the building. The foreground of the photograph displays greenery\n and there are some tall trees as well.\nsubject_terms_1:jails (buildings) prisons (buildings) prisoner-of-war camps\nsubject_terms_2:Colour photography Outram Road Prison (Outram\n Singapore)\nsubject_terms_3:Photography Pearl\\u0027s Hill Prison\nsgcool_label_text:Not indicated","createdDate":"20201018182635","version":0,"latest":false,"roles":[],"metadata":{"accession_no_csv":"2014-00285-035","Image":"","object_work_type":"colour photographs","title_text":"Outram Road Jail Photography Album (donation from Anthony Robert Saint Claire)","preference":"main alternate","title_language":"","creator_2":"Robert Arthur Polglaze","creator_1":"Not indicated","creator_role":"photographers","creation_date":"1940s","creation_place_original_location":"Singapore","inscriptions":"","inscription_language":"","shape":"rectangular","materials_name":"paper (fiber product)","techniques_name":"printing (process) photographic processes","object_colour":"grey monochrome","physical_appearance":"The image shows a colour photograph. It is rectangular and it features a building that is light pink in colour. It has two roofed segments and numerous windows. There are a couple of people standing at the entrance of the building. The foreground of the photograph displays greenery, and there are some tall trees as well.","subject_terms_1":"jails (buildings) prisons (buildings) prisoner-of-war camps","subject_terms_2":"Colour photography Outram Road Prison (Outram, Singapore)","subject_terms_3":"Photography Pearl\u0027s Hill Prison","sgcool_label_text":"Not indicated"},"nlpDate":"20201018182635","connectorId":0,"tags":{}}