{
  "id": "2014-00916-002",
  "title": "$peechle$$ Corner by fFurious Big O covers (3)",
  "source": "Bumblebee",
  "path": "./Data/json/",
  "content": "\n  accession_no_csv: 2014-00916-002\n\n  Image: \n\n  object_work_type: magazines (periodicals)\n\n  title_text: $peechle$$ Corner by fFurious Big O covers (3)\n\n  preference: main alternate\n\n  title_language: \n\n  creator_2: Little Ong\n\n  creator_1: Not indicated\n\n  creator_role: designers\n\n  creation_date: Not indicated\n\n  inscriptions: \n\n  inscription_language: \n\n  shape: rectangular\n\n  materials_name: paper (fiber product)\n\n  techniques_name: printing (process) bookbinding (process)\n\n  object_colour: multicoloured\n\n  physical_appearance: \\The image shows a rectangular magazine cover. \\\\Try quitting with this big pack!\\\\ is the headline for the magazine cover in the middle. It features the images of three packets of cigarettes. The words \\\\Adult Size\\\\ are printed on the front of the cigarette packets. At the bottom left hand side\n\n  subject_terms_1: smoking (activity) four square pictures are featured packets (containers)\n\n  subject_terms_2: depicting the cut-out of a packet of cigarette being kicked.\\ Smoking cessation Satire\n\n  subject_terms_3: satire (artistic device) Satire and humour\n\n  subject_terms_4: Periodicals\n\n  context_1: Periodicals\n",
  "createdDate": "20201201203309",
  "version": 0,
  "latest": false,
  "roles": [],
  "metadata": {
    "accession_no_csv": "2014-00916-002",
    "Image": "",
    "object_work_type": "magazines (periodicals)",
    "title_text": "$peechle$$ Corner by fFurious Big O covers (3)",
    "preference": "main alternate",
    "title_language": "",
    "creator_2": "Little Ong",
    "creator_1": "Not indicated",
    "creator_role": "designers",
    "creation_date": "Not indicated",
    "inscriptions": "",
    "inscription_language": "",
    "shape": "rectangular",
    "materials_name": "paper (fiber product)",
    "techniques_name": "printing (process) bookbinding (process)",
    "object_colour": "multicoloured",
    "physical_appearance": "\"The image shows a rectangular magazine cover. \"\"Try quitting with this big pack!\"\" is the headline for the magazine cover in the middle. It features the images of three packets of cigarettes. The words \"\"Adult Size\"\" are printed on the front of the cigarette packets. At the bottom left hand side",
    "subject_terms_1": "smoking (activity) four square pictures are featured packets (containers)",
    "subject_terms_2": "depicting the cut-out of a packet of cigarette being kicked.\" Smoking cessation Satire",
    "subject_terms_3": "satire (artistic device) Satire and humour",
    "subject_terms_4": "Periodicals",
    "context_1": "Periodicals"
  },
  "nlpDate": "20201201203309",
  "connectorId": 0,
  "tags": {}
}