{"id":"2014-00505-002","title":"The Orient The Story of the Indian Independence Movement in East Asia","source":"Bumblebee","path":"./Data/json/","content":"accession_no_csv:2014-00505-002\nImage:\nobject_work_type:clippings (information artifacts) articles\ntitle_text:The Orient The Story of the Indian Independence Movement in East Asia\npreference:alternate main\ntitle_language:\ncreator_2:Lt. K. E. Kochunni Nair\n I. N. A. (?)\ncreator_role:author\ncreation_date:30/6/46\ncreation_place_original_location:Singapore Malaya India\ninscriptions:\ninscription_language:\nshape:rectangular\nmaterials_name:paper (fiber product)\ntechniques_name:printing processes\nobject_colour:black-and-white prints (prints on paper)\nphysical_appearance:This clipping is an article from the periodical \\u0027The Orient Illustrated Weekly\\u0027 published on 30 June 1946. An excerpt of the article is printed on the center of the publication. The article includes three black-and-white photographs. There is a small tear at the top-center of the clipping.\nsubject_terms_1:nationalism Indian (South Asian) armies periodicals\nsubject_terms_2:National liberation movements self-determination\n national Nationalism Anti-imperialist movements Indian National Army Provisional Government of Free India Independence movements Bose\n Subhas Chandra\n 1897-1945 Periodicals\nsubject_terms_3:Bose\n Subhas Chandra Indian National Army (Singapore) Indian National Army Monument Site periodicals\nsgcool_label_text:\\Prior to the World War II period\n Indians in Singapore and Malaya retained strong political\n sentimental and economic ties with their home country. Anti-colonial thoughts and actions\n inspired by the \\\\call for freedom\\\\ in India","createdDate":"20201119143405","version":0,"latest":false,"roles":[],"metadata":{"accession_no_csv":"2014-00505-002","Image":"","object_work_type":"clippings (information artifacts) articles","title_text":"The Orient The Story of the Indian Independence Movement in East Asia","preference":"alternate main","title_language":"","creator_2":"Lt. K. E. Kochunni Nair, I. N. A. (?)","creator_role":"author","creation_date":"30/6/46","creation_place_original_location":"Singapore Malaya India","inscriptions":"","inscription_language":"","shape":"rectangular","materials_name":"paper (fiber product)","techniques_name":"printing processes","object_colour":"black-and-white prints (prints on paper)","physical_appearance":"This clipping is an article from the periodical \u0027The Orient Illustrated Weekly\u0027 published on 30 June 1946. An excerpt of the article is printed on the center of the publication. The article includes three black-and-white photographs. There is a small tear at the top-center of the clipping.","subject_terms_1":"nationalism Indian (South Asian) armies periodicals","subject_terms_2":"National liberation movements self-determination, national Nationalism Anti-imperialist movements Indian National Army Provisional Government of Free India Independence movements Bose, Subhas Chandra, 1897-1945 Periodicals","subject_terms_3":"Bose, Subhas Chandra Indian National Army (Singapore) Indian National Army Monument Site periodicals","sgcool_label_text":"\"Prior to the World War II period, Indians in Singapore and Malaya retained strong political, sentimental and economic ties with their home country. Anti-colonial thoughts and actions, inspired by the \"\"call for freedom\"\" in India"},"nlpDate":"20201119143405","connectorId":0,"tags":{}}