{
  "id": "2014-00507",
  "title": "The Orient Shah Nawaz in Netaji\u0027s Room",
  "source": "Bumblebee",
  "path": "./Data/json/",
  "content": "\n  accession_no_csv: 2014-00507\n\n  Image: \n\n  object_work_type: clippings (information artifacts) pages (components)\n\n  title_text: The Orient Shah Nawaz in Netaji\\u0027s Room\n\n  preference: main alternate\n\n  title_language: \n\n  creation_date: 2/10/46\n\n  creation_place_original_location: India Singapore Malaya\n\n  inscriptions: \n\n  inscription_language: \n\n  shape: rectangular\n\n  materials_name: paper (fiber product)\n\n  techniques_name: printing processes\n\n  object_colour: black-and-white prints (prints on paper)\n\n  physical_appearance: This clipping is a page from the periodical \\u0027The Orient Illustrsted Weekly\\u0027 published on 10 February 1946. The title is printed at the top of the page. This page features six photographs with captions at the bottom. The edges of the page are slightly torn\n especially on the left\n with folded edges on the right.\n\n  subject_terms_1: periodicals Indian (South Asian) nationalism\n\n  subject_terms_2: Periodicals Bose\n Subhas Chandra\n 1897-1945 Indian National Army Khan\n Shah Nawaz\n 1914-\n\n  subject_terms_3: Indian National Army Monument Site Indian National Army (Singapore) Bose\n Subhas Chandra periodicals\n\n  sgcool_label_text: \\Prior to the World War II period\n Indians in Singapore and Malaya retained strong political\n sentimental and economic ties with their home country. Anti-colonial thoughts and actions\n inspired by the \\\\call for freedom\\\\ in India\n",
  "createdDate": "20201125084545",
  "version": 0,
  "latest": false,
  "roles": [],
  "metadata": {
    "accession_no_csv": "2014-00507",
    "Image": "",
    "object_work_type": "clippings (information artifacts) pages (components)",
    "title_text": "The Orient Shah Nawaz in Netaji\u0027s Room",
    "preference": "main alternate",
    "title_language": "",
    "creation_date": "2/10/46",
    "creation_place_original_location": "India Singapore Malaya",
    "inscriptions": "",
    "inscription_language": "",
    "shape": "rectangular",
    "materials_name": "paper (fiber product)",
    "techniques_name": "printing processes",
    "object_colour": "black-and-white prints (prints on paper)",
    "physical_appearance": "This clipping is a page from the periodical \u0027The Orient Illustrsted Weekly\u0027 published on 10 February 1946. The title is printed at the top of the page. This page features six photographs with captions at the bottom. The edges of the page are slightly torn, especially on the left, with folded edges on the right.",
    "subject_terms_1": "periodicals Indian (South Asian) nationalism",
    "subject_terms_2": "Periodicals Bose, Subhas Chandra, 1897-1945 Indian National Army Khan, Shah Nawaz, 1914-",
    "subject_terms_3": "Indian National Army Monument Site Indian National Army (Singapore) Bose, Subhas Chandra periodicals",
    "sgcool_label_text": "\"Prior to the World War II period, Indians in Singapore and Malaya retained strong political, sentimental and economic ties with their home country. Anti-colonial thoughts and actions, inspired by the \"\"call for freedom\"\" in India"
  },
  "nlpDate": "20201125084545",
  "connectorId": 0,
  "tags": {}
}