{
  "id": "2014-00351",
  "title": "The British entering Singapore after its cession in 1824",
  "source": "Bumblebee",
  "path": "./Data/json/",
  "content": "\n  accession_no_csv: 2014-00351\n\n  Image: \n\n  object_work_type: prints (visual works)\n\n  title_text: The British entering Singapore after its cession in 1824\n\n  preference: main\n\n  title_language: \n\n  creator_2: Illustrated London News\n 1902 R.  Canto Woodville\n\n  creator_1: Woodville\n Richard Caton\n 1856 - 1927 Illustrated London news\n\n  creator_role: publishers painters (artists)\n\n  creation_date: 1902\n\n  creation_place_original_location: Singapore\n\n  inscriptions: \n\n  inscription_language: \n\n  shape: rectangular\n\n  materials_name: paper (fiber product) paint (coating)\n\n  techniques_name: printing processes painting (image-making)\n\n  object_colour: multicoloured\n\n  physical_appearance: \\The image depicts a rectangular print. The style and artist of the print\n \\\\The British Dominons Beyond The Seas - No. XVIII: Singapore \\\\ and \\\\Drawn by R. Caton Woodville\\\\\n\n  subject_terms_1: colonists indigenous people are stated at the top centre of the artwork. \\\\R. Caton Woodville 1902.\\\\ is indicated at the bottom left hand corner of the artwork. The title of the print colonial settlements\n\n  subject_terms_2: \\\\The British Entering Singapore After Its Cession in 1824\\\\ is stated below the artwork. There are three lines of text lines of text explaining the importance of Singapore as a trading hub for the British imperialists and the key historical events which led to her being colonized are stated. The painting depicts a large group of indigenous people who are mostly looking towards the background of the painting. There are several horses and an elephant travelling from the east to the west. Atop the elephant Painting Colonization East India Company Singapore Indigenous people colonial administrators Annexation (International law)\n\n  subject_terms_3: Colonial administrators East India Company a British officer and a sultan sits on a seat. They are being fanned by a person standing behind them. The elephant is being guided by another men sitting on its neck. There is a tall building with three flags at the background on the right hand side of the artwork. \\ 1819-1826 Founding and early years\n\n  subject_terms_4: history paintings\n\n  context_1: prints\n\n  context_2: Visual arts\n\n  context_4: The print depicts the entry of the British into Singapore after the 1824 Treaty of Friendship and Alliance was signed between the East India Company (EIC) and the sultans of Johor\n\n  context_5: treaties\n\n  context_6: 18240802\n\n  context_7: 18240802\n\n  context_8: 18240802\n\n  context_9: Fort Canning Hill\n",
  "createdDate": "20201201203309",
  "version": 0,
  "latest": false,
  "roles": [],
  "metadata": {
    "accession_no_csv": "2014-00351",
    "Image": "",
    "object_work_type": "prints (visual works)",
    "title_text": "The British entering Singapore after its cession in 1824",
    "preference": "main",
    "title_language": "",
    "creator_2": "Illustrated London News, 1902 R.  Canto Woodville",
    "creator_1": "Woodville, Richard Caton, 1856 - 1927 Illustrated London news",
    "creator_role": "publishers painters (artists)",
    "creation_date": "1902",
    "creation_place_original_location": "Singapore",
    "inscriptions": "",
    "inscription_language": "",
    "shape": "rectangular",
    "materials_name": "paper (fiber product) paint (coating)",
    "techniques_name": "printing processes painting (image-making)",
    "object_colour": "multicoloured",
    "physical_appearance": "\"The image depicts a rectangular print. The style and artist of the print, \"\"The British Dominons Beyond The Seas - No. XVIII: Singapore \"\" and \"\"Drawn by R. Caton Woodville\"\"",
    "subject_terms_1": "colonists indigenous people are stated at the top centre of the artwork. \"\"R. Caton Woodville 1902.\"\" is indicated at the bottom left hand corner of the artwork. The title of the print colonial settlements",
    "subject_terms_2": "\"\"The British Entering Singapore After Its Cession in 1824\"\" is stated below the artwork. There are three lines of text lines of text explaining the importance of Singapore as a trading hub for the British imperialists and the key historical events which led to her being colonized are stated. The painting depicts a large group of indigenous people who are mostly looking towards the background of the painting. There are several horses and an elephant travelling from the east to the west. Atop the elephant Painting Colonization East India Company Singapore Indigenous people colonial administrators Annexation (International law)",
    "subject_terms_3": "Colonial administrators East India Company a British officer and a sultan sits on a seat. They are being fanned by a person standing behind them. The elephant is being guided by another men sitting on its neck. There is a tall building with three flags at the background on the right hand side of the artwork. \" 1819-1826 Founding and early years",
    "subject_terms_4": "history paintings",
    "context_1": "prints",
    "context_2": "Visual arts",
    "context_4": "The print depicts the entry of the British into Singapore after the 1824 Treaty of Friendship and Alliance was signed between the East India Company (EIC) and the sultans of Johor",
    "context_5": "treaties",
    "context_6": "18240802",
    "context_7": "18240802",
    "context_8": "18240802",
    "context_9": "Fort Canning Hill"
  },
  "nlpDate": "20201201203309",
  "connectorId": 0,
  "tags": {}
}