{
  "id": "2014-00205",
  "title": "Set of Postcards “Java-China-Japan” (x3) Three Postcards entitled “Java-China-Japan Lijn\"\"",
  "source": "Bumblebee",
  "path": "./Data/json/",
  "content": "\n  accession_no_csv: 2014-00205\n\n  Image: \n\n  object_work_type: picture postcards\n\n  title_text: Set of Postcards “Java-China-Japan” (x3) Three Postcards entitled “Java-China-Japan Lijn\\\\\n\n  preference: main alternate\n\n  title_language: \n\n  creator_2: Not indicated\n\n  creation_date: Not indicated\n\n  creation_place_original_location: Not indicated\n\n  inscriptions: \n\n  inscription_language: \n\n  shape: rectangular\n\n  materials_name: paper (fiber product) printing paper\n\n  techniques_name: printing processes\n\n  object_colour: multicoloured\n\n  physical_appearance: \\The image displays three picture postcards. All of them are rectangular in shape. Each postcard contains an image of a woman. She is dressed in her ethnic costume\n with stalks of a red flower as her headdress. The postcard on the left shows her holding a kris. The postcard in the middle depicts her holding a bow and an arrow. The postcard in on the right shows her in a bending sideways at the hips in a pose. All three postcards have the words \\\\Java-China-Japan Lijn\\\\ stated at the bottom.\\\n\n  subject_terms_1: women (female humans) companies folk costume\n\n  subject_terms_2: Ethnic costume Java-China-Japan Lyn Women postcards\n\n  subject_terms_3: Photography Business enterprises Ethnic costumes Women\n\n  sgcool_label_text: Not indicated\n",
  "createdDate": "20201125084547",
  "version": 0,
  "latest": false,
  "roles": [],
  "metadata": {
    "accession_no_csv": "2014-00205",
    "Image": "",
    "object_work_type": "picture postcards",
    "title_text": "Set of Postcards “Java-China-Japan” (x3) Three Postcards entitled “Java-China-Japan Lijn\"\"",
    "preference": "main alternate",
    "title_language": "",
    "creator_2": "Not indicated",
    "creation_date": "Not indicated",
    "creation_place_original_location": "Not indicated",
    "inscriptions": "",
    "inscription_language": "",
    "shape": "rectangular",
    "materials_name": "paper (fiber product) printing paper",
    "techniques_name": "printing processes",
    "object_colour": "multicoloured",
    "physical_appearance": "\"The image displays three picture postcards. All of them are rectangular in shape. Each postcard contains an image of a woman. She is dressed in her ethnic costume, with stalks of a red flower as her headdress. The postcard on the left shows her holding a kris. The postcard in the middle depicts her holding a bow and an arrow. The postcard in on the right shows her in a bending sideways at the hips in a pose. All three postcards have the words \"\"Java-China-Japan Lijn\"\" stated at the bottom.\"",
    "subject_terms_1": "women (female humans) companies folk costume",
    "subject_terms_2": "Ethnic costume Java-China-Japan Lyn Women postcards",
    "subject_terms_3": "Photography Business enterprises Ethnic costumes Women",
    "sgcool_label_text": "Not indicated"
  },
  "nlpDate": "20201125084547",
  "connectorId": 0,
  "tags": {}
}