{
  "id": "2014-00499-003",
  "title": "The Orient Weekly The Story Of The Indian Independence Movement in East Asia",
  "source": "Bumblebee",
  "path": "./Data/json/",
  "content": "\n  accession_no_csv: 2014-00499-003\n\n  Image: \n\n  object_work_type: articles clippings (information artifacts)\n\n  title_text: The Orient Weekly The Story Of The Indian Independence Movement in East Asia\n\n  preference: main alternate\n\n  title_language: \n\n  creator_2: Lt. K. E. Kochunni Nair\n I.N.A. (?)\n\n  creator_role: author\n\n  creation_date: 1946\n\n  creation_place_original_location: India Singapore Malaya\n\n  inscriptions: \n\n  inscription_language: \n\n  shape: rectangular\n\n  materials_name: paper (fiber product)\n\n  techniques_name: printing processes\n\n  object_colour: black-and-white prints (prints on paper)\n\n  physical_appearance: This clipping is an article from the periodical \\u0027The Orient Illustrated Weekly\\u0027 published on 7 July 1946. The clipping includes an excerpt of the article in the center of the page. The page also features four black-and-white photographs. The left and right edges of the page are torn.\\r\\n\\r\\n\\r\\n\\r\\n\n\n  subject_terms_1: periodicals Indian (South Asian) battles nationalism\n\n  subject_terms_2: Periodicals Anti-imperialist movements Independence movements National liberation movements Battles Provisional Government of Free India Nationalism Bose\n Subhas Chandra\n 1897-1945 self-determination\n national Indian National Army\n\n  subject_terms_3: Indian National Army Monument Site Indian National Army (Singapore) Bose\n Subhas Chandra periodicals\n\n  sgcool_label_text: \\Prior to the World War II period\n Indians in Singapore and Malaya retained strong political\n sentimental and economic ties with their home country. Anti-colonial thoughts and actions\n inspired by the \\\\call for freedom\\\\ in India\n",
  "createdDate": "20201125084545",
  "version": 0,
  "latest": false,
  "roles": [],
  "metadata": {
    "accession_no_csv": "2014-00499-003",
    "Image": "",
    "object_work_type": "articles clippings (information artifacts)",
    "title_text": "The Orient Weekly The Story Of The Indian Independence Movement in East Asia",
    "preference": "main alternate",
    "title_language": "",
    "creator_2": "Lt. K. E. Kochunni Nair, I.N.A. (?)",
    "creator_role": "author",
    "creation_date": "1946",
    "creation_place_original_location": "India Singapore Malaya",
    "inscriptions": "",
    "inscription_language": "",
    "shape": "rectangular",
    "materials_name": "paper (fiber product)",
    "techniques_name": "printing processes",
    "object_colour": "black-and-white prints (prints on paper)",
    "physical_appearance": "This clipping is an article from the periodical \u0027The Orient Illustrated Weekly\u0027 published on 7 July 1946. The clipping includes an excerpt of the article in the center of the page. The page also features four black-and-white photographs. The left and right edges of the page are torn.\r\n\r\n\r\n\r\n",
    "subject_terms_1": "periodicals Indian (South Asian) battles nationalism",
    "subject_terms_2": "Periodicals Anti-imperialist movements Independence movements National liberation movements Battles Provisional Government of Free India Nationalism Bose, Subhas Chandra, 1897-1945 self-determination, national Indian National Army",
    "subject_terms_3": "Indian National Army Monument Site Indian National Army (Singapore) Bose, Subhas Chandra periodicals",
    "sgcool_label_text": "\"Prior to the World War II period, Indians in Singapore and Malaya retained strong political, sentimental and economic ties with their home country. Anti-colonial thoughts and actions, inspired by the \"\"call for freedom\"\" in India"
  },
  "nlpDate": "20201125084545",
  "connectorId": 0,
  "tags": {}
}