{
  "id": "2014-00285-016",
  "title": "Kuala Lumpur railway station Photography Album (donation from Anthony Robert Saint Claire)",
  "source": "Bumblebee",
  "path": "./Data/json/",
  "content": "\n  accession_no_csv: 2014-00285-016\n\n  Image: \n\n  object_work_type: black-and-white photographs\n\n  title_text: Kuala Lumpur railway station Photography Album (donation from Anthony Robert Saint Claire)\n\n  preference: main alternate\n\n  title_language: \n\n  creator_2: Robert Arthur Polglaze\n\n  creator_1: Not indicated\n\n  creator_role: photographers\n\n  creation_date: 1940s\n\n  creation_place_original_location: Singapore\n\n  inscriptions: \n\n  inscription_language: \n\n  shape: rectangular\n\n  materials_name: paper (fiber product)\n\n  techniques_name: printing (process) photographic processes\n\n  object_colour: grey monochrome\n\n  physical_appearance: The image shows a black-and-white photograph. It is rectangular and it features a building that contains several domes\n minarets\n and pointed arches from the parapet. There are numerous windows that are circular and rectangular in shape. The entrances to the building are wide and dome-shaped. The foreground of the photograph shows a road. A lady and a man can be seen walking\n at the right hand side of the photograph. There are people who are entering the building\n on the left hand side of the photograph.\n\n  subject_terms_1: railroad stations\n\n  subject_terms_2: Pertadbiran Keretapi Tanah Melayu Railroad stations Black-and-white photography\n\n  subject_terms_3: Rail transport (Stations) Photography Pertadbiran Keretapi Tanah Melayu\n\n  sgcool_label_text: Not indicated\n",
  "createdDate": "20201125084547",
  "version": 0,
  "latest": false,
  "roles": [],
  "metadata": {
    "accession_no_csv": "2014-00285-016",
    "Image": "",
    "object_work_type": "black-and-white photographs",
    "title_text": "Kuala Lumpur railway station Photography Album (donation from Anthony Robert Saint Claire)",
    "preference": "main alternate",
    "title_language": "",
    "creator_2": "Robert Arthur Polglaze",
    "creator_1": "Not indicated",
    "creator_role": "photographers",
    "creation_date": "1940s",
    "creation_place_original_location": "Singapore",
    "inscriptions": "",
    "inscription_language": "",
    "shape": "rectangular",
    "materials_name": "paper (fiber product)",
    "techniques_name": "printing (process) photographic processes",
    "object_colour": "grey monochrome",
    "physical_appearance": "The image shows a black-and-white photograph. It is rectangular and it features a building that contains several domes, minarets, and pointed arches from the parapet. There are numerous windows that are circular and rectangular in shape. The entrances to the building are wide and dome-shaped. The foreground of the photograph shows a road. A lady and a man can be seen walking, at the right hand side of the photograph. There are people who are entering the building, on the left hand side of the photograph.",
    "subject_terms_1": "railroad stations",
    "subject_terms_2": "Pertadbiran Keretapi Tanah Melayu Railroad stations Black-and-white photography",
    "subject_terms_3": "Rail transport (Stations) Photography Pertadbiran Keretapi Tanah Melayu",
    "sgcool_label_text": "Not indicated"
  },
  "nlpDate": "20201125084547",
  "connectorId": 0,
  "tags": {}
}