{
  "id": "2014-00285-024",
  "title": "Photography Album (donation from Anthony Robert Saint Claire) Cathay Building",
  "source": "Bumblebee",
  "path": "./Data/json/",
  "content": "\n  accession_no_csv: 2014-00285-024\n\n  Image: \n\n  object_work_type: black-and-white photographs\n\n  title_text: Photography Album (donation from Anthony Robert Saint Claire) Cathay Building\n\n  preference: main alternate\n\n  title_language: \n\n  creator_2: Robert Arthur Polglaze\n\n  creator_1: Not indicated\n\n  creator_role: photographers\n\n  creation_date: 1940s\n\n  creation_place_original_location: Singapore\n\n  inscriptions: \n\n  inscription_language: \n\n  shape: rectangular\n\n  materials_name: paper (fiber product)\n\n  techniques_name: printing (process) photographic processes\n\n  object_colour: grey monochrome\n\n  physical_appearance: The image shows a black-and-white photograph. It is rectangular and it features a tall building in the background. There are five flags erected atop the roof of the building. Numerous vehicles are parked in front of the building. Two people who are dressed in uniforms are standing near a truck\n on the left hand side of the photograph.\n\n  subject_terms_1: land vehicles high-rise buildings\n\n  subject_terms_2: Vehicles Cathay (Organization) Tall buildings Black-and-white photography\n\n  subject_terms_3: Photography Cathay Building\n\n  sgcool_label_text: Not indicated\n",
  "createdDate": "20201125084546",
  "version": 0,
  "latest": false,
  "roles": [],
  "metadata": {
    "accession_no_csv": "2014-00285-024",
    "Image": "",
    "object_work_type": "black-and-white photographs",
    "title_text": "Photography Album (donation from Anthony Robert Saint Claire) Cathay Building",
    "preference": "main alternate",
    "title_language": "",
    "creator_2": "Robert Arthur Polglaze",
    "creator_1": "Not indicated",
    "creator_role": "photographers",
    "creation_date": "1940s",
    "creation_place_original_location": "Singapore",
    "inscriptions": "",
    "inscription_language": "",
    "shape": "rectangular",
    "materials_name": "paper (fiber product)",
    "techniques_name": "printing (process) photographic processes",
    "object_colour": "grey monochrome",
    "physical_appearance": "The image shows a black-and-white photograph. It is rectangular and it features a tall building in the background. There are five flags erected atop the roof of the building. Numerous vehicles are parked in front of the building. Two people who are dressed in uniforms are standing near a truck, on the left hand side of the photograph.",
    "subject_terms_1": "land vehicles high-rise buildings",
    "subject_terms_2": "Vehicles Cathay (Organization) Tall buildings Black-and-white photography",
    "subject_terms_3": "Photography Cathay Building",
    "sgcool_label_text": "Not indicated"
  },
  "nlpDate": "20201125084546",
  "connectorId": 0,
  "tags": {}
}