{
  "id": "2014-00285-022",
  "title": "Photography Album (donation from Anthony Robert Saint Claire) Esplanade / Padang",
  "source": "Bumblebee",
  "path": "./Data/json/",
  "content": "\n  accession_no_csv: 2014-00285-022\n\n  Image: \n\n  object_work_type: colour photographs\n\n  title_text: Photography Album (donation from Anthony Robert Saint Claire) Esplanade / Padang\n\n  preference: main alternate\n\n  title_language: \n\n  creator_2: Robert Arthur Polglaze\n\n  creator_1: Not indicated\n\n  creator_role: photographers\n\n  creation_date: 1940s\n\n  creation_place_original_location: Singapore\n\n  inscriptions: \n\n  inscription_language: \n\n  shape: rectangular\n\n  materials_name: paper (fiber product)\n\n  techniques_name: printing (process) photographic processes\n\n  object_colour: grey monochrome\n\n  physical_appearance: The image shows a colour photograph. It is rectangular and it features a body of water on the right hand side and a field with trees on the left hand side and the foreground of the photograph. A ladder descending into the water can be seen\n and numerous sampans are stationed around it. There are people who are standing around and leaning on the ladder as well. A row of rickshaws are parked at the left hand side of the photograph.\n\n  subject_terms_1: banks (landforms) rivers sampans fields (land)\n\n  subject_terms_2: Colour photography Singapore River (Singapore) Boats and boating Padang\n The (Singapore)\n\n  subject_terms_3: Photography Padang (Singapore) Singapore River\n\n  sgcool_label_text: Not indicated\n",
  "createdDate": "20201125084547",
  "version": 0,
  "latest": false,
  "roles": [],
  "metadata": {
    "accession_no_csv": "2014-00285-022",
    "Image": "",
    "object_work_type": "colour photographs",
    "title_text": "Photography Album (donation from Anthony Robert Saint Claire) Esplanade / Padang",
    "preference": "main alternate",
    "title_language": "",
    "creator_2": "Robert Arthur Polglaze",
    "creator_1": "Not indicated",
    "creator_role": "photographers",
    "creation_date": "1940s",
    "creation_place_original_location": "Singapore",
    "inscriptions": "",
    "inscription_language": "",
    "shape": "rectangular",
    "materials_name": "paper (fiber product)",
    "techniques_name": "printing (process) photographic processes",
    "object_colour": "grey monochrome",
    "physical_appearance": "The image shows a colour photograph. It is rectangular and it features a body of water on the right hand side and a field with trees on the left hand side and the foreground of the photograph. A ladder descending into the water can be seen, and numerous sampans are stationed around it. There are people who are standing around and leaning on the ladder as well. A row of rickshaws are parked at the left hand side of the photograph.",
    "subject_terms_1": "banks (landforms) rivers sampans fields (land)",
    "subject_terms_2": "Colour photography Singapore River (Singapore) Boats and boating Padang, The (Singapore)",
    "subject_terms_3": "Photography Padang (Singapore) Singapore River",
    "sgcool_label_text": "Not indicated"
  },
  "nlpDate": "20201125084547",
  "connectorId": 0,
  "tags": {}
}