{
  "id": "2014-00228",
  "title": "Wedding necklace with flowers and case Wedding necklace with flowers",
  "source": "Bumblebee",
  "path": "./Data/json/",
  "content": "\n  accession_no_csv: 2014-00228\n\n  Image: \n\n  object_work_type: necklaces\n\n  title_text: Wedding necklace with flowers and case Wedding necklace with flowers\n\n  preference: main alternate\n\n  title_language: \n\n  creation_date: Late 19th or early 20th century\n\n  creation_place_original_location: Java (Indonesia)\n\n  styles_periods_indexing_terms: Peranakan\n\n  inscriptions: \n\n  inscription_language: \n\n  shape: irregular\n\n  materials_name: gold (metal)\n\n  techniques_name: metalworking jewellery making\n\n  object_colour: gold (colour)\n\n  physical_appearance: The image shows a gold necklace that is placed inside an open container. The container is triangular but with curved sides instead. It has a blue padding at the top and dark blue cushion at the bottom to hold the necklace in place. The necklace is gold in colour. It is made up of several chains that link panels depicting flowery and foliage designs together. A pendant hangs from the necklace and there are three segments to it.\n\n  subject_terms_1: jewellery goldwork (visual works) neck ornaments cases (containers) filigree flower (motif) foliage (motif) costume accessories weddings (ceremonies)\n\n  subject_terms_2: Gold jewellery Goldwork Necklaces Containers Filigree Motifs Ethnic jewellery Dress accessories Marriage customs and rites\n\n  subject_terms_3: Jewellery Marriage customs Peranakan costumes\n\n  sgcool_label_text: This gold wedding necklace is richly decorated with filigree panels that are embellished with flowers and leaves. Peonies are a symbol of love\n affection\n feminine beauty\n and spring\n making them auspicious flowers for weddings. The intricacy and refinement of the necklace indicate the importance of jewellery in Peranakan weddings.\\r\\n\\r\\nWedding necklaces such as this were worn by Peranakan Chinese brides throughout the Straits Settlements and the Dutch East Indies. The ornateness of this example appears to have originated from Jakarta (Batavia)\n although the exceptional quality of the necklace makes a precise geographical assignment difficult. Brides were draped with several necklaces to form an impressive assemblage and other jewelled ornamentation as a sign of the wealth and splendour of the occasion. Such necklaces became prized family heirlooms and were passed down the generations.\n",
  "createdDate": "20201120223706",
  "version": 0,
  "latest": false,
  "roles": [],
  "metadata": {
    "accession_no_csv": "2014-00228",
    "Image": "",
    "object_work_type": "necklaces",
    "title_text": "Wedding necklace with flowers and case Wedding necklace with flowers",
    "preference": "main alternate",
    "title_language": "",
    "creation_date": "Late 19th or early 20th century",
    "creation_place_original_location": "Java (Indonesia)",
    "styles_periods_indexing_terms": "Peranakan",
    "inscriptions": "",
    "inscription_language": "",
    "shape": "irregular",
    "materials_name": "gold (metal)",
    "techniques_name": "metalworking jewellery making",
    "object_colour": "gold (colour)",
    "physical_appearance": "The image shows a gold necklace that is placed inside an open container. The container is triangular but with curved sides instead. It has a blue padding at the top and dark blue cushion at the bottom to hold the necklace in place. The necklace is gold in colour. It is made up of several chains that link panels depicting flowery and foliage designs together. A pendant hangs from the necklace and there are three segments to it.",
    "subject_terms_1": "jewellery goldwork (visual works) neck ornaments cases (containers) filigree flower (motif) foliage (motif) costume accessories weddings (ceremonies)",
    "subject_terms_2": "Gold jewellery Goldwork Necklaces Containers Filigree Motifs Ethnic jewellery Dress accessories Marriage customs and rites",
    "subject_terms_3": "Jewellery Marriage customs Peranakan costumes",
    "sgcool_label_text": "This gold wedding necklace is richly decorated with filigree panels that are embellished with flowers and leaves. Peonies are a symbol of love, affection, feminine beauty, and spring, making them auspicious flowers for weddings. The intricacy and refinement of the necklace indicate the importance of jewellery in Peranakan weddings.\r\n\r\nWedding necklaces such as this were worn by Peranakan Chinese brides throughout the Straits Settlements and the Dutch East Indies. The ornateness of this example appears to have originated from Jakarta (Batavia), although the exceptional quality of the necklace makes a precise geographical assignment difficult. Brides were draped with several necklaces to form an impressive assemblage and other jewelled ornamentation as a sign of the wealth and splendour of the occasion. Such necklaces became prized family heirlooms and were passed down the generations."
  },
  "nlpDate": "20201120223706",
  "connectorId": 0,
  "tags": {}
}