{
  "id": "2014-00512-002",
  "title": "The Orient From Here and There - Evolution of Radio",
  "source": "Bumblebee",
  "path": "./Data/json/",
  "content": "\n  accession_no_csv: 2014-00512-002\n\n  Image: \n\n  object_work_type: clippings (information artifacts) pages (components)\n\n  title_text: The Orient From Here and There - Evolution of Radio\n\n  preference: alternate main\n\n  title_language: \n\n  creation_date: 16/6/46\n\n  creation_place_original_location: Singapore Malaya India\n\n  inscriptions: \n\n  inscription_language: \n\n  shape: rectangular\n\n  materials_name: paper (fiber product)\n\n  techniques_name: printing processes\n\n  object_colour: black-and-white prints (prints on paper)\n\n  physical_appearance: This clipping is a page from a publication. The title is printed in the middle of the page. There are two black-and-white advertisements on the left most column of the publication. There are two black-and-white photographs at the top of the page\n with their respective captions below them. The edges of the paper is slightly torn\n especially on the right.\n\n  subject_terms_1: periodicals broadcasting\n\n  subject_terms_2: Periodicals Communications\n Military Broadcasting\n\n  subject_terms_3: Indian National Army Monument Site periodicals\n",
  "createdDate": "20201120223706",
  "version": 0,
  "latest": false,
  "roles": [],
  "metadata": {
    "accession_no_csv": "2014-00512-002",
    "Image": "",
    "object_work_type": "clippings (information artifacts) pages (components)",
    "title_text": "The Orient From Here and There - Evolution of Radio",
    "preference": "alternate main",
    "title_language": "",
    "creation_date": "16/6/46",
    "creation_place_original_location": "Singapore Malaya India",
    "inscriptions": "",
    "inscription_language": "",
    "shape": "rectangular",
    "materials_name": "paper (fiber product)",
    "techniques_name": "printing processes",
    "object_colour": "black-and-white prints (prints on paper)",
    "physical_appearance": "This clipping is a page from a publication. The title is printed in the middle of the page. There are two black-and-white advertisements on the left most column of the publication. There are two black-and-white photographs at the top of the page, with their respective captions below them. The edges of the paper is slightly torn, especially on the right.",
    "subject_terms_1": "periodicals broadcasting",
    "subject_terms_2": "Periodicals Communications, Military Broadcasting",
    "subject_terms_3": "Indian National Army Monument Site periodicals"
  },
  "nlpDate": "20201120223706",
  "connectorId": 0,
  "tags": {}
}