{"id":"2014-00909-011","title":"72-13 (02) Brochures and cards for performances by Theatreworks (20) - 72-13 (2/9)","source":"Bumblebee","path":"./Data/json/","content":"accession_no_csv:2014-00909-011\nImage:\nobject_work_type:brochures\ntitle_text:72-13 (02) Brochures and cards for performances by Theatreworks (20) - 72-13 (2/9)\npreference:main alternate\ntitle_language:\ncreator_2:Not indicated\ncreator_1:Not indicated\ncreator_role:Not indicated\ncreation_date:Not indicated\ncreation_place_original_location:Singapore\ninscriptions:\ninscription_language:\nshape:square (shape)\nmaterials_name:paper (fiber product)\ntechniques_name:printing (process)\nobject_colour:multicoloured\nphysical_appearance:\\The image shows a square brochure. \\\\72-13\\\\ is displayed at the centre of the brochure in blue font. \\\\02\\\\ is stated at the lower left hand corner of the brochure. \\\\Kyupi Kyupi\\\\ is stated at the centre near the bottom of the brochure in white font. The image at the background depicts two ladies who are dressed in uniforms for nurses. They are holding injections and pressing them into buttocks that protrude from the top surface of red boxes.\\\nsubject_terms_1:theatres (buildings)\nsubject_terms_2:Brochures Theatres\nsubject_terms_3:Theatre organisations\ncontext_20:72-13 was an old rice warehouse\ncontext_21:72-13 Mohammed Sultan Road\n Singapore 239007\ncontext_22:2005\ncontext_23:5-Sep\ncontext_24:5-Sep\nsgcool_label_text:Not indicated","createdDate":"20201018182635","version":0,"latest":false,"roles":[],"metadata":{"accession_no_csv":"2014-00909-011","Image":"","object_work_type":"brochures","title_text":"72-13 (02) Brochures and cards for performances by Theatreworks (20) - 72-13 (2/9)","preference":"main alternate","title_language":"","creator_2":"Not indicated","creator_1":"Not indicated","creator_role":"Not indicated","creation_date":"Not indicated","creation_place_original_location":"Singapore","inscriptions":"","inscription_language":"","shape":"square (shape)","materials_name":"paper (fiber product)","techniques_name":"printing (process)","object_colour":"multicoloured","physical_appearance":"\"The image shows a square brochure. \"\"72-13\"\" is displayed at the centre of the brochure in blue font. \"\"02\"\" is stated at the lower left hand corner of the brochure. \"\"Kyupi Kyupi\"\" is stated at the centre near the bottom of the brochure in white font. The image at the background depicts two ladies who are dressed in uniforms for nurses. They are holding injections and pressing them into buttocks that protrude from the top surface of red boxes.\"","subject_terms_1":"theatres (buildings)","subject_terms_2":"Brochures Theatres","subject_terms_3":"Theatre organisations","context_20":"72-13 was an old rice warehouse","context_21":"72-13 Mohammed Sultan Road, Singapore 239007","context_22":"2005","context_23":"5-Sep","context_24":"5-Sep","sgcool_label_text":"Not indicated"},"nlpDate":"20201018182635","connectorId":0,"tags":{}}