{"id":"2014-00198","title":"Pen","source":"Bumblebee","path":"./Data/json/","content":"accession_no_csv:2014-00198\nImage:\nobject_work_type:pens (drawing and writing implements)\ntitle_text:Pen\npreference:main\ntitle_language:\ncreator_2:Not indicated\ncreation_date:Not indicated\ncreation_place_original_location:Singapore\ninscriptions:\ninscription_language:\nshape:tubular\nmaterials_name:plastic (organic material)\ntechniques_name:forming (physical activity)\nobject_colour:multicoloured\nphysical_appearance:The image displays a pen. It has a wood texture design on its surface\n at the right hand side of the photograph. Towards the left hand side\n it has a black finish on its surface. It has an edged tip that protrudes from the side which has the black finish on its surface.\nsubject_terms_1:writing instruments\nsubject_terms_2:Pens\nsgcool_label_text:Not indicated","createdDate":"20201018182635","version":0,"latest":false,"roles":[],"metadata":{"accession_no_csv":"2014-00198","Image":"","object_work_type":"pens (drawing and writing implements)","title_text":"Pen","preference":"main","title_language":"","creator_2":"Not indicated","creation_date":"Not indicated","creation_place_original_location":"Singapore","inscriptions":"","inscription_language":"","shape":"tubular","materials_name":"plastic (organic material)","techniques_name":"forming (physical activity)","object_colour":"multicoloured","physical_appearance":"The image displays a pen. It has a wood texture design on its surface, at the right hand side of the photograph. Towards the left hand side, it has a black finish on its surface. It has an edged tip that protrudes from the side which has the black finish on its surface.","subject_terms_1":"writing instruments","subject_terms_2":"Pens","sgcool_label_text":"Not indicated"},"nlpDate":"20201018182635","connectorId":0,"tags":{}}