{"id":"2014-00352","title":"Chinese Passengers from Singapore to Hong Kong","source":"Bumblebee","path":"./Data/json/","content":"accession_no_csv:2014-00352\nImage:\nobject_work_type:prints (visual works)\ntitle_text:Chinese Passengers from Singapore to Hong Kong\npreference:main\ntitle_language:\ncreator_2:The Graphic\n London\ncreator_1:Not indicated\ncreator_role:publishers\ncreation_date:1885\ncreation_place_original_location:Singapore\ninscriptions:\ninscription_language:\nshape:rectangular\nmaterials_name:paper (fiber product)\ntechniques_name:printing processes\nobject_colour:multicoloured\nphysical_appearance:\\The image shows a rectangular print. There are 3 sets of images\n one on top of the other\n that are being depicted. \\\\Chinese Passengers to hong Kong\\\\ is stated below the image closest to the bottom of the print. \\\\Arrival at Hong Kong\\\\ is stated below the middle image of the print. \\\\The Cook\\\\\nsubject_terms_1:\\\\The Doctor\\\\ race (group of people) migrations (events) professions junks (vessels)\nsubject_terms_2:\\\\The Banker\\\\ Chinese Migrations Singapore Hong Kong (China) Professions Junks\nsubject_terms_3:and \\\\from sketches from J.F.\\\\ are stated in the top image of the print. The top image shows three Chinese individuals Migration\nsubject_terms_4:each of a different profession. The cook and the doctor are shown to be sitting barefoot on the floor while the banker sits on a chair in a Changshan. The middle image shows numerous junk ships and boats over a body of water. The one closest to the foreground contains numerous Chinese people. The bottom image focuses on the deck of a junk ship\ncontext_1:showing numerous Chinese people. Some of them are lying down while others are standing up.  \\\ncontext_2:emigrants\ncontext_3:prints\ncontext_4:Visual arts","createdDate":"20201119143405","version":0,"latest":false,"roles":[],"metadata":{"accession_no_csv":"2014-00352","Image":"","object_work_type":"prints (visual works)","title_text":"Chinese Passengers from Singapore to Hong Kong","preference":"main","title_language":"","creator_2":"The Graphic, London","creator_1":"Not indicated","creator_role":"publishers","creation_date":"1885","creation_place_original_location":"Singapore","inscriptions":"","inscription_language":"","shape":"rectangular","materials_name":"paper (fiber product)","techniques_name":"printing processes","object_colour":"multicoloured","physical_appearance":"\"The image shows a rectangular print. There are 3 sets of images, one on top of the other, that are being depicted. \"\"Chinese Passengers to hong Kong\"\" is stated below the image closest to the bottom of the print. \"\"Arrival at Hong Kong\"\" is stated below the middle image of the print. \"\"The Cook\"\"","subject_terms_1":"\"\"The Doctor\"\" race (group of people) migrations (events) professions junks (vessels)","subject_terms_2":"\"\"The Banker\"\" Chinese Migrations Singapore Hong Kong (China) Professions Junks","subject_terms_3":"and \"\"from sketches from J.F.\"\" are stated in the top image of the print. The top image shows three Chinese individuals Migration","subject_terms_4":"each of a different profession. The cook and the doctor are shown to be sitting barefoot on the floor while the banker sits on a chair in a Changshan. The middle image shows numerous junk ships and boats over a body of water. The one closest to the foreground contains numerous Chinese people. The bottom image focuses on the deck of a junk ship","context_1":"showing numerous Chinese people. Some of them are lying down while others are standing up.  \"","context_2":"emigrants","context_3":"prints","context_4":"Visual arts"},"nlpDate":"20201119143405","connectorId":0,"tags":{}}