{"id":"2014-00285-020","title":"Thian Hock Keng temple Photography Album (donation from Anthony Robert Saint Claire)","source":"Bumblebee","path":"./Data/json/","content":"accession_no_csv:2014-00285-020\nImage:\nobject_work_type:colour photographs\ntitle_text:Thian Hock Keng temple Photography Album (donation from Anthony Robert Saint Claire)\npreference:main alternate\ntitle_language:\ncreator_2:Robert Arthur Polglaze\ncreator_1:Not indicated\ncreator_role:photographers\ncreation_date:1940s\ncreation_place_original_location:Singapore\ninscriptions:\ninscription_language:\nshape:rectangular\nmaterials_name:paper (fiber product)\ntechniques_name:printing (process) photographic processes\nobject_colour:grey monochrome\nphysical_appearance:The image shows a clolur photograph. It is rectangular and it features a temple. The roofs are purple in colour and they are curving with wide eaves. The roofs are also tiled and there are figures of dragons and pheonix are present on the roofs as well. There is a row of rickshaws lined outside the temple and people can be seen walking past them.\nsubject_terms_1:temples (buildings) street scenes Buddhism\nsubject_terms_2:Colour photography Thian Hock Keng (Singapore) Temples Buddhism\nsubject_terms_3:Photography Thian Hock Keng Temples Buddhism\nsgcool_label_text:Not indicated","createdDate":"20201119143405","version":0,"latest":false,"roles":[],"metadata":{"accession_no_csv":"2014-00285-020","Image":"","object_work_type":"colour photographs","title_text":"Thian Hock Keng temple Photography Album (donation from Anthony Robert Saint Claire)","preference":"main alternate","title_language":"","creator_2":"Robert Arthur Polglaze","creator_1":"Not indicated","creator_role":"photographers","creation_date":"1940s","creation_place_original_location":"Singapore","inscriptions":"","inscription_language":"","shape":"rectangular","materials_name":"paper (fiber product)","techniques_name":"printing (process) photographic processes","object_colour":"grey monochrome","physical_appearance":"The image shows a clolur photograph. It is rectangular and it features a temple. The roofs are purple in colour and they are curving with wide eaves. The roofs are also tiled and there are figures of dragons and pheonix are present on the roofs as well. There is a row of rickshaws lined outside the temple and people can be seen walking past them.","subject_terms_1":"temples (buildings) street scenes Buddhism","subject_terms_2":"Colour photography Thian Hock Keng (Singapore) Temples Buddhism","subject_terms_3":"Photography Thian Hock Keng Temples Buddhism","sgcool_label_text":"Not indicated"},"nlpDate":"20201119143405","connectorId":0,"tags":{}}