{"id":"2014-00915","title":"Freak scene, a music performance Invite card for Freak scene, a music performance","source":"Bumblebee","path":"./Data/json/","content":"accession_no_csv:2014-00915\nImage:\nobject_work_type:invitations\ntitle_text:Freak scene\n a music performance Invite card for Freak scene\n a music performance\npreference:main alternate\ntitle_language:\ncreator_2:Not indicated\ncreation_date:1998\ncreation_place_original_location:Singapore\ninscriptions:\ninscription_language:\nshape:rectangular\nmaterials_name:paper (fiber product)\ntechniques_name:printing (process)\nobject_colour:multicoloured\nphysical_appearance:\\The image features a rectangular invitation card. It has a black background. \\\\Freak Scene\\\\ is stated at the top of the invitatin card in bold and in capital letters. A list of four bands are stated\nsubject_terms_1:with a specific date for each. \\\\Moods Entertainment Pub pubs music (performing arts)\nsubject_terms_2:Scotts Walk Bands (Music) Alternative rock music Bars (drinking establishments) Indie pop music\nsubject_terms_3:25 Scotts Road Rock music Musicians Pop groups\nsubject_terms_4:#01-02\ncontext_1:Singapore 228220\\\\ is stated at the bottom of the invitation card. \\\ncontext_2:bands (ensembles)\ncontext_3:Invitation cards\ncontext_4:Bands\ncontext_6:Freak Scene\ncontext_7:festivals\ncontext_8:Mar-98\ncontext_9:19980310\ncontext_10:19980331\ncontext_11:Moods Entertainment Pub\n Scotts Walk\n 25 Scotts Road\n #01-02\n Singapore 228220\ncontext_12:Not indicated\ncontext_13:Not indicated","createdDate":"20201018182635","version":0,"latest":false,"roles":[],"metadata":{"accession_no_csv":"2014-00915","Image":"","object_work_type":"invitations","title_text":"Freak scene, a music performance Invite card for Freak scene, a music performance","preference":"main alternate","title_language":"","creator_2":"Not indicated","creation_date":"1998","creation_place_original_location":"Singapore","inscriptions":"","inscription_language":"","shape":"rectangular","materials_name":"paper (fiber product)","techniques_name":"printing (process)","object_colour":"multicoloured","physical_appearance":"\"The image features a rectangular invitation card. It has a black background. \"\"Freak Scene\"\" is stated at the top of the invitatin card in bold and in capital letters. A list of four bands are stated","subject_terms_1":"with a specific date for each. \"\"Moods Entertainment Pub pubs music (performing arts)","subject_terms_2":"Scotts Walk Bands (Music) Alternative rock music Bars (drinking establishments) Indie pop music","subject_terms_3":"25 Scotts Road Rock music Musicians Pop groups","subject_terms_4":"#01-02","context_1":"Singapore 228220\"\" is stated at the bottom of the invitation card. \"","context_2":"bands (ensembles)","context_3":"Invitation cards","context_4":"Bands","context_6":"Freak Scene","context_7":"festivals","context_8":"Mar-98","context_9":"19980310","context_10":"19980331","context_11":"Moods Entertainment Pub, Scotts Walk, 25 Scotts Road, #01-02, Singapore 228220","context_12":"Not indicated","context_13":"Not indicated"},"nlpDate":"20201018182635","connectorId":0,"tags":{}}