{"id":"2014-00285-067","title":"Dog belonging to the \u0027JAG\u0027 (Justice Attorney General) branch Photography Album (donation from Anthony Robert Saint Claire)","source":"Bumblebee","path":"./Data/json/","content":"accession_no_csv:2014-00285-067\nImage:\nobject_work_type:black-and-white photographs\ntitle_text:Dog belonging to the \\u0027JAG\\u0027 (Justice Attorney General) branch Photography Album (donation from Anthony Robert Saint Claire)\npreference:main alternate\ntitle_language:\ncreator_2:Robert Arthur Polglaze\ncreator_1:Not indicated\ncreator_role:photographers\ncreation_date:1940s\ncreation_place_original_location:Singapore\ninscriptions:\ninscription_language:\nshape:rectangular\nmaterials_name:paper (fiber product)\ntechniques_name:printing (process) photographic processes\nobject_colour:grey monochrome\nphysical_appearance:The image shows a black-and-white photograph. It is rectangular and it features a dog. The dog is sitting down on a grass field. It has dropped ears and droopy eyes. The arm of a person can be seen as the dog is being held. The background of the photograph shows a part of a building as well.\nsubject_terms_1:animal portraits Canis (genus)\nsubject_terms_2:Black-and-white photography Portrait photography Dogs\nsubject_terms_3:Portrait photography\nsgcool_label_text:Not indicated","createdDate":"20201119143405","version":0,"latest":false,"roles":[],"metadata":{"accession_no_csv":"2014-00285-067","Image":"","object_work_type":"black-and-white photographs","title_text":"Dog belonging to the \u0027JAG\u0027 (Justice Attorney General) branch Photography Album (donation from Anthony Robert Saint Claire)","preference":"main alternate","title_language":"","creator_2":"Robert Arthur Polglaze","creator_1":"Not indicated","creator_role":"photographers","creation_date":"1940s","creation_place_original_location":"Singapore","inscriptions":"","inscription_language":"","shape":"rectangular","materials_name":"paper (fiber product)","techniques_name":"printing (process) photographic processes","object_colour":"grey monochrome","physical_appearance":"The image shows a black-and-white photograph. It is rectangular and it features a dog. The dog is sitting down on a grass field. It has dropped ears and droopy eyes. The arm of a person can be seen as the dog is being held. The background of the photograph shows a part of a building as well.","subject_terms_1":"animal portraits Canis (genus)","subject_terms_2":"Black-and-white photography Portrait photography Dogs","subject_terms_3":"Portrait photography","sgcool_label_text":"Not indicated"},"nlpDate":"20201119143405","connectorId":0,"tags":{}}