{
  "id": "2014-00367",
  "title": "Programme for the Far East Air Force Boxing Championships Far East Air Force Boxing Championships and advertisment for Pye radios \u0026 radiograms",
  "source": "Bumblebee",
  "path": "./Data/json/",
  "content": "\n  accession_no_csv: 2014-00367\n\n  Image: \n\n  object_work_type: programmes (documents) promotional materials\n\n  title_text: Programme for the Far East Air Force Boxing Championships Far East Air Force Boxing Championships and advertisment for Pye radios \\u0026 radiograms\n\n  preference: main alternate\n\n  title_language: \n\n  creator_2: Not indicated\n\n  creator_1: Not indicated\n\n  creation_date: 1953\n\n  creation_place_original_location: Singapore\n\n  inscriptions: \n\n  inscription_language: \n\n  shape: rectangular\n\n  materials_name: paper (fiber product)\n\n  techniques_name: printing (process)\n\n  object_colour: multicoloured\n\n  physical_appearance: \\The image shows a programme outline of a boxing tournament. \\\\Far East Air Force (Team and Individual) Boxing Championships 1952 - 53\\\\ is the title of the programme\n\n  subject_terms_1: advertisements radio (telecommunication system) boxing air forces companies stated directly below the crest. The venue\n\n  subject_terms_2: Military sports Great Britain. Royal Air Force Radio Receivers and reception date Pye (Firm) Promotional materials Boxing Tournaments\n\n  subject_terms_3: and organizer of the championships are stated as well. Words are written at the top and the sides of the programme Great Britain. Royal Air Force Business enterprises Media and advertising Boxing Tournaments\n\n  subject_terms_4: such as \\\\Hong Kong Boxing Team 1953\\\\. Below the programme is an advertisement by \\\\Pye Radios \\u0026 Radiograms\\\\. The distributor and its addresses in its Singapore and Malaysia branches are listed as well.\\\n\n  context_1: tournaments\n\n  context_2: Programmes\n\n  context_3: Boxing\n\n  context_5: The programme states that the boxing championships was held at the Royal Air Force Station\n Changi on 12th of Match 1953\n Thursday\n\n  context_6: tournaments\n\n  context_7: 19530312\n\n  context_8: 19530312\n\n  context_9: 19530312\n\n  context_10: Royal Air Force Station\n Changi\n",
  "createdDate": "20201125084545",
  "version": 0,
  "latest": false,
  "roles": [],
  "metadata": {
    "accession_no_csv": "2014-00367",
    "Image": "",
    "object_work_type": "programmes (documents) promotional materials",
    "title_text": "Programme for the Far East Air Force Boxing Championships Far East Air Force Boxing Championships and advertisment for Pye radios \u0026 radiograms",
    "preference": "main alternate",
    "title_language": "",
    "creator_2": "Not indicated",
    "creator_1": "Not indicated",
    "creation_date": "1953",
    "creation_place_original_location": "Singapore",
    "inscriptions": "",
    "inscription_language": "",
    "shape": "rectangular",
    "materials_name": "paper (fiber product)",
    "techniques_name": "printing (process)",
    "object_colour": "multicoloured",
    "physical_appearance": "\"The image shows a programme outline of a boxing tournament. \"\"Far East Air Force (Team and Individual) Boxing Championships 1952 - 53\"\" is the title of the programme",
    "subject_terms_1": "advertisements radio (telecommunication system) boxing air forces companies stated directly below the crest. The venue",
    "subject_terms_2": "Military sports Great Britain. Royal Air Force Radio Receivers and reception date Pye (Firm) Promotional materials Boxing Tournaments",
    "subject_terms_3": "and organizer of the championships are stated as well. Words are written at the top and the sides of the programme Great Britain. Royal Air Force Business enterprises Media and advertising Boxing Tournaments",
    "subject_terms_4": "such as \"\"Hong Kong Boxing Team 1953\"\". Below the programme is an advertisement by \"\"Pye Radios \u0026 Radiograms\"\". The distributor and its addresses in its Singapore and Malaysia branches are listed as well.\"",
    "context_1": "tournaments",
    "context_2": "Programmes",
    "context_3": "Boxing",
    "context_5": "The programme states that the boxing championships was held at the Royal Air Force Station, Changi on 12th of Match 1953, Thursday",
    "context_6": "tournaments",
    "context_7": "19530312",
    "context_8": "19530312",
    "context_9": "19530312",
    "context_10": "Royal Air Force Station, Changi"
  },
  "nlpDate": "20201125084545",
  "connectorId": 0,
  "tags": {}
}