{"id":"2014-00285-109","title":"Group of Military Personnel Photography Album (donation from Anthony Robert Saint Claire)","source":"Bumblebee","path":"./Data/json/","content":"accession_no_csv:2014-00285-109\nImage:\nobject_work_type:black-and-white photographs\ntitle_text:Group of Military Personnel Photography Album (donation from Anthony Robert Saint Claire)\npreference:main alternate\ntitle_language:\ncreator_2:Robert Arthur Polglaze\ncreator_1:Not indicated\ncreator_role:photographers\ncreation_date:1940s\ncreation_place_original_location:Singapore\ninscriptions:\ninscription_language:\nshape:rectangular\nmaterials_name:paper (fiber product)\ntechniques_name:printing (process) photographic processes\nobject_colour:grey monochrome\nphysical_appearance:The image shows a photograph in black-and-white. It is rectangular and it features a group of military personnel. All of them are males except for a female\n who is sitting at the front row\n second from the left. There is a also a boy and a man who is not wearing a military uniform. They are standing in the last row. There are three rows of people in total\n and only the people in the front row are sitting down. The background of the photograph shows the entrance of a building\n with its door\n window\n and columns.\nsubject_terms_1:group portraits military personnel children (people by age group)\nsubject_terms_2:Black-and-white photography Portrait photography Portraits\n Group Soldiers Boys\nsubject_terms_3:Portrait photography Children\nsgcool_label_text:Not indicated","createdDate":"20201119143405","version":0,"latest":false,"roles":[],"metadata":{"accession_no_csv":"2014-00285-109","Image":"","object_work_type":"black-and-white photographs","title_text":"Group of Military Personnel Photography Album (donation from Anthony Robert Saint Claire)","preference":"main alternate","title_language":"","creator_2":"Robert Arthur Polglaze","creator_1":"Not indicated","creator_role":"photographers","creation_date":"1940s","creation_place_original_location":"Singapore","inscriptions":"","inscription_language":"","shape":"rectangular","materials_name":"paper (fiber product)","techniques_name":"printing (process) photographic processes","object_colour":"grey monochrome","physical_appearance":"The image shows a photograph in black-and-white. It is rectangular and it features a group of military personnel. All of them are males except for a female, who is sitting at the front row, second from the left. There is a also a boy and a man who is not wearing a military uniform. They are standing in the last row. There are three rows of people in total, and only the people in the front row are sitting down. The background of the photograph shows the entrance of a building, with its door, window, and columns.","subject_terms_1":"group portraits military personnel children (people by age group)","subject_terms_2":"Black-and-white photography Portrait photography Portraits, Group Soldiers Boys","subject_terms_3":"Portrait photography Children","sgcool_label_text":"Not indicated"},"nlpDate":"20201119143405","connectorId":0,"tags":{}}