{
  "id": "2014-00901",
  "title": "Photography Exhibition Poster for Photography Exhibition",
  "source": "Bumblebee",
  "path": "./Data/json/",
  "content": "\n  accession_no_csv: 2014-00901\n\n  Image: \n\n  object_work_type: posters\n\n  title_text: Photography Exhibition Poster for Photography Exhibition\n\n  preference: main alternate\n\n  title_language: \n\n  creator_2: Akiko Koga\n\n  creator_1: Not indicated\n\n  creator_role: designers\n\n  creation_date: 2005\n\n  creation_place_original_location: Singapore\n\n  inscriptions: \n\n  inscription_language: \n\n  shape: rectangular\n\n  materials_name: paper (fiber product)\n\n  techniques_name: printing (process)\n\n  object_colour: multicoloured\n\n  physical_appearance: \\The image shows a poster. It is rectangular in shape and \\\\hello girlfriend\\\\ is displayed in pink letters at the top centre of the poster. The poster consists of 10 photographs and each of these photographs feature a different woman. Some of the photographs are close-up shots which capture only the faces of the women while others feature their upper torso and the background as well. The poster was designed by \\\\fFurious\\\\. The date\n\n  subject_terms_1: venue companies colour photographs\n\n  subject_terms_2: Colour photography Business enterprises time Exhibitions\n\n  subject_terms_3: Photography Professional services Private companies and the name of the artist of this exhibition are stated on the poster.\\\n\n  subject_terms_4: exhibitions (events)\n\n  context_1: Posters\n\n  context_2: Art exhibitions\n",
  "createdDate": "20201201203309",
  "version": 0,
  "latest": false,
  "roles": [],
  "metadata": {
    "accession_no_csv": "2014-00901",
    "Image": "",
    "object_work_type": "posters",
    "title_text": "Photography Exhibition Poster for Photography Exhibition",
    "preference": "main alternate",
    "title_language": "",
    "creator_2": "Akiko Koga",
    "creator_1": "Not indicated",
    "creator_role": "designers",
    "creation_date": "2005",
    "creation_place_original_location": "Singapore",
    "inscriptions": "",
    "inscription_language": "",
    "shape": "rectangular",
    "materials_name": "paper (fiber product)",
    "techniques_name": "printing (process)",
    "object_colour": "multicoloured",
    "physical_appearance": "\"The image shows a poster. It is rectangular in shape and \"\"hello girlfriend\"\" is displayed in pink letters at the top centre of the poster. The poster consists of 10 photographs and each of these photographs feature a different woman. Some of the photographs are close-up shots which capture only the faces of the women while others feature their upper torso and the background as well. The poster was designed by \"\"fFurious\"\". The date",
    "subject_terms_1": "venue companies colour photographs",
    "subject_terms_2": "Colour photography Business enterprises time Exhibitions",
    "subject_terms_3": "Photography Professional services Private companies and the name of the artist of this exhibition are stated on the poster.\"",
    "subject_terms_4": "exhibitions (events)",
    "context_1": "Posters",
    "context_2": "Art exhibitions"
  },
  "nlpDate": "20201201203309",
  "connectorId": 0,
  "tags": {}
}