{"id":"2014-00285-045","title":"Goodwood Park Hotel, Singapore 1946 Photography Album (donation from Anthony Robert Saint Claire)","source":"Bumblebee","path":"./Data/json/","content":"accession_no_csv:2014-00285-045\nImage:\nobject_work_type:black-and-white photographs\ntitle_text:Goodwood Park Hotel\n Singapore 1946 Photography Album (donation from Anthony Robert Saint Claire)\npreference:main alternate\ntitle_language:\ncreator_2:Robert Arthur Polglaze\ncreator_1:Not indicated\ncreator_role:photographers\ncreation_date:1940s\ncreation_place_original_location:Singapore\ninscriptions:\ninscription_language:\nshape:rectangular\nmaterials_name:paper (fiber product)\ntechniques_name:printing (process) photographic processes\nobject_colour:grey monochrome\nphysical_appearance:\\The image shows a black-and-white photograph. It is rectangular and it features a building with a tower and spires. The building has a decorated façade with arch tops and \\\\War Crimes Complaints\\\\ can be seen above the entrance\nsubject_terms_1:at the centre of the photograph. The building extends as a single storey roofed block to the right of the tower national monuments\nsubject_terms_2:as well as to the left of it. There are trees surrounding the perimeter of the building. \\ Goodwood Park Hotel National monuments\nsubject_terms_3:hotels (public accommodations) Goodwood Park Hotel (Place) National monuments\nsubject_terms_4:Black-and-white photography\ncontext_1:Photography","createdDate":"20201018182635","version":0,"latest":false,"roles":[],"metadata":{"accession_no_csv":"2014-00285-045","Image":"","object_work_type":"black-and-white photographs","title_text":"Goodwood Park Hotel, Singapore 1946 Photography Album (donation from Anthony Robert Saint Claire)","preference":"main alternate","title_language":"","creator_2":"Robert Arthur Polglaze","creator_1":"Not indicated","creator_role":"photographers","creation_date":"1940s","creation_place_original_location":"Singapore","inscriptions":"","inscription_language":"","shape":"rectangular","materials_name":"paper (fiber product)","techniques_name":"printing (process) photographic processes","object_colour":"grey monochrome","physical_appearance":"\"The image shows a black-and-white photograph. It is rectangular and it features a building with a tower and spires. The building has a decorated façade with arch tops and \"\"War Crimes Complaints\"\" can be seen above the entrance","subject_terms_1":"at the centre of the photograph. The building extends as a single storey roofed block to the right of the tower national monuments","subject_terms_2":"as well as to the left of it. There are trees surrounding the perimeter of the building. \" Goodwood Park Hotel National monuments","subject_terms_3":"hotels (public accommodations) Goodwood Park Hotel (Place) National monuments","subject_terms_4":"Black-and-white photography","context_1":"Photography"},"nlpDate":"20201018182635","connectorId":0,"tags":{}}