{"id":"2014-00285-037","title":"View from Cathay Buildings Photography Album (donation from Anthony Robert Saint Claire)","source":"Bumblebee","path":"./Data/json/","content":"accession_no_csv:2014-00285-037\nImage:\nobject_work_type:black-and-white photographs\ntitle_text:View from Cathay Buildings Photography Album (donation from Anthony Robert Saint Claire)\npreference:main alternate\ntitle_language:\ncreator_2:Robert Arthur Polglaze\ncreator_1:Not indicated\ncreator_role:photographers\ncreation_date:1940s\ncreation_place_original_location:Singapore\ninscriptions:\ninscription_language:\nshape:rectangular\nmaterials_name:paper (fiber product)\ntechniques_name:printing (process) photographic processes\nobject_colour:grey monochrome\nphysical_appearance:The image shows a black-and-white photograph. It is rectangular and it features a bird\\u0027s-eye view of the cityscape. Numerous roofed buildings are located very closely to one another. They are interspersed by tall trees as well. The trees become dense at the right hand side of the photograph. A building with a dome can be seen and further into the background towards the horizon is a building with a spire.\nsubject_terms_1:cityscapes (representations) colonial cities\nsubject_terms_2:Black-and-white photography Cityscapes Colonial cities\nsubject_terms_3:Photography Cathay Building\nsgcool_label_text:Not indicated","createdDate":"20201018182635","version":0,"latest":false,"roles":[],"metadata":{"accession_no_csv":"2014-00285-037","Image":"","object_work_type":"black-and-white photographs","title_text":"View from Cathay Buildings Photography Album (donation from Anthony Robert Saint Claire)","preference":"main alternate","title_language":"","creator_2":"Robert Arthur Polglaze","creator_1":"Not indicated","creator_role":"photographers","creation_date":"1940s","creation_place_original_location":"Singapore","inscriptions":"","inscription_language":"","shape":"rectangular","materials_name":"paper (fiber product)","techniques_name":"printing (process) photographic processes","object_colour":"grey monochrome","physical_appearance":"The image shows a black-and-white photograph. It is rectangular and it features a bird\u0027s-eye view of the cityscape. Numerous roofed buildings are located very closely to one another. They are interspersed by tall trees as well. The trees become dense at the right hand side of the photograph. A building with a dome can be seen and further into the background towards the horizon is a building with a spire.","subject_terms_1":"cityscapes (representations) colonial cities","subject_terms_2":"Black-and-white photography Cityscapes Colonial cities","subject_terms_3":"Photography Cathay Building","sgcool_label_text":"Not indicated"},"nlpDate":"20201018182635","connectorId":0,"tags":{}}