{
  "id": "2014-00512-001",
  "title": "The Story of the Indian Independence Movement The Orient",
  "source": "Bumblebee",
  "path": "./Data/json/",
  "content": "\n  accession_no_csv: 2014-00512-001\n\n  Image: \n\n  object_work_type: articles clippings (information artifacts)\n\n  title_text: The Story of the Indian Independence Movement The Orient\n\n  preference: main alternate\n\n  title_language: \n\n  creator_2: Lt. K. E. Kochunni Nair\n I. N. A. (?)\n\n  creator_role: author\n\n  creation_date: 16/6/46\n\n  creation_place_original_location: India Singapore Malaya\n\n  inscriptions: \n\n  inscription_language: \n\n  shape: rectangular\n\n  materials_name: paper (fiber product)\n\n  techniques_name: printing processes\n\n  object_colour: black-and-white prints (prints on paper)\n\n  physical_appearance: This is an article from the periodical \\u0027The Orient Illustrated Weekly\\u0027 published on 16 June 1946. The title is printed at the top-center of the page. There is an excerpt of the article printed in the center.  This article features four photographs of the Indian National Army. There are several small holes in the center of the page and along the spine.\n\n  subject_terms_1: armies periodicals Indian (South Asian) nationalism\n\n  subject_terms_2: Periodicals Anti-imperialist movements Independence movements National liberation movements Provisional Government of Free India Nationalism Bose\n Subhas Chandra\n 1897-1945 self-determination\n national Singapore Indian National Army\n\n  subject_terms_3: Indian National Army Monument Site Indian National Army (Singapore) Bose\n Subhas Chandra periodicals\n",
  "createdDate": "20201125084545",
  "version": 0,
  "latest": false,
  "roles": [],
  "metadata": {
    "accession_no_csv": "2014-00512-001",
    "Image": "",
    "object_work_type": "articles clippings (information artifacts)",
    "title_text": "The Story of the Indian Independence Movement The Orient",
    "preference": "main alternate",
    "title_language": "",
    "creator_2": "Lt. K. E. Kochunni Nair, I. N. A. (?)",
    "creator_role": "author",
    "creation_date": "16/6/46",
    "creation_place_original_location": "India Singapore Malaya",
    "inscriptions": "",
    "inscription_language": "",
    "shape": "rectangular",
    "materials_name": "paper (fiber product)",
    "techniques_name": "printing processes",
    "object_colour": "black-and-white prints (prints on paper)",
    "physical_appearance": "This is an article from the periodical \u0027The Orient Illustrated Weekly\u0027 published on 16 June 1946. The title is printed at the top-center of the page. There is an excerpt of the article printed in the center.  This article features four photographs of the Indian National Army. There are several small holes in the center of the page and along the spine.",
    "subject_terms_1": "armies periodicals Indian (South Asian) nationalism",
    "subject_terms_2": "Periodicals Anti-imperialist movements Independence movements National liberation movements Provisional Government of Free India Nationalism Bose, Subhas Chandra, 1897-1945 self-determination, national Singapore Indian National Army",
    "subject_terms_3": "Indian National Army Monument Site Indian National Army (Singapore) Bose, Subhas Chandra periodicals"
  },
  "nlpDate": "20201125084545",
  "connectorId": 0,
  "tags": {}
}