{"id":"2014-00285-005","title":"Sailboats and buildings Photography Album (donation from Anthony Robert Saint Claire)","source":"Bumblebee","path":"./Data/json/","content":"accession_no_csv:2014-00285-005\nImage:\nobject_work_type:black-and-white photographs\ntitle_text:Sailboats and buildings Photography Album (donation from Anthony Robert Saint Claire)\npreference:main alternate\ntitle_language:\ncreator_2:Robert Arthur Polglaze\ncreator_1:Not indicated\ncreator_role:photographers\ncreation_date:1940s\ncreation_place_original_location:Singapore\ninscriptions:\ninscription_language:\nshape:rectangular\nmaterials_name:paper (fiber product)\ntechniques_name:printing (process) photographic processes\nobject_colour:grey monochrome\nphysical_appearance:The image shows a black-and-white photograph. It is rectangular and it features a body of water in the foreground with numerous sailboats in operation. At the background\n there are roofed buildings\n trees\n as well as a taller building with a tower. The reflection of the sailboats can be seen on the surface of the water.\nsubject_terms_1:sailboats seascapes buildings (structures)\nsubject_terms_2:Black-and-white photography Sailboats Bodies of water Buildings Marine photography\nsubject_terms_3:Photography Buildings\nsgcool_label_text:Not indicated","createdDate":"20201018182635","version":0,"latest":false,"roles":[],"metadata":{"accession_no_csv":"2014-00285-005","Image":"","object_work_type":"black-and-white photographs","title_text":"Sailboats and buildings Photography Album (donation from Anthony Robert Saint Claire)","preference":"main alternate","title_language":"","creator_2":"Robert Arthur Polglaze","creator_1":"Not indicated","creator_role":"photographers","creation_date":"1940s","creation_place_original_location":"Singapore","inscriptions":"","inscription_language":"","shape":"rectangular","materials_name":"paper (fiber product)","techniques_name":"printing (process) photographic processes","object_colour":"grey monochrome","physical_appearance":"The image shows a black-and-white photograph. It is rectangular and it features a body of water in the foreground with numerous sailboats in operation. At the background, there are roofed buildings, trees, as well as a taller building with a tower. The reflection of the sailboats can be seen on the surface of the water.","subject_terms_1":"sailboats seascapes buildings (structures)","subject_terms_2":"Black-and-white photography Sailboats Bodies of water Buildings Marine photography","subject_terms_3":"Photography Buildings","sgcool_label_text":"Not indicated"},"nlpDate":"20201018182635","connectorId":0,"tags":{}}