{
  "id": "2014-00900",
  "title": "2 promotional posters for Ffurious Promotional poster for Ffurious (2)",
  "source": "Bumblebee",
  "path": "./Data/json/",
  "content": "\n  accession_no_csv: 2014-00900\n\n  Image: \n\n  object_work_type: posters\n\n  title_text: 2 promotional posters for Ffurious Promotional poster for Ffurious (2)\n\n  preference: main alternate\n\n  title_language: \n\n  creator_2: Not indicated\n\n  creator_1: Not indicated\n\n  creation_date: Not indicated\n\n  creation_place_original_location: Singapore\n\n  inscriptions: \n\n  inscription_language: \n\n  shape: rectangular\n\n  materials_name: paper (fiber product)\n\n  techniques_name: printing (process)\n\n  object_colour: multicoloured\n\n  physical_appearance: \\The image shows a set of 2 identical promotional posters. Both are rectangular in shape. Their backgrounds are predominantly white. There is a red line that is drawn horizontally across both posters at their mid-points. The image of a food cart with a sign bearing the words \\\\Penang Laksa\\\\ is drawn. Multiple images of humans and animals are drawn as well. \\\n\n  subject_terms_1: promotional materials companies drawings (visual works)\n\n  subject_terms_2: Promotional materials Posters Business enterprises Drawing\n\n  subject_terms_3: Private companies Professional services Drawing\n\n  sgcool_label_text: fFurious was formed in 1999 by Little Ong and his friends. It is now a multi-disciplinary creative communications company with clients that include advertising agencies\n publishing companies\n small businesses to MNCs\n non-profit organisations and government bodies.\\r\\nBesides offering services in graphic/motion/interactive design\n illustration and photography\n fFurious also has non-commercial pursuits in the form of exhibitions and the development of personal art projects that has included short films\n and even a comic series.\n",
  "createdDate": "20201120223706",
  "version": 0,
  "latest": false,
  "roles": [],
  "metadata": {
    "accession_no_csv": "2014-00900",
    "Image": "",
    "object_work_type": "posters",
    "title_text": "2 promotional posters for Ffurious Promotional poster for Ffurious (2)",
    "preference": "main alternate",
    "title_language": "",
    "creator_2": "Not indicated",
    "creator_1": "Not indicated",
    "creation_date": "Not indicated",
    "creation_place_original_location": "Singapore",
    "inscriptions": "",
    "inscription_language": "",
    "shape": "rectangular",
    "materials_name": "paper (fiber product)",
    "techniques_name": "printing (process)",
    "object_colour": "multicoloured",
    "physical_appearance": "\"The image shows a set of 2 identical promotional posters. Both are rectangular in shape. Their backgrounds are predominantly white. There is a red line that is drawn horizontally across both posters at their mid-points. The image of a food cart with a sign bearing the words \"\"Penang Laksa\"\" is drawn. Multiple images of humans and animals are drawn as well. \"",
    "subject_terms_1": "promotional materials companies drawings (visual works)",
    "subject_terms_2": "Promotional materials Posters Business enterprises Drawing",
    "subject_terms_3": "Private companies Professional services Drawing",
    "sgcool_label_text": "fFurious was formed in 1999 by Little Ong and his friends. It is now a multi-disciplinary creative communications company with clients that include advertising agencies, publishing companies, small businesses to MNCs, non-profit organisations and government bodies.\r\nBesides offering services in graphic/motion/interactive design, illustration and photography, fFurious also has non-commercial pursuits in the form of exhibitions and the development of personal art projects that has included short films, and even a comic series."
  },
  "nlpDate": "20201120223706",
  "connectorId": 0,
  "tags": {}
}