{
  "id": "2014-00285-91",
  "title": "Photography Album (donation from Anthony Robert Saint Claire) Malayan Jungle Foliage",
  "source": "Bumblebee",
  "path": "./Data/json/",
  "content": "\n  accession_no_csv: 2014-00285-91\n\n  Image: \n\n  object_work_type: black-and-white photographs\n\n  title_text: Photography Album (donation from Anthony Robert Saint Claire) Malayan Jungle Foliage\n\n  preference: main alternate\n\n  title_language: \n\n  creator_2: Robert Arthur Polglaze\n\n  creator_1: Not indicated\n\n  creator_role: photographers\n\n  creation_date: 1940s\n\n  creation_place_original_location: Singapore\n\n  inscriptions: \n\n  inscription_language: \n\n  shape: rectangular\n\n  materials_name: paper (fiber product)\n\n  techniques_name: printing (process) photographic processes\n\n  object_colour: grey monochrome\n\n  physical_appearance: The image shows a black-and-white photograph. It is rectangular and it features a jungle. The foliage is dense and there are tall trees as well. There is a clearing and a pathway\n slightly to the left hand side of the photograph. The leaves of the plants located at the foreground of the photograph are lanceolate in shape.\n\n  subject_terms_1: jungles natural landscapes\n\n  subject_terms_2: Landscape photography Landscapes Jungles Black-and-white photography\n\n  subject_terms_3: Landscape photography\n\n  sgcool_label_text: Not indicated\n",
  "createdDate": "20201201203309",
  "version": 0,
  "latest": false,
  "roles": [],
  "metadata": {
    "accession_no_csv": "2014-00285-91",
    "Image": "",
    "object_work_type": "black-and-white photographs",
    "title_text": "Photography Album (donation from Anthony Robert Saint Claire) Malayan Jungle Foliage",
    "preference": "main alternate",
    "title_language": "",
    "creator_2": "Robert Arthur Polglaze",
    "creator_1": "Not indicated",
    "creator_role": "photographers",
    "creation_date": "1940s",
    "creation_place_original_location": "Singapore",
    "inscriptions": "",
    "inscription_language": "",
    "shape": "rectangular",
    "materials_name": "paper (fiber product)",
    "techniques_name": "printing (process) photographic processes",
    "object_colour": "grey monochrome",
    "physical_appearance": "The image shows a black-and-white photograph. It is rectangular and it features a jungle. The foliage is dense and there are tall trees as well. There is a clearing and a pathway, slightly to the left hand side of the photograph. The leaves of the plants located at the foreground of the photograph are lanceolate in shape.",
    "subject_terms_1": "jungles natural landscapes",
    "subject_terms_2": "Landscape photography Landscapes Jungles Black-and-white photography",
    "subject_terms_3": "Landscape photography",
    "sgcool_label_text": "Not indicated"
  },
  "nlpDate": "20201201203309",
  "connectorId": 0,
  "tags": {}
}