{"id":"2014-00285-81","title":"Military Personnel Posing with a Dog Photography Album (donation from Anthony Robert Saint Claire)","source":"Bumblebee","path":"./Data/json/","content":"accession_no_csv:2014-00285-81\nImage:\nobject_work_type:black-and-white photographs\ntitle_text:Military Personnel Posing with a Dog Photography Album (donation from Anthony Robert Saint Claire)\npreference:main alternate\ntitle_language:\ncreator_2:Robert Arthur Polglaze\ncreator_1:Not indicated\ncreator_role:photographers\ncreation_date:1940s\ncreation_place_original_location:Singapore\ninscriptions:\ninscription_language:\nshape:rectangular\nmaterials_name:paper (fiber product)\ntechniques_name:printing (process) photographic processes\nobject_colour:grey monochrome\nphysical_appearance:The image shows a black-and-white photograph. It is rectangular and it features six military personnel\n of which one is a female and the other five are males. Two of the men are squatting down while the other four stand behind. They are all clad in military uniforms and looking in the direction where the photograph was captured. The man who is squatting down on the left hand side is cradling a dog in his arms. The background of the photograph shows greenery and trees.\nsubject_terms_1:group portraits military personnel Canis (genus)\nsubject_terms_2:Black-and-white photography Portrait photography Portraits\n Group Soldiers Dogs\nsubject_terms_3:Portrait photography\nsgcool_label_text:Not indicated","createdDate":"20201018182635","version":0,"latest":false,"roles":[],"metadata":{"accession_no_csv":"2014-00285-81","Image":"","object_work_type":"black-and-white photographs","title_text":"Military Personnel Posing with a Dog Photography Album (donation from Anthony Robert Saint Claire)","preference":"main alternate","title_language":"","creator_2":"Robert Arthur Polglaze","creator_1":"Not indicated","creator_role":"photographers","creation_date":"1940s","creation_place_original_location":"Singapore","inscriptions":"","inscription_language":"","shape":"rectangular","materials_name":"paper (fiber product)","techniques_name":"printing (process) photographic processes","object_colour":"grey monochrome","physical_appearance":"The image shows a black-and-white photograph. It is rectangular and it features six military personnel, of which one is a female and the other five are males. Two of the men are squatting down while the other four stand behind. They are all clad in military uniforms and looking in the direction where the photograph was captured. The man who is squatting down on the left hand side is cradling a dog in his arms. The background of the photograph shows greenery and trees.","subject_terms_1":"group portraits military personnel Canis (genus)","subject_terms_2":"Black-and-white photography Portrait photography Portraits, Group Soldiers Dogs","subject_terms_3":"Portrait photography","sgcool_label_text":"Not indicated"},"nlpDate":"20201018182635","connectorId":0,"tags":{}}