{
  "id": "2014-00285-076",
  "title": "Photography Album (donation from Anthony Robert Saint Claire) Chinatown Singapore",
  "source": "Bumblebee",
  "path": "./Data/json/",
  "content": "\n  accession_no_csv: 2014-00285-076\n\n  Image: \n\n  object_work_type: black-and-white photographs\n\n  title_text: Photography Album (donation from Anthony Robert Saint Claire) Chinatown Singapore\n\n  preference: main alternate\n\n  title_language: \n\n  creator_2: Robert Arthur Polglaze\n\n  creator_1: Not indicated\n\n  creator_role: photographers\n\n  creation_date: 1940s\n\n  creation_place_original_location: Singapore\n\n  inscriptions: \n\n  inscription_language: \n\n  shape: rectangular\n\n  materials_name: paper (fiber product)\n\n  techniques_name: printing (process) photographic processes\n\n  object_colour: grey monochrome\n\n  physical_appearance: The image shows a black-and-white photograph. It is rectangular and it features two rows of shophouses\n one on each side of the street. Several trishaws and pedestrians can be seen on the streets. Clothes such as tee shirts\n shorts\n and trousers protrude from the second and third levels of the shophouses.\n\n  subject_terms_1: residential structures mercantile buildings land vehicles street scenes Chinatowns\n\n  subject_terms_2: Shophouses Rickshaws Black-and-white photography Chinatowns\n\n  subject_terms_3: Chinatown (Singapore) Photography\n\n  sgcool_label_text: Not indicated\n",
  "createdDate": "20201125084546",
  "version": 0,
  "latest": false,
  "roles": [],
  "metadata": {
    "accession_no_csv": "2014-00285-076",
    "Image": "",
    "object_work_type": "black-and-white photographs",
    "title_text": "Photography Album (donation from Anthony Robert Saint Claire) Chinatown Singapore",
    "preference": "main alternate",
    "title_language": "",
    "creator_2": "Robert Arthur Polglaze",
    "creator_1": "Not indicated",
    "creator_role": "photographers",
    "creation_date": "1940s",
    "creation_place_original_location": "Singapore",
    "inscriptions": "",
    "inscription_language": "",
    "shape": "rectangular",
    "materials_name": "paper (fiber product)",
    "techniques_name": "printing (process) photographic processes",
    "object_colour": "grey monochrome",
    "physical_appearance": "The image shows a black-and-white photograph. It is rectangular and it features two rows of shophouses, one on each side of the street. Several trishaws and pedestrians can be seen on the streets. Clothes such as tee shirts, shorts, and trousers protrude from the second and third levels of the shophouses.",
    "subject_terms_1": "residential structures mercantile buildings land vehicles street scenes Chinatowns",
    "subject_terms_2": "Shophouses Rickshaws Black-and-white photography Chinatowns",
    "subject_terms_3": "Chinatown (Singapore) Photography",
    "sgcool_label_text": "Not indicated"
  },
  "nlpDate": "20201125084546",
  "connectorId": 0,
  "tags": {}
}