{"id":"2014-00285-060","title":"Soldier in a room Photography Album (donation from Anthony Robert Saint Claire)","source":"Bumblebee","path":"./Data/json/","content":"accession_no_csv:2014-00285-060\nImage:\nobject_work_type:black-and-white photographs\ntitle_text:Soldier in a room Photography Album (donation from Anthony Robert Saint Claire)\npreference:main alternate\ntitle_language:\ncreator_2:Robert Arthur Polglaze\ncreator_1:Not indicated\ncreator_role:photographers\ncreation_date:1940s\ncreation_place_original_location:Singapore\ninscriptions:\ninscription_language:\nshape:rectangular\nmaterials_name:paper (fiber product)\ntechniques_name:printing (process) photographic processes\nobject_colour:grey monochrome\nphysical_appearance:The image shows a black-and-white photograph. It is rectangular and it features a soldier sitting on a bed. The soldier is facing to the left of the photograph. He is wearing only his underpants and is holding a couple of rectangular papers in his hands. Cut-outs of people and picture frames of people are pasted on the wall and placed on a drawer respectively.\nsubject_terms_1:soldiers\nsubject_terms_2:Black-and-white photography Soldiers\nsubject_terms_3:Photography\nsgcool_label_text:Not indicated","createdDate":"20201119143405","version":0,"latest":false,"roles":[],"metadata":{"accession_no_csv":"2014-00285-060","Image":"","object_work_type":"black-and-white photographs","title_text":"Soldier in a room Photography Album (donation from Anthony Robert Saint Claire)","preference":"main alternate","title_language":"","creator_2":"Robert Arthur Polglaze","creator_1":"Not indicated","creator_role":"photographers","creation_date":"1940s","creation_place_original_location":"Singapore","inscriptions":"","inscription_language":"","shape":"rectangular","materials_name":"paper (fiber product)","techniques_name":"printing (process) photographic processes","object_colour":"grey monochrome","physical_appearance":"The image shows a black-and-white photograph. It is rectangular and it features a soldier sitting on a bed. The soldier is facing to the left of the photograph. He is wearing only his underpants and is holding a couple of rectangular papers in his hands. Cut-outs of people and picture frames of people are pasted on the wall and placed on a drawer respectively.","subject_terms_1":"soldiers","subject_terms_2":"Black-and-white photography Soldiers","subject_terms_3":"Photography","sgcool_label_text":"Not indicated"},"nlpDate":"20201119143405","connectorId":0,"tags":{}}