{"id":"2014-00510","title":"The Orient Netaji\u0027s Speeches and Statements","source":"Bumblebee","path":"./Data/json/","content":"accession_no_csv:2014-00510\nImage:\nobject_work_type:clippings (information artifacts) speeches (documents)\ntitle_text:The Orient Netaji\\u0027s Speeches and Statements\npreference:alternate main\ntitle_language:\ncreation_date:4/7/46\ncreation_place_original_location:Singapore Malaya India\ninscriptions:\ninscription_language:\nshape:rectangular\nmaterials_name:paper (fiber product)\ntechniques_name:printing processes\nobject_colour:black-and-white prints (prints on paper)\nphysical_appearance:This clipping is a page from the periodical \\u0027The Orient Illustrated Weekly\\u0027 published on 7 April 1946. The title is printed on the top-left of the page. The text is a printed statement from Netaji Subhas Chandra Bose. There are four black-and-white photographs with captions. The edges of the page are torn\n especially along the right.\nsubject_terms_1:nationalism Indian (South Asian) speeches (documents) periodicals\nsubject_terms_2:National liberation movements self-determination\n national Nationalism Anti-imperialist movements Indian National Army Provisional Government of Free India Independence movements Bose\n Subhas Chandra\n 1897-1945 Burma Periodicals\nsubject_terms_3:Bose\n Subhas Chandra Indian National Army (Singapore) Indian National Army Monument Site periodicals\nsgcool_label_text:Prior to the World War II period\n Indians in Singapore and Malaya retained strong political\n sentimental and economic ties with their home country. Anti-colonial thoughts and actions\n inspired by the “call for freedom” in India\n resonated in the region too. Radio broadcasts\n newspaper reports and visits by nationalist leaders strengthened the nationalistic mood among the migrant Indian community. The Indian National Army and Netaji Subhas Chandra Bose brought to the fore this spirit of nationalism. This collection provides rare documentary evidence of the involvement of the region\\u0027s Indian community in the Indian National Army and the Indian Independence League\n the army\\u0027s fund raising arm. This is a group of war time photographs\n newspapers\n magazines and ephemera collected by the sixth president of Singapore\n Mr.S.R.Nathan.","createdDate":"20201018182635","version":0,"latest":false,"roles":[],"metadata":{"accession_no_csv":"2014-00510","Image":"","object_work_type":"clippings (information artifacts) speeches (documents)","title_text":"The Orient Netaji\u0027s Speeches and Statements","preference":"alternate main","title_language":"","creation_date":"4/7/46","creation_place_original_location":"Singapore Malaya India","inscriptions":"","inscription_language":"","shape":"rectangular","materials_name":"paper (fiber product)","techniques_name":"printing processes","object_colour":"black-and-white prints (prints on paper)","physical_appearance":"This clipping is a page from the periodical \u0027The Orient Illustrated Weekly\u0027 published on 7 April 1946. The title is printed on the top-left of the page. The text is a printed statement from Netaji Subhas Chandra Bose. There are four black-and-white photographs with captions. The edges of the page are torn, especially along the right.","subject_terms_1":"nationalism Indian (South Asian) speeches (documents) periodicals","subject_terms_2":"National liberation movements self-determination, national Nationalism Anti-imperialist movements Indian National Army Provisional Government of Free India Independence movements Bose, Subhas Chandra, 1897-1945 Burma Periodicals","subject_terms_3":"Bose, Subhas Chandra Indian National Army (Singapore) Indian National Army Monument Site periodicals","sgcool_label_text":"Prior to the World War II period, Indians in Singapore and Malaya retained strong political, sentimental and economic ties with their home country. Anti-colonial thoughts and actions, inspired by the “call for freedom” in India, resonated in the region too. Radio broadcasts, newspaper reports and visits by nationalist leaders strengthened the nationalistic mood among the migrant Indian community. The Indian National Army and Netaji Subhas Chandra Bose brought to the fore this spirit of nationalism. This collection provides rare documentary evidence of the involvement of the region\u0027s Indian community in the Indian National Army and the Indian Independence League, the army\u0027s fund raising arm. This is a group of war time photographs, newspapers, magazines and ephemera collected by the sixth president of Singapore, Mr.S.R.Nathan."},"nlpDate":"20201018182635","connectorId":0,"tags":{}}