{
  "id": "2014-00285-054",
  "title": "Photography Album (donation from Anthony Robert Saint Claire) Soldiers Looking at Things on the Ground",
  "source": "Bumblebee",
  "path": "./Data/json/",
  "content": "\n  accession_no_csv: 2014-00285-054\n\n  Image: \n\n  object_work_type: colour photographs\n\n  title_text: Photography Album (donation from Anthony Robert Saint Claire) Soldiers Looking at Things on the Ground\n\n  preference: main alternate\n\n  title_language: \n\n  creator_2: Robert Arthur Polglaze\n\n  creator_1: Not indicated\n\n  creator_role: photographers\n\n  creation_date: 1940s\n\n  creation_place_original_location: Singapore\n\n  inscriptions: \n\n  inscription_language: \n\n  shape: rectangular\n\n  materials_name: paper (fiber product)\n\n  techniques_name: printing (process) photographic processes\n\n  object_colour: grey monochrome\n\n  physical_appearance: The image shows a colour photograph. It is rectangular and it features a group of soldiers standing around and looking at some things on the ground. At the left hand side of the photograph\n a soldier wearing shorts without any upperwear is carrying the things from the ground on a metal tray and walking away from the rest. Another soldier seems to be interacting with one of the labourers who is holding a spade\n at the left hand side of the photograph. The right hand side of the photograph shows a double storey roofed building in the background.\n\n  subject_terms_1: soldiers labourers\n\n  subject_terms_2: Colour photography Blue collar workers Soldiers\n\n  subject_terms_3: Photography\n\n  sgcool_label_text: Not indicated\n",
  "createdDate": "20201125084546",
  "version": 0,
  "latest": false,
  "roles": [],
  "metadata": {
    "accession_no_csv": "2014-00285-054",
    "Image": "",
    "object_work_type": "colour photographs",
    "title_text": "Photography Album (donation from Anthony Robert Saint Claire) Soldiers Looking at Things on the Ground",
    "preference": "main alternate",
    "title_language": "",
    "creator_2": "Robert Arthur Polglaze",
    "creator_1": "Not indicated",
    "creator_role": "photographers",
    "creation_date": "1940s",
    "creation_place_original_location": "Singapore",
    "inscriptions": "",
    "inscription_language": "",
    "shape": "rectangular",
    "materials_name": "paper (fiber product)",
    "techniques_name": "printing (process) photographic processes",
    "object_colour": "grey monochrome",
    "physical_appearance": "The image shows a colour photograph. It is rectangular and it features a group of soldiers standing around and looking at some things on the ground. At the left hand side of the photograph, a soldier wearing shorts without any upperwear is carrying the things from the ground on a metal tray and walking away from the rest. Another soldier seems to be interacting with one of the labourers who is holding a spade, at the left hand side of the photograph. The right hand side of the photograph shows a double storey roofed building in the background.",
    "subject_terms_1": "soldiers labourers",
    "subject_terms_2": "Colour photography Blue collar workers Soldiers",
    "subject_terms_3": "Photography",
    "sgcool_label_text": "Not indicated"
  },
  "nlpDate": "20201125084546",
  "connectorId": 0,
  "tags": {}
}