{
  "id": "2014-00502-003 \r\n2014-00502-004",
  "title": "The Orient Jai Hind Calcutta Celebrates Netaji\u0027s Birthday",
  "source": "Bumblebee",
  "path": "./Data/json/",
  "content": "\n  accession_no_csv: 2014-00502-003 \\r\\n2014-00502-004\n\n  Image: \n\n  object_work_type: clippings (information artifacts) pages (components)\n\n  title_text: The Orient Jai Hind Calcutta Celebrates Netaji\\u0027s Birthday\n\n  preference: alternate main\n\n  title_language: \n\n  creation_date: 2/3/46\n\n  creation_place_original_location: Singapore Malaya India\n\n  inscriptions: \n\n  inscription_language: \n\n  shape: rectangular\n\n  materials_name: paper (fiber product)\n\n  techniques_name: printing processes\n\n  object_colour: black-and-white prints (prints on paper)\n\n  physical_appearance: These are two identical pages of a publication. One is more well worn than the other. This is from the periodical \\u0027The Orient Illustrated Weekly\\u0027 published on 3 February 1946. The title is printed on the right\n and includes five black-and-white photographs with a short caption at the bottom of the page. The photographs are taken on the occasion of the 50th birthday celebrations of Netaji Subhas Chandra Bose\n depicting the procession through the streets of Calcutta. The edges of the page are slightly torn.\n\n  subject_terms_1: Indian (South Asian) parades celebrations birthdays periodicals\n\n  subject_terms_2: Indian National Army Bose\n Subhas Chandra\n 1897-1945 Kolkata (India) Birthdays Periodicals\n\n  subject_terms_3: Indian National Army (Singapore) Indian National Army Monument Site Bose\n Subhas Chandra periodicals\n\n  context_1: 50th birthday celebrations of Netaji Subhas Chandra Bose\n\n  context_2: parades\n\n  context_3: 2/3/46\n\n  context_4: 1946\n\n  context_5: 1946\n\n  context_6: Kolkata (India)\n\n  context_7: I. N. A. Relief Committee\n\n  context_8: organizations (groups)\n\n  sgcool_label_text: \\Prior to the World War II period\n Indians in Singapore and Malaya retained strong political\n sentimental and economic ties with their home country. Anti-colonial thoughts and actions\n inspired by the \\\\call for freedom\\\\ in India\n",
  "createdDate": "20201120223706",
  "version": 0,
  "latest": false,
  "roles": [],
  "metadata": {
    "accession_no_csv": "2014-00502-003 \r\n2014-00502-004",
    "Image": "",
    "object_work_type": "clippings (information artifacts) pages (components)",
    "title_text": "The Orient Jai Hind Calcutta Celebrates Netaji\u0027s Birthday",
    "preference": "alternate main",
    "title_language": "",
    "creation_date": "2/3/46",
    "creation_place_original_location": "Singapore Malaya India",
    "inscriptions": "",
    "inscription_language": "",
    "shape": "rectangular",
    "materials_name": "paper (fiber product)",
    "techniques_name": "printing processes",
    "object_colour": "black-and-white prints (prints on paper)",
    "physical_appearance": "These are two identical pages of a publication. One is more well worn than the other. This is from the periodical \u0027The Orient Illustrated Weekly\u0027 published on 3 February 1946. The title is printed on the right, and includes five black-and-white photographs with a short caption at the bottom of the page. The photographs are taken on the occasion of the 50th birthday celebrations of Netaji Subhas Chandra Bose, depicting the procession through the streets of Calcutta. The edges of the page are slightly torn.",
    "subject_terms_1": "Indian (South Asian) parades celebrations birthdays periodicals",
    "subject_terms_2": "Indian National Army Bose, Subhas Chandra, 1897-1945 Kolkata (India) Birthdays Periodicals",
    "subject_terms_3": "Indian National Army (Singapore) Indian National Army Monument Site Bose, Subhas Chandra periodicals",
    "context_1": "50th birthday celebrations of Netaji Subhas Chandra Bose",
    "context_2": "parades",
    "context_3": "2/3/46",
    "context_4": "1946",
    "context_5": "1946",
    "context_6": "Kolkata (India)",
    "context_7": "I. N. A. Relief Committee",
    "context_8": "organizations (groups)",
    "sgcool_label_text": "\"Prior to the World War II period, Indians in Singapore and Malaya retained strong political, sentimental and economic ties with their home country. Anti-colonial thoughts and actions, inspired by the \"\"call for freedom\"\" in India"
  },
  "nlpDate": "20201120223706",
  "connectorId": 0,
  "tags": {}
}