{"id":"2014-00285-015","title":"Harbour Area, Singapore Photography Album (donation from Anthony Robert Saint Claire)","source":"Bumblebee","path":"./Data/json/","content":"accession_no_csv:2014-00285-015\nImage:\nobject_work_type:black-and-white photographs\ntitle_text:Harbour Area\n Singapore Photography Album (donation from Anthony Robert Saint Claire)\npreference:main alternate\ntitle_language:\ncreator_2:Robert Arthur Polglaze\ncreator_1:Not indicated\ncreator_role:photographers\ncreation_date:1940s\ncreation_place_original_location:Singapore\ninscriptions:\ninscription_language:\nshape:rectangular\nmaterials_name:paper (fiber product)\ntechniques_name:printing (process) photographic processes\nobject_colour:grey monochrome\nphysical_appearance:The image shows a black-and-white photograph. It is rectangular and it features a bird\\u0027s-eye view of Singapore Harbour and the roads adjacent to it. There are numerous boats in the harbour\n as well as bigger ships further in the background. There are a number of vehicles\n such as cars\n trucks\n and motorcycles\n which are parked or in operation.\nsubject_terms_1:harbours boats watercraft street scenes land vehicles\nsubject_terms_2:Black-and-white photography Harbours Boats and boating Bodies of water Vehicles\nsubject_terms_3:Photography Singapore Harbour Waterways\nsgcool_label_text:Not indicated","createdDate":"20201018182635","version":0,"latest":false,"roles":[],"metadata":{"accession_no_csv":"2014-00285-015","Image":"","object_work_type":"black-and-white photographs","title_text":"Harbour Area, Singapore Photography Album (donation from Anthony Robert Saint Claire)","preference":"main alternate","title_language":"","creator_2":"Robert Arthur Polglaze","creator_1":"Not indicated","creator_role":"photographers","creation_date":"1940s","creation_place_original_location":"Singapore","inscriptions":"","inscription_language":"","shape":"rectangular","materials_name":"paper (fiber product)","techniques_name":"printing (process) photographic processes","object_colour":"grey monochrome","physical_appearance":"The image shows a black-and-white photograph. It is rectangular and it features a bird\u0027s-eye view of Singapore Harbour and the roads adjacent to it. There are numerous boats in the harbour, as well as bigger ships further in the background. There are a number of vehicles, such as cars, trucks, and motorcycles, which are parked or in operation.","subject_terms_1":"harbours boats watercraft street scenes land vehicles","subject_terms_2":"Black-and-white photography Harbours Boats and boating Bodies of water Vehicles","subject_terms_3":"Photography Singapore Harbour Waterways","sgcool_label_text":"Not indicated"},"nlpDate":"20201018182635","connectorId":0,"tags":{}}