{"id":"2014-00285-87","title":"Harry Rose Clayton \u0026 Pictures of Pin-up Girls Photography Album (donation from Anthony Robert Saint Claire)","source":"Bumblebee","path":"./Data/json/","content":"accession_no_csv:2014-00285-87\nImage:\nobject_work_type:black-and-white photographs\ntitle_text:Harry Rose Clayton \\u0026 Pictures of Pin-up Girls Photography Album (donation from Anthony Robert Saint Claire)\npreference:main alternate\ntitle_language:\ncreator_2:Robert Arthur Polglaze\ncreator_1:Not indicated\ncreator_role:photographers\ncreation_date:1940s\ncreation_place_original_location:Singapore\ninscriptions:\ninscription_language:\nshape:rectangular\nmaterials_name:paper (fiber product)\ntechniques_name:printing (process) photographic processes\nobject_colour:grey monochrome\nphysical_appearance:The image shows a black-and-white photograph. It is rectangular and it features a military personnel sitting cross-legged in a room. He is holding a piece of paper in his hand and looking at it. He is wearing only his underpants and his bed is located to his right. Cut-outs of nude women and pin-up models are put up on the wall. The shirt of the military personnel hangs behind him.\nsubject_terms_1:military personnel portraits pinups\nsubject_terms_2:Black-and-white photography Portrait photography Soldiers Glamour photography\nsubject_terms_3:Portrait photography\nsgcool_label_text:Not indicated","createdDate":"20201119143405","version":0,"latest":false,"roles":[],"metadata":{"accession_no_csv":"2014-00285-87","Image":"","object_work_type":"black-and-white photographs","title_text":"Harry Rose Clayton \u0026 Pictures of Pin-up Girls Photography Album (donation from Anthony Robert Saint Claire)","preference":"main alternate","title_language":"","creator_2":"Robert Arthur Polglaze","creator_1":"Not indicated","creator_role":"photographers","creation_date":"1940s","creation_place_original_location":"Singapore","inscriptions":"","inscription_language":"","shape":"rectangular","materials_name":"paper (fiber product)","techniques_name":"printing (process) photographic processes","object_colour":"grey monochrome","physical_appearance":"The image shows a black-and-white photograph. It is rectangular and it features a military personnel sitting cross-legged in a room. He is holding a piece of paper in his hand and looking at it. He is wearing only his underpants and his bed is located to his right. Cut-outs of nude women and pin-up models are put up on the wall. The shirt of the military personnel hangs behind him.","subject_terms_1":"military personnel portraits pinups","subject_terms_2":"Black-and-white photography Portrait photography Soldiers Glamour photography","subject_terms_3":"Portrait photography","sgcool_label_text":"Not indicated"},"nlpDate":"20201119143405","connectorId":0,"tags":{}}