{"id":"2014-00364-006","title":"Details about Maurice Clare\u0027s penchant for touring as a soloist and his violin 2 Maurice Clare programmes and related newspaper cuttings","source":"Bumblebee","path":"./Data/json/","content":"accession_no_csv:2014-00364-006\nImage:\nobject_work_type:clippings (information artifacts)\ntitle_text:Details about Maurice Clare\\u0027s penchant for touring as a soloist and his violin 2 Maurice Clare programmes and related newspaper cuttings\npreference:main alternate\ntitle_language:\ncreator_2:Not indicated\ncreator_1:Not indicated\ncreation_date:1953 - 1954\ncreation_place_original_location:Singapore\ninscriptions:\ninscription_language:\nshape:rectangular\nmaterials_name:paper (fiber product)\ntechniques_name:printing (process)\nobject_colour:black-and-white (colours)\nphysical_appearance:\\The image shows a newspaper clipping that is pasted onto a purple paper. There are two punched holes at its left side. \\\\The Wandering \\u0027Fiddler\\u0027\\\\ is the headline of the newspaper clipping. Below the headline is a picture of Maurice Clare playing his violin.\\\nsubject_terms_1:newspapers violinists violins recitals\nsubject_terms_2:Newspapers Clare\n Maurice Violin Concerts\nsubject_terms_3:Violinists Daily newspapers Music\nsgcool_label_text:Not indicated","createdDate":"20201018182635","version":0,"latest":false,"roles":[],"metadata":{"accession_no_csv":"2014-00364-006","Image":"","object_work_type":"clippings (information artifacts)","title_text":"Details about Maurice Clare\u0027s penchant for touring as a soloist and his violin 2 Maurice Clare programmes and related newspaper cuttings","preference":"main alternate","title_language":"","creator_2":"Not indicated","creator_1":"Not indicated","creation_date":"1953 - 1954","creation_place_original_location":"Singapore","inscriptions":"","inscription_language":"","shape":"rectangular","materials_name":"paper (fiber product)","techniques_name":"printing (process)","object_colour":"black-and-white (colours)","physical_appearance":"\"The image shows a newspaper clipping that is pasted onto a purple paper. There are two punched holes at its left side. \"\"The Wandering \u0027Fiddler\u0027\"\" is the headline of the newspaper clipping. Below the headline is a picture of Maurice Clare playing his violin.\"","subject_terms_1":"newspapers violinists violins recitals","subject_terms_2":"Newspapers Clare, Maurice Violin Concerts","subject_terms_3":"Violinists Daily newspapers Music","sgcool_label_text":"Not indicated"},"nlpDate":"20201018182635","connectorId":0,"tags":{}}