{"id":"2014-00211","title":"Set of Three Photograph Pins","source":"Bumblebee","path":"./Data/json/","content":"accession_no_csv:2014-00211\nImage:\nobject_work_type:pins (fasteners)\ntitle_text:Set of Three Photograph Pins\npreference:main\ntitle_language:\ncreator_2:Unknown\ncreation_date:Not indicated\ncreation_place_original_location:Singapore\nstyles_periods_indexing_terms:Not indicated\ninscriptions:\ninscription_language:\nscale_type:Not indicated\nshape:circular (shape)\nmaterials_name:plastic (organic material) metal\ntechniques_name:forming (physical activity) metalworking\nobject_colour:grey (colour)\nphysical_appearance:The image shows three photograph pins. The pins are all circular in shape. The photographs on all three pins are grey in colour. The pin on the left depicts a lady\n while the other two pins show two men. The coats and tie of the two men can be seen.\nsubject_terms_1:black-and-white photographs photographs women (female humans) men (male humans) hotelkeepers\nsubject_terms_2:Black-and-white photography Women Men Hotelkeepers\nsubject_terms_3:Photography Women\nsgcool_label_text:Not indicated","createdDate":"20201018182635","version":0,"latest":false,"roles":[],"metadata":{"accession_no_csv":"2014-00211","Image":"","object_work_type":"pins (fasteners)","title_text":"Set of Three Photograph Pins","preference":"main","title_language":"","creator_2":"Unknown","creation_date":"Not indicated","creation_place_original_location":"Singapore","styles_periods_indexing_terms":"Not indicated","inscriptions":"","inscription_language":"","scale_type":"Not indicated","shape":"circular (shape)","materials_name":"plastic (organic material) metal","techniques_name":"forming (physical activity) metalworking","object_colour":"grey (colour)","physical_appearance":"The image shows three photograph pins. The pins are all circular in shape. The photographs on all three pins are grey in colour. The pin on the left depicts a lady, while the other two pins show two men. The coats and tie of the two men can be seen.","subject_terms_1":"black-and-white photographs photographs women (female humans) men (male humans) hotelkeepers","subject_terms_2":"Black-and-white photography Women Men Hotelkeepers","subject_terms_3":"Photography Women","sgcool_label_text":"Not indicated"},"nlpDate":"20201018182635","connectorId":0,"tags":{}}