{
  "id": "2014-00285-025",
  "title": "Photography Album (donation from Anthony Robert Saint Claire) Old Supreme Court Building",
  "source": "Bumblebee",
  "path": "./Data/json/",
  "content": "\n  accession_no_csv: 2014-00285-025\n\n  Image: \n\n  object_work_type: black-and-white photographs\n\n  title_text: Photography Album (donation from Anthony Robert Saint Claire) Old Supreme Court Building\n\n  preference: main alternate\n\n  title_language: \n\n  creator_2: Robert Arthur Polglaze\n\n  creator_1: Not indicated\n\n  creator_role: photographers\n\n  creation_date: 1940s\n\n  creation_place_original_location: Singapore\n\n  inscriptions: \n\n  inscription_language: \n\n  shape: rectangular\n\n  materials_name: paper (fiber product)\n\n  techniques_name: printing (process) photographic processes\n\n  object_colour: grey monochrome\n\n  physical_appearance: The image shows a black-and-white photograph. It is rectangular and it features a building with a cupola at the centre of the photograph. The allegory of the sculpture of Lady Justice is also visible below the cupola. The building consists of a portico as well as colonnades. There are numerous windows that are dome-shaped as well.\n\n  subject_terms_1: national monuments courthouses\n\n  subject_terms_2: National monuments Appellate courts Black-and-white photography\n\n  subject_terms_3: Photography National monuments Former Supreme Court (Singapore)\n\n  sgcool_label_text: Not indicated\n",
  "createdDate": "20201201203309",
  "version": 0,
  "latest": false,
  "roles": [],
  "metadata": {
    "accession_no_csv": "2014-00285-025",
    "Image": "",
    "object_work_type": "black-and-white photographs",
    "title_text": "Photography Album (donation from Anthony Robert Saint Claire) Old Supreme Court Building",
    "preference": "main alternate",
    "title_language": "",
    "creator_2": "Robert Arthur Polglaze",
    "creator_1": "Not indicated",
    "creator_role": "photographers",
    "creation_date": "1940s",
    "creation_place_original_location": "Singapore",
    "inscriptions": "",
    "inscription_language": "",
    "shape": "rectangular",
    "materials_name": "paper (fiber product)",
    "techniques_name": "printing (process) photographic processes",
    "object_colour": "grey monochrome",
    "physical_appearance": "The image shows a black-and-white photograph. It is rectangular and it features a building with a cupola at the centre of the photograph. The allegory of the sculpture of Lady Justice is also visible below the cupola. The building consists of a portico as well as colonnades. There are numerous windows that are dome-shaped as well.",
    "subject_terms_1": "national monuments courthouses",
    "subject_terms_2": "National monuments Appellate courts Black-and-white photography",
    "subject_terms_3": "Photography National monuments Former Supreme Court (Singapore)",
    "sgcool_label_text": "Not indicated"
  },
  "nlpDate": "20201201203309",
  "connectorId": 0,
  "tags": {}
}