{"id":"2014-00345","title":"Erasure (2)","source":"Bumblebee","path":"./Data/json/","content":"accession_no_csv:2014-00345\nImage:\nobject_work_type:photographic prints photographs\ntitle_text:Erasure (2)\npreference:main\ntitle_language:\ncreator_2:John Clang\ncreator_1:Clang\n John\ncreator_role:photographers\ncreation_date:2011\ncreation_place_original_location:Singapore\ninscriptions:\ninscription_language:\nshape:rectangular\nmaterials_name:art paper\ntechniques_name:printing (process) photographic processes erasing\nobject_colour:multicoloured\nedition_description:Artist Print 1 of 2\nphysical_appearance:The image displays a colour photograph printed on a piece of white paper. There is a white border around the perimeter of the photograph. A woman is featured in the foreground\n but with her face and back facing the direction in which the photograph was captured. She has grey hair and is wearing a blouse and carrying a handbag. The image of the woman has been rubbed out and blurred\n leaving a greyish figure and outline amidst the dark background.\nsubject_terms_1:colour photographs portraits elderly\nsubject_terms_2:Portrait photography Colour photography Older people\nsubject_terms_3:Portrait photography Clang\n John Visual Arts\nsgcool_label_text:Artist Statement:\\r\\nErasure revolves around my aged parents and parents-in-law in their seventies and their photographs taken during a family trip to Tokyo several years ago. The series title refers to my painstaking act of fading their images from the photographs with an ink eraser as a graphic portrayal of how life quietly empties itself from them. The resulting faint images becomes an urgent testimony of their slowly fading existence from this world\n as well as from my life. Ironically\n they are resurrected in my emotional space as reawakened memories by the very act of erasure - at once emotionally torment and intimate. Despite the joyous association of a holiday destination\n this work speaks of my own uneasy anticipation of their final destination - death.\\r\\n\\r\\nThis dread extends even to the contemplation of my own death. Their fast aging faces become a reflection and questioning of my own mortality - a question I first asked myself many years ago as a child of four: what will happen to me when my parents die? This thought haunts me till this day.\\r\\n\\r\\nAbout the artist-photographer:\\r\\nJohn Clang is a photographer and visual artist. His fascination on time\n displacement and existentialism influence his work. He held his first exhibition at 20 years old and has since participated in more than 20 solo \\u0026 group exhibitions in China\n France\n Hong Kong\n Italy\n Malaysia\n Singapore and the United States. In 2010\n he became the first photographer in Singapore to receive the President\\u0027s Designer of the Year award\n which is the most prestigious design accolade in Singapore. Clang was also selected by a panel of jury from over 400 nominated entries\n as one of the 30 finalists for the 2010 Sovereign Asian Art Prize.\\r\\n","createdDate":"20201018182635","version":0,"latest":false,"roles":[],"metadata":{"accession_no_csv":"2014-00345","Image":"","object_work_type":"photographic prints photographs","title_text":"Erasure (2)","preference":"main","title_language":"","creator_2":"John Clang","creator_1":"Clang, John","creator_role":"photographers","creation_date":"2011","creation_place_original_location":"Singapore","inscriptions":"","inscription_language":"","shape":"rectangular","materials_name":"art paper","techniques_name":"printing (process) photographic processes erasing","object_colour":"multicoloured","edition_description":"Artist Print 1 of 2","physical_appearance":"The image displays a colour photograph printed on a piece of white paper. There is a white border around the perimeter of the photograph. A woman is featured in the foreground, but with her face and back facing the direction in which the photograph was captured. She has grey hair and is wearing a blouse and carrying a handbag. The image of the woman has been rubbed out and blurred, leaving a greyish figure and outline amidst the dark background.","subject_terms_1":"colour photographs portraits elderly","subject_terms_2":"Portrait photography Colour photography Older people","subject_terms_3":"Portrait photography Clang, John Visual Arts","sgcool_label_text":"Artist Statement:\r\nErasure revolves around my aged parents and parents-in-law in their seventies and their photographs taken during a family trip to Tokyo several years ago. The series title refers to my painstaking act of fading their images from the photographs with an ink eraser as a graphic portrayal of how life quietly empties itself from them. The resulting faint images becomes an urgent testimony of their slowly fading existence from this world, as well as from my life. Ironically, they are resurrected in my emotional space as reawakened memories by the very act of erasure - at once emotionally torment and intimate. Despite the joyous association of a holiday destination, this work speaks of my own uneasy anticipation of their final destination - death.\r\n\r\nThis dread extends even to the contemplation of my own death. Their fast aging faces become a reflection and questioning of my own mortality - a question I first asked myself many years ago as a child of four: what will happen to me when my parents die? This thought haunts me till this day.\r\n\r\nAbout the artist-photographer:\r\nJohn Clang is a photographer and visual artist. His fascination on time, displacement and existentialism influence his work. He held his first exhibition at 20 years old and has since participated in more than 20 solo \u0026 group exhibitions in China, France, Hong Kong, Italy, Malaysia, Singapore and the United States. In 2010, he became the first photographer in Singapore to receive the President\u0027s Designer of the Year award, which is the most prestigious design accolade in Singapore. Clang was also selected by a panel of jury from over 400 nominated entries, as one of the 30 finalists for the 2010 Sovereign Asian Art Prize.\r\n"},"nlpDate":"20201018182635","connectorId":0,"tags":{}}