{"id":"2014-00285-059","title":"Soldier in a military truck Photography Album (donation from Anthony Robert Saint Claire)","source":"Bumblebee","path":"./Data/json/","content":"accession_no_csv:2014-00285-059\nImage:\nobject_work_type:black-and-white photographs\ntitle_text:Soldier in a military truck Photography Album (donation from Anthony Robert Saint Claire)\npreference:main alternate\ntitle_language:\ncreator_2:Robert Arthur Polglaze\ncreator_1:Not indicated\ncreator_role:photographers\ncreation_date:1940s\ncreation_place_original_location:Singapore\ninscriptions:\ninscription_language:\nshape:rectangular\nmaterials_name:paper (fiber product)\ntechniques_name:printing (process) photographic processes\nobject_colour:grey monochrome\nphysical_appearance:\\The image shows a black-and-white photograph. It is rectangular and it features a soldier posing and looking in the direction where the photograph was captured. The soldier is sitting in the driver\\u0027s seat of a military truck and only his head\n shoulders\n and hands on the steering wheel are visible. \\\\Z4933\nsubject_terms_1:309\\\\ is stated on the exterior of the door of the military truck.  \\ portraits military vehicles trucks\nsubject_terms_2:soldiers Portrait photography Soldiers Vehicles\n Military Trucks\nsubject_terms_3:Black-and-white photography\nsubject_terms_4:Portrait photography","createdDate":"20201119143405","version":0,"latest":false,"roles":[],"metadata":{"accession_no_csv":"2014-00285-059","Image":"","object_work_type":"black-and-white photographs","title_text":"Soldier in a military truck Photography Album (donation from Anthony Robert Saint Claire)","preference":"main alternate","title_language":"","creator_2":"Robert Arthur Polglaze","creator_1":"Not indicated","creator_role":"photographers","creation_date":"1940s","creation_place_original_location":"Singapore","inscriptions":"","inscription_language":"","shape":"rectangular","materials_name":"paper (fiber product)","techniques_name":"printing (process) photographic processes","object_colour":"grey monochrome","physical_appearance":"\"The image shows a black-and-white photograph. It is rectangular and it features a soldier posing and looking in the direction where the photograph was captured. The soldier is sitting in the driver\u0027s seat of a military truck and only his head, shoulders, and hands on the steering wheel are visible. \"\"Z4933","subject_terms_1":"309\"\" is stated on the exterior of the door of the military truck.  \" portraits military vehicles trucks","subject_terms_2":"soldiers Portrait photography Soldiers Vehicles, Military Trucks","subject_terms_3":"Black-and-white photography","subject_terms_4":"Portrait photography"},"nlpDate":"20201119143405","connectorId":0,"tags":{}}