{
  "id": "2014-00499-002",
  "title": "The Flag of Freedom The Orient Weekly",
  "source": "Bumblebee",
  "path": "./Data/json/",
  "content": "\n  accession_no_csv: 2014-00499-002\n\n  Image: \n\n  object_work_type: clippings (information artifacts) pages (components)\n\n  title_text: The Flag of Freedom The Orient Weekly\n\n  preference: main alternate\n\n  title_language: \n\n  creation_date: 24/3/46\n\n  creation_place_original_location: India Singapore Malaya\n\n  inscriptions: \n\n  inscription_language: \n\n  shape: rectangular\n\n  materials_name: paper (fiber product)\n\n  techniques_name: printing processes\n\n  object_colour: multicoloured\n\n  physical_appearance: This is a clipping from the periodical publication \\u0027The Orient Illustrated Weekly.\\u0027 This page features the tricoloured flag of India of India Saffron\n white and green in the center. It is titled \\u0027The Flag of Freedom.\\u0027 At the bottom of the clipping\n the text reads three four-lined poems that calls for freedom of the nation. The edges of the page are slightly torn.\n\n  subject_terms_1: flags periodicals Indian (South Asian) nationalism\n\n  subject_terms_2: Periodicals Anti-imperialist movements Nationalism self-determination\n national Indian National Army Flags\n\n  subject_terms_3: Indian National Army Monument Site Indian National Army (Singapore) periodicals\n\n  sgcool_label_text: \\Prior to the World War II period\n Indians in Singapore and Malaya retained strong political\n sentimental and economic ties with their home country. Anti-colonial thoughts and actions\n inspired by the \\\\call for freedom\\\\ in India\n",
  "createdDate": "20201125084545",
  "version": 0,
  "latest": false,
  "roles": [],
  "metadata": {
    "accession_no_csv": "2014-00499-002",
    "Image": "",
    "object_work_type": "clippings (information artifacts) pages (components)",
    "title_text": "The Flag of Freedom The Orient Weekly",
    "preference": "main alternate",
    "title_language": "",
    "creation_date": "24/3/46",
    "creation_place_original_location": "India Singapore Malaya",
    "inscriptions": "",
    "inscription_language": "",
    "shape": "rectangular",
    "materials_name": "paper (fiber product)",
    "techniques_name": "printing processes",
    "object_colour": "multicoloured",
    "physical_appearance": "This is a clipping from the periodical publication \u0027The Orient Illustrated Weekly.\u0027 This page features the tricoloured flag of India of India Saffron, white and green in the center. It is titled \u0027The Flag of Freedom.\u0027 At the bottom of the clipping, the text reads three four-lined poems that calls for freedom of the nation. The edges of the page are slightly torn.",
    "subject_terms_1": "flags periodicals Indian (South Asian) nationalism",
    "subject_terms_2": "Periodicals Anti-imperialist movements Nationalism self-determination, national Indian National Army Flags",
    "subject_terms_3": "Indian National Army Monument Site Indian National Army (Singapore) periodicals",
    "sgcool_label_text": "\"Prior to the World War II period, Indians in Singapore and Malaya retained strong political, sentimental and economic ties with their home country. Anti-colonial thoughts and actions, inspired by the \"\"call for freedom\"\" in India"
  },
  "nlpDate": "20201125084545",
  "connectorId": 0,
  "tags": {}
}