{
  "id": "2014-00913",
  "title": "Brochure for Video Performance hosted by Singapore Art Museum Video Performance hosted by Singapore Art Museum",
  "source": "Bumblebee",
  "path": "./Data/json/",
  "content": "\n  accession_no_csv: 2014-00913\n\n  Image: \n\n  object_work_type: brochures\n\n  title_text: Brochure for Video Performance hosted by Singapore Art Museum Video Performance hosted by Singapore Art Museum\n\n  preference: main alternate\n\n  title_language: \n\n  creator_2: Not indicated\n\n  creation_date: No year\n\n  creation_place_original_location: Singapore\n\n  inscriptions: \n\n  inscription_language: \n\n  shape: rectangular\n\n  materials_name: paper (fiber product)\n\n  techniques_name: printing (process)\n\n  object_colour: black-and-white (colours)\n\n  physical_appearance: \\The image shows a rectangular brochure. It is has a white border and an interior black cover. \\\\Videoperformance 01 A Selection by The UnifiedField\\\\ is displayed on the brochure. \\\n\n  subject_terms_1: video art performance art\n\n  subject_terms_2: Brochures Performance art Video art\n\n  subject_terms_3: Arts events Video artists\n\n  context_7: Singapore Art Museum\n\n  context_8: Hosts\n\n  sgcool_label_text: The brochure was produced for a videoperformance hosted by the Singapore Art Museum\n",
  "createdDate": "20201201203309",
  "version": 0,
  "latest": false,
  "roles": [],
  "metadata": {
    "accession_no_csv": "2014-00913",
    "Image": "",
    "object_work_type": "brochures",
    "title_text": "Brochure for Video Performance hosted by Singapore Art Museum Video Performance hosted by Singapore Art Museum",
    "preference": "main alternate",
    "title_language": "",
    "creator_2": "Not indicated",
    "creation_date": "No year",
    "creation_place_original_location": "Singapore",
    "inscriptions": "",
    "inscription_language": "",
    "shape": "rectangular",
    "materials_name": "paper (fiber product)",
    "techniques_name": "printing (process)",
    "object_colour": "black-and-white (colours)",
    "physical_appearance": "\"The image shows a rectangular brochure. It is has a white border and an interior black cover. \"\"Videoperformance 01 A Selection by The UnifiedField\"\" is displayed on the brochure. \"",
    "subject_terms_1": "video art performance art",
    "subject_terms_2": "Brochures Performance art Video art",
    "subject_terms_3": "Arts events Video artists",
    "context_7": "Singapore Art Museum",
    "context_8": "Hosts",
    "sgcool_label_text": "The brochure was produced for a videoperformance hosted by the Singapore Art Museum"
  },
  "nlpDate": "20201201203309",
  "connectorId": 0,
  "tags": {}
}