{"id":"2014-00285-055","title":"Two-way Road Photography Album (donation from Anthony Robert Saint Claire)","source":"Bumblebee","path":"./Data/json/","content":"accession_no_csv:2014-00285-055\nImage:\nobject_work_type:black-and-white photographs\ntitle_text:Two-way Road Photography Album (donation from Anthony Robert Saint Claire)\npreference:main alternate\ntitle_language:\ncreator_2:Robert Arthur Polglaze\ncreator_1:Not indicated\ncreator_role:photographers\ncreation_date:1940s\ncreation_place_original_location:Singapore\ninscriptions:\ninscription_language:\nshape:rectangular\nmaterials_name:paper (fiber product)\ntechniques_name:printing (process) photographic processes\nobject_colour:grey monochrome\nphysical_appearance:\\The image shows a black-and-white photograph. It is rectangular and it features a two-way road. \\\\Slow\nsubject_terms_1:Keep Left Over Bridge\\\\ is stated on the sign that is placed on the road divider. A car can be seen on the right hand side of the photograph on one of the lanes. The lane on the left hand side has no vehicles on it. The distant background shows greenery and trees. \\ traffic signs\nsubject_terms_2:roads Roads Traffic signs and signals\nsubject_terms_3:Black-and-white photography\nsubject_terms_4:Photography","createdDate":"20201119143405","version":0,"latest":false,"roles":[],"metadata":{"accession_no_csv":"2014-00285-055","Image":"","object_work_type":"black-and-white photographs","title_text":"Two-way Road Photography Album (donation from Anthony Robert Saint Claire)","preference":"main alternate","title_language":"","creator_2":"Robert Arthur Polglaze","creator_1":"Not indicated","creator_role":"photographers","creation_date":"1940s","creation_place_original_location":"Singapore","inscriptions":"","inscription_language":"","shape":"rectangular","materials_name":"paper (fiber product)","techniques_name":"printing (process) photographic processes","object_colour":"grey monochrome","physical_appearance":"\"The image shows a black-and-white photograph. It is rectangular and it features a two-way road. \"\"Slow","subject_terms_1":"Keep Left Over Bridge\"\" is stated on the sign that is placed on the road divider. A car can be seen on the right hand side of the photograph on one of the lanes. The lane on the left hand side has no vehicles on it. The distant background shows greenery and trees. \" traffic signs","subject_terms_2":"roads Roads Traffic signs and signals","subject_terms_3":"Black-and-white photography","subject_terms_4":"Photography"},"nlpDate":"20201119143405","connectorId":0,"tags":{}}