{"id":"2014-00285-10","title":"Malacca Municipal Photography Album (donation from Anthony Robert Saint Claire)","source":"Bumblebee","path":"./Data/json/","content":"accession_no_csv:2014-00285-10\nImage:\nobject_work_type:black-and-white photographs\ntitle_text:Malacca Municipal Photography Album (donation from Anthony Robert Saint Claire)\npreference:main alternate\ntitle_language:\ncreator_2:Robert Arthur Polglaze\ncreator_1:Not indicated\ncreator_role:photographers\ncreation_date:1940s\ncreation_place_original_location:Singapore\ninscriptions:\ninscription_language:\nshape:rectangular\nmaterials_name:paper (fiber product)\ntechniques_name:printing (process) photographic processes\nobject_colour:grey monochrome\nphysical_appearance:The image shows a black-and-white photograph. It is rectangular and it features a tower with a dome at the dome-shaped top and a clock just below it. To the right of the tower\n there is a double storey roofed building with numerous windows. This building and the tower are separated by a road. A couple of people can be seen walking on the pavements.\nsubject_terms_1:buildings (structures) towers (single built works)\nsubject_terms_2:Black-and-white photography Buildings Towers\nsubject_terms_3:Photography Buildings\nsgcool_label_text:Not indicated","createdDate":"20201018182635","version":0,"latest":false,"roles":[],"metadata":{"accession_no_csv":"2014-00285-10","Image":"","object_work_type":"black-and-white photographs","title_text":"Malacca Municipal Photography Album (donation from Anthony Robert Saint Claire)","preference":"main alternate","title_language":"","creator_2":"Robert Arthur Polglaze","creator_1":"Not indicated","creator_role":"photographers","creation_date":"1940s","creation_place_original_location":"Singapore","inscriptions":"","inscription_language":"","shape":"rectangular","materials_name":"paper (fiber product)","techniques_name":"printing (process) photographic processes","object_colour":"grey monochrome","physical_appearance":"The image shows a black-and-white photograph. It is rectangular and it features a tower with a dome at the dome-shaped top and a clock just below it. To the right of the tower, there is a double storey roofed building with numerous windows. This building and the tower are separated by a road. A couple of people can be seen walking on the pavements.","subject_terms_1":"buildings (structures) towers (single built works)","subject_terms_2":"Black-and-white photography Buildings Towers","subject_terms_3":"Photography Buildings","sgcool_label_text":"Not indicated"},"nlpDate":"20201018182635","connectorId":0,"tags":{}}