{
  "id": "2014-00285-071",
  "title": "Photography Album (donation from Anthony Robert Saint Claire) Chinese Restaurants",
  "source": "Bumblebee",
  "path": "./Data/json/",
  "content": "\n  accession_no_csv: 2014-00285-071\n\n  Image: \n\n  object_work_type: black-and-white photographs\n\n  title_text: Photography Album (donation from Anthony Robert Saint Claire) Chinese Restaurants\n\n  preference: main alternate\n\n  title_language: \n\n  creator_2: Robert Arthur Polglaze\n\n  creator_1: Not indicated\n\n  creator_role: photographers\n\n  creation_date: 1940s\n\n  creation_place_original_location: Singapore\n\n  inscriptions: \n\n  inscription_language: \n\n  shape: rectangular\n\n  materials_name: paper (fiber product)\n\n  techniques_name: printing (process) photographic processes\n\n  object_colour: grey monochrome\n\n  physical_appearance: The image shows a black-and-white photograph. It is rectangular and it features two food stands. Behind these food stands is a large building. A couple of people can be seen sitting on the first level\n towards the left hand side of the photograph. There is an assortment of food items on display at the two food stands. The food stand to the left is unattended while the other one towards the right is being tended to by a man and a boy. A rickshaw can be seen on the extreme right hand side of the photograph.\n\n  subject_terms_1: stands (mercantile structures) food\n\n  subject_terms_2: Food Black-and-white photography\n\n  subject_terms_3: Photography\n\n  sgcool_label_text: Not indicated\n",
  "createdDate": "20201201203309",
  "version": 0,
  "latest": false,
  "roles": [],
  "metadata": {
    "accession_no_csv": "2014-00285-071",
    "Image": "",
    "object_work_type": "black-and-white photographs",
    "title_text": "Photography Album (donation from Anthony Robert Saint Claire) Chinese Restaurants",
    "preference": "main alternate",
    "title_language": "",
    "creator_2": "Robert Arthur Polglaze",
    "creator_1": "Not indicated",
    "creator_role": "photographers",
    "creation_date": "1940s",
    "creation_place_original_location": "Singapore",
    "inscriptions": "",
    "inscription_language": "",
    "shape": "rectangular",
    "materials_name": "paper (fiber product)",
    "techniques_name": "printing (process) photographic processes",
    "object_colour": "grey monochrome",
    "physical_appearance": "The image shows a black-and-white photograph. It is rectangular and it features two food stands. Behind these food stands is a large building. A couple of people can be seen sitting on the first level, towards the left hand side of the photograph. There is an assortment of food items on display at the two food stands. The food stand to the left is unattended while the other one towards the right is being tended to by a man and a boy. A rickshaw can be seen on the extreme right hand side of the photograph.",
    "subject_terms_1": "stands (mercantile structures) food",
    "subject_terms_2": "Food Black-and-white photography",
    "subject_terms_3": "Photography",
    "sgcool_label_text": "Not indicated"
  },
  "nlpDate": "20201201203309",
  "connectorId": 0,
  "tags": {}
}