{
  "id": "2014-00210",
  "title": "Three Paperweights",
  "source": "Bumblebee",
  "path": "./Data/json/",
  "content": "\n  accession_no_csv: 2014-00210\n\n  Image: \n\n  object_work_type: paperweights\n\n  title_text: Three Paperweights\n\n  preference: main\n\n  title_language: \n\n  creator_2: Not indicated\n\n  creation_date: Not indicated\n\n  creation_place_original_location: Singapore\n\n  inscriptions: \n\n  inscription_language: \n\n  shape: oval (shape)\n\n  materials_name: ceramic (material) (?) paint (coating)\n\n  techniques_name: forming (physical activity) painting (image-making)\n\n  object_colour: multicoloured\n\n  physical_appearance: The image displays three paperweights. All of them are oval in shape with a white background. Each of the paperweights has a flower painted on it. The flower painted on the paperweight in the middle is red\n while the flowers painted on the left and right paperweights are silver in colour.\n\n  subject_terms_1: flower (motif)\n\n  subject_terms_2: Motifs Paperweights\n\n  sgcool_label_text: Not indicated\n",
  "createdDate": "20201125084547",
  "version": 0,
  "latest": false,
  "roles": [],
  "metadata": {
    "accession_no_csv": "2014-00210",
    "Image": "",
    "object_work_type": "paperweights",
    "title_text": "Three Paperweights",
    "preference": "main",
    "title_language": "",
    "creator_2": "Not indicated",
    "creation_date": "Not indicated",
    "creation_place_original_location": "Singapore",
    "inscriptions": "",
    "inscription_language": "",
    "shape": "oval (shape)",
    "materials_name": "ceramic (material) (?) paint (coating)",
    "techniques_name": "forming (physical activity) painting (image-making)",
    "object_colour": "multicoloured",
    "physical_appearance": "The image displays three paperweights. All of them are oval in shape with a white background. Each of the paperweights has a flower painted on it. The flower painted on the paperweight in the middle is red, while the flowers painted on the left and right paperweights are silver in colour.",
    "subject_terms_1": "flower (motif)",
    "subject_terms_2": "Motifs Paperweights",
    "sgcool_label_text": "Not indicated"
  },
  "nlpDate": "20201125084547",
  "connectorId": 0,
  "tags": {}
}