{
  "id": "2014-00285-82",
  "title": "Building Photography Album (donation from Anthony Robert Saint Claire)",
  "source": "Bumblebee",
  "path": "./Data/json/",
  "content": "\n  accession_no_csv: 2014-00285-82\n\n  Image: \n\n  object_work_type: black-and-white photographs\n\n  title_text: Building Photography Album (donation from Anthony Robert Saint Claire)\n\n  preference: main alternate\n\n  title_language: \n\n  creator_2: Robert Arthur Polglaze\n\n  creator_1: Not indicated\n\n  creator_role: photographers\n\n  creation_date: 1940s\n\n  creation_place_original_location: Singapore\n\n  inscriptions: \n\n  inscription_language: \n\n  shape: rectangular\n\n  materials_name: paper (fiber product)\n\n  techniques_name: printing (process) photographic processes\n\n  object_colour: grey monochrome\n\n  physical_appearance: The image shows a black-and-white photograph. It is rectangular and it features double storey building on elevated ground. To the left of the photograph\n there is a stairway leading up to the building. The building has tiled pitch roofs as well as a tower at its middle. The tower has domed shaped windows near its roof.\n\n  subject_terms_1: buildings (structures)\n\n  subject_terms_2: Black-and-white photography Buildings\n\n  subject_terms_3: Photography Buildings\n\n  sgcool_label_text: Not indicated\n",
  "createdDate": "20201120223706",
  "version": 0,
  "latest": false,
  "roles": [],
  "metadata": {
    "accession_no_csv": "2014-00285-82",
    "Image": "",
    "object_work_type": "black-and-white photographs",
    "title_text": "Building Photography Album (donation from Anthony Robert Saint Claire)",
    "preference": "main alternate",
    "title_language": "",
    "creator_2": "Robert Arthur Polglaze",
    "creator_1": "Not indicated",
    "creator_role": "photographers",
    "creation_date": "1940s",
    "creation_place_original_location": "Singapore",
    "inscriptions": "",
    "inscription_language": "",
    "shape": "rectangular",
    "materials_name": "paper (fiber product)",
    "techniques_name": "printing (process) photographic processes",
    "object_colour": "grey monochrome",
    "physical_appearance": "The image shows a black-and-white photograph. It is rectangular and it features double storey building on elevated ground. To the left of the photograph, there is a stairway leading up to the building. The building has tiled pitch roofs as well as a tower at its middle. The tower has domed shaped windows near its roof.",
    "subject_terms_1": "buildings (structures)",
    "subject_terms_2": "Black-and-white photography Buildings",
    "subject_terms_3": "Photography Buildings",
    "sgcool_label_text": "Not indicated"
  },
  "nlpDate": "20201120223706",
  "connectorId": 0,
  "tags": {}
}