{
  "id": "2014-00285-106",
  "title": "Photography Album (donation from Anthony Robert Saint Claire) A group of people outside a house",
  "source": "Bumblebee",
  "path": "./Data/json/",
  "content": "\n  accession_no_csv: 2014-00285-106\n\n  Image: \n\n  object_work_type: black-and-white photographs\n\n  title_text: Photography Album (donation from Anthony Robert Saint Claire) A group of people outside a house\n\n  preference: main alternate\n\n  title_language: \n\n  creator_2: Robert Arthur Polglaze\n\n  creator_1: Not indicated\n\n  creator_role: photographers\n\n  creation_date: 1940s\n\n  creation_place_original_location: Singapore\n\n  inscriptions: \n\n  inscription_language: \n\n  shape: rectangular\n\n  materials_name: paper (fiber product)\n\n  techniques_name: printing (process) photographic processes\n\n  object_colour: grey monochrome\n\n  physical_appearance: The image shows a photograph in black-and-white. It is rectangular and it features a group of people. They are all standing\n except for an infant who is being carried\n and looking in the direction where the photograph was captured. Three children and an infant are present\n together with two ladies and three men. They are standing in front of a building\n on a grass patch.\n\n  subject_terms_1: adults children (people by age group) group portraits\n\n  subject_terms_2: Portraits\n Group Portrait photography Children and adults Black-and-white photography\n\n  subject_terms_3: Children Portrait photography\n\n  sgcool_label_text: Not indicated\n",
  "createdDate": "20201125084546",
  "version": 0,
  "latest": false,
  "roles": [],
  "metadata": {
    "accession_no_csv": "2014-00285-106",
    "Image": "",
    "object_work_type": "black-and-white photographs",
    "title_text": "Photography Album (donation from Anthony Robert Saint Claire) A group of people outside a house",
    "preference": "main alternate",
    "title_language": "",
    "creator_2": "Robert Arthur Polglaze",
    "creator_1": "Not indicated",
    "creator_role": "photographers",
    "creation_date": "1940s",
    "creation_place_original_location": "Singapore",
    "inscriptions": "",
    "inscription_language": "",
    "shape": "rectangular",
    "materials_name": "paper (fiber product)",
    "techniques_name": "printing (process) photographic processes",
    "object_colour": "grey monochrome",
    "physical_appearance": "The image shows a photograph in black-and-white. It is rectangular and it features a group of people. They are all standing, except for an infant who is being carried, and looking in the direction where the photograph was captured. Three children and an infant are present, together with two ladies and three men. They are standing in front of a building, on a grass patch.",
    "subject_terms_1": "adults children (people by age group) group portraits",
    "subject_terms_2": "Portraits, Group Portrait photography Children and adults Black-and-white photography",
    "subject_terms_3": "Children Portrait photography",
    "sgcool_label_text": "Not indicated"
  },
  "nlpDate": "20201125084546",
  "connectorId": 0,
  "tags": {}
}