{"id":"2014-00285-003","title":"Singapore River Photography Album (donation from Anthony Robert Saint Claire)","source":"Bumblebee","path":"./Data/json/","content":"accession_no_csv:2014-00285-003\nImage:\nobject_work_type:black-and-white photographs\ntitle_text:Singapore River Photography Album (donation from Anthony Robert Saint Claire)\npreference:main alternate\ntitle_language:\ncreator_2:Robert Arthur Polglaze\ncreator_1:Not indicated\ncreator_role:photographers\ncreation_date:1940s\ncreation_place_original_location:Singapore\ninscriptions:\ninscription_language:\nshape:rectangular\nmaterials_name:paper (fiber product)\ntechniques_name:printing (process) photographic processes\nobject_colour:grey monochrome\nphysical_appearance:The image shows a black-and-white photograph. It is rectangular and it features the Singpaore river\n along with several boats and rows of shophouses on the left hand side. Two human silhouettes can be seen rowing a smaller boat on the lower right hand side of the photograph. Numerous people can be seen walking on the street in between the boats and the shophouses.\nsubject_terms_1:rivers boats residential structures mercantile buildings\nsubject_terms_2:Black-and-white photography Singapore River (Singapore) Boats and boating Shophouses\nsubject_terms_3:Photography Singapore River Buildings\nsgcool_label_text:Not indicated","createdDate":"20201018182635","version":0,"latest":false,"roles":[],"metadata":{"accession_no_csv":"2014-00285-003","Image":"","object_work_type":"black-and-white photographs","title_text":"Singapore River Photography Album (donation from Anthony Robert Saint Claire)","preference":"main alternate","title_language":"","creator_2":"Robert Arthur Polglaze","creator_1":"Not indicated","creator_role":"photographers","creation_date":"1940s","creation_place_original_location":"Singapore","inscriptions":"","inscription_language":"","shape":"rectangular","materials_name":"paper (fiber product)","techniques_name":"printing (process) photographic processes","object_colour":"grey monochrome","physical_appearance":"The image shows a black-and-white photograph. It is rectangular and it features the Singpaore river, along with several boats and rows of shophouses on the left hand side. Two human silhouettes can be seen rowing a smaller boat on the lower right hand side of the photograph. Numerous people can be seen walking on the street in between the boats and the shophouses.","subject_terms_1":"rivers boats residential structures mercantile buildings","subject_terms_2":"Black-and-white photography Singapore River (Singapore) Boats and boating Shophouses","subject_terms_3":"Photography Singapore River Buildings","sgcool_label_text":"Not indicated"},"nlpDate":"20201018182635","connectorId":0,"tags":{}}