{
  "id": "2014-00109-002",
  "title": "Two Condiment Holders Condiment Holders",
  "source": "Bumblebee",
  "path": "./Data/json/",
  "content": "\n  accession_no_csv: 2014-00109-002\n\n  Image: \n\n  object_work_type: holders (containers) condiment vessels\n\n  title_text: Two Condiment Holders Condiment Holders\n\n  preference: main alternate\n\n  title_language: \n\n  creation_date: Not indicated\n\n  creation_place_original_location: Singapore\n\n  inscriptions: \n\n  inscription_language: \n\n  materials_name: metal\n\n  techniques_name: metalworking\n\n  object_colour: bronze (colour)\n\n  physical_appearance: The image shows a condiment holder. It has four circular slots and a ringed handle which has rivets running around its circumference. It is bronze in colour. Spherical stands at its base support the entire structure of the condiment.\n\n  subject_terms_1: utensils kitchenware\n\n  subject_terms_2: Kitchen utensils Raffles Hotel Containers Implements\n utensils\n etc.\n\n  subject_terms_3: Raffles Hotel\n\n  sgcool_label_text: Not indicated\n",
  "createdDate": "20201201203309",
  "version": 0,
  "latest": false,
  "roles": [],
  "metadata": {
    "accession_no_csv": "2014-00109-002",
    "Image": "",
    "object_work_type": "holders (containers) condiment vessels",
    "title_text": "Two Condiment Holders Condiment Holders",
    "preference": "main alternate",
    "title_language": "",
    "creation_date": "Not indicated",
    "creation_place_original_location": "Singapore",
    "inscriptions": "",
    "inscription_language": "",
    "materials_name": "metal",
    "techniques_name": "metalworking",
    "object_colour": "bronze (colour)",
    "physical_appearance": "The image shows a condiment holder. It has four circular slots and a ringed handle which has rivets running around its circumference. It is bronze in colour. Spherical stands at its base support the entire structure of the condiment.",
    "subject_terms_1": "utensils kitchenware",
    "subject_terms_2": "Kitchen utensils Raffles Hotel Containers Implements, utensils, etc.",
    "subject_terms_3": "Raffles Hotel",
    "sgcool_label_text": "Not indicated"
  },
  "nlpDate": "20201201203309",
  "connectorId": 0,
  "tags": {}
}