{"id":"2014-00360","title":"Travel Visa belonging to Mdm Wong Lai Tuan issued by the Chinese Consul-General in Singapore","source":"Bumblebee","path":"./Data/json/","content":"accession_no_csv:2014-00360\nImage:\nobject_work_type:visas\ntitle_text:Travel Visa belonging to Mdm Wong Lai Tuan issued by the Chinese Consul-General in Singapore\npreference:main\ntitle_language:\ncreator_2:Chinese Consul-General in Singapore Wu Paak-Shing\ncreator_1:Not indicated Not indicated\ncreator_role:creators consuls\ncreation_date:7th day of Oct 1946\ncreation_place_original_location:Singapore\ninscriptions:\ninscription_language:\nshape:rectangular\nmaterials_name:paper (fiber product)\ntechniques_name:printing (process)\nobject_colour:multicoloured\nphysical_appearance:\\The image shows a travel visa. It is rectangular in shape and \\\\Consulate General of the Republic of China Singapore\\\\ is stated at the top of the visa. Several vertical lines of Chinese characters are stated at the centre of the visa. There is a paragraph of English text below the Chinese characters. The last line states the date\nsubject_terms_1:\\\\7th day of Oct 1946\\\\. \\\\Wu Paak-Shing\\\\ is designated as the \\\\Consul-General\\\\. There are a couple of blue circular stamps with the words \\\\Consulate General of the Republic of China and Singapore\\\\ on them.\\ emigration certification\nsubject_terms_2:legal documents Visas Emigration and immigration Certification Chinese\nsubject_terms_3:Legal documents","createdDate":"20201119143405","version":0,"latest":false,"roles":[],"metadata":{"accession_no_csv":"2014-00360","Image":"","object_work_type":"visas","title_text":"Travel Visa belonging to Mdm Wong Lai Tuan issued by the Chinese Consul-General in Singapore","preference":"main","title_language":"","creator_2":"Chinese Consul-General in Singapore Wu Paak-Shing","creator_1":"Not indicated Not indicated","creator_role":"creators consuls","creation_date":"7th day of Oct 1946","creation_place_original_location":"Singapore","inscriptions":"","inscription_language":"","shape":"rectangular","materials_name":"paper (fiber product)","techniques_name":"printing (process)","object_colour":"multicoloured","physical_appearance":"\"The image shows a travel visa. It is rectangular in shape and \"\"Consulate General of the Republic of China Singapore\"\" is stated at the top of the visa. Several vertical lines of Chinese characters are stated at the centre of the visa. There is a paragraph of English text below the Chinese characters. The last line states the date","subject_terms_1":"\"\"7th day of Oct 1946\"\". \"\"Wu Paak-Shing\"\" is designated as the \"\"Consul-General\"\". There are a couple of blue circular stamps with the words \"\"Consulate General of the Republic of China and Singapore\"\" on them.\" emigration certification","subject_terms_2":"legal documents Visas Emigration and immigration Certification Chinese","subject_terms_3":"Legal documents"},"nlpDate":"20201119143405","connectorId":0,"tags":{}}