{
  "id": "2014-00285",
  "title": "Photography Album (donation from Anthony Robert Saint Claire)",
  "source": "Bumblebee",
  "path": "./Data/json/",
  "content": "\n  accession_no_csv: 2014-00285\n\n  Image: \n\n  object_work_type: documents (object genre) black-and-white photographs photograph albums colour photographs\n\n  title_text: Photography Album (donation from Anthony Robert Saint Claire)\n\n  preference: main\n\n  title_language: \n\n  creator_2: Robert Arthur Polglaze\n\n  creator_1: Not indicated\n\n  creator_role: photographers\n\n  creation_date: 1940s\n\n  creation_place_original_location: Singapore\n\n  inscriptions: \n\n  inscription_language: \n\n  shape: squares (geometric figures) rectangular\n\n  materials_name: paper (fiber product)\n\n  techniques_name: printing (process) photographic processes\n\n  object_colour: grey monochrome multicoloured\n\n  physical_appearance: \\The image displays a photograph album\n together with numerous photographs arranged and spread out into two rows. The front cover of the album is red in colour and the spine is black. There is a yellow string running through the spine. \\\\Photo album\\\\ is stated in black font on the front of the photograph album cover. The cover looks worn out at the edges. \\\n\n  subject_terms_1: residential structures Chinatowns natural landscapes national monuments photographs world wars buildings (structures) colonial cities boats prisoner-of-war camps bodies of water (natural) hotels (public accommodations) watercraft street scenes prisons (buildings) mercantile buildings land vehicles double portraits prisoners of war high-rise buildings seashores group portraits military personnel\n\n  subject_terms_2: Colour photography Cityscapes Buildings Shophouses Seashore Landscapes Photograph albums Soldiers Tall buildings Vehicles Boats and boating Landscape photography National monuments World War\n 1939 - 1945 Hotels Japan. Rikugun Bodies of water Portraits\n Group Great Britain\n Army Portrait photography Prisoner of war Capitulations\n Military Black-and-white photography Colonial cities Chinatowns\n\n  subject_terms_3: Waterways Buildings Wars Harbours Parks and gardens Singapore River Temples Rail transport (Stations) Chinatown (Singapore) Photography Landscape photography National monuments Churches Military transportation Surrender of Japan\n 1945\n\n  context_1: varies\n\n  context_2: varies\n\n  context_3: varies\n\n  context_4: varies\n\n  context_5: varies\n\n  context_6: varies\n\n  sgcool_label_text: This photo album contain various images of Singapore that were taken during Robert Arthur Polglaze\\u0027s time in Singapore during the 1940s. Polglaze signed with the Judge Advocate General\\u0027s section when was 16 years old\n and was posted to Singapore about a year later. He was posted to Singapore during the latter stages of the Japanese Occupation\n as he was present in the room of the Japanese Surrender as seen in some of the photographs of the surrender proceedings. Other photographs in the album also include scenes of the Singapore River\n Katong and Collyer Quay.\n",
  "createdDate": "20201125084547",
  "version": 0,
  "latest": false,
  "roles": [],
  "metadata": {
    "accession_no_csv": "2014-00285",
    "Image": "",
    "object_work_type": "documents (object genre) black-and-white photographs photograph albums colour photographs",
    "title_text": "Photography Album (donation from Anthony Robert Saint Claire)",
    "preference": "main",
    "title_language": "",
    "creator_2": "Robert Arthur Polglaze",
    "creator_1": "Not indicated",
    "creator_role": "photographers",
    "creation_date": "1940s",
    "creation_place_original_location": "Singapore",
    "inscriptions": "",
    "inscription_language": "",
    "shape": "squares (geometric figures) rectangular",
    "materials_name": "paper (fiber product)",
    "techniques_name": "printing (process) photographic processes",
    "object_colour": "grey monochrome multicoloured",
    "physical_appearance": "\"The image displays a photograph album, together with numerous photographs arranged and spread out into two rows. The front cover of the album is red in colour and the spine is black. There is a yellow string running through the spine. \"\"Photo album\"\" is stated in black font on the front of the photograph album cover. The cover looks worn out at the edges. \"",
    "subject_terms_1": "residential structures Chinatowns natural landscapes national monuments photographs world wars buildings (structures) colonial cities boats prisoner-of-war camps bodies of water (natural) hotels (public accommodations) watercraft street scenes prisons (buildings) mercantile buildings land vehicles double portraits prisoners of war high-rise buildings seashores group portraits military personnel",
    "subject_terms_2": "Colour photography Cityscapes Buildings Shophouses Seashore Landscapes Photograph albums Soldiers Tall buildings Vehicles Boats and boating Landscape photography National monuments World War, 1939 - 1945 Hotels Japan. Rikugun Bodies of water Portraits, Group Great Britain, Army Portrait photography Prisoner of war Capitulations, Military Black-and-white photography Colonial cities Chinatowns",
    "subject_terms_3": "Waterways Buildings Wars Harbours Parks and gardens Singapore River Temples Rail transport (Stations) Chinatown (Singapore) Photography Landscape photography National monuments Churches Military transportation Surrender of Japan, 1945",
    "context_1": "varies",
    "context_2": "varies",
    "context_3": "varies",
    "context_4": "varies",
    "context_5": "varies",
    "context_6": "varies",
    "sgcool_label_text": "This photo album contain various images of Singapore that were taken during Robert Arthur Polglaze\u0027s time in Singapore during the 1940s. Polglaze signed with the Judge Advocate General\u0027s section when was 16 years old, and was posted to Singapore about a year later. He was posted to Singapore during the latter stages of the Japanese Occupation, as he was present in the room of the Japanese Surrender as seen in some of the photographs of the surrender proceedings. Other photographs in the album also include scenes of the Singapore River, Katong and Collyer Quay."
  },
  "nlpDate": "20201125084547",
  "connectorId": 0,
  "tags": {}
}