{"id":"2014-00364-005","title":"Details about Maurice Clare\u0027s violin and concert tour 2 Maurice Clare programmes and related newspaper cuttings","source":"Bumblebee","path":"./Data/json/","content":"accession_no_csv:2014-00364-005\nImage:\nobject_work_type:clippings (information artifacts)\ntitle_text:Details about Maurice Clare\\u0027s violin and concert tour 2 Maurice Clare programmes and related newspaper cuttings\npreference:main alternate\ntitle_language:\ncreator_2:Not indicated\ncreator_1:Not indicated\ncreation_date:1953 - 1954\ncreation_place_original_location:Singapore\ninscriptions:\ninscription_language:\nshape:rectangular\nmaterials_name:paper (fiber product)\ntechniques_name:printing (process)\nobject_colour:black-and-white (colours)\nphysical_appearance:\\The image shows a newspaper clipping that is pasted onto a blue paper. There are two punched holes at its left side. \\\\A buzz almost ended his violin concert tour\\\\ is the headline of the newspaper clipping. At the bottom left hand corner of the clipping\nsubject_terms_1:an image of Maurice Clare playing the violin is featured\\ violinists violins recitals\nsubject_terms_2:newspapers Clare\n Maurice Violin Concerts\nsubject_terms_3:Newspapers Daily newspapers\nsubject_terms_4:Violinists","createdDate":"20201119143405","version":0,"latest":false,"roles":[],"metadata":{"accession_no_csv":"2014-00364-005","Image":"","object_work_type":"clippings (information artifacts)","title_text":"Details about Maurice Clare\u0027s violin and concert tour 2 Maurice Clare programmes and related newspaper cuttings","preference":"main alternate","title_language":"","creator_2":"Not indicated","creator_1":"Not indicated","creation_date":"1953 - 1954","creation_place_original_location":"Singapore","inscriptions":"","inscription_language":"","shape":"rectangular","materials_name":"paper (fiber product)","techniques_name":"printing (process)","object_colour":"black-and-white (colours)","physical_appearance":"\"The image shows a newspaper clipping that is pasted onto a blue paper. There are two punched holes at its left side. \"\"A buzz almost ended his violin concert tour\"\" is the headline of the newspaper clipping. At the bottom left hand corner of the clipping","subject_terms_1":"an image of Maurice Clare playing the violin is featured\" violinists violins recitals","subject_terms_2":"newspapers Clare, Maurice Violin Concerts","subject_terms_3":"Newspapers Daily newspapers","subject_terms_4":"Violinists"},"nlpDate":"20201119143405","connectorId":0,"tags":{}}