{
  "id": "2014-00206-014",
  "title": "Items Related to Doris Geddes World Tour of Doris Geddes",
  "source": "Bumblebee",
  "path": "./Data/json/",
  "content": "\n  accession_no_csv: 2014-00206-014\n\n  Image: \n\n  object_work_type: clippings (information artifacts)\n\n  title_text: Items Related to Doris Geddes World Tour of Doris Geddes\n\n  preference: main alternate\n\n  title_language: \n\n  creation_date: Not indicated\n\n  creation_place_original_location: Singapore\n\n  inscriptions: \n\n  inscription_language: \n\n  shape: rectangular\n\n  materials_name: paper (fiber product) printing paper\n\n  techniques_name: printing processes\n\n  object_colour: multicoloured\n\n  physical_appearance: \\The image shows a newspaper clipping. The headline\n \\\\World Tour with Wonder Fabrics\\\\\n\n  subject_terms_1: is displayed in capital letters at the left hand side of the clipping. To the right of the headline tours (journeys) couturiers (dressmakers)\n\n  subject_terms_2: Fashion designers an image of a lady in a formal dress and high heels is sitting on a couch with her legs crossed. Above the headlines and the image Tours\n\n  subject_terms_3: Fashion design a paragraph of a body of text is displayed. \\\n\n  subject_terms_4: newspapers\n\n  context_1: Newspapers\n\n  context_2: Daily newspapers\n",
  "createdDate": "20201125084547",
  "version": 0,
  "latest": false,
  "roles": [],
  "metadata": {
    "accession_no_csv": "2014-00206-014",
    "Image": "",
    "object_work_type": "clippings (information artifacts)",
    "title_text": "Items Related to Doris Geddes World Tour of Doris Geddes",
    "preference": "main alternate",
    "title_language": "",
    "creation_date": "Not indicated",
    "creation_place_original_location": "Singapore",
    "inscriptions": "",
    "inscription_language": "",
    "shape": "rectangular",
    "materials_name": "paper (fiber product) printing paper",
    "techniques_name": "printing processes",
    "object_colour": "multicoloured",
    "physical_appearance": "\"The image shows a newspaper clipping. The headline, \"\"World Tour with Wonder Fabrics\"\"",
    "subject_terms_1": "is displayed in capital letters at the left hand side of the clipping. To the right of the headline tours (journeys) couturiers (dressmakers)",
    "subject_terms_2": "Fashion designers an image of a lady in a formal dress and high heels is sitting on a couch with her legs crossed. Above the headlines and the image Tours",
    "subject_terms_3": "Fashion design a paragraph of a body of text is displayed. \"",
    "subject_terms_4": "newspapers",
    "context_1": "Newspapers",
    "context_2": "Daily newspapers"
  },
  "nlpDate": "20201125084547",
  "connectorId": 0,
  "tags": {}
}