{"id":"2014-00364","title":"2 Maurice Clare programmes and related newspaper cuttings","source":"Bumblebee","path":"./Data/json/","content":"accession_no_csv:2014-00364\nImage:\nobject_work_type:clippings (information artifacts) concert programmes\ntitle_text:2 Maurice Clare programmes and related newspaper cuttings\npreference:main\ntitle_language:\ncreator_2:Singapore Music Society Goh Soon Tioe\ncreator_1:Not indicated Goh\n Soon Tioe\n 1911-1982\ncreator_role:creators creators\ncreation_date:1953 - 1954\ncreation_place_original_location:Singapore\ninscriptions:\ninscription_language:\nshape:rectangular\nmaterials_name:paper (fiber product)\ntechniques_name:printing (process)\nobject_colour:multicoloured black-and-white (colours)\nphysical_appearance:The image contains seven sets of documents. Three of them are concert programmes of varying sizes. The other four consist of newspaper clippings that are pasted on blue or purple papers. Some of these documents contain pictures of Maurice Clare.\nsubject_terms_1:violinists recitals musicians music (performing arts) newspapers\nsubject_terms_2:Clare\n Maurice Concert programmes Concerts Violinists Musicians Art music Goh\n Soon Tioe\n 1911-1982 Newspapers\nsubject_terms_3:Musicians Music organisations Violinists Music Daily newspapers Goh\n Soon Tioe\nsgcool_label_text:These two programmes were of Maurice Clare\\u0027s violin recitals in Singapore in 1953 and 1954.The Scottish-born violinist had won critical acclaims for his performance\n and had performed in Europe\n New Zealand\n Australia\n Indonesia and Japan. When Clare came to Singapore\n he held his recitals at the War Memorial Hall at St. Andrew\\u0027s Cathedral in 1953\n and the Victoria Memorial Hall the following year in 1954.","createdDate":"20201018182635","version":0,"latest":false,"roles":[],"metadata":{"accession_no_csv":"2014-00364","Image":"","object_work_type":"clippings (information artifacts) concert programmes","title_text":"2 Maurice Clare programmes and related newspaper cuttings","preference":"main","title_language":"","creator_2":"Singapore Music Society Goh Soon Tioe","creator_1":"Not indicated Goh, Soon Tioe, 1911-1982","creator_role":"creators creators","creation_date":"1953 - 1954","creation_place_original_location":"Singapore","inscriptions":"","inscription_language":"","shape":"rectangular","materials_name":"paper (fiber product)","techniques_name":"printing (process)","object_colour":"multicoloured black-and-white (colours)","physical_appearance":"The image contains seven sets of documents. Three of them are concert programmes of varying sizes. The other four consist of newspaper clippings that are pasted on blue or purple papers. Some of these documents contain pictures of Maurice Clare.","subject_terms_1":"violinists recitals musicians music (performing arts) newspapers","subject_terms_2":"Clare, Maurice Concert programmes Concerts Violinists Musicians Art music Goh, Soon Tioe, 1911-1982 Newspapers","subject_terms_3":"Musicians Music organisations Violinists Music Daily newspapers Goh, Soon Tioe","sgcool_label_text":"These two programmes were of Maurice Clare\u0027s violin recitals in Singapore in 1953 and 1954.The Scottish-born violinist had won critical acclaims for his performance, and had performed in Europe, New Zealand, Australia, Indonesia and Japan. When Clare came to Singapore, he held his recitals at the War Memorial Hall at St. Andrew\u0027s Cathedral in 1953, and the Victoria Memorial Hall the following year in 1954."},"nlpDate":"20201018182635","connectorId":0,"tags":{}}