{
  "id": "2014-00285-042",
  "title": "Photography Album (donation from Anthony Robert Saint Claire) Top view of Kota Tinggi Waterfall",
  "source": "Bumblebee",
  "path": "./Data/json/",
  "content": "\n  accession_no_csv: 2014-00285-042\n\n  Image: \n\n  object_work_type: black-and-white photographs\n\n  title_text: Photography Album (donation from Anthony Robert Saint Claire) Top view of Kota Tinggi Waterfall\n\n  preference: main alternate\n\n  title_language: \n\n  creator_2: Robert Arthur Polglaze\n\n  creator_1: Not indicated\n\n  creator_role: photographers\n\n  creation_date: 1940s\n\n  creation_place_original_location: Singapore\n\n  inscriptions: \n\n  inscription_language: \n\n  shape: rectangular\n\n  materials_name: paper (fiber product)\n\n  techniques_name: printing (process) photographic processes\n\n  object_colour: grey monochrome\n\n  physical_appearance: The image shows a black-and-white photograph. It is rectangular and it features a waterfall. This photograph was taken at the apex of the waterfall. There are trees and greenery on either side of the waterfall\n as well as at the bottom.\n\n  subject_terms_1: waterfalls (natural bodies of water)\n\n  subject_terms_2: Waterfalls Kota Tinggi (Johor\n Malaysia) Black-and-white photography\n\n  subject_terms_3: Photography\n\n  sgcool_label_text: Not indicated\n",
  "createdDate": "20201125084546",
  "version": 0,
  "latest": false,
  "roles": [],
  "metadata": {
    "accession_no_csv": "2014-00285-042",
    "Image": "",
    "object_work_type": "black-and-white photographs",
    "title_text": "Photography Album (donation from Anthony Robert Saint Claire) Top view of Kota Tinggi Waterfall",
    "preference": "main alternate",
    "title_language": "",
    "creator_2": "Robert Arthur Polglaze",
    "creator_1": "Not indicated",
    "creator_role": "photographers",
    "creation_date": "1940s",
    "creation_place_original_location": "Singapore",
    "inscriptions": "",
    "inscription_language": "",
    "shape": "rectangular",
    "materials_name": "paper (fiber product)",
    "techniques_name": "printing (process) photographic processes",
    "object_colour": "grey monochrome",
    "physical_appearance": "The image shows a black-and-white photograph. It is rectangular and it features a waterfall. This photograph was taken at the apex of the waterfall. There are trees and greenery on either side of the waterfall, as well as at the bottom.",
    "subject_terms_1": "waterfalls (natural bodies of water)",
    "subject_terms_2": "Waterfalls Kota Tinggi (Johor, Malaysia) Black-and-white photography",
    "subject_terms_3": "Photography",
    "sgcool_label_text": "Not indicated"
  },
  "nlpDate": "20201125084546",
  "connectorId": 0,
  "tags": {}
}