{"id":"2014-00285-040","title":"Cenotaph and Harbour Photography Album (donation from Anthony Robert Saint Claire)","source":"Bumblebee","path":"./Data/json/","content":"accession_no_csv:2014-00285-040\nImage:\nobject_work_type:black-and-white photographs\ntitle_text:Cenotaph and Harbour Photography Album (donation from Anthony Robert Saint Claire)\npreference:main alternate\ntitle_language:\ncreator_2:Robert Arthur Polglaze\ncreator_1:Not indicated\ncreator_role:photographers\ncreation_date:1940s\ncreation_place_original_location:Singapore\ninscriptions:\ninscription_language:\nshape:rectangular\nmaterials_name:paper (fiber product)\ntechniques_name:printing (process) photographic processes\nobject_colour:grey monochrome\nphysical_appearance:The image shows a black-and-white photograph. It is rectangular and it features a body of water with several ships and boats on it\n which takes up about four-fifths of the photograph from the right hand side. There is a war memorial located on the land mass\n as shown at the left hand side of the photograph. It is a shaped like a tall vertical tower and there are steps leading to its base. There are numerous trees behind it\n and several roofed buildings can be seen in the background of the photograph as well.\nsubject_terms_1:harbours river memorials (monuments)\nsubject_terms_2:Black-and-white photography Singapore River (Singapore) Harbours War memorials\nsubject_terms_3:Photography Cenotaph Singapore River Harbours\nsgcool_label_text:Not indicated","createdDate":"20201119143405","version":0,"latest":false,"roles":[],"metadata":{"accession_no_csv":"2014-00285-040","Image":"","object_work_type":"black-and-white photographs","title_text":"Cenotaph and Harbour Photography Album (donation from Anthony Robert Saint Claire)","preference":"main alternate","title_language":"","creator_2":"Robert Arthur Polglaze","creator_1":"Not indicated","creator_role":"photographers","creation_date":"1940s","creation_place_original_location":"Singapore","inscriptions":"","inscription_language":"","shape":"rectangular","materials_name":"paper (fiber product)","techniques_name":"printing (process) photographic processes","object_colour":"grey monochrome","physical_appearance":"The image shows a black-and-white photograph. It is rectangular and it features a body of water with several ships and boats on it, which takes up about four-fifths of the photograph from the right hand side. There is a war memorial located on the land mass, as shown at the left hand side of the photograph. It is a shaped like a tall vertical tower and there are steps leading to its base. There are numerous trees behind it, and several roofed buildings can be seen in the background of the photograph as well.","subject_terms_1":"harbours river memorials (monuments)","subject_terms_2":"Black-and-white photography Singapore River (Singapore) Harbours War memorials","subject_terms_3":"Photography Cenotaph Singapore River Harbours","sgcool_label_text":"Not indicated"},"nlpDate":"20201119143405","connectorId":0,"tags":{}}