{"id":"2014-00285-050","title":"12 Scotts Road, Our Billett, 1946 Photography Album (donation from Anthony Robert Saint Claire)","source":"Bumblebee","path":"./Data/json/","content":"accession_no_csv:2014-00285-050\nImage:\nobject_work_type:black-and-white photographs\ntitle_text:12 Scotts Road\n Our Billett\n 1946 Photography Album (donation from Anthony Robert Saint Claire)\npreference:main alternate\ntitle_language:\ncreator_2:Robert Arthur Polglaze\ncreator_1:Not indicated\ncreator_role:photographers\ncreation_date:1940s\ncreation_place_original_location:Singapore\ninscriptions:\ninscription_language:\nshape:rectangular\nmaterials_name:paper (fiber product)\ntechniques_name:printing (process) photographic processes\nobject_colour:grey monochrome\nphysical_appearance:The image shows a black-and-white photograph. It is rectangular and it features a multi-storey roofed building in the background towards the left hand side of the photograph. The building comes with a portico and potted plants can be seen in it. The foreground of the photograph shows a garden where there are shrubs and greenery.\nsubject_terms_1:buildings (structures) residential structures gardens (open spaces)\nsubject_terms_2:Black-and-white photography Buildings Dwellings Gardens\nsubject_terms_3:Photography Buildings Parks and gardens\nsgcool_label_text:Not indicated","createdDate":"20201018182635","version":0,"latest":false,"roles":[],"metadata":{"accession_no_csv":"2014-00285-050","Image":"","object_work_type":"black-and-white photographs","title_text":"12 Scotts Road, Our Billett, 1946 Photography Album (donation from Anthony Robert Saint Claire)","preference":"main alternate","title_language":"","creator_2":"Robert Arthur Polglaze","creator_1":"Not indicated","creator_role":"photographers","creation_date":"1940s","creation_place_original_location":"Singapore","inscriptions":"","inscription_language":"","shape":"rectangular","materials_name":"paper (fiber product)","techniques_name":"printing (process) photographic processes","object_colour":"grey monochrome","physical_appearance":"The image shows a black-and-white photograph. It is rectangular and it features a multi-storey roofed building in the background towards the left hand side of the photograph. The building comes with a portico and potted plants can be seen in it. The foreground of the photograph shows a garden where there are shrubs and greenery.","subject_terms_1":"buildings (structures) residential structures gardens (open spaces)","subject_terms_2":"Black-and-white photography Buildings Dwellings Gardens","subject_terms_3":"Photography Buildings Parks and gardens","sgcool_label_text":"Not indicated"},"nlpDate":"20201018182635","connectorId":0,"tags":{}}