{
  "id": "2014-00285-046",
  "title": "JAG (Judge Advocate General) Office, Goodwood Park Hotel Singapore Photography Album (donation from Anthony Robert Saint Claire)",
  "source": "Bumblebee",
  "path": "./Data/json/",
  "content": "\n  accession_no_csv: 2014-00285-046\n\n  Image: \n\n  object_work_type: black-and-white photographs\n\n  title_text: JAG (Judge Advocate General) Office\n Goodwood Park Hotel Singapore Photography Album (donation from Anthony Robert Saint Claire)\n\n  preference: main alternate\n\n  title_language: \n\n  creator_2: Robert Arthur Polglaze\n\n  creator_1: Not indicated\n\n  creator_role: photographers\n\n  creation_date: 1940s\n\n  creation_place_original_location: Singapore\n\n  inscriptions: \n\n  inscription_language: \n\n  shape: rectangular\n\n  materials_name: paper (fiber product)\n\n  techniques_name: printing (process) photographic processes\n\n  object_colour: grey monochrome\n\n  physical_appearance: The image shows a black-and-white photograph. It is rectangular and it features a double storey roofed building. There are numerous doors on the first floor and railings on the second floor. Trees can be seen in the foreground and background of the photograph.\n\n  subject_terms_1: hotels (public accommodations) offices (work spaces)\n\n  subject_terms_2: Offices Goodwood Park Hotel Black-and-white photography\n\n  subject_terms_3: Photography Goodwood Park Hotel (Place)\n\n  sgcool_label_text: Not indicated\n",
  "createdDate": "20201201203309",
  "version": 0,
  "latest": false,
  "roles": [],
  "metadata": {
    "accession_no_csv": "2014-00285-046",
    "Image": "",
    "object_work_type": "black-and-white photographs",
    "title_text": "JAG (Judge Advocate General) Office, Goodwood Park Hotel Singapore Photography Album (donation from Anthony Robert Saint Claire)",
    "preference": "main alternate",
    "title_language": "",
    "creator_2": "Robert Arthur Polglaze",
    "creator_1": "Not indicated",
    "creator_role": "photographers",
    "creation_date": "1940s",
    "creation_place_original_location": "Singapore",
    "inscriptions": "",
    "inscription_language": "",
    "shape": "rectangular",
    "materials_name": "paper (fiber product)",
    "techniques_name": "printing (process) photographic processes",
    "object_colour": "grey monochrome",
    "physical_appearance": "The image shows a black-and-white photograph. It is rectangular and it features a double storey roofed building. There are numerous doors on the first floor and railings on the second floor. Trees can be seen in the foreground and background of the photograph.",
    "subject_terms_1": "hotels (public accommodations) offices (work spaces)",
    "subject_terms_2": "Offices Goodwood Park Hotel Black-and-white photography",
    "subject_terms_3": "Photography Goodwood Park Hotel (Place)",
    "sgcool_label_text": "Not indicated"
  },
  "nlpDate": "20201201203309",
  "connectorId": 0,
  "tags": {}
}