{
  "id": "2014-00909-006",
  "title": "Brochures and cards for performances by Theatreworks (20) - Play on earth book Play on Earth by TheatreWorks (2006)",
  "source": "Bumblebee",
  "path": "./Data/json/",
  "content": "\n  accession_no_csv: 2014-00909-006\n\n  Image: \n\n  object_work_type: artists\\u0027 books (books)\n\n  title_text: Brochures and cards for performances by Theatreworks (20) - Play on earth book Play on Earth by TheatreWorks (2006)\n\n  preference: main alternate\n\n  title_language: \n\n  creator_2: TheatreWorks (Singapore) Jeffrey Tan\n\n  creator_1: Tan\n Jeffrey\n 1968- TheatreWorks (Firm : Singapore)\n\n  creator_role: performance artists theatre directors\n\n  creation_date: 2006\n\n  creation_place_original_location: Singapore\n\n  inscriptions: \n\n  inscription_language: \n\n  shape: rectangular\n\n  materials_name: paper (fiber product)\n\n  techniques_name: printing (process)\n\n  object_colour: multicoloured\n\n  physical_appearance: \\The image shows a rectangular brochure. \\\\Play on Earth\\\\ is stated on the right hand side of the brochure. \\\\15 - 25 June 2006 72-13 (Singapore) The Guildhall (NewcastleGateshead) Teatro Paraiso\n\n  subject_terms_1: theater (discipline) time UNIP (Sao Paulo) is stated below the title. The background shows two people sitting at the same table\n\n  subject_terms_2: Time Performances on opposite sides Theatres\n\n  subject_terms_3: in a food and beverage establishment. The lady seems to be eating or drinking something while the man is looking in the distance. There are also the outlines of three white clocks to the left of the brochure title. The hands of the clock show 6.30\n\n  subject_terms_4: 4.07\n\n  context_1: and 8.05 respectively\\\n\n  context_2: performances (creative events)\n\n  context_3: Artists \\u0027 books\n\n  context_4: English theatre (Art)\n\n  context_6: Play on Earth The Guildhall (NewcastleGateshead) Teatro Paraiso\n UNIP (Sao Paulo)\n\n  context_7: British Council NewcastleGateshead: World Class Culture Philarmonia Brasileira performances (creative events)\n\n  context_8: 15 - 25 june 2006\n\n  context_9: 20060615\n\n  context_10: 20060625\n\n  context_11: 72-13 Mohammed Sultan Road\n Singapore 239007\n\n  context_12: Station House Opera\n\n  context_13: companies\n",
  "createdDate": "20201201203309",
  "version": 0,
  "latest": false,
  "roles": [],
  "metadata": {
    "accession_no_csv": "2014-00909-006",
    "Image": "",
    "object_work_type": "artists\u0027 books (books)",
    "title_text": "Brochures and cards for performances by Theatreworks (20) - Play on earth book Play on Earth by TheatreWorks (2006)",
    "preference": "main alternate",
    "title_language": "",
    "creator_2": "TheatreWorks (Singapore) Jeffrey Tan",
    "creator_1": "Tan, Jeffrey, 1968- TheatreWorks (Firm : Singapore)",
    "creator_role": "performance artists theatre directors",
    "creation_date": "2006",
    "creation_place_original_location": "Singapore",
    "inscriptions": "",
    "inscription_language": "",
    "shape": "rectangular",
    "materials_name": "paper (fiber product)",
    "techniques_name": "printing (process)",
    "object_colour": "multicoloured",
    "physical_appearance": "\"The image shows a rectangular brochure. \"\"Play on Earth\"\" is stated on the right hand side of the brochure. \"\"15 - 25 June 2006 72-13 (Singapore) The Guildhall (NewcastleGateshead) Teatro Paraiso",
    "subject_terms_1": "theater (discipline) time UNIP (Sao Paulo) is stated below the title. The background shows two people sitting at the same table",
    "subject_terms_2": "Time Performances on opposite sides Theatres",
    "subject_terms_3": "in a food and beverage establishment. The lady seems to be eating or drinking something while the man is looking in the distance. There are also the outlines of three white clocks to the left of the brochure title. The hands of the clock show 6.30",
    "subject_terms_4": "4.07",
    "context_1": "and 8.05 respectively\"",
    "context_2": "performances (creative events)",
    "context_3": "Artists \u0027 books",
    "context_4": "English theatre (Art)",
    "context_6": "Play on Earth The Guildhall (NewcastleGateshead) Teatro Paraiso, UNIP (Sao Paulo)",
    "context_7": "British Council NewcastleGateshead: World Class Culture Philarmonia Brasileira performances (creative events)",
    "context_8": "15 - 25 june 2006",
    "context_9": "20060615",
    "context_10": "20060625",
    "context_11": "72-13 Mohammed Sultan Road, Singapore 239007",
    "context_12": "Station House Opera",
    "context_13": "companies"
  },
  "nlpDate": "20201201203309",
  "connectorId": 0,
  "tags": {}
}