{"id":"2014-00362","title":"Memo from the Food Control Department Singapore addressed to Mdm Wong Lai Tuan","source":"Bumblebee","path":"./Data/json/","content":"accession_no_csv:2014-00362\nImage:\nobject_work_type:memorandums\ntitle_text:Memo from the Food Control Department Singapore addressed to Mdm Wong Lai Tuan\npreference:main\ntitle_language:\ncreator_2:Food Control Department Singapore\ncreator_1:Not indicated\ncreator_role:creators\ncreation_date:1946\ncreation_place_original_location:Singapore\ninscriptions:\ninscription_language:\nshape:rectangular\nmaterials_name:paper (fiber product)\ntechniques_name:printing (process)\nobject_colour:multicoloured\nphysical_appearance:\\The image displays a memorandum. It is rectangular in shape and there is a round purple stamp at its right side. Most of the words have already faded from the memorandum. At the top of the memo\n \\\\Food Control Dept Singapore\\\\ can be discerned. \\\\21.10.46\\\\ is stated at the right hand side of the memo. The ration card has been signed as well\nsubject_terms_1:beside the round purple stamp.\\ departments (organizational units)\nsubject_terms_2:emigration Rationing Emigration and immigration\nsubject_terms_3:Memorandums\nsubject_terms_4:1945-1955 Aftermath of war","createdDate":"20201018182635","version":0,"latest":false,"roles":[],"metadata":{"accession_no_csv":"2014-00362","Image":"","object_work_type":"memorandums","title_text":"Memo from the Food Control Department Singapore addressed to Mdm Wong Lai Tuan","preference":"main","title_language":"","creator_2":"Food Control Department Singapore","creator_1":"Not indicated","creator_role":"creators","creation_date":"1946","creation_place_original_location":"Singapore","inscriptions":"","inscription_language":"","shape":"rectangular","materials_name":"paper (fiber product)","techniques_name":"printing (process)","object_colour":"multicoloured","physical_appearance":"\"The image displays a memorandum. It is rectangular in shape and there is a round purple stamp at its right side. Most of the words have already faded from the memorandum. At the top of the memo, \"\"Food Control Dept Singapore\"\" can be discerned. \"\"21.10.46\"\" is stated at the right hand side of the memo. The ration card has been signed as well","subject_terms_1":"beside the round purple stamp.\" departments (organizational units)","subject_terms_2":"emigration Rationing Emigration and immigration","subject_terms_3":"Memorandums","subject_terms_4":"1945-1955 Aftermath of war"},"nlpDate":"20201018182635","connectorId":0,"tags":{}}