{
  "id": "2014-00334",
  "title": "Being Together (Krishnan Family / Yokohama / Teban Gardens)",
  "source": "Bumblebee",
  "path": "./Data/json/",
  "content": "\n  accession_no_csv: 2014-00334\n\n  Image: \n\n  object_work_type: photographs photographic prints\n\n  title_text: Being Together (Krishnan Family / Yokohama / Teban Gardens)\n\n  preference: main\n\n  title_language: \n\n  creator_2: John Clang\n\n  creator_1: Clang\n John\n\n  creator_role: photographers\n\n  creation_date: Not indicated\n\n  creation_place_original_location: Singapore\n\n  inscriptions: \n\n  inscription_language: \n\n  shape: rectangular\n\n  materials_name: art paper\n\n  techniques_name: printing (process) photographic processes\n\n  object_colour: multicoloured\n\n  edition_description: 1 of 3\n\n  physical_appearance: The image displays a colour photograph printed on a piece of white paper. There is a white border around the perimeter of the photograph. A family is featured and they are all standing up and looking towards the direction in which the photograph was captured. There is a total of four adults and two children whose images are projected on a screen. Their images are juxtaposed with a man\n who is standing beside a bed with an open laptop on it.\n\n  subject_terms_1: families (kinship groups) group portraits colour photographs\n\n  subject_terms_2: Colour photography Portraits\n Group Singaporeans Portrait photography Families\n\n  subject_terms_3: Clang\n John Portrait photography Visual Arts\n\n  sgcool_label_text: Being Together\n 2010 – 2012 \\r\\nby John Clang (b. 1973) \\r\\n\\r\\nArtist Statement: \\r\\nIn this series\n webcam was used to do live recording of families in Singapore. The recording was then transmitted via skype to countries where the main sitters are located and projected onto their living space. This is how families\n dis(membered) through time and space\n can be re(membered) and made whole again through the use of a third space\n a site that is able to reassemble them together within the photographic space that we call a family portrait.\\r\\n\\r\\nDrawing upon my own experiences of being separated from my family as a New York-based Singaporean\n this work documents and examines our condition of new-wave diaspora – Singaporean families of various races and ethnicities grappling with the same predicament of separation through time and space.\\r\\n\\r\\nI also want this project to document and interpret a contemporary social-historical blueprint as it happens\n allowing the future generations to reflect on it.\\r\\n\\r\\nIn addition\n this is also an extension of one of the recurring theme of my works: the fascination with the expressions of time and space and how we negotiate our human existences within these two dimensions. this work specifically addresses the phenomenon of differing time zones\n the different dimensions of our human representations\n and how we can finally coexist\n albeit in pixilated and two-dimensional forms.\\r\\n\\r\\nAbout the artist-photographer:\\r\\nJohn Clang is a photographer and visual artist. His fascination on time\n displacement and existentialism influence his work. He held his first exhibition at 20 years old and has since participated in more than 20 solo \\u0026 group exhibitions in China\n France\n Hong Kong\n Italy\n Malaysia\n Singapore and the United States. In 2010\n he became the first photographer in Singapore to receive the President\\u0027s Designer of the Year award\n which is the most prestigious design accolade in Singapore. Clang was also selected by a panel of jury from over 400 nominated entries\n as one of the 30 finalists for the 2010 Sovereign Asian Art Prize.\n",
  "createdDate": "20201125084545",
  "version": 0,
  "latest": false,
  "roles": [],
  "metadata": {
    "accession_no_csv": "2014-00334",
    "Image": "",
    "object_work_type": "photographs photographic prints",
    "title_text": "Being Together (Krishnan Family / Yokohama / Teban Gardens)",
    "preference": "main",
    "title_language": "",
    "creator_2": "John Clang",
    "creator_1": "Clang, John",
    "creator_role": "photographers",
    "creation_date": "Not indicated",
    "creation_place_original_location": "Singapore",
    "inscriptions": "",
    "inscription_language": "",
    "shape": "rectangular",
    "materials_name": "art paper",
    "techniques_name": "printing (process) photographic processes",
    "object_colour": "multicoloured",
    "edition_description": "1 of 3",
    "physical_appearance": "The image displays a colour photograph printed on a piece of white paper. There is a white border around the perimeter of the photograph. A family is featured and they are all standing up and looking towards the direction in which the photograph was captured. There is a total of four adults and two children whose images are projected on a screen. Their images are juxtaposed with a man, who is standing beside a bed with an open laptop on it.",
    "subject_terms_1": "families (kinship groups) group portraits colour photographs",
    "subject_terms_2": "Colour photography Portraits, Group Singaporeans Portrait photography Families",
    "subject_terms_3": "Clang, John Portrait photography Visual Arts",
    "sgcool_label_text": "Being Together, 2010 – 2012 \r\nby John Clang (b. 1973) \r\n\r\nArtist Statement: \r\nIn this series, webcam was used to do live recording of families in Singapore. The recording was then transmitted via skype to countries where the main sitters are located and projected onto their living space. This is how families, dis(membered) through time and space, can be re(membered) and made whole again through the use of a third space, a site that is able to reassemble them together within the photographic space that we call a family portrait.\r\n\r\nDrawing upon my own experiences of being separated from my family as a New York-based Singaporean, this work documents and examines our condition of new-wave diaspora – Singaporean families of various races and ethnicities grappling with the same predicament of separation through time and space.\r\n\r\nI also want this project to document and interpret a contemporary social-historical blueprint as it happens, allowing the future generations to reflect on it.\r\n\r\nIn addition, this is also an extension of one of the recurring theme of my works: the fascination with the expressions of time and space and how we negotiate our human existences within these two dimensions. this work specifically addresses the phenomenon of differing time zones, the different dimensions of our human representations, and how we can finally coexist, albeit in pixilated and two-dimensional forms.\r\n\r\nAbout the artist-photographer:\r\nJohn Clang is a photographer and visual artist. His fascination on time, displacement and existentialism influence his work. He held his first exhibition at 20 years old and has since participated in more than 20 solo \u0026 group exhibitions in China, France, Hong Kong, Italy, Malaysia, Singapore and the United States. In 2010, he became the first photographer in Singapore to receive the President\u0027s Designer of the Year award, which is the most prestigious design accolade in Singapore. Clang was also selected by a panel of jury from over 400 nominated entries, as one of the 30 finalists for the 2010 Sovereign Asian Art Prize."
  },
  "nlpDate": "20201125084545",
  "connectorId": 0,
  "tags": {}
}