{"id":"2014-00909-014","title":"72-13 (05) Brochures and cards for performances by Theatreworks (20) - 72-13 (5/9)","source":"Bumblebee","path":"./Data/json/","content":"accession_no_csv:2014-00909-014\nImage:\nobject_work_type:brochures\ntitle_text:72-13 (05) Brochures and cards for performances by Theatreworks (20) - 72-13 (5/9)\npreference:main alternate\ntitle_language:\ncreator_2:Not indicated\ncreator_1:Not indicated\ncreator_role:Not indicated\ncreation_date:Not indicated\ncreation_place_original_location:Singapore\ninscriptions:\ninscription_language:\nshape:square (shape)\nmaterials_name:paper (fiber product)\ntechniques_name:printing (process)\nobject_colour:multicoloured\nphysical_appearance:\\The image shows a square brochure. \\\\72-13\\\\ is displayed at the centre of the brochure in white font. \\\\05\\\\ is stated at the lower left hand corner of the brochure. The image at the background shows the interior of a building. There is a chair with handrests and a person is lying down on the floor. To the right of the chair\nsubject_terms_1:a container has been placed on top of a stool.     \\\nsubject_terms_2:theatres (buildings) Theatres\nsubject_terms_3:Brochures\nsubject_terms_4:Theatre organisations\ncontext_21:72-13 was an old rice warehouse\ncontext_22:72-13 Mohammed Sultan Road\n Singapore 239007\ncontext_23:2005\ncontext_24:5-Sep\nsgcool_label_text:5-Sep","createdDate":"20201119143405","version":0,"latest":false,"roles":[],"metadata":{"accession_no_csv":"2014-00909-014","Image":"","object_work_type":"brochures","title_text":"72-13 (05) Brochures and cards for performances by Theatreworks (20) - 72-13 (5/9)","preference":"main alternate","title_language":"","creator_2":"Not indicated","creator_1":"Not indicated","creator_role":"Not indicated","creation_date":"Not indicated","creation_place_original_location":"Singapore","inscriptions":"","inscription_language":"","shape":"square (shape)","materials_name":"paper (fiber product)","techniques_name":"printing (process)","object_colour":"multicoloured","physical_appearance":"\"The image shows a square brochure. \"\"72-13\"\" is displayed at the centre of the brochure in white font. \"\"05\"\" is stated at the lower left hand corner of the brochure. The image at the background shows the interior of a building. There is a chair with handrests and a person is lying down on the floor. To the right of the chair","subject_terms_1":"a container has been placed on top of a stool.     \"","subject_terms_2":"theatres (buildings) Theatres","subject_terms_3":"Brochures","subject_terms_4":"Theatre organisations","context_21":"72-13 was an old rice warehouse","context_22":"72-13 Mohammed Sultan Road, Singapore 239007","context_23":"2005","context_24":"5-Sep","sgcool_label_text":"5-Sep"},"nlpDate":"20201119143405","connectorId":0,"tags":{}}