{
  "id": "2014-00208",
  "title": "Picture of A Room at Raffles A Room at Raffles",
  "source": "Bumblebee",
  "path": "./Data/json/",
  "content": "\n  accession_no_csv: 2014-00208\n\n  Image: \n\n  object_work_type: illustrations (layout features)\n\n  title_text: Picture of A Room at Raffles A Room at Raffles\n\n  preference: main alternate\n\n  title_language: \n\n  creator_2: S.J. Perelman Hirschfeld\n\n  creator_1: Perelman\n S.J. (Sidney Joseph)\n 1904 - 1979 Hirschfeld\n Al\n\n  creator_role: authors illustrators\n\n  creation_date: 1947\n\n  creation_place_original_location: New York (State)\n\n  inscriptions: \n\n  inscription_language: \n\n  shape: rectangular\n\n  materials_name: paper (fiber product) printing paper\n\n  techniques_name: colour printing illustration (process)\n\n  object_colour: multicoloured\n\n  physical_appearance: \\The image displays an illustration from a book. There is a white border around the illustration. The illustration is a drawing of the interior of a hotel room with two single beds. Two men are sleeping\n one on each bed. Both beds have mosquito nets hung on their frames. A ceiling fan can be seen prominently and there are several bags and boxes with locks on them. The initials \\\\SJP\\\\ can be seen clearly on one of the bags\n\n  subject_terms_1: drawings (visual works) nonfiction situated near to the bed on the right. \\\\A Room at Raffles from the book Westward Ha! (New York travel literature pictures (object genre)\n\n  subject_terms_2: Illustration of books Travel writing Pictures Drawing Non-fiction. . . 1947) Words by S.J. Perelman and drawings by Hirschfeld\\\\ is stated below the image. \\\n\n  subject_terms_3: Drawing Non-fiction hotels (public accommodations) Description and travel\n\n  subject_terms_4: Raffles Hotel\n\n  context_1: Raffles Hotel\n",
  "createdDate": "20201201203309",
  "version": 0,
  "latest": false,
  "roles": [],
  "metadata": {
    "accession_no_csv": "2014-00208",
    "Image": "",
    "object_work_type": "illustrations (layout features)",
    "title_text": "Picture of A Room at Raffles A Room at Raffles",
    "preference": "main alternate",
    "title_language": "",
    "creator_2": "S.J. Perelman Hirschfeld",
    "creator_1": "Perelman, S.J. (Sidney Joseph), 1904 - 1979 Hirschfeld, Al",
    "creator_role": "authors illustrators",
    "creation_date": "1947",
    "creation_place_original_location": "New York (State)",
    "inscriptions": "",
    "inscription_language": "",
    "shape": "rectangular",
    "materials_name": "paper (fiber product) printing paper",
    "techniques_name": "colour printing illustration (process)",
    "object_colour": "multicoloured",
    "physical_appearance": "\"The image displays an illustration from a book. There is a white border around the illustration. The illustration is a drawing of the interior of a hotel room with two single beds. Two men are sleeping, one on each bed. Both beds have mosquito nets hung on their frames. A ceiling fan can be seen prominently and there are several bags and boxes with locks on them. The initials \"\"SJP\"\" can be seen clearly on one of the bags",
    "subject_terms_1": "drawings (visual works) nonfiction situated near to the bed on the right. \"\"A Room at Raffles from the book Westward Ha! (New York travel literature pictures (object genre)",
    "subject_terms_2": "Illustration of books Travel writing Pictures Drawing Non-fiction. . . 1947) Words by S.J. Perelman and drawings by Hirschfeld\"\" is stated below the image. \"",
    "subject_terms_3": "Drawing Non-fiction hotels (public accommodations) Description and travel",
    "subject_terms_4": "Raffles Hotel",
    "context_1": "Raffles Hotel"
  },
  "nlpDate": "20201201203309",
  "connectorId": 0,
  "tags": {}
}