{"id":"2014-00909-016","title":"72-13 (07) Brochures and cards for performances by Theatreworks (20) - 72-13 (7/9)","source":"Bumblebee","path":"./Data/json/","content":"accession_no_csv:2014-00909-016\nImage:\nobject_work_type:brochures\ntitle_text:72-13 (07) Brochures and cards for performances by Theatreworks (20) - 72-13 (7/9)\npreference:main alternate\ntitle_language:\ncreator_2:Not indicated\ncreator_1:Not indicated\ncreator_role:Not indicated\ncreation_date:Not indicated\ncreation_place_original_location:Singapore\ninscriptions:\ninscription_language:\nshape:square (shape)\nmaterials_name:paper (fiber product)\ntechniques_name:printing (process)\nobject_colour:multicoloured\nphysical_appearance:\\The image shows a square brochure. \\\\72-13\\\\ is displayed at the centre of the brochure in blue font. \\\\119 Videoworks 99 Artists 7 Communities\\\\ is stated at the bottom right hand corner of the brochure. \\\\07\\\\ is stated at the lower left hand corner of the brochure. \\\\Image by Ruangrupa\nsubject_terms_1:ANA Grantee video art artists (visual artists)\nsubject_terms_2:2007\\\\ is stated at the lower right hand corner of the brochure. The image at the background shows a man and a lady standing closely together. The man holds an electronic device that reflects light \\ Theatres Video art Artists\nsubject_terms_3:theatres (buildings) Artists\nsubject_terms_4:Brochures\ncontext_1:Theatre organisations\ncontext_22:72-13 was an old rice warehouse\ncontext_23:72-13 Mohammed Sultan Road\n Singapore 239007\ncontext_24:2005\nsgcool_label_text:5-Sep","createdDate":"20201018182635","version":0,"latest":false,"roles":[],"metadata":{"accession_no_csv":"2014-00909-016","Image":"","object_work_type":"brochures","title_text":"72-13 (07) Brochures and cards for performances by Theatreworks (20) - 72-13 (7/9)","preference":"main alternate","title_language":"","creator_2":"Not indicated","creator_1":"Not indicated","creator_role":"Not indicated","creation_date":"Not indicated","creation_place_original_location":"Singapore","inscriptions":"","inscription_language":"","shape":"square (shape)","materials_name":"paper (fiber product)","techniques_name":"printing (process)","object_colour":"multicoloured","physical_appearance":"\"The image shows a square brochure. \"\"72-13\"\" is displayed at the centre of the brochure in blue font. \"\"119 Videoworks 99 Artists 7 Communities\"\" is stated at the bottom right hand corner of the brochure. \"\"07\"\" is stated at the lower left hand corner of the brochure. \"\"Image by Ruangrupa","subject_terms_1":"ANA Grantee video art artists (visual artists)","subject_terms_2":"2007\"\" is stated at the lower right hand corner of the brochure. The image at the background shows a man and a lady standing closely together. The man holds an electronic device that reflects light \" Theatres Video art Artists","subject_terms_3":"theatres (buildings) Artists","subject_terms_4":"Brochures","context_1":"Theatre organisations","context_22":"72-13 was an old rice warehouse","context_23":"72-13 Mohammed Sultan Road, Singapore 239007","context_24":"2005","sgcool_label_text":"5-Sep"},"nlpDate":"20201018182635","connectorId":0,"tags":{}}