{"id":"2014-00285-004","title":"Rows of shophouses Photography Album (donation from Anthony Robert Saint Claire)","source":"Bumblebee","path":"./Data/json/","content":"accession_no_csv:2014-00285-004\nImage:\nobject_work_type:black-and-white photographs\ntitle_text:Rows of shophouses Photography Album (donation from Anthony Robert Saint Claire)\npreference:main alternate\ntitle_language:\ncreator_2:Robert Arthur Polglaze\ncreator_1:Not indicated\ncreator_role:photographers\ncreation_date:1940s\ncreation_place_original_location:Singapore\ninscriptions:\ninscription_language:\nshape:rectangular\nmaterials_name:paper (fiber product)\ntechniques_name:printing (process) photographic processes\nobject_colour:grey monochrome\nphysical_appearance:The image shows a black-and-white photograph. It is rectangular and it features a street that is flanked with shophouses on both sides. Clothes such as tee shirts\n shorts\n and trousers protrude from both levels of these shophouses\n from the sticks in which they are hung from. A couple of rickshaws and a car can be seen on the street.\nsubject_terms_1:street scenes residential structures mercantile buildings\nsubject_terms_2:Black-and-white photography Shophouses\nsubject_terms_3:Photography Buildings\nsgcool_label_text:Not indicated","createdDate":"20201119143405","version":0,"latest":false,"roles":[],"metadata":{"accession_no_csv":"2014-00285-004","Image":"","object_work_type":"black-and-white photographs","title_text":"Rows of shophouses Photography Album (donation from Anthony Robert Saint Claire)","preference":"main alternate","title_language":"","creator_2":"Robert Arthur Polglaze","creator_1":"Not indicated","creator_role":"photographers","creation_date":"1940s","creation_place_original_location":"Singapore","inscriptions":"","inscription_language":"","shape":"rectangular","materials_name":"paper (fiber product)","techniques_name":"printing (process) photographic processes","object_colour":"grey monochrome","physical_appearance":"The image shows a black-and-white photograph. It is rectangular and it features a street that is flanked with shophouses on both sides. Clothes such as tee shirts, shorts, and trousers protrude from both levels of these shophouses, from the sticks in which they are hung from. A couple of rickshaws and a car can be seen on the street.","subject_terms_1":"street scenes residential structures mercantile buildings","subject_terms_2":"Black-and-white photography Shophouses","subject_terms_3":"Photography Buildings","sgcool_label_text":"Not indicated"},"nlpDate":"20201119143405","connectorId":0,"tags":{}}