{
  "id": "2014-00206-017",
  "title": "Items Related to Doris Geddes Celebration of the Opening of the Little Shop, Raffles Hotel, 1947",
  "source": "Bumblebee",
  "path": "./Data/json/",
  "content": "\n  accession_no_csv: 2014-00206-017\n\n  Image: \n\n  object_work_type: black-and-white photographs\n\n  title_text: Items Related to Doris Geddes Celebration of the Opening of the Little Shop\n Raffles Hotel\n 1947\n\n  preference: main alternate\n\n  title_language: \n\n  creation_date: Not indicated\n\n  creation_place_original_location: Singapore\n\n  inscriptions: \n\n  inscription_language: \n\n  shape: rectangular\n\n  materials_name: paper (fiber product) printing paper\n\n  techniques_name: printing processes\n\n  object_colour: grey (colour) monochrome\n\n  physical_appearance: \\The image displays a black-and-white photograph. The photograph is encased in a black frame and it has a white border. Seven people are featured and they are posing and looking in the direction where the photograph was captured. They are separated in two groups\n one with three people and the other with four. Both groups are posing in front of a building\n at the open doors. Balustrades can be seen at the top of the building. There are numerous potted plants around them. Below the image\n \\\\Doris Geddes and friends celebrate opening of the Little Shop\n\n  subject_terms_1: celebrations Raffles Hotel retail stores hotels (public accommodations)\n\n  subject_terms_2: Stores\n Retail Portraits\n Group Raffles Hotel 1947\\\\ is stated \\\n\n  subject_terms_3: Raffles Hotel Retail group portraits\n\n  subject_terms_4: Black-and-white photography\n\n  context_1: Portrait photography\n",
  "createdDate": "20201201203309",
  "version": 0,
  "latest": false,
  "roles": [],
  "metadata": {
    "accession_no_csv": "2014-00206-017",
    "Image": "",
    "object_work_type": "black-and-white photographs",
    "title_text": "Items Related to Doris Geddes Celebration of the Opening of the Little Shop, Raffles Hotel, 1947",
    "preference": "main alternate",
    "title_language": "",
    "creation_date": "Not indicated",
    "creation_place_original_location": "Singapore",
    "inscriptions": "",
    "inscription_language": "",
    "shape": "rectangular",
    "materials_name": "paper (fiber product) printing paper",
    "techniques_name": "printing processes",
    "object_colour": "grey (colour) monochrome",
    "physical_appearance": "\"The image displays a black-and-white photograph. The photograph is encased in a black frame and it has a white border. Seven people are featured and they are posing and looking in the direction where the photograph was captured. They are separated in two groups, one with three people and the other with four. Both groups are posing in front of a building, at the open doors. Balustrades can be seen at the top of the building. There are numerous potted plants around them. Below the image, \"\"Doris Geddes and friends celebrate opening of the Little Shop",
    "subject_terms_1": "celebrations Raffles Hotel retail stores hotels (public accommodations)",
    "subject_terms_2": "Stores, Retail Portraits, Group Raffles Hotel 1947\"\" is stated \"",
    "subject_terms_3": "Raffles Hotel Retail group portraits",
    "subject_terms_4": "Black-and-white photography",
    "context_1": "Portrait photography"
  },
  "nlpDate": "20201201203309",
  "connectorId": 0,
  "tags": {}
}