{"id":"2014-00285-83","title":"School Group Photography Photography Album (donation from Anthony Robert Saint Claire)","source":"Bumblebee","path":"./Data/json/","content":"accession_no_csv:2014-00285-83\nImage:\nobject_work_type:black-and-white photographs\ntitle_text:School Group Photography Photography Album (donation from Anthony Robert Saint Claire)\npreference:main alternate\ntitle_language:\ncreator_2:Robert Arthur Polglaze\ncreator_1:Not indicated\ncreator_role:photographers\ncreation_date:1940s\ncreation_place_original_location:Singapore\ninscriptions:\ninscription_language:\nshape:rectangular\nmaterials_name:paper (fiber product)\ntechniques_name:printing (process) photographic processes\nobject_colour:grey monochrome\nphysical_appearance:The image shows a black-and-white photograph. It is rectangular and it features a group of schoolchildren and three adults. All of them are looking in the direction where the photograph was captured. Most of the chidren are standing up\n except for the ones in the front who are sitting or squatting down. All of them are dressed in the same kind of uniform\n that of a long white outfit. The background of the photograph shows a part of a building\n It is double storey and it has tiled pitched roofs and the second floor has railings around the balcony\nsubject_terms_1:group portraits schoolchildren\nsubject_terms_2:Black-and-white photography Portrait photography Portraits\n Group School children\nsubject_terms_3:Portrait photography Children\nsgcool_label_text:Not indicated","createdDate":"20201018182635","version":0,"latest":false,"roles":[],"metadata":{"accession_no_csv":"2014-00285-83","Image":"","object_work_type":"black-and-white photographs","title_text":"School Group Photography Photography Album (donation from Anthony Robert Saint Claire)","preference":"main alternate","title_language":"","creator_2":"Robert Arthur Polglaze","creator_1":"Not indicated","creator_role":"photographers","creation_date":"1940s","creation_place_original_location":"Singapore","inscriptions":"","inscription_language":"","shape":"rectangular","materials_name":"paper (fiber product)","techniques_name":"printing (process) photographic processes","object_colour":"grey monochrome","physical_appearance":"The image shows a black-and-white photograph. It is rectangular and it features a group of schoolchildren and three adults. All of them are looking in the direction where the photograph was captured. Most of the chidren are standing up, except for the ones in the front who are sitting or squatting down. All of them are dressed in the same kind of uniform, that of a long white outfit. The background of the photograph shows a part of a building, It is double storey and it has tiled pitched roofs and the second floor has railings around the balcony","subject_terms_1":"group portraits schoolchildren","subject_terms_2":"Black-and-white photography Portrait photography Portraits, Group School children","subject_terms_3":"Portrait photography Children","sgcool_label_text":"Not indicated"},"nlpDate":"20201018182635","connectorId":0,"tags":{}}