{"id":"2014-00363-001","title":"The Singapore Musical Society presents Joan Hammond Joan Hammond concert programme and related newspaper cuttings","source":"Bumblebee","path":"./Data/json/","content":"accession_no_csv:2014-00363-001\nImage:\nobject_work_type:concert programmes\ntitle_text:The Singapore Musical Society presents Joan Hammond Joan Hammond concert programme and related newspaper cuttings\npreference:main alternate\ntitle_language:\ncreator_2:Singapore Music Society Craftsman Press Ltd\ncreator_1:Not indicated Not indicated\ncreator_role:creators publishers\ncreation_date:1953\ncreation_place_original_location:Singapore\ninscriptions:\ninscription_language:\nshape:rectangular\nmaterials_name:paper (fiber product)\ntechniques_name:printing (process)\nobject_colour:multicoloured\nphysical_appearance:\\The image shows a concert programme. It is rectangular in shape and it features a picture of Joan Hammond in the middle. \\\\Joan Hammond\\\\ is written in blue cursive writing\nsubject_terms_1:just below the image of her face. The details of the concert like the venue celebrities conductors concerts\nsubject_terms_2:time Hammond\n Joan\n 1912 - 1996 Celebrities Concerts Susskind\n Walter\n 1913-1980\nsubject_terms_3:and price are stated below the picture of Hammond. Above her image Singers Conductors (Music) Music organisations\nsubject_terms_4:it stated that she is a \\\\world famous soprano\\\\ and that the concert was presented by the \\\\Singapore Musical Society\\\\\\\ncontext_1:opera singers\ncontext_2:Concert programmes\ncontext_3:Opera\ncontext_5:The concert programme states that the concert was held at the Victoria Memorial Hall on Friday\n 12th June 1953 at 8.45 p.m.\ncontext_6:concerts\ncontext_7:19530612\ncontext_8:19530612\ncontext_9:19530612\ncontext_10:Victoria Theatre and Concert Hall","createdDate":"20201119143405","version":0,"latest":false,"roles":[],"metadata":{"accession_no_csv":"2014-00363-001","Image":"","object_work_type":"concert programmes","title_text":"The Singapore Musical Society presents Joan Hammond Joan Hammond concert programme and related newspaper cuttings","preference":"main alternate","title_language":"","creator_2":"Singapore Music Society Craftsman Press Ltd","creator_1":"Not indicated Not indicated","creator_role":"creators publishers","creation_date":"1953","creation_place_original_location":"Singapore","inscriptions":"","inscription_language":"","shape":"rectangular","materials_name":"paper (fiber product)","techniques_name":"printing (process)","object_colour":"multicoloured","physical_appearance":"\"The image shows a concert programme. It is rectangular in shape and it features a picture of Joan Hammond in the middle. \"\"Joan Hammond\"\" is written in blue cursive writing","subject_terms_1":"just below the image of her face. The details of the concert like the venue celebrities conductors concerts","subject_terms_2":"time Hammond, Joan, 1912 - 1996 Celebrities Concerts Susskind, Walter, 1913-1980","subject_terms_3":"and price are stated below the picture of Hammond. Above her image Singers Conductors (Music) Music organisations","subject_terms_4":"it stated that she is a \"\"world famous soprano\"\" and that the concert was presented by the \"\"Singapore Musical Society\"\"\"","context_1":"opera singers","context_2":"Concert programmes","context_3":"Opera","context_5":"The concert programme states that the concert was held at the Victoria Memorial Hall on Friday, 12th June 1953 at 8.45 p.m.","context_6":"concerts","context_7":"19530612","context_8":"19530612","context_9":"19530612","context_10":"Victoria Theatre and Concert Hall"},"nlpDate":"20201119143405","connectorId":0,"tags":{}}