{"id":"2014-00285-108","title":"Military and civil clerks of JAG Branch, HQ, ALFSEA Photography Album (donation from Anthony Robert Saint Claire)","source":"Bumblebee","path":"./Data/json/","content":"accession_no_csv:2014-00285-108\nImage:\nobject_work_type:black-and-white photographs\ntitle_text:Military and civil clerks of JAG Branch\n HQ\n ALFSEA Photography Album (donation from Anthony Robert Saint Claire)\npreference:main alternate\ntitle_language:\ncreator_2:Robert Arthur Polglaze\ncreator_1:Not indicated\ncreator_role:photographers\ncreation_date:1940s\ncreation_place_original_location:Singapore\ninscriptions:\ninscription_language:\nshape:rectangular\nmaterials_name:paper (fiber product)\ntechniques_name:printing (process) photographic processes\nobject_colour:grey monochrome\nphysical_appearance:The image shows a photograph in black-and-white. It is rectangular and it features a group of ten people. All of them are looking in the direction where the photograph was captured. There is a boy\n who is standing at the left hand side of the photograph\n while the rest are adults. All the adults\n except for one man at the right hand side of the photograph at the back row\n are wearing their military uniforms. The background of the photograph shows a building\nsubject_terms_1:group portraits military personnel children (people by age group)\nsubject_terms_2:Black-and-white photography Portrait photography Portraits\n Group Soldiers Boys\nsubject_terms_3:Portrait photography Children\nsgcool_label_text:Not indicated","createdDate":"20201119143405","version":0,"latest":false,"roles":[],"metadata":{"accession_no_csv":"2014-00285-108","Image":"","object_work_type":"black-and-white photographs","title_text":"Military and civil clerks of JAG Branch, HQ, ALFSEA Photography Album (donation from Anthony Robert Saint Claire)","preference":"main alternate","title_language":"","creator_2":"Robert Arthur Polglaze","creator_1":"Not indicated","creator_role":"photographers","creation_date":"1940s","creation_place_original_location":"Singapore","inscriptions":"","inscription_language":"","shape":"rectangular","materials_name":"paper (fiber product)","techniques_name":"printing (process) photographic processes","object_colour":"grey monochrome","physical_appearance":"The image shows a photograph in black-and-white. It is rectangular and it features a group of ten people. All of them are looking in the direction where the photograph was captured. There is a boy, who is standing at the left hand side of the photograph, while the rest are adults. All the adults, except for one man at the right hand side of the photograph at the back row, are wearing their military uniforms. The background of the photograph shows a building","subject_terms_1":"group portraits military personnel children (people by age group)","subject_terms_2":"Black-and-white photography Portrait photography Portraits, Group Soldiers Boys","subject_terms_3":"Portrait photography Children","sgcool_label_text":"Not indicated"},"nlpDate":"20201119143405","connectorId":0,"tags":{}}