{"id":"2014-00363-003","title":"Details about Joan Hammond before and after her concert in Singapore  Joan Hammond concert programme and related newspaper cuttings","source":"Bumblebee","path":"./Data/json/","content":"accession_no_csv:2014-00363-003\nImage:\nobject_work_type:clippings (information artifacts)\ntitle_text:Details about Joan Hammond before and after her concert in Singapore  Joan Hammond concert programme and related newspaper cuttings\npreference:main alternate\ntitle_language:\ncreator_2:Not indicated\ncreator_1:Not indicated\ncreation_date:1953\ncreation_place_original_location:Singapore\ninscriptions:\ninscription_language:\nshape:rectangular\nmaterials_name:paper (fiber product)\ntechniques_name:printing (process)\nobject_colour:black-and-white (colours)\nphysical_appearance:\\The image shows three newspaper clippings that are pasted onto a light purple paper. There are several punched holes at its left side. \\\\Famous Soprano to sing here tonight\\\\\nsubject_terms_1:\\\\Joan hammond recital was great and varied\\\\ opera singers celebrities concerts recitals\nsubject_terms_2:and \\\\Joan Hammond in good voice\\\\ are the respective headlines of the three newspaper clippings. The clipping on the right hand side contians a picture of a smiling Joan Hammond in a formal dress.\\ Hammond\n Joan\n 1912 - 1996 Celebrities Concerts\nsubject_terms_3:newspapers Singers Conductors (Music) Daily newspapers\nsubject_terms_4:Newspapers\ncontext_1:Opera","createdDate":"20201119143405","version":0,"latest":false,"roles":[],"metadata":{"accession_no_csv":"2014-00363-003","Image":"","object_work_type":"clippings (information artifacts)","title_text":"Details about Joan Hammond before and after her concert in Singapore  Joan Hammond concert programme and related newspaper cuttings","preference":"main alternate","title_language":"","creator_2":"Not indicated","creator_1":"Not indicated","creation_date":"1953","creation_place_original_location":"Singapore","inscriptions":"","inscription_language":"","shape":"rectangular","materials_name":"paper (fiber product)","techniques_name":"printing (process)","object_colour":"black-and-white (colours)","physical_appearance":"\"The image shows three newspaper clippings that are pasted onto a light purple paper. There are several punched holes at its left side. \"\"Famous Soprano to sing here tonight\"\"","subject_terms_1":"\"\"Joan hammond recital was great and varied\"\" opera singers celebrities concerts recitals","subject_terms_2":"and \"\"Joan Hammond in good voice\"\" are the respective headlines of the three newspaper clippings. The clipping on the right hand side contians a picture of a smiling Joan Hammond in a formal dress.\" Hammond, Joan, 1912 - 1996 Celebrities Concerts","subject_terms_3":"newspapers Singers Conductors (Music) Daily newspapers","subject_terms_4":"Newspapers","context_1":"Opera"},"nlpDate":"20201119143405","connectorId":0,"tags":{}}