{"id":"2014-00285-028","title":"Japanese filing out after the signing the surrender Photography Album (donation from Anthony Robert Saint Claire)","source":"Bumblebee","path":"./Data/json/","content":"accession_no_csv:2014-00285-028\nImage:\nobject_work_type:black-and-white photographs\ntitle_text:Japanese filing out after the signing the surrender Photography Album (donation from Anthony Robert Saint Claire)\npreference:main alternate\ntitle_language:\ncreator_2:Robert Arthur Polglaze\ncreator_1:Not indicated\ncreator_role:photographers\ncreation_date:1940s\ncreation_place_original_location:Singapore\ninscriptions:\ninscription_language:\nshape:rectangular\nmaterials_name:paper (fiber product)\ntechniques_name:printing (process) photographic processes\nobject_colour:grey monochrome\nphysical_appearance:The image shows a black-and-white photograph. It is rectangular and it features military personnel in the interior of a building. They are dressed in different military uniforms. The left side of the photograph features military personnel seated in a single row\n behind a long table that has several documents on it. The right hand side of the photograph features two rows of military personnel who are standing up. To their right are more seated personnel.\nsubject_terms_1:world wars victories military personnel\nsubject_terms_2:Black-and-white photography World War\n 1939 - 1945 Japan. Rikugun Great Britain\n Army Capitulations\n Military\nsubject_terms_3:Photography Surrender of Japan\n 1945 Wars\ncontext_1:World War\n 1939 - 1945\ncontext_2:world wars\ncontext_3:1939 - 1945\ncontext_4:1939\ncontext_5:1945\ncontext_6:Southeast Asia\nsgcool_label_text:Not indicated","createdDate":"20201018182635","version":0,"latest":false,"roles":[],"metadata":{"accession_no_csv":"2014-00285-028","Image":"","object_work_type":"black-and-white photographs","title_text":"Japanese filing out after the signing the surrender Photography Album (donation from Anthony Robert Saint Claire)","preference":"main alternate","title_language":"","creator_2":"Robert Arthur Polglaze","creator_1":"Not indicated","creator_role":"photographers","creation_date":"1940s","creation_place_original_location":"Singapore","inscriptions":"","inscription_language":"","shape":"rectangular","materials_name":"paper (fiber product)","techniques_name":"printing (process) photographic processes","object_colour":"grey monochrome","physical_appearance":"The image shows a black-and-white photograph. It is rectangular and it features military personnel in the interior of a building. They are dressed in different military uniforms. The left side of the photograph features military personnel seated in a single row, behind a long table that has several documents on it. The right hand side of the photograph features two rows of military personnel who are standing up. To their right are more seated personnel.","subject_terms_1":"world wars victories military personnel","subject_terms_2":"Black-and-white photography World War, 1939 - 1945 Japan. Rikugun Great Britain, Army Capitulations, Military","subject_terms_3":"Photography Surrender of Japan, 1945 Wars","context_1":"World War, 1939 - 1945","context_2":"world wars","context_3":"1939 - 1945","context_4":"1939","context_5":"1945","context_6":"Southeast Asia","sgcool_label_text":"Not indicated"},"nlpDate":"20201018182635","connectorId":0,"tags":{}}