{
  "id": "2014-00285-90",
  "title": "Photography Album (donation from Anthony Robert Saint Claire) Group of Military Personnel",
  "source": "Bumblebee",
  "path": "./Data/json/",
  "content": "\n  accession_no_csv: 2014-00285-90\n\n  Image: \n\n  object_work_type: black-and-white photographs\n\n  title_text: Photography Album (donation from Anthony Robert Saint Claire) Group of Military Personnel\n\n  preference: main alternate\n\n  title_language: \n\n  creator_2: Robert Arthur Polglaze\n\n  creator_1: Not indicated\n\n  creator_role: photographers\n\n  creation_date: 1940s\n\n  creation_place_original_location: Singapore\n\n  inscriptions: \n\n  inscription_language: \n\n  shape: squares (geometric figures)\n\n  materials_name: paper (fiber product)\n\n  techniques_name: printing (process) photographic processes\n\n  object_colour: grey monochrome\n\n  physical_appearance: The image shows a black-and-white photograph. It is square and it features eight people. All of them are facing the direction in which the photograph was captured. Two of them are women while the other six are men\n and they are all adorned in military uniform. Four of them are squatting down while the other four are standing behind them. The background of the photograph shows greenery and trees.\n\n  subject_terms_1: group portraits military personnel\n\n  subject_terms_2: Portraits\n Group Portrait photography Soldiers Black-and-white photography\n\n  subject_terms_3: Portrait photography\n\n  sgcool_label_text: Not indicated\n",
  "createdDate": "20201201203309",
  "version": 0,
  "latest": false,
  "roles": [],
  "metadata": {
    "accession_no_csv": "2014-00285-90",
    "Image": "",
    "object_work_type": "black-and-white photographs",
    "title_text": "Photography Album (donation from Anthony Robert Saint Claire) Group of Military Personnel",
    "preference": "main alternate",
    "title_language": "",
    "creator_2": "Robert Arthur Polglaze",
    "creator_1": "Not indicated",
    "creator_role": "photographers",
    "creation_date": "1940s",
    "creation_place_original_location": "Singapore",
    "inscriptions": "",
    "inscription_language": "",
    "shape": "squares (geometric figures)",
    "materials_name": "paper (fiber product)",
    "techniques_name": "printing (process) photographic processes",
    "object_colour": "grey monochrome",
    "physical_appearance": "The image shows a black-and-white photograph. It is square and it features eight people. All of them are facing the direction in which the photograph was captured. Two of them are women while the other six are men, and they are all adorned in military uniform. Four of them are squatting down while the other four are standing behind them. The background of the photograph shows greenery and trees.",
    "subject_terms_1": "group portraits military personnel",
    "subject_terms_2": "Portraits, Group Portrait photography Soldiers Black-and-white photography",
    "subject_terms_3": "Portrait photography",
    "sgcool_label_text": "Not indicated"
  },
  "nlpDate": "20201201203309",
  "connectorId": 0,
  "tags": {}
}