{"id":"2014-00285-072","title":"Toddlers at play Photography Album (donation from Anthony Robert Saint Claire)","source":"Bumblebee","path":"./Data/json/","content":"accession_no_csv:2014-00285-072\nImage:\nobject_work_type:black-and-white photographs\ntitle_text:Toddlers at play Photography Album (donation from Anthony Robert Saint Claire)\npreference:main alternate\ntitle_language:\ncreator_2:Robert Arthur Polglaze\ncreator_1:Not indicated\ncreator_role:photographers\ncreation_date:1940s\ncreation_place_original_location:Singapore\ninscriptions:\ninscription_language:\nshape:rectangular\nmaterials_name:paper (fiber product)\ntechniques_name:printing (process) photographic processes\nobject_colour:grey monochrome\nphysical_appearance:The image shows a black-and-white photograph. It is rectangular and it features three toddlers. Two of them are sitting on the floor while the other one is squatting. The toddler on the left is looking in the direction where the photograph was captured. He is also holding a bowl in his left hand. The feet of an adult can be seen\n only slightly\n at the extreme left hand side of the photograph. The background of the photograph suggests that it was taken in the interior of a building.\nsubject_terms_1:toddlers\nsubject_terms_2:Black-and-white photography Toddlers\nsubject_terms_3:Photography Children\nsgcool_label_text:Not indicated","createdDate":"20201018182635","version":0,"latest":false,"roles":[],"metadata":{"accession_no_csv":"2014-00285-072","Image":"","object_work_type":"black-and-white photographs","title_text":"Toddlers at play Photography Album (donation from Anthony Robert Saint Claire)","preference":"main alternate","title_language":"","creator_2":"Robert Arthur Polglaze","creator_1":"Not indicated","creator_role":"photographers","creation_date":"1940s","creation_place_original_location":"Singapore","inscriptions":"","inscription_language":"","shape":"rectangular","materials_name":"paper (fiber product)","techniques_name":"printing (process) photographic processes","object_colour":"grey monochrome","physical_appearance":"The image shows a black-and-white photograph. It is rectangular and it features three toddlers. Two of them are sitting on the floor while the other one is squatting. The toddler on the left is looking in the direction where the photograph was captured. He is also holding a bowl in his left hand. The feet of an adult can be seen, only slightly, at the extreme left hand side of the photograph. The background of the photograph suggests that it was taken in the interior of a building.","subject_terms_1":"toddlers","subject_terms_2":"Black-and-white photography Toddlers","subject_terms_3":"Photography Children","sgcool_label_text":"Not indicated"},"nlpDate":"20201018182635","connectorId":0,"tags":{}}