{"id":"2014-00914","title":"Performance by the Padres Invite card for a performance by the Padres","source":"Bumblebee","path":"./Data/json/","content":"accession_no_csv:2014-00914\nImage:\nobject_work_type:invitations\ntitle_text:Performance by the Padres Invite card for a performance by the Padres\npreference:main alternate\ntitle_language:\ncreator_2:Not indicated\ncreation_date:1997\ncreation_place_original_location:Singapore\ninscriptions:\ninscription_language:\nshape:rectangular\nmaterials_name:paper (fiber product)\ntechniques_name:printing (process)\nobject_colour:multicoloured\nphysical_appearance:\\The image shows a rectangular invitation card. \\\\live at moods: Padres\\\\ is stated at the centre of the invitation card. The date\nsubject_terms_1:venue pubs music (performing arts)\nsubject_terms_2:and time are stated in red. The invitation card features the four band members of the Padres. Two of them are wearing sunglasses and all of them have black tops on.\\ Bands (Music) Rock groups Alternative rock music Bars (drinking establishments)\nsubject_terms_3:bands (ensembles) Rock music Musicians\nsubject_terms_4:Invitation cards\ncontext_1:Bands","createdDate":"20201018182635","version":0,"latest":false,"roles":[],"metadata":{"accession_no_csv":"2014-00914","Image":"","object_work_type":"invitations","title_text":"Performance by the Padres Invite card for a performance by the Padres","preference":"main alternate","title_language":"","creator_2":"Not indicated","creation_date":"1997","creation_place_original_location":"Singapore","inscriptions":"","inscription_language":"","shape":"rectangular","materials_name":"paper (fiber product)","techniques_name":"printing (process)","object_colour":"multicoloured","physical_appearance":"\"The image shows a rectangular invitation card. \"\"live at moods: Padres\"\" is stated at the centre of the invitation card. The date","subject_terms_1":"venue pubs music (performing arts)","subject_terms_2":"and time are stated in red. The invitation card features the four band members of the Padres. Two of them are wearing sunglasses and all of them have black tops on.\" Bands (Music) Rock groups Alternative rock music Bars (drinking establishments)","subject_terms_3":"bands (ensembles) Rock music Musicians","subject_terms_4":"Invitation cards","context_1":"Bands"},"nlpDate":"20201018182635","connectorId":0,"tags":{}}