{
  "id": "2015-00519",
  "title": "Hand Embroidered Bedspread",
  "source": "Bumblebee",
  "path": "./Data/json/",
  "content": "\n  accession_no_csv: 2015-00519\n\n  Image: \n\n  object_work_type: bedspreads\n\n  title_text: Hand Embroidered Bedspread\n\n  preference: main\n\n  title_language: \n\n  creator_2: Unknown\n\n  creation_date: 20th century\n\n  creation_place_original_location: Malaysia Singapore\n\n  styles_periods_indexing_terms: Not indicated\n\n  inscriptions: \n\n  inscription_language: \n\n  scale_type: Not indicated\n\n  shape: rectangular\n\n  materials_name: cotton (textile) thread\n\n  techniques_name: embroidering hand sewing\n\n  object_colour: multicoloured\n\n  physical_appearance: The image shows a bedspread. It is rectangular in shape. The bedspread has a white background. It is also embroidered with decorative elements. There are floral patterns that start at the middle of the top of the bedspread\n running through the right side and eventually ending at the bottom of the left side of the bedspread. These floral patterns are red in colour.\n\n  subject_terms_1: coverlets floral patterns household accessories\n\n  subject_terms_2: Motifs Coverlets\n\n  subject_terms_3: Textile art and design\n\n  sgcool_label_text: In the years preceding the Second World War Indian women in Singapore were essentially homemakers and contributed to community work\n arts and crafts. This is a bedspread from the collection of the late Lakshmi Rangasamy Davar; she was a woman pioneer – she was an educationist\n musician and philanthropist.\n",
  "createdDate": "20201125084544",
  "version": 0,
  "latest": false,
  "roles": [],
  "metadata": {
    "accession_no_csv": "2015-00519",
    "Image": "",
    "object_work_type": "bedspreads",
    "title_text": "Hand Embroidered Bedspread",
    "preference": "main",
    "title_language": "",
    "creator_2": "Unknown",
    "creation_date": "20th century",
    "creation_place_original_location": "Malaysia Singapore",
    "styles_periods_indexing_terms": "Not indicated",
    "inscriptions": "",
    "inscription_language": "",
    "scale_type": "Not indicated",
    "shape": "rectangular",
    "materials_name": "cotton (textile) thread",
    "techniques_name": "embroidering hand sewing",
    "object_colour": "multicoloured",
    "physical_appearance": "The image shows a bedspread. It is rectangular in shape. The bedspread has a white background. It is also embroidered with decorative elements. There are floral patterns that start at the middle of the top of the bedspread, running through the right side and eventually ending at the bottom of the left side of the bedspread. These floral patterns are red in colour.",
    "subject_terms_1": "coverlets floral patterns household accessories",
    "subject_terms_2": "Motifs Coverlets",
    "subject_terms_3": "Textile art and design",
    "sgcool_label_text": "In the years preceding the Second World War Indian women in Singapore were essentially homemakers and contributed to community work, arts and crafts. This is a bedspread from the collection of the late Lakshmi Rangasamy Davar; she was a woman pioneer – she was an educationist, musician and philanthropist."
  },
  "nlpDate": "20201125084544",
  "connectorId": 0,
  "tags": {}
}