{"id":"2015-00554","title":"14th year anniversary rally for the late Mr G Sarangapany","source":"Bumblebee","path":"./Data/json/","content":"accession_no_csv:2015-00554\nImage:\nobject_work_type:cards (information artefacts)\ntitle_text:14th year anniversary rally for the late Mr G Sarangapany\npreference:main\ntitle_language:\ncreator_2:Viknesh Printings\ncreator_1:Not indicated\ncreator_role:printers (people)\ncreation_date:1988\ncreation_place_original_location:Singapore\nstyles_periods_indexing_terms:Not indicated\ninscriptions:\ninscription_language:\nscale_type:Not indicated\nshape:rectangular\nmaterials_name:printing paper\ntechniques_name:printing (process)\nobject_colour:black-and-white (colours)\nphysical_appearance:\\The image shows a rectangular card. It was a border where a picture and several lines of Tamil scripts are displayed within. \\\\7-5-1988\\\\ is stated at the top. The picture shows a man who is dressed in a long sleeved shirt and sarong. \\\\Viknesh printings blk 1002 #03-1457 Lor 8 Toa Payoh S\\u0027pore Tel: 2504921\\\\ is displayed at the bottom outside the border. \\\nsubject_terms_1:rallies anniversaries founders (originators) reformers\nsubject_terms_2:Caran?kapa?n?i\n 1903-1974 Reformers Demonstrations Anniversaries\nsubject_terms_3:Thamizhavel Govindasamy Sarangapany Pioneers\nsgcool_label_text:G Sarangapany\n titled Thamizhavel\n arrived in Singapore in 1924. A believer of Periyar’s principles\n he played a key role in extending the Self-Respect Movement to Singapore and Malaya and became the agent for distribution of the movement’s magazine Kudi Arasu in British Malaya. He later helped arrange Periyar’s visits to Singapore and Malaya. \\r\\n\\r\\nHe was an active writer and publisher in his own right. In 1929 he set up the Tamil magazine Munnetram\n and Tamil Murasu in 1935. Through his writings he promoted the principles of the Tamil reform movement. He encouraged Tamils to make Singapore their home\n helped them gain citizenship and championed for the cause of the Tamil language to be recognised as one of the national languages in Singapore. This is a collection of archival photographs\n documents donated by the family of Sarangapany’s close associate\n Murugu Srinivasan.","createdDate":"20201018182635","version":0,"latest":false,"roles":[],"metadata":{"accession_no_csv":"2015-00554","Image":"","object_work_type":"cards (information artefacts)","title_text":"14th year anniversary rally for the late Mr G Sarangapany","preference":"main","title_language":"","creator_2":"Viknesh Printings","creator_1":"Not indicated","creator_role":"printers (people)","creation_date":"1988","creation_place_original_location":"Singapore","styles_periods_indexing_terms":"Not indicated","inscriptions":"","inscription_language":"","scale_type":"Not indicated","shape":"rectangular","materials_name":"printing paper","techniques_name":"printing (process)","object_colour":"black-and-white (colours)","physical_appearance":"\"The image shows a rectangular card. It was a border where a picture and several lines of Tamil scripts are displayed within. \"\"7-5-1988\"\" is stated at the top. The picture shows a man who is dressed in a long sleeved shirt and sarong. \"\"Viknesh printings blk 1002 #03-1457 Lor 8 Toa Payoh S\u0027pore Tel: 2504921\"\" is displayed at the bottom outside the border. \"","subject_terms_1":"rallies anniversaries founders (originators) reformers","subject_terms_2":"Caran?kapa?n?i, 1903-1974 Reformers Demonstrations Anniversaries","subject_terms_3":"Thamizhavel Govindasamy Sarangapany Pioneers","sgcool_label_text":"G Sarangapany, titled Thamizhavel, arrived in Singapore in 1924. A believer of Periyar’s principles, he played a key role in extending the Self-Respect Movement to Singapore and Malaya and became the agent for distribution of the movement’s magazine Kudi Arasu in British Malaya. He later helped arrange Periyar’s visits to Singapore and Malaya. \r\n\r\nHe was an active writer and publisher in his own right. In 1929 he set up the Tamil magazine Munnetram, and Tamil Murasu in 1935. Through his writings he promoted the principles of the Tamil reform movement. He encouraged Tamils to make Singapore their home, helped them gain citizenship and championed for the cause of the Tamil language to be recognised as one of the national languages in Singapore. This is a collection of archival photographs, documents donated by the family of Sarangapany’s close associate, Murugu Srinivasan."},"nlpDate":"20201018182635","connectorId":0,"tags":{}}