{
  "id": "2015-00528",
  "title": "Turban Pin",
  "source": "Bumblebee",
  "path": "./Data/json/",
  "content": "\n  accession_no_csv: 2015-00528\n\n  Image: \n\n  object_work_type: pins (jewellery)\n\n  title_text: Turban Pin\n\n  preference: main\n\n  title_language: \n\n  creator_2: Unknown\n\n  creation_date: 20th century\n\n  creation_place_original_location: India Singapore Malaysia\n\n  styles_periods_indexing_terms: Not indicated\n\n  inscriptions: \n\n  inscription_language: \n\n  scale_type: Not indicated\n\n  shape: irregular\n\n  materials_name: gold (metal)\n\n  techniques_name: forming (physical activity)\n\n  object_colour: gold (colour)\n\n  physical_appearance: The image shows a turban pin. It is gold in colour. The pin is shaped to be a peacock. The tips of the peacock-shaped ornament wings are pointy and the gold wires are formed into four circles. The peacock-shaped ornament is fashioned to be upright.\n\n  subject_terms_1: filigree jewellery ornaments (object genre) goldwork (visual works) decorative art (art genre) worn costume accessories turbans Pavo (genus)\n\n  subject_terms_2: Filigree Ethnic jewellery Gold jewellery Goldwork Dress accessories Turbans Peacocks\n\n  subject_terms_3: Jewellery Indian costumes\n\n  sgcool_label_text: Traditional south Indian jewellery is usually crafted to complement the shape and structure of the parts of the body\n from head to toe. This is an unusual gold filigree turban ornament in the shape of a peacock. This an heirloom collected by Dr. R. D. Gangatharan’s family.\n",
  "createdDate": "20201120223706",
  "version": 0,
  "latest": false,
  "roles": [],
  "metadata": {
    "accession_no_csv": "2015-00528",
    "Image": "",
    "object_work_type": "pins (jewellery)",
    "title_text": "Turban Pin",
    "preference": "main",
    "title_language": "",
    "creator_2": "Unknown",
    "creation_date": "20th century",
    "creation_place_original_location": "India Singapore Malaysia",
    "styles_periods_indexing_terms": "Not indicated",
    "inscriptions": "",
    "inscription_language": "",
    "scale_type": "Not indicated",
    "shape": "irregular",
    "materials_name": "gold (metal)",
    "techniques_name": "forming (physical activity)",
    "object_colour": "gold (colour)",
    "physical_appearance": "The image shows a turban pin. It is gold in colour. The pin is shaped to be a peacock. The tips of the peacock-shaped ornament wings are pointy and the gold wires are formed into four circles. The peacock-shaped ornament is fashioned to be upright.",
    "subject_terms_1": "filigree jewellery ornaments (object genre) goldwork (visual works) decorative art (art genre) worn costume accessories turbans Pavo (genus)",
    "subject_terms_2": "Filigree Ethnic jewellery Gold jewellery Goldwork Dress accessories Turbans Peacocks",
    "subject_terms_3": "Jewellery Indian costumes",
    "sgcool_label_text": "Traditional south Indian jewellery is usually crafted to complement the shape and structure of the parts of the body, from head to toe. This is an unusual gold filigree turban ornament in the shape of a peacock. This an heirloom collected by Dr. R. D. Gangatharan’s family."
  },
  "nlpDate": "20201120223706",
  "connectorId": 0,
  "tags": {}
}