{
  "id": "2015-00559",
  "title": "Tamil Murasu National Day Supplement",
  "source": "Bumblebee",
  "path": "./Data/json/",
  "content": "\n  accession_no_csv: 2015-00559\n\n  Image: \n\n  object_work_type: supplements (document genre)\n\n  title_text: Tamil Murasu National Day Supplement\n\n  preference: main\n\n  title_language: \n\n  creator_2: Tamil Murasu\n\n  creator_1: Not indicated\n\n  creator_role: publishers\n\n  creation_date: 20th century\n\n  creation_place_original_location: Singapore\n\n  styles_periods_indexing_terms: Not indicated\n\n  inscriptions: \n\n  inscription_language: \n\n  scale_type: Not indicated\n\n  shape: rectangular\n\n  materials_name: printing paper\n\n  techniques_name: printing (process)\n\n  object_colour: black-and-white (colours)\n\n  physical_appearance: The image shows a document. It is rectangular in shape. There are two paragraphs of Tamil scripts typewritten onto the document.\n\n  subject_terms_1: newspapers national holidays\n\n  subject_terms_2: Tamil newspapers Singaporean newspapers National Day (Singapore)\n\n  subject_terms_3: Daily newspapers National holidays\n\n  sgcool_label_text: G Sarangapany\n titled Thamizhavel\n arrived in Singapore in 1924. A believer of Periyar’s principles\n he played a key role in extending the Self-Respect Movement to Singapore and Malaya and became the agent for distribution of the movement’s magazine Kudi Arasu in British Malaya. He later helped arrange Periyar’s visits to Singapore and Malaya. \\r\\n\\r\\nHe was an active writer and publisher in his own right. In 1929 he set up the Tamil magazine Munnetram\n and Tamil Murasu in 1935. Through his writings he promoted the principles of the Tamil reform movement. He encouraged Tamils to make Singapore their home\n helped them gain citizenship and championed for the cause of the Tamil language to be recognised as one of the national languages in Singapore. This is a collection of archival photographs\n documents donated by the family of Sarangapany’s close associate\n Murugu Srinivasan.\n",
  "createdDate": "20201120223706",
  "version": 0,
  "latest": false,
  "roles": [],
  "metadata": {
    "accession_no_csv": "2015-00559",
    "Image": "",
    "object_work_type": "supplements (document genre)",
    "title_text": "Tamil Murasu National Day Supplement",
    "preference": "main",
    "title_language": "",
    "creator_2": "Tamil Murasu",
    "creator_1": "Not indicated",
    "creator_role": "publishers",
    "creation_date": "20th century",
    "creation_place_original_location": "Singapore",
    "styles_periods_indexing_terms": "Not indicated",
    "inscriptions": "",
    "inscription_language": "",
    "scale_type": "Not indicated",
    "shape": "rectangular",
    "materials_name": "printing paper",
    "techniques_name": "printing (process)",
    "object_colour": "black-and-white (colours)",
    "physical_appearance": "The image shows a document. It is rectangular in shape. There are two paragraphs of Tamil scripts typewritten onto the document.",
    "subject_terms_1": "newspapers national holidays",
    "subject_terms_2": "Tamil newspapers Singaporean newspapers National Day (Singapore)",
    "subject_terms_3": "Daily newspapers National holidays",
    "sgcool_label_text": "G Sarangapany, titled Thamizhavel, arrived in Singapore in 1924. A believer of Periyar’s principles, he played a key role in extending the Self-Respect Movement to Singapore and Malaya and became the agent for distribution of the movement’s magazine Kudi Arasu in British Malaya. He later helped arrange Periyar’s visits to Singapore and Malaya. \r\n\r\nHe was an active writer and publisher in his own right. In 1929 he set up the Tamil magazine Munnetram, and Tamil Murasu in 1935. Through his writings he promoted the principles of the Tamil reform movement. He encouraged Tamils to make Singapore their home, helped them gain citizenship and championed for the cause of the Tamil language to be recognised as one of the national languages in Singapore. This is a collection of archival photographs, documents donated by the family of Sarangapany’s close associate, Murugu Srinivasan."
  },
  "nlpDate": "20201120223706",
  "connectorId": 0,
  "tags": {}
}