{
  "id": "2015-00562",
  "title": "Tamils Festival Book",
  "source": "Bumblebee",
  "path": "./Data/json/",
  "content": "\n  accession_no_csv: 2015-00562\n\n  Image: \n\n  object_work_type: books\n\n  title_text: Tamils Festival Book\n\n  preference: main\n\n  title_language: \n\n  creator_2: Unknown\n\n  creation_date: 1974\n\n  creation_place_original_location: Singapore\n\n  styles_periods_indexing_terms: Not indicated\n\n  inscriptions: \n\n  inscription_language: \n\n  scale_type: Not indicated\n\n  shape: rectangular\n\n  materials_name: printing paper\n\n  techniques_name: printing (process)\n\n  object_colour: multicoloured\n\n  physical_appearance: \\The image shows the front cover of a book. It has a predominantly grey background and a green patterned border. \\\\Tamils Festival 1974\n\n  subject_terms_1: at National Theatre at 7.00 P.M. on Monday ethnic groups\n\n  subject_terms_2: Tamil (Indic people) 14th January 1974\\\\ is stated at the middle. There are several lines of Tamil scripts. \\ Ethnic festivals\n\n  subject_terms_3: festivals National Theatre (Singapore)\n\n  subject_terms_4: Books\n\n  context_1: Ethnic festivals\n",
  "createdDate": "20201125084543",
  "version": 0,
  "latest": false,
  "roles": [],
  "metadata": {
    "accession_no_csv": "2015-00562",
    "Image": "",
    "object_work_type": "books",
    "title_text": "Tamils Festival Book",
    "preference": "main",
    "title_language": "",
    "creator_2": "Unknown",
    "creation_date": "1974",
    "creation_place_original_location": "Singapore",
    "styles_periods_indexing_terms": "Not indicated",
    "inscriptions": "",
    "inscription_language": "",
    "scale_type": "Not indicated",
    "shape": "rectangular",
    "materials_name": "printing paper",
    "techniques_name": "printing (process)",
    "object_colour": "multicoloured",
    "physical_appearance": "\"The image shows the front cover of a book. It has a predominantly grey background and a green patterned border. \"\"Tamils Festival 1974",
    "subject_terms_1": "at National Theatre at 7.00 P.M. on Monday ethnic groups",
    "subject_terms_2": "Tamil (Indic people) 14th January 1974\"\" is stated at the middle. There are several lines of Tamil scripts. \" Ethnic festivals",
    "subject_terms_3": "festivals National Theatre (Singapore)",
    "subject_terms_4": "Books",
    "context_1": "Ethnic festivals"
  },
  "nlpDate": "20201125084543",
  "connectorId": 0,
  "tags": {}
}