{"id":"2015-00004","title":"National Service Call-Up Notice","source":"Bumblebee","path":"./Data/json/","content":"accession_no_csv:2015-00004\nImage:\nobject_work_type:documents (object genre)\ntitle_text:National Service Call-Up Notice\npreference:main\ntitle_language:\ncreator_2:MINDEF Central Manpower Base\ncreator_1:Not indicated\ncreator_role:creators\ncreation_date:October 2nd\n 1969\ncreation_place_original_location:Singapore\ninscriptions:\ninscription_language:\nshape:rectangular\nmaterials_name:paper (fiber product)\ntechniques_name:printing (process)\nobject_colour:grey (colour)\nphysical_appearance:\\The image shows a document. There are two punched holes on its left hand side. The address of \\\\William Oh\\\\ is displayed above the title of the notice. The title of the notice is \\\\National Service Call-up (Full Time) Community Centres\\\\ and it is underlined. There are four paragraphs written in English\nsubject_terms_1:followed by three paragraphs written in the Chinese language. The date \\\\20.10.69\\\\ is stated in purple. The coat-of-arms of the \\\\Central Manpower Base military service parties (events)\nsubject_terms_2:Kallang Draft parties\nsubject_terms_3:Singapore 14\\\\ is stamped at the upper right hand side of the document in purple.\\\nsubject_terms_4:armed forces\ncontext_1:Recruiting and enlistment","createdDate":"20201018182635","version":0,"latest":false,"roles":[],"metadata":{"accession_no_csv":"2015-00004","Image":"","object_work_type":"documents (object genre)","title_text":"National Service Call-Up Notice","preference":"main","title_language":"","creator_2":"MINDEF Central Manpower Base","creator_1":"Not indicated","creator_role":"creators","creation_date":"October 2nd, 1969","creation_place_original_location":"Singapore","inscriptions":"","inscription_language":"","shape":"rectangular","materials_name":"paper (fiber product)","techniques_name":"printing (process)","object_colour":"grey (colour)","physical_appearance":"\"The image shows a document. There are two punched holes on its left hand side. The address of \"\"William Oh\"\" is displayed above the title of the notice. The title of the notice is \"\"National Service Call-up (Full Time) Community Centres\"\" and it is underlined. There are four paragraphs written in English","subject_terms_1":"followed by three paragraphs written in the Chinese language. The date \"\"20.10.69\"\" is stated in purple. The coat-of-arms of the \"\"Central Manpower Base military service parties (events)","subject_terms_2":"Kallang Draft parties","subject_terms_3":"Singapore 14\"\" is stamped at the upper right hand side of the document in purple.\"","subject_terms_4":"armed forces","context_1":"Recruiting and enlistment"},"nlpDate":"20201018182635","connectorId":0,"tags":{}}