{"id":"2015-00520","title":"Sari","source":"Bumblebee","path":"./Data/json/","content":"accession_no_csv:2015-00520\nImage:\nobject_work_type:saris (garments)\ntitle_text:Sari\npreference:main\ntitle_language:\ncreator_2:Unknown\ncreation_date:20th century\ncreation_place_original_location:Singapore Malaysia\nstyles_periods_indexing_terms:Not indicated\ninscriptions:\ninscription_language:\nscale_type:Not indicated\nshape:rectangular\nmaterials_name:silk (textile)\ntechniques_name:machine sewing (technique) weaving\nobject_colour:multicoloured\nphysical_appearance:The image shows a sari. It is rectangular in shape. It has a red border and a lilac centre. The red border is decorated with a floral motif. Small white circles are present within the border of the sari. The numerous crease lines on the sari can be discerned. There are red and green tassels extending from the left hand side of the sari.\nsubject_terms_1:womenswear folk costume floral patterns geometric motifs\nsubject_terms_2:Ethnic costume Saris Women\\u0027s clothing Motifs\nsubject_terms_3:Indian costumes\nsgcool_label_text:The sari is a traditional pan-Indian drape\n woven in various parts of the sub-continent. Kanchipuram in Tamil Nadu\n an illustrious weaving centre\n is renowned for the “Kanchivaram Silk Sari”\n worn during special occasions as well as by Tamil brides. This collection of saris were donated by Dr.R.D.Gangatharan in memory of his mother\n the late Lakshmi Rangasamy Davar. Lakshmi Rangasamy Davar\n was a woman pioneer – she was an educationist\n musician and philanthropist.","createdDate":"20201018182635","version":0,"latest":false,"roles":[],"metadata":{"accession_no_csv":"2015-00520","Image":"","object_work_type":"saris (garments)","title_text":"Sari","preference":"main","title_language":"","creator_2":"Unknown","creation_date":"20th century","creation_place_original_location":"Singapore Malaysia","styles_periods_indexing_terms":"Not indicated","inscriptions":"","inscription_language":"","scale_type":"Not indicated","shape":"rectangular","materials_name":"silk (textile)","techniques_name":"machine sewing (technique) weaving","object_colour":"multicoloured","physical_appearance":"The image shows a sari. It is rectangular in shape. It has a red border and a lilac centre. The red border is decorated with a floral motif. Small white circles are present within the border of the sari. The numerous crease lines on the sari can be discerned. There are red and green tassels extending from the left hand side of the sari.","subject_terms_1":"womenswear folk costume floral patterns geometric motifs","subject_terms_2":"Ethnic costume Saris Women\u0027s clothing Motifs","subject_terms_3":"Indian costumes","sgcool_label_text":"The sari is a traditional pan-Indian drape, woven in various parts of the sub-continent. Kanchipuram in Tamil Nadu, an illustrious weaving centre, is renowned for the “Kanchivaram Silk Sari”, worn during special occasions as well as by Tamil brides. This collection of saris were donated by Dr.R.D.Gangatharan in memory of his mother, the late Lakshmi Rangasamy Davar. Lakshmi Rangasamy Davar, was a woman pioneer – she was an educationist, musician and philanthropist."},"nlpDate":"20201018182635","connectorId":0,"tags":{}}