{"id":"2015-00564","title":"Tamil Murasu Annual","source":"Bumblebee","path":"./Data/json/","content":"accession_no_csv:2015-00564\nImage:\nobject_work_type:annuals (publications)\ntitle_text:Tamil Murasu Annual\npreference:main\ntitle_language:\ncreator_2:Tamil Murasu K. Madhavan\ncreator_1:NA Not indicated\ncreator_role:publishers artists (visual artists)\ncreation_date:1958\ncreation_place_original_location:Singapore\nstyles_periods_indexing_terms:Not indicated\ninscriptions:\ninscription_language:\nscale_type:Not indicated\nshape:rectangular\nmaterials_name:printing paper\ntechniques_name:printing (process)\nobject_colour:multicoloured\nphysical_appearance:\\The image shows two sets of newspaper publications. The one on the left hand side has a black-and-white image of a painting. The one on the right hand side has the same painting\n but in colour. The painting depicts a man and a lady. The lady is unconscious and the man is holding her in his arms. The man has a quiver filled with arrows slung around his back. \\\\Tamil Murasu Annual 1958\\\\ is displayed at the bottom of both publications. \\\\K. Madhavan\\\\ is displayed at the bottom left hand corner of the publication to the right. Tamil scripts are displayed at the top of both publications. \\\nsubject_terms_1:newspapers paintings (visual works) ethnic groups\nsubject_terms_2:Tamil newspapers Paintings Tamil (Indic people) Singaporean newspapers\nsubject_terms_3:Daily newspapers Visual Arts Painting\nsgcool_label_text:G Sarangapany\n titled Thamizhavel\n arrived in Singapore in 1924. A believer of Periyar’s principles\n he played a key role in extending the Self-Respect Movement to Singapore and Malaya and became the agent for distribution of the movement’s magazine Kudi Arasu in British Malaya. He later helped arrange Periyar’s visits to Singapore and Malaya. \\r\\n\\r\\nHe was an active writer and publisher in his own right. In 1929 he set up the Tamil magazine Munnetram\n and Tamil Murasu in 1935. Through his writings he promoted the principles of the Tamil reform movement. He encouraged Tamils to make Singapore their home\n helped them gain citizenship and championed for the cause of the Tamil language to be recognised as one of the national languages in Singapore. This is a collection of archival photographs\n documents donated by the family of Sarangapany’s close associate\n Murugu Srinivasan.","createdDate":"20201018182635","version":0,"latest":false,"roles":[],"metadata":{"accession_no_csv":"2015-00564","Image":"","object_work_type":"annuals (publications)","title_text":"Tamil Murasu Annual","preference":"main","title_language":"","creator_2":"Tamil Murasu K. Madhavan","creator_1":"NA Not indicated","creator_role":"publishers artists (visual artists)","creation_date":"1958","creation_place_original_location":"Singapore","styles_periods_indexing_terms":"Not indicated","inscriptions":"","inscription_language":"","scale_type":"Not indicated","shape":"rectangular","materials_name":"printing paper","techniques_name":"printing (process)","object_colour":"multicoloured","physical_appearance":"\"The image shows two sets of newspaper publications. The one on the left hand side has a black-and-white image of a painting. The one on the right hand side has the same painting, but in colour. The painting depicts a man and a lady. The lady is unconscious and the man is holding her in his arms. The man has a quiver filled with arrows slung around his back. \"\"Tamil Murasu Annual 1958\"\" is displayed at the bottom of both publications. \"\"K. Madhavan\"\" is displayed at the bottom left hand corner of the publication to the right. Tamil scripts are displayed at the top of both publications. \"","subject_terms_1":"newspapers paintings (visual works) ethnic groups","subject_terms_2":"Tamil newspapers Paintings Tamil (Indic people) Singaporean newspapers","subject_terms_3":"Daily newspapers Visual Arts Painting","sgcool_label_text":"G Sarangapany, titled Thamizhavel, arrived in Singapore in 1924. A believer of Periyar’s principles, he played a key role in extending the Self-Respect Movement to Singapore and Malaya and became the agent for distribution of the movement’s magazine Kudi Arasu in British Malaya. He later helped arrange Periyar’s visits to Singapore and Malaya. \r\n\r\nHe was an active writer and publisher in his own right. In 1929 he set up the Tamil magazine Munnetram, and Tamil Murasu in 1935. Through his writings he promoted the principles of the Tamil reform movement. He encouraged Tamils to make Singapore their home, helped them gain citizenship and championed for the cause of the Tamil language to be recognised as one of the national languages in Singapore. This is a collection of archival photographs, documents donated by the family of Sarangapany’s close associate, Murugu Srinivasan."},"nlpDate":"20201018182635","connectorId":0,"tags":{}}