{
  "id": "2015-00539",
  "title": "Marriage certificate",
  "source": "Bumblebee",
  "path": "./Data/json/",
  "content": "\n  accession_no_csv: 2015-00539\n\n  Image: \n\n  object_work_type: marriage certificates\n\n  title_text: Marriage certificate\n\n  preference: main\n\n  title_language: \n\n  creator_2: Unknown\n\n  creation_date: 12-Dec-46\n\n  creation_place_original_location: Singapore\n\n  styles_periods_indexing_terms: Not indicated\n\n  inscriptions: \n\n  inscription_language: \n\n  scale_type: Not indicated\n\n  shape: rectangular\n\n  materials_name: printing paper\n\n  techniques_name: printing (process)\n\n  object_colour: grey (colour)\n\n  physical_appearance: \\The image shows a certificate. It consists of typewritten and handwritten words. \\\\Marriage agreement\\\\ is stated at the top. The particulars and signatures of the bridge and bridgegroom\n\n  subject_terms_1: together with the details on the marriage legal documents certification\n\n  subject_terms_2: Legal documents are stated below the title. \\ Certification\n\n  subject_terms_3: marriage (social construct)\n\n  subject_terms_4: Marriage\n",
  "createdDate": "20201125084544",
  "version": 0,
  "latest": false,
  "roles": [],
  "metadata": {
    "accession_no_csv": "2015-00539",
    "Image": "",
    "object_work_type": "marriage certificates",
    "title_text": "Marriage certificate",
    "preference": "main",
    "title_language": "",
    "creator_2": "Unknown",
    "creation_date": "12-Dec-46",
    "creation_place_original_location": "Singapore",
    "styles_periods_indexing_terms": "Not indicated",
    "inscriptions": "",
    "inscription_language": "",
    "scale_type": "Not indicated",
    "shape": "rectangular",
    "materials_name": "printing paper",
    "techniques_name": "printing (process)",
    "object_colour": "grey (colour)",
    "physical_appearance": "\"The image shows a certificate. It consists of typewritten and handwritten words. \"\"Marriage agreement\"\" is stated at the top. The particulars and signatures of the bridge and bridgegroom",
    "subject_terms_1": "together with the details on the marriage legal documents certification",
    "subject_terms_2": "Legal documents are stated below the title. \" Certification",
    "subject_terms_3": "marriage (social construct)",
    "subject_terms_4": "Marriage"
  },
  "nlpDate": "20201125084544",
  "connectorId": 0,
  "tags": {}
}