{"id":"2015-00566","title":"Tamil Murasu","source":"Bumblebee","path":"./Data/json/","content":"accession_no_csv:2015-00566\nImage:\nobject_work_type:clippings (information artefacts)\ntitle_text:Tamil Murasu\npreference:main\ntitle_language:\ncreator_2:Tamil Murasu\ncreator_role:publishers\ncreation_date:19-Mar-74\ncreation_place_original_location:Singapore\nstyles_periods_indexing_terms:Not indicated\ninscriptions:\ninscription_language:\nscale_type:Not indicated\nshape:rectangular\nmaterials_name:printing paper\ntechniques_name:printing (process)\nobject_colour:black-and-white (colours)\nphysical_appearance:The image shows a clipping. There are four images depicting groups of people on the clipping. The headlines and texts are all written entirely in Tamil script.\nsubject_terms_1:newspapers ethnic groups\nsubject_terms_2:Tamil newspapers Clippings (Books\n newspapers\n etc.) Singaporean newspapers Tamil (Indic people)\nsubject_terms_3:Daily newspapers\nsgcool_label_text:G Sarangapany\n titled Thamizhavel\n arrived in Singapore in 1924. A believer of Periyar’s principles\n he played a key role in extending the Self-Respect Movement to Singapore and Malaya and became the agent for distribution of the movement’s magazine Kudi Arasu in British Malaya. He later helped arrange Periyar’s visits to Singapore and Malaya. \\r\\n\\r\\nHe was an active writer and publisher in his own right. In 1929 he set up the Tamil magazine Munnetram\n and Tamil Murasu in 1935. Through his writings he promoted the principles of the Tamil reform movement. He encouraged Tamils to make Singapore their home\n helped them gain citizenship and championed for the cause of the Tamil language to be recognised as one of the national languages in Singapore. This is a collection of archival photographs\n documents donated by the family of Sarangapany’s close associate\n Murugu Srinivasan.","createdDate":"20201018182635","version":0,"latest":false,"roles":[],"metadata":{"accession_no_csv":"2015-00566","Image":"","object_work_type":"clippings (information artefacts)","title_text":"Tamil Murasu","preference":"main","title_language":"","creator_2":"Tamil Murasu","creator_role":"publishers","creation_date":"19-Mar-74","creation_place_original_location":"Singapore","styles_periods_indexing_terms":"Not indicated","inscriptions":"","inscription_language":"","scale_type":"Not indicated","shape":"rectangular","materials_name":"printing paper","techniques_name":"printing (process)","object_colour":"black-and-white (colours)","physical_appearance":"The image shows a clipping. There are four images depicting groups of people on the clipping. The headlines and texts are all written entirely in Tamil script.","subject_terms_1":"newspapers ethnic groups","subject_terms_2":"Tamil newspapers Clippings (Books, newspapers, etc.) Singaporean newspapers Tamil (Indic people)","subject_terms_3":"Daily newspapers","sgcool_label_text":"G Sarangapany, titled Thamizhavel, arrived in Singapore in 1924. A believer of Periyar’s principles, he played a key role in extending the Self-Respect Movement to Singapore and Malaya and became the agent for distribution of the movement’s magazine Kudi Arasu in British Malaya. He later helped arrange Periyar’s visits to Singapore and Malaya. \r\n\r\nHe was an active writer and publisher in his own right. In 1929 he set up the Tamil magazine Munnetram, and Tamil Murasu in 1935. Through his writings he promoted the principles of the Tamil reform movement. He encouraged Tamils to make Singapore their home, helped them gain citizenship and championed for the cause of the Tamil language to be recognised as one of the national languages in Singapore. This is a collection of archival photographs, documents donated by the family of Sarangapany’s close associate, Murugu Srinivasan."},"nlpDate":"20201018182635","connectorId":0,"tags":{}}