{"id":"2015-00545","title":"Tamil Murasu - Tamilar Thirunaal Sirappu Ithal","source":"Bumblebee","path":"./Data/json/","content":"accession_no_csv:2015-00545\nImage:\nobject_work_type:newspapers\ntitle_text:Tamil Murasu - Tamilar Thirunaal Sirappu Ithal\npreference:main\ntitle_language:\ncreator_2:Tamil Murasu\ncreator_role:publishers\ncreation_date:14-Jan-56\ncreation_place_original_location:Singapore\nstyles_periods_indexing_terms:Not indicated\ninscriptions:\ninscription_language:\nscale_type:Not indicated\nshape:rectangular\nmaterials_name:printing paper\ntechniques_name:printing (process)\nobject_colour:black-and-white (colours)\nphysical_appearance:\\The image displays the front page of a newspaper. There is a noticeable horizontal line passing the centre of the newspaper\n indicating the point at which the newspaper had been folded. The entire page is written in the Tamil script. \\\\14-1-1956\\\\ is stated at the upper left hand side. The centre of the page features a photograph of three men. They are dressed formally and looking towards the direction in which the photograph was captured.\\\nsubject_terms_1:dailies (publications) Hinduism festivals\nsubject_terms_2:Tamil newspapers Singaporean newspapers Tamil (Indic people) Harvest festivals Hinduism\nsubject_terms_3:Daily newspapers Ethnic festivals Religious festivals Hinduism\ncontext_1:Thai Pongal 1956\ncontext_2:harvest festivals\ncontext_3:14 - 17 Jan 1956\ncontext_4:19560114\ncontext_5:19560117\ncontext_6:Singapore\nsgcool_label_text:G Sarangapany\n titled Thamizhavel\n arrived in Singapore in 1924. A believer of Periyar’s principles\n he played a key role in extending the Self-Respect Movement to Singapore and Malaya and became the agent for distribution of the movement’s magazine Kudi Arasu in British Malaya. He later helped arrange Periyar’s visits to Singapore and Malaya. \\r\\n\\r\\nHe was an active writer and publisher in his own right. In 1929 he set up the Tamil magazine Munnetram\n and Tamil Murasu in 1935. Through his writings he promoted the principles of the Tamil reform movement. He encouraged Tamils to make Singapore their home\n helped them gain citizenship and championed for the cause of the Tamil language to be recognised as one of the national languages in Singapore. This is a collection of archival photographs\n documents donated by the family of Sarangapany’s close associate\n Murugu Srinivasan.","createdDate":"20201119143405","version":0,"latest":false,"roles":[],"metadata":{"accession_no_csv":"2015-00545","Image":"","object_work_type":"newspapers","title_text":"Tamil Murasu - Tamilar Thirunaal Sirappu Ithal","preference":"main","title_language":"","creator_2":"Tamil Murasu","creator_role":"publishers","creation_date":"14-Jan-56","creation_place_original_location":"Singapore","styles_periods_indexing_terms":"Not indicated","inscriptions":"","inscription_language":"","scale_type":"Not indicated","shape":"rectangular","materials_name":"printing paper","techniques_name":"printing (process)","object_colour":"black-and-white (colours)","physical_appearance":"\"The image displays the front page of a newspaper. There is a noticeable horizontal line passing the centre of the newspaper, indicating the point at which the newspaper had been folded. The entire page is written in the Tamil script. \"\"14-1-1956\"\" is stated at the upper left hand side. The centre of the page features a photograph of three men. They are dressed formally and looking towards the direction in which the photograph was captured.\"","subject_terms_1":"dailies (publications) Hinduism festivals","subject_terms_2":"Tamil newspapers Singaporean newspapers Tamil (Indic people) Harvest festivals Hinduism","subject_terms_3":"Daily newspapers Ethnic festivals Religious festivals Hinduism","context_1":"Thai Pongal 1956","context_2":"harvest festivals","context_3":"14 - 17 Jan 1956","context_4":"19560114","context_5":"19560117","context_6":"Singapore","sgcool_label_text":"G Sarangapany, titled Thamizhavel, arrived in Singapore in 1924. A believer of Periyar’s principles, he played a key role in extending the Self-Respect Movement to Singapore and Malaya and became the agent for distribution of the movement’s magazine Kudi Arasu in British Malaya. He later helped arrange Periyar’s visits to Singapore and Malaya. \r\n\r\nHe was an active writer and publisher in his own right. In 1929 he set up the Tamil magazine Munnetram, and Tamil Murasu in 1935. Through his writings he promoted the principles of the Tamil reform movement. He encouraged Tamils to make Singapore their home, helped them gain citizenship and championed for the cause of the Tamil language to be recognised as one of the national languages in Singapore. This is a collection of archival photographs, documents donated by the family of Sarangapany’s close associate, Murugu Srinivasan."},"nlpDate":"20201119143405","connectorId":0,"tags":{}}