{
  "id": "2015-00526",
  "title": "Sari",
  "source": "Bumblebee",
  "path": "./Data/json/",
  "content": "\n  accession_no_csv: 2015-00526\n\n  Image: \n\n  object_work_type: saris (garments)\n\n  title_text: Sari\n\n  preference: main\n\n  title_language: \n\n  creator_2: Unknown\n\n  creation_date: 20th century\n\n  creation_place_original_location: Malaysia Singapore\n\n  styles_periods_indexing_terms: Not indicated\n\n  inscriptions: \n\n  inscription_language: \n\n  scale_type: Not indicated\n\n  shape: rectangular\n\n  materials_name: silk (textile)\n\n  techniques_name: weaving machine sewing (technique)\n\n  object_colour: multicoloured\n\n  physical_appearance: The image shows two parts of a sari. Both are rectangular in shape\n with the first part at the top being bigger than the second one at the bottom. They are predominantly green in colour\n with yellow borders at the top and bottom for the first part of the garment\n and at the sides for the second part of the garment. There are floral patterns in these yellow borders. Checked patterns can be seen all over the green region of both garments. There are green tassels extending from the right hand side of the first garment\n and also from the top and bottom sides of the second garment.\n\n  subject_terms_1: womenswear checker pattern floral patterns folk costume allover patterns\n\n  subject_terms_2: Women\\u0027s clothing Motifs Saris Ethnic costume\n\n  subject_terms_3: Indian costumes\n\n  sgcool_label_text: The sari is a traditional pan-Indian drape\n woven in various parts of the sub-continent. Kanchipuram in Tamil Nadu\n an illustrious weaving centre\n is renowned for the “Kanchivaram Silk Sari”\n worn during special occasions as well as by Tamil brides. This collection of saris were donated by Dr.R.D.Gangatharan in memory of his mother\n the late Lakshmi Rangasamy Davar. Lakshmi Rangasamy Davar\n was a woman pioneer – she was an educationist\n musician and philanthropist.\n",
  "createdDate": "20201201203309",
  "version": 0,
  "latest": false,
  "roles": [],
  "metadata": {
    "accession_no_csv": "2015-00526",
    "Image": "",
    "object_work_type": "saris (garments)",
    "title_text": "Sari",
    "preference": "main",
    "title_language": "",
    "creator_2": "Unknown",
    "creation_date": "20th century",
    "creation_place_original_location": "Malaysia Singapore",
    "styles_periods_indexing_terms": "Not indicated",
    "inscriptions": "",
    "inscription_language": "",
    "scale_type": "Not indicated",
    "shape": "rectangular",
    "materials_name": "silk (textile)",
    "techniques_name": "weaving machine sewing (technique)",
    "object_colour": "multicoloured",
    "physical_appearance": "The image shows two parts of a sari. Both are rectangular in shape, with the first part at the top being bigger than the second one at the bottom. They are predominantly green in colour, with yellow borders at the top and bottom for the first part of the garment, and at the sides for the second part of the garment. There are floral patterns in these yellow borders. Checked patterns can be seen all over the green region of both garments. There are green tassels extending from the right hand side of the first garment, and also from the top and bottom sides of the second garment.",
    "subject_terms_1": "womenswear checker pattern floral patterns folk costume allover patterns",
    "subject_terms_2": "Women\u0027s clothing Motifs Saris Ethnic costume",
    "subject_terms_3": "Indian costumes",
    "sgcool_label_text": "The sari is a traditional pan-Indian drape, woven in various parts of the sub-continent. Kanchipuram in Tamil Nadu, an illustrious weaving centre, is renowned for the “Kanchivaram Silk Sari”, worn during special occasions as well as by Tamil brides. This collection of saris were donated by Dr.R.D.Gangatharan in memory of his mother, the late Lakshmi Rangasamy Davar. Lakshmi Rangasamy Davar, was a woman pioneer – she was an educationist, musician and philanthropist."
  },
  "nlpDate": "20201201203309",
  "connectorId": 0,
  "tags": {}
}