{
  "id": "2015-00548",
  "title": "Poster for Bukit Merah Tamilar Thirunaal",
  "source": "Bumblebee",
  "path": "./Data/json/",
  "content": "\n  accession_no_csv: 2015-00548\n\n  Image: \n\n  object_work_type: posters\n\n  title_text: Poster for Bukit Merah Tamilar Thirunaal\n\n  preference: main\n\n  title_language: \n\n  creator_2: Unknown\n\n  creation_date: 14-Feb-67\n\n  creation_place_original_location: Singapore\n\n  styles_periods_indexing_terms: Not indicated\n\n  inscriptions: \n\n  inscription_language: \n\n  scale_type: Not indicated\n\n  shape: rectangular\n\n  materials_name: printing paper\n\n  techniques_name: printing (process)\n\n  object_colour: black-and-white (colours)\n\n  physical_appearance: \\The image displays a poster. There is a rectangular border. Within this border\n the contents in the poster are written entirely in the Tamil script. \\\\14-2-1965\\\\ is stated in the first paragraph. \\\n\n  subject_terms_1: Hinduism festivals\n\n  subject_terms_2: Posters Bukit Merah (Singapore) Harvest festivals Hinduism\n\n  subject_terms_3: Ethnic festivals Religious festivals Hinduism Bukit Merah\n\n  context_1: Thai Pongal 1967\n\n  context_2: harvest festivals\n\n  context_3: 14-Feb-67\n\n  context_4: 19670214\n\n  context_5: 19670214\n\n  sgcool_label_text: G Sarangapany\n titled Thamizhavel\n arrived in Singapore in 1924. A believer of Periyar’s principles\n he played a key role in extending the Self-Respect Movement to Singapore and Malaya and became the agent for distribution of the movement’s magazine Kudi Arasu in British Malaya. He later helped arrange Periyar’s visits to Singapore and Malaya. \\r\\n\\r\\nHe was an active writer and publisher in his own right. In 1929 he set up the Tamil magazine Munnetram\n and Tamil Murasu in 1935. Through his writings he promoted the principles of the Tamil reform movement. He encouraged Tamils to make Singapore their home\n helped them gain citizenship and championed for the cause of the Tamil language to be recognised as one of the national languages in Singapore. This is a collection of archival photographs\n documents donated by the family of Sarangapany’s close associate\n Murugu Srinivasan.\n",
  "createdDate": "20201120223706",
  "version": 0,
  "latest": false,
  "roles": [],
  "metadata": {
    "accession_no_csv": "2015-00548",
    "Image": "",
    "object_work_type": "posters",
    "title_text": "Poster for Bukit Merah Tamilar Thirunaal",
    "preference": "main",
    "title_language": "",
    "creator_2": "Unknown",
    "creation_date": "14-Feb-67",
    "creation_place_original_location": "Singapore",
    "styles_periods_indexing_terms": "Not indicated",
    "inscriptions": "",
    "inscription_language": "",
    "scale_type": "Not indicated",
    "shape": "rectangular",
    "materials_name": "printing paper",
    "techniques_name": "printing (process)",
    "object_colour": "black-and-white (colours)",
    "physical_appearance": "\"The image displays a poster. There is a rectangular border. Within this border, the contents in the poster are written entirely in the Tamil script. \"\"14-2-1965\"\" is stated in the first paragraph. \"",
    "subject_terms_1": "Hinduism festivals",
    "subject_terms_2": "Posters Bukit Merah (Singapore) Harvest festivals Hinduism",
    "subject_terms_3": "Ethnic festivals Religious festivals Hinduism Bukit Merah",
    "context_1": "Thai Pongal 1967",
    "context_2": "harvest festivals",
    "context_3": "14-Feb-67",
    "context_4": "19670214",
    "context_5": "19670214",
    "sgcool_label_text": "G Sarangapany, titled Thamizhavel, arrived in Singapore in 1924. A believer of Periyar’s principles, he played a key role in extending the Self-Respect Movement to Singapore and Malaya and became the agent for distribution of the movement’s magazine Kudi Arasu in British Malaya. He later helped arrange Periyar’s visits to Singapore and Malaya. \r\n\r\nHe was an active writer and publisher in his own right. In 1929 he set up the Tamil magazine Munnetram, and Tamil Murasu in 1935. Through his writings he promoted the principles of the Tamil reform movement. He encouraged Tamils to make Singapore their home, helped them gain citizenship and championed for the cause of the Tamil language to be recognised as one of the national languages in Singapore. This is a collection of archival photographs, documents donated by the family of Sarangapany’s close associate, Murugu Srinivasan."
  },
  "nlpDate": "20201120223706",
  "connectorId": 0,
  "tags": {}
}