{"id":"2015-00551","title":"Invitation issued to K Govindasamy to attend a public meeting by Tamilar Sirthiruthar Sangam","source":"Bumblebee","path":"./Data/json/","content":"accession_no_csv:2015-00551\nImage:\nobject_work_type:invitations\ntitle_text:Invitation issued to K Govindasamy to attend a public meeting by Tamilar Sirthiruthar Sangam\npreference:main\ntitle_language:\ncreator_2:Unknown\ncreation_date:3-Jun-78\ncreation_place_original_location:Singapore\nstyles_periods_indexing_terms:Not indicated\ninscriptions:\ninscription_language:\nscale_type:Not indicated\nshape:rectangular\nmaterials_name:printing paper\ntechniques_name:printing (process)\nobject_colour:black-and-white (colours)\nphysical_appearance:The image displays five pages of an invitation. The contents in all the pages are written entirely in the Tamil script. For the page at the lower hand side of the image\n there is a blue stamp near its middle. As for the page at the lower right hand side of the image\n there are a couple of signatures just below the last paragraph.\nsubject_terms_1:meetings associations reformers\nsubject_terms_2:Invitation cards Tamil?ar Ci?rtiruttac Can?kam (Cin?kappu?r) Public meetings Reformers\nsubject_terms_3:Tamils Reform Association Indian clans and associations\nsgcool_label_text:G Sarangapany\n titled Thamizhavel\n arrived in Singapore in 1924. A believer of Periyar’s principles\n he played a key role in extending the Self-Respect Movement to Singapore and Malaya and became the agent for distribution of the movement’s magazine Kudi Arasu in British Malaya. He later helped arrange Periyar’s visits to Singapore and Malaya. \\r\\n\\r\\nHe was an active writer and publisher in his own right. In 1929 he set up the Tamil magazine Munnetram\n and Tamil Murasu in 1935. Through his writings he promoted the principles of the Tamil reform movement. He encouraged Tamils to make Singapore their home\n helped them gain citizenship and championed for the cause of the Tamil language to be recognised as one of the national languages in Singapore. This is a collection of archival photographs\n documents donated by the family of Sarangapany’s close associate\n Murugu Srinivasan.","createdDate":"20201119143405","version":0,"latest":false,"roles":[],"metadata":{"accession_no_csv":"2015-00551","Image":"","object_work_type":"invitations","title_text":"Invitation issued to K Govindasamy to attend a public meeting by Tamilar Sirthiruthar Sangam","preference":"main","title_language":"","creator_2":"Unknown","creation_date":"3-Jun-78","creation_place_original_location":"Singapore","styles_periods_indexing_terms":"Not indicated","inscriptions":"","inscription_language":"","scale_type":"Not indicated","shape":"rectangular","materials_name":"printing paper","techniques_name":"printing (process)","object_colour":"black-and-white (colours)","physical_appearance":"The image displays five pages of an invitation. The contents in all the pages are written entirely in the Tamil script. For the page at the lower hand side of the image, there is a blue stamp near its middle. As for the page at the lower right hand side of the image, there are a couple of signatures just below the last paragraph.","subject_terms_1":"meetings associations reformers","subject_terms_2":"Invitation cards Tamil?ar Ci?rtiruttac Can?kam (Cin?kappu?r) Public meetings Reformers","subject_terms_3":"Tamils Reform Association Indian clans and associations","sgcool_label_text":"G Sarangapany, titled Thamizhavel, arrived in Singapore in 1924. A believer of Periyar’s principles, he played a key role in extending the Self-Respect Movement to Singapore and Malaya and became the agent for distribution of the movement’s magazine Kudi Arasu in British Malaya. He later helped arrange Periyar’s visits to Singapore and Malaya. \r\n\r\nHe was an active writer and publisher in his own right. In 1929 he set up the Tamil magazine Munnetram, and Tamil Murasu in 1935. Through his writings he promoted the principles of the Tamil reform movement. He encouraged Tamils to make Singapore their home, helped them gain citizenship and championed for the cause of the Tamil language to be recognised as one of the national languages in Singapore. This is a collection of archival photographs, documents donated by the family of Sarangapany’s close associate, Murugu Srinivasan."},"nlpDate":"20201119143405","connectorId":0,"tags":{}}