{
  "id": "2016-00212-024",
  "title": "Dalada Maligawa, Temple of Buddha\u0027s Tooth, Kandy, Ceylon Photograph album of views and portraits in the Punjab, Cashmere, Ceylon, Burma, Penang, Singapore, and Java",
  "source": "Bumblebee",
  "path": "./Data/json/",
  "content": "\n  accession_no_csv: 2016-00212-024\n\n  Image: \n\n  object_work_type: black-and-white photographs\n\n  title_text: Dalada Maligawa\n Temple of Buddha\\u0027s Tooth\n Kandy\n Ceylon Photograph album of views and portraits in the Punjab\n Cashmere\n Ceylon\n Burma\n Penang\n Singapore\n and Java\n\n  preference: main alternate\n\n  title_language: \n\n  creator_2: John Thomson\n\n  creator_1: Thomson\n J. (John)\n 1837-1921\n\n  creator_role: photographers\n\n  creation_date: before 28 Jul 1876\n\n  creation_place_original_location: Singapore Kandy (Sri Lanka)\n\n  inscriptions: \n\n  inscription_language: \n\n  shape: rectangular\n\n  materials_name: albumen (egg white protein) paper (fiber product) albumen paper\n\n  techniques_name: albumen process\n\n  object_colour: black-and-white (colors)\n\n  physical_appearance: This is a photograph of the Dalada Maligawa or Temple of Buddha\\u0027s Tooth in Kandy\n Sri Lanka. The photograph shows the front of the temple from the left. There is a brick patterned wall in front of the temple. A man is kneeling on the steps leading up to the entrance. The octagon of the temple is seen at the back\n with a man leading on one of the open doorways. The title is written at the bottom\n below the photograph.\n\n  subject_terms_1: temples (buildings) Buddhism religious structures\n\n  subject_terms_2: Temple of the Tooth (Kandy\n Sri Lanka) Buddhism Photographs religious structures Thomson\n J. (John)\n 1837-1921 Kandy (Sri Lanka)\n\n  subject_terms_3: Temples Photography Buddhism\n",
  "createdDate": "20201201203309",
  "version": 0,
  "latest": false,
  "roles": [],
  "metadata": {
    "accession_no_csv": "2016-00212-024",
    "Image": "",
    "object_work_type": "black-and-white photographs",
    "title_text": "Dalada Maligawa, Temple of Buddha\u0027s Tooth, Kandy, Ceylon Photograph album of views and portraits in the Punjab, Cashmere, Ceylon, Burma, Penang, Singapore, and Java",
    "preference": "main alternate",
    "title_language": "",
    "creator_2": "John Thomson",
    "creator_1": "Thomson, J. (John), 1837-1921",
    "creator_role": "photographers",
    "creation_date": "before 28 Jul 1876",
    "creation_place_original_location": "Singapore Kandy (Sri Lanka)",
    "inscriptions": "",
    "inscription_language": "",
    "shape": "rectangular",
    "materials_name": "albumen (egg white protein) paper (fiber product) albumen paper",
    "techniques_name": "albumen process",
    "object_colour": "black-and-white (colors)",
    "physical_appearance": "This is a photograph of the Dalada Maligawa or Temple of Buddha\u0027s Tooth in Kandy, Sri Lanka. The photograph shows the front of the temple from the left. There is a brick patterned wall in front of the temple. A man is kneeling on the steps leading up to the entrance. The octagon of the temple is seen at the back, with a man leading on one of the open doorways. The title is written at the bottom, below the photograph.",
    "subject_terms_1": "temples (buildings) Buddhism religious structures",
    "subject_terms_2": "Temple of the Tooth (Kandy, Sri Lanka) Buddhism Photographs religious structures Thomson, J. (John), 1837-1921 Kandy (Sri Lanka)",
    "subject_terms_3": "Temples Photography Buddhism"
  },
  "nlpDate": "20201201203309",
  "connectorId": 0,
  "tags": {}
}