{"id":"2016-00598","title":"Mrs Marimuthu, Mr S Gopalakrishnan,  their son, Selva   Gopalakrishnan and  daughter Selvi Gopalakrishnan (2 years old)","source":"Bumblebee","path":"./Data/json/","content":"accession_no_csv:2016-00598\nImage:\nobject_work_type:black-and-white photographs\ntitle_text:Mrs Marimuthu\n Mr S Gopalakrishnan\n  their son\n Selva   Gopalakrishnan and  daughter Selvi Gopalakrishnan (2 years old)\npreference:main\ntitle_language:\ncreation_date:1966\ncreation_place_original_location:Singapore\ninscriptions:\ninscription_language:\nshape:rectangular\nmaterials_name:paper (fiber product)\ntechniques_name:printing (process) photographic processes\nobject_colour:grey monochrome\nphysical_appearance:The image shows a photograph that is in black-and-white. The photograph features a man and a lady who are sitting down. A young child is standing in front and in the middle of them. Behind them\n a young boy is standing in the middle of the two adults. Only the lady is wearing her ethnic costume. They are looking towards the direction in which this photograph was taken. The background of the photograph suggests that this was taken in the interior of a building.\nsubject_terms_1:folk costume families (kinship groups) group portraits studio portraits\nsubject_terms_2:Black-and-white photography Ethnic costume Families Portraits\n Group Tamil (Indic people) Portrait photography\nsubject_terms_3:Portrait photography Indian costumes\nsgcool_label_text:Mr. S Gopalakrishnan (b. in 1920 in Tanjavur) was a prominent violinist\n and Carnatic singer. He arrived in Singapore in 1939 and actively participated in the Indian classical music scene here. Mr Gopalakrishnan performed alongside veterans of classical performers such as Pandit M Ramalingam and MV Gurusamy at temple and other music festivals. He also taught violin lessons at the Singapore Malayalee Association from the 1970s to 2000s. He was a member of the Tamils Reform Association and performed his wedding according to the principles of the Self-Respect Movement. He was also employed as a compositor at the Far East Air Force from 1954 to 1970.","createdDate":"20201018182635","version":0,"latest":false,"roles":[],"metadata":{"accession_no_csv":"2016-00598","Image":"","object_work_type":"black-and-white photographs","title_text":"Mrs Marimuthu, Mr S Gopalakrishnan,  their son, Selva   Gopalakrishnan and  daughter Selvi Gopalakrishnan (2 years old)","preference":"main","title_language":"","creation_date":"1966","creation_place_original_location":"Singapore","inscriptions":"","inscription_language":"","shape":"rectangular","materials_name":"paper (fiber product)","techniques_name":"printing (process) photographic processes","object_colour":"grey monochrome","physical_appearance":"The image shows a photograph that is in black-and-white. The photograph features a man and a lady who are sitting down. A young child is standing in front and in the middle of them. Behind them, a young boy is standing in the middle of the two adults. Only the lady is wearing her ethnic costume. They are looking towards the direction in which this photograph was taken. The background of the photograph suggests that this was taken in the interior of a building.","subject_terms_1":"folk costume families (kinship groups) group portraits studio portraits","subject_terms_2":"Black-and-white photography Ethnic costume Families Portraits, Group Tamil (Indic people) Portrait photography","subject_terms_3":"Portrait photography Indian costumes","sgcool_label_text":"Mr. S Gopalakrishnan (b. in 1920 in Tanjavur) was a prominent violinist, and Carnatic singer. He arrived in Singapore in 1939 and actively participated in the Indian classical music scene here. Mr Gopalakrishnan performed alongside veterans of classical performers such as Pandit M Ramalingam and MV Gurusamy at temple and other music festivals. He also taught violin lessons at the Singapore Malayalee Association from the 1970s to 2000s. He was a member of the Tamils Reform Association and performed his wedding according to the principles of the Self-Respect Movement. He was also employed as a compositor at the Far East Air Force from 1954 to 1970."},"nlpDate":"20201018182635","connectorId":0,"tags":{}}