{"id":"2016-00613","title":"S Gopalakrishnan playing the violin at Tank Road Temple (80 years old)","source":"Bumblebee","path":"./Data/json/","content":"accession_no_csv:2016-00613\nImage:\nobject_work_type:colour photographs\ntitle_text:S Gopalakrishnan playing the violin at Tank Road Temple (80 years old)\npreference:main\ntitle_language:\ncreation_date:2000s\ncreation_place_original_location:Singapore\nstyles_periods_indexing_terms:Indian (South Asian)\ninscriptions:\ninscription_language:\nshape:rectangular\nmaterials_name:paper (fiber product)\ntechniques_name:printing (process) photographic processes\nobject_colour:multicoloured\nphysical_appearance:The image shows a rectangular photograph that is in colour. The photograph features an adult male sitting down. He is dressed totally in white and there are a microphone stand in front of him. He is drawing a bow across the strings of a violin. The background of the photograph suggests that it was taken in the interior of a temple\n as seen by the Hindu statues behind him.\nsubject_terms_1:musicians music (performing arts) musical performances temples (buidings) violinists violins\nsubject_terms_2:Colour photography Musicians Carnatic music Performances Hindu temples Tamil (Indic people) Violin\nsubject_terms_3:Photography Indian music Performing Arts Temples Sri Thendayuthapani Temple Musicians\nsgcool_label_text:Mr. S Gopalakrishnan (b. in 1920 in Tanjavur) was a prominent violinist\n and Carnatic singer. He arrived in Singapore in 1939 and actively participated in the Indian classical music scene here. Mr Gopalakrishnan performed alongside veterans of classical performers such as Pandit M Ramalingam and MV Gurusamy at temple and other music festivals. He also taught violin lessons at the Singapore Malayalee Association from the 1970s to 2000s. He was a member of the Tamils Reform Association and performed his wedding according to the principles of the Self-Respect Movement. He was also employed as a compositor at the Far East Air Force from 1954 to 1970.","createdDate":"20201018182635","version":0,"latest":false,"roles":[],"metadata":{"accession_no_csv":"2016-00613","Image":"","object_work_type":"colour photographs","title_text":"S Gopalakrishnan playing the violin at Tank Road Temple (80 years old)","preference":"main","title_language":"","creation_date":"2000s","creation_place_original_location":"Singapore","styles_periods_indexing_terms":"Indian (South Asian)","inscriptions":"","inscription_language":"","shape":"rectangular","materials_name":"paper (fiber product)","techniques_name":"printing (process) photographic processes","object_colour":"multicoloured","physical_appearance":"The image shows a rectangular photograph that is in colour. The photograph features an adult male sitting down. He is dressed totally in white and there are a microphone stand in front of him. He is drawing a bow across the strings of a violin. The background of the photograph suggests that it was taken in the interior of a temple, as seen by the Hindu statues behind him.","subject_terms_1":"musicians music (performing arts) musical performances temples (buidings) violinists violins","subject_terms_2":"Colour photography Musicians Carnatic music Performances Hindu temples Tamil (Indic people) Violin","subject_terms_3":"Photography Indian music Performing Arts Temples Sri Thendayuthapani Temple Musicians","sgcool_label_text":"Mr. S Gopalakrishnan (b. in 1920 in Tanjavur) was a prominent violinist, and Carnatic singer. He arrived in Singapore in 1939 and actively participated in the Indian classical music scene here. Mr Gopalakrishnan performed alongside veterans of classical performers such as Pandit M Ramalingam and MV Gurusamy at temple and other music festivals. He also taught violin lessons at the Singapore Malayalee Association from the 1970s to 2000s. He was a member of the Tamils Reform Association and performed his wedding according to the principles of the Self-Respect Movement. He was also employed as a compositor at the Far East Air Force from 1954 to 1970."},"nlpDate":"20201018182635","connectorId":0,"tags":{}}