{"id":"2016-00212-012","title":"Photograph album of views and portraits in the Punjab, Cashmere, Ceylon, Burma, Penang, Singapore, and Java Gateway of Jumma Musjid, Lahore","source":"Bumblebee","path":"./Data/json/","content":"accession_no_csv:2016-00212-012\nImage:\nobject_work_type:black-and-white photographs\ntitle_text:Photograph album of views and portraits in the Punjab\n Cashmere\n Ceylon\n Burma\n Penang\n Singapore\n and Java Gateway of Jumma Musjid\n Lahore\npreference:alternate main\ntitle_language:\ncreator_2:John Thomson\ncreator_1:Thomson\n J. (John)\n 1837-1921\ncreator_role:photographers\ncreation_date:before 28 Jul 1876\ncreation_place_original_location:Singapore Lahore (Pakistan)\nstyles_periods_indexing_terms:Mughal Islamic (culture or style)\ninscriptions:\ninscription_language:\nshape:rectangular\nmaterials_name:albumen (egg white protein) albumen paper paper (fiber product)\ntechniques_name:albumen process\nobject_colour:black-and-white (colors)\nphysical_appearance:This is a photograph of the gateway to the Jumma mosque in Lahore. The photograph features a central tower-like archway entrance with a tall half-dome\n and two smaller domed archways on either side. There is a man standing in the middle of the archway. On the left of the photo\n there is another man standing in the courtyard. The title is written at the bottom\n below the photograph.\nsubject_terms_1:buildings (structures) mosques (buildings) arches gateways\nsubject_terms_2:Photographs Thomson\n J. (John)\n 1837-1921 Lahore (Pakistan) Mosques Gateways Architecture\n Mogul Empire\nsubject_terms_3:Photography Buildings","createdDate":"20201119143405","version":0,"latest":false,"roles":[],"metadata":{"accession_no_csv":"2016-00212-012","Image":"","object_work_type":"black-and-white photographs","title_text":"Photograph album of views and portraits in the Punjab, Cashmere, Ceylon, Burma, Penang, Singapore, and Java Gateway of Jumma Musjid, Lahore","preference":"alternate main","title_language":"","creator_2":"John Thomson","creator_1":"Thomson, J. (John), 1837-1921","creator_role":"photographers","creation_date":"before 28 Jul 1876","creation_place_original_location":"Singapore Lahore (Pakistan)","styles_periods_indexing_terms":"Mughal Islamic (culture or style)","inscriptions":"","inscription_language":"","shape":"rectangular","materials_name":"albumen (egg white protein) albumen paper paper (fiber product)","techniques_name":"albumen process","object_colour":"black-and-white (colors)","physical_appearance":"This is a photograph of the gateway to the Jumma mosque in Lahore. The photograph features a central tower-like archway entrance with a tall half-dome, and two smaller domed archways on either side. There is a man standing in the middle of the archway. On the left of the photo, there is another man standing in the courtyard. The title is written at the bottom, below the photograph.","subject_terms_1":"buildings (structures) mosques (buildings) arches gateways","subject_terms_2":"Photographs Thomson, J. (John), 1837-1921 Lahore (Pakistan) Mosques Gateways Architecture, Mogul Empire","subject_terms_3":"Photography Buildings"},"nlpDate":"20201119143405","connectorId":0,"tags":{}}