{"id":"2016-00662","title":"Konica film squeegees A pair of Konica film squeegees","source":"Bumblebee","path":"./Data/json/","content":"accession_no_csv:2016-00662\nImage:\nobject_work_type:squeegees\ntitle_text:Konica film squeegees A pair of Konica film squeegees\npreference:main alternate\ntitle_language:\ncreator_2:Konica Trading Corporation\ncreator_1:Konika Kabushiki Kaisha\ncreator_role:manufacturers\ncreation_date:1980s-1990s\ncreation_place_original_location:Singapore Japan\ninscriptions:\ninscription_language:\nshape:irregular\nmaterials_name:plastic (organic material)\ntechniques_name:forming (physical activity)\nobject_colour:multicoloured\nphysical_appearance:The image shows a pair of squeegees enclosed in a transparent plastic packaging. The squeegees are white in colour with green tips at their bottoms. At the top and front of the plastic packaging\n the words \\u0027photo accessory\\u0027 and \\u0027Konica Trading Corporation Japan\\u0027 are displayed. The packaging looks crumpled.\nsubject_terms_1:photographic processing equipment tools\nsubject_terms_2:Photography Equipment and supplies Tools\nsubject_terms_3:Photography\ncontext_20:The set of equipment was used by The Picture Farm Pte Ltd\ncontext_21:45 Jalan Pemimpin\n #09-00 Foo Wah Industrial Building\n Thomson\n Singapore\ncontext_22:1970 - present\ncontext_23:1970\ncontext_24:present\nsgcool_label_text:Squeegees are used in handling photographic films during film processing. This pair of unused squeegees are part of the darkroom photography equipment that was previously used by The Picture Farm\n which was set up by the renowned photographer Willie Tang.","createdDate":"20201018182635","version":0,"latest":false,"roles":[],"metadata":{"accession_no_csv":"2016-00662","Image":"","object_work_type":"squeegees","title_text":"Konica film squeegees A pair of Konica film squeegees","preference":"main alternate","title_language":"","creator_2":"Konica Trading Corporation","creator_1":"Konika Kabushiki Kaisha","creator_role":"manufacturers","creation_date":"1980s-1990s","creation_place_original_location":"Singapore Japan","inscriptions":"","inscription_language":"","shape":"irregular","materials_name":"plastic (organic material)","techniques_name":"forming (physical activity)","object_colour":"multicoloured","physical_appearance":"The image shows a pair of squeegees enclosed in a transparent plastic packaging. The squeegees are white in colour with green tips at their bottoms. At the top and front of the plastic packaging, the words \u0027photo accessory\u0027 and \u0027Konica Trading Corporation Japan\u0027 are displayed. The packaging looks crumpled.","subject_terms_1":"photographic processing equipment tools","subject_terms_2":"Photography Equipment and supplies Tools","subject_terms_3":"Photography","context_20":"The set of equipment was used by The Picture Farm Pte Ltd","context_21":"45 Jalan Pemimpin, #09-00 Foo Wah Industrial Building, Thomson, Singapore","context_22":"1970 - present","context_23":"1970","context_24":"present","sgcool_label_text":"Squeegees are used in handling photographic films during film processing. This pair of unused squeegees are part of the darkroom photography equipment that was previously used by The Picture Farm, which was set up by the renowned photographer Willie Tang."},"nlpDate":"20201018182635","connectorId":0,"tags":{}}