{"id":"2016-00564","title":"Chinese-language newsletter of Partai Rakyat  Chinese-language newsletter of Partai Rakyat","source":"Bumblebee","path":"./Data/json/","content":"accession_no_csv:2016-00564\nImage:\nobject_work_type:newsletters newsletters\ntitle_text:Chinese-language newsletter of Partai Rakyat  Chinese-language newsletter of Partai Rakyat\npreference:main main\ntitle_language:\ncreator_2:Partai Rakyat Partai Rakyat\ncreator_1:Partai Rakyat\n Singapore State Division (TTE) Partai Rakyat\n Singapore State Division (TTE)\ncreator_role:creators creators\ncreation_date:1966 1966\ncreation_place_original_location:Singapore Singapore\nstyles_periods_indexing_terms:NA NA\ninscriptions:\ninscription_language:\nscale_type:NA NA\nshape:rectangular rectangular\nmaterials_name:printing paper printing paper\ntechniques_name:colour printing colour printing\nobject_colour:multicoloured multicoloured\nedition_description:NA NA\nphysical_appearance:\\The image shows the front cover of a newsletter. All the words and characters are typewritten in red. \\\\Partai Rakyat Negeri Singapure \\The image shows the front cover of a newsletter. All the words and characters are typewritten in red. \\\\Partai Rakyat Negeri Singapure\nsubject_terms_1:31 communism political organizations propaganda  31 communism political organizations propaganda\nsubject_terms_2:Lorong 32 Political party organization Communism Propaganda Political science  Lorong 32 Political party organization Communism Propaganda Political science\nsubject_terms_3:Geylang Road Singapore 14 Tel: 494006\\\\ is stated at the top. The articles are written in Chinese characters. The logo of a bull\\u0027s head can be seen at the upper left hand corner of the newsletter. \\  Geylang Road Singapore 14 Tel: 494006\\\\ is stated at the top. The articles are written in Chinese characters. The logo of a bull\\u0027s head can be seen at the upper left hand corner of the newsletter. \\\nsubject_terms_4:politics politics\ncontext_1:Newsletters Newsletters\ncontext_2:Newsletters Newsletters\ncontext_3:NA NA\ncontext_4:NA NA\ncontext_5:NA NA\ncontext_6:NA NA\ncontext_7:NA NA\ncontext_8:NA NA\ncontext_9:NA NA\ncontext_10:NA NA\ncontext_11:NA NA\ncontext_12:NA NA\ncontext_13:NA NA\ncontext_14:NA NA\ncontext_15:NA NA\ncontext_16:NA NA\ncontext_17:NA NA\ncontext_18:NA NA\ncontext_19:NA NA\ncontext_20:NA NA\ncontext_21:NA NA\ncontext_22:NA NA\ncontext_23:NA NA\ncontext_24:NA NA\nsgcool_label_text:NA NA","createdDate":"20201018182635","version":0,"latest":false,"roles":[],"metadata":{"accession_no_csv":"2016-00564","Image":"","object_work_type":"newsletters newsletters","title_text":"Chinese-language newsletter of Partai Rakyat  Chinese-language newsletter of Partai Rakyat","preference":"main main","title_language":"","creator_2":"Partai Rakyat Partai Rakyat","creator_1":"Partai Rakyat, Singapore State Division (TTE) Partai Rakyat, Singapore State Division (TTE)","creator_role":"creators creators","creation_date":"1966 1966","creation_place_original_location":"Singapore Singapore","styles_periods_indexing_terms":"NA NA","inscriptions":"","inscription_language":"","scale_type":"NA NA","shape":"rectangular rectangular","materials_name":"printing paper printing paper","techniques_name":"colour printing colour printing","object_colour":"multicoloured multicoloured","edition_description":"NA NA","physical_appearance":"\"The image shows the front cover of a newsletter. All the words and characters are typewritten in red. \"\"Partai Rakyat Negeri Singapure \"The image shows the front cover of a newsletter. All the words and characters are typewritten in red. \"\"Partai Rakyat Negeri Singapure","subject_terms_1":"31 communism political organizations propaganda  31 communism political organizations propaganda","subject_terms_2":"Lorong 32 Political party organization Communism Propaganda Political science  Lorong 32 Political party organization Communism Propaganda Political science","subject_terms_3":"Geylang Road Singapore 14 Tel: 494006\"\" is stated at the top. The articles are written in Chinese characters. The logo of a bull\u0027s head can be seen at the upper left hand corner of the newsletter. \"  Geylang Road Singapore 14 Tel: 494006\"\" is stated at the top. The articles are written in Chinese characters. The logo of a bull\u0027s head can be seen at the upper left hand corner of the newsletter. \"","subject_terms_4":"politics politics","context_1":"Newsletters Newsletters","context_2":"Newsletters Newsletters","context_3":"NA NA","context_4":"NA NA","context_5":"NA NA","context_6":"NA NA","context_7":"NA NA","context_8":"NA NA","context_9":"NA NA","context_10":"NA NA","context_11":"NA NA","context_12":"NA NA","context_13":"NA NA","context_14":"NA NA","context_15":"NA NA","context_16":"NA NA","context_17":"NA NA","context_18":"NA NA","context_19":"NA NA","context_20":"NA NA","context_21":"NA NA","context_22":"NA NA","context_23":"NA NA","context_24":"NA NA","sgcool_label_text":"NA NA"},"nlpDate":"20201018182635","connectorId":0,"tags":{}}