{"id":"2016-00212-049","title":"Photograph album of views and portraits in the Punjab, Cashmere, Ceylon, Burma, Penang, Singapore, and Java Sule Pagoda and Band stand, Rangoon","source":"Bumblebee","path":"./Data/json/","content":"accession_no_csv:2016-00212-049\nImage:\nobject_work_type:black-and-white photographs\ntitle_text:Photograph album of views and portraits in the Punjab\n Cashmere\n Ceylon\n Burma\n Penang\n Singapore\n and Java Sule Pagoda and Band stand\n Rangoon\npreference:alternate main\ntitle_language:\ncreator_2:John Thomson\ncreator_1:Thomson\n J. (John)\n 1837-1921\ncreator_role:photographers\ncreation_date:before 28 Jul 1876\ncreation_place_original_location:Singapore Rangoon (Burma)\ninscriptions:\ninscription_language:\nshape:rectangular\nmaterials_name:albumen (egg white protein) albumen paper paper (fiber product)\ntechniques_name:albumen process\nobject_colour:black-and-white (colors)\nphysical_appearance:This is a photograph of the Sule Pagoda in Rangoon\n Burma. The pagoda\n with its towering stupa\n is on the left of the photograph. On the right\n there is a two-tiered wooden structure with open archways\n with a three-step base. The structure is on an open plot of grass. The title is written at the bottom\n below the photograph.\nsubject_terms_1:pagodas (buildings) Buddhism scenery (landscape) stupas\nsubject_terms_2:Photographs Thomson\n J. (John)\n 1837-1921 Rangoon (Burma) Chu?? le Ceti? to? (Rangoon\n Burma) Buddhism Stupas Pagodas\nsubject_terms_3:Landscape photography Buddhism Religious buildings","createdDate":"20201018182635","version":0,"latest":false,"roles":[],"metadata":{"accession_no_csv":"2016-00212-049","Image":"","object_work_type":"black-and-white photographs","title_text":"Photograph album of views and portraits in the Punjab, Cashmere, Ceylon, Burma, Penang, Singapore, and Java Sule Pagoda and Band stand, Rangoon","preference":"alternate main","title_language":"","creator_2":"John Thomson","creator_1":"Thomson, J. (John), 1837-1921","creator_role":"photographers","creation_date":"before 28 Jul 1876","creation_place_original_location":"Singapore Rangoon (Burma)","inscriptions":"","inscription_language":"","shape":"rectangular","materials_name":"albumen (egg white protein) albumen paper paper (fiber product)","techniques_name":"albumen process","object_colour":"black-and-white (colors)","physical_appearance":"This is a photograph of the Sule Pagoda in Rangoon, Burma. The pagoda, with its towering stupa, is on the left of the photograph. On the right, there is a two-tiered wooden structure with open archways, with a three-step base. The structure is on an open plot of grass. The title is written at the bottom, below the photograph.","subject_terms_1":"pagodas (buildings) Buddhism scenery (landscape) stupas","subject_terms_2":"Photographs Thomson, J. (John), 1837-1921 Rangoon (Burma) Chu?? le Ceti? to? (Rangoon, Burma) Buddhism Stupas Pagodas","subject_terms_3":"Landscape photography Buddhism Religious buildings"},"nlpDate":"20201018182635","connectorId":0,"tags":{}}