{
  "id": "2016-00317",
  "title": "Indian Pioneer, Gnanapragasam Pillai Portrait of Indian Pioneer, Gnanapragasam Pillai",
  "source": "Bumblebee",
  "path": "./Data/json/",
  "content": "\n  accession_no_csv: 2016-00317\n\n  Image: \n\n  object_work_type: portraits paintings (visual works)\n\n  title_text: Indian Pioneer\n Gnanapragasam Pillai Portrait of Indian Pioneer\n Gnanapragasam Pillai\n\n  preference: main alternate\n\n  title_language: \n\n  creation_date: 1900 - 1939\n\n  creation_place_original_location: Singapore\n\n  inscriptions: \n\n  inscription_language: \n\n  shape: rectangular\n\n  materials_name: paint (coating)\n\n  techniques_name: painting (image-making)\n\n  object_colour: multicoloured\n\n  physical_appearance: Gnanapragasam Pillai is painted in this portrait. He is dressed formally\n with a formal green jacket with a flower attached to his left lapel. The jacket is not buttoned\n revealing a white shirt with a buttoned collar. He sports a moustache as well. The portrait is bounded with a brown frame. The brown frame contains an inner and outer border.  Both of these borders are demarcated by a wood-coloured region.\n\n  subject_terms_1: businessmen merchants founders (originators)\n\n  subject_terms_2: Tamil (Indic people) Portrait painitng Merchants Businessmen\n\n  subject_terms_3: Pioneers Business owners Visual arts\n\n  sgcool_label_text: Gnanapragasam Pillai (1872-1915)\n was born in India\n in Muthialpet\n the region of Pondicherry in south India; a French territory in colonial India. He migrated to Singapore/Malaya in search of a better fortune. He was an early Indian trader who owned a grocery business along Serangoon Road near Tekka Market in the early 1900s. He was a wealthy businessman who had two shop houses at number 44 and 46 Serangoon Road. His business was eventually taken over by P.Govindasamy Pillai after his demise. Having one’s portrait taken was common in early-mid 20th century Singapore among the upper middle class\n well to do businessmen.\n",
  "createdDate": "20201125084535",
  "version": 0,
  "latest": false,
  "roles": [],
  "metadata": {
    "accession_no_csv": "2016-00317",
    "Image": "",
    "object_work_type": "portraits paintings (visual works)",
    "title_text": "Indian Pioneer, Gnanapragasam Pillai Portrait of Indian Pioneer, Gnanapragasam Pillai",
    "preference": "main alternate",
    "title_language": "",
    "creation_date": "1900 - 1939",
    "creation_place_original_location": "Singapore",
    "inscriptions": "",
    "inscription_language": "",
    "shape": "rectangular",
    "materials_name": "paint (coating)",
    "techniques_name": "painting (image-making)",
    "object_colour": "multicoloured",
    "physical_appearance": "Gnanapragasam Pillai is painted in this portrait. He is dressed formally, with a formal green jacket with a flower attached to his left lapel. The jacket is not buttoned, revealing a white shirt with a buttoned collar. He sports a moustache as well. The portrait is bounded with a brown frame. The brown frame contains an inner and outer border.  Both of these borders are demarcated by a wood-coloured region.",
    "subject_terms_1": "businessmen merchants founders (originators)",
    "subject_terms_2": "Tamil (Indic people) Portrait painitng Merchants Businessmen",
    "subject_terms_3": "Pioneers Business owners Visual arts",
    "sgcool_label_text": "Gnanapragasam Pillai (1872-1915), was born in India, in Muthialpet, the region of Pondicherry in south India; a French territory in colonial India. He migrated to Singapore/Malaya in search of a better fortune. He was an early Indian trader who owned a grocery business along Serangoon Road near Tekka Market in the early 1900s. He was a wealthy businessman who had two shop houses at number 44 and 46 Serangoon Road. His business was eventually taken over by P.Govindasamy Pillai after his demise. Having one’s portrait taken was common in early-mid 20th century Singapore among the upper middle class, well to do businessmen."
  },
  "nlpDate": "20201125084535",
  "connectorId": 0,
  "tags": {}
}