{
  "id": "2016-00470-001",
  "title": "Pair of portraits (Peter Lim Ah Pin and Florence Yeo) Peter Lim Ah Pin",
  "source": "Bumblebee",
  "path": "./Data/json/",
  "content": "\n  accession_no_csv: 2016-00470-001\n\n  Image: \n\n  object_work_type: photographs studio portraits\n\n  title_text: Pair of portraits (Peter Lim Ah Pin and Florence Yeo) Peter Lim Ah Pin\n\n  preference: main alternate\n\n  title_language: \n\n  creation_date: Early 20th century\n\n  creation_place_original_location: Singapore\n\n  inscriptions: \n\n  inscription_language: \n\n  shape: rectangular\n\n  object_colour: multicolored\n\n  physical_appearance: This is a portrait of Lim Ah Pin. This portrait depicts a man in a cream-coloured shirt\n with a mandarin collar. His hair is clipped back\n and his head is slightly tilted to the left.\n\n  subject_terms_1: businessmen Peranakan\n\n  subject_terms_2: Peranakan (Asian people) Photographs Businessmen\n\n  subject_terms_3: Lim Ah Pin Road Portrait photography\n\n  sgcool_label_text: The portrait of Peter Lim Ah Pin depicts a man in a cream-coloured shirt with a simple mandarin collar. The other portrait shows Florence Yeo in a floral kebaya with a set of diamond kerosang made in the Melaka style. Both portraits are coloured photographs\n bear the signature of the same artist and were probably made as a pair. Peter Lim owned a successful bee hoon manufacturing business and was known as the ‘Bee Hoon King’. He also built several markets\n schools and houses. Lim Ah Pin Road and Florence Road were named after the couple\n who owned and rented out several properties in the area.\n",
  "createdDate": "20201201203309",
  "version": 0,
  "latest": false,
  "roles": [],
  "metadata": {
    "accession_no_csv": "2016-00470-001",
    "Image": "",
    "object_work_type": "photographs studio portraits",
    "title_text": "Pair of portraits (Peter Lim Ah Pin and Florence Yeo) Peter Lim Ah Pin",
    "preference": "main alternate",
    "title_language": "",
    "creation_date": "Early 20th century",
    "creation_place_original_location": "Singapore",
    "inscriptions": "",
    "inscription_language": "",
    "shape": "rectangular",
    "object_colour": "multicolored",
    "physical_appearance": "This is a portrait of Lim Ah Pin. This portrait depicts a man in a cream-coloured shirt, with a mandarin collar. His hair is clipped back, and his head is slightly tilted to the left.",
    "subject_terms_1": "businessmen Peranakan",
    "subject_terms_2": "Peranakan (Asian people) Photographs Businessmen",
    "subject_terms_3": "Lim Ah Pin Road Portrait photography",
    "sgcool_label_text": "The portrait of Peter Lim Ah Pin depicts a man in a cream-coloured shirt with a simple mandarin collar. The other portrait shows Florence Yeo in a floral kebaya with a set of diamond kerosang made in the Melaka style. Both portraits are coloured photographs, bear the signature of the same artist and were probably made as a pair. Peter Lim owned a successful bee hoon manufacturing business and was known as the ‘Bee Hoon King’. He also built several markets, schools and houses. Lim Ah Pin Road and Florence Road were named after the couple, who owned and rented out several properties in the area."
  },
  "nlpDate": "20201201203309",
  "connectorId": 0,
  "tags": {}
}