{"id":"2016-00504","title":"Untitled (locomotive at Bukit Timah railway station)","source":"Bumblebee","path":"./Data/json/","content":"accession_no_csv:2016-00504\nImage:\nobject_work_type:black-and-white photographs\ntitle_text:Untitled (locomotive at Bukit Timah railway station)\npreference:main\ntitle_language:\ncreator_2:Kwek Leng Joo\ncreator_1:Kwek\n Leng Joo\ncreator_role:photographers\ncreation_date:2010\ncreation_place_original_location:Singapore Malaysia\ninscriptions:\ninscription_language:\nshape:rectangular\nmaterials_name:paper (fiber product)\ntechniques_name:printing (process)\nobject_colour:grey monochrome\nphysical_appearance:The image shows a photograph in black-and-white. It has a black frame and its border is white in colour. A passenger train is visible in the photograph. Three workers are can be seen and one of them is the train driver. The other is standing by the door and the last one is located on the tracks. Both of them are holding a token as part of the railway signalling system. Also\n the worker standing on the tracks is holding a flag horizontally in his right hand. Some trees are located in the background of the photograph.\nsubject_terms_1:railroads (infrastructures) trains (vehicle groupings) passenger cars (railroad cars) historic monuments blue collar workers locomotives\nsubject_terms_2:Black-and-white photography Railroads Railroad passenger cars Historic monuments Blue collar workers Locomotives Pertadbiran Keretapi Tanah Melayu Bukit Timah (Singapore) Railroad trains\nsubject_terms_3:Rail transport Pertadbiran Keretapi Tanah Melayu Former Bukit Timah Railway Station Photography Rail transport (Stations)\nsgcool_label_text:\\This image features railway employees at work at the Bukit Timah railway station. It is part of the \\\\Tracking Memories\\\\ collection by the late Mr Kwek Leng Joo. The collection captures different aspects of the Malayan Railway story in Singapore","createdDate":"20201018182635","version":0,"latest":false,"roles":[],"metadata":{"accession_no_csv":"2016-00504","Image":"","object_work_type":"black-and-white photographs","title_text":"Untitled (locomotive at Bukit Timah railway station)","preference":"main","title_language":"","creator_2":"Kwek Leng Joo","creator_1":"Kwek, Leng Joo","creator_role":"photographers","creation_date":"2010","creation_place_original_location":"Singapore Malaysia","inscriptions":"","inscription_language":"","shape":"rectangular","materials_name":"paper (fiber product)","techniques_name":"printing (process)","object_colour":"grey monochrome","physical_appearance":"The image shows a photograph in black-and-white. It has a black frame and its border is white in colour. A passenger train is visible in the photograph. Three workers are can be seen and one of them is the train driver. The other is standing by the door and the last one is located on the tracks. Both of them are holding a token as part of the railway signalling system. Also, the worker standing on the tracks is holding a flag horizontally in his right hand. Some trees are located in the background of the photograph.","subject_terms_1":"railroads (infrastructures) trains (vehicle groupings) passenger cars (railroad cars) historic monuments blue collar workers locomotives","subject_terms_2":"Black-and-white photography Railroads Railroad passenger cars Historic monuments Blue collar workers Locomotives Pertadbiran Keretapi Tanah Melayu Bukit Timah (Singapore) Railroad trains","subject_terms_3":"Rail transport Pertadbiran Keretapi Tanah Melayu Former Bukit Timah Railway Station Photography Rail transport (Stations)","sgcool_label_text":"\"This image features railway employees at work at the Bukit Timah railway station. It is part of the \"\"Tracking Memories\"\" collection by the late Mr Kwek Leng Joo. The collection captures different aspects of the Malayan Railway story in Singapore"},"nlpDate":"20201018182635","connectorId":0,"tags":{}}