{
  "id": "2016-00212-082",
  "title": "Photograph album of views and portraits in the Punjab, Cashmere, Ceylon, Burma, Penang, Singapore, and Java Cisarua valley with Pangrango and Mount Gede in the distance, Java",
  "source": "Bumblebee",
  "path": "./Data/json/",
  "content": "\n  accession_no_csv: 2016-00212-082\n\n  Image: \n\n  object_work_type: black-and-white photographs\n\n  title_text: Photograph album of views and portraits in the Punjab\n Cashmere\n Ceylon\n Burma\n Penang\n Singapore\n and Java Cisarua valley with Pangrango and Mount Gede in the distance\n Java\n\n  preference: alternate main\n\n  title_language: \n\n  creator_2: John Thomson\n\n  creator_1: Thomson\n J. (John)\n 1837-1921\n\n  creator_role: photographers\n\n  creation_date: before 28 Jul 1876\n\n  creation_place_original_location: Singapore Java (Indonesia)\n\n  inscriptions: \n\n  inscription_language: \n\n  shape: rectangular\n\n  materials_name: albumen (egg white protein) albumen paper paper (fiber product)\n\n  techniques_name: albumen process\n\n  object_colour: black-and-white (colors)\n\n  physical_appearance: This is a photograph of a valley in Cisarua in Java\n Indonesia. Mount Pangrango and Mount Gede can be seen in the faint background in the distance. In the center of the photograph\n there are a few roofed houses\n with a sheltered bridge in the center. The title is written at the bottom\n below the photograph.\n\n  subject_terms_1: mountains scenery (landscape) valleys (landforms) hill settlements\n\n  subject_terms_2: Photographs Thomson\n J. (John)\n 1837-1921 Valleys Mountains Cisarua (Bogor\n Indonesia)\n\n  subject_terms_3: Landscape photography Nature and environment\n",
  "createdDate": "20201120223706",
  "version": 0,
  "latest": false,
  "roles": [],
  "metadata": {
    "accession_no_csv": "2016-00212-082",
    "Image": "",
    "object_work_type": "black-and-white photographs",
    "title_text": "Photograph album of views and portraits in the Punjab, Cashmere, Ceylon, Burma, Penang, Singapore, and Java Cisarua valley with Pangrango and Mount Gede in the distance, Java",
    "preference": "alternate main",
    "title_language": "",
    "creator_2": "John Thomson",
    "creator_1": "Thomson, J. (John), 1837-1921",
    "creator_role": "photographers",
    "creation_date": "before 28 Jul 1876",
    "creation_place_original_location": "Singapore Java (Indonesia)",
    "inscriptions": "",
    "inscription_language": "",
    "shape": "rectangular",
    "materials_name": "albumen (egg white protein) albumen paper paper (fiber product)",
    "techniques_name": "albumen process",
    "object_colour": "black-and-white (colors)",
    "physical_appearance": "This is a photograph of a valley in Cisarua in Java, Indonesia. Mount Pangrango and Mount Gede can be seen in the faint background in the distance. In the center of the photograph, there are a few roofed houses, with a sheltered bridge in the center. The title is written at the bottom, below the photograph.",
    "subject_terms_1": "mountains scenery (landscape) valleys (landforms) hill settlements",
    "subject_terms_2": "Photographs Thomson, J. (John), 1837-1921 Valleys Mountains Cisarua (Bogor, Indonesia)",
    "subject_terms_3": "Landscape photography Nature and environment"
  },
  "nlpDate": "20201120223706",
  "connectorId": 0,
  "tags": {}
}