{"id":"2016-00214","title":"Painting of William Henry Ker and Chinese attendant by Aaron Edwin Penley William Henry Ker with Chinese attendant","source":"Bumblebee","path":"./Data/json/","content":"accession_no_csv:2016-00214\nImage:\nobject_work_type:oil paintings (visual works) portraits\ntitle_text:Painting of William Henry Ker and Chinese attendant by Aaron Edwin Penley William Henry Ker with Chinese attendant\npreference:alternate main\ntitle_language:\ncreator_1:Penley\n Aaron\n 1806-1870\ncreator_role:painters (artists)\ncreation_date:19th century\ncreation_place_original_location:London (England)\ninscriptions:\ninscription_language:\nshape:rectangular\nmaterials_name:oil paint (paint) canvas (textile material)\ntechniques_name:oil painting (technique)\nobject_colour:multicolored\nphysical_appearance:This is an oil painting of William Henry Ker with his Chinese attendant. The painting depicts a boy on the left\n wearing a brown coat and light-coloured trousers. He is holding a stick and a hoop. On the right is a Chinese man\n wearing a loose blue attire with queue hair style. The background shows a countryside backdrop of the left\n with a hanging red curtain on the right.\nsubject_terms_1:colonialism domestics (servants)\nsubject_terms_2:Portrait painting Imperialism Nannies\nsubject_terms_3:Oil painting\nsgcool_label_text:This studio portrait with countryside backdrop and red curtains hanging near a column (conflating indoor and outdoor) derives from European paintings of the period. The large scale of the attendant compared to the boy is noteworthy\n and perhaps is intended to add an exotic appeal to the depiction of an English boy who grew up in a Southeast Asian colonial setting.  The child\n playing with a stick and hoop\n is William Henry Ker (1837-1864)\n son of William Wemyss Ker (1802–1874)\n a partner of Paterson\n Simons and C\n one of the earliest and largest trading firms in the Straits Settlements. \\r\\n\\r\\nThe artist\n Aaron Edwin Penley (1807–1870)\n was better known for watercolours\n and exhibited regularly at the Royal Academy exhibitions in London.\\r\\n","createdDate":"20201018182635","version":0,"latest":false,"roles":[],"metadata":{"accession_no_csv":"2016-00214","Image":"","object_work_type":"oil paintings (visual works) portraits","title_text":"Painting of William Henry Ker and Chinese attendant by Aaron Edwin Penley William Henry Ker with Chinese attendant","preference":"alternate main","title_language":"","creator_1":"Penley, Aaron, 1806-1870","creator_role":"painters (artists)","creation_date":"19th century","creation_place_original_location":"London (England)","inscriptions":"","inscription_language":"","shape":"rectangular","materials_name":"oil paint (paint) canvas (textile material)","techniques_name":"oil painting (technique)","object_colour":"multicolored","physical_appearance":"This is an oil painting of William Henry Ker with his Chinese attendant. The painting depicts a boy on the left, wearing a brown coat and light-coloured trousers. He is holding a stick and a hoop. On the right is a Chinese man, wearing a loose blue attire with queue hair style. The background shows a countryside backdrop of the left, with a hanging red curtain on the right.","subject_terms_1":"colonialism domestics (servants)","subject_terms_2":"Portrait painting Imperialism Nannies","subject_terms_3":"Oil painting","sgcool_label_text":"This studio portrait with countryside backdrop and red curtains hanging near a column (conflating indoor and outdoor) derives from European paintings of the period. The large scale of the attendant compared to the boy is noteworthy, and perhaps is intended to add an exotic appeal to the depiction of an English boy who grew up in a Southeast Asian colonial setting.  The child, playing with a stick and hoop, is William Henry Ker (1837-1864), son of William Wemyss Ker (1802–1874), a partner of Paterson, Simons and C, one of the earliest and largest trading firms in the Straits Settlements. \r\n\r\nThe artist, Aaron Edwin Penley (1807–1870), was better known for watercolours, and exhibited regularly at the Royal Academy exhibitions in London.\r\n"},"nlpDate":"20201018182635","connectorId":0,"tags":{}}