{"id":"2016-00144","title":"Brown cheongsam with matching jacket","source":"Bumblebee","path":"./Data/json/","content":"accession_no_csv:2016-00144\nImage:\nobject_work_type:folk costume jackets (garments)\ntitle_text:Brown cheongsam with matching jacket\npreference:main\ntitle_language:\ncreation_date:1960 - 1969\ncreation_place_original_location:Singapore\nstyles_periods_indexing_terms:Chinese (culture or style)\ninscriptions:\ninscription_language:\nshape:irregular\nmaterials_name:cloth\ntechniques_name:machine sewing (technique) knitting (process)\nobject_colour:brown (colour)\nphysical_appearance:This is a brown cheongsam that is paired with a long-sleeved matching jacket\n also brown in colour. The cheongsam is sleeveless. There are diaper patterns all over the jacket and the cheongsam. A collar is present on the cheongsam and on the jacket. There are three buttons running down the centre of the jacket\\u0027s front. They are circular in shape. There are no visible tears on the cheongsam and the jacket. There is no label tag on the jacket.\nsubject_terms_1:dresses (garments) womenswear allover patterns diaper patterns\nsubject_terms_2:Qipao Ethnic costume Jackets Women\\u0027s clothing Motifs\nsubject_terms_3:Ethnic costume Chinese costume\nsgcool_label_text:This is a sleeveless brown cheongsam in knitted fabric with a matching jacket. The cheongsam could have been wore on overseas trips to China\n during a time when the weather was cool. There is no label on the cheongsam.","createdDate":"20201119143405","version":0,"latest":false,"roles":[],"metadata":{"accession_no_csv":"2016-00144","Image":"","object_work_type":"folk costume jackets (garments)","title_text":"Brown cheongsam with matching jacket","preference":"main","title_language":"","creation_date":"1960 - 1969","creation_place_original_location":"Singapore","styles_periods_indexing_terms":"Chinese (culture or style)","inscriptions":"","inscription_language":"","shape":"irregular","materials_name":"cloth","techniques_name":"machine sewing (technique) knitting (process)","object_colour":"brown (colour)","physical_appearance":"This is a brown cheongsam that is paired with a long-sleeved matching jacket, also brown in colour. The cheongsam is sleeveless. There are diaper patterns all over the jacket and the cheongsam. A collar is present on the cheongsam and on the jacket. There are three buttons running down the centre of the jacket\u0027s front. They are circular in shape. There are no visible tears on the cheongsam and the jacket. There is no label tag on the jacket.","subject_terms_1":"dresses (garments) womenswear allover patterns diaper patterns","subject_terms_2":"Qipao Ethnic costume Jackets Women\u0027s clothing Motifs","subject_terms_3":"Ethnic costume Chinese costume","sgcool_label_text":"This is a sleeveless brown cheongsam in knitted fabric with a matching jacket. The cheongsam could have been wore on overseas trips to China, during a time when the weather was cool. There is no label on the cheongsam."},"nlpDate":"20201119143405","connectorId":0,"tags":{}}