{"id":"2016-00212-076","title":"Photograph album of views and portraits in the Punjab, Cashmere, Ceylon, Burma, Penang, Singapore, and Java View from the bridge over the Railway Station, Buitenzorg, Java","source":"Bumblebee","path":"./Data/json/","content":"accession_no_csv:2016-00212-076\nImage:\nobject_work_type:black-and-white photographs\ntitle_text:Photograph album of views and portraits in the Punjab\n Cashmere\n Ceylon\n Burma\n Penang\n Singapore\n and Java View from the bridge over the Railway Station\n Buitenzorg\n Java\npreference:alternate main\ntitle_language:\ncreator_2:John Thomson\ncreator_1:Thomson\n J. (John)\n 1837-1921\ncreator_role:photographers\ncreation_date:before 28 Jul 1876\ncreation_place_original_location:Singapore Bogor (Indonesia)\ninscriptions:\ninscription_language:\nshape:rectangular\nmaterials_name:albumen (egg white protein) albumen paper paper (fiber product)\ntechniques_name:albumen process\nobject_colour:black-and-white (colors)\nphysical_appearance:This is a photograph of a narrow river taken in Buitenzorg (Bogor)\n Indonesia. The river is in the middle of steep hills on either side. On the left side of the river\n there is a small waterfall. The edges of the photograph are curved. The title is written at the bottom\n below the photograph.\nsubject_terms_1:scenery (landscape) rivers\nsubject_terms_2:Photographs Thomson\n J. (John)\n 1837-1921 Bogor (Indonesia) Rivers\nsubject_terms_3:Landscape photography Rivers","createdDate":"20201119143405","version":0,"latest":false,"roles":[],"metadata":{"accession_no_csv":"2016-00212-076","Image":"","object_work_type":"black-and-white photographs","title_text":"Photograph album of views and portraits in the Punjab, Cashmere, Ceylon, Burma, Penang, Singapore, and Java View from the bridge over the Railway Station, Buitenzorg, Java","preference":"alternate main","title_language":"","creator_2":"John Thomson","creator_1":"Thomson, J. (John), 1837-1921","creator_role":"photographers","creation_date":"before 28 Jul 1876","creation_place_original_location":"Singapore Bogor (Indonesia)","inscriptions":"","inscription_language":"","shape":"rectangular","materials_name":"albumen (egg white protein) albumen paper paper (fiber product)","techniques_name":"albumen process","object_colour":"black-and-white (colors)","physical_appearance":"This is a photograph of a narrow river taken in Buitenzorg (Bogor), Indonesia. The river is in the middle of steep hills on either side. On the left side of the river, there is a small waterfall. The edges of the photograph are curved. The title is written at the bottom, below the photograph.","subject_terms_1":"scenery (landscape) rivers","subject_terms_2":"Photographs Thomson, J. (John), 1837-1921 Bogor (Indonesia) Rivers","subject_terms_3":"Landscape photography Rivers"},"nlpDate":"20201119143405","connectorId":0,"tags":{}}