{"id":"2016-00490","title":"Untitled (locomotive no. 25107 \u0026 6675)","source":"Bumblebee","path":"./Data/json/","content":"accession_no_csv:2016-00490\nImage:\nobject_work_type:black-and-white photographs\ntitle_text:Untitled (locomotive no. 25107 \\u0026 6675)\npreference:main\ntitle_language:\ncreator_2:Kwek Leng Joo\ncreator_1:Kwek\n Leng Joo\ncreator_role:photographers\ncreation_date:2010\ncreation_place_original_location:Singapore Malaysia\ninscriptions:\ninscription_language:\nshape:rectangular\nmaterials_name:paper (fiber product)\ntechniques_name:printing (process)\nobject_colour:grey monochrome\nphysical_appearance:\\The image shows a photograph in black-and-white. It has a black frame and its border is white in colour. There are three sets of railroads\n but only two of them are occupied by a train each. The track on the extreme right of the photograph has the numerals\n \\\\6675\\\\\nsubject_terms_1:located under its side window. The train on the middle track is slightly farther behind the other train. The numerals railroads (infrastructure) trains (vehicle groupings) passenger cars (railroad cars)\nsubject_terms_2:\\\\25107\\\\ Locomotives Railroads Railroad passenger cars Pertadbiran Keretapi Tanah Melayu Railroad trains\nsubject_terms_3:are displayed at its front. However Pertadbiran Keretapi Tanah Melayu Photography\nsubject_terms_4:the numerals\ncontext_1:\\\\1\\\\ and \\\\0\\\\\ncontext_2:are blocked by a metal bar and cannot be seen from the point at which the photograph was taken. Residential flats can be seen in the background at the top left hand side of the image.\\\ncontext_3:locomotives\ncontext_4:Black-and-white photography\ncontext_5:Rail transport","createdDate":"20201119143405","version":0,"latest":false,"roles":[],"metadata":{"accession_no_csv":"2016-00490","Image":"","object_work_type":"black-and-white photographs","title_text":"Untitled (locomotive no. 25107 \u0026 6675)","preference":"main","title_language":"","creator_2":"Kwek Leng Joo","creator_1":"Kwek, Leng Joo","creator_role":"photographers","creation_date":"2010","creation_place_original_location":"Singapore Malaysia","inscriptions":"","inscription_language":"","shape":"rectangular","materials_name":"paper (fiber product)","techniques_name":"printing (process)","object_colour":"grey monochrome","physical_appearance":"\"The image shows a photograph in black-and-white. It has a black frame and its border is white in colour. There are three sets of railroads, but only two of them are occupied by a train each. The track on the extreme right of the photograph has the numerals, \"\"6675\"\"","subject_terms_1":"located under its side window. The train on the middle track is slightly farther behind the other train. The numerals railroads (infrastructure) trains (vehicle groupings) passenger cars (railroad cars)","subject_terms_2":"\"\"25107\"\" Locomotives Railroads Railroad passenger cars Pertadbiran Keretapi Tanah Melayu Railroad trains","subject_terms_3":"are displayed at its front. However Pertadbiran Keretapi Tanah Melayu Photography","subject_terms_4":"the numerals","context_1":"\"\"1\"\" and \"\"0\"\"","context_2":"are blocked by a metal bar and cannot be seen from the point at which the photograph was taken. Residential flats can be seen in the background at the top left hand side of the image.\"","context_3":"locomotives","context_4":"Black-and-white photography","context_5":"Rail transport"},"nlpDate":"20201119143405","connectorId":0,"tags":{}}