{"id":"2016-00470-002","title":"Pair of portraits (Peter Lim Ah Pin and Florence Yeo) Florence Yeo","source":"Bumblebee","path":"./Data/json/","content":"accession_no_csv:2016-00470-002\nImage:\nobject_work_type:photographs studio portraits\ntitle_text:Pair of portraits (Peter Lim Ah Pin and Florence Yeo) Florence Yeo\npreference:alternate main\ntitle_language:\ncreation_date:Early 20th century\ncreation_place_original_location:Singapore\ninscriptions:\ninscription_language:\nshape:rectangular\nobject_colour:multicolored\nphysical_appearance:This is a portrait of Florence Yeo. The portrait depicts a woman wearing a kebaya adorned wit diamond brooch. Her hair is pulled back and secured with a pin.\nsubject_terms_1:Peranakan kebayas\nsubject_terms_2:Photographs Peranakan (Asian people)\nsubject_terms_3:Portrait photography Florence Road\nsgcool_label_text:The portrait of Peter Lim Ah Pin depicts a man in a cream-coloured shirt with a simple mandarin collar. The other portrait shows Florence Yeo in a floral kebaya with a set of diamond kerosang made in the Melaka style. Both portraits are coloured photographs\n bear the signature of the same artist and were probably made as a pair. Peter Lim owned a successful bee hoon manufacturing business and was known as the ‘Bee Hoon King’. He also built several markets\n schools and houses. Lim Ah Pin Road and Florence Road were named after the couple\n who owned and rented out several properties in the area.","createdDate":"20201119143405","version":0,"latest":false,"roles":[],"metadata":{"accession_no_csv":"2016-00470-002","Image":"","object_work_type":"photographs studio portraits","title_text":"Pair of portraits (Peter Lim Ah Pin and Florence Yeo) Florence Yeo","preference":"alternate main","title_language":"","creation_date":"Early 20th century","creation_place_original_location":"Singapore","inscriptions":"","inscription_language":"","shape":"rectangular","object_colour":"multicolored","physical_appearance":"This is a portrait of Florence Yeo. The portrait depicts a woman wearing a kebaya adorned wit diamond brooch. Her hair is pulled back and secured with a pin.","subject_terms_1":"Peranakan kebayas","subject_terms_2":"Photographs Peranakan (Asian people)","subject_terms_3":"Portrait photography Florence Road","sgcool_label_text":"The portrait of Peter Lim Ah Pin depicts a man in a cream-coloured shirt with a simple mandarin collar. The other portrait shows Florence Yeo in a floral kebaya with a set of diamond kerosang made in the Melaka style. Both portraits are coloured photographs, bear the signature of the same artist and were probably made as a pair. Peter Lim owned a successful bee hoon manufacturing business and was known as the ‘Bee Hoon King’. He also built several markets, schools and houses. Lim Ah Pin Road and Florence Road were named after the couple, who owned and rented out several properties in the area."},"nlpDate":"20201119143405","connectorId":0,"tags":{}}