{"id":"2016-00212-078","title":"Photograph album of views and portraits in the Punjab, Cashmere, Ceylon, Burma, Penang, Singapore, and Java Telaga Warna, Megamendung, Java","source":"Bumblebee","path":"./Data/json/","content":"accession_no_csv:2016-00212-078\nImage:\nobject_work_type:black-and-white photographs\ntitle_text:Photograph album of views and portraits in the Punjab\n Cashmere\n Ceylon\n Burma\n Penang\n Singapore\n and Java Telaga Warna\n Megamendung\n Java\npreference:alternate main\ntitle_language:\ncreator_2:John Thomson\ncreator_1:Thomson\n J. (John)\n 1837-1921\ncreator_role:photographers\ncreation_date:before 28 Jul 1876\ncreation_place_original_location:Singapore Bogor (Indonesia)\ninscriptions:\ninscription_language:\nshape:rectangular\nmaterials_name:albumen (egg white protein) albumen paper paper (fiber product)\ntechniques_name:albumen process\nobject_colour:black-and-white (colors)\nphysical_appearance:This is a photograph of an area beside the Telaga Warna lake in Bogor\n Indonesia. The lake is in the center of the photograph. In the foreground\n there are three men by the side of the lake on the grass. One man is standing\n one is lying down on the grass\n and the third is sitting down. The lake is surrounded by thick vegetation. The top of the photograph is folded inwards. The edges of the photograph are carved. The title is written at the bottom\n below the photograph.\nsubject_terms_1:scenery (landscape) lakes (bodies of water) forests (cultural landscapes) indigenous people\nsubject_terms_2:Photographs Thomson\n J. (John)\n 1837-1921 Bogor (Indonesia) Lakes indigenous peoples\nsubject_terms_3:Landscape photography Lakes","createdDate":"20201119143405","version":0,"latest":false,"roles":[],"metadata":{"accession_no_csv":"2016-00212-078","Image":"","object_work_type":"black-and-white photographs","title_text":"Photograph album of views and portraits in the Punjab, Cashmere, Ceylon, Burma, Penang, Singapore, and Java Telaga Warna, Megamendung, Java","preference":"alternate main","title_language":"","creator_2":"John Thomson","creator_1":"Thomson, J. (John), 1837-1921","creator_role":"photographers","creation_date":"before 28 Jul 1876","creation_place_original_location":"Singapore Bogor (Indonesia)","inscriptions":"","inscription_language":"","shape":"rectangular","materials_name":"albumen (egg white protein) albumen paper paper (fiber product)","techniques_name":"albumen process","object_colour":"black-and-white (colors)","physical_appearance":"This is a photograph of an area beside the Telaga Warna lake in Bogor, Indonesia. The lake is in the center of the photograph. In the foreground, there are three men by the side of the lake on the grass. One man is standing, one is lying down on the grass, and the third is sitting down. The lake is surrounded by thick vegetation. The top of the photograph is folded inwards. The edges of the photograph are carved. The title is written at the bottom, below the photograph.","subject_terms_1":"scenery (landscape) lakes (bodies of water) forests (cultural landscapes) indigenous people","subject_terms_2":"Photographs Thomson, J. (John), 1837-1921 Bogor (Indonesia) Lakes indigenous peoples","subject_terms_3":"Landscape photography Lakes"},"nlpDate":"20201119143405","connectorId":0,"tags":{}}