{
  "id": "2016-00694",
  "title": "Short-sleeved Jacket with Frog Buttons",
  "source": "Bumblebee",
  "path": "./Data/json/",
  "content": "\n  accession_no_csv: 2016-00694\n\n  Image: \n\n  object_work_type: jackets (garments)\n\n  title_text: Short-sleeved Jacket with Frog Buttons\n\n  preference: main\n\n  title_language: \n\n  creation_date: 20th century\n\n  creation_place_original_location: Indonesia Straits Settlements\n\n  styles_periods_indexing_terms: Peranakan\n\n  inscriptions: \n\n  inscription_language: \n\n  shape: irregular\n\n  materials_name: denim\n\n  techniques_name: sewing (needleworking technique)\n\n  object_colour: multicolored\n\n  physical_appearance: This is a short-sleeved denim jacket. It has a circular collar and frog buttons. It is lined with a brown striped fabric.\n\n  subject_terms_1: tops (garments\n general) Peranakan folk costume\n\n  subject_terms_2: Ethnic costume Peranakan (Asian people) Jackets\n\n  subject_terms_3: Peranakan costumes\n\n  sgcool_label_text: This short-sleeve jacket has a circular collar and frog buttons with a placket underneath. It is lined with a brown striped fabric.It is usually paired with a pair of black pants. It is part of a donation which contains a mixture of garments worn by Peranakan men and women.\n",
  "createdDate": "20201201203308",
  "version": 0,
  "latest": false,
  "roles": [],
  "metadata": {
    "accession_no_csv": "2016-00694",
    "Image": "",
    "object_work_type": "jackets (garments)",
    "title_text": "Short-sleeved Jacket with Frog Buttons",
    "preference": "main",
    "title_language": "",
    "creation_date": "20th century",
    "creation_place_original_location": "Indonesia Straits Settlements",
    "styles_periods_indexing_terms": "Peranakan",
    "inscriptions": "",
    "inscription_language": "",
    "shape": "irregular",
    "materials_name": "denim",
    "techniques_name": "sewing (needleworking technique)",
    "object_colour": "multicolored",
    "physical_appearance": "This is a short-sleeved denim jacket. It has a circular collar and frog buttons. It is lined with a brown striped fabric.",
    "subject_terms_1": "tops (garments, general) Peranakan folk costume",
    "subject_terms_2": "Ethnic costume Peranakan (Asian people) Jackets",
    "subject_terms_3": "Peranakan costumes",
    "sgcool_label_text": "This short-sleeve jacket has a circular collar and frog buttons with a placket underneath. It is lined with a brown striped fabric.It is usually paired with a pair of black pants. It is part of a donation which contains a mixture of garments worn by Peranakan men and women."
  },
  "nlpDate": "20201201203308",
  "connectorId": 0,
  "tags": {}
}