{
  "id": "2016-00057",
  "title": "Hand Billet -  Sri Thendayuthapani Temple, Johor Bahru",
  "source": "Bumblebee",
  "path": "./Data/json/",
  "content": "\n  accession_no_csv: 2016-00057\n\n  Image: \n\n  object_work_type: fliers (printed matter)\n\n  title_text: Hand Billet -  Sri Thendayuthapani Temple\n Johor Bahru\n\n  preference: main\n\n  title_language: \n\n  creator_2: Unknown\n\n  creation_date: 2-Feb-50\n\n  creation_place_original_location: Johor Bahru (Johor\n Malaysia)\n\n  styles_periods_indexing_terms: Not indicated\n\n  inscriptions: \n\n  inscription_language: \n\n  scale_type: Not indicated\n\n  shape: rectangular\n\n  materials_name: printing paper\n\n  techniques_name: printing (process)\n\n  object_colour: multicoloured\n\n  physical_appearance: \\The image shows a flyer. It is rectangular in shape with a light brown background. There is a purple border surrounding the details that are presented on the flyer. \\\\2-2-1950\\\\ is stated in the first paragraph. The entire page is written in the Tamil script. At the top of the page\n\n  subject_terms_1: there is an image of a Hindu deity with a peacock.\\ Hinduism\n\n  subject_terms_2: temples (buidings) Hinduism Fliers (Ephemera)\n\n  subject_terms_3: Hindu temples Sri Thendayuthapani Temple Hinduism\n\n  subject_terms_4: Temples\n",
  "createdDate": "20201120223706",
  "version": 0,
  "latest": false,
  "roles": [],
  "metadata": {
    "accession_no_csv": "2016-00057",
    "Image": "",
    "object_work_type": "fliers (printed matter)",
    "title_text": "Hand Billet -  Sri Thendayuthapani Temple, Johor Bahru",
    "preference": "main",
    "title_language": "",
    "creator_2": "Unknown",
    "creation_date": "2-Feb-50",
    "creation_place_original_location": "Johor Bahru (Johor, Malaysia)",
    "styles_periods_indexing_terms": "Not indicated",
    "inscriptions": "",
    "inscription_language": "",
    "scale_type": "Not indicated",
    "shape": "rectangular",
    "materials_name": "printing paper",
    "techniques_name": "printing (process)",
    "object_colour": "multicoloured",
    "physical_appearance": "\"The image shows a flyer. It is rectangular in shape with a light brown background. There is a purple border surrounding the details that are presented on the flyer. \"\"2-2-1950\"\" is stated in the first paragraph. The entire page is written in the Tamil script. At the top of the page",
    "subject_terms_1": "there is an image of a Hindu deity with a peacock.\" Hinduism",
    "subject_terms_2": "temples (buidings) Hinduism Fliers (Ephemera)",
    "subject_terms_3": "Hindu temples Sri Thendayuthapani Temple Hinduism",
    "subject_terms_4": "Temples"
  },
  "nlpDate": "20201120223706",
  "connectorId": 0,
  "tags": {}
}