{"id":"2016-00693","title":"Kebaya with Printed Foliate Pattern","source":"Bumblebee","path":"./Data/json/","content":"accession_no_csv:2016-00693\nImage:\nobject_work_type:kebayas womenswear\ntitle_text:Kebaya with Printed Foliate Pattern\npreference:main\ntitle_language:\ncreation_date:early-mid 20th century\ncreation_place_original_location:Java (Indonesia)\nstyles_periods_indexing_terms:Peranakan\ninscriptions:\ninscription_language:\nshape:irregular\nmaterials_name:cotton (textile)\ntechniques_name:sewing (needleworking technique)\nobject_colour:multicolored\nphysical_appearance:This is a kebaya top. It is made from a light fabric with a printed recurring motif of foliage and small flowers.\nsubject_terms_1:folk costume flowers (motifs) foliage (motif) Peranakan tops (garments\n general) blouses (main garments)\nsubject_terms_2:Ethnic costume Motifs Peranakan (Asian people) Blouses\nsubject_terms_3:Peranakan costumes\nsgcool_label_text:This kebaya is made from a light fabric printed with a recurring motif of foliage and small flowers. It is part of a donation which contains a mixture of garments worn by Peranakan men and women.","createdDate":"20201018182635","version":0,"latest":false,"roles":[],"metadata":{"accession_no_csv":"2016-00693","Image":"","object_work_type":"kebayas womenswear","title_text":"Kebaya with Printed Foliate Pattern","preference":"main","title_language":"","creation_date":"early-mid 20th century","creation_place_original_location":"Java (Indonesia)","styles_periods_indexing_terms":"Peranakan","inscriptions":"","inscription_language":"","shape":"irregular","materials_name":"cotton (textile)","techniques_name":"sewing (needleworking technique)","object_colour":"multicolored","physical_appearance":"This is a kebaya top. It is made from a light fabric with a printed recurring motif of foliage and small flowers.","subject_terms_1":"folk costume flowers (motifs) foliage (motif) Peranakan tops (garments, general) blouses (main garments)","subject_terms_2":"Ethnic costume Motifs Peranakan (Asian people) Blouses","subject_terms_3":"Peranakan costumes","sgcool_label_text":"This kebaya is made from a light fabric printed with a recurring motif of foliage and small flowers. It is part of a donation which contains a mixture of garments worn by Peranakan men and women."},"nlpDate":"20201018182635","connectorId":0,"tags":{}}