{"id":"2016-00468","title":"Lamp screen","source":"Bumblebee","path":"./Data/json/","content":"accession_no_csv:2016-00468\nImage:\nobject_work_type:screens (furniture)\ntitle_text:Lamp screen\npreference:main\ntitle_language:\ncreation_date:1900-1920\ncreation_place_original_location:Singapore\ninscriptions:\ninscription_language:\nshape:irregular\nmaterials_name:wood (plant material) glass (material)\ntechniques_name:woodcarving gilding (technique)\nobject_colour:red (color)\nphysical_appearance:This is a lamp screen. It is red\n with two panels of glass. At the top and bottom of the glass on each panel\n there is a gilded gold boards with carved foliage motifs. The gold gilding looks slightly faded.\nsubject_terms_1:foliage (motif) deities worship altar components Peranakan\nsubject_terms_2:Screens Worship Gods Buddhist altars Motifs Peranakan (Asian people)\nsubject_terms_3:Religious life and practices\nsgcool_label_text:This lamp screen is made of wood\n painted red and gilded\n with two panels of glass. The screen is placed on the higher altar altar to house an oil lamp\n helping to keep the flame lit.\\r\\n\\r\\nIn particular\n this lamp screen belonged to the family of Mdm Chua Geok Choo and Tan Eng Wah (1923-2013). It was passed down Mdm Chua’s side of the family and was used for the worship of Guanyin\n the Goddess of Mercy; in the family home at East Coast Avenue.\\r\\n\\r\\nTan Eng Wah was also the eldest son of Tan Lark Sye (1897-1972). Tan Lark Sye was a highly regarded Chinese businessman and philanthropist in Singapore.","createdDate":"20201018182635","version":0,"latest":false,"roles":[],"metadata":{"accession_no_csv":"2016-00468","Image":"","object_work_type":"screens (furniture)","title_text":"Lamp screen","preference":"main","title_language":"","creation_date":"1900-1920","creation_place_original_location":"Singapore","inscriptions":"","inscription_language":"","shape":"irregular","materials_name":"wood (plant material) glass (material)","techniques_name":"woodcarving gilding (technique)","object_colour":"red (color)","physical_appearance":"This is a lamp screen. It is red, with two panels of glass. At the top and bottom of the glass on each panel, there is a gilded gold boards with carved foliage motifs. The gold gilding looks slightly faded.","subject_terms_1":"foliage (motif) deities worship altar components Peranakan","subject_terms_2":"Screens Worship Gods Buddhist altars Motifs Peranakan (Asian people)","subject_terms_3":"Religious life and practices","sgcool_label_text":"This lamp screen is made of wood, painted red and gilded, with two panels of glass. The screen is placed on the higher altar altar to house an oil lamp, helping to keep the flame lit.\r\n\r\nIn particular, this lamp screen belonged to the family of Mdm Chua Geok Choo and Tan Eng Wah (1923-2013). It was passed down Mdm Chua’s side of the family and was used for the worship of Guanyin, the Goddess of Mercy; in the family home at East Coast Avenue.\r\n\r\nTan Eng Wah was also the eldest son of Tan Lark Sye (1897-1972). Tan Lark Sye was a highly regarded Chinese businessman and philanthropist in Singapore."},"nlpDate":"20201018182635","connectorId":0,"tags":{}}