{
  "id": "2016-00560",
  "title": "Barisan Sosialis Chinese-language party newsletters (160 copies) Barisan Sosialis Chinese-language party newsletters (160 copies)",
  "source": "Bumblebee",
  "path": "./Data/json/",
  "content": "\n  accession_no_csv: 2016-00560\n\n  Image: \n\n  object_work_type: weeklies (publications) newsletters weeklies (publications) newsletters\n\n  title_text: Barisan Sosialis Chinese-language party newsletters (160 copies) Barisan Sosialis Chinese-language party newsletters (160 copies)\n\n  preference: main main\n\n  title_language: \n\n  creator_2: Barisan Sosialis Barisan Sosialis\n\n  creator_1: Barisan Sosialis (Singapore) Barisan Sosialis (Singapore)\n\n  creator_role: creators publishers creators publishers\n\n  creation_date: 1963 - 1966 1963 - 1966\n\n  creation_place_original_location: Singapore Singapore\n\n  styles_periods_indexing_terms: NA NA\n\n  inscriptions: \n\n  inscription_language: \n\n  scale_type: NA NA\n\n  shape: rectangular rectangular\n\n  materials_name: printing paper printing paper\n\n  techniques_name: colour printing colour printing\n\n  object_colour: multicoloured multicoloured\n\n  edition_description: NA NA\n\n  physical_appearance: The image shows the a series of weekly newsletters. All of them are rectangular in shape. The background of the newsletters are a mixture of grey and red.The masthead\n headlines\n and articles are all written in Chinese characters. There are several handwritten lines of Chinese characters on the front cover of the newsletter as well. The image shows the a series of weekly newsletters. All of them are rectangular in shape. The background of the newsletters are a mixture of grey and red.The masthead\n headlines\n and articles are all written in Chinese characters. There are several handwritten lines of Chinese characters on the front cover of the newsletter as well.\n\n  subject_terms_1: politics propaganda socialism political organizations politics propaganda socialism political organizations\n\n  subject_terms_2: Newsletters Political party organization Socialist propaganda Newsletters Political party organization Socialist propaganda\n\n  subject_terms_3: Newsletters Barisan Sosialis Newsletters Barisan Sosialis\n\n  subject_terms_4: NA NA\n\n  context_1: NA NA\n\n  context_2: NA NA\n\n  context_3: NA NA\n\n  context_4: NA NA\n\n  context_5: NA NA\n\n  context_6: NA NA\n\n  context_7: NA NA\n\n  context_8: NA NA\n\n  context_9: NA NA\n\n  context_10: NA NA\n\n  context_11: NA NA\n\n  context_12: NA NA\n\n  context_13: NA NA\n\n  context_14: NA NA\n\n  context_15: NA NA\n\n  context_16: NA NA\n\n  context_17: NA NA\n\n  context_18: NA NA\n\n  context_19: NA NA\n\n  context_20: NA NA\n\n  context_21: NA NA\n\n  context_22: NA NA\n\n  context_23: NA NA\n\n  context_24: NA NA\n\n  sgcool_label_text: Chenxianbao (???) was the Chinese-language party newsletter of the Barisan Sosialis (Socialist Front)\n a left-wing political party established in Singapore in 1961. It was published weekly and sold at 10 cents a copy. Chenxianbao (???) was the Chinese-language party newsletter of the Barisan Sosialis (Socialist Front)\n a left-wing political party established in Singapore in 1961. It was published weekly and sold at 10 cents a copy.\n",
  "createdDate": "20201120223707",
  "version": 0,
  "latest": false,
  "roles": [],
  "metadata": {
    "accession_no_csv": "2016-00560",
    "Image": "",
    "object_work_type": "weeklies (publications) newsletters weeklies (publications) newsletters",
    "title_text": "Barisan Sosialis Chinese-language party newsletters (160 copies) Barisan Sosialis Chinese-language party newsletters (160 copies)",
    "preference": "main main",
    "title_language": "",
    "creator_2": "Barisan Sosialis Barisan Sosialis",
    "creator_1": "Barisan Sosialis (Singapore) Barisan Sosialis (Singapore)",
    "creator_role": "creators publishers creators publishers",
    "creation_date": "1963 - 1966 1963 - 1966",
    "creation_place_original_location": "Singapore Singapore",
    "styles_periods_indexing_terms": "NA NA",
    "inscriptions": "",
    "inscription_language": "",
    "scale_type": "NA NA",
    "shape": "rectangular rectangular",
    "materials_name": "printing paper printing paper",
    "techniques_name": "colour printing colour printing",
    "object_colour": "multicoloured multicoloured",
    "edition_description": "NA NA",
    "physical_appearance": "The image shows the a series of weekly newsletters. All of them are rectangular in shape. The background of the newsletters are a mixture of grey and red.The masthead, headlines, and articles are all written in Chinese characters. There are several handwritten lines of Chinese characters on the front cover of the newsletter as well. The image shows the a series of weekly newsletters. All of them are rectangular in shape. The background of the newsletters are a mixture of grey and red.The masthead, headlines, and articles are all written in Chinese characters. There are several handwritten lines of Chinese characters on the front cover of the newsletter as well.",
    "subject_terms_1": "politics propaganda socialism political organizations politics propaganda socialism political organizations",
    "subject_terms_2": "Newsletters Political party organization Socialist propaganda Newsletters Political party organization Socialist propaganda",
    "subject_terms_3": "Newsletters Barisan Sosialis Newsletters Barisan Sosialis",
    "subject_terms_4": "NA NA",
    "context_1": "NA NA",
    "context_2": "NA NA",
    "context_3": "NA NA",
    "context_4": "NA NA",
    "context_5": "NA NA",
    "context_6": "NA NA",
    "context_7": "NA NA",
    "context_8": "NA NA",
    "context_9": "NA NA",
    "context_10": "NA NA",
    "context_11": "NA NA",
    "context_12": "NA NA",
    "context_13": "NA NA",
    "context_14": "NA NA",
    "context_15": "NA NA",
    "context_16": "NA NA",
    "context_17": "NA NA",
    "context_18": "NA NA",
    "context_19": "NA NA",
    "context_20": "NA NA",
    "context_21": "NA NA",
    "context_22": "NA NA",
    "context_23": "NA NA",
    "context_24": "NA NA",
    "sgcool_label_text": "Chenxianbao (???) was the Chinese-language party newsletter of the Barisan Sosialis (Socialist Front), a left-wing political party established in Singapore in 1961. It was published weekly and sold at 10 cents a copy. Chenxianbao (???) was the Chinese-language party newsletter of the Barisan Sosialis (Socialist Front), a left-wing political party established in Singapore in 1961. It was published weekly and sold at 10 cents a copy."
  },
  "nlpDate": "20201120223707",
  "connectorId": 0,
  "tags": {}
}