{
  "id": "2016-00212-027",
  "title": "Photograph album of views and portraits in the Punjab, Cashmere, Ceylon, Burma, Penang, Singapore, and Java Sacred Bo Tree, Anaradjapoora, Ceylon",
  "source": "Bumblebee",
  "path": "./Data/json/",
  "content": "\n  accession_no_csv: 2016-00212-027\n\n  Image: \n\n  object_work_type: black-and-white photographs\n\n  title_text: Photograph album of views and portraits in the Punjab\n Cashmere\n Ceylon\n Burma\n Penang\n Singapore\n and Java Sacred Bo Tree\n Anaradjapoora\n Ceylon\n\n  preference: alternate main\n\n  title_language: \n\n  creator_2: John Thomson\n\n  creator_1: Thomson\n J. (John)\n 1837-1921\n\n  creator_role: photographers\n\n  creation_date: before 28 Jul 1876\n\n  creation_place_original_location: Singapore Anuradhapura (Sri Lanka)\n\n  inscriptions: \n\n  inscription_language: \n\n  shape: rectangular\n\n  materials_name: albumen (egg white protein) albumen paper paper (fiber product)\n\n  techniques_name: albumen process\n\n  object_colour: black-and-white (colors)\n\n  physical_appearance: This is a photograph of the Jaya Sri Maha Bodhi\n or Sacred Bo Tree\n in Anaradhapura\n Sri Lanka. There is a fence on the upper terrace of the structure\n in front of the tree. Near the center-left of the photograph\n there is a woman covered in all black\n standing by a pillar. At the bottom of the photograph\n there is the remains of the upper torso of a seated Buddha statue. The word \\u0027LAWTON\\u0027 is handwritten on the photograph on the right. The title is written at the bottom\n below the photograph.\n\n  subject_terms_1: sacred trees Buddhism\n\n  subject_terms_2: Photographs Thomson\n J. (John)\n 1837-1921 Anuradhapura (Sri Lanka) Buddhism Bodhi Tree\n\n  subject_terms_3: Photography Buddhism Historic Sites\n",
  "createdDate": "20201120223706",
  "version": 0,
  "latest": false,
  "roles": [],
  "metadata": {
    "accession_no_csv": "2016-00212-027",
    "Image": "",
    "object_work_type": "black-and-white photographs",
    "title_text": "Photograph album of views and portraits in the Punjab, Cashmere, Ceylon, Burma, Penang, Singapore, and Java Sacred Bo Tree, Anaradjapoora, Ceylon",
    "preference": "alternate main",
    "title_language": "",
    "creator_2": "John Thomson",
    "creator_1": "Thomson, J. (John), 1837-1921",
    "creator_role": "photographers",
    "creation_date": "before 28 Jul 1876",
    "creation_place_original_location": "Singapore Anuradhapura (Sri Lanka)",
    "inscriptions": "",
    "inscription_language": "",
    "shape": "rectangular",
    "materials_name": "albumen (egg white protein) albumen paper paper (fiber product)",
    "techniques_name": "albumen process",
    "object_colour": "black-and-white (colors)",
    "physical_appearance": "This is a photograph of the Jaya Sri Maha Bodhi, or Sacred Bo Tree, in Anaradhapura, Sri Lanka. There is a fence on the upper terrace of the structure, in front of the tree. Near the center-left of the photograph, there is a woman covered in all black, standing by a pillar. At the bottom of the photograph, there is the remains of the upper torso of a seated Buddha statue. The word \u0027LAWTON\u0027 is handwritten on the photograph on the right. The title is written at the bottom, below the photograph.",
    "subject_terms_1": "sacred trees Buddhism",
    "subject_terms_2": "Photographs Thomson, J. (John), 1837-1921 Anuradhapura (Sri Lanka) Buddhism Bodhi Tree",
    "subject_terms_3": "Photography Buddhism Historic Sites"
  },
  "nlpDate": "20201120223706",
  "connectorId": 0,
  "tags": {}
}