{
  "id": "2016-00212-050",
  "title": "Photograph album of views and portraits in the Punjab, Cashmere, Ceylon, Burma, Penang, Singapore, and Java Bombay Burma Trading Company\u0027s Timber Yard, Dallah, Rangoon.",
  "source": "Bumblebee",
  "path": "./Data/json/",
  "content": "\n  accession_no_csv: 2016-00212-050\n\n  Image: \n\n  object_work_type: black-and-white photographs\n\n  title_text: Photograph album of views and portraits in the Punjab\n Cashmere\n Ceylon\n Burma\n Penang\n Singapore\n and Java Bombay Burma Trading Company\\u0027s Timber Yard\n Dallah\n Rangoon.\n\n  preference: main alternate\n\n  title_language: \n\n  creator_2: John Thomson\n\n  creator_1: Thomson\n J. (John)\n 1837-1921\n\n  creator_role: photographers\n\n  creation_date: before 28 Jul 1876\n\n  creation_place_original_location: Singapore Rangoon (Burma)\n\n  inscriptions: \n\n  inscription_language: \n\n  shape: rectangular\n\n  materials_name: albumen (egg white protein) paper (fiber product) albumen paper\n\n  techniques_name: albumen process\n\n  object_colour: black-and-white (colors)\n\n  physical_appearance: This is a photograph of a timber yard in Rangoon. The photograph features a plot of land\n with numerous wood logs on the ground. There are seven men on elephants. They are accompanied by several other men standing amongst them\n with one men in the middle dressed in a suit and hat. The title is written at the bottom\n below the photograph.\n\n  subject_terms_1: lumberyards (buildings or lots) timber centers\n\n  subject_terms_2: Lumber-yards Photographs Timber Thomson\n J. (John)\n 1837-1921 Bombay Burmah Trading Corporation\n\n  subject_terms_3: Photography Trade and industry\n",
  "createdDate": "20201125084537",
  "version": 0,
  "latest": false,
  "roles": [],
  "metadata": {
    "accession_no_csv": "2016-00212-050",
    "Image": "",
    "object_work_type": "black-and-white photographs",
    "title_text": "Photograph album of views and portraits in the Punjab, Cashmere, Ceylon, Burma, Penang, Singapore, and Java Bombay Burma Trading Company\u0027s Timber Yard, Dallah, Rangoon.",
    "preference": "main alternate",
    "title_language": "",
    "creator_2": "John Thomson",
    "creator_1": "Thomson, J. (John), 1837-1921",
    "creator_role": "photographers",
    "creation_date": "before 28 Jul 1876",
    "creation_place_original_location": "Singapore Rangoon (Burma)",
    "inscriptions": "",
    "inscription_language": "",
    "shape": "rectangular",
    "materials_name": "albumen (egg white protein) paper (fiber product) albumen paper",
    "techniques_name": "albumen process",
    "object_colour": "black-and-white (colors)",
    "physical_appearance": "This is a photograph of a timber yard in Rangoon. The photograph features a plot of land, with numerous wood logs on the ground. There are seven men on elephants. They are accompanied by several other men standing amongst them, with one men in the middle dressed in a suit and hat. The title is written at the bottom, below the photograph.",
    "subject_terms_1": "lumberyards (buildings or lots) timber centers",
    "subject_terms_2": "Lumber-yards Photographs Timber Thomson, J. (John), 1837-1921 Bombay Burmah Trading Corporation",
    "subject_terms_3": "Photography Trade and industry"
  },
  "nlpDate": "20201125084537",
  "connectorId": 0,
  "tags": {}
}