{
  "id": "2016-00114",
  "title": "Untitled",
  "source": "Bumblebee",
  "path": "./Data/json/",
  "content": "\n  accession_no_csv: 2016-00114\n\n  Image: \n\n  object_work_type: charcoal drawings\n\n  title_text: Untitled\n\n  preference: main\n\n  title_language: \n\n  creator_2: May Oon Filmeridis\n\n  creator_1: Filmeridis\n May Oon\n\n  creator_role: artists (visual artists)\n\n  creation_date: 2015\n\n  creation_place_original_location: Singapore\n\n  inscriptions: \n\n  inscription_language: \n\n  shape: rectangular\n\n  materials_name: jute (fiber) charcoal (material)\n\n  techniques_name: screen printing  painting (image-making)\n\n  object_colour: multicoloured\n\n  physical_appearance: \\The image shows a rectangular painting. \\\\We will no longer be slaves\\\\ is displayed in red capital letters in 3 rows of lines. In between each row of words\n\n  subject_terms_1: there is an image of a man drawn with only black outlines. \\ labourers political art derivative works immigrants\n\n  subject_terms_2: paintings (visual works) Charcoal drawing Blue collar workers Derivative works Immigrants\n\n  subject_terms_3: Painting\n\n  subject_terms_4: Visual arts\n",
  "createdDate": "20201120223706",
  "version": 0,
  "latest": false,
  "roles": [],
  "metadata": {
    "accession_no_csv": "2016-00114",
    "Image": "",
    "object_work_type": "charcoal drawings",
    "title_text": "Untitled",
    "preference": "main",
    "title_language": "",
    "creator_2": "May Oon Filmeridis",
    "creator_1": "Filmeridis, May Oon",
    "creator_role": "artists (visual artists)",
    "creation_date": "2015",
    "creation_place_original_location": "Singapore",
    "inscriptions": "",
    "inscription_language": "",
    "shape": "rectangular",
    "materials_name": "jute (fiber) charcoal (material)",
    "techniques_name": "screen printing  painting (image-making)",
    "object_colour": "multicoloured",
    "physical_appearance": "\"The image shows a rectangular painting. \"\"We will no longer be slaves\"\" is displayed in red capital letters in 3 rows of lines. In between each row of words",
    "subject_terms_1": "there is an image of a man drawn with only black outlines. \" labourers political art derivative works immigrants",
    "subject_terms_2": "paintings (visual works) Charcoal drawing Blue collar workers Derivative works Immigrants",
    "subject_terms_3": "Painting",
    "subject_terms_4": "Visual arts"
  },
  "nlpDate": "20201120223706",
  "connectorId": 0,
  "tags": {}
}