{"id":"2016-00285","title":"Young Songwriters Society poster Young Songwriters Society poster 1988","source":"Bumblebee","path":"./Data/json/","content":"accession_no_csv:2016-00285\nImage:\nobject_work_type:posters\ntitle_text:Young Songwriters Society poster Young Songwriters Society poster 1988\npreference:main alternate\ntitle_language:\ncreator_2:Young Songwriters Society Anterluck Services\ncreator_1:NA NA\ncreator_role:creators designers\ncreation_date:1988\ncreation_place_original_location:Singapore\ninscriptions:\ninscription_language:\nshape:rectangular\nmaterials_name:paper (fiber product)\ntechniques_name:colour printing\nobject_colour:multicoloured\nphysical_appearance:\\The image shows a poster and it has white background. There are three Chinese characters and the year \\u00271988\\u0027 that are displayed in blue in large fonts near the top of the poster. At the top centre of the poster\n there is a single row of Chinese characters and the words \\\\The Young Songwriters Society\\\\. At the bottom of the poster\nsubject_terms_1:the logos of McDonald\\u0027s societies festivals music (performing arts) concerts\nsubject_terms_2:Metro department store Societies Folk musicians Music festivals Folk music Concerts\nsubject_terms_3:and PRS are displayed as sponsors. In the middle of the poster Music organisations\nsubject_terms_4:there are cartoon sketches of more than fifty human figures who are either dancing\ncontext_1:playing musical instruments and singing\ncontext_2:and holding a long blue banner. Below the cartoon sketches of the human figures\ncontext_3:there are several rows of Chinese characters together with English words and numbers denoting prices\ncontext_4:dates\ncontext_5:and a postal code. Ther are slight tears on the sides of the poster.\\\ncontext_6:musicians\ncontext_7:Posters\ncontext_8:Chinese folk songs","createdDate":"20201119143405","version":0,"latest":false,"roles":[],"metadata":{"accession_no_csv":"2016-00285","Image":"","object_work_type":"posters","title_text":"Young Songwriters Society poster Young Songwriters Society poster 1988","preference":"main alternate","title_language":"","creator_2":"Young Songwriters Society Anterluck Services","creator_1":"NA NA","creator_role":"creators designers","creation_date":"1988","creation_place_original_location":"Singapore","inscriptions":"","inscription_language":"","shape":"rectangular","materials_name":"paper (fiber product)","techniques_name":"colour printing","object_colour":"multicoloured","physical_appearance":"\"The image shows a poster and it has white background. There are three Chinese characters and the year \u00271988\u0027 that are displayed in blue in large fonts near the top of the poster. At the top centre of the poster, there is a single row of Chinese characters and the words \"\"The Young Songwriters Society\"\". At the bottom of the poster","subject_terms_1":"the logos of McDonald\u0027s societies festivals music (performing arts) concerts","subject_terms_2":"Metro department store Societies Folk musicians Music festivals Folk music Concerts","subject_terms_3":"and PRS are displayed as sponsors. In the middle of the poster Music organisations","subject_terms_4":"there are cartoon sketches of more than fifty human figures who are either dancing","context_1":"playing musical instruments and singing","context_2":"and holding a long blue banner. Below the cartoon sketches of the human figures","context_3":"there are several rows of Chinese characters together with English words and numbers denoting prices","context_4":"dates","context_5":"and a postal code. Ther are slight tears on the sides of the poster.\"","context_6":"musicians","context_7":"Posters","context_8":"Chinese folk songs"},"nlpDate":"20201119143405","connectorId":0,"tags":{}}