{
  "id": "2016-00665",
  "title": "Deluxe focus scope Focus scope",
  "source": "Bumblebee",
  "path": "./Data/json/",
  "content": "\n  accession_no_csv: 2016-00665\n\n  Image: \n\n  object_work_type: photograph viewing equipment\n\n  title_text: Deluxe focus scope Focus scope\n\n  preference: main alternate\n\n  title_language: \n\n  creator_2: LPL Co. Ltd Tokyo-Japan\n\n  creator_role: manufacturers\n\n  creation_date: 1980s-1990s\n\n  creation_place_original_location: Japan Singapore\n\n  inscriptions: \n\n  inscription_language: \n\n  shape: irregular\n\n  materials_name: plastic (organic material)\n\n  techniques_name: forming (physical activity)\n\n  object_colour: black (colour)\n\n  physical_appearance: The focus scope is black in colour. At the base of the scope\n there is a silver-coloured surface where information is displayed. The numerals \\u00275431\\u0027\n together with the company initials \\u0027LBL\\u0027 and the words \\u0027Deluxe Focus Scope Made in Japan\\u0027 are displayed. Some discolouration can be discerned on the body of the scope.\n\n  subject_terms_1: photographic equipment tools\n\n  subject_terms_2: Tools Photography Equipment and supplies\n\n  subject_terms_3: Photography\n\n  context_20: The set of equipment was used by The Picture Farm Pte Ltd\n\n  context_21: 45 Jalan Pemimpin\n #09-00 Foo Wah Industrial Building\n Thomson\n Singapore\n\n  context_22: 1970 - present\n\n  context_23: 1970\n\n  context_24: present\n\n  sgcool_label_text: A focus scope is a tool used to fine tune the focus of the grains of the negative in photographic film processing. This grain focuser is part of the darkroom photography equipment that was previously used by The Picture Farm\n which was set up by the renowned photographer Willie Tang.\n",
  "createdDate": "20201125084531",
  "version": 0,
  "latest": false,
  "roles": [],
  "metadata": {
    "accession_no_csv": "2016-00665",
    "Image": "",
    "object_work_type": "photograph viewing equipment",
    "title_text": "Deluxe focus scope Focus scope",
    "preference": "main alternate",
    "title_language": "",
    "creator_2": "LPL Co. Ltd Tokyo-Japan",
    "creator_role": "manufacturers",
    "creation_date": "1980s-1990s",
    "creation_place_original_location": "Japan Singapore",
    "inscriptions": "",
    "inscription_language": "",
    "shape": "irregular",
    "materials_name": "plastic (organic material)",
    "techniques_name": "forming (physical activity)",
    "object_colour": "black (colour)",
    "physical_appearance": "The focus scope is black in colour. At the base of the scope, there is a silver-coloured surface where information is displayed. The numerals \u00275431\u0027, together with the company initials \u0027LBL\u0027 and the words \u0027Deluxe Focus Scope Made in Japan\u0027 are displayed. Some discolouration can be discerned on the body of the scope.",
    "subject_terms_1": "photographic equipment tools",
    "subject_terms_2": "Tools Photography Equipment and supplies",
    "subject_terms_3": "Photography",
    "context_20": "The set of equipment was used by The Picture Farm Pte Ltd",
    "context_21": "45 Jalan Pemimpin, #09-00 Foo Wah Industrial Building, Thomson, Singapore",
    "context_22": "1970 - present",
    "context_23": "1970",
    "context_24": "present",
    "sgcool_label_text": "A focus scope is a tool used to fine tune the focus of the grains of the negative in photographic film processing. This grain focuser is part of the darkroom photography equipment that was previously used by The Picture Farm, which was set up by the renowned photographer Willie Tang."
  },
  "nlpDate": "20201125084531",
  "connectorId": 0,
  "tags": {}
}