{
  "id": "2016-00212-007",
  "title": "Photograph album of views and portraits in the Punjab, Cashmere, Ceylon, Burma, Penang, Singapore, and Java Government House, Lahore",
  "source": "Bumblebee",
  "path": "./Data/json/",
  "content": "\n  accession_no_csv: 2016-00212-007\n\n  Image: \n\n  object_work_type: black-and-white photographs\n\n  title_text: Photograph album of views and portraits in the Punjab\n Cashmere\n Ceylon\n Burma\n Penang\n Singapore\n and Java Government House\n Lahore\n\n  preference: alternate main\n\n  title_language: \n\n  creator_2: John Thomson\n\n  creator_1: Thomson\n J. (John)\n 1837-1921\n\n  creator_role: photographers\n\n  creation_date: before 28 Jul 1876\n\n  creation_place_original_location: Singapore Lahore (Pakistan)\n\n  inscriptions: \n\n  inscription_language: \n\n  shape: rectangular\n\n  materials_name: albumen (egg white protein) albumen paper paper (fiber product)\n\n  techniques_name: albumen process\n\n  object_colour: black-and-white (colors)\n\n  physical_appearance: This is a photograph of the Government House in Lahore\n Pakistan. In the center of the photograph\n there is a large building\n with staggered levels. The building has a large balcony with two roofed entrances.There are several trees along the outside of the building on the left and right of the photograph.\n\n  subject_terms_1: government office buildings colonization\n\n  subject_terms_2: Photographs Thomson\n J. (John)\n 1837-1921 Lahore (Pakistan) Governor\\u0027s House (Lahore\n Pakistan) Colonization\n\n  subject_terms_3: Photography Politics and government Historic buildings\n",
  "createdDate": "20201120223706",
  "version": 0,
  "latest": false,
  "roles": [],
  "metadata": {
    "accession_no_csv": "2016-00212-007",
    "Image": "",
    "object_work_type": "black-and-white photographs",
    "title_text": "Photograph album of views and portraits in the Punjab, Cashmere, Ceylon, Burma, Penang, Singapore, and Java Government House, Lahore",
    "preference": "alternate main",
    "title_language": "",
    "creator_2": "John Thomson",
    "creator_1": "Thomson, J. (John), 1837-1921",
    "creator_role": "photographers",
    "creation_date": "before 28 Jul 1876",
    "creation_place_original_location": "Singapore Lahore (Pakistan)",
    "inscriptions": "",
    "inscription_language": "",
    "shape": "rectangular",
    "materials_name": "albumen (egg white protein) albumen paper paper (fiber product)",
    "techniques_name": "albumen process",
    "object_colour": "black-and-white (colors)",
    "physical_appearance": "This is a photograph of the Government House in Lahore, Pakistan. In the center of the photograph, there is a large building, with staggered levels. The building has a large balcony with two roofed entrances.There are several trees along the outside of the building on the left and right of the photograph.",
    "subject_terms_1": "government office buildings colonization",
    "subject_terms_2": "Photographs Thomson, J. (John), 1837-1921 Lahore (Pakistan) Governor\u0027s House (Lahore, Pakistan) Colonization",
    "subject_terms_3": "Photography Politics and government Historic buildings"
  },
  "nlpDate": "20201120223706",
  "connectorId": 0,
  "tags": {}
}