{"id":"2016-00313","title":"Makara headed bangles","source":"Bumblebee","path":"./Data/json/","content":"accession_no_csv:2016-00313\nImage:\nobject_work_type:bangles\ntitle_text:Makara headed bangles\npreference:main\ntitle_language:\ncreation_place_original_location:Jaipur (India)\nstyles_periods_indexing_terms:Mughal\ninscriptions:\ninscription_language:\nshape:irregular\nmaterials_name:gold (metal) enamel paint quartz crystal diamond (mineral)\ntechniques_name:forging (metal forming) carving (processes) painting (image making)\nobject_colour:multicolored\nphysical_appearance:This is a pair of bangles that are closed by a clasp in the shape of Makara heads. It is decorated with gold and enamel paint. Small pieces of diamonds lined the outside of the bangle\n while the inside is painted with floral motifs.\nsubject_terms_1:foliage (motif) flower (motif) jewelry makara\nsubject_terms_2:Bracelets Diamond jewelry\n Mogul Empire Motifs Makara\nsubject_terms_3:Jewellery Indian decorative arts\nsgcool_label_text:A pair of gold and enamelled makara head bangles\n decorated with precious stones\n and exquisite enamelling on the inside of the shank. A makara is a mythical sea creature. This object shows the taste for luxury objects in Northern India in the 19th century. In Mughal India there was a great revival in the art of rock crystal carving\n and Mughal craftsmen reached new heights of technical virtuosity especially during the reign of Shah Jahan (1628-1658). The motifs in the gem work and enamelling of flowers\n plants\n scrolling vines and animal forms allude to paradise gardens on earth. It would have been highly prized and made for a privileged few.","createdDate":"20201119143405","version":0,"latest":false,"roles":[],"metadata":{"accession_no_csv":"2016-00313","Image":"","object_work_type":"bangles","title_text":"Makara headed bangles","preference":"main","title_language":"","creation_place_original_location":"Jaipur (India)","styles_periods_indexing_terms":"Mughal","inscriptions":"","inscription_language":"","shape":"irregular","materials_name":"gold (metal) enamel paint quartz crystal diamond (mineral)","techniques_name":"forging (metal forming) carving (processes) painting (image making)","object_colour":"multicolored","physical_appearance":"This is a pair of bangles that are closed by a clasp in the shape of Makara heads. It is decorated with gold and enamel paint. Small pieces of diamonds lined the outside of the bangle, while the inside is painted with floral motifs.","subject_terms_1":"foliage (motif) flower (motif) jewelry makara","subject_terms_2":"Bracelets Diamond jewelry, Mogul Empire Motifs Makara","subject_terms_3":"Jewellery Indian decorative arts","sgcool_label_text":"A pair of gold and enamelled makara head bangles, decorated with precious stones, and exquisite enamelling on the inside of the shank. A makara is a mythical sea creature. This object shows the taste for luxury objects in Northern India in the 19th century. In Mughal India there was a great revival in the art of rock crystal carving, and Mughal craftsmen reached new heights of technical virtuosity especially during the reign of Shah Jahan (1628-1658). The motifs in the gem work and enamelling of flowers, plants, scrolling vines and animal forms allude to paradise gardens on earth. It would have been highly prized and made for a privileged few."},"nlpDate":"20201119143405","connectorId":0,"tags":{}}