{"id":"2016-00277","title":"Jayaram S/o Rengasamy, runner-up, 440 yards, Singapore Amateur Athletic Association, Farrer Park","source":"Bumblebee","path":"./Data/json/","content":"accession_no_csv:2016-00277\nImage:\nobject_work_type:black-and-white photographs\ntitle_text:Jayaram S/o Rengasamy\n runner-up\n 440 yards\n Singapore Amateur Athletic Association\n Farrer Park\npreference:main\ntitle_language:\ncreation_date:1957\ncreation_place_original_location:Singapore\ninscriptions:\ninscription_language:\nshape:rectangular\nmaterials_name:paper (fiber product)\ntechniques_name:printing (process) photographic processes\nobject_colour:grey monochrome\nphysical_appearance:The image shows a photograph that is in black-and-white. It shows a setting in a stadium. Two males can be seen running towards the direction in which the photograph was taken. Both of them are dressed in atletic gear\n with sleeveless tops\n running shorts\n and track shoes. They are running on a stadium track with white lines to demarcate the individual track lanes. One male is ahead the other and is about to reach the white finishing line. Audiences can be seen to be in the background\n as well as cheering on the sides near the foreground.\nsubject_terms_1:athletes stadiums competitions (events) sportsmen races (events) running (physical activity)\nsubject_terms_2:Athletes Stadiums Running races Black-and-white photography\nsubject_terms_3:Photography Athletics Sports and recreational events Rengasamy Jayaram Runners (Athletes) Singapore Amateur Athletic Association\nsgcool_label_text:Jayaram s/o Rengasamy was an amateur athlete who competed at the club level in Singapore and Malaya in the 1940s and 50s. He started his sporting career at the age of 14 as a boxer. In 1953\n a friend and fellow athlete\n MS Maniam\n invited Mr Rengasamy to participate in the Tamil’s Festival or Tamilar Thirunnal. He then began training in athletics at Anglo-Chinese School Barker Road\n the grounds of Victoria School off Jalan Besar and at Farrer Park. Mr Rengasamy also started participating in different races as a middle distance runner at the Tamil’s Festival (1954 – 57)\n Singapore Amateur Athletic Association meets (1955 – 57)\n as well as the Merdeka Games\n Kuala Lumpur (1957). He was also a member of Swift Athletics Club.","createdDate":"20201119143405","version":0,"latest":false,"roles":[],"metadata":{"accession_no_csv":"2016-00277","Image":"","object_work_type":"black-and-white photographs","title_text":"Jayaram S/o Rengasamy, runner-up, 440 yards, Singapore Amateur Athletic Association, Farrer Park","preference":"main","title_language":"","creation_date":"1957","creation_place_original_location":"Singapore","inscriptions":"","inscription_language":"","shape":"rectangular","materials_name":"paper (fiber product)","techniques_name":"printing (process) photographic processes","object_colour":"grey monochrome","physical_appearance":"The image shows a photograph that is in black-and-white. It shows a setting in a stadium. Two males can be seen running towards the direction in which the photograph was taken. Both of them are dressed in atletic gear, with sleeveless tops, running shorts, and track shoes. They are running on a stadium track with white lines to demarcate the individual track lanes. One male is ahead the other and is about to reach the white finishing line. Audiences can be seen to be in the background, as well as cheering on the sides near the foreground.","subject_terms_1":"athletes stadiums competitions (events) sportsmen races (events) running (physical activity)","subject_terms_2":"Athletes Stadiums Running races Black-and-white photography","subject_terms_3":"Photography Athletics Sports and recreational events Rengasamy Jayaram Runners (Athletes) Singapore Amateur Athletic Association","sgcool_label_text":"Jayaram s/o Rengasamy was an amateur athlete who competed at the club level in Singapore and Malaya in the 1940s and 50s. He started his sporting career at the age of 14 as a boxer. In 1953, a friend and fellow athlete, MS Maniam, invited Mr Rengasamy to participate in the Tamil’s Festival or Tamilar Thirunnal. He then began training in athletics at Anglo-Chinese School Barker Road, the grounds of Victoria School off Jalan Besar and at Farrer Park. Mr Rengasamy also started participating in different races as a middle distance runner at the Tamil’s Festival (1954 – 57), Singapore Amateur Athletic Association meets (1955 – 57), as well as the Merdeka Games, Kuala Lumpur (1957). He was also a member of Swift Athletics Club."},"nlpDate":"20201119143405","connectorId":0,"tags":{}}