{
  "id": "2016-00185",
  "title": "SEA cultural plaque",
  "source": "Bumblebee",
  "path": "./Data/json/",
  "content": "\n  accession_no_csv: 2016-00185\n\n  Image: \n\n  object_work_type: plaques (flat objects)\n\n  title_text: SEA cultural plaque\n\n  preference: main\n\n  title_language: \n\n  creator_2: Feng Huang Motion Picture Co.\n\n  creator_1: Feng huang ying ye gong si\n\n  creator_role: companies\n\n  creation_date: 1963\n\n  creation_place_original_location: Singapore\n\n  inscriptions: \n\n  inscription_language: \n\n  shape: irregular\n\n  materials_name: wood (plant material) metal\n\n  techniques_name: forming (physical activity)\n\n  object_colour: multicoloured\n\n  physical_appearance: \\The image displays a plaque which has a brown border. A drawing of the front of the former Singapore National Theatre can be seen at the centre of the plaque. The year \\u00271963\\u0027 and \\u0027Singapore\\u0027 are displayed below the drawing. Within the border of the larger and small circle\n the words\n \\\\South East Asia Cultural Festival\\\\ is written between their circumferences. Below the two circular boundaries\n\n  subject_terms_1: there is a rectangle containing words in red capital letters inside. It states that the plaque is \\u0027presented to Feng Huang Motion Picture Co...\\u0027 Some of the colours on the words and images of the plaque have faded away. \\ commemoratives gift giving festivals honours\n\n  subject_terms_2: cultural ceremonies Festivals Cultural relations Feng huang ying ye gong si\n\n  subject_terms_3: Appreciation of a person’s creative works Victoria Theatre and Concert Hall National monuments\n\n  subject_terms_4: National Theatre (Singapore)\n\n  context_2: This plaque was presented to Feng Huang Motion Picture Co. at the South East Asia Cultural Festival that was held in Singapore\n\n  context_3: cultural ceremonies\n\n  context_4: 19630808 - 19630815\n\n  context_5: 19630808\n\n  context_6: 19630815\n\n  context_7: Singapore\n",
  "createdDate": "20201120223706",
  "version": 0,
  "latest": false,
  "roles": [],
  "metadata": {
    "accession_no_csv": "2016-00185",
    "Image": "",
    "object_work_type": "plaques (flat objects)",
    "title_text": "SEA cultural plaque",
    "preference": "main",
    "title_language": "",
    "creator_2": "Feng Huang Motion Picture Co.",
    "creator_1": "Feng huang ying ye gong si",
    "creator_role": "companies",
    "creation_date": "1963",
    "creation_place_original_location": "Singapore",
    "inscriptions": "",
    "inscription_language": "",
    "shape": "irregular",
    "materials_name": "wood (plant material) metal",
    "techniques_name": "forming (physical activity)",
    "object_colour": "multicoloured",
    "physical_appearance": "\"The image displays a plaque which has a brown border. A drawing of the front of the former Singapore National Theatre can be seen at the centre of the plaque. The year \u00271963\u0027 and \u0027Singapore\u0027 are displayed below the drawing. Within the border of the larger and small circle, the words, \"\"South East Asia Cultural Festival\"\" is written between their circumferences. Below the two circular boundaries",
    "subject_terms_1": "there is a rectangle containing words in red capital letters inside. It states that the plaque is \u0027presented to Feng Huang Motion Picture Co...\u0027 Some of the colours on the words and images of the plaque have faded away. \" commemoratives gift giving festivals honours",
    "subject_terms_2": "cultural ceremonies Festivals Cultural relations Feng huang ying ye gong si",
    "subject_terms_3": "Appreciation of a person’s creative works Victoria Theatre and Concert Hall National monuments",
    "subject_terms_4": "National Theatre (Singapore)",
    "context_2": "This plaque was presented to Feng Huang Motion Picture Co. at the South East Asia Cultural Festival that was held in Singapore",
    "context_3": "cultural ceremonies",
    "context_4": "19630808 - 19630815",
    "context_5": "19630808",
    "context_6": "19630815",
    "context_7": "Singapore"
  },
  "nlpDate": "20201120223706",
  "connectorId": 0,
  "tags": {}
}