{"id":"2016-00072","title":"Special issue of souvenir magazine dedicated to MV Gurusamy","source":"Bumblebee","path":"./Data/json/","content":"accession_no_csv:2016-00072\nImage:\nobject_work_type:magazines (periodicals)\ntitle_text:Special issue of souvenir magazine dedicated to MV Gurusamy\npreference:main\ntitle_language:\ncreator_2:Unknown\ncreation_date:19-Aug-78\ncreation_place_original_location:Singapore\nstyles_periods_indexing_terms:Not indicated\ninscriptions:\ninscription_language:\nscale_type:Not indicated\nshape:rectangular\nmaterials_name:printing paper\ntechniques_name:printing (process)\nobject_colour:multicoloured\nphysical_appearance:\\The image shows the front cover of a magazine. It has a white background. \\\\19-8-78\\\\ is stated near the bottom. The front page is filled with the Tamil script. The image on the page shows a man sitting cross-legged. In front of him is a mridangam and a microphone. At the upper left hand side of the page\nsubject_terms_1:a drawing of a Hindu deity is present. \\ souvenirs commemorations (events)\nsubject_terms_2:musicians Musicians Souvenirs (Keepsakes) Appreciation of a person’s creative works\nsubject_terms_3:Periodicals Musicians Performing Arts Indian music\nsubject_terms_4:Periodicals","createdDate":"20201018182635","version":0,"latest":false,"roles":[],"metadata":{"accession_no_csv":"2016-00072","Image":"","object_work_type":"magazines (periodicals)","title_text":"Special issue of souvenir magazine dedicated to MV Gurusamy","preference":"main","title_language":"","creator_2":"Unknown","creation_date":"19-Aug-78","creation_place_original_location":"Singapore","styles_periods_indexing_terms":"Not indicated","inscriptions":"","inscription_language":"","scale_type":"Not indicated","shape":"rectangular","materials_name":"printing paper","techniques_name":"printing (process)","object_colour":"multicoloured","physical_appearance":"\"The image shows the front cover of a magazine. It has a white background. \"\"19-8-78\"\" is stated near the bottom. The front page is filled with the Tamil script. The image on the page shows a man sitting cross-legged. In front of him is a mridangam and a microphone. At the upper left hand side of the page","subject_terms_1":"a drawing of a Hindu deity is present. \" souvenirs commemorations (events)","subject_terms_2":"musicians Musicians Souvenirs (Keepsakes) Appreciation of a person’s creative works","subject_terms_3":"Periodicals Musicians Performing Arts Indian music","subject_terms_4":"Periodicals"},"nlpDate":"20201018182635","connectorId":0,"tags":{}}