{
  "id": "2016-00212-020",
  "title": "Photograph album of views and portraits in the Punjab, Cashmere, Ceylon, Burma, Penang, Singapore, and Java Jhelum river, Kashmir",
  "source": "Bumblebee",
  "path": "./Data/json/",
  "content": "\n  accession_no_csv: 2016-00212-020\n\n  Image: \n\n  object_work_type: black-and-white photographs\n\n  title_text: Photograph album of views and portraits in the Punjab\n Cashmere\n Ceylon\n Burma\n Penang\n Singapore\n and Java Jhelum river\n Kashmir\n\n  preference: main alternate\n\n  title_language: \n\n  creator_2: John Thomson\n\n  creator_1: Thomson\n J. (John)\n 1837-1921\n\n  creator_role: photographers\n\n  creation_date: before 28 Jul 1876\n\n  creation_place_original_location: Singapore Kashmir (India)\n\n  inscriptions: \n\n  inscription_language: \n\n  shape: rectangular\n\n  materials_name: albumen (egg white protein) paper (fiber product) albumen paper\n\n  techniques_name: albumen process\n\n  object_colour: black-and-white (colors)\n\n  physical_appearance: This is a photograph of the Jhelum river in Kashmir. The river runs through a valley in the middle of the frame. There is thick vegetation on either side. The title is written at the bottom\n below the photograph.\n\n  subject_terms_1: scenery (landscape) rivers mountains\n\n  subject_terms_2: Jhelum River (India and Pakistan) Rivers Photographs Thomson\n J. (John)\n 1837-1921 Kashmir (India) Mountains\n\n  subject_terms_3: Landscape photography\n",
  "createdDate": "20201125084537",
  "version": 0,
  "latest": false,
  "roles": [],
  "metadata": {
    "accession_no_csv": "2016-00212-020",
    "Image": "",
    "object_work_type": "black-and-white photographs",
    "title_text": "Photograph album of views and portraits in the Punjab, Cashmere, Ceylon, Burma, Penang, Singapore, and Java Jhelum river, Kashmir",
    "preference": "main alternate",
    "title_language": "",
    "creator_2": "John Thomson",
    "creator_1": "Thomson, J. (John), 1837-1921",
    "creator_role": "photographers",
    "creation_date": "before 28 Jul 1876",
    "creation_place_original_location": "Singapore Kashmir (India)",
    "inscriptions": "",
    "inscription_language": "",
    "shape": "rectangular",
    "materials_name": "albumen (egg white protein) paper (fiber product) albumen paper",
    "techniques_name": "albumen process",
    "object_colour": "black-and-white (colors)",
    "physical_appearance": "This is a photograph of the Jhelum river in Kashmir. The river runs through a valley in the middle of the frame. There is thick vegetation on either side. The title is written at the bottom, below the photograph.",
    "subject_terms_1": "scenery (landscape) rivers mountains",
    "subject_terms_2": "Jhelum River (India and Pakistan) Rivers Photographs Thomson, J. (John), 1837-1921 Kashmir (India) Mountains",
    "subject_terms_3": "Landscape photography"
  },
  "nlpDate": "20201125084537",
  "connectorId": 0,
  "tags": {}
}