{"id":"2016-00399","title":"Tomy Pocketeer Rally handheld game Tomy Pocketeer Rally handheld game and box","source":"Bumblebee","path":"./Data/json/","content":"accession_no_csv:2016-00399\nImage:\nobject_work_type:mechanical toys\ntitle_text:Tomy Pocketeer Rally handheld game Tomy Pocketeer Rally handheld game and box\npreference:main alternative\ntitle_language:\ncreator_2:Tomy (present name: Takara Tomy)\ncreator_1:Takaratomi\n Kabushiki Kaisha\ncreator_role:toymakers\ncreation_date:1976\ncreation_place_original_location:Singapore\ninscriptions:\ninscription_language:\nshape:rectangular cuboid\nmaterials_name:paper (fiber product) plastic (organic material)\ntechniques_name:colour printing forming (physical activity)\nobject_colour:multicoloured\nphysical_appearance:\\A picture of a mechanical handheld game is depicted. This game comes in a detachable box that is predominantly green in colour. The name of the mechanical toy\n \\\\Racketeer\\u0027s Rally\\\\ is printed on the front and sides of the box. A \\\\Made in Singapore\\\\ statement is also stated at its bottom left hand corner. The game device has two white rotary buttons near the lower end\nsubject_terms_1:with a screen that takes up about four-fifth of the entire device. The image in the screen is one of roads games play (recreation) technology (general associated concept) brand name objects\nsubject_terms_2:straight and at times winding Games Amusements Technology Brand name products\nsubject_terms_3:with obstacles such as houses and grasses at the sides. A miniature red image of a car can be seen at the road closest to the bottom of the screen. \\\nsubject_terms_4:entertaining\ncontext_1:Mechanical toys","createdDate":"20201018182635","version":0,"latest":false,"roles":[],"metadata":{"accession_no_csv":"2016-00399","Image":"","object_work_type":"mechanical toys","title_text":"Tomy Pocketeer Rally handheld game Tomy Pocketeer Rally handheld game and box","preference":"main alternative","title_language":"","creator_2":"Tomy (present name: Takara Tomy)","creator_1":"Takaratomi, Kabushiki Kaisha","creator_role":"toymakers","creation_date":"1976","creation_place_original_location":"Singapore","inscriptions":"","inscription_language":"","shape":"rectangular cuboid","materials_name":"paper (fiber product) plastic (organic material)","techniques_name":"colour printing forming (physical activity)","object_colour":"multicoloured","physical_appearance":"\"A picture of a mechanical handheld game is depicted. This game comes in a detachable box that is predominantly green in colour. The name of the mechanical toy, \"\"Racketeer\u0027s Rally\"\" is printed on the front and sides of the box. A \"\"Made in Singapore\"\" statement is also stated at its bottom left hand corner. The game device has two white rotary buttons near the lower end","subject_terms_1":"with a screen that takes up about four-fifth of the entire device. The image in the screen is one of roads games play (recreation) technology (general associated concept) brand name objects","subject_terms_2":"straight and at times winding Games Amusements Technology Brand name products","subject_terms_3":"with obstacles such as houses and grasses at the sides. A miniature red image of a car can be seen at the road closest to the bottom of the screen. \"","subject_terms_4":"entertaining","context_1":"Mechanical toys"},"nlpDate":"20201018182635","connectorId":0,"tags":{}}