{"id":"2016-00274","title":"Singapore Delegation at Merdeka Games, Merdeka or Independence Stadium","source":"Bumblebee","path":"./Data/json/","content":"accession_no_csv:2016-00274\nImage:\nobject_work_type:black-and-white photographs\ntitle_text:Singapore Delegation at Merdeka Games\n Merdeka or Independence Stadium\npreference:main\ntitle_language:\ncreation_date:1957\ncreation_place_original_location:Kuala Lumpur (Malaysia)\ninscriptions:\ninscription_language:\nshape:rectangular\nmaterials_name:paper (fiber product)\ntechniques_name:printing (process) photographic processes\nobject_colour:grey monochrome\nphysical_appearance:\\The image shows a photograph that is in black-and-white. It shows a setiing in a stadium. There are numerous audiences sitting in the stands. However\n some parts of the stands are also empty. On the track\n there is a group of people walking out in a straight line. At the very front of the line\n a man is holding up a sign that reads \\u0027Singapore\\u0027. Some distance behind him\n another man is holding up the British Union flag. The people walking in the straight line behind the flag-bearer are separated into groups of female and male. Both the males and females are wearing tops that have the word \\\\Singapore\\\\.\\\nsubject_terms_1:stadiums competitions (events) delegates athletes sportsmen\nsubject_terms_2:Stadiums Athletes Black-and-white photography\nsubject_terms_3:Photography Athletics Sports and recreational events\ncontext_1:This photograph of the Singapore delegation was taken at the Merdeka Games\ncontext_2:cultural ceremonies\ncontext_3:1957\ncontext_4:1957\ncontext_5:1957\ncontext_6:Singapore http://eresources.nlb.gov.sg/newspapers/Microfilm/Search?RN\\u003dNL2619\nsgcool_label_text:Jayaram s/o Rengasamy was an amateur athlete who competed at the club level in Singapore and Malaya in the 1940s and 50s. He started his sporting career at the age of 14 as a boxer. In 1953\n a friend and fellow athlete\n MS Maniam\n invited Mr Rengasamy to participate in the Tamil’s Festival or Tamilar Thirunnal. He then began training in athletics at Anglo-Chinese School Barker Road\n the grounds of Victoria School off Jalan Besar and at Farrer Park. Mr Rengasamy also started participating in different races as a middle distance runner at the Tamil’s Festival (1954 – 57)\n Singapore Amateur Athletic Association meets (1955 – 57)\n as well as the Merdeka Games\n Kuala Lumpur (1957). He was also a member of Swift Athletics Club.","createdDate":"20201119143405","version":0,"latest":false,"roles":[],"metadata":{"accession_no_csv":"2016-00274","Image":"","object_work_type":"black-and-white photographs","title_text":"Singapore Delegation at Merdeka Games, Merdeka or Independence Stadium","preference":"main","title_language":"","creation_date":"1957","creation_place_original_location":"Kuala Lumpur (Malaysia)","inscriptions":"","inscription_language":"","shape":"rectangular","materials_name":"paper (fiber product)","techniques_name":"printing (process) photographic processes","object_colour":"grey monochrome","physical_appearance":"\"The image shows a photograph that is in black-and-white. It shows a setiing in a stadium. There are numerous audiences sitting in the stands. However, some parts of the stands are also empty. On the track, there is a group of people walking out in a straight line. At the very front of the line, a man is holding up a sign that reads \u0027Singapore\u0027. Some distance behind him, another man is holding up the British Union flag. The people walking in the straight line behind the flag-bearer are separated into groups of female and male. Both the males and females are wearing tops that have the word \"\"Singapore\"\".\"","subject_terms_1":"stadiums competitions (events) delegates athletes sportsmen","subject_terms_2":"Stadiums Athletes Black-and-white photography","subject_terms_3":"Photography Athletics Sports and recreational events","context_1":"This photograph of the Singapore delegation was taken at the Merdeka Games","context_2":"cultural ceremonies","context_3":"1957","context_4":"1957","context_5":"1957","context_6":"Singapore http://eresources.nlb.gov.sg/newspapers/Microfilm/Search?RN\u003dNL2619","sgcool_label_text":"Jayaram s/o Rengasamy was an amateur athlete who competed at the club level in Singapore and Malaya in the 1940s and 50s. He started his sporting career at the age of 14 as a boxer. In 1953, a friend and fellow athlete, MS Maniam, invited Mr Rengasamy to participate in the Tamil’s Festival or Tamilar Thirunnal. He then began training in athletics at Anglo-Chinese School Barker Road, the grounds of Victoria School off Jalan Besar and at Farrer Park. Mr Rengasamy also started participating in different races as a middle distance runner at the Tamil’s Festival (1954 – 57), Singapore Amateur Athletic Association meets (1955 – 57), as well as the Merdeka Games, Kuala Lumpur (1957). He was also a member of Swift Athletics Club."},"nlpDate":"20201119143405","connectorId":0,"tags":{}}