{
  "id": "2016-00049",
  "title": "A Map of the East Indies A Map of the East Indies by Herman Moll",
  "source": "Bumblebee",
  "path": "./Data/json/",
  "content": "\n  accession_no_csv: 2016-00049\n\n  Image: \n\n  object_work_type: zoning maps historical maps topographic maps\n\n  title_text: A Map of the East Indies A Map of the East Indies by Herman Moll\n\n  preference: main alternate\n\n  title_language: \n\n  creator_2: Herman Moll\n\n  creator_1: Moll\n Herman\n -1732\n\n  creator_role: cartographers\n\n  creation_date: 1800 - 1839\n\n  creation_place_original_location: London (England)\n\n  inscriptions: \n\n  inscription_language: \n\n  shape: rectangular\n\n  materials_name: paper (fiber product) printing paper\n\n  techniques_name: colour printing\n\n  object_colour: multicoloured\n\n  physical_appearance: This map is rectangular in shape and its perimeter is demarcated by dotted lines. It depicts the colonized territories of the East Indies by the different European powers. The different colours used to divide the East Indies correspond to the type of European colonizer controlling the lands. The map has a brown frame. The longitudes of the map indicate how many degrees every point is from London. The map has a brown frame and the logo of the East India company is displayed on the upper right of the map.\n\n  subject_terms_1: colonial settlements former territories/colonies/dependent states\n\n  subject_terms_2: Topographic maps Zoning Maps Historical geography Maps Colonization East Indies East India Company Asia\n\n  subject_terms_3: East India Company\n\n  sgcool_label_text: This map by Herman Moll\n a Dutch geographer based on London\n is dedicated to the Directors of the East India Company. It depicts the East Indies. with detailed captions explaining the territories belonging to England\n Spain\n France\n Holland\n Denmark and Portugal. It also features inset plans of the city of Bantam\n Fort St. George\n Madras and Batavia\n as well as inset views of the cities of Goa and Surat.\n",
  "createdDate": "20201120223706",
  "version": 0,
  "latest": false,
  "roles": [],
  "metadata": {
    "accession_no_csv": "2016-00049",
    "Image": "",
    "object_work_type": "zoning maps historical maps topographic maps",
    "title_text": "A Map of the East Indies A Map of the East Indies by Herman Moll",
    "preference": "main alternate",
    "title_language": "",
    "creator_2": "Herman Moll",
    "creator_1": "Moll, Herman, -1732",
    "creator_role": "cartographers",
    "creation_date": "1800 - 1839",
    "creation_place_original_location": "London (England)",
    "inscriptions": "",
    "inscription_language": "",
    "shape": "rectangular",
    "materials_name": "paper (fiber product) printing paper",
    "techniques_name": "colour printing",
    "object_colour": "multicoloured",
    "physical_appearance": "This map is rectangular in shape and its perimeter is demarcated by dotted lines. It depicts the colonized territories of the East Indies by the different European powers. The different colours used to divide the East Indies correspond to the type of European colonizer controlling the lands. The map has a brown frame. The longitudes of the map indicate how many degrees every point is from London. The map has a brown frame and the logo of the East India company is displayed on the upper right of the map.",
    "subject_terms_1": "colonial settlements former territories/colonies/dependent states",
    "subject_terms_2": "Topographic maps Zoning Maps Historical geography Maps Colonization East Indies East India Company Asia",
    "subject_terms_3": "East India Company",
    "sgcool_label_text": "This map by Herman Moll, a Dutch geographer based on London, is dedicated to the Directors of the East India Company. It depicts the East Indies. with detailed captions explaining the territories belonging to England, Spain, France, Holland, Denmark and Portugal. It also features inset plans of the city of Bantam, Fort St. George, Madras and Batavia, as well as inset views of the cities of Goa and Surat."
  },
  "nlpDate": "20201120223706",
  "connectorId": 0,
  "tags": {}
}