{"id":"2016-00212-036","title":"Photograph album of views and portraits in the Punjab, Cashmere, Ceylon, Burma, Penang, Singapore, and Java Merchant Street, Rangoon","source":"Bumblebee","path":"./Data/json/","content":"accession_no_csv:2016-00212-036\nImage:\nobject_work_type:black-and-white photographs\ntitle_text:Photograph album of views and portraits in the Punjab\n Cashmere\n Ceylon\n Burma\n Penang\n Singapore\n and Java Merchant Street\n Rangoon\npreference:alternate main\ntitle_language:\ncreator_2:John Thomson\ncreator_1:Thomson\n J. (John)\n 1837-1921\ncreator_role:photographers\ncreation_date:before 28 Jul 1876\ncreation_place_original_location:Singapore Rangoon (Burma)\ninscriptions:\ninscription_language:\nshape:rectangular\nmaterials_name:albumen (egg white protein) albumen paper paper (fiber product)\ntechniques_name:albumen process\nobject_colour:black-and-white (colors)\nphysical_appearance:This is a photograph of the Merchant Street in Rangoon\n Burma. There is a wide road in the middle of the photograph\n with a couple of carriages on it. On either side of the road there is a row of buildings. There is a clock tower in the distance. On the right of the photograph\n there is a view of the top of a pagoda. The title is written at the bottom\n below the photograph.\nsubject_terms_1:scenery (landscape) roads street scenes\nsubject_terms_2:Photographs Thomson\n J. (John)\n 1837-1921 Rangoon (Burma) Roads\nsubject_terms_3:Landscape photography Streets and Places","createdDate":"20201018182635","version":0,"latest":false,"roles":[],"metadata":{"accession_no_csv":"2016-00212-036","Image":"","object_work_type":"black-and-white photographs","title_text":"Photograph album of views and portraits in the Punjab, Cashmere, Ceylon, Burma, Penang, Singapore, and Java Merchant Street, Rangoon","preference":"alternate main","title_language":"","creator_2":"John Thomson","creator_1":"Thomson, J. (John), 1837-1921","creator_role":"photographers","creation_date":"before 28 Jul 1876","creation_place_original_location":"Singapore Rangoon (Burma)","inscriptions":"","inscription_language":"","shape":"rectangular","materials_name":"albumen (egg white protein) albumen paper paper (fiber product)","techniques_name":"albumen process","object_colour":"black-and-white (colors)","physical_appearance":"This is a photograph of the Merchant Street in Rangoon, Burma. There is a wide road in the middle of the photograph, with a couple of carriages on it. On either side of the road there is a row of buildings. There is a clock tower in the distance. On the right of the photograph, there is a view of the top of a pagoda. The title is written at the bottom, below the photograph.","subject_terms_1":"scenery (landscape) roads street scenes","subject_terms_2":"Photographs Thomson, J. (John), 1837-1921 Rangoon (Burma) Roads","subject_terms_3":"Landscape photography Streets and Places"},"nlpDate":"20201018182635","connectorId":0,"tags":{}}