{"id":"2016-00625","title":"Certificate of Extract from registrar of births of Kaliappan s/o Krishnasamy at Kandang Kerbau Hospital","source":"Bumblebee","path":"./Data/json/","content":"accession_no_csv:2016-00625\nImage:\nobject_work_type:birth certificates\ntitle_text:Certificate of Extract from registrar of births of Kaliappan s/o Krishnasamy at Kandang Kerbau Hospital\npreference:main\ntitle_language:\ncreator_2:Registrar of Births \\u0026 Deaths Singapore\ncreator_role:creators\ncreation_date:23-Aug-49\ncreation_place_original_location:Singapore\ninscriptions:\ninscription_language:\nshape:rectangular\nmaterials_name:paper (fiber product)\ntechniques_name:printing (process) handwriting\nobject_colour:multicoloured\nphysical_appearance:\\The image displays a birth certificate. At the top centre of the birth certificate\n \\\\Colony of Singapore\\\\ is stated and \\\\Certificate of Extract from Register of Births\\\\ is stated just below. The place of birth is stated as \\\\Kandang Kerbau Hospital\\\\ in black ink. At the bottom of the birth certificate\nsubject_terms_1:there is a blue stamp by the \\\\Passport Office Singapore 18936\\\\ and there is another blue stamp by the \\\\Registrar of Births \\u0026 Death Singapore\\\\. The particulars and home address of both parents are available as well. There is a space for the father to note down his occupation but there is none for the mother.\\ birth records birth registers births\nsubject_terms_2:certification Certification Registers of births\n etc.  Kandang Kerbau Hospital (Singapore)\nsubject_terms_3:Birth certificates Birth certificates\nsubject_terms_4:Former Kandang Kerbau Hospital","createdDate":"20201119143405","version":0,"latest":false,"roles":[],"metadata":{"accession_no_csv":"2016-00625","Image":"","object_work_type":"birth certificates","title_text":"Certificate of Extract from registrar of births of Kaliappan s/o Krishnasamy at Kandang Kerbau Hospital","preference":"main","title_language":"","creator_2":"Registrar of Births \u0026 Deaths Singapore","creator_role":"creators","creation_date":"23-Aug-49","creation_place_original_location":"Singapore","inscriptions":"","inscription_language":"","shape":"rectangular","materials_name":"paper (fiber product)","techniques_name":"printing (process) handwriting","object_colour":"multicoloured","physical_appearance":"\"The image displays a birth certificate. At the top centre of the birth certificate, \"\"Colony of Singapore\"\" is stated and \"\"Certificate of Extract from Register of Births\"\" is stated just below. The place of birth is stated as \"\"Kandang Kerbau Hospital\"\" in black ink. At the bottom of the birth certificate","subject_terms_1":"there is a blue stamp by the \"\"Passport Office Singapore 18936\"\" and there is another blue stamp by the \"\"Registrar of Births \u0026 Death Singapore\"\". The particulars and home address of both parents are available as well. There is a space for the father to note down his occupation but there is none for the mother.\" birth records birth registers births","subject_terms_2":"certification Certification Registers of births, etc.  Kandang Kerbau Hospital (Singapore)","subject_terms_3":"Birth certificates Birth certificates","subject_terms_4":"Former Kandang Kerbau Hospital"},"nlpDate":"20201119143405","connectorId":0,"tags":{}}