{
  "id": "2016-00467",
  "title": "Altar tables Set of altar tables",
  "source": "Bumblebee",
  "path": "./Data/json/",
  "content": "\n  accession_no_csv: 2016-00467\n\n  Image: \n\n  object_work_type: altar tables\n\n  title_text: Altar tables Set of altar tables\n\n  preference: main alternate\n\n  title_language: \n\n  creation_date: Late 19th to early 20th centuries\n\n  creation_place_original_location: Singapore\n\n  inscriptions: \n\n  inscription_language: \n\n  shape: irregular\n\n  materials_name: teak (wood)\n\n  techniques_name: woodcarving\n\n  object_colour: brown (color)\n\n  physical_appearance: This is a set of teak altar tables. It is carved with Chinese figural\n mythical and plant motifs. The front features the carving of \\u0027Shou Lou\\u0027\n the God of Longevity\n perched on a crane and holding a staff. There are pairs of dragon heads at the corners. The larger table has a slighly curved front while the smaller table is rectangular in shape.\n\n  subject_terms_1: deities Peranakan motifs worship figures (representations)\n\n  subject_terms_2: Motifs Buddhist altars Tables Peranakan (Asian people) Dragons Worship Gods\n\n  subject_terms_3: Religious life and practices\n\n  sgcool_label_text: This imposing set of teakwood altar tables was used for the worship of Chinese deities by a Peranakan family of Singapore at home. It is intricately carved with auspicious Chinese figural\n mythical and plant motifs\n with an unusual curved frontal surface for the higher\n rectangular table. The central motif on the rectangular table features Shou Lou\n the God of Longevity perched on the crane and holding a staff. Pairs of stylized dragon heads decorate the table corners. The deity images\n oil lamp and lamp screen were usually placed on the rectangular table while more elaborate offerings for festive occasions would have been presented on the lower square table. Such altar tables were usually positioned prominently in the front hall.\\r\\n\\r\\nIn particular\n this set of altar tables belonged to the family of Mdm Chua Geok Choo and Tan Eng Wah (1923-2013). They were passed down Mdm Chua’s side of the family and were used for the worship of Guanyin\n the Goddess of Mercy\n in the family home on East Coast Avenue.\\r\\n\\r\\nTan Eng Wah was also the eldest son of Tan Lark Sye (1897-1972). Tan Lark Sye was a highly regarded Chinese businessman and philanthropist in Singapore.\n",
  "createdDate": "20201125084534",
  "version": 0,
  "latest": false,
  "roles": [],
  "metadata": {
    "accession_no_csv": "2016-00467",
    "Image": "",
    "object_work_type": "altar tables",
    "title_text": "Altar tables Set of altar tables",
    "preference": "main alternate",
    "title_language": "",
    "creation_date": "Late 19th to early 20th centuries",
    "creation_place_original_location": "Singapore",
    "inscriptions": "",
    "inscription_language": "",
    "shape": "irregular",
    "materials_name": "teak (wood)",
    "techniques_name": "woodcarving",
    "object_colour": "brown (color)",
    "physical_appearance": "This is a set of teak altar tables. It is carved with Chinese figural, mythical and plant motifs. The front features the carving of \u0027Shou Lou\u0027, the God of Longevity, perched on a crane and holding a staff. There are pairs of dragon heads at the corners. The larger table has a slighly curved front while the smaller table is rectangular in shape.",
    "subject_terms_1": "deities Peranakan motifs worship figures (representations)",
    "subject_terms_2": "Motifs Buddhist altars Tables Peranakan (Asian people) Dragons Worship Gods",
    "subject_terms_3": "Religious life and practices",
    "sgcool_label_text": "This imposing set of teakwood altar tables was used for the worship of Chinese deities by a Peranakan family of Singapore at home. It is intricately carved with auspicious Chinese figural, mythical and plant motifs, with an unusual curved frontal surface for the higher, rectangular table. The central motif on the rectangular table features Shou Lou, the God of Longevity perched on the crane and holding a staff. Pairs of stylized dragon heads decorate the table corners. The deity images, oil lamp and lamp screen were usually placed on the rectangular table while more elaborate offerings for festive occasions would have been presented on the lower square table. Such altar tables were usually positioned prominently in the front hall.\r\n\r\nIn particular, this set of altar tables belonged to the family of Mdm Chua Geok Choo and Tan Eng Wah (1923-2013). They were passed down Mdm Chua’s side of the family and were used for the worship of Guanyin, the Goddess of Mercy, in the family home on East Coast Avenue.\r\n\r\nTan Eng Wah was also the eldest son of Tan Lark Sye (1897-1972). Tan Lark Sye was a highly regarded Chinese businessman and philanthropist in Singapore."
  },
  "nlpDate": "20201125084534",
  "connectorId": 0,
  "tags": {}
}