{"id":"2016-00315","title":"Display stand Display stand","source":"Bumblebee","path":"./Data/json/","content":"accession_no_csv:2016-00315\nImage:\nobject_work_type:stands (support objects)\ntitle_text:Display stand Display stand\npreference:main\ntitle_language:\ncreator_2:Not indicated\ncreator_1:Not indicated\ncreator_role:Not indicated\ncreation_date:18th century\ncreation_place_original_location:China\ninscriptions:\ninscription_language:\nshape:irregular\nmaterials_name:boxwood (wood)\ntechniques_name:woodcarving\nobject_colour:brown (colour)\nphysical_appearance:The image shows a display stand. It  is brown in colour. The top of the display stand has a flat upper surface. It is of a lighter shade of brown as compared to its base. The base of the display stand is carved to resemble intertwining roots. The roots are gnarled in appearance. The root formation closest to the foreground of the image extends outwards\n as compared to the others which tend to be clustered.\nsubject_terms_1:carvings (visual works) symbolism (artistic concept) cultural artefacts\nsubject_terms_2:Stands (Furniture) Symbolism\nsubject_terms_3:Artefacts\nsgcool_label_text:This huangyangmu (boxwood) stand has been carved\n at least partially\n to appear like a natural root formation. It consists of a flat upper surface supported by gnarled\n intertwining roots. The Chinese literati favoured furnishings that alluded to nature in form as well as materiality. Made of wood or stone\n these items which included tables\n stools and stands were also often depicted in Ming and Qing paintings.","createdDate":"20201119143405","version":0,"latest":false,"roles":[],"metadata":{"accession_no_csv":"2016-00315","Image":"","object_work_type":"stands (support objects)","title_text":"Display stand Display stand","preference":"main","title_language":"","creator_2":"Not indicated","creator_1":"Not indicated","creator_role":"Not indicated","creation_date":"18th century","creation_place_original_location":"China","inscriptions":"","inscription_language":"","shape":"irregular","materials_name":"boxwood (wood)","techniques_name":"woodcarving","object_colour":"brown (colour)","physical_appearance":"The image shows a display stand. It  is brown in colour. The top of the display stand has a flat upper surface. It is of a lighter shade of brown as compared to its base. The base of the display stand is carved to resemble intertwining roots. The roots are gnarled in appearance. The root formation closest to the foreground of the image extends outwards, as compared to the others which tend to be clustered.","subject_terms_1":"carvings (visual works) symbolism (artistic concept) cultural artefacts","subject_terms_2":"Stands (Furniture) Symbolism","subject_terms_3":"Artefacts","sgcool_label_text":"This huangyangmu (boxwood) stand has been carved, at least partially, to appear like a natural root formation. It consists of a flat upper surface supported by gnarled, intertwining roots. The Chinese literati favoured furnishings that alluded to nature in form as well as materiality. Made of wood or stone, these items which included tables, stools and stands were also often depicted in Ming and Qing paintings."},"nlpDate":"20201119143405","connectorId":0,"tags":{}}