{
  "id": "2016-00568-002",
  "title": "Informational leaflet on Tiger Oil Bottle of Tiger Oil with packaging box and photograph of three patrons to Tiger Balm Gardens",
  "source": "Bumblebee",
  "path": "./Data/json/",
  "content": "\n  accession_no_csv: 2016-00568-002\n\n  Image: \n\n  object_work_type: leaflets (printed works)\n\n  title_text: Informational leaflet on Tiger Oil Bottle of Tiger Oil with packaging box and photograph of three patrons to Tiger Balm Gardens\n\n  preference: main alternate\n\n  title_language: \n\n  creator_2: Aw Boon Haw Aw Boon Par Haw Par Brothers International Ltd Singapore\n\n  creator_1: Not indicated Haw Par Brothers International Limited (TTE) Hu\n Wenhu\n 1882-1954\n\n  creator_role: entrepreneurs companies\n\n  creation_date: Mid 1960s to Early 1970s 1960-1975\n\n  creation_place_original_location: Singapore\n\n  inscriptions: \n\n  inscription_language: \n\n  shape: rectangular\n\n  materials_name: printing paper\n\n  techniques_name: printing (process)\n\n  object_colour: grey (colour)\n\n  physical_appearance: \\The image shows a leaflet. It has a brown stain at the top centre and a brown stain line running down the left hand side. \\\\Aw Boon Par\\\\ and \\\\Aw Boon Haw\\\\ are stated at the top\n\n  subject_terms_1: below their respective pictures. There are three paragraphs written in Chinese characters brand name objects\n\n  subject_terms_2: Business enterprises Ointments Businesspeople English Brand name products\n\n  subject_terms_3: Business enterprises Business owners and in the Malay language respectively. \\\\Har Par Brothers International Ltd\\\\ is stated at the bottom\\\n\n  subject_terms_4: ointment\n\n  context_1: Pamphlets\n\n  context_2: Aw\n Boon Haw\n",
  "createdDate": "20201125084533",
  "version": 0,
  "latest": false,
  "roles": [],
  "metadata": {
    "accession_no_csv": "2016-00568-002",
    "Image": "",
    "object_work_type": "leaflets (printed works)",
    "title_text": "Informational leaflet on Tiger Oil Bottle of Tiger Oil with packaging box and photograph of three patrons to Tiger Balm Gardens",
    "preference": "main alternate",
    "title_language": "",
    "creator_2": "Aw Boon Haw Aw Boon Par Haw Par Brothers International Ltd Singapore",
    "creator_1": "Not indicated Haw Par Brothers International Limited (TTE) Hu, Wenhu, 1882-1954",
    "creator_role": "entrepreneurs companies",
    "creation_date": "Mid 1960s to Early 1970s 1960-1975",
    "creation_place_original_location": "Singapore",
    "inscriptions": "",
    "inscription_language": "",
    "shape": "rectangular",
    "materials_name": "printing paper",
    "techniques_name": "printing (process)",
    "object_colour": "grey (colour)",
    "physical_appearance": "\"The image shows a leaflet. It has a brown stain at the top centre and a brown stain line running down the left hand side. \"\"Aw Boon Par\"\" and \"\"Aw Boon Haw\"\" are stated at the top",
    "subject_terms_1": "below their respective pictures. There are three paragraphs written in Chinese characters brand name objects",
    "subject_terms_2": "Business enterprises Ointments Businesspeople English Brand name products",
    "subject_terms_3": "Business enterprises Business owners and in the Malay language respectively. \"\"Har Par Brothers International Ltd\"\" is stated at the bottom\"",
    "subject_terms_4": "ointment",
    "context_1": "Pamphlets",
    "context_2": "Aw, Boon Haw"
  },
  "nlpDate": "20201125084533",
  "connectorId": 0,
  "tags": {}
}