{"id":"2016-00495","title":"Untitled (station interior)","source":"Bumblebee","path":"./Data/json/","content":"accession_no_csv:2016-00495\nImage:\nobject_work_type:black-and-white photographs\ntitle_text:Untitled (station interior)\npreference:main\ntitle_language:\ncreator_2:Kwek Leng Joo Swan and Maclaren Architects\ncreator_1:Kwek\n Leng Joo Swan \\u0026 Maclaren\ncreator_role:photographers designers\ncreation_date:2010\ncreation_place_original_location:Singapore Malaysia\ninscriptions:\ninscription_language:\nshape:rectangular\nmaterials_name:paper (fiber product)\ntechniques_name:printing (process)\nobject_colour:grey monochrome\nphysical_appearance:\\The image shows a photograph in black-and-white. It has a black frame and its border is white in colour. The ceiling is concave and it is high from the ground. There are numerous people in the photograph\n some sitting down and standing up. A number of them are queueing up at the ticket counter\n which is located at the left hand side of the photograph. At the centre of the image\n a shop called \\\\Tourism Malaysia\\\\ is present. The framed initials of the Federated Malay States Railway\nsubject_terms_1:\\\\FMSR\\\\ Neoclassical interior spaces (spaces by location) railroad stations historic monuments\nsubject_terms_2:is displayed slightly above the centre of the photograph Motifs Art deco (Architecture) Neoclassicism (Architecture) Historic monuments Railroad stations Tanjong Pagar (Singapore) Pertadbiran Keretapi Tanah Melayu Federated Malay States Railways\nsubject_terms_3:at its background. Each capital letter is framed separately Tanjong Pagar Railway Station Pertadbiran Keretapi Tanah Melayu Photography Rail transport (Stations)\nsubject_terms_4:in a single row. The coat-of-arms of the Federated Malay States Railway is displayed in between the framed letters of \\\\FMSR\\\\\\\ncontext_1:Art Deco\ncontext_2:Black-and-white photography\ncontext_3:Rail transport","createdDate":"20201119143405","version":0,"latest":false,"roles":[],"metadata":{"accession_no_csv":"2016-00495","Image":"","object_work_type":"black-and-white photographs","title_text":"Untitled (station interior)","preference":"main","title_language":"","creator_2":"Kwek Leng Joo Swan and Maclaren Architects","creator_1":"Kwek, Leng Joo Swan \u0026 Maclaren","creator_role":"photographers designers","creation_date":"2010","creation_place_original_location":"Singapore Malaysia","inscriptions":"","inscription_language":"","shape":"rectangular","materials_name":"paper (fiber product)","techniques_name":"printing (process)","object_colour":"grey monochrome","physical_appearance":"\"The image shows a photograph in black-and-white. It has a black frame and its border is white in colour. The ceiling is concave and it is high from the ground. There are numerous people in the photograph, some sitting down and standing up. A number of them are queueing up at the ticket counter, which is located at the left hand side of the photograph. At the centre of the image, a shop called \"\"Tourism Malaysia\"\" is present. The framed initials of the Federated Malay States Railway","subject_terms_1":"\"\"FMSR\"\" Neoclassical interior spaces (spaces by location) railroad stations historic monuments","subject_terms_2":"is displayed slightly above the centre of the photograph Motifs Art deco (Architecture) Neoclassicism (Architecture) Historic monuments Railroad stations Tanjong Pagar (Singapore) Pertadbiran Keretapi Tanah Melayu Federated Malay States Railways","subject_terms_3":"at its background. Each capital letter is framed separately Tanjong Pagar Railway Station Pertadbiran Keretapi Tanah Melayu Photography Rail transport (Stations)","subject_terms_4":"in a single row. The coat-of-arms of the Federated Malay States Railway is displayed in between the framed letters of \"\"FMSR\"\"\"","context_1":"Art Deco","context_2":"Black-and-white photography","context_3":"Rail transport"},"nlpDate":"20201119143405","connectorId":0,"tags":{}}