{"id":"2016-00649","title":"Sarong kecil (young girl’s skirt cloth)","source":"Bumblebee","path":"./Data/json/","content":"accession_no_csv:2016-00649\nImage:\nobject_work_type:sarongs batik art\ntitle_text:Sarong kecil (young girl’s skirt cloth)\npreference:main\ntitle_language:\ncreation_date:1920\ncreation_place_original_location:Pekalongan (Indonesia)\nstyles_periods_indexing_terms:Javanese (culture or style)\ninscriptions:\ninscription_language:\nshape:rectangular\nmaterials_name:cotton (textile) dye\ntechniques_name:batik sewing (needleworking technique)\nobject_colour:multicolored\nphysical_appearance:This is a small batik sarong. It has a light beige background\n with a blue panel in the center. The cloth is decorated with floral motifs\n butterflies and birds.\nsubject_terms_1:Peranakan foliage (motif) birds (motifs) cultural diffusion folk costume\nsubject_terms_2:Ethnic costume Batik Peranakan (Asian people) Motifs Culture diffusion\nsubject_terms_3:Batik Peranakan costumes\nsgcool_label_text:This is a rare sarong kecil or young girl’s tube-like skirt cloth.  A typical sarong however\n is around 2.25 metres long\n with both ends sewn together to form a tube.  The flowering tendrils and butterflies on the white background occupy the main body of the cloth (or badan).  A large bouquet\n a motif known as buketan or ‘bouquet’ is the cloth’s characteristic design feature or head of the cloth (kepala).   The buketan motif is depicted on a dark blue background on this piece.  It is typically accompanied by butterflies and birds as seen in this example.  Although this motif was made popular by the Europeans in the pasisir\n it was later identified with Peranakan Chinese women\n (the nonya) and was a key design for ‘Batik Nonya’.  Other Batik Nonya designs include characters from European children’s fairy tales and other Western motifs. The buketan motif remains popular today and is seen in contemporary batik.","createdDate":"20201119143405","version":0,"latest":false,"roles":[],"metadata":{"accession_no_csv":"2016-00649","Image":"","object_work_type":"sarongs batik art","title_text":"Sarong kecil (young girl’s skirt cloth)","preference":"main","title_language":"","creation_date":"1920","creation_place_original_location":"Pekalongan (Indonesia)","styles_periods_indexing_terms":"Javanese (culture or style)","inscriptions":"","inscription_language":"","shape":"rectangular","materials_name":"cotton (textile) dye","techniques_name":"batik sewing (needleworking technique)","object_colour":"multicolored","physical_appearance":"This is a small batik sarong. It has a light beige background, with a blue panel in the center. The cloth is decorated with floral motifs, butterflies and birds.","subject_terms_1":"Peranakan foliage (motif) birds (motifs) cultural diffusion folk costume","subject_terms_2":"Ethnic costume Batik Peranakan (Asian people) Motifs Culture diffusion","subject_terms_3":"Batik Peranakan costumes","sgcool_label_text":"This is a rare sarong kecil or young girl’s tube-like skirt cloth.  A typical sarong however, is around 2.25 metres long, with both ends sewn together to form a tube.  The flowering tendrils and butterflies on the white background occupy the main body of the cloth (or badan).  A large bouquet, a motif known as buketan or ‘bouquet’ is the cloth’s characteristic design feature or head of the cloth (kepala).   The buketan motif is depicted on a dark blue background on this piece.  It is typically accompanied by butterflies and birds as seen in this example.  Although this motif was made popular by the Europeans in the pasisir, it was later identified with Peranakan Chinese women, (the nonya) and was a key design for ‘Batik Nonya’.  Other Batik Nonya designs include characters from European children’s fairy tales and other Western motifs. The buketan motif remains popular today and is seen in contemporary batik."},"nlpDate":"20201119143405","connectorId":0,"tags":{}}