{
  "id": "2016-00212-043",
  "title": "Photograph album of views and portraits in the Punjab, Cashmere, Ceylon, Burma, Penang, Singapore, and Java Girl with excessive facial hair disorder",
  "source": "Bumblebee",
  "path": "./Data/json/",
  "content": "\n  accession_no_csv: 2016-00212-043\n\n  Image: \n\n  object_work_type: black-and-white photographs portraits\n\n  title_text: Photograph album of views and portraits in the Punjab\n Cashmere\n Ceylon\n Burma\n Penang\n Singapore\n and Java Girl with excessive facial hair disorder\n\n  preference: alternate main\n\n  title_language: \n\n  creator_2: John Thomson\n\n  creator_1: Thomson\n J. (John)\n 1837-1921\n\n  creator_role: photographers\n\n  creation_date: before 28 Jul 1876\n\n  creation_place_original_location: Singapore\n\n  inscriptions: \n\n  inscription_language: \n\n  shape: rectangular\n\n  materials_name: albumen (egg white protein) albumen paper paper (fiber product)\n\n  techniques_name: albumen process\n\n  object_colour: black-and-white (colors)\n\n  physical_appearance: This is a portrait of a girl. She is sitting kneeled on the floor\n with her hands on her lap. She is wearing a long sleeved top and a wrapped skirt. She has excess hair growth especially on her face. The title is written at the bottom\n below the photograph.\n\n  subject_terms_1: disease girls indigenous people\n\n  subject_terms_2: Photographs Portrait photography Thomson\n J. (John)\n 1837-1921 Hypertrichosis Indigenous people\n\n  subject_terms_3: Portrait photography\n",
  "createdDate": "20201120223706",
  "version": 0,
  "latest": false,
  "roles": [],
  "metadata": {
    "accession_no_csv": "2016-00212-043",
    "Image": "",
    "object_work_type": "black-and-white photographs portraits",
    "title_text": "Photograph album of views and portraits in the Punjab, Cashmere, Ceylon, Burma, Penang, Singapore, and Java Girl with excessive facial hair disorder",
    "preference": "alternate main",
    "title_language": "",
    "creator_2": "John Thomson",
    "creator_1": "Thomson, J. (John), 1837-1921",
    "creator_role": "photographers",
    "creation_date": "before 28 Jul 1876",
    "creation_place_original_location": "Singapore",
    "inscriptions": "",
    "inscription_language": "",
    "shape": "rectangular",
    "materials_name": "albumen (egg white protein) albumen paper paper (fiber product)",
    "techniques_name": "albumen process",
    "object_colour": "black-and-white (colors)",
    "physical_appearance": "This is a portrait of a girl. She is sitting kneeled on the floor, with her hands on her lap. She is wearing a long sleeved top and a wrapped skirt. She has excess hair growth especially on her face. The title is written at the bottom, below the photograph.",
    "subject_terms_1": "disease girls indigenous people",
    "subject_terms_2": "Photographs Portrait photography Thomson, J. (John), 1837-1921 Hypertrichosis Indigenous people",
    "subject_terms_3": "Portrait photography"
  },
  "nlpDate": "20201120223706",
  "connectorId": 0,
  "tags": {}
}