{"id":"2016-00718","title":"Altar Cloth with Phoenix and the Three Star Deities","source":"Bumblebee","path":"./Data/json/","content":"accession_no_csv:2016-00718\nImage:\nobject_work_type:altar cloths\ntitle_text:Altar Cloth with Phoenix and the Three Star Deities\npreference:main\ntitle_language:\ncreation_date:late 19th-20th century\ncreation_place_original_location:Straits Settlements\ninscriptions:\ninscription_language:\nshape:irregular\nmaterials_name:metal thread paint (coating) paper (fiber product)\ntechniques_name:sewing (needleworking technique) embroidering painting (image-making)\nobject_colour:multicolored\nphysical_appearance:This is an altar cloth. It is embroided with depictions of the figures of deities\n against a background of gold thread. The faces of the figures are painted on paper and attached to the altar cloth. The top panel features a pair of phoenixes flanking a lotus bloom flower.\nsubject_terms_1:deities birds (motifs) flower (motif) Peranakan\nsubject_terms_2:Altar-cloths Gods Motifs Peranakan (Asian people)\nsubject_terms_3:Religious life and practices Textile art and design\nsgcool_label_text:The figures of the Three Star deities\n of happiness\n status and longevity\n are embroidered on this altar cloth\n against a background of gold thread. The faces\n including that of the two attendant figures seem to have been painted on paper and attached to the fabric. The top panel features a pair of phoenix flanking a lotus bloom. It is part of a donation which contains a mixture of garments worn by Peranakan men and women.","createdDate":"20201018182635","version":0,"latest":false,"roles":[],"metadata":{"accession_no_csv":"2016-00718","Image":"","object_work_type":"altar cloths","title_text":"Altar Cloth with Phoenix and the Three Star Deities","preference":"main","title_language":"","creation_date":"late 19th-20th century","creation_place_original_location":"Straits Settlements","inscriptions":"","inscription_language":"","shape":"irregular","materials_name":"metal thread paint (coating) paper (fiber product)","techniques_name":"sewing (needleworking technique) embroidering painting (image-making)","object_colour":"multicolored","physical_appearance":"This is an altar cloth. It is embroided with depictions of the figures of deities, against a background of gold thread. The faces of the figures are painted on paper and attached to the altar cloth. The top panel features a pair of phoenixes flanking a lotus bloom flower.","subject_terms_1":"deities birds (motifs) flower (motif) Peranakan","subject_terms_2":"Altar-cloths Gods Motifs Peranakan (Asian people)","subject_terms_3":"Religious life and practices Textile art and design","sgcool_label_text":"The figures of the Three Star deities, of happiness, status and longevity, are embroidered on this altar cloth, against a background of gold thread. The faces, including that of the two attendant figures seem to have been painted on paper and attached to the fabric. The top panel features a pair of phoenix flanking a lotus bloom. It is part of a donation which contains a mixture of garments worn by Peranakan men and women."},"nlpDate":"20201018182635","connectorId":0,"tags":{}}