{
  "id": "2016-00059",
  "title": "Hand Billet - “Kantha Shashti Vizha” at Sri Maha Mariamman Temple, Kuala Lumpur",
  "source": "Bumblebee",
  "path": "./Data/json/",
  "content": "\n  accession_no_csv: 2016-00059\n\n  Image: \n\n  object_work_type: fliers (printed matter)\n\n  title_text: Hand Billet - “Kantha Shashti Vizha” at Sri Maha Mariamman Temple\n Kuala Lumpur\n\n  preference: main\n\n  title_language: \n\n  creator_2: Unknown\n\n  creation_date: 2-Nov-54\n\n  creation_place_original_location: Kuala Lumpur (Malaysia)\n\n  styles_periods_indexing_terms: Not indicated\n\n  inscriptions: \n\n  inscription_language: \n\n  scale_type: Not indicated\n\n  shape: rectangular\n\n  materials_name: printing paper\n\n  techniques_name: printing (process)\n\n  object_colour: multicoloured\n\n  physical_appearance: The image shows a flyer. It is rectangular in shape with a brown background. There is a rectangular border with clover designs along its outline\n surrounding the details that are presented on the flyer. The entire page is written in the Tamil script. At the top of the page at the centre\n there is an image of a Hindu deity. To the left and right side of the Hindu deity are two figures which are depicted with wings.\n\n  subject_terms_1: temples (buidings) Hinduism religious functions\n\n  subject_terms_2: Hindu temples Hinduism Fliers (Ephemera) Murugan (Hindu deity)\n\n  subject_terms_3: Temples Hinduism\n\n  sgcool_label_text: M.V.Gurusamy (b. 1920 in Seremban) was an accomplished percussionist and mridangam artiste as well as a renowned percussion teacher in Singapore. He arrived in Singapore and participated in the Indian classical music scene here. He was a member of the cultural contingent led by the then Minister for Culture\n S. Rajaratnam\n which visited and performed at various centres in Sarawak\n Brunei and Sabah in 1965. He was the recipient of several titles including the Kala Ratna award given by the Singapore Indian Fine Arts Society in 1986.\n",
  "createdDate": "20201201203309",
  "version": 0,
  "latest": false,
  "roles": [],
  "metadata": {
    "accession_no_csv": "2016-00059",
    "Image": "",
    "object_work_type": "fliers (printed matter)",
    "title_text": "Hand Billet - “Kantha Shashti Vizha” at Sri Maha Mariamman Temple, Kuala Lumpur",
    "preference": "main",
    "title_language": "",
    "creator_2": "Unknown",
    "creation_date": "2-Nov-54",
    "creation_place_original_location": "Kuala Lumpur (Malaysia)",
    "styles_periods_indexing_terms": "Not indicated",
    "inscriptions": "",
    "inscription_language": "",
    "scale_type": "Not indicated",
    "shape": "rectangular",
    "materials_name": "printing paper",
    "techniques_name": "printing (process)",
    "object_colour": "multicoloured",
    "physical_appearance": "The image shows a flyer. It is rectangular in shape with a brown background. There is a rectangular border with clover designs along its outline, surrounding the details that are presented on the flyer. The entire page is written in the Tamil script. At the top of the page at the centre, there is an image of a Hindu deity. To the left and right side of the Hindu deity are two figures which are depicted with wings.",
    "subject_terms_1": "temples (buidings) Hinduism religious functions",
    "subject_terms_2": "Hindu temples Hinduism Fliers (Ephemera) Murugan (Hindu deity)",
    "subject_terms_3": "Temples Hinduism",
    "sgcool_label_text": "M.V.Gurusamy (b. 1920 in Seremban) was an accomplished percussionist and mridangam artiste as well as a renowned percussion teacher in Singapore. He arrived in Singapore and participated in the Indian classical music scene here. He was a member of the cultural contingent led by the then Minister for Culture, S. Rajaratnam, which visited and performed at various centres in Sarawak, Brunei and Sabah in 1965. He was the recipient of several titles including the Kala Ratna award given by the Singapore Indian Fine Arts Society in 1986."
  },
  "nlpDate": "20201201203309",
  "connectorId": 0,
  "tags": {}
}