{
  "id": "2016-00310",
  "title": "View of Ternate",
  "source": "Bumblebee",
  "path": "./Data/json/",
  "content": "\n  accession_no_csv: 2016-00310\n\n  Image: \n\n  object_work_type: prints (visual works)\n\n  title_text: View of Ternate\n\n  preference: main\n\n  title_language: \n\n  creator_2: Francois Valentijn\n\n  creator_1: Valentijn\n Francois\n 1666 - 1727\n\n  creator_role: artists (visual artists)\n\n  creation_date: 1726\n\n  creation_place_original_location: Holland (Netherlands : Province)\n\n  inscriptions: \n\n  inscription_language: \n\n  shape: rectangular\n\n  materials_name: paper (fiber product) printing paper\n\n  techniques_name: colour printing\n\n  object_colour: multicoloured\n\n  physical_appearance: \\This print depicts the island of Ternate and the coastal settlements\n as well as ships sailing near it. The title of the print is displayed at the top centre. At the background of the print is a volcano erupting. Smoke and fire can be seen emanating from its crater. The print is separated into a larger and smaller part. For the smaller part\n a map of the fortress\n \\\\Gamma-Lamma\\\\\n\n  subject_terms_1: is depicted. In the larger part landscape (representations) forts ships coastal settlements volcanic eruptions\n\n  subject_terms_2: Volcanic eruptions Coastal settlements Ternate (Dutch East Indies: Residency) Prints Landscapes a pier is shown to be extending from the coastline.The print is numbered from one to nine at certain areas Nederlandsche Oost-Indische Compagnie Ternate Island (Indonesia) Fortress\n\n  subject_terms_3: and these numbers serve as footnotes which are represented at the bottom.\\\n\n  subject_terms_4: colonial settlements\n\n  context_1: Colonization\n",
  "createdDate": "20201125084535",
  "version": 0,
  "latest": false,
  "roles": [],
  "metadata": {
    "accession_no_csv": "2016-00310",
    "Image": "",
    "object_work_type": "prints (visual works)",
    "title_text": "View of Ternate",
    "preference": "main",
    "title_language": "",
    "creator_2": "Francois Valentijn",
    "creator_1": "Valentijn, Francois, 1666 - 1727",
    "creator_role": "artists (visual artists)",
    "creation_date": "1726",
    "creation_place_original_location": "Holland (Netherlands : Province)",
    "inscriptions": "",
    "inscription_language": "",
    "shape": "rectangular",
    "materials_name": "paper (fiber product) printing paper",
    "techniques_name": "colour printing",
    "object_colour": "multicoloured",
    "physical_appearance": "\"This print depicts the island of Ternate and the coastal settlements, as well as ships sailing near it. The title of the print is displayed at the top centre. At the background of the print is a volcano erupting. Smoke and fire can be seen emanating from its crater. The print is separated into a larger and smaller part. For the smaller part, a map of the fortress, \"\"Gamma-Lamma\"\"",
    "subject_terms_1": "is depicted. In the larger part landscape (representations) forts ships coastal settlements volcanic eruptions",
    "subject_terms_2": "Volcanic eruptions Coastal settlements Ternate (Dutch East Indies: Residency) Prints Landscapes a pier is shown to be extending from the coastline.The print is numbered from one to nine at certain areas Nederlandsche Oost-Indische Compagnie Ternate Island (Indonesia) Fortress",
    "subject_terms_3": "and these numbers serve as footnotes which are represented at the bottom.\"",
    "subject_terms_4": "colonial settlements",
    "context_1": "Colonization"
  },
  "nlpDate": "20201125084535",
  "connectorId": 0,
  "tags": {}
}