{"id":"2016-00527","title":"‘Welcome to Singapore’ guide by Singapore Tourism  ‘Welcome to Singapore’ guide by Singapore Tourism","source":"Bumblebee","path":"./Data/json/","content":"accession_no_csv:2016-00527\nImage:\nobject_work_type:travel guidebooks travel guidebooks\ntitle_text:‘Welcome to Singapore’ guide by Singapore Tourism  ‘Welcome to Singapore’ guide by Singapore Tourism\npreference:main main\ntitle_language:\ncreator_2:Singapore Tourist Promotion Board (STPB) Singapore Tourist Promotion Board (STPB)\ncreator_1:Singapore Tourist Promotion Board Singapore Tourist Promotion Board\ncreator_role:creators creators\ncreation_date:Aug-78 Aug-78\ncreation_place_original_location:Singapore Singapore\nstyles_periods_indexing_terms:NA NA\ninscriptions:\ninscription_language:\nscale_type:NA NA\nshape:rectangular rectangular\nmaterials_name:printing paper printing paper\ntechniques_name:printing (process) printing (process)\nobject_colour:multicoloured multicoloured\nedition_description:8 8\nphysical_appearance:The image displays the front cover of a travel guidebook. It is rectangular in shape. The image on the front cover features two ladies posing and looking in the direction where the photograph was captured. They are dressed in sarong wear and the background features flowers and foliage. The lady in blue to the right is holding a vintage bird cage and leaning against a cane armchair\n which the other lady is sitting on.     The image displays the front cover of a travel guidebook. It is rectangular in shape. The image on the front cover features two ladies posing and looking in the direction where the photograph was captured. They are dressed in sarong wear and the background features flowers and foliage. The lady in blue to the right is holding a vintage bird cage and leaning against a cane armchair\n which the other lady is sitting on.\nsubject_terms_1:tourism cultural heritage travel tourism cultural heritage travel\nsubject_terms_2:Guidebooks Tourism Voyages and travels Singapore Guidebooks Tourism Voyages and travels Singapore\nsubject_terms_3:Description and travel Singapore Tourist Promotion Board Cultural development Description and travel Singapore Tourist Promotion Board Cultural development\nsubject_terms_4:NA NA\ncontext_1:NA NA\ncontext_2:NA NA\ncontext_3:NA NA\ncontext_4:NA NA\ncontext_5:NA NA\ncontext_6:NA NA\ncontext_7:NA NA\ncontext_8:NA NA\ncontext_9:NA NA\ncontext_10:NA NA\ncontext_11:NA NA\ncontext_12:NA NA\ncontext_13:NA NA\ncontext_14:NA NA\ncontext_15:NA NA\ncontext_16:NA NA\ncontext_17:NA NA\ncontext_18:NA NA\ncontext_19:NA NA\ncontext_20:NA NA\ncontext_21:NA NA\ncontext_22:NA NA\ncontext_23:NA NA\ncontext_24:NA NA\nsgcool_label_text:This “Welcome to Singapore” visitor guide was published in 1978 by the Singapore Tourist Promotion Board (STPB). Catered to tourists\n this free publication provides an overview of Singapore’s cultural heritage and introduces the main attractions of Singapore. \\r\\n\\r\\nThe cover of the visitor guide features a tropical scene of ladies dressed in sarong wear and contains a foreword by the Chairman of the Tourist Promotion Board.\\r\\nSTPB was created in 1964 as a statutory board by the government to develop and promote Singapore as a tourist destination. \\r\\n\\r\\nSTPB’s efforts in marketing Singapore as a holiday destination paid off\n with tourist arrivals increasing from 100\n000 in 1964 to over 2 million by 1978.  This “Welcome to Singapore” visitor guide was published in 1978 by the Singapore Tourist Promotion Board (STPB). Catered to tourists\n this free publication provides an overview of Singapore’s cultural heritage and introduces the main attractions of Singapore. \\r\\n\\r\\nThe cover of the visitor guide features a tropical scene of ladies dressed in sarong wear and contains a foreword by the Chairman of the Tourist Promotion Board.\\r\\nSTPB was created in 1964 as a statutory board by the government to develop and promote Singapore as a tourist destination. \\r\\n\\r\\nSTPB’s efforts in marketing Singapore as a holiday destination paid off\n with tourist arrivals increasing from 100\n000 in 1964 to over 2 million by 1978.","createdDate":"20201119143405","version":0,"latest":false,"roles":[],"metadata":{"accession_no_csv":"2016-00527","Image":"","object_work_type":"travel guidebooks travel guidebooks","title_text":"‘Welcome to Singapore’ guide by Singapore Tourism  ‘Welcome to Singapore’ guide by Singapore Tourism","preference":"main main","title_language":"","creator_2":"Singapore Tourist Promotion Board (STPB) Singapore Tourist Promotion Board (STPB)","creator_1":"Singapore Tourist Promotion Board Singapore Tourist Promotion Board","creator_role":"creators creators","creation_date":"Aug-78 Aug-78","creation_place_original_location":"Singapore Singapore","styles_periods_indexing_terms":"NA NA","inscriptions":"","inscription_language":"","scale_type":"NA NA","shape":"rectangular rectangular","materials_name":"printing paper printing paper","techniques_name":"printing (process) printing (process)","object_colour":"multicoloured multicoloured","edition_description":"8 8","physical_appearance":"The image displays the front cover of a travel guidebook. It is rectangular in shape. The image on the front cover features two ladies posing and looking in the direction where the photograph was captured. They are dressed in sarong wear and the background features flowers and foliage. The lady in blue to the right is holding a vintage bird cage and leaning against a cane armchair, which the other lady is sitting on.     The image displays the front cover of a travel guidebook. It is rectangular in shape. The image on the front cover features two ladies posing and looking in the direction where the photograph was captured. They are dressed in sarong wear and the background features flowers and foliage. The lady in blue to the right is holding a vintage bird cage and leaning against a cane armchair, which the other lady is sitting on.","subject_terms_1":"tourism cultural heritage travel tourism cultural heritage travel","subject_terms_2":"Guidebooks Tourism Voyages and travels Singapore Guidebooks Tourism Voyages and travels Singapore","subject_terms_3":"Description and travel Singapore Tourist Promotion Board Cultural development Description and travel Singapore Tourist Promotion Board Cultural development","subject_terms_4":"NA NA","context_1":"NA NA","context_2":"NA NA","context_3":"NA NA","context_4":"NA NA","context_5":"NA NA","context_6":"NA NA","context_7":"NA NA","context_8":"NA NA","context_9":"NA NA","context_10":"NA NA","context_11":"NA NA","context_12":"NA NA","context_13":"NA NA","context_14":"NA NA","context_15":"NA NA","context_16":"NA NA","context_17":"NA NA","context_18":"NA NA","context_19":"NA NA","context_20":"NA NA","context_21":"NA NA","context_22":"NA NA","context_23":"NA NA","context_24":"NA NA","sgcool_label_text":"This “Welcome to Singapore” visitor guide was published in 1978 by the Singapore Tourist Promotion Board (STPB). Catered to tourists, this free publication provides an overview of Singapore’s cultural heritage and introduces the main attractions of Singapore. \r\n\r\nThe cover of the visitor guide features a tropical scene of ladies dressed in sarong wear and contains a foreword by the Chairman of the Tourist Promotion Board.\r\nSTPB was created in 1964 as a statutory board by the government to develop and promote Singapore as a tourist destination. \r\n\r\nSTPB’s efforts in marketing Singapore as a holiday destination paid off, with tourist arrivals increasing from 100,000 in 1964 to over 2 million by 1978.  This “Welcome to Singapore” visitor guide was published in 1978 by the Singapore Tourist Promotion Board (STPB). Catered to tourists, this free publication provides an overview of Singapore’s cultural heritage and introduces the main attractions of Singapore. \r\n\r\nThe cover of the visitor guide features a tropical scene of ladies dressed in sarong wear and contains a foreword by the Chairman of the Tourist Promotion Board.\r\nSTPB was created in 1964 as a statutory board by the government to develop and promote Singapore as a tourist destination. \r\n\r\nSTPB’s efforts in marketing Singapore as a holiday destination paid off, with tourist arrivals increasing from 100,000 in 1964 to over 2 million by 1978."},"nlpDate":"20201119143405","connectorId":0,"tags":{}}