{"id":"2016-00557","title":"Pelarajan Perbualan (Conversation Lessons: Malay-English) Malay instructional booklet titled Pelarajan Perbualan (Conversation Lessons: Malay-English), published by the Institute of National Language and Culture   Pelarajan Perbualan (Conversation Lessons: Malay-English) Malay instructional booklet titled Pelarajan Perbualan (Conversation Lessons: Malay-English), published by the Institute of National Language and Culture","source":"Bumblebee","path":"./Data/json/","content":"accession_no_csv:2016-00557\nImage:\nobject_work_type:instructional materials instructional materials\ntitle_text:Pelarajan Perbualan (Conversation Lessons: Malay-English) Malay instructional booklet titled Pelarajan Perbualan (Conversation Lessons: Malay-English)\n published by the Institute of National Language and Culture   Pelarajan Perbualan (Conversation Lessons: Malay-English) Malay instructional booklet titled Pelarajan Perbualan (Conversation Lessons: Malay-English)\n published by the Institute of National Language and Culture\npreference:main alternate main alternate\ntitle_language:\ncreator_2:Dewan Bahasa Dan Kebudayaan Kebangsaan (DBKK) / Institute of National Language and Culture Suri Mohyani Ong Boon Tiong Dewan Bahasa Dan Kebudayaan Kebangsaan (DBKK) / Institute of National Language and Culture Suri Mohyani Ong Boon Tiong\ncreator_1:Dewan Bahasa Dan Kebudayaan Kebangsaan (Institute of National Language and Culture) (TTE) Not indicated Not indicated Dewan Bahasa Dan Kebudayaan Kebangsaan (Institute of National Language and Culture) (TTE) Not indicated Not indicated\ncreator_role:publishers contributors translators publishers contributors translators\ncreation_date:1964 1964\ncreation_place_original_location:Singapore Singapore\nstyles_periods_indexing_terms:NA NA\ninscriptions:\ninscription_language:\nscale_type:NA NA\nshape:rectangular rectangular\nmaterials_name:printing paper printing paper\ntechniques_name:colour printing colour printing\nobject_colour:multicoloured multicoloured\nedition_description:Siri 2 / Series 2 Siri 2 / Series 2\nphysical_appearance:\\The image shows the front cover of an instructional booklet. It has a green background.  \\\\Pelajaran Perbualan\\\\ is stated at the top in bold. \\\\Conversation Lessons Malay - English\\\\ is stated at the middle. \\\\Institute of Language and Culture\\\\ and \\\\Dewan Bahasa Dan Kebudayaan Kebangsaan\\\\ are stated near the bottom. There are some brown discolorations on the surface of the instructional booklet. \\ \\The image shows the front cover of an instructional booklet. It has a green background.  \\\\Pelajaran Perbualan\\\\ is stated at the top in bold. \\\\Conversation Lessons Malay - English\\\\ is stated at the middle. \\\\Institute of Language and Culture\\\\ and \\\\Dewan Bahasa Dan Kebudayaan Kebangsaan\\\\ are stated near the bottom. There are some brown discolorations on the surface of the instructional booklet. \\\nsubject_terms_1:booklets translation (function) governments (administrative bodies) booklets translation (function) governments (administrative bodies)\nsubject_terms_2:Pamphlets Instructional and educational works Translating and interpreting Government Institutes Pamphlets Instructional and educational works Translating and interpreting Government Institutes\nsubject_terms_3:Cultural development Malay languages and dialects Cultural development Malay languages and dialects\nsubject_terms_4:NA NA\ncontext_1:NA NA\ncontext_2:NA NA\ncontext_3:NA NA\ncontext_4:NA NA\ncontext_5:NA NA\ncontext_6:NA NA\ncontext_7:NA NA\ncontext_8:NA NA\ncontext_9:NA NA\ncontext_10:NA NA\ncontext_11:NA NA\ncontext_12:NA NA\ncontext_13:NA NA\ncontext_14:NA NA\ncontext_15:NA NA\ncontext_16:NA NA\ncontext_17:NA NA\ncontext_18:NA NA\ncontext_19:NA NA\ncontext_20:NA NA\ncontext_21:NA NA\ncontext_22:NA NA\ncontext_23:NA NA\ncontext_24:NA NA\nsgcool_label_text:This instructional booklet provides basic lessons on common Malay words that are used in everyday conversations. These lessons were printed in The Daily Mail and Radio Weekly\n and aired on Radio Malaysia and Radio Singapura as well. This booklet was published by the Dewan Bahasa Dan Kebudayaan Kebangsaan (DBKK)\n or Institute of National Language and Culture\n which was established in 1960. This was part of the government’s larger initiative to promote Malay as the national language\n as well as a Malayan culture. Besides publications\n the DBKK also organised a National Language week\n conferences for writers\n competitions\n exhibitions and cultural shows among other events to promote the national language.   This instructional booklet provides basic lessons on common Malay words that are used in everyday conversations. These lessons were printed in The Daily Mail and Radio Weekly\n and aired on Radio Malaysia and Radio Singapura as well. This booklet was published by the Dewan Bahasa Dan Kebudayaan Kebangsaan (DBKK)\n or Institute of National Language and Culture\n which was established in 1960. This was part of the government’s larger initiative to promote Malay as the national language\n as well as a Malayan culture. Besides publications\n the DBKK also organised a National Language week\n conferences for writers\n competitions\n exhibitions and cultural shows among other events to promote the national language.","createdDate":"20201018182635","version":0,"latest":false,"roles":[],"metadata":{"accession_no_csv":"2016-00557","Image":"","object_work_type":"instructional materials instructional materials","title_text":"Pelarajan Perbualan (Conversation Lessons: Malay-English) Malay instructional booklet titled Pelarajan Perbualan (Conversation Lessons: Malay-English), published by the Institute of National Language and Culture   Pelarajan Perbualan (Conversation Lessons: Malay-English) Malay instructional booklet titled Pelarajan Perbualan (Conversation Lessons: Malay-English), published by the Institute of National Language and Culture","preference":"main alternate main alternate","title_language":"","creator_2":"Dewan Bahasa Dan Kebudayaan Kebangsaan (DBKK) / Institute of National Language and Culture Suri Mohyani Ong Boon Tiong Dewan Bahasa Dan Kebudayaan Kebangsaan (DBKK) / Institute of National Language and Culture Suri Mohyani Ong Boon Tiong","creator_1":"Dewan Bahasa Dan Kebudayaan Kebangsaan (Institute of National Language and Culture) (TTE) Not indicated Not indicated Dewan Bahasa Dan Kebudayaan Kebangsaan (Institute of National Language and Culture) (TTE) Not indicated Not indicated","creator_role":"publishers contributors translators publishers contributors translators","creation_date":"1964 1964","creation_place_original_location":"Singapore Singapore","styles_periods_indexing_terms":"NA NA","inscriptions":"","inscription_language":"","scale_type":"NA NA","shape":"rectangular rectangular","materials_name":"printing paper printing paper","techniques_name":"colour printing colour printing","object_colour":"multicoloured multicoloured","edition_description":"Siri 2 / Series 2 Siri 2 / Series 2","physical_appearance":"\"The image shows the front cover of an instructional booklet. It has a green background.  \"\"Pelajaran Perbualan\"\" is stated at the top in bold. \"\"Conversation Lessons Malay - English\"\" is stated at the middle. \"\"Institute of Language and Culture\"\" and \"\"Dewan Bahasa Dan Kebudayaan Kebangsaan\"\" are stated near the bottom. There are some brown discolorations on the surface of the instructional booklet. \" \"The image shows the front cover of an instructional booklet. It has a green background.  \"\"Pelajaran Perbualan\"\" is stated at the top in bold. \"\"Conversation Lessons Malay - English\"\" is stated at the middle. \"\"Institute of Language and Culture\"\" and \"\"Dewan Bahasa Dan Kebudayaan Kebangsaan\"\" are stated near the bottom. There are some brown discolorations on the surface of the instructional booklet. \"","subject_terms_1":"booklets translation (function) governments (administrative bodies) booklets translation (function) governments (administrative bodies)","subject_terms_2":"Pamphlets Instructional and educational works Translating and interpreting Government Institutes Pamphlets Instructional and educational works Translating and interpreting Government Institutes","subject_terms_3":"Cultural development Malay languages and dialects Cultural development Malay languages and dialects","subject_terms_4":"NA NA","context_1":"NA NA","context_2":"NA NA","context_3":"NA NA","context_4":"NA NA","context_5":"NA NA","context_6":"NA NA","context_7":"NA NA","context_8":"NA NA","context_9":"NA NA","context_10":"NA NA","context_11":"NA NA","context_12":"NA NA","context_13":"NA NA","context_14":"NA NA","context_15":"NA NA","context_16":"NA NA","context_17":"NA NA","context_18":"NA NA","context_19":"NA NA","context_20":"NA NA","context_21":"NA NA","context_22":"NA NA","context_23":"NA NA","context_24":"NA NA","sgcool_label_text":"This instructional booklet provides basic lessons on common Malay words that are used in everyday conversations. These lessons were printed in The Daily Mail and Radio Weekly, and aired on Radio Malaysia and Radio Singapura as well. This booklet was published by the Dewan Bahasa Dan Kebudayaan Kebangsaan (DBKK), or Institute of National Language and Culture, which was established in 1960. This was part of the government’s larger initiative to promote Malay as the national language, as well as a Malayan culture. Besides publications, the DBKK also organised a National Language week, conferences for writers, competitions, exhibitions and cultural shows among other events to promote the national language.   This instructional booklet provides basic lessons on common Malay words that are used in everyday conversations. These lessons were printed in The Daily Mail and Radio Weekly, and aired on Radio Malaysia and Radio Singapura as well. This booklet was published by the Dewan Bahasa Dan Kebudayaan Kebangsaan (DBKK), or Institute of National Language and Culture, which was established in 1960. This was part of the government’s larger initiative to promote Malay as the national language, as well as a Malayan culture. Besides publications, the DBKK also organised a National Language week, conferences for writers, competitions, exhibitions and cultural shows among other events to promote the national language."},"nlpDate":"20201018182635","connectorId":0,"tags":{}}