{
  "id": "2016-00529",
  "title": "‘The Outlook’ newsletter for Singapore Airlines Group",
  "source": "Bumblebee",
  "path": "./Data/json/",
  "content": "\n  accession_no_csv: 2016-00529\n\n  Image: \n\n  object_work_type: newsletters\n\n  title_text: ‘The Outlook’ newsletter for Singapore Airlines Group\n\n  preference: main\n\n  title_language: \n\n  creator_2: Singapore Airlines Group\n\n  creator_1: Singapore Airlines\n\n  creator_role: creators\n\n  creation_date: 23-Sep-83\n\n  creation_place_original_location: Singapore\n\n  inscriptions: \n\n  inscription_language: \n\n  shape: rectangular\n\n  materials_name: printing paper\n\n  techniques_name: printing (process)\n\n  object_colour: multicoloured\n\n  edition_description: Not indicated\n\n  physical_appearance: \\The image displays a newsletter. \\\\Outlook\\\\ is displayed at the top left hand side as the mewsletter\\u0027s masthead. The logo of a company\n\n  subject_terms_1: corporate headquarters (inhabited places) hangars corporate headquarters (built works) The airline’s logo\n\n  subject_terms_2: Hangars Business enterprises a stylised version of a bird Office buildings\n\n  subject_terms_3: Singapore Airlines Commercial buildings Business enterprises can be seen beside the masthead. \\\\The Story of SIA\\\\\n\n  subject_terms_4: \\\\SIA\\u0027s New Home\\\\\n\n  context_1: and \\\\SIA\\u0027s New Home Opens Today: It\\u0027s Official\\\\ are the headlines . An image of a commercial building is displayed below the newsletter\\u0027s masthead.\\\n\n  context_2: companies\n\n  context_3: Newsletters\n\n  context_4: Newsletters\n",
  "createdDate": "20201125084533",
  "version": 0,
  "latest": false,
  "roles": [],
  "metadata": {
    "accession_no_csv": "2016-00529",
    "Image": "",
    "object_work_type": "newsletters",
    "title_text": "‘The Outlook’ newsletter for Singapore Airlines Group",
    "preference": "main",
    "title_language": "",
    "creator_2": "Singapore Airlines Group",
    "creator_1": "Singapore Airlines",
    "creator_role": "creators",
    "creation_date": "23-Sep-83",
    "creation_place_original_location": "Singapore",
    "inscriptions": "",
    "inscription_language": "",
    "shape": "rectangular",
    "materials_name": "printing paper",
    "techniques_name": "printing (process)",
    "object_colour": "multicoloured",
    "edition_description": "Not indicated",
    "physical_appearance": "\"The image displays a newsletter. \"\"Outlook\"\" is displayed at the top left hand side as the mewsletter\u0027s masthead. The logo of a company",
    "subject_terms_1": "corporate headquarters (inhabited places) hangars corporate headquarters (built works) The airline’s logo",
    "subject_terms_2": "Hangars Business enterprises a stylised version of a bird Office buildings",
    "subject_terms_3": "Singapore Airlines Commercial buildings Business enterprises can be seen beside the masthead. \"\"The Story of SIA\"\"",
    "subject_terms_4": "\"\"SIA\u0027s New Home\"\"",
    "context_1": "and \"\"SIA\u0027s New Home Opens Today: It\u0027s Official\"\" are the headlines . An image of a commercial building is displayed below the newsletter\u0027s masthead.\"",
    "context_2": "companies",
    "context_3": "Newsletters",
    "context_4": "Newsletters"
  },
  "nlpDate": "20201125084533",
  "connectorId": 0,
  "tags": {}
}