{"id":"2016-00528","title":"The Singapore Changi Airport Magazine The Singapore Changi Airport Magazine","source":"Bumblebee","path":"./Data/json/","content":"accession_no_csv:2016-00528\nImage:\nobject_work_type:magazines (periodicals) magazines (periodicals)\ntitle_text:The Singapore Changi Airport Magazine The Singapore Changi Airport Magazine\npreference:main main\ntitle_language:\ncreator_2:Singapore Changi Airport Singapore Changi Airport\ncreator_1:Singapore Changi Airport Singapore Changi Airport\ncreator_role:creators creators\ncreation_date:Aug-90 Aug-90\ncreation_place_original_location:Singapore Singapore\nstyles_periods_indexing_terms:NA NA\ninscriptions:\ninscription_language:\nscale_type:NA NA\nshape:rectangular rectangular\nmaterials_name:printing paper printing paper\ntechniques_name:printing (process) printing (process)\nobject_colour:multicoloured multicoloured\nedition_description:Not indicated Not indicated\nphysical_appearance:\\The image displays the front cover of a magazine. It has a red border. \\\\Changi\\\\ is displayed at the top. \\\\The Charm of Singapore\\\\ is displayed in red below the headline. Raffles Hotel is featured on the magazine cover. To the lower right side of the cover is a picture of child leaning against and looking over a railing.\\ \\The image displays the front cover of a magazine. It has a red border. \\\\Changi\\\\ is displayed at the top. \\\\The Charm of Singapore\\\\ is displayed in red below the headline. Raffles Hotel is featured on the magazine cover. To the lower right side of the cover is a picture of child leaning against and looking over a railing.\\\nsubject_terms_1:travel guidebooks tourism cultural heritage travel travel guidebooks tourism cultural heritage travel\nsubject_terms_2:Guidebooks Publications Tourism Voyages and travels Singapore Guidebooks Publications Tourism Voyages and travels Singapore\nsubject_terms_3:Periodicals Description and travel Cultural development Changi Airports International Pte. Ltd Periodicals Description and travel Cultural development Changi Airports International Pte. Ltd\nsubject_terms_4:NA NA\ncontext_1:NA NA\ncontext_2:NA NA\ncontext_3:NA NA\ncontext_4:NA NA\ncontext_5:NA NA\ncontext_6:NA NA\ncontext_7:NA NA\ncontext_8:NA NA\ncontext_9:NA NA\ncontext_10:NA NA\ncontext_11:NA NA\ncontext_12:NA NA\ncontext_13:NA NA\ncontext_14:NA NA\ncontext_15:NA NA\ncontext_16:NA NA\ncontext_17:NA NA\ncontext_18:NA NA\ncontext_19:NA NA\ncontext_20:NA NA\ncontext_21:NA NA\ncontext_22:NA NA\ncontext_23:NA NA\ncontext_24:NA NA\nsgcool_label_text:The Singapore Changi Airport Magazine provides a guide to tourists on the various sightseeing landmarks in Singapore. Published in August 1990\n this particular edition commemorates Singapore’s Silver Jubilee as an independent nation. \\r\\n\\r\\nThis magazine features an article on how Singapore has become an international business centre and air hub\n while retaining its historic charm. It sheds light on the various redevelopment projects in the Civic and Cultural District during that period\n such as the restoration of the 19th century Empress Place Building and Raffles Hotel\n which is featured on the magazine’s cover page. The Singapore Changi Airport Magazine provides a guide to tourists on the various sightseeing landmarks in Singapore. Published in August 1990\n this particular edition commemorates Singapore’s Silver Jubilee as an independent nation. \\r\\n\\r\\nThis magazine features an article on how Singapore has become an international business centre and air hub\n while retaining its historic charm. It sheds light on the various redevelopment projects in the Civic and Cultural District during that period\n such as the restoration of the 19th century Empress Place Building and Raffles Hotel\n which is featured on the magazine’s cover page.","createdDate":"20201018182635","version":0,"latest":false,"roles":[],"metadata":{"accession_no_csv":"2016-00528","Image":"","object_work_type":"magazines (periodicals) magazines (periodicals)","title_text":"The Singapore Changi Airport Magazine The Singapore Changi Airport Magazine","preference":"main main","title_language":"","creator_2":"Singapore Changi Airport Singapore Changi Airport","creator_1":"Singapore Changi Airport Singapore Changi Airport","creator_role":"creators creators","creation_date":"Aug-90 Aug-90","creation_place_original_location":"Singapore Singapore","styles_periods_indexing_terms":"NA NA","inscriptions":"","inscription_language":"","scale_type":"NA NA","shape":"rectangular rectangular","materials_name":"printing paper printing paper","techniques_name":"printing (process) printing (process)","object_colour":"multicoloured multicoloured","edition_description":"Not indicated Not indicated","physical_appearance":"\"The image displays the front cover of a magazine. It has a red border. \"\"Changi\"\" is displayed at the top. \"\"The Charm of Singapore\"\" is displayed in red below the headline. Raffles Hotel is featured on the magazine cover. To the lower right side of the cover is a picture of child leaning against and looking over a railing.\" \"The image displays the front cover of a magazine. It has a red border. \"\"Changi\"\" is displayed at the top. \"\"The Charm of Singapore\"\" is displayed in red below the headline. Raffles Hotel is featured on the magazine cover. To the lower right side of the cover is a picture of child leaning against and looking over a railing.\"","subject_terms_1":"travel guidebooks tourism cultural heritage travel travel guidebooks tourism cultural heritage travel","subject_terms_2":"Guidebooks Publications Tourism Voyages and travels Singapore Guidebooks Publications Tourism Voyages and travels Singapore","subject_terms_3":"Periodicals Description and travel Cultural development Changi Airports International Pte. Ltd Periodicals Description and travel Cultural development Changi Airports International Pte. Ltd","subject_terms_4":"NA NA","context_1":"NA NA","context_2":"NA NA","context_3":"NA NA","context_4":"NA NA","context_5":"NA NA","context_6":"NA NA","context_7":"NA NA","context_8":"NA NA","context_9":"NA NA","context_10":"NA NA","context_11":"NA NA","context_12":"NA NA","context_13":"NA NA","context_14":"NA NA","context_15":"NA NA","context_16":"NA NA","context_17":"NA NA","context_18":"NA NA","context_19":"NA NA","context_20":"NA NA","context_21":"NA NA","context_22":"NA NA","context_23":"NA NA","context_24":"NA NA","sgcool_label_text":"The Singapore Changi Airport Magazine provides a guide to tourists on the various sightseeing landmarks in Singapore. Published in August 1990, this particular edition commemorates Singapore’s Silver Jubilee as an independent nation. \r\n\r\nThis magazine features an article on how Singapore has become an international business centre and air hub, while retaining its historic charm. It sheds light on the various redevelopment projects in the Civic and Cultural District during that period, such as the restoration of the 19th century Empress Place Building and Raffles Hotel, which is featured on the magazine’s cover page. The Singapore Changi Airport Magazine provides a guide to tourists on the various sightseeing landmarks in Singapore. Published in August 1990, this particular edition commemorates Singapore’s Silver Jubilee as an independent nation. \r\n\r\nThis magazine features an article on how Singapore has become an international business centre and air hub, while retaining its historic charm. It sheds light on the various redevelopment projects in the Civic and Cultural District during that period, such as the restoration of the 19th century Empress Place Building and Raffles Hotel, which is featured on the magazine’s cover page."},"nlpDate":"20201018182635","connectorId":0,"tags":{}}