{
  "id": "2016-00146-001",
  "title": "Male polychrome wooden sculpture of a Musical \u0026 Dance Troupe holding a tuba Nine Polychrome Wooden Sculptures of a Musical \u0026 Dance Troupe",
  "source": "Bumblebee",
  "path": "./Data/json/",
  "content": "\n  accession_no_csv: 2016-00146-001\n\n  Image: \n\n  object_work_type: figurines sculpture (visual works)\n\n  title_text: Male polychrome wooden sculpture of a Musical \\u0026 Dance Troupe holding a tuba Nine Polychrome Wooden Sculptures of a Musical \\u0026 Dance Troupe\n\n  preference: main alternate\n\n  title_language: \n\n  creation_date: 1870 - 1899\n\n  creation_place_original_location: India\n South Cet?t?ina?t?u (India)\n\n  styles_periods_indexing_terms: British Colonial Indian\n\n  inscriptions: \n\n  inscription_language: \n\n  shape: irregular\n\n  materials_name: wood (plant material) paint (coating)\n\n  techniques_name: woodcarving forming (physical activity) painting (image-making)\n\n  object_colour: polychrome\n\n  physical_appearance: The image depicts a male figurine. It is holding a tuba in both hands. There is a headgear present. The figurine is standing atop a base that is painted red with a yellow band. It is rendered with breeches\n stockings\n and a military jacket.\n\n  subject_terms_1: carvings (visual works) dolls personification instrumentalists performing artists tubas\n\n  subject_terms_2: Wood-carved figurines Dolls Personification in art Instrumentalists Entertainers Wood sculpture Brass instruments\n\n  sgcool_label_text: India\n during the Company period\n produced paintings of typical Indian professions and trades. In similar fashion\n highly naturalistic terracotta/clay figures of Indian tradesmen were produced in regions such as Kondapalli in Andhra Pradesh and more importantly in the Bengal region. Krishnagar\n Hatwa\n Datan\n Muzzafarpur\n Dacca\n Burdwan\n Lucknow and Patna (the latter two later on in time than the preceding) such life-like figures\n predating photography\n were produced. This rare set was produced in Chettinad\n Tamil Nadu. \\r\\nThis musical troupe accompanied by a single female dancer of painted carved wood is a highly decorative\n superior example of south Indian dolls made in the 19th century. Every fold of cloth and each body movement and contour has been carefully captured by the wood carver. The faces of each performer are particularly sensitively rendered. The dancer has a metal girdle about her waist from which metal spheres are suspended but other than that\n the set is entirely composed of painted and gilded wood. Each member of the set is also taller than is usual. The set has no religious function; it was made purely for decorative reasons for a local client. Other than the female dancer\n the set comprises a bag pipe player\n a drummer\n a cymbals player and five other players of wind instruments. The troupe might well have been for a wedding or some other festivity. Certainly\n the troupe with its (part) Western forms of dress such as breeches\n stockings\n and military jackets and Westernised musical instruments personify musicians who would have performed for wealthy\n educated clients.\n",
  "createdDate": "20201120223706",
  "version": 0,
  "latest": false,
  "roles": [],
  "metadata": {
    "accession_no_csv": "2016-00146-001",
    "Image": "",
    "object_work_type": "figurines sculpture (visual works)",
    "title_text": "Male polychrome wooden sculpture of a Musical \u0026 Dance Troupe holding a tuba Nine Polychrome Wooden Sculptures of a Musical \u0026 Dance Troupe",
    "preference": "main alternate",
    "title_language": "",
    "creation_date": "1870 - 1899",
    "creation_place_original_location": "India, South Cet?t?ina?t?u (India)",
    "styles_periods_indexing_terms": "British Colonial Indian",
    "inscriptions": "",
    "inscription_language": "",
    "shape": "irregular",
    "materials_name": "wood (plant material) paint (coating)",
    "techniques_name": "woodcarving forming (physical activity) painting (image-making)",
    "object_colour": "polychrome",
    "physical_appearance": "The image depicts a male figurine. It is holding a tuba in both hands. There is a headgear present. The figurine is standing atop a base that is painted red with a yellow band. It is rendered with breeches, stockings, and a military jacket.",
    "subject_terms_1": "carvings (visual works) dolls personification instrumentalists performing artists tubas",
    "subject_terms_2": "Wood-carved figurines Dolls Personification in art Instrumentalists Entertainers Wood sculpture Brass instruments",
    "sgcool_label_text": "India, during the Company period, produced paintings of typical Indian professions and trades. In similar fashion, highly naturalistic terracotta/clay figures of Indian tradesmen were produced in regions such as Kondapalli in Andhra Pradesh and more importantly in the Bengal region. Krishnagar, Hatwa, Datan, Muzzafarpur, Dacca, Burdwan, Lucknow and Patna (the latter two later on in time than the preceding) such life-like figures, predating photography, were produced. This rare set was produced in Chettinad, Tamil Nadu. \r\nThis musical troupe accompanied by a single female dancer of painted carved wood is a highly decorative, superior example of south Indian dolls made in the 19th century. Every fold of cloth and each body movement and contour has been carefully captured by the wood carver. The faces of each performer are particularly sensitively rendered. The dancer has a metal girdle about her waist from which metal spheres are suspended but other than that, the set is entirely composed of painted and gilded wood. Each member of the set is also taller than is usual. The set has no religious function; it was made purely for decorative reasons for a local client. Other than the female dancer, the set comprises a bag pipe player, a drummer, a cymbals player and five other players of wind instruments. The troupe might well have been for a wedding or some other festivity. Certainly, the troupe with its (part) Western forms of dress such as breeches, stockings, and military jackets and Westernised musical instruments personify musicians who would have performed for wealthy, educated clients."
  },
  "nlpDate": "20201120223706",
  "connectorId": 0,
  "tags": {}
}