{
  "id": "2016-00295",
  "title": "A Qur\u0027an in three volumes Qur\u0027an in three volumes",
  "source": "Bumblebee",
  "path": "./Data/json/",
  "content": "\n  accession_no_csv: 2016-00295\n\n  Image: \n\n  object_work_type: Qur\\u0027ans\n\n  title_text: A Qur\\u0027an in three volumes Qur\\u0027an in three volumes\n\n  preference: alternate main\n\n  title_language: \n\n  creation_place_original_location: China\n\n  styles_periods_indexing_terms: Chinese (culture or style)\n\n  inscriptions: \n\n  inscription_language: \n\n  shape: rectangular\n\n  materials_name: polychrome ink paper (fiber product)\n\n  techniques_name: printing (process)\n\n  object_colour: multicolored\n\n  physical_appearance: This is a page from a Chinese-style Qur\\u0027an. The page presents a section of verses. The verses are printed in blank ink\n with a gold and multicolored\n floral motif patterned border around it. The edges of the page are slightly folded.\n\n  subject_terms_1: Islam calligraphy (visual works) flower (motif) cultural diffusion Arabic scripts Chinese (culture or style)\n\n  subject_terms_2: Qur\\u0027an Islam Motifs Culture diffusion\n\n  subject_terms_3: Islam\n\n  sgcool_label_text: Conventionally\n Quranic manuscripts are presented as single volumes or as a thirty-part series where each volume is called a juz. However\n this Quran copy has been unusually bound in three volumes. The main folios contain 11 lines of text in black. The script used is a distinctly Chinese script style inspired by the tapering brushstroke forms in traditional Chinese calligraphy\n known as sini.  Each volume features different polychrome and gold illumination on the first and final bifolios. The illumination is predominantly composed of floral motifs and has been painted in a most refined and sophisticated manner. The richness of these motifs echo Chinese embroidery on silk.\n",
  "createdDate": "20201120223706",
  "version": 0,
  "latest": false,
  "roles": [],
  "metadata": {
    "accession_no_csv": "2016-00295",
    "Image": "",
    "object_work_type": "Qur\u0027ans",
    "title_text": "A Qur\u0027an in three volumes Qur\u0027an in three volumes",
    "preference": "alternate main",
    "title_language": "",
    "creation_place_original_location": "China",
    "styles_periods_indexing_terms": "Chinese (culture or style)",
    "inscriptions": "",
    "inscription_language": "",
    "shape": "rectangular",
    "materials_name": "polychrome ink paper (fiber product)",
    "techniques_name": "printing (process)",
    "object_colour": "multicolored",
    "physical_appearance": "This is a page from a Chinese-style Qur\u0027an. The page presents a section of verses. The verses are printed in blank ink, with a gold and multicolored, floral motif patterned border around it. The edges of the page are slightly folded.",
    "subject_terms_1": "Islam calligraphy (visual works) flower (motif) cultural diffusion Arabic scripts Chinese (culture or style)",
    "subject_terms_2": "Qur\u0027an Islam Motifs Culture diffusion",
    "subject_terms_3": "Islam",
    "sgcool_label_text": "Conventionally, Quranic manuscripts are presented as single volumes or as a thirty-part series where each volume is called a juz. However, this Quran copy has been unusually bound in three volumes. The main folios contain 11 lines of text in black. The script used is a distinctly Chinese script style inspired by the tapering brushstroke forms in traditional Chinese calligraphy, known as sini.  Each volume features different polychrome and gold illumination on the first and final bifolios. The illumination is predominantly composed of floral motifs and has been painted in a most refined and sophisticated manner. The richness of these motifs echo Chinese embroidery on silk."
  },
  "nlpDate": "20201120223706",
  "connectorId": 0,
  "tags": {}
}