{
  "id": "2016-00079",
  "title": "Application for accommodation card issued by Singapore Improvement Trust, Registration No: 002991",
  "source": "Bumblebee",
  "path": "./Data/json/",
  "content": "\n  accession_no_csv: 2016-00079\n\n  Image: \n\n  object_work_type: cards (information artefacts)\n\n  title_text: Application for accommodation card issued by Singapore Improvement Trust\n Registration No: 002991\n\n  preference: main\n\n  title_language: \n\n  creator_2: Unknown\n\n  creation_date: Mid-20th century\n\n  creation_place_original_location: Singapore\n\n  styles_periods_indexing_terms: Not indicated\n\n  inscriptions: \n\n  inscription_language: \n\n  scale_type: Not indicated\n\n  shape: rectangular\n\n  materials_name: printing paper\n\n  techniques_name: printing (process)\n\n  object_colour: multicoloured\n\n  physical_appearance: \\The image shows a card. It is rectangular in shape and it has a grey background. There is a passport sized photograph of a man at the right hand side of the card. \\\\Singapore Improvement Trust\n\n  subject_terms_1: Application For Accomodation\\\\ is stated at the top. \\\\V. Gurusamy\\\\ musicians\n\n  subject_terms_2: Singapore Improvement Trust and \\\\14 Rappa Terrace Musicians\n\n  subject_terms_3: Singapore 8\\\\ are handwritten on the card. \\ Musicians\n\n  subject_terms_4: public housing\n\n  context_1: Housing\n\n  context_2: Singapore Improvement Trust\n",
  "createdDate": "20201201203309",
  "version": 0,
  "latest": false,
  "roles": [],
  "metadata": {
    "accession_no_csv": "2016-00079",
    "Image": "",
    "object_work_type": "cards (information artefacts)",
    "title_text": "Application for accommodation card issued by Singapore Improvement Trust, Registration No: 002991",
    "preference": "main",
    "title_language": "",
    "creator_2": "Unknown",
    "creation_date": "Mid-20th century",
    "creation_place_original_location": "Singapore",
    "styles_periods_indexing_terms": "Not indicated",
    "inscriptions": "",
    "inscription_language": "",
    "scale_type": "Not indicated",
    "shape": "rectangular",
    "materials_name": "printing paper",
    "techniques_name": "printing (process)",
    "object_colour": "multicoloured",
    "physical_appearance": "\"The image shows a card. It is rectangular in shape and it has a grey background. There is a passport sized photograph of a man at the right hand side of the card. \"\"Singapore Improvement Trust",
    "subject_terms_1": "Application For Accomodation\"\" is stated at the top. \"\"V. Gurusamy\"\" musicians",
    "subject_terms_2": "Singapore Improvement Trust and \"\"14 Rappa Terrace Musicians",
    "subject_terms_3": "Singapore 8\"\" are handwritten on the card. \" Musicians",
    "subject_terms_4": "public housing",
    "context_1": "Housing",
    "context_2": "Singapore Improvement Trust"
  },
  "nlpDate": "20201201203309",
  "connectorId": 0,
  "tags": {}
}