{
  "id": "2016-00026-004",
  "title": "East Indie Native: Woman with basket Watercolour Batavia Portraits",
  "source": "Bumblebee",
  "path": "./Data/json/",
  "content": "\n  accession_no_csv: 2016-00026-004\n\n  Image: \n\n  object_work_type: watercolors (paintings)\n\n  title_text: East Indie Native: Woman with basket Watercolour Batavia Portraits\n\n  preference: main alternate\n\n  title_language: \n\n  creation_date: 17th century\n\n  creation_place_original_location: Jakarta (Indonesia)\n\n  inscriptions: \n\n  inscription_language: \n\n  shape: rectangular\n\n  materials_name: paper (fiber product) watercolor (paint)\n\n  techniques_name: watercolor painting (technique)\n\n  object_colour: multicolored\n\n  physical_appearance: This is a watercolour painting of a native woman in Batavia. She is wearing a white long-sleeved top with a blue-and-white plaid long skirt. She is wearing an orange beaded necklace and beaded bracelet. She is smoking a cigarette\n and balancing a large basket of crops on her head. She is walking barefoot on the ground. There is a pinapple plant on the right of the painting.\n\n  subject_terms_1: ways of life indigenous people ethnicity folk costume\n\n  subject_terms_2: Ethnic costume Lifestyles Ethnicity Javanese (Indonesian people) Indigenous people Watercolour painting\n\n  subject_terms_3: Visual Arts Watercolour painting\n\n  sgcool_label_text: This set of 6 watercolour on paper drawings depict Dutch school observations of Natives in the East Indies. Each full-length portrait is a study of the various ethnic groups from Java as well the distinctive mestizo – persons of mixed European and Indonesian ethnic ancestry. It is likely that this set of watercolour drawings are from 17th century. Costumes worn by mestiza women in Dutch colonial towns indicate a clear 17th century style\n characterised by a baju with a V-shaped opening for the head\n a selendang\n and a wrapped skirt of Indian cloth. \\r\\n\\r\\nListed as an un-authored work of art\n elements of the drawing bear strong resemblance to prominent 17th century Dutch artist\n Andries Beeckman’s (active 1651-57 Dutch East Indies) watercolour drawings of “A Woman of Batavia”\n mid-17th century. A blonde and barefoot mestiza for example\n reveals the same composition and formal features as Beeckman’s drawings – Her hair is tied in a chignon and accompanied by curly tresses descending from the side and her body is angled sideways\n with her right hand placed upon her head. It is plausible that these drawings are likely to be a copy of Andries Beeckman’s watercolour drawings of the same period.\\r\\n\\r\\nThese watercolour drawings depict a diverse community of ethnic groups from Java\n as well the impact of Dutch colonialism in the form of mixed race populations and subsequent impact on social and cultural customs and practices. Such portrayals in watercolour are rare and seldom appear in the open market.\n",
  "createdDate": "20201201203309",
  "version": 0,
  "latest": false,
  "roles": [],
  "metadata": {
    "accession_no_csv": "2016-00026-004",
    "Image": "",
    "object_work_type": "watercolors (paintings)",
    "title_text": "East Indie Native: Woman with basket Watercolour Batavia Portraits",
    "preference": "main alternate",
    "title_language": "",
    "creation_date": "17th century",
    "creation_place_original_location": "Jakarta (Indonesia)",
    "inscriptions": "",
    "inscription_language": "",
    "shape": "rectangular",
    "materials_name": "paper (fiber product) watercolor (paint)",
    "techniques_name": "watercolor painting (technique)",
    "object_colour": "multicolored",
    "physical_appearance": "This is a watercolour painting of a native woman in Batavia. She is wearing a white long-sleeved top with a blue-and-white plaid long skirt. She is wearing an orange beaded necklace and beaded bracelet. She is smoking a cigarette, and balancing a large basket of crops on her head. She is walking barefoot on the ground. There is a pinapple plant on the right of the painting.",
    "subject_terms_1": "ways of life indigenous people ethnicity folk costume",
    "subject_terms_2": "Ethnic costume Lifestyles Ethnicity Javanese (Indonesian people) Indigenous people Watercolour painting",
    "subject_terms_3": "Visual Arts Watercolour painting",
    "sgcool_label_text": "This set of 6 watercolour on paper drawings depict Dutch school observations of Natives in the East Indies. Each full-length portrait is a study of the various ethnic groups from Java as well the distinctive mestizo – persons of mixed European and Indonesian ethnic ancestry. It is likely that this set of watercolour drawings are from 17th century. Costumes worn by mestiza women in Dutch colonial towns indicate a clear 17th century style, characterised by a baju with a V-shaped opening for the head, a selendang, and a wrapped skirt of Indian cloth. \r\n\r\nListed as an un-authored work of art, elements of the drawing bear strong resemblance to prominent 17th century Dutch artist, Andries Beeckman’s (active 1651-57 Dutch East Indies) watercolour drawings of “A Woman of Batavia”, mid-17th century. A blonde and barefoot mestiza for example, reveals the same composition and formal features as Beeckman’s drawings – Her hair is tied in a chignon and accompanied by curly tresses descending from the side and her body is angled sideways, with her right hand placed upon her head. It is plausible that these drawings are likely to be a copy of Andries Beeckman’s watercolour drawings of the same period.\r\n\r\nThese watercolour drawings depict a diverse community of ethnic groups from Java, as well the impact of Dutch colonialism in the form of mixed race populations and subsequent impact on social and cultural customs and practices. Such portrayals in watercolour are rare and seldom appear in the open market."
  },
  "nlpDate": "20201201203309",
  "connectorId": 0,
  "tags": {}
}