{
  "id": "2016-00352",
  "title": "Manila shawl",
  "source": "Bumblebee",
  "path": "./Data/json/",
  "content": "\n  accession_no_csv: 2016-00352\n\n  Image: \n\n  object_work_type: shawls\n\n  title_text: Manila shawl\n\n  preference: main\n\n  title_language: \n\n  creation_date: 1930s\n\n  creation_place_original_location: Guangzhou (China)\n\n  inscriptions: \n\n  inscription_language: \n\n  shape: rectangular\n\n  materials_name: silk (textile)\n\n  techniques_name: embroidering\n\n  object_colour: multicolored\n\n  physical_appearance: This black silk is fringed around the edges. It is embroided with floral motifs and pattenrs in polychrome colours. There is a bordered embroidery around the edge\n with larger flower embroidery at the top left and bottom right. At the bottom right\n there is a bird amongst the flowers. There are no tears seen.\n\n  subject_terms_1: leaf scrolls exports birds (motifs) flower (motif)\n\n  subject_terms_2: Motifs exports Embroidery Shawls\n\n  subject_terms_3: Textile art and design\n\n  sgcool_label_text: Shawls such as this object were often referred to as Manila shawl\n or Mantones de Manila. Manila shawls were popular in Europe during the 19th and 20th centuries\n especially in Spain. They are usually worn covering the shoulders or as a mantilla covering the heads of women. Made of silk and produced in China\n they were brought to European shores through trade routes earlier established by the Manila-Acapulco galleon trade (1565–1815). Although the shawls were made in China\n they were usually shipped to Europe via Manila on the galleons\n hence the misnomer\n “Manila shawls”.\n",
  "createdDate": "20201125084535",
  "version": 0,
  "latest": false,
  "roles": [],
  "metadata": {
    "accession_no_csv": "2016-00352",
    "Image": "",
    "object_work_type": "shawls",
    "title_text": "Manila shawl",
    "preference": "main",
    "title_language": "",
    "creation_date": "1930s",
    "creation_place_original_location": "Guangzhou (China)",
    "inscriptions": "",
    "inscription_language": "",
    "shape": "rectangular",
    "materials_name": "silk (textile)",
    "techniques_name": "embroidering",
    "object_colour": "multicolored",
    "physical_appearance": "This black silk is fringed around the edges. It is embroided with floral motifs and pattenrs in polychrome colours. There is a bordered embroidery around the edge, with larger flower embroidery at the top left and bottom right. At the bottom right, there is a bird amongst the flowers. There are no tears seen.",
    "subject_terms_1": "leaf scrolls exports birds (motifs) flower (motif)",
    "subject_terms_2": "Motifs exports Embroidery Shawls",
    "subject_terms_3": "Textile art and design",
    "sgcool_label_text": "Shawls such as this object were often referred to as Manila shawl, or Mantones de Manila. Manila shawls were popular in Europe during the 19th and 20th centuries, especially in Spain. They are usually worn covering the shoulders or as a mantilla covering the heads of women. Made of silk and produced in China, they were brought to European shores through trade routes earlier established by the Manila-Acapulco galleon trade (1565–1815). Although the shawls were made in China, they were usually shipped to Europe via Manila on the galleons, hence the misnomer, “Manila shawls”."
  },
  "nlpDate": "20201125084535",
  "connectorId": 0,
  "tags": {}
}