{
  "id": "2016-00212-045",
  "title": "Photograph album of views and portraits in the Punjab, Cashmere, Ceylon, Burma, Penang, Singapore, and Java Shwegyin Monastery, Rangoon",
  "source": "Bumblebee",
  "path": "./Data/json/",
  "content": "\n  accession_no_csv: 2016-00212-045\n\n  Image: \n\n  object_work_type: black-and-white photographs\n\n  title_text: Photograph album of views and portraits in the Punjab\n Cashmere\n Ceylon\n Burma\n Penang\n Singapore\n and Java Shwegyin Monastery\n Rangoon\n\n  preference: alternate main\n\n  title_language: \n\n  creator_2: John Thomson\n\n  creator_1: Thomson\n J. (John)\n 1837-1921\n\n  creator_role: photographers\n\n  creation_date: before 28 Jul 1876\n\n  creation_place_original_location: Singapore Rangoon (Burma)\n\n  inscriptions: \n\n  inscription_language: \n\n  shape: rectangular\n\n  materials_name: albumen (egg white protein) albumen paper paper (fiber product)\n\n  techniques_name: albumen process\n\n  object_colour: black-and-white (colors)\n\n  physical_appearance: This is a photograph of statues at the Shwegyin Monastery in Rangoon\n Burma. In the forefront of the photograph\n there is a platform decorated with intricate motif carvings. There is a reclining Buddha statue on the platform\n accompanied by twelve other statues of Buddha\\u0027s devotees. A part of the building structure of the monastery can be seen in the background of the photograph. The title is written at the bottom\n below the photograph.\n\n  subject_terms_1: monasteries (built complexes) Buddhism statues Buddhas (visual works)\n\n  subject_terms_2: Photographs Thomson\n J. (John)\n 1837-1921 Monasteries Statues Gautama Buddha\n\n  subject_terms_3: Photography Buddhism Religious buildings\n",
  "createdDate": "20201120223706",
  "version": 0,
  "latest": false,
  "roles": [],
  "metadata": {
    "accession_no_csv": "2016-00212-045",
    "Image": "",
    "object_work_type": "black-and-white photographs",
    "title_text": "Photograph album of views and portraits in the Punjab, Cashmere, Ceylon, Burma, Penang, Singapore, and Java Shwegyin Monastery, Rangoon",
    "preference": "alternate main",
    "title_language": "",
    "creator_2": "John Thomson",
    "creator_1": "Thomson, J. (John), 1837-1921",
    "creator_role": "photographers",
    "creation_date": "before 28 Jul 1876",
    "creation_place_original_location": "Singapore Rangoon (Burma)",
    "inscriptions": "",
    "inscription_language": "",
    "shape": "rectangular",
    "materials_name": "albumen (egg white protein) albumen paper paper (fiber product)",
    "techniques_name": "albumen process",
    "object_colour": "black-and-white (colors)",
    "physical_appearance": "This is a photograph of statues at the Shwegyin Monastery in Rangoon, Burma. In the forefront of the photograph, there is a platform decorated with intricate motif carvings. There is a reclining Buddha statue on the platform, accompanied by twelve other statues of Buddha\u0027s devotees. A part of the building structure of the monastery can be seen in the background of the photograph. The title is written at the bottom, below the photograph.",
    "subject_terms_1": "monasteries (built complexes) Buddhism statues Buddhas (visual works)",
    "subject_terms_2": "Photographs Thomson, J. (John), 1837-1921 Monasteries Statues Gautama Buddha",
    "subject_terms_3": "Photography Buddhism Religious buildings"
  },
  "nlpDate": "20201120223706",
  "connectorId": 0,
  "tags": {}
}