{"id":"2016-00212-046","title":"Photograph album of views and portraits in the Punjab, Cashmere, Ceylon, Burma, Penang, Singapore, and Java Burmese Funeral","source":"Bumblebee","path":"./Data/json/","content":"accession_no_csv:2016-00212-046\nImage:\nobject_work_type:black-and-white photographs\ntitle_text:Photograph album of views and portraits in the Punjab\n Cashmere\n Ceylon\n Burma\n Penang\n Singapore\n and Java Burmese Funeral\npreference:alternate main\ntitle_language:\ncreator_2:John Thomson\ncreator_1:Thomson\n J. (John)\n 1837-1921\ncreator_role:photographers\ncreation_date:before 28 Jul 1876\ncreation_place_original_location:Singapore\ninscriptions:\ninscription_language:\nshape:rectangular\nmaterials_name:albumen (egg white protein) albumen paper paper (fiber product)\ntechniques_name:albumen process\nobject_colour:black-and-white (colors)\nphysical_appearance:This is a photograph of a Burmese Funeral procession. The photograph shows a huge crowd accompanying the procession. In the center of the photograph\n there is a funeral car and spire. There are several other carts in the background. The carts all have white flags on them. The title is written at the bottom\n below the photograph.\nsubject_terms_1:funeral processions customs (social)\nsubject_terms_2:Photographs Thomson\n J. (John)\n 1837-1921 Burmese Funeral rites and ceremonies\nsubject_terms_3:Photography Death customs","createdDate":"20201018182635","version":0,"latest":false,"roles":[],"metadata":{"accession_no_csv":"2016-00212-046","Image":"","object_work_type":"black-and-white photographs","title_text":"Photograph album of views and portraits in the Punjab, Cashmere, Ceylon, Burma, Penang, Singapore, and Java Burmese Funeral","preference":"alternate main","title_language":"","creator_2":"John Thomson","creator_1":"Thomson, J. (John), 1837-1921","creator_role":"photographers","creation_date":"before 28 Jul 1876","creation_place_original_location":"Singapore","inscriptions":"","inscription_language":"","shape":"rectangular","materials_name":"albumen (egg white protein) albumen paper paper (fiber product)","techniques_name":"albumen process","object_colour":"black-and-white (colors)","physical_appearance":"This is a photograph of a Burmese Funeral procession. The photograph shows a huge crowd accompanying the procession. In the center of the photograph, there is a funeral car and spire. There are several other carts in the background. The carts all have white flags on them. The title is written at the bottom, below the photograph.","subject_terms_1":"funeral processions customs (social)","subject_terms_2":"Photographs Thomson, J. (John), 1837-1921 Burmese Funeral rites and ceremonies","subject_terms_3":"Photography Death customs"},"nlpDate":"20201018182635","connectorId":0,"tags":{}}