{"id":"2016-00500","title":"Untitled (railway station; locomotive 25107)","source":"Bumblebee","path":"./Data/json/","content":"accession_no_csv:2016-00500\nImage:\nobject_work_type:black-and-white photographs\ntitle_text:Untitled (railway station; locomotive 25107)\npreference:main\ntitle_language:\ncreator_2:Kwek Leng Joo\ncreator_1:Kwek\n Leng Joo\ncreator_role:photographers\ncreation_date:2010\ncreation_place_original_location:Singapore Malaysia\ninscriptions:\ninscription_language:\nshape:rectangular\nmaterials_name:paper (fiber product)\ntechniques_name:printing (process)\nobject_colour:grey monochrome\nphysical_appearance:The image shows a photograph in black-and-white. It has a black frame and its border is white in colour. There are at least three sets of railroads that are visible in this image. Two out of the three are occupied by trains. There is a train driver looking out of the window from the front compartment at another worker standing on the track. They are holding a token as part of the railway signalling system. To the right of the photograph\n there a group of visitors\n comprising of adults and children\n looking at the trains. Some of them are sitting while others are standing up\n and a man can be seen taking a photograph with a camera \n beside a camera stand. There are numerous trees located at the top left of the photograph\n with some of them coming into contact with the train nearest to the background of the image.\nsubject_terms_1:locomotives railroads (infrastructures) trains (vehicle groupings) passenger cars (railroad cars) blue collar workers visitors historic monuments\nsubject_terms_2:Black-and-white photography Locomotives Railroads Railroad passenger cars Historic monuments Blue collar workers Pertadbiran Keretapi Tanah Melayu Railroad trains\nsubject_terms_3:Rail transport Tanjong Pagar Railway Station Pertadbiran Keretapi Tanah Melayu Photography Rail transport (Stations)\nsgcool_label_text:\\This image captures a few visitors taking photographs of the locomotives at the railway station. It is part of the \\\\Tracking Memories\\\\ collection by the late Mr Kwek Leng Joo. The collection captures different aspects of the Malayan Railway story in Singapore","createdDate":"20201119143405","version":0,"latest":false,"roles":[],"metadata":{"accession_no_csv":"2016-00500","Image":"","object_work_type":"black-and-white photographs","title_text":"Untitled (railway station; locomotive 25107)","preference":"main","title_language":"","creator_2":"Kwek Leng Joo","creator_1":"Kwek, Leng Joo","creator_role":"photographers","creation_date":"2010","creation_place_original_location":"Singapore Malaysia","inscriptions":"","inscription_language":"","shape":"rectangular","materials_name":"paper (fiber product)","techniques_name":"printing (process)","object_colour":"grey monochrome","physical_appearance":"The image shows a photograph in black-and-white. It has a black frame and its border is white in colour. There are at least three sets of railroads that are visible in this image. Two out of the three are occupied by trains. There is a train driver looking out of the window from the front compartment at another worker standing on the track. They are holding a token as part of the railway signalling system. To the right of the photograph, there a group of visitors, comprising of adults and children, looking at the trains. Some of them are sitting while others are standing up, and a man can be seen taking a photograph with a camera , beside a camera stand. There are numerous trees located at the top left of the photograph, with some of them coming into contact with the train nearest to the background of the image.","subject_terms_1":"locomotives railroads (infrastructures) trains (vehicle groupings) passenger cars (railroad cars) blue collar workers visitors historic monuments","subject_terms_2":"Black-and-white photography Locomotives Railroads Railroad passenger cars Historic monuments Blue collar workers Pertadbiran Keretapi Tanah Melayu Railroad trains","subject_terms_3":"Rail transport Tanjong Pagar Railway Station Pertadbiran Keretapi Tanah Melayu Photography Rail transport (Stations)","sgcool_label_text":"\"This image captures a few visitors taking photographs of the locomotives at the railway station. It is part of the \"\"Tracking Memories\"\" collection by the late Mr Kwek Leng Joo. The collection captures different aspects of the Malayan Railway story in Singapore"},"nlpDate":"20201119143405","connectorId":0,"tags":{}}