{"id":"2016-00068","title":"Invitation card to concert (“Inisai Katcheri”)","source":"Bumblebee","path":"./Data/json/","content":"accession_no_csv:2016-00068\nImage:\nobject_work_type:invitations\ntitle_text:Invitation card to concert (“Inisai Katcheri”)\npreference:main\ntitle_language:\ncreator_2:Unknown\ncreation_date:3-Oct-53\ncreation_place_original_location:Singapore\nstyles_periods_indexing_terms:Not indicated\ninscriptions:\ninscription_language:\nscale_type:Not indicated\nshape:rectangular\nmaterials_name:printing paper\ntechniques_name:printing (process)\nobject_colour:multicoloured\nphysical_appearance:\\The image shows an invitation card. It is rectangular in shape. It has a yellow background. \\\\3-10-53\\\\ is stated at the bottom left hand side. The invitation card is filled with the Tamil script. \\\nsubject_terms_1:concerts (performances)\nsubject_terms_2:Invitation cards Concerts\nsubject_terms_3:Indian music Performing Arts\nsgcool_label_text:M.V.Gurusamy (b. 1920 in Seremban) was an accomplished percussionist and mridangam artiste as well as a renowned percussion teacher in Singapore. He arrived in Singapore and participated in the Indian classical music scene here. He was a member of the cultural contingent led by the then Minister for Culture\n S. Rajaratnam\n which visited and performed at various centres in Sarawak\n Brunei and Sabah in 1965. He was the recipient of several titles including the Kala Ratna award given by the Singapore Indian Fine Arts Society in 1986.","createdDate":"20201119143405","version":0,"latest":false,"roles":[],"metadata":{"accession_no_csv":"2016-00068","Image":"","object_work_type":"invitations","title_text":"Invitation card to concert (“Inisai Katcheri”)","preference":"main","title_language":"","creator_2":"Unknown","creation_date":"3-Oct-53","creation_place_original_location":"Singapore","styles_periods_indexing_terms":"Not indicated","inscriptions":"","inscription_language":"","scale_type":"Not indicated","shape":"rectangular","materials_name":"printing paper","techniques_name":"printing (process)","object_colour":"multicoloured","physical_appearance":"\"The image shows an invitation card. It is rectangular in shape. It has a yellow background. \"\"3-10-53\"\" is stated at the bottom left hand side. The invitation card is filled with the Tamil script. \"","subject_terms_1":"concerts (performances)","subject_terms_2":"Invitation cards Concerts","subject_terms_3":"Indian music Performing Arts","sgcool_label_text":"M.V.Gurusamy (b. 1920 in Seremban) was an accomplished percussionist and mridangam artiste as well as a renowned percussion teacher in Singapore. He arrived in Singapore and participated in the Indian classical music scene here. He was a member of the cultural contingent led by the then Minister for Culture, S. Rajaratnam, which visited and performed at various centres in Sarawak, Brunei and Sabah in 1965. He was the recipient of several titles including the Kala Ratna award given by the Singapore Indian Fine Arts Society in 1986."},"nlpDate":"20201119143405","connectorId":0,"tags":{}}