{"id":"2016-00363","title":"South Indian Necklaces A Pair of South Indian Necklaces m?nikka addigai and m?nga m?lai","source":"Bumblebee","path":"./Data/json/","content":"accession_no_csv:2016-00363\nImage:\nobject_work_type:necklaces chokers (necklaces)\ntitle_text:South Indian Necklaces A Pair of South Indian Necklaces m?nikka addigai and m?nga m?lai\npreference:main alternate main\ntitle_language:\ncreation_date:1801 - 1939\ncreation_place_original_location:India\n South\nstyles_periods_indexing_terms:Indian (South Asian)\ninscriptions:\ninscription_language:\nshape:U-shaped round (shape)\nmaterials_name:gold (metal) ruby (mineral) thread\ntechniques_name:metalworking jewellery making\nobject_colour:gold (colour)\nphysical_appearance:The image shows two types of jewellery. The one on the left has a tassel. The pendant attached to the strong comprises of numerous purple and grey round beads. The one on the right has a chain to be hooked and unhooked from the neck. It has numerous purle\n green\n and grey round beads that are shaped like teardrops. Floral patterns can be discerned from this necklace.\nsubject_terms_1:jewellery craftsmanship neck ornaments costume accessories floral patterns goldwork (visual works) neck ornaments\nsubject_terms_2:Ethnic jewellery Gold jewellery Workmanship Dress accessories Necklaces Goldwork\nsubject_terms_3:Jewellery\nsgcool_label_text:The m?nga m?lai (Tamil: Mango Garland or necklace) and the m?nikka Addigai (Tamil: Ruby Choker) are typical examples of Tamil necklaces\n both worn for celebratory occasions such as weddings and/or as part of dance costumes by bharatanatyam dancers. Nature inspired jewellery\n featuring flora and fauna were common in South India. The m?nga m?lai design can be traced as far back as the Chola period\n as seen in bronzes produced at the time. This pair of necklaces are important in many ways – they bear testimony to the socio-cultural heritage of Tamils in Singapore; they are also superior examples of Indian gold craftsmanship and of the material culture of Tamils in the region in the 19th/20th centuries.","createdDate":"20201119143405","version":0,"latest":false,"roles":[],"metadata":{"accession_no_csv":"2016-00363","Image":"","object_work_type":"necklaces chokers (necklaces)","title_text":"South Indian Necklaces A Pair of South Indian Necklaces m?nikka addigai and m?nga m?lai","preference":"main alternate main","title_language":"","creation_date":"1801 - 1939","creation_place_original_location":"India, South","styles_periods_indexing_terms":"Indian (South Asian)","inscriptions":"","inscription_language":"","shape":"U-shaped round (shape)","materials_name":"gold (metal) ruby (mineral) thread","techniques_name":"metalworking jewellery making","object_colour":"gold (colour)","physical_appearance":"The image shows two types of jewellery. The one on the left has a tassel. The pendant attached to the strong comprises of numerous purple and grey round beads. The one on the right has a chain to be hooked and unhooked from the neck. It has numerous purle, green, and grey round beads that are shaped like teardrops. Floral patterns can be discerned from this necklace.","subject_terms_1":"jewellery craftsmanship neck ornaments costume accessories floral patterns goldwork (visual works) neck ornaments","subject_terms_2":"Ethnic jewellery Gold jewellery Workmanship Dress accessories Necklaces Goldwork","subject_terms_3":"Jewellery","sgcool_label_text":"The m?nga m?lai (Tamil: Mango Garland or necklace) and the m?nikka Addigai (Tamil: Ruby Choker) are typical examples of Tamil necklaces, both worn for celebratory occasions such as weddings and/or as part of dance costumes by bharatanatyam dancers. Nature inspired jewellery, featuring flora and fauna were common in South India. The m?nga m?lai design can be traced as far back as the Chola period, as seen in bronzes produced at the time. This pair of necklaces are important in many ways – they bear testimony to the socio-cultural heritage of Tamils in Singapore; they are also superior examples of Indian gold craftsmanship and of the material culture of Tamils in the region in the 19th/20th centuries."},"nlpDate":"20201119143405","connectorId":0,"tags":{}}