{"id":"2016-00212-056","title":"Photograph album of views and portraits in the Punjab, Cashmere, Ceylon, Burma, Penang, Singapore, and Java Commercial Square, Singapore","source":"Bumblebee","path":"./Data/json/","content":"accession_no_csv:2016-00212-056\nImage:\nobject_work_type:black-and-white photographs\ntitle_text:Photograph album of views and portraits in the Punjab\n Cashmere\n Ceylon\n Burma\n Penang\n Singapore\n and Java Commercial Square\n Singapore\npreference:alternate main\ntitle_language:\ncreator_2:John Thomson\ncreator_1:Thomson\n J. (John)\n 1837-1921\ncreator_role:photographers\ncreation_date:before 28 Jul 1876\ncreation_place_original_location:Singapore\ninscriptions:\ninscription_language:\nshape:rectangular\nmaterials_name:albumen (egg white protein) albumen paper paper (fiber product)\ntechniques_name:albumen process\nobject_colour:black-and-white (colors)\nphysical_appearance:This is a photograph of Commercial Square in Singapore. The photograph shows a road\n with multi-storeyed buildings and shophouses on the right and trees on the left. There are vehicles along the road. There are a few people standing along the top balcony on the building on the right. The photograph is slightly faded around the edges. The title is written at the bottom\n below the photograph.\nsubject_terms_1:street scenes business districts squares (open spaces) colonization\nsubject_terms_2:Photographs Thomson\n J. (John)\n 1837-1921 Central business districts Singapore Colonization\nsubject_terms_3:Photography Commercial Square Raffles Place","createdDate":"20201018182635","version":0,"latest":false,"roles":[],"metadata":{"accession_no_csv":"2016-00212-056","Image":"","object_work_type":"black-and-white photographs","title_text":"Photograph album of views and portraits in the Punjab, Cashmere, Ceylon, Burma, Penang, Singapore, and Java Commercial Square, Singapore","preference":"alternate main","title_language":"","creator_2":"John Thomson","creator_1":"Thomson, J. (John), 1837-1921","creator_role":"photographers","creation_date":"before 28 Jul 1876","creation_place_original_location":"Singapore","inscriptions":"","inscription_language":"","shape":"rectangular","materials_name":"albumen (egg white protein) albumen paper paper (fiber product)","techniques_name":"albumen process","object_colour":"black-and-white (colors)","physical_appearance":"This is a photograph of Commercial Square in Singapore. The photograph shows a road, with multi-storeyed buildings and shophouses on the right and trees on the left. There are vehicles along the road. There are a few people standing along the top balcony on the building on the right. The photograph is slightly faded around the edges. The title is written at the bottom, below the photograph.","subject_terms_1":"street scenes business districts squares (open spaces) colonization","subject_terms_2":"Photographs Thomson, J. (John), 1837-1921 Central business districts Singapore Colonization","subject_terms_3":"Photography Commercial Square Raffles Place"},"nlpDate":"20201018182635","connectorId":0,"tags":{}}