{
  "id": "2016-00647",
  "title": "Altar cloth: Dewi Cina Bian Cai Tian goddess Altar cloth with Dewi Cina Bian Cai Tian goddess motif",
  "source": "Bumblebee",
  "path": "./Data/json/",
  "content": "\n  accession_no_csv: 2016-00647\n\n  Image: \n\n  object_work_type: batik art altar cloths\n\n  title_text: Altar cloth: Dewi Cina Bian Cai Tian goddess Altar cloth with Dewi Cina Bian Cai Tian goddess motif\n\n  preference: main alternate\n\n  title_language: \n\n  creation_date: 1900-1920\n\n  creation_place_original_location: Cirebon (Indonesia)\n\n  styles_periods_indexing_terms: Indonesian (culture or style)\n\n  inscriptions: \n\n  inscription_language: \n\n  shape: rectangular\n\n  materials_name: cotton (textile) natural dye\n\n  techniques_name: batik sewing (needleworking technique)\n\n  object_colour: multicolored\n\n  physical_appearance: This is an altar cloth. It has three horizontal panels. The lowest panel features the goddess Dewi Cina Bian Cai Tian\n seated playing the pipa\n a Chinese string instrument. Surrounding her are motifs of animals and figures. The middle panel features more stylized animals amongst foliage. The panels are bordered by fretwork.\n\n  subject_terms_1: deities Peranakan motifs Cantonese cultural diffusion\n\n  subject_terms_2: Altar-cloths Motifs Peranakan (Asian people) Culture diffusion Batik Gods\n\n  subject_terms_3: Religious life and practices Batik\n\n  sgcool_label_text: The goddess Dewi Cina Bian Cai Tian is shown on the lower panel of this tok wi or altar cloth.  This deity is adapted from Fujianese or Cantonese Buddhist folklore\n and is shown seated playing the pipa\n a Chinese string instrument.  Surrounding her are Chinese auspicious symbols\n aquatic animals and dancing celestial beings rendered in European style.  The two panels are bordered by fretwork\n possibly a variant of the banji pattern\n believed by the Chinese to contain talismanic properties.  This tok wi was likely produced in Cirebon\n a northern Javanese coastal town comprising a large population of Chinese.  The ‘cloud’ motif (megamendung) in particular\n is commonly associated with Cirebon.  It is derived from the Chinese auspicious ruyi cloud motif.  These cloths decorated the front of altar tables in homes and in some temples.  Instead of coloured silks or gold thread couchwork in imported Chinese examples\n batik altar cloths were more common in Java.\n",
  "createdDate": "20201201203308",
  "version": 0,
  "latest": false,
  "roles": [],
  "metadata": {
    "accession_no_csv": "2016-00647",
    "Image": "",
    "object_work_type": "batik art altar cloths",
    "title_text": "Altar cloth: Dewi Cina Bian Cai Tian goddess Altar cloth with Dewi Cina Bian Cai Tian goddess motif",
    "preference": "main alternate",
    "title_language": "",
    "creation_date": "1900-1920",
    "creation_place_original_location": "Cirebon (Indonesia)",
    "styles_periods_indexing_terms": "Indonesian (culture or style)",
    "inscriptions": "",
    "inscription_language": "",
    "shape": "rectangular",
    "materials_name": "cotton (textile) natural dye",
    "techniques_name": "batik sewing (needleworking technique)",
    "object_colour": "multicolored",
    "physical_appearance": "This is an altar cloth. It has three horizontal panels. The lowest panel features the goddess Dewi Cina Bian Cai Tian, seated playing the pipa, a Chinese string instrument. Surrounding her are motifs of animals and figures. The middle panel features more stylized animals amongst foliage. The panels are bordered by fretwork.",
    "subject_terms_1": "deities Peranakan motifs Cantonese cultural diffusion",
    "subject_terms_2": "Altar-cloths Motifs Peranakan (Asian people) Culture diffusion Batik Gods",
    "subject_terms_3": "Religious life and practices Batik",
    "sgcool_label_text": "The goddess Dewi Cina Bian Cai Tian is shown on the lower panel of this tok wi or altar cloth.  This deity is adapted from Fujianese or Cantonese Buddhist folklore, and is shown seated playing the pipa, a Chinese string instrument.  Surrounding her are Chinese auspicious symbols, aquatic animals and dancing celestial beings rendered in European style.  The two panels are bordered by fretwork, possibly a variant of the banji pattern, believed by the Chinese to contain talismanic properties.  This tok wi was likely produced in Cirebon, a northern Javanese coastal town comprising a large population of Chinese.  The ‘cloud’ motif (megamendung) in particular, is commonly associated with Cirebon.  It is derived from the Chinese auspicious ruyi cloud motif.  These cloths decorated the front of altar tables in homes and in some temples.  Instead of coloured silks or gold thread couchwork in imported Chinese examples, batik altar cloths were more common in Java."
  },
  "nlpDate": "20201201203308",
  "connectorId": 0,
  "tags": {}
}