{
  "id": "2016-00212-073",
  "title": "Photograph album of views and portraits in the Punjab, Cashmere, Ceylon, Burma, Penang, Singapore, and Java Gutta Percha Tree in the Gardens of the Governor General, Buitenzorg, Java",
  "source": "Bumblebee",
  "path": "./Data/json/",
  "content": "\n  accession_no_csv: 2016-00212-073\n\n  Image: \n\n  object_work_type: black-and-white photographs\n\n  title_text: Photograph album of views and portraits in the Punjab\n Cashmere\n Ceylon\n Burma\n Penang\n Singapore\n and Java Gutta Percha Tree in the Gardens of the Governor General\n Buitenzorg\n Java\n\n  preference: main alternate\n\n  title_language: \n\n  creator_2: John Thomson\n\n  creator_1: Thomson\n J. (John)\n 1837-1921\n\n  creator_role: photographers\n\n  creation_date: before 28 Jul 1876\n\n  creation_place_original_location: Bogor (Indonesia) Singapore\n\n  inscriptions: \n\n  inscription_language: \n\n  shape: rectangular\n\n  materials_name: albumen (egg white protein) paper (fiber product) albumen paper\n\n  techniques_name: albumen process\n\n  object_colour: black-and-white (colors)\n\n  physical_appearance: This is a photograph of the bark of a Gutta percha tree by a water body. The thick bark of the tree\n with numerous hanging roots\n is on the left foreground of the photograph. The edges of the photograph are curved. The title is handwritten at the bottom\n below the photograph.\n\n  subject_terms_1: trees Palaquium (genus)\n\n  subject_terms_2: Gutta-percha Bogor (Indonesia) Photographs Thomson\n J. (John)\n 1837-1921 Istana Bogor (Bogor\n Indonesia)\n\n  subject_terms_3: Photography Parks and gardens\n",
  "createdDate": "20201125084536",
  "version": 0,
  "latest": false,
  "roles": [],
  "metadata": {
    "accession_no_csv": "2016-00212-073",
    "Image": "",
    "object_work_type": "black-and-white photographs",
    "title_text": "Photograph album of views and portraits in the Punjab, Cashmere, Ceylon, Burma, Penang, Singapore, and Java Gutta Percha Tree in the Gardens of the Governor General, Buitenzorg, Java",
    "preference": "main alternate",
    "title_language": "",
    "creator_2": "John Thomson",
    "creator_1": "Thomson, J. (John), 1837-1921",
    "creator_role": "photographers",
    "creation_date": "before 28 Jul 1876",
    "creation_place_original_location": "Bogor (Indonesia) Singapore",
    "inscriptions": "",
    "inscription_language": "",
    "shape": "rectangular",
    "materials_name": "albumen (egg white protein) paper (fiber product) albumen paper",
    "techniques_name": "albumen process",
    "object_colour": "black-and-white (colors)",
    "physical_appearance": "This is a photograph of the bark of a Gutta percha tree by a water body. The thick bark of the tree, with numerous hanging roots, is on the left foreground of the photograph. The edges of the photograph are curved. The title is handwritten at the bottom, below the photograph.",
    "subject_terms_1": "trees Palaquium (genus)",
    "subject_terms_2": "Gutta-percha Bogor (Indonesia) Photographs Thomson, J. (John), 1837-1921 Istana Bogor (Bogor, Indonesia)",
    "subject_terms_3": "Photography Parks and gardens"
  },
  "nlpDate": "20201125084536",
  "connectorId": 0,
  "tags": {}
}