{"id":"2016-00663","title":"Grain focusing scope with instructions manual","source":"Bumblebee","path":"./Data/json/","content":"accession_no_csv:2016-00663\nImage:\nobject_work_type:photograph viewing equipment buyers\\u0027 guides packaging\ntitle_text:Grain focusing scope with instructions manual\npreference:main\ntitle_language:\ncreator_2:Bestwell Optical \\u0026 Instrument Corporation P.O. Box 396 Merrick\n N.Y. 11566\ncreator_role:manufacturers\ncreation_date:1980s-1990s\ncreation_place_original_location:Singapore United States\ninscriptions:\ninscription_language:\nshape:irregular\nmaterials_name:plastic (organic material) paper (fiber product)\ntechniques_name:forming (physical activity) colour printing\nobject_colour:multicoloured\nphysical_appearance:The grain focusing scope has a blue body. It comes in a paper box that is white and has blue outlines. The packaging on the box displays the words \\u0027mini sight\\u0027 as well as \\u0027grain focusing for super sharp enlargements\\u0027. It also displays the words \\u0027high performance\\u0027 at its top. The address and name of the manufacturer\n Bestwell Optical \\u0026 Instrument Corporation\n is displayed at the top left hand corner of the instruction manual. Also\n there are four images of the grain focuser\n drawn at different angles\n labelled \\u0027A\\u0027 to \\u0027D\\u0027. A brief description corresponding to each letter is stated in the buyers\\u0027 guide as well\n in single paragraphs.\nsubject_terms_1:photographic processing equipment tools manuals (instructional materials)\nsubject_terms_2:Photography Equipment and supplies Tools Handbooks and manuals Packaging\nsubject_terms_3:Photography\ncontext_20:The set of equipment was used by The Picture Farm Pte Ltd\ncontext_21:45 Jalan Pemimpin\n #09-00 Foo Wah Industrial Building\n Thomson\n Singapore\ncontext_22:1970 - present\ncontext_23:1970\ncontext_24:present\nsgcool_label_text:A grain focuser is a tool used to fine tune the focus of the grains of the negative in photographic film processing. This grain focuser is part of the darkroom photography equipment that was previously used by The Picture Farm\n which was set up by the renowned photographer Willie Tang.","createdDate":"20201119143405","version":0,"latest":false,"roles":[],"metadata":{"accession_no_csv":"2016-00663","Image":"","object_work_type":"photograph viewing equipment buyers\u0027 guides packaging","title_text":"Grain focusing scope with instructions manual","preference":"main","title_language":"","creator_2":"Bestwell Optical \u0026 Instrument Corporation P.O. Box 396 Merrick, N.Y. 11566","creator_role":"manufacturers","creation_date":"1980s-1990s","creation_place_original_location":"Singapore United States","inscriptions":"","inscription_language":"","shape":"irregular","materials_name":"plastic (organic material) paper (fiber product)","techniques_name":"forming (physical activity) colour printing","object_colour":"multicoloured","physical_appearance":"The grain focusing scope has a blue body. It comes in a paper box that is white and has blue outlines. The packaging on the box displays the words \u0027mini sight\u0027 as well as \u0027grain focusing for super sharp enlargements\u0027. It also displays the words \u0027high performance\u0027 at its top. The address and name of the manufacturer, Bestwell Optical \u0026 Instrument Corporation, is displayed at the top left hand corner of the instruction manual. Also, there are four images of the grain focuser, drawn at different angles, labelled \u0027A\u0027 to \u0027D\u0027. A brief description corresponding to each letter is stated in the buyers\u0027 guide as well, in single paragraphs.","subject_terms_1":"photographic processing equipment tools manuals (instructional materials)","subject_terms_2":"Photography Equipment and supplies Tools Handbooks and manuals Packaging","subject_terms_3":"Photography","context_20":"The set of equipment was used by The Picture Farm Pte Ltd","context_21":"45 Jalan Pemimpin, #09-00 Foo Wah Industrial Building, Thomson, Singapore","context_22":"1970 - present","context_23":"1970","context_24":"present","sgcool_label_text":"A grain focuser is a tool used to fine tune the focus of the grains of the negative in photographic film processing. This grain focuser is part of the darkroom photography equipment that was previously used by The Picture Farm, which was set up by the renowned photographer Willie Tang."},"nlpDate":"20201119143405","connectorId":0,"tags":{}}