{"id":"2016-00609-002","title":"Performance at Tank Road temple #2 4 photographs of  performances at Tank Road temple","source":"Bumblebee","path":"./Data/json/","content":"accession_no_csv:2016-00609-002\nImage:\nobject_work_type:black-and-white photographs\ntitle_text:Performance at Tank Road temple #2 4 photographs of  performances at Tank Road temple\npreference:main alternate\ntitle_language:\ncreation_date:1970s-1990s\ncreation_place_original_location:Singapore\nstyles_periods_indexing_terms:Indian (South Asian)\ninscriptions:\ninscription_language:\nshape:rectangular\nmaterials_name:paper (fiber product)\ntechniques_name:printing (process) photographic processes\nobject_colour:grey monochrome\nphysical_appearance:The image shows a rectangular photograph that is in black-and-white. The photograph features five males and one female. They are all sitting down on a raised platform that is covered with a carpet. There is a microphone stand close to the seated lady. The males are playing a number of different musical instruments\n such as the violin\n sitar\n harmonium\n and tabla. The background of the photograph displays a framed picture of a Hindu deity. The background of the photograph suggests that this was taken in the interior of a building.\nsubject_terms_1:musicians music (performing arts) singers musical performances temples (buidings) stages (performance spaces)\nsubject_terms_2:Black-and-white photography Musicians Carnatic music Singers Performances Hindu temples Tamil (Indic people)\nsubject_terms_3:Photography Indian music Performing Arts Temples Sri Thendayuthapani Temple Tank Road Musicians\nsgcool_label_text:Mr. S Gopalakrishnan (b. in 1920 in Tanjavur) was a prominent violinist\n and Carnatic singer. He arrived in Singapore in 1939 and actively participated in the Indian classical music scene here. Mr Gopalakrishnan performed alongside veterans of classical performers such as Pandit M Ramalingam and MV Gurusamy at temple and other music festivals. He also taught violin lessons at the Singapore Malayalee Association from the 1970s to 2000s. He was a member of the Tamils Reform Association and performed his wedding according to the principles of the Self-Respect Movement. He was also employed as a compositor at the Far East Air Force from 1954 to 1970.","createdDate":"20201119143405","version":0,"latest":false,"roles":[],"metadata":{"accession_no_csv":"2016-00609-002","Image":"","object_work_type":"black-and-white photographs","title_text":"Performance at Tank Road temple #2 4 photographs of  performances at Tank Road temple","preference":"main alternate","title_language":"","creation_date":"1970s-1990s","creation_place_original_location":"Singapore","styles_periods_indexing_terms":"Indian (South Asian)","inscriptions":"","inscription_language":"","shape":"rectangular","materials_name":"paper (fiber product)","techniques_name":"printing (process) photographic processes","object_colour":"grey monochrome","physical_appearance":"The image shows a rectangular photograph that is in black-and-white. The photograph features five males and one female. They are all sitting down on a raised platform that is covered with a carpet. There is a microphone stand close to the seated lady. The males are playing a number of different musical instruments, such as the violin, sitar, harmonium, and tabla. The background of the photograph displays a framed picture of a Hindu deity. The background of the photograph suggests that this was taken in the interior of a building.","subject_terms_1":"musicians music (performing arts) singers musical performances temples (buidings) stages (performance spaces)","subject_terms_2":"Black-and-white photography Musicians Carnatic music Singers Performances Hindu temples Tamil (Indic people)","subject_terms_3":"Photography Indian music Performing Arts Temples Sri Thendayuthapani Temple Tank Road Musicians","sgcool_label_text":"Mr. S Gopalakrishnan (b. in 1920 in Tanjavur) was a prominent violinist, and Carnatic singer. He arrived in Singapore in 1939 and actively participated in the Indian classical music scene here. Mr Gopalakrishnan performed alongside veterans of classical performers such as Pandit M Ramalingam and MV Gurusamy at temple and other music festivals. He also taught violin lessons at the Singapore Malayalee Association from the 1970s to 2000s. He was a member of the Tamils Reform Association and performed his wedding according to the principles of the Self-Respect Movement. He was also employed as a compositor at the Far East Air Force from 1954 to 1970."},"nlpDate":"20201119143405","connectorId":0,"tags":{}}