{"id":"2016-00494","title":"Untitled (ceiling)","source":"Bumblebee","path":"./Data/json/","content":"accession_no_csv:2016-00494\nImage:\nobject_work_type:black-and-white photographs\ntitle_text:Untitled (ceiling)\npreference:main\ntitle_language:\ncreator_2:Kwek Leng Joo Swan and Maclaren Architects\ncreator_1:Kwek\n Leng Joo Swan \\u0026 Maclaren\ncreator_role:photographers designers\ncreation_date:2010\ncreation_place_original_location:Singapore Malaysia\ninscriptions:\ninscription_language:\nshape:rectangular\nmaterials_name:paper (fiber product)\ntechniques_name:printing (process)\nobject_colour:grey monochrome\nphysical_appearance:The image shows a photograph in black-and-white. It has a black frame and its border is white in colour. The ceiling is white in colour and it has rectilinear lines running vertically and horizontally. Inside each big rectangle\n there are geometric motifs to form the shape of squares. Two squares are superimposed on one other\n with the one in below having a different orientation than the one on top. This allows for a figure that is similar to an eight-sided star to be displayed. Towards the bottom right hand side of the image\n there seems to be some cracks or chips on the white wall.\nsubject_terms_1:porticoes ceilings Art Deco Neoclassical geometric motifs\nsubject_terms_2:Black-and-white photography Motifs Art deco (Architecture) Neoclassicism (Architecture) Porticoes Ceilings Tanjong Pagar (Singapore) Pertadbiran Keretapi Tanah Melayu\nsubject_terms_3:Rail transport Tanjong Pagar Railway Station Pertadbiran Keretapi Tanah Melayu Photography Rail transport (Stations)\nsgcool_label_text:\\This image shows the Art Deco and neo-classical styles of the Tanjong Pagar railway station\n which it was known for. Designed by Swan and Maclaren\n the entrance of the station is sheltered by an arched portico. This image is part of the \\\\Tracking Memories\\\\ collection by the late Mr Kwek Leng Joo. The collection captures different aspects of the Malayan Railway story in Singapore","createdDate":"20201018182635","version":0,"latest":false,"roles":[],"metadata":{"accession_no_csv":"2016-00494","Image":"","object_work_type":"black-and-white photographs","title_text":"Untitled (ceiling)","preference":"main","title_language":"","creator_2":"Kwek Leng Joo Swan and Maclaren Architects","creator_1":"Kwek, Leng Joo Swan \u0026 Maclaren","creator_role":"photographers designers","creation_date":"2010","creation_place_original_location":"Singapore Malaysia","inscriptions":"","inscription_language":"","shape":"rectangular","materials_name":"paper (fiber product)","techniques_name":"printing (process)","object_colour":"grey monochrome","physical_appearance":"The image shows a photograph in black-and-white. It has a black frame and its border is white in colour. The ceiling is white in colour and it has rectilinear lines running vertically and horizontally. Inside each big rectangle, there are geometric motifs to form the shape of squares. Two squares are superimposed on one other, with the one in below having a different orientation than the one on top. This allows for a figure that is similar to an eight-sided star to be displayed. Towards the bottom right hand side of the image, there seems to be some cracks or chips on the white wall.","subject_terms_1":"porticoes ceilings Art Deco Neoclassical geometric motifs","subject_terms_2":"Black-and-white photography Motifs Art deco (Architecture) Neoclassicism (Architecture) Porticoes Ceilings Tanjong Pagar (Singapore) Pertadbiran Keretapi Tanah Melayu","subject_terms_3":"Rail transport Tanjong Pagar Railway Station Pertadbiran Keretapi Tanah Melayu Photography Rail transport (Stations)","sgcool_label_text":"\"This image shows the Art Deco and neo-classical styles of the Tanjong Pagar railway station, which it was known for. Designed by Swan and Maclaren, the entrance of the station is sheltered by an arched portico. This image is part of the \"\"Tracking Memories\"\" collection by the late Mr Kwek Leng Joo. The collection captures different aspects of the Malayan Railway story in Singapore"},"nlpDate":"20201018182635","connectorId":0,"tags":{}}