{
  "id": "2016-00138",
  "title": "Orange cheongsam with floral prints",
  "source": "Bumblebee",
  "path": "./Data/json/",
  "content": "\n  accession_no_csv: 2016-00138\n\n  Image: \n\n  object_work_type: folk costume\n\n  title_text: Orange cheongsam with floral prints\n\n  preference: main\n\n  title_language: \n\n  creation_date: Not indicated\n\n  creation_place_original_location: Singapore\n\n  styles_periods_indexing_terms: Chinese (culture or style)\n\n  inscriptions: \n\n  inscription_language: \n\n  shape: irregular\n\n  materials_name: cloth\n\n  techniques_name: machine sewing (technique)\n\n  object_colour: multicoloured\n\n  physical_appearance: This is an orange cheongsam and it is sleeveless. There is a collar present as well. There are no visible tears on the exterior of the cheongsam. There are red\n light oranger\n and purple coloured floral motifs appearing all over the cheongsam. They come in different shapes and sizes. The piping of the cheongsam runs from the collar to its left side\n just below its left arm hole.\n\n  subject_terms_1: dresses (garments) womenswear floral patterns allover patterns\n\n  subject_terms_2: Qipao Ethnic costume Women\\u0027s clothing Motifs\n\n  subject_terms_3: Ethnic costume Chinese costume\n\n  sgcool_label_text: This is a sleeveless orange cheongsam with pink\n brown and green floral prints. This cheongsam was wore by Mrs Lee In Tong in her younger days.\n",
  "createdDate": "20201120223706",
  "version": 0,
  "latest": false,
  "roles": [],
  "metadata": {
    "accession_no_csv": "2016-00138",
    "Image": "",
    "object_work_type": "folk costume",
    "title_text": "Orange cheongsam with floral prints",
    "preference": "main",
    "title_language": "",
    "creation_date": "Not indicated",
    "creation_place_original_location": "Singapore",
    "styles_periods_indexing_terms": "Chinese (culture or style)",
    "inscriptions": "",
    "inscription_language": "",
    "shape": "irregular",
    "materials_name": "cloth",
    "techniques_name": "machine sewing (technique)",
    "object_colour": "multicoloured",
    "physical_appearance": "This is an orange cheongsam and it is sleeveless. There is a collar present as well. There are no visible tears on the exterior of the cheongsam. There are red, light oranger, and purple coloured floral motifs appearing all over the cheongsam. They come in different shapes and sizes. The piping of the cheongsam runs from the collar to its left side, just below its left arm hole.",
    "subject_terms_1": "dresses (garments) womenswear floral patterns allover patterns",
    "subject_terms_2": "Qipao Ethnic costume Women\u0027s clothing Motifs",
    "subject_terms_3": "Ethnic costume Chinese costume",
    "sgcool_label_text": "This is a sleeveless orange cheongsam with pink, brown and green floral prints. This cheongsam was wore by Mrs Lee In Tong in her younger days."
  },
  "nlpDate": "20201120223706",
  "connectorId": 0,
  "tags": {}
}