{
  "id": "2016-00606",
  "title": "MV Gurusamy, Pandit Ramalingam and his son and S Gopalakrishnan Promotional shot of MV Gurusamy, Pandit Ramalingam and his son and S Gopalakrishnan",
  "source": "Bumblebee",
  "path": "./Data/json/",
  "content": "\n  accession_no_csv: 2016-00606\n\n  Image: \n\n  object_work_type: black-and-white photographs\n\n  title_text: MV Gurusamy\n Pandit Ramalingam and his son and S Gopalakrishnan Promotional shot of MV Gurusamy\n Pandit Ramalingam and his son and S Gopalakrishnan\n\n  preference: main alternate\n\n  title_language: \n\n  creation_date: 1950 - 1953\n\n  creation_place_original_location: Singapore\n\n  inscriptions: \n\n  inscription_language: \n\n  shape: rectangular\n\n  materials_name: paper (fiber product)\n\n  techniques_name: printing (process) photographic processes\n\n  object_colour: grey monochrome\n\n  physical_appearance: The image shows a rectangular photograph that is in black-and-white. The photograph features three adult males and a boy who are all sitting on the ground. The boy is holding a sitar and has propped it upright on his lap. The man to the left of the image has a dholak in both hands\n while the man to the right has a violin. All of them are fully dressed in clothes that are white in colour.\n\n  subject_terms_1: musicians musical instruments music (performing arts)\n\n  subject_terms_2: Music Musicians Musical instruments Black-and-white photography\n\n  subject_terms_3: Photography Indian music Musicians\n\n  sgcool_label_text: Mr. S Gopalakrishnan (b. in 1920 in Tanjavur) was a prominent violinist\n and Carnatic singer. He arrived in Singapore in 1939 and actively participated in the Indian classical music scene here. Mr Gopalakrishnan performed alongside veterans of classical performers such as Pandit M Ramalingam and MV Gurusamy at temple and other music festivals. He also taught violin lessons at the Singapore Malayalee Association from the 1970s to 2000s. He was a member of the Tamils Reform Association and performed his wedding according to the principles of the Self-Respect Movement. He was also employed as a compositor at the Far East Air Force from 1954 to 1970\n",
  "createdDate": "20201201203308",
  "version": 0,
  "latest": false,
  "roles": [],
  "metadata": {
    "accession_no_csv": "2016-00606",
    "Image": "",
    "object_work_type": "black-and-white photographs",
    "title_text": "MV Gurusamy, Pandit Ramalingam and his son and S Gopalakrishnan Promotional shot of MV Gurusamy, Pandit Ramalingam and his son and S Gopalakrishnan",
    "preference": "main alternate",
    "title_language": "",
    "creation_date": "1950 - 1953",
    "creation_place_original_location": "Singapore",
    "inscriptions": "",
    "inscription_language": "",
    "shape": "rectangular",
    "materials_name": "paper (fiber product)",
    "techniques_name": "printing (process) photographic processes",
    "object_colour": "grey monochrome",
    "physical_appearance": "The image shows a rectangular photograph that is in black-and-white. The photograph features three adult males and a boy who are all sitting on the ground. The boy is holding a sitar and has propped it upright on his lap. The man to the left of the image has a dholak in both hands, while the man to the right has a violin. All of them are fully dressed in clothes that are white in colour.",
    "subject_terms_1": "musicians musical instruments music (performing arts)",
    "subject_terms_2": "Music Musicians Musical instruments Black-and-white photography",
    "subject_terms_3": "Photography Indian music Musicians",
    "sgcool_label_text": "Mr. S Gopalakrishnan (b. in 1920 in Tanjavur) was a prominent violinist, and Carnatic singer. He arrived in Singapore in 1939 and actively participated in the Indian classical music scene here. Mr Gopalakrishnan performed alongside veterans of classical performers such as Pandit M Ramalingam and MV Gurusamy at temple and other music festivals. He also taught violin lessons at the Singapore Malayalee Association from the 1970s to 2000s. He was a member of the Tamils Reform Association and performed his wedding according to the principles of the Self-Respect Movement. He was also employed as a compositor at the Far East Air Force from 1954 to 1970"
  },
  "nlpDate": "20201201203308",
  "connectorId": 0,
  "tags": {}
}