{"id":"2016-00171","title":"Purple cheongsam with gold trimming and floral motif","source":"Bumblebee","path":"./Data/json/","content":"accession_no_csv:2016-00171\nImage:\nobject_work_type:folk costume womenswear\ntitle_text:Purple cheongsam with gold trimming and floral motif\npreference:main\ntitle_language:\ncreator_2:\ncreation_date:1900 - 1969\ncreation_place_original_location:Singapore\nstyles_periods_indexing_terms:Chinese (culture or style)\ninscriptions:\ninscription_language:\nshape:irregular\nmaterials_name:silk (textile) piping (trimming)\ntechniques_name:machine sewing (technique) piping (process)\nobject_colour:multicoloured\nphysical_appearance:This is a long-sleeved cheongsam that is predominantly purple in colour. The trimming is gold and the piping is turquoise in colour. There are floral patterns all over the cheongsam. There is a collar present as well. The cheongsam does not look worn out and there are no visible tears on it. There is also a slit on the right side of the costume.\nsubject_terms_1:floral patterns geometric motifs dtresses (garments)\nsubject_terms_2:Qipao Ethnic costume Motifs Women\\u0027s clothing\nsubject_terms_3:Ethnic costume Chinese costume\nsgcool_label_text:This ankle-length cheongsam with long sleeves has gold trimming and turquoise piping. The cheongsam also has turquoise floral and geometric motifs. The joints slightly visible at the centre front and back of the cheongsam reveal that it was likely made in the early 20th century as the width of the fabric then had limitations.","createdDate":"20201018182635","version":0,"latest":false,"roles":[],"metadata":{"accession_no_csv":"2016-00171","Image":"","object_work_type":"folk costume womenswear","title_text":"Purple cheongsam with gold trimming and floral motif","preference":"main","title_language":"","creator_2":"","creation_date":"1900 - 1969","creation_place_original_location":"Singapore","styles_periods_indexing_terms":"Chinese (culture or style)","inscriptions":"","inscription_language":"","shape":"irregular","materials_name":"silk (textile) piping (trimming)","techniques_name":"machine sewing (technique) piping (process)","object_colour":"multicoloured","physical_appearance":"This is a long-sleeved cheongsam that is predominantly purple in colour. The trimming is gold and the piping is turquoise in colour. There are floral patterns all over the cheongsam. There is a collar present as well. The cheongsam does not look worn out and there are no visible tears on it. There is also a slit on the right side of the costume.","subject_terms_1":"floral patterns geometric motifs dtresses (garments)","subject_terms_2":"Qipao Ethnic costume Motifs Women\u0027s clothing","subject_terms_3":"Ethnic costume Chinese costume","sgcool_label_text":"This ankle-length cheongsam with long sleeves has gold trimming and turquoise piping. The cheongsam also has turquoise floral and geometric motifs. The joints slightly visible at the centre front and back of the cheongsam reveal that it was likely made in the early 20th century as the width of the fabric then had limitations."},"nlpDate":"20201018182635","connectorId":0,"tags":{}}