{
  "id": "2016-00650",
  "title": "Celanda batik tulis (man’s pyjama pants)",
  "source": "Bumblebee",
  "path": "./Data/json/",
  "content": "\n  accession_no_csv: 2016-00650\n\n  Image: \n\n  object_work_type: batik art pajamas\n\n  title_text: Celanda batik tulis (man’s pyjama pants)\n\n  preference: main\n\n  title_language: \n\n  creation_date: 1930\n\n  creation_place_original_location: Pekalongan (Indonesia)\n\n  inscriptions: \n\n  inscription_language: \n\n  shape: irregular\n\n  materials_name: cotton (textile) natural dye\n\n  techniques_name: batik sewing (needleworking technique)\n\n  object_colour: multicolored\n\n  physical_appearance: This is a pair of batik pants. It has a symmetrical pattern of tendril-like blue flowering stems\n against a background of diagonal rows of black wavy lines. The rows of black lines are alternated with blue borders of white diamond-shaped motifs. The bottom of the pants are bordered my floral patterns on a blue background.\n\n  subject_terms_1: flowers (motifs) Peranakan lozenges cultural diffusion\n\n  subject_terms_2: Motifs Culture diffusion Peranakan (Asian people) Batik Pajamas\n\n  subject_terms_3: Batik\n\n  sgcool_label_text: This pair of batik pants contains a symmetrical pattern of tendril-like blue flowering stems.  They are set against a background of diagonal rows of black wavy lines that are framed by blue borders of white diamond-shaped motifs.  The batik cloth is carefully cut and joined in the middle to produce the symmetry of pattern.  Beginning in the 19th century\n batik was used to produce tailored garments.  For European men\n batik pyjama (celanda) trousers and sarong (for informal wear) became common as the Europeans adapted to the weather and lifestyle in Southeast Asia.  Children’s celanda were often tailored from used adult batik.\n",
  "createdDate": "20201201203308",
  "version": 0,
  "latest": false,
  "roles": [],
  "metadata": {
    "accession_no_csv": "2016-00650",
    "Image": "",
    "object_work_type": "batik art pajamas",
    "title_text": "Celanda batik tulis (man’s pyjama pants)",
    "preference": "main",
    "title_language": "",
    "creation_date": "1930",
    "creation_place_original_location": "Pekalongan (Indonesia)",
    "inscriptions": "",
    "inscription_language": "",
    "shape": "irregular",
    "materials_name": "cotton (textile) natural dye",
    "techniques_name": "batik sewing (needleworking technique)",
    "object_colour": "multicolored",
    "physical_appearance": "This is a pair of batik pants. It has a symmetrical pattern of tendril-like blue flowering stems, against a background of diagonal rows of black wavy lines. The rows of black lines are alternated with blue borders of white diamond-shaped motifs. The bottom of the pants are bordered my floral patterns on a blue background.",
    "subject_terms_1": "flowers (motifs) Peranakan lozenges cultural diffusion",
    "subject_terms_2": "Motifs Culture diffusion Peranakan (Asian people) Batik Pajamas",
    "subject_terms_3": "Batik",
    "sgcool_label_text": "This pair of batik pants contains a symmetrical pattern of tendril-like blue flowering stems.  They are set against a background of diagonal rows of black wavy lines that are framed by blue borders of white diamond-shaped motifs.  The batik cloth is carefully cut and joined in the middle to produce the symmetry of pattern.  Beginning in the 19th century, batik was used to produce tailored garments.  For European men, batik pyjama (celanda) trousers and sarong (for informal wear) became common as the Europeans adapted to the weather and lifestyle in Southeast Asia.  Children’s celanda were often tailored from used adult batik."
  },
  "nlpDate": "20201201203308",
  "connectorId": 0,
  "tags": {}
}