{
  "id": "2016-00405\r\n2016-00406\r\n2016-00407\r\n2016-00408\r\n2016-00409",
  "title": "Kopitiam (coffee shop) chair #1 - # 5",
  "source": "Bumblebee",
  "path": "./Data/json/",
  "content": "\n  accession_no_csv: 2016-00405\\r\\n2016-00406\\r\\n2016-00407\\r\\n2016-00408\\r\\n2016-00409\n\n  Image: \n\n  object_work_type: dining chairs chairs (furniture forms)\n\n  title_text: Kopitiam (coffee shop) chair #1 - # 5\n\n  preference: main\n\n  title_language: \n\n  creation_date: 1960s\n\n  creation_place_original_location: Czechoslovakia Singapore\n\n  inscriptions: \n\n  inscription_language: \n\n  shape: irregular\n\n  materials_name: plywood wood (plant material) bentwood\n\n  techniques_name: forming (physical activity)\n\n  object_colour: brown (colour)\n\n  physical_appearance: This is a set of five coffee shop chairs. They are wooden and brown in colour. All of them have a back but no arms. The chairs have a round seat. Each chair comprises of four legs with a circular spindle underneath the seat. There are no decorative motifs on the spindles\n legs\n and rails. Four of the chairs have geometric motifs visible on their seats\n while the last one has floral patterns instead. The chairs also have rails that connect the lower rail to the round seat.\n\n  subject_terms_1: geometric motifs coffee shops floral patterns portable furniture\n\n  subject_terms_2: Motifs Chairs Coffee shops\n\n  sgcool_label_text: In Singapore\n the kopitiam or coffee shop is a place where people meet\n socialise\n chit-chat and gossip over a cup of freshly-brewed coffee\n half-boiled eggs and kaya toast. From the 1950s to the 1980s\n the kopitiam had its signature ubiquitous furniture set\n comprising a wooden table with marble table top and wooden chairs with round seats. The old chairs were\n and are still made in Czechoslovakia. The first kopitiam chairs arrived in Singapore in the late 1930s. Made from pliable and hardy wood\n the chair is characterised by a contoured spindle back and moulded plywood seat\n using the bentwood technique that was invented by Michael Thonet in the 1830s. It is believed that the seats were knocked down and flat-packed before being shipped in bulk so as to lower freight costs. They were then assembled and varnished in workshops\n locally branded and sold. Some of these chairs also have decorative motifs on the seats. These durable chairs have been mostly replaced by plastic chairs and stools which are lightweight\n and can therefore be moved around easily and stacked to save space in the kopitiam.\n",
  "createdDate": "20201125084535",
  "version": 0,
  "latest": false,
  "roles": [],
  "metadata": {
    "accession_no_csv": "2016-00405\r\n2016-00406\r\n2016-00407\r\n2016-00408\r\n2016-00409",
    "Image": "",
    "object_work_type": "dining chairs chairs (furniture forms)",
    "title_text": "Kopitiam (coffee shop) chair #1 - # 5",
    "preference": "main",
    "title_language": "",
    "creation_date": "1960s",
    "creation_place_original_location": "Czechoslovakia Singapore",
    "inscriptions": "",
    "inscription_language": "",
    "shape": "irregular",
    "materials_name": "plywood wood (plant material) bentwood",
    "techniques_name": "forming (physical activity)",
    "object_colour": "brown (colour)",
    "physical_appearance": "This is a set of five coffee shop chairs. They are wooden and brown in colour. All of them have a back but no arms. The chairs have a round seat. Each chair comprises of four legs with a circular spindle underneath the seat. There are no decorative motifs on the spindles, legs, and rails. Four of the chairs have geometric motifs visible on their seats, while the last one has floral patterns instead. The chairs also have rails that connect the lower rail to the round seat.",
    "subject_terms_1": "geometric motifs coffee shops floral patterns portable furniture",
    "subject_terms_2": "Motifs Chairs Coffee shops",
    "sgcool_label_text": "In Singapore, the kopitiam or coffee shop is a place where people meet, socialise, chit-chat and gossip over a cup of freshly-brewed coffee, half-boiled eggs and kaya toast. From the 1950s to the 1980s, the kopitiam had its signature ubiquitous furniture set, comprising a wooden table with marble table top and wooden chairs with round seats. The old chairs were, and are still made in Czechoslovakia. The first kopitiam chairs arrived in Singapore in the late 1930s. Made from pliable and hardy wood, the chair is characterised by a contoured spindle back and moulded plywood seat, using the bentwood technique that was invented by Michael Thonet in the 1830s. It is believed that the seats were knocked down and flat-packed before being shipped in bulk so as to lower freight costs. They were then assembled and varnished in workshops, locally branded and sold. Some of these chairs also have decorative motifs on the seats. These durable chairs have been mostly replaced by plastic chairs and stools which are lightweight, and can therefore be moved around easily and stacked to save space in the kopitiam."
  },
  "nlpDate": "20201125084535",
  "connectorId": 0,
  "tags": {}
}