{
  "id": "2016-00212-034",
  "title": "Shwedagon Pagoda, Rangoon Photograph album of views and portraits in the Punjab, Cashmere, Ceylon, Burma, Penang, Singapore, and Java",
  "source": "Bumblebee",
  "path": "./Data/json/",
  "content": "\n  accession_no_csv: 2016-00212-034\n\n  Image: \n\n  object_work_type: black-and-white photographs\n\n  title_text: Shwedagon Pagoda\n Rangoon Photograph album of views and portraits in the Punjab\n Cashmere\n Ceylon\n Burma\n Penang\n Singapore\n and Java\n\n  preference: main alternate\n\n  title_language: \n\n  creator_2: John Thomson\n\n  creator_1: Thomson\n J. (John)\n 1837-1921\n\n  creator_role: photographers\n\n  creation_date: before 28 Jul 1876\n\n  creation_place_original_location: Singapore Rangoon (Burma)\n\n  inscriptions: \n\n  inscription_language: \n\n  shape: rectangular\n\n  materials_name: albumen (egg white protein) paper (fiber product) albumen paper\n\n  techniques_name: albumen process\n\n  object_colour: black-and-white (colors)\n\n  physical_appearance: This is a photograph of the Shwedagon Pagoda in Rangoon\n Burma. The photograph features the top of the Stupa in the background. On the right of the photograph\n there are several roofed pagodas amongst tall trees. The pagodas look slightly worn down. There is a small clearing on the bottom-right of the photograph\n with a small man-made structure. The title is written at the bottom\n below the photograph.\n\n  subject_terms_1: scenery (landscape) Buddhism religious structures stupas pagodas (buildings)\n\n  subject_terms_2: Buddhism Photographs Stupas Thomson\n J. (John)\n 1837-1921 Rangoon (Burma) Pagodas Rvhe ti gum? Ce ti? to? (Rangoon\n Burma)\n\n  subject_terms_3: Landscape photography Buddhism Religious buildings\n",
  "createdDate": "20201201203309",
  "version": 0,
  "latest": false,
  "roles": [],
  "metadata": {
    "accession_no_csv": "2016-00212-034",
    "Image": "",
    "object_work_type": "black-and-white photographs",
    "title_text": "Shwedagon Pagoda, Rangoon Photograph album of views and portraits in the Punjab, Cashmere, Ceylon, Burma, Penang, Singapore, and Java",
    "preference": "main alternate",
    "title_language": "",
    "creator_2": "John Thomson",
    "creator_1": "Thomson, J. (John), 1837-1921",
    "creator_role": "photographers",
    "creation_date": "before 28 Jul 1876",
    "creation_place_original_location": "Singapore Rangoon (Burma)",
    "inscriptions": "",
    "inscription_language": "",
    "shape": "rectangular",
    "materials_name": "albumen (egg white protein) paper (fiber product) albumen paper",
    "techniques_name": "albumen process",
    "object_colour": "black-and-white (colors)",
    "physical_appearance": "This is a photograph of the Shwedagon Pagoda in Rangoon, Burma. The photograph features the top of the Stupa in the background. On the right of the photograph, there are several roofed pagodas amongst tall trees. The pagodas look slightly worn down. There is a small clearing on the bottom-right of the photograph, with a small man-made structure. The title is written at the bottom, below the photograph.",
    "subject_terms_1": "scenery (landscape) Buddhism religious structures stupas pagodas (buildings)",
    "subject_terms_2": "Buddhism Photographs Stupas Thomson, J. (John), 1837-1921 Rangoon (Burma) Pagodas Rvhe ti gum? Ce ti? to? (Rangoon, Burma)",
    "subject_terms_3": "Landscape photography Buddhism Religious buildings"
  },
  "nlpDate": "20201201203309",
  "connectorId": 0,
  "tags": {}
}