{"id":"2016-00612-004","title":"S Gopalakrishnan singing at various temple performances #4 4 photographs of S Gopalakrishnan singing at various temple performances","source":"Bumblebee","path":"./Data/json/","content":"accession_no_csv:2016-00612-004\nImage:\nobject_work_type:colour photographs\ntitle_text:S Gopalakrishnan singing at various temple performances #4 4 photographs of S Gopalakrishnan singing at various temple performances\npreference:main alternate\ntitle_language:\ncreation_date:Late 1980s-Early 2000s\ncreation_place_original_location:Singapore\nstyles_periods_indexing_terms:Indian (South Asian)\ninscriptions:\ninscription_language:\nshape:rectangular\nmaterials_name:paper (fiber product)\ntechniques_name:printing (process) photographic processes\nobject_colour:multicoloured\nphysical_appearance:The image shows a rectangular photograph that is in colour. The photograph features four adult males sitting down. Three of them are playing with musical instruments\n namely a harmonium\n violin\n and tabla. The other one is singing into three microphones. The background of the photograph suggests that it was taken in the interior of a temple\n as seen by a large picture of a Hindu goddess holding a sitar.\nsubject_terms_1:musicians music (performing arts) singers musical performances temples (buidings) stages (performance spaces)\nsubject_terms_2:Colour photography Musicians Carnatic music Singers Performances Hindu temples Tamil (Indic people)\nsubject_terms_3:Photography Indian music Performing Arts Temples Musicians\nsgcool_label_text:Mr. S Gopalakrishnan (b. in 1920 in Tanjavur) was a prominent violinist\n and Carnatic singer. He arrived in Singapore in 1939 and actively participated in the Indian classical music scene here. Mr Gopalakrishnan performed alongside veterans of classical performers such as Pandit M Ramalingam and MV Gurusamy at temple and other music festivals. He also taught violin lessons at the Singapore Malayalee Association from the 1970s to 2000s. He was a member of the Tamils Reform Association and performed his wedding according to the principles of the Self-Respect Movement. He was also employed as a compositor at the Far East Air Force from 1954 to 1970.","createdDate":"20201119143405","version":0,"latest":false,"roles":[],"metadata":{"accession_no_csv":"2016-00612-004","Image":"","object_work_type":"colour photographs","title_text":"S Gopalakrishnan singing at various temple performances #4 4 photographs of S Gopalakrishnan singing at various temple performances","preference":"main alternate","title_language":"","creation_date":"Late 1980s-Early 2000s","creation_place_original_location":"Singapore","styles_periods_indexing_terms":"Indian (South Asian)","inscriptions":"","inscription_language":"","shape":"rectangular","materials_name":"paper (fiber product)","techniques_name":"printing (process) photographic processes","object_colour":"multicoloured","physical_appearance":"The image shows a rectangular photograph that is in colour. The photograph features four adult males sitting down. Three of them are playing with musical instruments, namely a harmonium, violin, and tabla. The other one is singing into three microphones. The background of the photograph suggests that it was taken in the interior of a temple, as seen by a large picture of a Hindu goddess holding a sitar.","subject_terms_1":"musicians music (performing arts) singers musical performances temples (buidings) stages (performance spaces)","subject_terms_2":"Colour photography Musicians Carnatic music Singers Performances Hindu temples Tamil (Indic people)","subject_terms_3":"Photography Indian music Performing Arts Temples Musicians","sgcool_label_text":"Mr. S Gopalakrishnan (b. in 1920 in Tanjavur) was a prominent violinist, and Carnatic singer. He arrived in Singapore in 1939 and actively participated in the Indian classical music scene here. Mr Gopalakrishnan performed alongside veterans of classical performers such as Pandit M Ramalingam and MV Gurusamy at temple and other music festivals. He also taught violin lessons at the Singapore Malayalee Association from the 1970s to 2000s. He was a member of the Tamils Reform Association and performed his wedding according to the principles of the Self-Respect Movement. He was also employed as a compositor at the Far East Air Force from 1954 to 1970."},"nlpDate":"20201119143405","connectorId":0,"tags":{}}