{
  "id": "2016-00272",
  "title": "Trophy being presented to Jayaram s/o Rengasamy, Individual Champion for the years 1955, 56 and 57 at the Tamil’s Festival conducted by the Tamils Reform  Association at Happy World Stadium",
  "source": "Bumblebee",
  "path": "./Data/json/",
  "content": "\n  accession_no_csv: 2016-00272\n\n  Image: \n\n  object_work_type: black-and-white photographs\n\n  title_text: Trophy being presented to Jayaram s/o Rengasamy\n Individual Champion for the years 1955\n 56 and 57 at the Tamil’s Festival conducted by the Tamils Reform  Association at Happy World Stadium\n\n  preference: main\n\n  title_language: \n\n  creation_date: 1957\n\n  creation_place_original_location: Singapore\n\n  inscriptions: \n\n  inscription_language: \n\n  shape: rectangular\n\n  materials_name: paper (fiber product)\n\n  techniques_name: printing (process) photographic processes\n\n  object_colour: grey monochrome\n\n  physical_appearance: \\The image shows a photograph that is in black-and-white. A man can be seen receiving a trophy from a lady\n who is dressed in her ethnic costume. Another man wearing a tie looks on but the trophy is blocking his face from the direction in which the photograph was taken. The trophy has a square base. The inscription on the trophy has the words \\\\champions\\\\ and \\\\Mr T.R. Gopal\\\\.\\\n\n  subject_terms_1: trophies (objects) festivals cultural ceremonies celebrations honours athletes Awards sportsmen associations\n\n  subject_terms_2: Awards Festivals Cultural relations Tamil?ar Ci?rtiruttac Can?kam (Cin?kappu?r) Athletes Black-and-white photography Associations\n institutions\n etc.\n\n  subject_terms_3: Photography Rengasamy Jayaram Tamils Reform Association Gay World Amusement Park Ethnic festivals Runners (Athletes) Indian clans and associations\n\n  context_1: The trophy was presented to Jayaram s/o Rengasamy at the Tamil\\u0027s Festival (Tamilar Thirunnal) that was held at Happy World Stadium in Singapore\n\n  context_2: cultural ceremonies\n\n  context_3: 1957\n\n  context_4: 1957\n\n  context_5: 1957\n\n  context_6: Singapore http://eresources.nlb.gov.sg/newspapers/Microfilm/Search?RN\\u003dNL7329\n\n  sgcool_label_text: Jayaram s/o Rengasamy was an amateur athlete who competed at the club level in Singapore and Malaya in the 1940s and 50s. He started his sporting career at the age of 14 as a boxer. In 1953\n a friend and fellow athlete\n MS Maniam\n invited Mr Rengasamy to participate in the Tamil’s Festival or Tamilar Thirunnal. He then began training in athletics at Anglo-Chinese School Barker Road\n the grounds of Victoria School off Jalan Besar and at Farrer Park. Mr Rengasamy also started participating in different races as a middle distance runner at the Tamil’s Festival (1954 – 57)\n Singapore Amateur Athletic Association meets (1955 – 57)\n as well as the Merdeka Games\n Kuala Lumpur (1957). He was also a member of Swift Athletics Club.\n",
  "createdDate": "20201120223706",
  "version": 0,
  "latest": false,
  "roles": [],
  "metadata": {
    "accession_no_csv": "2016-00272",
    "Image": "",
    "object_work_type": "black-and-white photographs",
    "title_text": "Trophy being presented to Jayaram s/o Rengasamy, Individual Champion for the years 1955, 56 and 57 at the Tamil’s Festival conducted by the Tamils Reform  Association at Happy World Stadium",
    "preference": "main",
    "title_language": "",
    "creation_date": "1957",
    "creation_place_original_location": "Singapore",
    "inscriptions": "",
    "inscription_language": "",
    "shape": "rectangular",
    "materials_name": "paper (fiber product)",
    "techniques_name": "printing (process) photographic processes",
    "object_colour": "grey monochrome",
    "physical_appearance": "\"The image shows a photograph that is in black-and-white. A man can be seen receiving a trophy from a lady, who is dressed in her ethnic costume. Another man wearing a tie looks on but the trophy is blocking his face from the direction in which the photograph was taken. The trophy has a square base. The inscription on the trophy has the words \"\"champions\"\" and \"\"Mr T.R. Gopal\"\".\"",
    "subject_terms_1": "trophies (objects) festivals cultural ceremonies celebrations honours athletes Awards sportsmen associations",
    "subject_terms_2": "Awards Festivals Cultural relations Tamil?ar Ci?rtiruttac Can?kam (Cin?kappu?r) Athletes Black-and-white photography Associations, institutions, etc.",
    "subject_terms_3": "Photography Rengasamy Jayaram Tamils Reform Association Gay World Amusement Park Ethnic festivals Runners (Athletes) Indian clans and associations",
    "context_1": "The trophy was presented to Jayaram s/o Rengasamy at the Tamil\u0027s Festival (Tamilar Thirunnal) that was held at Happy World Stadium in Singapore",
    "context_2": "cultural ceremonies",
    "context_3": "1957",
    "context_4": "1957",
    "context_5": "1957",
    "context_6": "Singapore http://eresources.nlb.gov.sg/newspapers/Microfilm/Search?RN\u003dNL7329",
    "sgcool_label_text": "Jayaram s/o Rengasamy was an amateur athlete who competed at the club level in Singapore and Malaya in the 1940s and 50s. He started his sporting career at the age of 14 as a boxer. In 1953, a friend and fellow athlete, MS Maniam, invited Mr Rengasamy to participate in the Tamil’s Festival or Tamilar Thirunnal. He then began training in athletics at Anglo-Chinese School Barker Road, the grounds of Victoria School off Jalan Besar and at Farrer Park. Mr Rengasamy also started participating in different races as a middle distance runner at the Tamil’s Festival (1954 – 57), Singapore Amateur Athletic Association meets (1955 – 57), as well as the Merdeka Games, Kuala Lumpur (1957). He was also a member of Swift Athletics Club."
  },
  "nlpDate": "20201120223706",
  "connectorId": 0,
  "tags": {}
}