{
  "id": "2016-00600",
  "title": "S Gopalakrishnan receiving the certificate presented by the Far East  Air Force",
  "source": "Bumblebee",
  "path": "./Data/json/",
  "content": "\n  accession_no_csv: 2016-00600\n\n  Image: \n\n  object_work_type: black-and-white photographs\n\n  title_text: S Gopalakrishnan receiving the certificate presented by the Far East  Air Force\n\n  preference: main\n\n  title_language: \n\n  creation_date: 19700130\n\n  creation_place_original_location: Singapore\n\n  inscriptions: \n\n  inscription_language: \n\n  shape: rectangular\n\n  materials_name: paper (fiber product)\n\n  techniques_name: printing (process) photographic processes\n\n  object_colour: grey monochrome\n\n  physical_appearance: The image shows a photograph that is in black-and-white. The photograph features a military personnel handing over a certificate over to an Indian man. Both of them are smiling and engaged in a handshake. There are several other men standing and seated behind\n some in military uniform and some in plain clothes\n and they are clapping their hands. The background of the photograph suggests that this was taken in the interior of a building.\n\n  subject_terms_1: commemoratives honours Awards certification compositors (printing industry) air forces\n\n  subject_terms_2: Black-and-white photography Certification Awards Great Britain. Royal Air Force\n\n  subject_terms_3: Photography Great Britain. Royal Air Force Military facilities\n\n  sgcool_label_text: Mr. S Gopalakrishnan (b. in 1920 in Tanjavur) was a prominent violinist\n and Carnatic singer. He arrived in Singapore in 1939 and actively participated in the Indian classical music scene here. Mr Gopalakrishnan performed alongside veterans of classical performers such as Pandit M Ramalingam and MV Gurusamy at temple and other music festivals. He also taught violin lessons at the Singapore Malayalee Association from the 1970s to 2000s. He was a member of the Tamils Reform Association and performed his wedding according to the principles of the Self-Respect Movement. He was also employed as a compositor at the Far East Air Force from 1954 to 1970.\n",
  "createdDate": "20201120223707",
  "version": 0,
  "latest": false,
  "roles": [],
  "metadata": {
    "accession_no_csv": "2016-00600",
    "Image": "",
    "object_work_type": "black-and-white photographs",
    "title_text": "S Gopalakrishnan receiving the certificate presented by the Far East  Air Force",
    "preference": "main",
    "title_language": "",
    "creation_date": "19700130",
    "creation_place_original_location": "Singapore",
    "inscriptions": "",
    "inscription_language": "",
    "shape": "rectangular",
    "materials_name": "paper (fiber product)",
    "techniques_name": "printing (process) photographic processes",
    "object_colour": "grey monochrome",
    "physical_appearance": "The image shows a photograph that is in black-and-white. The photograph features a military personnel handing over a certificate over to an Indian man. Both of them are smiling and engaged in a handshake. There are several other men standing and seated behind, some in military uniform and some in plain clothes, and they are clapping their hands. The background of the photograph suggests that this was taken in the interior of a building.",
    "subject_terms_1": "commemoratives honours Awards certification compositors (printing industry) air forces",
    "subject_terms_2": "Black-and-white photography Certification Awards Great Britain. Royal Air Force",
    "subject_terms_3": "Photography Great Britain. Royal Air Force Military facilities",
    "sgcool_label_text": "Mr. S Gopalakrishnan (b. in 1920 in Tanjavur) was a prominent violinist, and Carnatic singer. He arrived in Singapore in 1939 and actively participated in the Indian classical music scene here. Mr Gopalakrishnan performed alongside veterans of classical performers such as Pandit M Ramalingam and MV Gurusamy at temple and other music festivals. He also taught violin lessons at the Singapore Malayalee Association from the 1970s to 2000s. He was a member of the Tamils Reform Association and performed his wedding according to the principles of the Self-Respect Movement. He was also employed as a compositor at the Far East Air Force from 1954 to 1970."
  },
  "nlpDate": "20201120223707",
  "connectorId": 0,
  "tags": {}
}