{"id":"2016-00338","title":"Prayer Mat Janamaz","source":"Bumblebee","path":"./Data/json/","content":"accession_no_csv:2016-00338\nImage:\nobject_work_type:prayer rugs\ntitle_text:Prayer Mat Janamaz\npreference:main main\ntitle_language:\ncreation_date:1801 - 2000\ncreation_place_original_location:Hyderabad (India)\nstyles_periods_indexing_terms:Islamic Indian\ninscriptions:\ninscription_language:\nshape:rectangular\nmaterials_name:silk (textile) metal thread\ntechniques_name:sewing (needleworking technique) weaving\nobject_colour:pink (colour)\nphysical_appearance:The prayer rug is pink in colour. It is rectangular in shape. Near the bottom of the prayer rug\n there is an outline design of a mihrab with minarets on the side. A border that is golden in colour can be seen. It contains a geometrical shape as its pattern.\nsubject_terms_1:textiles (visual works) geometric patterns Islam prayers (oral works) motifs religious objects\nsubject_terms_2:Textiles Rugs\n Prayer Islam Islamic prayers and devotions Motifs\nsubject_terms_3:Islam\nsgcool_label_text:This janamaz (Persian/Urdu: prayer mat) is a fine example of a zari-woven silk textile. The central motif appears to be a stylised\n almost minimalistic\n version of a mihrab with minarets on the side\n surrounded by a geometric border. Prayer mats of this fine quality would have most likely been used by the upper classes or by royalty.\\r\\n","createdDate":"20201119143405","version":0,"latest":false,"roles":[],"metadata":{"accession_no_csv":"2016-00338","Image":"","object_work_type":"prayer rugs","title_text":"Prayer Mat Janamaz","preference":"main main","title_language":"","creation_date":"1801 - 2000","creation_place_original_location":"Hyderabad (India)","styles_periods_indexing_terms":"Islamic Indian","inscriptions":"","inscription_language":"","shape":"rectangular","materials_name":"silk (textile) metal thread","techniques_name":"sewing (needleworking technique) weaving","object_colour":"pink (colour)","physical_appearance":"The prayer rug is pink in colour. It is rectangular in shape. Near the bottom of the prayer rug, there is an outline design of a mihrab with minarets on the side. A border that is golden in colour can be seen. It contains a geometrical shape as its pattern.","subject_terms_1":"textiles (visual works) geometric patterns Islam prayers (oral works) motifs religious objects","subject_terms_2":"Textiles Rugs, Prayer Islam Islamic prayers and devotions Motifs","subject_terms_3":"Islam","sgcool_label_text":"This janamaz (Persian/Urdu: prayer mat) is a fine example of a zari-woven silk textile. The central motif appears to be a stylised, almost minimalistic, version of a mihrab with minarets on the side, surrounded by a geometric border. Prayer mats of this fine quality would have most likely been used by the upper classes or by royalty.\r\n"},"nlpDate":"20201119143405","connectorId":0,"tags":{}}