{"id":"2016-00174","title":"Samfoo with green and yellow floral motif","source":"Bumblebee","path":"./Data/json/","content":"accession_no_csv:2016-00174\nImage:\nobject_work_type:folk costume\ntitle_text:Samfoo with green and yellow floral motif\npreference:main\ntitle_language:\ncreation_date:1960 - 1969\ncreation_place_original_location:Singapore\nstyles_periods_indexing_terms:Chinese (culture or style)\ninscriptions:\ninscription_language:\nshape:irregular\nmaterials_name:cotton (textile) piping (trimming)\ntechniques_name:machine sewing (technique) piping (process)\nobject_colour:multicoloured\nphysical_appearance:This is a grey samfoo with long sleeves and long pants. A collar is present as well. This samfoo contains green piping at its collar\n side fastenings\n and at the edges of the cuffs. There are no visible tears on the samfoo. Green and yellow floral motifs appear all over the outfit. There are vertical crease lines present on both the shirt and pants.\nsubject_terms_1:floral patterns unisex clothing\nsubject_terms_2:Ethnic costume Motifs\nsubject_terms_3:Ethnic costume Chinese costume\nsgcool_label_text:This is a cotton samfoo with green and yellow floral motifs and green piping. The samfoo is a traditional Chinese outfit which consists of a top (‘sam’) with side fastenings and a mandarin collar\n worn over a pair of pants (‘foo’). Traditionally\n the samfoo is loose fitting and its cut makes it convenient for the wearer to carry out everyday activities.","createdDate":"20201119143405","version":0,"latest":false,"roles":[],"metadata":{"accession_no_csv":"2016-00174","Image":"","object_work_type":"folk costume","title_text":"Samfoo with green and yellow floral motif","preference":"main","title_language":"","creation_date":"1960 - 1969","creation_place_original_location":"Singapore","styles_periods_indexing_terms":"Chinese (culture or style)","inscriptions":"","inscription_language":"","shape":"irregular","materials_name":"cotton (textile) piping (trimming)","techniques_name":"machine sewing (technique) piping (process)","object_colour":"multicoloured","physical_appearance":"This is a grey samfoo with long sleeves and long pants. A collar is present as well. This samfoo contains green piping at its collar, side fastenings, and at the edges of the cuffs. There are no visible tears on the samfoo. Green and yellow floral motifs appear all over the outfit. There are vertical crease lines present on both the shirt and pants.","subject_terms_1":"floral patterns unisex clothing","subject_terms_2":"Ethnic costume Motifs","subject_terms_3":"Ethnic costume Chinese costume","sgcool_label_text":"This is a cotton samfoo with green and yellow floral motifs and green piping. The samfoo is a traditional Chinese outfit which consists of a top (‘sam’) with side fastenings and a mandarin collar, worn over a pair of pants (‘foo’). Traditionally, the samfoo is loose fitting and its cut makes it convenient for the wearer to carry out everyday activities."},"nlpDate":"20201119143405","connectorId":0,"tags":{}}