{
  "id": "2016-00531",
  "title": "Singapore citizenship registration Application form for Singapore citizenship registration Singapore citizenship registration Application form for Singapore citizenship registration",
  "source": "Bumblebee",
  "path": "./Data/json/",
  "content": "\n  accession_no_csv: 2016-00531\n\n  Image: \n\n  object_work_type: application forms application forms\n\n  title_text: Singapore citizenship registration Application form for Singapore citizenship registration Singapore citizenship registration Application form for Singapore citizenship registration\n\n  preference: main alternate main alternate\n\n  title_language: \n\n  creator_2: Registrar of Citizens\n Singapore Registrar of Citizens\n Singapore\n\n  creator_1: Not indicated Not indicated\n\n  creator_role: creators creators\n\n  creation_date: 1957 1957\n\n  creation_place_original_location: Singapore Singapore\n\n  styles_periods_indexing_terms: NA NA\n\n  inscriptions: \n\n  inscription_language: \n\n  scale_type: NA NA\n\n  shape: rectangular rectangular\n\n  materials_name: printing paper printing paper\n\n  techniques_name: printing (process) printing (process)\n\n  object_colour: grey (colour) grey (colour)\n\n  edition_description: NA NA\n\n  physical_appearance: \\The image shows the front cover of an application form. All the typewritten words are in black. \\\\Singapore Citizenship Ordinance 1957\\\\ \\The image shows the front cover of an application form. All the typewritten words are in black. \\\\Singapore Citizenship Ordinance 1957\\\\\n\n  subject_terms_1: The Singapore Citizenship (Initial) Registration Rules ordinances coat of arms  The Singapore Citizenship (Initial) Registration Rules ordinances coat of arms\n\n  subject_terms_2: 1957 Citizenship Devices (Heraldry)  1957 Citizenship Devices (Heraldry)\n\n  subject_terms_3: Rule 5 (2)\\\\ is stated at the top. \\\\Application By A Person Who Is A Subject Or Citizen Of A Foreign Country To Be Registered As A Citizen of Singapore\\\\ is stated above the coat of arms. The coat of arms consists of a lion represented on two feet and holding a banner upright  Rule 5 (2)\\\\ is stated at the top. \\\\Application By A Person Who Is A Subject Or Citizen Of A Foreign Country To Be Registered As A Citizen of Singapore\\\\ is stated above the coat of arms. The coat of arms consists of a lion represented on two feet and holding a banner upright\n\n  subject_terms_4: with another lion on all fours atop a battlement. \\  with another lion on all fours atop a battlement. \\\n\n  context_1: citizenship citizenship\n\n  context_2: Legal documents Legal documents\n\n  context_3: Demographics Demographics\n\n  context_4: NA NA\n\n  context_5: NA NA\n\n  context_6: NA NA\n\n  context_7: NA NA\n\n  context_8: NA NA\n\n  context_9: NA NA\n\n  context_10: NA NA\n\n  context_11: NA NA\n\n  context_12: NA NA\n\n  context_13: NA NA\n\n  context_14: NA NA\n\n  context_15: NA NA\n\n  context_16: NA NA\n\n  context_17: NA NA\n\n  context_18: NA NA\n\n  context_19: NA NA\n\n  context_20: NA NA\n\n  context_21: NA NA\n\n  context_22: NA NA\n\n  context_23: NA NA\n\n  context_24: NA NA\n\n  sgcool_label_text: NA NA\n",
  "createdDate": "20201120223707",
  "version": 0,
  "latest": false,
  "roles": [],
  "metadata": {
    "accession_no_csv": "2016-00531",
    "Image": "",
    "object_work_type": "application forms application forms",
    "title_text": "Singapore citizenship registration Application form for Singapore citizenship registration Singapore citizenship registration Application form for Singapore citizenship registration",
    "preference": "main alternate main alternate",
    "title_language": "",
    "creator_2": "Registrar of Citizens, Singapore Registrar of Citizens, Singapore",
    "creator_1": "Not indicated Not indicated",
    "creator_role": "creators creators",
    "creation_date": "1957 1957",
    "creation_place_original_location": "Singapore Singapore",
    "styles_periods_indexing_terms": "NA NA",
    "inscriptions": "",
    "inscription_language": "",
    "scale_type": "NA NA",
    "shape": "rectangular rectangular",
    "materials_name": "printing paper printing paper",
    "techniques_name": "printing (process) printing (process)",
    "object_colour": "grey (colour) grey (colour)",
    "edition_description": "NA NA",
    "physical_appearance": "\"The image shows the front cover of an application form. All the typewritten words are in black. \"\"Singapore Citizenship Ordinance 1957\"\" \"The image shows the front cover of an application form. All the typewritten words are in black. \"\"Singapore Citizenship Ordinance 1957\"\"",
    "subject_terms_1": "The Singapore Citizenship (Initial) Registration Rules ordinances coat of arms  The Singapore Citizenship (Initial) Registration Rules ordinances coat of arms",
    "subject_terms_2": "1957 Citizenship Devices (Heraldry)  1957 Citizenship Devices (Heraldry)",
    "subject_terms_3": "Rule 5 (2)\"\" is stated at the top. \"\"Application By A Person Who Is A Subject Or Citizen Of A Foreign Country To Be Registered As A Citizen of Singapore\"\" is stated above the coat of arms. The coat of arms consists of a lion represented on two feet and holding a banner upright  Rule 5 (2)\"\" is stated at the top. \"\"Application By A Person Who Is A Subject Or Citizen Of A Foreign Country To Be Registered As A Citizen of Singapore\"\" is stated above the coat of arms. The coat of arms consists of a lion represented on two feet and holding a banner upright",
    "subject_terms_4": "with another lion on all fours atop a battlement. \"  with another lion on all fours atop a battlement. \"",
    "context_1": "citizenship citizenship",
    "context_2": "Legal documents Legal documents",
    "context_3": "Demographics Demographics",
    "context_4": "NA NA",
    "context_5": "NA NA",
    "context_6": "NA NA",
    "context_7": "NA NA",
    "context_8": "NA NA",
    "context_9": "NA NA",
    "context_10": "NA NA",
    "context_11": "NA NA",
    "context_12": "NA NA",
    "context_13": "NA NA",
    "context_14": "NA NA",
    "context_15": "NA NA",
    "context_16": "NA NA",
    "context_17": "NA NA",
    "context_18": "NA NA",
    "context_19": "NA NA",
    "context_20": "NA NA",
    "context_21": "NA NA",
    "context_22": "NA NA",
    "context_23": "NA NA",
    "context_24": "NA NA",
    "sgcool_label_text": "NA NA"
  },
  "nlpDate": "20201120223707",
  "connectorId": 0,
  "tags": {}
}