{"id":"2016-00666","title":"Duka 50 universal darkroom safelight with instructions manual","source":"Bumblebee","path":"./Data/json/","content":"accession_no_csv:2016-00666\nImage:\nobject_work_type:safelights packing boxes manuals (instructional materials)\ntitle_text:Duka 50 universal darkroom safelight with instructions manual\npreference:main\ntitle_language:\ncreator_2:WOTAN (OSRAM GmbH)\ncreator_1:Osram (Firm)\ncreator_role:manufacturers\ncreation_date:1980s-1990s\ncreation_place_original_location:Singapore Germany (West)\ninscriptions:\ninscription_language:\nshape:irregular\nmaterials_name:plastic (organic material) glass (material)\ntechniques_name:forming (physical activity)\nobject_colour:multicoloured\nphysical_appearance:The darkroom safelight has a black body and a white lamp at its centre. It is accompanied with a two-pin black wire. It comes with an instruction manual and a packing box. The name \\u0027Wotan\\u0027 is displayed on the base\n at the right hand side\n of the darkroom safelight as well as its images on the packing box and on the instructional manual. A red switch is also present on the left side of the base of the darkroom safelight. The packing box contains an image of the Duka 50 Universal darkroom safelight\n attached to its front\nsubject_terms_1:photographic processing equipment lighting devices flourescent lighting\nsubject_terms_2:Photography Equipment and supplies Photography Lighting\nsubject_terms_3:Photography\ncontext_20:The set of equipment was used by The Picture Farm Pte Ltd\ncontext_21:45 Jalan Pemimpin\n #09-00 Foo Wah Industrial Building\n Thomson\n Singapore\ncontext_22:1970 - present\ncontext_23:1970\ncontext_24:present\nsgcool_label_text:A safelight is a light source that is appropriate to be used in a darkroom setting. It provides illumination without damaging the photographic material. This set of safelight is part of the darkroom photography equipment that was previously used by The Picture Farm\n which was set up by the renowned photographer Willie Tang.","createdDate":"20201119143405","version":0,"latest":false,"roles":[],"metadata":{"accession_no_csv":"2016-00666","Image":"","object_work_type":"safelights packing boxes manuals (instructional materials)","title_text":"Duka 50 universal darkroom safelight with instructions manual","preference":"main","title_language":"","creator_2":"WOTAN (OSRAM GmbH)","creator_1":"Osram (Firm)","creator_role":"manufacturers","creation_date":"1980s-1990s","creation_place_original_location":"Singapore Germany (West)","inscriptions":"","inscription_language":"","shape":"irregular","materials_name":"plastic (organic material) glass (material)","techniques_name":"forming (physical activity)","object_colour":"multicoloured","physical_appearance":"The darkroom safelight has a black body and a white lamp at its centre. It is accompanied with a two-pin black wire. It comes with an instruction manual and a packing box. The name \u0027Wotan\u0027 is displayed on the base, at the right hand side, of the darkroom safelight as well as its images on the packing box and on the instructional manual. A red switch is also present on the left side of the base of the darkroom safelight. The packing box contains an image of the Duka 50 Universal darkroom safelight, attached to its front","subject_terms_1":"photographic processing equipment lighting devices flourescent lighting","subject_terms_2":"Photography Equipment and supplies Photography Lighting","subject_terms_3":"Photography","context_20":"The set of equipment was used by The Picture Farm Pte Ltd","context_21":"45 Jalan Pemimpin, #09-00 Foo Wah Industrial Building, Thomson, Singapore","context_22":"1970 - present","context_23":"1970","context_24":"present","sgcool_label_text":"A safelight is a light source that is appropriate to be used in a darkroom setting. It provides illumination without damaging the photographic material. This set of safelight is part of the darkroom photography equipment that was previously used by The Picture Farm, which was set up by the renowned photographer Willie Tang."},"nlpDate":"20201119143405","connectorId":0,"tags":{}}