{
  "id": "2016-00212-025",
  "title": "Photograph album of views and portraits in the Punjab, Cashmere, Ceylon, Burma, Penang, Singapore, and Java River Mahawelligunga at Peridenia, Kandy, Ceylon",
  "source": "Bumblebee",
  "path": "./Data/json/",
  "content": "\n  accession_no_csv: 2016-00212-025\n\n  Image: \n\n  object_work_type: black-and-white photographs\n\n  title_text: Photograph album of views and portraits in the Punjab\n Cashmere\n Ceylon\n Burma\n Penang\n Singapore\n and Java River Mahawelligunga at Peridenia\n Kandy\n Ceylon\n\n  preference: alternate main\n\n  title_language: \n\n  creator_2: John Thomson\n\n  creator_1: Thomson\n J. (John)\n 1837-1921\n\n  creator_role: photographers\n\n  creation_date: before 28 Jul 1876\n\n  creation_place_original_location: Singapore Kandy (Sri Lanka)\n\n  inscriptions: \n\n  inscription_language: \n\n  shape: rectangular\n\n  materials_name: albumen (egg white protein) albumen paper paper (fiber product)\n\n  techniques_name: albumen process\n\n  object_colour: black-and-white (colors)\n\n  physical_appearance: This is a photograph of the Mahaweli Ganga River in Kandy\n Sri Lanka. There is thick vegetation on either side of the river. The photograph shows the river at low tide. There is a man swimming in the river in the middle of the photograph\n with a small boat behind him. The title is written at the bottom\n below the photograph.\n\n  subject_terms_1: scenery (landscape) rivers\n\n  subject_terms_2: Photographs Thomson\n J. (John)\n 1837-1921 Kandy (Sri Lanka) Mahaweli River (Sri Lanka)\n\n  subject_terms_3: Landscape photography\n",
  "createdDate": "20201120223706",
  "version": 0,
  "latest": false,
  "roles": [],
  "metadata": {
    "accession_no_csv": "2016-00212-025",
    "Image": "",
    "object_work_type": "black-and-white photographs",
    "title_text": "Photograph album of views and portraits in the Punjab, Cashmere, Ceylon, Burma, Penang, Singapore, and Java River Mahawelligunga at Peridenia, Kandy, Ceylon",
    "preference": "alternate main",
    "title_language": "",
    "creator_2": "John Thomson",
    "creator_1": "Thomson, J. (John), 1837-1921",
    "creator_role": "photographers",
    "creation_date": "before 28 Jul 1876",
    "creation_place_original_location": "Singapore Kandy (Sri Lanka)",
    "inscriptions": "",
    "inscription_language": "",
    "shape": "rectangular",
    "materials_name": "albumen (egg white protein) albumen paper paper (fiber product)",
    "techniques_name": "albumen process",
    "object_colour": "black-and-white (colors)",
    "physical_appearance": "This is a photograph of the Mahaweli Ganga River in Kandy, Sri Lanka. There is thick vegetation on either side of the river. The photograph shows the river at low tide. There is a man swimming in the river in the middle of the photograph, with a small boat behind him. The title is written at the bottom, below the photograph.",
    "subject_terms_1": "scenery (landscape) rivers",
    "subject_terms_2": "Photographs Thomson, J. (John), 1837-1921 Kandy (Sri Lanka) Mahaweli River (Sri Lanka)",
    "subject_terms_3": "Landscape photography"
  },
  "nlpDate": "20201120223706",
  "connectorId": 0,
  "tags": {}
}