{
  "id": "2016-00505",
  "title": "Untitled (station master at Bukit Timah railway station)",
  "source": "Bumblebee",
  "path": "./Data/json/",
  "content": "\n  accession_no_csv: 2016-00505\n\n  Image: \n\n  object_work_type: black-and-white photographs\n\n  title_text: Untitled (station master at Bukit Timah railway station)\n\n  preference: main\n\n  title_language: \n\n  creator_2: Kwek Leng Joo\n\n  creator_1: Kwek\n Leng Joo\n\n  creator_role: photographers\n\n  creation_date: 2010\n\n  creation_place_original_location: Malaysia Singapore\n\n  inscriptions: \n\n  inscription_language: \n\n  shape: rectangular\n\n  materials_name: paper (fiber product)\n\n  techniques_name: printing (process)\n\n  object_colour: grey monochrome\n\n  physical_appearance: \\The image shows a photograph in black-and-white. It has a black frame and its border is white in colour. The location of an administrative building\n with a television\n telephone\n desk\n and office chair\n is depicted. A man in uniform is sitting on the edge of the table and holding the receiver of the telephone. The flag of Malaysia is displayed on the wall\n at the upper left hand side of the photograph. Below the flag on the notice board\n the initials \\\\KTM\\\\ (Keretapi Tanah Melayu) are displayed\\\n\n  subject_terms_1: railroad stations historic monuments managers\n\n  subject_terms_2: Railroad srarions Railroad station managers Pertadbiran Keretapi Tanah Melayu Railroad trains Bukit Timah (Singapore) Historic monuments Black-and-white photography\n\n  subject_terms_3: Rail transport (Stations) Photography Pertadbiran Keretapi Tanah Melayu Former Bukit Timah Railway Station\n\n  sgcool_label_text: \\This image features the station master at the Bukit Timah railway station. It is part of the \\\\Tracking Memories\\\\ collection by the late Mr Kwek Leng Joo. The collection captures different aspects of the Malayan Railway story in Singapore\n",
  "createdDate": "20201201203309",
  "version": 0,
  "latest": false,
  "roles": [],
  "metadata": {
    "accession_no_csv": "2016-00505",
    "Image": "",
    "object_work_type": "black-and-white photographs",
    "title_text": "Untitled (station master at Bukit Timah railway station)",
    "preference": "main",
    "title_language": "",
    "creator_2": "Kwek Leng Joo",
    "creator_1": "Kwek, Leng Joo",
    "creator_role": "photographers",
    "creation_date": "2010",
    "creation_place_original_location": "Malaysia Singapore",
    "inscriptions": "",
    "inscription_language": "",
    "shape": "rectangular",
    "materials_name": "paper (fiber product)",
    "techniques_name": "printing (process)",
    "object_colour": "grey monochrome",
    "physical_appearance": "\"The image shows a photograph in black-and-white. It has a black frame and its border is white in colour. The location of an administrative building, with a television, telephone, desk, and office chair, is depicted. A man in uniform is sitting on the edge of the table and holding the receiver of the telephone. The flag of Malaysia is displayed on the wall, at the upper left hand side of the photograph. Below the flag on the notice board, the initials \"\"KTM\"\" (Keretapi Tanah Melayu) are displayed\"",
    "subject_terms_1": "railroad stations historic monuments managers",
    "subject_terms_2": "Railroad srarions Railroad station managers Pertadbiran Keretapi Tanah Melayu Railroad trains Bukit Timah (Singapore) Historic monuments Black-and-white photography",
    "subject_terms_3": "Rail transport (Stations) Photography Pertadbiran Keretapi Tanah Melayu Former Bukit Timah Railway Station",
    "sgcool_label_text": "\"This image features the station master at the Bukit Timah railway station. It is part of the \"\"Tracking Memories\"\" collection by the late Mr Kwek Leng Joo. The collection captures different aspects of the Malayan Railway story in Singapore"
  },
  "nlpDate": "20201201203309",
  "connectorId": 0,
  "tags": {}
}