{"id":"2016-00762","title":"Small censer","source":"Bumblebee","path":"./Data/json/","content":"accession_no_csv:2016-00762\nImage:\nobject_work_type:censers\ntitle_text:Small censer\npreference:main\ntitle_language:\ncreation_date:1900-1920\ncreation_place_original_location:Singapore\ninscriptions:\ninscription_language:\nshape:irregular\nmaterials_name:brass (alloy)\ntechniques_name:forging (metal forming)\nobject_colour:gray (color)\nphysical_appearance:This is a small censer. It is gray in colour. There is an engraving of Chinese characters along the tbody. The handles of the censer are curved outwards.\nsubject_terms_1:altar components Peranakan religious ceremonies foliage (motif) ceremonial objects\nsubject_terms_2:Censers Altars Peranakan (Asian people) Rites and ceremonies Motifs Ceremonial objects\nsubject_terms_3:Religious life and practices\nsgcool_label_text:This is a small\n simple censer used by Peranakans on an ancestral altar. The shape of the censer is a typical Chinese form\n with the Chinese characters engraved on the front. This form of the censer is reminiscent of archaic bronze vessels.  \\r\\n\\r\\nThis item is donated by the family of prominent Peranakan\n Ong Sam Leong (b. 1857\n Singapore – d. 7 February 1918\n Singapore). It comes from his ancestral home of Bukit Rose\n formerly at 259 Bukit Timah Road. Ong was a well-known successful businessman who made is money in the mining of phosphate on Christmas island\n which was historically a territory of colonial Singapore. \\r\\n","createdDate":"20201119143406","version":0,"latest":false,"roles":[],"metadata":{"accession_no_csv":"2016-00762","Image":"","object_work_type":"censers","title_text":"Small censer","preference":"main","title_language":"","creation_date":"1900-1920","creation_place_original_location":"Singapore","inscriptions":"","inscription_language":"","shape":"irregular","materials_name":"brass (alloy)","techniques_name":"forging (metal forming)","object_colour":"gray (color)","physical_appearance":"This is a small censer. It is gray in colour. There is an engraving of Chinese characters along the tbody. The handles of the censer are curved outwards.","subject_terms_1":"altar components Peranakan religious ceremonies foliage (motif) ceremonial objects","subject_terms_2":"Censers Altars Peranakan (Asian people) Rites and ceremonies Motifs Ceremonial objects","subject_terms_3":"Religious life and practices","sgcool_label_text":"This is a small, simple censer used by Peranakans on an ancestral altar. The shape of the censer is a typical Chinese form, with the Chinese characters engraved on the front. This form of the censer is reminiscent of archaic bronze vessels.  \r\n\r\nThis item is donated by the family of prominent Peranakan, Ong Sam Leong (b. 1857, Singapore – d. 7 February 1918, Singapore). It comes from his ancestral home of Bukit Rose, formerly at 259 Bukit Timah Road. Ong was a well-known successful businessman who made is money in the mining of phosphate on Christmas island, which was historically a territory of colonial Singapore. \r\n"},"nlpDate":"20201119143406","connectorId":0,"tags":{}}