{"id":"2016-00064","title":"Brochure of Singapore Hindu Sabai","source":"Bumblebee","path":"./Data/json/","content":"accession_no_csv:2016-00064\nImage:\nobject_work_type:brochures\ntitle_text:Brochure of Singapore Hindu Sabai\npreference:main\ntitle_language:\ncreator_2:Hindu Sabai\ncreator_1:Not indicated\ncreator_role:creators\ncreation_date:15-Apr-61\ncreation_place_original_location:Singapore\nstyles_periods_indexing_terms:Not indicated\ninscriptions:\ninscription_language:\nscale_type:Not indicated\nshape:rectangular\nmaterials_name:printing paper\ntechniques_name:printing (process)\nobject_colour:multicoloured\nphysical_appearance:\\The image displays a brochure. It is rectangular in shape and it has a brown background. The brochure is filled with the Tamil script\n on both its left and right side. There are several English alphabets and words on the brochure. The words \\\\Cup\\\\ and \\\\Challenge Cup\\\\ are stated on the right hand side of the brochure.\\\nsubject_terms_1:soccer tournaments\nsubject_terms_2:Brochures\nsubject_terms_3:\nsgcool_label_text:M.V.Gurusamy (b. 1920 in Seremban) was an accomplished percussionist and mridangam artiste as well as a renowned percussion teacher in Singapore. He arrived in Singapore and participated in the Indian classical music scene here. He was a member of the cultural contingent led by the then Minister for Culture\n S. Rajaratnam\n which visited and performed at various centres in Sarawak\n Brunei and Sabah in 1965. He was the recipient of several titles including the Kala Ratna award given by the Singapore Indian Fine Arts Society in 1986.","createdDate":"20201018182635","version":0,"latest":false,"roles":[],"metadata":{"accession_no_csv":"2016-00064","Image":"","object_work_type":"brochures","title_text":"Brochure of Singapore Hindu Sabai","preference":"main","title_language":"","creator_2":"Hindu Sabai","creator_1":"Not indicated","creator_role":"creators","creation_date":"15-Apr-61","creation_place_original_location":"Singapore","styles_periods_indexing_terms":"Not indicated","inscriptions":"","inscription_language":"","scale_type":"Not indicated","shape":"rectangular","materials_name":"printing paper","techniques_name":"printing (process)","object_colour":"multicoloured","physical_appearance":"\"The image displays a brochure. It is rectangular in shape and it has a brown background. The brochure is filled with the Tamil script, on both its left and right side. There are several English alphabets and words on the brochure. The words \"\"Cup\"\" and \"\"Challenge Cup\"\" are stated on the right hand side of the brochure.\"","subject_terms_1":"soccer tournaments","subject_terms_2":"Brochures","subject_terms_3":"","sgcool_label_text":"M.V.Gurusamy (b. 1920 in Seremban) was an accomplished percussionist and mridangam artiste as well as a renowned percussion teacher in Singapore. He arrived in Singapore and participated in the Indian classical music scene here. He was a member of the cultural contingent led by the then Minister for Culture, S. Rajaratnam, which visited and performed at various centres in Sarawak, Brunei and Sabah in 1965. He was the recipient of several titles including the Kala Ratna award given by the Singapore Indian Fine Arts Society in 1986."},"nlpDate":"20201018182635","connectorId":0,"tags":{}}