{"id":"2016-00543-002","title":"University Tribune “Nantah Unruly Elements expelled and warned” Page 6 and Page 3 University Tribune “Nantah Unruly Elements expelled and warned” University Tribune “Nantah Unruly Elements expelled and warned” Page 6 and Page 3 University Tribune “Nantah Unruly Elements expelled and warned”","source":"Bumblebee","path":"./Data/json/","content":"accession_no_csv:2016-00543-002\nImage:\nobject_work_type:newspapers newspapers\ntitle_text:University Tribune “Nantah Unruly Elements expelled and warned” Page 6 and Page 3 University Tribune “Nantah Unruly Elements expelled and warned” University Tribune “Nantah Unruly Elements expelled and warned” Page 6 and Page 3 University Tribune “Nantah Unruly Elements expelled and warned”\npreference:main alternate main alternate\ntitle_language:\ncreator_2:Publication Committee of the Nanyang University Students\\u0027 Union Tak Seng Press\n Singapore Publication Committee of the Nanyang University Students\\u0027 Union Tak Seng Press\n Singapore\ncreator_1:Not indicated Not indicated Not indicated Not indicated\ncreator_role:editors (people who revise) publishers printers (people) editors (people who revise) publishers printers (people)\ncreation_date:June\n 1961 June\n 1961\ncreation_place_original_location:Singapore Singapore\nstyles_periods_indexing_terms:NA NA\ninscriptions:\ninscription_language:\nscale_type:NA NA\nshape:rectangular rectangular\nmaterials_name:printing paper printing paper\ntechniques_name:colour printing colour printing\nobject_colour:multicoloured multicoloured\nedition_description:Issue 11 Issue 11\nphysical_appearance:\\The image shows two pages of a newspaper. \\\\Page 3\\\\ is indicated on the top right of the page on the right. \\\\Page 6\\\\ is indicated on the top left of the page on the left. \\\\NUSU\\u0027s Working Policy\\\\ serves as the headline of the page on the left. \\\\NUSU\\u0027s Statement On Recent Row\\\\ serves as the headline of the page on the right. \\ \\The image shows two pages of a newspaper. \\\\Page 3\\\\ is indicated on the top right of the page on the right. \\\\Page 6\\\\ is indicated on the top left of the page on the left. \\\\NUSU\\u0027s Working Policy\\\\ serves as the headline of the page on the left. \\\\NUSU\\u0027s Statement On Recent Row\\\\ serves as the headline of the page on the right. \\\nsubject_terms_1:universities (institutions) students editorials boycotts universities (institutions) students editorials boycotts\nsubject_terms_2:Newspapers Nanyang University Student unions Student expulsion Demonstrations Editorials boycotts Newspapers Nanyang University Student unions Student expulsion Demonstrations Editorials boycotts\nsubject_terms_3:Newspapers Nanyang University Newspapers Nanyang University\nsubject_terms_4:NA NA\ncontext_1:NA NA\ncontext_2:NA NA\ncontext_3:NA NA\ncontext_4:NA NA\ncontext_5:NA NA\ncontext_6:NA NA\ncontext_7:NA NA\ncontext_8:NA NA\ncontext_9:NA NA\ncontext_10:NA NA\ncontext_11:NA NA\ncontext_12:NA NA\ncontext_13:NA NA\ncontext_14:NA NA\ncontext_15:NA NA\ncontext_16:NA NA\ncontext_17:NA NA\ncontext_18:NA NA\ncontext_19:NA NA\ncontext_20:NA NA\ncontext_21:NA NA\ncontext_22:NA NA\ncontext_23:NA NA\ncontext_24:NA NA\nsgcool_label_text:Nanyang University was the first university outside of China catering to high school graduates from the Chinese stream. It was open from 1956 to 1980.\\r\\n\\r\\nThe University Tribune was published by the Nanyang University student union\n a union that all students that joined the university had to pay to be a part of. The issue is largely devoted to a protest on May 15 1961\n where a minority of students demonstrated against their mandatory inclusion in the student union. \\r\\n\\r\\nThe issue also includes a centrefold feature by Dr Han Suyin on Rabindranath Tagore\\r\\n Nanyang University was the first university outside of China catering to high school graduates from the Chinese stream. It was open from 1956 to 1980.\\r\\n\\r\\nThe University Tribune was published by the Nanyang University student union\n a union that all students that joined the university had to pay to be a part of. The issue is largely devoted to a protest on May 15 1961\n where a minority of students demonstrated against their mandatory inclusion in the student union. \\r\\n\\r\\nThe issue also includes a centrefold feature by Dr Han Suyin on Rabindranath Tagore\\r\\n","createdDate":"20201119143405","version":0,"latest":false,"roles":[],"metadata":{"accession_no_csv":"2016-00543-002","Image":"","object_work_type":"newspapers newspapers","title_text":"University Tribune “Nantah Unruly Elements expelled and warned” Page 6 and Page 3 University Tribune “Nantah Unruly Elements expelled and warned” University Tribune “Nantah Unruly Elements expelled and warned” Page 6 and Page 3 University Tribune “Nantah Unruly Elements expelled and warned”","preference":"main alternate main alternate","title_language":"","creator_2":"Publication Committee of the Nanyang University Students\u0027 Union Tak Seng Press, Singapore Publication Committee of the Nanyang University Students\u0027 Union Tak Seng Press, Singapore","creator_1":"Not indicated Not indicated Not indicated Not indicated","creator_role":"editors (people who revise) publishers printers (people) editors (people who revise) publishers printers (people)","creation_date":"June, 1961 June, 1961","creation_place_original_location":"Singapore Singapore","styles_periods_indexing_terms":"NA NA","inscriptions":"","inscription_language":"","scale_type":"NA NA","shape":"rectangular rectangular","materials_name":"printing paper printing paper","techniques_name":"colour printing colour printing","object_colour":"multicoloured multicoloured","edition_description":"Issue 11 Issue 11","physical_appearance":"\"The image shows two pages of a newspaper. \"\"Page 3\"\" is indicated on the top right of the page on the right. \"\"Page 6\"\" is indicated on the top left of the page on the left. \"\"NUSU\u0027s Working Policy\"\" serves as the headline of the page on the left. \"\"NUSU\u0027s Statement On Recent Row\"\" serves as the headline of the page on the right. \" \"The image shows two pages of a newspaper. \"\"Page 3\"\" is indicated on the top right of the page on the right. \"\"Page 6\"\" is indicated on the top left of the page on the left. \"\"NUSU\u0027s Working Policy\"\" serves as the headline of the page on the left. \"\"NUSU\u0027s Statement On Recent Row\"\" serves as the headline of the page on the right. \"","subject_terms_1":"universities (institutions) students editorials boycotts universities (institutions) students editorials boycotts","subject_terms_2":"Newspapers Nanyang University Student unions Student expulsion Demonstrations Editorials boycotts Newspapers Nanyang University Student unions Student expulsion Demonstrations Editorials boycotts","subject_terms_3":"Newspapers Nanyang University Newspapers Nanyang University","subject_terms_4":"NA NA","context_1":"NA NA","context_2":"NA NA","context_3":"NA NA","context_4":"NA NA","context_5":"NA NA","context_6":"NA NA","context_7":"NA NA","context_8":"NA NA","context_9":"NA NA","context_10":"NA NA","context_11":"NA NA","context_12":"NA NA","context_13":"NA NA","context_14":"NA NA","context_15":"NA NA","context_16":"NA NA","context_17":"NA NA","context_18":"NA NA","context_19":"NA NA","context_20":"NA NA","context_21":"NA NA","context_22":"NA NA","context_23":"NA NA","context_24":"NA NA","sgcool_label_text":"Nanyang University was the first university outside of China catering to high school graduates from the Chinese stream. It was open from 1956 to 1980.\r\n\r\nThe University Tribune was published by the Nanyang University student union, a union that all students that joined the university had to pay to be a part of. The issue is largely devoted to a protest on May 15 1961, where a minority of students demonstrated against their mandatory inclusion in the student union. \r\n\r\nThe issue also includes a centrefold feature by Dr Han Suyin on Rabindranath Tagore\r\n Nanyang University was the first university outside of China catering to high school graduates from the Chinese stream. It was open from 1956 to 1980.\r\n\r\nThe University Tribune was published by the Nanyang University student union, a union that all students that joined the university had to pay to be a part of. The issue is largely devoted to a protest on May 15 1961, where a minority of students demonstrated against their mandatory inclusion in the student union. \r\n\r\nThe issue also includes a centrefold feature by Dr Han Suyin on Rabindranath Tagore\r\n"},"nlpDate":"20201119143405","connectorId":0,"tags":{}}