{"id":"2016-00309","title":"Kaart van het Eiland Borneo (Map of the Island of Borneo)","source":"Bumblebee","path":"./Data/json/","content":"accession_no_csv:2016-00309\nImage:\nobject_work_type:maps (documents) copper engravings (visual works)\ntitle_text:Kaart van het Eiland Borneo (Map of the Island of Borneo)\npreference:main\ntitle_language:\ncreator_2:Francois Valentijn\ncreator_1:Valentijn\n Francois\n 1666 - 1727\ncreator_role:mapmakers\ncreation_date:1726\ncreation_place_original_location:Holland (Netherlands : Province)\ninscriptions:\ninscription_language:\nscale_type:1:30\nshape:rectangular\nmaterials_name:paper (fiber product) printing paper\ntechniques_name:mapmaking (process) colour printing\nobject_colour:multicoloured\nphysical_appearance:The map depicts the island of Borneo\n together with several islands that are much smaller in size. Different colours are used on the different islands\n ranging from pink to turquoise to yellow. The scale that is being utilized in this map is 1 : 30. There are no latitudes and longitudes on this map\n nor are there any black lines that extend out from the compass that is located near its bottom right hand side. There are pictorial representations of hills and mountains\n as well as trees.\nsubject_terms_1:colonial settlements islands (landforms)\nsubject_terms_2:Colonization East Indies Maps Islands Nederlandsche Oost-Indische Compagnie Expedition Borneo\nsgcool_label_text:Francois Valentijn (1666–1727) was a minister\n naturalist and writer who served the Dutch V.O.C. in the East Indies in the late 17th and early 18th centuries. His monumental work Oud en Nieuw Oost-Indien (Old and New East-India)\n published between 1724 and 1726\n offers a comprehensive mapping of the East Indies with a large selection of scale maps and views. This map of Borneo was published in that work.","createdDate":"20201119143405","version":0,"latest":false,"roles":[],"metadata":{"accession_no_csv":"2016-00309","Image":"","object_work_type":"maps (documents) copper engravings (visual works)","title_text":"Kaart van het Eiland Borneo (Map of the Island of Borneo)","preference":"main","title_language":"","creator_2":"Francois Valentijn","creator_1":"Valentijn, Francois, 1666 - 1727","creator_role":"mapmakers","creation_date":"1726","creation_place_original_location":"Holland (Netherlands : Province)","inscriptions":"","inscription_language":"","scale_type":"1:30","shape":"rectangular","materials_name":"paper (fiber product) printing paper","techniques_name":"mapmaking (process) colour printing","object_colour":"multicoloured","physical_appearance":"The map depicts the island of Borneo, together with several islands that are much smaller in size. Different colours are used on the different islands, ranging from pink to turquoise to yellow. The scale that is being utilized in this map is 1 : 30. There are no latitudes and longitudes on this map, nor are there any black lines that extend out from the compass that is located near its bottom right hand side. There are pictorial representations of hills and mountains, as well as trees.","subject_terms_1":"colonial settlements islands (landforms)","subject_terms_2":"Colonization East Indies Maps Islands Nederlandsche Oost-Indische Compagnie Expedition Borneo","sgcool_label_text":"Francois Valentijn (1666–1727) was a minister, naturalist and writer who served the Dutch V.O.C. in the East Indies in the late 17th and early 18th centuries. His monumental work Oud en Nieuw Oost-Indien (Old and New East-India), published between 1724 and 1726, offers a comprehensive mapping of the East Indies with a large selection of scale maps and views. This map of Borneo was published in that work."},"nlpDate":"20201119143405","connectorId":0,"tags":{}}