{"id":"2016-00546","title":"Singapore Economic Situation Singapore Economic Situation, a report in Mandarin published by the team from the University of Singapore Student Union investigating employment and retrenchment of workers in Singapore Singapore Economic Situation Singapore Economic Situation, a report in Mandarin published by the team from the University of Singapore Student Union investigating employment and retrenchment of workers in Singapore","source":"Bumblebee","path":"./Data/json/","content":"accession_no_csv:2016-00546\nImage:\nobject_work_type:reports reports\ntitle_text:Singapore Economic Situation Singapore Economic Situation\n a report in Mandarin published by the team from the University of Singapore Student Union investigating employment and retrenchment of workers in Singapore Singapore Economic Situation Singapore Economic Situation\n a report in Mandarin published by the team from the University of Singapore Student Union investigating employment and retrenchment of workers in Singapore\npreference:main alternate main alternate\ntitle_language:\ncreator_2:University of Singpaore Student Union University of Singpaore Student Union\ncreator_1:Not indciated Not indciated\ncreator_role:creators creators\ncreation_date:1975 1975\ncreation_place_original_location:Singapore Singapore\nstyles_periods_indexing_terms:NA NA\ninscriptions:\ninscription_language:\nscale_type:NA NA\nshape:rectangular rectangular\nmaterials_name:printing paper printing paper\ntechniques_name:colour printing colour printing\nobject_colour:multicoloured multicoloured\nedition_description:Not indicated Not indicated\nphysical_appearance:The image shows the front cover of a report. It is blue in colour. There are Chinese characters displayed at the top centre and at the bottom. The line of Chinese characters directly below the title is stated on a white paper that seems to be pasted onto the front cover of the report. The image shows the front cover of a report. It is blue in colour. There are Chinese characters displayed at the top centre and at the bottom. The line of Chinese characters directly below the title is stated on a white paper that seems to be pasted onto the front cover of the report.\nsubject_terms_1:workers economy employment (general economic concept) workers economy employment (general economic concept)\nsubject_terms_2:Employees University of Singapore Student unions Employees University of Singapore Student unions\nsubject_terms_3:Labour and employment University of Singapore Labour and employment University of Singapore\nsubject_terms_4:NA NA\ncontext_1:NA NA\ncontext_2:NA NA\ncontext_3:NA NA\ncontext_4:NA NA\ncontext_5:NA NA\ncontext_6:NA NA\ncontext_7:NA NA\ncontext_8:NA NA\ncontext_9:NA NA\ncontext_10:NA NA\ncontext_11:NA NA\ncontext_12:NA NA\ncontext_13:NA NA\ncontext_14:NA NA\ncontext_15:NA NA\ncontext_16:NA NA\ncontext_17:NA NA\ncontext_18:NA NA\ncontext_19:NA NA\ncontext_20:NA NA\ncontext_21:NA NA\ncontext_22:NA NA\ncontext_23:NA NA\ncontext_24:NA NA\nsgcool_label_text:The dress cap and khaki shirt belonged to Major W.J.F. Sutton\n a British veteran of the Malayan Emergency. The daggers and sheaths\n jungle scarf and Communist peaked cap were retrieved from the body of a Communist whom he killed.\\r\\n\\r\\nFormed in 1930\n the Malayan Communist Party (MCP) was allowed to operate openly during the post-war British Military Administration period as it had been Britain’s ally during the war. However\n when the MCP attempted to infiltrate trade unions to exploit popular grievances\n the British clamped down on its activities. By May 1948\n most Communists had left Singapore for the Federation of Malaya to prepare for armed struggle in the jungles. The dress cap and khaki shirt belonged to Major W.J.F. Sutton\n a British veteran of the Malayan Emergency. The daggers and sheaths\n jungle scarf and Communist peaked cap were retrieved from the body of a Communist whom he killed.\\r\\n\\r\\nFormed in 1930\n the Malayan Communist Party (MCP) was allowed to operate openly during the post-war British Military Administration period as it had been Britain’s ally during the war. However\n when the MCP attempted to infiltrate trade unions to exploit popular grievances\n the British clamped down on its activities. By May 1948\n most Communists had left Singapore for the Federation of Malaya to prepare for armed struggle in the jungles.","createdDate":"20201119143405","version":0,"latest":false,"roles":[],"metadata":{"accession_no_csv":"2016-00546","Image":"","object_work_type":"reports reports","title_text":"Singapore Economic Situation Singapore Economic Situation, a report in Mandarin published by the team from the University of Singapore Student Union investigating employment and retrenchment of workers in Singapore Singapore Economic Situation Singapore Economic Situation, a report in Mandarin published by the team from the University of Singapore Student Union investigating employment and retrenchment of workers in Singapore","preference":"main alternate main alternate","title_language":"","creator_2":"University of Singpaore Student Union University of Singpaore Student Union","creator_1":"Not indciated Not indciated","creator_role":"creators creators","creation_date":"1975 1975","creation_place_original_location":"Singapore Singapore","styles_periods_indexing_terms":"NA NA","inscriptions":"","inscription_language":"","scale_type":"NA NA","shape":"rectangular rectangular","materials_name":"printing paper printing paper","techniques_name":"colour printing colour printing","object_colour":"multicoloured multicoloured","edition_description":"Not indicated Not indicated","physical_appearance":"The image shows the front cover of a report. It is blue in colour. There are Chinese characters displayed at the top centre and at the bottom. The line of Chinese characters directly below the title is stated on a white paper that seems to be pasted onto the front cover of the report. The image shows the front cover of a report. It is blue in colour. There are Chinese characters displayed at the top centre and at the bottom. The line of Chinese characters directly below the title is stated on a white paper that seems to be pasted onto the front cover of the report.","subject_terms_1":"workers economy employment (general economic concept) workers economy employment (general economic concept)","subject_terms_2":"Employees University of Singapore Student unions Employees University of Singapore Student unions","subject_terms_3":"Labour and employment University of Singapore Labour and employment University of Singapore","subject_terms_4":"NA NA","context_1":"NA NA","context_2":"NA NA","context_3":"NA NA","context_4":"NA NA","context_5":"NA NA","context_6":"NA NA","context_7":"NA NA","context_8":"NA NA","context_9":"NA NA","context_10":"NA NA","context_11":"NA NA","context_12":"NA NA","context_13":"NA NA","context_14":"NA NA","context_15":"NA NA","context_16":"NA NA","context_17":"NA NA","context_18":"NA NA","context_19":"NA NA","context_20":"NA NA","context_21":"NA NA","context_22":"NA NA","context_23":"NA NA","context_24":"NA NA","sgcool_label_text":"The dress cap and khaki shirt belonged to Major W.J.F. Sutton, a British veteran of the Malayan Emergency. The daggers and sheaths, jungle scarf and Communist peaked cap were retrieved from the body of a Communist whom he killed.\r\n\r\nFormed in 1930, the Malayan Communist Party (MCP) was allowed to operate openly during the post-war British Military Administration period as it had been Britain’s ally during the war. However, when the MCP attempted to infiltrate trade unions to exploit popular grievances, the British clamped down on its activities. By May 1948, most Communists had left Singapore for the Federation of Malaya to prepare for armed struggle in the jungles. The dress cap and khaki shirt belonged to Major W.J.F. Sutton, a British veteran of the Malayan Emergency. The daggers and sheaths, jungle scarf and Communist peaked cap were retrieved from the body of a Communist whom he killed.\r\n\r\nFormed in 1930, the Malayan Communist Party (MCP) was allowed to operate openly during the post-war British Military Administration period as it had been Britain’s ally during the war. However, when the MCP attempted to infiltrate trade unions to exploit popular grievances, the British clamped down on its activities. By May 1948, most Communists had left Singapore for the Federation of Malaya to prepare for armed struggle in the jungles."},"nlpDate":"20201119143405","connectorId":0,"tags":{}}