{
  "id": "2016-00056 ",
  "title": "Hand Billet - Musical Entertainment performance at Victoria Theatre",
  "source": "Bumblebee",
  "path": "./Data/json/",
  "content": "\n  accession_no_csv: 2016-00056 \n\n  Image: \n\n  object_work_type: fliers (printed matter)\n\n  title_text: Hand Billet - Musical Entertainment performance at Victoria Theatre\n\n  preference: main\n\n  title_language: \n\n  creator_2: Unknown\n\n  creation_date: 5-Aug-46\n\n  creation_place_original_location: Singapore\n\n  styles_periods_indexing_terms: Not indicated\n\n  inscriptions: \n\n  inscription_language: \n\n  scale_type: Not indicated\n\n  shape: rectangular\n\n  materials_name: printing paper\n\n  techniques_name: printing (process)\n\n  object_colour: multicoloured\n\n  physical_appearance: \\The image shows a flyer. It is rectangular in shape. The flyer has a brown background. \\\\Musical Entertainment at Victoria Theatre\\\\ is stated at the top. The date\n\n  subject_terms_1: trade unions musicians timing of performance music (performing arts)\n\n  subject_terms_2: and ticketing prices are stated. \\\\Tamil Labour School: Under the Labour Union\\\\ is stated at the middle. The names of the different musicians and the type of instruments they play are stated as well.\\ Fliers (Ephemera) Musicians Labor unions\n\n  subject_terms_3: Performing Arts musical performances Indian music Musicians\n\n  subject_terms_4: Performances\n\n  context_1: Victoria Theatre and Concert Hall\n",
  "createdDate": "20201125084543",
  "version": 0,
  "latest": false,
  "roles": [],
  "metadata": {
    "accession_no_csv": "2016-00056 ",
    "Image": "",
    "object_work_type": "fliers (printed matter)",
    "title_text": "Hand Billet - Musical Entertainment performance at Victoria Theatre",
    "preference": "main",
    "title_language": "",
    "creator_2": "Unknown",
    "creation_date": "5-Aug-46",
    "creation_place_original_location": "Singapore",
    "styles_periods_indexing_terms": "Not indicated",
    "inscriptions": "",
    "inscription_language": "",
    "scale_type": "Not indicated",
    "shape": "rectangular",
    "materials_name": "printing paper",
    "techniques_name": "printing (process)",
    "object_colour": "multicoloured",
    "physical_appearance": "\"The image shows a flyer. It is rectangular in shape. The flyer has a brown background. \"\"Musical Entertainment at Victoria Theatre\"\" is stated at the top. The date",
    "subject_terms_1": "trade unions musicians timing of performance music (performing arts)",
    "subject_terms_2": "and ticketing prices are stated. \"\"Tamil Labour School: Under the Labour Union\"\" is stated at the middle. The names of the different musicians and the type of instruments they play are stated as well.\" Fliers (Ephemera) Musicians Labor unions",
    "subject_terms_3": "Performing Arts musical performances Indian music Musicians",
    "subject_terms_4": "Performances",
    "context_1": "Victoria Theatre and Concert Hall"
  },
  "nlpDate": "20201125084543",
  "connectorId": 0,
  "tags": {}
}