{"id":"2016-00730","title":"Peak of the Trading Period","source":"Bumblebee","path":"./Data/json/","content":"accession_no_csv:2016-00730\nImage:\nobject_work_type:black-and-white photographs\ntitle_text:Peak of the Trading Period\npreference:main\ntitle_language:\ncreator_2:Loke Hong Seng\ncreator_1:Loke\n Hong Seng\ncreator_role:photographers\ncreation_date:2015 [1972]\ncreation_place_original_location:Singapore\ninscriptions:\ninscription_language:\nshape:rectangular\nmaterials_name:paper (fiber product)\ntechniques_name:printing (process)\nobject_colour:grey monochrome\nedition_description:15-Feb\nphysical_appearance:\\The image shows a photograph in black-and-white that is enclosed by a white frame. There are two lorries\n one from its back and the other from its side captured in the photograph. There are several wicker baskets present on the open cargo areas of the lorries. Workers are also standing on the lorries as well as on the ground. One wicker basket is shown being transferred from one lorry to the other by a couple of workers. The background of the photograph shows several roofed buildings. At the bottom of the photograph to the left hand side\n there is a designation of \\\\2/15\\\\. At the bottom right hand side\nsubject_terms_1:there is a signature in Chinese characters. \\ blue collar workers transporting baskets (containers) trade (function)\nsubject_terms_2:trucks Street photography Blue collar workers Trucks Singapore Wicker baskets Business\nsubject_terms_3:Black-and-white photography\nsubject_terms_4:Photography","createdDate":"20201119143406","version":0,"latest":false,"roles":[],"metadata":{"accession_no_csv":"2016-00730","Image":"","object_work_type":"black-and-white photographs","title_text":"Peak of the Trading Period","preference":"main","title_language":"","creator_2":"Loke Hong Seng","creator_1":"Loke, Hong Seng","creator_role":"photographers","creation_date":"2015 [1972]","creation_place_original_location":"Singapore","inscriptions":"","inscription_language":"","shape":"rectangular","materials_name":"paper (fiber product)","techniques_name":"printing (process)","object_colour":"grey monochrome","edition_description":"15-Feb","physical_appearance":"\"The image shows a photograph in black-and-white that is enclosed by a white frame. There are two lorries, one from its back and the other from its side captured in the photograph. There are several wicker baskets present on the open cargo areas of the lorries. Workers are also standing on the lorries as well as on the ground. One wicker basket is shown being transferred from one lorry to the other by a couple of workers. The background of the photograph shows several roofed buildings. At the bottom of the photograph to the left hand side, there is a designation of \"\"2/15\"\". At the bottom right hand side","subject_terms_1":"there is a signature in Chinese characters. \" blue collar workers transporting baskets (containers) trade (function)","subject_terms_2":"trucks Street photography Blue collar workers Trucks Singapore Wicker baskets Business","subject_terms_3":"Black-and-white photography","subject_terms_4":"Photography"},"nlpDate":"20201119143406","connectorId":0,"tags":{}}