{
  "id": "2016-00492",
  "title": "Untitled (locomotive)",
  "source": "Bumblebee",
  "path": "./Data/json/",
  "content": "\n  accession_no_csv: 2016-00492\n\n  Image: \n\n  object_work_type: black-and-white photographs\n\n  title_text: Untitled (locomotive)\n\n  preference: main\n\n  title_language: \n\n  creator_2: Kwek Leng Joo\n\n  creator_1: Kwek\n Leng Joo\n\n  creator_role: photographers\n\n  creation_date: 2010\n\n  creation_place_original_location: Malaysia Singapore\n\n  inscriptions: \n\n  inscription_language: \n\n  shape: rectangular\n\n  materials_name: paper (fiber product)\n\n  techniques_name: printing (process)\n\n  object_colour: grey monochrome\n\n  physical_appearance: \\The image shows a photograph in black-and-white. It has a black frame and its border is white in colour. There is just a single set of railroad present in the photograph. A train is travelling on that railroad. The shadow of the trees\n occupying the hill on the right side of the photograph\n is cast on the top of the train. The numerals\n \\\\26100\\\\\n\n  subject_terms_1: is displayed on the side of the train railroads (infrastructure) trains (vehicle groupings)\n\n  subject_terms_2: Railroads at the centre bottom of the photograph. The railroad is not going in a straight line but is curving to the left instead. There are trees and plants on both sides of the photograph. \\ Locomotives Pertadbiran Keretapi Tanah Melayu Railroad trains\n\n  subject_terms_3: locomotives Photography Pertadbiran Keretapi Tanah Melayu\n\n  subject_terms_4: Black-and-white photography\n\n  context_1: Rail transport\n",
  "createdDate": "20201201203309",
  "version": 0,
  "latest": false,
  "roles": [],
  "metadata": {
    "accession_no_csv": "2016-00492",
    "Image": "",
    "object_work_type": "black-and-white photographs",
    "title_text": "Untitled (locomotive)",
    "preference": "main",
    "title_language": "",
    "creator_2": "Kwek Leng Joo",
    "creator_1": "Kwek, Leng Joo",
    "creator_role": "photographers",
    "creation_date": "2010",
    "creation_place_original_location": "Malaysia Singapore",
    "inscriptions": "",
    "inscription_language": "",
    "shape": "rectangular",
    "materials_name": "paper (fiber product)",
    "techniques_name": "printing (process)",
    "object_colour": "grey monochrome",
    "physical_appearance": "\"The image shows a photograph in black-and-white. It has a black frame and its border is white in colour. There is just a single set of railroad present in the photograph. A train is travelling on that railroad. The shadow of the trees, occupying the hill on the right side of the photograph, is cast on the top of the train. The numerals, \"\"26100\"\"",
    "subject_terms_1": "is displayed on the side of the train railroads (infrastructure) trains (vehicle groupings)",
    "subject_terms_2": "Railroads at the centre bottom of the photograph. The railroad is not going in a straight line but is curving to the left instead. There are trees and plants on both sides of the photograph. \" Locomotives Pertadbiran Keretapi Tanah Melayu Railroad trains",
    "subject_terms_3": "locomotives Photography Pertadbiran Keretapi Tanah Melayu",
    "subject_terms_4": "Black-and-white photography",
    "context_1": "Rail transport"
  },
  "nlpDate": "20201201203309",
  "connectorId": 0,
  "tags": {}
}