{"id":"2016-00033","title":"Altar cloth Embroidered Peranakan Tokwi","source":"Bumblebee","path":"./Data/json/","content":"accession_no_csv:2016-00033\nImage:\nobject_work_type:altar cloths\ntitle_text:Altar cloth Embroidered Peranakan Tokwi\npreference:alternate main\ntitle_language:\ncreation_date:Early 20th century\ncreation_place_original_location:Straits Settlements\nstyles_periods_indexing_terms:Peranakan\ninscriptions:\ninscription_language:\nshape:rectangular\nmaterials_name:gold thread cotton (textile) silk (textile)\ntechniques_name:embroidering\nobject_colour:multicolored\nphysical_appearance:This is an altar cloth that is embroided with gold thread\n and decorated with motifs. It is split into two panels. The top panel has the top folded down\n with two cloth hooks by the side. The top panel features ritual vessels such as censors and incense burners\n with a lion and a crane. The lower panel is decorated with phoenixes\n quails\n chickens\n magpies\n and peacocks\n intersparsed with large peonies. The decorations are bordered by a black outline.\nsubject_terms_1:ceremonial objects flower (motif) birds (motifs) embroidery (visual works)\nsubject_terms_2:Altar-cloths Chinese New Year decorations Motifs Embroidery\n Peranakan\nsubject_terms_3:Textile art and design\nsubject_terms_4:Tokwi\nsgcool_label_text:The altar cloth is embroidered with gold and silk thread\n possibly made in the Straits Settlements. The upper panel is decorated by embroidered ritual vessels and such as censors and incense burners\n as well as a lion and crane. The lower panel is very crowded and decorated by phoenixes\n quails\n a cock and hen\n magpies and peacocks. Large peonies also intersperse the animals.\\r\\n\\r\\n Altar cloths are Chinese textiles hung on the household altar during special occasions such as Chinese New Year. Known as tok wi in Hokkien meaning table cover\n the term entered Baba Malay\n the Malay dialect spoken by Peranakans.","createdDate":"20201119143405","version":0,"latest":false,"roles":[],"metadata":{"accession_no_csv":"2016-00033","Image":"","object_work_type":"altar cloths","title_text":"Altar cloth Embroidered Peranakan Tokwi","preference":"alternate main","title_language":"","creation_date":"Early 20th century","creation_place_original_location":"Straits Settlements","styles_periods_indexing_terms":"Peranakan","inscriptions":"","inscription_language":"","shape":"rectangular","materials_name":"gold thread cotton (textile) silk (textile)","techniques_name":"embroidering","object_colour":"multicolored","physical_appearance":"This is an altar cloth that is embroided with gold thread, and decorated with motifs. It is split into two panels. The top panel has the top folded down, with two cloth hooks by the side. The top panel features ritual vessels such as censors and incense burners, with a lion and a crane. The lower panel is decorated with phoenixes, quails, chickens, magpies, and peacocks, intersparsed with large peonies. The decorations are bordered by a black outline.","subject_terms_1":"ceremonial objects flower (motif) birds (motifs) embroidery (visual works)","subject_terms_2":"Altar-cloths Chinese New Year decorations Motifs Embroidery, Peranakan","subject_terms_3":"Textile art and design","subject_terms_4":"Tokwi","sgcool_label_text":"The altar cloth is embroidered with gold and silk thread, possibly made in the Straits Settlements. The upper panel is decorated by embroidered ritual vessels and such as censors and incense burners, as well as a lion and crane. The lower panel is very crowded and decorated by phoenixes, quails, a cock and hen, magpies and peacocks. Large peonies also intersperse the animals.\r\n\r\n Altar cloths are Chinese textiles hung on the household altar during special occasions such as Chinese New Year. Known as tok wi in Hokkien meaning table cover, the term entered Baba Malay, the Malay dialect spoken by Peranakans."},"nlpDate":"20201119143405","connectorId":0,"tags":{}}