{
  "id": "2016-00401",
  "title": "Hall-Welter Speedrite 914 cheque writer and cover Hall-Welter Speedrite 914 cheque writer",
  "source": "Bumblebee",
  "path": "./Data/json/",
  "content": "\n  accession_no_csv: 2016-00401\n\n  Image: \n\n  object_work_type: machines (general equipment)\n\n  title_text: Hall-Welter Speedrite 914 cheque writer and cover Hall-Welter Speedrite 914 cheque writer\n\n  preference: main alternative\n\n  title_language: \n\n  creator_2: Hall-Welter Co Inc\n\n  creator_role: manufacturers\n\n  creation_date: 1970s - 1980s\n\n  creation_place_original_location: United States Singapore\n\n  inscriptions: \n\n  inscription_language: \n\n  shape: irregular\n\n  materials_name: plastic (organic material) metal\n\n  techniques_name: forming (physical activity) metalworking\n\n  object_colour: multicoloured\n\n  physical_appearance: The image depicts a gray cover with a device underneath. The lever on the right side of the device is protruding out from the covers. A cheque writer with red and white tops lies underneath. All the tops are aligned in a straight row near the top of the cheque writer. In the middle of the device\n there is a list of numbers\n and the ones from three to nine are visible. The name of the cheque writer\n Speedrite\n is displaye din capital letters at its front. There are no visible chips or cracks on the device. At the top of the device\n several small screens displaying the number two in a straight row can be seen. They are coloured either in red or black. Each number is aligned to a top that is located under the former.\n\n  subject_terms_1: stamping (marking) technology (general associated concept) brand name objects checks (bank checks)\n\n  subject_terms_2: Checks Embossing (Printing) Technology Brand name products\n\n  sgcool_label_text: This Speedrite cheque writer (also termed ‘cheque protector’) by Hall-Welter Co Inc\n one of the established American manufacturers of cheque writers\n was manufactured in USA around the 1970s\n and was used to produce inked figures on a cheque by pulling the lever on the side of the machine. Machines like this would have been used by banks\n merchants and other financial institutions as they provided precise\n clear and quality output\n and prevented any fraudulent action such as alteration of the amount on the cheque.\n",
  "createdDate": "20201201203309",
  "version": 0,
  "latest": false,
  "roles": [],
  "metadata": {
    "accession_no_csv": "2016-00401",
    "Image": "",
    "object_work_type": "machines (general equipment)",
    "title_text": "Hall-Welter Speedrite 914 cheque writer and cover Hall-Welter Speedrite 914 cheque writer",
    "preference": "main alternative",
    "title_language": "",
    "creator_2": "Hall-Welter Co Inc",
    "creator_role": "manufacturers",
    "creation_date": "1970s - 1980s",
    "creation_place_original_location": "United States Singapore",
    "inscriptions": "",
    "inscription_language": "",
    "shape": "irregular",
    "materials_name": "plastic (organic material) metal",
    "techniques_name": "forming (physical activity) metalworking",
    "object_colour": "multicoloured",
    "physical_appearance": "The image depicts a gray cover with a device underneath. The lever on the right side of the device is protruding out from the covers. A cheque writer with red and white tops lies underneath. All the tops are aligned in a straight row near the top of the cheque writer. In the middle of the device, there is a list of numbers, and the ones from three to nine are visible. The name of the cheque writer, Speedrite, is displaye din capital letters at its front. There are no visible chips or cracks on the device. At the top of the device, several small screens displaying the number two in a straight row can be seen. They are coloured either in red or black. Each number is aligned to a top that is located under the former.",
    "subject_terms_1": "stamping (marking) technology (general associated concept) brand name objects checks (bank checks)",
    "subject_terms_2": "Checks Embossing (Printing) Technology Brand name products",
    "sgcool_label_text": "This Speedrite cheque writer (also termed ‘cheque protector’) by Hall-Welter Co Inc, one of the established American manufacturers of cheque writers, was manufactured in USA around the 1970s, and was used to produce inked figures on a cheque by pulling the lever on the side of the machine. Machines like this would have been used by banks, merchants and other financial institutions as they provided precise, clear and quality output, and prevented any fraudulent action such as alteration of the amount on the cheque."
  },
  "nlpDate": "20201201203309",
  "connectorId": 0,
  "tags": {}
}