{"id":"2016-00431-036","title":"The End of History - Rolled Painting (Boy)","source":"Bumblebee","path":"./Data/json/","content":"accession_no_csv:2016-00431-036\nImage:\nobject_work_type:paintings (visual works)\ntitle_text:The End of History - Rolled Painting (Boy)\npreference:main\ntitle_language:\ncreator_2:Alan Oei\ncreator_1:Oei\n Alan\n 1976-\ncreator_role:painters (artists)\ncreation_date:2008-2013\ncreation_place_original_location:Singapore\ninscriptions:\ninscription_language:\nshape:irregular\nmaterials_name:canvas (textile material)\ntechniques_name:rolling (preparation for storage and transporting) painting (image-making)\nobject_colour:multicolored\nphysical_appearance:This is a rolled up painting. It is unevenly rolled. Some part of the painting of a boy can be seen. A small piece of newspaper sticks out from the roll of painting on the right.\nsubject_terms_1:storage boys aliases\nsubject_terms_2:Painting Storage Boys\nsubject_terms_3:Painting\nsubject_terms_4:\nsgcool_label_text:In 2009\n the local art public found – to its surprise – that a Singaporean painter active in the Nanyang period had escaped recognition from history books despite leaving behind 76 notable paintings. It was later revealed that Huang Wei never existed – at least not in real life – but was a fiction created by artist-curator Alan Oei. Oei has an enduring fixation with history painting but is troubled that it possesses pale relevance to art-making in the present day. In Huang Wei\n Oei entwined fiction with fact and created a character who stands as a metaphor for a vital but missing part of Singapore’s art history. In effect\n Huang Wei may be regarded as a performance on several levels\n and the relationship between creator and created echoes that of a two-way mirror. On one side\n the character of Huang Wei is a conduit and device for Oei to unravel his conundrum about time and history. Yet to ‘use’ Huang Wei entails Oei becoming a medium himself and ‘channelling’ his creation so that the meta-artist can step through time’s portals and enter a realm where history painting still reigns. Still\n even liminal spaces offer fleeting refuge and the stop-motion video Goliath unfolds to reveal the artist’s hand (Huang Wei\n and/or Oei?) in a continuous cycle of creating-destroying his painting\n time and again. Alan Oei (b. 1976\n Singapore) is an artist-curator interested in the workings between art history\n politics and community. He holds a Bachelor’s degree in Art History from Columbia University and a Diploma in Fine Arts from Lasalle College of the Arts. Huang Wei – a fictional post-war painter of maimed children – is the alter-ego Oei uses to present his paintings. His work has been shown in Malaysia\n Hong Kong\n Melbourne and New York. In addition\n Oei’s curatorial projects include the ‘OH! Open House’\n an annual art walkabout inside local neighbourhoods and residences. He was recently appointed the Artistic Director of Substation\n Singapore.","createdDate":"20201018182635","version":0,"latest":false,"roles":[],"metadata":{"accession_no_csv":"2016-00431-036","Image":"","object_work_type":"paintings (visual works)","title_text":"The End of History - Rolled Painting (Boy)","preference":"main","title_language":"","creator_2":"Alan Oei","creator_1":"Oei, Alan, 1976-","creator_role":"painters (artists)","creation_date":"2008-2013","creation_place_original_location":"Singapore","inscriptions":"","inscription_language":"","shape":"irregular","materials_name":"canvas (textile material)","techniques_name":"rolling (preparation for storage and transporting) painting (image-making)","object_colour":"multicolored","physical_appearance":"This is a rolled up painting. It is unevenly rolled. Some part of the painting of a boy can be seen. A small piece of newspaper sticks out from the roll of painting on the right.","subject_terms_1":"storage boys aliases","subject_terms_2":"Painting Storage Boys","subject_terms_3":"Painting","subject_terms_4":"","sgcool_label_text":"In 2009, the local art public found – to its surprise – that a Singaporean painter active in the Nanyang period had escaped recognition from history books despite leaving behind 76 notable paintings. It was later revealed that Huang Wei never existed – at least not in real life – but was a fiction created by artist-curator Alan Oei. Oei has an enduring fixation with history painting but is troubled that it possesses pale relevance to art-making in the present day. In Huang Wei, Oei entwined fiction with fact and created a character who stands as a metaphor for a vital but missing part of Singapore’s art history. In effect, Huang Wei may be regarded as a performance on several levels, and the relationship between creator and created echoes that of a two-way mirror. On one side, the character of Huang Wei is a conduit and device for Oei to unravel his conundrum about time and history. Yet to ‘use’ Huang Wei entails Oei becoming a medium himself and ‘channelling’ his creation so that the meta-artist can step through time’s portals and enter a realm where history painting still reigns. Still, even liminal spaces offer fleeting refuge and the stop-motion video Goliath unfolds to reveal the artist’s hand (Huang Wei, and/or Oei?) in a continuous cycle of creating-destroying his painting, time and again. Alan Oei (b. 1976, Singapore) is an artist-curator interested in the workings between art history, politics and community. He holds a Bachelor’s degree in Art History from Columbia University and a Diploma in Fine Arts from Lasalle College of the Arts. Huang Wei – a fictional post-war painter of maimed children – is the alter-ego Oei uses to present his paintings. His work has been shown in Malaysia, Hong Kong, Melbourne and New York. In addition, Oei’s curatorial projects include the ‘OH! Open House’, an annual art walkabout inside local neighbourhoods and residences. He was recently appointed the Artistic Director of Substation, Singapore."},"nlpDate":"20201018182635","connectorId":0,"tags":{}}