{"id":"2016-00648","title":"Kain panjang (hip wrapper)","source":"Bumblebee","path":"./Data/json/","content":"accession_no_csv:2016-00648\nImage:\nobject_work_type:folk costume batik art\ntitle_text:Kain panjang (hip wrapper)\npreference:main\ntitle_language:\ncreation_date:1930\ncreation_place_original_location:Jawa Tengah (Indonesia)\nstyles_periods_indexing_terms:Javanese (culture or style)\ninscriptions:\ninscription_language:\nshape:rectangular\nmaterials_name:cotton (textile) natural dye\ntechniques_name:batik sewing (needleworking technique)\nobject_colour:multicolored\nphysical_appearance:This is a kain panjang\n a long hip wrapper cloth. It has a light brown background\n with patterns of black ad brown. It is decorated with figures of winged-men\n horned villains\n and other reptiles\n amongst foliage patterns.\nsubject_terms_1:comic strips motifs foliage (motif) Peranakan\nsubject_terms_2:Ethnic costume Batik Flash Gordon (comic strip) Motifs Comics (Graphic works) Peranakan (Asian people)\nsubject_terms_3:Batik Peranakan costumes\nsgcool_label_text:The comic strip\n the Flash Gordon was the inspiration for the design on this kain panjang.  First published in 1934\n the comic strip was celebrated for its exotic storyline and science fiction theme.  Winged-men\n horned villains and ferocious reptiles are rendered in a background of densely packed small curls (ukel).  Although the comic contains aggressive action and scantily-clad women\n these are not reproduced on cloth.  Instead\n the artist tames these characters and creatures by clothing them in textile patterns\n and setting them in a benign floral setting.  The combination of natural soga brown and indigo dyes are favoured in central Java batik.  Both the batik\\u0027s subject matter and laborious patterning are indicative of the owner\\u0027s and artist\\u0027s high economic status.  Unlike a sarong\n a kain panjang is not sewn into a tube.  It is wrapped around the lower body\n and then fastened by tucking in the folded ends of the kain at the waist.","createdDate":"20201018182635","version":0,"latest":false,"roles":[],"metadata":{"accession_no_csv":"2016-00648","Image":"","object_work_type":"folk costume batik art","title_text":"Kain panjang (hip wrapper)","preference":"main","title_language":"","creation_date":"1930","creation_place_original_location":"Jawa Tengah (Indonesia)","styles_periods_indexing_terms":"Javanese (culture or style)","inscriptions":"","inscription_language":"","shape":"rectangular","materials_name":"cotton (textile) natural dye","techniques_name":"batik sewing (needleworking technique)","object_colour":"multicolored","physical_appearance":"This is a kain panjang, a long hip wrapper cloth. It has a light brown background, with patterns of black ad brown. It is decorated with figures of winged-men, horned villains, and other reptiles, amongst foliage patterns.","subject_terms_1":"comic strips motifs foliage (motif) Peranakan","subject_terms_2":"Ethnic costume Batik Flash Gordon (comic strip) Motifs Comics (Graphic works) Peranakan (Asian people)","subject_terms_3":"Batik Peranakan costumes","sgcool_label_text":"The comic strip, the Flash Gordon was the inspiration for the design on this kain panjang.  First published in 1934, the comic strip was celebrated for its exotic storyline and science fiction theme.  Winged-men, horned villains and ferocious reptiles are rendered in a background of densely packed small curls (ukel).  Although the comic contains aggressive action and scantily-clad women, these are not reproduced on cloth.  Instead, the artist tames these characters and creatures by clothing them in textile patterns, and setting them in a benign floral setting.  The combination of natural soga brown and indigo dyes are favoured in central Java batik.  Both the batik\u0027s subject matter and laborious patterning are indicative of the owner\u0027s and artist\u0027s high economic status.  Unlike a sarong, a kain panjang is not sewn into a tube.  It is wrapped around the lower body, and then fastened by tucking in the folded ends of the kain at the waist."},"nlpDate":"20201018182635","connectorId":0,"tags":{}}