{"id":"2016-00491","title":"Untitled (locomotive)","source":"Bumblebee","path":"./Data/json/","content":"accession_no_csv:2016-00491\nImage:\nobject_work_type:black-and-white photographs\ntitle_text:Untitled (locomotive)\npreference:main\ntitle_language:\ncreator_2:Kwek Leng Joo\ncreator_1:Kwek\n Leng Joo\ncreator_role:photographers\ncreation_date:2010\ncreation_place_original_location:Singapore Malaysia\ninscriptions:\ninscription_language:\nshape:rectangular\nmaterials_name:paper (fiber product)\ntechniques_name:printing (process)\nobject_colour:grey monochrome\nphysical_appearance:The image shows a photograph in black-and-white. It has a black frame and its border is white in colour. There are four sets of railroad tracks present. Two of them on the right of the image are converged at the start\n but diverge later. The railroad which is second from the right then merges with the reailroad which is second from the left side of the image. A train is occupying the railroad which is seconf from the left side of the photograph. There is a rowof windows running along its side carriages. Trees separate the four tracks from the road which is situated on the extreme left hand side of the photograph.\nsubject_terms_1:locomotives railroads (infrastructure) trains (vehicle groupings) passenger cars (railroad cars)\nsubject_terms_2:Black-and-white photography Locomotives Railroads Railroad passenger cars Pertadbiran Keretapi Tanah Melayu Railroad trains\nsubject_terms_3:Rail transport Pertadbiran Keretapi Tanah Melayu Photography\nsgcool_label_text:\\This image is part of the \\\\Tracking Memories\\\\ collection by the late Mr Kwek Leng Joo. The collection captures different aspects of the Malayan Railway story in Singapore","createdDate":"20201119143405","version":0,"latest":false,"roles":[],"metadata":{"accession_no_csv":"2016-00491","Image":"","object_work_type":"black-and-white photographs","title_text":"Untitled (locomotive)","preference":"main","title_language":"","creator_2":"Kwek Leng Joo","creator_1":"Kwek, Leng Joo","creator_role":"photographers","creation_date":"2010","creation_place_original_location":"Singapore Malaysia","inscriptions":"","inscription_language":"","shape":"rectangular","materials_name":"paper (fiber product)","techniques_name":"printing (process)","object_colour":"grey monochrome","physical_appearance":"The image shows a photograph in black-and-white. It has a black frame and its border is white in colour. There are four sets of railroad tracks present. Two of them on the right of the image are converged at the start, but diverge later. The railroad which is second from the right then merges with the reailroad which is second from the left side of the image. A train is occupying the railroad which is seconf from the left side of the photograph. There is a rowof windows running along its side carriages. Trees separate the four tracks from the road which is situated on the extreme left hand side of the photograph.","subject_terms_1":"locomotives railroads (infrastructure) trains (vehicle groupings) passenger cars (railroad cars)","subject_terms_2":"Black-and-white photography Locomotives Railroads Railroad passenger cars Pertadbiran Keretapi Tanah Melayu Railroad trains","subject_terms_3":"Rail transport Pertadbiran Keretapi Tanah Melayu Photography","sgcool_label_text":"\"This image is part of the \"\"Tracking Memories\"\" collection by the late Mr Kwek Leng Joo. The collection captures different aspects of the Malayan Railway story in Singapore"},"nlpDate":"20201119143405","connectorId":0,"tags":{}}