{"id":"2016-00496","title":"Untitled (station clock)","source":"Bumblebee","path":"./Data/json/","content":"accession_no_csv:2016-00496\nImage:\nobject_work_type:black-and-white photographs\ntitle_text:Untitled (station clock)\npreference:main\ntitle_language:\ncreator_2:Kwek Leng Joo Swan and Maclaren Architects\ncreator_1:Kwek\n Leng Joo Swan \\u0026 Maclaren\ncreator_role:photographers designers\ncreation_date:2010\ncreation_place_original_location:Singapore Malaysia\ninscriptions:\ninscription_language:\nshape:rectangular\nmaterials_name:paper (fiber product)\ntechniques_name:printing (process)\nobject_colour:grey\nphysical_appearance:The image shows a photograph in black-and-white. It has a black frame and its border is white in colour. The background of the photograph is predominantly filled with clouds. There is a clock that is attached to one of the ceiling walls from the side. The hour hand stands at the numeral twelve\n while the minute hand points to the middle of the numerals five and six. The face of the clock is circular in shape and the numeric system is represented by Roman numerals.\nsubject_terms_1:railroad stations historic monuments clocks\nsubject_terms_2:Black-and-white photography Historic monuments Railroad stations Clocks and watches Pertadbiran Keretapi Tanah Melayu Tanjong Pagar (Singapore)\nsubject_terms_3:Rail transport Tanjong Pagar Railway Station Pertadbiran Keretapi Tanah Melayu Photography Rail transport (Stations)\nsgcool_label_text:\\This image shows the iconic clock of the Tanjong Pagar railway station. The station was known for its Art Deco and neo-classical architectural styles. Designed by Swan and Maclaren\n the entrance of the station is sheltered by an arched portico. This image is part of the \\\\Tracking Memories\\\\ collection by the late Mr Kwek Leng Joo. The collection captures different aspects of the Malayan Railway story in Singapore","createdDate":"20201119143405","version":0,"latest":false,"roles":[],"metadata":{"accession_no_csv":"2016-00496","Image":"","object_work_type":"black-and-white photographs","title_text":"Untitled (station clock)","preference":"main","title_language":"","creator_2":"Kwek Leng Joo Swan and Maclaren Architects","creator_1":"Kwek, Leng Joo Swan \u0026 Maclaren","creator_role":"photographers designers","creation_date":"2010","creation_place_original_location":"Singapore Malaysia","inscriptions":"","inscription_language":"","shape":"rectangular","materials_name":"paper (fiber product)","techniques_name":"printing (process)","object_colour":"grey","physical_appearance":"The image shows a photograph in black-and-white. It has a black frame and its border is white in colour. The background of the photograph is predominantly filled with clouds. There is a clock that is attached to one of the ceiling walls from the side. The hour hand stands at the numeral twelve, while the minute hand points to the middle of the numerals five and six. The face of the clock is circular in shape and the numeric system is represented by Roman numerals.","subject_terms_1":"railroad stations historic monuments clocks","subject_terms_2":"Black-and-white photography Historic monuments Railroad stations Clocks and watches Pertadbiran Keretapi Tanah Melayu Tanjong Pagar (Singapore)","subject_terms_3":"Rail transport Tanjong Pagar Railway Station Pertadbiran Keretapi Tanah Melayu Photography Rail transport (Stations)","sgcool_label_text":"\"This image shows the iconic clock of the Tanjong Pagar railway station. The station was known for its Art Deco and neo-classical architectural styles. Designed by Swan and Maclaren, the entrance of the station is sheltered by an arched portico. This image is part of the \"\"Tracking Memories\"\" collection by the late Mr Kwek Leng Joo. The collection captures different aspects of the Malayan Railway story in Singapore"},"nlpDate":"20201119143405","connectorId":0,"tags":{}}