{
  "id": "2016-00418",
  "title": "Beaded Pouch with Dragon and Phoenix Designs",
  "source": "Bumblebee",
  "path": "./Data/json/",
  "content": "\n  accession_no_csv: 2016-00418\n\n  Image: \n\n  object_work_type: pouches\n\n  title_text: Beaded Pouch with Dragon and Phoenix Designs\n\n  preference: main\n\n  title_language: \n\n  creation_date: 1900-1920\n\n  creation_place_original_location: Indonesia\n\n  inscriptions: \n\n  inscription_language: \n\n  shape: irregular\n\n  materials_name: glass (material) sequins (sprangles) velvet (fabric weave) metal\n\n  techniques_name: sewing (needleworking technique) embroidering\n\n  object_colour: multicolored\n\n  physical_appearance: This is a beaded purse. It is adorned with an embroidery of patterned sequins and beads\n against a background of maroon velvet. On the flap of the purse\n there is a depiction of a dragon\\u0027s head in the center. The rest of the purse is decorated with floral motifs.\n\n  subject_terms_1: beadwork (visual works) purses (ladies\\u0027 accessories) plant-derived motifs dragons\n\n  subject_terms_2: Motifs Pouches (Containers) Beadwork Dragons Handbags\n\n  subject_terms_3: Decorative arts\n\n  sgcool_label_text: This purse is embroidered with a figure of a dragon on one side and a phoenix on the other. As shown on this piece\n the phoenix is a combination of the neck of a crane\n feathers of a golden pheasant and tail of a peacock\n which is effectively depicted here with both metal and glass seed beads. It was a symbol of honour and riches. It was said to appear only in times of peace.\n",
  "createdDate": "20201125084535",
  "version": 0,
  "latest": false,
  "roles": [],
  "metadata": {
    "accession_no_csv": "2016-00418",
    "Image": "",
    "object_work_type": "pouches",
    "title_text": "Beaded Pouch with Dragon and Phoenix Designs",
    "preference": "main",
    "title_language": "",
    "creation_date": "1900-1920",
    "creation_place_original_location": "Indonesia",
    "inscriptions": "",
    "inscription_language": "",
    "shape": "irregular",
    "materials_name": "glass (material) sequins (sprangles) velvet (fabric weave) metal",
    "techniques_name": "sewing (needleworking technique) embroidering",
    "object_colour": "multicolored",
    "physical_appearance": "This is a beaded purse. It is adorned with an embroidery of patterned sequins and beads, against a background of maroon velvet. On the flap of the purse, there is a depiction of a dragon\u0027s head in the center. The rest of the purse is decorated with floral motifs.",
    "subject_terms_1": "beadwork (visual works) purses (ladies\u0027 accessories) plant-derived motifs dragons",
    "subject_terms_2": "Motifs Pouches (Containers) Beadwork Dragons Handbags",
    "subject_terms_3": "Decorative arts",
    "sgcool_label_text": "This purse is embroidered with a figure of a dragon on one side and a phoenix on the other. As shown on this piece, the phoenix is a combination of the neck of a crane, feathers of a golden pheasant and tail of a peacock, which is effectively depicted here with both metal and glass seed beads. It was a symbol of honour and riches. It was said to appear only in times of peace."
  },
  "nlpDate": "20201125084535",
  "connectorId": 0,
  "tags": {}
}