{"id":"2016-00242","title":"Painting of Lee Kuan Yew Lee Kuan Yew","source":"Bumblebee","path":"./Data/json/","content":"accession_no_csv:2016-00242\nImage:\nobject_work_type:oil paintings (visual works) portraits\ntitle_text:Painting of Lee Kuan Yew Lee Kuan Yew\npreference:alternate main\ntitle_language:\ncreator_1:Alvin Ong\ncreator_role:painters (artists)\ncreation_date:2015\ncreation_place_original_location:Singapore\ninscriptions:\ninscription_language:\nshape:rectangular\nmaterials_name:Canvas (textile material) oil paint (paint)\ntechniques_name:oil painting (technique)\nobject_colour:multicolored\nphysical_appearance:This is a portrait painting of Lee Kuan Yew. He is dressed in a suit and tie. He is sitting sideways\n body facing towards the left. His gaze is towards the front. The painting uses muted colours of gray\n beige\n white and black. There is a signature on the bottom-right of the painting.\nsubject_terms_1:prime ministers leaders (people) commissions (orders for works)\nsubject_terms_2:Portrait painting Lee\n Kuan Yew\n 1923-2015 Prime ministers Painting\nsubject_terms_3:Oil Painting Lee\n Kuan Yew Politicians The Arts House at The Old Parliament\nsgcool_label_text:This posthumous oil painting of Lee Kuan Yew by Alvin Ong depicts the first Prime Minister of Singapore as a young man. It is based on a photograph of Mr Lee at Assembly House (now known as the Arts House or Old Parliament House)\n in December 1958.","createdDate":"20201119143405","version":0,"latest":false,"roles":[],"metadata":{"accession_no_csv":"2016-00242","Image":"","object_work_type":"oil paintings (visual works) portraits","title_text":"Painting of Lee Kuan Yew Lee Kuan Yew","preference":"alternate main","title_language":"","creator_1":"Alvin Ong","creator_role":"painters (artists)","creation_date":"2015","creation_place_original_location":"Singapore","inscriptions":"","inscription_language":"","shape":"rectangular","materials_name":"Canvas (textile material) oil paint (paint)","techniques_name":"oil painting (technique)","object_colour":"multicolored","physical_appearance":"This is a portrait painting of Lee Kuan Yew. He is dressed in a suit and tie. He is sitting sideways, body facing towards the left. His gaze is towards the front. The painting uses muted colours of gray, beige, white and black. There is a signature on the bottom-right of the painting.","subject_terms_1":"prime ministers leaders (people) commissions (orders for works)","subject_terms_2":"Portrait painting Lee, Kuan Yew, 1923-2015 Prime ministers Painting","subject_terms_3":"Oil Painting Lee, Kuan Yew Politicians The Arts House at The Old Parliament","sgcool_label_text":"This posthumous oil painting of Lee Kuan Yew by Alvin Ong depicts the first Prime Minister of Singapore as a young man. It is based on a photograph of Mr Lee at Assembly House (now known as the Arts House or Old Parliament House), in December 1958."},"nlpDate":"20201119143405","connectorId":0,"tags":{}}