{
  "id": "2016-00212-074",
  "title": "Photograph album of views and portraits in the Punjab, Cashmere, Ceylon, Burma, Penang, Singapore, and Java Palace of the Governor-General, Buitenzorg, Java.",
  "source": "Bumblebee",
  "path": "./Data/json/",
  "content": "\n  accession_no_csv: 2016-00212-074\n\n  Image: \n\n  object_work_type: black-and-white photographs\n\n  title_text: Photograph album of views and portraits in the Punjab\n Cashmere\n Ceylon\n Burma\n Penang\n Singapore\n and Java Palace of the Governor-General\n Buitenzorg\n Java.\n\n  preference: main alternate\n\n  title_language: \n\n  creator_2: John Thomson\n\n  creator_1: Thomson\n J. (John)\n 1837-1921\n\n  creator_role: photographers\n\n  creation_date: before 28 Jul 1876\n\n  creation_place_original_location: Bogor (Indonesia) Singapore\n\n  inscriptions: \n\n  inscription_language: \n\n  shape: rectangular\n\n  materials_name: albumen (egg white protein) paper (fiber product) albumen paper\n\n  techniques_name: albumen process\n\n  object_colour: black-and-white (colors)\n\n  physical_appearance: This is a photograph of the Palace of the General Governor in Buitenzorg (Bogor)\n Indonesia. The forefront of the photograph shows the vast grounds of the building. The building is created in the neoclassical colonial architecture\n with tall columns lining the exterior\n with a pediment at the front. There is a tower dome in the center of the building. The edges of the photograph is curved. The title is written at the bottom\n below the photograph.\n\n  subject_terms_1: colonization presidential residences\n\n  subject_terms_2: Bogor (Indonesia) Colonization Photographs Thomson\n J. (John)\n 1837-1921 Istana Bogor (Bogor\n Indonesia)\n\n  subject_terms_3: Colonial architecture Photograph\n",
  "createdDate": "20201125084536",
  "version": 0,
  "latest": false,
  "roles": [],
  "metadata": {
    "accession_no_csv": "2016-00212-074",
    "Image": "",
    "object_work_type": "black-and-white photographs",
    "title_text": "Photograph album of views and portraits in the Punjab, Cashmere, Ceylon, Burma, Penang, Singapore, and Java Palace of the Governor-General, Buitenzorg, Java.",
    "preference": "main alternate",
    "title_language": "",
    "creator_2": "John Thomson",
    "creator_1": "Thomson, J. (John), 1837-1921",
    "creator_role": "photographers",
    "creation_date": "before 28 Jul 1876",
    "creation_place_original_location": "Bogor (Indonesia) Singapore",
    "inscriptions": "",
    "inscription_language": "",
    "shape": "rectangular",
    "materials_name": "albumen (egg white protein) paper (fiber product) albumen paper",
    "techniques_name": "albumen process",
    "object_colour": "black-and-white (colors)",
    "physical_appearance": "This is a photograph of the Palace of the General Governor in Buitenzorg (Bogor), Indonesia. The forefront of the photograph shows the vast grounds of the building. The building is created in the neoclassical colonial architecture, with tall columns lining the exterior, with a pediment at the front. There is a tower dome in the center of the building. The edges of the photograph is curved. The title is written at the bottom, below the photograph.",
    "subject_terms_1": "colonization presidential residences",
    "subject_terms_2": "Bogor (Indonesia) Colonization Photographs Thomson, J. (John), 1837-1921 Istana Bogor (Bogor, Indonesia)",
    "subject_terms_3": "Colonial architecture Photograph"
  },
  "nlpDate": "20201125084536",
  "connectorId": 0,
  "tags": {}
}