{
  "id": "2016-00035",
  "title": "Shrine with Sumatinatha, the Fifth Jain Tirthankara",
  "source": "Bumblebee",
  "path": "./Data/json/",
  "content": "\n  accession_no_csv: 2016-00035\n\n  Image: \n\n  object_work_type: shrines (structures)\n\n  title_text: Shrine with Sumatinatha\n the Fifth Jain Tirthankara\n\n  preference: main\n\n  title_language: \n\n  creation_date: 13th century\n\n  creation_place_original_location: Gujarat (India)\n\n  inscriptions: \n\n  inscription_language: \n\n  shape: irregular\n\n  materials_name: silver (metal) copper (metal) bronze (metal)\n\n  techniques_name: welding\n\n  object_colour: bronze (color)\n\n  physical_appearance: This is a shrine of Sumatinatha\n the fifth Jain Tirthankara. There is a central figure in the middle of the shrine\n seated in meditation on a throne supported by two lions. The canopy of the throne is supported by a pair of elephants. The deity is accompanied by 23 other figures surrounding it. There are open-worked star-shaped patterns along the base of the shrine.\n\n  subject_terms_1: Jainism deities worship\n\n  subject_terms_2: Jainism Shrines Worship Ti?rthan?karas Gods\n\n  subject_terms_3: Religious life and practices\n\n  sgcool_label_text: Jains revere twenty-four Jinas\n who have attained a state of bliss and transcendence. Jina means “liberator” or “conqueror”. They help all creatures to liberate their souls from the confines of the body. Jinas are also called “river crossers” or “forders” (tirthankaras)\n because they have been released from the eternal cycle of rebirth.\\r\\n\\r\\nThis shrine contains a central image of Sumatinatha\n the fifth Jain Tirthankara\n identified by geese on the throne. He is believed to possess miraculous powers to fulfil the wishes of pilgrims. He is surrounded by the other twenty-three Jinas. The naked Jina’s indicate that the patrons of the temple for which this shrine was made were devoted to the Digambara sect.\n",
  "createdDate": "20201201203309",
  "version": 0,
  "latest": false,
  "roles": [],
  "metadata": {
    "accession_no_csv": "2016-00035",
    "Image": "",
    "object_work_type": "shrines (structures)",
    "title_text": "Shrine with Sumatinatha, the Fifth Jain Tirthankara",
    "preference": "main",
    "title_language": "",
    "creation_date": "13th century",
    "creation_place_original_location": "Gujarat (India)",
    "inscriptions": "",
    "inscription_language": "",
    "shape": "irregular",
    "materials_name": "silver (metal) copper (metal) bronze (metal)",
    "techniques_name": "welding",
    "object_colour": "bronze (color)",
    "physical_appearance": "This is a shrine of Sumatinatha, the fifth Jain Tirthankara. There is a central figure in the middle of the shrine, seated in meditation on a throne supported by two lions. The canopy of the throne is supported by a pair of elephants. The deity is accompanied by 23 other figures surrounding it. There are open-worked star-shaped patterns along the base of the shrine.",
    "subject_terms_1": "Jainism deities worship",
    "subject_terms_2": "Jainism Shrines Worship Ti?rthan?karas Gods",
    "subject_terms_3": "Religious life and practices",
    "sgcool_label_text": "Jains revere twenty-four Jinas, who have attained a state of bliss and transcendence. Jina means “liberator” or “conqueror”. They help all creatures to liberate their souls from the confines of the body. Jinas are also called “river crossers” or “forders” (tirthankaras), because they have been released from the eternal cycle of rebirth.\r\n\r\nThis shrine contains a central image of Sumatinatha, the fifth Jain Tirthankara, identified by geese on the throne. He is believed to possess miraculous powers to fulfil the wishes of pilgrims. He is surrounded by the other twenty-three Jinas. The naked Jina’s indicate that the patrons of the temple for which this shrine was made were devoted to the Digambara sect."
  },
  "nlpDate": "20201201203309",
  "connectorId": 0,
  "tags": {}
}