{
  "id": "2016-00734",
  "title": "Vegetable Farm, Potong Pasir",
  "source": "Bumblebee",
  "path": "./Data/json/",
  "content": "\n  accession_no_csv: 2016-00734\n\n  Image: \n\n  object_work_type: black-and-white photographs\n\n  title_text: Vegetable Farm\n Potong Pasir\n\n  preference: main\n\n  title_language: \n\n  creator_2: Loke Hong Seng\n\n  creator_1: Loke\n Hong Seng\n\n  creator_role: photographers\n\n  creation_date: 2015 [1972]\n\n  creation_place_original_location: Singapore\n\n  inscriptions: \n\n  inscription_language: \n\n  shape: rectangular\n\n  materials_name: paper (fiber product)\n\n  techniques_name: printing (process)\n\n  object_colour: grey monochrome\n\n  edition_description: 15-Feb\n\n  physical_appearance: The image shows a photograph in black-and-white that is enclosed by a white frame. The background of the image contains buildings\n specifically that of high-rise flats. The majority of the photograph shows a farm with neatly divided plots of vegetation. A farmer wearing a hat can be seen working on the farm\n towards the right hand side of the image. On the left hand side of the image\n there are is a hut and a smaller shed beside it.\n\n  subject_terms_1: farms urban development farmhouses farmers (people in agriculture) new towns (modern settlements)\n\n  subject_terms_2: Farms Farmhouses Farmers Singapore Urban development Black-and-white photography New towns\n\n  subject_terms_3: Photography Potong Pasir\n\n  sgcool_label_text: Loke Hong Seng (b. 1943) was working as a radio announcer with Radio Television Singapore in the 1960s when he picked up photography and subsequently grew to specialize in street photography. His images of 1960s and 1970s Singapore offer a candid view of everyday life in the early days of the nation’s development. This photograph shows a vegetable farm at Potong Pasir\n contrasted against new developments in the background\n signaling a time of resettlement and redevelopment taking place in Singapore.\n",
  "createdDate": "20201125084530",
  "version": 0,
  "latest": false,
  "roles": [],
  "metadata": {
    "accession_no_csv": "2016-00734",
    "Image": "",
    "object_work_type": "black-and-white photographs",
    "title_text": "Vegetable Farm, Potong Pasir",
    "preference": "main",
    "title_language": "",
    "creator_2": "Loke Hong Seng",
    "creator_1": "Loke, Hong Seng",
    "creator_role": "photographers",
    "creation_date": "2015 [1972]",
    "creation_place_original_location": "Singapore",
    "inscriptions": "",
    "inscription_language": "",
    "shape": "rectangular",
    "materials_name": "paper (fiber product)",
    "techniques_name": "printing (process)",
    "object_colour": "grey monochrome",
    "edition_description": "15-Feb",
    "physical_appearance": "The image shows a photograph in black-and-white that is enclosed by a white frame. The background of the image contains buildings, specifically that of high-rise flats. The majority of the photograph shows a farm with neatly divided plots of vegetation. A farmer wearing a hat can be seen working on the farm, towards the right hand side of the image. On the left hand side of the image, there are is a hut and a smaller shed beside it.",
    "subject_terms_1": "farms urban development farmhouses farmers (people in agriculture) new towns (modern settlements)",
    "subject_terms_2": "Farms Farmhouses Farmers Singapore Urban development Black-and-white photography New towns",
    "subject_terms_3": "Photography Potong Pasir",
    "sgcool_label_text": "Loke Hong Seng (b. 1943) was working as a radio announcer with Radio Television Singapore in the 1960s when he picked up photography and subsequently grew to specialize in street photography. His images of 1960s and 1970s Singapore offer a candid view of everyday life in the early days of the nation’s development. This photograph shows a vegetable farm at Potong Pasir, contrasted against new developments in the background, signaling a time of resettlement and redevelopment taking place in Singapore."
  },
  "nlpDate": "20201125084530",
  "connectorId": 0,
  "tags": {}
}