{
  "id": "2016-00722\r\n",
  "title": "Five lace strips Group of 5 laces",
  "source": "Bumblebee",
  "path": "./Data/json/",
  "content": "\n  accession_no_csv: 2016-00722\\r\\n\n\n  Image: \n\n  object_work_type: lace (needlework)\n\n  title_text: Five lace strips Group of 5 laces\n\n  preference: main alternate\n\n  title_language: \n\n  creation_date: 20th century\n\n  creation_place_original_location: France Indonesia Straits Settlements\n\n  inscriptions: \n\n  inscription_language: \n\n  shape: irregular\n\n  materials_name: cotton (textile)\n\n  techniques_name: sewing (needleworking technique)\n\n  object_colour: white (color)\n\n  physical_appearance: This is a set of five lace strips. They are of varying lengths and design. All of them feature repeated scrolling patterns.\n\n  subject_terms_1: exports flower (motif) scrolls (motifs) trimming (material)\n\n  subject_terms_2: Exports Motifs Bobbin lace\n\n  subject_terms_3: Textile art and design\n\n  sgcool_label_text: There are 5 strips of lace of varying lengths and design.The making of bobbin lace was an established tradition in port cities like Malacca and Palembang by the early 20th century.It is part of a donation which contains a mixture of materials used in the making of kebayas and baju panjangs.\n",
  "createdDate": "20201125084531",
  "version": 0,
  "latest": false,
  "roles": [],
  "metadata": {
    "accession_no_csv": "2016-00722\r\n",
    "Image": "",
    "object_work_type": "lace (needlework)",
    "title_text": "Five lace strips Group of 5 laces",
    "preference": "main alternate",
    "title_language": "",
    "creation_date": "20th century",
    "creation_place_original_location": "France Indonesia Straits Settlements",
    "inscriptions": "",
    "inscription_language": "",
    "shape": "irregular",
    "materials_name": "cotton (textile)",
    "techniques_name": "sewing (needleworking technique)",
    "object_colour": "white (color)",
    "physical_appearance": "This is a set of five lace strips. They are of varying lengths and design. All of them feature repeated scrolling patterns.",
    "subject_terms_1": "exports flower (motif) scrolls (motifs) trimming (material)",
    "subject_terms_2": "Exports Motifs Bobbin lace",
    "subject_terms_3": "Textile art and design",
    "sgcool_label_text": "There are 5 strips of lace of varying lengths and design.The making of bobbin lace was an established tradition in port cities like Malacca and Palembang by the early 20th century.It is part of a donation which contains a mixture of materials used in the making of kebayas and baju panjangs."
  },
  "nlpDate": "20201125084531",
  "connectorId": 0,
  "tags": {}
}