{
  "id": "2016-00440",
  "title": "Gold and enamel dome table clock in cloisonné enamel by Patek Philippe Gold and enamel dome table clock in cloisonné enamel with its documents and packaging",
  "source": "Bumblebee",
  "path": "./Data/json/",
  "content": "\n  accession_no_csv: 2016-00440\n\n  Image: \n\n  object_work_type: table clocks documents (object genre) manuals (instructional manuals) bags (generic containers)\n\n  title_text: Gold and enamel dome table clock in cloisonné enamel by Patek Philippe Gold and enamel dome table clock in cloisonné enamel with its documents and packaging\n\n  preference: main alternate\n\n  title_language: \n\n  creator_2: Patek Philippe\n\n  creator_1: Patek Philippe (Firm)\n\n  creator_role: creators\n\n  creation_date: 2015\n\n  creation_place_original_location: Singapore Geneva (Switzerland)\n\n  inscriptions: \n\n  inscription_language: \n\n  shape: dome topped (shape) irregular\n\n  materials_name: enamel (fused coating) gold (metal) silver (metal)\n\n  techniques_name: forming (physical activity) cloisonné\n\n  object_colour: multicoloured\n\n  physical_appearance: \\The image shows a set item comprising of a dome table clock inside an open box with several other items. Alongside it are the packaging\n as well as several documents and a bag. The interior of the box is white and its exterior is dark brown\n similar to the exteriors of the briefcase\n bag\n and the packaging. The dome table clock has floral and bird motifs all over it\n and its centre contains a clock face with the hour and minute hands. The clock face is gold in colour\n and the inner circle has a guilloche pattern. The name of the creator\n \\\\Patek Philippe Geneve\\\\ is displayed in capital letters above the mid-point of the clock.\\\n\n  subject_terms_1: guilloche commemoratives floral patterns natural history birds (motifs)\n\n  subject_terms_2: Motifs Farquhar\n William\n 1774-1839 Handbooks and manuals Patek Philippe (Firm) Natural history Bags Cloisonne Clocks and watches\n\n  subject_terms_3: \n\n  context_1: Singapore50\n\n  context_2: anniversaries\n\n  context_3: 2015\n\n  context_4: 2015\n\n  context_5: 2015\n\n  context_6: Singapore\n\n  sgcool_label_text: This piece was specially created to celebrate SG50\n Singapore\\u0027s 50th year of independence\n in 2015 and it was inspired by the William Farquhar collection of natural history drawings from the National Museum of Singapore. Farquhar was the first Resident and Commandant of Singapore\n and the 477 watercolours from the collection were commissioned by him when he served as British Resident and Commandant of Melaka from 1803 to 1818. The drawings combine traditional Chinese painting methods with European\n providing an insight into the local flora and fauna\n as well as a glimpse into the history of British rule in the Malay Peninsula during the early 19th century.\n",
  "createdDate": "20201125084534",
  "version": 0,
  "latest": false,
  "roles": [],
  "metadata": {
    "accession_no_csv": "2016-00440",
    "Image": "",
    "object_work_type": "table clocks documents (object genre) manuals (instructional manuals) bags (generic containers)",
    "title_text": "Gold and enamel dome table clock in cloisonné enamel by Patek Philippe Gold and enamel dome table clock in cloisonné enamel with its documents and packaging",
    "preference": "main alternate",
    "title_language": "",
    "creator_2": "Patek Philippe",
    "creator_1": "Patek Philippe (Firm)",
    "creator_role": "creators",
    "creation_date": "2015",
    "creation_place_original_location": "Singapore Geneva (Switzerland)",
    "inscriptions": "",
    "inscription_language": "",
    "shape": "dome topped (shape) irregular",
    "materials_name": "enamel (fused coating) gold (metal) silver (metal)",
    "techniques_name": "forming (physical activity) cloisonné",
    "object_colour": "multicoloured",
    "physical_appearance": "\"The image shows a set item comprising of a dome table clock inside an open box with several other items. Alongside it are the packaging, as well as several documents and a bag. The interior of the box is white and its exterior is dark brown, similar to the exteriors of the briefcase, bag, and the packaging. The dome table clock has floral and bird motifs all over it, and its centre contains a clock face with the hour and minute hands. The clock face is gold in colour, and the inner circle has a guilloche pattern. The name of the creator, \"\"Patek Philippe Geneve\"\" is displayed in capital letters above the mid-point of the clock.\"",
    "subject_terms_1": "guilloche commemoratives floral patterns natural history birds (motifs)",
    "subject_terms_2": "Motifs Farquhar, William, 1774-1839 Handbooks and manuals Patek Philippe (Firm) Natural history Bags Cloisonne Clocks and watches",
    "subject_terms_3": "",
    "context_1": "Singapore50",
    "context_2": "anniversaries",
    "context_3": "2015",
    "context_4": "2015",
    "context_5": "2015",
    "context_6": "Singapore",
    "sgcool_label_text": "This piece was specially created to celebrate SG50, Singapore\u0027s 50th year of independence, in 2015 and it was inspired by the William Farquhar collection of natural history drawings from the National Museum of Singapore. Farquhar was the first Resident and Commandant of Singapore, and the 477 watercolours from the collection were commissioned by him when he served as British Resident and Commandant of Melaka from 1803 to 1818. The drawings combine traditional Chinese painting methods with European, providing an insight into the local flora and fauna, as well as a glimpse into the history of British rule in the Malay Peninsula during the early 19th century."
  },
  "nlpDate": "20201125084534",
  "connectorId": 0,
  "tags": {}
}