{
  "id": "2016-00212-066",
  "title": "Photograph album of views and portraits in the Punjab, Cashmere, Ceylon, Burma, Penang, Singapore, and Java Rijswijk, Batavia, Java",
  "source": "Bumblebee",
  "path": "./Data/json/",
  "content": "\n  accession_no_csv: 2016-00212-066\n\n  Image: \n\n  object_work_type: black-and-white photographs\n\n  title_text: Photograph album of views and portraits in the Punjab\n Cashmere\n Ceylon\n Burma\n Penang\n Singapore\n and Java Rijswijk\n Batavia\n Java\n\n  preference: main alternate\n\n  title_language: \n\n  creator_2: John Thomson\n\n  creator_1: Thomson\n J. (John)\n 1837-1921\n\n  creator_role: photographers\n\n  creation_date: before 28 Jul 1876\n\n  creation_place_original_location: Singapore Jakarta (Indonesia)\n\n  inscriptions: \n\n  inscription_language: \n\n  shape: rectangular\n\n  materials_name: albumen (egg white protein) paper (fiber product) albumen paper\n\n  techniques_name: albumen process\n\n  object_colour: black-and-white (colors)\n\n  physical_appearance: This is a photograph of a road in Rijswijk\n Batavia (Jakarta) in Indonesia. There is a wide road in the middle of the photograph. On the right of the road\n there is a fence. The road is lined with trees on either side. On the left\n behind the trees\n there is a building with a canopy front facing the road. The edges of the photograph are rounded. The photograph is slightly faded around the edges. The title is written at the bottom\n below the photograph.\n\n  subject_terms_1: streets\n\n  subject_terms_2: Photographs Streets Thomson\n J. (John)\n 1837-1921 Jakarta (Indonesia)\n\n  subject_terms_3: Photography Streets and Places\n",
  "createdDate": "20201125084536",
  "version": 0,
  "latest": false,
  "roles": [],
  "metadata": {
    "accession_no_csv": "2016-00212-066",
    "Image": "",
    "object_work_type": "black-and-white photographs",
    "title_text": "Photograph album of views and portraits in the Punjab, Cashmere, Ceylon, Burma, Penang, Singapore, and Java Rijswijk, Batavia, Java",
    "preference": "main alternate",
    "title_language": "",
    "creator_2": "John Thomson",
    "creator_1": "Thomson, J. (John), 1837-1921",
    "creator_role": "photographers",
    "creation_date": "before 28 Jul 1876",
    "creation_place_original_location": "Singapore Jakarta (Indonesia)",
    "inscriptions": "",
    "inscription_language": "",
    "shape": "rectangular",
    "materials_name": "albumen (egg white protein) paper (fiber product) albumen paper",
    "techniques_name": "albumen process",
    "object_colour": "black-and-white (colors)",
    "physical_appearance": "This is a photograph of a road in Rijswijk, Batavia (Jakarta) in Indonesia. There is a wide road in the middle of the photograph. On the right of the road, there is a fence. The road is lined with trees on either side. On the left, behind the trees, there is a building with a canopy front facing the road. The edges of the photograph are rounded. The photograph is slightly faded around the edges. The title is written at the bottom, below the photograph.",
    "subject_terms_1": "streets",
    "subject_terms_2": "Photographs Streets Thomson, J. (John), 1837-1921 Jakarta (Indonesia)",
    "subject_terms_3": "Photography Streets and Places"
  },
  "nlpDate": "20201125084536",
  "connectorId": 0,
  "tags": {}
}