{"id":"2016-00623","title":"Rengasamy Malaiammal, P Letchimi and Meena Photograph of Rengasamy Malaiammal, P Letchimi and Meena","source":"Bumblebee","path":"./Data/json/","content":"accession_no_csv:2016-00623\nImage:\nobject_work_type:black-and-white photographs\ntitle_text:Rengasamy Malaiammal\n P Letchimi and Meena Photograph of Rengasamy Malaiammal\n P Letchimi and Meena\npreference:main alternate\ntitle_language:\ncreation_date:Early 1940s\ncreation_place_original_location:Singapore\ninscriptions:\ninscription_language:\nshape:rectangular\nmaterials_name:paper (fiber product)\ntechniques_name:printing (process) photographic processes\nobject_colour:grey monochrome\nphysical_appearance:The image shows a photograph that is in black-and-white. A group of three Indian women\n dressed in their ethnic costumes\n are looking towards the direction in which the photograph was captured. They are all standing up. The background of the photograph suggests that it was taken inside a building.\nsubject_terms_1:women (female humans) folk costume ethnic groups group portraits studio portraits\nsubject_terms_2:Black-and-white photography Women Ethnic costume Portraits\n Group Portrait photography\nsubject_terms_3:Portrait photography Women Indian costumes\nsgcool_label_text:Not indicated","createdDate":"20201119143405","version":0,"latest":false,"roles":[],"metadata":{"accession_no_csv":"2016-00623","Image":"","object_work_type":"black-and-white photographs","title_text":"Rengasamy Malaiammal, P Letchimi and Meena Photograph of Rengasamy Malaiammal, P Letchimi and Meena","preference":"main alternate","title_language":"","creation_date":"Early 1940s","creation_place_original_location":"Singapore","inscriptions":"","inscription_language":"","shape":"rectangular","materials_name":"paper (fiber product)","techniques_name":"printing (process) photographic processes","object_colour":"grey monochrome","physical_appearance":"The image shows a photograph that is in black-and-white. A group of three Indian women, dressed in their ethnic costumes, are looking towards the direction in which the photograph was captured. They are all standing up. The background of the photograph suggests that it was taken inside a building.","subject_terms_1":"women (female humans) folk costume ethnic groups group portraits studio portraits","subject_terms_2":"Black-and-white photography Women Ethnic costume Portraits, Group Portrait photography","subject_terms_3":"Portrait photography Women Indian costumes","sgcool_label_text":"Not indicated"},"nlpDate":"20201119143405","connectorId":0,"tags":{}}