{"id":"2016-00187","title":"Talentime related award, vinyl record with cover (3 items)","source":"Bumblebee","path":"./Data/json/","content":"accession_no_csv:2016-00187\nImage:\nobject_work_type:awards 45 rpm records record covers\ntitle_text:Talentime related award\n vinyl record with cover (3 items)\npreference:main\ntitle_language:\ncreator_2:Radio Television Singapore\ncreator_1:Radio-Television Singapore\ncreator_role:creators\ncreation_date:1968\ncreation_place_original_location:Singapore\ninscriptions:\ninscription_language:\nshape:irregular\nmaterials_name:vinyl paper (fiber product) plastic (organic material)\ntechniques_name:forming (physical activity)\nobject_colour:multicoloured\nphysical_appearance:\\The image shows an award\n a vinyl record and its cover. The award is yellow in colour with a black base. The yellow part is shaped like a four sided star and there are two rows of Chinese characters and the year \\u00271968\\u0027 stated at its middle. The cover of the vinyl record is predominantly yellow in colour and is square in shape. The logo and initials of RTS are displayed at the bottom right hand corner of the vinyl cover. The years \\u00271968 - 9\\u0027 are displayed at the top left hand corner of the vinyl cover.Two lines of Chinese characters\n one in black and the other in pink\n are shown as well. The vinyl is circular in shape and its outer region is black while the inner region is blue in colour. In the inner circle of the vinyl record\n the logo and the initials of RTS are displayed at the top\n followed by RTS\\u0027s copyright notice\n the indication of \\u002745 rpm\\u0027\n \\u0027Stereo\\u0027\n \\u0027Side 1\\u0027\n several Chinese characters\n and the names \\u0027Ahmad Jaffar\\u0027 and \\u0027C. Lazaroo\\u0027. Finally\n the copyright formality of \\\\All Rights Reserved\\\\ is stated at the bottom of the inner circle.\\\nsubject_terms_1:competitions (events) phonograph records prizes television programmes\nsubject_terms_2:Awards Sound recordings Sound recordings Album covers Contests Television programmes\nsubject_terms_3:Radio-Television Singapore\ncontext_1:Radio Television Talentime 1968 - 1969\ncontext_2:competitions (events)\ncontext_3:1968 - 1969\ncontext_4:1968\ncontext_5:1969\ncontext_6:Singapore\nsgcool_label_text:This group of 3 items are related to Talentime from 1968 which was under the Radio Television Singapore. The award shaped like the RTS logo and the vinyl record with cover are important souvenirs of this popular competition - now hailed as a precursor to the Singapore idol on television.\\r\\nRadio Malaya started the competition called Talentime in the mid1950s.The competiion was meant as a platform to showcase musicians and this attracted many local groupos\n several of whom went on to become famous.","createdDate":"20201119143405","version":0,"latest":false,"roles":[],"metadata":{"accession_no_csv":"2016-00187","Image":"","object_work_type":"awards 45 rpm records record covers","title_text":"Talentime related award, vinyl record with cover (3 items)","preference":"main","title_language":"","creator_2":"Radio Television Singapore","creator_1":"Radio-Television Singapore","creator_role":"creators","creation_date":"1968","creation_place_original_location":"Singapore","inscriptions":"","inscription_language":"","shape":"irregular","materials_name":"vinyl paper (fiber product) plastic (organic material)","techniques_name":"forming (physical activity)","object_colour":"multicoloured","physical_appearance":"\"The image shows an award, a vinyl record and its cover. The award is yellow in colour with a black base. The yellow part is shaped like a four sided star and there are two rows of Chinese characters and the year \u00271968\u0027 stated at its middle. The cover of the vinyl record is predominantly yellow in colour and is square in shape. The logo and initials of RTS are displayed at the bottom right hand corner of the vinyl cover. The years \u00271968 - 9\u0027 are displayed at the top left hand corner of the vinyl cover.Two lines of Chinese characters, one in black and the other in pink, are shown as well. The vinyl is circular in shape and its outer region is black while the inner region is blue in colour. In the inner circle of the vinyl record, the logo and the initials of RTS are displayed at the top, followed by RTS\u0027s copyright notice, the indication of \u002745 rpm\u0027, \u0027Stereo\u0027, \u0027Side 1\u0027, several Chinese characters, and the names \u0027Ahmad Jaffar\u0027 and \u0027C. Lazaroo\u0027. Finally, the copyright formality of \"\"All Rights Reserved\"\" is stated at the bottom of the inner circle.\"","subject_terms_1":"competitions (events) phonograph records prizes television programmes","subject_terms_2":"Awards Sound recordings Sound recordings Album covers Contests Television programmes","subject_terms_3":"Radio-Television Singapore","context_1":"Radio Television Talentime 1968 - 1969","context_2":"competitions (events)","context_3":"1968 - 1969","context_4":"1968","context_5":"1969","context_6":"Singapore","sgcool_label_text":"This group of 3 items are related to Talentime from 1968 which was under the Radio Television Singapore. The award shaped like the RTS logo and the vinyl record with cover are important souvenirs of this popular competition - now hailed as a precursor to the Singapore idol on television.\r\nRadio Malaya started the competition called Talentime in the mid1950s.The competiion was meant as a platform to showcase musicians and this attracted many local groupos, several of whom went on to become famous."},"nlpDate":"20201119143405","connectorId":0,"tags":{}}