{
  "id": "2016-00095",
  "title": "A set of four photographs of Appavoo Kandiar’s residence Appavoo Kandiar’s residence",
  "source": "Bumblebee",
  "path": "./Data/json/",
  "content": "\n  accession_no_csv: 2016-00095\n\n  Image: \n\n  object_work_type: black-and-white photographs\n\n  title_text: A set of four photographs of Appavoo Kandiar’s residence Appavoo Kandiar’s residence\n\n  preference: main alternate\n\n  title_language: \n\n  creation_date: 1940s\n\n  creation_place_original_location: Singapore\n\n  inscriptions: \n\n  inscription_language: \n\n  shape: rectangular\n\n  materials_name: paper (fiber product)\n\n  techniques_name: printing (process) photographic processes\n\n  object_colour: grey monochrome\n\n  physical_appearance: This is a set of four rectangular photographs. All of them are in black-and-white. The photograph at the top left hand side shows two single-storey houses in a rural area. Kitchen utensils such as pots and pans can be seen from a window. The photograph at the top right hand side also shows two single-storey houses as well. However\n there is a bicycle and several chairs situated outside one of the houses. At the bottom left hand side\n the photograph shows four men standing outside a single storey building. Beside this photograph at the bottom right hand side\n five people can be seen standing outside a single-storey house. Three of them are standing up\n while one of them is sitting down and the other is kneeling and tending to some plants.\n\n  subject_terms_1: rural houses general stores villages quarters (districts) workers dwellings kitchens\n\n  subject_terms_2: Housing Villages Kitchens Employees Dwellings General stores Singapore Black-and-white photography\n\n  subject_terms_3: Photography Coronation Road West\n\n  sgcool_label_text: A native of Karuvakurichi village\n near Mannargudi town in Tamil Nadu\n S. Appavoo Kandiar was a general contractor specializing in pipe and cable laying\n handling of cargo and a concrete bricks supplier. Mr.Kandiar was a successful contractor; called a millionaire by the Straits Times in 1957\n he owned properties in Bukit Timah and Coronation Road areas. He was a contemporary of Indian pioneers such as P.Govindasamy Pillai\n Govindasamy Sarangapany\n Pakkirisami Pillai\n and had friendly associations with them.\n",
  "createdDate": "20201201203309",
  "version": 0,
  "latest": false,
  "roles": [],
  "metadata": {
    "accession_no_csv": "2016-00095",
    "Image": "",
    "object_work_type": "black-and-white photographs",
    "title_text": "A set of four photographs of Appavoo Kandiar’s residence Appavoo Kandiar’s residence",
    "preference": "main alternate",
    "title_language": "",
    "creation_date": "1940s",
    "creation_place_original_location": "Singapore",
    "inscriptions": "",
    "inscription_language": "",
    "shape": "rectangular",
    "materials_name": "paper (fiber product)",
    "techniques_name": "printing (process) photographic processes",
    "object_colour": "grey monochrome",
    "physical_appearance": "This is a set of four rectangular photographs. All of them are in black-and-white. The photograph at the top left hand side shows two single-storey houses in a rural area. Kitchen utensils such as pots and pans can be seen from a window. The photograph at the top right hand side also shows two single-storey houses as well. However, there is a bicycle and several chairs situated outside one of the houses. At the bottom left hand side, the photograph shows four men standing outside a single storey building. Beside this photograph at the bottom right hand side, five people can be seen standing outside a single-storey house. Three of them are standing up, while one of them is sitting down and the other is kneeling and tending to some plants.",
    "subject_terms_1": "rural houses general stores villages quarters (districts) workers dwellings kitchens",
    "subject_terms_2": "Housing Villages Kitchens Employees Dwellings General stores Singapore Black-and-white photography",
    "subject_terms_3": "Photography Coronation Road West",
    "sgcool_label_text": "A native of Karuvakurichi village, near Mannargudi town in Tamil Nadu, S. Appavoo Kandiar was a general contractor specializing in pipe and cable laying, handling of cargo and a concrete bricks supplier. Mr.Kandiar was a successful contractor; called a millionaire by the Straits Times in 1957, he owned properties in Bukit Timah and Coronation Road areas. He was a contemporary of Indian pioneers such as P.Govindasamy Pillai, Govindasamy Sarangapany, Pakkirisami Pillai, and had friendly associations with them."
  },
  "nlpDate": "20201201203309",
  "connectorId": 0,
  "tags": {}
}