{
  "id": "2016-00501",
  "title": "Untitled (railway track)",
  "source": "Bumblebee",
  "path": "./Data/json/",
  "content": "\n  accession_no_csv: 2016-00501\n\n  Image: \n\n  object_work_type: black-and-white photographs\n\n  title_text: Untitled (railway track)\n\n  preference: main\n\n  title_language: \n\n  creator_2: Kwek Leng Joo\n\n  creator_1: Kwek\n Leng Joo\n\n  creator_role: photographers\n\n  creation_date: 2010\n\n  creation_place_original_location: Malaysia Singapore\n\n  inscriptions: \n\n  inscription_language: \n\n  shape: rectangular\n\n  materials_name: paper (fiber product)\n\n  techniques_name: printing (process)\n\n  object_colour: grey monochrome\n\n  physical_appearance: The image shows a photograph in black-and-white. It has a black frame and its border is white in colour. There is a single set of railroad that is visible in the image. The railroad proceeds in a straight line. The components of the railroad\n such as the ballast\n beams\n and clips\n are also visible in the image. At the top left hand corner of the photograph\n the sky can be seen.\n\n  subject_terms_1: railroads (infrastructures)\n\n  subject_terms_2: Railroads Pertadbiran Keretapi Tanah Melayu Black-and-white photography\n\n  subject_terms_3: Pertadbiran Keretapi Tanah Melayu Rail transport Artistic photography\n\n  sgcool_label_text: \\This image is part of the \\\\Tracking Memories\\\\ collection by the late Mr Kwek Leng Joo. The collection captures different aspects of the Malayan Railway story in Singapore\n",
  "createdDate": "20201125084533",
  "version": 0,
  "latest": false,
  "roles": [],
  "metadata": {
    "accession_no_csv": "2016-00501",
    "Image": "",
    "object_work_type": "black-and-white photographs",
    "title_text": "Untitled (railway track)",
    "preference": "main",
    "title_language": "",
    "creator_2": "Kwek Leng Joo",
    "creator_1": "Kwek, Leng Joo",
    "creator_role": "photographers",
    "creation_date": "2010",
    "creation_place_original_location": "Malaysia Singapore",
    "inscriptions": "",
    "inscription_language": "",
    "shape": "rectangular",
    "materials_name": "paper (fiber product)",
    "techniques_name": "printing (process)",
    "object_colour": "grey monochrome",
    "physical_appearance": "The image shows a photograph in black-and-white. It has a black frame and its border is white in colour. There is a single set of railroad that is visible in the image. The railroad proceeds in a straight line. The components of the railroad, such as the ballast, beams, and clips, are also visible in the image. At the top left hand corner of the photograph, the sky can be seen.",
    "subject_terms_1": "railroads (infrastructures)",
    "subject_terms_2": "Railroads Pertadbiran Keretapi Tanah Melayu Black-and-white photography",
    "subject_terms_3": "Pertadbiran Keretapi Tanah Melayu Rail transport Artistic photography",
    "sgcool_label_text": "\"This image is part of the \"\"Tracking Memories\"\" collection by the late Mr Kwek Leng Joo. The collection captures different aspects of the Malayan Railway story in Singapore"
  },
  "nlpDate": "20201125084533",
  "connectorId": 0,
  "tags": {}
}