{"id":"2016-00704","title":"Brown Checked Baju Panjang","source":"Bumblebee","path":"./Data/json/","content":"accession_no_csv:2016-00704\nImage:\nobject_work_type:folk costume\ntitle_text:Brown Checked Baju Panjang\npreference:main\ntitle_language:\ncreation_date:late 19th - early 20th century\ncreation_place_original_location:Pulau Pinang (Malaysia : State)\nstyles_periods_indexing_terms:Peranakan\ninscriptions:\ninscription_language:\nshape:irregular\ntechniques_name:sewing (needleworking technique)\nobject_colour:brown (color) yellow (color) dark purple\nphysical_appearance:This is a baju panjang. It is printed with yellow and dark purple checked pattern\n against a dark brown background. There is a floral bouquet motif printed within each square.\nsubject_terms_1:flowers (motifs) Peranakan checker pattern tops (garments\n general) blouses (main garments)\nsubject_terms_2:Ethnic costume Motifs Peranakan (Asian people) Blouses\nsubject_terms_3:Peranakan costumes\nsubject_terms_4:Baju Panjang\nsgcool_label_text:The baju panjang is printed with yellow and dark purple checks against a dark brown background\n with a floral bouquet motif within each square. It is lined with panels of linen on the inside. Block-printed batik cotton like this was popular in the Straits Settlements in the late 19th-early 20th century. It is part of a donation which contains a mixture of garments worn by Peranakan men and women.","createdDate":"20201018182635","version":0,"latest":false,"roles":[],"metadata":{"accession_no_csv":"2016-00704","Image":"","object_work_type":"folk costume","title_text":"Brown Checked Baju Panjang","preference":"main","title_language":"","creation_date":"late 19th - early 20th century","creation_place_original_location":"Pulau Pinang (Malaysia : State)","styles_periods_indexing_terms":"Peranakan","inscriptions":"","inscription_language":"","shape":"irregular","techniques_name":"sewing (needleworking technique)","object_colour":"brown (color) yellow (color) dark purple","physical_appearance":"This is a baju panjang. It is printed with yellow and dark purple checked pattern, against a dark brown background. There is a floral bouquet motif printed within each square.","subject_terms_1":"flowers (motifs) Peranakan checker pattern tops (garments, general) blouses (main garments)","subject_terms_2":"Ethnic costume Motifs Peranakan (Asian people) Blouses","subject_terms_3":"Peranakan costumes","subject_terms_4":"Baju Panjang","sgcool_label_text":"The baju panjang is printed with yellow and dark purple checks against a dark brown background, with a floral bouquet motif within each square. It is lined with panels of linen on the inside. Block-printed batik cotton like this was popular in the Straits Settlements in the late 19th-early 20th century. It is part of a donation which contains a mixture of garments worn by Peranakan men and women."},"nlpDate":"20201018182635","connectorId":0,"tags":{}}