{
  "id": "2016-00681",
  "title": "A Group of 4 Ribbons Patterned Ribbons",
  "source": "Bumblebee",
  "path": "./Data/json/",
  "content": "\n  accession_no_csv: 2016-00681\n\n  Image: \n\n  object_work_type: ribbon (material)\n\n  title_text: A Group of 4 Ribbons Patterned Ribbons\n\n  preference: alternate main\n\n  title_language: \n\n  creation_date: 20th century\n\n  creation_place_original_location: Straits Settlements Indonesia\n\n  styles_periods_indexing_terms: Peranakan\n\n  inscriptions: \n\n  inscription_language: \n\n  shape: irregular\n\n  materials_name: cotton (textile)\n\n  techniques_name: sewing (needleworking technique) embroidering\n\n  object_colour: multicolored\n\n  physical_appearance: This is a set of four rolls of ribbons. They are of varying lengths and embroided designs. The roll on the top-left has a light background\n with a scrolling red and blue lace pattern. The roll on the bottom-left has a scallop edge on one side\n with a scrolling flower and leaf pattern in red. The roll in the center has a blue geometric pattern. The roll on the right has a repeated square pattern in blue and gray.\n\n  subject_terms_1: scrolls (motifs) motifs implements (object genre)\n\n  subject_terms_2: Ribbons Motifs\n\n  subject_terms_3: Textile art and design\n\n  sgcool_label_text: There are 4 rolls of ribbon of varying lengths and embroidered designs. It is part of a donation which contains a mixture of materials used in the making of kebayas and baju panjangs.\n",
  "createdDate": "20201120223707",
  "version": 0,
  "latest": false,
  "roles": [],
  "metadata": {
    "accession_no_csv": "2016-00681",
    "Image": "",
    "object_work_type": "ribbon (material)",
    "title_text": "A Group of 4 Ribbons Patterned Ribbons",
    "preference": "alternate main",
    "title_language": "",
    "creation_date": "20th century",
    "creation_place_original_location": "Straits Settlements Indonesia",
    "styles_periods_indexing_terms": "Peranakan",
    "inscriptions": "",
    "inscription_language": "",
    "shape": "irregular",
    "materials_name": "cotton (textile)",
    "techniques_name": "sewing (needleworking technique) embroidering",
    "object_colour": "multicolored",
    "physical_appearance": "This is a set of four rolls of ribbons. They are of varying lengths and embroided designs. The roll on the top-left has a light background, with a scrolling red and blue lace pattern. The roll on the bottom-left has a scallop edge on one side, with a scrolling flower and leaf pattern in red. The roll in the center has a blue geometric pattern. The roll on the right has a repeated square pattern in blue and gray.",
    "subject_terms_1": "scrolls (motifs) motifs implements (object genre)",
    "subject_terms_2": "Ribbons Motifs",
    "subject_terms_3": "Textile art and design",
    "sgcool_label_text": "There are 4 rolls of ribbon of varying lengths and embroidered designs. It is part of a donation which contains a mixture of materials used in the making of kebayas and baju panjangs."
  },
  "nlpDate": "20201120223707",
  "connectorId": 0,
  "tags": {}
}