{"id":"2016-00370","title":"Turban ornament in the form of a parrot","source":"Bumblebee","path":"./Data/json/","content":"accession_no_csv:2016-00370\nImage:\nobject_work_type:folk costume jewelry worn on costume\ntitle_text:Turban ornament in the form of a parrot\npreference:main\ntitle_language:\ncreation_date:19th century\ncreation_place_original_location:Jaipur (India)\nstyles_periods_indexing_terms:Indian (South Asian)\ninscriptions:\ninscription_language:\nshape:irregular\nmaterials_name:enamel paint diamond (mineral) gold (metal) pearl (animal material) emerald (mineral)\ntechniques_name:carving (processes) painting (image making)\nobject_colour:multicolored\nphysical_appearance:This turban ornament is in a shape of a parrot\n decorated in gold\n enamel\n and gems. The parrot is perched on a curling leaf. It is decorated with red and green enamel\n with added elements of white enamel and gold. The wings are decorated with tear-drop diamonds. On its head\n there is a rosette attached by a stem. The bird holds in its beak a semi-spherical ornament with seed pearl and emerald tassels. The ornament is perched on a stand.\nsubject_terms_1:flower (motif) birds (motifs) worn costume accessories ornaments (object genre) jewelry\nsubject_terms_2:Jewelry Dress accessories Motifs Ethnic costume\nsubject_terms_3:Indian costumes Jewellery\nsubject_terms_4:turra\nsgcool_label_text:A gold\n enamelled\n and gem-set turban ornament (turra) in the form of a parrot perched on a curling leaf. It is decorated with translucent red and green enamel\n with highlights of opaque white enamel. The wings are denoted by large\n tear-drop diamonds. A rosette above is hinged at the stem and quivers when worn. The bird holds a semi-spherical ornament with seed pearl and emerald tassels (probably a later replacement) which also tremble when worn. This object shows the taste for luxury objects in Northern India in the 19th century. In Mughal India craftsmen reached new heights of technical virtuosity especially during the reign of Shah Jahan (1628-1658). The motifs in the gem work and enamelling of flowers\n plants\n and scrolling vines\n and the parrot\n allude to paradise gardens on earth. It would have been highly prized and made for a privileged few.","createdDate":"20201018182635","version":0,"latest":false,"roles":[],"metadata":{"accession_no_csv":"2016-00370","Image":"","object_work_type":"folk costume jewelry worn on costume","title_text":"Turban ornament in the form of a parrot","preference":"main","title_language":"","creation_date":"19th century","creation_place_original_location":"Jaipur (India)","styles_periods_indexing_terms":"Indian (South Asian)","inscriptions":"","inscription_language":"","shape":"irregular","materials_name":"enamel paint diamond (mineral) gold (metal) pearl (animal material) emerald (mineral)","techniques_name":"carving (processes) painting (image making)","object_colour":"multicolored","physical_appearance":"This turban ornament is in a shape of a parrot, decorated in gold, enamel, and gems. The parrot is perched on a curling leaf. It is decorated with red and green enamel, with added elements of white enamel and gold. The wings are decorated with tear-drop diamonds. On its head, there is a rosette attached by a stem. The bird holds in its beak a semi-spherical ornament with seed pearl and emerald tassels. The ornament is perched on a stand.","subject_terms_1":"flower (motif) birds (motifs) worn costume accessories ornaments (object genre) jewelry","subject_terms_2":"Jewelry Dress accessories Motifs Ethnic costume","subject_terms_3":"Indian costumes Jewellery","subject_terms_4":"turra","sgcool_label_text":"A gold, enamelled, and gem-set turban ornament (turra) in the form of a parrot perched on a curling leaf. It is decorated with translucent red and green enamel, with highlights of opaque white enamel. The wings are denoted by large, tear-drop diamonds. A rosette above is hinged at the stem and quivers when worn. The bird holds a semi-spherical ornament with seed pearl and emerald tassels (probably a later replacement) which also tremble when worn. This object shows the taste for luxury objects in Northern India in the 19th century. In Mughal India craftsmen reached new heights of technical virtuosity especially during the reign of Shah Jahan (1628-1658). The motifs in the gem work and enamelling of flowers, plants, and scrolling vines, and the parrot, allude to paradise gardens on earth. It would have been highly prized and made for a privileged few."},"nlpDate":"20201018182635","connectorId":0,"tags":{}}