{"id":"2016-00632","title":"Wedding invitation of Velautham Rengasamy and Davamani Krishnasamy","source":"Bumblebee","path":"./Data/json/","content":"accession_no_csv:2016-00632\nImage:\nobject_work_type:invitations\ntitle_text:Wedding invitation of Velautham Rengasamy and Davamani Krishnasamy\npreference:main\ntitle_language:\ncreation_date:12-Dec-76\ncreation_place_original_location:Singapore\ninscriptions:\ninscription_language:\nshape:rectangular\nmaterials_name:paper (fiber product)\ntechniques_name:printing (process)\nobject_colour:multicoloured\nphysical_appearance:\\The image displays an invitation card. The invitation card is written both in Tamil scripts and the English language. Near the bottom of the invitation\n the word \\\\Wedding\\\\ is stated in a type of font that utilizes musical instruments for the strokes of each letter. At the middle of the invitation\nsubject_terms_1:the date \\\\12.12.1976\\\\ is stated. There is a passport-sized photograph of a man at the top centre of the invitation.   \\ weddings (ceremonies) customs (social concepts)\nsubject_terms_2:Wedding announcements Marriage Special events Marriage customs and rites\nsubject_terms_3:Invitation cards\nsubject_terms_4:Marriage customs","createdDate":"20201018182635","version":0,"latest":false,"roles":[],"metadata":{"accession_no_csv":"2016-00632","Image":"","object_work_type":"invitations","title_text":"Wedding invitation of Velautham Rengasamy and Davamani Krishnasamy","preference":"main","title_language":"","creation_date":"12-Dec-76","creation_place_original_location":"Singapore","inscriptions":"","inscription_language":"","shape":"rectangular","materials_name":"paper (fiber product)","techniques_name":"printing (process)","object_colour":"multicoloured","physical_appearance":"\"The image displays an invitation card. The invitation card is written both in Tamil scripts and the English language. Near the bottom of the invitation, the word \"\"Wedding\"\" is stated in a type of font that utilizes musical instruments for the strokes of each letter. At the middle of the invitation","subject_terms_1":"the date \"\"12.12.1976\"\" is stated. There is a passport-sized photograph of a man at the top centre of the invitation.   \" weddings (ceremonies) customs (social concepts)","subject_terms_2":"Wedding announcements Marriage Special events Marriage customs and rites","subject_terms_3":"Invitation cards","subject_terms_4":"Marriage customs"},"nlpDate":"20201018182635","connectorId":0,"tags":{}}