{"id":"2016-00758","title":"Oil lamp","source":"Bumblebee","path":"./Data/json/","content":"accession_no_csv:2016-00758\nImage:\nobject_work_type:oil lamps\ntitle_text:Oil lamp\npreference:main\ntitle_language:\ncreation_date:1900-1920\ncreation_place_original_location:Singapore\ninscriptions:\ninscription_language:\nshape:irregular\nmaterials_name:brass (alloy)\ntechniques_name:forging (metal forming)\nobject_colour:bronze (color)\nphysical_appearance:This is a brass oil lamp. It stands on a circular base. There is a dish just above the base. The dish is connected to the top dish by a thin metal body. The body has several decorative circular ridges. There is a gold spoon sitting in the bottom dish.\nsubject_terms_1:altar components Peranakan religious ceremonies Ceremonial objects\nsubject_terms_2:Lamps Altars Peranakan (Asian people) Rites and ceremonies Ceremonial objects\nsubject_terms_3:Religious life and practices\nsgcool_label_text:This brass oil lamp was used by Peranakans for their altars and was placed within a red and gold lamp screen. The oil lamp comes with a small brass spoon which is used to add oil to the lamp to keep the fire going for religious ceremonies or on special occasions like Chinese New Year.\\r\\n\\r\\nThis item is donated by the family of prominent Peranakan\n Ong Sam Leong (b. 1857\n Singapore – d. 7 February 1918\n Singapore). It comes from his ancestral home of Bukit Rose\n formerly at 259 Bukit Timah Road. Ong was a well-known successful businessman who made is money in the mining of phosphate on Christmas island\n which was historically a territory of colonial Singapore.","createdDate":"20201018182636","version":0,"latest":false,"roles":[],"metadata":{"accession_no_csv":"2016-00758","Image":"","object_work_type":"oil lamps","title_text":"Oil lamp","preference":"main","title_language":"","creation_date":"1900-1920","creation_place_original_location":"Singapore","inscriptions":"","inscription_language":"","shape":"irregular","materials_name":"brass (alloy)","techniques_name":"forging (metal forming)","object_colour":"bronze (color)","physical_appearance":"This is a brass oil lamp. It stands on a circular base. There is a dish just above the base. The dish is connected to the top dish by a thin metal body. The body has several decorative circular ridges. There is a gold spoon sitting in the bottom dish.","subject_terms_1":"altar components Peranakan religious ceremonies Ceremonial objects","subject_terms_2":"Lamps Altars Peranakan (Asian people) Rites and ceremonies Ceremonial objects","subject_terms_3":"Religious life and practices","sgcool_label_text":"This brass oil lamp was used by Peranakans for their altars and was placed within a red and gold lamp screen. The oil lamp comes with a small brass spoon which is used to add oil to the lamp to keep the fire going for religious ceremonies or on special occasions like Chinese New Year.\r\n\r\nThis item is donated by the family of prominent Peranakan, Ong Sam Leong (b. 1857, Singapore – d. 7 February 1918, Singapore). It comes from his ancestral home of Bukit Rose, formerly at 259 Bukit Timah Road. Ong was a well-known successful businessman who made is money in the mining of phosphate on Christmas island, which was historically a territory of colonial Singapore."},"nlpDate":"20201018182636","connectorId":0,"tags":{}}