{
  "id": "2016-00080",
  "title": "Invitation card for farewell performance of Carnatic music",
  "source": "Bumblebee",
  "path": "./Data/json/",
  "content": "\n  accession_no_csv: 2016-00080\n\n  Image: \n\n  object_work_type: invitations\n\n  title_text: Invitation card for farewell performance of Carnatic music\n\n  preference: main\n\n  title_language: \n\n  creator_2: Unknown\n\n  creation_date: 7-Mar-65\n\n  creation_place_original_location: Singapore\n\n  styles_periods_indexing_terms: Not indicated\n\n  inscriptions: \n\n  inscription_language: \n\n  scale_type: Not indicated\n\n  shape: rectangular\n\n  materials_name: printing paper\n\n  techniques_name: printing (process)\n\n  object_colour: multicoloured\n\n  physical_appearance: \\The image shows an invitation card. It is rectangular in shape and it has a brown background. \\\\M.V. Gurusamy\\\\ is handwritten on the invitation card. \\\\Sunday\n\n  subject_terms_1: 7th March musical performances associations\n\n  subject_terms_2: 1965 at 6.30 p.m. at The Indian Association Performances Carnatic music Singapore Indian Association Musicians\n\n  subject_terms_3: Balestier Road Performing Arts Indian music Singapore Indian Association\n\n  subject_terms_4: Singapore\\\\ is stated at the bottom. \\\n\n  context_1: musicians\n\n  context_2: Invitation cards\n\n  context_3: Musicians\n",
  "createdDate": "20201120223706",
  "version": 0,
  "latest": false,
  "roles": [],
  "metadata": {
    "accession_no_csv": "2016-00080",
    "Image": "",
    "object_work_type": "invitations",
    "title_text": "Invitation card for farewell performance of Carnatic music",
    "preference": "main",
    "title_language": "",
    "creator_2": "Unknown",
    "creation_date": "7-Mar-65",
    "creation_place_original_location": "Singapore",
    "styles_periods_indexing_terms": "Not indicated",
    "inscriptions": "",
    "inscription_language": "",
    "scale_type": "Not indicated",
    "shape": "rectangular",
    "materials_name": "printing paper",
    "techniques_name": "printing (process)",
    "object_colour": "multicoloured",
    "physical_appearance": "\"The image shows an invitation card. It is rectangular in shape and it has a brown background. \"\"M.V. Gurusamy\"\" is handwritten on the invitation card. \"\"Sunday",
    "subject_terms_1": "7th March musical performances associations",
    "subject_terms_2": "1965 at 6.30 p.m. at The Indian Association Performances Carnatic music Singapore Indian Association Musicians",
    "subject_terms_3": "Balestier Road Performing Arts Indian music Singapore Indian Association",
    "subject_terms_4": "Singapore\"\" is stated at the bottom. \"",
    "context_1": "musicians",
    "context_2": "Invitation cards",
    "context_3": "Musicians"
  },
  "nlpDate": "20201120223706",
  "connectorId": 0,
  "tags": {}
}