{"id":"2016-00112-001","title":"Newspaper clipping in Tamil reporting the kidnapping of Mr. Appavoo Kandiar #1 A set of five newspaper clippings reporting the kidnapping of Mr.Appavoo Kandiar","source":"Bumblebee","path":"./Data/json/","content":"accession_no_csv:2016-00112-001\nImage:\nobject_work_type:clippings (information artifacts)\ntitle_text:Newspaper clipping in Tamil reporting the kidnapping of Mr. Appavoo Kandiar #1 A set of five newspaper clippings reporting the kidnapping of Mr.Appavoo Kandiar\npreference:main alternate\ntitle_language:\ncreator_2:Tamil Murasu\ncreator_role:publishers\ncreation_date:19570924\ncreation_place_original_location:Singapore\ninscriptions:\ninscription_language:\nshape:rectangular\nmaterials_name:paper (fiber product)\ntechniques_name:printing (process)\nobject_colour:black-and-white (colours)\nphysical_appearance:\\The image shows a newspaper clipping. All of the words are written in Tamil. The date\n \\\\24.09.1957\\\\\nsubject_terms_1:is displayed on upper left hand side of the newspaper. ture of Mr Appavoo Kandiar is displayed at the right hand side of the newspaper crime contractors newspapers\nsubject_terms_2:below the headlines in Tamil. A picture of several wooden crates and containers are displayed at the left hand side of the newspaper.\\ Ransom Contractors Kidnapping victims Millionaires Clippings (Books\n newspapers\n etc.)\nsubject_terms_3:abduction Crime Kandiar\n Appavoo\nsubject_terms_4:Newspapers\ncontext_1:Daily newspapers","createdDate":"20201018182635","version":0,"latest":false,"roles":[],"metadata":{"accession_no_csv":"2016-00112-001","Image":"","object_work_type":"clippings (information artifacts)","title_text":"Newspaper clipping in Tamil reporting the kidnapping of Mr. Appavoo Kandiar #1 A set of five newspaper clippings reporting the kidnapping of Mr.Appavoo Kandiar","preference":"main alternate","title_language":"","creator_2":"Tamil Murasu","creator_role":"publishers","creation_date":"19570924","creation_place_original_location":"Singapore","inscriptions":"","inscription_language":"","shape":"rectangular","materials_name":"paper (fiber product)","techniques_name":"printing (process)","object_colour":"black-and-white (colours)","physical_appearance":"\"The image shows a newspaper clipping. All of the words are written in Tamil. The date, \"\"24.09.1957\"\"","subject_terms_1":"is displayed on upper left hand side of the newspaper. ture of Mr Appavoo Kandiar is displayed at the right hand side of the newspaper crime contractors newspapers","subject_terms_2":"below the headlines in Tamil. A picture of several wooden crates and containers are displayed at the left hand side of the newspaper.\" Ransom Contractors Kidnapping victims Millionaires Clippings (Books, newspapers, etc.)","subject_terms_3":"abduction Crime Kandiar, Appavoo","subject_terms_4":"Newspapers","context_1":"Daily newspapers"},"nlpDate":"20201018182635","connectorId":0,"tags":{}}