{
  "id": "2016-00922",
  "title": "Miss Symes Memorial Plaque  Miss Symes Memorial Plaque",
  "source": "Bumblebee",
  "path": "./Data/json/",
  "content": "\n  accession_no_csv: 2016-00922\n\n  Image: \n\n  object_work_type: commemorative plaques plaques (flat objects) commemorative plaques plaques (flat objects)\n\n  title_text: Miss Symes Memorial Plaque  Miss Symes Memorial Plaque\n\n  preference: main main\n\n  title_language: \n\n  creator_2: British Servicemen British Servicemen\n\n  creator_1: Great Britain. Army Great Britain. Army\n\n  creator_role: creators creators\n\n  creation_date: 1960s 1960s\n\n  creation_place_original_location: Singapore Singapore\n\n  styles_periods_indexing_terms: NA NA\n\n  inscriptions: \n\n  inscription_language: \n\n  scale_type: NA NA\n\n  shape: rectangular cuboid rectangular cuboid\n\n  materials_name: stone (worked rock) stone (worked rock)\n\n  techniques_name: forming (physical activity) carving (processes) forming (physical activity) carving (processes)\n\n  object_colour: grey (colour) grey (colour)\n\n  edition_description: NA NA\n\n  physical_appearance: \\The image shows a commemorative plaque. It is rectangular in shape and it has a grey background. There are inscriptions on the front of the commemorative plaque\n relating to the death of \\\\Miss Kathleen Leslie Symes\\\\ and her contributions to the \\\\Sandes Soldiers\\u0027 Home\\\\.\\ \\The image shows a commemorative plaque. It is rectangular in shape and it has a grey background. There are inscriptions on the front of the commemorative plaque\n relating to the death of \\\\Miss Kathleen Leslie Symes\\\\ and her contributions to the \\\\Sandes Soldiers\\u0027 Home\\\\.\\\n\n  subject_terms_1: recreation areas military personnel soldiers founders (originators) recreation areas military personnel soldiers founders (originators)\n\n  subject_terms_2: Plaques\n plaquettes Recreation areas Soldiers Plaques\n plaquettes Recreation areas Soldiers\n\n  subject_terms_3: Sandes Soldiers Home (Singapore) Pioneers Sandes Soldiers Home (Singapore) Pioneers\n\n  subject_terms_4: NA NA\n\n  context_1: NA NA\n\n  context_2: NA NA\n\n  context_3: NA NA\n\n  context_4: NA NA\n\n  context_5: NA NA\n\n  context_6: NA NA\n\n  context_7: NA NA\n\n  context_8: NA NA\n\n  context_9: NA NA\n\n  context_10: NA NA\n\n  context_11: NA NA\n\n  context_12: NA NA\n\n  context_13: NA NA\n\n  context_14: NA NA\n\n  context_15: NA NA\n\n  context_16: NA NA\n\n  context_17: NA NA\n\n  context_18: NA NA\n\n  context_19: NA NA\n\n  context_20: NA NA\n\n  context_21: NA NA\n\n  context_22: NA NA\n\n  context_23: NA NA\n\n  context_24: NA NA\n\n  sgcool_label_text: \\This plaque was built by former British servicemen in memory of the founder of the Sandes Soldiers Home in Singapore\n Miss Kathleen Leslie Symes. The Home\n orignally located at Portsdown Road where The Temasek Club used to be\n was opened in 1949. With facilities such as a swimming pool\n canteen\n tennis courts and a billiards room\n the Home provided a recreational space for British servicemen to relax and to get together with their family while they were on leave. Built on the premise of a \\\\home away from home\\\\ \\This plaque was built by former British servicemen in memory of the founder of the Sandes Soldiers Home in Singapore\n Miss Kathleen Leslie Symes. The Home\n orignally located at Portsdown Road where The Temasek Club used to be\n was opened in 1949. With facilities such as a swimming pool\n canteen\n tennis courts and a billiards room\n the Home provided a recreational space for British servicemen to relax and to get together with their family while they were on leave. Built on the premise of a \\\\home away from home\\\\\n",
  "createdDate": "20201120223707",
  "version": 0,
  "latest": false,
  "roles": [],
  "metadata": {
    "accession_no_csv": "2016-00922",
    "Image": "",
    "object_work_type": "commemorative plaques plaques (flat objects) commemorative plaques plaques (flat objects)",
    "title_text": "Miss Symes Memorial Plaque  Miss Symes Memorial Plaque",
    "preference": "main main",
    "title_language": "",
    "creator_2": "British Servicemen British Servicemen",
    "creator_1": "Great Britain. Army Great Britain. Army",
    "creator_role": "creators creators",
    "creation_date": "1960s 1960s",
    "creation_place_original_location": "Singapore Singapore",
    "styles_periods_indexing_terms": "NA NA",
    "inscriptions": "",
    "inscription_language": "",
    "scale_type": "NA NA",
    "shape": "rectangular cuboid rectangular cuboid",
    "materials_name": "stone (worked rock) stone (worked rock)",
    "techniques_name": "forming (physical activity) carving (processes) forming (physical activity) carving (processes)",
    "object_colour": "grey (colour) grey (colour)",
    "edition_description": "NA NA",
    "physical_appearance": "\"The image shows a commemorative plaque. It is rectangular in shape and it has a grey background. There are inscriptions on the front of the commemorative plaque, relating to the death of \"\"Miss Kathleen Leslie Symes\"\" and her contributions to the \"\"Sandes Soldiers\u0027 Home\"\".\" \"The image shows a commemorative plaque. It is rectangular in shape and it has a grey background. There are inscriptions on the front of the commemorative plaque, relating to the death of \"\"Miss Kathleen Leslie Symes\"\" and her contributions to the \"\"Sandes Soldiers\u0027 Home\"\".\"",
    "subject_terms_1": "recreation areas military personnel soldiers founders (originators) recreation areas military personnel soldiers founders (originators)",
    "subject_terms_2": "Plaques, plaquettes Recreation areas Soldiers Plaques, plaquettes Recreation areas Soldiers",
    "subject_terms_3": "Sandes Soldiers Home (Singapore) Pioneers Sandes Soldiers Home (Singapore) Pioneers",
    "subject_terms_4": "NA NA",
    "context_1": "NA NA",
    "context_2": "NA NA",
    "context_3": "NA NA",
    "context_4": "NA NA",
    "context_5": "NA NA",
    "context_6": "NA NA",
    "context_7": "NA NA",
    "context_8": "NA NA",
    "context_9": "NA NA",
    "context_10": "NA NA",
    "context_11": "NA NA",
    "context_12": "NA NA",
    "context_13": "NA NA",
    "context_14": "NA NA",
    "context_15": "NA NA",
    "context_16": "NA NA",
    "context_17": "NA NA",
    "context_18": "NA NA",
    "context_19": "NA NA",
    "context_20": "NA NA",
    "context_21": "NA NA",
    "context_22": "NA NA",
    "context_23": "NA NA",
    "context_24": "NA NA",
    "sgcool_label_text": "\"This plaque was built by former British servicemen in memory of the founder of the Sandes Soldiers Home in Singapore, Miss Kathleen Leslie Symes. The Home, orignally located at Portsdown Road where The Temasek Club used to be, was opened in 1949. With facilities such as a swimming pool, canteen, tennis courts and a billiards room, the Home provided a recreational space for British servicemen to relax and to get together with their family while they were on leave. Built on the premise of a \"\"home away from home\"\" \"This plaque was built by former British servicemen in memory of the founder of the Sandes Soldiers Home in Singapore, Miss Kathleen Leslie Symes. The Home, orignally located at Portsdown Road where The Temasek Club used to be, was opened in 1949. With facilities such as a swimming pool, canteen, tennis courts and a billiards room, the Home provided a recreational space for British servicemen to relax and to get together with their family while they were on leave. Built on the premise of a \"\"home away from home\"\""
  },
  "nlpDate": "20201120223707",
  "connectorId": 0,
  "tags": {}
}