{"id":"2016-00489","title":"Untitled (locomotive no. 25107)","source":"Bumblebee","path":"./Data/json/","content":"accession_no_csv:2016-00489\nImage:\nobject_work_type:black-and-white photographs\ntitle_text:Untitled (locomotive no. 25107)\npreference:main\ntitle_language:\ncreator_2:Kwek Leng Joo\ncreator_1:Kwek\n Leng Joo\ncreator_role:photographers\ncreation_date:2010\ncreation_place_original_location:Singapore Malaysia\ninscriptions:\ninscription_language:\nshape:rectangular\nmaterials_name:paper (fiber product)\ntechniques_name:printing (process)\nobject_colour:grey monochrome\nphysical_appearance:\\The image shows a photograph in black-and-white. It has a black frame and its border is white in colour. Two sets of railroads can be seen\n but only one set is occupied by a train. The train has more more than five carriages attached to it\n and all these carriages have a single row of windows on their sides. The numerals \\\\25107\\\\ are displayed at the front of the locomotive\nsubject_terms_1:below its windscreen. The numbers and words railroads (infrastructure) trains (vehicle groupings) passenger cars (railroad cars)\nsubject_terms_2:\\\\P. Langkawi\\\\ and \\\\25107\\\\ Locomotives Railroads Railroad passenger cars Pertadbiran Keretapi Tanah Melayu Railroad trains\nsubject_terms_3:are displayed at the bottom front of the locomotive respectively.\\ Pertadbiran Keretapi Tanah Melayu Photography\nsubject_terms_4:locomotives\ncontext_1:Black-and-white photography\ncontext_2:Rail transport","createdDate":"20201018182635","version":0,"latest":false,"roles":[],"metadata":{"accession_no_csv":"2016-00489","Image":"","object_work_type":"black-and-white photographs","title_text":"Untitled (locomotive no. 25107)","preference":"main","title_language":"","creator_2":"Kwek Leng Joo","creator_1":"Kwek, Leng Joo","creator_role":"photographers","creation_date":"2010","creation_place_original_location":"Singapore Malaysia","inscriptions":"","inscription_language":"","shape":"rectangular","materials_name":"paper (fiber product)","techniques_name":"printing (process)","object_colour":"grey monochrome","physical_appearance":"\"The image shows a photograph in black-and-white. It has a black frame and its border is white in colour. Two sets of railroads can be seen, but only one set is occupied by a train. The train has more more than five carriages attached to it, and all these carriages have a single row of windows on their sides. The numerals \"\"25107\"\" are displayed at the front of the locomotive","subject_terms_1":"below its windscreen. The numbers and words railroads (infrastructure) trains (vehicle groupings) passenger cars (railroad cars)","subject_terms_2":"\"\"P. Langkawi\"\" and \"\"25107\"\" Locomotives Railroads Railroad passenger cars Pertadbiran Keretapi Tanah Melayu Railroad trains","subject_terms_3":"are displayed at the bottom front of the locomotive respectively.\" Pertadbiran Keretapi Tanah Melayu Photography","subject_terms_4":"locomotives","context_1":"Black-and-white photography","context_2":"Rail transport"},"nlpDate":"20201018182635","connectorId":0,"tags":{}}