{"id":"2016-00431-011","title":"The End of History - Intonation and Lautgebung (Book #2)","source":"Bumblebee","path":"./Data/json/","content":"accession_no_csv:2016-00431-011\nImage:\nobject_work_type:books\ntitle_text:The End of History - Intonation and Lautgebung (Book #2)\npreference:main\ntitle_language:English\ncreator_2:Alan Oei Herbert Rohmann (?)\ncreator_role:authors\ncreation_date:2008-2013 1939\ncreation_place_original_location:Berlin (Germany) Singapore\ninscriptions:\ninscription_language:\nshape:rectangular\nmaterials_name:paper (fiber product)\ntechniques_name:printing (process)\nobject_colour:orange (color)\nphysical_appearance:This is a German book titled \\u0027Intonation and Lautgebung in der Sprache von Lloyd George von Herbert Rohmann\\u0027. The title\n author and publisher is printed on the front cover. The cover is orange in colour. The edges are slightly folded.\nsubject_terms_1:\nsubject_terms_2:Books Intonation (Phonetics)\nsubject_terms_3:Non-fiction\nsubject_terms_4:\nsgcool_label_text:In 2009\n the local art public found – to its surprise – that a Singaporean painter active in the Nanyang period had escaped recognition from history books despite leaving behind 76 notable paintings. It was later revealed that Huang Wei never existed – at least not in real life – but was a fiction created by artist-curator Alan Oei. Oei has an enduring fixation with history painting but is troubled that it possesses pale relevance to art-making in the present day. In Huang Wei\n Oei entwined fiction with fact and created a character who stands as a metaphor for a vital but missing part of Singapore’s art history. In effect\n Huang Wei may be regarded as a performance on several levels\n and the relationship between creator and created echoes that of a two-way mirror. On one side\n the character of Huang Wei is a conduit and device for Oei to unravel his conundrum about time and history. Yet to ‘use’ Huang Wei entails Oei becoming a medium himself and ‘channelling’ his creation so that the meta-artist can step through time’s portals and enter a realm where history painting still reigns. Still\n even liminal spaces offer fleeting refuge and the stop-motion video Goliath unfolds to reveal the artist’s hand (Huang Wei\n and/or Oei?) in a continuous cycle of creating-destroying his painting\n time and again. Alan Oei (b. 1976\n Singapore) is an artist-curator interested in the workings between art history\n politics and community. He holds a Bachelor’s degree in Art History from Columbia University and a Diploma in Fine Arts from Lasalle College of the Arts. Huang Wei – a fictional post-war painter of maimed children – is the alter-ego Oei uses to present his paintings. His work has been shown in Malaysia\n Hong Kong\n Melbourne and New York. In addition\n Oei’s curatorial projects include the ‘OH! Open House’\n an annual art walkabout inside local neighbourhoods and residences. He was recently appointed the Artistic Director of Substation\n Singapore.","createdDate":"20201018182635","version":0,"latest":false,"roles":[],"metadata":{"accession_no_csv":"2016-00431-011","Image":"","object_work_type":"books","title_text":"The End of History - Intonation and Lautgebung (Book #2)","preference":"main","title_language":"English","creator_2":"Alan Oei Herbert Rohmann (?)","creator_role":"authors","creation_date":"2008-2013 1939","creation_place_original_location":"Berlin (Germany) Singapore","inscriptions":"","inscription_language":"","shape":"rectangular","materials_name":"paper (fiber product)","techniques_name":"printing (process)","object_colour":"orange (color)","physical_appearance":"This is a German book titled \u0027Intonation and Lautgebung in der Sprache von Lloyd George von Herbert Rohmann\u0027. The title, author and publisher is printed on the front cover. The cover is orange in colour. The edges are slightly folded.","subject_terms_1":"","subject_terms_2":"Books Intonation (Phonetics)","subject_terms_3":"Non-fiction","subject_terms_4":"","sgcool_label_text":"In 2009, the local art public found – to its surprise – that a Singaporean painter active in the Nanyang period had escaped recognition from history books despite leaving behind 76 notable paintings. It was later revealed that Huang Wei never existed – at least not in real life – but was a fiction created by artist-curator Alan Oei. Oei has an enduring fixation with history painting but is troubled that it possesses pale relevance to art-making in the present day. In Huang Wei, Oei entwined fiction with fact and created a character who stands as a metaphor for a vital but missing part of Singapore’s art history. In effect, Huang Wei may be regarded as a performance on several levels, and the relationship between creator and created echoes that of a two-way mirror. On one side, the character of Huang Wei is a conduit and device for Oei to unravel his conundrum about time and history. Yet to ‘use’ Huang Wei entails Oei becoming a medium himself and ‘channelling’ his creation so that the meta-artist can step through time’s portals and enter a realm where history painting still reigns. Still, even liminal spaces offer fleeting refuge and the stop-motion video Goliath unfolds to reveal the artist’s hand (Huang Wei, and/or Oei?) in a continuous cycle of creating-destroying his painting, time and again. Alan Oei (b. 1976, Singapore) is an artist-curator interested in the workings between art history, politics and community. He holds a Bachelor’s degree in Art History from Columbia University and a Diploma in Fine Arts from Lasalle College of the Arts. Huang Wei – a fictional post-war painter of maimed children – is the alter-ego Oei uses to present his paintings. His work has been shown in Malaysia, Hong Kong, Melbourne and New York. In addition, Oei’s curatorial projects include the ‘OH! Open House’, an annual art walkabout inside local neighbourhoods and residences. He was recently appointed the Artistic Director of Substation, Singapore."},"nlpDate":"20201018182635","connectorId":0,"tags":{}}