{
  "id": "2016-00692",
  "title": "Batik Bib",
  "source": "Bumblebee",
  "path": "./Data/json/",
  "content": "\n  accession_no_csv: 2016-00692\n\n  Image: \n\n  object_work_type: bibs (protective wear) batik art\n\n  title_text: Batik Bib\n\n  preference: main\n\n  title_language: \n\n  creation_date: 20th century\n\n  creation_place_original_location: Straits Settlements Indonesia\n\n  styles_periods_indexing_terms: Peranakan\n\n  inscriptions: \n\n  inscription_language: \n\n  shape: triangular\n\n  materials_name: cotton (textile) dye\n\n  techniques_name: sewing (needleworking technique) batik\n\n  object_colour: multicolored\n\n  physical_appearance: This is a batik bib. It is triangular in shape\n with a string at the top. It is embroided with a floral border at the top. The center of the bib features a patchwork triangular pattern.\n\n  subject_terms_1: flowers (motifs) embroidery (visual works) Peranakan childrenswear\n\n  subject_terms_2: Batik  Motifs Embroidery Peranakan (Asian people) Children\\u0027s clothing\n\n  subject_terms_3: Peranakan costumes Batik\n\n  sgcool_label_text: This triangular-shaped bib is made from a patchwork of cotton batik and simply embroidered with a floral border where it would have been tied around the neck of the child. It is part of a donation which contains a mixture of garments worn by Peranakan men and women.\n",
  "createdDate": "20201120223707",
  "version": 0,
  "latest": false,
  "roles": [],
  "metadata": {
    "accession_no_csv": "2016-00692",
    "Image": "",
    "object_work_type": "bibs (protective wear) batik art",
    "title_text": "Batik Bib",
    "preference": "main",
    "title_language": "",
    "creation_date": "20th century",
    "creation_place_original_location": "Straits Settlements Indonesia",
    "styles_periods_indexing_terms": "Peranakan",
    "inscriptions": "",
    "inscription_language": "",
    "shape": "triangular",
    "materials_name": "cotton (textile) dye",
    "techniques_name": "sewing (needleworking technique) batik",
    "object_colour": "multicolored",
    "physical_appearance": "This is a batik bib. It is triangular in shape, with a string at the top. It is embroided with a floral border at the top. The center of the bib features a patchwork triangular pattern.",
    "subject_terms_1": "flowers (motifs) embroidery (visual works) Peranakan childrenswear",
    "subject_terms_2": "Batik  Motifs Embroidery Peranakan (Asian people) Children\u0027s clothing",
    "subject_terms_3": "Peranakan costumes Batik",
    "sgcool_label_text": "This triangular-shaped bib is made from a patchwork of cotton batik and simply embroidered with a floral border where it would have been tied around the neck of the child. It is part of a donation which contains a mixture of garments worn by Peranakan men and women."
  },
  "nlpDate": "20201120223707",
  "connectorId": 0,
  "tags": {}
}