{
  "id": "2016-00525",
  "title": "Darul Islam Darul Islam",
  "source": "Bumblebee",
  "path": "./Data/json/",
  "content": "\n  accession_no_csv: 2016-00525\n\n  Image: \n\n  object_work_type: magazines (periodicals) magazines (periodicals)\n\n  title_text: Darul Islam Darul Islam\n\n  preference: main main\n\n  title_language: \n\n  creator_2: Not indicated Not indicated\n\n  creator_1: Not indicated Not indicated\n\n  creator_role: Not indicated Not indicated\n\n  creation_date: 1950 1950\n\n  creation_place_original_location: Singapore Singapore\n\n  styles_periods_indexing_terms: NA NA\n\n  inscriptions: \n\n  inscription_language: \n\n  scale_type: NA NA\n\n  shape: rectangular rectangular\n\n  materials_name: printing paper printing paper\n\n  techniques_name: printing (process) printing (process)\n\n  object_colour: multicoloured multicoloured\n\n  edition_description: Not indicated Not indicated\n\n  physical_appearance: \\The image displays the front cover of a magazine. Tamil inscriptions are present at the upper half of the front page. The numeral \\u00276\\u0027 can be seen at the bottom left hand side. \\\\Darul Islam\\\\ is stated at the bottom right hand side. The image of a palanquin being carried and transported by a group of people is depicted. Groups of men in religious headgear can be seen looking in the direction of the palanquin. A horse can also be discerned at the bottom left hand corner of the image. The left hand side of the magazine cover features a drawing depicting a palanquin on an elephant decked out in decorative coverings.\\ \\The image displays the front cover of a magazine. Tamil inscriptions are present at the upper half of the front page. The numeral \\u00276\\u0027 can be seen at the bottom left hand side. \\\\Darul Islam\\\\ is stated at the bottom right hand side. The image of a palanquin being carried and transported by a group of people is depicted. Groups of men in religious headgear can be seen looking in the direction of the palanquin. A horse can also be discerned at the bottom left hand corner of the image. The left hand side of the magazine cover features a drawing depicting a palanquin on an elephant decked out in decorative coverings.\\\n\n  subject_terms_1: politics Islam palanquins politics Islam palanquins\n\n  subject_terms_2: Periodicals Islam and politics Litters Periodicals Islam and politics Litters\n\n  subject_terms_3: Periodicals Islam Periodicals Islam\n\n  subject_terms_4: NA NA\n\n  context_1: NA NA\n\n  context_2: NA NA\n\n  context_3: NA NA\n\n  context_4: NA NA\n\n  context_5: NA NA\n\n  context_6: NA NA\n\n  context_7: NA NA\n\n  context_8: NA NA\n\n  context_9: NA NA\n\n  context_10: NA NA\n\n  context_11: NA NA\n\n  context_12: NA NA\n\n  context_13: NA NA\n\n  context_14: NA NA\n\n  context_15: NA NA\n\n  context_16: NA NA\n\n  context_17: NA NA\n\n  context_18: NA NA\n\n  context_19: NA NA\n\n  context_20: NA NA\n\n  context_21: NA NA\n\n  context_22: NA NA\n\n  context_23: NA NA\n\n  context_24: NA NA\n\n  sgcool_label_text: This is a rare magazine as it shows another aspect of the South Asian Muslim community in Singapore.  It reveals the presence of the Singapore Indian Muslim League who were sympathetic to Mr Muhammad Ali Jinnah (1876- 1948). This is a rare magazine as it shows another aspect of the South Asian Muslim community in Singapore.  It reveals the presence of the Singapore Indian Muslim League who were sympathetic to Mr Muhammad Ali Jinnah (1876- 1948).\n",
  "createdDate": "20201120223707",
  "version": 0,
  "latest": false,
  "roles": [],
  "metadata": {
    "accession_no_csv": "2016-00525",
    "Image": "",
    "object_work_type": "magazines (periodicals) magazines (periodicals)",
    "title_text": "Darul Islam Darul Islam",
    "preference": "main main",
    "title_language": "",
    "creator_2": "Not indicated Not indicated",
    "creator_1": "Not indicated Not indicated",
    "creator_role": "Not indicated Not indicated",
    "creation_date": "1950 1950",
    "creation_place_original_location": "Singapore Singapore",
    "styles_periods_indexing_terms": "NA NA",
    "inscriptions": "",
    "inscription_language": "",
    "scale_type": "NA NA",
    "shape": "rectangular rectangular",
    "materials_name": "printing paper printing paper",
    "techniques_name": "printing (process) printing (process)",
    "object_colour": "multicoloured multicoloured",
    "edition_description": "Not indicated Not indicated",
    "physical_appearance": "\"The image displays the front cover of a magazine. Tamil inscriptions are present at the upper half of the front page. The numeral \u00276\u0027 can be seen at the bottom left hand side. \"\"Darul Islam\"\" is stated at the bottom right hand side. The image of a palanquin being carried and transported by a group of people is depicted. Groups of men in religious headgear can be seen looking in the direction of the palanquin. A horse can also be discerned at the bottom left hand corner of the image. The left hand side of the magazine cover features a drawing depicting a palanquin on an elephant decked out in decorative coverings.\" \"The image displays the front cover of a magazine. Tamil inscriptions are present at the upper half of the front page. The numeral \u00276\u0027 can be seen at the bottom left hand side. \"\"Darul Islam\"\" is stated at the bottom right hand side. The image of a palanquin being carried and transported by a group of people is depicted. Groups of men in religious headgear can be seen looking in the direction of the palanquin. A horse can also be discerned at the bottom left hand corner of the image. The left hand side of the magazine cover features a drawing depicting a palanquin on an elephant decked out in decorative coverings.\"",
    "subject_terms_1": "politics Islam palanquins politics Islam palanquins",
    "subject_terms_2": "Periodicals Islam and politics Litters Periodicals Islam and politics Litters",
    "subject_terms_3": "Periodicals Islam Periodicals Islam",
    "subject_terms_4": "NA NA",
    "context_1": "NA NA",
    "context_2": "NA NA",
    "context_3": "NA NA",
    "context_4": "NA NA",
    "context_5": "NA NA",
    "context_6": "NA NA",
    "context_7": "NA NA",
    "context_8": "NA NA",
    "context_9": "NA NA",
    "context_10": "NA NA",
    "context_11": "NA NA",
    "context_12": "NA NA",
    "context_13": "NA NA",
    "context_14": "NA NA",
    "context_15": "NA NA",
    "context_16": "NA NA",
    "context_17": "NA NA",
    "context_18": "NA NA",
    "context_19": "NA NA",
    "context_20": "NA NA",
    "context_21": "NA NA",
    "context_22": "NA NA",
    "context_23": "NA NA",
    "context_24": "NA NA",
    "sgcool_label_text": "This is a rare magazine as it shows another aspect of the South Asian Muslim community in Singapore.  It reveals the presence of the Singapore Indian Muslim League who were sympathetic to Mr Muhammad Ali Jinnah (1876- 1948). This is a rare magazine as it shows another aspect of the South Asian Muslim community in Singapore.  It reveals the presence of the Singapore Indian Muslim League who were sympathetic to Mr Muhammad Ali Jinnah (1876- 1948)."
  },
  "nlpDate": "20201120223707",
  "connectorId": 0,
  "tags": {}
}