{
  "id": "2016-00158",
  "title": "Bul-bul-tara and a pick Bul-bul-tara",
  "source": "Bumblebee",
  "path": "./Data/json/",
  "content": "\n  accession_no_csv: 2016-00158\n\n  Image: \n\n  object_work_type: stringed instruments (musical instruments) plectra\n\n  title_text: Bul-bul-tara and a pick Bul-bul-tara\n\n  preference: main alternate\n\n  title_language: \n\n  creation_date: 1940-1980\n\n  creation_place_original_location: Singapore\n\n  inscriptions: \n\n  inscription_language: \n\n  shape: irregular\n\n  materials_name: string (fiber product) wood (plant material) paint (coating)\n\n  techniques_name: forming (physical activity) woodcarving painting (image-making)\n\n  object_colour: multicoloured\n\n  physical_appearance: The image shows a musical instrument and pick. The pick is red in colour and it is triangle in shape. A signature can be seen on one side of the pick. The body of the instrument looks worn out as the paintwork is chipped at some areas. Two strings can be seen along the neck of the bul-bul-tara\n from the bridge to the tuning pegs. A drawing of mountains can be discerned at the middle of the bul-bul-tara. There are numerous keys on on the instrument\n and they are white at the top and brown at the bottom.\n\n  subject_terms_1: music (performing arts) cultural artifacts\n\n  subject_terms_2: Bulbultarang Plectra (Music) Carnatic music Musical instruments\n\n  subject_terms_3: Instrumental music Indian music\n\n  sgcool_label_text: Mr. Retnam (b. 1918) was a prominent musician and a bul-bul-tara (Indian Banjo or Nagoya Harp) player. Born in Penang in 1918\n he arrived in Singapore in 1929 and pursued his interest in Indian music. He popularized the use of the bul-bul-tara in Indian classical music in Singapore. Mr Retnam formed the Rama Bhajana Mandali at Sri Veeramakaliamman Temple\n and performed alongside veterans of Indian music such as Pandit M Ramalingam and MV Gurusamy. He was also a member of the Ramakrishna Sangeetha Sabha\n and Singapore Carnatic Orchestra until 1984.\n",
  "createdDate": "20201120223706",
  "version": 0,
  "latest": false,
  "roles": [],
  "metadata": {
    "accession_no_csv": "2016-00158",
    "Image": "",
    "object_work_type": "stringed instruments (musical instruments) plectra",
    "title_text": "Bul-bul-tara and a pick Bul-bul-tara",
    "preference": "main alternate",
    "title_language": "",
    "creation_date": "1940-1980",
    "creation_place_original_location": "Singapore",
    "inscriptions": "",
    "inscription_language": "",
    "shape": "irregular",
    "materials_name": "string (fiber product) wood (plant material) paint (coating)",
    "techniques_name": "forming (physical activity) woodcarving painting (image-making)",
    "object_colour": "multicoloured",
    "physical_appearance": "The image shows a musical instrument and pick. The pick is red in colour and it is triangle in shape. A signature can be seen on one side of the pick. The body of the instrument looks worn out as the paintwork is chipped at some areas. Two strings can be seen along the neck of the bul-bul-tara, from the bridge to the tuning pegs. A drawing of mountains can be discerned at the middle of the bul-bul-tara. There are numerous keys on on the instrument, and they are white at the top and brown at the bottom.",
    "subject_terms_1": "music (performing arts) cultural artifacts",
    "subject_terms_2": "Bulbultarang Plectra (Music) Carnatic music Musical instruments",
    "subject_terms_3": "Instrumental music Indian music",
    "sgcool_label_text": "Mr. Retnam (b. 1918) was a prominent musician and a bul-bul-tara (Indian Banjo or Nagoya Harp) player. Born in Penang in 1918, he arrived in Singapore in 1929 and pursued his interest in Indian music. He popularized the use of the bul-bul-tara in Indian classical music in Singapore. Mr Retnam formed the Rama Bhajana Mandali at Sri Veeramakaliamman Temple, and performed alongside veterans of Indian music such as Pandit M Ramalingam and MV Gurusamy. He was also a member of the Ramakrishna Sangeetha Sabha, and Singapore Carnatic Orchestra until 1984."
  },
  "nlpDate": "20201120223706",
  "connectorId": 0,
  "tags": {}
}