{
  "id": "2016-00710",
  "title": "Green Baju (Top) Peiki and Koon (Skirt)",
  "source": "Bumblebee",
  "path": "./Data/json/",
  "content": "\n  accession_no_csv: 2016-00710\n\n  Image: \n\n  object_work_type: folk costume\n\n  title_text: Green Baju (Top) Peiki and Koon (Skirt)\n\n  preference: main\n\n  title_language: \n\n  creation_date: late 19th-20th century\n\n  creation_place_original_location: Straits Settlements\n\n  styles_periods_indexing_terms: Peranakan\n\n  inscriptions: \n\n  inscription_language: \n\n  shape: irregular\n\n  materials_name: silk (textile)\n\n  techniques_name: sewing (needleworking technique)\n\n  object_colour: green (color)\n\n  physical_appearance: This is a set baju peiki with top and skirt. It is made from patterned green silk fabric. The top is a long-sleeved jacket with mandarin collar lined with lace and frog buttons. The hem and cuffs are formed by a row of pleats.\n\n  subject_terms_1: Peranakan motifs pleats\n\n  subject_terms_2: Ethnic costume Peranakan (Asian people) Motifs Pleats (Sewing)\n\n  subject_terms_3: Peranakan costumes\n\n  subject_terms_4: Baju Peiki\n\n  sgcool_label_text: Known as a baju peiki or baju shanghai\n this long-sleeved jacket with a mandarin collar lined with lace and frog buttons is made from a richly patterned green silk fabric and thickly lined on the inside. Its hem and cuffs are formed by a single row of pleats. The matching skirt or koon is made using the same material and techniques. The cotton baju peiki could have been paired with batik sarong in less formal occasions. It is part of a donation which contains a mixture of garments worn by Peranakan men and women.\n",
  "createdDate": "20201120223707",
  "version": 0,
  "latest": false,
  "roles": [],
  "metadata": {
    "accession_no_csv": "2016-00710",
    "Image": "",
    "object_work_type": "folk costume",
    "title_text": "Green Baju (Top) Peiki and Koon (Skirt)",
    "preference": "main",
    "title_language": "",
    "creation_date": "late 19th-20th century",
    "creation_place_original_location": "Straits Settlements",
    "styles_periods_indexing_terms": "Peranakan",
    "inscriptions": "",
    "inscription_language": "",
    "shape": "irregular",
    "materials_name": "silk (textile)",
    "techniques_name": "sewing (needleworking technique)",
    "object_colour": "green (color)",
    "physical_appearance": "This is a set baju peiki with top and skirt. It is made from patterned green silk fabric. The top is a long-sleeved jacket with mandarin collar lined with lace and frog buttons. The hem and cuffs are formed by a row of pleats.",
    "subject_terms_1": "Peranakan motifs pleats",
    "subject_terms_2": "Ethnic costume Peranakan (Asian people) Motifs Pleats (Sewing)",
    "subject_terms_3": "Peranakan costumes",
    "subject_terms_4": "Baju Peiki",
    "sgcool_label_text": "Known as a baju peiki or baju shanghai, this long-sleeved jacket with a mandarin collar lined with lace and frog buttons is made from a richly patterned green silk fabric and thickly lined on the inside. Its hem and cuffs are formed by a single row of pleats. The matching skirt or koon is made using the same material and techniques. The cotton baju peiki could have been paired with batik sarong in less formal occasions. It is part of a donation which contains a mixture of garments worn by Peranakan men and women."
  },
  "nlpDate": "20201120223707",
  "connectorId": 0,
  "tags": {}
}