{"id":"2016-00096","title":"Thamizhavel G Sarangapany being garlanded","source":"Bumblebee","path":"./Data/json/","content":"accession_no_csv:2016-00096\nImage:\nobject_work_type:black-and-white photographs\ntitle_text:Thamizhavel G Sarangapany being garlanded\npreference:main\ntitle_language:\ncreation_date:1960s\ncreation_place_original_location:Singapore\ninscriptions:\ninscription_language:\nshape:rectangular\nmaterials_name:paper (fiber product)\ntechniques_name:printing (process) photographic processes\nobject_colour:grey monochrome\nphysical_appearance:The image shows a photograph that is in black-and-white. It is rectangular and it features four men\n of which two are sitting down while the other two are standing up. One man is adorned with a garland around his neck and another man standing across him is adjusting the position of the garland. Both of them are smiling. The background of the photograph suggests that it was taken in the interior of a building.\nsubject_terms_1:commemorations (events) honours\nsubject_terms_2:Black-and-white photography Caran?kapa?n?i\n 1903-1974 Tamil (Indic people)\nsubject_terms_3:Photography Thamizhavel Govindasamy Sarangapany\nsgcool_label_text:A native of Karuvakurichi village\n near Mannargudi town in Tamil Nadu\n S. Appavoo Kandiar was a general contractor specializing in pipe and cable laying\n handling of cargo and a concrete bricks supplier. Mr.Kandiar was a successful contractor; called a millionaire by the Straits Times in 1957\n he owned properties in Bukit Timah and Coronation Road areas. He was a contemporary of Indian pioneers such as P.Govindasamy Pillai\n Govindasamy Sarangapany\n Pakkirisami Pillai\n and had friendly associations with them.","createdDate":"20201119143405","version":0,"latest":false,"roles":[],"metadata":{"accession_no_csv":"2016-00096","Image":"","object_work_type":"black-and-white photographs","title_text":"Thamizhavel G Sarangapany being garlanded","preference":"main","title_language":"","creation_date":"1960s","creation_place_original_location":"Singapore","inscriptions":"","inscription_language":"","shape":"rectangular","materials_name":"paper (fiber product)","techniques_name":"printing (process) photographic processes","object_colour":"grey monochrome","physical_appearance":"The image shows a photograph that is in black-and-white. It is rectangular and it features four men, of which two are sitting down while the other two are standing up. One man is adorned with a garland around his neck and another man standing across him is adjusting the position of the garland. Both of them are smiling. The background of the photograph suggests that it was taken in the interior of a building.","subject_terms_1":"commemorations (events) honours","subject_terms_2":"Black-and-white photography Caran?kapa?n?i, 1903-1974 Tamil (Indic people)","subject_terms_3":"Photography Thamizhavel Govindasamy Sarangapany","sgcool_label_text":"A native of Karuvakurichi village, near Mannargudi town in Tamil Nadu, S. Appavoo Kandiar was a general contractor specializing in pipe and cable laying, handling of cargo and a concrete bricks supplier. Mr.Kandiar was a successful contractor; called a millionaire by the Straits Times in 1957, he owned properties in Bukit Timah and Coronation Road areas. He was a contemporary of Indian pioneers such as P.Govindasamy Pillai, Govindasamy Sarangapany, Pakkirisami Pillai, and had friendly associations with them."},"nlpDate":"20201119143405","connectorId":0,"tags":{}}