{"id":"2016-00419","title":"Dompet with Beaded Butterfly and Flower Design Beaded purse with butterfly and flower design","source":"Bumblebee","path":"./Data/json/","content":"accession_no_csv:2016-00419\nImage:\nobject_work_type:purses (ladies\\u0027 accessories)\ntitle_text:Dompet with Beaded Butterfly and Flower Design Beaded purse with butterfly and flower design\npreference:alternate main\ntitle_language:\ncreation_date:c. 1900\ncreation_place_original_location:Java (Indonesia)\ninscriptions:\ninscription_language:\nshape:semicircular\nmaterials_name:velvet (fabric weave) glass (material) metal sequins (sprangles)\ntechniques_name:sewing (needleworking technique) embroidering\nobject_colour:multicolored\nphysical_appearance:This is a beaded purse in a semicircular shape. Made from red velvet\n the face of the purse is decorated with embroided beads and stitching. There is a bead button in the center\n holding the flap closed. The purse is decorated with floral motifs along the border. In the center\n there is a beaded butterfly\n with a flower stalk on either side.\nsubject_terms_1:beadwork (visual works) flower (motif) Peranakan pouches\nsubject_terms_2:Beadwork Motifs Pouches (Containers) Peranakan (Asian people)\nsubject_terms_3:Decorative arts\nsgcool_label_text:This dompet has a unique semi-circular shape quite unlike other envelope purses. Chain and bullion stiches are used to create the contours of a butterfly and two stalks of flowers. Unlike Chinese purses which were either square or circular in shape\n the purses made for or by the Peranakan community show more variation.","createdDate":"20201018182635","version":0,"latest":false,"roles":[],"metadata":{"accession_no_csv":"2016-00419","Image":"","object_work_type":"purses (ladies\u0027 accessories)","title_text":"Dompet with Beaded Butterfly and Flower Design Beaded purse with butterfly and flower design","preference":"alternate main","title_language":"","creation_date":"c. 1900","creation_place_original_location":"Java (Indonesia)","inscriptions":"","inscription_language":"","shape":"semicircular","materials_name":"velvet (fabric weave) glass (material) metal sequins (sprangles)","techniques_name":"sewing (needleworking technique) embroidering","object_colour":"multicolored","physical_appearance":"This is a beaded purse in a semicircular shape. Made from red velvet, the face of the purse is decorated with embroided beads and stitching. There is a bead button in the center, holding the flap closed. The purse is decorated with floral motifs along the border. In the center, there is a beaded butterfly, with a flower stalk on either side.","subject_terms_1":"beadwork (visual works) flower (motif) Peranakan pouches","subject_terms_2":"Beadwork Motifs Pouches (Containers) Peranakan (Asian people)","subject_terms_3":"Decorative arts","sgcool_label_text":"This dompet has a unique semi-circular shape quite unlike other envelope purses. Chain and bullion stiches are used to create the contours of a butterfly and two stalks of flowers. Unlike Chinese purses which were either square or circular in shape, the purses made for or by the Peranakan community show more variation."},"nlpDate":"20201018182635","connectorId":0,"tags":{}}