{"id":"2016-00615","title":"Wedding sari and blouse belonging to Mrs Marimuthu Ammal, purchased at the P Govindasamy Pillai store","source":"Bumblebee","path":"./Data/json/","content":"accession_no_csv:2016-00615\nImage:\nobject_work_type:saris (garments)\ntitle_text:Wedding sari and blouse belonging to Mrs Marimuthu Ammal\n purchased at the P Govindasamy Pillai store\npreference:main\ntitle_language:\ncreation_date:Aug-51\ncreation_place_original_location:Singapore\ninscriptions:\ninscription_language:\nshape:irregular\nmaterials_name:silk (textile)\ntechniques_name:sewing (needleworking technique)\nobject_colour:multicoloured\nphysical_appearance:The image shows a set consisting of a blouse and a sari. The blouse is white in colour and it has patterns all over its surface. It is also short sleeved. The sari is maroon in colour\n with gold bands at its top and bottom. There are lines of floral patterns running vertically down the sari\n as well as horizontally on the gold bands. There is a tear at the bottom right of the sari\n on the gold band.\nsubject_terms_1:womenswear wedding dresses folk costume allover patterns floral patterns blouses (main garments)\nsubject_terms_2:Ethnic costume Wedding costume Blouses Saris Motifs Women\\u0027s clothing\nsubject_terms_3:Indian costumes\nsgcool_label_text:Mr. S Gopalakrishnan (b. in 1920 in Tanjavur) was a prominent violinist\n and Carnatic singer. He arrived in Singapore in 1939 and actively participated in the Indian classical music scene here. Mr Gopalakrishnan performed alongside veterans of classical performers such as Pandit M Ramalingam and MV Gurusamy at temple and other music festivals. He also taught violin lessons at the Singapore Malayalee Association from the 1970s to 2000s. He was a member of the Tamils Reform Association and performed his wedding according to the principles of the Self-Respect Movement. He was also employed as a compositor at the Far East Air Force from 1954 to 1970.","createdDate":"20201018182635","version":0,"latest":false,"roles":[],"metadata":{"accession_no_csv":"2016-00615","Image":"","object_work_type":"saris (garments)","title_text":"Wedding sari and blouse belonging to Mrs Marimuthu Ammal, purchased at the P Govindasamy Pillai store","preference":"main","title_language":"","creation_date":"Aug-51","creation_place_original_location":"Singapore","inscriptions":"","inscription_language":"","shape":"irregular","materials_name":"silk (textile)","techniques_name":"sewing (needleworking technique)","object_colour":"multicoloured","physical_appearance":"The image shows a set consisting of a blouse and a sari. The blouse is white in colour and it has patterns all over its surface. It is also short sleeved. The sari is maroon in colour, with gold bands at its top and bottom. There are lines of floral patterns running vertically down the sari, as well as horizontally on the gold bands. There is a tear at the bottom right of the sari, on the gold band.","subject_terms_1":"womenswear wedding dresses folk costume allover patterns floral patterns blouses (main garments)","subject_terms_2":"Ethnic costume Wedding costume Blouses Saris Motifs Women\u0027s clothing","subject_terms_3":"Indian costumes","sgcool_label_text":"Mr. S Gopalakrishnan (b. in 1920 in Tanjavur) was a prominent violinist, and Carnatic singer. He arrived in Singapore in 1939 and actively participated in the Indian classical music scene here. Mr Gopalakrishnan performed alongside veterans of classical performers such as Pandit M Ramalingam and MV Gurusamy at temple and other music festivals. He also taught violin lessons at the Singapore Malayalee Association from the 1970s to 2000s. He was a member of the Tamils Reform Association and performed his wedding according to the principles of the Self-Respect Movement. He was also employed as a compositor at the Far East Air Force from 1954 to 1970."},"nlpDate":"20201018182635","connectorId":0,"tags":{}}