{
  "id": "2016-00212-018",
  "title": "Chumba Valley, Punjab Photograph album of views and portraits in the Punjab, Cashmere, Ceylon, Burma, Penang, Singapore, and Java",
  "source": "Bumblebee",
  "path": "./Data/json/",
  "content": "\n  accession_no_csv: 2016-00212-018\n\n  Image: \n\n  object_work_type: black-and-white photographs\n\n  title_text: Chumba Valley\n Punjab Photograph album of views and portraits in the Punjab\n Cashmere\n Ceylon\n Burma\n Penang\n Singapore\n and Java\n\n  preference: main alternate\n\n  title_language: \n\n  creator_2: John Thomson\n\n  creator_1: Thomson\n J. (John)\n 1837-1921\n\n  creator_role: photographers\n\n  creation_date: before 28 Jul 1876\n\n  creation_place_original_location: Punjab (India) Singapore\n\n  inscriptions: \n\n  inscription_language: \n\n  shape: rectangular\n\n  materials_name: albumen (egg white protein) paper (fiber product) albumen paper\n\n  techniques_name: albumen process\n\n  object_colour: black-and-white (colors)\n\n  physical_appearance: This is a photograph of a valley in Chumba\n Punjab. In the background\n there are several mountain-tops in the distance. The foreground features thick vegetation\n and tall trees along the hill on the right\n with a lone tall tree on the left of the photograph. The title is written at the bottom\n below the photograph.\n\n  subject_terms_1: scenery (landscape) valleys (landforms) rural areas mountains\n\n  subject_terms_2: Punjab (India) Photographs Valleys Thomson\n J. (John)\n 1837-1921 Mountains\n\n  subject_terms_3: Landscape photography\n",
  "createdDate": "20201125084537",
  "version": 0,
  "latest": false,
  "roles": [],
  "metadata": {
    "accession_no_csv": "2016-00212-018",
    "Image": "",
    "object_work_type": "black-and-white photographs",
    "title_text": "Chumba Valley, Punjab Photograph album of views and portraits in the Punjab, Cashmere, Ceylon, Burma, Penang, Singapore, and Java",
    "preference": "main alternate",
    "title_language": "",
    "creator_2": "John Thomson",
    "creator_1": "Thomson, J. (John), 1837-1921",
    "creator_role": "photographers",
    "creation_date": "before 28 Jul 1876",
    "creation_place_original_location": "Punjab (India) Singapore",
    "inscriptions": "",
    "inscription_language": "",
    "shape": "rectangular",
    "materials_name": "albumen (egg white protein) paper (fiber product) albumen paper",
    "techniques_name": "albumen process",
    "object_colour": "black-and-white (colors)",
    "physical_appearance": "This is a photograph of a valley in Chumba, Punjab. In the background, there are several mountain-tops in the distance. The foreground features thick vegetation, and tall trees along the hill on the right, with a lone tall tree on the left of the photograph. The title is written at the bottom, below the photograph.",
    "subject_terms_1": "scenery (landscape) valleys (landforms) rural areas mountains",
    "subject_terms_2": "Punjab (India) Photographs Valleys Thomson, J. (John), 1837-1921 Mountains",
    "subject_terms_3": "Landscape photography"
  },
  "nlpDate": "20201125084537",
  "connectorId": 0,
  "tags": {}
}