{"id":"2016-00696","title":"Lace Pillowcase","source":"Bumblebee","path":"./Data/json/","content":"accession_no_csv:2016-00696\nImage:\nobject_work_type:pillowcases\ntitle_text:Lace Pillowcase\npreference:main\ntitle_language:\ncreation_date:20th century\ncreation_place_original_location:Indonesia\ninscriptions:\ninscription_language:\nshape:rectangular\nmaterials_name:cotton (textile)\ntechniques_name:sewing (needleworking technique)\nobject_colour:white (color)\nphysical_appearance:This is a lace pillowcase. It is white with a scalloped border. A line of button clasps can be found along its opening. The words ‘Mevr Ooi Foon Ling’ is embroidered in white thread on the reverse.\nsubject_terms_1:bobbin lace Peranakan\nsubject_terms_2:Pillowcases Bobbin lace Peranakan (Asian people)\nsubject_terms_3:Peranakan costumes\nsgcool_label_text:This pillow case is covered with white delicate white lace. A line of button clasps can be found along its opening. The words ‘Mevr Ooi Foon Ling’ is embroidered in white thread on the reverse. The making of bobbin lace was an established tradition in port cities like Malacca and Palembang by the early 20th century. It is part of a donation which contains a mixture of garments worn by Peranakan men and women.","createdDate":"20201018182635","version":0,"latest":false,"roles":[],"metadata":{"accession_no_csv":"2016-00696","Image":"","object_work_type":"pillowcases","title_text":"Lace Pillowcase","preference":"main","title_language":"","creation_date":"20th century","creation_place_original_location":"Indonesia","inscriptions":"","inscription_language":"","shape":"rectangular","materials_name":"cotton (textile)","techniques_name":"sewing (needleworking technique)","object_colour":"white (color)","physical_appearance":"This is a lace pillowcase. It is white with a scalloped border. A line of button clasps can be found along its opening. The words ‘Mevr Ooi Foon Ling’ is embroidered in white thread on the reverse.","subject_terms_1":"bobbin lace Peranakan","subject_terms_2":"Pillowcases Bobbin lace Peranakan (Asian people)","subject_terms_3":"Peranakan costumes","sgcool_label_text":"This pillow case is covered with white delicate white lace. A line of button clasps can be found along its opening. The words ‘Mevr Ooi Foon Ling’ is embroidered in white thread on the reverse. The making of bobbin lace was an established tradition in port cities like Malacca and Palembang by the early 20th century. It is part of a donation which contains a mixture of garments worn by Peranakan men and women."},"nlpDate":"20201018182635","connectorId":0,"tags":{}}