{"id":"2016-00212-067","title":"Photograph album of views and portraits in the Punjab, Cashmere, Ceylon, Burma, Penang, Singapore, and Java Rijswijk, Batavia, Java","source":"Bumblebee","path":"./Data/json/","content":"accession_no_csv:2016-00212-067\nImage:\nobject_work_type:black-and-white photographs\ntitle_text:Photograph album of views and portraits in the Punjab\n Cashmere\n Ceylon\n Burma\n Penang\n Singapore\n and Java Rijswijk\n Batavia\n Java\npreference:alternate main\ntitle_language:\ncreator_2:John Thomson\ncreator_1:Thomson\n J. (John)\n 1837-1921\ncreator_role:photographers\ncreation_date:before 28 Jul 1876\ncreation_place_original_location:Singapore Jakarta (Indonesia)\ninscriptions:\ninscription_language:\nshape:rectangular\nmaterials_name:albumen (egg white protein) albumen paper paper (fiber product)\ntechniques_name:albumen process\nobject_colour:black-and-white (colors)\nphysical_appearance:This is a photograph of the Harmonie Society clubhouse on the left\n and the Oger Freres tailor house on the right. The road in the photograph crosses over the Ciliwung River\n seen on the left. The buildings have a neoclassical colonial architecture style. The edges of the photographs are rounded. The title is written at the bottom\n below the photograph.\nsubject_terms_1:colonization societies clubhouses Neoclassical\nsubject_terms_2:Photographs Thomson\n J. (John)\n 1837-1921 Jakarta (Indonesia) Colonization Clubhouses Societies Neoclassical (Architecture)\nsubject_terms_3:Photography Places of interest Recreation clubs Colonial architecture","createdDate":"20201018182635","version":0,"latest":false,"roles":[],"metadata":{"accession_no_csv":"2016-00212-067","Image":"","object_work_type":"black-and-white photographs","title_text":"Photograph album of views and portraits in the Punjab, Cashmere, Ceylon, Burma, Penang, Singapore, and Java Rijswijk, Batavia, Java","preference":"alternate main","title_language":"","creator_2":"John Thomson","creator_1":"Thomson, J. (John), 1837-1921","creator_role":"photographers","creation_date":"before 28 Jul 1876","creation_place_original_location":"Singapore Jakarta (Indonesia)","inscriptions":"","inscription_language":"","shape":"rectangular","materials_name":"albumen (egg white protein) albumen paper paper (fiber product)","techniques_name":"albumen process","object_colour":"black-and-white (colors)","physical_appearance":"This is a photograph of the Harmonie Society clubhouse on the left, and the Oger Freres tailor house on the right. The road in the photograph crosses over the Ciliwung River, seen on the left. The buildings have a neoclassical colonial architecture style. The edges of the photographs are rounded. The title is written at the bottom, below the photograph.","subject_terms_1":"colonization societies clubhouses Neoclassical","subject_terms_2":"Photographs Thomson, J. (John), 1837-1921 Jakarta (Indonesia) Colonization Clubhouses Societies Neoclassical (Architecture)","subject_terms_3":"Photography Places of interest Recreation clubs Colonial architecture"},"nlpDate":"20201018182635","connectorId":0,"tags":{}}