{
  "id": "2016-00671",
  "title": "Revere 8mm vintage movie projector with case Case containing Revere 8mm vintage movie projector",
  "source": "Bumblebee",
  "path": "./Data/json/",
  "content": "\n  accession_no_csv: 2016-00671\n\n  Image: \n\n  object_work_type: cases (containers) projectors (image projectors)\n\n  title_text: Revere 8mm vintage movie projector with case Case containing Revere 8mm vintage movie projector\n\n  preference: main alternate\n\n  title_language: \n\n  creator_2: Revere Camera Company\n\n  creator_role: manufacturers\n\n  creation_date: 1940s-1950s\n\n  creation_place_original_location: United States Singapore\n\n  inscriptions: \n\n  inscription_language: \n\n  shape: irregular\n\n  materials_name: wood (plant material) plastic (organic material) metal\n\n  techniques_name: forming (physical activity) metalworking\n\n  object_colour: multicoloured\n\n  physical_appearance: \\The image shows a movie projector that is placed inside an open box. The box is made of wood and the words\n \\\\Lishing Products St. Louis\n\n  subject_terms_1: Missouri\\\\ and the logo of the firm are displayed on the interior of the case cover. There are cables attached to the movie projector. There are numerous knobs and levers situated on the body of the projector. The spool of the projector is located to the left of the projector frame.\\\n\n  subject_terms_2: Containers film projection systems\n\n  subject_terms_3: Motion picture projectors\n\n  context_21: The set of equipment was used by The Picture Farm Pte Ltd\n\n  context_22: 45 Jalan Pemimpin\n #09-00 Foo Wah Industrial Building\n Thomson\n Singapore\n\n  context_23: 1970 - present\n\n  context_24: 1970\n\n  sgcool_label_text: present\n",
  "createdDate": "20201125084531",
  "version": 0,
  "latest": false,
  "roles": [],
  "metadata": {
    "accession_no_csv": "2016-00671",
    "Image": "",
    "object_work_type": "cases (containers) projectors (image projectors)",
    "title_text": "Revere 8mm vintage movie projector with case Case containing Revere 8mm vintage movie projector",
    "preference": "main alternate",
    "title_language": "",
    "creator_2": "Revere Camera Company",
    "creator_role": "manufacturers",
    "creation_date": "1940s-1950s",
    "creation_place_original_location": "United States Singapore",
    "inscriptions": "",
    "inscription_language": "",
    "shape": "irregular",
    "materials_name": "wood (plant material) plastic (organic material) metal",
    "techniques_name": "forming (physical activity) metalworking",
    "object_colour": "multicoloured",
    "physical_appearance": "\"The image shows a movie projector that is placed inside an open box. The box is made of wood and the words, \"\"Lishing Products St. Louis",
    "subject_terms_1": "Missouri\"\" and the logo of the firm are displayed on the interior of the case cover. There are cables attached to the movie projector. There are numerous knobs and levers situated on the body of the projector. The spool of the projector is located to the left of the projector frame.\"",
    "subject_terms_2": "Containers film projection systems",
    "subject_terms_3": "Motion picture projectors",
    "context_21": "The set of equipment was used by The Picture Farm Pte Ltd",
    "context_22": "45 Jalan Pemimpin, #09-00 Foo Wah Industrial Building, Thomson, Singapore",
    "context_23": "1970 - present",
    "context_24": "1970",
    "sgcool_label_text": "present"
  },
  "nlpDate": "20201125084531",
  "connectorId": 0,
  "tags": {}
}