{
  "id": "2016-00186",
  "title": "SEA badge SEA badge (frame to be removed)",
  "source": "Bumblebee",
  "path": "./Data/json/",
  "content": "\n  accession_no_csv: 2016-00186\n\n  Image: \n\n  object_work_type: badges\n\n  title_text: SEA badge SEA badge (frame to be removed)\n\n  preference: main alternate\n\n  title_language: \n\n  creation_date: 1963\n\n  creation_place_original_location: Singapore\n\n  inscriptions: \n\n  inscription_language: \n\n  shape: irregular\n\n  materials_name: metal\n\n  techniques_name: forming (physical activity)\n\n  object_colour: multicoloured\n\n  physical_appearance: \\The image displays a badge. A drawing of the front of the former Singapore National Theatre can be seen at the centre of the plaque. The year \\u00271963\\u0027 and \\u0027Singapore\\u0027 are displayed below the drawing. Within the border of the larger and small circle\n the words\n \\\\South East Asia Cultural Festival\\\\ is written between their circumferences. Below the circular badge\n\n  subject_terms_1: commemoratives \\\\Singapore Artiste\\\\ is printed in white capital letters below the on the rectangular block\\ festivals\n\n  subject_terms_2: cultural ceremonies Cultural relations Festivals\n\n  subject_terms_3: Victoria Theatre and Concert Hall Badges\n\n  subject_terms_4: National Theatre (Singapore)\n\n  context_2: This badge was issued for the South East Asia Cultural Festival that was held in Singapore\n\n  context_3: cultural ceremonies\n\n  context_4: 19630808 - 19630815\n\n  context_5: 19630808\n\n  context_6: 19630815\n\n  context_7: Singapore\n\n  context_8: Singapore\n Ministry of Culture (1959 - 1965)\n",
  "createdDate": "20201201203309",
  "version": 0,
  "latest": false,
  "roles": [],
  "metadata": {
    "accession_no_csv": "2016-00186",
    "Image": "",
    "object_work_type": "badges",
    "title_text": "SEA badge SEA badge (frame to be removed)",
    "preference": "main alternate",
    "title_language": "",
    "creation_date": "1963",
    "creation_place_original_location": "Singapore",
    "inscriptions": "",
    "inscription_language": "",
    "shape": "irregular",
    "materials_name": "metal",
    "techniques_name": "forming (physical activity)",
    "object_colour": "multicoloured",
    "physical_appearance": "\"The image displays a badge. A drawing of the front of the former Singapore National Theatre can be seen at the centre of the plaque. The year \u00271963\u0027 and \u0027Singapore\u0027 are displayed below the drawing. Within the border of the larger and small circle, the words, \"\"South East Asia Cultural Festival\"\" is written between their circumferences. Below the circular badge",
    "subject_terms_1": "commemoratives \"\"Singapore Artiste\"\" is printed in white capital letters below the on the rectangular block\" festivals",
    "subject_terms_2": "cultural ceremonies Cultural relations Festivals",
    "subject_terms_3": "Victoria Theatre and Concert Hall Badges",
    "subject_terms_4": "National Theatre (Singapore)",
    "context_2": "This badge was issued for the South East Asia Cultural Festival that was held in Singapore",
    "context_3": "cultural ceremonies",
    "context_4": "19630808 - 19630815",
    "context_5": "19630808",
    "context_6": "19630815",
    "context_7": "Singapore",
    "context_8": "Singapore, Ministry of Culture (1959 - 1965)"
  },
  "nlpDate": "20201201203309",
  "connectorId": 0,
  "tags": {}
}