{
  "id": "2016-00738",
  "title": "Built From The Ground Up, A Layer At A Time",
  "source": "Bumblebee",
  "path": "./Data/json/",
  "content": "\n  accession_no_csv: 2016-00738\n\n  Image: \n\n  object_work_type: black-and-white photographs\n\n  title_text: Built From The Ground Up\n A Layer At A Time\n\n  preference: main\n\n  title_language: \n\n  creator_2: Loke Hong Seng\n\n  creator_1: Loke\n Hong Seng\n\n  creator_role: photographers\n\n  creation_date: 2015 [1970]\n\n  creation_place_original_location: Singapore\n\n  inscriptions: \n\n  inscription_language: \n\n  shape: rectangular\n\n  materials_name: paper (fiber product)\n\n  techniques_name: printing (process)\n\n  object_colour: grey monochrome\n\n  edition_description: 15-Jun\n\n  physical_appearance: The image shows a photograph in black-and-white that is enclosed by a white frame. The foreground of the photograph captures the image of three male workers standing on a rooftop of a flat. One of them is standing on a wheelbarrow with two wheels and holding onto the handlebars. In front of him\n another worker is using a spade to work the ground. The background of the photograph shows several residential buildings\n all in the various stages of construction and completion.\n\n  subject_terms_1: construction workers flats (apartments) residential structures rooftops urban development planned communities new towns (modern settlements) construction sites\n\n  subject_terms_2: Black-and-white photography Construction workers Apartments Roofs Urban development Planned communities New towns Toa Payoh (Singapore) Building Singapore\n Housing and Development Board\n\n  subject_terms_3: Photography Toa Payoh Housing Estate Singapore. Housing and Development Board\n\n  sgcool_label_text: Loke Hong Seng (b. 1943) was working as a radio announcer with Radio Television Singapore in the 1960s when he picked up photography and subsequently grew to specialize in street photography. His images of 1960s and 1970s Singapore offer a candid view of everyday life in the early days of the nation’s development. This photograph shows workers at a HDB rooftop working on the construction of the Toa Payoh HDB new town. Newly constructed blocks can be seen in the background.\n",
  "createdDate": "20201120223707",
  "version": 0,
  "latest": false,
  "roles": [],
  "metadata": {
    "accession_no_csv": "2016-00738",
    "Image": "",
    "object_work_type": "black-and-white photographs",
    "title_text": "Built From The Ground Up, A Layer At A Time",
    "preference": "main",
    "title_language": "",
    "creator_2": "Loke Hong Seng",
    "creator_1": "Loke, Hong Seng",
    "creator_role": "photographers",
    "creation_date": "2015 [1970]",
    "creation_place_original_location": "Singapore",
    "inscriptions": "",
    "inscription_language": "",
    "shape": "rectangular",
    "materials_name": "paper (fiber product)",
    "techniques_name": "printing (process)",
    "object_colour": "grey monochrome",
    "edition_description": "15-Jun",
    "physical_appearance": "The image shows a photograph in black-and-white that is enclosed by a white frame. The foreground of the photograph captures the image of three male workers standing on a rooftop of a flat. One of them is standing on a wheelbarrow with two wheels and holding onto the handlebars. In front of him, another worker is using a spade to work the ground. The background of the photograph shows several residential buildings, all in the various stages of construction and completion.",
    "subject_terms_1": "construction workers flats (apartments) residential structures rooftops urban development planned communities new towns (modern settlements) construction sites",
    "subject_terms_2": "Black-and-white photography Construction workers Apartments Roofs Urban development Planned communities New towns Toa Payoh (Singapore) Building Singapore, Housing and Development Board",
    "subject_terms_3": "Photography Toa Payoh Housing Estate Singapore. Housing and Development Board",
    "sgcool_label_text": "Loke Hong Seng (b. 1943) was working as a radio announcer with Radio Television Singapore in the 1960s when he picked up photography and subsequently grew to specialize in street photography. His images of 1960s and 1970s Singapore offer a candid view of everyday life in the early days of the nation’s development. This photograph shows workers at a HDB rooftop working on the construction of the Toa Payoh HDB new town. Newly constructed blocks can be seen in the background."
  },
  "nlpDate": "20201120223707",
  "connectorId": 0,
  "tags": {}
}