{"id":"2016-00515","title":"Untitled (locomotive)","source":"Bumblebee","path":"./Data/json/","content":"accession_no_csv:2016-00515\nImage:\nobject_work_type:black-and-white photographs\ntitle_text:Untitled (locomotive)\npreference:main\ntitle_language:\ncreator_2:Kwek Leng Joo\ncreator_1:Kwek\n Leng Joo\ncreator_role:photographers\ncreation_date:2010\ncreation_place_original_location:Singapore Malaysia\ninscriptions:\ninscription_language:\nshape:rectangular\nmaterials_name:paper (fiber product)\ntechniques_name:printing (process)\nobject_colour:grey monochrome\nphysical_appearance:The image shows a photograph in black-and-white. It has a black frame and its border is white in colour. There are 3 sets of railroads running side by side vertically. A train occupies the middle track. The background and sides of the photograph comprises of trees. The railroad on the rightr connects with the middle railroad at several points.\nsubject_terms_1:locomotives railroads (infrastructure) trains (vehicle groupings)\nsubject_terms_2:Black-and-white photography Locomotives Railroads Pertadbiran Keretapi Tanah Melayu Railroad trains\nsubject_terms_3:Rail transport Pertadbiran Keretapi Tanah Melayu Photography\nsgcool_label_text:\\This image is part of the \\\\Tracking Memories\\\\ collection by the late Mr Kwek Leng Joo. The collection captures different aspects of the Malayan Railway story in Singapore","createdDate":"20201119143405","version":0,"latest":false,"roles":[],"metadata":{"accession_no_csv":"2016-00515","Image":"","object_work_type":"black-and-white photographs","title_text":"Untitled (locomotive)","preference":"main","title_language":"","creator_2":"Kwek Leng Joo","creator_1":"Kwek, Leng Joo","creator_role":"photographers","creation_date":"2010","creation_place_original_location":"Singapore Malaysia","inscriptions":"","inscription_language":"","shape":"rectangular","materials_name":"paper (fiber product)","techniques_name":"printing (process)","object_colour":"grey monochrome","physical_appearance":"The image shows a photograph in black-and-white. It has a black frame and its border is white in colour. There are 3 sets of railroads running side by side vertically. A train occupies the middle track. The background and sides of the photograph comprises of trees. The railroad on the rightr connects with the middle railroad at several points.","subject_terms_1":"locomotives railroads (infrastructure) trains (vehicle groupings)","subject_terms_2":"Black-and-white photography Locomotives Railroads Pertadbiran Keretapi Tanah Melayu Railroad trains","subject_terms_3":"Rail transport Pertadbiran Keretapi Tanah Melayu Photography","sgcool_label_text":"\"This image is part of the \"\"Tracking Memories\"\" collection by the late Mr Kwek Leng Joo. The collection captures different aspects of the Malayan Railway story in Singapore"},"nlpDate":"20201119143405","connectorId":0,"tags":{}}