{
  "id": "2016-00551",
  "title": "Pyongyang Cultural Mission at the National Theatre  Programme booklet for the Pyongyang Cultural Mission at the National Theatre  Pyongyang Cultural Mission at the National Theatre  Programme booklet for the Pyongyang Cultural Mission at the National Theatre",
  "source": "Bumblebee",
  "path": "./Data/json/",
  "content": "\n  accession_no_csv: 2016-00551\n\n  Image: \n\n  object_work_type: booklets booklets\n\n  title_text: Pyongyang Cultural Mission at the National Theatre  Programme booklet for the Pyongyang Cultural Mission at the National Theatre  Pyongyang Cultural Mission at the National Theatre  Programme booklet for the Pyongyang Cultural Mission at the National Theatre\n\n  preference: main alternate main alternate\n\n  title_language: \n\n  creator_2: Pyongyang Cultural Mission Pyongyang Cultural Mission\n\n  creator_1: Not indicated Not indicated\n\n  creator_role: performing artists performing artists\n\n  creation_date: 1974 1974\n\n  creation_place_original_location: Singapore Singapore\n\n  styles_periods_indexing_terms: NA NA\n\n  inscriptions: \n\n  inscription_language: \n\n  scale_type: NA NA\n\n  shape: rectangular rectangular\n\n  materials_name: printing paper printing paper\n\n  techniques_name: colour printing colour printing\n\n  object_colour: multicoloured multicoloured\n\n  edition_description: NA NA\n\n  physical_appearance: \\The image shows the front cover of a booklet. It is blue in colour and \\\\Pyongyang cultural mission\\\\ is stated at the left hand side. \\\\National Theatre \\The image shows the front cover of a booklet. It is blue in colour and \\\\Pyongyang cultural mission\\\\ is stated at the left hand side. \\\\National Theatre\n\n  subject_terms_1: December 12 - 18 1974 theaters (institutions) cultural events  December 12 - 18 1974 theaters (institutions) cultural events\n\n  subject_terms_2: 8.30p.m\\\\ is stated at the bottom right hand side. \\\\National Theatre Trust in association with the Consulate-General of Democratic People\\u0027s Republic of Korea\\\\ is stated at the top right hand side. The image shows a single row of women posing in the same manner. All of them are wearing the same ethnic costume. \\ Theaters Pamphlets  8.30p.m\\\\ is stated at the bottom right hand side. \\\\National Theatre Trust in association with the Consulate-General of Democratic People\\u0027s Republic of Korea\\\\ is stated at the top right hand side. The image shows a single row of women posing in the same manner. All of them are wearing the same ethnic costume. \\ Theaters Pamphlets\n\n  subject_terms_3: performances (creative events) National Theatre (Singapore) Cultural development performances (creative events) National Theatre (Singapore) Cultural development\n\n  subject_terms_4: Performances Performances\n\n  context_1: Performing Arts Performing Arts\n\n  context_2: NA NA\n\n  context_3: NA NA\n\n  context_4: NA NA\n\n  context_5: NA NA\n\n  context_6: NA NA\n\n  context_7: NA NA\n\n  context_8: NA NA\n\n  context_9: NA NA\n\n  context_10: NA NA\n\n  context_11: NA NA\n\n  context_12: NA NA\n\n  context_13: NA NA\n\n  context_14: NA NA\n\n  context_15: NA NA\n\n  context_16: NA NA\n\n  context_17: NA NA\n\n  context_18: NA NA\n\n  context_19: NA NA\n\n  context_20: NA NA\n\n  context_21: NA NA\n\n  context_22: NA NA\n\n  context_23: NA NA\n\n  context_24: NA NA\n\n  sgcool_label_text: NA NA\n",
  "createdDate": "20201120223707",
  "version": 0,
  "latest": false,
  "roles": [],
  "metadata": {
    "accession_no_csv": "2016-00551",
    "Image": "",
    "object_work_type": "booklets booklets",
    "title_text": "Pyongyang Cultural Mission at the National Theatre  Programme booklet for the Pyongyang Cultural Mission at the National Theatre  Pyongyang Cultural Mission at the National Theatre  Programme booklet for the Pyongyang Cultural Mission at the National Theatre",
    "preference": "main alternate main alternate",
    "title_language": "",
    "creator_2": "Pyongyang Cultural Mission Pyongyang Cultural Mission",
    "creator_1": "Not indicated Not indicated",
    "creator_role": "performing artists performing artists",
    "creation_date": "1974 1974",
    "creation_place_original_location": "Singapore Singapore",
    "styles_periods_indexing_terms": "NA NA",
    "inscriptions": "",
    "inscription_language": "",
    "scale_type": "NA NA",
    "shape": "rectangular rectangular",
    "materials_name": "printing paper printing paper",
    "techniques_name": "colour printing colour printing",
    "object_colour": "multicoloured multicoloured",
    "edition_description": "NA NA",
    "physical_appearance": "\"The image shows the front cover of a booklet. It is blue in colour and \"\"Pyongyang cultural mission\"\" is stated at the left hand side. \"\"National Theatre \"The image shows the front cover of a booklet. It is blue in colour and \"\"Pyongyang cultural mission\"\" is stated at the left hand side. \"\"National Theatre",
    "subject_terms_1": "December 12 - 18 1974 theaters (institutions) cultural events  December 12 - 18 1974 theaters (institutions) cultural events",
    "subject_terms_2": "8.30p.m\"\" is stated at the bottom right hand side. \"\"National Theatre Trust in association with the Consulate-General of Democratic People\u0027s Republic of Korea\"\" is stated at the top right hand side. The image shows a single row of women posing in the same manner. All of them are wearing the same ethnic costume. \" Theaters Pamphlets  8.30p.m\"\" is stated at the bottom right hand side. \"\"National Theatre Trust in association with the Consulate-General of Democratic People\u0027s Republic of Korea\"\" is stated at the top right hand side. The image shows a single row of women posing in the same manner. All of them are wearing the same ethnic costume. \" Theaters Pamphlets",
    "subject_terms_3": "performances (creative events) National Theatre (Singapore) Cultural development performances (creative events) National Theatre (Singapore) Cultural development",
    "subject_terms_4": "Performances Performances",
    "context_1": "Performing Arts Performing Arts",
    "context_2": "NA NA",
    "context_3": "NA NA",
    "context_4": "NA NA",
    "context_5": "NA NA",
    "context_6": "NA NA",
    "context_7": "NA NA",
    "context_8": "NA NA",
    "context_9": "NA NA",
    "context_10": "NA NA",
    "context_11": "NA NA",
    "context_12": "NA NA",
    "context_13": "NA NA",
    "context_14": "NA NA",
    "context_15": "NA NA",
    "context_16": "NA NA",
    "context_17": "NA NA",
    "context_18": "NA NA",
    "context_19": "NA NA",
    "context_20": "NA NA",
    "context_21": "NA NA",
    "context_22": "NA NA",
    "context_23": "NA NA",
    "context_24": "NA NA",
    "sgcool_label_text": "NA NA"
  },
  "nlpDate": "20201120223707",
  "connectorId": 0,
  "tags": {}
}