{
  "id": "2016-00289",
  "title": "Setron Deluxe Model Television Set",
  "source": "Bumblebee",
  "path": "./Data/json/",
  "content": "\n  accession_no_csv: 2016-00289\n\n  Image: \n\n  object_work_type: television (telecommunication system)\n\n  title_text: Setron Deluxe Model Television Set\n\n  preference: main\n\n  title_language: \n\n  creator_2: Setron\n\n  creator_1: Not indicated\n\n  creator_role: manufacturers\n\n  creation_date: 1970s\n\n  creation_place_original_location: Singapore\n\n  inscriptions: \n\n  inscription_language: \n\n  shape: irregular\n\n  materials_name: teak (wood) glass (material) metal plastic (organic material)\n\n  techniques_name: forming (physical activity) metalworking\n\n  object_colour: multicoloured\n\n  physical_appearance: The image depicts a television set. It comes with a cabinet that contains a horizontal railing shelf\n below the shelf which supports the television. The television is predominantly black due to its casing\n but it has a grey screen at its sentre. Beside the screen to its right\n there is a remote controller. There are no cracks on the television screen. However\n the paint on the wood of the front right leg of the cabinet has been chipped.\n\n  subject_terms_1: technology (general associated concept) brand name objects electronics\n\n  subject_terms_2: Television Technology Brand name products\n\n  sgcool_label_text: Setron was a household name in Singapore during the 1960s and 1970s. Granted pioneer status by the Singapore Government in 1964\n Setron was the first local company to produce television sets. It was the only television assembly plant in Southeast Asia at the time when it began operations.\n",
  "createdDate": "20201201203309",
  "version": 0,
  "latest": false,
  "roles": [],
  "metadata": {
    "accession_no_csv": "2016-00289",
    "Image": "",
    "object_work_type": "television (telecommunication system)",
    "title_text": "Setron Deluxe Model Television Set",
    "preference": "main",
    "title_language": "",
    "creator_2": "Setron",
    "creator_1": "Not indicated",
    "creator_role": "manufacturers",
    "creation_date": "1970s",
    "creation_place_original_location": "Singapore",
    "inscriptions": "",
    "inscription_language": "",
    "shape": "irregular",
    "materials_name": "teak (wood) glass (material) metal plastic (organic material)",
    "techniques_name": "forming (physical activity) metalworking",
    "object_colour": "multicoloured",
    "physical_appearance": "The image depicts a television set. It comes with a cabinet that contains a horizontal railing shelf, below the shelf which supports the television. The television is predominantly black due to its casing, but it has a grey screen at its sentre. Beside the screen to its right, there is a remote controller. There are no cracks on the television screen. However, the paint on the wood of the front right leg of the cabinet has been chipped.",
    "subject_terms_1": "technology (general associated concept) brand name objects electronics",
    "subject_terms_2": "Television Technology Brand name products",
    "sgcool_label_text": "Setron was a household name in Singapore during the 1960s and 1970s. Granted pioneer status by the Singapore Government in 1964, Setron was the first local company to produce television sets. It was the only television assembly plant in Southeast Asia at the time when it began operations."
  },
  "nlpDate": "20201201203309",
  "connectorId": 0,
  "tags": {}
}