{"id":"2016-00299","title":"East India House, Leadenhall Street","source":"Bumblebee","path":"./Data/json/","content":"accession_no_csv:2016-00299\nImage:\nobject_work_type:prints (visual works) steel engravings (visual works)\ntitle_text:East India House\n Leadenhall Street\npreference:main\ntitle_language:\ncreator_2:Thomas Hosmer Shepherd William Tombleson\ncreator_1:Shepherd\n Thomas H. (Thomas Hosmer) Tombleson\n William\n 1795 -\ncreator_role:artists (visual artists) engravers\ncreation_date:1829\ncreation_place_original_location:London (England)\ninscriptions:\ninscription_language:\nshape:rectangular\nmaterials_name:paper (fiber product)\ntechniques_name:printing (process) hand colouring\nobject_colour:multicoloured\nphysical_appearance:This print depicts the headquarters of the East India Company. The title of the print is located at the bottom centre\n in capital letters. The print is bordered by a wooden frame\n There are no visible tears or chips on the both the print and frame. There are images of human figures riding on horse carriages outside the main building. At the bottom left and bottom right of the print\n the names of the artist and the engraver of this print are stated respectively. The colours on the print do not look smudged.\nsubject_terms_1:historic buildings corporate headquarters (built works) street scenes\nsubject_terms_2:East India Company Prints Engraving Corporations\n Headquarters Historic buildings\nsubject_terms_3:East India Company Historic buildings Visual arts\nsgcool_label_text:East India House on Leadenhall Street was formerly Craven House\n when it was acquired by the East India Company in 1648 for use as its headquarters in London. This print shows the East India House after remodelling and extension of its frontage was completed by the end of the 18th century. The engraving was based on a drawing by Thomas Hosmer Shepherd (1792-1864)\n an English topographical artist.","createdDate":"20201119143405","version":0,"latest":false,"roles":[],"metadata":{"accession_no_csv":"2016-00299","Image":"","object_work_type":"prints (visual works) steel engravings (visual works)","title_text":"East India House, Leadenhall Street","preference":"main","title_language":"","creator_2":"Thomas Hosmer Shepherd William Tombleson","creator_1":"Shepherd, Thomas H. (Thomas Hosmer) Tombleson, William, 1795 -","creator_role":"artists (visual artists) engravers","creation_date":"1829","creation_place_original_location":"London (England)","inscriptions":"","inscription_language":"","shape":"rectangular","materials_name":"paper (fiber product)","techniques_name":"printing (process) hand colouring","object_colour":"multicoloured","physical_appearance":"This print depicts the headquarters of the East India Company. The title of the print is located at the bottom centre, in capital letters. The print is bordered by a wooden frame, There are no visible tears or chips on the both the print and frame. There are images of human figures riding on horse carriages outside the main building. At the bottom left and bottom right of the print, the names of the artist and the engraver of this print are stated respectively. The colours on the print do not look smudged.","subject_terms_1":"historic buildings corporate headquarters (built works) street scenes","subject_terms_2":"East India Company Prints Engraving Corporations, Headquarters Historic buildings","subject_terms_3":"East India Company Historic buildings Visual arts","sgcool_label_text":"East India House on Leadenhall Street was formerly Craven House, when it was acquired by the East India Company in 1648 for use as its headquarters in London. This print shows the East India House after remodelling and extension of its frontage was completed by the end of the 18th century. The engraving was based on a drawing by Thomas Hosmer Shepherd (1792-1864), an English topographical artist."},"nlpDate":"20201119143405","connectorId":0,"tags":{}}