{"id":"2016-00674","title":"Yellow Kebaya with Small Flowers","source":"Bumblebee","path":"./Data/json/","content":"accession_no_csv:2016-00674\nImage:\nobject_work_type:kebayas womenswear\ntitle_text:Yellow Kebaya with Small Flowers\npreference:main\ntitle_language:\ncreation_date:early-mid 20th century\ncreation_place_original_location:Java (Indonesia)\nstyles_periods_indexing_terms:Peranakan\ninscriptions:\ninscription_language:\nshape:irregular\nmaterials_name:cotton (textile)\ntechniques_name:sewing (needleworking technique) embroidering\nobject_colour:multicolored\nphysical_appearance:This is a yellow kebaya top. This kebaya features scalloped borders edged with small floral embroidery. It is made of checked fabric with red dot details. The ends of the kebaya is elongated and tapered.\nsubject_terms_1:folk costume flowers (motifs) Peranakan tops (garments\n general) blouses (main garments)\nsubject_terms_2:Ethnic costume Motifs Peranakan (Asian people) Blouses\nsubject_terms_3:Peranakan costumes\nsgcool_label_text:This kebaya has scalloped borders edged with small red flower embroidery. The checked fabric is double-faced and features red dot details. Kebayas with elongated tapered ends were popular in the 1930s and many were commissioned by Peranakan women. It is part of a donation which contains a mixture of garments worn by Peranakan men and women.","createdDate":"20201018182635","version":0,"latest":false,"roles":[],"metadata":{"accession_no_csv":"2016-00674","Image":"","object_work_type":"kebayas womenswear","title_text":"Yellow Kebaya with Small Flowers","preference":"main","title_language":"","creation_date":"early-mid 20th century","creation_place_original_location":"Java (Indonesia)","styles_periods_indexing_terms":"Peranakan","inscriptions":"","inscription_language":"","shape":"irregular","materials_name":"cotton (textile)","techniques_name":"sewing (needleworking technique) embroidering","object_colour":"multicolored","physical_appearance":"This is a yellow kebaya top. This kebaya features scalloped borders edged with small floral embroidery. It is made of checked fabric with red dot details. The ends of the kebaya is elongated and tapered.","subject_terms_1":"folk costume flowers (motifs) Peranakan tops (garments, general) blouses (main garments)","subject_terms_2":"Ethnic costume Motifs Peranakan (Asian people) Blouses","subject_terms_3":"Peranakan costumes","sgcool_label_text":"This kebaya has scalloped borders edged with small red flower embroidery. The checked fabric is double-faced and features red dot details. Kebayas with elongated tapered ends were popular in the 1930s and many were commissioned by Peranakan women. It is part of a donation which contains a mixture of garments worn by Peranakan men and women."},"nlpDate":"20201018182635","connectorId":0,"tags":{}}