{
  "id": "2016-00695",
  "title": "Kebaya with Pink Peonies",
  "source": "Bumblebee",
  "path": "./Data/json/",
  "content": "\n  accession_no_csv: 2016-00695\n\n  Image: \n\n  object_work_type: womenswear kebayas\n\n  title_text: Kebaya with Pink Peonies\n\n  preference: main\n\n  title_language: \n\n  creation_date: early-mid 20th century\n\n  creation_place_original_location: Java (Indonesia)\n\n  styles_periods_indexing_terms: Peranakan\n\n  inscriptions: \n\n  inscription_language: \n\n  shape: irregular\n\n  materials_name: cotton (textile)\n\n  techniques_name: sewing (needleworking technique)\n\n  object_colour: multicolored\n\n  physical_appearance: This is a kebaya. The fabric is printed with pink peonies. The kebaya is scalloped around the edges. It has an elongated tapered ends and sleeves.\n\n  subject_terms_1: tops (garments\n general) flowers (motifs) Peranakan blouses (main garments) folk costume\n\n  subject_terms_2: Blouses Motifs Ethnic costume Peranakan (Asian people)\n\n  subject_terms_3: Peranakan costumes\n\n  sgcool_label_text: This kebaya is printed with sprays of pink peonies and scalloped at its finely sewn edges. Kebayas with elongated tapered ends were popular in the 1930s and many were commissioned by Peranakan women. It is part of a donation which contains a mixture of garments worn by Peranakan men and women.\n",
  "createdDate": "20201125084531",
  "version": 0,
  "latest": false,
  "roles": [],
  "metadata": {
    "accession_no_csv": "2016-00695",
    "Image": "",
    "object_work_type": "womenswear kebayas",
    "title_text": "Kebaya with Pink Peonies",
    "preference": "main",
    "title_language": "",
    "creation_date": "early-mid 20th century",
    "creation_place_original_location": "Java (Indonesia)",
    "styles_periods_indexing_terms": "Peranakan",
    "inscriptions": "",
    "inscription_language": "",
    "shape": "irregular",
    "materials_name": "cotton (textile)",
    "techniques_name": "sewing (needleworking technique)",
    "object_colour": "multicolored",
    "physical_appearance": "This is a kebaya. The fabric is printed with pink peonies. The kebaya is scalloped around the edges. It has an elongated tapered ends and sleeves.",
    "subject_terms_1": "tops (garments, general) flowers (motifs) Peranakan blouses (main garments) folk costume",
    "subject_terms_2": "Blouses Motifs Ethnic costume Peranakan (Asian people)",
    "subject_terms_3": "Peranakan costumes",
    "sgcool_label_text": "This kebaya is printed with sprays of pink peonies and scalloped at its finely sewn edges. Kebayas with elongated tapered ends were popular in the 1930s and many were commissioned by Peranakan women. It is part of a donation which contains a mixture of garments worn by Peranakan men and women."
  },
  "nlpDate": "20201125084531",
  "connectorId": 0,
  "tags": {}
}