{"id":"2016-00431-010","title":"The End of History - Flemish Painting (Book #1)","source":"Bumblebee","path":"./Data/json/","content":"accession_no_csv:2016-00431-010\nImage:\nobject_work_type:books\ntitle_text:The End of History - Flemish Painting (Book #1)\npreference:main\ntitle_language:English\ncreator_2:Alan Oei Lambotte (?)\ncreator_1:Lambotte\n Paul\n 1862-1939\ncreator_role:authors\ncreation_date:2008-2013 1927\ncreation_place_original_location:London (England) Singapore\ninscriptions:\ninscription_language:\nshape:rectangular\nmaterials_name:paper (fiber product)\ntechniques_name:printing (process)\nobject_colour:green (color)\nphysical_appearance:\\This is a book titled \\u0027Flemish Painting Before the XVIIITH Century\\\\. The title is printed in the center of the book with a logo below it. It is also printed on the spine of the book\nsubject_terms_1:with the author\\u0027s name. The book has a green cover. It is faded\nsubject_terms_2:with a stain at the bottom and worn out edges.\\ Painting\n Flemish\nsubject_terms_3:Flemish (culture or style)\nsubject_terms_4:Books\ncontext_1:Non-fiction\ncontext_2:\nsgcool_label_text:NA In effect\n Huang Wei may be regarded as a performance on several levels\n and the relationship between creator and created echoes that of a two-way mirror. On one side\n the character of Huang Wei is a conduit and device for Oei to unravel his conundrum about time and history. Yet to ‘use’ Huang Wei entails Oei becoming a medium himself and ‘channelling’ his creation so that the meta-artist can step through time’s portals and enter a realm where history painting still reigns. Still\n even liminal spaces offer fleeting refuge and the stop-motion video Goliath unfolds to reveal the artist’s hand (Huang Wei\n and/or Oei?) in a continuous cycle of creating-destroying his painting\n time and again. Alan Oei (b. 1976\n Singapore) is an artist-curator interested in the workings between art history\n politics and community. He holds a Bachelor’s degree in Art History from Columbia University and a Diploma in Fine Arts from Lasalle College of the Arts. Huang Wei – a fictional post-war painter of maimed children – is the alter-ego Oei uses to present his paintings. His work has been shown in Malaysia\n Hong Kong\n Melbourne and New York. In addition\n Oei’s curatorial projects include the ‘OH! Open House’\n an annual art walkabout inside local neighbourhoods and residences. He was recently appointed the Artistic Director of Substation\n Singapore.","createdDate":"20201119143405","version":0,"latest":false,"roles":[],"metadata":{"accession_no_csv":"2016-00431-010","Image":"","object_work_type":"books","title_text":"The End of History - Flemish Painting (Book #1)","preference":"main","title_language":"English","creator_2":"Alan Oei Lambotte (?)","creator_1":"Lambotte, Paul, 1862-1939","creator_role":"authors","creation_date":"2008-2013 1927","creation_place_original_location":"London (England) Singapore","inscriptions":"","inscription_language":"","shape":"rectangular","materials_name":"paper (fiber product)","techniques_name":"printing (process)","object_colour":"green (color)","physical_appearance":"\"This is a book titled \u0027Flemish Painting Before the XVIIITH Century\"\". The title is printed in the center of the book with a logo below it. It is also printed on the spine of the book","subject_terms_1":"with the author\u0027s name. The book has a green cover. It is faded","subject_terms_2":"with a stain at the bottom and worn out edges.\" Painting, Flemish","subject_terms_3":"Flemish (culture or style)","subject_terms_4":"Books","context_1":"Non-fiction","context_2":"","sgcool_label_text":"NA In effect, Huang Wei may be regarded as a performance on several levels, and the relationship between creator and created echoes that of a two-way mirror. On one side, the character of Huang Wei is a conduit and device for Oei to unravel his conundrum about time and history. Yet to ‘use’ Huang Wei entails Oei becoming a medium himself and ‘channelling’ his creation so that the meta-artist can step through time’s portals and enter a realm where history painting still reigns. Still, even liminal spaces offer fleeting refuge and the stop-motion video Goliath unfolds to reveal the artist’s hand (Huang Wei, and/or Oei?) in a continuous cycle of creating-destroying his painting, time and again. Alan Oei (b. 1976, Singapore) is an artist-curator interested in the workings between art history, politics and community. He holds a Bachelor’s degree in Art History from Columbia University and a Diploma in Fine Arts from Lasalle College of the Arts. Huang Wei – a fictional post-war painter of maimed children – is the alter-ego Oei uses to present his paintings. His work has been shown in Malaysia, Hong Kong, Melbourne and New York. In addition, Oei’s curatorial projects include the ‘OH! Open House’, an annual art walkabout inside local neighbourhoods and residences. He was recently appointed the Artistic Director of Substation, Singapore."},"nlpDate":"20201119143405","connectorId":0,"tags":{}}