{"id":"2016-00254","title":"Comb Peineta gold and silver comb","source":"Bumblebee","path":"./Data/json/","content":"accession_no_csv:2016-00254\nImage:\nobject_work_type:combs (hair ornaments)\ntitle_text:Comb Peineta gold and silver comb\npreference:alternate main\ntitle_language:\ncreation_date:Late 19th early 20th century\ncreation_place_original_location:Philippines\nstyles_periods_indexing_terms:Philippine\ninscriptions:\ninscription_language:\nshape:irregular\nmaterials_name:gold (metal) silver (metal) pearl (animal material)\ntechniques_name:forming (physical activity) forging (metal forming)\nobject_colour:multicolored\nphysical_appearance:This is a decorative hair comb. The teeth of the comb is made of metal. The comb is topped with a gold decorative head\n with floral and foliage motifs. The comb is also adorned with pearl beads.\nsubject_terms_1:cultural diffusion flower (motif) exports hair ornaments\nsubject_terms_2:Ornamental combs Culture diffusion Motifs Exports Hair ornaments\nsubject_terms_3:Ethnic costume\nsgcool_label_text:Peineta are decorative hair combs which first became popular in the Philippines. Based on original Spanish as well as Chinese designs such combs were produced in Manila for local consumption as well as for export. Today old examples can be found all over Southeast Asia. Such combs went out of fashion when shorter hair styles came into vogue in the 20th century.","createdDate":"20201018182635","version":0,"latest":false,"roles":[],"metadata":{"accession_no_csv":"2016-00254","Image":"","object_work_type":"combs (hair ornaments)","title_text":"Comb Peineta gold and silver comb","preference":"alternate main","title_language":"","creation_date":"Late 19th early 20th century","creation_place_original_location":"Philippines","styles_periods_indexing_terms":"Philippine","inscriptions":"","inscription_language":"","shape":"irregular","materials_name":"gold (metal) silver (metal) pearl (animal material)","techniques_name":"forming (physical activity) forging (metal forming)","object_colour":"multicolored","physical_appearance":"This is a decorative hair comb. The teeth of the comb is made of metal. The comb is topped with a gold decorative head, with floral and foliage motifs. The comb is also adorned with pearl beads.","subject_terms_1":"cultural diffusion flower (motif) exports hair ornaments","subject_terms_2":"Ornamental combs Culture diffusion Motifs Exports Hair ornaments","subject_terms_3":"Ethnic costume","sgcool_label_text":"Peineta are decorative hair combs which first became popular in the Philippines. Based on original Spanish as well as Chinese designs such combs were produced in Manila for local consumption as well as for export. Today old examples can be found all over Southeast Asia. Such combs went out of fashion when shorter hair styles came into vogue in the 20th century."},"nlpDate":"20201018182635","connectorId":0,"tags":{}}