{
  "id": "2016-00759",
  "title": "Lamp screen",
  "source": "Bumblebee",
  "path": "./Data/json/",
  "content": "\n  accession_no_csv: 2016-00759\n\n  Image: \n\n  object_work_type: screens (furniture)\n\n  title_text: Lamp screen\n\n  preference: main\n\n  title_language: \n\n  creation_date: 1900-1920\n\n  creation_place_original_location: Singapore\n\n  inscriptions: \n\n  inscription_language: \n\n  shape: irregular\n\n  materials_name: wood (plant material)\n\n  techniques_name: woodcarving gilding (technique)\n\n  object_colour: multicolored\n\n  physical_appearance: This is a lamp screen. It takes the shape of a rectangular box\n with panels of glass on the back\n right and left side. The screen has decorative foliage carvings along the sides. The body of the screen is painted red. The paint is slightly faded.\n\n  subject_terms_1: ceremonial objects Peranakan religious ceremonies foliage (motif) altar components\n\n  subject_terms_2: Motifs Rites and ceremonies Peranakan (Asian people) Screens Altars Ceremonial objects\n\n  subject_terms_3: Religious life and practices\n\n  sgcool_label_text: This lamp screen is made of wood painted red and gilded\n with three panels of glass. The screen is placed on the altar to house an oil lamp that would be lit on the altar during religious ceremonies or on special occasions like Chinese New Year.\\r\\n\\r\\nThis item is donated by the family of prominent Peranakan\n Ong Sam Leong (b. 1857\n Singapore – d. 7 February 1918\n Singapore). It comes from his ancestral home of Bukit Rose\n formerly at 259 Bukit Timah Road. Ong was a well-known successful businessman who made is money in the mining of phosphate on Christmas island\n which was historically a territory of colonial Singapore.\n",
  "createdDate": "20201125084530",
  "version": 0,
  "latest": false,
  "roles": [],
  "metadata": {
    "accession_no_csv": "2016-00759",
    "Image": "",
    "object_work_type": "screens (furniture)",
    "title_text": "Lamp screen",
    "preference": "main",
    "title_language": "",
    "creation_date": "1900-1920",
    "creation_place_original_location": "Singapore",
    "inscriptions": "",
    "inscription_language": "",
    "shape": "irregular",
    "materials_name": "wood (plant material)",
    "techniques_name": "woodcarving gilding (technique)",
    "object_colour": "multicolored",
    "physical_appearance": "This is a lamp screen. It takes the shape of a rectangular box, with panels of glass on the back, right and left side. The screen has decorative foliage carvings along the sides. The body of the screen is painted red. The paint is slightly faded.",
    "subject_terms_1": "ceremonial objects Peranakan religious ceremonies foliage (motif) altar components",
    "subject_terms_2": "Motifs Rites and ceremonies Peranakan (Asian people) Screens Altars Ceremonial objects",
    "subject_terms_3": "Religious life and practices",
    "sgcool_label_text": "This lamp screen is made of wood painted red and gilded, with three panels of glass. The screen is placed on the altar to house an oil lamp that would be lit on the altar during religious ceremonies or on special occasions like Chinese New Year.\r\n\r\nThis item is donated by the family of prominent Peranakan, Ong Sam Leong (b. 1857, Singapore – d. 7 February 1918, Singapore). It comes from his ancestral home of Bukit Rose, formerly at 259 Bukit Timah Road. Ong was a well-known successful businessman who made is money in the mining of phosphate on Christmas island, which was historically a territory of colonial Singapore."
  },
  "nlpDate": "20201125084530",
  "connectorId": 0,
  "tags": {}
}