{
  "id": "2016-00567",
  "title": "The Government’s Usage of Public Funds The Government’s Usage of Public Funds, a Mandarin booklet published by the Ministry of Culture The Government’s Usage of Public Funds The Government’s Usage of Public Funds, a Mandarin booklet published by the Ministry of Culture",
  "source": "Bumblebee",
  "path": "./Data/json/",
  "content": "\n  accession_no_csv: 2016-00567\n\n  Image: \n\n  object_work_type: booklets booklets\n\n  title_text: The Government’s Usage of Public Funds The Government’s Usage of Public Funds\n a Mandarin booklet published by the Ministry of Culture The Government’s Usage of Public Funds The Government’s Usage of Public Funds\n a Mandarin booklet published by the Ministry of Culture\n\n  preference: main alternate main alternate\n\n  title_language: \n\n  creator_2: Ministry of Culture Ministry of Culture\n\n  creator_1: Ministry of Culture (TTE) Ministry of Culture (TTE)\n\n  creator_role: publishers publishers\n\n  creation_date: 1960 1960\n\n  creation_place_original_location: Singapore Singapore\n\n  styles_periods_indexing_terms: NA NA\n\n  inscriptions: \n\n  inscription_language: \n\n  scale_type: NA NA\n\n  shape: rectangular rectangular\n\n  materials_name: printing paper printing paper\n\n  techniques_name: colour printing colour printing\n\n  object_colour: multicoloured multicoloured\n\n  edition_description: NA NA\n\n  physical_appearance: The image shows the front cover of a booklet. It has a yellow background. There are four lines of Chinese characters at the centre. There are two lines of Chinese characters near the bottom. There are drawings of buildings around the booklet as well. The image shows the front cover of a booklet. It has a yellow background. There are four lines of Chinese characters at the centre. There are two lines of Chinese characters near the bottom. There are drawings of buildings around the booklet as well.\n\n  subject_terms_1: governments (administrative bodies) politics economy economic development government policy budgets governments (administrative bodies) politics economy economic development government policy budgets\n\n  subject_terms_2: Pamphlets Government Institutes Political science Government policy Economic policy Budget Pamphlets Government Institutes Political science Government policy Economic policy Budget\n\n  subject_terms_3: Politics and Government Economic development Politics and Government Economic development\n\n  subject_terms_4: NA NA\n\n  context_1: NA NA\n\n  context_2: NA NA\n\n  context_3: NA NA\n\n  context_4: NA NA\n\n  context_5: NA NA\n\n  context_6: NA NA\n\n  context_7: NA NA\n\n  context_8: NA NA\n\n  context_9: NA NA\n\n  context_10: NA NA\n\n  context_11: NA NA\n\n  context_12: NA NA\n\n  context_13: NA NA\n\n  context_14: NA NA\n\n  context_15: NA NA\n\n  context_16: NA NA\n\n  context_17: NA NA\n\n  context_18: NA NA\n\n  context_19: NA NA\n\n  context_20: NA NA\n\n  context_21: NA NA\n\n  context_22: NA NA\n\n  context_23: NA NA\n\n  context_24: NA NA\n\n  sgcool_label_text: This booklet was published by the Ministry of Culture to communicate the new government’s messages and larger concerns regarding the state of the nation. The budget that Minister for Finance Dr Goh Keng Swee presented to the Legislative Assembly in 1960 is reproduced in Mandarin here. Topics that were brought up centred round the government’s economic policy\n the review of the year’s expenditure and various revenue proposals such as property tax and business registration tax. This booklet was the third of the Towards Socialism series by the Ministry of Culture.  This booklet was published by the Ministry of Culture to communicate the new government’s messages and larger concerns regarding the state of the nation. The budget that Minister for Finance Dr Goh Keng Swee presented to the Legislative Assembly in 1960 is reproduced in Mandarin here. Topics that were brought up centred round the government’s economic policy\n the review of the year’s expenditure and various revenue proposals such as property tax and business registration tax. This booklet was the third of the Towards Socialism series by the Ministry of Culture.\n",
  "createdDate": "20201120223707",
  "version": 0,
  "latest": false,
  "roles": [],
  "metadata": {
    "accession_no_csv": "2016-00567",
    "Image": "",
    "object_work_type": "booklets booklets",
    "title_text": "The Government’s Usage of Public Funds The Government’s Usage of Public Funds, a Mandarin booklet published by the Ministry of Culture The Government’s Usage of Public Funds The Government’s Usage of Public Funds, a Mandarin booklet published by the Ministry of Culture",
    "preference": "main alternate main alternate",
    "title_language": "",
    "creator_2": "Ministry of Culture Ministry of Culture",
    "creator_1": "Ministry of Culture (TTE) Ministry of Culture (TTE)",
    "creator_role": "publishers publishers",
    "creation_date": "1960 1960",
    "creation_place_original_location": "Singapore Singapore",
    "styles_periods_indexing_terms": "NA NA",
    "inscriptions": "",
    "inscription_language": "",
    "scale_type": "NA NA",
    "shape": "rectangular rectangular",
    "materials_name": "printing paper printing paper",
    "techniques_name": "colour printing colour printing",
    "object_colour": "multicoloured multicoloured",
    "edition_description": "NA NA",
    "physical_appearance": "The image shows the front cover of a booklet. It has a yellow background. There are four lines of Chinese characters at the centre. There are two lines of Chinese characters near the bottom. There are drawings of buildings around the booklet as well. The image shows the front cover of a booklet. It has a yellow background. There are four lines of Chinese characters at the centre. There are two lines of Chinese characters near the bottom. There are drawings of buildings around the booklet as well.",
    "subject_terms_1": "governments (administrative bodies) politics economy economic development government policy budgets governments (administrative bodies) politics economy economic development government policy budgets",
    "subject_terms_2": "Pamphlets Government Institutes Political science Government policy Economic policy Budget Pamphlets Government Institutes Political science Government policy Economic policy Budget",
    "subject_terms_3": "Politics and Government Economic development Politics and Government Economic development",
    "subject_terms_4": "NA NA",
    "context_1": "NA NA",
    "context_2": "NA NA",
    "context_3": "NA NA",
    "context_4": "NA NA",
    "context_5": "NA NA",
    "context_6": "NA NA",
    "context_7": "NA NA",
    "context_8": "NA NA",
    "context_9": "NA NA",
    "context_10": "NA NA",
    "context_11": "NA NA",
    "context_12": "NA NA",
    "context_13": "NA NA",
    "context_14": "NA NA",
    "context_15": "NA NA",
    "context_16": "NA NA",
    "context_17": "NA NA",
    "context_18": "NA NA",
    "context_19": "NA NA",
    "context_20": "NA NA",
    "context_21": "NA NA",
    "context_22": "NA NA",
    "context_23": "NA NA",
    "context_24": "NA NA",
    "sgcool_label_text": "This booklet was published by the Ministry of Culture to communicate the new government’s messages and larger concerns regarding the state of the nation. The budget that Minister for Finance Dr Goh Keng Swee presented to the Legislative Assembly in 1960 is reproduced in Mandarin here. Topics that were brought up centred round the government’s economic policy, the review of the year’s expenditure and various revenue proposals such as property tax and business registration tax. This booklet was the third of the Towards Socialism series by the Ministry of Culture.  This booklet was published by the Ministry of Culture to communicate the new government’s messages and larger concerns regarding the state of the nation. The budget that Minister for Finance Dr Goh Keng Swee presented to the Legislative Assembly in 1960 is reproduced in Mandarin here. Topics that were brought up centred round the government’s economic policy, the review of the year’s expenditure and various revenue proposals such as property tax and business registration tax. This booklet was the third of the Towards Socialism series by the Ministry of Culture."
  },
  "nlpDate": "20201120223707",
  "connectorId": 0,
  "tags": {}
}