{"id":"2016-00591","title":"Priest\u0027s Vestments","source":"Bumblebee","path":"./Data/json/","content":"accession_no_csv:2016-00591\nImage:No image on SCMS\nobject_work_type:vestments\ntitle_text:Priest\\u0027s Vestments\npreference:main\ntitle_language:\ncreator_2:Unknown\ncreation_date:Not indicated\ncreation_place_original_location:Not indicated\nstyles_periods_indexing_terms:Not indicated\ninscriptions:\ninscription_language:\nscale_type:Not indicated\nshape:irregular\nmaterials_name:Not indicated\ntechniques_name:Not indicated\nobject_colour:pink (colour) red (colour)\nphysical_appearance:The image shows a set of garment. All of them are pink in colour except for one that is in red. The garment on the right hand side is shaped as a quadrant. It has floral designs on one of its sides. There is an image of a cross on the garment as well. The red garment on the left hand side is shaped as a square. The rest of the garments are rectangular in shape.\nsubject_terms_1:menswear liturgical costume costume accessories\nsubject_terms_2:Church vestments Men\\u0027s clothing\nsgcool_label_text:Not indicated","createdDate":"20201119143405","version":0,"latest":false,"roles":[],"metadata":{"accession_no_csv":"2016-00591","Image":"No image on SCMS","object_work_type":"vestments","title_text":"Priest\u0027s Vestments","preference":"main","title_language":"","creator_2":"Unknown","creation_date":"Not indicated","creation_place_original_location":"Not indicated","styles_periods_indexing_terms":"Not indicated","inscriptions":"","inscription_language":"","scale_type":"Not indicated","shape":"irregular","materials_name":"Not indicated","techniques_name":"Not indicated","object_colour":"pink (colour) red (colour)","physical_appearance":"The image shows a set of garment. All of them are pink in colour except for one that is in red. The garment on the right hand side is shaped as a quadrant. It has floral designs on one of its sides. There is an image of a cross on the garment as well. The red garment on the left hand side is shaped as a square. The rest of the garments are rectangular in shape.","subject_terms_1":"menswear liturgical costume costume accessories","subject_terms_2":"Church vestments Men\u0027s clothing","sgcool_label_text":"Not indicated"},"nlpDate":"20201119143405","connectorId":0,"tags":{}}