{
  "id": "2016-00066",
  "title": "Invitation to complimentary variety concert",
  "source": "Bumblebee",
  "path": "./Data/json/",
  "content": "\n  accession_no_csv: 2016-00066\n\n  Image: \n\n  object_work_type: invitations\n\n  title_text: Invitation to complimentary variety concert\n\n  preference: main\n\n  title_language: \n\n  creator_2: Unknown\n\n  creation_date: 8-Dec-55\n\n  creation_place_original_location: Singapore\n\n  styles_periods_indexing_terms: Not indicated\n\n  inscriptions: \n\n  inscription_language: \n\n  scale_type: Not indicated\n\n  shape: rectangular\n\n  materials_name: printing paper\n\n  techniques_name: printing (process)\n\n  object_colour: multicoloured\n\n  physical_appearance: \\The image shows an invitation card. It is rectangular in shape. It has a brown background. \\\\Complimentary Variety Concert by Ananda Kala Mandram\\\\ is stated. \\\\In Aid of Tamil is Our Life Fund at Beatty Secondary School Hall (Near Rumah Miskin) on Saturday\n\n  subject_terms_1: fund raising 8th December 1956 at 8p.m.\\\\ is stated. \\\\Sponsored by Vennila Kalai Arangam\\\\ is stated .  \\\n\n  subject_terms_2: Concerts concerts (performances) Benefit performances\n\n  subject_terms_3: Invitation cards Music Beatty Secondary School\n\n  subject_terms_4: Performing Arts\n\n  context_8: Vennila Kalai Arangam\n\n  context_9: sponsors\n",
  "createdDate": "20201201203309",
  "version": 0,
  "latest": false,
  "roles": [],
  "metadata": {
    "accession_no_csv": "2016-00066",
    "Image": "",
    "object_work_type": "invitations",
    "title_text": "Invitation to complimentary variety concert",
    "preference": "main",
    "title_language": "",
    "creator_2": "Unknown",
    "creation_date": "8-Dec-55",
    "creation_place_original_location": "Singapore",
    "styles_periods_indexing_terms": "Not indicated",
    "inscriptions": "",
    "inscription_language": "",
    "scale_type": "Not indicated",
    "shape": "rectangular",
    "materials_name": "printing paper",
    "techniques_name": "printing (process)",
    "object_colour": "multicoloured",
    "physical_appearance": "\"The image shows an invitation card. It is rectangular in shape. It has a brown background. \"\"Complimentary Variety Concert by Ananda Kala Mandram\"\" is stated. \"\"In Aid of Tamil is Our Life Fund at Beatty Secondary School Hall (Near Rumah Miskin) on Saturday",
    "subject_terms_1": "fund raising 8th December 1956 at 8p.m.\"\" is stated. \"\"Sponsored by Vennila Kalai Arangam\"\" is stated .  \"",
    "subject_terms_2": "Concerts concerts (performances) Benefit performances",
    "subject_terms_3": "Invitation cards Music Beatty Secondary School",
    "subject_terms_4": "Performing Arts",
    "context_8": "Vennila Kalai Arangam",
    "context_9": "sponsors"
  },
  "nlpDate": "20201201203309",
  "connectorId": 0,
  "tags": {}
}