{
  "id": "2016-00212-058",
  "title": "Photograph album of views and portraits in the Punjab, Cashmere, Ceylon, Burma, Penang, Singapore, and Java Singapore",
  "source": "Bumblebee",
  "path": "./Data/json/",
  "content": "\n  accession_no_csv: 2016-00212-058\n\n  Image: \n\n  object_work_type: black-and-white photographs\n\n  title_text: Photograph album of views and portraits in the Punjab\n Cashmere\n Ceylon\n Burma\n Penang\n Singapore\n and Java Singapore\n\n  preference: main alternate\n\n  title_language: \n\n  creator_2: John Thomson\n\n  creator_1: Thomson\n J. (John)\n 1837-1921\n\n  creator_role: photographers\n\n  creation_date: before 28 Jul 1876\n\n  creation_place_original_location: Singapore\n\n  inscriptions: \n\n  inscription_language: \n\n  shape: rectangular\n\n  materials_name: albumen (egg white protein) paper (fiber product) albumen paper\n\n  techniques_name: albumen process\n\n  object_colour: black-and-white (colors)\n\n  physical_appearance: This is a photograph of a view of Singapore from a high view point. The photograph features numerous roofed buildings\n with an empty field in the center. The background of the photograph shows the coast\n with a large number of ships at the harbour. The forefront of the photograph shows some treetops at the edge of a cliff\n with a man sitting near the bottom-right. The title is written at the bottom\n below the photograph.\n\n  subject_terms_1: scenery (landscape) harbours downtowns coastal settlements port settlements\n\n  subject_terms_2: Photographs Harbours Thomson\n J. (John)\n 1837-1921 coastal settlements Singapore\n\n  subject_terms_3: Landscape photography\n",
  "createdDate": "20201125084536",
  "version": 0,
  "latest": false,
  "roles": [],
  "metadata": {
    "accession_no_csv": "2016-00212-058",
    "Image": "",
    "object_work_type": "black-and-white photographs",
    "title_text": "Photograph album of views and portraits in the Punjab, Cashmere, Ceylon, Burma, Penang, Singapore, and Java Singapore",
    "preference": "main alternate",
    "title_language": "",
    "creator_2": "John Thomson",
    "creator_1": "Thomson, J. (John), 1837-1921",
    "creator_role": "photographers",
    "creation_date": "before 28 Jul 1876",
    "creation_place_original_location": "Singapore",
    "inscriptions": "",
    "inscription_language": "",
    "shape": "rectangular",
    "materials_name": "albumen (egg white protein) paper (fiber product) albumen paper",
    "techniques_name": "albumen process",
    "object_colour": "black-and-white (colors)",
    "physical_appearance": "This is a photograph of a view of Singapore from a high view point. The photograph features numerous roofed buildings, with an empty field in the center. The background of the photograph shows the coast, with a large number of ships at the harbour. The forefront of the photograph shows some treetops at the edge of a cliff, with a man sitting near the bottom-right. The title is written at the bottom, below the photograph.",
    "subject_terms_1": "scenery (landscape) harbours downtowns coastal settlements port settlements",
    "subject_terms_2": "Photographs Harbours Thomson, J. (John), 1837-1921 coastal settlements Singapore",
    "subject_terms_3": "Landscape photography"
  },
  "nlpDate": "20201125084536",
  "connectorId": 0,
  "tags": {}
}