{
  "id": "2016-00368",
  "title": "An oratory Portable Namban shrine",
  "source": "Bumblebee",
  "path": "./Data/json/",
  "content": "\n  accession_no_csv: 2016-00368\n\n  Image: \n\n  object_work_type: portable altarpieces\n\n  title_text: An oratory Portable Namban shrine\n\n  preference: alternate main\n\n  title_language: \n\n  creation_date: Early 17th century\n\n  creation_place_original_location: Japan Macau (China) (from curator\\u0027s notes)\n\n  styles_periods_indexing_terms: Japanese lacquer styles Momoyama\n\n  inscriptions: \n\n  inscription_language: \n\n  shape: irregular\n\n  materials_name: wood (plant material) lacquer (material) gold (metal) copper (metal) mother of pearl oil paint (paint) copper (metal)\n\n  techniques_name: painting (image-making) engraving (printing process)\n\n  object_colour: multicolored\n\n  physical_appearance: This is a portable altarpiece. It is composed of a rectangular wooden case.The sides of the case are decorated with Japanese lacquer techniques. There is a latch in the centre of the shrine. The doors of the shrine are painted with flower motifs\n scrolling leaves and trees\n with some images of birds. There are some small minor scratches and indents seen.\n\n  subject_terms_1: Japanese lacquer styles exports Roman Catholicism plant-derived motifs birds (motifs) lacquerware cultural diffusion oratories devotional objects\n\n  subject_terms_2: Altarpieces Triptychs Lacquer and lacquering Japan Namban art Exports Catholic Church Motifs cultural diffusion\n\n  subject_terms_3: Christianity Religious life and practices\n\n  sgcool_label_text: The decoration of this portable shrine\n probably used for private devotion\n combines Japanese lacquer craftsmanship\n European Christian subject matter\n and the late Mannerist painting style of Spain or Flanders. It is a striking example of interaction of cultures.  The crowned Virgin and sleeping Christ Child are flanked by St Joseph and the infant St John the Baptist. The inside and outside of the doors are decorated with Japanese lacquer techniques.  Lacquered furniture was one of the most prized Japanese products exported to Europe and Asia. Cabinets\n chests\n and other objects were decorated in the namban (literally\n “foreigners from the south”) style. The term came to be associated with artefacts made for foreigners. The principal customers for namban lacquer were the Portuguese\n who first arrived in Japan around 1542\n followed by the Spanish and the Dutch.\n",
  "createdDate": "20201120223706",
  "version": 0,
  "latest": false,
  "roles": [],
  "metadata": {
    "accession_no_csv": "2016-00368",
    "Image": "",
    "object_work_type": "portable altarpieces",
    "title_text": "An oratory Portable Namban shrine",
    "preference": "alternate main",
    "title_language": "",
    "creation_date": "Early 17th century",
    "creation_place_original_location": "Japan Macau (China) (from curator\u0027s notes)",
    "styles_periods_indexing_terms": "Japanese lacquer styles Momoyama",
    "inscriptions": "",
    "inscription_language": "",
    "shape": "irregular",
    "materials_name": "wood (plant material) lacquer (material) gold (metal) copper (metal) mother of pearl oil paint (paint) copper (metal)",
    "techniques_name": "painting (image-making) engraving (printing process)",
    "object_colour": "multicolored",
    "physical_appearance": "This is a portable altarpiece. It is composed of a rectangular wooden case.The sides of the case are decorated with Japanese lacquer techniques. There is a latch in the centre of the shrine. The doors of the shrine are painted with flower motifs, scrolling leaves and trees, with some images of birds. There are some small minor scratches and indents seen.",
    "subject_terms_1": "Japanese lacquer styles exports Roman Catholicism plant-derived motifs birds (motifs) lacquerware cultural diffusion oratories devotional objects",
    "subject_terms_2": "Altarpieces Triptychs Lacquer and lacquering Japan Namban art Exports Catholic Church Motifs cultural diffusion",
    "subject_terms_3": "Christianity Religious life and practices",
    "sgcool_label_text": "The decoration of this portable shrine, probably used for private devotion, combines Japanese lacquer craftsmanship, European Christian subject matter, and the late Mannerist painting style of Spain or Flanders. It is a striking example of interaction of cultures.  The crowned Virgin and sleeping Christ Child are flanked by St Joseph and the infant St John the Baptist. The inside and outside of the doors are decorated with Japanese lacquer techniques.  Lacquered furniture was one of the most prized Japanese products exported to Europe and Asia. Cabinets, chests, and other objects were decorated in the namban (literally, “foreigners from the south”) style. The term came to be associated with artefacts made for foreigners. The principal customers for namban lacquer were the Portuguese, who first arrived in Japan around 1542, followed by the Spanish and the Dutch."
  },
  "nlpDate": "20201120223706",
  "connectorId": 0,
  "tags": {}
}