{"id":"2016-00026-006","title":"Watercolour Batavia Portraits East Indie Native: Man in folk costume with spear","source":"Bumblebee","path":"./Data/json/","content":"accession_no_csv:2016-00026-006\nImage:\nobject_work_type:watercolors (paintings)\ntitle_text:Watercolour Batavia Portraits East Indie Native: Man in folk costume with spear\npreference:alternate main\ntitle_language:\ncreation_date:17th century\ncreation_place_original_location:Jakarta (Indonesia)\ninscriptions:\ninscription_language:\nshape:rectangular\nmaterials_name:watercolor (paint) paper (fiber product)\ntechniques_name:watercolor painting (technique)\nobject_colour:multicolored\nphysical_appearance:This is a watercolour painting of a native man in Batavia. The main is wearing a long-sleeved\n blue loose top\n a red-and-white striped shorts\n and a yellow hat with two ears. He is barefoot. He is holding a long spear in his left hand.\nsubject_terms_1:indigenous people ways of life ethnicity folk costume hunting spears\nsubject_terms_2:Watercolour painting Indigenous people Javanese (Indonesian people) Lifestyles Ethnicity Ethnic costume Hunting Equipment and supplies\nsubject_terms_3:Watercolour painting Visual Arts\nsgcool_label_text:This set of 6 watercolour on paper drawings depict Dutch school observations of Natives in the East Indies. Each full-length portrait is a study of the various ethnic groups from Java as well the distinctive mestizo – persons of mixed European and Indonesian ethnic ancestry. It is likely that this set of watercolour drawings are from 17th century. Costumes worn by mestiza women in Dutch colonial towns indicate a clear 17th century style\n characterised by a baju with a V-shaped opening for the head\n a selendang\n and a wrapped skirt of Indian cloth. \\r\\n\\r\\nListed as an un-authored work of art\n elements of the drawing bear strong resemblance to prominent 17th century Dutch artist\n Andries Beeckman’s (active 1651-57 Dutch East Indies) watercolour drawings of “A Woman of Batavia”\n mid-17th century. A blonde and barefoot mestiza for example\n reveals the same composition and formal features as Beeckman’s drawings – Her hair is tied in a chignon and accompanied by curly tresses descending from the side and her body is angled sideways\n with her right hand placed upon her head. It is plausible that these drawings are likely to be a copy of Andries Beeckman’s watercolour drawings of the same period.\\r\\n\\r\\nThese watercolour drawings depict a diverse community of ethnic groups from Java\n as well the impact of Dutch colonialism in the form of mixed race populations and subsequent impact on social and cultural customs and practices. Such portrayals in watercolour are rare and seldom appear in the open market.","createdDate":"20201018182635","version":0,"latest":false,"roles":[],"metadata":{"accession_no_csv":"2016-00026-006","Image":"","object_work_type":"watercolors (paintings)","title_text":"Watercolour Batavia Portraits East Indie Native: Man in folk costume with spear","preference":"alternate main","title_language":"","creation_date":"17th century","creation_place_original_location":"Jakarta (Indonesia)","inscriptions":"","inscription_language":"","shape":"rectangular","materials_name":"watercolor (paint) paper (fiber product)","techniques_name":"watercolor painting (technique)","object_colour":"multicolored","physical_appearance":"This is a watercolour painting of a native man in Batavia. The main is wearing a long-sleeved, blue loose top, a red-and-white striped shorts, and a yellow hat with two ears. He is barefoot. He is holding a long spear in his left hand.","subject_terms_1":"indigenous people ways of life ethnicity folk costume hunting spears","subject_terms_2":"Watercolour painting Indigenous people Javanese (Indonesian people) Lifestyles Ethnicity Ethnic costume Hunting Equipment and supplies","subject_terms_3":"Watercolour painting Visual Arts","sgcool_label_text":"This set of 6 watercolour on paper drawings depict Dutch school observations of Natives in the East Indies. Each full-length portrait is a study of the various ethnic groups from Java as well the distinctive mestizo – persons of mixed European and Indonesian ethnic ancestry. It is likely that this set of watercolour drawings are from 17th century. Costumes worn by mestiza women in Dutch colonial towns indicate a clear 17th century style, characterised by a baju with a V-shaped opening for the head, a selendang, and a wrapped skirt of Indian cloth. \r\n\r\nListed as an un-authored work of art, elements of the drawing bear strong resemblance to prominent 17th century Dutch artist, Andries Beeckman’s (active 1651-57 Dutch East Indies) watercolour drawings of “A Woman of Batavia”, mid-17th century. A blonde and barefoot mestiza for example, reveals the same composition and formal features as Beeckman’s drawings – Her hair is tied in a chignon and accompanied by curly tresses descending from the side and her body is angled sideways, with her right hand placed upon her head. It is plausible that these drawings are likely to be a copy of Andries Beeckman’s watercolour drawings of the same period.\r\n\r\nThese watercolour drawings depict a diverse community of ethnic groups from Java, as well the impact of Dutch colonialism in the form of mixed race populations and subsequent impact on social and cultural customs and practices. Such portrayals in watercolour are rare and seldom appear in the open market."},"nlpDate":"20201018182635","connectorId":0,"tags":{}}