{"id":"2016-00586","title":"Mortar Chinese stoneware mortar","source":"Bumblebee","path":"./Data/json/","content":"accession_no_csv:2016-00586\nImage:\nobject_work_type:mortars (grinding tools)\ntitle_text:Mortar Chinese stoneware mortar\npreference:alternate main\ntitle_language:\ncreation_date:960-1279\ncreation_place_original_location:China\nstyles_periods_indexing_terms:Song (Chinese culture\n style\n and period)\ninscriptions:\ninscription_language:\nshape:irregular\nmaterials_name:clay ceramic glaze\ntechniques_name:firing (technique) pottery glazing (process or technique)\nobject_colour:dark brown\nphysical_appearance:This stoneware mortar has a circular shape\n with a hollow center. The exterior of the mortar is carved with ribs\n resembling a cog. It is covered with a dark-brown glaze. The glaze is uneven\n especially along the bottom. The edges of the mortar\n especially along the exterior ridges\n are faded.\nsubject_terms_1:ceramics (object genre) kitchenware\nsubject_terms_2:Mortars Ceramics Kitchen utensils China History Song dynasty\n 960-1279\nsubject_terms_3:Ceramics\nsgcool_label_text:This heavily-potted stoneware mortar is carved with ribs around the exterior\n resembling a cog. It is covered with a dense\n darkly-brown glaze that thins at the extremities of the ribs to reveal a buff body beneath. At the same time\n the glaze pools to thick drops around the base. Vessels of such form were sometimes thought to have been used as a bowl for offerings. However\n the heaviness of this example indicates it was most probably used as a mortar\n possibly for the preparation of food or medicinal ingredients.","createdDate":"20201018182635","version":0,"latest":false,"roles":[],"metadata":{"accession_no_csv":"2016-00586","Image":"","object_work_type":"mortars (grinding tools)","title_text":"Mortar Chinese stoneware mortar","preference":"alternate main","title_language":"","creation_date":"960-1279","creation_place_original_location":"China","styles_periods_indexing_terms":"Song (Chinese culture, style, and period)","inscriptions":"","inscription_language":"","shape":"irregular","materials_name":"clay ceramic glaze","techniques_name":"firing (technique) pottery glazing (process or technique)","object_colour":"dark brown","physical_appearance":"This stoneware mortar has a circular shape, with a hollow center. The exterior of the mortar is carved with ribs, resembling a cog. It is covered with a dark-brown glaze. The glaze is uneven, especially along the bottom. The edges of the mortar, especially along the exterior ridges, are faded.","subject_terms_1":"ceramics (object genre) kitchenware","subject_terms_2":"Mortars Ceramics Kitchen utensils China History Song dynasty, 960-1279","subject_terms_3":"Ceramics","sgcool_label_text":"This heavily-potted stoneware mortar is carved with ribs around the exterior, resembling a cog. It is covered with a dense, darkly-brown glaze that thins at the extremities of the ribs to reveal a buff body beneath. At the same time, the glaze pools to thick drops around the base. Vessels of such form were sometimes thought to have been used as a bowl for offerings. However, the heaviness of this example indicates it was most probably used as a mortar, possibly for the preparation of food or medicinal ingredients."},"nlpDate":"20201018182635","connectorId":0,"tags":{}}