{
  "id": "2016-00652",
  "title": "Dutch colonial settee",
  "source": "Bumblebee",
  "path": "./Data/json/",
  "content": "\n  accession_no_csv: 2016-00652\n\n  Image: \n\n  object_work_type: settees (multiple-seating furniture)\n\n  title_text: Dutch colonial settee\n\n  preference: main\n\n  title_language: \n\n  creation_date: Late-19th century\n\n  creation_place_original_location: Dutch East Indies Indonesia\n\n  inscriptions: \n\n  inscription_language: \n\n  shape: irregular\n\n  materials_name: amboyna wood\n\n  techniques_name: woodworking\n\n  object_colour: multicoloured\n\n  physical_appearance: The image depicts a settee. The frames of the settee are made of a wooden material and it is brown in colour. The cushions on the seat and back have tiny holes arranged in straight lines. The design on the frame of the sette\n at the centre\n is of the shape of a scallop. On either side of the scalloped shape\n there are symmetrical wave patterns and a scroll motif. The legs of the settee are designed to be paw feet. There are no visible tears or cracks in the paintwork of the settee.\n\n  subject_terms_1: chairs (furniture forms) Dutch Colonial wave pattern scroll (motifs) paw feet\n\n  subject_terms_2: Chairs Furniture\n Dutch colonial Motifs\n\n  sgcool_label_text: \\This settee belonged to Paul Victor Emanuel Warnars (1876-1940) and his wife Maria Warnars-Krol (1885-1930). Warnars was involved in the tin mining industry\n living an working in Muntok\n which was at that time the capital of the Dutch Indies Bangka-Belitung Residency. The settee is made of Amboyna wood\n and was of a style popular across Dutch and British colonies in the 19th century. It bears the influence of the early 19th century \\\\Grecian\\\\ sofas designed by Thomas Sheraton.\\\n",
  "createdDate": "20201120223707",
  "version": 0,
  "latest": false,
  "roles": [],
  "metadata": {
    "accession_no_csv": "2016-00652",
    "Image": "",
    "object_work_type": "settees (multiple-seating furniture)",
    "title_text": "Dutch colonial settee",
    "preference": "main",
    "title_language": "",
    "creation_date": "Late-19th century",
    "creation_place_original_location": "Dutch East Indies Indonesia",
    "inscriptions": "",
    "inscription_language": "",
    "shape": "irregular",
    "materials_name": "amboyna wood",
    "techniques_name": "woodworking",
    "object_colour": "multicoloured",
    "physical_appearance": "The image depicts a settee. The frames of the settee are made of a wooden material and it is brown in colour. The cushions on the seat and back have tiny holes arranged in straight lines. The design on the frame of the sette, at the centre, is of the shape of a scallop. On either side of the scalloped shape, there are symmetrical wave patterns and a scroll motif. The legs of the settee are designed to be paw feet. There are no visible tears or cracks in the paintwork of the settee.",
    "subject_terms_1": "chairs (furniture forms) Dutch Colonial wave pattern scroll (motifs) paw feet",
    "subject_terms_2": "Chairs Furniture, Dutch colonial Motifs",
    "sgcool_label_text": "\"This settee belonged to Paul Victor Emanuel Warnars (1876-1940) and his wife Maria Warnars-Krol (1885-1930). Warnars was involved in the tin mining industry, living an working in Muntok, which was at that time the capital of the Dutch Indies Bangka-Belitung Residency. The settee is made of Amboyna wood, and was of a style popular across Dutch and British colonies in the 19th century. It bears the influence of the early 19th century \"\"Grecian\"\" sofas designed by Thomas Sheraton.\""
  },
  "nlpDate": "20201120223707",
  "connectorId": 0,
  "tags": {}
}