{
  "id": "2016-00173",
  "title": "Purple cheongsam",
  "source": "Bumblebee",
  "path": "./Data/json/",
  "content": "\n  accession_no_csv: 2016-00173\n\n  Image: \n\n  object_work_type: womenswear folk costume\n\n  title_text: Purple cheongsam\n\n  preference: main\n\n  title_language: \n\n  creation_date: 1960 - 1969\n\n  creation_place_original_location: Singapore\n\n  styles_periods_indexing_terms: Chinese (culture or style)\n\n  inscriptions: \n\n  inscription_language: \n\n  shape: irregular\n\n  materials_name: synthetic fiber\n\n  techniques_name: piping (process) machine sewing (technique)\n\n  object_colour: purple (colour)\n\n  physical_appearance: This is a purple cheongsam with very short sleeves. There is a collar present as well. There are no visible tears on the cheongsam\n but its exterior looks worn out. The collar tag of the cheongsam is visible. Abstract prints appear all over the purple cheongsam.\n\n  subject_terms_1: dresses (garments) allover patterns\n\n  subject_terms_2: Women\\u0027s clothing Qipao Ethnic costume Patterns for crafts\n\n  subject_terms_3: Ethnic costume Chinese costume\n",
  "createdDate": "20201201203309",
  "version": 0,
  "latest": false,
  "roles": [],
  "metadata": {
    "accession_no_csv": "2016-00173",
    "Image": "",
    "object_work_type": "womenswear folk costume",
    "title_text": "Purple cheongsam",
    "preference": "main",
    "title_language": "",
    "creation_date": "1960 - 1969",
    "creation_place_original_location": "Singapore",
    "styles_periods_indexing_terms": "Chinese (culture or style)",
    "inscriptions": "",
    "inscription_language": "",
    "shape": "irregular",
    "materials_name": "synthetic fiber",
    "techniques_name": "piping (process) machine sewing (technique)",
    "object_colour": "purple (colour)",
    "physical_appearance": "This is a purple cheongsam with very short sleeves. There is a collar present as well. There are no visible tears on the cheongsam, but its exterior looks worn out. The collar tag of the cheongsam is visible. Abstract prints appear all over the purple cheongsam.",
    "subject_terms_1": "dresses (garments) allover patterns",
    "subject_terms_2": "Women\u0027s clothing Qipao Ethnic costume Patterns for crafts",
    "subject_terms_3": "Ethnic costume Chinese costume"
  },
  "nlpDate": "20201201203309",
  "connectorId": 0,
  "tags": {}
}