{"id":"2016-00095-003","title":"Workers annex and shop at Coronation West Road, late 1940s","source":"Bumblebee","path":"./Data/json/","content":"accession_no_csv:2016-00095-003\nImage:\nobject_work_type:black-and-white photographs\ntitle_text:Workers annex and shop at Coronation West Road\n late 1940s\npreference:main\ntitle_language:\ncreation_date:1940s\ncreation_place_original_location:Singapore\ninscriptions:\ninscription_language:\nshape:rectangular\nmaterials_name:paper (fiber product)\ntechniques_name:printing (process) photographic processes\nobject_colour:grey monochrome\nphysical_appearance:\\The image shows a photograph that is in black-and-white. It is rectangular and it features a single storey building in the background. In front of the building\n four men are standing and looking in the direction where the photograph was captured. They are dressed in a variety of outfits. There are several items in the building behind them\n and the words \\\\Magnolia\\\\ can be seen pasted on a container\\\nsubject_terms_1:general stores workers\nsubject_terms_2:Black-and-white photography General stores Employees Singapore\nsubject_terms_3:Photography Coronation Road West\nsgcool_label_text:A native of Karuvakurichi village\n near Mannargudi town in Tamil Nadu\n S. Appavoo Kandiar was a general contractor specializing in pipe and cable laying\n handling of cargo and a concrete bricks supplier. Mr.Kandiar was a successful contractor; called a millionaire by the Straits Times in 1957\n he owned properties in Bukit Timah and Coronation Road areas. He was a contemporary of Indian pioneers such as P.Govindasamy Pillai\n Govindasamy Sarangapany\n Pakkirisami Pillai\n and had friendly associations with them.","createdDate":"20201018182635","version":0,"latest":false,"roles":[],"metadata":{"accession_no_csv":"2016-00095-003","Image":"","object_work_type":"black-and-white photographs","title_text":"Workers annex and shop at Coronation West Road, late 1940s","preference":"main","title_language":"","creation_date":"1940s","creation_place_original_location":"Singapore","inscriptions":"","inscription_language":"","shape":"rectangular","materials_name":"paper (fiber product)","techniques_name":"printing (process) photographic processes","object_colour":"grey monochrome","physical_appearance":"\"The image shows a photograph that is in black-and-white. It is rectangular and it features a single storey building in the background. In front of the building, four men are standing and looking in the direction where the photograph was captured. They are dressed in a variety of outfits. There are several items in the building behind them, and the words \"\"Magnolia\"\" can be seen pasted on a container\"","subject_terms_1":"general stores workers","subject_terms_2":"Black-and-white photography General stores Employees Singapore","subject_terms_3":"Photography Coronation Road West","sgcool_label_text":"A native of Karuvakurichi village, near Mannargudi town in Tamil Nadu, S. Appavoo Kandiar was a general contractor specializing in pipe and cable laying, handling of cargo and a concrete bricks supplier. Mr.Kandiar was a successful contractor; called a millionaire by the Straits Times in 1957, he owned properties in Bukit Timah and Coronation Road areas. He was a contemporary of Indian pioneers such as P.Govindasamy Pillai, Govindasamy Sarangapany, Pakkirisami Pillai, and had friendly associations with them."},"nlpDate":"20201018182635","connectorId":0,"tags":{}}