{
  "id": "2016-00046",
  "title": "The Further Side of Silence The Further Side of Silence by Hugh Clifford",
  "source": "Bumblebee",
  "path": "./Data/json/",
  "content": "\n  accession_no_csv: 2016-00046\n\n  Image: \n\n  object_work_type: hardcover books illustrated books\n\n  title_text: The Further Side of Silence The Further Side of Silence by Hugh Clifford\n\n  preference: main alternate\n\n  title_language: \n\n  creator_2: Sir Hugh Charles Clifford Mahlon Blaine\n\n  creator_1: Clifford\n Hugh Charles\n Sir\n 1866 - 1941 Blaine\n Mahlon\n\n  creator_role: authors illustrators\n\n  creation_date: 1927\n\n  creation_place_original_location: United States\n\n  inscriptions: \n\n  inscription_language: \n\n  shape: rectangular\n\n  materials_name: paper (fiber product) printing paper\n\n  techniques_name: colour printing bookbinding (process) book cloth (textile material)\n\n  object_colour: multicoloured\n\n  physical_appearance: The book is hardcover and its front cover is predominantly sepia in colour. There is an image of a scimitar in a decorated square border at the top centre of the front cover. The title and author of the book are displayed inside this square border as well. On the book\\u0027s spine\n the same images are displayed\n but they are enclosed in a rectangular border instead.  There are no visible tears and the book looks slightly worn out near its top.\n\n  subject_terms_1: autofiction short stories ethnic groups colonial settlements Orientalism\n\n  subject_terms_2: Malay Peninsula Colonization Malays (Asian people) Illustrated books Orientalism\n\n  subject_terms_3: Fiction Colonial administrators Clifford\n Hugh Charles\n Sir\n\n  sgcool_label_text: \\The Further Side of Silence is a collection of short stories by Hugh Clifford\n British Resident of Penang (1896-1900)\n Governor of North Borneo (1900-1901) and Governor of the Straits Settlements (1927-1930). The short stories in this collection\n while fictional\n are based on Clifford\\u0027s personal experiences in the Malay Peninsula. In his preface\n Clifford claims that these stories \\\\faithfully reproduce the conditions of life as they existed in the Malayan Peninsula before the white man took a hand in the government of the native states\n",
  "createdDate": "20201120223706",
  "version": 0,
  "latest": false,
  "roles": [],
  "metadata": {
    "accession_no_csv": "2016-00046",
    "Image": "",
    "object_work_type": "hardcover books illustrated books",
    "title_text": "The Further Side of Silence The Further Side of Silence by Hugh Clifford",
    "preference": "main alternate",
    "title_language": "",
    "creator_2": "Sir Hugh Charles Clifford Mahlon Blaine",
    "creator_1": "Clifford, Hugh Charles, Sir, 1866 - 1941 Blaine, Mahlon",
    "creator_role": "authors illustrators",
    "creation_date": "1927",
    "creation_place_original_location": "United States",
    "inscriptions": "",
    "inscription_language": "",
    "shape": "rectangular",
    "materials_name": "paper (fiber product) printing paper",
    "techniques_name": "colour printing bookbinding (process) book cloth (textile material)",
    "object_colour": "multicoloured",
    "physical_appearance": "The book is hardcover and its front cover is predominantly sepia in colour. There is an image of a scimitar in a decorated square border at the top centre of the front cover. The title and author of the book are displayed inside this square border as well. On the book\u0027s spine, the same images are displayed, but they are enclosed in a rectangular border instead.  There are no visible tears and the book looks slightly worn out near its top.",
    "subject_terms_1": "autofiction short stories ethnic groups colonial settlements Orientalism",
    "subject_terms_2": "Malay Peninsula Colonization Malays (Asian people) Illustrated books Orientalism",
    "subject_terms_3": "Fiction Colonial administrators Clifford, Hugh Charles, Sir",
    "sgcool_label_text": "\"The Further Side of Silence is a collection of short stories by Hugh Clifford, British Resident of Penang (1896-1900), Governor of North Borneo (1900-1901) and Governor of the Straits Settlements (1927-1930). The short stories in this collection, while fictional, are based on Clifford\u0027s personal experiences in the Malay Peninsula. In his preface, Clifford claims that these stories \"\"faithfully reproduce the conditions of life as they existed in the Malayan Peninsula before the white man took a hand in the government of the native states"
  },
  "nlpDate": "20201120223706",
  "connectorId": 0,
  "tags": {}
}