{"id":"2016-00212-016","title":"Photograph album of views and portraits in the Punjab, Cashmere, Ceylon, Burma, Penang, Singapore, and Java Kajyara, Chumba, Punjab","source":"Bumblebee","path":"./Data/json/","content":"accession_no_csv:2016-00212-016\nImage:\nobject_work_type:black-and-white photographs\ntitle_text:Photograph album of views and portraits in the Punjab\n Cashmere\n Ceylon\n Burma\n Penang\n Singapore\n and Java Kajyara\n Chumba\n Punjab\npreference:alternate main\ntitle_language:\ncreator_2:John Thomson\ncreator_1:Thomson\n J. (John)\n 1837-1921\ncreator_role:photographers\ncreation_date:before 28 Jul 1876\ncreation_place_original_location:Singapore Punjab (India)\ninscriptions:\ninscription_language:\nshape:rectangular\nmaterials_name:albumen (egg white protein) albumen paper paper (fiber product)\ntechniques_name:albumen process\nobject_colour:black-and-white (colors)\nphysical_appearance:This is a photograph of a small town in Kajyara\n in Punjab. The photograph shows a clearing at the bottom of a hill. There is a wooden fence snaking through the clearing from the left of the photograph. There are two roofed houses in the photograph. On the right of the photograph\n there is a man on a narrow path. There is a small tear on the bottom-left of the photograph. The title is written at the bottom\n below the photograph.\nsubject_terms_1:villages scenery (landscape) rural areas\nsubject_terms_2:Photographs Thomson\n J. (John)\n 1837-1921 Punjab (India)\nsubject_terms_3:Landscape photography","createdDate":"20201018182635","version":0,"latest":false,"roles":[],"metadata":{"accession_no_csv":"2016-00212-016","Image":"","object_work_type":"black-and-white photographs","title_text":"Photograph album of views and portraits in the Punjab, Cashmere, Ceylon, Burma, Penang, Singapore, and Java Kajyara, Chumba, Punjab","preference":"alternate main","title_language":"","creator_2":"John Thomson","creator_1":"Thomson, J. (John), 1837-1921","creator_role":"photographers","creation_date":"before 28 Jul 1876","creation_place_original_location":"Singapore Punjab (India)","inscriptions":"","inscription_language":"","shape":"rectangular","materials_name":"albumen (egg white protein) albumen paper paper (fiber product)","techniques_name":"albumen process","object_colour":"black-and-white (colors)","physical_appearance":"This is a photograph of a small town in Kajyara, in Punjab. The photograph shows a clearing at the bottom of a hill. There is a wooden fence snaking through the clearing from the left of the photograph. There are two roofed houses in the photograph. On the right of the photograph, there is a man on a narrow path. There is a small tear on the bottom-left of the photograph. The title is written at the bottom, below the photograph.","subject_terms_1":"villages scenery (landscape) rural areas","subject_terms_2":"Photographs Thomson, J. (John), 1837-1921 Punjab (India)","subject_terms_3":"Landscape photography"},"nlpDate":"20201018182635","connectorId":0,"tags":{}}