{"id":"2016-00719","title":"White Kebaya with Grid-like Embroidery","source":"Bumblebee","path":"./Data/json/","content":"accession_no_csv:2016-00719\nImage:\nobject_work_type:kebayas womenswear\ntitle_text:White Kebaya with Grid-like Embroidery\npreference:main\ntitle_language:\ncreation_date:early-mid 20th century\ncreation_place_original_location:Java (Indonesia)\ninscriptions:\ninscription_language:\nshape:irregular\nmaterials_name:cotton (textile)\ntechniques_name:sewing (needleworking technique) embroidering\nobject_colour:white (color)\nphysical_appearance:This is a white kebaya top. It has a intricate grid-like pattern embroided across the fabric. The edges of the top is decorated with lace.\nsubject_terms_1:folk costume Peranakan cultural diffusion tops (garments\n general) blouses (main garments)\nsubject_terms_2:Ethnic costume Peranakan (Asian people) Culture diffusion Blouses\nsubject_terms_3:Peranakan costumes\nsgcool_label_text:This white kebaya has an intricate grid-like pattern embroidered across its surface. Modest amount of lace decorates the edges. Paired with a sarong\n kebayas would have been worn by European and Eurasian women before it was adopted by Peranakan women sometime around the turn of the 20th century. It is part of a donation which contains a mixture of garments worn by Peranakan men and women.","createdDate":"20201119143406","version":0,"latest":false,"roles":[],"metadata":{"accession_no_csv":"2016-00719","Image":"","object_work_type":"kebayas womenswear","title_text":"White Kebaya with Grid-like Embroidery","preference":"main","title_language":"","creation_date":"early-mid 20th century","creation_place_original_location":"Java (Indonesia)","inscriptions":"","inscription_language":"","shape":"irregular","materials_name":"cotton (textile)","techniques_name":"sewing (needleworking technique) embroidering","object_colour":"white (color)","physical_appearance":"This is a white kebaya top. It has a intricate grid-like pattern embroided across the fabric. The edges of the top is decorated with lace.","subject_terms_1":"folk costume Peranakan cultural diffusion tops (garments, general) blouses (main garments)","subject_terms_2":"Ethnic costume Peranakan (Asian people) Culture diffusion Blouses","subject_terms_3":"Peranakan costumes","sgcool_label_text":"This white kebaya has an intricate grid-like pattern embroidered across its surface. Modest amount of lace decorates the edges. Paired with a sarong, kebayas would have been worn by European and Eurasian women before it was adopted by Peranakan women sometime around the turn of the 20th century. It is part of a donation which contains a mixture of garments worn by Peranakan men and women."},"nlpDate":"20201119143406","connectorId":0,"tags":{}}