{
  "id": "2016-00139",
  "title": "Purple and pink striped cheongsam",
  "source": "Bumblebee",
  "path": "./Data/json/",
  "content": "\n  accession_no_csv: 2016-00139\n\n  Image: \n\n  object_work_type: folk costume\n\n  title_text: Purple and pink striped cheongsam\n\n  preference: main\n\n  title_language: \n\n  creation_date: Not indicated\n\n  creation_place_original_location: Singapore\n\n  styles_periods_indexing_terms: Chinese (culture or style)\n\n  inscriptions: \n\n  inscription_language: \n\n  shape: irregular\n\n  materials_name: cloth\n\n  techniques_name: embroidering machine sewing (technique)\n\n  object_colour: multicoloured\n\n  physical_appearance: This is a purple and pink cheongsam and it is sleeveless. There is a collar present as well. There are no visible tears on the exterior of the cheongsam. There is no piping on the front of the cheongsam as well. Stripes that run vertically down the cheongsam are present on its front as well as the collar. Also\n running down the middle of the cheongsam is patterned embroidery that is symmetrical in design. The embroidery is pink in colour.\n\n  subject_terms_1: dresses (garments) womenswear geometric patterns lace (needlework) running ornament stripes\n\n  subject_terms_2: Women\\u0027s clothing Motifs Qipao Ethnic costume\n\n  subject_terms_3: Ethnic costume Chinese costume\n\n  sgcool_label_text: This is a sleeveless cheongsam in light purple and pink stripes. A patterned embroidery in light pink runs down the centre of the cheongsam on the front. This cheongsam was wore by Mrs Lee In Tong in her younger days.\n",
  "createdDate": "20201201203309",
  "version": 0,
  "latest": false,
  "roles": [],
  "metadata": {
    "accession_no_csv": "2016-00139",
    "Image": "",
    "object_work_type": "folk costume",
    "title_text": "Purple and pink striped cheongsam",
    "preference": "main",
    "title_language": "",
    "creation_date": "Not indicated",
    "creation_place_original_location": "Singapore",
    "styles_periods_indexing_terms": "Chinese (culture or style)",
    "inscriptions": "",
    "inscription_language": "",
    "shape": "irregular",
    "materials_name": "cloth",
    "techniques_name": "embroidering machine sewing (technique)",
    "object_colour": "multicoloured",
    "physical_appearance": "This is a purple and pink cheongsam and it is sleeveless. There is a collar present as well. There are no visible tears on the exterior of the cheongsam. There is no piping on the front of the cheongsam as well. Stripes that run vertically down the cheongsam are present on its front as well as the collar. Also, running down the middle of the cheongsam is patterned embroidery that is symmetrical in design. The embroidery is pink in colour.",
    "subject_terms_1": "dresses (garments) womenswear geometric patterns lace (needlework) running ornament stripes",
    "subject_terms_2": "Women\u0027s clothing Motifs Qipao Ethnic costume",
    "subject_terms_3": "Ethnic costume Chinese costume",
    "sgcool_label_text": "This is a sleeveless cheongsam in light purple and pink stripes. A patterned embroidery in light pink runs down the centre of the cheongsam on the front. This cheongsam was wore by Mrs Lee In Tong in her younger days."
  },
  "nlpDate": "20201201203309",
  "connectorId": 0,
  "tags": {}
}