{"id":"2016-00339","title":"Dish cover Thaalposh","source":"Bumblebee","path":"./Data/json/","content":"accession_no_csv:2016-00339\nImage:\nobject_work_type:covers (closures)\ntitle_text:Dish cover Thaalposh\npreference:main main\ntitle_language:\ncreation_date:1901 - 2000\ncreation_place_original_location:Deccan (India)\nstyles_periods_indexing_terms:Islamic Indian\ninscriptions:\ninscription_language:\nshape:heptagons\nmaterials_name:silk (textile) cotton (textile) ink\ntechniques_name:sewing (needleworking technique) kalamkari calligraphy (process)\nobject_colour:multicoloured\nphysical_appearance:The Thaalposh\n or dish cover\n is heptagonal in shape. An outline of a circle is situated within the heptagon. It has an inner and outer circumference and the border in between has numerous patterns of fruits in the colour of red. Within the inner circumference\n A line of calligraphy is written in each of the four straight sections that extend from the inner circle of the circular dish to the outer circle. The sections facing the directions of East and West are dark red in colour\n while the ones in the directions of North and South are light brown in colour. All four sections contain similar patterns of scrolls. At the centre of the heptagon\n there is a single flower. This flower is surrounded by numerous smaller flowers\n that are drawn together to form a smaller circle as well.\nsubject_terms_1:decorative art (art genre) Islam ritual objects textiles (visual works) floral patterns scrolls (motifs) allover patterns\nsubject_terms_2:Islam Calligraphy\n Urdu Textiles Motifs\nsubject_terms_3:Islam\nsgcool_label_text:This hand printed cotton thaalposh or large dish cover originates from the Deccan region. It would have been used to cover dishes during religious festivals by Deccani Muslims\n both sunnis and shiyas. The kalamkari print shows not only the traditional floral designs and red-ochre colours\n but also incorporates four sections of calligraphy\n highlighting the textile’s use in ritual. The kalamkari printing can be attributed to the south Indian centre of Masulipatnam.","createdDate":"20201119143405","version":0,"latest":false,"roles":[],"metadata":{"accession_no_csv":"2016-00339","Image":"","object_work_type":"covers (closures)","title_text":"Dish cover Thaalposh","preference":"main main","title_language":"","creation_date":"1901 - 2000","creation_place_original_location":"Deccan (India)","styles_periods_indexing_terms":"Islamic Indian","inscriptions":"","inscription_language":"","shape":"heptagons","materials_name":"silk (textile) cotton (textile) ink","techniques_name":"sewing (needleworking technique) kalamkari calligraphy (process)","object_colour":"multicoloured","physical_appearance":"The Thaalposh, or dish cover, is heptagonal in shape. An outline of a circle is situated within the heptagon. It has an inner and outer circumference and the border in between has numerous patterns of fruits in the colour of red. Within the inner circumference, A line of calligraphy is written in each of the four straight sections that extend from the inner circle of the circular dish to the outer circle. The sections facing the directions of East and West are dark red in colour, while the ones in the directions of North and South are light brown in colour. All four sections contain similar patterns of scrolls. At the centre of the heptagon, there is a single flower. This flower is surrounded by numerous smaller flowers, that are drawn together to form a smaller circle as well.","subject_terms_1":"decorative art (art genre) Islam ritual objects textiles (visual works) floral patterns scrolls (motifs) allover patterns","subject_terms_2":"Islam Calligraphy, Urdu Textiles Motifs","subject_terms_3":"Islam","sgcool_label_text":"This hand printed cotton thaalposh or large dish cover originates from the Deccan region. It would have been used to cover dishes during religious festivals by Deccani Muslims, both sunnis and shiyas. The kalamkari print shows not only the traditional floral designs and red-ochre colours, but also incorporates four sections of calligraphy, highlighting the textile’s use in ritual. The kalamkari printing can be attributed to the south Indian centre of Masulipatnam."},"nlpDate":"20201119143405","connectorId":0,"tags":{}}