{
  "id": "2016-00276",
  "title": "Gold Medal from the collection of Jayaram S/o Rengasamy who was part of Singapore’s 4x440 yards athletes at Merdeka Games, Kuala Lumpur Gold Medal from the collection Jayaram S/o Rengasamy who was part of Singapore’s 4x440 yards athletes at Merdeka Games, Kuala Lumpur",
  "source": "Bumblebee",
  "path": "./Data/json/",
  "content": "\n  accession_no_csv: 2016-00276\n\n  Image: \n\n  object_work_type: medals\n\n  title_text: Gold Medal from the collection of Jayaram S/o Rengasamy who was part of Singapore’s 4x440 yards athletes at Merdeka Games\n Kuala Lumpur Gold Medal from the collection Jayaram S/o Rengasamy who was part of Singapore’s 4x440 yards athletes at Merdeka Games\n Kuala Lumpur\n\n  preference: main alternate\n\n  title_language: \n\n  creator_2: F. Phillips Medallists Aldershot\n\n  creator_1: Not indicated\n\n  creator_role: manufacturers\n\n  creation_date: 1957\n\n  creation_place_original_location: Kuala Lumpur (Malaysia)\n\n  inscriptions: \n\n  inscription_language: \n\n  shape: rectangular cuboid circular (shape)\n\n  materials_name: metal\n\n  techniques_name: metalworking\n\n  object_colour: multicoloured\n\n  physical_appearance: \\A gold medal placed in an open case are displayed in the picture. The box is rectangular and light blue in colour. At the centre of the top surface of the case\n it states \\\\F. Phillips Medallist Aldershot\\\\. The padding is light brown in colour and it holds the circular gold medal in place. At the centre of the gold medal\n\n  subject_terms_1: cases (containers) it states \\\\4 x 440 YDS Relay\\\\. There is also a laurel wreath design on the gold medal commemoratives prizes honours athletes competitions (events) foliage (motif) races (events)\n\n  subject_terms_2: Running races Motifs Athletes Containers surrounding the words.\\ Awards\n\n  subject_terms_3: sportsmen Sports and recreational events Athletics Runners (Athletes)\n\n  subject_terms_4: Medals\n\n  context_1: Rengasamy Jayaram\n",
  "createdDate": "20201201203309",
  "version": 0,
  "latest": false,
  "roles": [],
  "metadata": {
    "accession_no_csv": "2016-00276",
    "Image": "",
    "object_work_type": "medals",
    "title_text": "Gold Medal from the collection of Jayaram S/o Rengasamy who was part of Singapore’s 4x440 yards athletes at Merdeka Games, Kuala Lumpur Gold Medal from the collection Jayaram S/o Rengasamy who was part of Singapore’s 4x440 yards athletes at Merdeka Games, Kuala Lumpur",
    "preference": "main alternate",
    "title_language": "",
    "creator_2": "F. Phillips Medallists Aldershot",
    "creator_1": "Not indicated",
    "creator_role": "manufacturers",
    "creation_date": "1957",
    "creation_place_original_location": "Kuala Lumpur (Malaysia)",
    "inscriptions": "",
    "inscription_language": "",
    "shape": "rectangular cuboid circular (shape)",
    "materials_name": "metal",
    "techniques_name": "metalworking",
    "object_colour": "multicoloured",
    "physical_appearance": "\"A gold medal placed in an open case are displayed in the picture. The box is rectangular and light blue in colour. At the centre of the top surface of the case, it states \"\"F. Phillips Medallist Aldershot\"\". The padding is light brown in colour and it holds the circular gold medal in place. At the centre of the gold medal",
    "subject_terms_1": "cases (containers) it states \"\"4 x 440 YDS Relay\"\". There is also a laurel wreath design on the gold medal commemoratives prizes honours athletes competitions (events) foliage (motif) races (events)",
    "subject_terms_2": "Running races Motifs Athletes Containers surrounding the words.\" Awards",
    "subject_terms_3": "sportsmen Sports and recreational events Athletics Runners (Athletes)",
    "subject_terms_4": "Medals",
    "context_1": "Rengasamy Jayaram"
  },
  "nlpDate": "20201201203309",
  "connectorId": 0,
  "tags": {}
}