{"id":"2016-00749","title":"The Day I Lost My Shadow","source":"Bumblebee","path":"./Data/json/","content":"accession_no_csv:2016-00749\nImage:\nobject_work_type:video art\ntitle_text:The Day I Lost My Shadow\npreference:main\ntitle_language:\ncreator_2:Rajagopal K\ncreator_role:creators\ncreation_date:2016\ncreation_place_original_location:Singapore\ninscriptions:\ninscription_language:\nmaterials_name:mixed media\ntechniques_name:videography creating (artistic activity)\nphysical_appearance:\\This is an image of a two still frames from within a video clip. Both of the still frames are in black-and-white. The one on the left displays the words \\\\The Day\nsubject_terms_1:Race Course Road\\\\. The still frame shows the interior of a building ethnohistory film (performing arts) historical figures multiculturalism social history reconstructions (visual works) cultural diffusion\nsubject_terms_2:where there is a shovel and some sandbags lying on the sandy ground. The still frame on the right displays a vast landscape of greenery. There are numerous trees and shrubs that can be seen on the foreground as well as towards the horizon. \\ Little India (Singapore) Ethnohistory Social change Multiculturalism Motion pictures Culture diffusion\nsubject_terms_3:video recordings Campbell Lane Race Course Road Syed Alwi Road Little India Sub Zone\nsubject_terms_4:Video recordings\ncontext_1:Films","createdDate":"20201119143406","version":0,"latest":false,"roles":[],"metadata":{"accession_no_csv":"2016-00749","Image":"","object_work_type":"video art","title_text":"The Day I Lost My Shadow","preference":"main","title_language":"","creator_2":"Rajagopal K","creator_role":"creators","creation_date":"2016","creation_place_original_location":"Singapore","inscriptions":"","inscription_language":"","materials_name":"mixed media","techniques_name":"videography creating (artistic activity)","physical_appearance":"\"This is an image of a two still frames from within a video clip. Both of the still frames are in black-and-white. The one on the left displays the words \"\"The Day","subject_terms_1":"Race Course Road\"\". The still frame shows the interior of a building ethnohistory film (performing arts) historical figures multiculturalism social history reconstructions (visual works) cultural diffusion","subject_terms_2":"where there is a shovel and some sandbags lying on the sandy ground. The still frame on the right displays a vast landscape of greenery. There are numerous trees and shrubs that can be seen on the foreground as well as towards the horizon. \" Little India (Singapore) Ethnohistory Social change Multiculturalism Motion pictures Culture diffusion","subject_terms_3":"video recordings Campbell Lane Race Course Road Syed Alwi Road Little India Sub Zone","subject_terms_4":"Video recordings","context_1":"Films"},"nlpDate":"20201119143406","connectorId":0,"tags":{}}