{"id":"2016-00360","title":"Certificate of Membership, Certificate of Membership, (“This is certify that Tamil Murasu is a member of the Audit Bureau of Circulations”)","source":"Bumblebee","path":"./Data/json/","content":"accession_no_csv:2016-00360\nImage:\nobject_work_type:certificates\ntitle_text:Certificate of Membership\n Certificate of Membership\n (“This is certify that Tamil Murasu is a member of the Audit Bureau of Circulations”)\npreference:main alternate\ntitle_language:\ncreator_2:Audit Bureau of Circulations (UK)\ncreator_1:Audit Bureau of Circulations (Great Britain)\ncreator_role:creators\ncreation_date:19580212\ncreation_place_original_location:Singapore\ninscriptions:\ninscription_language:\nshape:rectangular\nmaterials_name:paper (fiber product)\ntechniques_name:printing (process) woodcarving\nobject_colour:multicoloured\nphysical_appearance:\\The image shows a legal certificate of membership. It is rectangular in shape. The logo of the Audit Bureau of Circulations (UK) is displayed at the top\n together with the words \\\\Incorporated October 14th 1931\\\\. \\\\Audit Bureau of Circulation Limited (By Guarantee)\\\\ is stated just below the logo. The certificate states the following\nsubject_terms_1:\\\\Certificate of Membership. This is to certify that Tamil Murasu is a member of Audit Bureau of Circulation Ltd. Given under our hands and the common seal of the company of London the twelfth day of February legal documents bureaus (offices) businesses (business enterprises) newspapers\nsubject_terms_2:one thousand nine hundred and fifty eight\\\\. At the bottom left hand side of the certificate Legal documents Business enterprises Membership Newspapers\nsubject_terms_3:there is a red embossed seal together with signatures by members of the council.\\\nsubject_terms_4:certification\ncontext_1:Certification\ncontext_2:Daily newspapers","createdDate":"20201119143405","version":0,"latest":false,"roles":[],"metadata":{"accession_no_csv":"2016-00360","Image":"","object_work_type":"certificates","title_text":"Certificate of Membership, Certificate of Membership, (“This is certify that Tamil Murasu is a member of the Audit Bureau of Circulations”)","preference":"main alternate","title_language":"","creator_2":"Audit Bureau of Circulations (UK)","creator_1":"Audit Bureau of Circulations (Great Britain)","creator_role":"creators","creation_date":"19580212","creation_place_original_location":"Singapore","inscriptions":"","inscription_language":"","shape":"rectangular","materials_name":"paper (fiber product)","techniques_name":"printing (process) woodcarving","object_colour":"multicoloured","physical_appearance":"\"The image shows a legal certificate of membership. It is rectangular in shape. The logo of the Audit Bureau of Circulations (UK) is displayed at the top, together with the words \"\"Incorporated October 14th 1931\"\". \"\"Audit Bureau of Circulation Limited (By Guarantee)\"\" is stated just below the logo. The certificate states the following","subject_terms_1":"\"\"Certificate of Membership. This is to certify that Tamil Murasu is a member of Audit Bureau of Circulation Ltd. Given under our hands and the common seal of the company of London the twelfth day of February legal documents bureaus (offices) businesses (business enterprises) newspapers","subject_terms_2":"one thousand nine hundred and fifty eight\"\". At the bottom left hand side of the certificate Legal documents Business enterprises Membership Newspapers","subject_terms_3":"there is a red embossed seal together with signatures by members of the council.\"","subject_terms_4":"certification","context_1":"Certification","context_2":"Daily newspapers"},"nlpDate":"20201119143405","connectorId":0,"tags":{}}