{
  "id": "2016-00112-005",
  "title": "Appavoo Kandiar kidnapped in a box for thirteen days A set of five newspaper clippings reporting the kidnapping of Mr.Appavoo Kandiar",
  "source": "Bumblebee",
  "path": "./Data/json/",
  "content": "\n  accession_no_csv: 2016-00112-005\n\n  Image: \n\n  object_work_type: clippings (information artifacts)\n\n  title_text: Appavoo Kandiar kidnapped in a box for thirteen days A set of five newspaper clippings reporting the kidnapping of Mr.Appavoo Kandiar\n\n  preference: main alternate\n\n  title_language: \n\n  creator_2: The Straits Times\n\n  creator_1: Straits times\n\n  creator_role: publishers\n\n  creation_date: 19570924\n\n  creation_place_original_location: Singapore\n\n  inscriptions: \n\n  inscription_language: \n\n  shape: rectangular\n\n  materials_name: paper (fiber product)\n\n  techniques_name: printing (process)\n\n  object_colour: black-and-white (colours)\n\n  physical_appearance: \\The image shows a newspaper clipping. Above the headlines at the top right hand side of the article\n \\\\24th September 1957\n\n  subject_terms_1: Straits Times\\\\. Towards the middle of the article crime contractors newspapers\n\n  subject_terms_2: there are three images running from the top to the bottom. A picture of Mr.Appavoo Kandiar\\u0027s face Ransom Contractors Kidnapping victims Millionaires Clippings (Books\n newspapers\n etc.)\n\n  subject_terms_3: followed by a picture of two policemen looking into a box Crime Kandiar\n Appavoo\n\n  subject_terms_4: and a picture of a single-storey house are shown. Each individual picture is accompanied by English text. There are two columns of text\n\n  context_1: one on the extreme left and the other on the extreme right of the article.\\\n\n  context_2: abduction\n\n  context_3: Newspapers\n\n  context_4: Daily newspapers\n",
  "createdDate": "20201120223706",
  "version": 0,
  "latest": false,
  "roles": [],
  "metadata": {
    "accession_no_csv": "2016-00112-005",
    "Image": "",
    "object_work_type": "clippings (information artifacts)",
    "title_text": "Appavoo Kandiar kidnapped in a box for thirteen days A set of five newspaper clippings reporting the kidnapping of Mr.Appavoo Kandiar",
    "preference": "main alternate",
    "title_language": "",
    "creator_2": "The Straits Times",
    "creator_1": "Straits times",
    "creator_role": "publishers",
    "creation_date": "19570924",
    "creation_place_original_location": "Singapore",
    "inscriptions": "",
    "inscription_language": "",
    "shape": "rectangular",
    "materials_name": "paper (fiber product)",
    "techniques_name": "printing (process)",
    "object_colour": "black-and-white (colours)",
    "physical_appearance": "\"The image shows a newspaper clipping. Above the headlines at the top right hand side of the article, \"\"24th September 1957",
    "subject_terms_1": "Straits Times\"\". Towards the middle of the article crime contractors newspapers",
    "subject_terms_2": "there are three images running from the top to the bottom. A picture of Mr.Appavoo Kandiar\u0027s face Ransom Contractors Kidnapping victims Millionaires Clippings (Books, newspapers, etc.)",
    "subject_terms_3": "followed by a picture of two policemen looking into a box Crime Kandiar, Appavoo",
    "subject_terms_4": "and a picture of a single-storey house are shown. Each individual picture is accompanied by English text. There are two columns of text",
    "context_1": "one on the extreme left and the other on the extreme right of the article.\"",
    "context_2": "abduction",
    "context_3": "Newspapers",
    "context_4": "Daily newspapers"
  },
  "nlpDate": "20201120223706",
  "connectorId": 0,
  "tags": {}
}