{"id":"2016-00298","title":"Historical Relics of the Old East India Company","source":"Bumblebee","path":"./Data/json/","content":"accession_no_csv:2016-00298\nImage:\nobject_work_type:prints (visual works)\ntitle_text:Historical Relics of the Old East India Company\npreference:main\ntitle_language:\ncreator_2:Illustrated London News\ncreator_1:Illustrated London news\ncreator_role:publishers\ncreation_date:1890\ncreation_place_original_location:London (England)\ninscriptions:\ninscription_language:\nshape:rectangular\nmaterials_name:paper (fiber product) printing paper\ntechniques_name:colour printing\nobject_colour:multicoloured\nphysical_appearance:This print depicts the historical artefacts relating to the East India Company. Four categories of images take up the entire space of the artwork. Under each set of images\n there are texts that name the images. The print has a wooden frame and there are no visible tears or chips on them. The title of the print is displayed at the bottom\n in capital letters. The colours on the print do not look smudged.\nsubject_terms_1:historic buildings mantels (fireplace components) seals (artifacts) corporate headquarters (built works)\nsubject_terms_2:East India Company Prints Historic buildings Crosby Hall (London\n England) Mantels Corporations\n Headquarters\nsubject_terms_3:East India Company Historic buildings Visual arts\nsgcool_label_text:This print was published in the Illustrated London News on 30 August 1890. It features\n clockwise from top left\n the mantelpiece formerly in the Directors’ court-room of the old East India House\n the old East India House on Leadenhall Street (1648-1726)\n the old Crosby House at Bishopsgate occupied by the East India Company from 1621 to 1638\n the re-faced East India House on Leadenhall Street in 1726\n and obverse and reverse views of the Great Seal of the Commonwealth (1651) appended to a warrant of Oliver Cromwell.","createdDate":"20201018182635","version":0,"latest":false,"roles":[],"metadata":{"accession_no_csv":"2016-00298","Image":"","object_work_type":"prints (visual works)","title_text":"Historical Relics of the Old East India Company","preference":"main","title_language":"","creator_2":"Illustrated London News","creator_1":"Illustrated London news","creator_role":"publishers","creation_date":"1890","creation_place_original_location":"London (England)","inscriptions":"","inscription_language":"","shape":"rectangular","materials_name":"paper (fiber product) printing paper","techniques_name":"colour printing","object_colour":"multicoloured","physical_appearance":"This print depicts the historical artefacts relating to the East India Company. Four categories of images take up the entire space of the artwork. Under each set of images, there are texts that name the images. The print has a wooden frame and there are no visible tears or chips on them. The title of the print is displayed at the bottom, in capital letters. The colours on the print do not look smudged.","subject_terms_1":"historic buildings mantels (fireplace components) seals (artifacts) corporate headquarters (built works)","subject_terms_2":"East India Company Prints Historic buildings Crosby Hall (London, England) Mantels Corporations, Headquarters","subject_terms_3":"East India Company Historic buildings Visual arts","sgcool_label_text":"This print was published in the Illustrated London News on 30 August 1890. It features, clockwise from top left, the mantelpiece formerly in the Directors’ court-room of the old East India House, the old East India House on Leadenhall Street (1648-1726), the old Crosby House at Bishopsgate occupied by the East India Company from 1621 to 1638, the re-faced East India House on Leadenhall Street in 1726, and obverse and reverse views of the Great Seal of the Commonwealth (1651) appended to a warrant of Oliver Cromwell."},"nlpDate":"20201018182635","connectorId":0,"tags":{}}