{"id":"2016-00763","title":"Incense stick holder","source":"Bumblebee","path":"./Data/json/","content":"accession_no_csv:2016-00763\nImage:\nobject_work_type:holders (containers)\ntitle_text:Incense stick holder\npreference:main\ntitle_language:\ncreation_date:1900-1920\ncreation_place_original_location:Singapore\ninscriptions:\ninscription_language:\nshape:irregular\nmaterials_name:wood (plant material)\ntechniques_name:woodcarving\nobject_colour:gray (color) gold (color)\nphysical_appearance:This is a wooden incense stick holder. It is cylindrical in shape\n with a wide circular base. On the body\n there is a carving of a dragon. The dragon is gilded in gold. The gilding is faded especially around the head of the dragon.\nsubject_terms_1:dragons Religious ceremonies ceremonial objects incense sticks Peranakan\nsubject_terms_2:Incense burners and containers Rites and ceremonies Dragons Ceremonial objects Peranakan (Asian people)\nsubject_terms_3:Religious life and practices\nsgcool_label_text:This is a heavy wooden incense stick holder with a dragon carved wrapped around the body of it. The dragon is gilded and the holder is also decorated with a Chinese key fret pattern band running around it.\\r\\n\\r\\nThis item is donated by the family of prominent Peranakan\n Ong Sam Leong (b. 1857\n Singapore – d. 7 February 1918\n Singapore). It comes from his ancestral home of Bukit Rose\n formerly at 259 Bukit Timah Road. Ong was a well-known successful businessman who made is money in the mining of phosphate on Christmas island\n which was historically a territory of colonial Singapore.","createdDate":"20201119143406","version":0,"latest":false,"roles":[],"metadata":{"accession_no_csv":"2016-00763","Image":"","object_work_type":"holders (containers)","title_text":"Incense stick holder","preference":"main","title_language":"","creation_date":"1900-1920","creation_place_original_location":"Singapore","inscriptions":"","inscription_language":"","shape":"irregular","materials_name":"wood (plant material)","techniques_name":"woodcarving","object_colour":"gray (color) gold (color)","physical_appearance":"This is a wooden incense stick holder. It is cylindrical in shape, with a wide circular base. On the body, there is a carving of a dragon. The dragon is gilded in gold. The gilding is faded especially around the head of the dragon.","subject_terms_1":"dragons Religious ceremonies ceremonial objects incense sticks Peranakan","subject_terms_2":"Incense burners and containers Rites and ceremonies Dragons Ceremonial objects Peranakan (Asian people)","subject_terms_3":"Religious life and practices","sgcool_label_text":"This is a heavy wooden incense stick holder with a dragon carved wrapped around the body of it. The dragon is gilded and the holder is also decorated with a Chinese key fret pattern band running around it.\r\n\r\nThis item is donated by the family of prominent Peranakan, Ong Sam Leong (b. 1857, Singapore – d. 7 February 1918, Singapore). It comes from his ancestral home of Bukit Rose, formerly at 259 Bukit Timah Road. Ong was a well-known successful businessman who made is money in the mining of phosphate on Christmas island, which was historically a territory of colonial Singapore."},"nlpDate":"20201119143406","connectorId":0,"tags":{}}