{
  "id": "2016-00083",
  "title": "Invitation letter to MV Gurusamy by Singapore Tamilar Iyakam",
  "source": "Bumblebee",
  "path": "./Data/json/",
  "content": "\n  accession_no_csv: 2016-00083\n\n  Image: \n\n  object_work_type: invitations\n\n  title_text: Invitation letter to MV Gurusamy by Singapore Tamilar Iyakam\n\n  preference: main\n\n  title_language: \n\n  creator_2: Unknown\n\n  creation_date: 19-Sep-81\n\n  creation_place_original_location: Singapore\n\n  styles_periods_indexing_terms: Not indicated\n\n  inscriptions: \n\n  inscription_language: \n\n  scale_type: Not indicated\n\n  shape: rectangular\n\n  materials_name: printing paper\n\n  techniques_name: printing (process)\n\n  object_colour: grey (colour)\n\n  physical_appearance: \\The image shows an invitation letter. It is rectangular in shape and it has a grey background. The entire page is filled with the Tamil script. The signatures at the bottom of the invitiation letter are handwritten in pen. \\\\19-9-81\\\\ is stated at the bottom. \\\n\n  subject_terms_1: associations musicians letters (correspondence)\n\n  subject_terms_2: Invitation cards Musicians Associations\n institutions\n etc. Letters\n\n  subject_terms_3: Musicians Clans and associations Letters\n\n  sgcool_label_text: M.V.Gurusamy (b. 1920 in Seremban) was an accomplished percussionist and mridangam artiste as well as a renowned percussion teacher in Singapore. He arrived in Singapore and participated in the Indian classical music scene here. He was a member of the cultural contingent led by the then Minister for Culture\n S. Rajaratnam\n which visited and performed at various centres in Sarawak\n Brunei and Sabah in 1965. He was the recipient of several titles including the Kala Ratna award given by the Singapore Indian Fine Arts Society in 1986.\n",
  "createdDate": "20201120223706",
  "version": 0,
  "latest": false,
  "roles": [],
  "metadata": {
    "accession_no_csv": "2016-00083",
    "Image": "",
    "object_work_type": "invitations",
    "title_text": "Invitation letter to MV Gurusamy by Singapore Tamilar Iyakam",
    "preference": "main",
    "title_language": "",
    "creator_2": "Unknown",
    "creation_date": "19-Sep-81",
    "creation_place_original_location": "Singapore",
    "styles_periods_indexing_terms": "Not indicated",
    "inscriptions": "",
    "inscription_language": "",
    "scale_type": "Not indicated",
    "shape": "rectangular",
    "materials_name": "printing paper",
    "techniques_name": "printing (process)",
    "object_colour": "grey (colour)",
    "physical_appearance": "\"The image shows an invitation letter. It is rectangular in shape and it has a grey background. The entire page is filled with the Tamil script. The signatures at the bottom of the invitiation letter are handwritten in pen. \"\"19-9-81\"\" is stated at the bottom. \"",
    "subject_terms_1": "associations musicians letters (correspondence)",
    "subject_terms_2": "Invitation cards Musicians Associations, institutions, etc. Letters",
    "subject_terms_3": "Musicians Clans and associations Letters",
    "sgcool_label_text": "M.V.Gurusamy (b. 1920 in Seremban) was an accomplished percussionist and mridangam artiste as well as a renowned percussion teacher in Singapore. He arrived in Singapore and participated in the Indian classical music scene here. He was a member of the cultural contingent led by the then Minister for Culture, S. Rajaratnam, which visited and performed at various centres in Sarawak, Brunei and Sabah in 1965. He was the recipient of several titles including the Kala Ratna award given by the Singapore Indian Fine Arts Society in 1986."
  },
  "nlpDate": "20201120223706",
  "connectorId": 0,
  "tags": {}
}