{"id":"2016-00181","title":"Cheongsam and matching jacket with blue floral motif","source":"Bumblebee","path":"./Data/json/","content":"accession_no_csv:2016-00181\nImage:\nobject_work_type:folk costume jackets (garments)\ntitle_text:Cheongsam and matching jacket with blue floral motif\npreference:main\ntitle_language:\ncreator_2:Peony\ncreator_role:creators\ncreation_date:Not indicated\ncreation_place_original_location:Singapore\nstyles_periods_indexing_terms:Chinese (culture or style)\ninscriptions:\ninscription_language:\nshape:irregular\nmaterials_name:cloth\ntechniques_name:machine sewing (technique)\nobject_colour:multicoloured\nphysical_appearance:\\This is a cheongsam that is paired with a long-sleeved matching jacket. The cheongsam hs short sleeves. There are floral patterns all over the cheongsam and the jacket. A collar is present on the cheongsam and on the jacket. There are three buttons running down the centre of the jacket\\u0027s front. They are circular in shape. There are no visible tears on the cheongsam and the jacket. There is a label tag that is titled\n \\\\Peony\\\\ located at the collar of the jacket.\\\nsubject_terms_1:dresses (garments) womenswear allover patterns floral patterns tailor-made\nsubject_terms_2:Qipao Ethnic costume Jackets Women\\u0027s clothing Motifs Custom-made clothing\nsubject_terms_3:Ethnic costume Chinese costume\ncontext_20:This item was located at a local tailor shop called Peony\ncontext_21:No. 8 Lorong 22 Geylang\n Singapore 398668\ncontext_22:Not indicated\nsgcool_label_text:This cheongsam and its matching jacket were made from fabric purchased from Liberty London. The jacket has a tailor’s label and address. The cheongsam and jacket was tailored at a local tailor\n “Peony”\n at No. 8 Lorong 22 Geylang\n Singapore. Cheongsams with matching jackets were usually worn at more formal occasions.","createdDate":"20201119143405","version":0,"latest":false,"roles":[],"metadata":{"accession_no_csv":"2016-00181","Image":"","object_work_type":"folk costume jackets (garments)","title_text":"Cheongsam and matching jacket with blue floral motif","preference":"main","title_language":"","creator_2":"Peony","creator_role":"creators","creation_date":"Not indicated","creation_place_original_location":"Singapore","styles_periods_indexing_terms":"Chinese (culture or style)","inscriptions":"","inscription_language":"","shape":"irregular","materials_name":"cloth","techniques_name":"machine sewing (technique)","object_colour":"multicoloured","physical_appearance":"\"This is a cheongsam that is paired with a long-sleeved matching jacket. The cheongsam hs short sleeves. There are floral patterns all over the cheongsam and the jacket. A collar is present on the cheongsam and on the jacket. There are three buttons running down the centre of the jacket\u0027s front. They are circular in shape. There are no visible tears on the cheongsam and the jacket. There is a label tag that is titled, \"\"Peony\"\" located at the collar of the jacket.\"","subject_terms_1":"dresses (garments) womenswear allover patterns floral patterns tailor-made","subject_terms_2":"Qipao Ethnic costume Jackets Women\u0027s clothing Motifs Custom-made clothing","subject_terms_3":"Ethnic costume Chinese costume","context_20":"This item was located at a local tailor shop called Peony","context_21":"No. 8 Lorong 22 Geylang, Singapore 398668","context_22":"Not indicated","sgcool_label_text":"This cheongsam and its matching jacket were made from fabric purchased from Liberty London. The jacket has a tailor’s label and address. The cheongsam and jacket was tailored at a local tailor, “Peony”, at No. 8 Lorong 22 Geylang, Singapore. Cheongsams with matching jackets were usually worn at more formal occasions."},"nlpDate":"20201119143405","connectorId":0,"tags":{}}