{
  "id": "2016-00768",
  "title": "Vase with spades",
  "source": "Bumblebee",
  "path": "./Data/json/",
  "content": "\n  accession_no_csv: 2016-00768\n\n  Image: \n\n  object_work_type: vases\n\n  title_text: Vase with spades\n\n  preference: main\n\n  title_language: \n\n  creation_date: 1900-1920\n\n  creation_place_original_location: Singapore\n\n  inscriptions: \n\n  inscription_language: \n\n  shape: irregular\n\n  materials_name: brass (alloy)\n\n  techniques_name: forging (metal forming)\n\n  object_colour: bronze (color)\n\n  physical_appearance: This is a set of brass vase container containing several spades and tongs. The base is a circular and curved\n with four small holes. The body of the vase is engraved with floral designs. The spades and tongs sit inside the vase through the opening at the top.\n\n  subject_terms_1: ceremonial objects Peranakan religious ceremonies flower (motif) altar components\n\n  subject_terms_2: Motifs Rites and ceremonies Peranakan (Asian people) Altars Vases Ceremonial objects\n\n  subject_terms_3: Religious life and practices\n\n  sgcool_label_text: This brass vase contains several spades and tongs. The vase is engraved with flowers and the faces of phoenixes on its side. The spades are used to scoop ashes and incense into censers and burners and the tongs are used to remove old incense buds.\\r\\n\\r\\nThis item is donated by the family of prominent Peranakan\n Ong Sam Leong (b. 1857\n Singapore – d. 7 February 1918\n Singapore). It comes from his ancestral home of Bukit Rose\n formerly at 259 Bukit Timah Road. Ong was a well-known successful businessman who made is money in the mining of phosphate on Christmas island\n which was historically a territory of colonial Singapore. \\r\\n\n",
  "createdDate": "20201201203308",
  "version": 0,
  "latest": false,
  "roles": [],
  "metadata": {
    "accession_no_csv": "2016-00768",
    "Image": "",
    "object_work_type": "vases",
    "title_text": "Vase with spades",
    "preference": "main",
    "title_language": "",
    "creation_date": "1900-1920",
    "creation_place_original_location": "Singapore",
    "inscriptions": "",
    "inscription_language": "",
    "shape": "irregular",
    "materials_name": "brass (alloy)",
    "techniques_name": "forging (metal forming)",
    "object_colour": "bronze (color)",
    "physical_appearance": "This is a set of brass vase container containing several spades and tongs. The base is a circular and curved, with four small holes. The body of the vase is engraved with floral designs. The spades and tongs sit inside the vase through the opening at the top.",
    "subject_terms_1": "ceremonial objects Peranakan religious ceremonies flower (motif) altar components",
    "subject_terms_2": "Motifs Rites and ceremonies Peranakan (Asian people) Altars Vases Ceremonial objects",
    "subject_terms_3": "Religious life and practices",
    "sgcool_label_text": "This brass vase contains several spades and tongs. The vase is engraved with flowers and the faces of phoenixes on its side. The spades are used to scoop ashes and incense into censers and burners and the tongs are used to remove old incense buds.\r\n\r\nThis item is donated by the family of prominent Peranakan, Ong Sam Leong (b. 1857, Singapore – d. 7 February 1918, Singapore). It comes from his ancestral home of Bukit Rose, formerly at 259 Bukit Timah Road. Ong was a well-known successful businessman who made is money in the mining of phosphate on Christmas island, which was historically a territory of colonial Singapore. \r\n"
  },
  "nlpDate": "20201201203308",
  "connectorId": 0,
  "tags": {}
}