{
  "id": "2016-00478",
  "title": "Olivetti Studio 46 typewriter Olivetti Studio 46 typewriter with box cover",
  "source": "Bumblebee",
  "path": "./Data/json/",
  "content": "\n  accession_no_csv: 2016-00478\n\n  Image: \n\n  object_work_type: typewriters\n\n  title_text: Olivetti Studio 46 typewriter Olivetti Studio 46 typewriter with box cover\n\n  preference: main alternate\n\n  title_language: \n\n  creator_2: Olivetti S.p.A.\n\n  creator_role: manufacturers\n\n  creation_date: 1980s\n\n  creation_place_original_location: Spain Singapore\n\n  inscriptions: \n\n  inscription_language: \n\n  shape: irregular\n\n  materials_name: metal plastic (organic material)\n\n  techniques_name: forming (physical activity)\n\n  object_colour: multicoloured\n\n  physical_appearance: \\The image depicts a typewriter. It is being placed in an open box. The brand name of the typewriter\n \\\\Olivetti Studio 46\\\\\n\n  subject_terms_1: is displayed at its front. The typewriter is predominantly blue in colour and its keyboard is black with white keys. Only the tabulator (TAB) key is coloured red. The box that holds the typewriter is black in colour and it comes with a handle. The box has square designs on its exterior. On its top at the interior surface brand name objects\n\n  subject_terms_2: the words \\\\Made in Spain\\\\ are stated.\\ Technology Typewriters\n\n  subject_terms_3: technology (general associated concept)\n\n  subject_terms_4: Brand name products\n",
  "createdDate": "20201125084534",
  "version": 0,
  "latest": false,
  "roles": [],
  "metadata": {
    "accession_no_csv": "2016-00478",
    "Image": "",
    "object_work_type": "typewriters",
    "title_text": "Olivetti Studio 46 typewriter Olivetti Studio 46 typewriter with box cover",
    "preference": "main alternate",
    "title_language": "",
    "creator_2": "Olivetti S.p.A.",
    "creator_role": "manufacturers",
    "creation_date": "1980s",
    "creation_place_original_location": "Spain Singapore",
    "inscriptions": "",
    "inscription_language": "",
    "shape": "irregular",
    "materials_name": "metal plastic (organic material)",
    "techniques_name": "forming (physical activity)",
    "object_colour": "multicoloured",
    "physical_appearance": "\"The image depicts a typewriter. It is being placed in an open box. The brand name of the typewriter, \"\"Olivetti Studio 46\"\"",
    "subject_terms_1": "is displayed at its front. The typewriter is predominantly blue in colour and its keyboard is black with white keys. Only the tabulator (TAB) key is coloured red. The box that holds the typewriter is black in colour and it comes with a handle. The box has square designs on its exterior. On its top at the interior surface brand name objects",
    "subject_terms_2": "the words \"\"Made in Spain\"\" are stated.\" Technology Typewriters",
    "subject_terms_3": "technology (general associated concept)",
    "subject_terms_4": "Brand name products"
  },
  "nlpDate": "20201125084534",
  "connectorId": 0,
  "tags": {}
}