{
  "id": "2016-00304",
  "title": "Het Eyland Sangir/De Talautse Eylanden (The Sangir Island/The Talaud Islands)",
  "source": "Bumblebee",
  "path": "./Data/json/",
  "content": "\n  accession_no_csv: 2016-00304\n\n  Image: \n\n  object_work_type: maps (documents) copper engravings (visual works)\n\n  title_text: Het Eyland Sangir/De Talautse Eylanden (The Sangir Island/The Talaud Islands)\n\n  preference: main\n\n  title_language: \n\n  creator_2: Francois Valentijn\n\n  creator_1: Valentijn\n Francois\n 1666 - 1727\n\n  creator_role: mapmakers\n\n  creation_date: 1726\n\n  creation_place_original_location: Holland (Netherlands : Province)\n\n  inscriptions: \n\n  inscription_language: \n\n  scale_type: 1:05\n\n  shape: rectangular\n\n  materials_name: paper (fiber product) printing paper\n\n  techniques_name: mapmaking (process) colour printing\n\n  object_colour: multicoloured\n\n  physical_appearance: This map depicts the islands of Sangir and Talaud.  Different colours are used on the different islands\n ranging from pink to turquoise to yellow. The map is divided in the middle with vertical line. However\n the same set of scales\n 1: 05\n are being utilized on both parts. Straight black lines that run diagonal\n vertical\n and horizontal extend out from the two compasses that are located in both parts of the map.Pictorial representations of mountains and hills are drawn in many of the islands.\n\n  subject_terms_1: islands (landforms) colonial settlements\n\n  subject_terms_2: Colonization Maps Islands East Indies Sangihe-Talaud (Indonesia) Nederlandsche Oost-Indische Compagnie\n\n  sgcool_label_text: Francois Valentijn (1666–1727) was a minister\n naturalist and writer who served the Dutch V.O.C. in the East Indies in the late 17th and early 18th centuries. His monumental work Oud en Nieuw Oost-Indien (Old and New East-India)\n published between 1724 and 1726\n offers a comprehensive mapping of the East Indies with a large selection of scale maps and views. These charts of the Sangir (left) and Talaud (right) islands in North Sulawesi were published in that work.\n",
  "createdDate": "20201201203309",
  "version": 0,
  "latest": false,
  "roles": [],
  "metadata": {
    "accession_no_csv": "2016-00304",
    "Image": "",
    "object_work_type": "maps (documents) copper engravings (visual works)",
    "title_text": "Het Eyland Sangir/De Talautse Eylanden (The Sangir Island/The Talaud Islands)",
    "preference": "main",
    "title_language": "",
    "creator_2": "Francois Valentijn",
    "creator_1": "Valentijn, Francois, 1666 - 1727",
    "creator_role": "mapmakers",
    "creation_date": "1726",
    "creation_place_original_location": "Holland (Netherlands : Province)",
    "inscriptions": "",
    "inscription_language": "",
    "scale_type": "1:05",
    "shape": "rectangular",
    "materials_name": "paper (fiber product) printing paper",
    "techniques_name": "mapmaking (process) colour printing",
    "object_colour": "multicoloured",
    "physical_appearance": "This map depicts the islands of Sangir and Talaud.  Different colours are used on the different islands, ranging from pink to turquoise to yellow. The map is divided in the middle with vertical line. However, the same set of scales, 1: 05, are being utilized on both parts. Straight black lines that run diagonal, vertical, and horizontal extend out from the two compasses that are located in both parts of the map.Pictorial representations of mountains and hills are drawn in many of the islands.",
    "subject_terms_1": "islands (landforms) colonial settlements",
    "subject_terms_2": "Colonization Maps Islands East Indies Sangihe-Talaud (Indonesia) Nederlandsche Oost-Indische Compagnie",
    "sgcool_label_text": "Francois Valentijn (1666–1727) was a minister, naturalist and writer who served the Dutch V.O.C. in the East Indies in the late 17th and early 18th centuries. His monumental work Oud en Nieuw Oost-Indien (Old and New East-India), published between 1724 and 1726, offers a comprehensive mapping of the East Indies with a large selection of scale maps and views. These charts of the Sangir (left) and Talaud (right) islands in North Sulawesi were published in that work."
  },
  "nlpDate": "20201201203309",
  "connectorId": 0,
  "tags": {}
}