{
  "id": "2016-00711",
  "title": "Embroidered Slippers with Central Floral Motif in Metallic Thread",
  "source": "Bumblebee",
  "path": "./Data/json/",
  "content": "\n  accession_no_csv: 2016-00711\n\n  Image: \n\n  object_work_type: slippers (shoes)\n\n  title_text: Embroidered Slippers with Central Floral Motif in Metallic Thread\n\n  preference: main\n\n  title_language: \n\n  creation_date: early-mid 20th century\n\n  creation_place_original_location: Indonesia Straits Settlements\n\n  styles_periods_indexing_terms: Peranakan\n\n  inscriptions: \n\n  inscription_language: \n\n  shape: irregular\n\n  materials_name: paper (fiber product)\n\n  techniques_name: sewing (needleworking technique)\n\n  object_colour: multicolored\n\n  physical_appearance: This is a pair of square-toe slippers. It is couched with metallic threads to create a floral background. There is also an embroided floral motif in the centre\n surrounded by a bordered pattern.\n\n  subject_terms_1: flowers (motifs) Peranakan embroidery (visual works) footwear\n\n  subject_terms_2: Motifs Embroidery Peranakan (Asian people) Women\\u0027s shoes\n\n  subject_terms_3: Peranakan costumes\n\n  sgcool_label_text: This pair of square-toe slippers is couched with metallic threads to create a floral background. Metallic thread is also used to embroider the raised floral motif in the centre and border patterns. Such shoes were worn in the early 1900s but quickly fell out of favour in the Straits Settlements. It is part of a donation which contains a mixture of garments worn by Peranakan men and women.\n",
  "createdDate": "20201125084531",
  "version": 0,
  "latest": false,
  "roles": [],
  "metadata": {
    "accession_no_csv": "2016-00711",
    "Image": "",
    "object_work_type": "slippers (shoes)",
    "title_text": "Embroidered Slippers with Central Floral Motif in Metallic Thread",
    "preference": "main",
    "title_language": "",
    "creation_date": "early-mid 20th century",
    "creation_place_original_location": "Indonesia Straits Settlements",
    "styles_periods_indexing_terms": "Peranakan",
    "inscriptions": "",
    "inscription_language": "",
    "shape": "irregular",
    "materials_name": "paper (fiber product)",
    "techniques_name": "sewing (needleworking technique)",
    "object_colour": "multicolored",
    "physical_appearance": "This is a pair of square-toe slippers. It is couched with metallic threads to create a floral background. There is also an embroided floral motif in the centre, surrounded by a bordered pattern.",
    "subject_terms_1": "flowers (motifs) Peranakan embroidery (visual works) footwear",
    "subject_terms_2": "Motifs Embroidery Peranakan (Asian people) Women\u0027s shoes",
    "subject_terms_3": "Peranakan costumes",
    "sgcool_label_text": "This pair of square-toe slippers is couched with metallic threads to create a floral background. Metallic thread is also used to embroider the raised floral motif in the centre and border patterns. Such shoes were worn in the early 1900s but quickly fell out of favour in the Straits Settlements. It is part of a donation which contains a mixture of garments worn by Peranakan men and women."
  },
  "nlpDate": "20201125084531",
  "connectorId": 0,
  "tags": {}
}