{
  "id": "2016-00147",
  "title": "Ganpa or Ganjifa Cards in a box A Set of Ganpa or Ganjifa Cards",
  "source": "Bumblebee",
  "path": "./Data/json/",
  "content": "\n  accession_no_csv: 2016-00147\n\n  Image: \n\n  object_work_type: playing cards playing card boxes\n\n  title_text: Ganpa or Ganjifa Cards in a box A Set of Ganpa or Ganjifa Cards\n\n  preference: main alternate\n\n  title_language: \n\n  creation_date: 1800 - 1899\n\n  creation_place_original_location: Odisha (India)\n\n  inscriptions: \n\n  inscription_language: \n\n  shape: circular (shape) rectangular\n\n  materials_name: wood (plant material) paint (coating)\n\n  techniques_name: woodcarving painting (image-making)\n\n  object_colour: multicoloured\n\n  physical_appearance: The image depicts a box with a top cover. The top cover is slightly slanted\n revealing the interior of the box and its contents. A line of circular cards can be discerned inside. The sides of the exterior of the box are painted with different colours in horizontal lines\n along with motifs of scrolls. The top cover is depicts an image of a male figure with long hair and a beard. The figure is standing on one leg\n with the other folded across his knees. His right hand is shown to be holding a shiny circular object.\n\n  subject_terms_1: recreation card games (game sets) entertaining cultural diffusion scrolls (motifs) figures (representations)\n\n  subject_terms_2: Motifs Boxes Culture diffusion Card games Playing cards Amusements\n\n  subject_terms_3: Games\n\n  sgcool_label_text: Ganjifa is pan-Indian\n played in its various forms in Indian regions including Maharashtra\n Rajasthan\n Bengal\n Orissa\n Karnataka\n among others. The ganjifa game of cards originated in Persia but it really flourished in India where the game developed in various forms. Meanwhile\n in Persia\n the game largely died out. Initially in India\n the game was played by the Mughals of northern India\n but it soon spread to most parts of the country. The proposed set underscore a rare aspect of Indian heritage – a craft tradition akin to miniature painting and a lesser known Indian game.\n",
  "createdDate": "20201125084539",
  "version": 0,
  "latest": false,
  "roles": [],
  "metadata": {
    "accession_no_csv": "2016-00147",
    "Image": "",
    "object_work_type": "playing cards playing card boxes",
    "title_text": "Ganpa or Ganjifa Cards in a box A Set of Ganpa or Ganjifa Cards",
    "preference": "main alternate",
    "title_language": "",
    "creation_date": "1800 - 1899",
    "creation_place_original_location": "Odisha (India)",
    "inscriptions": "",
    "inscription_language": "",
    "shape": "circular (shape) rectangular",
    "materials_name": "wood (plant material) paint (coating)",
    "techniques_name": "woodcarving painting (image-making)",
    "object_colour": "multicoloured",
    "physical_appearance": "The image depicts a box with a top cover. The top cover is slightly slanted, revealing the interior of the box and its contents. A line of circular cards can be discerned inside. The sides of the exterior of the box are painted with different colours in horizontal lines, along with motifs of scrolls. The top cover is depicts an image of a male figure with long hair and a beard. The figure is standing on one leg, with the other folded across his knees. His right hand is shown to be holding a shiny circular object.",
    "subject_terms_1": "recreation card games (game sets) entertaining cultural diffusion scrolls (motifs) figures (representations)",
    "subject_terms_2": "Motifs Boxes Culture diffusion Card games Playing cards Amusements",
    "subject_terms_3": "Games",
    "sgcool_label_text": "Ganjifa is pan-Indian, played in its various forms in Indian regions including Maharashtra, Rajasthan, Bengal, Orissa, Karnataka, among others. The ganjifa game of cards originated in Persia but it really flourished in India where the game developed in various forms. Meanwhile, in Persia, the game largely died out. Initially in India, the game was played by the Mughals of northern India, but it soon spread to most parts of the country. The proposed set underscore a rare aspect of Indian heritage – a craft tradition akin to miniature painting and a lesser known Indian game."
  },
  "nlpDate": "20201125084539",
  "connectorId": 0,
  "tags": {}
}