{
  "id": "2016-00030",
  "title": "Ewer Brass ewer",
  "source": "Bumblebee",
  "path": "./Data/json/",
  "content": "\n  accession_no_csv: 2016-00030\n\n  Image: \n\n  object_work_type: ablution ewers\n\n  title_text: Ewer Brass ewer\n\n  preference: main alternate\n\n  title_language: \n\n  creation_date: 17th or early 18th century\n\n  creation_place_original_location: Deccan (India)\n\n  inscriptions: \n\n  inscription_language: \n\n  shape: irregular\n\n  materials_name: brass (alloy)\n\n  techniques_name: welding\n\n  object_colour: bronze\n\n  physical_appearance: This is a brass ewer. It has a pear-shaped body with flat sides. It has a slender handle on the left\n and an S-shaped spout on the right. There is a hinged lid\n and a circular\n flaring base. The body of the ewer is engraved with scrolling arabesque motifs.\n\n  subject_terms_1: palmette (motif) ablutions Islamic (culture or style) ewers (vessels) scrolls (motifs)\n\n  subject_terms_2: Motifs Ablutions (Islamic law) Islam Ewers\n\n  subject_terms_3: Heritage and Culture\n\n  sgcool_label_text: Because the Quran states that “we made everything alive from water” (surah 21:30)\n ewers carry great significance. Usually paired with a matching basin\n ewers are used by Muslims to wash their hands before prayer and many other acitivities. Because of their durability\n brass and bronze were commonly used to make ewers and other vessels to hold liquids.\n",
  "createdDate": "20201201203309",
  "version": 0,
  "latest": false,
  "roles": [],
  "metadata": {
    "accession_no_csv": "2016-00030",
    "Image": "",
    "object_work_type": "ablution ewers",
    "title_text": "Ewer Brass ewer",
    "preference": "main alternate",
    "title_language": "",
    "creation_date": "17th or early 18th century",
    "creation_place_original_location": "Deccan (India)",
    "inscriptions": "",
    "inscription_language": "",
    "shape": "irregular",
    "materials_name": "brass (alloy)",
    "techniques_name": "welding",
    "object_colour": "bronze",
    "physical_appearance": "This is a brass ewer. It has a pear-shaped body with flat sides. It has a slender handle on the left, and an S-shaped spout on the right. There is a hinged lid, and a circular, flaring base. The body of the ewer is engraved with scrolling arabesque motifs.",
    "subject_terms_1": "palmette (motif) ablutions Islamic (culture or style) ewers (vessels) scrolls (motifs)",
    "subject_terms_2": "Motifs Ablutions (Islamic law) Islam Ewers",
    "subject_terms_3": "Heritage and Culture",
    "sgcool_label_text": "Because the Quran states that “we made everything alive from water” (surah 21:30), ewers carry great significance. Usually paired with a matching basin, ewers are used by Muslims to wash their hands before prayer and many other acitivities. Because of their durability, brass and bronze were commonly used to make ewers and other vessels to hold liquids."
  },
  "nlpDate": "20201201203309",
  "connectorId": 0,
  "tags": {}
}