{"id":"2016-00414","title":"Pink dress with purl fringe","source":"Bumblebee","path":"./Data/json/","content":"accession_no_csv:2016-00414\nImage:\nobject_work_type:dresses (garments) womenswear\ntitle_text:Pink dress with purl fringe\npreference:main\ntitle_language:\ncreation_date:1920s-1930s\ncreation_place_original_location:Indonesia\nstyles_periods_indexing_terms:Western European\ninscriptions:\ninscription_language:\nshape:irregular\nmaterials_name:cloth fringe\ntechniques_name:sewing (needleworking technique)\nobject_colour:pink (color)\nphysical_appearance:This pink dress has a scoop neckline\n decorated waistline\n and a scallop hem at the bottom. Its sleeves and front skirt is decorated with a bronze fringe. It is also decorated with bangle beads across the skirt\n along the neckline\n and along the sleeves. On the front of the dress\n there are beads sewn to form the shape of winged creatures.\nsubject_terms_1:motifs Peranakan fashion (concept) beadwork (visual works) cultural diffusion\nsubject_terms_2:Dresses Motifs Peranakan (Asian people) Fashion Culture diffusion\nsubject_terms_3:\nsgcool_label_text:The pink dress is lavishly beaded along its scoop neckline\n high waistline and scalloped hem. Purl fringe hangs from the sleeves as well as from the fabric that is draped asymmetrically across the body. Bugle beads embellish buttons and form a pair of winged creatures on the front of the dress.  By the early 20th century\n Peranakan women were wearing European dress although many continued to wear the sarong kebaya and Chinese dress. The decoration of this garment may have been influenced by 1920s fashion in Europe and the United States of America which saw the popularity of heavy embellishment on tubular silhouettes.","createdDate":"20201018182635","version":0,"latest":false,"roles":[],"metadata":{"accession_no_csv":"2016-00414","Image":"","object_work_type":"dresses (garments) womenswear","title_text":"Pink dress with purl fringe","preference":"main","title_language":"","creation_date":"1920s-1930s","creation_place_original_location":"Indonesia","styles_periods_indexing_terms":"Western European","inscriptions":"","inscription_language":"","shape":"irregular","materials_name":"cloth fringe","techniques_name":"sewing (needleworking technique)","object_colour":"pink (color)","physical_appearance":"This pink dress has a scoop neckline, decorated waistline, and a scallop hem at the bottom. Its sleeves and front skirt is decorated with a bronze fringe. It is also decorated with bangle beads across the skirt, along the neckline, and along the sleeves. On the front of the dress, there are beads sewn to form the shape of winged creatures.","subject_terms_1":"motifs Peranakan fashion (concept) beadwork (visual works) cultural diffusion","subject_terms_2":"Dresses Motifs Peranakan (Asian people) Fashion Culture diffusion","subject_terms_3":"","sgcool_label_text":"The pink dress is lavishly beaded along its scoop neckline, high waistline and scalloped hem. Purl fringe hangs from the sleeves as well as from the fabric that is draped asymmetrically across the body. Bugle beads embellish buttons and form a pair of winged creatures on the front of the dress.  By the early 20th century, Peranakan women were wearing European dress although many continued to wear the sarong kebaya and Chinese dress. The decoration of this garment may have been influenced by 1920s fashion in Europe and the United States of America which saw the popularity of heavy embellishment on tubular silhouettes."},"nlpDate":"20201018182635","connectorId":0,"tags":{}}