{"id":"2016-00212-055","title":"Photograph album of views and portraits in the Punjab, Cashmere, Ceylon, Burma, Penang, Singapore, and Java The Waterfall, Penang","source":"Bumblebee","path":"./Data/json/","content":"accession_no_csv:2016-00212-055\nImage:\nobject_work_type:black-and-white photographs\ntitle_text:Photograph album of views and portraits in the Punjab\n Cashmere\n Ceylon\n Burma\n Penang\n Singapore\n and Java The Waterfall\n Penang\npreference:alternate main\ntitle_language:\ncreator_2:John Thomson\ncreator_1:Thomson\n J. (John)\n 1837-1921\ncreator_role:photographers\ncreation_date:before 28 Jul 1876\ncreation_place_original_location:Singapore Pulau Pinang (Malaysia : State)\ninscriptions:\ninscription_language:\nshape:rectangular\nmaterials_name:albumen (egg white protein) albumen paper paper (fiber product)\ntechniques_name:albumen process\nobject_colour:black-and-white (colors)\nphysical_appearance:This is a photograph of a waterfall in Penang\n Malaysia. The waterfall is in the center of the photograph\n amidst thick vegetation on either side. At the bottom left of the photograph\n there is a small sheltered dwelling. A man is standing by the railings in front of the dwelling. To his right\n there are three men sitting along the bridge at the bottom of the waterfall. There is another man sitting on a rock on the right of the photograph. The title is written at the bottom\n below the photograph.\nsubject_terms_1:scenery (landscape) waterfalls (natural bodies of water)\nsubject_terms_2:Photographs Thomson\n J. (John)\n 1837-1921 Waterfalls Pulau Pinang (Malaysia : State)\nsubject_terms_3:Landscape photography","createdDate":"20201119143405","version":0,"latest":false,"roles":[],"metadata":{"accession_no_csv":"2016-00212-055","Image":"","object_work_type":"black-and-white photographs","title_text":"Photograph album of views and portraits in the Punjab, Cashmere, Ceylon, Burma, Penang, Singapore, and Java The Waterfall, Penang","preference":"alternate main","title_language":"","creator_2":"John Thomson","creator_1":"Thomson, J. (John), 1837-1921","creator_role":"photographers","creation_date":"before 28 Jul 1876","creation_place_original_location":"Singapore Pulau Pinang (Malaysia : State)","inscriptions":"","inscription_language":"","shape":"rectangular","materials_name":"albumen (egg white protein) albumen paper paper (fiber product)","techniques_name":"albumen process","object_colour":"black-and-white (colors)","physical_appearance":"This is a photograph of a waterfall in Penang, Malaysia. The waterfall is in the center of the photograph, amidst thick vegetation on either side. At the bottom left of the photograph, there is a small sheltered dwelling. A man is standing by the railings in front of the dwelling. To his right, there are three men sitting along the bridge at the bottom of the waterfall. There is another man sitting on a rock on the right of the photograph. The title is written at the bottom, below the photograph.","subject_terms_1":"scenery (landscape) waterfalls (natural bodies of water)","subject_terms_2":"Photographs Thomson, J. (John), 1837-1921 Waterfalls Pulau Pinang (Malaysia : State)","subject_terms_3":"Landscape photography"},"nlpDate":"20201119143405","connectorId":0,"tags":{}}