{
  "id": "2016-00101",
  "title": "Mr. S Appavoo Namecard of S Appavoo",
  "source": "Bumblebee",
  "path": "./Data/json/",
  "content": "\n  accession_no_csv: 2016-00101\n\n  Image: \n\n  object_work_type: business cards\n\n  title_text: Mr. S Appavoo Namecard of S Appavoo\n\n  preference: main alternate\n\n  title_language: \n\n  creation_date: 20th century\n\n  creation_place_original_location: Singapore\n\n  inscriptions: \n\n  inscription_language: \n\n  shape: rectangular\n\n  materials_name: paper (fiber product)\n\n  techniques_name: printing (process)\n\n  object_colour: black-and-white (colours)\n\n  physical_appearance: \\The image shows a rectangular card which has words and numbers printed in black ink. The card is grey in colour. At the top right hand corner\n \\\\Tel. 34583\\\\ is stated. At the middle\n\n  subject_terms_1: \\\\S. Appavoo general contractors proprietors companies\n\n  subject_terms_2: General Contractor Street addresses Contractors Business enterprises\n\n  subject_terms_3: No. 79 Bukit Timah Road Businesspeople Kandiar\n Appavoo\n\n  subject_terms_4: Singapore-9\\\\ is displayed. At the bottom left hand side\n\n  context_1: \\\\Managing Proprietor: A. Narayanasamy\\\\ is displayed. \\\n\n  context_2: street addresses\n\n  context_3: Business cards\n\n  context_4: Business enterprises\n",
  "createdDate": "20201120223706",
  "version": 0,
  "latest": false,
  "roles": [],
  "metadata": {
    "accession_no_csv": "2016-00101",
    "Image": "",
    "object_work_type": "business cards",
    "title_text": "Mr. S Appavoo Namecard of S Appavoo",
    "preference": "main alternate",
    "title_language": "",
    "creation_date": "20th century",
    "creation_place_original_location": "Singapore",
    "inscriptions": "",
    "inscription_language": "",
    "shape": "rectangular",
    "materials_name": "paper (fiber product)",
    "techniques_name": "printing (process)",
    "object_colour": "black-and-white (colours)",
    "physical_appearance": "\"The image shows a rectangular card which has words and numbers printed in black ink. The card is grey in colour. At the top right hand corner, \"\"Tel. 34583\"\" is stated. At the middle",
    "subject_terms_1": "\"\"S. Appavoo general contractors proprietors companies",
    "subject_terms_2": "General Contractor Street addresses Contractors Business enterprises",
    "subject_terms_3": "No. 79 Bukit Timah Road Businesspeople Kandiar, Appavoo",
    "subject_terms_4": "Singapore-9\"\" is displayed. At the bottom left hand side",
    "context_1": "\"\"Managing Proprietor: A. Narayanasamy\"\" is displayed. \"",
    "context_2": "street addresses",
    "context_3": "Business cards",
    "context_4": "Business enterprises"
  },
  "nlpDate": "20201120223706",
  "connectorId": 0,
  "tags": {}
}