{
  "id": "2016-00212-080",
  "title": "Durian, Java Photograph album of views and portraits in the Punjab, Cashmere, Ceylon, Burma, Penang, Singapore, and Java",
  "source": "Bumblebee",
  "path": "./Data/json/",
  "content": "\n  accession_no_csv: 2016-00212-080\n\n  Image: \n\n  object_work_type: black-and-white photographs\n\n  title_text: Durian\n Java Photograph album of views and portraits in the Punjab\n Cashmere\n Ceylon\n Burma\n Penang\n Singapore\n and Java\n\n  preference: main alternate\n\n  title_language: \n\n  creator_2: John Thomson\n\n  creator_1: Thomson\n J. (John)\n 1837-1921\n\n  creator_role: photographers\n\n  creation_date: before 28 Jul 1876\n\n  creation_place_original_location: Java (Indonesia) Singapore\n\n  inscriptions: \n\n  inscription_language: \n\n  shape: rectangular\n\n  materials_name: albumen (egg white protein) paper (fiber product) albumen paper\n\n  techniques_name: albumen process\n\n  object_colour: black-and-white (colors)\n\n  physical_appearance: This is a photograph of a durian fruit on a small branch. The durian is in the center of the photograph\n still attached to its narrow branch\n with a few branches of leaves around it. The edges of the photograph are curved. The title is written at the bottom\n below the photograph.\n\n  subject_terms_1: fruit (plant components)\n\n  subject_terms_2: Durian Photographs Thomson\n J. (John)\n 1837-1921\n\n  subject_terms_3: Plants Photography\n",
  "createdDate": "20201125084536",
  "version": 0,
  "latest": false,
  "roles": [],
  "metadata": {
    "accession_no_csv": "2016-00212-080",
    "Image": "",
    "object_work_type": "black-and-white photographs",
    "title_text": "Durian, Java Photograph album of views and portraits in the Punjab, Cashmere, Ceylon, Burma, Penang, Singapore, and Java",
    "preference": "main alternate",
    "title_language": "",
    "creator_2": "John Thomson",
    "creator_1": "Thomson, J. (John), 1837-1921",
    "creator_role": "photographers",
    "creation_date": "before 28 Jul 1876",
    "creation_place_original_location": "Java (Indonesia) Singapore",
    "inscriptions": "",
    "inscription_language": "",
    "shape": "rectangular",
    "materials_name": "albumen (egg white protein) paper (fiber product) albumen paper",
    "techniques_name": "albumen process",
    "object_colour": "black-and-white (colors)",
    "physical_appearance": "This is a photograph of a durian fruit on a small branch. The durian is in the center of the photograph, still attached to its narrow branch, with a few branches of leaves around it. The edges of the photograph are curved. The title is written at the bottom, below the photograph.",
    "subject_terms_1": "fruit (plant components)",
    "subject_terms_2": "Durian Photographs Thomson, J. (John), 1837-1921",
    "subject_terms_3": "Plants Photography"
  },
  "nlpDate": "20201125084536",
  "connectorId": 0,
  "tags": {}
}