{
  "id": "2016-00486",
  "title": "Untitled (locomotive no. 6423)",
  "source": "Bumblebee",
  "path": "./Data/json/",
  "content": "\n  accession_no_csv: 2016-00486\n\n  Image: \n\n  object_work_type: black-and-white photographs\n\n  title_text: Untitled (locomotive no. 6423)\n\n  preference: main\n\n  title_language: \n\n  creator_2: Kwek Leng Joo\n\n  creator_1: Kwek\n Leng Joo\n\n  creator_role: photographers\n\n  creation_date: 2010\n\n  creation_place_original_location: Malaysia Singapore\n\n  inscriptions: \n\n  inscription_language: \n\n  shape: rectangular\n\n  materials_name: paper (fiber product)\n\n  techniques_name: printing (process)\n\n  object_colour: grey monochrome\n\n  physical_appearance: \\The image shows a photograph in black-and-white. It does not have a frame and its sides are whitened out. A man in uniforms can be seen on the right hand side of the image. He is using a long metal tool and is bending to the left and applying some force to it. A large portion of the photograph is taken up by the head of a locomotive. It is stationed at a railway turntable. The number \\\\6423\\\\ is displayed at the front of the locomotive\n\n  subject_terms_1: railroads (infrastructure) blue collar workers turntables (rail transportation structure) slightly above the middle point of the photograph. The initials of the Malaysia rail operator trains (vehicle groupings)\n\n  subject_terms_2: Railroads Locomotives Pertadbiran Keretapi Tanah Melayu Railroad trains Tanjong Pagar (Singapore) Blue collar workers Turntables (Railroads) \\\\KTM\\\\\n\n  subject_terms_3: Photography Pertadbiran Keretapi Tanah Melayu is displayed on top of the front door of the locomotive as well.\\\n\n  subject_terms_4: locomotives\n\n  context_1: Black-and-white photography\n\n  context_2: Rail transport\n",
  "createdDate": "20201125084534",
  "version": 0,
  "latest": false,
  "roles": [],
  "metadata": {
    "accession_no_csv": "2016-00486",
    "Image": "",
    "object_work_type": "black-and-white photographs",
    "title_text": "Untitled (locomotive no. 6423)",
    "preference": "main",
    "title_language": "",
    "creator_2": "Kwek Leng Joo",
    "creator_1": "Kwek, Leng Joo",
    "creator_role": "photographers",
    "creation_date": "2010",
    "creation_place_original_location": "Malaysia Singapore",
    "inscriptions": "",
    "inscription_language": "",
    "shape": "rectangular",
    "materials_name": "paper (fiber product)",
    "techniques_name": "printing (process)",
    "object_colour": "grey monochrome",
    "physical_appearance": "\"The image shows a photograph in black-and-white. It does not have a frame and its sides are whitened out. A man in uniforms can be seen on the right hand side of the image. He is using a long metal tool and is bending to the left and applying some force to it. A large portion of the photograph is taken up by the head of a locomotive. It is stationed at a railway turntable. The number \"\"6423\"\" is displayed at the front of the locomotive",
    "subject_terms_1": "railroads (infrastructure) blue collar workers turntables (rail transportation structure) slightly above the middle point of the photograph. The initials of the Malaysia rail operator trains (vehicle groupings)",
    "subject_terms_2": "Railroads Locomotives Pertadbiran Keretapi Tanah Melayu Railroad trains Tanjong Pagar (Singapore) Blue collar workers Turntables (Railroads) \"\"KTM\"\"",
    "subject_terms_3": "Photography Pertadbiran Keretapi Tanah Melayu is displayed on top of the front door of the locomotive as well.\"",
    "subject_terms_4": "locomotives",
    "context_1": "Black-and-white photography",
    "context_2": "Rail transport"
  },
  "nlpDate": "20201125084534",
  "connectorId": 0,
  "tags": {}
}