{
  "id": "2016-00182",
  "title": "Brown samfoo",
  "source": "Bumblebee",
  "path": "./Data/json/",
  "content": "\n  accession_no_csv: 2016-00182\n\n  Image: \n\n  object_work_type: folk costume\n\n  title_text: Brown samfoo\n\n  preference: main\n\n  title_language: \n\n  creation_date: Not indicated\n\n  creation_place_original_location: Singapore\n\n  styles_periods_indexing_terms: Chinese (culture or style)\n\n  inscriptions: \n\n  inscription_language: \n\n  shape: irregular\n\n  materials_name: cloth\n\n  techniques_name: machine sewing (technique)\n\n  object_colour: brown (colour)\n\n  physical_appearance: This is a brown samfoo with long sleeves and long pants. A mandarin collar is present as well. This samfoo contains orange piping at its collar and its side fastenings. The edges of the cuffs contain white piping. There are three buttons above the piping which ends just below the point where the left sleeve begins. There are no visible tears on the samfoo. There are vertical crease lines present on both the shirt and pants.\n\n  subject_terms_1: unisex clothing\n\n  subject_terms_2: Ethnic costume\n\n  subject_terms_3: Ethnic costume Chinese costume\n\n  sgcool_label_text: The samfoo is a traditional Chinese outfit which consists of a top (‘sam’) with side fastenings and a mandarin collar\n worn over a pair of pants (‘foo’). Traditionally\n the samfoo is loose fitting and its cut makes it convenient for the wearer to carry out everyday activities.\n",
  "createdDate": "20201201203309",
  "version": 0,
  "latest": false,
  "roles": [],
  "metadata": {
    "accession_no_csv": "2016-00182",
    "Image": "",
    "object_work_type": "folk costume",
    "title_text": "Brown samfoo",
    "preference": "main",
    "title_language": "",
    "creation_date": "Not indicated",
    "creation_place_original_location": "Singapore",
    "styles_periods_indexing_terms": "Chinese (culture or style)",
    "inscriptions": "",
    "inscription_language": "",
    "shape": "irregular",
    "materials_name": "cloth",
    "techniques_name": "machine sewing (technique)",
    "object_colour": "brown (colour)",
    "physical_appearance": "This is a brown samfoo with long sleeves and long pants. A mandarin collar is present as well. This samfoo contains orange piping at its collar and its side fastenings. The edges of the cuffs contain white piping. There are three buttons above the piping which ends just below the point where the left sleeve begins. There are no visible tears on the samfoo. There are vertical crease lines present on both the shirt and pants.",
    "subject_terms_1": "unisex clothing",
    "subject_terms_2": "Ethnic costume",
    "subject_terms_3": "Ethnic costume Chinese costume",
    "sgcool_label_text": "The samfoo is a traditional Chinese outfit which consists of a top (‘sam’) with side fastenings and a mandarin collar, worn over a pair of pants (‘foo’). Traditionally, the samfoo is loose fitting and its cut makes it convenient for the wearer to carry out everyday activities."
  },
  "nlpDate": "20201201203309",
  "connectorId": 0,
  "tags": {}
}