{"id":"2016-00712","title":"Beaded Slippers with Peacock Motif","source":"Bumblebee","path":"./Data/json/","content":"accession_no_csv:2016-00712\nImage:\nobject_work_type:slippers (shoes)\ntitle_text:Beaded Slippers with Peacock Motif\npreference:main\ntitle_language:\ncreation_date:early-mid 20th century\ncreation_place_original_location:Straits Settlements\nstyles_periods_indexing_terms:Peranakan\ninscriptions:\ninscription_language:\nshape:irregular\nmaterials_name:beads (pierced objects)\ntechniques_name:sewing (needleworking technique)\nobject_colour:multicolored\nphysical_appearance:This is a pair of beaded slippers. The face of the slippers in the front features a peacock\n standing upon a branch with flowers in full bloom. The slippers have a low heel.\nsubject_terms_1:Peranakan birds (motifs) flowers (motifs) embroidery (visual works) footwear\nsubject_terms_2:Women\\u0027s shoes Peranakan (Asian people) Motifs Embroidery\nsubject_terms_3:Peranakan costumes\nsgcool_label_text:The beaded face of this kasot manek depicts a peacock standing upon a branch with flowers in full bloom. A printed mark ‘122…Beaded Slip…’ is visible on the insole. The heel is low. The popularity of the kasot manek was firmly established by the 1920s. It is part of a donation which contains a mixture of garments worn by Peranakan men and women.","createdDate":"20201018182635","version":0,"latest":false,"roles":[],"metadata":{"accession_no_csv":"2016-00712","Image":"","object_work_type":"slippers (shoes)","title_text":"Beaded Slippers with Peacock Motif","preference":"main","title_language":"","creation_date":"early-mid 20th century","creation_place_original_location":"Straits Settlements","styles_periods_indexing_terms":"Peranakan","inscriptions":"","inscription_language":"","shape":"irregular","materials_name":"beads (pierced objects)","techniques_name":"sewing (needleworking technique)","object_colour":"multicolored","physical_appearance":"This is a pair of beaded slippers. The face of the slippers in the front features a peacock, standing upon a branch with flowers in full bloom. The slippers have a low heel.","subject_terms_1":"Peranakan birds (motifs) flowers (motifs) embroidery (visual works) footwear","subject_terms_2":"Women\u0027s shoes Peranakan (Asian people) Motifs Embroidery","subject_terms_3":"Peranakan costumes","sgcool_label_text":"The beaded face of this kasot manek depicts a peacock standing upon a branch with flowers in full bloom. A printed mark ‘122…Beaded Slip…’ is visible on the insole. The heel is low. The popularity of the kasot manek was firmly established by the 1920s. It is part of a donation which contains a mixture of garments worn by Peranakan men and women."},"nlpDate":"20201018182635","connectorId":0,"tags":{}}