{"id":"2016-00707","title":"White Floral Kebaya","source":"Bumblebee","path":"./Data/json/","content":"accession_no_csv:2016-00707\nImage:\nobject_work_type:kebayas womenswear\ntitle_text:White Floral Kebaya\npreference:main\ntitle_language:\ncreation_date:early-mid 20th century\ncreation_place_original_location:Java (Indonesia)\nstyles_periods_indexing_terms:Peranakan\ninscriptions:\ninscription_language:\nshape:irregular\nmaterials_name:cotton (textile)\ntechniques_name:sewing (needleworking technique)\nobject_colour:white (color)\nphysical_appearance:This is a white kebaya. The weaved fabric features a three-lobe floral motif. The edges are decorated with a floral border of bobbin-lace. The sleeves and bottom of the kebaya is elongated and tapered.\nsubject_terms_1:flowers (motifs) Peranakan folk costume bobbin lace tops (garments\n general) blouses (main garments)\nsubject_terms_2:Motifs Peranakan (Asian people) Ethnic costume Bobbin lace Blouses\nsubject_terms_3:Peranakan costumes\nsgcool_label_text:This white kebaya is made from open-weaved cotton fabric with three-lobe floral motif. A floral border of bobbin-lace decorates the edges and tapers to a point. Kebayas with elongated tapered ends were popular in the 1930s and many were commissioned by Peranakan women. Its label reads ‘Na Sin Sie\n Cheribon’. It is part of a donation which contains a mixture of garments worn by Peranakan men and women.","createdDate":"20201119143405","version":0,"latest":false,"roles":[],"metadata":{"accession_no_csv":"2016-00707","Image":"","object_work_type":"kebayas womenswear","title_text":"White Floral Kebaya","preference":"main","title_language":"","creation_date":"early-mid 20th century","creation_place_original_location":"Java (Indonesia)","styles_periods_indexing_terms":"Peranakan","inscriptions":"","inscription_language":"","shape":"irregular","materials_name":"cotton (textile)","techniques_name":"sewing (needleworking technique)","object_colour":"white (color)","physical_appearance":"This is a white kebaya. The weaved fabric features a three-lobe floral motif. The edges are decorated with a floral border of bobbin-lace. The sleeves and bottom of the kebaya is elongated and tapered.","subject_terms_1":"flowers (motifs) Peranakan folk costume bobbin lace tops (garments, general) blouses (main garments)","subject_terms_2":"Motifs Peranakan (Asian people) Ethnic costume Bobbin lace Blouses","subject_terms_3":"Peranakan costumes","sgcool_label_text":"This white kebaya is made from open-weaved cotton fabric with three-lobe floral motif. A floral border of bobbin-lace decorates the edges and tapers to a point. Kebayas with elongated tapered ends were popular in the 1930s and many were commissioned by Peranakan women. Its label reads ‘Na Sin Sie, Cheribon’. It is part of a donation which contains a mixture of garments worn by Peranakan men and women."},"nlpDate":"20201119143405","connectorId":0,"tags":{}}