{
  "id": "2016-00715",
  "title": "Chiu Thau Garment for Men",
  "source": "Bumblebee",
  "path": "./Data/json/",
  "content": "\n  accession_no_csv: 2016-00715\n\n  Image: \n\n  object_work_type: menswear folk costume\n\n  title_text: Chiu Thau Garment for Men\n\n  preference: main\n\n  title_language: \n\n  creation_date: late 19th-20th century\n\n  creation_place_original_location: Straits Settlements\n\n  styles_periods_indexing_terms: Peranakan\n\n  inscriptions: \n\n  inscription_language: \n\n  shape: irregular\n\n  materials_name: silk (textile)\n\n  techniques_name: sewing (needleworking technique)\n\n  object_colour: white (color)\n\n  physical_appearance: This is a white silk garment. It has a mandarin collar and frog buttons. It is long-sleeved. There are no patterns or embroidery seen.\n\n  subject_terms_1: cultural ceremonies tops (garments\n general) Peranakan wedding clothes\n\n  subject_terms_2: Rites and ceremonies Ethnic costume Peranakan (Asian people) Wedding costume\n\n  subject_terms_3: Peranakan costumes\n\n  sgcool_label_text: This silk Chiu Thau has a mandarin collar and frog buttons. It would have been worn by the groom during the hair combing ceremony\n which takes place on the first day of the twelve-day wedding celebrations. It is part of a donation which contains a mixture of garments worn by Peranakan men and women.\n",
  "createdDate": "20201201203308",
  "version": 0,
  "latest": false,
  "roles": [],
  "metadata": {
    "accession_no_csv": "2016-00715",
    "Image": "",
    "object_work_type": "menswear folk costume",
    "title_text": "Chiu Thau Garment for Men",
    "preference": "main",
    "title_language": "",
    "creation_date": "late 19th-20th century",
    "creation_place_original_location": "Straits Settlements",
    "styles_periods_indexing_terms": "Peranakan",
    "inscriptions": "",
    "inscription_language": "",
    "shape": "irregular",
    "materials_name": "silk (textile)",
    "techniques_name": "sewing (needleworking technique)",
    "object_colour": "white (color)",
    "physical_appearance": "This is a white silk garment. It has a mandarin collar and frog buttons. It is long-sleeved. There are no patterns or embroidery seen.",
    "subject_terms_1": "cultural ceremonies tops (garments, general) Peranakan wedding clothes",
    "subject_terms_2": "Rites and ceremonies Ethnic costume Peranakan (Asian people) Wedding costume",
    "subject_terms_3": "Peranakan costumes",
    "sgcool_label_text": "This silk Chiu Thau has a mandarin collar and frog buttons. It would have been worn by the groom during the hair combing ceremony, which takes place on the first day of the twelve-day wedding celebrations. It is part of a donation which contains a mixture of garments worn by Peranakan men and women."
  },
  "nlpDate": "20201201203308",
  "connectorId": 0,
  "tags": {}
}