{
  "id": "2016-00568-004",
  "title": "Photograph of three patrons to Tiger Balm Gardens\r\n Bottle of Tiger Oil with packaging box and photograph of three patrons to Tiger Balm Gardens Photograph of three patrons to Tiger Balm Gardens\r\n Bottle of Tiger Oil with packaging box and photograph of three patrons to Tiger Balm Gardens",
  "source": "Bumblebee",
  "path": "./Data/json/",
  "content": "\n  accession_no_csv: 2016-00568-004\n\n  Image: \n\n  object_work_type: black-and-white photographs photographs black-and-white photographs photographs\n\n  title_text: Photograph of three patrons to Tiger Balm Gardens\\r\\n Bottle of Tiger Oil with packaging box and photograph of three patrons to Tiger Balm Gardens Photograph of three patrons to Tiger Balm Gardens\\r\\n Bottle of Tiger Oil with packaging box and photograph of three patrons to Tiger Balm Gardens\n\n  preference: main alternate main alternate\n\n  title_language: \n\n  creator_2: Not indicated Not indicated\n\n  creator_1: Not indicated Not indicated\n\n  creator_role: NA NA\n\n  creation_date: 1960-1975 Mid 1960s to Early 1970s\n\n  creation_place_original_location: Singapore Singapore\n\n  styles_periods_indexing_terms: NA NA\n\n  inscriptions: \n\n  inscription_language: \n\n  scale_type: NA NA\n\n  shape: rectangular rectangular\n\n  materials_name: paper (fiber product) paper (fiber product)\n\n  techniques_name: printing (process) photographic processes printing (process) photographic processes\n\n  object_colour: grey monochrome grey monochrome\n\n  edition_description: NA NA\n\n  physical_appearance: The image shows a black-and-white photograph. It is rectangular in shape. There are three people posing and they are looking towards the direction in which the photograph was captured. They are standing in front of three cartoon figurines in the form of tigers. These cartoon figurines are placed on poles and they are depicted to be holding enlarged versions of Tiger oil packaging.  The image shows a black-and-white photograph. It is rectangular in shape. There are three people posing and they are looking towards the direction in which the photograph was captured. They are standing in front of three cartoon figurines in the form of tigers. These cartoon figurines are placed on poles and they are depicted to be holding enlarged versions of Tiger oil packaging.\n\n  subject_terms_1: snapshots visitors theme parks snapshots visitors theme parks\n\n  subject_terms_2: Black-and-white photography Men Women Amusement parks Black-and-white photography Men Women Amusement parks\n\n  subject_terms_3: Photography Haw Par Villa Parks and gardens Photography Haw Par Villa Parks and gardens\n\n  subject_terms_4: NA NA\n\n  context_1: NA NA\n\n  context_2: NA NA\n\n  context_3: NA NA\n\n  context_4: NA NA\n\n  context_5: NA NA\n\n  context_6: NA NA\n\n  context_7: NA NA\n\n  context_8: NA NA\n\n  context_9: NA NA\n\n  context_10: NA NA\n\n  context_11: NA NA\n\n  context_12: NA NA\n\n  context_13: NA NA\n\n  context_14: NA NA\n\n  context_15: NA NA\n\n  context_16: NA NA\n\n  context_17: NA NA\n\n  context_18: NA NA\n\n  context_19: NA NA\n\n  context_20: NA NA\n\n  context_21: NA NA\n\n  context_22: NA NA\n\n  context_23: NA NA\n\n  context_24: NA NA\n\n  sgcool_label_text: The Tiger balm brand remains today an important local brand and traces its history back to the Aw brothers—Au Boon Haw and Aw Boon Par. Their father\n Au Chu Kin was an herbalist who started Eng Aun Tong (the Hall of Everlasting Peace) and passed the product formula to his sons in the early 1900s.  The Aw brothers perfected the formula in oil and balm form.  The oil form was the original form and was popular in Singapore households from the 1930s onwards.\\r\\nThe photograph depicts three visitors to the Tiger Balm gardens (also known as the Haw Par Villa). This villa garden was an entertainment park to teach and preserve traditional Chinese values (such as filial piety) through the exposition of folklore\n legends and historical events in the form of tableaux and figurines. \\r\\n The Tiger balm brand remains today an important local brand and traces its history back to the Aw brothers—Au Boon Haw and Aw Boon Par. Their father\n Au Chu Kin was an herbalist who started Eng Aun Tong (the Hall of Everlasting Peace) and passed the product formula to his sons in the early 1900s.  The Aw brothers perfected the formula in oil and balm form.  The oil form was the original form and was popular in Singapore households from the 1930s onwards.\\r\\nThe photograph depicts three visitors to the Tiger Balm gardens (also known as the Haw Par Villa). This villa garden was an entertainment park to teach and preserve traditional Chinese values (such as filial piety) through the exposition of folklore\n legends and historical events in the form of tableaux and figurines. \\r\\n\n",
  "createdDate": "20201120223707",
  "version": 0,
  "latest": false,
  "roles": [],
  "metadata": {
    "accession_no_csv": "2016-00568-004",
    "Image": "",
    "object_work_type": "black-and-white photographs photographs black-and-white photographs photographs",
    "title_text": "Photograph of three patrons to Tiger Balm Gardens\r\n Bottle of Tiger Oil with packaging box and photograph of three patrons to Tiger Balm Gardens Photograph of three patrons to Tiger Balm Gardens\r\n Bottle of Tiger Oil with packaging box and photograph of three patrons to Tiger Balm Gardens",
    "preference": "main alternate main alternate",
    "title_language": "",
    "creator_2": "Not indicated Not indicated",
    "creator_1": "Not indicated Not indicated",
    "creator_role": "NA NA",
    "creation_date": "1960-1975 Mid 1960s to Early 1970s",
    "creation_place_original_location": "Singapore Singapore",
    "styles_periods_indexing_terms": "NA NA",
    "inscriptions": "",
    "inscription_language": "",
    "scale_type": "NA NA",
    "shape": "rectangular rectangular",
    "materials_name": "paper (fiber product) paper (fiber product)",
    "techniques_name": "printing (process) photographic processes printing (process) photographic processes",
    "object_colour": "grey monochrome grey monochrome",
    "edition_description": "NA NA",
    "physical_appearance": "The image shows a black-and-white photograph. It is rectangular in shape. There are three people posing and they are looking towards the direction in which the photograph was captured. They are standing in front of three cartoon figurines in the form of tigers. These cartoon figurines are placed on poles and they are depicted to be holding enlarged versions of Tiger oil packaging.  The image shows a black-and-white photograph. It is rectangular in shape. There are three people posing and they are looking towards the direction in which the photograph was captured. They are standing in front of three cartoon figurines in the form of tigers. These cartoon figurines are placed on poles and they are depicted to be holding enlarged versions of Tiger oil packaging.",
    "subject_terms_1": "snapshots visitors theme parks snapshots visitors theme parks",
    "subject_terms_2": "Black-and-white photography Men Women Amusement parks Black-and-white photography Men Women Amusement parks",
    "subject_terms_3": "Photography Haw Par Villa Parks and gardens Photography Haw Par Villa Parks and gardens",
    "subject_terms_4": "NA NA",
    "context_1": "NA NA",
    "context_2": "NA NA",
    "context_3": "NA NA",
    "context_4": "NA NA",
    "context_5": "NA NA",
    "context_6": "NA NA",
    "context_7": "NA NA",
    "context_8": "NA NA",
    "context_9": "NA NA",
    "context_10": "NA NA",
    "context_11": "NA NA",
    "context_12": "NA NA",
    "context_13": "NA NA",
    "context_14": "NA NA",
    "context_15": "NA NA",
    "context_16": "NA NA",
    "context_17": "NA NA",
    "context_18": "NA NA",
    "context_19": "NA NA",
    "context_20": "NA NA",
    "context_21": "NA NA",
    "context_22": "NA NA",
    "context_23": "NA NA",
    "context_24": "NA NA",
    "sgcool_label_text": "The Tiger balm brand remains today an important local brand and traces its history back to the Aw brothers—Au Boon Haw and Aw Boon Par. Their father, Au Chu Kin was an herbalist who started Eng Aun Tong (the Hall of Everlasting Peace) and passed the product formula to his sons in the early 1900s.  The Aw brothers perfected the formula in oil and balm form.  The oil form was the original form and was popular in Singapore households from the 1930s onwards.\r\nThe photograph depicts three visitors to the Tiger Balm gardens (also known as the Haw Par Villa). This villa garden was an entertainment park to teach and preserve traditional Chinese values (such as filial piety) through the exposition of folklore, legends and historical events in the form of tableaux and figurines. \r\n The Tiger balm brand remains today an important local brand and traces its history back to the Aw brothers—Au Boon Haw and Aw Boon Par. Their father, Au Chu Kin was an herbalist who started Eng Aun Tong (the Hall of Everlasting Peace) and passed the product formula to his sons in the early 1900s.  The Aw brothers perfected the formula in oil and balm form.  The oil form was the original form and was popular in Singapore households from the 1930s onwards.\r\nThe photograph depicts three visitors to the Tiger Balm gardens (also known as the Haw Par Villa). This villa garden was an entertainment park to teach and preserve traditional Chinese values (such as filial piety) through the exposition of folklore, legends and historical events in the form of tableaux and figurines. \r\n"
  },
  "nlpDate": "20201120223707",
  "connectorId": 0,
  "tags": {}
}