{"id":"2016-00335","title":"Brocade Stole","source":"Bumblebee","path":"./Data/json/","content":"accession_no_csv:2016-00335\nImage:\nobject_work_type:stoles (outerwears) shawls scarves (costume accessories)\ntitle_text:Brocade Stole\npreference:main\ntitle_language:\ncreation_date:1801 - 2000\ncreation_place_original_location:Varanasi (Uttar Pradesh\n India)\nstyles_periods_indexing_terms:Indian (South Asian)\ninscriptions:\ninscription_language:\nshape:rectangular\nmaterials_name:silk (textile) metal thread brocade (textile)\ntechniques_name:sewing (needleworking technique) weaving\nobject_colour:brown colours\nphysical_appearance:This brocade stole is predominantly light brown in colour. It is rectangular in shape. Along its sides are floral patterns that extend and follow the rectangular perimeter. Within the border of floral patterns\n the figures of Hindu deities Krishna and Radha are present all over the brocade stole. Along Krishna and Radha are patterns of tree branches that are in green in colour and come with flowers and parakeets. There is a distinct stain line that runs vertically down the brocade stole at its mid-point.\nsubject_terms_1:textiles (visual works) deities Hinduism allover patterns plant-derived motifs birds (motifs)\nsubject_terms_2:Textiles Radha (Hindu deity) Krishna (Hindu deity) Stoles (Clothing) Shawls Motifs\nsubject_terms_3:Hinduism\nsgcool_label_text:This gold kimkhab brocade would have been woven in Benaras\n which was the epicentre of fine brocade weaving during the 19th and 20th centuries. Benarasi brocades gained prominence during the Mughal period\n and continued to be patronised by royalty and the British up to the 20th century. Over time\n patterns and techniques evolved\n and the export market provided new designs for weavers.\\r\\n\\r\\nThis stole shows a very unusual repeated pattern of Krishna and Radha sitting on a swing\n which is hanging from the branch of a tree. A pair of parakeets is perched on the tree. Designs such as these can be seen from the 20th century onwards.","createdDate":"20201018182635","version":0,"latest":false,"roles":[],"metadata":{"accession_no_csv":"2016-00335","Image":"","object_work_type":"stoles (outerwears) shawls scarves (costume accessories)","title_text":"Brocade Stole","preference":"main","title_language":"","creation_date":"1801 - 2000","creation_place_original_location":"Varanasi (Uttar Pradesh, India)","styles_periods_indexing_terms":"Indian (South Asian)","inscriptions":"","inscription_language":"","shape":"rectangular","materials_name":"silk (textile) metal thread brocade (textile)","techniques_name":"sewing (needleworking technique) weaving","object_colour":"brown colours","physical_appearance":"This brocade stole is predominantly light brown in colour. It is rectangular in shape. Along its sides are floral patterns that extend and follow the rectangular perimeter. Within the border of floral patterns, the figures of Hindu deities Krishna and Radha are present all over the brocade stole. Along Krishna and Radha are patterns of tree branches that are in green in colour and come with flowers and parakeets. There is a distinct stain line that runs vertically down the brocade stole at its mid-point.","subject_terms_1":"textiles (visual works) deities Hinduism allover patterns plant-derived motifs birds (motifs)","subject_terms_2":"Textiles Radha (Hindu deity) Krishna (Hindu deity) Stoles (Clothing) Shawls Motifs","subject_terms_3":"Hinduism","sgcool_label_text":"This gold kimkhab brocade would have been woven in Benaras, which was the epicentre of fine brocade weaving during the 19th and 20th centuries. Benarasi brocades gained prominence during the Mughal period, and continued to be patronised by royalty and the British up to the 20th century. Over time, patterns and techniques evolved, and the export market provided new designs for weavers.\r\n\r\nThis stole shows a very unusual repeated pattern of Krishna and Radha sitting on a swing, which is hanging from the branch of a tree. A pair of parakeets is perched on the tree. Designs such as these can be seen from the 20th century onwards."},"nlpDate":"20201018182635","connectorId":0,"tags":{}}