{
  "id": "2016-00239",
  "title": "Bedcover Chinese silk bedcover",
  "source": "Bumblebee",
  "path": "./Data/json/",
  "content": "\n  accession_no_csv: 2016-00239\n\n  Image: \n\n  object_work_type: bedcovers\n\n  title_text: Bedcover Chinese silk bedcover\n\n  preference: main alternate\n\n  title_language: \n\n  creation_date: 1730-1740\n\n  creation_place_original_location: Macau (China)\n\n  styles_periods_indexing_terms: European\n\n  inscriptions: \n\n  inscription_language: \n\n  shape: rectangular\n\n  materials_name: pigment satin silk gold thread\n\n  techniques_name: weaving embroidering\n\n  object_colour: multicolored\n\n  physical_appearance: This is a bedcover embroided with decorative elements. The border of the bedcover is lined with red trimmings\n with tassels attached to each corner. The bedcover features a scrolling foliage multicolored motif. The center of the bedcover has a double-headed eagle motif.\n\n  subject_terms_1: exports scrolling foliage birds (motifs) Roman Catholicism\n\n  subject_terms_2: Exports Double-headed eagle (Emblem) Augustinians Coverlets Catholic Church\n\n  subject_terms_3: Textile art and design\n\n  sgcool_label_text: The double-headed eagle motif in the centre of this bedcover derives from the emblem of the Augustinian Order. This Catholic order established missions in Asian port cities\n including Manila and Macao. \\r\\n\\r\\nChinese silks like this were commissioned for a wide range of purposes – furnishing\n clothing\n and liturgical vestments – and their designs combine Chinese techniques and decorative elements with European motifs\n often copied from European engravings. These silks were primarily made for Portugal and the rest of Europe.\n",
  "createdDate": "20201201203309",
  "version": 0,
  "latest": false,
  "roles": [],
  "metadata": {
    "accession_no_csv": "2016-00239",
    "Image": "",
    "object_work_type": "bedcovers",
    "title_text": "Bedcover Chinese silk bedcover",
    "preference": "main alternate",
    "title_language": "",
    "creation_date": "1730-1740",
    "creation_place_original_location": "Macau (China)",
    "styles_periods_indexing_terms": "European",
    "inscriptions": "",
    "inscription_language": "",
    "shape": "rectangular",
    "materials_name": "pigment satin silk gold thread",
    "techniques_name": "weaving embroidering",
    "object_colour": "multicolored",
    "physical_appearance": "This is a bedcover embroided with decorative elements. The border of the bedcover is lined with red trimmings, with tassels attached to each corner. The bedcover features a scrolling foliage multicolored motif. The center of the bedcover has a double-headed eagle motif.",
    "subject_terms_1": "exports scrolling foliage birds (motifs) Roman Catholicism",
    "subject_terms_2": "Exports Double-headed eagle (Emblem) Augustinians Coverlets Catholic Church",
    "subject_terms_3": "Textile art and design",
    "sgcool_label_text": "The double-headed eagle motif in the centre of this bedcover derives from the emblem of the Augustinian Order. This Catholic order established missions in Asian port cities, including Manila and Macao. \r\n\r\nChinese silks like this were commissioned for a wide range of purposes – furnishing, clothing, and liturgical vestments – and their designs combine Chinese techniques and decorative elements with European motifs, often copied from European engravings. These silks were primarily made for Portugal and the rest of Europe."
  },
  "nlpDate": "20201201203309",
  "connectorId": 0,
  "tags": {}
}