{
  "id": "2016-00728 - 2016-00739",
  "title": "Photographs by Loke Hong Seng",
  "source": "Bumblebee",
  "path": "./Data/json/",
  "content": "\n  accession_no_csv: 2016-00728 - 2016-00739\n\n  Image: \n\n  object_work_type: black-and-white photographs\n\n  title_text: Photographs by Loke Hong Seng\n\n  preference: main\n\n  title_language: \n\n  creator_2: Loke Hong Seng\n\n  creator_1: Loke\n Hong Seng\n\n  creator_role: photographers\n\n  creation_date: 2015 [1964] - 2015 [1973]\n\n  creation_place_original_location: Singapore\n\n  inscriptions: \n\n  inscription_language: \n\n  shape: rectangular square (shape)\n\n  materials_name: paper (fiber product)\n\n  techniques_name: printing (process)\n\n  object_colour: grey monochrome\n\n  edition_description: varies\n\n  physical_appearance: All of the photographs are in black-and-white\n which are enclosed by a white frame. They are either in landscape or portrait arrangement. Most of the photographs depict people in them\n from youths to blue collar workers. A number of photographs contain images of high-rise flats as well as villages. At the bottom of every photograph to the left hand side\n there is a designation of the edition number. At the bottom right hand side of every photograph\n there is a signature in Chinese characters.\n\n  subject_terms_1: residential structures blue collar workers urban development villages planned communities new towns (modern settlements) dwellings flats (apartments)\n\n  subject_terms_2: Planned communities Villages Apartments Dwellings Singapore Blue collar workers Urban development Black-and-white photography Street photography New towns\n\n  subject_terms_3: Photography Artistic photography\n\n  sgcool_label_text: varies\n",
  "createdDate": "20201201203308",
  "version": 0,
  "latest": false,
  "roles": [],
  "metadata": {
    "accession_no_csv": "2016-00728 - 2016-00739",
    "Image": "",
    "object_work_type": "black-and-white photographs",
    "title_text": "Photographs by Loke Hong Seng",
    "preference": "main",
    "title_language": "",
    "creator_2": "Loke Hong Seng",
    "creator_1": "Loke, Hong Seng",
    "creator_role": "photographers",
    "creation_date": "2015 [1964] - 2015 [1973]",
    "creation_place_original_location": "Singapore",
    "inscriptions": "",
    "inscription_language": "",
    "shape": "rectangular square (shape)",
    "materials_name": "paper (fiber product)",
    "techniques_name": "printing (process)",
    "object_colour": "grey monochrome",
    "edition_description": "varies",
    "physical_appearance": "All of the photographs are in black-and-white, which are enclosed by a white frame. They are either in landscape or portrait arrangement. Most of the photographs depict people in them, from youths to blue collar workers. A number of photographs contain images of high-rise flats as well as villages. At the bottom of every photograph to the left hand side, there is a designation of the edition number. At the bottom right hand side of every photograph, there is a signature in Chinese characters.",
    "subject_terms_1": "residential structures blue collar workers urban development villages planned communities new towns (modern settlements) dwellings flats (apartments)",
    "subject_terms_2": "Planned communities Villages Apartments Dwellings Singapore Blue collar workers Urban development Black-and-white photography Street photography New towns",
    "subject_terms_3": "Photography Artistic photography",
    "sgcool_label_text": "varies"
  },
  "nlpDate": "20201201203308",
  "connectorId": 0,
  "tags": {}
}