{
  "id": "2016-00270",
  "title": "Garuda Garuda Sculpture",
  "source": "Bumblebee",
  "path": "./Data/json/",
  "content": "\n  accession_no_csv: 2016-00270\n\n  Image: \n\n  object_work_type: sculpture (visual works)\n\n  title_text: Garuda Garuda Sculpture\n\n  preference: alternate main\n\n  title_language: \n\n  creation_date: 15th century\n\n  creation_place_original_location: Tibet Autonomous Region (China)\n\n  inscriptions: \n\n  inscription_language: \n\n  shape: irregular\n\n  materials_name: copper (metal)\n\n  techniques_name: sculpting\n\n  object_colour: bronze (color)\n\n  physical_appearance: This is a sculpture of Garuda. The sculpture has opened wings\n with a featured head with horns. The sculpture\\u0027s hands are outstretched\n palm facing the front\n with the tip of the middle finger and thumb touching. The legs of the sculpture are featured\n with feet having three clawed toes. The sculpture is mounted on a stand. It has a slight orange tint around the surface of its head.\n\n  subject_terms_1: deities Hinduism Buddhism\n\n  subject_terms_2: Sculpture Garuda (Mythical bird) Hindu mythology Buddhist mythology Gods\n\n  subject_terms_3: Sculpture Religious life and practices\n\n  sgcool_label_text: Garuda is a figure who transcends specific religion\n as he is worshipped in an independent cult. His image is also found in Buddhist as well as Hindu art. In Hinduism he is Vishnu\\u0027s mount\n while in Buddhism he is a guardian deity.\\r\\n\\r\\nThis sculpture emphasizes the connections between and makes an important addition to the Himalayan collection\n which is envisioned to be a small\n choice collection which covered different functions and types. The artistic qualities of this proposed work are strong: there is a clear sense of character and a Garuda is a figure who transcends specific religion\n as he is worshipped in an independent cult. His image is also found in Buddhist as well as Hindu art. In Hinduism he is Vishnu\\u0027s mount\n while in Buddhism he is a guardian deity.\n",
  "createdDate": "20201120223706",
  "version": 0,
  "latest": false,
  "roles": [],
  "metadata": {
    "accession_no_csv": "2016-00270",
    "Image": "",
    "object_work_type": "sculpture (visual works)",
    "title_text": "Garuda Garuda Sculpture",
    "preference": "alternate main",
    "title_language": "",
    "creation_date": "15th century",
    "creation_place_original_location": "Tibet Autonomous Region (China)",
    "inscriptions": "",
    "inscription_language": "",
    "shape": "irregular",
    "materials_name": "copper (metal)",
    "techniques_name": "sculpting",
    "object_colour": "bronze (color)",
    "physical_appearance": "This is a sculpture of Garuda. The sculpture has opened wings, with a featured head with horns. The sculpture\u0027s hands are outstretched, palm facing the front, with the tip of the middle finger and thumb touching. The legs of the sculpture are featured, with feet having three clawed toes. The sculpture is mounted on a stand. It has a slight orange tint around the surface of its head.",
    "subject_terms_1": "deities Hinduism Buddhism",
    "subject_terms_2": "Sculpture Garuda (Mythical bird) Hindu mythology Buddhist mythology Gods",
    "subject_terms_3": "Sculpture Religious life and practices",
    "sgcool_label_text": "Garuda is a figure who transcends specific religion, as he is worshipped in an independent cult. His image is also found in Buddhist as well as Hindu art. In Hinduism he is Vishnu\u0027s mount, while in Buddhism he is a guardian deity.\r\n\r\nThis sculpture emphasizes the connections between and makes an important addition to the Himalayan collection, which is envisioned to be a small, choice collection which covered different functions and types. The artistic qualities of this proposed work are strong: there is a clear sense of character and a Garuda is a figure who transcends specific religion, as he is worshipped in an independent cult. His image is also found in Buddhist as well as Hindu art. In Hinduism he is Vishnu\u0027s mount, while in Buddhism he is a guardian deity."
  },
  "nlpDate": "20201120223706",
  "connectorId": 0,
  "tags": {}
}