{"id":"2016-00604","title":"S Gopalakrishnan with the employees of the Far East Air Force (inside the grounds)","source":"Bumblebee","path":"./Data/json/","content":"accession_no_csv:2016-00604\nImage:\nobject_work_type:black-and-white photographs\ntitle_text:S Gopalakrishnan with the employees of the Far East Air Force (inside the grounds)\npreference:main\ntitle_language:\ncreation_date:1941 - 1970\ncreation_place_original_location:Singapore\ninscriptions:\ninscription_language:\nshape:rectangular\nmaterials_name:paper (fiber product)\ntechniques_name:printing (process) photographic processes\nobject_colour:grey monochrome\nphysical_appearance:The image shows a rectangular photograph that is in black-and-white. The photograph features four rows of men posing as a group. The men in the last two rows are standing up while the men in the front two rows are either sitting on chairs or on the grass. All of them are looking towards the direction in which the photograph was captured. Some of the men are decked in military uniform while others are in formal plain clothes. There is a large single storey roofed building at the background.\nsubject_terms_1:air forces personnel groups (organizations) group portraits studio portraits\nsubject_terms_2:Black-and-white photography Great Britain. Royal Air Force Employees Portraits\n Group Portrait photography\nsubject_terms_3:Portrait photography Great Britain. Royal Air Force Military facilities\nsgcool_label_text:Mr. S Gopalakrishnan (b. in 1920 in Tanjavur) was a prominent violinist\n and Carnatic singer. He arrived in Singapore in 1939 and actively participated in the Indian classical music scene here. Mr Gopalakrishnan performed alongside veterans of classical performers such as Pandit M Ramalingam and MV Gurusamy at temple and other music festivals. He also taught violin lessons at the Singapore Malayalee Association from the 1970s to 2000s. He was a member of the Tamils Reform Association and performed his wedding according to the principles of the Self-Respect Movement. He was also employed as a compositor at the Far East Air Force from 1954 to 1970.","createdDate":"20201018182635","version":0,"latest":false,"roles":[],"metadata":{"accession_no_csv":"2016-00604","Image":"","object_work_type":"black-and-white photographs","title_text":"S Gopalakrishnan with the employees of the Far East Air Force (inside the grounds)","preference":"main","title_language":"","creation_date":"1941 - 1970","creation_place_original_location":"Singapore","inscriptions":"","inscription_language":"","shape":"rectangular","materials_name":"paper (fiber product)","techniques_name":"printing (process) photographic processes","object_colour":"grey monochrome","physical_appearance":"The image shows a rectangular photograph that is in black-and-white. The photograph features four rows of men posing as a group. The men in the last two rows are standing up while the men in the front two rows are either sitting on chairs or on the grass. All of them are looking towards the direction in which the photograph was captured. Some of the men are decked in military uniform while others are in formal plain clothes. There is a large single storey roofed building at the background.","subject_terms_1":"air forces personnel groups (organizations) group portraits studio portraits","subject_terms_2":"Black-and-white photography Great Britain. Royal Air Force Employees Portraits, Group Portrait photography","subject_terms_3":"Portrait photography Great Britain. Royal Air Force Military facilities","sgcool_label_text":"Mr. S Gopalakrishnan (b. in 1920 in Tanjavur) was a prominent violinist, and Carnatic singer. He arrived in Singapore in 1939 and actively participated in the Indian classical music scene here. Mr Gopalakrishnan performed alongside veterans of classical performers such as Pandit M Ramalingam and MV Gurusamy at temple and other music festivals. He also taught violin lessons at the Singapore Malayalee Association from the 1970s to 2000s. He was a member of the Tamils Reform Association and performed his wedding according to the principles of the Self-Respect Movement. He was also employed as a compositor at the Far East Air Force from 1954 to 1970."},"nlpDate":"20201018182635","connectorId":0,"tags":{}}