{"id":"2016-00754","title":"Altar – 2 parts Gilded altar tables","source":"Bumblebee","path":"./Data/json/","content":"accession_no_csv:2016-00754\nImage:\nobject_work_type:altar tables\ntitle_text:Altar – 2 parts Gilded altar tables\npreference:alternate main\ntitle_language:\ncreation_date:1900-1920\ncreation_place_original_location:Singapore\ninscriptions:\ninscription_language:\nshape:irregular\nmaterials_name:teak (wood)\ntechniques_name:woodcarving gilding (technique)\nobject_colour:multicolored\nphysical_appearance:This is a set of gilded altar tables. The back table is taller than the front table. The front table is gilded in sections. The tables have floral and vine engravings on the front and down the sides. At the edges of both tables\n there are carvings of lion heads. On top of the tables sit various ornaments.\nsubject_terms_1:altars flower (motif) Peranakan religious ceremonies lion\\u0027s head (motif) carvings (visual works) worship\nsubject_terms_2:Tables Altars Motifs Peranakan (Asian people) Rites and ceremonies Worship\nsubject_terms_3:Religious life and practices\nsgcool_label_text:This gilded altar comes in two parts. The two tables are made of teak and was gilded in sections. The heads of ferocious lions are carved at the edges of both tables\n with flowers and vines carved along the sides. The base of the tables is carved in the shape of lion’s claws griping a ball. Though the gilding is still very apparent on the lower table\n suggesting a recent re-gilding\n most of the gilding has faded on the taller table.\\r\\n\\r\\nThis item is donated by the family of prominent Peranakan\n Ong Sam Leong (b. 1857\n Singapore – d. 7 February 1918\n Singapore). It comes from his ancestral home of Bukit Rose\n formerly at 259 Bukit Timah Road. Ong was a well-known successful businessman who made is money in the mining of phosphate on Christmas island\n which was historically a territory of colonial Singapore.","createdDate":"20201018182635","version":0,"latest":false,"roles":[],"metadata":{"accession_no_csv":"2016-00754","Image":"","object_work_type":"altar tables","title_text":"Altar – 2 parts Gilded altar tables","preference":"alternate main","title_language":"","creation_date":"1900-1920","creation_place_original_location":"Singapore","inscriptions":"","inscription_language":"","shape":"irregular","materials_name":"teak (wood)","techniques_name":"woodcarving gilding (technique)","object_colour":"multicolored","physical_appearance":"This is a set of gilded altar tables. The back table is taller than the front table. The front table is gilded in sections. The tables have floral and vine engravings on the front and down the sides. At the edges of both tables, there are carvings of lion heads. On top of the tables sit various ornaments.","subject_terms_1":"altars flower (motif) Peranakan religious ceremonies lion\u0027s head (motif) carvings (visual works) worship","subject_terms_2":"Tables Altars Motifs Peranakan (Asian people) Rites and ceremonies Worship","subject_terms_3":"Religious life and practices","sgcool_label_text":"This gilded altar comes in two parts. The two tables are made of teak and was gilded in sections. The heads of ferocious lions are carved at the edges of both tables, with flowers and vines carved along the sides. The base of the tables is carved in the shape of lion’s claws griping a ball. Though the gilding is still very apparent on the lower table, suggesting a recent re-gilding, most of the gilding has faded on the taller table.\r\n\r\nThis item is donated by the family of prominent Peranakan, Ong Sam Leong (b. 1857, Singapore – d. 7 February 1918, Singapore). It comes from his ancestral home of Bukit Rose, formerly at 259 Bukit Timah Road. Ong was a well-known successful businessman who made is money in the mining of phosphate on Christmas island, which was historically a territory of colonial Singapore."},"nlpDate":"20201018182635","connectorId":0,"tags":{}}