{"id":"2016-00626","title":"Certificate of Service issued to Kaliappan s/o Krishnasamy","source":"Bumblebee","path":"./Data/json/","content":"accession_no_csv:2016-00626\nImage:\nobject_work_type:certificates\ntitle_text:Certificate of Service issued to Kaliappan s/o Krishnasamy\npreference:main\ntitle_language:\ncreator_2:Far East Air Force (Royal Air Force)\ncreator_1:Great Britain. Royal Air Force\ncreator_role:creators\ncreation_date:4-Jan-67\ncreation_place_original_location:Singapore\ninscriptions:\ninscription_language:\nshape:rectangular\nmaterials_name:paper (fiber product)\ntechniques_name:printing (process)\nobject_colour:grey (colour)\nphysical_appearance:\\The image displays a document. \\\\Certificate of Service\\\\ is displayed and underlined at the top of the document\nsubject_terms_1:just below the logo. \\\\Royal Air Force Tengah\\\\ is stated as the employer. The signature and particulars of \\\\D.C. Rabot\\\\ air forces labourers discharges\nsubject_terms_2:\\\\Officer Commanding Royal Air Force Tengah\\\\ Great Britain. Royal Air Force Blue collar workers Resignation\nsubject_terms_3:are present and stated at the bottom right hand side of the document. At the top right hand side of the certificate Military facilities Tengah Air Base\nsubject_terms_4:\\\\F.E.A.F. Form 219\\\\ is stated\ncontext_1:serving as the abbrievation for Far East Air Force. There are some stains on the right hand side of the document.\\\ncontext_2:certification\ncontext_3:Certification\ncontext_4:Great Britain. Royal Air Force\nsgcool_label_text:This certificate of service was issued by the Air Ministry which was based in what is presently known as Tengah Air Base","createdDate":"20201119143405","version":0,"latest":false,"roles":[],"metadata":{"accession_no_csv":"2016-00626","Image":"","object_work_type":"certificates","title_text":"Certificate of Service issued to Kaliappan s/o Krishnasamy","preference":"main","title_language":"","creator_2":"Far East Air Force (Royal Air Force)","creator_1":"Great Britain. Royal Air Force","creator_role":"creators","creation_date":"4-Jan-67","creation_place_original_location":"Singapore","inscriptions":"","inscription_language":"","shape":"rectangular","materials_name":"paper (fiber product)","techniques_name":"printing (process)","object_colour":"grey (colour)","physical_appearance":"\"The image displays a document. \"\"Certificate of Service\"\" is displayed and underlined at the top of the document","subject_terms_1":"just below the logo. \"\"Royal Air Force Tengah\"\" is stated as the employer. The signature and particulars of \"\"D.C. Rabot\"\" air forces labourers discharges","subject_terms_2":"\"\"Officer Commanding Royal Air Force Tengah\"\" Great Britain. Royal Air Force Blue collar workers Resignation","subject_terms_3":"are present and stated at the bottom right hand side of the document. At the top right hand side of the certificate Military facilities Tengah Air Base","subject_terms_4":"\"\"F.E.A.F. Form 219\"\" is stated","context_1":"serving as the abbrievation for Far East Air Force. There are some stains on the right hand side of the document.\"","context_2":"certification","context_3":"Certification","context_4":"Great Britain. Royal Air Force","sgcool_label_text":"This certificate of service was issued by the Air Ministry which was based in what is presently known as Tengah Air Base"},"nlpDate":"20201119143405","connectorId":0,"tags":{}}