{
  "id": "2016-00553",
  "title": "50 issues of Majallah Bahasa Kebangsaan 50 issues of Majallah Bahasa Kebangsaan, a magazine to promote the learning of the Malay language, published by the World Book Co. (M) Ltd.  50 issues of Majallah Bahasa Kebangsaan 50 issues of Majallah Bahasa Kebangsaan, a magazine to promote the learning of the Malay language, published by the World Book Co. (M) Ltd.",
  "source": "Bumblebee",
  "path": "./Data/json/",
  "content": "\n  accession_no_csv: 2016-00553\n\n  Image: \n\n  object_work_type: magazines (periodicals) magazines (periodicals)\n\n  title_text: 50 issues of Majallah Bahasa Kebangsaan 50 issues of Majallah Bahasa Kebangsaan\n a magazine to promote the learning of the Malay language\n published by the World Book Co. (M) Ltd.  50 issues of Majallah Bahasa Kebangsaan 50 issues of Majallah Bahasa Kebangsaan\n a magazine to promote the learning of the Malay language\n published by the World Book Co. (M) Ltd.\n\n  preference: main alternate main alternate\n\n  title_language: \n\n  creator_2: World Book Co. (M) Ltd.  World Book Co. (M) Ltd.\n\n  creator_1: Not indicated Not indicated\n\n  creator_role: publishers publishers\n\n  creation_date: 1960s - 1970s  1960s - 1970s\n\n  creation_place_original_location: Singapore Singapore\n\n  styles_periods_indexing_terms: NA NA\n\n  inscriptions: \n\n  inscription_language: \n\n  scale_type: NA NA\n\n  shape: rectangular rectangular\n\n  materials_name: printing paper printing paper\n\n  techniques_name: colour printing colour printing\n\n  object_colour: multicoloured multicoloured\n\n  edition_description: NA NA\n\n  physical_appearance: \\The image shows five sets of magazines. All of them are rectangular in shape. And their front cover is navy blue and green in colour. \\\\Majallah Bahasa Kebangsaan\\\\ is stated at the top of each magazine cover. \\\\The World Book Co. (M) Ltd. \\\\ is stated at the bottom of each magazine cover. There are Chinese characters on the magazine cover. The magazine covers are numbered from two to six.\\ \\The image shows five sets of magazines. All of them are rectangular in shape. And their front cover is navy blue and green in colour. \\\\Majallah Bahasa Kebangsaan\\\\ is stated at the top of each magazine cover. \\\\The World Book Co. (M) Ltd. \\\\ is stated at the bottom of each magazine cover. There are Chinese characters on the magazine cover. The magazine covers are numbered from two to six.\\\n\n  subject_terms_1: education languages (study discipline) education languages (study discipline)\n\n  subject_terms_2: Periodicals Education Language and languages Periodicals Education Language and languages\n\n  subject_terms_3: Periodicals Malay languages and dialects Education Periodicals Malay languages and dialects Education\n\n  subject_terms_4: NA NA\n\n  context_1: NA NA\n\n  context_2: NA NA\n\n  context_3: NA NA\n\n  context_4: NA NA\n\n  context_5: NA NA\n\n  context_6: NA NA\n\n  context_7: NA NA\n\n  context_8: NA NA\n\n  context_9: NA NA\n\n  context_10: NA NA\n\n  context_11: NA NA\n\n  context_12: NA NA\n\n  context_13: NA NA\n\n  context_14: NA NA\n\n  context_15: NA NA\n\n  context_16: NA NA\n\n  context_17: NA NA\n\n  context_18: NA NA\n\n  context_19: NA NA\n\n  context_20: NA NA\n\n  context_21: NA NA\n\n  context_22: NA NA\n\n  context_23: NA NA\n\n  context_24: NA NA\n\n  sgcool_label_text: Published in Malaysia\n the Majallah Bahasa Kebangsaan was an educational magazine that encouraged and promoted the learning of Malay the national language among Chinese. Published in Malaysia\n the Majallah Bahasa Kebangsaan was an educational magazine that encouraged and promoted the learning of Malay the national language among Chinese.\n",
  "createdDate": "20201120223707",
  "version": 0,
  "latest": false,
  "roles": [],
  "metadata": {
    "accession_no_csv": "2016-00553",
    "Image": "",
    "object_work_type": "magazines (periodicals) magazines (periodicals)",
    "title_text": "50 issues of Majallah Bahasa Kebangsaan 50 issues of Majallah Bahasa Kebangsaan, a magazine to promote the learning of the Malay language, published by the World Book Co. (M) Ltd.  50 issues of Majallah Bahasa Kebangsaan 50 issues of Majallah Bahasa Kebangsaan, a magazine to promote the learning of the Malay language, published by the World Book Co. (M) Ltd.",
    "preference": "main alternate main alternate",
    "title_language": "",
    "creator_2": "World Book Co. (M) Ltd.  World Book Co. (M) Ltd.",
    "creator_1": "Not indicated Not indicated",
    "creator_role": "publishers publishers",
    "creation_date": "1960s - 1970s  1960s - 1970s",
    "creation_place_original_location": "Singapore Singapore",
    "styles_periods_indexing_terms": "NA NA",
    "inscriptions": "",
    "inscription_language": "",
    "scale_type": "NA NA",
    "shape": "rectangular rectangular",
    "materials_name": "printing paper printing paper",
    "techniques_name": "colour printing colour printing",
    "object_colour": "multicoloured multicoloured",
    "edition_description": "NA NA",
    "physical_appearance": "\"The image shows five sets of magazines. All of them are rectangular in shape. And their front cover is navy blue and green in colour. \"\"Majallah Bahasa Kebangsaan\"\" is stated at the top of each magazine cover. \"\"The World Book Co. (M) Ltd. \"\" is stated at the bottom of each magazine cover. There are Chinese characters on the magazine cover. The magazine covers are numbered from two to six.\" \"The image shows five sets of magazines. All of them are rectangular in shape. And their front cover is navy blue and green in colour. \"\"Majallah Bahasa Kebangsaan\"\" is stated at the top of each magazine cover. \"\"The World Book Co. (M) Ltd. \"\" is stated at the bottom of each magazine cover. There are Chinese characters on the magazine cover. The magazine covers are numbered from two to six.\"",
    "subject_terms_1": "education languages (study discipline) education languages (study discipline)",
    "subject_terms_2": "Periodicals Education Language and languages Periodicals Education Language and languages",
    "subject_terms_3": "Periodicals Malay languages and dialects Education Periodicals Malay languages and dialects Education",
    "subject_terms_4": "NA NA",
    "context_1": "NA NA",
    "context_2": "NA NA",
    "context_3": "NA NA",
    "context_4": "NA NA",
    "context_5": "NA NA",
    "context_6": "NA NA",
    "context_7": "NA NA",
    "context_8": "NA NA",
    "context_9": "NA NA",
    "context_10": "NA NA",
    "context_11": "NA NA",
    "context_12": "NA NA",
    "context_13": "NA NA",
    "context_14": "NA NA",
    "context_15": "NA NA",
    "context_16": "NA NA",
    "context_17": "NA NA",
    "context_18": "NA NA",
    "context_19": "NA NA",
    "context_20": "NA NA",
    "context_21": "NA NA",
    "context_22": "NA NA",
    "context_23": "NA NA",
    "context_24": "NA NA",
    "sgcool_label_text": "Published in Malaysia, the Majallah Bahasa Kebangsaan was an educational magazine that encouraged and promoted the learning of Malay the national language among Chinese. Published in Malaysia, the Majallah Bahasa Kebangsaan was an educational magazine that encouraged and promoted the learning of Malay the national language among Chinese."
  },
  "nlpDate": "20201120223707",
  "connectorId": 0,
  "tags": {}
}