{"id":"2016-00641","title":"Chitty Melaka Necklace","source":"Bumblebee","path":"./Data/json/","content":"accession_no_csv:2016-00641\nImage:\nobject_work_type:necklaces\ntitle_text:Chitty Melaka Necklace\npreference:main\ntitle_language:\ncreation_date:Early 20th century\ncreation_place_original_location:Singapore\nstyles_periods_indexing_terms:Peranakan\ninscriptions:\ninscription_language:\nshape:irregular\nmaterials_name:silver gilding gemstone\ntechniques_name:gilding (technique) forging (metal forming)\nobject_colour:multicolored\nphysical_appearance:This necklace features a thick chain with a large central pendant that is inset with several gemstones. At the bottom of the pendant\n there are several beads attached. The main chain of the necklace where the pendant is attached to has a butterfly link chain\n that is also inset with gemstones.\nsubject_terms_1:cultural diffusion Peranakan\nsubject_terms_2:Necklaces Jewelry Culture diffusion Intermarriage Peranakan (Asian people)\nsubject_terms_3:Peranakan costumes Jewellery\nsgcool_label_text:The necklace is made of gilded silver and features a large central pendant inset with gemstones\n with beads at the bottom of the pendant. The pendant is attached to the main chain of the necklace with a butterfly decoration similarly set with gemstones. They were often crafted by Indian goldsmiths. The intricacy of the patterns and designs were closely associated with the financial and social status of the wearer.  Although commonly used in China to prevent tarnishing\n the practice of gilding silver did not become popular in India.  Peranakan Indians were descended from marriages between South Indian Hindu merchants and local inhabitants.","createdDate":"20201119143405","version":0,"latest":false,"roles":[],"metadata":{"accession_no_csv":"2016-00641","Image":"","object_work_type":"necklaces","title_text":"Chitty Melaka Necklace","preference":"main","title_language":"","creation_date":"Early 20th century","creation_place_original_location":"Singapore","styles_periods_indexing_terms":"Peranakan","inscriptions":"","inscription_language":"","shape":"irregular","materials_name":"silver gilding gemstone","techniques_name":"gilding (technique) forging (metal forming)","object_colour":"multicolored","physical_appearance":"This necklace features a thick chain with a large central pendant that is inset with several gemstones. At the bottom of the pendant, there are several beads attached. The main chain of the necklace where the pendant is attached to has a butterfly link chain, that is also inset with gemstones.","subject_terms_1":"cultural diffusion Peranakan","subject_terms_2":"Necklaces Jewelry Culture diffusion Intermarriage Peranakan (Asian people)","subject_terms_3":"Peranakan costumes Jewellery","sgcool_label_text":"The necklace is made of gilded silver and features a large central pendant inset with gemstones, with beads at the bottom of the pendant. The pendant is attached to the main chain of the necklace with a butterfly decoration similarly set with gemstones. They were often crafted by Indian goldsmiths. The intricacy of the patterns and designs were closely associated with the financial and social status of the wearer.  Although commonly used in China to prevent tarnishing, the practice of gilding silver did not become popular in India.  Peranakan Indians were descended from marriages between South Indian Hindu merchants and local inhabitants."},"nlpDate":"20201119143405","connectorId":0,"tags":{}}