{"id":"2016-00212-061","title":"Photograph album of views and portraits in the Punjab, Cashmere, Ceylon, Burma, Penang, Singapore, and Java Old Harbour, Singapore","source":"Bumblebee","path":"./Data/json/","content":"accession_no_csv:2016-00212-061\nImage:\nobject_work_type:black-and-white photographs\ntitle_text:Photograph album of views and portraits in the Punjab\n Cashmere\n Ceylon\n Burma\n Penang\n Singapore\n and Java Old Harbour\n Singapore\npreference:alternate main\ntitle_language:\ncreator_2:John Thomson\ncreator_1:Thomson\n J. (John)\n 1837-1921\ncreator_role:photographers\ncreation_date:before 28 Jul 1876\ncreation_place_original_location:Singapore\ninscriptions:\ninscription_language:\nshape:rectangular\nmaterials_name:albumen (egg white protein) albumen paper paper (fiber product)\ntechniques_name:albumen process\nobject_colour:black-and-white (colors)\nphysical_appearance:This is a photograph of the Old Harbour in Singapore from a high view point. The foreground of the photograph shows the roofs of numerous buildings by the harbour. There are several ships by the harbour in the background of the photograph. The title is written at the bottom\n below the photograph.\nsubject_terms_1:aerial views harbors coastal settlements port settlements\nsubject_terms_2:Photographs Thomson\n J. (John)\n 1837-1921 Singapore Aerial views Harbors coastal settlements\nsubject_terms_3:Photography Singapore Harbour","createdDate":"20201119143405","version":0,"latest":false,"roles":[],"metadata":{"accession_no_csv":"2016-00212-061","Image":"","object_work_type":"black-and-white photographs","title_text":"Photograph album of views and portraits in the Punjab, Cashmere, Ceylon, Burma, Penang, Singapore, and Java Old Harbour, Singapore","preference":"alternate main","title_language":"","creator_2":"John Thomson","creator_1":"Thomson, J. (John), 1837-1921","creator_role":"photographers","creation_date":"before 28 Jul 1876","creation_place_original_location":"Singapore","inscriptions":"","inscription_language":"","shape":"rectangular","materials_name":"albumen (egg white protein) albumen paper paper (fiber product)","techniques_name":"albumen process","object_colour":"black-and-white (colors)","physical_appearance":"This is a photograph of the Old Harbour in Singapore from a high view point. The foreground of the photograph shows the roofs of numerous buildings by the harbour. There are several ships by the harbour in the background of the photograph. The title is written at the bottom, below the photograph.","subject_terms_1":"aerial views harbors coastal settlements port settlements","subject_terms_2":"Photographs Thomson, J. (John), 1837-1921 Singapore Aerial views Harbors coastal settlements","subject_terms_3":"Photography Singapore Harbour"},"nlpDate":"20201119143405","connectorId":0,"tags":{}}