{
  "id": "2016-00069",
  "title": "Invitation to music performance at  British Council Hall, Singapore",
  "source": "Bumblebee",
  "path": "./Data/json/",
  "content": "\n  accession_no_csv: 2016-00069\n\n  Image: \n\n  object_work_type: invitations\n\n  title_text: Invitation to music performance at  British Council Hall\n Singapore\n\n  preference: main\n\n  title_language: \n\n  creator_2: Unknown\n\n  creation_date: 5-Sep-51\n\n  creation_place_original_location: Singapore\n\n  styles_periods_indexing_terms: Not indicated\n\n  inscriptions: \n\n  inscription_language: \n\n  scale_type: Not indicated\n\n  shape: rectangular\n\n  materials_name: printing paper\n\n  techniques_name: printing (process)\n\n  object_colour: multicoloured\n\n  physical_appearance: \\The image shows an invitation card. It is rectangular in shape. It has a yellow background. The \\\\British Council Hall\n\n  subject_terms_1: musicians Stamford Road\n\n  subject_terms_2: British Council (Singapore) Singapore at 6p.m. on Wednesday Musicians Performances\n\n  subject_terms_3: Performing Arts British Council (Singapore) the 5th September Musicians\n\n  subject_terms_4: 1951\\\\ is stated at the middle. \\\\M.V. Gurusamy - Miruthangam\\\\ is stated at the bottom. \\\n\n  context_1: musical performances\n\n  context_2: Invitation cards\n\n  context_3: Indian music\n",
  "createdDate": "20201125084542",
  "version": 0,
  "latest": false,
  "roles": [],
  "metadata": {
    "accession_no_csv": "2016-00069",
    "Image": "",
    "object_work_type": "invitations",
    "title_text": "Invitation to music performance at  British Council Hall, Singapore",
    "preference": "main",
    "title_language": "",
    "creator_2": "Unknown",
    "creation_date": "5-Sep-51",
    "creation_place_original_location": "Singapore",
    "styles_periods_indexing_terms": "Not indicated",
    "inscriptions": "",
    "inscription_language": "",
    "scale_type": "Not indicated",
    "shape": "rectangular",
    "materials_name": "printing paper",
    "techniques_name": "printing (process)",
    "object_colour": "multicoloured",
    "physical_appearance": "\"The image shows an invitation card. It is rectangular in shape. It has a yellow background. The \"\"British Council Hall",
    "subject_terms_1": "musicians Stamford Road",
    "subject_terms_2": "British Council (Singapore) Singapore at 6p.m. on Wednesday Musicians Performances",
    "subject_terms_3": "Performing Arts British Council (Singapore) the 5th September Musicians",
    "subject_terms_4": "1951\"\" is stated at the middle. \"\"M.V. Gurusamy - Miruthangam\"\" is stated at the bottom. \"",
    "context_1": "musical performances",
    "context_2": "Invitation cards",
    "context_3": "Indian music"
  },
  "nlpDate": "20201125084542",
  "connectorId": 0,
  "tags": {}
}