{"id":"2016-00619","title":"Wedding certificate of Sadaram and Shanmuga Vadivu","source":"Bumblebee","path":"./Data/json/","content":"accession_no_csv:2016-00619\nImage:\nobject_work_type:marriage certificates\ntitle_text:Wedding certificate of Sadaram and Shanmuga Vadivu\npreference:main\ntitle_language:\ncreator_2:Dravidian Association\n Singapore (translated from Tamil script)\ncreator_role:creators\ncreation_date:1953\ncreation_place_original_location:Singapore\ninscriptions:\ninscription_language:\nshape:rectangular\nmaterials_name:paper (fiber product)\ntechniques_name:printing (process) handwriting\nobject_colour:multicoloured\nphysical_appearance:\\The image displays a wedding certificate. The Tamil scripts are printed in blue and black ink and handwritten in this certificate. At the top of the certificate\n a logo of a flag along with the Tamil script denoting the Dravidian Association Singapore is displayed. The date \\\\1953\\\\ is handwritten near the bottom of the certificate. There is a border which separates the Tamil scripts from the outer perimeter of the certificate.\\\nsubject_terms_1:marriage (social construct) certification legal documents\nsubject_terms_2:Marriage Certification Legal documents Special events\nsgcool_label_text:Mr. S Gopalakrishnan (b. in 1920 in Tanjavur) was a prominent violinist\n and Carnatic singer. He arrived in Singapore in 1939 and actively participated in the Indian classical music scene here. Mr Gopalakrishnan performed alongside veterans of classical performers such as Pandit M Ramalingam and MV Gurusamy at temple and other music festivals. He also taught violin lessons at the Singapore Malayalee Association from the 1970s to 2000s. He was a member of the Tamils Reform Association and performed his wedding according to the principles of the Self-Respect Movement. He was also employed as a compositor at the Far East Air Force from 1954 to 1970.","createdDate":"20201119143405","version":0,"latest":false,"roles":[],"metadata":{"accession_no_csv":"2016-00619","Image":"","object_work_type":"marriage certificates","title_text":"Wedding certificate of Sadaram and Shanmuga Vadivu","preference":"main","title_language":"","creator_2":"Dravidian Association, Singapore (translated from Tamil script)","creator_role":"creators","creation_date":"1953","creation_place_original_location":"Singapore","inscriptions":"","inscription_language":"","shape":"rectangular","materials_name":"paper (fiber product)","techniques_name":"printing (process) handwriting","object_colour":"multicoloured","physical_appearance":"\"The image displays a wedding certificate. The Tamil scripts are printed in blue and black ink and handwritten in this certificate. At the top of the certificate, a logo of a flag along with the Tamil script denoting the Dravidian Association Singapore is displayed. The date \"\"1953\"\" is handwritten near the bottom of the certificate. There is a border which separates the Tamil scripts from the outer perimeter of the certificate.\"","subject_terms_1":"marriage (social construct) certification legal documents","subject_terms_2":"Marriage Certification Legal documents Special events","sgcool_label_text":"Mr. S Gopalakrishnan (b. in 1920 in Tanjavur) was a prominent violinist, and Carnatic singer. He arrived in Singapore in 1939 and actively participated in the Indian classical music scene here. Mr Gopalakrishnan performed alongside veterans of classical performers such as Pandit M Ramalingam and MV Gurusamy at temple and other music festivals. He also taught violin lessons at the Singapore Malayalee Association from the 1970s to 2000s. He was a member of the Tamils Reform Association and performed his wedding according to the principles of the Self-Respect Movement. He was also employed as a compositor at the Far East Air Force from 1954 to 1970."},"nlpDate":"20201119143405","connectorId":0,"tags":{}}