{
  "id": "2016-00413",
  "title": "Jacket with matching skirt Chinese jacket with matching skirt",
  "source": "Bumblebee",
  "path": "./Data/json/",
  "content": "\n  accession_no_csv: 2016-00413\n\n  Image: \n\n  object_work_type: jackets (garments) skirts (garments) womenswear\n\n  title_text: Jacket with matching skirt Chinese jacket with matching skirt\n\n  preference: alternate main\n\n  title_language: \n\n  creation_date: 1920s-1930s\n\n  creation_place_original_location: China Indonesia\n\n  styles_periods_indexing_terms: Chinese (culture or style)\n\n  inscriptions: \n\n  inscription_language: \n\n  scale_type: NA NA\n\n  shape: irregular\n\n  materials_name: silk (textile) beads (pierced objects)\n\n  techniques_name: sewing (needleworking technique)\n\n  object_colour: multicolored\n\n  physical_appearance: This is a Chinese-style jacket with matching skirt. The edges are scalloped-shape\n and are trimmed with bugle beads. The silk fabric is patterned with floral motifs. On the front of the jacket\n there is a flower stalk formed by bugle beads. There are buttons along the decorative lining on the jacket and the skirt.\n\n  subject_terms_1: folk costume flower (motif)\n\n  subject_terms_2: Ethnic costume Skirts Jackets Motifs\n\n  subject_terms_3: Chinese costumes\n\n  sgcool_label_text: This jacket was worn with the matching skirt. The scalloped edges of the jacket and skirt are trimmed with bugle beads\n as are the faux cuffs and medallion details on both garments. Round buttons are here only used for decorative effect. Both jacket and skirt are secured by hooks and press studs. On the front is a flower stalk formed by bugle beads\n echoing the floral pattern of the silk fabric. Garments like these were fashionable in China in the 1920s\n especially among women in their late teens and early twenties.\n",
  "createdDate": "20201120223706",
  "version": 0,
  "latest": false,
  "roles": [],
  "metadata": {
    "accession_no_csv": "2016-00413",
    "Image": "",
    "object_work_type": "jackets (garments) skirts (garments) womenswear",
    "title_text": "Jacket with matching skirt Chinese jacket with matching skirt",
    "preference": "alternate main",
    "title_language": "",
    "creation_date": "1920s-1930s",
    "creation_place_original_location": "China Indonesia",
    "styles_periods_indexing_terms": "Chinese (culture or style)",
    "inscriptions": "",
    "inscription_language": "",
    "scale_type": "NA NA",
    "shape": "irregular",
    "materials_name": "silk (textile) beads (pierced objects)",
    "techniques_name": "sewing (needleworking technique)",
    "object_colour": "multicolored",
    "physical_appearance": "This is a Chinese-style jacket with matching skirt. The edges are scalloped-shape, and are trimmed with bugle beads. The silk fabric is patterned with floral motifs. On the front of the jacket, there is a flower stalk formed by bugle beads. There are buttons along the decorative lining on the jacket and the skirt.",
    "subject_terms_1": "folk costume flower (motif)",
    "subject_terms_2": "Ethnic costume Skirts Jackets Motifs",
    "subject_terms_3": "Chinese costumes",
    "sgcool_label_text": "This jacket was worn with the matching skirt. The scalloped edges of the jacket and skirt are trimmed with bugle beads, as are the faux cuffs and medallion details on both garments. Round buttons are here only used for decorative effect. Both jacket and skirt are secured by hooks and press studs. On the front is a flower stalk formed by bugle beads, echoing the floral pattern of the silk fabric. Garments like these were fashionable in China in the 1920s, especially among women in their late teens and early twenties."
  },
  "nlpDate": "20201120223706",
  "connectorId": 0,
  "tags": {}
}