{"id":"2016-00119","title":"Chinese junk at anchor","source":"Bumblebee","path":"./Data/json/","content":"accession_no_csv:2016-00119\nImage:\nobject_work_type:oil paintings (visual works)\ntitle_text:Chinese junk at anchor\npreference:main\ntitle_language:\ncreator_1:???? (Ye-Chung Studio)\ncreator_role:creator\ncreation_date:19th century\ncreation_place_original_location:Hong Kong (China)\ninscriptions:\ninscription_language:\nshape:rectangular\nmaterials_name:oil paint (paint) canvas (textile material)\ntechniques_name:oil painting (technique)\nobject_colour:multicolored\nphysical_appearance:This painting shows a ship at anchor. On the stern of the ship\n there is an image of a large bird with the sun. There is another ship on the background on the left. On the right of the painting there is a structure on land. On the foreground of the image there are two boats with men rowing.\nsubject_terms_1:junks (vessels) harbors seaports Chinese (culture or style) trade (function)\nsubject_terms_2:Painting Junks Harbors China trade painting\nsubject_terms_3:Oil painting Harbours Ports\nsgcool_label_text:This painting shows a Chinese junk at anchor\n probably outside a trading port in China\n perhaps Canton. The ships were used for trade with Southeast Asia and other areas\n transporting rattan\n bamboo\n tea\n tin\n lead\n sago\n salt\n porcelain\n and other goods. The large bird near the sun on the stern is likely the mythical phoenix (feng huang). At right is a structure on land\n possibly a fort. \\r\\n\\r\\nProduced largely for visiting tourists and foreign traders\n these works were known as China trade paintings\n and were popular in the 18th and 19th centuries. They were produced by local and foreign artists\n working in a Western style\n to appeal to the market.","createdDate":"20201119143405","version":0,"latest":false,"roles":[],"metadata":{"accession_no_csv":"2016-00119","Image":"","object_work_type":"oil paintings (visual works)","title_text":"Chinese junk at anchor","preference":"main","title_language":"","creator_1":"???? (Ye-Chung Studio)","creator_role":"creator","creation_date":"19th century","creation_place_original_location":"Hong Kong (China)","inscriptions":"","inscription_language":"","shape":"rectangular","materials_name":"oil paint (paint) canvas (textile material)","techniques_name":"oil painting (technique)","object_colour":"multicolored","physical_appearance":"This painting shows a ship at anchor. On the stern of the ship, there is an image of a large bird with the sun. There is another ship on the background on the left. On the right of the painting there is a structure on land. On the foreground of the image there are two boats with men rowing.","subject_terms_1":"junks (vessels) harbors seaports Chinese (culture or style) trade (function)","subject_terms_2":"Painting Junks Harbors China trade painting","subject_terms_3":"Oil painting Harbours Ports","sgcool_label_text":"This painting shows a Chinese junk at anchor, probably outside a trading port in China, perhaps Canton. The ships were used for trade with Southeast Asia and other areas, transporting rattan, bamboo, tea, tin, lead, sago, salt, porcelain, and other goods. The large bird near the sun on the stern is likely the mythical phoenix (feng huang). At right is a structure on land, possibly a fort. \r\n\r\nProduced largely for visiting tourists and foreign traders, these works were known as China trade paintings, and were popular in the 18th and 19th centuries. They were produced by local and foreign artists, working in a Western style, to appeal to the market."},"nlpDate":"20201119143405","connectorId":0,"tags":{}}