{
  "id": "2016-00498",
  "title": "Untitled (locomotive)",
  "source": "Bumblebee",
  "path": "./Data/json/",
  "content": "\n  accession_no_csv: 2016-00498\n\n  Image: \n\n  object_work_type: colour photographs\n\n  title_text: Untitled (locomotive)\n\n  preference: main\n\n  title_language: \n\n  creator_2: Kwek Leng Joo\n\n  creator_1: Kwek\n Leng Joo\n\n  creator_role: photographers\n\n  creation_date: 2010\n\n  creation_place_original_location: Malaysia Singapore\n\n  inscriptions: \n\n  inscription_language: \n\n  shape: rectangular\n\n  materials_name: paper (fiber product)\n\n  techniques_name: printing (process)\n\n  object_colour: multicoloured\n\n  physical_appearance: The image shows a photograph with colour. It has a black frame and its border is white in colour. A set of railroad and a traffic light to the left of the photograph can be seen. The train has more than one carriage attached to it and it has two rows of windows on its side. There are a number of different colours which are only on the body of the locomotive\n while the rest of the photograph is in monochrome. There are colourful images of butterflies and flora that are coloured on the body of the locomotive.\n\n  subject_terms_1: locomotives passenger cars (railroad cars) trains (vehicle groupings) railroads (infrastructures)\n\n  subject_terms_2: Railroads Railroad passenger cars Locomotives Pertadbiran Keretapi Tanah Melayu Railroad trains Photographs\n\n  subject_terms_3: Photography Pertadbiran Keretapi Tanah Melayu Rail transport\n\n  sgcool_label_text: \\This image is part of the \\\\Tracking Memories\\\\ collection by the late Mr Kwek Leng Joo. The collection captures different aspects of the Malayan Railway story in Singapore\n",
  "createdDate": "20201201203309",
  "version": 0,
  "latest": false,
  "roles": [],
  "metadata": {
    "accession_no_csv": "2016-00498",
    "Image": "",
    "object_work_type": "colour photographs",
    "title_text": "Untitled (locomotive)",
    "preference": "main",
    "title_language": "",
    "creator_2": "Kwek Leng Joo",
    "creator_1": "Kwek, Leng Joo",
    "creator_role": "photographers",
    "creation_date": "2010",
    "creation_place_original_location": "Malaysia Singapore",
    "inscriptions": "",
    "inscription_language": "",
    "shape": "rectangular",
    "materials_name": "paper (fiber product)",
    "techniques_name": "printing (process)",
    "object_colour": "multicoloured",
    "physical_appearance": "The image shows a photograph with colour. It has a black frame and its border is white in colour. A set of railroad and a traffic light to the left of the photograph can be seen. The train has more than one carriage attached to it and it has two rows of windows on its side. There are a number of different colours which are only on the body of the locomotive, while the rest of the photograph is in monochrome. There are colourful images of butterflies and flora that are coloured on the body of the locomotive.",
    "subject_terms_1": "locomotives passenger cars (railroad cars) trains (vehicle groupings) railroads (infrastructures)",
    "subject_terms_2": "Railroads Railroad passenger cars Locomotives Pertadbiran Keretapi Tanah Melayu Railroad trains Photographs",
    "subject_terms_3": "Photography Pertadbiran Keretapi Tanah Melayu Rail transport",
    "sgcool_label_text": "\"This image is part of the \"\"Tracking Memories\"\" collection by the late Mr Kwek Leng Joo. The collection captures different aspects of the Malayan Railway story in Singapore"
  },
  "nlpDate": "20201201203309",
  "connectorId": 0,
  "tags": {}
}