{
  "id": "2016-00684",
  "title": "2 Rolls of Lace Rolls of Lace",
  "source": "Bumblebee",
  "path": "./Data/json/",
  "content": "\n  accession_no_csv: 2016-00684\n\n  Image: \n\n  object_work_type: lace (needlework)\n\n  title_text: 2 Rolls of Lace Rolls of Lace\n\n  preference: alternate main\n\n  title_language: \n\n  creation_date: 20th century\n\n  creation_place_original_location: Straits Settlements Indonesia\n\n  styles_periods_indexing_terms: Peranakan\n\n  inscriptions: \n\n  inscription_language: \n\n  shape: irregular\n\n  materials_name: cotton (textile)\n\n  techniques_name: sewing (needleworking technique)\n\n  object_colour: cream (color)\n\n  physical_appearance: These are two rolls of lace. The roll on the left is bound by two gold strings. It has a shop label on top with some written inscriptions. The roll on the right is bound by a strip of paper\n also with some inscriptions. The rolls of lace look old and stained.\n\n  subject_terms_1: Peranakan implements (object genre)\n\n  subject_terms_2: Lace and lace making Peranakan (Asian people) Textiles\n\n  subject_terms_3: Textile art and design\n\n  sgcool_label_text: There are 2 rolls of lace of different design. The making of bobbin lace was an established tradition in port cities like Malacca and Palembang by the early 20th century. It is part of a donation which contains a mixture of materials used in the making of kebayas and baju panjangs.\n",
  "createdDate": "20201120223707",
  "version": 0,
  "latest": false,
  "roles": [],
  "metadata": {
    "accession_no_csv": "2016-00684",
    "Image": "",
    "object_work_type": "lace (needlework)",
    "title_text": "2 Rolls of Lace Rolls of Lace",
    "preference": "alternate main",
    "title_language": "",
    "creation_date": "20th century",
    "creation_place_original_location": "Straits Settlements Indonesia",
    "styles_periods_indexing_terms": "Peranakan",
    "inscriptions": "",
    "inscription_language": "",
    "shape": "irregular",
    "materials_name": "cotton (textile)",
    "techniques_name": "sewing (needleworking technique)",
    "object_colour": "cream (color)",
    "physical_appearance": "These are two rolls of lace. The roll on the left is bound by two gold strings. It has a shop label on top with some written inscriptions. The roll on the right is bound by a strip of paper, also with some inscriptions. The rolls of lace look old and stained.",
    "subject_terms_1": "Peranakan implements (object genre)",
    "subject_terms_2": "Lace and lace making Peranakan (Asian people) Textiles",
    "subject_terms_3": "Textile art and design",
    "sgcool_label_text": "There are 2 rolls of lace of different design. The making of bobbin lace was an established tradition in port cities like Malacca and Palembang by the early 20th century. It is part of a donation which contains a mixture of materials used in the making of kebayas and baju panjangs."
  },
  "nlpDate": "20201120223707",
  "connectorId": 0,
  "tags": {}
}