{"id":"2016-00280","title":"Silver Medal from the collection Jayaram S/o Rengasamy who was part of the winning 4x440 yards athletes at the Singapore Amateur Athletic Association, Farrer Park Silver Medal from the collection Jayaram S/o Rengasamy who was part of the winning 4x440 yards athletes at the Singapore Amateur Athletic Association, Farrer Park","source":"Bumblebee","path":"./Data/json/","content":"accession_no_csv:2016-00280\nImage:\nobject_work_type:medals\ntitle_text:Silver Medal from the collection Jayaram S/o Rengasamy who was part of the winning 4x440 yards athletes at the Singapore Amateur Athletic Association\n Farrer Park Silver Medal from the collection Jayaram S/o Rengasamy who was part of the winning 4x440 yards athletes at the Singapore Amateur Athletic Association\n Farrer Park\npreference:main alternate\ntitle_language:\ncreator_2:F. Phillips Medallists Aldershot\ncreator_1:Not indicated\ncreator_role:manufacturers\ncreation_date:1957\ncreation_place_original_location:Singapore\ninscriptions:\ninscription_language:\nshape:rectangular cuboid circular (shape)\nmaterials_name:paper (fiber product) metal\ntechniques_name:printing (process) metalworking\nobject_colour:multicoloured\nphysical_appearance:\\A silver medal placed in an open case are displayed in the picture. The box is rectangular and light blue in colour. At the centre of the top surface of the case\n it states \\\\F. Phillips Medallist Aldershot\\\\. The padding is light brown in colour and it holds the circular gold medal in place. At the left side of the round medal\nsubject_terms_1:it states \\\\1957 4 x 440 Relay 1st\\\\.\\ athletes competitions (events) cases (containers) prizes honours\nsubject_terms_2:sportsmen Athletes Containers Awards\nsubject_terms_3:Medals Athletics Runners (Athletes) Sports and recreational events Singapore Amateur Athletic Association\nsubject_terms_4:Rengasamy Jayaram","createdDate":"20201119143405","version":0,"latest":false,"roles":[],"metadata":{"accession_no_csv":"2016-00280","Image":"","object_work_type":"medals","title_text":"Silver Medal from the collection Jayaram S/o Rengasamy who was part of the winning 4x440 yards athletes at the Singapore Amateur Athletic Association, Farrer Park Silver Medal from the collection Jayaram S/o Rengasamy who was part of the winning 4x440 yards athletes at the Singapore Amateur Athletic Association, Farrer Park","preference":"main alternate","title_language":"","creator_2":"F. Phillips Medallists Aldershot","creator_1":"Not indicated","creator_role":"manufacturers","creation_date":"1957","creation_place_original_location":"Singapore","inscriptions":"","inscription_language":"","shape":"rectangular cuboid circular (shape)","materials_name":"paper (fiber product) metal","techniques_name":"printing (process) metalworking","object_colour":"multicoloured","physical_appearance":"\"A silver medal placed in an open case are displayed in the picture. The box is rectangular and light blue in colour. At the centre of the top surface of the case, it states \"\"F. Phillips Medallist Aldershot\"\". The padding is light brown in colour and it holds the circular gold medal in place. At the left side of the round medal","subject_terms_1":"it states \"\"1957 4 x 440 Relay 1st\"\".\" athletes competitions (events) cases (containers) prizes honours","subject_terms_2":"sportsmen Athletes Containers Awards","subject_terms_3":"Medals Athletics Runners (Athletes) Sports and recreational events Singapore Amateur Athletic Association","subject_terms_4":"Rengasamy Jayaram"},"nlpDate":"20201119143405","connectorId":0,"tags":{}}