{
  "id": "2016-00212-022",
  "title": "Photograph album of views and portraits in the Punjab, Cashmere, Ceylon, Burma, Penang, Singapore, and Java Tsoont Kol, Apple Tree Canal, Kashmir",
  "source": "Bumblebee",
  "path": "./Data/json/",
  "content": "\n  accession_no_csv: 2016-00212-022\n\n  Image: \n\n  object_work_type: black-and-white photographs\n\n  title_text: Photograph album of views and portraits in the Punjab\n Cashmere\n Ceylon\n Burma\n Penang\n Singapore\n and Java Tsoont Kol\n Apple Tree Canal\n Kashmir\n\n  preference: alternate main\n\n  title_language: \n\n  creator_2: John Thomson\n\n  creator_1: Thomson\n J. (John)\n 1837-1921\n\n  creator_role: photographers\n\n  creation_date: before 28 Jul 1876\n\n  creation_place_original_location: Singapore Kashmir (India)\n\n  inscriptions: \n\n  inscription_language: \n\n  shape: rectangular\n\n  materials_name: albumen (egg white protein) albumen paper paper (fiber product)\n\n  techniques_name: albumen process\n\n  object_colour: black-and-white (colors)\n\n  physical_appearance: This is a photograph of the Tsoont Kol or Apple Tree Canal in Kashmir. The photograph features a large canal in the middle. On the left\n in the forefront\n there is a small boatwith a man. On the right of the photograph in the background\n there is a building by the bank\n with another small boat in front of it. The title is written at the bottom\n below the photograph.\n\n  subject_terms_1: scenery (landscape) canals (waterways)\n\n  subject_terms_2: Photographs Thomson\n J. (John)\n 1837-1921 Kashmir (India) Canals\n\n  subject_terms_3: Landscape photography\n",
  "createdDate": "20201120223706",
  "version": 0,
  "latest": false,
  "roles": [],
  "metadata": {
    "accession_no_csv": "2016-00212-022",
    "Image": "",
    "object_work_type": "black-and-white photographs",
    "title_text": "Photograph album of views and portraits in the Punjab, Cashmere, Ceylon, Burma, Penang, Singapore, and Java Tsoont Kol, Apple Tree Canal, Kashmir",
    "preference": "alternate main",
    "title_language": "",
    "creator_2": "John Thomson",
    "creator_1": "Thomson, J. (John), 1837-1921",
    "creator_role": "photographers",
    "creation_date": "before 28 Jul 1876",
    "creation_place_original_location": "Singapore Kashmir (India)",
    "inscriptions": "",
    "inscription_language": "",
    "shape": "rectangular",
    "materials_name": "albumen (egg white protein) albumen paper paper (fiber product)",
    "techniques_name": "albumen process",
    "object_colour": "black-and-white (colors)",
    "physical_appearance": "This is a photograph of the Tsoont Kol or Apple Tree Canal in Kashmir. The photograph features a large canal in the middle. On the left, in the forefront, there is a small boatwith a man. On the right of the photograph in the background, there is a building by the bank, with another small boat in front of it. The title is written at the bottom, below the photograph.",
    "subject_terms_1": "scenery (landscape) canals (waterways)",
    "subject_terms_2": "Photographs Thomson, J. (John), 1837-1921 Kashmir (India) Canals",
    "subject_terms_3": "Landscape photography"
  },
  "nlpDate": "20201120223706",
  "connectorId": 0,
  "tags": {}
}