{"id":"2016-00724","title":"A Group of 4 Laces Four lace strips","source":"Bumblebee","path":"./Data/json/","content":"accession_no_csv:2016-00724\nImage:\nobject_work_type:lace (needlework)\ntitle_text:A Group of 4 Laces Four lace strips\npreference:alternate main\ntitle_language:\ncreation_date:20th century\ncreation_place_original_location:Straits Settlements Indonesia France\ninscriptions:\ninscription_language:\nshape:irregular\nmaterials_name:cotton (textile)\ntechniques_name:sewing (needleworking technique)\nobject_colour:white (color)\nphysical_appearance:This is a set of four lace strips. They are of varying lengths and design. They feature a repeated scrolling pattern.\nsubject_terms_1:scrolls (motifs) flower (motif) trimming (material) exports\nsubject_terms_2:Bobbin lace Motifs Exports\nsubject_terms_3:Textile art and design\nsgcool_label_text:There are 4 strips of lace of varying lengths and design. The making of bobbin lace was an established tradition in port cities like Malacca and Palembang by the early 20th century. It is part of a donation which contains a mixture of materials used in the making of kebayas and baju panjangs.","createdDate":"20201119143406","version":0,"latest":false,"roles":[],"metadata":{"accession_no_csv":"2016-00724","Image":"","object_work_type":"lace (needlework)","title_text":"A Group of 4 Laces Four lace strips","preference":"alternate main","title_language":"","creation_date":"20th century","creation_place_original_location":"Straits Settlements Indonesia France","inscriptions":"","inscription_language":"","shape":"irregular","materials_name":"cotton (textile)","techniques_name":"sewing (needleworking technique)","object_colour":"white (color)","physical_appearance":"This is a set of four lace strips. They are of varying lengths and design. They feature a repeated scrolling pattern.","subject_terms_1":"scrolls (motifs) flower (motif) trimming (material) exports","subject_terms_2":"Bobbin lace Motifs Exports","subject_terms_3":"Textile art and design","sgcool_label_text":"There are 4 strips of lace of varying lengths and design. The making of bobbin lace was an established tradition in port cities like Malacca and Palembang by the early 20th century. It is part of a donation which contains a mixture of materials used in the making of kebayas and baju panjangs."},"nlpDate":"20201119143406","connectorId":0,"tags":{}}