{
  "id": "2016-00576",
  "title": "WWII British Army bayonet frog",
  "source": "Bumblebee",
  "path": "./Data/json/",
  "content": "\n  accession_no_csv: 2016-00576\n\n  Image: \n\n  object_work_type: sheaths (cases) fasteners\n\n  title_text: WWII British Army bayonet frog\n\n  preference: main\n\n  title_language: \n\n  creation_date: 1942 - 1945\n\n  creation_place_original_location: Malaya Singapore\n\n  inscriptions: \n\n  inscription_language: \n\n  shape: rectangular\n\n  materials_name: cloth\n\n  techniques_name: sewing (needleworking technique)\n\n  object_colour: khaki (colour)\n\n  physical_appearance: A Second World War bayonet frog used by the British army is displayed. It is khaki in colour. At the right hand side of the middle of the image\n a button is visible on the sheath. There is a slight tear on the bayonet frog. The stitching on the sheath can be seen running around its perimeter\n as well as towards the middle.\n\n  subject_terms_1: equipment soldiers world wars bayonets\n\n  subject_terms_2: World War\n 1939 - 1945 Great Britain. Army Bayonets Scabbards\n\n  subject_terms_3: Wars\n\n  subject_terms_4: \n\n  context_1: World War\n 1939 - 1945\n\n  context_2: world wars\n\n  context_3: 1939 - 1945\n\n  context_4: 1939\n\n  context_5: 1945\n\n  context_6: Southeast Asia\n\n  context_7: Great Britain. Army\n\n  sgcool_label_text: This was standard issue of the British Army during WWII\n which soldiers carried to sheath their bayonets.\n",
  "createdDate": "20201120223707",
  "version": 0,
  "latest": false,
  "roles": [],
  "metadata": {
    "accession_no_csv": "2016-00576",
    "Image": "",
    "object_work_type": "sheaths (cases) fasteners",
    "title_text": "WWII British Army bayonet frog",
    "preference": "main",
    "title_language": "",
    "creation_date": "1942 - 1945",
    "creation_place_original_location": "Malaya Singapore",
    "inscriptions": "",
    "inscription_language": "",
    "shape": "rectangular",
    "materials_name": "cloth",
    "techniques_name": "sewing (needleworking technique)",
    "object_colour": "khaki (colour)",
    "physical_appearance": "A Second World War bayonet frog used by the British army is displayed. It is khaki in colour. At the right hand side of the middle of the image, a button is visible on the sheath. There is a slight tear on the bayonet frog. The stitching on the sheath can be seen running around its perimeter, as well as towards the middle.",
    "subject_terms_1": "equipment soldiers world wars bayonets",
    "subject_terms_2": "World War, 1939 - 1945 Great Britain. Army Bayonets Scabbards",
    "subject_terms_3": "Wars",
    "subject_terms_4": "",
    "context_1": "World War, 1939 - 1945",
    "context_2": "world wars",
    "context_3": "1939 - 1945",
    "context_4": "1939",
    "context_5": "1945",
    "context_6": "Southeast Asia",
    "context_7": "Great Britain. Army",
    "sgcool_label_text": "This was standard issue of the British Army during WWII, which soldiers carried to sheath their bayonets."
  },
  "nlpDate": "20201120223707",
  "connectorId": 0,
  "tags": {}
}