{"id":"2016-00075","title":"Envelope of Madura MV Gurusamy","source":"Bumblebee","path":"./Data/json/","content":"accession_no_csv:2016-00075\nImage:\nobject_work_type:envelopes\ntitle_text:Envelope of Madura MV Gurusamy\npreference:main\ntitle_language:\ncreator_2:Unknown\ncreation_date:20th century\ncreation_place_original_location:Singapore\nstyles_periods_indexing_terms:Not indicated\ninscriptions:\ninscription_language:\nscale_type:Not indicated\nshape:rectangular\nmaterials_name:printing paper\ntechniques_name:printing (process)\nobject_colour:grey (colour)\nphysical_appearance:\\The image shows an envelope. It is rectangular in shape and it has a grey background. \\\\Madura M.V. Gurusamy\nsubject_terms_1:14 Rappa Terrace\\\\ is stated at the top of the envelope. \\\\Mirudangist\\\\ is stated at the left hand side of the envelope. The image of a man is also displayed on the envelope. He is dressed in a white long sleeved shirt and white pants. A mridangam is placed on his lap. \\ instrumentalists\nsubject_terms_2:musicians Musicians Instrumentalists Mridanga\nsubject_terms_3:Envelopes (Stationery) Performing Arts Musicians\nsubject_terms_4:Indian music","createdDate":"20201119143405","version":0,"latest":false,"roles":[],"metadata":{"accession_no_csv":"2016-00075","Image":"","object_work_type":"envelopes","title_text":"Envelope of Madura MV Gurusamy","preference":"main","title_language":"","creator_2":"Unknown","creation_date":"20th century","creation_place_original_location":"Singapore","styles_periods_indexing_terms":"Not indicated","inscriptions":"","inscription_language":"","scale_type":"Not indicated","shape":"rectangular","materials_name":"printing paper","techniques_name":"printing (process)","object_colour":"grey (colour)","physical_appearance":"\"The image shows an envelope. It is rectangular in shape and it has a grey background. \"\"Madura M.V. Gurusamy","subject_terms_1":"14 Rappa Terrace\"\" is stated at the top of the envelope. \"\"Mirudangist\"\" is stated at the left hand side of the envelope. The image of a man is also displayed on the envelope. He is dressed in a white long sleeved shirt and white pants. A mridangam is placed on his lap. \" instrumentalists","subject_terms_2":"musicians Musicians Instrumentalists Mridanga","subject_terms_3":"Envelopes (Stationery) Performing Arts Musicians","subject_terms_4":"Indian music"},"nlpDate":"20201119143405","connectorId":0,"tags":{}}