{"id":"2016-00359","title":"“Your Passport to the Home ‘N’ Hearts of Tamils in Singapore”, Tamil Murasu","source":"Bumblebee","path":"./Data/json/","content":"accession_no_csv:2016-00359\nImage:\nobject_work_type:folders (containers)\ntitle_text:“Your Passport to the Home ‘N’ Hearts of Tamils in Singapore”\n Tamil Murasu\npreference:main\ntitle_language:\ncreation_date:1940 - 1969\ncreation_place_original_location:Singapore\ninscriptions:\ninscription_language:\nshape:rectangular\nmaterials_name:paper (fiber product)\ntechniques_name:printing (process)\nobject_colour:red (colour)\nphysical_appearance:\\The image shows a rectangular folder. It is light red in colour. On the surface of the folder\n \\\\Your Passport to the Homes \\u0027N\\u0027 Hearts of Tamils in Singapore\\\\ are displayed in gold letterings. The numbers \\\\012345\\\\ is displayed on the first page inside the folder\nsubject_terms_1:which is seen near the top. The words \\\\Tamil Murasu\\\\ is displayed on the first page inside the folder documents (object genre) personalia\nsubject_terms_2:which is seen near the bottom. The document folder looks slightly weathered Letters Personal archives Containers\nsubject_terms_3:with stains on its sides.\\\nsubject_terms_4:newspapers\ncontext_1:Newspapers\ncontext_2:Daily newspapers","createdDate":"20201119143405","version":0,"latest":false,"roles":[],"metadata":{"accession_no_csv":"2016-00359","Image":"","object_work_type":"folders (containers)","title_text":"“Your Passport to the Home ‘N’ Hearts of Tamils in Singapore”, Tamil Murasu","preference":"main","title_language":"","creation_date":"1940 - 1969","creation_place_original_location":"Singapore","inscriptions":"","inscription_language":"","shape":"rectangular","materials_name":"paper (fiber product)","techniques_name":"printing (process)","object_colour":"red (colour)","physical_appearance":"\"The image shows a rectangular folder. It is light red in colour. On the surface of the folder, \"\"Your Passport to the Homes \u0027N\u0027 Hearts of Tamils in Singapore\"\" are displayed in gold letterings. The numbers \"\"012345\"\" is displayed on the first page inside the folder","subject_terms_1":"which is seen near the top. The words \"\"Tamil Murasu\"\" is displayed on the first page inside the folder documents (object genre) personalia","subject_terms_2":"which is seen near the bottom. The document folder looks slightly weathered Letters Personal archives Containers","subject_terms_3":"with stains on its sides.\"","subject_terms_4":"newspapers","context_1":"Newspapers","context_2":"Daily newspapers"},"nlpDate":"20201119143405","connectorId":0,"tags":{}}