{"id":"2016-00209","title":"Candelabra Qing dynasty candleholder","source":"Bumblebee","path":"./Data/json/","content":"accession_no_csv:2016-00209\nImage:\nobject_work_type:candelabras (candleholders)\ntitle_text:Candelabra Qing dynasty candleholder\npreference:alternate main\ntitle_language:\ncreation_date:1736-1795\ncreation_place_original_location:China\nstyles_periods_indexing_terms:Qianlong (Chinese dynastic style)\ninscriptions:\ninscription_language:\nshape:irregular\nmaterials_name:copper (material) enamel paint\ntechniques_name:welding painting (image-making)\nobject_colour:multicolored\nphysical_appearance:This is a branched candleholder\n decorated with bright enamel paint. The stem supports five candleholders\n with the middle candleholder higher than the rest. The candleholders are shaped like lotuses. There are floral motifs around the base of the candleholder and around the stem. There are no chips seen.\nsubject_terms_1:lotus (motif) flower (motif) exports\nsubject_terms_2:Candelabra Qianlong\n Emperor of China\n 1711-1799 Enamel and enameling China History Ming-Qing dynasties\n 1368-1912 Motifs Exports\nsubject_terms_3:Chinese decorative arts\nsgcool_label_text:This branched holder for candles (called a candelabrum or candelabra) is decorated with bright enamels. The double-baluster stem supports five candleholders shaped like lotuses. Candelabra were made for dining tables in Europe and America. However\n much of the design and decoration of this object is distinctly Chinese.\\r\\n\\r\\nThe form of this candelabra was made in copper\n which was then coated with pigments containing ground glass. The object was then fired to create a bright glassy coating. In the 18th century\n this type was production for foreign export in Guangzhou (Canton)\n with the result that the type is often called Canton enamel.","createdDate":"20201119143405","version":0,"latest":false,"roles":[],"metadata":{"accession_no_csv":"2016-00209","Image":"","object_work_type":"candelabras (candleholders)","title_text":"Candelabra Qing dynasty candleholder","preference":"alternate main","title_language":"","creation_date":"1736-1795","creation_place_original_location":"China","styles_periods_indexing_terms":"Qianlong (Chinese dynastic style)","inscriptions":"","inscription_language":"","shape":"irregular","materials_name":"copper (material) enamel paint","techniques_name":"welding painting (image-making)","object_colour":"multicolored","physical_appearance":"This is a branched candleholder, decorated with bright enamel paint. The stem supports five candleholders, with the middle candleholder higher than the rest. The candleholders are shaped like lotuses. There are floral motifs around the base of the candleholder and around the stem. There are no chips seen.","subject_terms_1":"lotus (motif) flower (motif) exports","subject_terms_2":"Candelabra Qianlong, Emperor of China, 1711-1799 Enamel and enameling China History Ming-Qing dynasties, 1368-1912 Motifs Exports","subject_terms_3":"Chinese decorative arts","sgcool_label_text":"This branched holder for candles (called a candelabrum or candelabra) is decorated with bright enamels. The double-baluster stem supports five candleholders shaped like lotuses. Candelabra were made for dining tables in Europe and America. However, much of the design and decoration of this object is distinctly Chinese.\r\n\r\nThe form of this candelabra was made in copper, which was then coated with pigments containing ground glass. The object was then fired to create a bright glassy coating. In the 18th century, this type was production for foreign export in Guangzhou (Canton), with the result that the type is often called Canton enamel."},"nlpDate":"20201119143405","connectorId":0,"tags":{}}