{
  "id": "2016-00110",
  "title": "Testimonial letter about Mr Appavoo Kandiar by United Engineers Limited Testimonial letter given to Mr Appavoo Kandiar by United Engineers Limited",
  "source": "Bumblebee",
  "path": "./Data/json/",
  "content": "\n  accession_no_csv: 2016-00110\n\n  Image: \n\n  object_work_type: testimonials\n\n  title_text: Testimonial letter about Mr Appavoo Kandiar by United Engineers Limited Testimonial letter given to Mr Appavoo Kandiar by United Engineers Limited\n\n  preference: main alternate\n\n  title_language: \n\n  creator_2: Oriental Telephone Company\n\n  creator_role: firms\n\n  creation_date: 19550820\n\n  creation_place_original_location: Singapore\n\n  inscriptions: \n\n  inscription_language: \n\n  shape: rectangular\n\n  materials_name: paper (fiber product)\n\n  techniques_name: printing (process)\n\n  object_colour: multicoloured\n\n  physical_appearance: \\The image shows a rectangular letter. The letter is not addressed to anyone in particular\n and \\\\To Whom It May Concern\\\\ serves as the salutation. At the end of the letter\n\n  subject_terms_1: there is a signature as well as the words \\\\Deputy Chief Lines Engineer\\\\\\ letters of recommendation contractors companies engineers\n\n  subject_terms_2: Contractors Engineers Letters Employment references letters (correspondence)\n\n  subject_terms_3: Business enterprises Letters Kandiar\n Appavoo\n\n  subject_terms_4: Business enterprises\n",
  "createdDate": "20201125084540",
  "version": 0,
  "latest": false,
  "roles": [],
  "metadata": {
    "accession_no_csv": "2016-00110",
    "Image": "",
    "object_work_type": "testimonials",
    "title_text": "Testimonial letter about Mr Appavoo Kandiar by United Engineers Limited Testimonial letter given to Mr Appavoo Kandiar by United Engineers Limited",
    "preference": "main alternate",
    "title_language": "",
    "creator_2": "Oriental Telephone Company",
    "creator_role": "firms",
    "creation_date": "19550820",
    "creation_place_original_location": "Singapore",
    "inscriptions": "",
    "inscription_language": "",
    "shape": "rectangular",
    "materials_name": "paper (fiber product)",
    "techniques_name": "printing (process)",
    "object_colour": "multicoloured",
    "physical_appearance": "\"The image shows a rectangular letter. The letter is not addressed to anyone in particular, and \"\"To Whom It May Concern\"\" serves as the salutation. At the end of the letter",
    "subject_terms_1": "there is a signature as well as the words \"\"Deputy Chief Lines Engineer\"\"\" letters of recommendation contractors companies engineers",
    "subject_terms_2": "Contractors Engineers Letters Employment references letters (correspondence)",
    "subject_terms_3": "Business enterprises Letters Kandiar, Appavoo",
    "subject_terms_4": "Business enterprises"
  },
  "nlpDate": "20201125084540",
  "connectorId": 0,
  "tags": {}
}