{"id":"2016-00658","title":"35mm developing tank","source":"Bumblebee","path":"./Data/json/","content":"accession_no_csv:2016-00658\nImage:\nobject_work_type:developing  tanks\ntitle_text:35mm developing tank\npreference:main\ntitle_language:\ncreation_date:1980s-1990s\ncreation_place_original_location:Singapore\ninscriptions:\ninscription_language:\nshape:irregular\nmaterials_name:Not indicated\ntechniques_name:Not indicated\nobject_colour:multicoloured\nphysical_appearance:The image depicts a the constituents of a developing tank. All the components are black in colour\n except for a red rim on the developing tank container. The lid of the container is separated from its body\n and so is its centre column. There are no visible scratches or marks on the exterior of the components of the developing tank.\nsubject_terms_1:photographic equipment container (receptacles) storage containers\nsubject_terms_2:Photography Equipment and supplies Containers\nsubject_terms_3:Photography\ncontext_20:The set of equipment was used by The Picture Farm Pte Ltd\ncontext_21:45 Jalan Pemimpin\n #09-00 Foo Wah Industrial Building\n Thomson\n Singapore\ncontext_22:1970 - present\ncontext_23:1970\ncontext_24:present\nsgcool_label_text:Such a tank is used to load reels of photographic film just before the development process\n which involves various steps such as the stop bath and the washing of film. This developing tank is part of the darkroom photography equipment that was previously used by The Picture Farm\n which was set up by renowned photographer Willie Tang.","createdDate":"20201119143405","version":0,"latest":false,"roles":[],"metadata":{"accession_no_csv":"2016-00658","Image":"","object_work_type":"developing  tanks","title_text":"35mm developing tank","preference":"main","title_language":"","creation_date":"1980s-1990s","creation_place_original_location":"Singapore","inscriptions":"","inscription_language":"","shape":"irregular","materials_name":"Not indicated","techniques_name":"Not indicated","object_colour":"multicoloured","physical_appearance":"The image depicts a the constituents of a developing tank. All the components are black in colour, except for a red rim on the developing tank container. The lid of the container is separated from its body, and so is its centre column. There are no visible scratches or marks on the exterior of the components of the developing tank.","subject_terms_1":"photographic equipment container (receptacles) storage containers","subject_terms_2":"Photography Equipment and supplies Containers","subject_terms_3":"Photography","context_20":"The set of equipment was used by The Picture Farm Pte Ltd","context_21":"45 Jalan Pemimpin, #09-00 Foo Wah Industrial Building, Thomson, Singapore","context_22":"1970 - present","context_23":"1970","context_24":"present","sgcool_label_text":"Such a tank is used to load reels of photographic film just before the development process, which involves various steps such as the stop bath and the washing of film. This developing tank is part of the darkroom photography equipment that was previously used by The Picture Farm, which was set up by renowned photographer Willie Tang."},"nlpDate":"20201119143405","connectorId":0,"tags":{}}