{"id":"2016-00212-011","title":"Photograph album of views and portraits in the Punjab, Cashmere, Ceylon, Burma, Penang, Singapore, and Java Marble Baradari, Hooseini Bagh, Lahore","source":"Bumblebee","path":"./Data/json/","content":"accession_no_csv:2016-00212-011\nImage:\nobject_work_type:black-and-white photographs\ntitle_text:Photograph album of views and portraits in the Punjab\n Cashmere\n Ceylon\n Burma\n Penang\n Singapore\n and Java Marble Baradari\n Hooseini Bagh\n Lahore\npreference:alternate main\ntitle_language:\ncreator_2:John Thomson\ncreator_1:Thomson\n J. (John)\n 1837-1921\ncreator_role:photographers\ncreation_date:before 28 Jul 1876\ncreation_place_original_location:Singapore Lahore (Pakistan)\nstyles_periods_indexing_terms:Mughal Islamic (culture or style)\ninscriptions:\ninscription_language:\nshape:rectangular\nmaterials_name:albumen (egg white protein) albumen paper paper (fiber product)\ntechniques_name:albumen process\nobject_colour:black-and-white (colors)\nphysical_appearance:This is a photograph of the marble baradari pavillion in Lahore. In the photograph\n there is a clearing with a path leading up to the building. The building is a two-leveled pavillion\n with pillars supporting three arches. There is a fence behind the building. There are no individuals in the photograph. The title is written at the bottom\n below the photograph.\nsubject_terms_1:buildings (structures) pavilions (building divisions) arches\nsubject_terms_2:Photographs Thomson\n J. (John)\n 1837-1921 Lahore (Pakistan) Pavilions Arches Architecture\n Mogul Empire\nsubject_terms_3:Photography Buildings","createdDate":"20201018182635","version":0,"latest":false,"roles":[],"metadata":{"accession_no_csv":"2016-00212-011","Image":"","object_work_type":"black-and-white photographs","title_text":"Photograph album of views and portraits in the Punjab, Cashmere, Ceylon, Burma, Penang, Singapore, and Java Marble Baradari, Hooseini Bagh, Lahore","preference":"alternate main","title_language":"","creator_2":"John Thomson","creator_1":"Thomson, J. (John), 1837-1921","creator_role":"photographers","creation_date":"before 28 Jul 1876","creation_place_original_location":"Singapore Lahore (Pakistan)","styles_periods_indexing_terms":"Mughal Islamic (culture or style)","inscriptions":"","inscription_language":"","shape":"rectangular","materials_name":"albumen (egg white protein) albumen paper paper (fiber product)","techniques_name":"albumen process","object_colour":"black-and-white (colors)","physical_appearance":"This is a photograph of the marble baradari pavillion in Lahore. In the photograph, there is a clearing with a path leading up to the building. The building is a two-leveled pavillion, with pillars supporting three arches. There is a fence behind the building. There are no individuals in the photograph. The title is written at the bottom, below the photograph.","subject_terms_1":"buildings (structures) pavilions (building divisions) arches","subject_terms_2":"Photographs Thomson, J. (John), 1837-1921 Lahore (Pakistan) Pavilions Arches Architecture, Mogul Empire","subject_terms_3":"Photography Buildings"},"nlpDate":"20201018182635","connectorId":0,"tags":{}}