{
  "id": "2016-00520",
  "title": "Malaya Nanban",
  "source": "Bumblebee",
  "path": "./Data/json/",
  "content": "\n  accession_no_csv: 2016-00520\n\n  Image: \n\n  object_work_type: dailies (publications)\n\n  title_text: Malaya Nanban\n\n  preference: main\n\n  title_language: \n\n  creator_2: Karim Ghani\n\n  creator_1: Not indicated\n\n  creator_role: editors (people who revise)\n\n  creation_date: 1950\n\n  creation_place_original_location: Singapore Malaya\n\n  inscriptions: \n\n  inscription_language: \n\n  shape: rectangular\n\n  materials_name: printing paper\n\n  techniques_name: printing (process)\n\n  object_colour: multicoloured\n\n  physical_appearance: \\The image displays the front cover of a newspaper. There is a green border around the perimeter of the newspaper. Tamil inscriptions are present at the upper half of the front page. The date \\\\29-1-1950\\\\ is stated below the headlines. The image of a man in a suit and tie is displayed at the lower half of the page.\\\n\n  subject_terms_1: newspapers\n\n  subject_terms_2: Southeast Asian newspapers Tamil newspapers\n\n  subject_terms_3: Daily newspapers\n\n  sgcool_label_text: Malaya Nanban is a Tamil language daily edited by Karim Ghani.  Ghani who managed the Muslim Publishing House and was editor of the Malay language daily called Dawn.  .\n",
  "createdDate": "20201201203309",
  "version": 0,
  "latest": false,
  "roles": [],
  "metadata": {
    "accession_no_csv": "2016-00520",
    "Image": "",
    "object_work_type": "dailies (publications)",
    "title_text": "Malaya Nanban",
    "preference": "main",
    "title_language": "",
    "creator_2": "Karim Ghani",
    "creator_1": "Not indicated",
    "creator_role": "editors (people who revise)",
    "creation_date": "1950",
    "creation_place_original_location": "Singapore Malaya",
    "inscriptions": "",
    "inscription_language": "",
    "shape": "rectangular",
    "materials_name": "printing paper",
    "techniques_name": "printing (process)",
    "object_colour": "multicoloured",
    "physical_appearance": "\"The image displays the front cover of a newspaper. There is a green border around the perimeter of the newspaper. Tamil inscriptions are present at the upper half of the front page. The date \"\"29-1-1950\"\" is stated below the headlines. The image of a man in a suit and tie is displayed at the lower half of the page.\"",
    "subject_terms_1": "newspapers",
    "subject_terms_2": "Southeast Asian newspapers Tamil newspapers",
    "subject_terms_3": "Daily newspapers",
    "sgcool_label_text": "Malaya Nanban is a Tamil language daily edited by Karim Ghani.  Ghani who managed the Muslim Publishing House and was editor of the Malay language daily called Dawn.  ."
  },
  "nlpDate": "20201201203309",
  "connectorId": 0,
  "tags": {}
}