{
  "id": "2016-00706",
  "title": "Cream Baju Panjang",
  "source": "Bumblebee",
  "path": "./Data/json/",
  "content": "\n  accession_no_csv: 2016-00706\n\n  Image: \n\n  object_work_type: folk costume womenswear\n\n  title_text: Cream Baju Panjang\n\n  preference: main\n\n  title_language: \n\n  creation_date: late 19th - early 20th century\n\n  creation_place_original_location: Pulau Pinang (Malaysia : State)\n\n  styles_periods_indexing_terms: Peranakan\n\n  inscriptions: \n\n  inscription_language: \n\n  shape: irregular\n\n  materials_name: silk (textile)\n\n  techniques_name: sewing (needleworking technique)\n\n  object_colour: cream (color)\n\n  physical_appearance: This is a cream coloured baju panjang. It has embossed floral patterns\n and short sleeves.\n\n  subject_terms_1: flowers (motifs) Peranakan embossed prints tops (garments\n general) blouses (main garments)\n\n  subject_terms_2: Ethnic costume Motifs Peranakan (Asian people) Blouses\n\n  subject_terms_3: Peranakan costumes\n\n  subject_terms_4: Baju Panjang\n\n  sgcool_label_text: The baju panjang is made of silk fabric with embossed floral patterns\n and lined with panels of linen on the inside. In late 19th century Penang \n there was a large selection of materials to choose from for the making of  baju panjang\n including silk\n European cotton and velvet. It is part of a donation which contains a mixture of garments worn by Peranakan men and women.\n",
  "createdDate": "20201120223707",
  "version": 0,
  "latest": false,
  "roles": [],
  "metadata": {
    "accession_no_csv": "2016-00706",
    "Image": "",
    "object_work_type": "folk costume womenswear",
    "title_text": "Cream Baju Panjang",
    "preference": "main",
    "title_language": "",
    "creation_date": "late 19th - early 20th century",
    "creation_place_original_location": "Pulau Pinang (Malaysia : State)",
    "styles_periods_indexing_terms": "Peranakan",
    "inscriptions": "",
    "inscription_language": "",
    "shape": "irregular",
    "materials_name": "silk (textile)",
    "techniques_name": "sewing (needleworking technique)",
    "object_colour": "cream (color)",
    "physical_appearance": "This is a cream coloured baju panjang. It has embossed floral patterns, and short sleeves.",
    "subject_terms_1": "flowers (motifs) Peranakan embossed prints tops (garments, general) blouses (main garments)",
    "subject_terms_2": "Ethnic costume Motifs Peranakan (Asian people) Blouses",
    "subject_terms_3": "Peranakan costumes",
    "subject_terms_4": "Baju Panjang",
    "sgcool_label_text": "The baju panjang is made of silk fabric with embossed floral patterns, and lined with panels of linen on the inside. In late 19th century Penang , there was a large selection of materials to choose from for the making of  baju panjang, including silk, European cotton and velvet. It is part of a donation which contains a mixture of garments worn by Peranakan men and women."
  },
  "nlpDate": "20201120223707",
  "connectorId": 0,
  "tags": {}
}