{
  "id": "2016-00278",
  "title": "Medal issued to Jayaram S/o Rengasamy, runner-up, 440 yards, Singapore Amateur Athletic Association, Farrer Park",
  "source": "Bumblebee",
  "path": "./Data/json/",
  "content": "\n  accession_no_csv: 2016-00278\n\n  Image: \n\n  object_work_type: medals\n\n  title_text: Medal issued to Jayaram S/o Rengasamy\n runner-up\n 440 yards\n Singapore Amateur Athletic Association\n Farrer Park\n\n  preference: main\n\n  title_language: \n\n  creation_date: 1957\n\n  creation_place_original_location: Singapore\n\n  inscriptions: \n\n  inscription_language: \n\n  shape: circular (shape)\n\n  materials_name: metal\n\n  techniques_name: metalworking\n\n  object_colour: brown (colour)\n\n  physical_appearance: \\The image shows a bronze medal. It is circular in shape. At the left side of the round medal\n it states \\\\1957 440 YDS 3\\u0027\\u0027\\\\. The centre of the medal contains a design of three human figures. They are depicted ot be running in the same direction\n\n  subject_terms_1: prizes honours with one being in front of the other.\\ athletes competitions (events) races (events)\n\n  subject_terms_2: Athletes sportsmen Awards Relay racing\n\n  subject_terms_3: Singapore Amateur Athletic Association Medals Sports and recreational events Athletics Runners (Athletes)\n\n  subject_terms_4: Rengasamy Jayaram\n",
  "createdDate": "20201201203309",
  "version": 0,
  "latest": false,
  "roles": [],
  "metadata": {
    "accession_no_csv": "2016-00278",
    "Image": "",
    "object_work_type": "medals",
    "title_text": "Medal issued to Jayaram S/o Rengasamy, runner-up, 440 yards, Singapore Amateur Athletic Association, Farrer Park",
    "preference": "main",
    "title_language": "",
    "creation_date": "1957",
    "creation_place_original_location": "Singapore",
    "inscriptions": "",
    "inscription_language": "",
    "shape": "circular (shape)",
    "materials_name": "metal",
    "techniques_name": "metalworking",
    "object_colour": "brown (colour)",
    "physical_appearance": "\"The image shows a bronze medal. It is circular in shape. At the left side of the round medal, it states \"\"1957 440 YDS 3\u0027\u0027\"\". The centre of the medal contains a design of three human figures. They are depicted ot be running in the same direction",
    "subject_terms_1": "prizes honours with one being in front of the other.\" athletes competitions (events) races (events)",
    "subject_terms_2": "Athletes sportsmen Awards Relay racing",
    "subject_terms_3": "Singapore Amateur Athletic Association Medals Sports and recreational events Athletics Runners (Athletes)",
    "subject_terms_4": "Rengasamy Jayaram"
  },
  "nlpDate": "20201201203309",
  "connectorId": 0,
  "tags": {}
}