{"id":"2016-00251","title":"Tray or pillow cover","source":"Bumblebee","path":"./Data/json/","content":"accession_no_csv:2016-00251\nImage:\nobject_work_type:slipcovers (furniture coverings)\ntitle_text:Tray or pillow cover\npreference:main\ntitle_language:\ncreation_date:Early 20th century\ncreation_place_original_location:Pulau Pinang (Malaysia : State)\ninscriptions:\ninscription_language:\nshape:rectangular\nmaterials_name:thread\ntechniques_name:embroidering\nobject_colour:white (color) blue (color) red (color)\nphysical_appearance:This cover is embroided with red and blue threads to create motif patterns. The border consists of multiple bands of floral and abstract designs. In the center\n there is a hexagonal shape\n decorated with vases of flowers\n peacocks and butterflies.\nsubject_terms_1:drawn thread work birds (motifs) flower (motif) foliage (motif) geometric motifs embroidery (visual works)\nsubject_terms_2:Slip covers Embroidery\n Peranakan Motifs\nsubject_terms_3:Textile art and design\nsgcool_label_text:This textile is probably a tray or pillow cover. An elaborately embroidered red and blue border\n made up of multiple bands of floral and abstract designs\n surrounds a hexagonal field. One recurring motif is a vase of flowers in full bloom. Peacocks perch on its branches\n their feathers spread like a fan. This was produced using the technique known as drawn thread embroidery\n whiich involves the extraction of warp and weft threads from a piece of cloth stretched upon a wooden frame. Not only does drawn thread embroidery demand expertise\n it is also extremely labour intensive. Penang was especially known for the use of this technique in the early 20th century.","createdDate":"20201119143405","version":0,"latest":false,"roles":[],"metadata":{"accession_no_csv":"2016-00251","Image":"","object_work_type":"slipcovers (furniture coverings)","title_text":"Tray or pillow cover","preference":"main","title_language":"","creation_date":"Early 20th century","creation_place_original_location":"Pulau Pinang (Malaysia : State)","inscriptions":"","inscription_language":"","shape":"rectangular","materials_name":"thread","techniques_name":"embroidering","object_colour":"white (color) blue (color) red (color)","physical_appearance":"This cover is embroided with red and blue threads to create motif patterns. The border consists of multiple bands of floral and abstract designs. In the center, there is a hexagonal shape, decorated with vases of flowers, peacocks and butterflies.","subject_terms_1":"drawn thread work birds (motifs) flower (motif) foliage (motif) geometric motifs embroidery (visual works)","subject_terms_2":"Slip covers Embroidery, Peranakan Motifs","subject_terms_3":"Textile art and design","sgcool_label_text":"This textile is probably a tray or pillow cover. An elaborately embroidered red and blue border, made up of multiple bands of floral and abstract designs, surrounds a hexagonal field. One recurring motif is a vase of flowers in full bloom. Peacocks perch on its branches, their feathers spread like a fan. This was produced using the technique known as drawn thread embroidery, whiich involves the extraction of warp and weft threads from a piece of cloth stretched upon a wooden frame. Not only does drawn thread embroidery demand expertise, it is also extremely labour intensive. Penang was especially known for the use of this technique in the early 20th century."},"nlpDate":"20201119143405","connectorId":0,"tags":{}}