{
  "id": "2016-00085",
  "title": "Testimonial presented to MV Gurusamy by the Singapore Indian Association",
  "source": "Bumblebee",
  "path": "./Data/json/",
  "content": "\n  accession_no_csv: 2016-00085\n\n  Image: \n\n  object_work_type: testimonials\n\n  title_text: Testimonial presented to MV Gurusamy by the Singapore Indian Association\n\n  preference: main\n\n  title_language: \n\n  creator_2: Unknown\n\n  creation_date: 1-Nov-80\n\n  creation_place_original_location: Singapore\n\n  styles_periods_indexing_terms: Not indicated\n\n  inscriptions: \n\n  inscription_language: \n\n  scale_type: Not indicated\n\n  shape: rectangular\n\n  materials_name: printing paper\n\n  techniques_name: printing (process)\n\n  object_colour: multicoloured\n\n  physical_appearance: \\The image shows a testimonial. It is rectangular in shape and it has a beige background. There is a blue border with a logo at the top centre. Within the border are all the words. \\\\Singapore Indian Association\n\n  subject_terms_1: religious holidays 69 Balestier Road: Singapore 1232\\\\ is stated at the top. \\\\Deepavali Cultural Nite\\\\ is stated at the middle. \\\\Victoria Theatre on 1st November 1980\\\\ is stated near the bottom. \\ honours cultural events associations\n\n  subject_terms_2: musicians Singapore Indian Association Divali Appreciation of a person’s creative works Musicians\n\n  subject_terms_3: Invitation cards Religious Festivals Victoria Theatre and Concert Hall Singapore Indian Association\n\n  subject_terms_4: Musicians\n",
  "createdDate": "20201201203309",
  "version": 0,
  "latest": false,
  "roles": [],
  "metadata": {
    "accession_no_csv": "2016-00085",
    "Image": "",
    "object_work_type": "testimonials",
    "title_text": "Testimonial presented to MV Gurusamy by the Singapore Indian Association",
    "preference": "main",
    "title_language": "",
    "creator_2": "Unknown",
    "creation_date": "1-Nov-80",
    "creation_place_original_location": "Singapore",
    "styles_periods_indexing_terms": "Not indicated",
    "inscriptions": "",
    "inscription_language": "",
    "scale_type": "Not indicated",
    "shape": "rectangular",
    "materials_name": "printing paper",
    "techniques_name": "printing (process)",
    "object_colour": "multicoloured",
    "physical_appearance": "\"The image shows a testimonial. It is rectangular in shape and it has a beige background. There is a blue border with a logo at the top centre. Within the border are all the words. \"\"Singapore Indian Association",
    "subject_terms_1": "religious holidays 69 Balestier Road: Singapore 1232\"\" is stated at the top. \"\"Deepavali Cultural Nite\"\" is stated at the middle. \"\"Victoria Theatre on 1st November 1980\"\" is stated near the bottom. \" honours cultural events associations",
    "subject_terms_2": "musicians Singapore Indian Association Divali Appreciation of a person’s creative works Musicians",
    "subject_terms_3": "Invitation cards Religious Festivals Victoria Theatre and Concert Hall Singapore Indian Association",
    "subject_terms_4": "Musicians"
  },
  "nlpDate": "20201201203309",
  "connectorId": 0,
  "tags": {}
}