{
  "id": "2016-00568-003",
  "title": "Tiger Oil packaging box Bottle of Tiger Oil with packaging box and photograph of three patrons to Tiger Balm Gardens Tiger Oil packaging box Bottle of Tiger Oil with packaging box and photograph of three patrons to Tiger Balm Gardens",
  "source": "Bumblebee",
  "path": "./Data/json/",
  "content": "\n  accession_no_csv: 2016-00568-003\n\n  Image: \n\n  object_work_type: packaging  packaging\n\n  title_text: Tiger Oil packaging box Bottle of Tiger Oil with packaging box and photograph of three patrons to Tiger Balm Gardens Tiger Oil packaging box Bottle of Tiger Oil with packaging box and photograph of three patrons to Tiger Balm Gardens\n\n  preference: main alternate main alternate\n\n  title_language: \n\n  creator_2: Haw Par Brothers International Ltd Singapore Haw Par Brothers International Ltd Singapore\n\n  creator_1: Haw Par Brothers International Limited (TTE) Haw Par Brothers International Limited (TTE)\n\n  creator_role: companies companies\n\n  creation_date: 1960-1975 Mid 1960s to Early 1970s\n\n  creation_place_original_location: Singapore Singapore\n\n  styles_periods_indexing_terms: NA NA\n\n  inscriptions: \n\n  inscription_language: \n\n  scale_type: NA NA\n\n  shape: rectangular cuboid rectangular cuboid\n\n  materials_name: printing paper printing paper\n\n  techniques_name: colour printing colour printing\n\n  object_colour: multicoloured multicoloured\n\n  edition_description: NA NA\n\n  physical_appearance: \\The image shows a rectangular packaging for an ointment. The Chinese characters for \\\\Tiger Oil\\\\ are stated at the front surface. Also \\The image shows a rectangular packaging for an ointment. The Chinese characters for \\\\Tiger Oil\\\\ are stated at the front surface. Also\n\n  subject_terms_1: \\\\Tiger Trademark brand name objects  \\\\Tiger Trademark brand name objects\n\n  subject_terms_2: Registered Tjap Harimau\\\\ is stated at the front surface alongisde an image of a tiger. The \\u0027formula\\u0027 showing the different percentages of components are displayed on the side surface. \\ Business enterprises Packaging Brand name products  Registered Tjap Harimau\\\\ is stated at the front surface alongisde an image of a tiger. The \\u0027formula\\u0027 showing the different percentages of components are displayed on the side surface. \\ Business enterprises Packaging Brand name products\n\n  subject_terms_3: ointment ointment\n\n  subject_terms_4: Ointments Ointments\n\n  context_1: Business enterprises Business enterprises\n\n  context_2: NA NA\n\n  context_3: NA NA\n\n  context_4: NA NA\n\n  context_5: NA NA\n\n  context_6: NA NA\n\n  context_7: NA NA\n\n  context_8: NA NA\n\n  context_9: NA NA\n\n  context_10: NA NA\n\n  context_11: NA NA\n\n  context_12: NA NA\n\n  context_13: NA NA\n\n  context_14: NA NA\n\n  context_15: NA NA\n\n  context_16: NA NA\n\n  context_17: NA NA\n\n  context_18: NA NA\n\n  context_19: NA NA\n\n  context_20: NA NA\n\n  context_21: NA NA\n\n  context_22: NA NA\n\n  context_23: NA NA\n\n  context_24: NA NA\n\n  sgcool_label_text: NA NA\n",
  "createdDate": "20201120223707",
  "version": 0,
  "latest": false,
  "roles": [],
  "metadata": {
    "accession_no_csv": "2016-00568-003",
    "Image": "",
    "object_work_type": "packaging  packaging",
    "title_text": "Tiger Oil packaging box Bottle of Tiger Oil with packaging box and photograph of three patrons to Tiger Balm Gardens Tiger Oil packaging box Bottle of Tiger Oil with packaging box and photograph of three patrons to Tiger Balm Gardens",
    "preference": "main alternate main alternate",
    "title_language": "",
    "creator_2": "Haw Par Brothers International Ltd Singapore Haw Par Brothers International Ltd Singapore",
    "creator_1": "Haw Par Brothers International Limited (TTE) Haw Par Brothers International Limited (TTE)",
    "creator_role": "companies companies",
    "creation_date": "1960-1975 Mid 1960s to Early 1970s",
    "creation_place_original_location": "Singapore Singapore",
    "styles_periods_indexing_terms": "NA NA",
    "inscriptions": "",
    "inscription_language": "",
    "scale_type": "NA NA",
    "shape": "rectangular cuboid rectangular cuboid",
    "materials_name": "printing paper printing paper",
    "techniques_name": "colour printing colour printing",
    "object_colour": "multicoloured multicoloured",
    "edition_description": "NA NA",
    "physical_appearance": "\"The image shows a rectangular packaging for an ointment. The Chinese characters for \"\"Tiger Oil\"\" are stated at the front surface. Also \"The image shows a rectangular packaging for an ointment. The Chinese characters for \"\"Tiger Oil\"\" are stated at the front surface. Also",
    "subject_terms_1": "\"\"Tiger Trademark brand name objects  \"\"Tiger Trademark brand name objects",
    "subject_terms_2": "Registered Tjap Harimau\"\" is stated at the front surface alongisde an image of a tiger. The \u0027formula\u0027 showing the different percentages of components are displayed on the side surface. \" Business enterprises Packaging Brand name products  Registered Tjap Harimau\"\" is stated at the front surface alongisde an image of a tiger. The \u0027formula\u0027 showing the different percentages of components are displayed on the side surface. \" Business enterprises Packaging Brand name products",
    "subject_terms_3": "ointment ointment",
    "subject_terms_4": "Ointments Ointments",
    "context_1": "Business enterprises Business enterprises",
    "context_2": "NA NA",
    "context_3": "NA NA",
    "context_4": "NA NA",
    "context_5": "NA NA",
    "context_6": "NA NA",
    "context_7": "NA NA",
    "context_8": "NA NA",
    "context_9": "NA NA",
    "context_10": "NA NA",
    "context_11": "NA NA",
    "context_12": "NA NA",
    "context_13": "NA NA",
    "context_14": "NA NA",
    "context_15": "NA NA",
    "context_16": "NA NA",
    "context_17": "NA NA",
    "context_18": "NA NA",
    "context_19": "NA NA",
    "context_20": "NA NA",
    "context_21": "NA NA",
    "context_22": "NA NA",
    "context_23": "NA NA",
    "context_24": "NA NA",
    "sgcool_label_text": "NA NA"
  },
  "nlpDate": "20201120223707",
  "connectorId": 0,
  "tags": {}
}