{"id":"2016-00212-006","title":"Photograph album of views and portraits in the Punjab, Cashmere, Ceylon, Burma, Penang, Singapore, and Java Murree, Punjab","source":"Bumblebee","path":"./Data/json/","content":"accession_no_csv:2016-00212-006\nImage:\nobject_work_type:black-and-white photographs\ntitle_text:Photograph album of views and portraits in the Punjab\n Cashmere\n Ceylon\n Burma\n Penang\n Singapore\n and Java Murree\n Punjab\npreference:alternate main\ntitle_language:\ncreator_2:John Thomson\ncreator_1:Thomson\n J. (John)\n 1837-1921\ncreator_role:photographers\ncreation_date:before 28 Jul 1876\ncreation_place_original_location:Singapore Murree (Pakistan)\ninscriptions:\ninscription_language:\nshape:rectangular\nmaterials_name:albumen (egg white protein) albumen paper paper (fiber product)\ntechniques_name:albumen process\nobject_colour:black-and-white (colors)\nphysical_appearance:This is a photograph of a snowy landscape in Murree\n Punjab. On the left of the photograph\n there is a road along the hill\n bordered by a fence. There is a roof buikding in the center. In the background\n there is a hilly landscape of houses interspersed with trees.\nsubject_terms_1:snow (precipitation) winter scenery (landscape) mountains hill settlements\nsubject_terms_2:Photographs Thomson\n J. (John)\n 1837-1921 Murree (Pakistan) Landscape photography Snow Winter Mountains\nsubject_terms_3:Landscape photography","createdDate":"20201119143405","version":0,"latest":false,"roles":[],"metadata":{"accession_no_csv":"2016-00212-006","Image":"","object_work_type":"black-and-white photographs","title_text":"Photograph album of views and portraits in the Punjab, Cashmere, Ceylon, Burma, Penang, Singapore, and Java Murree, Punjab","preference":"alternate main","title_language":"","creator_2":"John Thomson","creator_1":"Thomson, J. (John), 1837-1921","creator_role":"photographers","creation_date":"before 28 Jul 1876","creation_place_original_location":"Singapore Murree (Pakistan)","inscriptions":"","inscription_language":"","shape":"rectangular","materials_name":"albumen (egg white protein) albumen paper paper (fiber product)","techniques_name":"albumen process","object_colour":"black-and-white (colors)","physical_appearance":"This is a photograph of a snowy landscape in Murree, Punjab. On the left of the photograph, there is a road along the hill, bordered by a fence. There is a roof buikding in the center. In the background, there is a hilly landscape of houses interspersed with trees.","subject_terms_1":"snow (precipitation) winter scenery (landscape) mountains hill settlements","subject_terms_2":"Photographs Thomson, J. (John), 1837-1921 Murree (Pakistan) Landscape photography Snow Winter Mountains","subject_terms_3":"Landscape photography"},"nlpDate":"20201119143405","connectorId":0,"tags":{}}