{
  "id": "2016-00283",
  "title": "Jayaram S/o Rengasamy with members of the Swift Athletic Club at Jalan Besar Stadium",
  "source": "Bumblebee",
  "path": "./Data/json/",
  "content": "\n  accession_no_csv: 2016-00283\n\n  Image: \n\n  object_work_type: black-and-white photographs\n\n  title_text: Jayaram S/o Rengasamy with members of the Swift Athletic Club at Jalan Besar Stadium\n\n  preference: main\n\n  title_language: \n\n  creation_date: 1956\n\n  creation_place_original_location: Singapore\n\n  inscriptions: \n\n  inscription_language: \n\n  shape: rectangular\n\n  materials_name: paper (fiber product)\n\n  techniques_name: printing (process) photographic processes\n\n  object_colour: grey monochrome\n\n  physical_appearance: \\The image shows a photograph that is in black-and-white. A large group of people are facing in the direction where the photograph was captured. Some of them are standing up while others are kneeling down. In this group of people\n there are males\n females\n and some children. At the front of the group\n there are numerous trophies placed on the ground. A man in the centre of the group is holding up a flag pole. The word on the flag states\n \\\\Swift\\\\.\\\n\n  subject_terms_1: trophies (objects) sportsmen stadiums studio portraits clubs (associations) athletes group portraits\n\n  subject_terms_2: Athletic clubs Athletes Portraits\n Group Portrait photography Awards Black-and-white photography Stadiums\n\n  subject_terms_3: Jalan Besar Stadium Athletics Portrait photography Rengasamy Jayaram\n\n  sgcool_label_text: Jayaram s/o Rengasamy was an amateur athlete who competed at the club level in Singapore and Malaya in the 1940s and 50s. He started his sporting career at the age of 14 as a boxer. In 1953\n a friend and fellow athlete\n MS Maniam\n invited Mr Rengasamy to participate in the Tamil’s Festival or Tamilar Thirunnal. He then began training in athletics at Anglo-Chinese School Barker Road\n the grounds of Victoria School off Jalan Besar and at Farrer Park. Mr Rengasamy also started participating in different races as a middle distance runner at the Tamil’s Festival (1954 – 57)\n Singapore Amateur Athletic Association meets (1955 – 57)\n as well as the Merdeka Games\n Kuala Lumpur (1957). He was also a member of Swift Athletics Club.\n",
  "createdDate": "20201125084536",
  "version": 0,
  "latest": false,
  "roles": [],
  "metadata": {
    "accession_no_csv": "2016-00283",
    "Image": "",
    "object_work_type": "black-and-white photographs",
    "title_text": "Jayaram S/o Rengasamy with members of the Swift Athletic Club at Jalan Besar Stadium",
    "preference": "main",
    "title_language": "",
    "creation_date": "1956",
    "creation_place_original_location": "Singapore",
    "inscriptions": "",
    "inscription_language": "",
    "shape": "rectangular",
    "materials_name": "paper (fiber product)",
    "techniques_name": "printing (process) photographic processes",
    "object_colour": "grey monochrome",
    "physical_appearance": "\"The image shows a photograph that is in black-and-white. A large group of people are facing in the direction where the photograph was captured. Some of them are standing up while others are kneeling down. In this group of people, there are males, females, and some children. At the front of the group, there are numerous trophies placed on the ground. A man in the centre of the group is holding up a flag pole. The word on the flag states, \"\"Swift\"\".\"",
    "subject_terms_1": "trophies (objects) sportsmen stadiums studio portraits clubs (associations) athletes group portraits",
    "subject_terms_2": "Athletic clubs Athletes Portraits, Group Portrait photography Awards Black-and-white photography Stadiums",
    "subject_terms_3": "Jalan Besar Stadium Athletics Portrait photography Rengasamy Jayaram",
    "sgcool_label_text": "Jayaram s/o Rengasamy was an amateur athlete who competed at the club level in Singapore and Malaya in the 1940s and 50s. He started his sporting career at the age of 14 as a boxer. In 1953, a friend and fellow athlete, MS Maniam, invited Mr Rengasamy to participate in the Tamil’s Festival or Tamilar Thirunnal. He then began training in athletics at Anglo-Chinese School Barker Road, the grounds of Victoria School off Jalan Besar and at Farrer Park. Mr Rengasamy also started participating in different races as a middle distance runner at the Tamil’s Festival (1954 – 57), Singapore Amateur Athletic Association meets (1955 – 57), as well as the Merdeka Games, Kuala Lumpur (1957). He was also a member of Swift Athletics Club."
  },
  "nlpDate": "20201125084536",
  "connectorId": 0,
  "tags": {}
}