{"id":"2016-00644","title":"Coinafon – Orange Public Phone","source":"Bumblebee","path":"./Data/json/","content":"accession_no_csv:2016-00644\nImage:\nobject_work_type:telephones\ntitle_text:Coinafon – Orange Public Phone\npreference:main\ntitle_language:\ncreator_2:Singapore Telecoms\ncreator_1:Telecommunication Authority of Singapore (LC) Telecommunication Authority of Singapore (TTE)\ncreator_role:manufacturers\ncreation_date:1980s\ncreation_place_original_location:Singapore\nstyles_periods_indexing_terms:Not indicated\ninscriptions:\ninscription_language:\nscale_type:Not indicated\nshape:irregular\nmaterials_name:metal plastic (organic material) wire\ntechniques_name:metalworking forming (physical activity)\nobject_colour:multicoloured\nphysical_appearance:\\The image shows a telephone. It is predominantly orange in colour. The handset is connected to the telephone body through black wires. There is an opening at the top of the telephone body and \\\\10¢\\\\ is displayed beside the opening slot. The number pad of the telephone is also visible and to the left of the image is a series of eight images. The images depict symbols and words for instructions on how to use the telephone.\\\nsubject_terms_1:technology (general associated concept) brand name objects\nsubject_terms_2:Telephone Brand name products Technology\nsgcool_label_text:A common sight in Singapore during the 1970s and 1980s\n this orange public phone was introduced by the Singapore Telephone Board in 1971. Users would have to insert 10 cents to operate the pay phone. The rise of mobile phone technology in the late 1990s led to the decline in usage of such public phone services.","createdDate":"20201018182635","version":0,"latest":false,"roles":[],"metadata":{"accession_no_csv":"2016-00644","Image":"","object_work_type":"telephones","title_text":"Coinafon – Orange Public Phone","preference":"main","title_language":"","creator_2":"Singapore Telecoms","creator_1":"Telecommunication Authority of Singapore (LC) Telecommunication Authority of Singapore (TTE)","creator_role":"manufacturers","creation_date":"1980s","creation_place_original_location":"Singapore","styles_periods_indexing_terms":"Not indicated","inscriptions":"","inscription_language":"","scale_type":"Not indicated","shape":"irregular","materials_name":"metal plastic (organic material) wire","techniques_name":"metalworking forming (physical activity)","object_colour":"multicoloured","physical_appearance":"\"The image shows a telephone. It is predominantly orange in colour. The handset is connected to the telephone body through black wires. There is an opening at the top of the telephone body and \"\"10¢\"\" is displayed beside the opening slot. The number pad of the telephone is also visible and to the left of the image is a series of eight images. The images depict symbols and words for instructions on how to use the telephone.\"","subject_terms_1":"technology (general associated concept) brand name objects","subject_terms_2":"Telephone Brand name products Technology","sgcool_label_text":"A common sight in Singapore during the 1970s and 1980s, this orange public phone was introduced by the Singapore Telephone Board in 1971. Users would have to insert 10 cents to operate the pay phone. The rise of mobile phone technology in the late 1990s led to the decline in usage of such public phone services."},"nlpDate":"20201018182635","connectorId":0,"tags":{}}