{
  "id": "2016-00540",
  "title": "Anti-Littering / Cleaning-up Campaign Pamphlet",
  "source": "Bumblebee",
  "path": "./Data/json/",
  "content": "\n  accession_no_csv: 2016-00540\n\n  Image: \n\n  object_work_type: pamphlets\n\n  title_text: Anti-Littering / Cleaning-up Campaign Pamphlet\n\n  preference: main\n\n  title_language: \n\n  creator_2: City Council of Singapore\n\n  creator_1: City Council (TTE)\n\n  creator_role: creators\n\n  creation_date: 1958\n\n  creation_place_original_location: Singapore\n\n  inscriptions: \n\n  inscription_language: \n\n  shape: rectangular\n\n  materials_name: printing paper\n\n  techniques_name: colour printing\n\n  object_colour: multicoloured\n\n  physical_appearance: The image displays a pamphlet. It is rectangular in shape and Chinese characters are present at the top and bottom half of the pamphlet. There is an image at the centre of the pamphlet\n with a triangular perimeter in blue surrounding it. It shows a silhouette of a rubbish bin that is overflowing with trash.\n\n  subject_terms_1: public health rubbish promotional materials hygiene\n\n  subject_terms_2: Public health Hygiene Informational pamphlets Promotional materials Litter (Trash)\n\n  subject_terms_3: Public health\n\n  sgcool_label_text: This Anti-Littering pamphlet was used what was then termed a “Mass Health Movement” – three campaigns on “Anti-Spitting”\n “Anti-Litter” and “Anti-Pests” organised by the Singapore City Council in 1958.\n",
  "createdDate": "20201125084533",
  "version": 0,
  "latest": false,
  "roles": [],
  "metadata": {
    "accession_no_csv": "2016-00540",
    "Image": "",
    "object_work_type": "pamphlets",
    "title_text": "Anti-Littering / Cleaning-up Campaign Pamphlet",
    "preference": "main",
    "title_language": "",
    "creator_2": "City Council of Singapore",
    "creator_1": "City Council (TTE)",
    "creator_role": "creators",
    "creation_date": "1958",
    "creation_place_original_location": "Singapore",
    "inscriptions": "",
    "inscription_language": "",
    "shape": "rectangular",
    "materials_name": "printing paper",
    "techniques_name": "colour printing",
    "object_colour": "multicoloured",
    "physical_appearance": "The image displays a pamphlet. It is rectangular in shape and Chinese characters are present at the top and bottom half of the pamphlet. There is an image at the centre of the pamphlet, with a triangular perimeter in blue surrounding it. It shows a silhouette of a rubbish bin that is overflowing with trash.",
    "subject_terms_1": "public health rubbish promotional materials hygiene",
    "subject_terms_2": "Public health Hygiene Informational pamphlets Promotional materials Litter (Trash)",
    "subject_terms_3": "Public health",
    "sgcool_label_text": "This Anti-Littering pamphlet was used what was then termed a “Mass Health Movement” – three campaigns on “Anti-Spitting”, “Anti-Litter” and “Anti-Pests” organised by the Singapore City Council in 1958."
  },
  "nlpDate": "20201125084533",
  "connectorId": 0,
  "tags": {}
}