{"id":"2016-00212-008","title":"Photograph album of views and portraits in the Punjab, Cashmere, Ceylon, Burma, Penang, Singapore, and Java L. Berkeley\u0027s House, Lahore","source":"Bumblebee","path":"./Data/json/","content":"accession_no_csv:2016-00212-008\nImage:\nobject_work_type:black-and-white photographs\ntitle_text:Photograph album of views and portraits in the Punjab\n Cashmere\n Ceylon\n Burma\n Penang\n Singapore\n and Java L. Berkeley\\u0027s House\n Lahore\npreference:alternate main\ntitle_language:\ncreator_2:John Thomson\ncreator_1:Thomson\n J. (John)\n 1837-1921\ncreator_role:photographers\ncreation_date:before 28 Jul 1876\ncreation_place_original_location:Singapore Lahore (Pakistan)\ninscriptions:\ninscription_language:\nshape:rectangular\nmaterials_name:albumen (egg white protein) albumen paper paper (fiber product)\ntechniques_name:albumen process\nobject_colour:black-and-white (colors)\nphysical_appearance:This is a photograph of L. Berkeley\\u0027s House in Lahore. There is a building in the middle of the photograph\n located in the middle of a garden with short hedges and a few trees. The front of the building is made of square columns with high pointed-arched spaces in between. There is a road that cuts across the yard to the building. In front of the building\n there is a horse-drawn carriage. There are four people in the photograph. The title is written at the bottom\n below the photograph.\nsubject_terms_1:buildings (structures) carriages (vehicles) columns (architectural elements colonization\nsubject_terms_2:Photographs Thomson\n J. (John)\n 1837-1921 Lahore (Pakistan) Government buildings Columns Colonization\nsubject_terms_3:Photography Buildings","createdDate":"20201018182635","version":0,"latest":false,"roles":[],"metadata":{"accession_no_csv":"2016-00212-008","Image":"","object_work_type":"black-and-white photographs","title_text":"Photograph album of views and portraits in the Punjab, Cashmere, Ceylon, Burma, Penang, Singapore, and Java L. Berkeley\u0027s House, Lahore","preference":"alternate main","title_language":"","creator_2":"John Thomson","creator_1":"Thomson, J. (John), 1837-1921","creator_role":"photographers","creation_date":"before 28 Jul 1876","creation_place_original_location":"Singapore Lahore (Pakistan)","inscriptions":"","inscription_language":"","shape":"rectangular","materials_name":"albumen (egg white protein) albumen paper paper (fiber product)","techniques_name":"albumen process","object_colour":"black-and-white (colors)","physical_appearance":"This is a photograph of L. Berkeley\u0027s House in Lahore. There is a building in the middle of the photograph, located in the middle of a garden with short hedges and a few trees. The front of the building is made of square columns with high pointed-arched spaces in between. There is a road that cuts across the yard to the building. In front of the building, there is a horse-drawn carriage. There are four people in the photograph. The title is written at the bottom, below the photograph.","subject_terms_1":"buildings (structures) carriages (vehicles) columns (architectural elements colonization","subject_terms_2":"Photographs Thomson, J. (John), 1837-1921 Lahore (Pakistan) Government buildings Columns Colonization","subject_terms_3":"Photography Buildings"},"nlpDate":"20201018182635","connectorId":0,"tags":{}}