{
  "id": "2016-00766",
  "title": "Turtle shaped censer",
  "source": "Bumblebee",
  "path": "./Data/json/",
  "content": "\n  accession_no_csv: 2016-00766\n\n  Image: \n\n  object_work_type: censers\n\n  title_text: Turtle shaped censer\n\n  preference: main\n\n  title_language: \n\n  creation_date: 1900-1920\n\n  creation_place_original_location: Singapore\n\n  inscriptions: \n\n  inscription_language: \n\n  shape: irregular\n\n  materials_name: brass (alloy)\n\n  techniques_name: forging (metal forming)\n\n  object_colour: bronze (color)\n\n  physical_appearance: This is a small censer. It is engraved decoratively with carvings. The lid is depicted as a turtle. There is a small handle on the right of the lid in the shape of a turtle head.\n\n  subject_terms_1: altar components Peranakan religious ceremonies ceremonial objects\n\n  subject_terms_2: Censers Altars Peranakan (Asian people) Rites and ceremonies Ceremonial objects\n\n  subject_terms_3: Religious life and practices\n\n  sgcool_label_text: This small censer is engraved decoratively with carvings which depict the lid as a turtle. In Chinese symbolism\n turtles signify long life and would be an appropriate motif for the ancestral altar. Incense and ashes would be placed within the body of the turtle and a small hole at the top would allow the smoke of incense to escape.\\r\\n\\r\\nThis item is donated by the family of prominent Peranakan\n Ong Sam Leong (b. 1857\n Singapore – d. 7 February 1918\n Singapore). It comes from his ancestral home of Bukit Rose\n formerly at 259 Bukit Timah Road. Ong was a well-known successful businessman who made is money in the mining of phosphate on Christmas island\n which was historically a territory of colonial Singapore.\n",
  "createdDate": "20201120223707",
  "version": 0,
  "latest": false,
  "roles": [],
  "metadata": {
    "accession_no_csv": "2016-00766",
    "Image": "",
    "object_work_type": "censers",
    "title_text": "Turtle shaped censer",
    "preference": "main",
    "title_language": "",
    "creation_date": "1900-1920",
    "creation_place_original_location": "Singapore",
    "inscriptions": "",
    "inscription_language": "",
    "shape": "irregular",
    "materials_name": "brass (alloy)",
    "techniques_name": "forging (metal forming)",
    "object_colour": "bronze (color)",
    "physical_appearance": "This is a small censer. It is engraved decoratively with carvings. The lid is depicted as a turtle. There is a small handle on the right of the lid in the shape of a turtle head.",
    "subject_terms_1": "altar components Peranakan religious ceremonies ceremonial objects",
    "subject_terms_2": "Censers Altars Peranakan (Asian people) Rites and ceremonies Ceremonial objects",
    "subject_terms_3": "Religious life and practices",
    "sgcool_label_text": "This small censer is engraved decoratively with carvings which depict the lid as a turtle. In Chinese symbolism, turtles signify long life and would be an appropriate motif for the ancestral altar. Incense and ashes would be placed within the body of the turtle and a small hole at the top would allow the smoke of incense to escape.\r\n\r\nThis item is donated by the family of prominent Peranakan, Ong Sam Leong (b. 1857, Singapore – d. 7 February 1918, Singapore). It comes from his ancestral home of Bukit Rose, formerly at 259 Bukit Timah Road. Ong was a well-known successful businessman who made is money in the mining of phosphate on Christmas island, which was historically a territory of colonial Singapore."
  },
  "nlpDate": "20201120223707",
  "connectorId": 0,
  "tags": {}
}