{
  "id": "2016-00620",
  "title": "Krishnasamy and Malaiammal (wearing sarong) Krishnasamy and Malaiammal",
  "source": "Bumblebee",
  "path": "./Data/json/",
  "content": "\n  accession_no_csv: 2016-00620\n\n  Image: \n\n  object_work_type: black-and-white photographs\n\n  title_text: Krishnasamy and Malaiammal (wearing sarong) Krishnasamy and Malaiammal\n\n  preference: main alternate\n\n  title_language: \n\n  creation_date: 1945\n\n  creation_place_original_location: Singapore\n\n  inscriptions: \n\n  inscription_language: \n\n  shape: rectangular\n\n  materials_name: paper (fiber product)\n\n  techniques_name: printing (process) photographic processes\n\n  object_colour: grey monochrome\n\n  physical_appearance: The image shows a photograph that is in black-and-white. A man and a woman are featured in the photograph\n from head to toe. The lady is standing on the right hand side and she is wearing a blouse and sarong\n while the man is wearing a short sleeved shirt\n pants\n and covered shoes. Both of them are looking in the direction where the photograph was captured. The background of the photograph suggests that it was taken in the interior of a building\n\n  subject_terms_1: double portraits spouses studio portraits folk costume\n\n  subject_terms_2: Spouses Ethnic costume Portrait photography Black-and-white photography\n\n  subject_terms_3: Portrait photography Ethnic costumes\n\n  sgcool_label_text: Not indicated\n",
  "createdDate": "20201201203308",
  "version": 0,
  "latest": false,
  "roles": [],
  "metadata": {
    "accession_no_csv": "2016-00620",
    "Image": "",
    "object_work_type": "black-and-white photographs",
    "title_text": "Krishnasamy and Malaiammal (wearing sarong) Krishnasamy and Malaiammal",
    "preference": "main alternate",
    "title_language": "",
    "creation_date": "1945",
    "creation_place_original_location": "Singapore",
    "inscriptions": "",
    "inscription_language": "",
    "shape": "rectangular",
    "materials_name": "paper (fiber product)",
    "techniques_name": "printing (process) photographic processes",
    "object_colour": "grey monochrome",
    "physical_appearance": "The image shows a photograph that is in black-and-white. A man and a woman are featured in the photograph, from head to toe. The lady is standing on the right hand side and she is wearing a blouse and sarong, while the man is wearing a short sleeved shirt, pants, and covered shoes. Both of them are looking in the direction where the photograph was captured. The background of the photograph suggests that it was taken in the interior of a building",
    "subject_terms_1": "double portraits spouses studio portraits folk costume",
    "subject_terms_2": "Spouses Ethnic costume Portrait photography Black-and-white photography",
    "subject_terms_3": "Portrait photography Ethnic costumes",
    "sgcool_label_text": "Not indicated"
  },
  "nlpDate": "20201201203308",
  "connectorId": 0,
  "tags": {}
}