{
  "id": "2016-00506",
  "title": "Untitled (train to Johor Bahru)",
  "source": "Bumblebee",
  "path": "./Data/json/",
  "content": "\n  accession_no_csv: 2016-00506\n\n  Image: \n\n  object_work_type: black-and-white photographs\n\n  title_text: Untitled (train to Johor Bahru)\n\n  preference: main\n\n  title_language: \n\n  creator_2: Kwek Leng Joo\n\n  creator_1: Kwek\n Leng Joo\n\n  creator_role: photographers\n\n  creation_date: 2010\n\n  creation_place_original_location: Singapore\n\n  inscriptions: \n\n  inscription_language: \n\n  shape: rectangular\n\n  materials_name: paper (fiber product)\n\n  techniques_name: printing (process)\n\n  object_colour: grey\n\n  physical_appearance: The image shows a photograph in black-and-white. It has a black frame and its border is white in colour. There is a single set of railroad that is visible in the image. In the middle of the photograph at its background\n there are several tall trees without any leaves. Nearer to the railroad at the foregroud\n grass is present as well as trees with leaves.\n\n  subject_terms_1: railroads (infrastructures)\n\n  subject_terms_2: Black-and-white photography\n\n  subject_terms_3: Rail transport\n\n  sgcool_label_text: \\This image features the scenery that was seen from the train bound for Johor Bahru. It is part of the \\\\Tracking Memories\\\\ collection by the late Mr Kwek Leng Joo. The collection captures different aspects of the Malayan Railway story in Singapore\n",
  "createdDate": "20201120223707",
  "version": 0,
  "latest": false,
  "roles": [],
  "metadata": {
    "accession_no_csv": "2016-00506",
    "Image": "",
    "object_work_type": "black-and-white photographs",
    "title_text": "Untitled (train to Johor Bahru)",
    "preference": "main",
    "title_language": "",
    "creator_2": "Kwek Leng Joo",
    "creator_1": "Kwek, Leng Joo",
    "creator_role": "photographers",
    "creation_date": "2010",
    "creation_place_original_location": "Singapore",
    "inscriptions": "",
    "inscription_language": "",
    "shape": "rectangular",
    "materials_name": "paper (fiber product)",
    "techniques_name": "printing (process)",
    "object_colour": "grey",
    "physical_appearance": "The image shows a photograph in black-and-white. It has a black frame and its border is white in colour. There is a single set of railroad that is visible in the image. In the middle of the photograph at its background, there are several tall trees without any leaves. Nearer to the railroad at the foregroud, grass is present as well as trees with leaves.",
    "subject_terms_1": "railroads (infrastructures)",
    "subject_terms_2": "Black-and-white photography",
    "subject_terms_3": "Rail transport",
    "sgcool_label_text": "\"This image features the scenery that was seen from the train bound for Johor Bahru. It is part of the \"\"Tracking Memories\"\" collection by the late Mr Kwek Leng Joo. The collection captures different aspects of the Malayan Railway story in Singapore"
  },
  "nlpDate": "20201120223707",
  "connectorId": 0,
  "tags": {}
}