{
  "id": "2016-00212-075",
  "title": "Mount Salak from Ballavue Hotel, Buitenzorg, Java Photograph album of views and portraits in the Punjab, Cashmere, Ceylon, Burma, Penang, Singapore, and Java",
  "source": "Bumblebee",
  "path": "./Data/json/",
  "content": "\n  accession_no_csv: 2016-00212-075\n\n  Image: \n\n  object_work_type: black-and-white photographs\n\n  title_text: Mount Salak from Ballavue Hotel\n Buitenzorg\n Java Photograph album of views and portraits in the Punjab\n Cashmere\n Ceylon\n Burma\n Penang\n Singapore\n and Java\n\n  preference: main alternate\n\n  title_language: \n\n  creator_2: John Thomson\n\n  creator_1: Thomson\n J. (John)\n 1837-1921\n\n  creator_role: photographers\n\n  creation_date: before 28 Jul 1876\n\n  creation_place_original_location: Bogor (Indonesia) Singapore\n\n  inscriptions: \n\n  inscription_language: \n\n  shape: rectangular\n\n  materials_name: albumen (egg white protein) paper (fiber product) albumen paper\n\n  techniques_name: albumen process\n\n  object_colour: black-and-white (colors)\n\n  physical_appearance: This is a photograph of a river taken in Buitenzorg (Bogor)\n Indonesia. In the background of the photo is a view of the Mount Salak. The photograph shows dense foliage on either side of the river\n with a small clearing at the bottom-left of the photograph. The edges of the photograph are curved. The title is written at the bottom\n below the photograph.\n\n  subject_terms_1: scenery (landscape) rivers mountains\n\n  subject_terms_2: Bogor (Indonesia) Rivers Photographs Thomson\n J. (John)\n 1837-1921 Salak\n Mount (Indonesia)\n\n  subject_terms_3: Rivers Landscape photography\n",
  "createdDate": "20201125084536",
  "version": 0,
  "latest": false,
  "roles": [],
  "metadata": {
    "accession_no_csv": "2016-00212-075",
    "Image": "",
    "object_work_type": "black-and-white photographs",
    "title_text": "Mount Salak from Ballavue Hotel, Buitenzorg, Java Photograph album of views and portraits in the Punjab, Cashmere, Ceylon, Burma, Penang, Singapore, and Java",
    "preference": "main alternate",
    "title_language": "",
    "creator_2": "John Thomson",
    "creator_1": "Thomson, J. (John), 1837-1921",
    "creator_role": "photographers",
    "creation_date": "before 28 Jul 1876",
    "creation_place_original_location": "Bogor (Indonesia) Singapore",
    "inscriptions": "",
    "inscription_language": "",
    "shape": "rectangular",
    "materials_name": "albumen (egg white protein) paper (fiber product) albumen paper",
    "techniques_name": "albumen process",
    "object_colour": "black-and-white (colors)",
    "physical_appearance": "This is a photograph of a river taken in Buitenzorg (Bogor), Indonesia. In the background of the photo is a view of the Mount Salak. The photograph shows dense foliage on either side of the river, with a small clearing at the bottom-left of the photograph. The edges of the photograph are curved. The title is written at the bottom, below the photograph.",
    "subject_terms_1": "scenery (landscape) rivers mountains",
    "subject_terms_2": "Bogor (Indonesia) Rivers Photographs Thomson, J. (John), 1837-1921 Salak, Mount (Indonesia)",
    "subject_terms_3": "Rivers Landscape photography"
  },
  "nlpDate": "20201125084536",
  "connectorId": 0,
  "tags": {}
}