{"id":"2016-00544","title":"Assembly Songs Songbook, Young Singaporean Supplement Assembly Songs Songbook, Young Singaporean Supplement","source":"Bumblebee","path":"./Data/json/","content":"accession_no_csv:2016-00544\nImage:\nobject_work_type:songbooks songbooks\ntitle_text:Assembly Songs Songbook\n Young Singaporean Supplement Assembly Songs Songbook\n Young Singaporean Supplement\npreference:main main\ntitle_language:\ncreator_2:Singapore Education Publishing Bureau Ministry of Education Singapore Education Publishing Bureau Ministry of Education\ncreator_1:Not indicated Singapore\n Ministry of Education Not indicated Singapore\n Ministry of Education\ncreator_role:publishers creators publishers creators\ncreation_date:1967 - 1980 1967 - 1980\ncreation_place_original_location:Singapore Singapore\nstyles_periods_indexing_terms:NA NA\ninscriptions:\ninscription_language:\nscale_type:NA NA\nshape:rectangular rectangular\nmaterials_name:printing paper printing paper\ntechniques_name:colour printing colour printing\nobject_colour:multicoloured multicoloured\nedition_description:Not indicated Not indicated\nphysical_appearance:\\The image shows the front cover of a songbook. It is rectangular in shape and there are patterned drawings of leaves in a circular direction. \\\\Assembly Songs\\\\ is stated at the centre. \\\\Young Singaporeans Supplement\\\\ is stated at the bottom. There are Chinese characters present on the songbook as well.\\ \\The image shows the front cover of a songbook. It is rectangular in shape and there are patterned drawings of leaves in a circular direction. \\\\Assembly Songs\\\\ is stated at the centre. \\\\Young Singaporeans Supplement\\\\ is stated at the bottom. There are Chinese characters present on the songbook as well.\\\nsubject_terms_1:schools (institutions) students songs (oral or performed works) cultural heritage education schools (institutions) students songs (oral or performed works) cultural heritage education\nsubject_terms_2:School songbooks Students Songs Singapore Education School songbooks Students Songs Singapore Education\nsubject_terms_3:Singapore. Ministry of Education Heritage and Culture Education Singapore. Ministry of Education Heritage and Culture Education\nsubject_terms_4:NA NA\ncontext_1:NA NA\ncontext_2:NA NA\ncontext_3:NA NA\ncontext_4:NA NA\ncontext_5:NA NA\ncontext_6:NA NA\ncontext_7:NA NA\ncontext_8:NA NA\ncontext_9:NA NA\ncontext_10:NA NA\ncontext_11:NA NA\ncontext_12:NA NA\ncontext_13:NA NA\ncontext_14:NA NA\ncontext_15:NA NA\ncontext_16:NA NA\ncontext_17:NA NA\ncontext_18:NA NA\ncontext_19:NA NA\ncontext_20:NA NA\ncontext_21:NA NA\ncontext_22:NA NA\ncontext_23:NA NA\ncontext_24:NA NA\nsgcool_label_text:The Singapore Education Publishing Bureau (EPB) was set up by the Singapore Ministry of Education (MOE) in 1967.  EPB worked with the MOE to develop syllabus for Civic and moral education and mother tongue languages. \\r\\n\\r\\nThis included song books such as this assembly songs book for young Singaporeans which includes “Singapura” written in 1962 and the national anthem written in 1958. The Singapore Education Publishing Bureau (EPB) was set up by the Singapore Ministry of Education (MOE) in 1967.  EPB worked with the MOE to develop syllabus for Civic and moral education and mother tongue languages. \\r\\n\\r\\nThis included song books such as this assembly songs book for young Singaporeans which includes “Singapura” written in 1962 and the national anthem written in 1958.","createdDate":"20201018182635","version":0,"latest":false,"roles":[],"metadata":{"accession_no_csv":"2016-00544","Image":"","object_work_type":"songbooks songbooks","title_text":"Assembly Songs Songbook, Young Singaporean Supplement Assembly Songs Songbook, Young Singaporean Supplement","preference":"main main","title_language":"","creator_2":"Singapore Education Publishing Bureau Ministry of Education Singapore Education Publishing Bureau Ministry of Education","creator_1":"Not indicated Singapore, Ministry of Education Not indicated Singapore, Ministry of Education","creator_role":"publishers creators publishers creators","creation_date":"1967 - 1980 1967 - 1980","creation_place_original_location":"Singapore Singapore","styles_periods_indexing_terms":"NA NA","inscriptions":"","inscription_language":"","scale_type":"NA NA","shape":"rectangular rectangular","materials_name":"printing paper printing paper","techniques_name":"colour printing colour printing","object_colour":"multicoloured multicoloured","edition_description":"Not indicated Not indicated","physical_appearance":"\"The image shows the front cover of a songbook. It is rectangular in shape and there are patterned drawings of leaves in a circular direction. \"\"Assembly Songs\"\" is stated at the centre. \"\"Young Singaporeans Supplement\"\" is stated at the bottom. There are Chinese characters present on the songbook as well.\" \"The image shows the front cover of a songbook. It is rectangular in shape and there are patterned drawings of leaves in a circular direction. \"\"Assembly Songs\"\" is stated at the centre. \"\"Young Singaporeans Supplement\"\" is stated at the bottom. There are Chinese characters present on the songbook as well.\"","subject_terms_1":"schools (institutions) students songs (oral or performed works) cultural heritage education schools (institutions) students songs (oral or performed works) cultural heritage education","subject_terms_2":"School songbooks Students Songs Singapore Education School songbooks Students Songs Singapore Education","subject_terms_3":"Singapore. Ministry of Education Heritage and Culture Education Singapore. Ministry of Education Heritage and Culture Education","subject_terms_4":"NA NA","context_1":"NA NA","context_2":"NA NA","context_3":"NA NA","context_4":"NA NA","context_5":"NA NA","context_6":"NA NA","context_7":"NA NA","context_8":"NA NA","context_9":"NA NA","context_10":"NA NA","context_11":"NA NA","context_12":"NA NA","context_13":"NA NA","context_14":"NA NA","context_15":"NA NA","context_16":"NA NA","context_17":"NA NA","context_18":"NA NA","context_19":"NA NA","context_20":"NA NA","context_21":"NA NA","context_22":"NA NA","context_23":"NA NA","context_24":"NA NA","sgcool_label_text":"The Singapore Education Publishing Bureau (EPB) was set up by the Singapore Ministry of Education (MOE) in 1967.  EPB worked with the MOE to develop syllabus for Civic and moral education and mother tongue languages. \r\n\r\nThis included song books such as this assembly songs book for young Singaporeans which includes “Singapura” written in 1962 and the national anthem written in 1958. The Singapore Education Publishing Bureau (EPB) was set up by the Singapore Ministry of Education (MOE) in 1967.  EPB worked with the MOE to develop syllabus for Civic and moral education and mother tongue languages. \r\n\r\nThis included song books such as this assembly songs book for young Singaporeans which includes “Singapura” written in 1962 and the national anthem written in 1958."},"nlpDate":"20201018182635","connectorId":0,"tags":{}}