{
  "id": "2016-00364",
  "title": "Drawings of South Indian Architectural Temple Figures Drawings of South Indian Architectural Temple Figures with note",
  "source": "Bumblebee",
  "path": "./Data/json/",
  "content": "\n  accession_no_csv: 2016-00364\n\n  Image: \n\n  object_work_type: architectural drawings (visual works)\n\n  title_text: Drawings of South Indian Architectural Temple Figures Drawings of South Indian Architectural Temple Figures with note\n\n  preference: main alternate\n\n  title_language: \n\n  creation_date: 1871 - 1900\n\n  creation_place_original_location: Tamil Nadu (India)\n\n  styles_periods_indexing_terms: Company (style)\n\n  inscriptions: \n\n  inscription_language: \n\n  shape: rectangular\n\n  materials_name: paper (fiber product)\n\n  techniques_name: drawing (image-making)\n\n  object_colour: black-and-white (colours)\n\n  physical_appearance: \\The image shows a set of twenty four pieces of paper. The one on the extreme top left is a note. There is a note that states\n \\\\These drawings of Indian heathen temples \\u0026 idols were done by a native artist and given to me by the Rev Symons (?) of Madras\\\\. Four of the drawings are in the portrait orientation while the other nineteen are in the landscape orientation. The drawings follow a similar pattern in that a single pillar is featured\n\n  subject_terms_1: together with an image of a Hindu deity or idol in the middle.\\ temples (buildings) notes deities idols Hinduism\n\n  subject_terms_2: religious art Hindu temples Drawing Art and architecture Idols and images Hindu gods\n\n  subject_terms_3: Drawing Hinduism Religious art\n\n  subject_terms_4: Architecture\n",
  "createdDate": "20201201203309",
  "version": 0,
  "latest": false,
  "roles": [],
  "metadata": {
    "accession_no_csv": "2016-00364",
    "Image": "",
    "object_work_type": "architectural drawings (visual works)",
    "title_text": "Drawings of South Indian Architectural Temple Figures Drawings of South Indian Architectural Temple Figures with note",
    "preference": "main alternate",
    "title_language": "",
    "creation_date": "1871 - 1900",
    "creation_place_original_location": "Tamil Nadu (India)",
    "styles_periods_indexing_terms": "Company (style)",
    "inscriptions": "",
    "inscription_language": "",
    "shape": "rectangular",
    "materials_name": "paper (fiber product)",
    "techniques_name": "drawing (image-making)",
    "object_colour": "black-and-white (colours)",
    "physical_appearance": "\"The image shows a set of twenty four pieces of paper. The one on the extreme top left is a note. There is a note that states, \"\"These drawings of Indian heathen temples \u0026 idols were done by a native artist and given to me by the Rev Symons (?) of Madras\"\". Four of the drawings are in the portrait orientation while the other nineteen are in the landscape orientation. The drawings follow a similar pattern in that a single pillar is featured",
    "subject_terms_1": "together with an image of a Hindu deity or idol in the middle.\" temples (buildings) notes deities idols Hinduism",
    "subject_terms_2": "religious art Hindu temples Drawing Art and architecture Idols and images Hindu gods",
    "subject_terms_3": "Drawing Hinduism Religious art",
    "subject_terms_4": "Architecture"
  },
  "nlpDate": "20201201203309",
  "connectorId": 0,
  "tags": {}
}