{
  "id": "2016-00469",
  "title": "Oil lamp",
  "source": "Bumblebee",
  "path": "./Data/json/",
  "content": "\n  accession_no_csv: 2016-00469\n\n  Image: \n\n  object_work_type: oil lamps\n\n  title_text: Oil lamp\n\n  preference: main\n\n  title_language: \n\n  creation_date: 1900-1920\n\n  creation_place_original_location: Singapore\n\n  inscriptions: \n\n  inscription_language: \n\n  shape: irregular\n\n  materials_name: brass (alloy)\n\n  techniques_name: forging (metal forming)\n\n  object_colour: bronze (color)\n\n  physical_appearance: This is a brass oil lamp. It has two shallow dishes that is connected by a thin\n long body. The body of the lamp has five pairs of decorative bands. The base of the lamp is a circular dish.\n\n  subject_terms_1: worship Peranakan ceremonial objects\n\n  subject_terms_2: Lamps Worship Buddhist altars Peranakan (Asian people) Ceremonial objects\n\n  subject_terms_3: Religious life and practices\n\n  sgcool_label_text: This brass oil lamp was used by Peranakans for their altars and was placed within a red and gold lamp screen. Together\n they were placed at a corner of the higher altar table. The key function of the oil lamp was to keep a constant fire burning\n especially for the burning of joss sticks used for prayers.\\r\\n\\r\\nIn particular\n this oil lamp belonged to the family of Mdm Chua Geok Choo and Tan Eng Wah (1923-2013). It was passed down Mdm Chua’s side of the family and was used for the worship of Guanyin\n the Goddess of Mercy; in the family home at East Coast Avenue.\\r\\n\\r\\nTan Eng Wah was also the eldest son of Tan Lark Sye (1897-1972). Tan Lark Sye was a highly regarded Chinese businessman and philanthropist in Singapore.\n",
  "createdDate": "20201120223706",
  "version": 0,
  "latest": false,
  "roles": [],
  "metadata": {
    "accession_no_csv": "2016-00469",
    "Image": "",
    "object_work_type": "oil lamps",
    "title_text": "Oil lamp",
    "preference": "main",
    "title_language": "",
    "creation_date": "1900-1920",
    "creation_place_original_location": "Singapore",
    "inscriptions": "",
    "inscription_language": "",
    "shape": "irregular",
    "materials_name": "brass (alloy)",
    "techniques_name": "forging (metal forming)",
    "object_colour": "bronze (color)",
    "physical_appearance": "This is a brass oil lamp. It has two shallow dishes that is connected by a thin, long body. The body of the lamp has five pairs of decorative bands. The base of the lamp is a circular dish.",
    "subject_terms_1": "worship Peranakan ceremonial objects",
    "subject_terms_2": "Lamps Worship Buddhist altars Peranakan (Asian people) Ceremonial objects",
    "subject_terms_3": "Religious life and practices",
    "sgcool_label_text": "This brass oil lamp was used by Peranakans for their altars and was placed within a red and gold lamp screen. Together, they were placed at a corner of the higher altar table. The key function of the oil lamp was to keep a constant fire burning, especially for the burning of joss sticks used for prayers.\r\n\r\nIn particular, this oil lamp belonged to the family of Mdm Chua Geok Choo and Tan Eng Wah (1923-2013). It was passed down Mdm Chua’s side of the family and was used for the worship of Guanyin, the Goddess of Mercy; in the family home at East Coast Avenue.\r\n\r\nTan Eng Wah was also the eldest son of Tan Lark Sye (1897-1972). Tan Lark Sye was a highly regarded Chinese businessman and philanthropist in Singapore."
  },
  "nlpDate": "20201120223706",
  "connectorId": 0,
  "tags": {}
}