{"id":"2016-00680","title":"Fabric with 2 Pieces of Cloth","source":"Bumblebee","path":"./Data/json/","content":"accession_no_csv:2016-00680\nImage:\nobject_work_type:cloth\ntitle_text:Fabric with 2 Pieces of Cloth\npreference:main\ntitle_language:\ncreation_date:20th century\ncreation_place_original_location:Indonesia\nstyles_periods_indexing_terms:Peranakan\ninscriptions:\ninscription_language:\nshape:irregular\nmaterials_name:cotton (textile)\nobject_colour:multicolored\nphysical_appearance:This is a set of items that include a fabric with two pieces of cloth. The fabric is white with stripes. One of the cloth has a cat image\n while the other has a globe beneath vines and a winged figure.\nsubject_terms_1:stripes motifs Peranakan cultural diffusion\nsubject_terms_2:Textiles Motifs Culture diffusion Peranakan (Asian people)\nsubject_terms_3:Textile art and design\nsgcool_label_text:This striped white fabric is accompanied by two pieces of cloth printed with shop marks?‘N.V.HANDEL MAATSCHAPPY VORHEEN G.HOPPENSTEDT’ with a cat image on one; ‘PRIMATEXCO’ before a globe beneath vines and a winged figure on the other. It is part of a donation which contains a mixture of materials used in the making of kebayas and baju panjangs.","createdDate":"20201018182635","version":0,"latest":false,"roles":[],"metadata":{"accession_no_csv":"2016-00680","Image":"","object_work_type":"cloth","title_text":"Fabric with 2 Pieces of Cloth","preference":"main","title_language":"","creation_date":"20th century","creation_place_original_location":"Indonesia","styles_periods_indexing_terms":"Peranakan","inscriptions":"","inscription_language":"","shape":"irregular","materials_name":"cotton (textile)","object_colour":"multicolored","physical_appearance":"This is a set of items that include a fabric with two pieces of cloth. The fabric is white with stripes. One of the cloth has a cat image, while the other has a globe beneath vines and a winged figure.","subject_terms_1":"stripes motifs Peranakan cultural diffusion","subject_terms_2":"Textiles Motifs Culture diffusion Peranakan (Asian people)","subject_terms_3":"Textile art and design","sgcool_label_text":"This striped white fabric is accompanied by two pieces of cloth printed with shop marks?‘N.V.HANDEL MAATSCHAPPY VORHEEN G.HOPPENSTEDT’ with a cat image on one; ‘PRIMATEXCO’ before a globe beneath vines and a winged figure on the other. It is part of a donation which contains a mixture of materials used in the making of kebayas and baju panjangs."},"nlpDate":"20201018182635","connectorId":0,"tags":{}}