{"id":"2016-00548","title":"Singapore River Singapore River, programme booklet of a performance booklet by the Singapore Federation of Chinese Drama Association at the Victoria Theatre and Concert Hall (1990) Singapore River Singapore River, programme booklet of a performance booklet by the Singapore Federation of Chinese Drama Association at the Victoria Theatre and Concert Hall (1990)","source":"Bumblebee","path":"./Data/json/","content":"accession_no_csv:2016-00548\nImage:\nobject_work_type:booklets booklets\ntitle_text:Singapore River Singapore River\n programme booklet of a performance booklet by the Singapore Federation of Chinese Drama Association at the Victoria Theatre and Concert Hall (1990) Singapore River Singapore River\n programme booklet of a performance booklet by the Singapore Federation of Chinese Drama Association at the Victoria Theatre and Concert Hall (1990)\npreference:main alternate main alternate\ntitle_language:\ncreator_2:Singapore Federation of Chinese Drama Association Singapore Federation of Chinese Drama Association\ncreator_1:Not indicated Not indicated\ncreator_role:performing artists performing artists\ncreation_date:1990 1990\ncreation_place_original_location:Singapore Singapore\nstyles_periods_indexing_terms:NA NA\ninscriptions:\ninscription_language:\nscale_type:NA NA\nshape:rectangular rectangular\nmaterials_name:printing paper printing paper\ntechniques_name:colour printing colour printing\nobject_colour:multicoloured multicoloured\nedition_description:NA NA\nphysical_appearance:The image shows the front cover of a booklet. It is rectangular in shape and there are Chinese characters on the sides and bottom. To the right of the booklet is a vertical line of four red coloured Chinese characters executed in a calligraphic style. The number \\u002725\\u0027 can be seen directly below. The image on the booklet shows a drawing of a boat on water. The image shows the front cover of a booklet. It is rectangular in shape and there are Chinese characters on the sides and bottom. To the right of the booklet is a vertical line of four red coloured Chinese characters executed in a calligraphic style. The number \\u002725\\u0027 can be seen directly below. The image on the booklet shows a drawing of a boat on water.\nsubject_terms_1:performances (creative events) rivers celebrations performing arts centres performances (creative events) rivers celebrations performing arts centres\nsubject_terms_2:Performances Singapore River (Singapore) Centres for the performing arts Pamphlets Performances Singapore River (Singapore) Centres for the performing arts Pamphlets\nsubject_terms_3:Performing Arts Singapore River Victoria Theatre and Concert Hall Performing Arts Singapore River Victoria Theatre and Concert Hall\nsubject_terms_4:NA NA\ncontext_1:Singapore’s 25th year of independence Singapore’s 25th year of independence\ncontext_2:national holidays national holidays\ncontext_3:9-Aug-90 9-Aug-90\ncontext_4:19900809 19900809\ncontext_5:19900809 19900809\ncontext_6:Singapore Singapore\ncontext_7:NA NA\ncontext_8:NA NA\ncontext_9:NA NA\ncontext_10:NA NA\ncontext_11:NA NA\ncontext_12:NA NA\ncontext_13:NA NA\ncontext_14:NA NA\ncontext_15:NA NA\ncontext_16:NA NA\ncontext_17:NA NA\ncontext_18:NA NA\ncontext_19:NA NA\ncontext_20:NA NA\ncontext_21:NA NA\ncontext_22:NA NA\ncontext_23:NA NA\ncontext_24:NA NA\nsgcool_label_text:This was a performance put up by the Singapore Federation of Chinese Drama Association. The performance was about the Singapore River\n which was held in conjunction with the celebrations of Singapore’s 25th year of independence. The performance was held at the Victoria Theatre and Concert Hall\n one of the oldest performances spaces in Singapore whose origins can be traced to 1909 when it first opened. It was originally known as the Victoria Memorial Hall – in memory of Queen Victoria – being being renamed Victoria Concert Hall after renovations in 1979.\\r\\n  This was a performance put up by the Singapore Federation of Chinese Drama Association. The performance was about the Singapore River\n which was held in conjunction with the celebrations of Singapore’s 25th year of independence. The performance was held at the Victoria Theatre and Concert Hall\n one of the oldest performances spaces in Singapore whose origins can be traced to 1909 when it first opened. It was originally known as the Victoria Memorial Hall – in memory of Queen Victoria – being being renamed Victoria Concert Hall after renovations in 1979.\\r\\n","createdDate":"20201018182635","version":0,"latest":false,"roles":[],"metadata":{"accession_no_csv":"2016-00548","Image":"","object_work_type":"booklets booklets","title_text":"Singapore River Singapore River, programme booklet of a performance booklet by the Singapore Federation of Chinese Drama Association at the Victoria Theatre and Concert Hall (1990) Singapore River Singapore River, programme booklet of a performance booklet by the Singapore Federation of Chinese Drama Association at the Victoria Theatre and Concert Hall (1990)","preference":"main alternate main alternate","title_language":"","creator_2":"Singapore Federation of Chinese Drama Association Singapore Federation of Chinese Drama Association","creator_1":"Not indicated Not indicated","creator_role":"performing artists performing artists","creation_date":"1990 1990","creation_place_original_location":"Singapore Singapore","styles_periods_indexing_terms":"NA NA","inscriptions":"","inscription_language":"","scale_type":"NA NA","shape":"rectangular rectangular","materials_name":"printing paper printing paper","techniques_name":"colour printing colour printing","object_colour":"multicoloured multicoloured","edition_description":"NA NA","physical_appearance":"The image shows the front cover of a booklet. It is rectangular in shape and there are Chinese characters on the sides and bottom. To the right of the booklet is a vertical line of four red coloured Chinese characters executed in a calligraphic style. The number \u002725\u0027 can be seen directly below. The image on the booklet shows a drawing of a boat on water. The image shows the front cover of a booklet. It is rectangular in shape and there are Chinese characters on the sides and bottom. To the right of the booklet is a vertical line of four red coloured Chinese characters executed in a calligraphic style. The number \u002725\u0027 can be seen directly below. The image on the booklet shows a drawing of a boat on water.","subject_terms_1":"performances (creative events) rivers celebrations performing arts centres performances (creative events) rivers celebrations performing arts centres","subject_terms_2":"Performances Singapore River (Singapore) Centres for the performing arts Pamphlets Performances Singapore River (Singapore) Centres for the performing arts Pamphlets","subject_terms_3":"Performing Arts Singapore River Victoria Theatre and Concert Hall Performing Arts Singapore River Victoria Theatre and Concert Hall","subject_terms_4":"NA NA","context_1":"Singapore’s 25th year of independence Singapore’s 25th year of independence","context_2":"national holidays national holidays","context_3":"9-Aug-90 9-Aug-90","context_4":"19900809 19900809","context_5":"19900809 19900809","context_6":"Singapore Singapore","context_7":"NA NA","context_8":"NA NA","context_9":"NA NA","context_10":"NA NA","context_11":"NA NA","context_12":"NA NA","context_13":"NA NA","context_14":"NA NA","context_15":"NA NA","context_16":"NA NA","context_17":"NA NA","context_18":"NA NA","context_19":"NA NA","context_20":"NA NA","context_21":"NA NA","context_22":"NA NA","context_23":"NA NA","context_24":"NA NA","sgcool_label_text":"This was a performance put up by the Singapore Federation of Chinese Drama Association. The performance was about the Singapore River, which was held in conjunction with the celebrations of Singapore’s 25th year of independence. The performance was held at the Victoria Theatre and Concert Hall, one of the oldest performances spaces in Singapore whose origins can be traced to 1909 when it first opened. It was originally known as the Victoria Memorial Hall – in memory of Queen Victoria – being being renamed Victoria Concert Hall after renovations in 1979.\r\n  This was a performance put up by the Singapore Federation of Chinese Drama Association. The performance was about the Singapore River, which was held in conjunction with the celebrations of Singapore’s 25th year of independence. The performance was held at the Victoria Theatre and Concert Hall, one of the oldest performances spaces in Singapore whose origins can be traced to 1909 when it first opened. It was originally known as the Victoria Memorial Hall – in memory of Queen Victoria – being being renamed Victoria Concert Hall after renovations in 1979.\r\n"},"nlpDate":"20201018182635","connectorId":0,"tags":{}}