{"id":"2016-00175","title":"Pink cheongsam with metallic shimmer","source":"Bumblebee","path":"./Data/json/","content":"accession_no_csv:2016-00175\nImage:\nobject_work_type:folk costume womenswear\ntitle_text:Pink cheongsam with metallic shimmer\npreference:main\ntitle_language:\ncreator_2:“Tailor Chu” (?????) \\u0026 “??????”\ncreator_role:creators\ncreation_date:1960 - 1969\ncreation_place_original_location:Singapore Hong Kong (China)\nstyles_periods_indexing_terms:Chinese (culture or style)\ninscriptions:\ninscription_language:\nshape:irregular\nmaterials_name:Lurex (TM)\ntechniques_name:machine sewing (technique)\nobject_colour:pink colours\nphysical_appearance:This is a pink cheongsam with very short sleeves. There are light pink patches present throughout the exterior of the outfit. A collar is present on the cheongsam as well.  The collar tag of the cheongsam is visible\n with English words and Chinese characters present on it. There are no visible tears on the cheongsam.\nsubject_terms_1:tailor-made dresses (garments) allover patterns\nsubject_terms_2:Ethnic costume Qipao Custom-made clothing Women\\u0027s clothing Patterns for crafts\nsubject_terms_3:Ethnic costume Chinese costume\nsgcool_label_text:The cheongsam is made of lurex material\n which has silver thread woven into the fabric. Lurex was a popular choice of fabric for clothing in the 1960s. The shiny effect created by the metallic fibre made the fabric suitable for evening wear dresses. The cheongsam has a Hong Kong-based tailor label\n “Tailor Chu” (?????) and another label that reads “??????”.","createdDate":"20201119143405","version":0,"latest":false,"roles":[],"metadata":{"accession_no_csv":"2016-00175","Image":"","object_work_type":"folk costume womenswear","title_text":"Pink cheongsam with metallic shimmer","preference":"main","title_language":"","creator_2":"“Tailor Chu” (?????) \u0026 “??????”","creator_role":"creators","creation_date":"1960 - 1969","creation_place_original_location":"Singapore Hong Kong (China)","styles_periods_indexing_terms":"Chinese (culture or style)","inscriptions":"","inscription_language":"","shape":"irregular","materials_name":"Lurex (TM)","techniques_name":"machine sewing (technique)","object_colour":"pink colours","physical_appearance":"This is a pink cheongsam with very short sleeves. There are light pink patches present throughout the exterior of the outfit. A collar is present on the cheongsam as well.  The collar tag of the cheongsam is visible, with English words and Chinese characters present on it. There are no visible tears on the cheongsam.","subject_terms_1":"tailor-made dresses (garments) allover patterns","subject_terms_2":"Ethnic costume Qipao Custom-made clothing Women\u0027s clothing Patterns for crafts","subject_terms_3":"Ethnic costume Chinese costume","sgcool_label_text":"The cheongsam is made of lurex material, which has silver thread woven into the fabric. Lurex was a popular choice of fabric for clothing in the 1960s. The shiny effect created by the metallic fibre made the fabric suitable for evening wear dresses. The cheongsam has a Hong Kong-based tailor label, “Tailor Chu” (?????) and another label that reads “??????”."},"nlpDate":"20201119143405","connectorId":0,"tags":{}}