{
  "id": "2016-00537",
  "title": "Open  Space\u0027 magazine \u0027Open  Space\u0027 magazine by Substation  Open  Space\u0027 magazine \u0027Open  Space\u0027 magazine by Substation",
  "source": "Bumblebee",
  "path": "./Data/json/",
  "content": "\n  accession_no_csv: 2016-00537\n\n  Image: \n\n  object_work_type: serials (publications) magazines (periodicals) serials (publications) magazines (periodicals)\n\n  title_text: Open  Space\\u0027 magazine \\u0027Open  Space\\u0027 magazine by Substation  Open  Space\\u0027 magazine \\u0027Open  Space\\u0027 magazine by Substation\n\n  preference: main alternate main alternate\n\n  title_language: \n\n  creator_2: Kuo Pao Kun Joe Ng Kuo Pao Kun Joe Ng\n\n  creator_1: Kuo\n Pao Kun. 1939-2002 Not indicated Kuo\n Pao Kun. 1939-2002 Not indicated\n\n  creator_role: creators illustrators creators illustrators\n\n  creation_date: 1990-1991 Dec 1990 - Jan 1991\n\n  creation_place_original_location: Singapore Singapore\n\n  styles_periods_indexing_terms: NA NA\n\n  inscriptions: \n\n  inscription_language: \n\n  scale_type: NA NA\n\n  shape: rectangular rectangular\n\n  materials_name: printing paper printing paper\n\n  techniques_name: printing (process) printing (process)\n\n  object_colour: grey (colour) grey (colour)\n\n  edition_description: Not indicated Not indicated\n\n  physical_appearance: \\The image displays the front cover of a magazine. It is grey in colour. \\\\Open Space\\\\ is displayed at the top. The dates \\\\28/12/90 to 6/1/91\\\\ is displayed at the bottom right hand side. A picture of a woman wearing a kebaya and sitting down on a chair in the interior of a building can be seen.\\ \\The image displays the front cover of a magazine. It is grey in colour. \\\\Open Space\\\\ is displayed at the top. The dates \\\\28/12/90 to 6/1/91\\\\ is displayed at the bottom right hand side. A picture of a woman wearing a kebaya and sitting down on a chair in the interior of a building can be seen.\\\n\n  subject_terms_1: cultural heritage art centres performing arts centres cultural heritage art centres performing arts centres\n\n  subject_terms_2: Periodicals Publications Art centres Centres for the performing arts Periodicals Publications Art centres Centres for the performing arts\n\n  subject_terms_3: Periodicals Cultural development The Substation (Arts centre) Kuo\n Pao Kun Periodicals Cultural development The Substation (Arts centre) Kuo\n Pao Kun\n\n  subject_terms_4: NA NA\n\n  context_1: NA NA\n\n  context_2: NA NA\n\n  context_3: NA NA\n\n  context_4: NA NA\n\n  context_5: NA NA\n\n  context_6: NA NA\n\n  context_7: NA NA\n\n  context_8: NA NA\n\n  context_9: NA NA\n\n  context_10: NA NA\n\n  context_11: NA NA\n\n  context_12: NA NA\n\n  context_13: NA NA\n\n  context_14: NA NA\n\n  context_15: NA NA\n\n  context_16: NA NA\n\n  context_17: NA NA\n\n  context_18: NA NA\n\n  context_19: NA NA\n\n  context_20: NA NA\n\n  context_21: NA NA\n\n  context_22: NA NA\n\n  context_23: NA NA\n\n  context_24: NA NA\n\n  sgcool_label_text: The inaugural issue of Open Space\n a bi-monthly bilingual magazine with events and reviews which ran till December 1992. This important issue documents the launch of the Substation\n perhaps the definitive independent art space in Singapore. \\r\\n\\r\\nWith a forward by its founder Kuo Pao Kun and featuring images and events of its different functioned spaces\n the issue also features a rare full-colour centrefold collage by Joe Ng\n a local music archivist of a gig in what was then the Substation’s open air garden. Open Space was distributed for free at the Substation’s Box Office. The inaugural issue of Open Space\n a bi-monthly bilingual magazine with events and reviews which ran till December 1992. This important issue documents the launch of the Substation\n perhaps the definitive independent art space in Singapore. \\r\\n\\r\\nWith a forward by its founder Kuo Pao Kun and featuring images and events of its different functioned spaces\n the issue also features a rare full-colour centrefold collage by Joe Ng\n a local music archivist of a gig in what was then the Substation’s open air garden. Open Space was distributed for free at the Substation’s Box Office.\n",
  "createdDate": "20201120223707",
  "version": 0,
  "latest": false,
  "roles": [],
  "metadata": {
    "accession_no_csv": "2016-00537",
    "Image": "",
    "object_work_type": "serials (publications) magazines (periodicals) serials (publications) magazines (periodicals)",
    "title_text": "Open  Space\u0027 magazine \u0027Open  Space\u0027 magazine by Substation  Open  Space\u0027 magazine \u0027Open  Space\u0027 magazine by Substation",
    "preference": "main alternate main alternate",
    "title_language": "",
    "creator_2": "Kuo Pao Kun Joe Ng Kuo Pao Kun Joe Ng",
    "creator_1": "Kuo, Pao Kun. 1939-2002 Not indicated Kuo, Pao Kun. 1939-2002 Not indicated",
    "creator_role": "creators illustrators creators illustrators",
    "creation_date": "1990-1991 Dec 1990 - Jan 1991",
    "creation_place_original_location": "Singapore Singapore",
    "styles_periods_indexing_terms": "NA NA",
    "inscriptions": "",
    "inscription_language": "",
    "scale_type": "NA NA",
    "shape": "rectangular rectangular",
    "materials_name": "printing paper printing paper",
    "techniques_name": "printing (process) printing (process)",
    "object_colour": "grey (colour) grey (colour)",
    "edition_description": "Not indicated Not indicated",
    "physical_appearance": "\"The image displays the front cover of a magazine. It is grey in colour. \"\"Open Space\"\" is displayed at the top. The dates \"\"28/12/90 to 6/1/91\"\" is displayed at the bottom right hand side. A picture of a woman wearing a kebaya and sitting down on a chair in the interior of a building can be seen.\" \"The image displays the front cover of a magazine. It is grey in colour. \"\"Open Space\"\" is displayed at the top. The dates \"\"28/12/90 to 6/1/91\"\" is displayed at the bottom right hand side. A picture of a woman wearing a kebaya and sitting down on a chair in the interior of a building can be seen.\"",
    "subject_terms_1": "cultural heritage art centres performing arts centres cultural heritage art centres performing arts centres",
    "subject_terms_2": "Periodicals Publications Art centres Centres for the performing arts Periodicals Publications Art centres Centres for the performing arts",
    "subject_terms_3": "Periodicals Cultural development The Substation (Arts centre) Kuo, Pao Kun Periodicals Cultural development The Substation (Arts centre) Kuo, Pao Kun",
    "subject_terms_4": "NA NA",
    "context_1": "NA NA",
    "context_2": "NA NA",
    "context_3": "NA NA",
    "context_4": "NA NA",
    "context_5": "NA NA",
    "context_6": "NA NA",
    "context_7": "NA NA",
    "context_8": "NA NA",
    "context_9": "NA NA",
    "context_10": "NA NA",
    "context_11": "NA NA",
    "context_12": "NA NA",
    "context_13": "NA NA",
    "context_14": "NA NA",
    "context_15": "NA NA",
    "context_16": "NA NA",
    "context_17": "NA NA",
    "context_18": "NA NA",
    "context_19": "NA NA",
    "context_20": "NA NA",
    "context_21": "NA NA",
    "context_22": "NA NA",
    "context_23": "NA NA",
    "context_24": "NA NA",
    "sgcool_label_text": "The inaugural issue of Open Space, a bi-monthly bilingual magazine with events and reviews which ran till December 1992. This important issue documents the launch of the Substation, perhaps the definitive independent art space in Singapore. \r\n\r\nWith a forward by its founder Kuo Pao Kun and featuring images and events of its different functioned spaces, the issue also features a rare full-colour centrefold collage by Joe Ng, a local music archivist of a gig in what was then the Substation’s open air garden. Open Space was distributed for free at the Substation’s Box Office. The inaugural issue of Open Space, a bi-monthly bilingual magazine with events and reviews which ran till December 1992. This important issue documents the launch of the Substation, perhaps the definitive independent art space in Singapore. \r\n\r\nWith a forward by its founder Kuo Pao Kun and featuring images and events of its different functioned spaces, the issue also features a rare full-colour centrefold collage by Joe Ng, a local music archivist of a gig in what was then the Substation’s open air garden. Open Space was distributed for free at the Substation’s Box Office."
  },
  "nlpDate": "20201120223707",
  "connectorId": 0,
  "tags": {}
}