{
  "id": "2016-00070",
  "title": "Invitation card to Carnatic \u0026 Hindustani Musical Entertainment",
  "source": "Bumblebee",
  "path": "./Data/json/",
  "content": "\n  accession_no_csv: 2016-00070\n\n  Image: \n\n  object_work_type: invitations\n\n  title_text: Invitation card to Carnatic \\u0026 Hindustani Musical Entertainment\n\n  preference: main\n\n  title_language: \n\n  creator_2: Unknown\n\n  creation_date: 8-Oct-50\n\n  creation_place_original_location: Singapore\n\n  styles_periods_indexing_terms: Not indicated\n\n  inscriptions: \n\n  inscription_language: \n\n  scale_type: Not indicated\n\n  shape: rectangular\n\n  materials_name: printing paper\n\n  techniques_name: printing (process)\n\n  object_colour: multicoloured\n\n  physical_appearance: \\The image shows an invitation card. It is rectangular in shape. It has a brown background. \\\\Carnatic and Hindustani Musical Entertainment\\\\ is stated at the top. \\\\Ramakrishna Mission Hall No. 9 Norris Road\n\n  subject_terms_1: musical performances musicians religious organizations religious institutions religious centres Singapore at 5.30p.m. on Sunday\n\n  subject_terms_2: Carnatic music Hindustani music 8th October Ramakrishna Mission Musicians Performances\n\n  subject_terms_3: Performing Arts Ramakrishna Mission Singapore Musicians 1950\\\\ is stated at the bottom. \\\n\n  subject_terms_4: entertainment events\n\n  context_1: Invitation cards\n\n  context_2: Indian music\n",
  "createdDate": "20201201203309",
  "version": 0,
  "latest": false,
  "roles": [],
  "metadata": {
    "accession_no_csv": "2016-00070",
    "Image": "",
    "object_work_type": "invitations",
    "title_text": "Invitation card to Carnatic \u0026 Hindustani Musical Entertainment",
    "preference": "main",
    "title_language": "",
    "creator_2": "Unknown",
    "creation_date": "8-Oct-50",
    "creation_place_original_location": "Singapore",
    "styles_periods_indexing_terms": "Not indicated",
    "inscriptions": "",
    "inscription_language": "",
    "scale_type": "Not indicated",
    "shape": "rectangular",
    "materials_name": "printing paper",
    "techniques_name": "printing (process)",
    "object_colour": "multicoloured",
    "physical_appearance": "\"The image shows an invitation card. It is rectangular in shape. It has a brown background. \"\"Carnatic and Hindustani Musical Entertainment\"\" is stated at the top. \"\"Ramakrishna Mission Hall No. 9 Norris Road",
    "subject_terms_1": "musical performances musicians religious organizations religious institutions religious centres Singapore at 5.30p.m. on Sunday",
    "subject_terms_2": "Carnatic music Hindustani music 8th October Ramakrishna Mission Musicians Performances",
    "subject_terms_3": "Performing Arts Ramakrishna Mission Singapore Musicians 1950\"\" is stated at the bottom. \"",
    "subject_terms_4": "entertainment events",
    "context_1": "Invitation cards",
    "context_2": "Indian music"
  },
  "nlpDate": "20201201203309",
  "connectorId": 0,
  "tags": {}
}