{
  "id": "2016-00127",
  "title": "Ivory Fan Handle",
  "source": "Bumblebee",
  "path": "./Data/json/",
  "content": "\n  accession_no_csv: 2016-00127\n\n  Image: \n\n  object_work_type: handles\n\n  title_text: Ivory Fan Handle\n\n  preference: main\n\n  title_language: \n\n  creation_date: 1700 - 1799\n\n  creation_place_original_location: Sri Lanka\n\n  styles_periods_indexing_terms: Sri Lankan\n\n  inscriptions: \n\n  inscription_language: \n\n  shape: cylindrical\n\n  materials_name: ivory (material)\n\n  techniques_name: forming (physical activity)\n\n  object_colour: multicoloured\n\n  physical_appearance: The image shows a fan handle that is cylindrical in shape. The mouth of the fan handle is shaped  like and designed to look like the head of a snake. The motifs of lozenges\n scrolls\n and foliage are displayed on both the handle and the mouth. The designs run around the object in concentric forms and are of a variety of colours.\n\n  subject_terms_1: ceremonial objects Buddhism lozenges foliage (motif) decorative art (art genre) carvings (visual works)\n\n  subject_terms_2: Aesthetics\n Sri Lankan Motifs Ceremonial objects Buddhism Customs and practices Buddhist religious articles\n\n  subject_terms_3: Buddhism Religious life and practices\n\n  sgcool_label_text: This fan handle is made of two pieces of carved ivory that are screwed together. The handle itself is turned and decorated in red and black pigment with concentric forms; the mouth is densely carved with tightly scrolling leaf-work. \\r\\n\\r\\nThe fan handle would have been a part of a vatapatha or semi-circular fan of the kind that are carried by Buddhist monks in Sri Lanka for processions and ceremonies. Large and beautifully ornamented fan handles such as this one would have been treasured and were also given to the monks as gifts.\n",
  "createdDate": "20201201203309",
  "version": 0,
  "latest": false,
  "roles": [],
  "metadata": {
    "accession_no_csv": "2016-00127",
    "Image": "",
    "object_work_type": "handles",
    "title_text": "Ivory Fan Handle",
    "preference": "main",
    "title_language": "",
    "creation_date": "1700 - 1799",
    "creation_place_original_location": "Sri Lanka",
    "styles_periods_indexing_terms": "Sri Lankan",
    "inscriptions": "",
    "inscription_language": "",
    "shape": "cylindrical",
    "materials_name": "ivory (material)",
    "techniques_name": "forming (physical activity)",
    "object_colour": "multicoloured",
    "physical_appearance": "The image shows a fan handle that is cylindrical in shape. The mouth of the fan handle is shaped  like and designed to look like the head of a snake. The motifs of lozenges, scrolls, and foliage are displayed on both the handle and the mouth. The designs run around the object in concentric forms and are of a variety of colours.",
    "subject_terms_1": "ceremonial objects Buddhism lozenges foliage (motif) decorative art (art genre) carvings (visual works)",
    "subject_terms_2": "Aesthetics, Sri Lankan Motifs Ceremonial objects Buddhism Customs and practices Buddhist religious articles",
    "subject_terms_3": "Buddhism Religious life and practices",
    "sgcool_label_text": "This fan handle is made of two pieces of carved ivory that are screwed together. The handle itself is turned and decorated in red and black pigment with concentric forms; the mouth is densely carved with tightly scrolling leaf-work. \r\n\r\nThe fan handle would have been a part of a vatapatha or semi-circular fan of the kind that are carried by Buddhist monks in Sri Lanka for processions and ceremonies. Large and beautifully ornamented fan handles such as this one would have been treasured and were also given to the monks as gifts."
  },
  "nlpDate": "20201201203309",
  "connectorId": 0,
  "tags": {}
}