{"id":"2016-00314","title":"Rock crystal gem-set fluted cup and cover","source":"Bumblebee","path":"./Data/json/","content":"accession_no_csv:2016-00314\nImage:\nobject_work_type:cups (drinking vessels)\ntitle_text:Rock crystal gem-set fluted cup and cover\npreference:main\ntitle_language:\ncreation_place_original_location:India\n North\nstyles_periods_indexing_terms:Mughal\ninscriptions:\ninscription_language:\nshape:irregular\nmaterials_name:gold (metal) enamel paint quartz crystal diamond (mineral)\ntechniques_name:carving (processes) painting (image making)\nobject_colour:multicolored\nphysical_appearance:This is an eight-lobed cup and cover. It is carved and inlaid with crystals\n decorated with gold wire and enamel paint. The exterior is decorated with floral motifs and scrolling leaves\n with some diamonds embedded within the motif design.\nsubject_terms_1:foliage (motif) flower (motif)\nsubject_terms_2:Drinking cups Diamond jewelry\n Mogul Empire Motifs\nsubject_terms_3:Indian decorative arts\nsgcool_label_text:The carved rock crystal eight-lobed cup and cover is inlaid with precious stones within a system of gold wire.  This object shows the taste for luxury objects in Northern India in the 19th century. In Mughal India there was a great revival in the art of rock crystal carving\n and Mughal craftsmen reached new heights of technical virtuosity especially during the reign of Shah Jahan (1628-1658). The motifs in the gem work and enamelling of flowers\n plants\n scrolling vines and animal forms allude to paradise gardens on earth. It would have been highly prized and made for a privileged few.","createdDate":"20201018182635","version":0,"latest":false,"roles":[],"metadata":{"accession_no_csv":"2016-00314","Image":"","object_work_type":"cups (drinking vessels)","title_text":"Rock crystal gem-set fluted cup and cover","preference":"main","title_language":"","creation_place_original_location":"India, North","styles_periods_indexing_terms":"Mughal","inscriptions":"","inscription_language":"","shape":"irregular","materials_name":"gold (metal) enamel paint quartz crystal diamond (mineral)","techniques_name":"carving (processes) painting (image making)","object_colour":"multicolored","physical_appearance":"This is an eight-lobed cup and cover. It is carved and inlaid with crystals, decorated with gold wire and enamel paint. The exterior is decorated with floral motifs and scrolling leaves, with some diamonds embedded within the motif design.","subject_terms_1":"foliage (motif) flower (motif)","subject_terms_2":"Drinking cups Diamond jewelry, Mogul Empire Motifs","subject_terms_3":"Indian decorative arts","sgcool_label_text":"The carved rock crystal eight-lobed cup and cover is inlaid with precious stones within a system of gold wire.  This object shows the taste for luxury objects in Northern India in the 19th century. In Mughal India there was a great revival in the art of rock crystal carving, and Mughal craftsmen reached new heights of technical virtuosity especially during the reign of Shah Jahan (1628-1658). The motifs in the gem work and enamelling of flowers, plants, scrolling vines and animal forms allude to paradise gardens on earth. It would have been highly prized and made for a privileged few."},"nlpDate":"20201018182635","connectorId":0,"tags":{}}