{
  "id": "2016-00212-047",
  "title": "Photograph album of views and portraits in the Punjab, Cashmere, Ceylon, Burma, Penang, Singapore, and Java Gautama Buddha statue",
  "source": "Bumblebee",
  "path": "./Data/json/",
  "content": "\n  accession_no_csv: 2016-00212-047\n\n  Image: \n\n  object_work_type: black-and-white photographs\n\n  title_text: Photograph album of views and portraits in the Punjab\n Cashmere\n Ceylon\n Burma\n Penang\n Singapore\n and Java Gautama Buddha statue\n\n  preference: alternate main\n\n  title_language: \n\n  creator_2: John Thomson\n\n  creator_1: Thomson\n J. (John)\n 1837-1921\n\n  creator_role: photographers\n\n  creation_date: before 28 Jul 1876\n\n  creation_place_original_location: Singapore\n\n  inscriptions: \n\n  inscription_language: \n\n  shape: rectangular\n\n  materials_name: albumen (egg white protein) albumen paper paper (fiber product)\n\n  techniques_name: albumen process\n\n  object_colour: black-and-white (colors)\n\n  physical_appearance: This is a photograph of a Gautama Buddha statue. The seated Buddha statue has crossed legs\n with the left hand in the lap\n and right hand pointing to the ground with the palm facing inward. The seat is a carved decorated seat. The title is written at the bottom\n below the photograph.\n\n  subject_terms_1: Buddhas (visual works) Buddhism statues\n\n  subject_terms_2: Photographs Thomson\n J. (John)\n 1837-1921 Gautama Buddha Statues\n\n  subject_terms_3: Photography Buddhism\n",
  "createdDate": "20201120223706",
  "version": 0,
  "latest": false,
  "roles": [],
  "metadata": {
    "accession_no_csv": "2016-00212-047",
    "Image": "",
    "object_work_type": "black-and-white photographs",
    "title_text": "Photograph album of views and portraits in the Punjab, Cashmere, Ceylon, Burma, Penang, Singapore, and Java Gautama Buddha statue",
    "preference": "alternate main",
    "title_language": "",
    "creator_2": "John Thomson",
    "creator_1": "Thomson, J. (John), 1837-1921",
    "creator_role": "photographers",
    "creation_date": "before 28 Jul 1876",
    "creation_place_original_location": "Singapore",
    "inscriptions": "",
    "inscription_language": "",
    "shape": "rectangular",
    "materials_name": "albumen (egg white protein) albumen paper paper (fiber product)",
    "techniques_name": "albumen process",
    "object_colour": "black-and-white (colors)",
    "physical_appearance": "This is a photograph of a Gautama Buddha statue. The seated Buddha statue has crossed legs, with the left hand in the lap, and right hand pointing to the ground with the palm facing inward. The seat is a carved decorated seat. The title is written at the bottom, below the photograph.",
    "subject_terms_1": "Buddhas (visual works) Buddhism statues",
    "subject_terms_2": "Photographs Thomson, J. (John), 1837-1921 Gautama Buddha Statues",
    "subject_terms_3": "Photography Buddhism"
  },
  "nlpDate": "20201120223706",
  "connectorId": 0,
  "tags": {}
}