{
  "id": "2016-00657",
  "title": "36-ounce measuring graduate used for mixing the stop bath 36-ounce measuring graduate",
  "source": "Bumblebee",
  "path": "./Data/json/",
  "content": "\n  accession_no_csv: 2016-00657\n\n  Image: \n\n  object_work_type: graduates\n\n  title_text: 36-ounce measuring graduate used for mixing the stop bath 36-ounce measuring graduate\n\n  preference: main alternate\n\n  title_language: \n\n  creation_date: 1980s-1990s\n\n  creation_place_original_location: Singapore\n\n  inscriptions: \n\n  inscription_language: \n\n  shape: cylindrical\n\n  materials_name: glass (material)\n\n  techniques_name: forming (physical activity)\n\n  object_colour: colourless\n\n  physical_appearance: \\The image shows an empty measuring graduate. It is colourless and transparent. There are calibrated markings on the exterior of the measuring cylinder. A tape with the words\n \\\\Stop Bath\\\\\n\n  subject_terms_1: quantity measuring devices is pasted on the front of the measuring device. It is written in black ink. There are no cracks on the measuring cylinder.\\\n\n  subject_terms_2: photographic equipment Measuring instruments\n\n  subject_terms_3: Photography Equipment and supplies\n\n  subject_terms_4: Photography\n\n  context_21: The set of equipment was used by The Picture Farm Pte Ltd\n\n  context_22: 45 Jalan Pemimpin\n #09-00 Foo Wah Industrial Building\n Thomson\n Singapore\n\n  context_23: 1970 - present\n\n  context_24: 1970\n\n  sgcool_label_text: present\n",
  "createdDate": "20201125084531",
  "version": 0,
  "latest": false,
  "roles": [],
  "metadata": {
    "accession_no_csv": "2016-00657",
    "Image": "",
    "object_work_type": "graduates",
    "title_text": "36-ounce measuring graduate used for mixing the stop bath 36-ounce measuring graduate",
    "preference": "main alternate",
    "title_language": "",
    "creation_date": "1980s-1990s",
    "creation_place_original_location": "Singapore",
    "inscriptions": "",
    "inscription_language": "",
    "shape": "cylindrical",
    "materials_name": "glass (material)",
    "techniques_name": "forming (physical activity)",
    "object_colour": "colourless",
    "physical_appearance": "\"The image shows an empty measuring graduate. It is colourless and transparent. There are calibrated markings on the exterior of the measuring cylinder. A tape with the words, \"\"Stop Bath\"\"",
    "subject_terms_1": "quantity measuring devices is pasted on the front of the measuring device. It is written in black ink. There are no cracks on the measuring cylinder.\"",
    "subject_terms_2": "photographic equipment Measuring instruments",
    "subject_terms_3": "Photography Equipment and supplies",
    "subject_terms_4": "Photography",
    "context_21": "The set of equipment was used by The Picture Farm Pte Ltd",
    "context_22": "45 Jalan Pemimpin, #09-00 Foo Wah Industrial Building, Thomson, Singapore",
    "context_23": "1970 - present",
    "context_24": "1970",
    "sgcool_label_text": "present"
  },
  "nlpDate": "20201125084531",
  "connectorId": 0,
  "tags": {}
}