{
  "id": "2016-00362",
  "title": "A Pair of Mother of Pearl Doors",
  "source": "Bumblebee",
  "path": "./Data/json/",
  "content": "\n  accession_no_csv: 2016-00362\n\n  Image: \n\n  object_work_type: double doors\n\n  title_text: A Pair of Mother of Pearl Doors\n\n  preference: main\n\n  title_language: \n\n  creation_date: 1701 - 1800\n\n  creation_place_original_location: India\n\n  inscriptions: \n\n  inscription_language: \n\n  shape: rectangular\n\n  materials_name: mica (mineral) hardwood ormolu metal mother of pearl paint (coating)\n\n  techniques_name: forming (physical activity) woodcarving painting (coating) metalworking\n\n  object_colour: multicoloured\n\n  physical_appearance: The image shows a pair of doors. It is rectangular in shape. The ring handle on the left door panel is positioned slightly lower than the ring handle on the right door panel. There are geometric patterns as well as the motif of rosette all over the door stiles. The upper rail of the left door panel is cracked.\n\n  subject_terms_1: residential structures geometric patterns rosette (motif) floral patterns allover patterns\n\n  subject_terms_2: Motifs Doors\n\n  sgcool_label_text: This is a rare pair of Indian hardwood painted doors\n clad in mother-of-pearl and secured with gilt-metal pins and rosettes. On each narrow door\n there is a gilt-bronze ring handle. The surface of the doors is entirely decorated with a mother-of-pearl geometric design and inset with mother-of-pearl flowers overlaid on top of painted mica. These doors are made in the same Gujarati tradition as mother-of-pearl decorated objects made for the export market (mainly to Portugal) during the 16th and 17th centuries. During this period\n mother-of-pearl Kunstkammer works were highly sought after by European collectors. In terms of composition and technique\n these doors share the same decorative characteristics as the luxury caskets\n powder horns\n rifles and daggers produced in Gujarat.\n",
  "createdDate": "20201201203309",
  "version": 0,
  "latest": false,
  "roles": [],
  "metadata": {
    "accession_no_csv": "2016-00362",
    "Image": "",
    "object_work_type": "double doors",
    "title_text": "A Pair of Mother of Pearl Doors",
    "preference": "main",
    "title_language": "",
    "creation_date": "1701 - 1800",
    "creation_place_original_location": "India",
    "inscriptions": "",
    "inscription_language": "",
    "shape": "rectangular",
    "materials_name": "mica (mineral) hardwood ormolu metal mother of pearl paint (coating)",
    "techniques_name": "forming (physical activity) woodcarving painting (coating) metalworking",
    "object_colour": "multicoloured",
    "physical_appearance": "The image shows a pair of doors. It is rectangular in shape. The ring handle on the left door panel is positioned slightly lower than the ring handle on the right door panel. There are geometric patterns as well as the motif of rosette all over the door stiles. The upper rail of the left door panel is cracked.",
    "subject_terms_1": "residential structures geometric patterns rosette (motif) floral patterns allover patterns",
    "subject_terms_2": "Motifs Doors",
    "sgcool_label_text": "This is a rare pair of Indian hardwood painted doors, clad in mother-of-pearl and secured with gilt-metal pins and rosettes. On each narrow door, there is a gilt-bronze ring handle. The surface of the doors is entirely decorated with a mother-of-pearl geometric design and inset with mother-of-pearl flowers overlaid on top of painted mica. These doors are made in the same Gujarati tradition as mother-of-pearl decorated objects made for the export market (mainly to Portugal) during the 16th and 17th centuries. During this period, mother-of-pearl Kunstkammer works were highly sought after by European collectors. In terms of composition and technique, these doors share the same decorative characteristics as the luxury caskets, powder horns, rifles and daggers produced in Gujarat."
  },
  "nlpDate": "20201201203309",
  "connectorId": 0,
  "tags": {}
}