{"id":"2016-00212-077","title":"Photograph album of views and portraits in the Punjab, Cashmere, Ceylon, Burma, Penang, Singapore, and Java View in Buitenzorg, Java","source":"Bumblebee","path":"./Data/json/","content":"accession_no_csv:2016-00212-077\nImage:\nobject_work_type:black-and-white photographs\ntitle_text:Photograph album of views and portraits in the Punjab\n Cashmere\n Ceylon\n Burma\n Penang\n Singapore\n and Java View in Buitenzorg\n Java\npreference:alternate main\ntitle_language:\ncreator_2:John Thomson\ncreator_1:Thomson\n J. (John)\n 1837-1921\ncreator_role:photographers\ncreation_date:before 28 Jul 1876\ncreation_place_original_location:Singapore Bogor (Indonesia)\ninscriptions:\ninscription_language:\nshape:rectangular\nmaterials_name:albumen (egg white protein) albumen paper paper (fiber product)\ntechniques_name:albumen process\nobject_colour:black-and-white (colors)\nphysical_appearance:This is a photograph of a forested area in Buitenzorg (Bogor)\n Indonesia. The photograph shows thick vegetation\n with a river cutting across the photograph in the middle. On the bottom left\n there is a flight of stairs heading up a slope. There is a man on the stairs\n wearing long sleeved top and white pants\n with a hat. The edges of the photograph are curved. The title is written at the bottom-right\n below the photograph.\nsubject_terms_1:scenery (landscape) rivers forests (cultural landscapes)\nsubject_terms_2:Photographs Thomson\n J. (John)\n 1837-1921 Bogor (Indonesia) Rivers\nsubject_terms_3:Landscape photography Rivers","createdDate":"20201018182635","version":0,"latest":false,"roles":[],"metadata":{"accession_no_csv":"2016-00212-077","Image":"","object_work_type":"black-and-white photographs","title_text":"Photograph album of views and portraits in the Punjab, Cashmere, Ceylon, Burma, Penang, Singapore, and Java View in Buitenzorg, Java","preference":"alternate main","title_language":"","creator_2":"John Thomson","creator_1":"Thomson, J. (John), 1837-1921","creator_role":"photographers","creation_date":"before 28 Jul 1876","creation_place_original_location":"Singapore Bogor (Indonesia)","inscriptions":"","inscription_language":"","shape":"rectangular","materials_name":"albumen (egg white protein) albumen paper paper (fiber product)","techniques_name":"albumen process","object_colour":"black-and-white (colors)","physical_appearance":"This is a photograph of a forested area in Buitenzorg (Bogor), Indonesia. The photograph shows thick vegetation, with a river cutting across the photograph in the middle. On the bottom left, there is a flight of stairs heading up a slope. There is a man on the stairs, wearing long sleeved top and white pants, with a hat. The edges of the photograph are curved. The title is written at the bottom-right, below the photograph.","subject_terms_1":"scenery (landscape) rivers forests (cultural landscapes)","subject_terms_2":"Photographs Thomson, J. (John), 1837-1921 Bogor (Indonesia) Rivers","subject_terms_3":"Landscape photography Rivers"},"nlpDate":"20201018182635","connectorId":0,"tags":{}}