{
  "id": "2016-00307",
  "title": "Kaart der Zuyd-Wester Eylanden van Banda (Map of the South-wastern Banda Islands)",
  "source": "Bumblebee",
  "path": "./Data/json/",
  "content": "\n  accession_no_csv: 2016-00307\n\n  Image: \n\n  object_work_type: maps (documents) copper engravings (visual works)\n\n  title_text: Kaart der Zuyd-Wester Eylanden van Banda (Map of the South-wastern Banda Islands)\n\n  preference: main\n\n  title_language: \n\n  creator_2: Francois Valentijn\n\n  creator_1: Valentijn\n Francois\n 1666 - 1727\n\n  creator_role: mapmakers\n\n  creation_date: 1726\n\n  creation_place_original_location: Holland (Netherlands : Province)\n\n  inscriptions: \n\n  inscription_language: \n\n  scale_type: 1:15\n\n  shape: rectangular\n\n  materials_name: paper (fiber product) printing paper\n\n  techniques_name: mapmaking (process) colour printing\n\n  object_colour: multicoloured\n\n  physical_appearance: The map depicts the South-western region of the Banda islands. Different colours are used on the different islands\n ranging from pink to turquoise to yellow. The scale that is being utilized in this map is 1 : 15. There are no latitudes and longitudes on this map\n nor are there any black lines that extend out from the compass that is located on the upper right hand side of the map. On many of the islands\n there are pictorial representations of hills and mountains\n as well as trees.\n\n  subject_terms_1: islands (landforms) colonial settlements\n\n  subject_terms_2: Colonization depictions (visual works) Maps Islands East Indies Banda Islands (Indonesia) Nederlandsche Oost-Indische Compagnie\n\n  sgcool_label_text: Francois Valentijn (1666–1727) was a minister\n naturalist and writer who served the Dutch V.O.C. in the East Indies in the late 17th and early 18th centuries. His monumental work Oud en Nieuw Oost-Indien (Old and New East-India)\n published between 1724 and 1726\n offers a comprehensive mapping of the East Indies with a large selection of scale maps and views. This map of the South-western Banda islands was published in that work.\n",
  "createdDate": "20201201203309",
  "version": 0,
  "latest": false,
  "roles": [],
  "metadata": {
    "accession_no_csv": "2016-00307",
    "Image": "",
    "object_work_type": "maps (documents) copper engravings (visual works)",
    "title_text": "Kaart der Zuyd-Wester Eylanden van Banda (Map of the South-wastern Banda Islands)",
    "preference": "main",
    "title_language": "",
    "creator_2": "Francois Valentijn",
    "creator_1": "Valentijn, Francois, 1666 - 1727",
    "creator_role": "mapmakers",
    "creation_date": "1726",
    "creation_place_original_location": "Holland (Netherlands : Province)",
    "inscriptions": "",
    "inscription_language": "",
    "scale_type": "1:15",
    "shape": "rectangular",
    "materials_name": "paper (fiber product) printing paper",
    "techniques_name": "mapmaking (process) colour printing",
    "object_colour": "multicoloured",
    "physical_appearance": "The map depicts the South-western region of the Banda islands. Different colours are used on the different islands, ranging from pink to turquoise to yellow. The scale that is being utilized in this map is 1 : 15. There are no latitudes and longitudes on this map, nor are there any black lines that extend out from the compass that is located on the upper right hand side of the map. On many of the islands, there are pictorial representations of hills and mountains, as well as trees.",
    "subject_terms_1": "islands (landforms) colonial settlements",
    "subject_terms_2": "Colonization depictions (visual works) Maps Islands East Indies Banda Islands (Indonesia) Nederlandsche Oost-Indische Compagnie",
    "sgcool_label_text": "Francois Valentijn (1666–1727) was a minister, naturalist and writer who served the Dutch V.O.C. in the East Indies in the late 17th and early 18th centuries. His monumental work Oud en Nieuw Oost-Indien (Old and New East-India), published between 1724 and 1726, offers a comprehensive mapping of the East Indies with a large selection of scale maps and views. This map of the South-western Banda islands was published in that work."
  },
  "nlpDate": "20201201203309",
  "connectorId": 0,
  "tags": {}
}