{
  "id": "2016-00400",
  "title": "Nintendo 1983 Family Computer (Famicom) game console and tennis game",
  "source": "Bumblebee",
  "path": "./Data/json/",
  "content": "\n  accession_no_csv: 2016-00400\n\n  Image: \n\n  object_work_type: toys (recreational artifacts)\n\n  title_text: Nintendo 1983 Family Computer (Famicom) game console and tennis game\n\n  preference: main\n\n  title_language: \n\n  creator_2: Nintendo\n\n  creator_1: Nintendo Kabushiki Kaisha\n\n  creator_role: creators\n\n  creation_date: 1983\n\n  creation_place_original_location: Japan Singapore\n\n  inscriptions: \n\n  inscription_language: \n\n  shape: irregular\n\n  materials_name: paper (fiber product) plastic (organic material) metal\n\n  techniques_name: forming (physical activity) metalworking colour printing\n\n  object_colour: multicoloured\n\n  physical_appearance: \\The image depicts an electronic device for gaming and entertainment purposes\n as well as a gaming cartridge. There are two controllers with black buttons which are joined by wires. However\n they are not connected to the gaming console. There is a slot on the top of the gaming console that is the same length and width of the gaming cartridge. The gaming cartridge has the word\n \\\\Tennis\\\\\n\n  subject_terms_1: electronic (technology-related concept) play (recreation) technology (general associated concept) printed on it in capital letters. There is a speaker at the top of the electronic console brand name objects\n\n  subject_terms_2: as well as a speaker on one of the controllers. On the gaming console Video games Nintendo video games Toys Technology Brand name products Amusements\n\n  subject_terms_3: there is a \\u0027Reset\\u0027 and a \\u0027Power\\u0027 button which are maroon in colour\n\n  subject_terms_4: as well as an \\u0027Eject\\u0027 switch. \\\n\n  context_1: video games\n\n  context_2: Games\n",
  "createdDate": "20201125084535",
  "version": 0,
  "latest": false,
  "roles": [],
  "metadata": {
    "accession_no_csv": "2016-00400",
    "Image": "",
    "object_work_type": "toys (recreational artifacts)",
    "title_text": "Nintendo 1983 Family Computer (Famicom) game console and tennis game",
    "preference": "main",
    "title_language": "",
    "creator_2": "Nintendo",
    "creator_1": "Nintendo Kabushiki Kaisha",
    "creator_role": "creators",
    "creation_date": "1983",
    "creation_place_original_location": "Japan Singapore",
    "inscriptions": "",
    "inscription_language": "",
    "shape": "irregular",
    "materials_name": "paper (fiber product) plastic (organic material) metal",
    "techniques_name": "forming (physical activity) metalworking colour printing",
    "object_colour": "multicoloured",
    "physical_appearance": "\"The image depicts an electronic device for gaming and entertainment purposes, as well as a gaming cartridge. There are two controllers with black buttons which are joined by wires. However, they are not connected to the gaming console. There is a slot on the top of the gaming console that is the same length and width of the gaming cartridge. The gaming cartridge has the word, \"\"Tennis\"\"",
    "subject_terms_1": "electronic (technology-related concept) play (recreation) technology (general associated concept) printed on it in capital letters. There is a speaker at the top of the electronic console brand name objects",
    "subject_terms_2": "as well as a speaker on one of the controllers. On the gaming console Video games Nintendo video games Toys Technology Brand name products Amusements",
    "subject_terms_3": "there is a \u0027Reset\u0027 and a \u0027Power\u0027 button which are maroon in colour",
    "subject_terms_4": "as well as an \u0027Eject\u0027 switch. \"",
    "context_1": "video games",
    "context_2": "Games"
  },
  "nlpDate": "20201125084535",
  "connectorId": 0,
  "tags": {}
}