{"id":"2016-00217","title":"Ramakrishna Mission Singapore Group photograph at the Ramakrishna Mission Singapore","source":"Bumblebee","path":"./Data/json/","content":"accession_no_csv:2016-00217\nImage:\nobject_work_type:black-and-white photographs\ntitle_text:Ramakrishna Mission Singapore Group photograph at the Ramakrishna Mission Singapore\npreference:main alternate\ntitle_language:\ncreator_2:Choo Kong Studio\ncreator_1:Not indicated\ncreator_role:photography studios (organizations)\ncreation_date:1928\ncreation_place_original_location:Singapore\ninscriptions:\ninscription_language:\nshape:rectangular\nmaterials_name:paper (fiber product)\ntechniques_name:printing (process) photographic processes\nobject_colour:grey monochrome\nphysical_appearance:\\The image shows a photograph that is in black-and-white. There is no frame. At the bottom right hand side beyond the photograph\\u0027s border\n  \\\\Choo Kong Studio\\\\ and \\\\No 102 Serangoon Road\nsubject_terms_1:Singapore\\\\ are displayed. The image depicts a large group of people posing in front of a building. \\\\Ramakrishna Mission\\\\ is displayed at the top of the building above its balcony on the second level. The people who are sitting down on chairs are adults and the ones who are standing up are children and young adults religious centres religious institutions religious organizations religious schools (institutions) group portraits Hinduism circles (social groups) studio portraits\nsubject_terms_2:except for the front row where most of the children are kneeling on the ground. They are all looking towards the direction where the photograph was taken at. \\ Portraits\n Group Ramakrishna Mission Religious institutions Social groups Hinduism Portrait photography\nsubject_terms_3:religious (people) Ramakrishna Mission Singapore Ramakrishna Mission Temple (Place) Hinduism\nsubject_terms_4:Black-and-white photography\ncontext_1:Portrait photography\ncontext_22:This item was produced at a photographic studio called Choo Kong.\ncontext_23:No 102 Serangoon Road\n Singapore.\ncontext_24:Not indicated","createdDate":"20201119143405","version":0,"latest":false,"roles":[],"metadata":{"accession_no_csv":"2016-00217","Image":"","object_work_type":"black-and-white photographs","title_text":"Ramakrishna Mission Singapore Group photograph at the Ramakrishna Mission Singapore","preference":"main alternate","title_language":"","creator_2":"Choo Kong Studio","creator_1":"Not indicated","creator_role":"photography studios (organizations)","creation_date":"1928","creation_place_original_location":"Singapore","inscriptions":"","inscription_language":"","shape":"rectangular","materials_name":"paper (fiber product)","techniques_name":"printing (process) photographic processes","object_colour":"grey monochrome","physical_appearance":"\"The image shows a photograph that is in black-and-white. There is no frame. At the bottom right hand side beyond the photograph\u0027s border,  \"\"Choo Kong Studio\"\" and \"\"No 102 Serangoon Road","subject_terms_1":"Singapore\"\" are displayed. The image depicts a large group of people posing in front of a building. \"\"Ramakrishna Mission\"\" is displayed at the top of the building above its balcony on the second level. The people who are sitting down on chairs are adults and the ones who are standing up are children and young adults religious centres religious institutions religious organizations religious schools (institutions) group portraits Hinduism circles (social groups) studio portraits","subject_terms_2":"except for the front row where most of the children are kneeling on the ground. They are all looking towards the direction where the photograph was taken at. \" Portraits, Group Ramakrishna Mission Religious institutions Social groups Hinduism Portrait photography","subject_terms_3":"religious (people) Ramakrishna Mission Singapore Ramakrishna Mission Temple (Place) Hinduism","subject_terms_4":"Black-and-white photography","context_1":"Portrait photography","context_22":"This item was produced at a photographic studio called Choo Kong.","context_23":"No 102 Serangoon Road, Singapore.","context_24":"Not indicated"},"nlpDate":"20201119143405","connectorId":0,"tags":{}}