{
  "id": "2016-00188",
  "title": "Egammai Achi, Citizen of India Passport of Egammai Achi, Citizen of India",
  "source": "Bumblebee",
  "path": "./Data/json/",
  "content": "\n  accession_no_csv: 2016-00188\n\n  Image: \n\n  object_work_type: passports\n\n  title_text: Egammai Achi\n Citizen of India Passport of Egammai Achi\n Citizen of India\n\n  preference: main alternate\n\n  title_language: \n\n  creator_2: Ministry of External Affairs\n Regional Passport Office\n Madras\n\n  creator_1: India\n Ministry of External Affairs\n\n  creator_role: creators\n\n  creation_date: 19600119\n\n  creation_place_original_location: Chennai (India)\n\n  inscriptions: \n\n  inscription_language: \n\n  shape: rectangular\n\n  materials_name: paper (fiber product)\n\n  techniques_name: printing (process)\n\n  object_colour: navy blue\n\n  physical_appearance: \\The image shows a rectangular passport. It is navy blue in colour. The words \\\\Passport\\\\ and \\\\Republic of India\\\\ are stated on the front of the passport. Below the state emblem of India\n\n  subject_terms_1: there is a line of Hindi script. The state emblem consists of three lions standing back to back citizenship emblems (allegorical pictures)\n\n  subject_terms_2: on a base that has a wheel on its front.\\ Citizenship India Emblems\n State\n\n  subject_terms_3: citizenship papers\n\n  subject_terms_4: Passports\n",
  "createdDate": "20201120223706",
  "version": 0,
  "latest": false,
  "roles": [],
  "metadata": {
    "accession_no_csv": "2016-00188",
    "Image": "",
    "object_work_type": "passports",
    "title_text": "Egammai Achi, Citizen of India Passport of Egammai Achi, Citizen of India",
    "preference": "main alternate",
    "title_language": "",
    "creator_2": "Ministry of External Affairs, Regional Passport Office, Madras",
    "creator_1": "India, Ministry of External Affairs",
    "creator_role": "creators",
    "creation_date": "19600119",
    "creation_place_original_location": "Chennai (India)",
    "inscriptions": "",
    "inscription_language": "",
    "shape": "rectangular",
    "materials_name": "paper (fiber product)",
    "techniques_name": "printing (process)",
    "object_colour": "navy blue",
    "physical_appearance": "\"The image shows a rectangular passport. It is navy blue in colour. The words \"\"Passport\"\" and \"\"Republic of India\"\" are stated on the front of the passport. Below the state emblem of India",
    "subject_terms_1": "there is a line of Hindi script. The state emblem consists of three lions standing back to back citizenship emblems (allegorical pictures)",
    "subject_terms_2": "on a base that has a wheel on its front.\" Citizenship India Emblems, State",
    "subject_terms_3": "citizenship papers",
    "subject_terms_4": "Passports"
  },
  "nlpDate": "20201120223706",
  "connectorId": 0,
  "tags": {}
}