{"id":"2016-00667","title":"Paterson 35mm proof printer","source":"Bumblebee","path":"./Data/json/","content":"accession_no_csv:2016-00667\nImage:\nobject_work_type:contact printing frames packaging\ntitle_text:Paterson 35mm proof printer\npreference:main\ntitle_language:\ncreator_2:Paterson Photographic Equipment\ncreator_role:manufacturers\ncreation_date:1980s-1990s\ncreation_place_original_location:Singapore Tipton (England)\ninscriptions:\ninscription_language:\nshape:rectangular\nmaterials_name:plastic (organic material) metal\ntechniques_name:forming (physical activity) metalworking\nobject_colour:multicoloured\nphysical_appearance:The image shows a packaging which contains the name and logo of a company called \\u0027Paterson\\u0027. The rectangular box is predominantly red in colour. The images of the proof printer and two contact prints appear at the middle of the packaging. Four lines describing the features of the printer are stated near the bottom of the box. There are some slight tears on the lower and upper left edges of the box.\nsubject_terms_1:photographic processing equipment printers (output devices) contact prints\nsubject_terms_2:Photography Equipment and supplies Packaging Contact printing Computer printers\nsubject_terms_3:Photography\ncontext_20:The set of equipment was used by The Picture Farm Pte Ltd\ncontext_21:45 Jalan Pemimpin\n #09-00 Foo Wah Industrial Building\n Thomson\n Singapore\ncontext_22:1970 - present\ncontext_23:1970\ncontext_24:present\nsgcool_label_text:A proof printer is used produce contact prints. This proof printer is part of the darkroom photography equipment that was previously used by The Picture Farm\n which was set up by the renowned photographer Willie Tang.","createdDate":"20201018182635","version":0,"latest":false,"roles":[],"metadata":{"accession_no_csv":"2016-00667","Image":"","object_work_type":"contact printing frames packaging","title_text":"Paterson 35mm proof printer","preference":"main","title_language":"","creator_2":"Paterson Photographic Equipment","creator_role":"manufacturers","creation_date":"1980s-1990s","creation_place_original_location":"Singapore Tipton (England)","inscriptions":"","inscription_language":"","shape":"rectangular","materials_name":"plastic (organic material) metal","techniques_name":"forming (physical activity) metalworking","object_colour":"multicoloured","physical_appearance":"The image shows a packaging which contains the name and logo of a company called \u0027Paterson\u0027. The rectangular box is predominantly red in colour. The images of the proof printer and two contact prints appear at the middle of the packaging. Four lines describing the features of the printer are stated near the bottom of the box. There are some slight tears on the lower and upper left edges of the box.","subject_terms_1":"photographic processing equipment printers (output devices) contact prints","subject_terms_2":"Photography Equipment and supplies Packaging Contact printing Computer printers","subject_terms_3":"Photography","context_20":"The set of equipment was used by The Picture Farm Pte Ltd","context_21":"45 Jalan Pemimpin, #09-00 Foo Wah Industrial Building, Thomson, Singapore","context_22":"1970 - present","context_23":"1970","context_24":"present","sgcool_label_text":"A proof printer is used produce contact prints. This proof printer is part of the darkroom photography equipment that was previously used by The Picture Farm, which was set up by the renowned photographer Willie Tang."},"nlpDate":"20201018182635","connectorId":0,"tags":{}}