{
  "id": "2016-00612-002",
  "title": "4 photographs of S Gopalakrishnan singing at various temple performances S Gopalakrishnan singing at various temple performances #2",
  "source": "Bumblebee",
  "path": "./Data/json/",
  "content": "\n  accession_no_csv: 2016-00612-002\n\n  Image: \n\n  object_work_type: colour photographs\n\n  title_text: 4 photographs of S Gopalakrishnan singing at various temple performances S Gopalakrishnan singing at various temple performances #2\n\n  preference: main alternate\n\n  title_language: \n\n  creation_date: Late 1980s-Early 2000s\n\n  creation_place_original_location: Singapore\n\n  styles_periods_indexing_terms: Indian (South Asian)\n\n  inscriptions: \n\n  inscription_language: \n\n  shape: rectangular\n\n  materials_name: paper (fiber product)\n\n  techniques_name: printing (process) photographic processes\n\n  object_colour: multicoloured\n\n  physical_appearance: The image shows a rectangular photograph that is in colour. The photograph features four adult males sitting down. Three of them are playing with musical instruments\n namely a harmonium\n violin\n and tabla. The other one is singing into two microphones. There are numerous people in the background. Some of them are sitting down whole others are worshipping. he background of the photograph suggests that it was taken in the interior of a temple.\n\n  subject_terms_1: temples (buidings) singers musical performances musicians music (performing arts)\n\n  subject_terms_2: Carnatic music Colour photography Tamil (Indic people) Hindu temples Singers Musicians Performances\n\n  subject_terms_3: Temples Performing Arts Photography Indian music Musicians\n\n  sgcool_label_text: Mr. S Gopalakrishnan (b. in 1920 in Tanjavur) was a prominent violinist\n and Carnatic singer. He arrived in Singapore in 1939 and actively participated in the Indian classical music scene here. Mr Gopalakrishnan performed alongside veterans of classical performers such as Pandit M Ramalingam and MV Gurusamy at temple and other music festivals. He also taught violin lessons at the Singapore Malayalee Association from the 1970s to 2000s. He was a member of the Tamils Reform Association and performed his wedding according to the principles of the Self-Respect Movement. He was also employed as a compositor at the Far East Air Force from 1954 to 1970.\n",
  "createdDate": "20201201203308",
  "version": 0,
  "latest": false,
  "roles": [],
  "metadata": {
    "accession_no_csv": "2016-00612-002",
    "Image": "",
    "object_work_type": "colour photographs",
    "title_text": "4 photographs of S Gopalakrishnan singing at various temple performances S Gopalakrishnan singing at various temple performances #2",
    "preference": "main alternate",
    "title_language": "",
    "creation_date": "Late 1980s-Early 2000s",
    "creation_place_original_location": "Singapore",
    "styles_periods_indexing_terms": "Indian (South Asian)",
    "inscriptions": "",
    "inscription_language": "",
    "shape": "rectangular",
    "materials_name": "paper (fiber product)",
    "techniques_name": "printing (process) photographic processes",
    "object_colour": "multicoloured",
    "physical_appearance": "The image shows a rectangular photograph that is in colour. The photograph features four adult males sitting down. Three of them are playing with musical instruments, namely a harmonium, violin, and tabla. The other one is singing into two microphones. There are numerous people in the background. Some of them are sitting down whole others are worshipping. he background of the photograph suggests that it was taken in the interior of a temple.",
    "subject_terms_1": "temples (buidings) singers musical performances musicians music (performing arts)",
    "subject_terms_2": "Carnatic music Colour photography Tamil (Indic people) Hindu temples Singers Musicians Performances",
    "subject_terms_3": "Temples Performing Arts Photography Indian music Musicians",
    "sgcool_label_text": "Mr. S Gopalakrishnan (b. in 1920 in Tanjavur) was a prominent violinist, and Carnatic singer. He arrived in Singapore in 1939 and actively participated in the Indian classical music scene here. Mr Gopalakrishnan performed alongside veterans of classical performers such as Pandit M Ramalingam and MV Gurusamy at temple and other music festivals. He also taught violin lessons at the Singapore Malayalee Association from the 1970s to 2000s. He was a member of the Tamils Reform Association and performed his wedding according to the principles of the Self-Respect Movement. He was also employed as a compositor at the Far East Air Force from 1954 to 1970."
  },
  "nlpDate": "20201201203308",
  "connectorId": 0,
  "tags": {}
}