{"id":"2016-00148","title":"Dashavatara Ganjifa Playing Card Box Complete Dashavatara Ganjifa Playing Card Set \u0026 Box","source":"Bumblebee","path":"./Data/json/","content":"accession_no_csv:2016-00148\nImage:\nobject_work_type:playing card boxes\ntitle_text:Dashavatara Ganjifa Playing Card Box Complete Dashavatara Ganjifa Playing Card Set \\u0026 Box\npreference:main alternate\ntitle_language:\ncreation_date:1900 - 1939\ncreation_place_original_location:Maharashtra (India)\ninscriptions:\ninscription_language:\nshape:rectangular cuboid\nmaterials_name:wood (plant material) paint (coating)\ntechniques_name:woodcarving painting (image-making)\nobject_colour:multicoloured\nphysical_appearance:The image depicts a box. The sides and the edges of the box have been worn out. Each exterior face of the box is predominantly red\n surrounded by a yellow with dots painted on it as the motif. An image of a Hindu avatar of Vishnu\n in a seated position\n is depicted on each side of the box.\nsubject_terms_1:card games (game sets) recreation entertaining cultural diffusion avatara Hinduism dots\nsubject_terms_2:Boxes Card games Amusements Culture diffusion Avatars (Religion) Hinduism Motifs\nsubject_terms_3:Hinduism\nsgcool_label_text:Ganjifa is pan-Indian\n played in its various forms in Indian regions including Maharashtra\n Rajasthan\n Bengal\n Orissa\n Karnataka\n among others. The ganjifa game of cards originated in Persia but it really flourished in India where the game developed in various forms. Meanwhile\n in Persia\n the game largely died out. Initially in India\n the game was played by the Mughals of northern India\n but it soon spread to most parts of the country. The proposed set underscore a rare aspect of Indian heritage – a craft tradition akin to miniature painting and a lesser known Indian game.","createdDate":"20201119143405","version":0,"latest":false,"roles":[],"metadata":{"accession_no_csv":"2016-00148","Image":"","object_work_type":"playing card boxes","title_text":"Dashavatara Ganjifa Playing Card Box Complete Dashavatara Ganjifa Playing Card Set \u0026 Box","preference":"main alternate","title_language":"","creation_date":"1900 - 1939","creation_place_original_location":"Maharashtra (India)","inscriptions":"","inscription_language":"","shape":"rectangular cuboid","materials_name":"wood (plant material) paint (coating)","techniques_name":"woodcarving painting (image-making)","object_colour":"multicoloured","physical_appearance":"The image depicts a box. The sides and the edges of the box have been worn out. Each exterior face of the box is predominantly red, surrounded by a yellow with dots painted on it as the motif. An image of a Hindu avatar of Vishnu, in a seated position, is depicted on each side of the box.","subject_terms_1":"card games (game sets) recreation entertaining cultural diffusion avatara Hinduism dots","subject_terms_2":"Boxes Card games Amusements Culture diffusion Avatars (Religion) Hinduism Motifs","subject_terms_3":"Hinduism","sgcool_label_text":"Ganjifa is pan-Indian, played in its various forms in Indian regions including Maharashtra, Rajasthan, Bengal, Orissa, Karnataka, among others. The ganjifa game of cards originated in Persia but it really flourished in India where the game developed in various forms. Meanwhile, in Persia, the game largely died out. Initially in India, the game was played by the Mughals of northern India, but it soon spread to most parts of the country. The proposed set underscore a rare aspect of Indian heritage – a craft tradition akin to miniature painting and a lesser known Indian game."},"nlpDate":"20201119143405","connectorId":0,"tags":{}}