{
  "id": "2016-00420",
  "title": "Dompet with Pomegranate and Mango Designs Beaded purse with pomegranate and mango designs",
  "source": "Bumblebee",
  "path": "./Data/json/",
  "content": "\n  accession_no_csv: 2016-00420\n\n  Image: \n\n  object_work_type: purses (ladies\\u0027 accessories)\n\n  title_text: Dompet with Pomegranate and Mango Designs Beaded purse with pomegranate and mango designs\n\n  preference: main alternate\n\n  title_language: \n\n  creation_date: 20th century\n\n  creation_place_original_location: Indonesia\n\n  inscriptions: \n\n  inscription_language: \n\n  shape: semicircular\n\n  materials_name: glass (material) velvet (fabric weave)\n\n  techniques_name: sewing (needleworking technique) embroidering\n\n  object_colour: multicolored\n\n  physical_appearance: This is a beaded purse in a semicircular shape. It is made from red velvet\n and decorated with embroided beads and stitching. There is a bead button at the bottom-center\n holding the flap closed. The purse is decorated with floral motifs. In the center\n there is a beaded design of a pomegranate\n surrounded by flowers.\n\n  subject_terms_1: pouches beadwork (visual works) plant-derived motifs\n\n  subject_terms_2: Motifs Pouches (Containers) Beadwork\n\n  subject_terms_3: Decorative arts\n\n  sgcool_label_text: This dompet has a unique semi-circular shape quite unlike other envelope purses. The front flap is adorned with a fully beaded bouquet of flowers and what is possibly a pomegranate\n a symbol of fertility. The flap opens to reveal a cluster of flowers and mango fruits. This dompet is also embroidered with gold thread in a style known as tekad timbol. Tekad timbol was not only practised by the Peranakans but also by the Malays\n for whom it was better known as tekat.\n",
  "createdDate": "20201201203309",
  "version": 0,
  "latest": false,
  "roles": [],
  "metadata": {
    "accession_no_csv": "2016-00420",
    "Image": "",
    "object_work_type": "purses (ladies\u0027 accessories)",
    "title_text": "Dompet with Pomegranate and Mango Designs Beaded purse with pomegranate and mango designs",
    "preference": "main alternate",
    "title_language": "",
    "creation_date": "20th century",
    "creation_place_original_location": "Indonesia",
    "inscriptions": "",
    "inscription_language": "",
    "shape": "semicircular",
    "materials_name": "glass (material) velvet (fabric weave)",
    "techniques_name": "sewing (needleworking technique) embroidering",
    "object_colour": "multicolored",
    "physical_appearance": "This is a beaded purse in a semicircular shape. It is made from red velvet, and decorated with embroided beads and stitching. There is a bead button at the bottom-center, holding the flap closed. The purse is decorated with floral motifs. In the center, there is a beaded design of a pomegranate, surrounded by flowers.",
    "subject_terms_1": "pouches beadwork (visual works) plant-derived motifs",
    "subject_terms_2": "Motifs Pouches (Containers) Beadwork",
    "subject_terms_3": "Decorative arts",
    "sgcool_label_text": "This dompet has a unique semi-circular shape quite unlike other envelope purses. The front flap is adorned with a fully beaded bouquet of flowers and what is possibly a pomegranate, a symbol of fertility. The flap opens to reveal a cluster of flowers and mango fruits. This dompet is also embroidered with gold thread in a style known as tekad timbol. Tekad timbol was not only practised by the Peranakans but also by the Malays, for whom it was better known as tekat."
  },
  "nlpDate": "20201201203309",
  "connectorId": 0,
  "tags": {}
}