{
  "id": "2016-00109",
  "title": "Testimonial letter about Mr Appavoo Kandiar by United Engineers Limited’s Contractor’s Engineer Testimonial letter given to Mr Appavoo Kandiar by United Engineers Limited’s Contractor’s Engineer",
  "source": "Bumblebee",
  "path": "./Data/json/",
  "content": "\n  accession_no_csv: 2016-00109\n\n  Image: \n\n  object_work_type: testimonials\n\n  title_text: Testimonial letter about Mr Appavoo Kandiar by United Engineers Limited’s Contractor’s Engineer Testimonial letter given to Mr Appavoo Kandiar by United Engineers Limited’s Contractor’s Engineer\n\n  preference: main alternate\n\n  title_language: \n\n  creator_2: United Engineers Ltd\n\n  creator_role: firms\n\n  creation_date: 19300306\n\n  creation_place_original_location: Singapore\n\n  inscriptions: \n\n  inscription_language: \n\n  shape: rectangular\n\n  materials_name: paper (fiber product)\n\n  techniques_name: printing (process)\n\n  object_colour: multicoloured\n\n  physical_appearance: \\The image shows a rectangular letter. There are two punch holes at the top of the paper. The letter is not addressed to anyone in particular\n and \\\\To Whom It May Concern\\\\ serves as the salutation. At the end of the letter\n\n  subject_terms_1: there is a signature as well as the words \\\\United Engineers letters of recommendation contractors companies engineers\n\n  subject_terms_2: Contractors Ltd\\\\ and \\\\Civic Engineering Department\\\\. There are some stains present on the letter and a tiny hole can be seen near the top left hand corner.\\ Engineers Letters Employment references\n\n  subject_terms_3: Letters Kandiar\n Appavoo letters (correspondence)\n\n  subject_terms_4: Business enterprises\n\n  context_1: Business enterprises\n",
  "createdDate": "20201125084540",
  "version": 0,
  "latest": false,
  "roles": [],
  "metadata": {
    "accession_no_csv": "2016-00109",
    "Image": "",
    "object_work_type": "testimonials",
    "title_text": "Testimonial letter about Mr Appavoo Kandiar by United Engineers Limited’s Contractor’s Engineer Testimonial letter given to Mr Appavoo Kandiar by United Engineers Limited’s Contractor’s Engineer",
    "preference": "main alternate",
    "title_language": "",
    "creator_2": "United Engineers Ltd",
    "creator_role": "firms",
    "creation_date": "19300306",
    "creation_place_original_location": "Singapore",
    "inscriptions": "",
    "inscription_language": "",
    "shape": "rectangular",
    "materials_name": "paper (fiber product)",
    "techniques_name": "printing (process)",
    "object_colour": "multicoloured",
    "physical_appearance": "\"The image shows a rectangular letter. There are two punch holes at the top of the paper. The letter is not addressed to anyone in particular, and \"\"To Whom It May Concern\"\" serves as the salutation. At the end of the letter",
    "subject_terms_1": "there is a signature as well as the words \"\"United Engineers letters of recommendation contractors companies engineers",
    "subject_terms_2": "Contractors Ltd\"\" and \"\"Civic Engineering Department\"\". There are some stains present on the letter and a tiny hole can be seen near the top left hand corner.\" Engineers Letters Employment references",
    "subject_terms_3": "Letters Kandiar, Appavoo letters (correspondence)",
    "subject_terms_4": "Business enterprises",
    "context_1": "Business enterprises"
  },
  "nlpDate": "20201125084540",
  "connectorId": 0,
  "tags": {}
}