{"id":"2016-00212-068","title":"Photograph album of views and portraits in the Punjab, Cashmere, Ceylon, Burma, Penang, Singapore, and Java Wilhelm\u0027s Kirk, Koning\u0027s Plein, Batavia, Java","source":"Bumblebee","path":"./Data/json/","content":"accession_no_csv:2016-00212-068\nImage:\nobject_work_type:black-and-white photographs\ntitle_text:Photograph album of views and portraits in the Punjab\n Cashmere\n Ceylon\n Burma\n Penang\n Singapore\n and Java Wilhelm\\u0027s Kirk\n Koning\\u0027s Plein\n Batavia\n Java\npreference:alternate main\ntitle_language:\ncreator_2:John Thomson\ncreator_1:Thomson\n J. (John)\n 1837-1921\ncreator_role:photographers\ncreation_date:before 28 Jul 1876\ncreation_place_original_location:Singapore Jakarta (Indonesia)\ninscriptions:\ninscription_language:\nshape:rectangular\nmaterials_name:albumen (egg white protein) albumen paper paper (fiber product)\ntechniques_name:albumen process\nobject_colour:black-and-white (colors)\nphysical_appearance:This photograph shows the Willemskerk church in Batavia (Jakarta) in Indonesia. The church has a circular center\n with a dome top\n and a pediment on the right. The neoclassical architecture of the building features large\n tall columns. The church sits on a bricked platform\n with steps leading up to the front. In front of the church\n there are a few cows grazing on the grass. The edges of the photograph are rounded. The title is written at the bottom\n below the photograph.\nsubject_terms_1:colonization churches (buildings) Protestantism Neoclassical\nsubject_terms_2:Photographs Thomson\n J. (John)\n 1837-1921 Jakarta (Indonesia) Colonization Protestant churches Protestantism Neoclassical (Architecture)\nsubject_terms_3:Photography Churches","createdDate":"20201018182635","version":0,"latest":false,"roles":[],"metadata":{"accession_no_csv":"2016-00212-068","Image":"","object_work_type":"black-and-white photographs","title_text":"Photograph album of views and portraits in the Punjab, Cashmere, Ceylon, Burma, Penang, Singapore, and Java Wilhelm\u0027s Kirk, Koning\u0027s Plein, Batavia, Java","preference":"alternate main","title_language":"","creator_2":"John Thomson","creator_1":"Thomson, J. (John), 1837-1921","creator_role":"photographers","creation_date":"before 28 Jul 1876","creation_place_original_location":"Singapore Jakarta (Indonesia)","inscriptions":"","inscription_language":"","shape":"rectangular","materials_name":"albumen (egg white protein) albumen paper paper (fiber product)","techniques_name":"albumen process","object_colour":"black-and-white (colors)","physical_appearance":"This photograph shows the Willemskerk church in Batavia (Jakarta) in Indonesia. The church has a circular center, with a dome top, and a pediment on the right. The neoclassical architecture of the building features large, tall columns. The church sits on a bricked platform, with steps leading up to the front. In front of the church, there are a few cows grazing on the grass. The edges of the photograph are rounded. The title is written at the bottom, below the photograph.","subject_terms_1":"colonization churches (buildings) Protestantism Neoclassical","subject_terms_2":"Photographs Thomson, J. (John), 1837-1921 Jakarta (Indonesia) Colonization Protestant churches Protestantism Neoclassical (Architecture)","subject_terms_3":"Photography Churches"},"nlpDate":"20201018182635","connectorId":0,"tags":{}}