{"id":"2016-00350","title":"Claës Fredrik Hornstedt examining natural history specimens, attended by his slave Ali, in Java","source":"Bumblebee","path":"./Data/json/","content":"accession_no_csv:2016-00350\nImage:\nobject_work_type:watercolours (paintings) paintings (visual works)\ntitle_text:Claës Fredrik Hornstedt examining natural history specimens\n attended by his slave Ali\n in Java\npreference:main\ntitle_language:\ncreator_2:Not Indicated\ncreator_1:Not Indicated\ncreator_role:Not Indicated\ncreation_date:1780s\ncreation_place_original_location:Stockholm (Sweden)\ninscriptions:\ninscription_language:\nshape:rectangular\nmaterials_name:paper (fiber product)\ntechniques_name:watercolour painting (technique)\nobject_colour:multicoloured\nphysical_appearance:This painting depicts the natural historian Claës Fredrik Hornstedt\n alongside with his slave who is named as Ali\n examing several animal specimens behind a table. The background of the painting comprises of trees and the sky. The painting has a wooden frame and a pink border. Hornsted\\u0027s skin is painted as pale whereas Ali\\u0027s skin is painted as dark brown. Hornsted is also dressed totally in a white colonial outfit while Ali only adorns a pair of brown shorts and is barefoot. There is a crocodile and a monkey standing on the ground alongside Hornstedt and Ali. There is one dead bird on the table and another in a transparent jar.Ali is holding an animal in his hands and Hornstedt is looking at it.\nsubject_terms_1:slaves (people) natural history naturalists colonial settlements\nsubject_terms_2:Colonization Slaves Natural history Hornstedt\n C.F. (Clas Fredrik)\n 1758 - 1809 Watercolour painting Jakarta (Indonesia) Naturalist\nsubject_terms_3:Watercolour Painting Visual arts\nsgcool_label_text:\\This watercolour depicts the Swedish naturalist Claës Fredrik Hornstedt examining natural history specimens. The setting for this scene is Java\n where Hornstedt spent a year between 1783 and 1784\n supported by the Batavian Society of Arts and Science. He is attended to by a slave named Ali\n as indicated in the accompanying inscription\n Ali being a name he gave to his slave in replacement of his \\\\long Javanese name\\\\. The inscription is dated 1788","createdDate":"20201018182635","version":0,"latest":false,"roles":[],"metadata":{"accession_no_csv":"2016-00350","Image":"","object_work_type":"watercolours (paintings) paintings (visual works)","title_text":"Claës Fredrik Hornstedt examining natural history specimens, attended by his slave Ali, in Java","preference":"main","title_language":"","creator_2":"Not Indicated","creator_1":"Not Indicated","creator_role":"Not Indicated","creation_date":"1780s","creation_place_original_location":"Stockholm (Sweden)","inscriptions":"","inscription_language":"","shape":"rectangular","materials_name":"paper (fiber product)","techniques_name":"watercolour painting (technique)","object_colour":"multicoloured","physical_appearance":"This painting depicts the natural historian Claës Fredrik Hornstedt, alongside with his slave who is named as Ali, examing several animal specimens behind a table. The background of the painting comprises of trees and the sky. The painting has a wooden frame and a pink border. Hornsted\u0027s skin is painted as pale whereas Ali\u0027s skin is painted as dark brown. Hornsted is also dressed totally in a white colonial outfit while Ali only adorns a pair of brown shorts and is barefoot. There is a crocodile and a monkey standing on the ground alongside Hornstedt and Ali. There is one dead bird on the table and another in a transparent jar.Ali is holding an animal in his hands and Hornstedt is looking at it.","subject_terms_1":"slaves (people) natural history naturalists colonial settlements","subject_terms_2":"Colonization Slaves Natural history Hornstedt, C.F. (Clas Fredrik), 1758 - 1809 Watercolour painting Jakarta (Indonesia) Naturalist","subject_terms_3":"Watercolour Painting Visual arts","sgcool_label_text":"\"This watercolour depicts the Swedish naturalist Claës Fredrik Hornstedt examining natural history specimens. The setting for this scene is Java, where Hornstedt spent a year between 1783 and 1784, supported by the Batavian Society of Arts and Science. He is attended to by a slave named Ali, as indicated in the accompanying inscription, Ali being a name he gave to his slave in replacement of his \"\"long Javanese name\"\". The inscription is dated 1788"},"nlpDate":"20201018182635","connectorId":0,"tags":{}}