{
  "id": "2016-00518",
  "title": "8 Toy Cars [8 AFX Aurora Slot Cars] Box of 8 Toy Cars [8 AFX Aurora Slot Cars]  8 Toy Cars [8 AFX Aurora Slot Cars] Box of 8 Toy Cars [8 AFX Aurora Slot Cars]",
  "source": "Bumblebee",
  "path": "./Data/json/",
  "content": "\n  accession_no_csv: 2016-00518\n\n  Image: \n\n  object_work_type: miniatures (toys) miniatures (toys)\n\n  title_text: 8 Toy Cars [8 AFX Aurora Slot Cars] Box of 8 Toy Cars [8 AFX Aurora Slot Cars]  8 Toy Cars [8 AFX Aurora Slot Cars] Box of 8 Toy Cars [8 AFX Aurora Slot Cars]\n\n  preference: main alternate main alternate\n\n  title_language: \n\n  creator_2: Aurora Products Corporation Asia Pte Ltd Aurora Products Corporation Asia Pte Ltd\n\n  creator_1: Not indicated Not indicated\n\n  creator_role: toymakers manufacturers toymakers manufacturers\n\n  creation_date: 1977 - 1983 1977 - 1983\n\n  creation_place_original_location: Singapore Singapore\n\n  styles_periods_indexing_terms: NA NA\n\n  inscriptions: \n\n  inscription_language: \n\n  scale_type: NA NA\n\n  shape: irregular irregular\n\n  materials_name: plastic (organic material) metal plastic (organic material) metal\n\n  techniques_name: forming (physical activity) toy making metalworking forming (physical activity) toy making metalworking\n\n  object_colour: multicoloured multicoloured\n\n  edition_description: NA NA\n\n  physical_appearance: The image displays a number of toy cars. They are placed on an open transparent plastic packaging. The cars come with an assortment of colours. The miniature cars are of different structural designs and some of them have bumpers attached. A couple of the toy cars are wrapped in plastic\n while the majority are out in the open.   The image displays a number of toy cars. They are placed on an open transparent plastic packaging. The cars come with an assortment of colours. The miniature cars are of different structural designs and some of them have bumpers attached. A couple of the toy cars are wrapped in plastic\n while the majority are out in the open.\n\n  subject_terms_1: brand name objects entertaining brand name objects entertaining\n\n  subject_terms_2: Brand name products Miniature objects Amusements Slot cars Brand name products Miniature objects Amusements Slot cars\n\n  subject_terms_3: NA NA\n\n  subject_terms_4: NA NA\n\n  context_1: NA NA\n\n  context_2: NA NA\n\n  context_3: NA NA\n\n  context_4: NA NA\n\n  context_5: NA NA\n\n  context_6: NA NA\n\n  context_7: NA NA\n\n  context_8: NA NA\n\n  context_9: NA NA\n\n  context_10: NA NA\n\n  context_11: NA NA\n\n  context_12: NA NA\n\n  context_13: NA NA\n\n  context_14: NA NA\n\n  context_15: NA NA\n\n  context_16: NA NA\n\n  context_17: NA NA\n\n  context_18: NA NA\n\n  context_19: NA NA\n\n  context_20: NA NA\n\n  context_21: NA NA\n\n  context_22: NA NA\n\n  context_23: NA NA\n\n  context_24: NA NA\n\n  sgcool_label_text: The American Plastics corporation\n Aurora Products Corporation Asia Pte Ltd\n produced slot cars from 1974-1983 such as the ones features in this box. Its main factory opened on 31 March 1977 and manufactured a wide range of quality electric toy-racing cars for the world market (primarily USA\n Europe and Australia). \\r\\n\\r\\nThese electric toy cars\n also known as slot cars\n ran on a track with grooves or slots that guided the cars. Primarily slot cars were used in the competitive hobby of slot car racing. Typically modelled on actual racing automobiles\n slot cars share a relationship with popular interest in racing and have been featured at F1 events since 2010 in Singapore. The American Plastics corporation\n Aurora Products Corporation Asia Pte Ltd\n produced slot cars from 1974-1983 such as the ones features in this box. Its main factory opened on 31 March 1977 and manufactured a wide range of quality electric toy-racing cars for the world market (primarily USA\n Europe and Australia). \\r\\n\\r\\nThese electric toy cars\n also known as slot cars\n ran on a track with grooves or slots that guided the cars. Primarily slot cars were used in the competitive hobby of slot car racing. Typically modelled on actual racing automobiles\n slot cars share a relationship with popular interest in racing and have been featured at F1 events since 2010 in Singapore.\n",
  "createdDate": "20201120223707",
  "version": 0,
  "latest": false,
  "roles": [],
  "metadata": {
    "accession_no_csv": "2016-00518",
    "Image": "",
    "object_work_type": "miniatures (toys) miniatures (toys)",
    "title_text": "8 Toy Cars [8 AFX Aurora Slot Cars] Box of 8 Toy Cars [8 AFX Aurora Slot Cars]  8 Toy Cars [8 AFX Aurora Slot Cars] Box of 8 Toy Cars [8 AFX Aurora Slot Cars]",
    "preference": "main alternate main alternate",
    "title_language": "",
    "creator_2": "Aurora Products Corporation Asia Pte Ltd Aurora Products Corporation Asia Pte Ltd",
    "creator_1": "Not indicated Not indicated",
    "creator_role": "toymakers manufacturers toymakers manufacturers",
    "creation_date": "1977 - 1983 1977 - 1983",
    "creation_place_original_location": "Singapore Singapore",
    "styles_periods_indexing_terms": "NA NA",
    "inscriptions": "",
    "inscription_language": "",
    "scale_type": "NA NA",
    "shape": "irregular irregular",
    "materials_name": "plastic (organic material) metal plastic (organic material) metal",
    "techniques_name": "forming (physical activity) toy making metalworking forming (physical activity) toy making metalworking",
    "object_colour": "multicoloured multicoloured",
    "edition_description": "NA NA",
    "physical_appearance": "The image displays a number of toy cars. They are placed on an open transparent plastic packaging. The cars come with an assortment of colours. The miniature cars are of different structural designs and some of them have bumpers attached. A couple of the toy cars are wrapped in plastic, while the majority are out in the open.   The image displays a number of toy cars. They are placed on an open transparent plastic packaging. The cars come with an assortment of colours. The miniature cars are of different structural designs and some of them have bumpers attached. A couple of the toy cars are wrapped in plastic, while the majority are out in the open.",
    "subject_terms_1": "brand name objects entertaining brand name objects entertaining",
    "subject_terms_2": "Brand name products Miniature objects Amusements Slot cars Brand name products Miniature objects Amusements Slot cars",
    "subject_terms_3": "NA NA",
    "subject_terms_4": "NA NA",
    "context_1": "NA NA",
    "context_2": "NA NA",
    "context_3": "NA NA",
    "context_4": "NA NA",
    "context_5": "NA NA",
    "context_6": "NA NA",
    "context_7": "NA NA",
    "context_8": "NA NA",
    "context_9": "NA NA",
    "context_10": "NA NA",
    "context_11": "NA NA",
    "context_12": "NA NA",
    "context_13": "NA NA",
    "context_14": "NA NA",
    "context_15": "NA NA",
    "context_16": "NA NA",
    "context_17": "NA NA",
    "context_18": "NA NA",
    "context_19": "NA NA",
    "context_20": "NA NA",
    "context_21": "NA NA",
    "context_22": "NA NA",
    "context_23": "NA NA",
    "context_24": "NA NA",
    "sgcool_label_text": "The American Plastics corporation, Aurora Products Corporation Asia Pte Ltd, produced slot cars from 1974-1983 such as the ones features in this box. Its main factory opened on 31 March 1977 and manufactured a wide range of quality electric toy-racing cars for the world market (primarily USA, Europe and Australia). \r\n\r\nThese electric toy cars, also known as slot cars, ran on a track with grooves or slots that guided the cars. Primarily slot cars were used in the competitive hobby of slot car racing. Typically modelled on actual racing automobiles, slot cars share a relationship with popular interest in racing and have been featured at F1 events since 2010 in Singapore. The American Plastics corporation, Aurora Products Corporation Asia Pte Ltd, produced slot cars from 1974-1983 such as the ones features in this box. Its main factory opened on 31 March 1977 and manufactured a wide range of quality electric toy-racing cars for the world market (primarily USA, Europe and Australia). \r\n\r\nThese electric toy cars, also known as slot cars, ran on a track with grooves or slots that guided the cars. Primarily slot cars were used in the competitive hobby of slot car racing. Typically modelled on actual racing automobiles, slot cars share a relationship with popular interest in racing and have been featured at F1 events since 2010 in Singapore."
  },
  "nlpDate": "20201120223707",
  "connectorId": 0,
  "tags": {}
}