{"id":"2016-00099","title":"Mr.Appavoo Kandiar and Mdm Chinnammal A Photograph of Mr.Appavoo Kandiar and Mdm Chinnammal","source":"Bumblebee","path":"./Data/json/","content":"accession_no_csv:2016-00099\nImage:\nobject_work_type:black-and-white photographs\ntitle_text:Mr.Appavoo Kandiar and Mdm Chinnammal A Photograph of Mr.Appavoo Kandiar and Mdm Chinnammal\npreference:main alternate\ntitle_language:\ncreation_date:1954\ncreation_place_original_location:Singapore India\ninscriptions:\ninscription_language:\nshape:rectangular\nmaterials_name:paper (fiber product)\ntechniques_name:printing (process) photographic processes\nobject_colour:grey monochrome\nphysical_appearance:The image shows a photograph that is in black-and-white. There is an inner and outer border. Both of these borders are demarcated by a gold band. The surrounding frame is light red in colour. A man and a woman are featured in the photograph\n from head to toe. The lady is standing on the left hand side and she is wearing a sari\n while the man is wearing a long sleeved shirt\n pants\n and covered shoes. Both of them are looking in the direction where the photograph was captured. Both of them are wearing a neck accessory around their neck that holds a flower\n which hangs at their respective torsos.\nsubject_terms_1:spouses folk costume double portraits founders (originators) studio portraits\nsubject_terms_2:Black-and-white photography Spouses Ethnic costume Portraits Portrait photography\nsubject_terms_3:Portrait photography Pioneers Kandiar\n Appavoo\nsgcool_label_text:A native of Karuvakurichi village\n near Mannargudi town in Tamil Nadu\n S. Appavoo Kandiar was a general contractor specializing in pipe and cable laying\n handling of cargo and a concrete bricks supplier. Mr.Kandiar was a successful contractor; called a millionaire by the Straits Times in 1957\n he owned properties in Bukit Timah and Coronation Road areas. He was a contemporary of Indian pioneers such as P.Govindasamy Pillai\n Govindasamy Sarangapany\n Pakkirisami Pillai\n and had friendly associations with them.","createdDate":"20201018182635","version":0,"latest":false,"roles":[],"metadata":{"accession_no_csv":"2016-00099","Image":"","object_work_type":"black-and-white photographs","title_text":"Mr.Appavoo Kandiar and Mdm Chinnammal A Photograph of Mr.Appavoo Kandiar and Mdm Chinnammal","preference":"main alternate","title_language":"","creation_date":"1954","creation_place_original_location":"Singapore India","inscriptions":"","inscription_language":"","shape":"rectangular","materials_name":"paper (fiber product)","techniques_name":"printing (process) photographic processes","object_colour":"grey monochrome","physical_appearance":"The image shows a photograph that is in black-and-white. There is an inner and outer border. Both of these borders are demarcated by a gold band. The surrounding frame is light red in colour. A man and a woman are featured in the photograph, from head to toe. The lady is standing on the left hand side and she is wearing a sari, while the man is wearing a long sleeved shirt, pants, and covered shoes. Both of them are looking in the direction where the photograph was captured. Both of them are wearing a neck accessory around their neck that holds a flower, which hangs at their respective torsos.","subject_terms_1":"spouses folk costume double portraits founders (originators) studio portraits","subject_terms_2":"Black-and-white photography Spouses Ethnic costume Portraits Portrait photography","subject_terms_3":"Portrait photography Pioneers Kandiar, Appavoo","sgcool_label_text":"A native of Karuvakurichi village, near Mannargudi town in Tamil Nadu, S. Appavoo Kandiar was a general contractor specializing in pipe and cable laying, handling of cargo and a concrete bricks supplier. Mr.Kandiar was a successful contractor; called a millionaire by the Straits Times in 1957, he owned properties in Bukit Timah and Coronation Road areas. He was a contemporary of Indian pioneers such as P.Govindasamy Pillai, Govindasamy Sarangapany, Pakkirisami Pillai, and had friendly associations with them."},"nlpDate":"20201018182635","connectorId":0,"tags":{}}