{"id":"2016-00728","title":"Gaming, Crawford Street","source":"Bumblebee","path":"./Data/json/","content":"accession_no_csv:2016-00728\nImage:\nobject_work_type:black-and-white photographs\ntitle_text:Gaming\n Crawford Street\npreference:main\ntitle_language:\ncreator_2:Loke Hong Seng\ncreator_1:Loke\n Hong Seng\ncreator_role:photographers\ncreation_date:2015 [1969]\ncreation_place_original_location:Singapore\ninscriptions:\ninscription_language:\nshape:rectangular\nmaterials_name:paper (fiber product)\ntechniques_name:printing (process)\nobject_colour:grey monochrome\nedition_description:15-Jan\nphysical_appearance:\\The image shows a photograph in black-and-white that is enclosed by a white frame. Five sets of carom tables can be discerned in the photograph. They are surrounded by youths\n who are mostly boys. Some of these boys are holding cue sticks to hit the strikers. At the bottom of the photograph to the left hand side\n there is a designation of \\\\1/15\\\\. And at the bottom right hand side\nsubject_terms_1:there is a signature in Chinese characters.\\ table games social issues\nsubject_terms_2:youth (people) Youth Street photography Caroms (Game) Singapore Social problems Gangs\nsubject_terms_3:Black-and-white photography Youth Crawford Street\nsubject_terms_4:Photography","createdDate":"20201119143406","version":0,"latest":false,"roles":[],"metadata":{"accession_no_csv":"2016-00728","Image":"","object_work_type":"black-and-white photographs","title_text":"Gaming, Crawford Street","preference":"main","title_language":"","creator_2":"Loke Hong Seng","creator_1":"Loke, Hong Seng","creator_role":"photographers","creation_date":"2015 [1969]","creation_place_original_location":"Singapore","inscriptions":"","inscription_language":"","shape":"rectangular","materials_name":"paper (fiber product)","techniques_name":"printing (process)","object_colour":"grey monochrome","edition_description":"15-Jan","physical_appearance":"\"The image shows a photograph in black-and-white that is enclosed by a white frame. Five sets of carom tables can be discerned in the photograph. They are surrounded by youths, who are mostly boys. Some of these boys are holding cue sticks to hit the strikers. At the bottom of the photograph to the left hand side, there is a designation of \"\"1/15\"\". And at the bottom right hand side","subject_terms_1":"there is a signature in Chinese characters.\" table games social issues","subject_terms_2":"youth (people) Youth Street photography Caroms (Game) Singapore Social problems Gangs","subject_terms_3":"Black-and-white photography Youth Crawford Street","subject_terms_4":"Photography"},"nlpDate":"20201119143406","connectorId":0,"tags":{}}