{
  "id": "2017-01039-005",
  "title": "Photograph album presented to George Lowe as a souvenir of his visit to Singapore George Lowe album: Photograph of lecture attendees",
  "source": "Bumblebee",
  "path": "./Data/json/",
  "content": "\n  accession_no_csv: 2017-01039-005\n\n  Image: \n\n  object_work_type: black-and-white photographs photographs\n\n  title_text: Photograph album presented to George Lowe as a souvenir of his visit to Singapore George Lowe album: Photograph of lecture attendees\n\n  preference: alternate main\n\n  title_language: \n\n  creation_date: 1953\n\n  creation_place_original_location: Singapore\n\n  inscriptions: \n\n  inscription_language: \n\n  shape: rectangular\n\n  materials_name: paper (fiber product)\n\n  techniques_name: photographic processes\n\n  object_colour: black-and-white (colors)\n\n  physical_appearance: This is a black-and-white photograph of a lecture hall. The hall is filled with students in uniform\n seated in rows. Two aisles separate the seats into three columns. There is a second mezanine level of seats above. There are no tears or folds seen on the photograph.\n\n  subject_terms_1: Photographs souvenirs presentations (communicative events) students\n\n  subject_terms_2: Photographs Photograph albums Souvenir Lowe\n George\n 1924-2013 Hillary\n Edmund\n 1919-2008 Lectures and lecture courses Students\n\n  subject_terms_3: Photography Odeon Cinema (Place)\n\n  subject_terms_4: \n\n  sgcool_label_text: George Lowe was a member of the British Expedition that saw Sir Edmund Hillary scale Mount Everest on 29 May 1953. In September that year\n Lowe accompanied Hillary on a visit to Singapore to deliver their first Everest lecture outside of New Zealand at the Odeon Theatre to an audience of 1\n620 schoolchildren. This photograph album\n with the coat of arms of the City of Singapore in gilt on the cover\n was presented to Lowe as a souvenir of his visit.\n",
  "createdDate": "20201120223708",
  "version": 0,
  "latest": false,
  "roles": [],
  "metadata": {
    "accession_no_csv": "2017-01039-005",
    "Image": "",
    "object_work_type": "black-and-white photographs photographs",
    "title_text": "Photograph album presented to George Lowe as a souvenir of his visit to Singapore George Lowe album: Photograph of lecture attendees",
    "preference": "alternate main",
    "title_language": "",
    "creation_date": "1953",
    "creation_place_original_location": "Singapore",
    "inscriptions": "",
    "inscription_language": "",
    "shape": "rectangular",
    "materials_name": "paper (fiber product)",
    "techniques_name": "photographic processes",
    "object_colour": "black-and-white (colors)",
    "physical_appearance": "This is a black-and-white photograph of a lecture hall. The hall is filled with students in uniform, seated in rows. Two aisles separate the seats into three columns. There is a second mezanine level of seats above. There are no tears or folds seen on the photograph.",
    "subject_terms_1": "Photographs souvenirs presentations (communicative events) students",
    "subject_terms_2": "Photographs Photograph albums Souvenir Lowe, George, 1924-2013 Hillary, Edmund, 1919-2008 Lectures and lecture courses Students",
    "subject_terms_3": "Photography Odeon Cinema (Place)",
    "subject_terms_4": "",
    "sgcool_label_text": "George Lowe was a member of the British Expedition that saw Sir Edmund Hillary scale Mount Everest on 29 May 1953. In September that year, Lowe accompanied Hillary on a visit to Singapore to deliver their first Everest lecture outside of New Zealand at the Odeon Theatre to an audience of 1,620 schoolchildren. This photograph album, with the coat of arms of the City of Singapore in gilt on the cover, was presented to Lowe as a souvenir of his visit."
  },
  "nlpDate": "20201120223708",
  "connectorId": 0,
  "tags": {}
}