{"id":"2017-01036","title":"Chinese opera actors on stage Photograph of Chinese opera actors on stage","source":"Bumblebee","path":"./Data/json/","content":"accession_no_csv:2017-01036\nImage:\nobject_work_type:black-and-white photographs photographs\ntitle_text:Chinese opera actors on stage Photograph of Chinese opera actors on stage\npreference:main\ntitle_language:\ncreator_2:John Thomson\ncreator_1:Thomson\n J. (John)\n 1837-1921\ncreator_role:photographers\ncreation_date:1860s\ncreation_place_original_location:Singapore\ninscriptions:\ninscription_language:\nshape:rectangular\nmaterials_name:paper (fiber product)\ntechniques_name:photographic processes\nobject_colour:black-and-white (colors)\nphysical_appearance:This is a black-and-white photograph. It features two Chinese opera singers on stage. They are elaborately dressed in opera costumes\n on either side of a draped textile. The woman on the left is holding a fan in her hand. The photograph is slightly faded\n especially along the right side. There are no tears or folds seen.\nsubject_terms_1:operas (performances) folk costume\nsubject_terms_2:Carte de visite photographs Photographs Chinese operas Ethnic costume\nsubject_terms_3:Photography Chinese costumes Chinese operas (Music)\nsubject_terms_4:\nsgcool_label_text:This carte-de-visite format photograph of two Chinese opera actors was taken by John Thomson\n who arrived in Singapore in 1862 and established a studio at Beach Road on 16 June that year. Thomson would later travel to photograph in Siam and China before embarking on a series on street life in London.\\r\\n","createdDate":"20201018182636","version":0,"latest":false,"roles":[],"metadata":{"accession_no_csv":"2017-01036","Image":"","object_work_type":"black-and-white photographs photographs","title_text":"Chinese opera actors on stage Photograph of Chinese opera actors on stage","preference":"main","title_language":"","creator_2":"John Thomson","creator_1":"Thomson, J. (John), 1837-1921","creator_role":"photographers","creation_date":"1860s","creation_place_original_location":"Singapore","inscriptions":"","inscription_language":"","shape":"rectangular","materials_name":"paper (fiber product)","techniques_name":"photographic processes","object_colour":"black-and-white (colors)","physical_appearance":"This is a black-and-white photograph. It features two Chinese opera singers on stage. They are elaborately dressed in opera costumes, on either side of a draped textile. The woman on the left is holding a fan in her hand. The photograph is slightly faded, especially along the right side. There are no tears or folds seen.","subject_terms_1":"operas (performances) folk costume","subject_terms_2":"Carte de visite photographs Photographs Chinese operas Ethnic costume","subject_terms_3":"Photography Chinese costumes Chinese operas (Music)","subject_terms_4":"","sgcool_label_text":"This carte-de-visite format photograph of two Chinese opera actors was taken by John Thomson, who arrived in Singapore in 1862 and established a studio at Beach Road on 16 June that year. Thomson would later travel to photograph in Siam and China before embarking on a series on street life in London.\r\n"},"nlpDate":"20201018182636","connectorId":0,"tags":{}}