{
  "id": "2017-00900",
  "title": "Majie’s black ribbon",
  "source": "Bumblebee",
  "path": "./Data/json/",
  "content": "\n  accession_no_csv: 2017-00900\n\n  Image: \n\n  object_work_type: ribbon (material)\n\n  title_text: Majie’s black ribbon\n\n  preference: main\n\n  title_language: \n\n  creation_date: Mid-20th century\n\n  creation_place_original_location: Singapore\n\n  inscriptions: \n\n  inscription_language: \n\n  shape: rectangular\n\n  materials_name: silk (textile)\n\n  techniques_name: sewing (needleworking technique)\n\n  object_colour: black (color)\n\n  physical_appearance: This is a black ribbon. It is long and is folded at four points. The ribbon features a repeated rounded geometric pattern embossed into the fabric.\n\n  subject_terms_1: cultural ceremonies ceremonial objects maids (servants) customs (social concepts)\n\n  subject_terms_2: Rites and ceremonies Ceremonial objects Household employees Ribbons\n\n  subject_terms_3: Lu\n Earl Ming-Teh\n\n  subject_terms_4: \n\n  sgcool_label_text: This black ribbon belonged to a majie\n a Cantonese female domestic helper. In adherence to tradition\n majies underwent a sor hei (combing up) ceremony where they took an oath before a statuette of Guan Yin (Goddess of Mercy) to remain unmarried and celibate. Sor hei\n in literal terms\n means to “comb up” the hair into a bun or plait. \\r\\n\\r\\nWhile some majies wore their hair in a plait\n some also clipped their hair in a bun\n using a hairclip as shown. The choice of an unassuming colour like black for the ribbon blends in with black hair\n which also ties in with the majie’s fidelity to their vow of modesty and humility.\n",
  "createdDate": "20201125084515",
  "version": 0,
  "latest": false,
  "roles": [],
  "metadata": {
    "accession_no_csv": "2017-00900",
    "Image": "",
    "object_work_type": "ribbon (material)",
    "title_text": "Majie’s black ribbon",
    "preference": "main",
    "title_language": "",
    "creation_date": "Mid-20th century",
    "creation_place_original_location": "Singapore",
    "inscriptions": "",
    "inscription_language": "",
    "shape": "rectangular",
    "materials_name": "silk (textile)",
    "techniques_name": "sewing (needleworking technique)",
    "object_colour": "black (color)",
    "physical_appearance": "This is a black ribbon. It is long and is folded at four points. The ribbon features a repeated rounded geometric pattern embossed into the fabric.",
    "subject_terms_1": "cultural ceremonies ceremonial objects maids (servants) customs (social concepts)",
    "subject_terms_2": "Rites and ceremonies Ceremonial objects Household employees Ribbons",
    "subject_terms_3": "Lu, Earl Ming-Teh",
    "subject_terms_4": "",
    "sgcool_label_text": "This black ribbon belonged to a majie, a Cantonese female domestic helper. In adherence to tradition, majies underwent a sor hei (combing up) ceremony where they took an oath before a statuette of Guan Yin (Goddess of Mercy) to remain unmarried and celibate. Sor hei, in literal terms, means to “comb up” the hair into a bun or plait. \r\n\r\nWhile some majies wore their hair in a plait, some also clipped their hair in a bun, using a hairclip as shown. The choice of an unassuming colour like black for the ribbon blends in with black hair, which also ties in with the majie’s fidelity to their vow of modesty and humility."
  },
  "nlpDate": "20201125084515",
  "connectorId": 0,
  "tags": {}
}