{
  "id": "2017-00145-016",
  "title": "Reflections of Tan Chong Tee: Notice On Lim Bo Seng\u0027s Memorial Service Reflections of Tan Chong Tee: Letters, Notes, and Photographs  ?1946.1.1?",
  "source": "Bumblebee",
  "path": "./Data/json/",
  "content": "\n  accession_no_csv: 2017-00145-016\n\n  Image: \n\n  object_work_type: reproductions (derivative objects)\n\n  title_text: Reflections of Tan Chong Tee: Notice On Lim Bo Seng\\u0027s Memorial Service Reflections of Tan Chong Tee: Letters\n Notes\n and Photographs  ?1946.1.1?\n\n  preference: main alternate\n\n  title_language: \n\n  creation_date: 1-Jan-46\n\n  creation_place_original_location: Singapore\n\n  inscriptions: \n\n  inscription_language: \n\n  shape: Square\n\n  materials_name: paper (fiber product)\n\n  techniques_name: black-and-white photography\n\n  object_colour: black-and-white (colors)\n\n  physical_appearance: This is a reproduction of a notice written by Tan Chong Tee (in traditional Chinese script) regarding Lim Bo Seng\\u0027s public memorial service. The original document is torn on the bottom right corner\n and has hole-punture marks on the left.\n\n  subject_terms_1: memorial services funeral processions resistance movements local histories documents (object genre) world wars announcements? armed forces guerilla warfare\n\n  subject_terms_2: Memorial service World War\n 1939-1945 Lim\n Bo Seng\n 1909-1944 Fascimiles Chen\n Chongzhi\n 1916- Armed Forces Guerillas Great Britain. Army. Force 136 Local history Force 136 (Guerilla movement) Military funerals War resistance movements\n\n  subject_terms_3: History Tan\n Chong Tee Lim\n Bo Seng 1942-1945 Japanese Occupation Force 136 (Guerilla movement) war personalities\n\n  context_1: Lim Bo Seng\\u0027s Memorial Service\n\n  context_2: memorial services\n\n  context_3: 13-Jan-46\n\n  context_4: 13-Jan-46\n\n  context_5: 13-Jan-46\n\n  context_6: MacRitchie Reservoir City Hall (Singapore)\n\n  context_7: Great Britain. Army. Force 136\n\n  context_8: planners\n\n  sgcool_label_text: These documents and photographs belong to a larger part of a collection of artefacts related to the World War II underground resistance movement known as Force 136. The collection of materials was gathered by Tan Chong Tee (1916- 2012)\n who was a key member of this resistance group. The collection consists of original materials belonging to Tan and other members of Force 136 dating from the 1940s to new materials reproduced from memory by Tan Chong Tee\n which date from the late 1980s to early 2000s. \\r\\n\\r\\nForce 136 was set up in July 1942 as part of the British Special Operations Executive (SOE). It recruited and trained local guerillas to gather intelligence and create an underground spy network to support planned British invasion of Japanese-occupied Malaya.\\r\\n\n",
  "createdDate": "20201125084528",
  "version": 0,
  "latest": false,
  "roles": [],
  "metadata": {
    "accession_no_csv": "2017-00145-016",
    "Image": "",
    "object_work_type": "reproductions (derivative objects)",
    "title_text": "Reflections of Tan Chong Tee: Notice On Lim Bo Seng\u0027s Memorial Service Reflections of Tan Chong Tee: Letters, Notes, and Photographs  ?1946.1.1?",
    "preference": "main alternate",
    "title_language": "",
    "creation_date": "1-Jan-46",
    "creation_place_original_location": "Singapore",
    "inscriptions": "",
    "inscription_language": "",
    "shape": "Square",
    "materials_name": "paper (fiber product)",
    "techniques_name": "black-and-white photography",
    "object_colour": "black-and-white (colors)",
    "physical_appearance": "This is a reproduction of a notice written by Tan Chong Tee (in traditional Chinese script) regarding Lim Bo Seng\u0027s public memorial service. The original document is torn on the bottom right corner, and has hole-punture marks on the left.",
    "subject_terms_1": "memorial services funeral processions resistance movements local histories documents (object genre) world wars announcements? armed forces guerilla warfare",
    "subject_terms_2": "Memorial service World War, 1939-1945 Lim, Bo Seng, 1909-1944 Fascimiles Chen, Chongzhi, 1916- Armed Forces Guerillas Great Britain. Army. Force 136 Local history Force 136 (Guerilla movement) Military funerals War resistance movements",
    "subject_terms_3": "History Tan, Chong Tee Lim, Bo Seng 1942-1945 Japanese Occupation Force 136 (Guerilla movement) war personalities",
    "context_1": "Lim Bo Seng\u0027s Memorial Service",
    "context_2": "memorial services",
    "context_3": "13-Jan-46",
    "context_4": "13-Jan-46",
    "context_5": "13-Jan-46",
    "context_6": "MacRitchie Reservoir City Hall (Singapore)",
    "context_7": "Great Britain. Army. Force 136",
    "context_8": "planners",
    "sgcool_label_text": "These documents and photographs belong to a larger part of a collection of artefacts related to the World War II underground resistance movement known as Force 136. The collection of materials was gathered by Tan Chong Tee (1916- 2012), who was a key member of this resistance group. The collection consists of original materials belonging to Tan and other members of Force 136 dating from the 1940s to new materials reproduced from memory by Tan Chong Tee, which date from the late 1980s to early 2000s. \r\n\r\nForce 136 was set up in July 1942 as part of the British Special Operations Executive (SOE). It recruited and trained local guerillas to gather intelligence and create an underground spy network to support planned British invasion of Japanese-occupied Malaya.\r\n"
  },
  "nlpDate": "20201125084528",
  "connectorId": 0,
  "tags": {}
}