{"id":"2017-00063","title":"Ceremonial handkerchief or dowry tray cover","source":"Bumblebee","path":"./Data/json/","content":"accession_no_csv:2017-00063\nImage:\nobject_work_type:handkerchiefs covers (overlying objects)\ntitle_text:Ceremonial handkerchief or dowry tray cover\npreference:main\ntitle_language:\ncreation_date:early 20th century\ncreation_place_original_location:Sumatra (Indonesia)\ninscriptions:\ninscription_language:\nshape:square (shape)\nmaterials_name:silk (textile) metal thread\ntechniques_name:sewing (needleworking technique) embroidering\nobject_colour:multicolored\nphysical_appearance:This is a square handkerchief. It features a multicolored embroidery depicting several animal and floral motifs. The center circular medallion contains phoenixes and a peony bloom. It is outlined by lotuses\n and framed by an elephant\n a tiger\n a lion\n and a gillan on the four corners. The handkerchief is decorated with two borders of repeated geometric shapes and stylised animals.\nsubject_terms_1:embroidery (visual works) ceremonial objects flower (motif) geometric motifs birds (motifs) Taoism trousseaux\nsubject_terms_2:Handkerchiefs Embroidery Ceremonial objects Motifs Taoism Dowry\nsubject_terms_3:Textile art and design Taoism\nsgcool_label_text:This handkerchief (sapu tangan) was probably used as a decorative tray cover that was placed over items presented on trays as part of a ceremony.  A circular medallion comprising a pair of confronting phoenixes and a peony bloom occupy the centre of the cloth.  It is outlined by a band of lotuses.  The medallion is further framed by four qilins\n each demarcated by Chinese cloud scroll patterns in silver thread.  Two borders comprising silk floss in satin and voided stitches\n and drawn work embroidery enclose the main square decoration.  The drawn work embroidery consists of repeated geometric shapes and stylised animals.  Given the auspicious motifs on this piece\n this handkerchief could have been part of the bridal trousseau prepared for the groom and his family.  The phoenix is symbolic of martial harmony while the qilin represents fertility and longevity.","createdDate":"20201119143406","version":0,"latest":false,"roles":[],"metadata":{"accession_no_csv":"2017-00063","Image":"","object_work_type":"handkerchiefs covers (overlying objects)","title_text":"Ceremonial handkerchief or dowry tray cover","preference":"main","title_language":"","creation_date":"early 20th century","creation_place_original_location":"Sumatra (Indonesia)","inscriptions":"","inscription_language":"","shape":"square (shape)","materials_name":"silk (textile) metal thread","techniques_name":"sewing (needleworking technique) embroidering","object_colour":"multicolored","physical_appearance":"This is a square handkerchief. It features a multicolored embroidery depicting several animal and floral motifs. The center circular medallion contains phoenixes and a peony bloom. It is outlined by lotuses, and framed by an elephant, a tiger, a lion, and a gillan on the four corners. The handkerchief is decorated with two borders of repeated geometric shapes and stylised animals.","subject_terms_1":"embroidery (visual works) ceremonial objects flower (motif) geometric motifs birds (motifs) Taoism trousseaux","subject_terms_2":"Handkerchiefs Embroidery Ceremonial objects Motifs Taoism Dowry","subject_terms_3":"Textile art and design Taoism","sgcool_label_text":"This handkerchief (sapu tangan) was probably used as a decorative tray cover that was placed over items presented on trays as part of a ceremony.  A circular medallion comprising a pair of confronting phoenixes and a peony bloom occupy the centre of the cloth.  It is outlined by a band of lotuses.  The medallion is further framed by four qilins, each demarcated by Chinese cloud scroll patterns in silver thread.  Two borders comprising silk floss in satin and voided stitches, and drawn work embroidery enclose the main square decoration.  The drawn work embroidery consists of repeated geometric shapes and stylised animals.  Given the auspicious motifs on this piece, this handkerchief could have been part of the bridal trousseau prepared for the groom and his family.  The phoenix is symbolic of martial harmony while the qilin represents fertility and longevity."},"nlpDate":"20201119143406","connectorId":0,"tags":{}}