{"id":"2017-00048","title":"A View of the East India Docks A View of the East India Docks","source":"Bumblebee","path":"./Data/json/","content":"accession_no_csv:2017-00048\nImage:\nobject_work_type:aquatints (prints) engravings (prints) paperwork (visual works)  aerial views aquatints\ntitle_text:A View of the East India Docks A View of the East India Docks\npreference:main main\ntitle_language:\ncreator_2:William Daniell (engraver) (1769 - 1837) William Daniell (engraver)\ncreator_1:Daniell\n William\n 1769 - 1837 Daniell\n William\n 1769-1837\ncreator_role:artists (visual artists) landscapists artists (visual artists)\ncreation_date:1808 1808\ncreation_place_original_location:London (England) London (England) Blackwall (London\n England)\nstyles_periods_indexing_terms:NA NA\ninscriptions:\ninscription_language:\nscale_type:NA NA\nshape:rectangular Rectangular\nmaterials_name:paper (fiber product) paper (fiber product)\ntechniques_name:aquatint (printing process) aquatint (printing process)\nobject_colour:multicoloured black-and-white (colours) ??\nedition_description:NA NA\nphysical_appearance:This artwork depicts a landscape view of the East India Docks. The top half of the aquatint consists of the sky and clouds\n while the bottom half depicts the ships\n docks\n and rivers. The artwork has a wooden frame and it has a white border with a brown perimeter in between. At the bottom of the artwork\n its title is displayed in capital letters. Under its title\n there are four rows of paragraphs describing aspects of the East India docks. The colours on the aquatint do not look smudged.  This is an aerial view of a dock. The meandering river is filled with ships of various sizes\n and the land across seems vast and expansive with sparse settlement.\nsubject_terms_1:landscapes (representations) marines (visual works) dockyards docks (waterfront spaces) shipping  landscapes (representations) ships\nsubject_terms_2:Landscapes Aquatint Engraving Docks England East India Company prints Thames River (England) Blackwall (London\n England) East India Company  Thames River (England) Greenwich (London\n England)  Daniell\n Thomas\n 1749-1840? Aerial views  Docks  Indiamen Landscapes  Aquatint\nsubject_terms_3:Visual arts East India Company East India Company  Visual Arts\nsubject_terms_4:NA NA\ncontext_1:NA NA\ncontext_2:NA NA\ncontext_3:NA NA\ncontext_4:NA NA\ncontext_5:NA NA\ncontext_6:NA NA\ncontext_7:NA NA\ncontext_8:NA NA\ncontext_9:NA NA\ncontext_10:NA NA\ncontext_11:NA NA\ncontext_12:NA NA\ncontext_13:NA NA\ncontext_14:NA NA\ncontext_15:NA NA\ncontext_16:NA NA\ncontext_17:NA NA\ncontext_18:NA NA\ncontext_19:NA NA\ncontext_20:NA East India Docks\ncontext_21:NA Blackwall (London\n England)\ncontext_22:NA 1808\ncontext_23:NA 1808\ncontext_24:NA 1808\nsgcool_label_text:The East India Docks were opened in 1806 in Blackwall\n London\n to accommodate the shipping needs of the East India Company. This aquatint presents an aerial view of the docks\n with the Thames in the middle ground\n and Greenwich in the distance to the right. It was drawn\n engraved and published by William Daniell\n an English landscape and marine artist who together with his uncle Thomas Daniell  travelled extensively in India. The East India Docks were opened in 1806 in Blackwall\n London\n to accommodate the shipping needs of the East India Company. This aquatint presents an aerial view of the docks\n with the Thames in the middle ground\n and Greenwich in the distance to the right. It was drawn\n engraved and published by William Daniell\n an English landscape and marine artist who together with his uncle Thomas Daniell  travelled extensively in India.","createdDate":"20201018182636","version":0,"latest":false,"roles":[],"metadata":{"accession_no_csv":"2017-00048","Image":"","object_work_type":"aquatints (prints) engravings (prints) paperwork (visual works)  aerial views aquatints","title_text":"A View of the East India Docks A View of the East India Docks","preference":"main main","title_language":"","creator_2":"William Daniell (engraver) (1769 - 1837) William Daniell (engraver)","creator_1":"Daniell, William, 1769 - 1837 Daniell, William, 1769-1837","creator_role":"artists (visual artists) landscapists artists (visual artists)","creation_date":"1808 1808","creation_place_original_location":"London (England) London (England) Blackwall (London, England)","styles_periods_indexing_terms":"NA NA","inscriptions":"","inscription_language":"","scale_type":"NA NA","shape":"rectangular Rectangular","materials_name":"paper (fiber product) paper (fiber product)","techniques_name":"aquatint (printing process) aquatint (printing process)","object_colour":"multicoloured black-and-white (colours) ??","edition_description":"NA NA","physical_appearance":"This artwork depicts a landscape view of the East India Docks. The top half of the aquatint consists of the sky and clouds, while the bottom half depicts the ships, docks, and rivers. The artwork has a wooden frame and it has a white border with a brown perimeter in between. At the bottom of the artwork, its title is displayed in capital letters. Under its title, there are four rows of paragraphs describing aspects of the East India docks. The colours on the aquatint do not look smudged.  This is an aerial view of a dock. The meandering river is filled with ships of various sizes, and the land across seems vast and expansive with sparse settlement.","subject_terms_1":"landscapes (representations) marines (visual works) dockyards docks (waterfront spaces) shipping  landscapes (representations) ships","subject_terms_2":"Landscapes Aquatint Engraving Docks England East India Company prints Thames River (England) Blackwall (London, England) East India Company  Thames River (England) Greenwich (London, England)  Daniell, Thomas, 1749-1840? Aerial views  Docks  Indiamen Landscapes  Aquatint","subject_terms_3":"Visual arts East India Company East India Company  Visual Arts","subject_terms_4":"NA NA","context_1":"NA NA","context_2":"NA NA","context_3":"NA NA","context_4":"NA NA","context_5":"NA NA","context_6":"NA NA","context_7":"NA NA","context_8":"NA NA","context_9":"NA NA","context_10":"NA NA","context_11":"NA NA","context_12":"NA NA","context_13":"NA NA","context_14":"NA NA","context_15":"NA NA","context_16":"NA NA","context_17":"NA NA","context_18":"NA NA","context_19":"NA NA","context_20":"NA East India Docks","context_21":"NA Blackwall (London, England)","context_22":"NA 1808","context_23":"NA 1808","context_24":"NA 1808","sgcool_label_text":"The East India Docks were opened in 1806 in Blackwall, London, to accommodate the shipping needs of the East India Company. This aquatint presents an aerial view of the docks, with the Thames in the middle ground, and Greenwich in the distance to the right. It was drawn, engraved and published by William Daniell, an English landscape and marine artist who together with his uncle Thomas Daniell  travelled extensively in India. The East India Docks were opened in 1806 in Blackwall, London, to accommodate the shipping needs of the East India Company. This aquatint presents an aerial view of the docks, with the Thames in the middle ground, and Greenwich in the distance to the right. It was drawn, engraved and published by William Daniell, an English landscape and marine artist who together with his uncle Thomas Daniell  travelled extensively in India."},"nlpDate":"20201018182636","connectorId":0,"tags":{}}