{"id":"2017-00495 ","title":"Handmade Swiss white lace from Sylvia Kho’s collection","source":"Bumblebee","path":"./Data/json/","content":"accession_no_csv:2017-00495 \nImage:\nobject_work_type:lace (needlework) textile art (visual works)\ntitle_text:Handmade Swiss white lace from Sylvia Kho’s collection\npreference:main\ntitle_language:\ncreator_2:A. Naef.co\ncreator_role:makers?\ncreation_date:1960s-1980s\ncreation_place_original_location:Switzerland\ninscriptions:\ninscription_language:\nshape:Rectangular\nmaterials_name:lace (needlework)\ntechniques_name:lace making\nobject_colour:white (colour)\nphysical_appearance:This is a lace sample with floral and leaf motifs.\nsubject_terms_1:flower (motif)  plant-derived motif  imports  handmade\nsubject_terms_2:Lace and lace making  Flowers in art  Leaves in art  Textile crafts  Switzerland  Imports  Kho\n Sylvia\n 1917- Handmade style?\nsubject_terms_3:Textile art and design\nsgcool_label_text:This handmade lace sample is from the collection of Sylvia Kho who was a prominent bridal couturier in Singapore from the 1950s to 1990s. Sylvia Kho designed and custom-made wedding gowns using elaborate laces imported from Europe.  She travelled extensively to France and USA to learn how wedding gowns were designed and made. She also became one of the greatest buyers of wedding gown lace in France. This exquisite lace sample still has its original label from the maker\n a certain A.Naef.co which is no longer in existence.","createdDate":"20201119143406","version":0,"latest":false,"roles":[],"metadata":{"accession_no_csv":"2017-00495 ","Image":"","object_work_type":"lace (needlework) textile art (visual works)","title_text":"Handmade Swiss white lace from Sylvia Kho’s collection","preference":"main","title_language":"","creator_2":"A. Naef.co","creator_role":"makers?","creation_date":"1960s-1980s","creation_place_original_location":"Switzerland","inscriptions":"","inscription_language":"","shape":"Rectangular","materials_name":"lace (needlework)","techniques_name":"lace making","object_colour":"white (colour)","physical_appearance":"This is a lace sample with floral and leaf motifs.","subject_terms_1":"flower (motif)  plant-derived motif  imports  handmade","subject_terms_2":"Lace and lace making  Flowers in art  Leaves in art  Textile crafts  Switzerland  Imports  Kho, Sylvia, 1917- Handmade style?","subject_terms_3":"Textile art and design","sgcool_label_text":"This handmade lace sample is from the collection of Sylvia Kho who was a prominent bridal couturier in Singapore from the 1950s to 1990s. Sylvia Kho designed and custom-made wedding gowns using elaborate laces imported from Europe.  She travelled extensively to France and USA to learn how wedding gowns were designed and made. She also became one of the greatest buyers of wedding gown lace in France. This exquisite lace sample still has its original label from the maker, a certain A.Naef.co which is no longer in existence."},"nlpDate":"20201119143406","connectorId":0,"tags":{}}