{"id":"2017-00192-004","title":"Chan Phui Kong Collection: Japanese Flag, Parachute Cloth, Photographs, Maps, Documents and Scarfs  Chan Phui Kong Collection: Parachute cloth","source":"Bumblebee","path":"./Data/json/","content":"accession_no_csv:2017-00192-004\nImage:\nobject_work_type:cloth\ntitle_text:Chan Phui Kong Collection: Japanese Flag\n Parachute Cloth\n Photographs\n Maps\n Documents and Scarfs  Chan Phui Kong Collection: Parachute cloth\npreference:alternate main\ntitle_language:\ncreation_date:1942-2000\ncreation_place_original_location:Singapore Kelantan (Malaysia)\ninscriptions:\ninscription_language:\nshape:rectangular\nmaterials_name:cloth\ntechniques_name:sewing (needleworking technique) embroidering\nobject_colour:multicolored\nphysical_appearance:This is a piece of cloth decorated with multicolored embroidery. The cloth is square in shape. Near the top-right corner\n there is a white and blue embroidery of the face of a man in a military shirt and beret. Near the bottom-left corner\n there is a embroidery of a hot air balloon with two outstretched wings\n with a circular emblem of a bird. There are some sewn on inscription above and below the parachute.\nsubject_terms_1:world wars resistance movements parachutes (life-saving equipment)\nsubject_terms_2:World War\n 1939-1945 Great Britain. Army. Force 136 Force 136 (Guerilla movement) Chin\n Phui Kong\n 1923- Parachute troops Parachutes Textile fabrics\nsubject_terms_3:Force 136 (Guerilla movement) 1942-1945 Japanese occupation Chin\n Phui Kong\n 1923- Textile art and design war personalities\nsubject_terms_4:\ncontext_1:World War\n 1939-1945 1942-1945 Japanese Occupation\ncontext_2:world wars occupations (armed conflicts)\ncontext_3:1939-1945 1942-1945\ncontext_4:1939 1942\ncontext_5:1945 1945\ncontext_6:Malaya Singapore\ncontext_7:Great Britain. Army. Force 136\ncontext_8:armed forces\nsgcool_label_text:These materials belong to Chan Phui Kong and consist of items which he used in guerrilla warfare as a member of the World War II underground resistance movement known as Force 136.  They form part of a larger collection of materials gathered by Tan Chong Tee (1916- 2012)\n who was a key member of this resistance group. The collection consists of original materials belonging to Tan and other members of Force 136 dating from the 1940s to new materials reproduced from memory by Tan Chong Tee\n which date from the late 1980s to early 2000s.\\r\\n\\r\\nForce 136 was set up in July 1942 as part of the British Special Operations Executive (SOE). It recruited and trained local guerillas to gather intelligence and create an underground spy network to support planned British invasion of Japanese-occupied Malaya.","createdDate":"20201119143406","version":0,"latest":false,"roles":[],"metadata":{"accession_no_csv":"2017-00192-004","Image":"","object_work_type":"cloth","title_text":"Chan Phui Kong Collection: Japanese Flag, Parachute Cloth, Photographs, Maps, Documents and Scarfs  Chan Phui Kong Collection: Parachute cloth","preference":"alternate main","title_language":"","creation_date":"1942-2000","creation_place_original_location":"Singapore Kelantan (Malaysia)","inscriptions":"","inscription_language":"","shape":"rectangular","materials_name":"cloth","techniques_name":"sewing (needleworking technique) embroidering","object_colour":"multicolored","physical_appearance":"This is a piece of cloth decorated with multicolored embroidery. The cloth is square in shape. Near the top-right corner, there is a white and blue embroidery of the face of a man in a military shirt and beret. Near the bottom-left corner, there is a embroidery of a hot air balloon with two outstretched wings, with a circular emblem of a bird. There are some sewn on inscription above and below the parachute.","subject_terms_1":"world wars resistance movements parachutes (life-saving equipment)","subject_terms_2":"World War, 1939-1945 Great Britain. Army. Force 136 Force 136 (Guerilla movement) Chin, Phui Kong, 1923- Parachute troops Parachutes Textile fabrics","subject_terms_3":"Force 136 (Guerilla movement) 1942-1945 Japanese occupation Chin, Phui Kong, 1923- Textile art and design war personalities","subject_terms_4":"","context_1":"World War, 1939-1945 1942-1945 Japanese Occupation","context_2":"world wars occupations (armed conflicts)","context_3":"1939-1945 1942-1945","context_4":"1939 1942","context_5":"1945 1945","context_6":"Malaya Singapore","context_7":"Great Britain. Army. Force 136","context_8":"armed forces","sgcool_label_text":"These materials belong to Chan Phui Kong and consist of items which he used in guerrilla warfare as a member of the World War II underground resistance movement known as Force 136.  They form part of a larger collection of materials gathered by Tan Chong Tee (1916- 2012), who was a key member of this resistance group. The collection consists of original materials belonging to Tan and other members of Force 136 dating from the 1940s to new materials reproduced from memory by Tan Chong Tee, which date from the late 1980s to early 2000s.\r\n\r\nForce 136 was set up in July 1942 as part of the British Special Operations Executive (SOE). It recruited and trained local guerillas to gather intelligence and create an underground spy network to support planned British invasion of Japanese-occupied Malaya."},"nlpDate":"20201119143406","connectorId":0,"tags":{}}