{
  "id": "2017-00598",
  "title": "Embroidered blouse Kanjari",
  "source": "Bumblebee",
  "path": "./Data/json/",
  "content": "\n  accession_no_csv: 2017-00598\n\n  Image: \n\n  object_work_type: blouses (main garments) womenswear\n\n  title_text: Embroidered blouse Kanjari\n\n  preference: main alternate\n\n  title_language: English\n\n  creation_date: 20th century\n\n  creation_place_original_location: Kachchh (India)\n\n  inscriptions: \n\n  inscription_language: \n\n  shape: irregular\n\n  materials_name: brocade (textile)\n\n  techniques_name: sewing (needleworking technique) embroidering\n\n  object_colour: multicolored\n\n  physical_appearance: This is an embroidered kanjari blouse. It is red\n featuring multicolored embroided diamond and floral patterns across the body. In the center\n there is a black panel. The sleeves feature a brocade panel.\n\n  subject_terms_1: folk costume embroidery (visual works) flower (motif) lozenges blouses (main garments) tops (garments\n general)\n\n  subject_terms_2: Ethnic costume Blouses Embroidery Brocade Motifs Jains\n\n  subject_terms_3: Indian costumes\n\n  subject_terms_4: \n\n  sgcool_label_text: Blouse worn by the Jain community of eastern Kutch. The sleeves of the blouse are made of brocade\n while the rest is covered in fine embroidery.\n",
  "createdDate": "20201120223708",
  "version": 0,
  "latest": false,
  "roles": [],
  "metadata": {
    "accession_no_csv": "2017-00598",
    "Image": "",
    "object_work_type": "blouses (main garments) womenswear",
    "title_text": "Embroidered blouse Kanjari",
    "preference": "main alternate",
    "title_language": "English",
    "creation_date": "20th century",
    "creation_place_original_location": "Kachchh (India)",
    "inscriptions": "",
    "inscription_language": "",
    "shape": "irregular",
    "materials_name": "brocade (textile)",
    "techniques_name": "sewing (needleworking technique) embroidering",
    "object_colour": "multicolored",
    "physical_appearance": "This is an embroidered kanjari blouse. It is red, featuring multicolored embroided diamond and floral patterns across the body. In the center, there is a black panel. The sleeves feature a brocade panel.",
    "subject_terms_1": "folk costume embroidery (visual works) flower (motif) lozenges blouses (main garments) tops (garments, general)",
    "subject_terms_2": "Ethnic costume Blouses Embroidery Brocade Motifs Jains",
    "subject_terms_3": "Indian costumes",
    "subject_terms_4": "",
    "sgcool_label_text": "Blouse worn by the Jain community of eastern Kutch. The sleeves of the blouse are made of brocade, while the rest is covered in fine embroidery."
  },
  "nlpDate": "20201120223708",
  "connectorId": 0,
  "tags": {}
}