{
  "id": "2017-00540",
  "title": "Deity Figure  Bulul",
  "source": "Bumblebee",
  "path": "./Data/json/",
  "content": "\n  accession_no_csv: 2017-00540\n\n  Image: \n\n  object_work_type: figurines  fetishes\n\n  title_text: Deity Figure  Bulul\n\n  preference: main  alternate\n\n  title_language: \n\n  creation_date: 19th century\n\n  creation_place_original_location: NA Luzon (Philippines)\n\n  inscriptions: \n\n  inscription_language: \n\n  shape: irregular\n\n  materials_name: wood (plant material)\n\n  techniques_name: carving (processes)\n\n  object_colour: brown (colour)\n\n  physical_appearance: This is a fetish figurine depicted to be in a squatting position with its hands folded in front.\n\n  subject_terms_1: indigenous people  magic  ancestor worship  sculpture\n\n  subject_terms_2: Fetishes (Ceremonial objects) Wood-carved figurines  Ifugao (Philippines people)  Ancestor worship  Protection magic  Figurative art Sculpture\n\n  subject_terms_3: Religious life and practices  Sculpture\n\n  subject_terms_4: \n\n  sgcool_label_text: Bulul figures represent deified ancestors.  They were believed to be inhabited by living spirits which if properly looked after could keep away disease and misfortune. Bulul were often stored in rice granaries where they were believed to keep away marauding vermin and evil spirits alike. Figures carved in a squatting position are a widespread and archaic style common to many indigenous peoples around island Southeast Asia.\n",
  "createdDate": "20201120223708",
  "version": 0,
  "latest": false,
  "roles": [],
  "metadata": {
    "accession_no_csv": "2017-00540",
    "Image": "",
    "object_work_type": "figurines  fetishes",
    "title_text": "Deity Figure  Bulul",
    "preference": "main  alternate",
    "title_language": "",
    "creation_date": "19th century",
    "creation_place_original_location": "NA Luzon (Philippines)",
    "inscriptions": "",
    "inscription_language": "",
    "shape": "irregular",
    "materials_name": "wood (plant material)",
    "techniques_name": "carving (processes)",
    "object_colour": "brown (colour)",
    "physical_appearance": "This is a fetish figurine depicted to be in a squatting position with its hands folded in front.",
    "subject_terms_1": "indigenous people  magic  ancestor worship  sculpture",
    "subject_terms_2": "Fetishes (Ceremonial objects) Wood-carved figurines  Ifugao (Philippines people)  Ancestor worship  Protection magic  Figurative art Sculpture",
    "subject_terms_3": "Religious life and practices  Sculpture",
    "subject_terms_4": "",
    "sgcool_label_text": "Bulul figures represent deified ancestors.  They were believed to be inhabited by living spirits which if properly looked after could keep away disease and misfortune. Bulul were often stored in rice granaries where they were believed to keep away marauding vermin and evil spirits alike. Figures carved in a squatting position are a widespread and archaic style common to many indigenous peoples around island Southeast Asia."
  },
  "nlpDate": "20201120223708",
  "connectorId": 0,
  "tags": {}
}