{
  "id": "2017-00658",
  "title": "Knee rest Ghutalyun",
  "source": "Bumblebee",
  "path": "./Data/json/",
  "content": "\n  accession_no_csv: 2017-00658\n\n  Image: \n\n  object_work_type: footstools (stools)\n\n  title_text: Knee rest Ghutalyun\n\n  preference: main alternate\n\n  title_language: \n\n  creation_date: 20th century\n\n  creation_place_original_location: Gujarat (India)\n\n  inscriptions: \n\n  inscription_language: \n\n  shape: irregular\n\n  materials_name: wood (plant material) glass (material)\n\n  techniques_name: woodcarving sewing (needleworking technique) embroidering\n\n  object_colour: multicolored\n\n  physical_appearance: This is a knee rest with a beaded decorative exterior. The embroided beadwork features multicolored geometric patterns\n with diamonds lining the bottom and middle section\n with scattered leaves and flowers along the body.\n\n  subject_terms_1: beadwork (visual works) flower (motif) embroidery (visual works) foliage (motif)\n\n  subject_terms_2: Motifs Embroidery Stools\n\n  subject_terms_3: Furniture design\n\n  subject_terms_4: \n",
  "createdDate": "20201201203308",
  "version": 0,
  "latest": false,
  "roles": [],
  "metadata": {
    "accession_no_csv": "2017-00658",
    "Image": "",
    "object_work_type": "footstools (stools)",
    "title_text": "Knee rest Ghutalyun",
    "preference": "main alternate",
    "title_language": "",
    "creation_date": "20th century",
    "creation_place_original_location": "Gujarat (India)",
    "inscriptions": "",
    "inscription_language": "",
    "shape": "irregular",
    "materials_name": "wood (plant material) glass (material)",
    "techniques_name": "woodcarving sewing (needleworking technique) embroidering",
    "object_colour": "multicolored",
    "physical_appearance": "This is a knee rest with a beaded decorative exterior. The embroided beadwork features multicolored geometric patterns, with diamonds lining the bottom and middle section, with scattered leaves and flowers along the body.",
    "subject_terms_1": "beadwork (visual works) flower (motif) embroidery (visual works) foliage (motif)",
    "subject_terms_2": "Motifs Embroidery Stools",
    "subject_terms_3": "Furniture design",
    "subject_terms_4": ""
  },
  "nlpDate": "20201201203308",
  "connectorId": 0,
  "tags": {}
}