{
  "id": "2017-00951-023",
  "title": "Sabun Cream Ponsel Tanah Impian (Dream Land)",
  "source": "Bumblebee",
  "path": "./Data/json/",
  "content": "\n  accession_no_csv: 2017-00951-023\n\n  Image: \n\n  object_work_type: screen prints adaptations (derivative objects)\n\n  title_text: Sabun Cream Ponsel Tanah Impian (Dream Land)\n\n  preference: main alternate\n\n  title_language: \n\n  creator_2: Krack Studio\n\n  creator_role: artists (visual artists)\n\n  creation_date: 2014\n\n  creation_place_original_location: Indonesia\n\n  styles_periods_indexing_terms: Contemporary (style of art)\n\n  inscriptions: \n\n  inscription_language: \n\n  shape: Rectangular\n\n  materials_name: paper (fiber product)\n\n  techniques_name: screen printing\n\n  object_colour: multicoloured\n\n  edition_description: 2-Oct\n\n  physical_appearance: \\This print is a promotional material for a washing/ laundry detergent \\\\Ponsel\\\\. It proclaims that it is able to thoroughly wash one\\u0027s laundry\n\n  subject_terms_1: advertisements ways of life appropriation (imagery) posters detergent (cleaning compound) and is pleasantly scented. An image of a mobile phone is seen on the top right corner. \\ popular culture redesign nationalism\n\n  subject_terms_2: Popular culture Appropriation (Art) Identity Art\n Indonesian Nationalism promotional materials Adaptations Ways of life identity Posters Detergents\n\n  subject_terms_3: Popular culture Serigraphy Poster art National identity Media and advertising\n\n  subject_terms_4: Visual arts\n",
  "createdDate": "20201201203308",
  "version": 0,
  "latest": false,
  "roles": [],
  "metadata": {
    "accession_no_csv": "2017-00951-023",
    "Image": "",
    "object_work_type": "screen prints adaptations (derivative objects)",
    "title_text": "Sabun Cream Ponsel Tanah Impian (Dream Land)",
    "preference": "main alternate",
    "title_language": "",
    "creator_2": "Krack Studio",
    "creator_role": "artists (visual artists)",
    "creation_date": "2014",
    "creation_place_original_location": "Indonesia",
    "styles_periods_indexing_terms": "Contemporary (style of art)",
    "inscriptions": "",
    "inscription_language": "",
    "shape": "Rectangular",
    "materials_name": "paper (fiber product)",
    "techniques_name": "screen printing",
    "object_colour": "multicoloured",
    "edition_description": "2-Oct",
    "physical_appearance": "\"This print is a promotional material for a washing/ laundry detergent \"\"Ponsel\"\". It proclaims that it is able to thoroughly wash one\u0027s laundry",
    "subject_terms_1": "advertisements ways of life appropriation (imagery) posters detergent (cleaning compound) and is pleasantly scented. An image of a mobile phone is seen on the top right corner. \" popular culture redesign nationalism",
    "subject_terms_2": "Popular culture Appropriation (Art) Identity Art, Indonesian Nationalism promotional materials Adaptations Ways of life identity Posters Detergents",
    "subject_terms_3": "Popular culture Serigraphy Poster art National identity Media and advertising",
    "subject_terms_4": "Visual arts"
  },
  "nlpDate": "20201201203308",
  "connectorId": 0,
  "tags": {}
}