{
  "id": "2017-00538-001 to 011",
  "title": "Carved Ebony and Ivory Box",
  "source": "Bumblebee",
  "path": "./Data/json/",
  "content": "\n  accession_no_csv: 2017-00538-001 to 011\n\n  Image: \n\n  object_work_type: boxes (containers)\n\n  title_text: Carved Ebony and Ivory Box\n\n  preference: main\n\n  title_language: \n\n  creation_date: mid-19th century\n\n  creation_place_original_location: Sri Lanka\n\n  styles_periods_indexing_terms: Ceylonese\n\n  inscriptions: \n\n  inscription_language: \n\n  shape: Rectangular\n\n  materials_name: ebony (wood)  ivory (material)\n\n  techniques_name: carving (processes)\n\n  object_colour: multicoloured\n\n  physical_appearance: This is an ebony box with flower and scrolling leaf motifs carved all around. It is lidded and hinged\n and has a key hole.\n\n  subject_terms_1: flower (motif)  scrolling foliage  jewelry boxes  exports\n\n  subject_terms_2: Ornamental boxes  Flowers in art floral decorations  Foliage plants  Colombo (Sri Lanka)\n\n  subject_terms_3: Decorative arts\n\n  subject_terms_4: \n\n  sgcool_label_text: This box of solid ebony is carved on all sides with bold flower and scrolling leaf designs which are known in Sri Lanka\n Southern India and the Malay world as the floral pineapple motif.  The top is carved with a central sword-fruit flower motif.  Inside the box is a tray of lightly coloured wood with nine compartments\n each with a lid inlaid with ebony and ivory which has been engraved with scrolling motifs and in-filled wtih black and red lac.  Boxes such as these were used in Sri Lanka by ladies to store jewellery and hair ornaments.  They were also produced for the colonial market.\n",
  "createdDate": "20201120223708",
  "version": 0,
  "latest": false,
  "roles": [],
  "metadata": {
    "accession_no_csv": "2017-00538-001 to 011",
    "Image": "",
    "object_work_type": "boxes (containers)",
    "title_text": "Carved Ebony and Ivory Box",
    "preference": "main",
    "title_language": "",
    "creation_date": "mid-19th century",
    "creation_place_original_location": "Sri Lanka",
    "styles_periods_indexing_terms": "Ceylonese",
    "inscriptions": "",
    "inscription_language": "",
    "shape": "Rectangular",
    "materials_name": "ebony (wood)  ivory (material)",
    "techniques_name": "carving (processes)",
    "object_colour": "multicoloured",
    "physical_appearance": "This is an ebony box with flower and scrolling leaf motifs carved all around. It is lidded and hinged, and has a key hole.",
    "subject_terms_1": "flower (motif)  scrolling foliage  jewelry boxes  exports",
    "subject_terms_2": "Ornamental boxes  Flowers in art floral decorations  Foliage plants  Colombo (Sri Lanka)",
    "subject_terms_3": "Decorative arts",
    "subject_terms_4": "",
    "sgcool_label_text": "This box of solid ebony is carved on all sides with bold flower and scrolling leaf designs which are known in Sri Lanka, Southern India and the Malay world as the floral pineapple motif.  The top is carved with a central sword-fruit flower motif.  Inside the box is a tray of lightly coloured wood with nine compartments, each with a lid inlaid with ebony and ivory which has been engraved with scrolling motifs and in-filled wtih black and red lac.  Boxes such as these were used in Sri Lanka by ladies to store jewellery and hair ornaments.  They were also produced for the colonial market."
  },
  "nlpDate": "20201120223708",
  "connectorId": 0,
  "tags": {}
}