{
  "id": "2017-00025",
  "title": "Unknown",
  "source": "Bumblebee",
  "path": "./Data/json/",
  "content": "\n  accession_no_csv: 2017-00025\n\n  Image: \n\n  object_work_type: gelatin silver prints  photographic prints colour prints (photographs)\n\n  title_text: Unknown\n\n  preference: main\n\n  title_language: \n\n  creator_2: Koon\n Sang Ho\n\n  creator_role: photographers\n\n  creation_date: c.1960\n\n  creation_place_original_location: Singapore\n\n  inscriptions: \n\n  inscription_language: \n\n  shape: rectangular\n\n  materials_name: gelatin  paper (fibre product)  silver sulfide  baryta paper\n\n  techniques_name: gelatin silver process photographic printing techniques colour photography\n\n  object_colour: multicoloured\n\n  physical_appearance: Central to this coloured gelatin silver print is a piler. Around it\n there are numerous construction workers who don a safety helmet. In the background\n there are blocks of high rise apartment houses. There is a strip of yellow running across the top of the image.\n\n  subject_terms_1: pile driving  construction sites constructing  construction workers apartment houses piles (structural elements)\n\n  subject_terms_2: Building  Construction Workers Apartment houses Piling (Civil engineering)  Photography\n Artistic\n\n  subject_terms_3: Building and Construction  Public buildings  visual arts Artistic photography\n\n  sgcool_label_text: Ho Koon Sang was a member of the Photographic Society of Singapore and an Associate of the Royal Photographic Society in London. This is a very early and unique print shot on colour film.\n",
  "createdDate": "20201120223707",
  "version": 0,
  "latest": false,
  "roles": [],
  "metadata": {
    "accession_no_csv": "2017-00025",
    "Image": "",
    "object_work_type": "gelatin silver prints  photographic prints colour prints (photographs)",
    "title_text": "Unknown",
    "preference": "main",
    "title_language": "",
    "creator_2": "Koon, Sang Ho",
    "creator_role": "photographers",
    "creation_date": "c.1960",
    "creation_place_original_location": "Singapore",
    "inscriptions": "",
    "inscription_language": "",
    "shape": "rectangular",
    "materials_name": "gelatin  paper (fibre product)  silver sulfide  baryta paper",
    "techniques_name": "gelatin silver process photographic printing techniques colour photography",
    "object_colour": "multicoloured",
    "physical_appearance": "Central to this coloured gelatin silver print is a piler. Around it, there are numerous construction workers who don a safety helmet. In the background, there are blocks of high rise apartment houses. There is a strip of yellow running across the top of the image.",
    "subject_terms_1": "pile driving  construction sites constructing  construction workers apartment houses piles (structural elements)",
    "subject_terms_2": "Building  Construction Workers Apartment houses Piling (Civil engineering)  Photography, Artistic",
    "subject_terms_3": "Building and Construction  Public buildings  visual arts Artistic photography",
    "sgcool_label_text": "Ho Koon Sang was a member of the Photographic Society of Singapore and an Associate of the Royal Photographic Society in London. This is a very early and unique print shot on colour film."
  },
  "nlpDate": "20201120223707",
  "connectorId": 0,
  "tags": {}
}