{"id":"2017-00113","title":"Extorting confessions through torture ??: a scroll depicting an extortion scene, Tan Chong Tee Under Fierce Interrogation by the Japanese and a Final Battle of Wits Extorting confessions through torture","source":"Bumblebee","path":"./Data/json/","content":"accession_no_csv:2017-00113\nImage:\nobject_work_type:drawings (visual works)\ntitle_text:Extorting confessions through torture ??: a scroll depicting an extortion scene\n Tan Chong Tee Under Fierce Interrogation by the Japanese and a Final Battle of Wits Extorting confessions through torture\npreference:alternate main\ntitle_language:\ncreator_2:Tan Chong Tee\ncreator_1:Chen\n Chongzhi\n 1916-\ncreator_role:artists (visual artists)\ncreation_date:2000\ncreation_place_original_location:Singapore\ninscriptions:\ninscription_language:\nshape:rectangular\nmaterials_name:paper (fiber product) ink colour (pigment)\ntechniques_name:painting (image-making)\nobject_colour:multicolored\nphysical_appearance:This is a scroll drawing of various scenes depicting an extortion scene. The right most part of the scroll shows the Japanese torturing the prisoner of war\n with the rest of the scenes showing fierce interrogation and extortion. There are some inscriptions in between and amongst the scenes drawn.\nsubject_terms_1:world wars depictions (visual works) resistance movements torturing scroll paintings prisoners of war Chinese scripts\nsubject_terms_2:Painting World War\n 1939-1945 Great Britain. Army. Force 136 Force 136 (Guerilla movement) Chen\n Chongzhi\n 1916- Torture Prisoners of war Scrolls (Decorative arts)\nsubject_terms_3:Painting Force 136 (Guerilla movement) Tan\n Chong Tee 1942-1945 Japanese occupation\nsubject_terms_4:\nsgcool_label_text:This drawing belongs to part of a collection of artefacts related to the World War II underground resistance movement known as Force 136. The collection of materials was gathered by Tan Chong Tee (1916- 2012)\n who was a key member of this resistance group. The collection consists of original materials belonging to Tan and other members of Force 136 dating from the 1940s to new materials reproduced from memory by Tan Chong Tee\n which date from mid 1990s to early 2000s. \\r\\n\\r\\nForce 136 was set up in July 1942 as part of the British Special Operations Executive (SOE). It recruited and trained local guerrillas to gather intelligence and create an underground spy network to support planned British invasion of Japanese-occupied Malaya.\\r\\n\\r\\nThis scroll depicts the trials undergone by members of Force 136 and drawn from the memory of Tan Chong Tee. The first part of the scroll (from right) depicts torturing of the members to force confessions out of them\n fierce interrogation of Tan Chong Tee and him trying to outwit the Japanese. \\r\\n","createdDate":"20201018182636","version":0,"latest":false,"roles":[],"metadata":{"accession_no_csv":"2017-00113","Image":"","object_work_type":"drawings (visual works)","title_text":"Extorting confessions through torture ??: a scroll depicting an extortion scene, Tan Chong Tee Under Fierce Interrogation by the Japanese and a Final Battle of Wits Extorting confessions through torture","preference":"alternate main","title_language":"","creator_2":"Tan Chong Tee","creator_1":"Chen, Chongzhi, 1916-","creator_role":"artists (visual artists)","creation_date":"2000","creation_place_original_location":"Singapore","inscriptions":"","inscription_language":"","shape":"rectangular","materials_name":"paper (fiber product) ink colour (pigment)","techniques_name":"painting (image-making)","object_colour":"multicolored","physical_appearance":"This is a scroll drawing of various scenes depicting an extortion scene. The right most part of the scroll shows the Japanese torturing the prisoner of war, with the rest of the scenes showing fierce interrogation and extortion. There are some inscriptions in between and amongst the scenes drawn.","subject_terms_1":"world wars depictions (visual works) resistance movements torturing scroll paintings prisoners of war Chinese scripts","subject_terms_2":"Painting World War, 1939-1945 Great Britain. Army. Force 136 Force 136 (Guerilla movement) Chen, Chongzhi, 1916- Torture Prisoners of war Scrolls (Decorative arts)","subject_terms_3":"Painting Force 136 (Guerilla movement) Tan, Chong Tee 1942-1945 Japanese occupation","subject_terms_4":"","sgcool_label_text":"This drawing belongs to part of a collection of artefacts related to the World War II underground resistance movement known as Force 136. The collection of materials was gathered by Tan Chong Tee (1916- 2012), who was a key member of this resistance group. The collection consists of original materials belonging to Tan and other members of Force 136 dating from the 1940s to new materials reproduced from memory by Tan Chong Tee, which date from mid 1990s to early 2000s. \r\n\r\nForce 136 was set up in July 1942 as part of the British Special Operations Executive (SOE). It recruited and trained local guerrillas to gather intelligence and create an underground spy network to support planned British invasion of Japanese-occupied Malaya.\r\n\r\nThis scroll depicts the trials undergone by members of Force 136 and drawn from the memory of Tan Chong Tee. The first part of the scroll (from right) depicts torturing of the members to force confessions out of them, fierce interrogation of Tan Chong Tee and him trying to outwit the Japanese. \r\n"},"nlpDate":"20201018182636","connectorId":0,"tags":{}}