{
  "id": "2017-00482-014",
  "title": "Pantjangan Pertama The First Signpost",
  "source": "Bumblebee",
  "path": "./Data/json/",
  "content": "\n  accession_no_csv: 2017-00482-014\n\n  Image: \n\n  object_work_type: artists\\u0027 books (books) linocuts (prints)\n\n  title_text: Pantjangan Pertama The First Signpost\n\n  preference: alternate\n\n  title_language: \n\n  creator_2: Mochtar Apin\n\n  creator_1: Apin\n Mochtar\n\n  creator_role: artists (visual artists)\n\n  creation_date: 1948\n\n  creation_place_original_location: Bandung (Indonesia)\n\n  styles_periods_indexing_terms: Indonesian (culture or style)\n\n  inscriptions: \n\n  inscription_language: \n\n  shape: Rectangular\n\n  materials_name: paper (fiber product)\n\n  techniques_name: linoleum block printing\n\n  object_colour: black-and-white (colour)\n\n  edition_description: Artist Proof\n\n  physical_appearance: \\The title of this section is \\\\sepatah kata tentang pahatan-lino\\\\ which translates to \\\\a word about lino-carvings\\\\. It outlines the lino-carving procedure\n\n  subject_terms_1: and even has an illustration of the process. \\\n\n  subject_terms_2: Apin\n Mochtar instructions (document genre) Instruction guide series Linoleum block-printing\n\n  subject_terms_3: Prints\n Indonesian\n\n  subject_terms_4: Visual arts\n",
  "createdDate": "20201125084519",
  "version": 0,
  "latest": false,
  "roles": [],
  "metadata": {
    "accession_no_csv": "2017-00482-014",
    "Image": "",
    "object_work_type": "artists\u0027 books (books) linocuts (prints)",
    "title_text": "Pantjangan Pertama The First Signpost",
    "preference": "alternate",
    "title_language": "",
    "creator_2": "Mochtar Apin",
    "creator_1": "Apin, Mochtar",
    "creator_role": "artists (visual artists)",
    "creation_date": "1948",
    "creation_place_original_location": "Bandung (Indonesia)",
    "styles_periods_indexing_terms": "Indonesian (culture or style)",
    "inscriptions": "",
    "inscription_language": "",
    "shape": "Rectangular",
    "materials_name": "paper (fiber product)",
    "techniques_name": "linoleum block printing",
    "object_colour": "black-and-white (colour)",
    "edition_description": "Artist Proof",
    "physical_appearance": "\"The title of this section is \"\"sepatah kata tentang pahatan-lino\"\" which translates to \"\"a word about lino-carvings\"\". It outlines the lino-carving procedure",
    "subject_terms_1": "and even has an illustration of the process. \"",
    "subject_terms_2": "Apin, Mochtar instructions (document genre) Instruction guide series Linoleum block-printing",
    "subject_terms_3": "Prints, Indonesian",
    "subject_terms_4": "Visual arts"
  },
  "nlpDate": "20201125084519",
  "connectorId": 0,
  "tags": {}
}