{"id":"2017-00145-004","title":"Reflections of Tan Chong Tee: Letters, Notes, and Photographs Reflections of Tan Chong Tee: Caption with list of names of Force 136 liaison officers","source":"Bumblebee","path":"./Data/json/","content":"accession_no_csv:2017-00145-004\nImage:\nobject_work_type:captions\ntitle_text:Reflections of Tan Chong Tee: Letters\n Notes\n and Photographs Reflections of Tan Chong Tee: Caption with list of names of Force 136 liaison officers\npreference:alternate  main\ntitle_language:\ncreation_place_original_location:Ipoh (Perak\n Malaysia)\ninscriptions:\ninscription_language:\nshape:Rectangular\nmaterials_name:paper (fiber product)\ntechniques_name:handwriting\nobject_colour:blue (colour)\nphysical_appearance:This is a caption for the image 003 and it lists the names of the liaison officers of Force 136.\nsubject_terms_1:group portraits  world wars resistance movements  guerilla warfare local histories ceremonies  officers (administrators)\nsubject_terms_2:Portraits\n Group Zhongguo guo min dang  War resistance movements  Guerillas  Local history Photographs  Farewells Chinese diaspora  Force 136 (Guerilla movement) Public officers  Writing  Chen\n Chongzhi\n 1916-  Great Britain. Army. Force 136 World War\n 1939-1945\nsubject_terms_3:Portrait photography  1942-1945 Japanese Occupation  Wars Force 136 (Guerilla movement) Tan\n Chong Tee Government officials  History  war personalities  Chuang\n Hui Tsuan  Lee\n Han Kong Tham\n Sien Yen  Lung\n Chiu Ying\ncontext_1:1942-1945 Japanese Occupation\ncontext_2:occupations (armed conflicts)\ncontext_3:1942-1945\ncontext_4:1942\ncontext_5:1945\ncontext_6:Singapore\ncontext_7:Japan. Rikugun  Imperial Japanese Army\ncontext_8:colonists\nsgcool_label_text:These documents and photographs belong to a larger part of a collection of artefacts related to the World War II underground resistance movement known as Force 136. The collection of materials was gathered by Tan Chong Tee (1916- 2012)\n who was a key member of this resistance group. The collection consists of original materials belonging to Tan and other members of Force 136 dating from the 1940s to new materials reproduced from memory by Tan Chong Tee\n which date from the late 1980s to early 2000s. \\r\\n\\r\\nForce 136 was set up in July 1942 as part of the British Special Operations Executive (SOE). It recruited and trained local guerillas to gather intelligence and create an underground spy network to support planned British invasion of Japanese-occupied Malaya.\\r\\n","createdDate":"20201119143406","version":0,"latest":false,"roles":[],"metadata":{"accession_no_csv":"2017-00145-004","Image":"","object_work_type":"captions","title_text":"Reflections of Tan Chong Tee: Letters, Notes, and Photographs Reflections of Tan Chong Tee: Caption with list of names of Force 136 liaison officers","preference":"alternate  main","title_language":"","creation_place_original_location":"Ipoh (Perak, Malaysia)","inscriptions":"","inscription_language":"","shape":"Rectangular","materials_name":"paper (fiber product)","techniques_name":"handwriting","object_colour":"blue (colour)","physical_appearance":"This is a caption for the image 003 and it lists the names of the liaison officers of Force 136.","subject_terms_1":"group portraits  world wars resistance movements  guerilla warfare local histories ceremonies  officers (administrators)","subject_terms_2":"Portraits, Group Zhongguo guo min dang  War resistance movements  Guerillas  Local history Photographs  Farewells Chinese diaspora  Force 136 (Guerilla movement) Public officers  Writing  Chen, Chongzhi, 1916-  Great Britain. Army. Force 136 World War, 1939-1945","subject_terms_3":"Portrait photography  1942-1945 Japanese Occupation  Wars Force 136 (Guerilla movement) Tan, Chong Tee Government officials  History  war personalities  Chuang, Hui Tsuan  Lee, Han Kong Tham, Sien Yen  Lung, Chiu Ying","context_1":"1942-1945 Japanese Occupation","context_2":"occupations (armed conflicts)","context_3":"1942-1945","context_4":"1942","context_5":"1945","context_6":"Singapore","context_7":"Japan. Rikugun  Imperial Japanese Army","context_8":"colonists","sgcool_label_text":"These documents and photographs belong to a larger part of a collection of artefacts related to the World War II underground resistance movement known as Force 136. The collection of materials was gathered by Tan Chong Tee (1916- 2012), who was a key member of this resistance group. The collection consists of original materials belonging to Tan and other members of Force 136 dating from the 1940s to new materials reproduced from memory by Tan Chong Tee, which date from the late 1980s to early 2000s. \r\n\r\nForce 136 was set up in July 1942 as part of the British Special Operations Executive (SOE). It recruited and trained local guerillas to gather intelligence and create an underground spy network to support planned British invasion of Japanese-occupied Malaya.\r\n"},"nlpDate":"20201119143406","connectorId":0,"tags":{}}