{
  "id": "2017-00013",
  "title": "Dish Dishes with Eight Immortals",
  "source": "Bumblebee",
  "path": "./Data/json/",
  "content": "\n  accession_no_csv: 2017-00013\n\n  Image: \n\n  object_work_type: ceramics (object genre) dishes (vessels for food)\n\n  title_text: Dish Dishes with Eight Immortals\n\n  preference: alternate main\n\n  title_language: \n\n  creation_date: 1821-1850\n\n  creation_place_original_location: China\n\n  styles_periods_indexing_terms: Daoguang\n\n  inscriptions: \n\n  inscription_language: \n\n  shape: concave\n\n  materials_name: ceramic (material) enamel paint\n\n  techniques_name: firing (technique) pottery technique\n\n  object_colour: multicolored\n\n  physical_appearance: This is a set of two ceramic dishes. The interior of these dishes feture a variety of birds flying amongst several flowers against a lime green background. On the exterior\n the Eight Immortals are depicted riding the waves amidst clouds. There are no cracks seen on the dishes.\n\n  subject_terms_1: tableware flower (motif) birds (motifs) deities depictions (visual works) Taoism\n\n  subject_terms_2: Ceramics Tableware Motifs Gods Ba Xian (Taoist mythology)\n\n  subject_terms_3: Decorative arts Ceramics Taoism\n\n  context_18: NAN\n\n  context_19: A\n\n  sgcool_label_text: A beautiful and lively medley of auspicious Chinese birds and flowers are painted on the broad base of the interior of this pair of famille rose dishes. The phoenix\n pheasant\n cranes\n magpies and swallows fly and wonder amidst luscious blooms of the flowers of the four seasons; the peony\n lotus\n chrysanthemum and prunus. Set against a vibrant lime green ground\n the birds\n foliage and plumage are skillfully rendered\n with realistic veining\n and subtle colour gradations in the enamels. The lack of proportion of the motifs and dense decoration also create a romantic and whimsical charm to the overall composition. On the exterior of the slightly flaring shallow sides of the dishes\n the Eight Immortals are depicted riding the waves amidst auspicious ruyi clouds\n a reference to a key mythical story of crossing the ocean. Together\n the auspicious decoration convey wishes of longevity\n prosperity and good fortune. \\r\\n\\r\\nThe lime-green bases of both dishes carry the six-character\n “Da Qing Daoguang Nian Zhi” (Made in the Daoguang reign of the great Qing dynasty) in iron-red. The technical mastery evident in the brushwork reflects how high-quality production continued in the late Qing period\n especially the Daoguang and Guangxu periods.\n",
  "createdDate": "20201120223707",
  "version": 0,
  "latest": false,
  "roles": [],
  "metadata": {
    "accession_no_csv": "2017-00013",
    "Image": "",
    "object_work_type": "ceramics (object genre) dishes (vessels for food)",
    "title_text": "Dish Dishes with Eight Immortals",
    "preference": "alternate main",
    "title_language": "",
    "creation_date": "1821-1850",
    "creation_place_original_location": "China",
    "styles_periods_indexing_terms": "Daoguang",
    "inscriptions": "",
    "inscription_language": "",
    "shape": "concave",
    "materials_name": "ceramic (material) enamel paint",
    "techniques_name": "firing (technique) pottery technique",
    "object_colour": "multicolored",
    "physical_appearance": "This is a set of two ceramic dishes. The interior of these dishes feture a variety of birds flying amongst several flowers against a lime green background. On the exterior, the Eight Immortals are depicted riding the waves amidst clouds. There are no cracks seen on the dishes.",
    "subject_terms_1": "tableware flower (motif) birds (motifs) deities depictions (visual works) Taoism",
    "subject_terms_2": "Ceramics Tableware Motifs Gods Ba Xian (Taoist mythology)",
    "subject_terms_3": "Decorative arts Ceramics Taoism",
    "context_18": "NAN",
    "context_19": "A",
    "sgcool_label_text": "A beautiful and lively medley of auspicious Chinese birds and flowers are painted on the broad base of the interior of this pair of famille rose dishes. The phoenix, pheasant, cranes, magpies and swallows fly and wonder amidst luscious blooms of the flowers of the four seasons; the peony, lotus, chrysanthemum and prunus. Set against a vibrant lime green ground, the birds, foliage and plumage are skillfully rendered, with realistic veining, and subtle colour gradations in the enamels. The lack of proportion of the motifs and dense decoration also create a romantic and whimsical charm to the overall composition. On the exterior of the slightly flaring shallow sides of the dishes, the Eight Immortals are depicted riding the waves amidst auspicious ruyi clouds, a reference to a key mythical story of crossing the ocean. Together, the auspicious decoration convey wishes of longevity, prosperity and good fortune. \r\n\r\nThe lime-green bases of both dishes carry the six-character, “Da Qing Daoguang Nian Zhi” (Made in the Daoguang reign of the great Qing dynasty) in iron-red. The technical mastery evident in the brushwork reflects how high-quality production continued in the late Qing period, especially the Daoguang and Guangxu periods."
  },
  "nlpDate": "20201120223707",
  "connectorId": 0,
  "tags": {}
}