{
  "id": "2017-00532-001 to 003",
  "title": "The Mystical Reality Reinvented --Metamorphosis",
  "source": "Bumblebee",
  "path": "./Data/json/",
  "content": "\n  accession_no_csv: 2017-00532-001 to 003\n\n  Image: \n\n  object_work_type: photographic prints  installations (visual works)\n\n  title_text: The Mystical Reality Reinvented --Metamorphosis\n\n  preference: main\n\n  title_language: \n\n  creator_2: Sulaiman Esa\n\n  creator_1: Sulaiman Hj. Esa\n 1941-\n\n  creator_role: artists (visual artists)\n\n  creation_date: 2015\n\n  creation_place_original_location: Malaysia\n\n  inscriptions: \n\n  inscription_language: \n\n  shape: Rectangular\n\n  materials_name: photographic paper\n\n  techniques_name: colour photography\n\n  object_colour: multicoloured\n\n  physical_appearance: This work consists of three A3 sized photographic prints. The first of which shows a stained rain coat\n the second captures a figure standing within an angular black perimeter with his/her head covered by a black conical hat\n and the last being the same figure with his/her hands outstretched with his/her finger attached to some cords. The raincoat is also progressively stained over the course of the three images.\n\n  subject_terms_1: atrocities prisoners justice (philosophical concept)  torturing\n\n  subject_terms_2: Abu Ghraib Prison Muslim prisoners Justice Torture  Prints  Installations (Art)\n\n  subject_terms_3: visual arts\n\n  sgcool_label_text: As graduates from the Hornsey College of Art in London (1962-1968)\n Sulaiman and fellow Malaysian art student Redza Piyadasa co-created a seminal artwork-cum-exhibition called “Towards a Mystical Reality: A Documentation of Jointly Initiated Experienced by Redza Piyadasa and Suleiman Esa” (TMR) at the Dewan Bahasa dan Pustaka (Institute of Language and Literature) in Kuala Lumpur from 2-7 August\n 1974.  The exhibition showed an assortment of everyday objects and detritus but each indexing an event. In so doing\n the artists presented a paradigm shift in how art was received and theorised in Malaysia at the time:  art became a means of critical enquiry and discussions about the definitions of art informed their enquiries and creations\n where the art object was secondary to the ideas and experiences provoked by it.\\r\\n  \\r\\nFor the inaugural exhibition of the Southeast Asia Gallery and to complement its archival display of the historic 1974 exhibition of TMR\n the Gallery is commissioning the artist Sulaiman Esa (the surviving half of the duo) to produce a new work titled “A Mystical Reality Reinvented”\n which looks back at TMR but interpreting this from the vantage point of today and also his own practice\n",
  "createdDate": "20201120223708",
  "version": 0,
  "latest": false,
  "roles": [],
  "metadata": {
    "accession_no_csv": "2017-00532-001 to 003",
    "Image": "",
    "object_work_type": "photographic prints  installations (visual works)",
    "title_text": "The Mystical Reality Reinvented --Metamorphosis",
    "preference": "main",
    "title_language": "",
    "creator_2": "Sulaiman Esa",
    "creator_1": "Sulaiman Hj. Esa, 1941-",
    "creator_role": "artists (visual artists)",
    "creation_date": "2015",
    "creation_place_original_location": "Malaysia",
    "inscriptions": "",
    "inscription_language": "",
    "shape": "Rectangular",
    "materials_name": "photographic paper",
    "techniques_name": "colour photography",
    "object_colour": "multicoloured",
    "physical_appearance": "This work consists of three A3 sized photographic prints. The first of which shows a stained rain coat, the second captures a figure standing within an angular black perimeter with his/her head covered by a black conical hat, and the last being the same figure with his/her hands outstretched with his/her finger attached to some cords. The raincoat is also progressively stained over the course of the three images.",
    "subject_terms_1": "atrocities prisoners justice (philosophical concept)  torturing",
    "subject_terms_2": "Abu Ghraib Prison Muslim prisoners Justice Torture  Prints  Installations (Art)",
    "subject_terms_3": "visual arts",
    "sgcool_label_text": "As graduates from the Hornsey College of Art in London (1962-1968), Sulaiman and fellow Malaysian art student Redza Piyadasa co-created a seminal artwork-cum-exhibition called “Towards a Mystical Reality: A Documentation of Jointly Initiated Experienced by Redza Piyadasa and Suleiman Esa” (TMR) at the Dewan Bahasa dan Pustaka (Institute of Language and Literature) in Kuala Lumpur from 2-7 August, 1974.  The exhibition showed an assortment of everyday objects and detritus but each indexing an event. In so doing, the artists presented a paradigm shift in how art was received and theorised in Malaysia at the time:  art became a means of critical enquiry and discussions about the definitions of art informed their enquiries and creations, where the art object was secondary to the ideas and experiences provoked by it.\r\n  \r\nFor the inaugural exhibition of the Southeast Asia Gallery and to complement its archival display of the historic 1974 exhibition of TMR, the Gallery is commissioning the artist Sulaiman Esa (the surviving half of the duo) to produce a new work titled “A Mystical Reality Reinvented”, which looks back at TMR but interpreting this from the vantage point of today and also his own practice"
  },
  "nlpDate": "20201120223708",
  "connectorId": 0,
  "tags": {}
}