{
  "id": "2017-01150-001 TO 039",
  "title": "Violin from the collection of Mrs Marimuthu Gopalakrishnan Violin And Case",
  "source": "Bumblebee",
  "path": "./Data/json/",
  "content": "\n  accession_no_csv: 2017-01150-001 TO 039\n\n  Image: \n\n  object_work_type: violins\n\n  title_text: Violin from the collection of Mrs Marimuthu Gopalakrishnan Violin And Case\n\n  preference: alternate main\n\n  title_language: \n\n  creation_date: 1980-2000\n\n  creation_place_original_location: Singapore\n\n  inscriptions: \n\n  inscription_language: \n\n  materials_name: wood (plant material)\n\n  techniques_name: assembling (additive and joining process)\n\n  object_colour: multicolored\n\n  physical_appearance: This is a violin with its case and accessories. The case is black\n and has a red inner cushioning. It has two clasps at each end\n and a handle in the middle for easy carrying.\n\n  subject_terms_1: violin cases  rosin bows (chordophone components) stringed instruments (musical instruments)  music (performing arts)\n\n  subject_terms_2: Violin Violin cases Gums and resins Violin bows Stringed instruments  Music  Performing arts\n\n  subject_terms_3: Music Performing Arts\n\n  subject_terms_4: \n\n  sgcool_label_text: Mr. S Gopalakrishnan (b. in 1920 in Tanjavur) was a prominent violinist\n and Carnatic singer. He arrived in Singapore in 1939 and actively participated in the Indian classical music scene here. Mr Gopalakrishnan performed alongside veterans of classical performers such as Pandit M Ramalingam and MV Gurusamy at temple and other music festivals. He also taught violin lessons at the Singapore Malayalee Association from the 1970s to 2000s. He was a member of the Tamils Reform Association and performed his wedding according to the principles of the Self-Respect Movement. He was also employed as a compositor at the Far East Air Force from 1954 to 1970.\n",
  "createdDate": "20201120223708",
  "version": 0,
  "latest": false,
  "roles": [],
  "metadata": {
    "accession_no_csv": "2017-01150-001 TO 039",
    "Image": "",
    "object_work_type": "violins",
    "title_text": "Violin from the collection of Mrs Marimuthu Gopalakrishnan Violin And Case",
    "preference": "alternate main",
    "title_language": "",
    "creation_date": "1980-2000",
    "creation_place_original_location": "Singapore",
    "inscriptions": "",
    "inscription_language": "",
    "materials_name": "wood (plant material)",
    "techniques_name": "assembling (additive and joining process)",
    "object_colour": "multicolored",
    "physical_appearance": "This is a violin with its case and accessories. The case is black, and has a red inner cushioning. It has two clasps at each end, and a handle in the middle for easy carrying.",
    "subject_terms_1": "violin cases  rosin bows (chordophone components) stringed instruments (musical instruments)  music (performing arts)",
    "subject_terms_2": "Violin Violin cases Gums and resins Violin bows Stringed instruments  Music  Performing arts",
    "subject_terms_3": "Music Performing Arts",
    "subject_terms_4": "",
    "sgcool_label_text": "Mr. S Gopalakrishnan (b. in 1920 in Tanjavur) was a prominent violinist, and Carnatic singer. He arrived in Singapore in 1939 and actively participated in the Indian classical music scene here. Mr Gopalakrishnan performed alongside veterans of classical performers such as Pandit M Ramalingam and MV Gurusamy at temple and other music festivals. He also taught violin lessons at the Singapore Malayalee Association from the 1970s to 2000s. He was a member of the Tamils Reform Association and performed his wedding according to the principles of the Self-Respect Movement. He was also employed as a compositor at the Far East Air Force from 1954 to 1970."
  },
  "nlpDate": "20201120223708",
  "connectorId": 0,
  "tags": {}
}