{"id":"2017-00294-009","title":"Group of 50 photographs of P.O.W James Steele and regiment when stationed in Malaysia in 1941 (and 2 later photographs of Steele placing a wreath at ceremony of remembrance)  Tom Hey, Naval Base Singapore 1941","source":"Bumblebee","path":"./Data/json/","content":"accession_no_csv:2017-00294-009\nImage:\nobject_work_type:black-and-white photographs\ntitle_text:Group of 50 photographs of P.O.W James Steele and regiment when stationed in Malaysia in 1941 (and 2 later photographs of Steele placing a wreath at ceremony of remembrance)  Tom Hey\n Naval Base Singapore 1941\npreference:alternate main\ntitle_language:\ncreation_date:1941-1945\ncreation_place_original_location:Singapore Naval Base\ninscriptions:\ninscription_language:\nshape:rectangular\nmaterials_name:paper (fiber product)\ntechniques_name:photographic processes\nobject_colour:black-and-white (colors)\nphysical_appearance:This is a black-and-white photograph. It features a man\n dressed in mid-length light-coloured pants and shoes. He is standing casually poised with his arms by his side. Behind him\n there is a section of a wall\n with some small bushes in front of it. There are no tears or folds seen on the photograph.\nsubject_terms_1:world wars portraits soldiers\nsubject_terms_2:World War\n 1939-1945 Portrait photography Singapore Naval Base Soldiers\nsubject_terms_3:Portrait photography war personalities\nsubject_terms_4:\ncontext_1:World War\n 1939-1945\ncontext_2:world wars\ncontext_3:1939-1945\ncontext_4:1939\ncontext_5:1945\ncontext_6:Malaya\ncontext_7:Great Britain. Army. Royal Field Artillery\ncontext_8:armed forces\nsgcool_label_text:A variety of portraits of British soldiers that show them at leisure as well as two photographs of James Steele placing a wreath at a remembrance ceremony\n this collection is part of the archive of James Steele\n Royal Artillery (Field) who served in Malaya from January 1941-February 1942\n when interned as a P.O.W at Changi until his release in October 1945.","createdDate":"20201018182636","version":0,"latest":false,"roles":[],"metadata":{"accession_no_csv":"2017-00294-009","Image":"","object_work_type":"black-and-white photographs","title_text":"Group of 50 photographs of P.O.W James Steele and regiment when stationed in Malaysia in 1941 (and 2 later photographs of Steele placing a wreath at ceremony of remembrance)  Tom Hey, Naval Base Singapore 1941","preference":"alternate main","title_language":"","creation_date":"1941-1945","creation_place_original_location":"Singapore Naval Base","inscriptions":"","inscription_language":"","shape":"rectangular","materials_name":"paper (fiber product)","techniques_name":"photographic processes","object_colour":"black-and-white (colors)","physical_appearance":"This is a black-and-white photograph. It features a man, dressed in mid-length light-coloured pants and shoes. He is standing casually poised with his arms by his side. Behind him, there is a section of a wall, with some small bushes in front of it. There are no tears or folds seen on the photograph.","subject_terms_1":"world wars portraits soldiers","subject_terms_2":"World War, 1939-1945 Portrait photography Singapore Naval Base Soldiers","subject_terms_3":"Portrait photography war personalities","subject_terms_4":"","context_1":"World War, 1939-1945","context_2":"world wars","context_3":"1939-1945","context_4":"1939","context_5":"1945","context_6":"Malaya","context_7":"Great Britain. Army. Royal Field Artillery","context_8":"armed forces","sgcool_label_text":"A variety of portraits of British soldiers that show them at leisure as well as two photographs of James Steele placing a wreath at a remembrance ceremony, this collection is part of the archive of James Steele, Royal Artillery (Field) who served in Malaya from January 1941-February 1942, when interned as a P.O.W at Changi until his release in October 1945."},"nlpDate":"20201018182636","connectorId":0,"tags":{}}