{
  "id": "2017-00476",
  "title": "Batik Variant Truntum II",
  "source": "Bumblebee",
  "path": "./Data/json/",
  "content": "\n  accession_no_csv: 2017-00476\n\n  Image: \n\n  object_work_type: canvas paintings acrylic paintings (visual works)\n\n  title_text: Batik Variant Truntum II\n\n  preference: main\n\n  title_language: \n\n  creator_2: Mochtar Apin\n\n  creator_1: Apin\n Mochtar\n\n  creator_role: artists (visual artists)\n\n  creation_date: 1985\n\n  creation_place_original_location: Bandung (Indonesia)\n\n  styles_periods_indexing_terms: Indonesian (culture or style)\n\n  inscriptions: \n\n  inscription_language: \n\n  shape: Rectangular\n\n  materials_name: canvas board acrylic paint\n\n  techniques_name: acrylic painting (technique)\n\n  object_colour: multicoloured\n\n  physical_appearance: This is a multicoloured painting of batik prints. Its composition comprises of repeated geometric patterns.\n\n  subject_terms_1: batik art geometric patterns repeated motif\n\n  subject_terms_2: Arts\n Indonesian Reinterpreting history Batik Geometry in art\n\n  subject_terms_3: visual arts acrylic painting\n\n  sgcool_label_text: This work continues Apin’s investigations into the batik tradition in relation to its role in Indonesian art history.  This investigation started in the 1970s with his batik print works. The period also saw many modern Indonesian artists re-visiting traditional culture and mythology. Subsequently some would incorporate these elements into their visual language.\n",
  "createdDate": "20201201203308",
  "version": 0,
  "latest": false,
  "roles": [],
  "metadata": {
    "accession_no_csv": "2017-00476",
    "Image": "",
    "object_work_type": "canvas paintings acrylic paintings (visual works)",
    "title_text": "Batik Variant Truntum II",
    "preference": "main",
    "title_language": "",
    "creator_2": "Mochtar Apin",
    "creator_1": "Apin, Mochtar",
    "creator_role": "artists (visual artists)",
    "creation_date": "1985",
    "creation_place_original_location": "Bandung (Indonesia)",
    "styles_periods_indexing_terms": "Indonesian (culture or style)",
    "inscriptions": "",
    "inscription_language": "",
    "shape": "Rectangular",
    "materials_name": "canvas board acrylic paint",
    "techniques_name": "acrylic painting (technique)",
    "object_colour": "multicoloured",
    "physical_appearance": "This is a multicoloured painting of batik prints. Its composition comprises of repeated geometric patterns.",
    "subject_terms_1": "batik art geometric patterns repeated motif",
    "subject_terms_2": "Arts, Indonesian Reinterpreting history Batik Geometry in art",
    "subject_terms_3": "visual arts acrylic painting",
    "sgcool_label_text": "This work continues Apin’s investigations into the batik tradition in relation to its role in Indonesian art history.  This investigation started in the 1970s with his batik print works. The period also saw many modern Indonesian artists re-visiting traditional culture and mythology. Subsequently some would incorporate these elements into their visual language."
  },
  "nlpDate": "20201201203308",
  "connectorId": 0,
  "tags": {}
}