{
  "id": "2017-00105",
  "title": "Malayan Contact Network Established by the Allied Commandos in 1943",
  "source": "Bumblebee",
  "path": "./Data/json/",
  "content": "\n  accession_no_csv: 2017-00105\n\n  Image: \n\n  object_work_type: drawings (visual works) maps (documents)\n\n  title_text: Malayan Contact Network Established by the Allied Commandos in 1943\n\n  preference: main alternate\n\n  title_language: \n\n  creator_2: Tan Chong Tee\n\n  creator_1: Chen\n Chongzhi\n 1916-\n\n  creator_role: artists (visual artists)\n\n  creation_date: 1943\n\n  creation_place_original_location: Singapore\n\n  inscriptions: \n\n  inscription_language: \n\n  scale_type: Not indicated\n\n  shape: rectangular\n\n  materials_name: paper (fiber product) ink\n\n  techniques_name: painting (image-making)\n\n  object_colour: black-and-white (colors)\n\n  physical_appearance: This is a drawn map of the Malayan Contact Network establised by the Allied Commandos. The title is inscribed on the left side of the map. It shows a part of Peninsula West Malaya\n labelling several points in both English and Chinese\n with a network drawn between points. The map is in black and white.\n\n  subject_terms_1: resistance movements world wars Chinese scripts\n\n  subject_terms_2: World War\n 1939-1945 Chen\n Chongzhi\n 1916- Maps Drawing Great Britain. Army. Force 136 Force 136 (Guerilla movement) Malaya\n\n  subject_terms_3: 1942-1945 Japanese occupation Tan\n Chong Tee Drawing Force 136 (Guerilla movement)\n\n  subject_terms_4: \n\n  context_1: World War\n 1939-1945 1942-1945 Japanese Occupation\n\n  context_2: occupations (armed conflicts) world wars\n\n  context_3: 1942-1945 1939-1945\n\n  context_4: 1939 1942\n\n  context_5: 1945\n\n  context_6: Singapore Malaya\n\n  context_7: Great Britain. Army. Force 136\n\n  context_8: armed forces\n\n  sgcool_label_text: This drawing belongs to part of a collection of artefacts related to the World War II underground resistance movement known as Force 136. The collection of materials was gathered by Tan Chong Tee (1916- 2012)\n who was a key member of this resistance group. The collection consists of original materials belonging to Tan and other members of Force 136 dating from the 1940s to new materials reproduced from memory by Tan Chong Tee\n which date from mid 1990s to early 2000s. \\r\\n\\r\\nForce 136 was set up in July 1942 as part of the British Special Operations Executive (SOE). It recruited and trained local guerrillas to gather intelligence and create an underground spy network to support planned British invasion of Japanese-occupied Malaya.\\r\\n\\r\\nThis map is a depiction of the Malayan Contact Network Established by the Allied Commandos in 1943. \\r\\n\n",
  "createdDate": "20201125084529",
  "version": 0,
  "latest": false,
  "roles": [],
  "metadata": {
    "accession_no_csv": "2017-00105",
    "Image": "",
    "object_work_type": "drawings (visual works) maps (documents)",
    "title_text": "Malayan Contact Network Established by the Allied Commandos in 1943",
    "preference": "main alternate",
    "title_language": "",
    "creator_2": "Tan Chong Tee",
    "creator_1": "Chen, Chongzhi, 1916-",
    "creator_role": "artists (visual artists)",
    "creation_date": "1943",
    "creation_place_original_location": "Singapore",
    "inscriptions": "",
    "inscription_language": "",
    "scale_type": "Not indicated",
    "shape": "rectangular",
    "materials_name": "paper (fiber product) ink",
    "techniques_name": "painting (image-making)",
    "object_colour": "black-and-white (colors)",
    "physical_appearance": "This is a drawn map of the Malayan Contact Network establised by the Allied Commandos. The title is inscribed on the left side of the map. It shows a part of Peninsula West Malaya, labelling several points in both English and Chinese, with a network drawn between points. The map is in black and white.",
    "subject_terms_1": "resistance movements world wars Chinese scripts",
    "subject_terms_2": "World War, 1939-1945 Chen, Chongzhi, 1916- Maps Drawing Great Britain. Army. Force 136 Force 136 (Guerilla movement) Malaya",
    "subject_terms_3": "1942-1945 Japanese occupation Tan, Chong Tee Drawing Force 136 (Guerilla movement)",
    "subject_terms_4": "",
    "context_1": "World War, 1939-1945 1942-1945 Japanese Occupation",
    "context_2": "occupations (armed conflicts) world wars",
    "context_3": "1942-1945 1939-1945",
    "context_4": "1939 1942",
    "context_5": "1945",
    "context_6": "Singapore Malaya",
    "context_7": "Great Britain. Army. Force 136",
    "context_8": "armed forces",
    "sgcool_label_text": "This drawing belongs to part of a collection of artefacts related to the World War II underground resistance movement known as Force 136. The collection of materials was gathered by Tan Chong Tee (1916- 2012), who was a key member of this resistance group. The collection consists of original materials belonging to Tan and other members of Force 136 dating from the 1940s to new materials reproduced from memory by Tan Chong Tee, which date from mid 1990s to early 2000s. \r\n\r\nForce 136 was set up in July 1942 as part of the British Special Operations Executive (SOE). It recruited and trained local guerrillas to gather intelligence and create an underground spy network to support planned British invasion of Japanese-occupied Malaya.\r\n\r\nThis map is a depiction of the Malayan Contact Network Established by the Allied Commandos in 1943. \r\n"
  },
  "nlpDate": "20201125084529",
  "connectorId": 0,
  "tags": {}
}