{
  "id": "2017-00145-027",
  "title": "Reflections of Tan Chong Tee: Letters, Notes, and Photographs ???????????????????????????? Reflections of Tan Chong Tee: Photograph of Lim\u0027s funeral procession",
  "source": "Bumblebee",
  "path": "./Data/json/",
  "content": "\n  accession_no_csv: 2017-00145-027\n\n  Image: \n\n  object_work_type: black-and-white photographs photographs\n\n  title_text: Reflections of Tan Chong Tee: Letters\n Notes\n and Photographs ???????????????????????????? Reflections of Tan Chong Tee: Photograph of Lim\\u0027s funeral procession\n\n  preference: alternate alternate main\n\n  title_language: \n\n  creation_date: 13-Jan-46\n\n  creation_place_original_location: Singapore\n\n  inscriptions: \n\n  inscription_language: \n\n  shape: Rectangular\n\n  materials_name: paper (fiber product)\n\n  techniques_name: black-and-white photography\n\n  object_colour: black-and-white (colors)\n\n  physical_appearance: This black and white photograph captures the scene where the military vehicle carrying Lim Bo Seng\\u0027s coffin traverses the streets. Throngs of people line up the streets to watch his coffin pass. Two armed forces personnel can be seen heading the procession whilst carrying a banner. The photograph is noticeably blur on the top right corner.\n\n  subject_terms_1: resistance movements  guerilla warfare local histories armed forces  funeral processions military vehicles  world wars\n\n  subject_terms_2: Force 136 (Guerilla movement) War resistance movements  Guerillas  Local history Photographs  Armed Forces  Great Britain. Army. Force 136 Military funerals  Vehicles\n Military Chen\n Chongzhi\n 1916-  World War\n 1939-1945\n\n  subject_terms_3: Force 136 (Guerilla movement) Death customs  Military transportation History  Tan\n Chong Tee war personalities  1942-1945 Japanese Occupation\n\n  context_1: Lim Bo Seng\\u0027s Memorial Service\n\n  context_2: memorial services\n\n  context_3: 13-Jan-46\n\n  context_4: 13-Jan-46\n\n  context_5: 13-Jan-46\n\n  context_6: City Hall (Singapore) MacRitchie Reservoir\n\n  context_7: Great Britain. Army. Force 136\n\n  context_8: planners\n\n  sgcool_label_text: These documents and photographs belong to a larger part of a collection of artefacts related to the World War II underground resistance movement known as Force 136. The collection of materials was gathered by Tan Chong Tee (1916- 2012)\n who was a key member of this resistance group. The collection consists of original materials belonging to Tan and other members of Force 136 dating from the 1940s to new materials reproduced from memory by Tan Chong Tee\n which date from the late 1980s to early 2000s. \\r\\n\\r\\nForce 136 was set up in July 1942 as part of the British Special Operations Executive (SOE). It recruited and trained local guerillas to gather intelligence and create an underground spy network to support planned British invasion of Japanese-occupied Malaya.\\r\\n\n",
  "createdDate": "20201120223707",
  "version": 0,
  "latest": false,
  "roles": [],
  "metadata": {
    "accession_no_csv": "2017-00145-027",
    "Image": "",
    "object_work_type": "black-and-white photographs photographs",
    "title_text": "Reflections of Tan Chong Tee: Letters, Notes, and Photographs ???????????????????????????? Reflections of Tan Chong Tee: Photograph of Lim\u0027s funeral procession",
    "preference": "alternate alternate main",
    "title_language": "",
    "creation_date": "13-Jan-46",
    "creation_place_original_location": "Singapore",
    "inscriptions": "",
    "inscription_language": "",
    "shape": "Rectangular",
    "materials_name": "paper (fiber product)",
    "techniques_name": "black-and-white photography",
    "object_colour": "black-and-white (colors)",
    "physical_appearance": "This black and white photograph captures the scene where the military vehicle carrying Lim Bo Seng\u0027s coffin traverses the streets. Throngs of people line up the streets to watch his coffin pass. Two armed forces personnel can be seen heading the procession whilst carrying a banner. The photograph is noticeably blur on the top right corner.",
    "subject_terms_1": "resistance movements  guerilla warfare local histories armed forces  funeral processions military vehicles  world wars",
    "subject_terms_2": "Force 136 (Guerilla movement) War resistance movements  Guerillas  Local history Photographs  Armed Forces  Great Britain. Army. Force 136 Military funerals  Vehicles, Military Chen, Chongzhi, 1916-  World War, 1939-1945",
    "subject_terms_3": "Force 136 (Guerilla movement) Death customs  Military transportation History  Tan, Chong Tee war personalities  1942-1945 Japanese Occupation",
    "context_1": "Lim Bo Seng\u0027s Memorial Service",
    "context_2": "memorial services",
    "context_3": "13-Jan-46",
    "context_4": "13-Jan-46",
    "context_5": "13-Jan-46",
    "context_6": "City Hall (Singapore) MacRitchie Reservoir",
    "context_7": "Great Britain. Army. Force 136",
    "context_8": "planners",
    "sgcool_label_text": "These documents and photographs belong to a larger part of a collection of artefacts related to the World War II underground resistance movement known as Force 136. The collection of materials was gathered by Tan Chong Tee (1916- 2012), who was a key member of this resistance group. The collection consists of original materials belonging to Tan and other members of Force 136 dating from the 1940s to new materials reproduced from memory by Tan Chong Tee, which date from the late 1980s to early 2000s. \r\n\r\nForce 136 was set up in July 1942 as part of the British Special Operations Executive (SOE). It recruited and trained local guerillas to gather intelligence and create an underground spy network to support planned British invasion of Japanese-occupied Malaya.\r\n"
  },
  "nlpDate": "20201120223707",
  "connectorId": 0,
  "tags": {}
}