{"id":"2017-00351","title":"Sarong","source":"Bumblebee","path":"./Data/json/","content":"accession_no_csv:2017-00351\nImage:\nobject_work_type:sarongs batik art\ntitle_text:Sarong\npreference:main\ntitle_language:\ncreator_2:Kok Sing Oey\ncreator_role:textile designers\ncreation_date:Early 20th century\ncreation_place_original_location:Pekalongan (Indonesia)\nstyles_periods_indexing_terms:Peranakan\ninscriptions:\ninscription_language:\nshape:rectangular\nmaterials_name:cotton (textile)\ntechniques_name:batik\nobject_colour:multicolored\nphysical_appearance:This is a batik sarong. It features a repeated pattern of large bouquets of European flowers interspersed with butterflies. The background of the batik sarong is brown and filled with dense motifs of white flowers. There is a slit at the bottom-center of the batik\n and the ends are frayed especially by the sides. There is no signature seen on this batik sarong.\nsubject_terms_1:Peranakan folk costume flower (motif) birds (motifs) cultural diffusion\nsubject_terms_2:Batik Ethnic costume Peranakan (Asian people) Motifs Culture diffusion\nsubject_terms_3:Batik Peranakan costumes\nsgcool_label_text:The buketan design\n comprising large bouquets of European flowers interspersed with butterflies and birds\n is depicted on both the badan (‘body’ or main design field) and kepala (broad vertical panel) of this sarong.  Although only two colours are shown\n the variety and density of filler motifs enliven the overall design.  This batik comes from the family collection of Oey Kok Sing (1896-1966)\n the second in three generations of documented batik-makers in Pekalongan.  Her later batik designs attest to her virtuosity in technique and inventive colour palette.  Her repertoire of tiny isen-isen motifs (filler motifs within the outlines of the key motifs) in particular\n exudes a strong sense of artistic individuality\n possibly informed by modernist designs on European printed cloths.  Her treatment of floral bouquets is also charactertistic of the undulating and curving lines of the Art Noveau style that was introduced in the northern coast of Java by the Europeans.  This piece is signed “Nj Oey Kok Sing “.","createdDate":"20201018182636","version":0,"latest":false,"roles":[],"metadata":{"accession_no_csv":"2017-00351","Image":"","object_work_type":"sarongs batik art","title_text":"Sarong","preference":"main","title_language":"","creator_2":"Kok Sing Oey","creator_role":"textile designers","creation_date":"Early 20th century","creation_place_original_location":"Pekalongan (Indonesia)","styles_periods_indexing_terms":"Peranakan","inscriptions":"","inscription_language":"","shape":"rectangular","materials_name":"cotton (textile)","techniques_name":"batik","object_colour":"multicolored","physical_appearance":"This is a batik sarong. It features a repeated pattern of large bouquets of European flowers interspersed with butterflies. The background of the batik sarong is brown and filled with dense motifs of white flowers. There is a slit at the bottom-center of the batik, and the ends are frayed especially by the sides. There is no signature seen on this batik sarong.","subject_terms_1":"Peranakan folk costume flower (motif) birds (motifs) cultural diffusion","subject_terms_2":"Batik Ethnic costume Peranakan (Asian people) Motifs Culture diffusion","subject_terms_3":"Batik Peranakan costumes","sgcool_label_text":"The buketan design, comprising large bouquets of European flowers interspersed with butterflies and birds, is depicted on both the badan (‘body’ or main design field) and kepala (broad vertical panel) of this sarong.  Although only two colours are shown, the variety and density of filler motifs enliven the overall design.  This batik comes from the family collection of Oey Kok Sing (1896-1966), the second in three generations of documented batik-makers in Pekalongan.  Her later batik designs attest to her virtuosity in technique and inventive colour palette.  Her repertoire of tiny isen-isen motifs (filler motifs within the outlines of the key motifs) in particular, exudes a strong sense of artistic individuality, possibly informed by modernist designs on European printed cloths.  Her treatment of floral bouquets is also charactertistic of the undulating and curving lines of the Art Noveau style that was introduced in the northern coast of Java by the Europeans.  This piece is signed “Nj Oey Kok Sing “."},"nlpDate":"20201018182636","connectorId":0,"tags":{}}