{"id":"2017-01084","title":"Lectern With The Jesuit Monogram","source":"Bumblebee","path":"./Data/json/","content":"accession_no_csv:2017-01084\nImage:\nobject_work_type:lecterns\ntitle_text:Lectern With The Jesuit Monogram\npreference:main\ntitle_language:\ncreation_date:Late 16th or early 17th century\ncreation_place_original_location:China Southeast Asia\nstyles_periods_indexing_terms:Japanese lacquer styles?\ninscriptions:\ninscription_language:\nshape:irregular\nmaterials_name:wood (plant material) mother of pearl lacquer (material) metal\ntechniques_name:carving (processes) inlay (process)\nobject_colour:multicoloured\nphysical_appearance:This is a lacquered lectern with inlaid mother-of-pearl. The central medallion shows a sunburst\n within which is the word IHS with three nails; the symbol of the Society of Jesus. Surrounding the central sunburst medallion are vegetative motifs in gold. The back panel shares a similar aesthetic scheme but with the addition of a pair of birds in flight.\nsubject_terms_1:missal stands plant-derived motifs  Christianity  Roman Catholicism monograms\nsubject_terms_2:Catholic Church  Christianity  Leaves in art Flowers in art Birds in art  Furniture  Jesuits  Monograms\nsubject_terms_3:Decorative arts  Christianity\nsubject_terms_4:\nsgcool_label_text:All surfaces of this wooden book stand are coated with lacquer\n and enhanced with gold and mother-of-pearl designs. The Jesuit emblem is prominent in the decoration. An elaborate lectern of this type\n emblazoned with the symbol of a religious order\n was likely meant to support a missal\n the book of texts and instructions used to celebrate the Catholic Mass.\\r\\n\\r\\nThe object was probably made in one of the port cities of Southeast Asia or China\n imitating similar Japanese objects\n which were in high demand at this time.\\r\\n","createdDate":"20201119143407","version":0,"latest":false,"roles":[],"metadata":{"accession_no_csv":"2017-01084","Image":"","object_work_type":"lecterns","title_text":"Lectern With The Jesuit Monogram","preference":"main","title_language":"","creation_date":"Late 16th or early 17th century","creation_place_original_location":"China Southeast Asia","styles_periods_indexing_terms":"Japanese lacquer styles?","inscriptions":"","inscription_language":"","shape":"irregular","materials_name":"wood (plant material) mother of pearl lacquer (material) metal","techniques_name":"carving (processes) inlay (process)","object_colour":"multicoloured","physical_appearance":"This is a lacquered lectern with inlaid mother-of-pearl. The central medallion shows a sunburst, within which is the word IHS with three nails; the symbol of the Society of Jesus. Surrounding the central sunburst medallion are vegetative motifs in gold. The back panel shares a similar aesthetic scheme but with the addition of a pair of birds in flight.","subject_terms_1":"missal stands plant-derived motifs  Christianity  Roman Catholicism monograms","subject_terms_2":"Catholic Church  Christianity  Leaves in art Flowers in art Birds in art  Furniture  Jesuits  Monograms","subject_terms_3":"Decorative arts  Christianity","subject_terms_4":"","sgcool_label_text":"All surfaces of this wooden book stand are coated with lacquer, and enhanced with gold and mother-of-pearl designs. The Jesuit emblem is prominent in the decoration. An elaborate lectern of this type, emblazoned with the symbol of a religious order, was likely meant to support a missal, the book of texts and instructions used to celebrate the Catholic Mass.\r\n\r\nThe object was probably made in one of the port cities of Southeast Asia or China, imitating similar Japanese objects, which were in high demand at this time.\r\n"},"nlpDate":"20201119143407","connectorId":0,"tags":{}}