{
  "id": "2017-00080",
  "title": "Bombing of Gong Guo Bridge",
  "source": "Bumblebee",
  "path": "./Data/json/",
  "content": "\n  accession_no_csv: 2017-00080\n\n  Image: \n\n  object_work_type: paintings (visual works)\n\n  title_text: Bombing of Gong Guo Bridge\n\n  preference: main alternate\n\n  title_language: \n\n  creator_2: Tan Chong Tee\n\n  creator_1: Chen\n Chongzhi\n 1916-\n\n  creator_role: artists (visual artists)\n\n  creation_date: 1989\n\n  creation_place_original_location: Singapore\n\n  inscriptions: \n\n  inscription_language: \n\n  shape: rectangular\n\n  materials_name: paper (fiber product) ink colour (pigment)\n\n  techniques_name: painting (image-making)\n\n  object_colour: multicolored\n\n  physical_appearance: This is a multicoloured painting depicting the bombing of Gong Guo Bridge. There are several men on the foregroup. A large tree occupies most of the painting on the right. There are several soldiers marching along the bath at the bottom. The background features  mountainous region. The painting is presented on a vertical scroll. There is a title and description written on the top left.\n\n  subject_terms_1: depictions (visual works) resistance movements scroll paintings world wars Chinese scripts\n\n  subject_terms_2: Burma Road (China and Burma) World War\n 1939-1945 Painting Chen\n Chongzhi\n 1916- Great Britain. Army. Force 136 Force 136 (Guerilla movement)\n\n  subject_terms_3: Painting 1942-1945 Japanese occupation Tan\n Chong Tee Force 136 (Guerilla movement)\n\n  subject_terms_4: \n\n  sgcool_label_text: This painting belongs to part of a collection of artefacts related to the World War II underground resistance movement known as Force 136. The collection of materials was gathered by Tan Chong Tee (1916-2012)\n who was a key member of this resistance group. The collection consists of original materials belonging to Tan and other members of Force 136 dating from the 1940s to new materials reproduced from memory by Tan Chong Tee\n which date from mid 1990s to early 2000s.\\r\\n\\r\\nForce 136 was set up in 1942-45 as part of the British Special Operations Executive (SOE). It recruited and trained local guerillas to gather intelligence and create an underground spy network to support planned British invasion of Japanese-occupied Malaya.\n",
  "createdDate": "20201201203308",
  "version": 0,
  "latest": false,
  "roles": [],
  "metadata": {
    "accession_no_csv": "2017-00080",
    "Image": "",
    "object_work_type": "paintings (visual works)",
    "title_text": "Bombing of Gong Guo Bridge",
    "preference": "main alternate",
    "title_language": "",
    "creator_2": "Tan Chong Tee",
    "creator_1": "Chen, Chongzhi, 1916-",
    "creator_role": "artists (visual artists)",
    "creation_date": "1989",
    "creation_place_original_location": "Singapore",
    "inscriptions": "",
    "inscription_language": "",
    "shape": "rectangular",
    "materials_name": "paper (fiber product) ink colour (pigment)",
    "techniques_name": "painting (image-making)",
    "object_colour": "multicolored",
    "physical_appearance": "This is a multicoloured painting depicting the bombing of Gong Guo Bridge. There are several men on the foregroup. A large tree occupies most of the painting on the right. There are several soldiers marching along the bath at the bottom. The background features  mountainous region. The painting is presented on a vertical scroll. There is a title and description written on the top left.",
    "subject_terms_1": "depictions (visual works) resistance movements scroll paintings world wars Chinese scripts",
    "subject_terms_2": "Burma Road (China and Burma) World War, 1939-1945 Painting Chen, Chongzhi, 1916- Great Britain. Army. Force 136 Force 136 (Guerilla movement)",
    "subject_terms_3": "Painting 1942-1945 Japanese occupation Tan, Chong Tee Force 136 (Guerilla movement)",
    "subject_terms_4": "",
    "sgcool_label_text": "This painting belongs to part of a collection of artefacts related to the World War II underground resistance movement known as Force 136. The collection of materials was gathered by Tan Chong Tee (1916-2012), who was a key member of this resistance group. The collection consists of original materials belonging to Tan and other members of Force 136 dating from the 1940s to new materials reproduced from memory by Tan Chong Tee, which date from mid 1990s to early 2000s.\r\n\r\nForce 136 was set up in 1942-45 as part of the British Special Operations Executive (SOE). It recruited and trained local guerillas to gather intelligence and create an underground spy network to support planned British invasion of Japanese-occupied Malaya."
  },
  "nlpDate": "20201201203308",
  "connectorId": 0,
  "tags": {}
}