{
  "id": "2017-01031",
  "title": "Untitled (MT_109)",
  "source": "Bumblebee",
  "path": "./Data/json/",
  "content": "\n  accession_no_csv: 2017-01031\n\n  Image: \n\n  object_work_type: acrylic painting (visual works) canvas paintings\n\n  title_text: Untitled (MT_109)\n\n  preference: main\n\n  title_language: \n\n  creator_2: Maria Taniguchi\n\n  creator_role: artists (visual artists)\n\n  creation_date: 2017\n\n  creation_place_original_location: Philippines\n\n  styles_periods_indexing_terms: Contemporary (style of art)\n\n  inscriptions: \n\n  inscription_language: \n\n  shape: Rectangular\n\n  materials_name: canvas (textile material) acrylic paint\n\n  techniques_name: acrylic painting (technique)\n\n  object_colour: black (colour)\n\n  edition_description: unique\n\n  physical_appearance: This is an acrylic on canvas painting in black. Brick lines are drawn in uniform grids. Notably\n the size of the painting is much smaller than its counterpart.\n\n  subject_terms_1: repetition (artistic concept) Minimal monochrome\n\n  subject_terms_2: Acrylic painting Repetition (Aesthetics) Minimal art\n\n  subject_terms_3: Acrylic painting\n\n  sgcool_label_text: Like monochromatic monoliths\n Maria Taniguchi’s ‘Brick’ paintings occupy a silent but palpable presence in space. Each painting in this body of works is covered by a uniform grid of brick lines pencil-drawn onto the surface\n and the brick lines perform simultaneously as a formal\n visual schema and conceptual device that conjoins each painting to the next – and all other ‘Brick’ pieces – in this decade-long series. An impeccable surface underscores the work’s quality as a two-dimensional painting\n yet the work’s objecthood is emphasized by how each ‘Brick’ is often installed leaning against the wall rather than hanging off it\n such that the work oscillates between abstract painting and/or minimalist sculpture. And despite appearing like a wall against a wall\n each ‘Brick’ is\n in actuality\n an environment or world unto itself: it does not represent anything other than itself. Each stands rather\n as a record of time and pain-staking labour for Taniguchi paints each brick individually – an exercise of repetition that transforms the paintings into temporal registers of artistic process. \\r\\n\\r\\nTaniguchi is best known for her large-scaled ‘Bricks’ which make their most impactful statements  – not merely in terms of physical presence\n but more significantly\n as visual documents to the passage of time – and MT_116 stands as one of her rare\n few works that approaches such a monumental scale. \\r\\n\\r\\nMaria Taniguchi (b. 1981\n Dumaguete City\n Philippines\n in 1981) won the Hugo Boss Asia Art Award in 2015 and was a LUX Associate Artist in 2009. Recent exhibitions include History of a vanishing present: A prologue\n the Mistake Room\n Los Angeles (2016); Afterwork\n Para Site\n Hong Kong (2016); Globale: New sensorium\n ZKM Centre for Art and Media\n Karlsruhe\n Germany (2016); The vexed contemporary\n Museum of Contemporary Art and Design\n Manila (2015); and the 8th Asia Pacific Triennial of Contemporary Art\n QAGOMA\n Brisbane (2015). Her work is held in a number of collections including the M+ Museum\n Hong Kong; the Burger Collection\n Hong Kong; Kadist Art Foundation\n San Francisco; QAGOMA\n Brisbane; and the K11 Art Foundation\n Shanghai. \\r\\n\n",
  "createdDate": "20201201203308",
  "version": 0,
  "latest": false,
  "roles": [],
  "metadata": {
    "accession_no_csv": "2017-01031",
    "Image": "",
    "object_work_type": "acrylic painting (visual works) canvas paintings",
    "title_text": "Untitled (MT_109)",
    "preference": "main",
    "title_language": "",
    "creator_2": "Maria Taniguchi",
    "creator_role": "artists (visual artists)",
    "creation_date": "2017",
    "creation_place_original_location": "Philippines",
    "styles_periods_indexing_terms": "Contemporary (style of art)",
    "inscriptions": "",
    "inscription_language": "",
    "shape": "Rectangular",
    "materials_name": "canvas (textile material) acrylic paint",
    "techniques_name": "acrylic painting (technique)",
    "object_colour": "black (colour)",
    "edition_description": "unique",
    "physical_appearance": "This is an acrylic on canvas painting in black. Brick lines are drawn in uniform grids. Notably, the size of the painting is much smaller than its counterpart.",
    "subject_terms_1": "repetition (artistic concept) Minimal monochrome",
    "subject_terms_2": "Acrylic painting Repetition (Aesthetics) Minimal art",
    "subject_terms_3": "Acrylic painting",
    "sgcool_label_text": "Like monochromatic monoliths, Maria Taniguchi’s ‘Brick’ paintings occupy a silent but palpable presence in space. Each painting in this body of works is covered by a uniform grid of brick lines pencil-drawn onto the surface, and the brick lines perform simultaneously as a formal, visual schema and conceptual device that conjoins each painting to the next – and all other ‘Brick’ pieces – in this decade-long series. An impeccable surface underscores the work’s quality as a two-dimensional painting, yet the work’s objecthood is emphasized by how each ‘Brick’ is often installed leaning against the wall rather than hanging off it, such that the work oscillates between abstract painting and/or minimalist sculpture. And despite appearing like a wall against a wall, each ‘Brick’ is, in actuality, an environment or world unto itself: it does not represent anything other than itself. Each stands rather, as a record of time and pain-staking labour for Taniguchi paints each brick individually – an exercise of repetition that transforms the paintings into temporal registers of artistic process. \r\n\r\nTaniguchi is best known for her large-scaled ‘Bricks’ which make their most impactful statements  – not merely in terms of physical presence, but more significantly, as visual documents to the passage of time – and MT_116 stands as one of her rare, few works that approaches such a monumental scale. \r\n\r\nMaria Taniguchi (b. 1981, Dumaguete City, Philippines, in 1981) won the Hugo Boss Asia Art Award in 2015 and was a LUX Associate Artist in 2009. Recent exhibitions include History of a vanishing present: A prologue, the Mistake Room, Los Angeles (2016); Afterwork, Para Site, Hong Kong (2016); Globale: New sensorium, ZKM Centre for Art and Media, Karlsruhe, Germany (2016); The vexed contemporary, Museum of Contemporary Art and Design, Manila (2015); and the 8th Asia Pacific Triennial of Contemporary Art, QAGOMA, Brisbane (2015). Her work is held in a number of collections including the M+ Museum, Hong Kong; the Burger Collection, Hong Kong; Kadist Art Foundation, San Francisco; QAGOMA, Brisbane; and the K11 Art Foundation, Shanghai. \r\n"
  },
  "nlpDate": "20201201203308",
  "connectorId": 0,
  "tags": {}
}