{
  "id": "2017-00798",
  "title": "Moth #5",
  "source": "Bumblebee",
  "path": "./Data/json/",
  "content": "\n  accession_no_csv: 2017-00798\n\n  Image: \n\n  object_work_type: shaped canvases (paintings by form) canvas paintings\n\n  title_text: Moth #5\n\n  preference: main\n\n  title_language: \n\n  creator_2: Genevieve Chua\n\n  creator_1: Chua\n Genevieve\n\n  creator_role: artists (visual artists)\n\n  creation_date: 2016\n\n  creation_place_original_location: Singapore\n\n  inscriptions: \n\n  inscription_language: \n\n  shape: irregular\n\n  materials_name: canvas (textile material) acrylic paint\n\n  techniques_name: acrylic painting (technique) screen printing\n\n  object_colour: black-and-white (colours)\n\n  edition_description: unique\n\n  physical_appearance: This is a shaped canvas painting. There are splashes of white across the canvas comprising of a series of dots.\n\n  subject_terms_1: screen prints moths (general) abstraction Orchidaceae (family)\n\n  subject_terms_2: Shaped canvas Art\n Singaporean Orchids in art Acrylic painting Prints Moths in art Abstraction\n\n  subject_terms_3: Acrylic painting\n\n  context_1: Unnatural History Drawings\n\n  context_2: exhibitions (events)\n\n  context_3: 8-Sep-2016 to 10-Sep-2016\n\n  context_4: 8-Sep-16\n\n  context_5: 10-Sep-16\n\n  context_6: Singapore\n\n  context_7: Artspace@Helutrans\n Singapore\n\n  context_8: planners\n\n  sgcool_label_text: Moth #5 brings together two interests that have coursed through Genevieve Chua’s practice: nature and the wild\n as well as the intertwining relationship between sound and image. Part of Chua’s ‘Unnatural History Drawings’\n the shaped canvas takes as its starting point\n the extensive collection of natural history drawings that were commissioned by William Farquhar in the early 19th century. With an abiding interest to explore abstraction in painting\n the work also incorporates the ultrasound image as a means to probe the relationship between sound and vision\n and how sensorial experiences can translate across one other. Chua’s use of the ultrasound gestures towards the realm of possibility of what lies beyond the range of human sensory detection\n as made realisable by science and technology. \\r\\n\\r\\nThe Moth series\n the second of the arcs\n draws upon Darwinian hypothesis that living creatures’ characteristics or forms evolve to over time\n through a process of beneficial mutations. In this instance\n the paintings revolve around a moth with an unusually long proboscis that enables it to pollinate a species of orchid with a highly elongated nectary. Evolution of the moth and orchid have thus unfolded in tandem\n a progression in parallel. The symmetrical shape of Moth #5 calls to mind the insect’s form at rest\n and the ultrasound patterns which were derived from the vibratory patterns of the walls or ground on which the moths were perched.\\r\\n\\r\\nGenevieve Chua (b. 1984\n Singapore) is a visual artist who works primarily through abstraction. Chua pursues an unfurling narrative that is informed by natural history and linguistics. Selected solo exhibitions include “Rehearsals for the Wilful” (Manila\n 2016); “Parabola” (Singapore\n 2014); “Cicadas Cicadas” (Los Angeles\n 2014) and “Birthing Ground not a Sound” (Singapore\n 2012). She has alos participated in the Singapore Biennale (2011)\n and was a recipient of the NAC Georgette Chen Scholarship in 2003/4 and the Young Artist Award in 2012 conferred by the National Arts Council\n Singapore.\n",
  "createdDate": "20201201203308",
  "version": 0,
  "latest": false,
  "roles": [],
  "metadata": {
    "accession_no_csv": "2017-00798",
    "Image": "",
    "object_work_type": "shaped canvases (paintings by form) canvas paintings",
    "title_text": "Moth #5",
    "preference": "main",
    "title_language": "",
    "creator_2": "Genevieve Chua",
    "creator_1": "Chua, Genevieve",
    "creator_role": "artists (visual artists)",
    "creation_date": "2016",
    "creation_place_original_location": "Singapore",
    "inscriptions": "",
    "inscription_language": "",
    "shape": "irregular",
    "materials_name": "canvas (textile material) acrylic paint",
    "techniques_name": "acrylic painting (technique) screen printing",
    "object_colour": "black-and-white (colours)",
    "edition_description": "unique",
    "physical_appearance": "This is a shaped canvas painting. There are splashes of white across the canvas comprising of a series of dots.",
    "subject_terms_1": "screen prints moths (general) abstraction Orchidaceae (family)",
    "subject_terms_2": "Shaped canvas Art, Singaporean Orchids in art Acrylic painting Prints Moths in art Abstraction",
    "subject_terms_3": "Acrylic painting",
    "context_1": "Unnatural History Drawings",
    "context_2": "exhibitions (events)",
    "context_3": "8-Sep-2016 to 10-Sep-2016",
    "context_4": "8-Sep-16",
    "context_5": "10-Sep-16",
    "context_6": "Singapore",
    "context_7": "Artspace@Helutrans, Singapore",
    "context_8": "planners",
    "sgcool_label_text": "Moth #5 brings together two interests that have coursed through Genevieve Chua’s practice: nature and the wild, as well as the intertwining relationship between sound and image. Part of Chua’s ‘Unnatural History Drawings’, the shaped canvas takes as its starting point, the extensive collection of natural history drawings that were commissioned by William Farquhar in the early 19th century. With an abiding interest to explore abstraction in painting, the work also incorporates the ultrasound image as a means to probe the relationship between sound and vision, and how sensorial experiences can translate across one other. Chua’s use of the ultrasound gestures towards the realm of possibility of what lies beyond the range of human sensory detection, as made realisable by science and technology. \r\n\r\nThe Moth series, the second of the arcs, draws upon Darwinian hypothesis that living creatures’ characteristics or forms evolve to over time, through a process of beneficial mutations. In this instance, the paintings revolve around a moth with an unusually long proboscis that enables it to pollinate a species of orchid with a highly elongated nectary. Evolution of the moth and orchid have thus unfolded in tandem, a progression in parallel. The symmetrical shape of Moth #5 calls to mind the insect’s form at rest, and the ultrasound patterns which were derived from the vibratory patterns of the walls or ground on which the moths were perched.\r\n\r\nGenevieve Chua (b. 1984, Singapore) is a visual artist who works primarily through abstraction. Chua pursues an unfurling narrative that is informed by natural history and linguistics. Selected solo exhibitions include “Rehearsals for the Wilful” (Manila, 2016); “Parabola” (Singapore, 2014); “Cicadas Cicadas” (Los Angeles, 2014) and “Birthing Ground not a Sound” (Singapore, 2012). She has alos participated in the Singapore Biennale (2011), and was a recipient of the NAC Georgette Chen Scholarship in 2003/4 and the Young Artist Award in 2012 conferred by the National Arts Council, Singapore."
  },
  "nlpDate": "20201201203308",
  "connectorId": 0,
  "tags": {}
}