{
  "id": "2017-01040-111",
  "title": "\"Personal photograph album titled \"\"Sixteen Months in Singapore\"\"\" Sixteen Months in Singapore: Photograph of children eating by a fence",
  "source": "Bumblebee",
  "path": "./Data/json/",
  "content": "\n  accession_no_csv: 2017-01040-111\n\n  Image: \n\n  object_work_type: photographs black-and-white photographs\n\n  title_text: \\Personal photograph album titled \\\\Sixteen Months in Singapore\\\\\\ Sixteen Months in Singapore: Photograph of children eating by a fence\n\n  preference: main alternate\n\n  title_language: \n\n  creation_date: 1951-1952\n\n  creation_place_original_location: Singapore\n\n  inscriptions: \n\n  inscription_language: \n\n  shape: rectangular\n\n  materials_name: paper (fiber product)\n\n  techniques_name: photographic processes\n\n  object_colour: black-and-white (colors)\n\n  physical_appearance: This is a black-and-white photograph. It is rectangular in shape and portrait in orientation. The photograph features two children\n sitting on a bench\n and eating from a plate with their hands. The girl is wearing a dress\n while the boy is in a white shirts. There is a wired fence on the left. There are several other people captured on the top of the photograph. There are no inscriptions on the photograph. There are no tears or folds seen.\n\n  subject_terms_1: children (people by age group) snapshots\n\n  subject_terms_2: Children Photographs\n\n  subject_terms_3: Photography\n\n  subject_terms_4: \n\n  sgcool_label_text: This is a personal photograph album that belonged to a Corporal A. Silver who spent 16 months in Singapore between 1951 and 1952. Silver was presumably a Jewish lady who was stationed in Singapore to serve at the Royal Air Force (RAF) Hospital at Changi. The album contains photographs that document her working and personal life\n including friends she made within the Jewish community in Singapore.\n",
  "createdDate": "20201201203308",
  "version": 0,
  "latest": false,
  "roles": [],
  "metadata": {
    "accession_no_csv": "2017-01040-111",
    "Image": "",
    "object_work_type": "photographs black-and-white photographs",
    "title_text": "\"Personal photograph album titled \"\"Sixteen Months in Singapore\"\"\" Sixteen Months in Singapore: Photograph of children eating by a fence",
    "preference": "main alternate",
    "title_language": "",
    "creation_date": "1951-1952",
    "creation_place_original_location": "Singapore",
    "inscriptions": "",
    "inscription_language": "",
    "shape": "rectangular",
    "materials_name": "paper (fiber product)",
    "techniques_name": "photographic processes",
    "object_colour": "black-and-white (colors)",
    "physical_appearance": "This is a black-and-white photograph. It is rectangular in shape and portrait in orientation. The photograph features two children, sitting on a bench, and eating from a plate with their hands. The girl is wearing a dress, while the boy is in a white shirts. There is a wired fence on the left. There are several other people captured on the top of the photograph. There are no inscriptions on the photograph. There are no tears or folds seen.",
    "subject_terms_1": "children (people by age group) snapshots",
    "subject_terms_2": "Children Photographs",
    "subject_terms_3": "Photography",
    "subject_terms_4": "",
    "sgcool_label_text": "This is a personal photograph album that belonged to a Corporal A. Silver who spent 16 months in Singapore between 1951 and 1952. Silver was presumably a Jewish lady who was stationed in Singapore to serve at the Royal Air Force (RAF) Hospital at Changi. The album contains photographs that document her working and personal life, including friends she made within the Jewish community in Singapore."
  },
  "nlpDate": "20201201203308",
  "connectorId": 0,
  "tags": {}
}