{"id":"2017-00034","title":"Fisherman","source":"Bumblebee","path":"./Data/json/","content":"accession_no_csv:2017-00034\nImage:\nobject_work_type:black-and-white prints (photographs) gelatin silver prints  photographic prints\ntitle_text:Fisherman\npreference:main\ntitle_language:\ncreator_2:Koon\n Sang Ho\ncreator_role:photographers\ncreation_date:c.1956\ncreation_place_original_location:Singapore\ninscriptions:\ninscription_language:\nshape:Rectangular\nmaterials_name:gelatin  paper (fibre product)  silver sulfide  baryta paper\ntechniques_name:gelatin silver process photographic printing techniques black-and-white photography\nobject_colour:black-and-white (colours)\nphysical_appearance:This is a pictorial of a half dressed fisherman who has his head wrapped with a piece of cloth. The print shows yellowing along its edges. In particular\n a strip of browning/ blacking has occurred on its top right corner. Spotting can also be seen on the backing which the print is mounted on.\nsubject_terms_1:fishermen (people)  fishing\nsubject_terms_2:Photography\n Artistic  Portrait photography  Fishers Fishing\nsubject_terms_3:visual arts  Artistic photography Potrait photography\ncontext_21:40 Holloway  Lane\n Singapore 7\nsgcool_label_text:Ho Koon Sang was a member of the Photographic Society of Singapore and an Associate of the Royal Photographic Society in London. This photograph was part of a set of 12 prints sent to the Royal Photographic Society in 1956.","createdDate":"20201018182636","version":0,"latest":false,"roles":[],"metadata":{"accession_no_csv":"2017-00034","Image":"","object_work_type":"black-and-white prints (photographs) gelatin silver prints  photographic prints","title_text":"Fisherman","preference":"main","title_language":"","creator_2":"Koon, Sang Ho","creator_role":"photographers","creation_date":"c.1956","creation_place_original_location":"Singapore","inscriptions":"","inscription_language":"","shape":"Rectangular","materials_name":"gelatin  paper (fibre product)  silver sulfide  baryta paper","techniques_name":"gelatin silver process photographic printing techniques black-and-white photography","object_colour":"black-and-white (colours)","physical_appearance":"This is a pictorial of a half dressed fisherman who has his head wrapped with a piece of cloth. The print shows yellowing along its edges. In particular, a strip of browning/ blacking has occurred on its top right corner. Spotting can also be seen on the backing which the print is mounted on.","subject_terms_1":"fishermen (people)  fishing","subject_terms_2":"Photography, Artistic  Portrait photography  Fishers Fishing","subject_terms_3":"visual arts  Artistic photography Potrait photography","context_21":"40 Holloway  Lane, Singapore 7","sgcool_label_text":"Ho Koon Sang was a member of the Photographic Society of Singapore and an Associate of the Royal Photographic Society in London. This photograph was part of a set of 12 prints sent to the Royal Photographic Society in 1956."},"nlpDate":"20201018182636","connectorId":0,"tags":{}}