{
  "id": "2017-00583",
  "title": "3.5.62",
  "source": "Bumblebee",
  "path": "./Data/json/",
  "content": "\n  accession_no_csv: 2017-00583\n\n  Image: \n\n  object_work_type: oil painting (visual works) canvas paintings\n\n  title_text: 3.5.62\n\n  preference: main\n\n  title_language: \n\n  creator_2: Wou Ki Zao\n\n  creator_1: Zao\n Wou-ki\n 1920-2013\n\n  creator_role: artists (visual artists)\n\n  creation_date: 1962\n\n  inscriptions: \n\n  inscription_language: \n\n  shape: Rectangular\n\n  materials_name: oil paint (paint)  canvas board\n\n  techniques_name: oil painting (technique)\n\n  object_colour: multicoloured\n\n  physical_appearance: The is an abstract painting comprising of overlapping strokes of paint. Most of the strokes are congregated in the center of the composition\n where horizontal strokes break into the swirl of overlapping colours.\n\n  subject_terms_1: abstraction\n\n  subject_terms_2: Art\n Abstract Ink painting\n Chinese\n\n  subject_terms_3: Chinese ink painting  visual arts\n\n  sgcool_label_text: Zao Wou-ki (1920 - 2013) is a Chinese-French artist who was recognised internationally as a significant figure in the modernist movement of Post-World War II. He was also regarded as a leading master in the context of the modern Asian art\n and was widely considered to be one of the most successful living Chinese artists. 3.5.62 is a good example of Zao\\u0027s early abstract imagery. As shown in this example\n Zao\\u0027s abstract schema is often framed within stable and simplified structures sectioned by horizontal segments. In the middle of the composition\n forces and tensions are generated by layered interweaving colours and brushstrokes\n which echo atmospheric energy and natural momentum. The imagery denotes the spiritual essence of the landscape-and-mountain painting in the tradition of Chinese art.\n",
  "createdDate": "20201120223708",
  "version": 0,
  "latest": false,
  "roles": [],
  "metadata": {
    "accession_no_csv": "2017-00583",
    "Image": "",
    "object_work_type": "oil painting (visual works) canvas paintings",
    "title_text": "3.5.62",
    "preference": "main",
    "title_language": "",
    "creator_2": "Wou Ki Zao",
    "creator_1": "Zao, Wou-ki, 1920-2013",
    "creator_role": "artists (visual artists)",
    "creation_date": "1962",
    "inscriptions": "",
    "inscription_language": "",
    "shape": "Rectangular",
    "materials_name": "oil paint (paint)  canvas board",
    "techniques_name": "oil painting (technique)",
    "object_colour": "multicoloured",
    "physical_appearance": "The is an abstract painting comprising of overlapping strokes of paint. Most of the strokes are congregated in the center of the composition, where horizontal strokes break into the swirl of overlapping colours.",
    "subject_terms_1": "abstraction",
    "subject_terms_2": "Art, Abstract Ink painting, Chinese",
    "subject_terms_3": "Chinese ink painting  visual arts",
    "sgcool_label_text": "Zao Wou-ki (1920 - 2013) is a Chinese-French artist who was recognised internationally as a significant figure in the modernist movement of Post-World War II. He was also regarded as a leading master in the context of the modern Asian art, and was widely considered to be one of the most successful living Chinese artists. 3.5.62 is a good example of Zao\u0027s early abstract imagery. As shown in this example, Zao\u0027s abstract schema is often framed within stable and simplified structures sectioned by horizontal segments. In the middle of the composition, forces and tensions are generated by layered interweaving colours and brushstrokes, which echo atmospheric energy and natural momentum. The imagery denotes the spiritual essence of the landscape-and-mountain painting in the tradition of Chinese art."
  },
  "nlpDate": "20201120223708",
  "connectorId": 0,
  "tags": {}
}