{"id":"2017-01040-097","title":"\"Personal photograph album titled \"\"Sixteen Months in Singapore\"\"\" Sixteen Months in Singapore: Photograph of Corporal A. Silver and man with Royal Air Force sign","source":"Bumblebee","path":"./Data/json/","content":"accession_no_csv:2017-01040-097\nImage:\nobject_work_type:black-and-white photographs photographs\ntitle_text:\\Personal photograph album titled \\\\Sixteen Months in Singapore\\\\\\ Sixteen Months in Singapore: Photograph of Corporal A. Silver and man with Royal Air Force sign\npreference:alternate main\ntitle_language:\ncreation_date:1951-1952\ncreation_place_original_location:Singapore Sri Lanka\ninscriptions:\ninscription_language:\nshape:rectangular\nmaterials_name:paper (fiber product)\ntechniques_name:photographic processes\nobject_colour:black-and-white (colors)\nphysical_appearance:This is a black-and-white photograph. It is rectangular in shape and landscape in orientation. It features a man and a woman\n posing beside a sign board for the Royal Air Force Combat Training School. The man is wearing a military uniform and beret\n while the woman is dressed in a white shirt and skirt. Behind them\n there is a roofed building structure. The photograph is quite faded\n with black spots all over.\nsubject_terms_1:double portraits soldiers schools (institutions)\nsubject_terms_2:Photographs Portraits\n Group Soldiers Military education\nsubject_terms_3:Photography Great Britain. Royal Air Force.\nsubject_terms_4:\nsgcool_label_text:This is a personal photograph album that belonged to a Corporal A. Silver who spent 16 months in Singapore between 1951 and 1952. Silver was presumably a Jewish lady who was stationed in Singapore to serve at the Royal Air Force (RAF) Hospital at Changi. The album contains photographs that document her working and personal life\n including friends she made within the Jewish community in Singapore.","createdDate":"20201119143407","version":0,"latest":false,"roles":[],"metadata":{"accession_no_csv":"2017-01040-097","Image":"","object_work_type":"black-and-white photographs photographs","title_text":"\"Personal photograph album titled \"\"Sixteen Months in Singapore\"\"\" Sixteen Months in Singapore: Photograph of Corporal A. Silver and man with Royal Air Force sign","preference":"alternate main","title_language":"","creation_date":"1951-1952","creation_place_original_location":"Singapore Sri Lanka","inscriptions":"","inscription_language":"","shape":"rectangular","materials_name":"paper (fiber product)","techniques_name":"photographic processes","object_colour":"black-and-white (colors)","physical_appearance":"This is a black-and-white photograph. It is rectangular in shape and landscape in orientation. It features a man and a woman, posing beside a sign board for the Royal Air Force Combat Training School. The man is wearing a military uniform and beret, while the woman is dressed in a white shirt and skirt. Behind them, there is a roofed building structure. The photograph is quite faded, with black spots all over.","subject_terms_1":"double portraits soldiers schools (institutions)","subject_terms_2":"Photographs Portraits, Group Soldiers Military education","subject_terms_3":"Photography Great Britain. Royal Air Force.","subject_terms_4":"","sgcool_label_text":"This is a personal photograph album that belonged to a Corporal A. Silver who spent 16 months in Singapore between 1951 and 1952. Silver was presumably a Jewish lady who was stationed in Singapore to serve at the Royal Air Force (RAF) Hospital at Changi. The album contains photographs that document her working and personal life, including friends she made within the Jewish community in Singapore."},"nlpDate":"20201119143407","connectorId":0,"tags":{}}