{
  "id": "2017-00225-001",
  "title": "Scenery Of Boats Sailing On The Ocean Miniatures from The Sunny Orient where Sorrow Smiles and Poverty and Riches – Sin and Sanctity – Beauty and Ugliness all keep company",
  "source": "Bumblebee",
  "path": "./Data/json/",
  "content": "\n  accession_no_csv: 2017-00225-001\n\n  Image: \n\n  object_work_type: black-and-white prints (photographs) photographic prints gelatin silver prints\n\n  title_text: Scenery Of Boats Sailing On The Ocean Miniatures from The Sunny Orient where Sorrow Smiles and Poverty and Riches – Sin and Sanctity – Beauty and Ugliness all keep company\n\n  preference: main alternate\n\n  title_language: \n\n  creator_2: SHEAF\n Egbert Thomas.\n\n  creator_role: photographers\n\n  creation_date: 1922-1925\n\n  creation_place_original_location: Asia\n\n  inscriptions: \n\n  inscription_language: \n\n  shape: Rectangular\n\n  materials_name: silver sulfide baryta paper gelatin\n\n  techniques_name: gelatin silver process photographic printing techniques black-and-white photography\n\n  object_colour: black-and-white (colours)\n\n  physical_appearance: This print captures a boat setting sail on the ocean. In the foreground there is lush greenery whilst the background is filled with mountain ranges.\n\n  subject_terms_1: seascapes travel photography nature photography boats bodies of water (natural) bird\\u0027s-eye-views\n\n  subject_terms_2: Nature photography Aerial views Boats and boating Landscape photography Views Bodies of water Prints Travel photography\n\n  subject_terms_3: Waterways Landscape photography Travel photography Visual arts\n\n  subject_terms_4: \n\n  sgcool_label_text: These photographs were taken by Egbert Sheaf\n the Australian Trade Commissioner in Singapore\n several taken before and some of which were most likely taken when he was posted here between 1922-25. Sheaf conscientiously studied South-East Asia\\u0027s ethnography and his scholarship was coupled with a passion for travel and adventure. His photographs cover various aspects of daily and cultural life such as weaving\n the rice agriculture and other rituals of Javanese and Malayan communities\n as explained and illustrated in the portfolios and albums.\n",
  "createdDate": "20201201203308",
  "version": 0,
  "latest": false,
  "roles": [],
  "metadata": {
    "accession_no_csv": "2017-00225-001",
    "Image": "",
    "object_work_type": "black-and-white prints (photographs) photographic prints gelatin silver prints",
    "title_text": "Scenery Of Boats Sailing On The Ocean Miniatures from The Sunny Orient where Sorrow Smiles and Poverty and Riches – Sin and Sanctity – Beauty and Ugliness all keep company",
    "preference": "main alternate",
    "title_language": "",
    "creator_2": "SHEAF, Egbert Thomas.",
    "creator_role": "photographers",
    "creation_date": "1922-1925",
    "creation_place_original_location": "Asia",
    "inscriptions": "",
    "inscription_language": "",
    "shape": "Rectangular",
    "materials_name": "silver sulfide baryta paper gelatin",
    "techniques_name": "gelatin silver process photographic printing techniques black-and-white photography",
    "object_colour": "black-and-white (colours)",
    "physical_appearance": "This print captures a boat setting sail on the ocean. In the foreground there is lush greenery whilst the background is filled with mountain ranges.",
    "subject_terms_1": "seascapes travel photography nature photography boats bodies of water (natural) bird\u0027s-eye-views",
    "subject_terms_2": "Nature photography Aerial views Boats and boating Landscape photography Views Bodies of water Prints Travel photography",
    "subject_terms_3": "Waterways Landscape photography Travel photography Visual arts",
    "subject_terms_4": "",
    "sgcool_label_text": "These photographs were taken by Egbert Sheaf, the Australian Trade Commissioner in Singapore, several taken before and some of which were most likely taken when he was posted here between 1922-25. Sheaf conscientiously studied South-East Asia\u0027s ethnography and his scholarship was coupled with a passion for travel and adventure. His photographs cover various aspects of daily and cultural life such as weaving, the rice agriculture and other rituals of Javanese and Malayan communities, as explained and illustrated in the portfolios and albums."
  },
  "nlpDate": "20201201203308",
  "connectorId": 0,
  "tags": {}
}