{"id":"2017-00259","title":"Street Scene in Bombay","source":"Bumblebee","path":"./Data/json/","content":"accession_no_csv:2017-00259\nImage:\nobject_work_type:watercolours (paintings)\ntitle_text:Street Scene in Bombay\npreference:main\ntitle_language:\ncreator_2:William Simpson\ncreator_1:Simpson\n William\n 1823-1899\ncreator_role:watercolourists painters (artists)\ncreation_date:1862\ncreation_place_original_location:Great Britain\ninscriptions:\ninscription_language:\nshape:rectangular\nmaterials_name:paper (fibre product)  watercolour (paint) watercolour paper pencils (marking material)\ntechniques_name:watercolour painting (technique) sketching linear perspective (technique)\nobject_colour:multicoloured\nphysical_appearance:This is a watercolour painting that depicts a bustling street in Bombay in the 19th century. Horse carriages are seen to be passing amidst a throng of people\n evidencing the busy nature of the streets. The plethora of costumes worn by the figures in the image also points to the cosmopolitan nature of the city.\nsubject_terms_1:perspective views (images)  colonialism  carriages (vehicles)  merchants street vendors street scenes\nsubject_terms_2:Cosmopolitanism  Imperialism  Perspective  Merchants Street vendors  Mumbai (India)\nsubject_terms_3:visual arts  watercolour painting\nsubject_terms_4:\nsgcool_label_text:The watercolour shows a bustling street in Bombay in the 19th century. A European gentleman in a top hat rides in a carriage between merchants and street sellers. It shows the cosmopolitan nature of port cities at the time\n with everyone jostling for space on the busy streets. \\r\\n\\r\\nWilliam Simpson (1823-1899) was a successful topographical artist who after a series of acclaimed images of the Crimean War\n was commissioned in 1859 by the publishers Day and Son\n to produce images of India for publication. On his return he produced the book India: Ancient and Modern London\n 1867\n a series of illustrations with a descriptive text by John William Kaye. He made several later trips to India as well.\\r\\n","createdDate":"20201119143406","version":0,"latest":false,"roles":[],"metadata":{"accession_no_csv":"2017-00259","Image":"","object_work_type":"watercolours (paintings)","title_text":"Street Scene in Bombay","preference":"main","title_language":"","creator_2":"William Simpson","creator_1":"Simpson, William, 1823-1899","creator_role":"watercolourists painters (artists)","creation_date":"1862","creation_place_original_location":"Great Britain","inscriptions":"","inscription_language":"","shape":"rectangular","materials_name":"paper (fibre product)  watercolour (paint) watercolour paper pencils (marking material)","techniques_name":"watercolour painting (technique) sketching linear perspective (technique)","object_colour":"multicoloured","physical_appearance":"This is a watercolour painting that depicts a bustling street in Bombay in the 19th century. Horse carriages are seen to be passing amidst a throng of people, evidencing the busy nature of the streets. The plethora of costumes worn by the figures in the image also points to the cosmopolitan nature of the city.","subject_terms_1":"perspective views (images)  colonialism  carriages (vehicles)  merchants street vendors street scenes","subject_terms_2":"Cosmopolitanism  Imperialism  Perspective  Merchants Street vendors  Mumbai (India)","subject_terms_3":"visual arts  watercolour painting","subject_terms_4":"","sgcool_label_text":"The watercolour shows a bustling street in Bombay in the 19th century. A European gentleman in a top hat rides in a carriage between merchants and street sellers. It shows the cosmopolitan nature of port cities at the time, with everyone jostling for space on the busy streets. \r\n\r\nWilliam Simpson (1823-1899) was a successful topographical artist who after a series of acclaimed images of the Crimean War, was commissioned in 1859 by the publishers Day and Son, to produce images of India for publication. On his return he produced the book India: Ancient and Modern London, 1867, a series of illustrations with a descriptive text by John William Kaye. He made several later trips to India as well.\r\n"},"nlpDate":"20201119143406","connectorId":0,"tags":{}}