{
  "id": "2017-00951-001 ",
  "title": "Tanah Impian (Dream Land) Exposition de Paris",
  "source": "Bumblebee",
  "path": "./Data/json/",
  "content": "\n  accession_no_csv: 2017-00951-001 \n\n  Image: \n\n  object_work_type: screen prints  adaptations (derivative objects)\n\n  title_text: Tanah Impian (Dream Land) Exposition de Paris\n\n  preference: alternate main\n\n  title_language: \n\n  creator_2: Krack Studio\n\n  creator_role: artists (visual artists)\n\n  creation_date: 2014\n\n  creation_place_original_location: Indonesia\n\n  styles_periods_indexing_terms: Contemporary (style of art)\n\n  inscriptions: \n\n  inscription_language: \n\n  shape: Rectangular\n\n  materials_name: paper (fiber product)\n\n  techniques_name: screen printing\n\n  object_colour: multicoloured\n\n  edition_description: 2-Oct\n\n  physical_appearance: This is a silkscreen print depicting a scene outside of the exhibition compounds of the Exposition de Paris in 1900. The Indonesian flag is seen to be hanging on a pole that is attached to a roof on the top right corner.\n\n  subject_terms_1: identity  nationalism  world\\u0027s fairs  posters ways of life  popular culture  appropriation (imagery) redesign\n\n  subject_terms_2: Serigraphy Art\n Indonesian Nationalism Identity  Exposition universelle (1900: Paris\n France) Posters Ways of life Popular culture  Appropriation (Art) Adaptations\n\n  subject_terms_3: Visual arts  Art exhibitions National identity  Poster art  Media and advertising  Popular culture\n\n  context_1: Exposition de Paris\n\n  context_2: exhibition (events)\n\n  context_3: 15-Apr-1900 to 12-Nov-1990\n\n  context_4: 15-Apr-00\n\n  context_5: 12-Nov-90\n\n  context_6: Paris (France)\n\n  context_7: Exposition Universelle\n\n  context_8: planners?\n\n  sgcool_label_text: Tanah Impian (Dream Land) is a series of prints based on images drawn from Indonesian popular culture\n spanning 100 years. The project was conceived in 2014\n the year of the elections in Indonesia when nationalist rhetoric dominated public consciousness\n Artist collective Krack Studio sifted through a mass of research and archival material\n eventually selecting 24 images that referenced the idea of the Indonesian Dream and / or told an interesting story about changing definitions of the ‘Nation’. Ranging from political posters to advertisements\n comic strips\n movie posters and magazines\n these images\n reconstructed and re-imagined by the artist collective\n chronicle Indonesia’s evolving aspirations\n desires and identity\n as well as how Indonesia has been perceived and imaged for the ‘Western’ gaze.\n",
  "createdDate": "20201120223708",
  "version": 0,
  "latest": false,
  "roles": [],
  "metadata": {
    "accession_no_csv": "2017-00951-001 ",
    "Image": "",
    "object_work_type": "screen prints  adaptations (derivative objects)",
    "title_text": "Tanah Impian (Dream Land) Exposition de Paris",
    "preference": "alternate main",
    "title_language": "",
    "creator_2": "Krack Studio",
    "creator_role": "artists (visual artists)",
    "creation_date": "2014",
    "creation_place_original_location": "Indonesia",
    "styles_periods_indexing_terms": "Contemporary (style of art)",
    "inscriptions": "",
    "inscription_language": "",
    "shape": "Rectangular",
    "materials_name": "paper (fiber product)",
    "techniques_name": "screen printing",
    "object_colour": "multicoloured",
    "edition_description": "2-Oct",
    "physical_appearance": "This is a silkscreen print depicting a scene outside of the exhibition compounds of the Exposition de Paris in 1900. The Indonesian flag is seen to be hanging on a pole that is attached to a roof on the top right corner.",
    "subject_terms_1": "identity  nationalism  world\u0027s fairs  posters ways of life  popular culture  appropriation (imagery) redesign",
    "subject_terms_2": "Serigraphy Art, Indonesian Nationalism Identity  Exposition universelle (1900: Paris, France) Posters Ways of life Popular culture  Appropriation (Art) Adaptations",
    "subject_terms_3": "Visual arts  Art exhibitions National identity  Poster art  Media and advertising  Popular culture",
    "context_1": "Exposition de Paris",
    "context_2": "exhibition (events)",
    "context_3": "15-Apr-1900 to 12-Nov-1990",
    "context_4": "15-Apr-00",
    "context_5": "12-Nov-90",
    "context_6": "Paris (France)",
    "context_7": "Exposition Universelle",
    "context_8": "planners?",
    "sgcool_label_text": "Tanah Impian (Dream Land) is a series of prints based on images drawn from Indonesian popular culture, spanning 100 years. The project was conceived in 2014, the year of the elections in Indonesia when nationalist rhetoric dominated public consciousness, Artist collective Krack Studio sifted through a mass of research and archival material, eventually selecting 24 images that referenced the idea of the Indonesian Dream and / or told an interesting story about changing definitions of the ‘Nation’. Ranging from political posters to advertisements, comic strips, movie posters and magazines, these images, reconstructed and re-imagined by the artist collective, chronicle Indonesia’s evolving aspirations, desires and identity, as well as how Indonesia has been perceived and imaged for the ‘Western’ gaze."
  },
  "nlpDate": "20201120223708",
  "connectorId": 0,
  "tags": {}
}