{"id":"2017-00023","title":"Square and Circle","source":"Bumblebee","path":"./Data/json/","content":"accession_no_csv:2017-00023\nImage:\nobject_work_type:black-and-white prints (photographs) gelatin silver prints  photographic prints\ntitle_text:Square and Circle\npreference:main\ntitle_language:\ncreator_2:Koon\n Sang Ho\ncreator_role:photographers\ncreation_date:c.1960\ncreation_place_original_location:Singapore\ninscriptions:\ninscription_language:\nshape:rectangular\nmaterials_name:gelatin  paper (fibre product)  silver sulfide  baryta paper\ntechniques_name:gelatin silver process photographic printing techniques black-and-white photography\nobject_colour:black-and-white (colours)\nphysical_appearance:This is a gelatin silver print and the image is a top-down perspective of a bespectacled near-bald  man viewing a piece of hanging artwork with his hands behind his back.  The man in the image is fellow photographer Mun Chor Koon. On the verso\n there is a chop for the 14th SIngapore Salon 1963 by The Photographic Society of Singapore. It also has the number and title of work\n as well as an address addressed to the artist.\nsubject_terms_1:bird\\u0027s eye views stylized portraits exhibitions (events)\nsubject_terms_2:Bird\\u0027s-eye views in art Photography\n Artistic  Portrait photography  Art Exhibitions\nsubject_terms_3:visual arts  Artistic photography  Art exhibitions  Mun\n Chor Koon\ncontext_1:An exhibition of 318 monochrome and colour prints were selected from a total of 2925 prints submitted. Record entry of more than 700 photographers from 44 countries participated.\ncontext_2:exhibitions (events)\ncontext_3:May 4th to May 12th. 1963.\ncontext_4:4th May 1963\ncontext_5:12th May 1963\ncontext_6:National Library (Singapore)\ncontext_7:The Photographic Society of Singapore\ncontext_8:planners\ncontext_20:Address indicated on photography studio\\u0027s chop.\ncontext_21:19 Lorong 11. Geylang Road. Singapore 14.\ncontext_22:c.1960\ncontext_23:1955\ncontext_24:1965\nsgcool_label_text:Ho Koon Sang was a member of the Photographic Society of Singapore and an Associate of the Royal Photographic Society in London. These photos are typical of the salon photography style of the time\n with an emphasis on technique\n composition and tone. The subject in this photo is fellow photographer Mun Chor Kun.","createdDate":"20201018182636","version":0,"latest":false,"roles":[],"metadata":{"accession_no_csv":"2017-00023","Image":"","object_work_type":"black-and-white prints (photographs) gelatin silver prints  photographic prints","title_text":"Square and Circle","preference":"main","title_language":"","creator_2":"Koon, Sang Ho","creator_role":"photographers","creation_date":"c.1960","creation_place_original_location":"Singapore","inscriptions":"","inscription_language":"","shape":"rectangular","materials_name":"gelatin  paper (fibre product)  silver sulfide  baryta paper","techniques_name":"gelatin silver process photographic printing techniques black-and-white photography","object_colour":"black-and-white (colours)","physical_appearance":"This is a gelatin silver print and the image is a top-down perspective of a bespectacled near-bald  man viewing a piece of hanging artwork with his hands behind his back.  The man in the image is fellow photographer Mun Chor Koon. On the verso, there is a chop for the 14th SIngapore Salon 1963 by The Photographic Society of Singapore. It also has the number and title of work, as well as an address addressed to the artist.","subject_terms_1":"bird\u0027s eye views stylized portraits exhibitions (events)","subject_terms_2":"Bird\u0027s-eye views in art Photography, Artistic  Portrait photography  Art Exhibitions","subject_terms_3":"visual arts  Artistic photography  Art exhibitions  Mun, Chor Koon","context_1":"An exhibition of 318 monochrome and colour prints were selected from a total of 2925 prints submitted. Record entry of more than 700 photographers from 44 countries participated.","context_2":"exhibitions (events)","context_3":"May 4th to May 12th. 1963.","context_4":"4th May 1963","context_5":"12th May 1963","context_6":"National Library (Singapore)","context_7":"The Photographic Society of Singapore","context_8":"planners","context_20":"Address indicated on photography studio\u0027s chop.","context_21":"19 Lorong 11. Geylang Road. Singapore 14.","context_22":"c.1960","context_23":"1955","context_24":"1965","sgcool_label_text":"Ho Koon Sang was a member of the Photographic Society of Singapore and an Associate of the Royal Photographic Society in London. These photos are typical of the salon photography style of the time, with an emphasis on technique, composition and tone. The subject in this photo is fellow photographer Mun Chor Kun."},"nlpDate":"20201018182636","connectorId":0,"tags":{}}