{
  "id": "2017-01039-014",
  "title": "Photograph album presented to George Lowe as a souvenir of his visit to Singapore George Lowe album: Photograph of Singapore City Council meeting",
  "source": "Bumblebee",
  "path": "./Data/json/",
  "content": "\n  accession_no_csv: 2017-01039-014\n\n  Image: \n\n  object_work_type: photographs black-and-white photographs\n\n  title_text: Photograph album presented to George Lowe as a souvenir of his visit to Singapore George Lowe album: Photograph of Singapore City Council meeting\n\n  preference: main alternate\n\n  title_language: \n\n  creation_date: 1953\n\n  creation_place_original_location: Singapore\n\n  inscriptions: \n\n  inscription_language: \n\n  shape: rectangular\n\n  materials_name: paper (fiber product)\n\n  techniques_name: photographic processes\n\n  object_colour: black-and-white (colors)\n\n  physical_appearance: This is a black-and-white photograph. It is a photograph of a meeting\n in a room that holds a semi-circular table on the bottom-right\n with four rows of tables facing it on the top-left. There is a large group of men seated on the tables\n each with a nameplate in front of them. There are no tears or folds seen on the photograph.\n\n  subject_terms_1: souvenirs Photographs city councils meetings\n\n  subject_terms_2: Meetings Lowe\n George\n 1924-2013 Photographs Hillary\n Edmund\n 1919-2008 Photograph albums City councils Souvenir\n\n  subject_terms_3: Photography City Council City Hall (Singapore)\n\n  subject_terms_4: \n\n  sgcool_label_text: George Lowe was a member of the British Expedition that saw Sir Edmund Hillary scale Mount Everest on 29 May 1953. In September that year\n Lowe accompanied Hillary on a visit to Singapore to deliver their first Everest lecture outside of New Zealand at the Odeon Theatre to an audience of 1\n620 schoolchildren. This photograph album\n with the coat of arms of the City of Singapore in gilt on the cover\n was presented to Lowe as a souvenir of his visit.\n",
  "createdDate": "20201125084513",
  "version": 0,
  "latest": false,
  "roles": [],
  "metadata": {
    "accession_no_csv": "2017-01039-014",
    "Image": "",
    "object_work_type": "photographs black-and-white photographs",
    "title_text": "Photograph album presented to George Lowe as a souvenir of his visit to Singapore George Lowe album: Photograph of Singapore City Council meeting",
    "preference": "main alternate",
    "title_language": "",
    "creation_date": "1953",
    "creation_place_original_location": "Singapore",
    "inscriptions": "",
    "inscription_language": "",
    "shape": "rectangular",
    "materials_name": "paper (fiber product)",
    "techniques_name": "photographic processes",
    "object_colour": "black-and-white (colors)",
    "physical_appearance": "This is a black-and-white photograph. It is a photograph of a meeting, in a room that holds a semi-circular table on the bottom-right, with four rows of tables facing it on the top-left. There is a large group of men seated on the tables, each with a nameplate in front of them. There are no tears or folds seen on the photograph.",
    "subject_terms_1": "souvenirs Photographs city councils meetings",
    "subject_terms_2": "Meetings Lowe, George, 1924-2013 Photographs Hillary, Edmund, 1919-2008 Photograph albums City councils Souvenir",
    "subject_terms_3": "Photography City Council City Hall (Singapore)",
    "subject_terms_4": "",
    "sgcool_label_text": "George Lowe was a member of the British Expedition that saw Sir Edmund Hillary scale Mount Everest on 29 May 1953. In September that year, Lowe accompanied Hillary on a visit to Singapore to deliver their first Everest lecture outside of New Zealand at the Odeon Theatre to an audience of 1,620 schoolchildren. This photograph album, with the coat of arms of the City of Singapore in gilt on the cover, was presented to Lowe as a souvenir of his visit."
  },
  "nlpDate": "20201125084513",
  "connectorId": 0,
  "tags": {}
}