{
  "id": "2017-00256",
  "title": "Relief panel depicting St Francis Xavier",
  "source": "Bumblebee",
  "path": "./Data/json/",
  "content": "\n  accession_no_csv: 2017-00256\n\n  Image: \n\n  object_work_type: Sculpture (visual works)\n\n  title_text: Relief panel depicting St Francis Xavier\n\n  preference: main\n\n  title_language: \n\n  creation_date: 17th century\n\n  creation_place_original_location: Velha Goa (India)\n\n  styles_periods_indexing_terms: European  Indian (South Asian)\n\n  inscriptions: \n\n  inscription_language: \n\n  shape: irregular\n\n  materials_name: teak (wood)  gilding (material)  paint (coating)\n\n  techniques_name: gilding (technique)  panel painting (image-making) carving (proceses)  relief (sculpture technique)\n\n  object_colour: multicoloured\n\n  physical_appearance: This painted carved panel  in high relief depicts the moment when a crab returns Saint Francis his crucifix which had fallen into the sea during a storm. The carving is clean and the forms are vividly articulated. Varying colours of the paint as well as the gilding further enhances its dimensionality.  This panel may have been a part of a larger ensemble.\n\n  subject_terms_1: reliefs (sculptures)  religious art Roman Catholicism  religious characters  missionaries Jesuit (Christian order)  parables religious visual works religious symbolism\n\n  subject_terms_2: Religious art Christian art and symbolism Jesuit Missions Saints  Ceram Island (Indonesia)  Ambon Island (Indonesia)\n\n  subject_terms_3: churches Religious life and practices  visual arts\n\n  subject_terms_4: \n\n  context_21: Goa\n India\n\n  sgcool_label_text: This carved panel shows one of the most famous miracles related to the Catholic missionary Saint Francis Xavier. When Francis Xavier was travelling between the islands of Ambon and Seram on his evangelizing mission\n his ship encountered a storm\n and Francis lost his crucifix in the rough waters. The ship managed to dock safely. Just then a crab appeared holding the crucifix in its claws\n returning it to Francis Xavier. \\r\\nThis is one of the most popular episodes from the life of the saint\n and served as inspiration for many artworks after his death. From the panel’s size and high quality of carving\n it was likely commissioned for a church. \\r\\n\n",
  "createdDate": "20201120223707",
  "version": 0,
  "latest": false,
  "roles": [],
  "metadata": {
    "accession_no_csv": "2017-00256",
    "Image": "",
    "object_work_type": "Sculpture (visual works)",
    "title_text": "Relief panel depicting St Francis Xavier",
    "preference": "main",
    "title_language": "",
    "creation_date": "17th century",
    "creation_place_original_location": "Velha Goa (India)",
    "styles_periods_indexing_terms": "European  Indian (South Asian)",
    "inscriptions": "",
    "inscription_language": "",
    "shape": "irregular",
    "materials_name": "teak (wood)  gilding (material)  paint (coating)",
    "techniques_name": "gilding (technique)  panel painting (image-making) carving (proceses)  relief (sculpture technique)",
    "object_colour": "multicoloured",
    "physical_appearance": "This painted carved panel  in high relief depicts the moment when a crab returns Saint Francis his crucifix which had fallen into the sea during a storm. The carving is clean and the forms are vividly articulated. Varying colours of the paint as well as the gilding further enhances its dimensionality.  This panel may have been a part of a larger ensemble.",
    "subject_terms_1": "reliefs (sculptures)  religious art Roman Catholicism  religious characters  missionaries Jesuit (Christian order)  parables religious visual works religious symbolism",
    "subject_terms_2": "Religious art Christian art and symbolism Jesuit Missions Saints  Ceram Island (Indonesia)  Ambon Island (Indonesia)",
    "subject_terms_3": "churches Religious life and practices  visual arts",
    "subject_terms_4": "",
    "context_21": "Goa, India",
    "sgcool_label_text": "This carved panel shows one of the most famous miracles related to the Catholic missionary Saint Francis Xavier. When Francis Xavier was travelling between the islands of Ambon and Seram on his evangelizing mission, his ship encountered a storm, and Francis lost his crucifix in the rough waters. The ship managed to dock safely. Just then a crab appeared holding the crucifix in its claws, returning it to Francis Xavier. \r\nThis is one of the most popular episodes from the life of the saint, and served as inspiration for many artworks after his death. From the panel’s size and high quality of carving, it was likely commissioned for a church. \r\n"
  },
  "nlpDate": "20201120223707",
  "connectorId": 0,
  "tags": {}
}