{"id":"2017-00482-004","title":"The First Signpost Pantjangan Pertama Ibu dan Anak","source":"Bumblebee","path":"./Data/json/","content":"accession_no_csv:2017-00482-004\nImage:\nobject_work_type:linocuts (prints)  artists\\u0027 books (books)\ntitle_text:The First Signpost Pantjangan Pertama Ibu dan Anak\npreference:alternate alternate main\ntitle_language:\ncreator_2:Mochtar Apin\ncreator_1:Apin\n Mochtar\ncreator_role:artists (visual artists)\ncreation_date:1948\ncreation_place_original_location:Bandung (Indonesia)\nstyles_periods_indexing_terms:Indonesian (culture or style)\ninscriptions:\ninscription_language:\nshape:Rectangular\nmaterials_name:paper (fiber product)\ntechniques_name:linoleum block printing\nobject_colour:black-and-white (colour)\nedition_description:Artist Proof\nphysical_appearance:This print is an image of a mother nursing her child. The artist\\u0027s initials can be found on the bottom left. It is noticeable that the paper is browning.\nsubject_terms_1:social realism  Mother  figurative art  Children (people by age group)  nursing (mammal feeding)\nsubject_terms_2:Prints\n Indonesian  Apin\n Mochtar Social realism  Mother and child  Figurative art  Breastfeeding Indonesians\nsubject_terms_3:Visual arts\nsgcool_label_text:Pantjangan Pertama is another folio of linocut prints following Apin’s collaboration with Baharoedin in 1946. Funded by the Gelanggang collective this time round\n it consists of 12 works on paper. Featuring a collection of images of objects and people going about their daily activities\n they represent the ‘daily realities’ of the different societies within the Indonesian community.\\r\\n\\r\\nDuring the post-WW II period\n the print medium was generally associated with the Social Realist art movements\n looking at the few examples in Southeast Asia. Apin’s prints works\n though maintaining the socialist bent is as much\n if not more\n about the print medium itself as a possible new direction in modern Indonesian art. Culturally dominated by paintings\n Apin’s folio of prints and the activities of the Gelanggang collective are testament towards this push.","createdDate":"20201018182636","version":0,"latest":false,"roles":[],"metadata":{"accession_no_csv":"2017-00482-004","Image":"","object_work_type":"linocuts (prints)  artists\u0027 books (books)","title_text":"The First Signpost Pantjangan Pertama Ibu dan Anak","preference":"alternate alternate main","title_language":"","creator_2":"Mochtar Apin","creator_1":"Apin, Mochtar","creator_role":"artists (visual artists)","creation_date":"1948","creation_place_original_location":"Bandung (Indonesia)","styles_periods_indexing_terms":"Indonesian (culture or style)","inscriptions":"","inscription_language":"","shape":"Rectangular","materials_name":"paper (fiber product)","techniques_name":"linoleum block printing","object_colour":"black-and-white (colour)","edition_description":"Artist Proof","physical_appearance":"This print is an image of a mother nursing her child. The artist\u0027s initials can be found on the bottom left. It is noticeable that the paper is browning.","subject_terms_1":"social realism  Mother  figurative art  Children (people by age group)  nursing (mammal feeding)","subject_terms_2":"Prints, Indonesian  Apin, Mochtar Social realism  Mother and child  Figurative art  Breastfeeding Indonesians","subject_terms_3":"Visual arts","sgcool_label_text":"Pantjangan Pertama is another folio of linocut prints following Apin’s collaboration with Baharoedin in 1946. Funded by the Gelanggang collective this time round, it consists of 12 works on paper. Featuring a collection of images of objects and people going about their daily activities, they represent the ‘daily realities’ of the different societies within the Indonesian community.\r\n\r\nDuring the post-WW II period, the print medium was generally associated with the Social Realist art movements, looking at the few examples in Southeast Asia. Apin’s prints works, though maintaining the socialist bent is as much, if not more, about the print medium itself as a possible new direction in modern Indonesian art. Culturally dominated by paintings, Apin’s folio of prints and the activities of the Gelanggang collective are testament towards this push."},"nlpDate":"20201018182636","connectorId":0,"tags":{}}