{"id":"2017-00317","title":"Orchids under Bamboo Shade","source":"Bumblebee","path":"./Data/json/","content":"accession_no_csv:2017-00317\nImage:\nobject_work_type:ink wash paintings\ntitle_text:Orchids under Bamboo Shade\npreference:main\ntitle_language:\ncreator_2:Fan\n Chang Tien\ncreator_1:Fan\n Changqian\n 1907-1987\ncreator_role:artists (visual artists)\ncreation_date:1965\nstyles_periods_indexing_terms:Chinese (culture or style)\ninscriptions:\ninscription_language:\nshape:Rectangular\nmaterials_name:Chinese ink\ntechniques_name:xieyi\nobject_colour:black-and-white (colours)\nphysical_appearance:This is a chinese ink painting of bamboos and orchids. The strokes are clean and measured\n and comprise of both wet and dry brush strokes. Cutting across the paper in a zig-zag fashion\n the leaves provide a visual rhythm that works in harmony with the void. An inscription has been written on the top left in a semi-cursive script. Two seals can be found at the end of the last two lines of the inscription\n as well as the bottom  right corner.\nsubject_terms_1:Orchidaceae (family)\nsubject_terms_2:Bamboo in art\nsubject_terms_3:Chinese ink painting\nsgcool_label_text:\\As one of the most influential pioneer artists in local art scene\n Fan Chang Tien(1907-1987) was significant in shaping the direction for the modern development of ink painting in Singapore. During the 1920s\n Fan studied in Shanghai Xin Hua Art Academy and then Shanghai Changming Academy of Art. He was taught by renowned Shanghai school artists such as Wang Geyi\n Wang Yiting\n Zhu Wenyun and Pan Tianshou. Fan arrived in Singapore in 1956 and began teaching art in Chung Cheng High School and Whampoa Secondary School respectively. Over decades\n the artist nurtured a group of ink painters\n and some of them become the leading figures of modern ink innovation in Singapore such Chua Ek Kay\n Tan Oe Pang and Chen Kezhan. \\r\\nFan is specialised in the\\\\ xieyi\\\\ style (an expressive and sketchy style of Chinese ink painting) Chinese painting and competent both in the traditional genres of mountain-and-water and flower-and-bird. \\r","createdDate":"20201119143406","version":0,"latest":false,"roles":[],"metadata":{"accession_no_csv":"2017-00317","Image":"","object_work_type":"ink wash paintings","title_text":"Orchids under Bamboo Shade","preference":"main","title_language":"","creator_2":"Fan, Chang Tien","creator_1":"Fan, Changqian, 1907-1987","creator_role":"artists (visual artists)","creation_date":"1965","styles_periods_indexing_terms":"Chinese (culture or style)","inscriptions":"","inscription_language":"","shape":"Rectangular","materials_name":"Chinese ink","techniques_name":"xieyi","object_colour":"black-and-white (colours)","physical_appearance":"This is a chinese ink painting of bamboos and orchids. The strokes are clean and measured, and comprise of both wet and dry brush strokes. Cutting across the paper in a zig-zag fashion, the leaves provide a visual rhythm that works in harmony with the void. An inscription has been written on the top left in a semi-cursive script. Two seals can be found at the end of the last two lines of the inscription, as well as the bottom  right corner.","subject_terms_1":"Orchidaceae (family)","subject_terms_2":"Bamboo in art","subject_terms_3":"Chinese ink painting","sgcool_label_text":"\"As one of the most influential pioneer artists in local art scene, Fan Chang Tien(1907-1987) was significant in shaping the direction for the modern development of ink painting in Singapore. During the 1920s, Fan studied in Shanghai Xin Hua Art Academy and then Shanghai Changming Academy of Art. He was taught by renowned Shanghai school artists such as Wang Geyi, Wang Yiting, Zhu Wenyun and Pan Tianshou. Fan arrived in Singapore in 1956 and began teaching art in Chung Cheng High School and Whampoa Secondary School respectively. Over decades, the artist nurtured a group of ink painters, and some of them become the leading figures of modern ink innovation in Singapore such Chua Ek Kay, Tan Oe Pang and Chen Kezhan. \r\nFan is specialised in the\"\" xieyi\"\" style (an expressive and sketchy style of Chinese ink painting) Chinese painting and competent both in the traditional genres of mountain-and-water and flower-and-bird. \r"},"nlpDate":"20201119143406","connectorId":0,"tags":{}}