{
  "id": "2017-00156-019",
  "title": "Lung Chui Ying Collection: Photographs, Printed Images, Pamphlets and Clippings  collected by Lung Chui Ying ., Lung Chui Ying Collection:  Photograph of a Group While On Holiday In Chong Qing \r\n",
  "source": "Bumblebee",
  "path": "./Data/json/",
  "content": "\n  accession_no_csv: 2017-00156-019\n\n  Image: \n\n  object_work_type: photographs black-and-white photographs\n\n  title_text: Lung Chui Ying Collection: Photographs\n Printed Images\n Pamphlets and Clippings  collected by Lung Chui Ying .\n Lung Chui Ying Collection:  Photograph of a Group While On Holiday In Chong Qing \\r\\n\n\n  preference: main alternate\n\n  title_language: \n\n  creation_date: Not indicated\n\n  creation_place_original_location: Chongqing Singapore China\n\n  inscriptions: \n\n  inscription_language: \n\n  shape: Rectangular\n\n  materials_name: paper (fiber product)\n\n  techniques_name: printing (process) black-and-white photography handwriting\n\n  object_colour: black-and-white (colors)\n\n  physical_appearance: This is a black and white photograph of a group trip to the hotsprings at Chong Qing. The front row is squatting\n while the individuals in the row behind are standing. There is a little child squatting in the arms of the third individual from the left.\n\n  subject_terms_1: resistance movements local histories world wars Chinese scripts armed forces guerilla warfare\n\n  subject_terms_2: World War\n 1939-1945 Armed Forces Guerillas Photographs Great Britain. Army. Force 136 Chinese characters Local history Force 136 (Guerilla movement) War resistance movements Writing\n\n  subject_terms_3: History Photography 1942-1945 Japanese Occupation Force 136 (Guerilla movement) Lung\n Chiu Ying\n\n  sgcool_label_text: These photographs\n printed images\n pamphlets and clippings belong to Lung Chui Ying and is part of a larger collection related to the World War II underground resistance movement known as Force 136. The collection of materials was gathered by Tan Chong Tee (1916- 2012)\n who was a key member of this resistance group. The collection consists of original materials belonging to Tan and other members of Force 136 dating from the 1940s to new materials reproduced from memory by Tan Chong Tee\n which date from the mid-1990s to early 2000s. \\r\\n\\r\\nForce 136 was set up in July 1942 as part of the British Special Operations Executive (SOE). It recruited and trained local guerillas to gather intelligence and create an underground spy network to support planned British invasion of Japanese-occupied Malaya.\\r\\n\\r\\nLung Chui Ying was a Hainanese born in Johor and recruited as a Force 136 member to fight against the Japanese in Malaya.\n",
  "createdDate": "20201201203308",
  "version": 0,
  "latest": false,
  "roles": [],
  "metadata": {
    "accession_no_csv": "2017-00156-019",
    "Image": "",
    "object_work_type": "photographs black-and-white photographs",
    "title_text": "Lung Chui Ying Collection: Photographs, Printed Images, Pamphlets and Clippings  collected by Lung Chui Ying ., Lung Chui Ying Collection:  Photograph of a Group While On Holiday In Chong Qing \r\n",
    "preference": "main alternate",
    "title_language": "",
    "creation_date": "Not indicated",
    "creation_place_original_location": "Chongqing Singapore China",
    "inscriptions": "",
    "inscription_language": "",
    "shape": "Rectangular",
    "materials_name": "paper (fiber product)",
    "techniques_name": "printing (process) black-and-white photography handwriting",
    "object_colour": "black-and-white (colors)",
    "physical_appearance": "This is a black and white photograph of a group trip to the hotsprings at Chong Qing. The front row is squatting, while the individuals in the row behind are standing. There is a little child squatting in the arms of the third individual from the left.",
    "subject_terms_1": "resistance movements local histories world wars Chinese scripts armed forces guerilla warfare",
    "subject_terms_2": "World War, 1939-1945 Armed Forces Guerillas Photographs Great Britain. Army. Force 136 Chinese characters Local history Force 136 (Guerilla movement) War resistance movements Writing",
    "subject_terms_3": "History Photography 1942-1945 Japanese Occupation Force 136 (Guerilla movement) Lung, Chiu Ying",
    "sgcool_label_text": "These photographs, printed images, pamphlets and clippings belong to Lung Chui Ying and is part of a larger collection related to the World War II underground resistance movement known as Force 136. The collection of materials was gathered by Tan Chong Tee (1916- 2012), who was a key member of this resistance group. The collection consists of original materials belonging to Tan and other members of Force 136 dating from the 1940s to new materials reproduced from memory by Tan Chong Tee, which date from the mid-1990s to early 2000s. \r\n\r\nForce 136 was set up in July 1942 as part of the British Special Operations Executive (SOE). It recruited and trained local guerillas to gather intelligence and create an underground spy network to support planned British invasion of Japanese-occupied Malaya.\r\n\r\nLung Chui Ying was a Hainanese born in Johor and recruited as a Force 136 member to fight against the Japanese in Malaya."
  },
  "nlpDate": "20201201203308",
  "connectorId": 0,
  "tags": {}
}