{
  "id": "2017-00599",
  "title": "Embroidered Blouse Choli",
  "source": "Bumblebee",
  "path": "./Data/json/",
  "content": "\n  accession_no_csv: 2017-00599\n\n  Image: \n\n  object_work_type: cholis womenswear\n\n  title_text: Embroidered Blouse Choli\n\n  preference: main alternate\n\n  title_language: English\n\n  creation_date: 20th century\n\n  creation_place_original_location: Kachchh (India)\n\n  inscriptions: \n\n  inscription_language: \n\n  shape: irregular\n\n  materials_name: cotton (textile) silk (textile)\n\n  techniques_name: sewing (needleworking technique) embroidering\n\n  object_colour: multicolored\n\n  physical_appearance: This is an embroidered choli. It features a dense embroided design along the lower half of the garment\n with geometric patterns. The sleeves feature a gold brocade panel.\n\n  subject_terms_1: folk costume embroidery (visual works) geometric motifs blouses (main garments) tops (garments\n general)\n\n  subject_terms_2: Ethnic costume Blouses Embroidery Brocade Motifs Rabaris\n\n  subject_terms_3: Indian costumes\n\n  subject_terms_4: \n\n  sgcool_label_text: A blouse from the Dhebaria Rebari community of Kutch\n Gujarat\n",
  "createdDate": "20201120223708",
  "version": 0,
  "latest": false,
  "roles": [],
  "metadata": {
    "accession_no_csv": "2017-00599",
    "Image": "",
    "object_work_type": "cholis womenswear",
    "title_text": "Embroidered Blouse Choli",
    "preference": "main alternate",
    "title_language": "English",
    "creation_date": "20th century",
    "creation_place_original_location": "Kachchh (India)",
    "inscriptions": "",
    "inscription_language": "",
    "shape": "irregular",
    "materials_name": "cotton (textile) silk (textile)",
    "techniques_name": "sewing (needleworking technique) embroidering",
    "object_colour": "multicolored",
    "physical_appearance": "This is an embroidered choli. It features a dense embroided design along the lower half of the garment, with geometric patterns. The sleeves feature a gold brocade panel.",
    "subject_terms_1": "folk costume embroidery (visual works) geometric motifs blouses (main garments) tops (garments, general)",
    "subject_terms_2": "Ethnic costume Blouses Embroidery Brocade Motifs Rabaris",
    "subject_terms_3": "Indian costumes",
    "subject_terms_4": "",
    "sgcool_label_text": "A blouse from the Dhebaria Rebari community of Kutch, Gujarat"
  },
  "nlpDate": "20201120223708",
  "connectorId": 0,
  "tags": {}
}