{
  "id": "2017-00147",
  "title": "Lung Chiu Ying Collection: Force 136 badge Lung Chui Ying Collection: Force 136 badge",
  "source": "Bumblebee",
  "path": "./Data/json/",
  "content": "\n  accession_no_csv: 2017-00147\n\n  Image: \n\n  object_work_type: badges\n\n  title_text: Lung Chiu Ying Collection: Force 136 badge Lung Chui Ying Collection: Force 136 badge\n\n  preference: main alternate\n\n  title_language: \n\n  creation_date: 1943-1945\n\n  creation_place_original_location: Singapore\n\n  inscriptions: \n\n  inscription_language: \n\n  shape: rectangular\n\n  materials_name: thread\n\n  techniques_name: embroidering\n\n  object_colour: multicolored\n\n  physical_appearance: This is a set of two badges from Force 136. The top one is rectangular shaped\n and striped in the colours blue\n yellow\n red and light blue. The badge below it is in the shape of a circle. Within it\n there is a bird with outstretched wings against a beige background. Underneath the bird\n there is a red flame pattern. The thread on the right of the badge is slightly frayed.\n\n  subject_terms_1: resistance movements world wars\n\n  subject_terms_2: World War\n 1939-1945 Wings (Insignia) Great Britain. Army. Force 136 Force 136 (Guerilla movement)\n\n  subject_terms_3: 1942-1945 Japanese occupation Force 136 (Guerilla movement) Lung\n Chiu Ying\n\n  subject_terms_4: \n\n  context_1: World War\n 1939-1945 1942-1945 Japanese Occupation\n\n  context_2: occupations (armed conflicts) world wars\n\n  context_3: 1942-1945 1939-1945\n\n  context_4: 1939 1942\n\n  context_5: 1945\n\n  context_6: Singapore Malaya\n\n  context_7: Great Britain. Army. Force 136\n\n  context_8: armed forces\n",
  "createdDate": "20201125084526",
  "version": 0,
  "latest": false,
  "roles": [],
  "metadata": {
    "accession_no_csv": "2017-00147",
    "Image": "",
    "object_work_type": "badges",
    "title_text": "Lung Chiu Ying Collection: Force 136 badge Lung Chui Ying Collection: Force 136 badge",
    "preference": "main alternate",
    "title_language": "",
    "creation_date": "1943-1945",
    "creation_place_original_location": "Singapore",
    "inscriptions": "",
    "inscription_language": "",
    "shape": "rectangular",
    "materials_name": "thread",
    "techniques_name": "embroidering",
    "object_colour": "multicolored",
    "physical_appearance": "This is a set of two badges from Force 136. The top one is rectangular shaped, and striped in the colours blue, yellow, red and light blue. The badge below it is in the shape of a circle. Within it, there is a bird with outstretched wings against a beige background. Underneath the bird, there is a red flame pattern. The thread on the right of the badge is slightly frayed.",
    "subject_terms_1": "resistance movements world wars",
    "subject_terms_2": "World War, 1939-1945 Wings (Insignia) Great Britain. Army. Force 136 Force 136 (Guerilla movement)",
    "subject_terms_3": "1942-1945 Japanese occupation Force 136 (Guerilla movement) Lung, Chiu Ying",
    "subject_terms_4": "",
    "context_1": "World War, 1939-1945 1942-1945 Japanese Occupation",
    "context_2": "occupations (armed conflicts) world wars",
    "context_3": "1942-1945 1939-1945",
    "context_4": "1939 1942",
    "context_5": "1945",
    "context_6": "Singapore Malaya",
    "context_7": "Great Britain. Army. Force 136",
    "context_8": "armed forces"
  },
  "nlpDate": "20201125084526",
  "connectorId": 0,
  "tags": {}
}