{
  "id": "2017-00151",
  "title": "Lung Chui Ying Collection: Image and interior plan of an Allied submarine Lung Chiu Ying Collection: Image and interior plan of an Allied submarine",
  "source": "Bumblebee",
  "path": "./Data/json/",
  "content": "\n  accession_no_csv: 2017-00151\n\n  Image: \n\n  object_work_type: documents (object genre)\n\n  title_text: Lung Chui Ying Collection: Image and interior plan of an Allied submarine Lung Chiu Ying Collection: Image and interior plan of an Allied submarine\n\n  preference: main alternate\n\n  title_language: \n\n  creation_date: 1940s\n\n  creation_place_original_location: Singapore\n\n  inscriptions: \n\n  inscription_language: \n\n  shape: rectangular\n\n  materials_name: paper (fiber product)\n\n  techniques_name: printing (process)\n\n  object_colour: black-and-white (colors)\n\n  physical_appearance: This is a set of black-and-white documents featuring photographs of an Allied submarine and its interior plan. The first document at the top shows the interior plan through four different sections\n with labels for each room and compartment. The second document below it shows two photographs of the submarine above water. The photographs are accompanied with Chinese captions underneath them. There are no tears seen on either documents.\n\n  subject_terms_1: submarines resistance movements world wars ships plans\n\n  subject_terms_2: World War\n 1939-1945 Submarines (Ships) Great Britain. Army. Force 136 Force 136 (Guerilla movement)\n\n  subject_terms_3: 1942-1945 Japanese occupation Force 136 (Guerilla movement) Lung\n Chiu Ying\n\n  subject_terms_4: \n\n  context_1: World War\n 1939-1945 1942-1945 Japanese Occupation\n\n  context_2: occupations (armed conflicts) world wars\n\n  context_3: 1942-1945 1939-1945\n\n  context_4: 1939 1942\n\n  context_5: 1945\n\n  context_6: Singapore Malaya\n\n  context_7: Great Britain. Army. Force 136\n\n  context_8: armed forces\n\n  sgcool_label_text: This image and interior plan of an Allied Submarine belong to Lung Chui Ying and are part of a larger collection of artefacts related to the World War II underground resistance movement known as Force 136. The collection of materials was amassed by Tan Chong Tee (1916- 2012)\n who was a key member of this resistance group. The collection consists of original materials belonging to Tan and other members of Force 136 dating from the 1940s to new materials reproduced from memory by Tan Chong Tee\n which date from the mid-1990s to early 2000s. \\r\\n\\r\\nForce 136 was set up in July 1942 as part of the British Special Operations Executive (SOE). It recruited and trained local guerillas to gather intelligence and create an underground spy network to support planned British invasion of Japanese-occupied Malaya.\\r\\n\n",
  "createdDate": "20201201203308",
  "version": 0,
  "latest": false,
  "roles": [],
  "metadata": {
    "accession_no_csv": "2017-00151",
    "Image": "",
    "object_work_type": "documents (object genre)",
    "title_text": "Lung Chui Ying Collection: Image and interior plan of an Allied submarine Lung Chiu Ying Collection: Image and interior plan of an Allied submarine",
    "preference": "main alternate",
    "title_language": "",
    "creation_date": "1940s",
    "creation_place_original_location": "Singapore",
    "inscriptions": "",
    "inscription_language": "",
    "shape": "rectangular",
    "materials_name": "paper (fiber product)",
    "techniques_name": "printing (process)",
    "object_colour": "black-and-white (colors)",
    "physical_appearance": "This is a set of black-and-white documents featuring photographs of an Allied submarine and its interior plan. The first document at the top shows the interior plan through four different sections, with labels for each room and compartment. The second document below it shows two photographs of the submarine above water. The photographs are accompanied with Chinese captions underneath them. There are no tears seen on either documents.",
    "subject_terms_1": "submarines resistance movements world wars ships plans",
    "subject_terms_2": "World War, 1939-1945 Submarines (Ships) Great Britain. Army. Force 136 Force 136 (Guerilla movement)",
    "subject_terms_3": "1942-1945 Japanese occupation Force 136 (Guerilla movement) Lung, Chiu Ying",
    "subject_terms_4": "",
    "context_1": "World War, 1939-1945 1942-1945 Japanese Occupation",
    "context_2": "occupations (armed conflicts) world wars",
    "context_3": "1942-1945 1939-1945",
    "context_4": "1939 1942",
    "context_5": "1945",
    "context_6": "Singapore Malaya",
    "context_7": "Great Britain. Army. Force 136",
    "context_8": "armed forces",
    "sgcool_label_text": "This image and interior plan of an Allied Submarine belong to Lung Chui Ying and are part of a larger collection of artefacts related to the World War II underground resistance movement known as Force 136. The collection of materials was amassed by Tan Chong Tee (1916- 2012), who was a key member of this resistance group. The collection consists of original materials belonging to Tan and other members of Force 136 dating from the 1940s to new materials reproduced from memory by Tan Chong Tee, which date from the mid-1990s to early 2000s. \r\n\r\nForce 136 was set up in July 1942 as part of the British Special Operations Executive (SOE). It recruited and trained local guerillas to gather intelligence and create an underground spy network to support planned British invasion of Japanese-occupied Malaya.\r\n"
  },
  "nlpDate": "20201201203308",
  "connectorId": 0,
  "tags": {}
}