{
  "id": "2017-00804",
  "title": "Men’s light blue silk long robe (Changshan)",
  "source": "Bumblebee",
  "path": "./Data/json/",
  "content": "\n  accession_no_csv: 2017-00804\n\n  Image: \n\n  object_work_type: robes (main garments) silks (costume by material)\n\n  title_text: Men’s light blue silk long robe (Changshan)\n\n  preference: main\n\n  title_language: \n\n  creation_date: 1920s\n\n  creation_place_original_location: Hong Kong (China)\n\n  styles_periods_indexing_terms: Chinese (culture or style)\n\n  inscriptions: \n\n  inscription_language: \n\n  shape: T-shaped?\n\n  materials_name: silk (textile)\n\n  techniques_name: sewing (needleworking technique)\n\n  object_colour: blue (colour)\n\n  physical_appearance: This is a blue silk robe that is buttoned on the proper right. The sleeves are broad\n and the robes are decorated with curvilinear and linear forms.\n\n  subject_terms_1: menswear folk costume casual wear\n\n  subject_terms_2: Silk Ethnic costume Men\\u0027s clothing Robes\n\n  subject_terms_3: Chinese costumes\n\n  context_20: Bullion Trading Company “Yee Shing”\n\n  context_21: 20 Canal Road in Singapore\n\n  context_22: 1930s\n\n  context_23: 1930\n\n  context_24: 1939\n\n  sgcool_label_text: The long robe (known as ‘changshan’in Southern China and Hong Kong and ‘changpao’  in Northern China) was the standard informal garment worn by men during the early Republican period in China and Hong Kong. It is a one-piece long robe that can be worn alone or under a short jacket known as a ‘magua’ . This robe was tailored at a certain tailor shop by the name of Lu Xin Long   in Hong Kong.\\r\\n\\r\\nThis exquisite robe belonged to Mr Kaan Tat Choi\n who was a successful businessman in the bullion business in Hong Kong. Mr Kaan expanded his business to Malaya in the 1920s\n acquiring several rubber plantations along the east coast of Malaya. He also opened a bullion trading company called “Yee Shing” at 20 Canal Road in Singapore in the 1930s. \\r\\n\n",
  "createdDate": "20201201203308",
  "version": 0,
  "latest": false,
  "roles": [],
  "metadata": {
    "accession_no_csv": "2017-00804",
    "Image": "",
    "object_work_type": "robes (main garments) silks (costume by material)",
    "title_text": "Men’s light blue silk long robe (Changshan)",
    "preference": "main",
    "title_language": "",
    "creation_date": "1920s",
    "creation_place_original_location": "Hong Kong (China)",
    "styles_periods_indexing_terms": "Chinese (culture or style)",
    "inscriptions": "",
    "inscription_language": "",
    "shape": "T-shaped?",
    "materials_name": "silk (textile)",
    "techniques_name": "sewing (needleworking technique)",
    "object_colour": "blue (colour)",
    "physical_appearance": "This is a blue silk robe that is buttoned on the proper right. The sleeves are broad, and the robes are decorated with curvilinear and linear forms.",
    "subject_terms_1": "menswear folk costume casual wear",
    "subject_terms_2": "Silk Ethnic costume Men\u0027s clothing Robes",
    "subject_terms_3": "Chinese costumes",
    "context_20": "Bullion Trading Company “Yee Shing”",
    "context_21": "20 Canal Road in Singapore",
    "context_22": "1930s",
    "context_23": "1930",
    "context_24": "1939",
    "sgcool_label_text": "The long robe (known as ‘changshan’in Southern China and Hong Kong and ‘changpao’  in Northern China) was the standard informal garment worn by men during the early Republican period in China and Hong Kong. It is a one-piece long robe that can be worn alone or under a short jacket known as a ‘magua’ . This robe was tailored at a certain tailor shop by the name of Lu Xin Long   in Hong Kong.\r\n\r\nThis exquisite robe belonged to Mr Kaan Tat Choi, who was a successful businessman in the bullion business in Hong Kong. Mr Kaan expanded his business to Malaya in the 1920s, acquiring several rubber plantations along the east coast of Malaya. He also opened a bullion trading company called “Yee Shing” at 20 Canal Road in Singapore in the 1930s. \r\n"
  },
  "nlpDate": "20201201203308",
  "connectorId": 0,
  "tags": {}
}