{"id":"2017-00145-056","title":"Reflections of Tan Chong Tee: Letters, Notes, and Photographs Reflections of Tan Chong Tee: Account Of  World War II","source":"Bumblebee","path":"./Data/json/","content":"accession_no_csv:2017-00145-056\nImage:\nobject_work_type:document (object genre) clippings (information artifacts)\ntitle_text:Reflections of Tan Chong Tee: Letters\n Notes\n and Photographs Reflections of Tan Chong Tee: Account Of  World War II\npreference:alternate main\ntitle_language:\ncreation_place_original_location:Singapore\ninscriptions:\ninscription_language:\nshape:Rectangular\nmaterials_name:paper (fiber product)\ntechniques_name:handwriting\nobject_colour:multicoloured\nphysical_appearance:This is an account of the author\\u0027s experiences during the second world war. This paper is folded down the middle and on the bottom right and left. It is also torn along the bottom length.  It reads from right to left and is written in traditional Chinese script with blue ink.\nsubject_terms_1:resistance movements  guerilla warfare local histories armed forces  Chinese scripts world wars diaries\nsubject_terms_2:Force 136 (Guerilla movement) War resistance movements  Guerillas  Local history Armed Forces  Great Britain. Army. Force 136 Writing  Chinese characters  Chen\n Chongzhi\n 1916-  World War\n 1939-1945 Diaries\nsubject_terms_3:Force 136 (Guerilla movement) History  Tan\n Chong Tee 1942-1945 Japanese Occupation  war personalities  \\r\\n\\r\\n\nsgcool_label_text:These documents and photographs belong to a larger part of a collection of artefacts related to the World War II underground resistance movement known as Force 136. The collection of materials was gathered by Tan Chong Tee (1916- 2012)\n who was a key member of this resistance group. The collection consists of original materials belonging to Tan and other members of Force 136 dating from the 1940s to new materials reproduced from memory by Tan Chong Tee\n which date from the late 1980s to early 2000s. \\r\\n\\r\\nForce 136 was set up in July 1942 as part of the British Special Operations Executive (SOE). It recruited and trained local guerillas to gather intelligence and create an underground spy network to support planned British invasion of Japanese-occupied Malaya.\\r\\n","createdDate":"20201119143406","version":0,"latest":false,"roles":[],"metadata":{"accession_no_csv":"2017-00145-056","Image":"","object_work_type":"document (object genre) clippings (information artifacts)","title_text":"Reflections of Tan Chong Tee: Letters, Notes, and Photographs Reflections of Tan Chong Tee: Account Of  World War II","preference":"alternate main","title_language":"","creation_place_original_location":"Singapore","inscriptions":"","inscription_language":"","shape":"Rectangular","materials_name":"paper (fiber product)","techniques_name":"handwriting","object_colour":"multicoloured","physical_appearance":"This is an account of the author\u0027s experiences during the second world war. This paper is folded down the middle and on the bottom right and left. It is also torn along the bottom length.  It reads from right to left and is written in traditional Chinese script with blue ink.","subject_terms_1":"resistance movements  guerilla warfare local histories armed forces  Chinese scripts world wars diaries","subject_terms_2":"Force 136 (Guerilla movement) War resistance movements  Guerillas  Local history Armed Forces  Great Britain. Army. Force 136 Writing  Chinese characters  Chen, Chongzhi, 1916-  World War, 1939-1945 Diaries","subject_terms_3":"Force 136 (Guerilla movement) History  Tan, Chong Tee 1942-1945 Japanese Occupation  war personalities  \r\n\r\n","sgcool_label_text":"These documents and photographs belong to a larger part of a collection of artefacts related to the World War II underground resistance movement known as Force 136. The collection of materials was gathered by Tan Chong Tee (1916- 2012), who was a key member of this resistance group. The collection consists of original materials belonging to Tan and other members of Force 136 dating from the 1940s to new materials reproduced from memory by Tan Chong Tee, which date from the late 1980s to early 2000s. \r\n\r\nForce 136 was set up in July 1942 as part of the British Special Operations Executive (SOE). It recruited and trained local guerillas to gather intelligence and create an underground spy network to support planned British invasion of Japanese-occupied Malaya.\r\n"},"nlpDate":"20201119143406","connectorId":0,"tags":{}}