{"id":"2017-00179-001","title":"Lim Hong Pei Collection ????? Lim Hong Pei Collection: army men","source":"Bumblebee","path":"./Data/json/","content":"accession_no_csv:2017-00179-001\nImage:\nobject_work_type:black-and-white photographs\ntitle_text:Lim Hong Pei Collection ????? Lim Hong Pei Collection: army men\npreference:alternate alternate main\ntitle_language:\ncreation_date:1946\ncreation_place_original_location:Singapore\ninscriptions:\ninscription_language:\nshape:rectangular\nmaterials_name:paper (fiber product)\ntechniques_name:photographic processes printing (process)\nobject_colour:black-and-white (colors)\nphysical_appearance:This is a black-and-white photograph. It features thirteen men in military uniform posing for the photogram. The front row is seated on the ground\n cross-legged\n while the back row stands behind them with their hands behind their back. There are no tears seen on this photograph.\nsubject_terms_1:world wars resistance movements soldiers\nsubject_terms_2:World War\n 1939-1945 Great Britain. Army. Force 136 Force 136 (Guerilla movement) Lim\n Hong Pei\n 1922- Photography Soldiers\nsubject_terms_3:Force 136 (Guerilla movement) 1942-1945 Japanese occupation Photography war personalities\nsubject_terms_4:\nsgcool_label_text:These photographs belong to part of a collection of artefacts related to the World War II underground resistance movement known as Force 136. The collection of materials was gathered by Tan Chong Tee (1916- 2012)\n who was a key member of this resistance group. The collection consists of original materials belonging to Tan and other members of Force 136 dating from the 1940s to new materials reproduced from memory by Tan Chong Tee\n which date from the late 1980s to early 2000s. \\r\\n\\r\\nForce 136 was set up in July 1942 as part of the British Special Operations Executive (SOE). It recruited and trained local guerillas to gather intelligence and create an underground spy network to support planned British invasion of Japanese-occupied Malaya.\\r\\n","createdDate":"20201119143406","version":0,"latest":false,"roles":[],"metadata":{"accession_no_csv":"2017-00179-001","Image":"","object_work_type":"black-and-white photographs","title_text":"Lim Hong Pei Collection ????? Lim Hong Pei Collection: army men","preference":"alternate alternate main","title_language":"","creation_date":"1946","creation_place_original_location":"Singapore","inscriptions":"","inscription_language":"","shape":"rectangular","materials_name":"paper (fiber product)","techniques_name":"photographic processes printing (process)","object_colour":"black-and-white (colors)","physical_appearance":"This is a black-and-white photograph. It features thirteen men in military uniform posing for the photogram. The front row is seated on the ground, cross-legged, while the back row stands behind them with their hands behind their back. There are no tears seen on this photograph.","subject_terms_1":"world wars resistance movements soldiers","subject_terms_2":"World War, 1939-1945 Great Britain. Army. Force 136 Force 136 (Guerilla movement) Lim, Hong Pei, 1922- Photography Soldiers","subject_terms_3":"Force 136 (Guerilla movement) 1942-1945 Japanese occupation Photography war personalities","subject_terms_4":"","sgcool_label_text":"These photographs belong to part of a collection of artefacts related to the World War II underground resistance movement known as Force 136. The collection of materials was gathered by Tan Chong Tee (1916- 2012), who was a key member of this resistance group. The collection consists of original materials belonging to Tan and other members of Force 136 dating from the 1940s to new materials reproduced from memory by Tan Chong Tee, which date from the late 1980s to early 2000s. \r\n\r\nForce 136 was set up in July 1942 as part of the British Special Operations Executive (SOE). It recruited and trained local guerillas to gather intelligence and create an underground spy network to support planned British invasion of Japanese-occupied Malaya.\r\n"},"nlpDate":"20201119143406","connectorId":0,"tags":{}}