{"id":"2017-00419","title":"Kain panjang","source":"Bumblebee","path":"./Data/json/","content":"accession_no_csv:2017-00419\nImage:\nobject_work_type:folk costume batik art\ntitle_text:Kain panjang\npreference:main\ntitle_language:\ncreator_2:Jane Hendromartono\ncreator_role:textile designers\ncreation_date:1965-1980s\ncreation_place_original_location:Pekalongan (Indonesia)\nstyles_periods_indexing_terms:Peranakan\ninscriptions:\ninscription_language:\nshape:rectangular\nmaterials_name:cotton (textile)\ntechniques_name:batik\nobject_colour:multicolored\nphysical_appearance:This is a batik kain panjang. It features garuda wings and tail feathers amidst spiralling cloud formations  and flowering tendrils. The motifs are set against a purple background\n decorated with starburst speckles to create a dense design. There is a signature on the bottom-left of the batik kain panjang.\nsubject_terms_1:Peranakan birds (motifs) foliage (motif)\nsubject_terms_2:Batik Ethnic costume Peranakan (Asian people) Motifs\nsubject_terms_3:Batik Peranakan costumes\nsgcool_label_text:Spiralling cloud formations\n an ancient megamendung motif\n are shown amidst flowering tendrils. Interspersed among them are the double wings and tail feathers of the garuda\n yet another ancient motif known as sawat.  Both of these motifs were commonly associated with the Cirebon and Javanese courts respectively.  This batik comes from the family collection of Oey Djien Nio (1929-1987)\n the last in three generations of documented batik-makers in Pekalongan.  In her earlier signatures\n she used her husband’s name\n Liem Siok Hien.  But from 1965 onwards\n she used Jane Hendromartono\n combining her husband’s new Indonesian family name\n Hendromartono with Jane\n as people addressed her by.  She developed a personal style distinct from her mother and grandmother\n and experimented with a wide spectrum of colours and exotic combinations of birds\n rock formations and mythical animals.  Jane Hendromartono’s clientele expanded beyond the elite in Indonesia to include Europe\n America and Japan\n especially in the 1980s.  This piece is signed “Hendromartono’s Batik Art” Unique Pekalongan Ind”.","createdDate":"20201119143406","version":0,"latest":false,"roles":[],"metadata":{"accession_no_csv":"2017-00419","Image":"","object_work_type":"folk costume batik art","title_text":"Kain panjang","preference":"main","title_language":"","creator_2":"Jane Hendromartono","creator_role":"textile designers","creation_date":"1965-1980s","creation_place_original_location":"Pekalongan (Indonesia)","styles_periods_indexing_terms":"Peranakan","inscriptions":"","inscription_language":"","shape":"rectangular","materials_name":"cotton (textile)","techniques_name":"batik","object_colour":"multicolored","physical_appearance":"This is a batik kain panjang. It features garuda wings and tail feathers amidst spiralling cloud formations  and flowering tendrils. The motifs are set against a purple background, decorated with starburst speckles to create a dense design. There is a signature on the bottom-left of the batik kain panjang.","subject_terms_1":"Peranakan birds (motifs) foliage (motif)","subject_terms_2":"Batik Ethnic costume Peranakan (Asian people) Motifs","subject_terms_3":"Batik Peranakan costumes","sgcool_label_text":"Spiralling cloud formations, an ancient megamendung motif, are shown amidst flowering tendrils. Interspersed among them are the double wings and tail feathers of the garuda, yet another ancient motif known as sawat.  Both of these motifs were commonly associated with the Cirebon and Javanese courts respectively.  This batik comes from the family collection of Oey Djien Nio (1929-1987), the last in three generations of documented batik-makers in Pekalongan.  In her earlier signatures, she used her husband’s name, Liem Siok Hien.  But from 1965 onwards, she used Jane Hendromartono, combining her husband’s new Indonesian family name, Hendromartono with Jane, as people addressed her by.  She developed a personal style distinct from her mother and grandmother, and experimented with a wide spectrum of colours and exotic combinations of birds, rock formations and mythical animals.  Jane Hendromartono’s clientele expanded beyond the elite in Indonesia to include Europe, America and Japan, especially in the 1980s.  This piece is signed “Hendromartono’s Batik Art” Unique Pekalongan Ind”."},"nlpDate":"20201119143406","connectorId":0,"tags":{}}