{
  "id": "2017-00071",
  "title": "Dashakarmapaddhati Manual for Ten Rituals - On Marriage",
  "source": "Bumblebee",
  "path": "./Data/json/",
  "content": "\n  accession_no_csv: 2017-00071\n\n  Image: \n\n  object_work_type: manuals (instructional materials) scripts (writing)\n\n  title_text: Dashakarmapaddhati Manual for Ten Rituals - On Marriage\n\n  preference: main alternate\n\n  title_language: English\n\n  creation_date: 19th century\n\n  creation_place_original_location: Bengal (India)\n\n  styles_periods_indexing_terms: Indian (South Asian)\n\n  inscriptions: \n\n  inscription_language: \n\n  shape: irregular\n\n  materials_name: palm leaf (material)\n\n  techniques_name: inscribing\n\n  object_colour: brown (color)\n\n  physical_appearance: This is a compiled palm leaf manuscript. The manuscript is compiled within two rounded palm leaf cases. It is bound by a red and orange band. There is a hole through the center of the palm leaf manuscript.\n\n  subject_terms_1: religious texts weddings (ceremonies) Hinduism inscriptions\n\n  subject_terms_2: Rites and ceremonies Marriage service Classical texts Hinduism Handbooks and manuals Palm-leaf inscriptions Tamil language\n\n  subject_terms_3: Religion and Philosophy\n\n  subject_terms_4: \n\n  sgcool_label_text: The dashakarma or “ten rites” of Hindu tradition\n encompass all aspects of a Hindu’s life from conception to death. The methods or paddhati of these ten rites have been described\n to enable correct observance of each rite. This manuscript is the manual of marriage\n thus describing the steps to be taken for a marriage ceremony. The text originates from the Bengal region of eastern India\n and as it dates to the 19th century\n would serve as an important record of the rites observed at the time.\n",
  "createdDate": "20201201203308",
  "version": 0,
  "latest": false,
  "roles": [],
  "metadata": {
    "accession_no_csv": "2017-00071",
    "Image": "",
    "object_work_type": "manuals (instructional materials) scripts (writing)",
    "title_text": "Dashakarmapaddhati Manual for Ten Rituals - On Marriage",
    "preference": "main alternate",
    "title_language": "English",
    "creation_date": "19th century",
    "creation_place_original_location": "Bengal (India)",
    "styles_periods_indexing_terms": "Indian (South Asian)",
    "inscriptions": "",
    "inscription_language": "",
    "shape": "irregular",
    "materials_name": "palm leaf (material)",
    "techniques_name": "inscribing",
    "object_colour": "brown (color)",
    "physical_appearance": "This is a compiled palm leaf manuscript. The manuscript is compiled within two rounded palm leaf cases. It is bound by a red and orange band. There is a hole through the center of the palm leaf manuscript.",
    "subject_terms_1": "religious texts weddings (ceremonies) Hinduism inscriptions",
    "subject_terms_2": "Rites and ceremonies Marriage service Classical texts Hinduism Handbooks and manuals Palm-leaf inscriptions Tamil language",
    "subject_terms_3": "Religion and Philosophy",
    "subject_terms_4": "",
    "sgcool_label_text": "The dashakarma or “ten rites” of Hindu tradition, encompass all aspects of a Hindu’s life from conception to death. The methods or paddhati of these ten rites have been described, to enable correct observance of each rite. This manuscript is the manual of marriage, thus describing the steps to be taken for a marriage ceremony. The text originates from the Bengal region of eastern India, and as it dates to the 19th century, would serve as an important record of the rites observed at the time."
  },
  "nlpDate": "20201201203308",
  "connectorId": 0,
  "tags": {}
}