{"id":"2017-00176","title":"Materials on Lim Bo Seng ????????","source":"Bumblebee","path":"./Data/json/","content":"accession_no_csv:2017-00176\nImage:\nobject_work_type:documents (object genre)\ntitle_text:Materials on Lim Bo Seng ????????\npreference:main alternate\ntitle_language:\ncreation_date:Not indicated\ncreation_place_original_location:Singapore\ninscriptions:\ninscription_language:\nshape:rectangular\nmaterials_name:paper (fiber product)\ntechniques_name:writing (processes) printing (process)\nobject_colour:black-and-white (color)\nphysical_appearance:This is a photocopy of a document\n printed in black and white. The document is  written in Chinese\n in vertical lines. There is a darker outline of the original document. The original document had two holes punched along the left.\nsubject_terms_1:world wars resistance movements photocopies Chinese scripts\nsubject_terms_2:World War\n 1939-1945 Great Britain. Army. Force 136 Force 136 (Guerilla movement) Chen\n Chongzhi\n 1916- Lim\n Bo Seng\n 1909-1944 Facsimiles\nsubject_terms_3:Force 136 (Guerilla movement) 1942-1945 Japanese occupation Tan\n Chong Tee Lim\n Bo Seng war personalities\nsubject_terms_4:\ncontext_1:World War\n 1939-1945 1942-1945 Japanese Occupation\ncontext_2:world wars occupations (armed conflicts)\ncontext_3:1939-1945 1942-1945\ncontext_4:1939 1942\ncontext_5:1945 1945\ncontext_6:Malaya Singapore\ncontext_7:Great Britain. Army. Force 136\ncontext_8:armed forces\nsgcool_label_text:These materials on Lim Bo Seng belongs to part of a collection of artefacts related to the World War II underground resistance movement known as Force 136. The collection of materials was gathered by Tan Chong Tee (1916- 2012)\n who was a key member of this resistance group. The collection consists of original materials belonging to Tan and other members of Force 136 dating from the 1940s to new materials reproduced from memory by Tan Chong Tee\n which date from the late 1980s to early 2000s. \\r\\n\\r\\nForce 136 was set up in July 1942 as part of the British Special Operations Executive (SOE). It recruited and trained local guerillas to gather intelligence and create an underground spy network to support planned British invasion of Japanese-occupied Malaya\\r\\n","createdDate":"20201018182636","version":0,"latest":false,"roles":[],"metadata":{"accession_no_csv":"2017-00176","Image":"","object_work_type":"documents (object genre)","title_text":"Materials on Lim Bo Seng ????????","preference":"main alternate","title_language":"","creation_date":"Not indicated","creation_place_original_location":"Singapore","inscriptions":"","inscription_language":"","shape":"rectangular","materials_name":"paper (fiber product)","techniques_name":"writing (processes) printing (process)","object_colour":"black-and-white (color)","physical_appearance":"This is a photocopy of a document, printed in black and white. The document is  written in Chinese, in vertical lines. There is a darker outline of the original document. The original document had two holes punched along the left.","subject_terms_1":"world wars resistance movements photocopies Chinese scripts","subject_terms_2":"World War, 1939-1945 Great Britain. Army. Force 136 Force 136 (Guerilla movement) Chen, Chongzhi, 1916- Lim, Bo Seng, 1909-1944 Facsimiles","subject_terms_3":"Force 136 (Guerilla movement) 1942-1945 Japanese occupation Tan, Chong Tee Lim, Bo Seng war personalities","subject_terms_4":"","context_1":"World War, 1939-1945 1942-1945 Japanese Occupation","context_2":"world wars occupations (armed conflicts)","context_3":"1939-1945 1942-1945","context_4":"1939 1942","context_5":"1945 1945","context_6":"Malaya Singapore","context_7":"Great Britain. Army. Force 136","context_8":"armed forces","sgcool_label_text":"These materials on Lim Bo Seng belongs to part of a collection of artefacts related to the World War II underground resistance movement known as Force 136. The collection of materials was gathered by Tan Chong Tee (1916- 2012), who was a key member of this resistance group. The collection consists of original materials belonging to Tan and other members of Force 136 dating from the 1940s to new materials reproduced from memory by Tan Chong Tee, which date from the late 1980s to early 2000s. \r\n\r\nForce 136 was set up in July 1942 as part of the British Special Operations Executive (SOE). It recruited and trained local guerillas to gather intelligence and create an underground spy network to support planned British invasion of Japanese-occupied Malaya\r\n"},"nlpDate":"20201018182636","connectorId":0,"tags":{}}