{"id":"2017-00008","title":"Unknown","source":"Bumblebee","path":"./Data/json/","content":"accession_no_csv:2017-00008\nImage:\nobject_work_type:gelatin silver prints  black-and-white prints (photographs)  photographic prints\ntitle_text:Unknown\npreference:main\ntitle_language:\ncreator_2:Lee\n Lim\ncreator_1:Lee\n Lim\ncreator_role:photographers\ncreation_date:c. 1970\ncreation_place_original_location:Not indicated\ninscriptions:\ninscription_language:\nshape:rectangular\nmaterials_name:gelatin  paper (fibre product)  silver sulfide  baryta paper\ntechniques_name:gelatin silver process photographic printing techniques black-and-white photography\nobject_colour:black-and-white (colours)\nphysical_appearance:This image is a gelatin silver print that depicts a lone female figure washing a bucket of linen whilst squatting on a wooden plank to keep afloat near shore.  Enveloping her from a distance in the background\n is a shroud of fog. Lining the parameters of the bottom half of the picture are outstretched branches of leafy trees on the left\n a sandy shore\n and a thatched house on the right. There is a description of the work followed by the artist\\u0027s signature and seal on the top left hand corner. The artist\\u0027s photography studio seal is on the verso.\nsubject_terms_1:genre (visual works)  river settlements\nsubject_terms_2:Genre prints  Photography\n Artistic  Royal Photographic Society of Great Britain\nsubject_terms_3:visual arts  Artistic photography\ncontext_20:Address indicated on photography studio\\u0027s chop.\ncontext_21:No 1 Tiong Bahru Road\n Singapore 3\ncontext_22:c. 1970\ncontext_23:1965\ncontext_24:1975\nsgcool_label_text:Lee Lim was one of the most important modern photographers in Singapore\n influencing a generation of photographers in the pictorial photography circles. Between 1952 and 1979\n Lee took part in more than 100 photographic competitions and won numerous awards and honours. He received the Fellowship of the Royal Photographic Society (UK) in 1959 and the Artist Distinction by the International Federation of Photographic Art (FIAP) in 1977. He was also conferred an honorary fellowship by the Photographic Society of Singapore and won the Cultural Medallion in 1987.","createdDate":"20201018182636","version":0,"latest":false,"roles":[],"metadata":{"accession_no_csv":"2017-00008","Image":"","object_work_type":"gelatin silver prints  black-and-white prints (photographs)  photographic prints","title_text":"Unknown","preference":"main","title_language":"","creator_2":"Lee, Lim","creator_1":"Lee, Lim","creator_role":"photographers","creation_date":"c. 1970","creation_place_original_location":"Not indicated","inscriptions":"","inscription_language":"","shape":"rectangular","materials_name":"gelatin  paper (fibre product)  silver sulfide  baryta paper","techniques_name":"gelatin silver process photographic printing techniques black-and-white photography","object_colour":"black-and-white (colours)","physical_appearance":"This image is a gelatin silver print that depicts a lone female figure washing a bucket of linen whilst squatting on a wooden plank to keep afloat near shore.  Enveloping her from a distance in the background, is a shroud of fog. Lining the parameters of the bottom half of the picture are outstretched branches of leafy trees on the left, a sandy shore, and a thatched house on the right. There is a description of the work followed by the artist\u0027s signature and seal on the top left hand corner. The artist\u0027s photography studio seal is on the verso.","subject_terms_1":"genre (visual works)  river settlements","subject_terms_2":"Genre prints  Photography, Artistic  Royal Photographic Society of Great Britain","subject_terms_3":"visual arts  Artistic photography","context_20":"Address indicated on photography studio\u0027s chop.","context_21":"No 1 Tiong Bahru Road, Singapore 3","context_22":"c. 1970","context_23":"1965","context_24":"1975","sgcool_label_text":"Lee Lim was one of the most important modern photographers in Singapore, influencing a generation of photographers in the pictorial photography circles. Between 1952 and 1979, Lee took part in more than 100 photographic competitions and won numerous awards and honours. He received the Fellowship of the Royal Photographic Society (UK) in 1959 and the Artist Distinction by the International Federation of Photographic Art (FIAP) in 1977. He was also conferred an honorary fellowship by the Photographic Society of Singapore and won the Cultural Medallion in 1987."},"nlpDate":"20201018182636","connectorId":0,"tags":{}}