{
  "id": "2017-00225-012",
  "title": "Miniatures from The Sunny Orient where Sorrow Smiles and Poverty and Riches – Sin and Sanctity – Beauty and Ugliness all keep company Wooden Boat Riding a Tide",
  "source": "Bumblebee",
  "path": "./Data/json/",
  "content": "\n  accession_no_csv: 2017-00225-012\n\n  Image: \n\n  object_work_type: gelatin silver prints  photographic prints  black-and-white prints (photographs)\n\n  title_text: Miniatures from The Sunny Orient where Sorrow Smiles and Poverty and Riches – Sin and Sanctity – Beauty and Ugliness all keep company Wooden Boat Riding a Tide\n\n  preference: alternate  main\n\n  title_language: \n\n  creator_2: SHEAF\n Egbert Thomas.\n\n  creator_role: photographers\n\n  creation_date: 1922-1925\n\n  creation_place_original_location: Asia\n\n  inscriptions: \n\n  inscription_language: \n\n  shape: Rectangular\n\n  materials_name: gelatin  baryta paper  silver sulfide\n\n  techniques_name: gelatin silver process  photographic printing techniques  black-and-white photography\n\n  object_colour: black-and-white (colours)\n\n  physical_appearance: This print shows a wooden boat riding a tide. Several individuals are seen steering at the hull of the boat. The edge of a hill/mountain/ landform can be seen in the background.\n\n  subject_terms_1: travel photography boats  sampans  bodies of water (natural)\n\n  subject_terms_2: Prints  Travel photography  Boats and boating  Bodies of water\n\n  subject_terms_3: Travel photography Waterways Visual arts\n\n  subject_terms_4: \n\n  sgcool_label_text: These photographs were taken by Egbert Sheaf\n the Australian Trade Commissioner in Singapore\n several taken before and some of which were most likely taken when he was posted here between 1922-25. Sheaf conscientiously studied South-East Asia\\u0027s ethnography and his scholarship was coupled with a passion for travel and adventure. His photographs cover various aspects of daily and cultural life such as weaving\n the rice agriculture and other rituals of Javanese and Malayan communities\n as explained and illustrated in the portfolios and albums.\n",
  "createdDate": "20201120223707",
  "version": 0,
  "latest": false,
  "roles": [],
  "metadata": {
    "accession_no_csv": "2017-00225-012",
    "Image": "",
    "object_work_type": "gelatin silver prints  photographic prints  black-and-white prints (photographs)",
    "title_text": "Miniatures from The Sunny Orient where Sorrow Smiles and Poverty and Riches – Sin and Sanctity – Beauty and Ugliness all keep company Wooden Boat Riding a Tide",
    "preference": "alternate  main",
    "title_language": "",
    "creator_2": "SHEAF, Egbert Thomas.",
    "creator_role": "photographers",
    "creation_date": "1922-1925",
    "creation_place_original_location": "Asia",
    "inscriptions": "",
    "inscription_language": "",
    "shape": "Rectangular",
    "materials_name": "gelatin  baryta paper  silver sulfide",
    "techniques_name": "gelatin silver process  photographic printing techniques  black-and-white photography",
    "object_colour": "black-and-white (colours)",
    "physical_appearance": "This print shows a wooden boat riding a tide. Several individuals are seen steering at the hull of the boat. The edge of a hill/mountain/ landform can be seen in the background.",
    "subject_terms_1": "travel photography boats  sampans  bodies of water (natural)",
    "subject_terms_2": "Prints  Travel photography  Boats and boating  Bodies of water",
    "subject_terms_3": "Travel photography Waterways Visual arts",
    "subject_terms_4": "",
    "sgcool_label_text": "These photographs were taken by Egbert Sheaf, the Australian Trade Commissioner in Singapore, several taken before and some of which were most likely taken when he was posted here between 1922-25. Sheaf conscientiously studied South-East Asia\u0027s ethnography and his scholarship was coupled with a passion for travel and adventure. His photographs cover various aspects of daily and cultural life such as weaving, the rice agriculture and other rituals of Javanese and Malayan communities, as explained and illustrated in the portfolios and albums."
  },
  "nlpDate": "20201120223707",
  "connectorId": 0,
  "tags": {}
}