{"id":"2017-00163","title":"Lee Shao Meng Collection: Letter  ?????","source":"Bumblebee","path":"./Data/json/","content":"accession_no_csv:2017-00163\nImage:\nobject_work_type:letters (correspondence)\ntitle_text:Lee Shao Meng Collection: Letter  ?????\npreference:main alternate\ntitle_language:\ncreation_date:1940s\ncreation_place_original_location:Singapore\ninscriptions:\ninscription_language:\nshape:rectangular\nmaterials_name:paper (fiber product)\ntechniques_name:writing (processes)\nobject_colour:multicolored\nphysical_appearance:This is a letter written in Chinese. It consists of three pages. The letter is printed on papers with vertical boxes outlined in red. It is printed in black ink. Each page is vertically folded along the center. The edges of the pages are badly folded\n with the top right corner of the second page torn.\nsubject_terms_1:world wars resistance movements documents (object genre) Chinese scripts handwriting\nsubject_terms_2:World War\n 1939-1945 Great Britain. Army. Force 136 Force 136 (Guerilla movement) Letters Writing\nsubject_terms_3:Force 136 (Guerilla movement) 1942-1945 Japanese occupation Lee\n Shao Meng Letters\nsubject_terms_4:\ncontext_1:World War\n 1939-1945 1942-1945 Japanese Occupation\ncontext_2:world wars occupations (armed conflicts)\ncontext_3:1939-1945 1942-1945\ncontext_4:1939 1942\ncontext_5:1945 1945\ncontext_6:Malaya Singapore\ncontext_7:Great Britain. Army. Force 136\ncontext_8:armed forces\nsgcool_label_text:This letter belongs to part of a collection of artefacts related to the World War II underground resistance movement known as Force 136. The collection of materials was gathered by Tan Chong Tee (1916- 2012)\n who was a key member of this resistance group. The collection consists of original materials belonging to Tan and other members of Force 136 dating from the 1940s to new materials reproduced from memory by Tan Chong Tee\n which date from the late 1980s to early 2000s. \\r\\n\\r\\nForce 136 was set up in July 1942 as part of the British Special Operations Executive (SOE). It recruited and trained local guerillas to gather intelligence and create an underground spy network to support planned British invasion of Japanese-occupied Malaya.\\r\\n\\r\\nLee Shao Meng was the wife of Tan Chong Tee and was also involved in the war resistance movement in Malaya against the Japanese.","createdDate":"20201018182636","version":0,"latest":false,"roles":[],"metadata":{"accession_no_csv":"2017-00163","Image":"","object_work_type":"letters (correspondence)","title_text":"Lee Shao Meng Collection: Letter  ?????","preference":"main alternate","title_language":"","creation_date":"1940s","creation_place_original_location":"Singapore","inscriptions":"","inscription_language":"","shape":"rectangular","materials_name":"paper (fiber product)","techniques_name":"writing (processes)","object_colour":"multicolored","physical_appearance":"This is a letter written in Chinese. It consists of three pages. The letter is printed on papers with vertical boxes outlined in red. It is printed in black ink. Each page is vertically folded along the center. The edges of the pages are badly folded, with the top right corner of the second page torn.","subject_terms_1":"world wars resistance movements documents (object genre) Chinese scripts handwriting","subject_terms_2":"World War, 1939-1945 Great Britain. Army. Force 136 Force 136 (Guerilla movement) Letters Writing","subject_terms_3":"Force 136 (Guerilla movement) 1942-1945 Japanese occupation Lee, Shao Meng Letters","subject_terms_4":"","context_1":"World War, 1939-1945 1942-1945 Japanese Occupation","context_2":"world wars occupations (armed conflicts)","context_3":"1939-1945 1942-1945","context_4":"1939 1942","context_5":"1945 1945","context_6":"Malaya Singapore","context_7":"Great Britain. Army. Force 136","context_8":"armed forces","sgcool_label_text":"This letter belongs to part of a collection of artefacts related to the World War II underground resistance movement known as Force 136. The collection of materials was gathered by Tan Chong Tee (1916- 2012), who was a key member of this resistance group. The collection consists of original materials belonging to Tan and other members of Force 136 dating from the 1940s to new materials reproduced from memory by Tan Chong Tee, which date from the late 1980s to early 2000s. \r\n\r\nForce 136 was set up in July 1942 as part of the British Special Operations Executive (SOE). It recruited and trained local guerillas to gather intelligence and create an underground spy network to support planned British invasion of Japanese-occupied Malaya.\r\n\r\nLee Shao Meng was the wife of Tan Chong Tee and was also involved in the war resistance movement in Malaya against the Japanese."},"nlpDate":"20201018182636","connectorId":0,"tags":{}}