{
  "id": "2017-00156-013",
  "title": "Lung Chui Ying Collection: Photographs, Printed Images, Pamphlets and Clippings  collected by Lung Chui Ying Lung Chiu Ying Collection: military memorial service",
  "source": "Bumblebee",
  "path": "./Data/json/",
  "content": "\n  accession_no_csv: 2017-00156-013\n\n  Image: \n\n  object_work_type: black-and-white photographs\n\n  title_text: Lung Chui Ying Collection: Photographs\n Printed Images\n Pamphlets and Clippings  collected by Lung Chui Ying Lung Chiu Ying Collection: military memorial service\n\n  preference: main alternate\n\n  title_language: \n\n  creation_date: Not indicated\n\n  creation_place_original_location: Singapore\n\n  inscriptions: \n\n  inscription_language: \n\n  shape: rectangular\n\n  materials_name: paper (fiber product)\n\n  techniques_name: printing (process) photography (process)\n\n  object_colour: black-and-white (colors)\n\n  physical_appearance: This is a black-and-white photograph. It captures a military memorial service on the steps of a building. A row of soldiers in uniform is standing on the steps on the left\n saluting towards the center. There is a portrait at the top of the stairs. A large garland decoration is laid out on the steps in front of it. On the right of the photograph\n four men are carrying a covered object\n possibly a casket.\n\n  subject_terms_1: memorial services resistance movements world wars\n\n  subject_terms_2: Memorial service World War\n 1939-1945 Lim\n Bo Seng\n 1909-1944 Photographs Great Britain. Army. Force 136 Force 136 (Guerilla movement)\n\n  subject_terms_3: 1942-1945 Japanese occupation Photography Lim\n Bo Seng City Hall (Singapore) Force 136 (Guerilla movement) Lung\n Chiu Ying\n\n  subject_terms_4: \n\n  sgcool_label_text: These photographs\n printed images\n pamphlets and clippings belong to Lung Chui Ying and is part of a larger collection related to the World War II underground resistance movement known as Force 136. The collection of materials was gathered by Tan Chong Tee (1916- 2012)\n who was a key member of this resistance group. The collection consists of original materials belonging to Tan and other members of Force 136 dating from the 1940s to new materials reproduced from memory by Tan Chong Tee\n which date from the mid-1990s to early 2000s. \\r\\n\\r\\nForce 136 was set up in July 1942 as part of the British Special Operations Executive (SOE). It recruited and trained local guerillas to gather intelligence and create an underground spy network to support planned British invasion of Japanese-occupied Malaya.\\r\\n\\r\\nLung Chui Ying was a Hainanese born in Johor and recruited as a Force 136 member to fight against the Japanese in Malaya. \\r\\n\n",
  "createdDate": "20201125084526",
  "version": 0,
  "latest": false,
  "roles": [],
  "metadata": {
    "accession_no_csv": "2017-00156-013",
    "Image": "",
    "object_work_type": "black-and-white photographs",
    "title_text": "Lung Chui Ying Collection: Photographs, Printed Images, Pamphlets and Clippings  collected by Lung Chui Ying Lung Chiu Ying Collection: military memorial service",
    "preference": "main alternate",
    "title_language": "",
    "creation_date": "Not indicated",
    "creation_place_original_location": "Singapore",
    "inscriptions": "",
    "inscription_language": "",
    "shape": "rectangular",
    "materials_name": "paper (fiber product)",
    "techniques_name": "printing (process) photography (process)",
    "object_colour": "black-and-white (colors)",
    "physical_appearance": "This is a black-and-white photograph. It captures a military memorial service on the steps of a building. A row of soldiers in uniform is standing on the steps on the left, saluting towards the center. There is a portrait at the top of the stairs. A large garland decoration is laid out on the steps in front of it. On the right of the photograph, four men are carrying a covered object, possibly a casket.",
    "subject_terms_1": "memorial services resistance movements world wars",
    "subject_terms_2": "Memorial service World War, 1939-1945 Lim, Bo Seng, 1909-1944 Photographs Great Britain. Army. Force 136 Force 136 (Guerilla movement)",
    "subject_terms_3": "1942-1945 Japanese occupation Photography Lim, Bo Seng City Hall (Singapore) Force 136 (Guerilla movement) Lung, Chiu Ying",
    "subject_terms_4": "",
    "sgcool_label_text": "These photographs, printed images, pamphlets and clippings belong to Lung Chui Ying and is part of a larger collection related to the World War II underground resistance movement known as Force 136. The collection of materials was gathered by Tan Chong Tee (1916- 2012), who was a key member of this resistance group. The collection consists of original materials belonging to Tan and other members of Force 136 dating from the 1940s to new materials reproduced from memory by Tan Chong Tee, which date from the mid-1990s to early 2000s. \r\n\r\nForce 136 was set up in July 1942 as part of the British Special Operations Executive (SOE). It recruited and trained local guerillas to gather intelligence and create an underground spy network to support planned British invasion of Japanese-occupied Malaya.\r\n\r\nLung Chui Ying was a Hainanese born in Johor and recruited as a Force 136 member to fight against the Japanese in Malaya. \r\n"
  },
  "nlpDate": "20201125084526",
  "connectorId": 0,
  "tags": {}
}