{"id":"2017-00290-001 to 006","title":"A bound journal with bible cover and information on the Malayan Campaign  A bound journal with bible cover and information on the Malayan Campaign","source":"Bumblebee","path":"./Data/json/","content":"accession_no_csv:2017-00290-001 to 006\nImage:\nobject_work_type:notes covers (closure)\ntitle_text:A bound journal with bible cover and information on the Malayan Campaign  A bound journal with bible cover and information on the Malayan Campaign\npreference:alternate main\ntitle_language:\ncreator_2:Lt. Gen. Sir Lewis Heath\ncreator_role:Creator\ncreation_date:1941 - 1945\ncreation_place_original_location:Singapore\ninscriptions:\ninscription_language:\nshape:rectangular\nmaterials_name:paper (fiber product)\ntechniques_name:writing (processes) printing (process)\nobject_colour:brown (colour) multicoloured\nphysical_appearance:A cover of the Bible is displayed. It is brown in colour. The spine of the Bible is a lighter shade of brown than its front cover. The cover of the Bible looks very worn out and there are scratches on its surface. There are also slight tears on its edges.The paper scraps in the Bible are not torn\n but they contain numerous stains. The words are not smudged.\nsubject_terms_1:world wars Bibles soldiers military campaigns\nsubject_terms_2:World War\n 1939 - 1945 Great Britain. Army Notes  Bible\nsubject_terms_3:1942-1945 Japanese occupation Wars\ncontext_1:World War\n 1939 - 1945\ncontext_2:world wars\ncontext_3:1939 - 1945\ncontext_4:1939\ncontext_5:1945\ncontext_6:Southeast Asia\ncontext_7:Southeast Asia\nsgcool_label_text:The journal includes various paper scraps containing information related to the “Selarang incident”\n namely Selarang Special Orders issued by the Colonel and Commander of British and Australian troops which direct troops to sign the Japanese order promising that they will not try to escape. Most interesting of these orders is the assurance that pensions will be ensured upon the P.O.Ws’ release. The journal also includes a message from Major General Beckwith-smith on the unconditional surrender of Singapore as well as Lt. Gen. Sir Lewis Heath’s account of the Malayan campaign. This artefact is part of the archive of James Steele\n Royal Artillery (Field) who served in Malaya from January 1941-February 1942\n when interned as a P.O.W at Changi until his release in October 1945.","createdDate":"20201018182636","version":0,"latest":false,"roles":[],"metadata":{"accession_no_csv":"2017-00290-001 to 006","Image":"","object_work_type":"notes covers (closure)","title_text":"A bound journal with bible cover and information on the Malayan Campaign  A bound journal with bible cover and information on the Malayan Campaign","preference":"alternate main","title_language":"","creator_2":"Lt. Gen. Sir Lewis Heath","creator_role":"Creator","creation_date":"1941 - 1945","creation_place_original_location":"Singapore","inscriptions":"","inscription_language":"","shape":"rectangular","materials_name":"paper (fiber product)","techniques_name":"writing (processes) printing (process)","object_colour":"brown (colour) multicoloured","physical_appearance":"A cover of the Bible is displayed. It is brown in colour. The spine of the Bible is a lighter shade of brown than its front cover. The cover of the Bible looks very worn out and there are scratches on its surface. There are also slight tears on its edges.The paper scraps in the Bible are not torn, but they contain numerous stains. The words are not smudged.","subject_terms_1":"world wars Bibles soldiers military campaigns","subject_terms_2":"World War, 1939 - 1945 Great Britain. Army Notes  Bible","subject_terms_3":"1942-1945 Japanese occupation Wars","context_1":"World War, 1939 - 1945","context_2":"world wars","context_3":"1939 - 1945","context_4":"1939","context_5":"1945","context_6":"Southeast Asia","context_7":"Southeast Asia","sgcool_label_text":"The journal includes various paper scraps containing information related to the “Selarang incident”, namely Selarang Special Orders issued by the Colonel and Commander of British and Australian troops which direct troops to sign the Japanese order promising that they will not try to escape. Most interesting of these orders is the assurance that pensions will be ensured upon the P.O.Ws’ release. The journal also includes a message from Major General Beckwith-smith on the unconditional surrender of Singapore as well as Lt. Gen. Sir Lewis Heath’s account of the Malayan campaign. This artefact is part of the archive of James Steele, Royal Artillery (Field) who served in Malaya from January 1941-February 1942, when interned as a P.O.W at Changi until his release in October 1945."},"nlpDate":"20201018182636","connectorId":0,"tags":{}}