{"id":"2017-00951-002","title":"Tanah Impian (Dream Land) Reblane Model Baru","source":"Bumblebee","path":"./Data/json/","content":"accession_no_csv:2017-00951-002\nImage:\nobject_work_type:screen prints  adaptations (derivative objects)\ntitle_text:Tanah Impian (Dream Land) Reblane Model Baru\npreference:alternate main\ntitle_language:\ncreator_2:Krack Studio\ncreator_role:artists (visual artists)\ncreation_date:2014\ncreation_place_original_location:Indonesia\nstyles_periods_indexing_terms:Contemporary (style of art)\ninscriptions:\ninscription_language:\nshape:Rectangular\nmaterials_name:paper (fiber product)\ntechniques_name:screen printing\nobject_colour:multicoloured\nedition_description:2-Oct\nphysical_appearance:This silkscreen print depicts a series of items ranging from clothing\n shoes\n to rackets. Three biplanes are seen on the top of the print beneath the title. Two sailors are seen on a boat at the bottom right corner.\nsubject_terms_1:identity  nationalism  posters  ways of life  popular culture  appropriation (imagery) redesign advertisements  imports\nsubject_terms_2:Serigraphy Art\n Indonesian Nationalism Identity  Posters  Ways of life Popular culture  Appropriation (Art) Adaptations Advertising  Imports\nsubject_terms_3:Visual arts  National identity  Poster art  Popular culture  Media and advertising\nsgcool_label_text:Tanah Impian (Dream Land) is a series of prints based on images drawn from Indonesian popular culture\n spanning 100 years. The project was conceived in 2014\n the year of the elections in Indonesia when nationalist rhetoric dominated public consciousness\n Artist collective Krack Studio sifted through a mass of research and archival material\n eventually selecting 24 images that referenced the idea of the Indonesian Dream and / or told an interesting story about changing definitions of the ‘Nation’. Ranging from political posters to advertisements\n comic strips\n movie posters and magazines\n these images\n reconstructed and re-imagined by the artist collective\n chronicle Indonesia’s evolving aspirations\n desires and identity\n as well as how Indonesia has been perceived and imaged for the ‘Western’ gaze.","createdDate":"20201018182636","version":0,"latest":false,"roles":[],"metadata":{"accession_no_csv":"2017-00951-002","Image":"","object_work_type":"screen prints  adaptations (derivative objects)","title_text":"Tanah Impian (Dream Land) Reblane Model Baru","preference":"alternate main","title_language":"","creator_2":"Krack Studio","creator_role":"artists (visual artists)","creation_date":"2014","creation_place_original_location":"Indonesia","styles_periods_indexing_terms":"Contemporary (style of art)","inscriptions":"","inscription_language":"","shape":"Rectangular","materials_name":"paper (fiber product)","techniques_name":"screen printing","object_colour":"multicoloured","edition_description":"2-Oct","physical_appearance":"This silkscreen print depicts a series of items ranging from clothing, shoes, to rackets. Three biplanes are seen on the top of the print beneath the title. Two sailors are seen on a boat at the bottom right corner.","subject_terms_1":"identity  nationalism  posters  ways of life  popular culture  appropriation (imagery) redesign advertisements  imports","subject_terms_2":"Serigraphy Art, Indonesian Nationalism Identity  Posters  Ways of life Popular culture  Appropriation (Art) Adaptations Advertising  Imports","subject_terms_3":"Visual arts  National identity  Poster art  Popular culture  Media and advertising","sgcool_label_text":"Tanah Impian (Dream Land) is a series of prints based on images drawn from Indonesian popular culture, spanning 100 years. The project was conceived in 2014, the year of the elections in Indonesia when nationalist rhetoric dominated public consciousness, Artist collective Krack Studio sifted through a mass of research and archival material, eventually selecting 24 images that referenced the idea of the Indonesian Dream and / or told an interesting story about changing definitions of the ‘Nation’. Ranging from political posters to advertisements, comic strips, movie posters and magazines, these images, reconstructed and re-imagined by the artist collective, chronicle Indonesia’s evolving aspirations, desires and identity, as well as how Indonesia has been perceived and imaged for the ‘Western’ gaze."},"nlpDate":"20201018182636","connectorId":0,"tags":{}}