{
  "id": "2017-00075",
  "title": "Hanuman",
  "source": "Bumblebee",
  "path": "./Data/json/",
  "content": "\n  accession_no_csv: 2017-00075\n\n  Image: \n\n  object_work_type: canvas paintings  oil paintings (visual works) religious art\n\n  title_text: Hanuman\n\n  preference: main\n\n  title_language: \n\n  creator_2: Thawan Duchanee (*1939)\n\n  creator_1: Thawan Datchani\n 1939-\n\n  creator_role: artists (visual artists)\n\n  creation_date: 1973\n\n  creation_place_original_location: Thailand\n\n  inscriptions: \n\n  inscription_language: \n\n  shape: Rectangular\n\n  materials_name: oil paint (paint)  canvas (textile material)\n\n  techniques_name: oil painting (technique)  shading  dry-brush painting\n\n  object_colour: multicoloured\n\n  physical_appearance: This central focus of this painting is Hanuman\n a monkey deity featured in the Ramayana. His jaw is ajar\n revealing a set of sharp teeth. Depicted to be on all fours with the exception of his raised right palm\n he tilts his head backwards and stares at the top right corner where a red circle is. Duchanee\\u0027s paint strokes are strong\n decisive and swift. Outlining only certain areas\n he uses a combination of shading techniques to give the body of Hanuman its form. His head is fully coloured\n and his palms have been realistically portrayed.\n\n  subject_terms_1: Hinduism gods (deities)  religious characters folk tales outlines (linear forms)\n\n  subject_terms_2: Hinduism and culture Hindu gods Hanuman Folklore Faith in art\n\n  subject_terms_3: Hinduism Religious life and practices visual arts\n\n  context_1: This painting was part of a solo exhibition held at the British Council in 1973 showing art that depicted characters from the Thai epic Ramakian.\n\n  context_2: exhibitions (events)\n\n  context_3: 1973\n\n  context_4: 1973\n\n  context_5: 1973\n\n  context_6: British Council (Thailand)\n\n  context_7: British Council (Thailand)\n\n  sgcool_label_text: Thawan Duchanee is one of Thailand’s foremost artists and whose vivid and visceral interpretations of Buddhist teachings and visual motifs have won him international acclaim. \\r\\nDespite being an avowed Buddhist\n Thawan has invoked the importance Hinduism has within Thai folk culture with his depiction of Hanuman\n a central figure of the Ramayanan or Ramakien (in Thai). Popularly known as the Monkey God\n Hanuman is in Hindu accounts\n the incarnation or avatar of Shiva and represents divine strength\n power and agility. Here in this painting\n Thawan captures a chapter in the chronicles of Hanuman in which the monkey deity is ravenous with hunger and mistakes the sun for a ripened mango. As he chases the sun\n the god Indra intervenes by striking Hanuman in the jaw\n triggering a saga of retaliation from Hanuman’s father.\\r\\nHanuman was part of a renowned series of 14 paintings shown at his solo exhibition at the British Council in Bangkok in 1973. This work comes from a period just after Thawan’s paintings were slashed by students in 1971 for supposedly desecrating Buddhism as he had juxtaposed erotic\n monstrous forms with the Buddha\n and he was at the time residing at the Student Christian Centre which led to a misconception that Thawan was a sacrilegious Christian railing against Buddhist beliefs. The Ramayana series however did not cause the same controversy of his earlier works because the depicted subjects were monkeys and demons rather than Buddhism.\n",
  "createdDate": "20201120223707",
  "version": 0,
  "latest": false,
  "roles": [],
  "metadata": {
    "accession_no_csv": "2017-00075",
    "Image": "",
    "object_work_type": "canvas paintings  oil paintings (visual works) religious art",
    "title_text": "Hanuman",
    "preference": "main",
    "title_language": "",
    "creator_2": "Thawan Duchanee (*1939)",
    "creator_1": "Thawan Datchani, 1939-",
    "creator_role": "artists (visual artists)",
    "creation_date": "1973",
    "creation_place_original_location": "Thailand",
    "inscriptions": "",
    "inscription_language": "",
    "shape": "Rectangular",
    "materials_name": "oil paint (paint)  canvas (textile material)",
    "techniques_name": "oil painting (technique)  shading  dry-brush painting",
    "object_colour": "multicoloured",
    "physical_appearance": "This central focus of this painting is Hanuman, a monkey deity featured in the Ramayana. His jaw is ajar, revealing a set of sharp teeth. Depicted to be on all fours with the exception of his raised right palm, he tilts his head backwards and stares at the top right corner where a red circle is. Duchanee\u0027s paint strokes are strong, decisive and swift. Outlining only certain areas, he uses a combination of shading techniques to give the body of Hanuman its form. His head is fully coloured, and his palms have been realistically portrayed.",
    "subject_terms_1": "Hinduism gods (deities)  religious characters folk tales outlines (linear forms)",
    "subject_terms_2": "Hinduism and culture Hindu gods Hanuman Folklore Faith in art",
    "subject_terms_3": "Hinduism Religious life and practices visual arts",
    "context_1": "This painting was part of a solo exhibition held at the British Council in 1973 showing art that depicted characters from the Thai epic Ramakian.",
    "context_2": "exhibitions (events)",
    "context_3": "1973",
    "context_4": "1973",
    "context_5": "1973",
    "context_6": "British Council (Thailand)",
    "context_7": "British Council (Thailand)",
    "sgcool_label_text": "Thawan Duchanee is one of Thailand’s foremost artists and whose vivid and visceral interpretations of Buddhist teachings and visual motifs have won him international acclaim. \r\nDespite being an avowed Buddhist, Thawan has invoked the importance Hinduism has within Thai folk culture with his depiction of Hanuman, a central figure of the Ramayanan or Ramakien (in Thai). Popularly known as the Monkey God, Hanuman is in Hindu accounts, the incarnation or avatar of Shiva and represents divine strength, power and agility. Here in this painting, Thawan captures a chapter in the chronicles of Hanuman in which the monkey deity is ravenous with hunger and mistakes the sun for a ripened mango. As he chases the sun, the god Indra intervenes by striking Hanuman in the jaw, triggering a saga of retaliation from Hanuman’s father.\r\nHanuman was part of a renowned series of 14 paintings shown at his solo exhibition at the British Council in Bangkok in 1973. This work comes from a period just after Thawan’s paintings were slashed by students in 1971 for supposedly desecrating Buddhism as he had juxtaposed erotic, monstrous forms with the Buddha, and he was at the time residing at the Student Christian Centre which led to a misconception that Thawan was a sacrilegious Christian railing against Buddhist beliefs. The Ramayana series however did not cause the same controversy of his earlier works because the depicted subjects were monkeys and demons rather than Buddhism."
  },
  "nlpDate": "20201120223707",
  "connectorId": 0,
  "tags": {}
}