{
  "id": "2017-00262",
  "title": "Blue and white dish with aster pattern",
  "source": "Bumblebee",
  "path": "./Data/json/",
  "content": "\n  accession_no_csv: 2017-00262\n\n  Image: \n\n  object_work_type: porcelain (visual works)  dishes (object genre)  Ceramics (object genre)\n\n  title_text: Blue and white dish with aster pattern\n\n  preference: main\n\n  title_language: \n\n  creation_date: Qing dynasty\n late 17th or early 18th century\n\n  creation_place_original_location: China\n\n  styles_periods_indexing_terms: Qing (dynastic styles and periods)  Chinese ceramics styles\n\n  inscriptions: \n\n  inscription_language: \n\n  shape: concave\n\n  materials_name: blue-and-white (ceramic glaze) porcelain (material)  cobalt blue (pigment)  clay  ceramic glaze\n\n  techniques_name: glazing (coating process)  throwing (pottery techniques)  underglazing molding (forming)  firing (technique)  stamping (marking)\n\n  object_colour: multicoloured\n\n  physical_appearance: \\This is a Qing dynasty dish and its interior is decorated with the \\\\China aster\\\\ pattern. While the outer rim consists of repeated asters divided by a thin free-handed stroke\n\n  subject_terms_1: the center of the dish is comprised of five aster flower heads surrounded by repeated swirl motifs. A leaf motif as well as three stickers and its accession number can be found on the underside of the dish. \\ symbolism  floral patterns  stamps (marks)\n\n  subject_terms_2: repeated motif China aster Porcelain\n Chinese Ming- Qing dynasties\n 1368-1912 China painting\n\n  subject_terms_3: Blue and white ware China Decorative arts Ceramics\n\n  subject_terms_4: visual arts\n\n  context_1: \n\n  context_2: It was exhibited at the Exhibition of Chinese Blue-and-White Ceramics held at the National Museum of Singapore in 1978.\n\n  context_3: exhibitions (events)\n\n  context_4: Apr-78\n\n  context_5: 18-Apr-78\n\n  context_6: 18-Apr-78\n\n  context_7: National Museum of Singapore\n\n  context_8: National Museum (Singapore) curators\n\n  context_9: planners\n",
  "createdDate": "20201120223707",
  "version": 0,
  "latest": false,
  "roles": [],
  "metadata": {
    "accession_no_csv": "2017-00262",
    "Image": "",
    "object_work_type": "porcelain (visual works)  dishes (object genre)  Ceramics (object genre)",
    "title_text": "Blue and white dish with aster pattern",
    "preference": "main",
    "title_language": "",
    "creation_date": "Qing dynasty, late 17th or early 18th century",
    "creation_place_original_location": "China",
    "styles_periods_indexing_terms": "Qing (dynastic styles and periods)  Chinese ceramics styles",
    "inscriptions": "",
    "inscription_language": "",
    "shape": "concave",
    "materials_name": "blue-and-white (ceramic glaze) porcelain (material)  cobalt blue (pigment)  clay  ceramic glaze",
    "techniques_name": "glazing (coating process)  throwing (pottery techniques)  underglazing molding (forming)  firing (technique)  stamping (marking)",
    "object_colour": "multicoloured",
    "physical_appearance": "\"This is a Qing dynasty dish and its interior is decorated with the \"\"China aster\"\" pattern. While the outer rim consists of repeated asters divided by a thin free-handed stroke",
    "subject_terms_1": "the center of the dish is comprised of five aster flower heads surrounded by repeated swirl motifs. A leaf motif as well as three stickers and its accession number can be found on the underside of the dish. \" symbolism  floral patterns  stamps (marks)",
    "subject_terms_2": "repeated motif China aster Porcelain, Chinese Ming- Qing dynasties, 1368-1912 China painting",
    "subject_terms_3": "Blue and white ware China Decorative arts Ceramics",
    "subject_terms_4": "visual arts",
    "context_1": "",
    "context_2": "It was exhibited at the Exhibition of Chinese Blue-and-White Ceramics held at the National Museum of Singapore in 1978.",
    "context_3": "exhibitions (events)",
    "context_4": "Apr-78",
    "context_5": "18-Apr-78",
    "context_6": "18-Apr-78",
    "context_7": "National Museum of Singapore",
    "context_8": "National Museum (Singapore) curators",
    "context_9": "planners"
  },
  "nlpDate": "20201120223707",
  "connectorId": 0,
  "tags": {}
}