{"id":"2017-00619","title":"Pair of Chased \u0026 Gadrooned Silver Bowls (Batil) Chased \u0026 Gadrooned Silver Bowls (Batil)","source":"Bumblebee","path":"./Data/json/","content":"accession_no_csv:2017-00619\nImage:\nobject_work_type:bowls\ntitle_text:Pair of Chased \\u0026 Gadrooned Silver Bowls (Batil) Chased \\u0026 Gadrooned Silver Bowls (Batil)\npreference:alternate main\ntitle_language:\ncreation_date:circa 1900\ncreation_place_original_location:Brunei\ninscriptions:\ninscription_language:\nshape:hemispherical\nmaterials_name:silver (metal)\ntechniques_name:forging (metal forming) engraving (action)\nobject_colour:silver (color)\nphysical_appearance:This is a pair of silver engraved bowls. Each bowl is engraved with a foliage and petal border\n with a decorative edging down the body. The inner edge of the bowl are also decorated with engravings of foliage and petal scrolls. There are no scratches seen on the bowls.\nsubject_terms_1:foliage (motif) scrolls (motifs) tableware\nsubject_terms_2:Silver bowls Motifs Tableware\nsubject_terms_3:Malay decorative arts\nsubject_terms_4:","createdDate":"20201119143406","version":0,"latest":false,"roles":[],"metadata":{"accession_no_csv":"2017-00619","Image":"","object_work_type":"bowls","title_text":"Pair of Chased \u0026 Gadrooned Silver Bowls (Batil) Chased \u0026 Gadrooned Silver Bowls (Batil)","preference":"alternate main","title_language":"","creation_date":"circa 1900","creation_place_original_location":"Brunei","inscriptions":"","inscription_language":"","shape":"hemispherical","materials_name":"silver (metal)","techniques_name":"forging (metal forming) engraving (action)","object_colour":"silver (color)","physical_appearance":"This is a pair of silver engraved bowls. Each bowl is engraved with a foliage and petal border, with a decorative edging down the body. The inner edge of the bowl are also decorated with engravings of foliage and petal scrolls. There are no scratches seen on the bowls.","subject_terms_1":"foliage (motif) scrolls (motifs) tableware","subject_terms_2":"Silver bowls Motifs Tableware","subject_terms_3":"Malay decorative arts","subject_terms_4":""},"nlpDate":"20201119143406","connectorId":0,"tags":{}}