{
  "id": "2017-00021",
  "title": "Labourer  Worker",
  "source": "Bumblebee",
  "path": "./Data/json/",
  "content": "\n  accession_no_csv: 2017-00021\n\n  Image: \n\n  object_work_type: black-and-white prints (photographs) gelatin silver prints  photographic prints\n\n  title_text: Labourer  Worker\n\n  preference: alternate  main\n\n  title_language: \n\n  creator_2: Koon\n Sang Ho\n\n  creator_role: photographers\n\n  creation_date: c.1958\n\n  creation_place_original_location: Singapore\n\n  inscriptions: \n\n  inscription_language: \n\n  shape: rectangular\n\n  materials_name: gelatin  paper (fibre product)  silver sulfide  baryta paper\n\n  techniques_name: gelatin silver process photographic printing techniques black-and-white photography\n\n  object_colour: black-and-white (colours)\n\n  physical_appearance: An upright ladder cuts across the image. To its right lies a raised wooden plank\n where a man in cap sits with his left leg raised. He anchors this stance by supporting himself with a plank. The man is fellow artist\n Yip Cheong Fan. A long shadow of the ladder is casted to the left of the image. On the verso\n there is a Biennale Di Genova chop\n as well as the artist\\u0027s photography studio chop and title of work.\n\n  subject_terms_1: construction sites constructing  construction workers shadows  stylized portraits\n\n  subject_terms_2: Photography\n Artistic  Construction Workers Portrait photography  Yip\n Cheong Fun\n 1903-1989 Royal Photographic Society of Great Britain\n\n  subject_terms_3: visual arts  Artistic photography  Building and Construction  Yip\n Cheong Fun\n\n  context_1: Biennale Di Genova International Focus Salon Amsterdam\n\n  context_2: biennials (exhibitions)  exhibitions (events)\n\n  context_3: NA NA\n\n  context_4: NA NA\n\n  context_5: NA NA\n\n  context_6: Genoa (Italy)  Bloemendaal (North Holland\n Netherlands)\n\n  context_7: Biennale Di Genova  International Focus Salon Amsterdam\n\n  context_8: planners planners\n\n  context_20: Address indicated on photography studio\\u0027s chop.\n\n  context_21: 40 Holloway  Lane\n Singapore 7\n\n  context_22: c.1958\n\n  context_23: 1953\n\n  context_24: 1963\n\n  sgcool_label_text: Ho Koon Sang was a member of the Photographic Society of Singapore and an Associate of the Royal Photographic Society in London. These photos are typical of the salon photography style of the time\n with an emphasis on technique\n composition and tone. The subject in this photo is fellow photographer Yip Cheong Fun.\n",
  "createdDate": "20201120223707",
  "version": 0,
  "latest": false,
  "roles": [],
  "metadata": {
    "accession_no_csv": "2017-00021",
    "Image": "",
    "object_work_type": "black-and-white prints (photographs) gelatin silver prints  photographic prints",
    "title_text": "Labourer  Worker",
    "preference": "alternate  main",
    "title_language": "",
    "creator_2": "Koon, Sang Ho",
    "creator_role": "photographers",
    "creation_date": "c.1958",
    "creation_place_original_location": "Singapore",
    "inscriptions": "",
    "inscription_language": "",
    "shape": "rectangular",
    "materials_name": "gelatin  paper (fibre product)  silver sulfide  baryta paper",
    "techniques_name": "gelatin silver process photographic printing techniques black-and-white photography",
    "object_colour": "black-and-white (colours)",
    "physical_appearance": "An upright ladder cuts across the image. To its right lies a raised wooden plank, where a man in cap sits with his left leg raised. He anchors this stance by supporting himself with a plank. The man is fellow artist, Yip Cheong Fan. A long shadow of the ladder is casted to the left of the image. On the verso, there is a Biennale Di Genova chop, as well as the artist\u0027s photography studio chop and title of work.",
    "subject_terms_1": "construction sites constructing  construction workers shadows  stylized portraits",
    "subject_terms_2": "Photography, Artistic  Construction Workers Portrait photography  Yip, Cheong Fun, 1903-1989 Royal Photographic Society of Great Britain",
    "subject_terms_3": "visual arts  Artistic photography  Building and Construction  Yip, Cheong Fun",
    "context_1": "Biennale Di Genova International Focus Salon Amsterdam",
    "context_2": "biennials (exhibitions)  exhibitions (events)",
    "context_3": "NA NA",
    "context_4": "NA NA",
    "context_5": "NA NA",
    "context_6": "Genoa (Italy)  Bloemendaal (North Holland, Netherlands)",
    "context_7": "Biennale Di Genova  International Focus Salon Amsterdam",
    "context_8": "planners planners",
    "context_20": "Address indicated on photography studio\u0027s chop.",
    "context_21": "40 Holloway  Lane, Singapore 7",
    "context_22": "c.1958",
    "context_23": "1953",
    "context_24": "1963",
    "sgcool_label_text": "Ho Koon Sang was a member of the Photographic Society of Singapore and an Associate of the Royal Photographic Society in London. These photos are typical of the salon photography style of the time, with an emphasis on technique, composition and tone. The subject in this photo is fellow photographer Yip Cheong Fun."
  },
  "nlpDate": "20201120223707",
  "connectorId": 0,
  "tags": {}
}