{
  "id": "2017-00175",
  "title": "Materials on Lim Bo Seng: Singapore Chinese Chamber of Commerce \u0026 Industry letter",
  "source": "Bumblebee",
  "path": "./Data/json/",
  "content": "\n  accession_no_csv: 2017-00175\n\n  Image: \n\n  object_work_type: letters (correspondence)\n\n  title_text: Materials on Lim Bo Seng: Singapore Chinese Chamber of Commerce \\u0026 Industry letter\n\n  preference: main alternate\n\n  title_language: \n\n  creator_2: Caroline Ee-Lee Sook Chin (?)\n\n  creator_role: authors\n\n  creation_date: Not indicated\n\n  creation_place_original_location: Singapore\n\n  inscriptions: \n\n  inscription_language: \n\n  shape: rectangular\n\n  materials_name: paper (fiber product)\n\n  techniques_name: printing (process) writing (processes)\n\n  object_colour: black-and-white (colors)\n\n  physical_appearance: This is a printed letter. It consists of a company logo\n name and contact details printed at the top of the document. The logo is of a tall building with roofed gate. The letter contains a reply slip as a segment at the bottom. The signature is printed in the center\n on the left. The two pages are identical.\n\n  subject_terms_1: memorial services anniversaries resistance movements documents (object genre) world wars\n\n  subject_terms_2: Anniversaries World War\n 1939-1945 Lim\n Bo Seng\n 1909-1944 Chen\n Chongzhi\n 1916- Singapore Chinese Chamber of Commerce \\u0026 Industry Great Britain. Army. Force 136 Letters Force 136 (Guerilla movement) Memorials\n\n  subject_terms_3: 1942-1945 Japanese occupation Tan\n Chong Tee Singapore Chinese Chamber of Commerce \\u0026 Industry Lim\n Bo Seng Letters Force 136 (Guerilla movement) war personalities\n\n  subject_terms_4: \n\n  sgcool_label_text: These materials regarding Lim Bo Seng belongs to part of a collection of artefacts related to the World War II underground resistance movement known as Force 136. The collection of materials was gathered by Tan Chong Tee (1916- 2012)\n who was a key member of this resistance group. The collection consists of original materials belonging to Tan and other members of Force 136 dating from the 1940s to new materials reproduced from memory by Tan Chong Tee\n which date from the late 1980s to early 2000s. \\r\\n\\r\\nForce 136 was set up in July 1942 as part of the British Special Operations Executive (SOE). It recruited and trained local guerillas to gather intelligence and create an underground spy network to support planned British invasion of Japanese-occupied Malaya.\n",
  "createdDate": "20201125084525",
  "version": 0,
  "latest": false,
  "roles": [],
  "metadata": {
    "accession_no_csv": "2017-00175",
    "Image": "",
    "object_work_type": "letters (correspondence)",
    "title_text": "Materials on Lim Bo Seng: Singapore Chinese Chamber of Commerce \u0026 Industry letter",
    "preference": "main alternate",
    "title_language": "",
    "creator_2": "Caroline Ee-Lee Sook Chin (?)",
    "creator_role": "authors",
    "creation_date": "Not indicated",
    "creation_place_original_location": "Singapore",
    "inscriptions": "",
    "inscription_language": "",
    "shape": "rectangular",
    "materials_name": "paper (fiber product)",
    "techniques_name": "printing (process) writing (processes)",
    "object_colour": "black-and-white (colors)",
    "physical_appearance": "This is a printed letter. It consists of a company logo, name and contact details printed at the top of the document. The logo is of a tall building with roofed gate. The letter contains a reply slip as a segment at the bottom. The signature is printed in the center, on the left. The two pages are identical.",
    "subject_terms_1": "memorial services anniversaries resistance movements documents (object genre) world wars",
    "subject_terms_2": "Anniversaries World War, 1939-1945 Lim, Bo Seng, 1909-1944 Chen, Chongzhi, 1916- Singapore Chinese Chamber of Commerce \u0026 Industry Great Britain. Army. Force 136 Letters Force 136 (Guerilla movement) Memorials",
    "subject_terms_3": "1942-1945 Japanese occupation Tan, Chong Tee Singapore Chinese Chamber of Commerce \u0026 Industry Lim, Bo Seng Letters Force 136 (Guerilla movement) war personalities",
    "subject_terms_4": "",
    "sgcool_label_text": "These materials regarding Lim Bo Seng belongs to part of a collection of artefacts related to the World War II underground resistance movement known as Force 136. The collection of materials was gathered by Tan Chong Tee (1916- 2012), who was a key member of this resistance group. The collection consists of original materials belonging to Tan and other members of Force 136 dating from the 1940s to new materials reproduced from memory by Tan Chong Tee, which date from the late 1980s to early 2000s. \r\n\r\nForce 136 was set up in July 1942 as part of the British Special Operations Executive (SOE). It recruited and trained local guerillas to gather intelligence and create an underground spy network to support planned British invasion of Japanese-occupied Malaya."
  },
  "nlpDate": "20201125084525",
  "connectorId": 0,
  "tags": {}
}