{"id":"2017-00156-018","title":"Lung Chui Ying Collection: Photographs, Printed Images, Pamphlets and Clippings  collected by Lung Chui Ying ?????\r\n Lung Chui Ying Collection: Photograph of Side View Of The National College of Art Dormitory  ?????????????.?????????????(???)","source":"Bumblebee","path":"./Data/json/","content":"accession_no_csv:2017-00156-018\nImage:\nobject_work_type:black-and-white photographs photographs\ntitle_text:Lung Chui Ying Collection: Photographs\n Printed Images\n Pamphlets and Clippings  collected by Lung Chui Ying ?????\\r\\n Lung Chui Ying Collection: Photograph of Side View Of The National College of Art Dormitory  ?????????????.?????????????(???)\npreference:alternate  alternate main alternate\ntitle_language:\ncreation_date:Not indicated\ncreation_place_original_location:Singapore  China Hunan Sheng (China)\ninscriptions:\ninscription_language:\nshape:Rectangular\nmaterials_name:paper (fiber product)\ntechniques_name:black-and-white photography  printing (process) handwriting\nobject_colour:black-and-white (colors)\nphysical_appearance:This is a black and white photograph of the side view of a building. There are four individuals standing in front of the buliding. The photograph is yellowed\n faded\n and weathered along its edges.\nsubject_terms_1:resistance movements guerilla warfare local histories armed forces  Chinese scripts world wars side views  dormitories\nsubject_terms_2:Great Britain. Army. Force 136 Force 136 (Guerilla movement) Photographs Armed Forces  War resistance movements  Guerillas  Writing  Chinese characters  Local history Armed Forces  World War\n 1939-1945 Dormitories\nsubject_terms_3:Force 136 (Guerilla movement) Lung\n Chiu Ying History  1942-1945 Japanese Occupation\nsgcool_label_text:These photographs\n printed images\n pamphlets and clippings belong to Lung Chui Ying and is part of a larger collection related to the World War II underground resistance movement known as Force 136. The collection of materials was gathered by Tan Chong Tee (1916- 2012)\n who was a key member of this resistance group. The collection consists of original materials belonging to Tan and other members of Force 136 dating from the 1940s to new materials reproduced from memory by Tan Chong Tee\n which date from the mid-1990s to early 2000s. \\r\\n\\r\\nForce 136 was set up in July 1942 as part of the British Special Operations Executive (SOE). It recruited and trained local guerillas to gather intelligence and create an underground spy network to support planned British invasion of Japanese-occupied Malaya.\\r\\n\\r\\nLung Chui Ying was a Hainanese born in Johor and recruited as a Force 136 member to fight against the Japanese in Malaya.","createdDate":"20201119143406","version":0,"latest":false,"roles":[],"metadata":{"accession_no_csv":"2017-00156-018","Image":"","object_work_type":"black-and-white photographs photographs","title_text":"Lung Chui Ying Collection: Photographs, Printed Images, Pamphlets and Clippings  collected by Lung Chui Ying ?????\r\n Lung Chui Ying Collection: Photograph of Side View Of The National College of Art Dormitory  ?????????????.?????????????(???)","preference":"alternate  alternate main alternate","title_language":"","creation_date":"Not indicated","creation_place_original_location":"Singapore  China Hunan Sheng (China)","inscriptions":"","inscription_language":"","shape":"Rectangular","materials_name":"paper (fiber product)","techniques_name":"black-and-white photography  printing (process) handwriting","object_colour":"black-and-white (colors)","physical_appearance":"This is a black and white photograph of the side view of a building. There are four individuals standing in front of the buliding. The photograph is yellowed, faded, and weathered along its edges.","subject_terms_1":"resistance movements guerilla warfare local histories armed forces  Chinese scripts world wars side views  dormitories","subject_terms_2":"Great Britain. Army. Force 136 Force 136 (Guerilla movement) Photographs Armed Forces  War resistance movements  Guerillas  Writing  Chinese characters  Local history Armed Forces  World War, 1939-1945 Dormitories","subject_terms_3":"Force 136 (Guerilla movement) Lung, Chiu Ying History  1942-1945 Japanese Occupation","sgcool_label_text":"These photographs, printed images, pamphlets and clippings belong to Lung Chui Ying and is part of a larger collection related to the World War II underground resistance movement known as Force 136. The collection of materials was gathered by Tan Chong Tee (1916- 2012), who was a key member of this resistance group. The collection consists of original materials belonging to Tan and other members of Force 136 dating from the 1940s to new materials reproduced from memory by Tan Chong Tee, which date from the mid-1990s to early 2000s. \r\n\r\nForce 136 was set up in July 1942 as part of the British Special Operations Executive (SOE). It recruited and trained local guerillas to gather intelligence and create an underground spy network to support planned British invasion of Japanese-occupied Malaya.\r\n\r\nLung Chui Ying was a Hainanese born in Johor and recruited as a Force 136 member to fight against the Japanese in Malaya."},"nlpDate":"20201119143406","connectorId":0,"tags":{}}