{"id":"2017-00299","title":"122 Field Regiment Royal Artillery’s involvement in the Malayan Campaign Drawing memorializing 122 Field Regiment Royal Artillery’s involvement in the Malayan Campaign","source":"Bumblebee","path":"./Data/json/","content":"accession_no_csv:2017-00299\nImage:\nobject_work_type:sketches\ntitle_text:122 Field Regiment Royal Artillery’s involvement in the Malayan Campaign Drawing memorializing 122 Field Regiment Royal Artillery’s involvement in the Malayan Campaign\npreference:alternate main\ntitle_language:\ncreator_2:James Steele\n Royal Artillery (Field)\ncreator_role:Creator\ncreation_date:1941 - 1945\ncreation_place_original_location:Singapore\ninscriptions:\ninscription_language:\nshape:rectangular\nmaterials_name:paper (fiber product)\ntechniques_name:drawing (image-making)\nobject_colour:multicoloured\nphysical_appearance:The drawing is made on a piece of paper that has been torn on its bottom right side and the upper left corner. The drawing depicts the military insignia of the 122 Field Regiment Royal Artillery. It also includes the names of places where the Regiment fought at during the Malayan Campaign in World War II. The paper does not look creased. The location where the drawing is created is also stated at the bottom centre.\nsubject_terms_1:world wars prisoners of war prisoner-of-war camps commemoratives\nsubject_terms_2:World War\n 1939 - 1945 Great Britain. Army Prisoner of war Prisoner-of-war camps Drawing Changi POW Camp (Changi\n Singapore)\nsubject_terms_3:1942-1945 Japanese occupation Wars\ncontext_1:World War\n 1939 - 1945\ncontext_2:world wars\ncontext_3:1939 - 1945\ncontext_4:1939\ncontext_5:1945\ncontext_6:Southeast Asia\ncontext_7:Southeast Asia\nsgcool_label_text:\\A drawing that memorializes the involvement of the 122 Field Regiment Royal Artillery in the Malayan Campaign\n this diagram includes all the areas in which they fought during the campaign and their motto” Quo Fas Et Gloria Ducunt” (\\\\Where Right And Glory Lead\\\\; in Latin fas implies \\\\sacred duty\\\\). This is a particularly important historical document. Effectively","createdDate":"20201119143406","version":0,"latest":false,"roles":[],"metadata":{"accession_no_csv":"2017-00299","Image":"","object_work_type":"sketches","title_text":"122 Field Regiment Royal Artillery’s involvement in the Malayan Campaign Drawing memorializing 122 Field Regiment Royal Artillery’s involvement in the Malayan Campaign","preference":"alternate main","title_language":"","creator_2":"James Steele, Royal Artillery (Field)","creator_role":"Creator","creation_date":"1941 - 1945","creation_place_original_location":"Singapore","inscriptions":"","inscription_language":"","shape":"rectangular","materials_name":"paper (fiber product)","techniques_name":"drawing (image-making)","object_colour":"multicoloured","physical_appearance":"The drawing is made on a piece of paper that has been torn on its bottom right side and the upper left corner. The drawing depicts the military insignia of the 122 Field Regiment Royal Artillery. It also includes the names of places where the Regiment fought at during the Malayan Campaign in World War II. The paper does not look creased. The location where the drawing is created is also stated at the bottom centre.","subject_terms_1":"world wars prisoners of war prisoner-of-war camps commemoratives","subject_terms_2":"World War, 1939 - 1945 Great Britain. Army Prisoner of war Prisoner-of-war camps Drawing Changi POW Camp (Changi, Singapore)","subject_terms_3":"1942-1945 Japanese occupation Wars","context_1":"World War, 1939 - 1945","context_2":"world wars","context_3":"1939 - 1945","context_4":"1939","context_5":"1945","context_6":"Southeast Asia","context_7":"Southeast Asia","sgcool_label_text":"\"A drawing that memorializes the involvement of the 122 Field Regiment Royal Artillery in the Malayan Campaign, this diagram includes all the areas in which they fought during the campaign and their motto” Quo Fas Et Gloria Ducunt” (\"\"Where Right And Glory Lead\"\"; in Latin fas implies \"\"sacred duty\"\"). This is a particularly important historical document. Effectively"},"nlpDate":"20201119143406","connectorId":0,"tags":{}}