{
  "id": "2017-00921",
  "title": "No. 4 Cartridge Kodak",
  "source": "Bumblebee",
  "path": "./Data/json/",
  "content": "\n  accession_no_csv: 2017-00921\n\n  Image: \n\n  object_work_type: folding cameras\n\n  title_text: No. 4 Cartridge Kodak\n\n  preference: main\n\n  title_language: \n\n  creator_2: Kodak (?)\n\n  creator_1: Eastman Kodak Company\n\n  creator_role: manufacturers\n\n  creation_date: 1897\n\n  creation_place_original_location: United States\n\n  inscriptions: \n\n  inscription_language: \n\n  shape: irregular\n\n  materials_name: glass (material) metal\n\n  object_colour: black (color)\n\n  physical_appearance: This is a Cartridge Kodak roll film camera. It is closed in a form of a rectangular box\n with a handle attached at the top. The front of the camera has a lid at the front that can be opened outwards to reveal the lens and view finder. The body of the camera is covered in black leather.\n\n  subject_terms_1: vintage (period) photography (discipline) cameras (photographic equipment)\n\n  subject_terms_2: Photography Cameras Kodak camera Vintage\n\n  subject_terms_3: Photography\n\n  sgcool_label_text: This is a Cartridge Kodak roll film camera with rubber pneumatic bulb and film spool. Before the advent of the portable camera in the late 19th century\n the taking of photographs was limited to the studio. However portable cameras remained affordable only to the rich until the first decades of the 20th century.\n",
  "createdDate": "20201125084515",
  "version": 0,
  "latest": false,
  "roles": [],
  "metadata": {
    "accession_no_csv": "2017-00921",
    "Image": "",
    "object_work_type": "folding cameras",
    "title_text": "No. 4 Cartridge Kodak",
    "preference": "main",
    "title_language": "",
    "creator_2": "Kodak (?)",
    "creator_1": "Eastman Kodak Company",
    "creator_role": "manufacturers",
    "creation_date": "1897",
    "creation_place_original_location": "United States",
    "inscriptions": "",
    "inscription_language": "",
    "shape": "irregular",
    "materials_name": "glass (material) metal",
    "object_colour": "black (color)",
    "physical_appearance": "This is a Cartridge Kodak roll film camera. It is closed in a form of a rectangular box, with a handle attached at the top. The front of the camera has a lid at the front that can be opened outwards to reveal the lens and view finder. The body of the camera is covered in black leather.",
    "subject_terms_1": "vintage (period) photography (discipline) cameras (photographic equipment)",
    "subject_terms_2": "Photography Cameras Kodak camera Vintage",
    "subject_terms_3": "Photography",
    "sgcool_label_text": "This is a Cartridge Kodak roll film camera with rubber pneumatic bulb and film spool. Before the advent of the portable camera in the late 19th century, the taking of photographs was limited to the studio. However portable cameras remained affordable only to the rich until the first decades of the 20th century."
  },
  "nlpDate": "20201125084515",
  "connectorId": 0,
  "tags": {}
}