{"id":"2017-00652","title":"Cushion cover","source":"Bumblebee","path":"./Data/json/","content":"accession_no_csv:2017-00652\nImage:\nobject_work_type:coverings for soft furnishings\ntitle_text:Cushion cover\npreference:main\ntitle_language:\ncreation_date:20th century\ncreation_place_original_location:Gujarat (India)\ninscriptions:\ninscription_language:\nshape:square (shape)\nmaterials_name:glass (material) textile materials\ntechniques_name:sewing (needleworking technique) embroidering\nobject_colour:multicolored\nphysical_appearance:This is a cushion cover. It is square in shape\n with a multicolored geometric scrolling border\n and a cotton weave in the center.  The cotton weave features a stylized embroidery of two parrots and two peacocks facing each other\n with a potted plant in the middleand four small animals alongside them.\nsubject_terms_1:embroidery (visual works) flower (motif) birds (motifs) beadwork (visual works) cushions\nsubject_terms_2:Pillowcases Embroidery Motifs Cushions\nsubject_terms_3:Textile art and design\nsubject_terms_4:","createdDate":"20201119143406","version":0,"latest":false,"roles":[],"metadata":{"accession_no_csv":"2017-00652","Image":"","object_work_type":"coverings for soft furnishings","title_text":"Cushion cover","preference":"main","title_language":"","creation_date":"20th century","creation_place_original_location":"Gujarat (India)","inscriptions":"","inscription_language":"","shape":"square (shape)","materials_name":"glass (material) textile materials","techniques_name":"sewing (needleworking technique) embroidering","object_colour":"multicolored","physical_appearance":"This is a cushion cover. It is square in shape, with a multicolored geometric scrolling border, and a cotton weave in the center.  The cotton weave features a stylized embroidery of two parrots and two peacocks facing each other, with a potted plant in the middleand four small animals alongside them.","subject_terms_1":"embroidery (visual works) flower (motif) birds (motifs) beadwork (visual works) cushions","subject_terms_2":"Pillowcases Embroidery Motifs Cushions","subject_terms_3":"Textile art and design","subject_terms_4":""},"nlpDate":"20201119143406","connectorId":0,"tags":{}}