{
  "id": "2017-00161",
  "title": "Lee Shao Meng Collection: Letter",
  "source": "Bumblebee",
  "path": "./Data/json/",
  "content": "\n  accession_no_csv: 2017-00161\n\n  Image: \n\n  object_work_type: letters (correspondence)\n\n  title_text: Lee Shao Meng Collection: Letter\n\n  preference: main alternate\n\n  title_language: \n\n  creation_date: Not indicated\n\n  creation_place_original_location: Singapore\n\n  inscriptions: \n\n  inscription_language: \n\n  shape: rectangular\n\n  materials_name: paper (fiber product)\n\n  techniques_name: writing (processes)\n\n  object_colour: multicolored\n\n  physical_appearance: This is a handwritten letter. It consists of two pages\n handwritten in black ink against a template printed in red. The letter is written in Chinese\n in vertical columns. The edges of the pages are slightly torn .\n\n  subject_terms_1: resistance movements documents (object genre) world wars Chinese scripts handwriting\n\n  subject_terms_2: World War\n 1939-1945 Great Britain. Army. Force 136 Letters Force 136 (Guerilla movement) Writing\n\n  subject_terms_3: 1942-1945 Japanese occupation Letters Force 136 (Guerilla movement) Lee\n Shao Meng\n\n  subject_terms_4: \n\n  context_1: World War\n 1939-1945 1942-1945 Japanese Occupation\n\n  context_2: occupations (armed conflicts) world wars\n\n  context_3: 1942-1945 1939-1945\n\n  context_4: 1939 1942\n\n  context_5: 1945\n\n  context_6: Singapore Malaya\n\n  context_7: Great Britain. Army. Force 136\n\n  context_8: armed forces\n\n  sgcool_label_text: This letter belongs to part of a collection of artefacts related to the World War II underground resistance movement known as Force 136. The collection of materials was gathered by Tan Chong Tee (1916- 2012)\n who was a key member of this resistance group. The collection consists of original materials belonging to Tan and other members of Force 136 dating from the 1940s to new materials reproduced from memory by Tan Chong Tee\n which date from the late 1980s to early 2000s. \\r\\n\\r\\nForce 136 was set up in July 1942 as part of the British Special Operations Executive (SOE). It recruited and trained local guerillas to gather intelligence and create an underground spy network to support planned British invasion of Japanese-occupied Malaya.\\r\\n\\r\\nLee Shao Meng was the wife of Tan Chong Tee and was also involved in the war resistance movement in Malaya against the Japanese.\\r\\n\n",
  "createdDate": "20201201203308",
  "version": 0,
  "latest": false,
  "roles": [],
  "metadata": {
    "accession_no_csv": "2017-00161",
    "Image": "",
    "object_work_type": "letters (correspondence)",
    "title_text": "Lee Shao Meng Collection: Letter",
    "preference": "main alternate",
    "title_language": "",
    "creation_date": "Not indicated",
    "creation_place_original_location": "Singapore",
    "inscriptions": "",
    "inscription_language": "",
    "shape": "rectangular",
    "materials_name": "paper (fiber product)",
    "techniques_name": "writing (processes)",
    "object_colour": "multicolored",
    "physical_appearance": "This is a handwritten letter. It consists of two pages, handwritten in black ink against a template printed in red. The letter is written in Chinese, in vertical columns. The edges of the pages are slightly torn .",
    "subject_terms_1": "resistance movements documents (object genre) world wars Chinese scripts handwriting",
    "subject_terms_2": "World War, 1939-1945 Great Britain. Army. Force 136 Letters Force 136 (Guerilla movement) Writing",
    "subject_terms_3": "1942-1945 Japanese occupation Letters Force 136 (Guerilla movement) Lee, Shao Meng",
    "subject_terms_4": "",
    "context_1": "World War, 1939-1945 1942-1945 Japanese Occupation",
    "context_2": "occupations (armed conflicts) world wars",
    "context_3": "1942-1945 1939-1945",
    "context_4": "1939 1942",
    "context_5": "1945",
    "context_6": "Singapore Malaya",
    "context_7": "Great Britain. Army. Force 136",
    "context_8": "armed forces",
    "sgcool_label_text": "This letter belongs to part of a collection of artefacts related to the World War II underground resistance movement known as Force 136. The collection of materials was gathered by Tan Chong Tee (1916- 2012), who was a key member of this resistance group. The collection consists of original materials belonging to Tan and other members of Force 136 dating from the 1940s to new materials reproduced from memory by Tan Chong Tee, which date from the late 1980s to early 2000s. \r\n\r\nForce 136 was set up in July 1942 as part of the British Special Operations Executive (SOE). It recruited and trained local guerillas to gather intelligence and create an underground spy network to support planned British invasion of Japanese-occupied Malaya.\r\n\r\nLee Shao Meng was the wife of Tan Chong Tee and was also involved in the war resistance movement in Malaya against the Japanese.\r\n"
  },
  "nlpDate": "20201201203308",
  "connectorId": 0,
  "tags": {}
}