{
  "id": "2017-00282-001 and 002",
  "title": "The Supreme Goddess as a pouring vessel symbol",
  "source": "Bumblebee",
  "path": "./Data/json/",
  "content": "\n  accession_no_csv: 2017-00282-001 and 002\n\n  Image: \n\n  object_work_type: ceremonial vessels copperwork (visual works)\n\n  title_text: The Supreme Goddess as a pouring vessel symbol\n\n  preference: main\n\n  title_language: \n\n  creation_date: 18th/19th Century\n\n  creation_place_original_location: Bangladesh\n\n  inscriptions: \n\n  inscription_language: \n\n  shape: concave\n\n  materials_name: copper (metal)\n\n  techniques_name: sculpting\n\n  object_colour: copper (colour)\n\n  physical_appearance: This is a pair of tear-shaped vessel. Both have a bulbous bottom\n but while 001 tapers to a tip\n 002 tapers to a spout. The hammered indentation at the centre of both however\n are both hollow. Oxidisation appears to have occurred on 002.\n\n  subject_terms_1: religious symbolism Hinduism religious objects\n\n  subject_terms_2: Hinduism Religious articles Hindu bronzes Hindu gods\n\n  subject_terms_3: visual arts Religious life and practices\n\n  subject_terms_4: \n\n  sgcool_label_text: This object is a ceremonial vessel possibly used for holy water.  It is tear-shaped with a small\n hammered indentation at the centre. It is thought to be a symbol of the Great Goddess\n the yoni (or vulva)\n and the indentation is thought to indicate the male counterpart\n the god Shiva in the form of a linga (phallus). \\r\\n\\r\\nThe goddess is the energy of the god\n or his shakti. Her presence galvanises him into action. Therefore the combination of the male and female principal brings all things into being. \\r\\n\n",
  "createdDate": "20201125084523",
  "version": 0,
  "latest": false,
  "roles": [],
  "metadata": {
    "accession_no_csv": "2017-00282-001 and 002",
    "Image": "",
    "object_work_type": "ceremonial vessels copperwork (visual works)",
    "title_text": "The Supreme Goddess as a pouring vessel symbol",
    "preference": "main",
    "title_language": "",
    "creation_date": "18th/19th Century",
    "creation_place_original_location": "Bangladesh",
    "inscriptions": "",
    "inscription_language": "",
    "shape": "concave",
    "materials_name": "copper (metal)",
    "techniques_name": "sculpting",
    "object_colour": "copper (colour)",
    "physical_appearance": "This is a pair of tear-shaped vessel. Both have a bulbous bottom, but while 001 tapers to a tip, 002 tapers to a spout. The hammered indentation at the centre of both however, are both hollow. Oxidisation appears to have occurred on 002.",
    "subject_terms_1": "religious symbolism Hinduism religious objects",
    "subject_terms_2": "Hinduism Religious articles Hindu bronzes Hindu gods",
    "subject_terms_3": "visual arts Religious life and practices",
    "subject_terms_4": "",
    "sgcool_label_text": "This object is a ceremonial vessel possibly used for holy water.  It is tear-shaped with a small, hammered indentation at the centre. It is thought to be a symbol of the Great Goddess, the yoni (or vulva), and the indentation is thought to indicate the male counterpart, the god Shiva in the form of a linga (phallus). \r\n\r\nThe goddess is the energy of the god, or his shakti. Her presence galvanises him into action. Therefore the combination of the male and female principal brings all things into being. \r\n"
  },
  "nlpDate": "20201125084523",
  "connectorId": 0,
  "tags": {}
}