{"id":"2017-00156-015","title":"Lung Chui Ying Collection: Photographs, Printed Images, Pamphlets and Clippings  collected by Lung Chui Ying ????? Lung Chiu Ying Collection: uniformed man by staircase","source":"Bumblebee","path":"./Data/json/","content":"accession_no_csv:2017-00156-015\nImage:\nobject_work_type:black-and-white photographs\ntitle_text:Lung Chui Ying Collection: Photographs\n Printed Images\n Pamphlets and Clippings  collected by Lung Chui Ying ????? Lung Chiu Ying Collection: uniformed man by staircase\npreference:alternate alternate main\ntitle_language:\ncreation_date:Not indicated\ncreation_place_original_location:Singapore\ninscriptions:\ninscription_language:\nshape:rectangular\nmaterials_name:paper (fiber product)\ntechniques_name:photography (process) printing (process)\nobject_colour:black-and-white (colors)\nphysical_appearance:This is a black-and-white photograph featuring a bespectacled man in a uniform standing on by a flight of stairs. He is photographed gazing towards the left\n with his hands resting on the staircase railing. The photograph is quite faded\n especially around the top-left corner.\nsubject_terms_1:world wars resistance movements soldiers\nsubject_terms_2:World War\n 1939-1945 Great Britain. Army. Force 136 Force 136 (Guerilla movement) Photographs Soldiers\nsubject_terms_3:Force 136 (Guerilla movement) Lung\n Chiu Ying 1942-1945 Japanese occupation Photography\nsubject_terms_4:\nsgcool_label_text:These photographs\n printed images\n pamphlets and clippings belong to Lung Chui Ying and is part of a larger collection related to the World War II underground resistance movement known as Force 136. The collection of materials was gathered by Tan Chong Tee (1916- 2012)\n who was a key member of this resistance group. The collection consists of original materials belonging to Tan and other members of Force 136 dating from the 1940s to new materials reproduced from memory by Tan Chong Tee\n which date from the mid-1990s to early 2000s. \\r\\n\\r\\nForce 136 was set up in July 1942 as part of the British Special Operations Executive (SOE). It recruited and trained local guerillas to gather intelligence and create an underground spy network to support planned British invasion of Japanese-occupied Malaya.\\r\\n\\r\\nLung Chui Ying was a Hainanese born in Johor and recruited as a Force 136 member to fight against the Japanese in Malaya. \\r\\n","createdDate":"20201119143406","version":0,"latest":false,"roles":[],"metadata":{"accession_no_csv":"2017-00156-015","Image":"","object_work_type":"black-and-white photographs","title_text":"Lung Chui Ying Collection: Photographs, Printed Images, Pamphlets and Clippings  collected by Lung Chui Ying ????? Lung Chiu Ying Collection: uniformed man by staircase","preference":"alternate alternate main","title_language":"","creation_date":"Not indicated","creation_place_original_location":"Singapore","inscriptions":"","inscription_language":"","shape":"rectangular","materials_name":"paper (fiber product)","techniques_name":"photography (process) printing (process)","object_colour":"black-and-white (colors)","physical_appearance":"This is a black-and-white photograph featuring a bespectacled man in a uniform standing on by a flight of stairs. He is photographed gazing towards the left, with his hands resting on the staircase railing. The photograph is quite faded, especially around the top-left corner.","subject_terms_1":"world wars resistance movements soldiers","subject_terms_2":"World War, 1939-1945 Great Britain. Army. Force 136 Force 136 (Guerilla movement) Photographs Soldiers","subject_terms_3":"Force 136 (Guerilla movement) Lung, Chiu Ying 1942-1945 Japanese occupation Photography","subject_terms_4":"","sgcool_label_text":"These photographs, printed images, pamphlets and clippings belong to Lung Chui Ying and is part of a larger collection related to the World War II underground resistance movement known as Force 136. The collection of materials was gathered by Tan Chong Tee (1916- 2012), who was a key member of this resistance group. The collection consists of original materials belonging to Tan and other members of Force 136 dating from the 1940s to new materials reproduced from memory by Tan Chong Tee, which date from the mid-1990s to early 2000s. \r\n\r\nForce 136 was set up in July 1942 as part of the British Special Operations Executive (SOE). It recruited and trained local guerillas to gather intelligence and create an underground spy network to support planned British invasion of Japanese-occupied Malaya.\r\n\r\nLung Chui Ying was a Hainanese born in Johor and recruited as a Force 136 member to fight against the Japanese in Malaya. \r\n"},"nlpDate":"20201119143406","connectorId":0,"tags":{}}