{"id":"2017-00097","title":"Canoes for Camp Raiding Exercise ???????","source":"Bumblebee","path":"./Data/json/","content":"accession_no_csv:2017-00097\nImage:\nobject_work_type:paintings (visual works)\ntitle_text:Canoes for Camp Raiding Exercise ???????\npreference:main alternate\ntitle_language:\ncreator_2:Tan Chong Tee\ncreator_1:Chen\n Chongzhi\n 1916-\ncreator_role:artists (visual artists)\ncreation_date:Not indicated\ncreation_place_original_location:Singapore\ninscriptions:\ninscription_language:\nshape:rectangular\nmaterials_name:canvas (textile material) oil paint (paint)\ntechniques_name:painting (image-making)\nobject_colour:multicolored\nphysical_appearance:This is an oil painting depicting canoes for camp raiding exercise. It features two canoes in the foreground\n one red and one blue. They are resting by the riverbed. Across the river in the background of the painting\n there is a person squating on the edge of the water.\nsubject_terms_1:world wars depictions (visual works) resistance movements canoes\nsubject_terms_2:Painting World War\n 1939-1945 Great Britain. Army. Force 136 Force 136 (Guerilla movement) Chen\n Chongzhi\n 1916- Canoes and canoeing\nsubject_terms_3:Watercolour painting Force 136 (Guerilla movement) Tan\n Chong Tee 1942-1945 Japanese occupation\nsubject_terms_4:\ncontext_1:World War\n 1939-1945 1942-1945 Japanese Occupation\ncontext_2:world wars occupations (armed conflicts)\ncontext_3:1939-1945 1942-1945\ncontext_4:1939 1942\ncontext_5:1945 1945\ncontext_6:Malaya Singapore\ncontext_7:Great Britain. Army. Force 136\ncontext_8:armed forces\nsgcool_label_text:This painting belongs to part of a collection of artefacts related to the World War II underground resistance movement known as Force 136. The collection of materials was gathered by Tan Chong Tee (1916-2012)\n who was a key member of this resistance group. The collection consists of original materials belonging to Tan and other members of Force 136 dating from the 1940s to new materials reproduced from memory by Tan Chong Tee\n which date from mid 1990s to early 2000s. \\r\\n\\r\\nForce 136 was set up in 1942-45 as part of the British Special Operations Executive (SOE). It recruited and trained local guerillas to gather intelligence and create an underground spy network to support planned British invasion of Japanese-occupied Malaya.\\r\\n\\r\\nThis painting depicts the canoes used for a camp raiding exercise. \\r\\n","createdDate":"20201119143406","version":0,"latest":false,"roles":[],"metadata":{"accession_no_csv":"2017-00097","Image":"","object_work_type":"paintings (visual works)","title_text":"Canoes for Camp Raiding Exercise ???????","preference":"main alternate","title_language":"","creator_2":"Tan Chong Tee","creator_1":"Chen, Chongzhi, 1916-","creator_role":"artists (visual artists)","creation_date":"Not indicated","creation_place_original_location":"Singapore","inscriptions":"","inscription_language":"","shape":"rectangular","materials_name":"canvas (textile material) oil paint (paint)","techniques_name":"painting (image-making)","object_colour":"multicolored","physical_appearance":"This is an oil painting depicting canoes for camp raiding exercise. It features two canoes in the foreground, one red and one blue. They are resting by the riverbed. Across the river in the background of the painting, there is a person squating on the edge of the water.","subject_terms_1":"world wars depictions (visual works) resistance movements canoes","subject_terms_2":"Painting World War, 1939-1945 Great Britain. Army. Force 136 Force 136 (Guerilla movement) Chen, Chongzhi, 1916- Canoes and canoeing","subject_terms_3":"Watercolour painting Force 136 (Guerilla movement) Tan, Chong Tee 1942-1945 Japanese occupation","subject_terms_4":"","context_1":"World War, 1939-1945 1942-1945 Japanese Occupation","context_2":"world wars occupations (armed conflicts)","context_3":"1939-1945 1942-1945","context_4":"1939 1942","context_5":"1945 1945","context_6":"Malaya Singapore","context_7":"Great Britain. Army. Force 136","context_8":"armed forces","sgcool_label_text":"This painting belongs to part of a collection of artefacts related to the World War II underground resistance movement known as Force 136. The collection of materials was gathered by Tan Chong Tee (1916-2012), who was a key member of this resistance group. The collection consists of original materials belonging to Tan and other members of Force 136 dating from the 1940s to new materials reproduced from memory by Tan Chong Tee, which date from mid 1990s to early 2000s. \r\n\r\nForce 136 was set up in 1942-45 as part of the British Special Operations Executive (SOE). It recruited and trained local guerillas to gather intelligence and create an underground spy network to support planned British invasion of Japanese-occupied Malaya.\r\n\r\nThis painting depicts the canoes used for a camp raiding exercise. \r\n"},"nlpDate":"20201119143406","connectorId":0,"tags":{}}