{
  "id": "2017-00608",
  "title": "Trousers Red silk trousers",
  "source": "Bumblebee",
  "path": "./Data/json/",
  "content": "\n  accession_no_csv: 2017-00608\n\n  Image: \n\n  object_work_type: trousers womenswear\n\n  title_text: Trousers Red silk trousers\n\n  preference: alternate main\n\n  title_language: \n\n  creation_date: 20th century\n\n  creation_place_original_location: Kachchh (India)\n\n  inscriptions: \n\n  inscription_language: \n\n  shape: irregular\n\n  materials_name: silk (textile) silver thread\n\n  techniques_name: sewing (needleworking technique)\n\n  object_colour: red (color) silver (color)\n\n  physical_appearance: This is a pair of silk trousers. It is red\n with silver embroided floral and foliage design along the bottom. The trousers are mid-length.\n\n  subject_terms_1: folk costume flower (motif) foliage (motif)\n\n  subject_terms_2: Ethnic costume Pants Motifs Memons\n\n  subject_terms_3: Indian costumes\n\n  subject_terms_4: \n\n  sgcool_label_text: Ladies trousers\n worn by the Kutchi Memon community. The trousers would have been manufactured and embroidered in north India\n",
  "createdDate": "20201120223708",
  "version": 0,
  "latest": false,
  "roles": [],
  "metadata": {
    "accession_no_csv": "2017-00608",
    "Image": "",
    "object_work_type": "trousers womenswear",
    "title_text": "Trousers Red silk trousers",
    "preference": "alternate main",
    "title_language": "",
    "creation_date": "20th century",
    "creation_place_original_location": "Kachchh (India)",
    "inscriptions": "",
    "inscription_language": "",
    "shape": "irregular",
    "materials_name": "silk (textile) silver thread",
    "techniques_name": "sewing (needleworking technique)",
    "object_colour": "red (color) silver (color)",
    "physical_appearance": "This is a pair of silk trousers. It is red, with silver embroided floral and foliage design along the bottom. The trousers are mid-length.",
    "subject_terms_1": "folk costume flower (motif) foliage (motif)",
    "subject_terms_2": "Ethnic costume Pants Motifs Memons",
    "subject_terms_3": "Indian costumes",
    "subject_terms_4": "",
    "sgcool_label_text": "Ladies trousers, worn by the Kutchi Memon community. The trousers would have been manufactured and embroidered in north India"
  },
  "nlpDate": "20201120223708",
  "connectorId": 0,
  "tags": {}
}