{
  "id": "2017-00302-029",
  "title": "Miscellaneous scraps of paper from P.O.W James Steele Archives (30 pieces) P.O.W. James Steele Archives: Drawn diagram of engine fuel",
  "source": "Bumblebee",
  "path": "./Data/json/",
  "content": "\n  accession_no_csv: 2017-00302-029\n\n  Image: \n\n  object_work_type: drawings (visual works)\n\n  title_text: Miscellaneous scraps of paper from P.O.W James Steele Archives (30 pieces) P.O.W. James Steele Archives: Drawn diagram of engine fuel\n\n  preference: alternate main\n\n  title_language: \n\n  creation_date: 1941-1945\n\n  creation_place_original_location: Singapore\n\n  inscriptions: \n\n  inscription_language: \n\n  shape: rectangular\n\n  materials_name: paper (fiber product)\n\n  techniques_name: drawing (image-making)\n\n  object_colour: black-and-white (colors)\n\n  physical_appearance: This is a drawn diagram of an engine fuel system. There are six cylinders drawn in the center of the paper\n with arrows along a saft at the bottom. The bottom of the diagram shows a top view of an adjusting collar\n with a circular diagram in the center marking out the angles. The edges of the document is slightly folded and torn\n especially on the bottom-right corner.\n\n  subject_terms_1: world wars prisoners of war diagrams gas engines\n\n  subject_terms_2: World War\n 1939-1945 Prisoners of war Drawing Graphs Internal combustion engines\n\n  subject_terms_3: war personalities Drawing\n\n  subject_terms_4: \n\n  sgcool_label_text: Loose papers from the James Steele\n P.O.W archive that include a symbolic drawing\n Japanese banana money\n map of camp\n administrative papers from Changi prison pre-dating internment\n list of soldiers of a regiment as well as James Steele’s warrant to  join the army. These papers are part of the archive of James Steele\n Royal Artillery (Field) who served in Malaya from January 1941-February 1942\n when interned as a P.O.W at Changi until his release in October 1945.\n",
  "createdDate": "20201120223707",
  "version": 0,
  "latest": false,
  "roles": [],
  "metadata": {
    "accession_no_csv": "2017-00302-029",
    "Image": "",
    "object_work_type": "drawings (visual works)",
    "title_text": "Miscellaneous scraps of paper from P.O.W James Steele Archives (30 pieces) P.O.W. James Steele Archives: Drawn diagram of engine fuel",
    "preference": "alternate main",
    "title_language": "",
    "creation_date": "1941-1945",
    "creation_place_original_location": "Singapore",
    "inscriptions": "",
    "inscription_language": "",
    "shape": "rectangular",
    "materials_name": "paper (fiber product)",
    "techniques_name": "drawing (image-making)",
    "object_colour": "black-and-white (colors)",
    "physical_appearance": "This is a drawn diagram of an engine fuel system. There are six cylinders drawn in the center of the paper, with arrows along a saft at the bottom. The bottom of the diagram shows a top view of an adjusting collar, with a circular diagram in the center marking out the angles. The edges of the document is slightly folded and torn, especially on the bottom-right corner.",
    "subject_terms_1": "world wars prisoners of war diagrams gas engines",
    "subject_terms_2": "World War, 1939-1945 Prisoners of war Drawing Graphs Internal combustion engines",
    "subject_terms_3": "war personalities Drawing",
    "subject_terms_4": "",
    "sgcool_label_text": "Loose papers from the James Steele, P.O.W archive that include a symbolic drawing, Japanese banana money, map of camp, administrative papers from Changi prison pre-dating internment, list of soldiers of a regiment as well as James Steele’s warrant to  join the army. These papers are part of the archive of James Steele, Royal Artillery (Field) who served in Malaya from January 1941-February 1942, when interned as a P.O.W at Changi until his release in October 1945."
  },
  "nlpDate": "20201120223707",
  "connectorId": 0,
  "tags": {}
}