{"id":"2017-00393","title":"Kain panjang","source":"Bumblebee","path":"./Data/json/","content":"accession_no_csv:2017-00393\nImage:\nobject_work_type:folk costume batik art\ntitle_text:Kain panjang\npreference:main\ntitle_language:\ncreator_2:Jane Hendromartono\ncreator_role:textile designers\ncreation_date:1965-1980s\ncreation_place_original_location:Pekalongan (Indonesia)\nstyles_periods_indexing_terms:Peranakan\ninscriptions:\ninscription_language:\nshape:rectangular\nmaterials_name:cotton (textile)\ntechniques_name:batik\nobject_colour:multicolored\nphysical_appearance:This is a batik kain panjang. It features hexagon squares against a dark red background. Enclosed within each hexagon square is a stylised depiction of a variety of animals and plant forms. On the right of the batik there is a vertical row of elongated triangles. A vertical panel segments the triangles from the main body of the batik. Both the panel and the triangles also contain the stylised designs.\nsubject_terms_1:Peranakan foliage (motif) depictions (visual works) cultural diffusion\nsubject_terms_2:Batik Ethnic costume Peranakan (Asian people) Motifs Culture diffusion\nsubject_terms_3:Batik Peranakan costumes\nsgcool_label_text:Curious animals and plant forms embellish this kain panjang.  Enclosed within squares with hexagon corners and elaborate borders\n the layout of the badan (or ‘body’ and main design feature of the batik) emphasises the creativity of the artist.  On one end of the batik\n a row of interlocking triangles\n known as tumpal is shown.  This batik comes from the family collection of Oey Djien Nio (1929-1987)\n the last in three generations of documented batik-makers in Pekalongan.  In her earlier signatures\n she used her husband’s name\n Liem Siok Hien.  But from 1965 onwards\n she used Jane Hendromartono\n combining her husband’s new Indonesian family name\n Hendromartono with Jane\n as people addressed her by.  She developed a personal style distinct from her mother and grandmother\n and experimented with a wide spectrum of colours and exotic combinations of birds\n rock formations and mythical animals.  Jane Hendromartono’s clientele expanded beyond the elite in Indonesia to include Europe\n America and Japan\n especially in the 1980s.  This piece is signed “Jane Hendromartono Pekalongan Java”.","createdDate":"20201018182636","version":0,"latest":false,"roles":[],"metadata":{"accession_no_csv":"2017-00393","Image":"","object_work_type":"folk costume batik art","title_text":"Kain panjang","preference":"main","title_language":"","creator_2":"Jane Hendromartono","creator_role":"textile designers","creation_date":"1965-1980s","creation_place_original_location":"Pekalongan (Indonesia)","styles_periods_indexing_terms":"Peranakan","inscriptions":"","inscription_language":"","shape":"rectangular","materials_name":"cotton (textile)","techniques_name":"batik","object_colour":"multicolored","physical_appearance":"This is a batik kain panjang. It features hexagon squares against a dark red background. Enclosed within each hexagon square is a stylised depiction of a variety of animals and plant forms. On the right of the batik there is a vertical row of elongated triangles. A vertical panel segments the triangles from the main body of the batik. Both the panel and the triangles also contain the stylised designs.","subject_terms_1":"Peranakan foliage (motif) depictions (visual works) cultural diffusion","subject_terms_2":"Batik Ethnic costume Peranakan (Asian people) Motifs Culture diffusion","subject_terms_3":"Batik Peranakan costumes","sgcool_label_text":"Curious animals and plant forms embellish this kain panjang.  Enclosed within squares with hexagon corners and elaborate borders, the layout of the badan (or ‘body’ and main design feature of the batik) emphasises the creativity of the artist.  On one end of the batik, a row of interlocking triangles, known as tumpal is shown.  This batik comes from the family collection of Oey Djien Nio (1929-1987), the last in three generations of documented batik-makers in Pekalongan.  In her earlier signatures, she used her husband’s name, Liem Siok Hien.  But from 1965 onwards, she used Jane Hendromartono, combining her husband’s new Indonesian family name, Hendromartono with Jane, as people addressed her by.  She developed a personal style distinct from her mother and grandmother, and experimented with a wide spectrum of colours and exotic combinations of birds, rock formations and mythical animals.  Jane Hendromartono’s clientele expanded beyond the elite in Indonesia to include Europe, America and Japan, especially in the 1980s.  This piece is signed “Jane Hendromartono Pekalongan Java”."},"nlpDate":"20201018182636","connectorId":0,"tags":{}}