{
  "id": "2017-00474\r\n2017-00475",
  "title": "Bamboo vest",
  "source": "Bumblebee",
  "path": "./Data/json/",
  "content": "\n  accession_no_csv: 2017-00474\\r\\n2017-00475\n\n  Image: \n\n  object_work_type: wedding clothes vests (garments)\n\n  title_text: Bamboo vest\n\n  preference: main\n\n  title_language: \n\n  creation_date: 1930s-1940s\n\n  creation_place_original_location: China Indonesia\n\n  inscriptions: \n\n  inscription_language: \n\n  shape: irregular\n\n  materials_name: bamboo (material)\n\n  techniques_name: sewing (needleworking technique)\n\n  object_colour: multicolored\n\n  physical_appearance: This is a set of two bamboo vests. It is made from strips of bamboo\n strung together to create a lattice structure. A blue trim runs along the neckline of the vest as well as down the front and along the sleeveless arm holes.\n\n  subject_terms_1: ceremonial costume underwear\n\n  subject_terms_2: Vests Wedding costume Rites and ceremonies Underwear\n\n  subject_terms_3: Peranakan costumes\n\n  sgcool_label_text: Bamboo vests were worn by both bride and bridegroom under their wedding garments. Strips of bamboo are strung to form a diamond-shaped mesh. A blue trim runs along the vest’s circular neckline\n sleeveless arm holes and down the front. It is secured by frog fasteners at the neck and stomach. Bamboo vests were worn to allow for ventilation beneath the thick and heavily embroidered wedding garments. As wedding robes were often made from delicate silk\n bamboo vests would have prevented sweat stains and fabric damage.\n",
  "createdDate": "20201120223708",
  "version": 0,
  "latest": false,
  "roles": [],
  "metadata": {
    "accession_no_csv": "2017-00474\r\n2017-00475",
    "Image": "",
    "object_work_type": "wedding clothes vests (garments)",
    "title_text": "Bamboo vest",
    "preference": "main",
    "title_language": "",
    "creation_date": "1930s-1940s",
    "creation_place_original_location": "China Indonesia",
    "inscriptions": "",
    "inscription_language": "",
    "shape": "irregular",
    "materials_name": "bamboo (material)",
    "techniques_name": "sewing (needleworking technique)",
    "object_colour": "multicolored",
    "physical_appearance": "This is a set of two bamboo vests. It is made from strips of bamboo, strung together to create a lattice structure. A blue trim runs along the neckline of the vest as well as down the front and along the sleeveless arm holes.",
    "subject_terms_1": "ceremonial costume underwear",
    "subject_terms_2": "Vests Wedding costume Rites and ceremonies Underwear",
    "subject_terms_3": "Peranakan costumes",
    "sgcool_label_text": "Bamboo vests were worn by both bride and bridegroom under their wedding garments. Strips of bamboo are strung to form a diamond-shaped mesh. A blue trim runs along the vest’s circular neckline, sleeveless arm holes and down the front. It is secured by frog fasteners at the neck and stomach. Bamboo vests were worn to allow for ventilation beneath the thick and heavily embroidered wedding garments. As wedding robes were often made from delicate silk, bamboo vests would have prevented sweat stains and fabric damage."
  },
  "nlpDate": "20201120223708",
  "connectorId": 0,
  "tags": {}
}