{"id":"2017-00104","title":"The Submarine Contact Base at Pangkor Island\u0027s Keling Wang ????????????","source":"Bumblebee","path":"./Data/json/","content":"accession_no_csv:2017-00104\nImage:\nobject_work_type:paintings (visual works)\ntitle_text:The Submarine Contact Base at Pangkor Island\\u0027s Keling Wang ????????????\npreference:main alternate\ntitle_language:\ncreator_2:Tan Chong Tee\ncreator_1:Chen\n Chongzhi\n 1916-\ncreator_role:artists (visual artists)\ncreation_date:1990-2000\ncreation_place_original_location:Singapore\ninscriptions:\ninscription_language:\nshape:rectangular\nmaterials_name:paper (fiber product) Watercolour (paint)\ntechniques_name:painting (image-making)\nobject_colour:multicolored\nphysical_appearance:This is a painting of the submarine contact base at Pangkor Island\\u0027s Keling Wang. It features a few roofed structures on stilts over a water body\n with curved road from the bottom-left to the right of the painting. There are some boats along the jetties in the background. There is an inscription at the bottom-left of the painting.\nsubject_terms_1:world wars depictions (visual works) resistance movements army camps\nsubject_terms_2:Painting World War\n 1939-1945 Great Britain. Army. Force 136 Force 136 (Guerilla movement) Chen\n Chongzhi\n 1916- Pangkor Island (Perak\n Malaysia) Military training camps\nsubject_terms_3:Painting Force 136 (Guerilla movement) Tan\n Chong Tee 1942-1945 Japanese occupation\nsubject_terms_4:\nsgcool_label_text:This drawing belongs to part of a collection of artefacts related to the World War II underground resistance movement known as Force 136. The collection of materials was gathered by Tan Chong Tee (1916- 2012)\n who was a key member of this resistance group. The collection consists of original materials belonging to Tan and other members of Force 136 dating from the 1940s to new materials reproduced from memory by Tan Chong Tee\n which date from mid 1990s to early 2000s.\\r\\n\\r\\nForce 136 was set up in July 1942 as part of the British Special Operations Executive (SOE). It recruited and trained local guerrillas to gather intelligence and create an underground spy network to support planned British invasion of Japanese-occupied Malaya. \\r\\n\\r\\nThis drawing is a depiction of the Submarine Contact Base at Pangkor Island\\u0027s Keling Wang derived from Tan Chong Tee’s memories.","createdDate":"20201018182636","version":0,"latest":false,"roles":[],"metadata":{"accession_no_csv":"2017-00104","Image":"","object_work_type":"paintings (visual works)","title_text":"The Submarine Contact Base at Pangkor Island\u0027s Keling Wang ????????????","preference":"main alternate","title_language":"","creator_2":"Tan Chong Tee","creator_1":"Chen, Chongzhi, 1916-","creator_role":"artists (visual artists)","creation_date":"1990-2000","creation_place_original_location":"Singapore","inscriptions":"","inscription_language":"","shape":"rectangular","materials_name":"paper (fiber product) Watercolour (paint)","techniques_name":"painting (image-making)","object_colour":"multicolored","physical_appearance":"This is a painting of the submarine contact base at Pangkor Island\u0027s Keling Wang. It features a few roofed structures on stilts over a water body, with curved road from the bottom-left to the right of the painting. There are some boats along the jetties in the background. There is an inscription at the bottom-left of the painting.","subject_terms_1":"world wars depictions (visual works) resistance movements army camps","subject_terms_2":"Painting World War, 1939-1945 Great Britain. Army. Force 136 Force 136 (Guerilla movement) Chen, Chongzhi, 1916- Pangkor Island (Perak, Malaysia) Military training camps","subject_terms_3":"Painting Force 136 (Guerilla movement) Tan, Chong Tee 1942-1945 Japanese occupation","subject_terms_4":"","sgcool_label_text":"This drawing belongs to part of a collection of artefacts related to the World War II underground resistance movement known as Force 136. The collection of materials was gathered by Tan Chong Tee (1916- 2012), who was a key member of this resistance group. The collection consists of original materials belonging to Tan and other members of Force 136 dating from the 1940s to new materials reproduced from memory by Tan Chong Tee, which date from mid 1990s to early 2000s.\r\n\r\nForce 136 was set up in July 1942 as part of the British Special Operations Executive (SOE). It recruited and trained local guerrillas to gather intelligence and create an underground spy network to support planned British invasion of Japanese-occupied Malaya. \r\n\r\nThis drawing is a depiction of the Submarine Contact Base at Pangkor Island\u0027s Keling Wang derived from Tan Chong Tee’s memories."},"nlpDate":"20201018182636","connectorId":0,"tags":{}}