{
  "id": "2017-00415",
  "title": "Tablecloth",
  "source": "Bumblebee",
  "path": "./Data/json/",
  "content": "\n  accession_no_csv: 2017-00415\n\n  Image: \n\n  object_work_type: tablecloths batik art\n\n  title_text: Tablecloth\n\n  preference: main\n\n  title_language: \n\n  creator_2: Jane Hendromartono\n\n  creator_role: textile designers\n\n  creation_date: 1950-1980s\n\n  creation_place_original_location: Pekalongan (Indonesia)\n\n  styles_periods_indexing_terms: Peranakan\n\n  inscriptions: \n\n  inscription_language: \n\n  shape: square (shape)\n\n  materials_name: cotton (textile)\n\n  techniques_name: batik\n\n  object_colour: multicolored\n\n  physical_appearance: \\This is a batik tablecloth. It features characters from the fairytale \\\\Snow White and the Seven Dwarfs\\\\. A portrait of snow white is depicted in the center of the tablecloth\n\n  subject_terms_1: with the seven dwarfs surrounding her in a circle within a medallion. Clumps of mushrooms decorate the outer border of the medallion. The background of the medallion is pink depictions (visual works) fairy tales\n\n  subject_terms_2: while the exterior is set against a darker shade.\\ Peranakan (Asian people) Snow White (tale) Fairy tales Tablecloths\n\n  subject_terms_3: Peranakan\n\n  subject_terms_4: Batik\n\n  context_1: Batik\n",
  "createdDate": "20201120223708",
  "version": 0,
  "latest": false,
  "roles": [],
  "metadata": {
    "accession_no_csv": "2017-00415",
    "Image": "",
    "object_work_type": "tablecloths batik art",
    "title_text": "Tablecloth",
    "preference": "main",
    "title_language": "",
    "creator_2": "Jane Hendromartono",
    "creator_role": "textile designers",
    "creation_date": "1950-1980s",
    "creation_place_original_location": "Pekalongan (Indonesia)",
    "styles_periods_indexing_terms": "Peranakan",
    "inscriptions": "",
    "inscription_language": "",
    "shape": "square (shape)",
    "materials_name": "cotton (textile)",
    "techniques_name": "batik",
    "object_colour": "multicolored",
    "physical_appearance": "\"This is a batik tablecloth. It features characters from the fairytale \"\"Snow White and the Seven Dwarfs\"\". A portrait of snow white is depicted in the center of the tablecloth",
    "subject_terms_1": "with the seven dwarfs surrounding her in a circle within a medallion. Clumps of mushrooms decorate the outer border of the medallion. The background of the medallion is pink depictions (visual works) fairy tales",
    "subject_terms_2": "while the exterior is set against a darker shade.\" Peranakan (Asian people) Snow White (tale) Fairy tales Tablecloths",
    "subject_terms_3": "Peranakan",
    "subject_terms_4": "Batik",
    "context_1": "Batik"
  },
  "nlpDate": "20201120223708",
  "connectorId": 0,
  "tags": {}
}