{
  "id": "2017-00179-006",
  "title": "Lim Hong Pei Collection ????? Lim Hong Pei Collection: group in front of fence",
  "source": "Bumblebee",
  "path": "./Data/json/",
  "content": "\n  accession_no_csv: 2017-00179-006\n\n  Image: \n\n  object_work_type: black-and-white photographs\n\n  title_text: Lim Hong Pei Collection ????? Lim Hong Pei Collection: group in front of fence\n\n  preference: alternate alternate main\n\n  title_language: \n\n  creation_date: 1946\n\n  creation_place_original_location: Singapore\n\n  inscriptions: \n\n  inscription_language: \n\n  shape: rectangular\n\n  materials_name: paper (fiber product)\n\n  techniques_name: photographic processes printing (process)\n\n  object_colour: black-and-white (colors)\n\n  physical_appearance: This is a black-and-white photograph. It features three men dressed in a uniform with tie\n standing behind two girls dressed in jumpsuits. They are posing in front of a wooden gate. The photograph is badly faded\n especially along the sides.\n\n  subject_terms_1: world wars resistance movements soldiers\n\n  subject_terms_2: World War\n 1939-1945 Great Britain. Army. Force 136 Force 136 (Guerilla movement) Lim\n Hong Pei\n 1922- Photography Soldiers\n\n  subject_terms_3: Force 136 (Guerilla movement) 1942-1945 Japanese occupation Photography war personalities\n\n  subject_terms_4: \n\n  sgcool_label_text: These photographs belong to part of a collection of artefacts related to the World War II underground resistance movement known as Force 136. The collection of materials was gathered by Tan Chong Tee (1916- 2012)\n who was a key member of this resistance group. The collection consists of original materials belonging to Tan and other members of Force 136 dating from the 1940s to new materials reproduced from memory by Tan Chong Tee\n which date from the late 1980s to early 2000s. \\r\\n\\r\\nForce 136 was set up in July 1942 as part of the British Special Operations Executive (SOE). It recruited and trained local guerillas to gather intelligence and create an underground spy network to support planned British invasion of Japanese-occupied Malaya.\\r\\n\n",
  "createdDate": "20201120223707",
  "version": 0,
  "latest": false,
  "roles": [],
  "metadata": {
    "accession_no_csv": "2017-00179-006",
    "Image": "",
    "object_work_type": "black-and-white photographs",
    "title_text": "Lim Hong Pei Collection ????? Lim Hong Pei Collection: group in front of fence",
    "preference": "alternate alternate main",
    "title_language": "",
    "creation_date": "1946",
    "creation_place_original_location": "Singapore",
    "inscriptions": "",
    "inscription_language": "",
    "shape": "rectangular",
    "materials_name": "paper (fiber product)",
    "techniques_name": "photographic processes printing (process)",
    "object_colour": "black-and-white (colors)",
    "physical_appearance": "This is a black-and-white photograph. It features three men dressed in a uniform with tie, standing behind two girls dressed in jumpsuits. They are posing in front of a wooden gate. The photograph is badly faded, especially along the sides.",
    "subject_terms_1": "world wars resistance movements soldiers",
    "subject_terms_2": "World War, 1939-1945 Great Britain. Army. Force 136 Force 136 (Guerilla movement) Lim, Hong Pei, 1922- Photography Soldiers",
    "subject_terms_3": "Force 136 (Guerilla movement) 1942-1945 Japanese occupation Photography war personalities",
    "subject_terms_4": "",
    "sgcool_label_text": "These photographs belong to part of a collection of artefacts related to the World War II underground resistance movement known as Force 136. The collection of materials was gathered by Tan Chong Tee (1916- 2012), who was a key member of this resistance group. The collection consists of original materials belonging to Tan and other members of Force 136 dating from the 1940s to new materials reproduced from memory by Tan Chong Tee, which date from the late 1980s to early 2000s. \r\n\r\nForce 136 was set up in July 1942 as part of the British Special Operations Executive (SOE). It recruited and trained local guerillas to gather intelligence and create an underground spy network to support planned British invasion of Japanese-occupied Malaya.\r\n"
  },
  "nlpDate": "20201120223707",
  "connectorId": 0,
  "tags": {}
}