{
  "id": "2017-01040-113",
  "title": "\"Personal photograph album titled \"\"Sixteen Months in Singapore\"\"\" Sixteen Months in Singapore: Photograph of Corporal A. Silver  taken from side angle",
  "source": "Bumblebee",
  "path": "./Data/json/",
  "content": "\n  accession_no_csv: 2017-01040-113\n\n  Image: \n\n  object_work_type: black-and-white photographs photographs\n\n  title_text: \\Personal photograph album titled \\\\Sixteen Months in Singapore\\\\\\ Sixteen Months in Singapore: Photograph of Corporal A. Silver  taken from side angle\n\n  preference: alternate main\n\n  title_language: \n\n  creation_date: 1951-1952\n\n  creation_place_original_location: Singapore\n\n  inscriptions: \n\n  inscription_language: \n\n  shape: rectangular\n\n  materials_name: paper (fiber product)\n\n  techniques_name: photographic processes\n\n  object_colour: black-and-white (colors)\n\n  physical_appearance: This is a black-and-white photograph. It is rectangular in shape and portrait in orientation. It features a woman\n framing only her torso and head. The photograph is taken from the side. The woman is looking down towards the camera. She is dressed in a striped top\n and is wearing a pair of glasses. In the background of the photograph\n there is a canopy of a tree seen.\n\n  subject_terms_1: snapshots women (female humans)\n\n  subject_terms_2: Portrait photography Women\n\n  subject_terms_3: Portrait photography Women\n\n  subject_terms_4: \n\n  sgcool_label_text: This is a personal photograph album that belonged to a Corporal A. Silver who spent 16 months in Singapore between 1951 and 1952. Silver was presumably a Jewish lady who was stationed in Singapore to serve at the Royal Air Force (RAF) Hospital at Changi. The album contains photographs that document her working and personal life\n including friends she made within the Jewish community in Singapore.\n",
  "createdDate": "20201120223708",
  "version": 0,
  "latest": false,
  "roles": [],
  "metadata": {
    "accession_no_csv": "2017-01040-113",
    "Image": "",
    "object_work_type": "black-and-white photographs photographs",
    "title_text": "\"Personal photograph album titled \"\"Sixteen Months in Singapore\"\"\" Sixteen Months in Singapore: Photograph of Corporal A. Silver  taken from side angle",
    "preference": "alternate main",
    "title_language": "",
    "creation_date": "1951-1952",
    "creation_place_original_location": "Singapore",
    "inscriptions": "",
    "inscription_language": "",
    "shape": "rectangular",
    "materials_name": "paper (fiber product)",
    "techniques_name": "photographic processes",
    "object_colour": "black-and-white (colors)",
    "physical_appearance": "This is a black-and-white photograph. It is rectangular in shape and portrait in orientation. It features a woman, framing only her torso and head. The photograph is taken from the side. The woman is looking down towards the camera. She is dressed in a striped top, and is wearing a pair of glasses. In the background of the photograph, there is a canopy of a tree seen.",
    "subject_terms_1": "snapshots women (female humans)",
    "subject_terms_2": "Portrait photography Women",
    "subject_terms_3": "Portrait photography Women",
    "subject_terms_4": "",
    "sgcool_label_text": "This is a personal photograph album that belonged to a Corporal A. Silver who spent 16 months in Singapore between 1951 and 1952. Silver was presumably a Jewish lady who was stationed in Singapore to serve at the Royal Air Force (RAF) Hospital at Changi. The album contains photographs that document her working and personal life, including friends she made within the Jewish community in Singapore."
  },
  "nlpDate": "20201120223708",
  "connectorId": 0,
  "tags": {}
}