{"id":"2017-00145-080","title":"Reflections of Tan Chong Tee: Letters, Notes, and Photographs Reflections of Tan Chong Tee: Memoir","source":"Bumblebee","path":"./Data/json/","content":"accession_no_csv:2017-00145-080\nImage:\nobject_work_type:document (object genre) memoirs\ntitle_text:Reflections of Tan Chong Tee: Letters\n Notes\n and Photographs Reflections of Tan Chong Tee: Memoir\npreference:alternate main\ntitle_language:\ncreator_2:Tan Chong Tee\ncreator_1:Chen\n Chongzhi\n 1916-  Tan\n Chong Tee\ncreator_role:authors\ncreation_place_original_location:Singapore\ninscriptions:\ninscription_language:\nshape:Rectangular\nmaterials_name:paper (fiber product)\ntechniques_name:handwriting\nobject_colour:multicoloured\nphysical_appearance:It is visible that the top of this sheet has been torn. Taped to its bottom are two sheets of paper. The tape has yellowed with time. This memoir outlined the reasons why the author had disagreed with the Force terminating their missions. It also ended with the author stating that he will report back on their departure from  Bukit Segari on a later date.\nsubject_terms_1:resistance movements  guerilla warfare local histories armed forces  Chinese scripts world wars\nsubject_terms_2:Force 136 (Guerilla movement) War resistance movements  Guerillas  Local history Armed Forces  Great Britain. Army. Force 136 Writing  Chinese characters  Chen\n Chongzhi\n 1916-\nsubject_terms_3:Force 136 (Guerilla movement) History  Tan\n Chong Tee war personalities  1942-1945 Japanese Occupation  \\r\\n\\r\\n\nsgcool_label_text:These documents and photographs belong to a larger part of a collection of artefacts related to the World War II underground resistance movement known as Force 136. The collection of materials was gathered by Tan Chong Tee (1916- 2012)\n who was a key member of this resistance group. The collection consists of original materials belonging to Tan and other members of Force 136 dating from the 1940s to new materials reproduced from memory by Tan Chong Tee\n which date from the late 1980s to early 2000s. \\r\\n\\r\\nForce 136 was set up in July 1942 as part of the British Special Operations Executive (SOE). It recruited and trained local guerillas to gather intelligence and create an underground spy network to support planned British invasion of Japanese-occupied Malaya.\\r\\n","createdDate":"20201018182636","version":0,"latest":false,"roles":[],"metadata":{"accession_no_csv":"2017-00145-080","Image":"","object_work_type":"document (object genre) memoirs","title_text":"Reflections of Tan Chong Tee: Letters, Notes, and Photographs Reflections of Tan Chong Tee: Memoir","preference":"alternate main","title_language":"","creator_2":"Tan Chong Tee","creator_1":"Chen, Chongzhi, 1916-  Tan, Chong Tee","creator_role":"authors","creation_place_original_location":"Singapore","inscriptions":"","inscription_language":"","shape":"Rectangular","materials_name":"paper (fiber product)","techniques_name":"handwriting","object_colour":"multicoloured","physical_appearance":"It is visible that the top of this sheet has been torn. Taped to its bottom are two sheets of paper. The tape has yellowed with time. This memoir outlined the reasons why the author had disagreed with the Force terminating their missions. It also ended with the author stating that he will report back on their departure from  Bukit Segari on a later date.","subject_terms_1":"resistance movements  guerilla warfare local histories armed forces  Chinese scripts world wars","subject_terms_2":"Force 136 (Guerilla movement) War resistance movements  Guerillas  Local history Armed Forces  Great Britain. Army. Force 136 Writing  Chinese characters  Chen, Chongzhi, 1916-","subject_terms_3":"Force 136 (Guerilla movement) History  Tan, Chong Tee war personalities  1942-1945 Japanese Occupation  \r\n\r\n","sgcool_label_text":"These documents and photographs belong to a larger part of a collection of artefacts related to the World War II underground resistance movement known as Force 136. The collection of materials was gathered by Tan Chong Tee (1916- 2012), who was a key member of this resistance group. The collection consists of original materials belonging to Tan and other members of Force 136 dating from the 1940s to new materials reproduced from memory by Tan Chong Tee, which date from the late 1980s to early 2000s. \r\n\r\nForce 136 was set up in July 1942 as part of the British Special Operations Executive (SOE). It recruited and trained local guerillas to gather intelligence and create an underground spy network to support planned British invasion of Japanese-occupied Malaya.\r\n"},"nlpDate":"20201018182636","connectorId":0,"tags":{}}