{
  "id": "2017-00334",
  "title": "Kain panjang",
  "source": "Bumblebee",
  "path": "./Data/json/",
  "content": "\n  accession_no_csv: 2017-00334\n\n  Image: \n\n  object_work_type: batik art folk costume\n\n  title_text: Kain panjang\n\n  preference: main\n\n  title_language: \n\n  creator_2: Soen King Oey\n\n  creator_role: textile designers\n\n  creation_date: Late 19th-early 20th century\n\n  creation_place_original_location: Pekalongan (Indonesia)\n\n  styles_periods_indexing_terms: Peranakan\n\n  inscriptions: \n\n  inscription_language: \n\n  shape: rectangular\n\n  materials_name: cotton (textile)\n\n  techniques_name: batik\n\n  object_colour: multicolored\n\n  physical_appearance: This is a batik kain panjang. The design features elongated triangles at both ends of the kain panjang\n against a dark background with rosette patterns. The middle section of the kain panjang is decorated with repeated floral bouquets against a cream background. There are no signatures on this kain panjang.\n\n  subject_terms_1: Peranakan birds (motifs) flower (motif) foliage (motif)\n\n  subject_terms_2: Motifs Ethnic costume Peranakan (Asian people) Batik\n\n  subject_terms_3: Peranakan costumes Batik\n\n  subject_terms_4: Kain panjang\n\n  sgcool_label_text: The design structure of this kain panjang is typical of north coast batik from the same period\n in particular the split kepalas (or elongated triangles) on both ends of the batik.  Bouquets of flowers embellish the main design field (badan) of the cloth\n creating a wallpaper effect.  They are reminiscent of the “wallpaper” patterns that are stamped on wallpaper with the wooden blocks.  This batik comes from the family collection of Oey Soen King (1861-1942)\n the first in three generations of documented batik-makers in Pekalongan.  Her batiks feature the classic layout typical of her time\n and are embellished with Chinese traditional motifs.  These motifs include lotus flowers\n centipedes and cloud motifs\n which are rendered sensitively and imaginatively.  The combination of natural red and blue dyes on a cream ground is also characteristic of batiks made during this period in the north coast of Java\n before the invention and widespread popularity of chemical dyes in batik sarongs by the late 19th century.  Oey Soen King’s pieces were all unsigned as signatures were not yet fashionable.\n",
  "createdDate": "20201125084521",
  "version": 0,
  "latest": false,
  "roles": [],
  "metadata": {
    "accession_no_csv": "2017-00334",
    "Image": "",
    "object_work_type": "batik art folk costume",
    "title_text": "Kain panjang",
    "preference": "main",
    "title_language": "",
    "creator_2": "Soen King Oey",
    "creator_role": "textile designers",
    "creation_date": "Late 19th-early 20th century",
    "creation_place_original_location": "Pekalongan (Indonesia)",
    "styles_periods_indexing_terms": "Peranakan",
    "inscriptions": "",
    "inscription_language": "",
    "shape": "rectangular",
    "materials_name": "cotton (textile)",
    "techniques_name": "batik",
    "object_colour": "multicolored",
    "physical_appearance": "This is a batik kain panjang. The design features elongated triangles at both ends of the kain panjang, against a dark background with rosette patterns. The middle section of the kain panjang is decorated with repeated floral bouquets against a cream background. There are no signatures on this kain panjang.",
    "subject_terms_1": "Peranakan birds (motifs) flower (motif) foliage (motif)",
    "subject_terms_2": "Motifs Ethnic costume Peranakan (Asian people) Batik",
    "subject_terms_3": "Peranakan costumes Batik",
    "subject_terms_4": "Kain panjang",
    "sgcool_label_text": "The design structure of this kain panjang is typical of north coast batik from the same period, in particular the split kepalas (or elongated triangles) on both ends of the batik.  Bouquets of flowers embellish the main design field (badan) of the cloth, creating a wallpaper effect.  They are reminiscent of the “wallpaper” patterns that are stamped on wallpaper with the wooden blocks.  This batik comes from the family collection of Oey Soen King (1861-1942), the first in three generations of documented batik-makers in Pekalongan.  Her batiks feature the classic layout typical of her time, and are embellished with Chinese traditional motifs.  These motifs include lotus flowers, centipedes and cloud motifs, which are rendered sensitively and imaginatively.  The combination of natural red and blue dyes on a cream ground is also characteristic of batiks made during this period in the north coast of Java, before the invention and widespread popularity of chemical dyes in batik sarongs by the late 19th century.  Oey Soen King’s pieces were all unsigned as signatures were not yet fashionable."
  },
  "nlpDate": "20201125084521",
  "connectorId": 0,
  "tags": {}
}