{"id":"2017-00486","title":"Bryde’s Fountain (After Marcel Duchamp)","source":"Bumblebee","path":"./Data/json/","content":"accession_no_csv:2017-00486\nImage:\nobject_work_type:installations (visual works)\ntitle_text:Bryde’s Fountain (After Marcel Duchamp)\npreference:main\ntitle_language:\ncreator_2:Krit Ngamsom\ncreator_1:Not indicated\ncreator_role:sculptors\ncreation_date:2016\ncreation_place_original_location:Thailand\nstyles_periods_indexing_terms:Contemporary (style of art)\ninscriptions:\ninscription_language:\nshape:irregular\nmaterials_name:fibreglass stainless steel ceramic (material) cement (construction material) mixed media\ntechniques_name:forming (physical activity) sculpting\nobject_colour:multicoloured\nedition_description:1 of 3\nphysical_appearance:The installation art depicts a sculpture that is positioned on the floor. The base of the sculpture is that of a whale. Its tail and its left flipper can be seen. The whale is sculpted in a curved shape\n with its mouth and tail curling upwards. Attached to its blowhole is a sculpture of a fountain. It has an oval basin and five tiers\n and water can be seen to be released at the top\nsubject_terms_1:sculpture (visual works) whales fountains adaptations (derivative objects)\nsubject_terms_2:Kinetic sculpture Installations (Art) Bryde whale Fountains Art Adaptations\nsubject_terms_3:Installation Art Sculpture\nsubject_terms_4:\nsgcool_label_text:Especially commissioned by SAM for the Exhibition Imaginarium: Over the Ocean\n Under the Sea\n Bryde’s Fountain is an adaptation of Krit Ngamsom’s earlier work R. Mutt’s Fountain from his widely praised series of works from his solo exhibition Already Mades (2011). The working fountain\n now placed above a stainless steel representation of a Bryde’s whale\n playfully evokes a whale’s blowhole. The whale\n also known as the Buddha’s whale\n resides in the Gulf of Thailand and is an auspicious sight. In presenting the work to audiences\n he hopes that good fortunes will smile down upon them.","createdDate":"20201018182636","version":0,"latest":false,"roles":[],"metadata":{"accession_no_csv":"2017-00486","Image":"","object_work_type":"installations (visual works)","title_text":"Bryde’s Fountain (After Marcel Duchamp)","preference":"main","title_language":"","creator_2":"Krit Ngamsom","creator_1":"Not indicated","creator_role":"sculptors","creation_date":"2016","creation_place_original_location":"Thailand","styles_periods_indexing_terms":"Contemporary (style of art)","inscriptions":"","inscription_language":"","shape":"irregular","materials_name":"fibreglass stainless steel ceramic (material) cement (construction material) mixed media","techniques_name":"forming (physical activity) sculpting","object_colour":"multicoloured","edition_description":"1 of 3","physical_appearance":"The installation art depicts a sculpture that is positioned on the floor. The base of the sculpture is that of a whale. Its tail and its left flipper can be seen. The whale is sculpted in a curved shape, with its mouth and tail curling upwards. Attached to its blowhole is a sculpture of a fountain. It has an oval basin and five tiers, and water can be seen to be released at the top","subject_terms_1":"sculpture (visual works) whales fountains adaptations (derivative objects)","subject_terms_2":"Kinetic sculpture Installations (Art) Bryde whale Fountains Art Adaptations","subject_terms_3":"Installation Art Sculpture","subject_terms_4":"","sgcool_label_text":"Especially commissioned by SAM for the Exhibition Imaginarium: Over the Ocean, Under the Sea, Bryde’s Fountain is an adaptation of Krit Ngamsom’s earlier work R. Mutt’s Fountain from his widely praised series of works from his solo exhibition Already Mades (2011). The working fountain, now placed above a stainless steel representation of a Bryde’s whale, playfully evokes a whale’s blowhole. The whale, also known as the Buddha’s whale, resides in the Gulf of Thailand and is an auspicious sight. In presenting the work to audiences, he hopes that good fortunes will smile down upon them."},"nlpDate":"20201018182636","connectorId":0,"tags":{}}