{
  "id": "2017-00179-002",
  "title": "Lim Hong Pei Collection Lim Hong Pei Collection: soldier on street",
  "source": "Bumblebee",
  "path": "./Data/json/",
  "content": "\n  accession_no_csv: 2017-00179-002\n\n  Image: \n\n  object_work_type: black-and-white photographs\n\n  title_text: Lim Hong Pei Collection Lim Hong Pei Collection: soldier on street\n\n  preference: main alternate\n\n  title_language: \n\n  creation_date: 1946\n\n  creation_place_original_location: Singapore\n\n  inscriptions: \n\n  inscription_language: \n\n  shape: rectangular\n\n  materials_name: paper (fiber product)\n\n  techniques_name: printing (process) photographic processes\n\n  object_colour: black-and-white (colors)\n\n  physical_appearance: This is a black-and-white photograph. It features a soldier in military uniform\n walking down a crowded street. On the right of the photograph\n is a cropped image of a woman\\u0027s back. The background of the photograph showsthe crowd wallking along the street flanked by rows of shops. There are no folds seen on the photograph.\n\n  subject_terms_1: resistance movements world wars soldiers\n\n  subject_terms_2: Lim\n Hong Pei\n 1922- World War\n 1939-1945 Photography Great Britain. Army. Force 136 Force 136 (Guerilla movement) Soldiers\n\n  subject_terms_3: 1942-1945 Japanese occupation Photography Force 136 (Guerilla movement) war personalities\n\n  subject_terms_4: \n\n  sgcool_label_text: These photographs belong to part of a collection of artefacts related to the World War II underground resistance movement known as Force 136. The collection of materials was gathered by Tan Chong Tee (1916- 2012)\n who was a key member of this resistance group. The collection consists of original materials belonging to Tan and other members of Force 136 dating from the 1940s to new materials reproduced from memory by Tan Chong Tee\n which date from the late 1980s to early 2000s. \\r\\n\\r\\nForce 136 was set up in July 1942 as part of the British Special Operations Executive (SOE). It recruited and trained local guerillas to gather intelligence and create an underground spy network to support planned British invasion of Japanese-occupied Malaya.\\r\\n\n",
  "createdDate": "20201125084525",
  "version": 0,
  "latest": false,
  "roles": [],
  "metadata": {
    "accession_no_csv": "2017-00179-002",
    "Image": "",
    "object_work_type": "black-and-white photographs",
    "title_text": "Lim Hong Pei Collection Lim Hong Pei Collection: soldier on street",
    "preference": "main alternate",
    "title_language": "",
    "creation_date": "1946",
    "creation_place_original_location": "Singapore",
    "inscriptions": "",
    "inscription_language": "",
    "shape": "rectangular",
    "materials_name": "paper (fiber product)",
    "techniques_name": "printing (process) photographic processes",
    "object_colour": "black-and-white (colors)",
    "physical_appearance": "This is a black-and-white photograph. It features a soldier in military uniform, walking down a crowded street. On the right of the photograph, is a cropped image of a woman\u0027s back. The background of the photograph showsthe crowd wallking along the street flanked by rows of shops. There are no folds seen on the photograph.",
    "subject_terms_1": "resistance movements world wars soldiers",
    "subject_terms_2": "Lim, Hong Pei, 1922- World War, 1939-1945 Photography Great Britain. Army. Force 136 Force 136 (Guerilla movement) Soldiers",
    "subject_terms_3": "1942-1945 Japanese occupation Photography Force 136 (Guerilla movement) war personalities",
    "subject_terms_4": "",
    "sgcool_label_text": "These photographs belong to part of a collection of artefacts related to the World War II underground resistance movement known as Force 136. The collection of materials was gathered by Tan Chong Tee (1916- 2012), who was a key member of this resistance group. The collection consists of original materials belonging to Tan and other members of Force 136 dating from the 1940s to new materials reproduced from memory by Tan Chong Tee, which date from the late 1980s to early 2000s. \r\n\r\nForce 136 was set up in July 1942 as part of the British Special Operations Executive (SOE). It recruited and trained local guerillas to gather intelligence and create an underground spy network to support planned British invasion of Japanese-occupied Malaya.\r\n"
  },
  "nlpDate": "20201125084525",
  "connectorId": 0,
  "tags": {}
}