{"id":"2017-00923","title":"Rolleiflex I, Franke \u0026 Heidecke","source":"Bumblebee","path":"./Data/json/","content":"accession_no_csv:2017-00923\nImage:\nobject_work_type:box cameras\ntitle_text:Rolleiflex I\n Franke \\u0026 Heidecke\npreference:main\ntitle_language:\ncreator_2:Rollei (?)\ncreator_role:manufacturers\ncreation_date:1928\ncreation_place_original_location:Germany\ninscriptions:\ninscription_language:\nshape:irregular\nmaterials_name:metal glass (material)\nobject_colour:black (color)\nphysical_appearance:This is a Rolleiflex box camera. It is a black box camera with a leather exterior. The front of the camera consists of two lenses\n arranged vertically on top of one another. There are inscriptions around the lens as well as the top front of the camera. The edges of the camera is slightly faded.\nsubject_terms_1:cameras (photographic equipment) photography (discipline) vintage (period)\nsubject_terms_2:Cameras Photography Vintage Rolleiflex camera\nsubject_terms_3:Photography\nsgcool_label_text:The Rolleiflex was introduced by the German company Franke \\u0026 Heidecke in 1929. It was a welcomed improvement from the smaller format of the 35mm film and was popular among both professional and amateur photographers. In Singapore\n the camera was available in shops like Singapore Photo Co. which was located at High Street in 1931. \\r\\n\\r\\nBefore the advent of the portable camera in the late 19th century\n the taking of photographs was limited to the studio. However portable cameras remained affordable only to the rich until the first decades of the 20th century.","createdDate":"20201018182636","version":0,"latest":false,"roles":[],"metadata":{"accession_no_csv":"2017-00923","Image":"","object_work_type":"box cameras","title_text":"Rolleiflex I, Franke \u0026 Heidecke","preference":"main","title_language":"","creator_2":"Rollei (?)","creator_role":"manufacturers","creation_date":"1928","creation_place_original_location":"Germany","inscriptions":"","inscription_language":"","shape":"irregular","materials_name":"metal glass (material)","object_colour":"black (color)","physical_appearance":"This is a Rolleiflex box camera. It is a black box camera with a leather exterior. The front of the camera consists of two lenses, arranged vertically on top of one another. There are inscriptions around the lens as well as the top front of the camera. The edges of the camera is slightly faded.","subject_terms_1":"cameras (photographic equipment) photography (discipline) vintage (period)","subject_terms_2":"Cameras Photography Vintage Rolleiflex camera","subject_terms_3":"Photography","sgcool_label_text":"The Rolleiflex was introduced by the German company Franke \u0026 Heidecke in 1929. It was a welcomed improvement from the smaller format of the 35mm film and was popular among both professional and amateur photographers. In Singapore, the camera was available in shops like Singapore Photo Co. which was located at High Street in 1931. \r\n\r\nBefore the advent of the portable camera in the late 19th century, the taking of photographs was limited to the studio. However portable cameras remained affordable only to the rich until the first decades of the 20th century."},"nlpDate":"20201018182636","connectorId":0,"tags":{}}