{
  "id": "2017-00806",
  "title": "Men\u0027s dark brown long silk gown (Changshan) with underlying weave of dots",
  "source": "Bumblebee",
  "path": "./Data/json/",
  "content": "\n  accession_no_csv: 2017-00806\n\n  Image: \n\n  object_work_type: robes (main garments) silks (costume by material)\n\n  title_text: Men\\u0027s dark brown long silk gown (Changshan) with underlying weave of dots\n\n  preference: main\n\n  title_language: \n\n  creation_date: 1920s-1930s\n\n  creation_place_original_location: Hong Kong (China)\n\n  styles_periods_indexing_terms: Chinese (culture or style)\n\n  inscriptions: \n\n  inscription_language: \n\n  shape: T-shaped?\n\n  materials_name: silk (textile)\n\n  techniques_name: weaving sewing (needleworking technique)\n\n  object_colour: brown (colour)\n\n  physical_appearance: This is a dark brown long silk gown that has mandarin buttons running from the collar down the proper right of the garment.\n\n  subject_terms_1: menswear folk costume? casual wear\n\n  subject_terms_2: Silk Ethnic costume Men\\u0027s clothing Robes\n\n  subject_terms_3: Chinese costumes\n\n  context_20: Bullion Trading Company “Yee Shing”\n\n  context_21: 20 Canal Road in Singapore\n\n  context_22: 1930s\n\n  context_23: 1930\n\n  context_24: 1939\n\n  sgcool_label_text: The long robe (known as ‘changshan’in Southern China and Hong Kong and ‘changpao’  in Northern China) was the standard informal garment worn by men during the early Republican period in China and Hong Kong. It is a one-piece long robe that can be worn alone or under a short jacket known as a ‘magua’ .\\r\\n\\r\\nThis long robe belonged to Mr Kaan Tat Choi\n who was a successful businessman in the bullion business. Mr Kaan expanded his business from Hong Kong to Malaya in the 1920s\n acquiring several rubber plantations along the east coast of Malaya. He also opened a bullion trading company called “Yee Shing” at 20 Canal Road in Singapore in the 1930s. \\r\\n\n",
  "createdDate": "20201125084516",
  "version": 0,
  "latest": false,
  "roles": [],
  "metadata": {
    "accession_no_csv": "2017-00806",
    "Image": "",
    "object_work_type": "robes (main garments) silks (costume by material)",
    "title_text": "Men\u0027s dark brown long silk gown (Changshan) with underlying weave of dots",
    "preference": "main",
    "title_language": "",
    "creation_date": "1920s-1930s",
    "creation_place_original_location": "Hong Kong (China)",
    "styles_periods_indexing_terms": "Chinese (culture or style)",
    "inscriptions": "",
    "inscription_language": "",
    "shape": "T-shaped?",
    "materials_name": "silk (textile)",
    "techniques_name": "weaving sewing (needleworking technique)",
    "object_colour": "brown (colour)",
    "physical_appearance": "This is a dark brown long silk gown that has mandarin buttons running from the collar down the proper right of the garment.",
    "subject_terms_1": "menswear folk costume? casual wear",
    "subject_terms_2": "Silk Ethnic costume Men\u0027s clothing Robes",
    "subject_terms_3": "Chinese costumes",
    "context_20": "Bullion Trading Company “Yee Shing”",
    "context_21": "20 Canal Road in Singapore",
    "context_22": "1930s",
    "context_23": "1930",
    "context_24": "1939",
    "sgcool_label_text": "The long robe (known as ‘changshan’in Southern China and Hong Kong and ‘changpao’  in Northern China) was the standard informal garment worn by men during the early Republican period in China and Hong Kong. It is a one-piece long robe that can be worn alone or under a short jacket known as a ‘magua’ .\r\n\r\nThis long robe belonged to Mr Kaan Tat Choi, who was a successful businessman in the bullion business. Mr Kaan expanded his business from Hong Kong to Malaya in the 1920s, acquiring several rubber plantations along the east coast of Malaya. He also opened a bullion trading company called “Yee Shing” at 20 Canal Road in Singapore in the 1930s. \r\n"
  },
  "nlpDate": "20201125084516",
  "connectorId": 0,
  "tags": {}
}