{
  "id": "2017-00837 to 00841",
  "title": "\"\"\"Spotted Nyona\"\" series \"",
  "source": "Bumblebee",
  "path": "./Data/json/",
  "content": "\n  accession_no_csv: 2017-00837 to 00841\n\n  Image: \n\n  object_work_type: porcelain (visual works) containers (receptacles)\n\n  title_text: \\\\\\Spotted Nyona\\\\ series \\\n\n  preference: main\n\n  title_language: \n\n  creator_2: Hans Tan\n\n  creator_role: designers\n\n  creation_date: 2012\n\n  creation_place_original_location: Singapore\n\n  styles_periods_indexing_terms: Contemporary (style of art)\n\n  inscriptions: \n\n  inscription_language: \n\n  shape: concave cylindrical biconvex irregular\n\n  materials_name: clay ceramic glaze porcelain (material)\n\n  object_colour: technique of sandblasting taken from SGCOOL label field\n\n  physical_appearance: This is a set of porcelain ware whose original aesthetic remains in the form of spots/dots while the rest have been sandblasted away\n thereby exposing the white porcelain beneath.\n\n  subject_terms_1: Chinese (culture or style) commissions (orders for works) Peranakan\n\n  subject_terms_2: Reinterpreting history Porcelain\n Peranakan Contemporary art Geometry in art Zhongguo wen hua xi lie\n\n  subject_terms_3: customs Decorative arts\n\n  sgcool_label_text: refer to parts\n",
  "createdDate": "20201125084516",
  "version": 0,
  "latest": false,
  "roles": [],
  "metadata": {
    "accession_no_csv": "2017-00837 to 00841",
    "Image": "",
    "object_work_type": "porcelain (visual works) containers (receptacles)",
    "title_text": "\"\"\"Spotted Nyona\"\" series \"",
    "preference": "main",
    "title_language": "",
    "creator_2": "Hans Tan",
    "creator_role": "designers",
    "creation_date": "2012",
    "creation_place_original_location": "Singapore",
    "styles_periods_indexing_terms": "Contemporary (style of art)",
    "inscriptions": "",
    "inscription_language": "",
    "shape": "concave cylindrical biconvex irregular",
    "materials_name": "clay ceramic glaze porcelain (material)",
    "object_colour": "technique of sandblasting taken from SGCOOL label field",
    "physical_appearance": "This is a set of porcelain ware whose original aesthetic remains in the form of spots/dots while the rest have been sandblasted away, thereby exposing the white porcelain beneath.",
    "subject_terms_1": "Chinese (culture or style) commissions (orders for works) Peranakan",
    "subject_terms_2": "Reinterpreting history Porcelain, Peranakan Contemporary art Geometry in art Zhongguo wen hua xi lie",
    "subject_terms_3": "customs Decorative arts",
    "sgcool_label_text": "refer to parts"
  },
  "nlpDate": "20201125084516",
  "connectorId": 0,
  "tags": {}
}