{
  "id": "2017-00156-024",
  "title": "Lung Chui Ying Collection: Photographs, Printed Images, Pamphlets and Clippings  collected by Lung Chui Ying ????? Lung Chiu Ying Collection: three men in front of Cathay Building",
  "source": "Bumblebee",
  "path": "./Data/json/",
  "content": "\n  accession_no_csv: 2017-00156-024\n\n  Image: \n\n  object_work_type: clippings (information artifacts)\n\n  title_text: Lung Chui Ying Collection: Photographs\n Printed Images\n Pamphlets and Clippings  collected by Lung Chui Ying ????? Lung Chiu Ying Collection: three men in front of Cathay Building\n\n  preference: alternate alternate main\n\n  title_language: \n\n  creation_date: Not indicated\n\n  creation_place_original_location: Singapore\n\n  inscriptions: \n\n  inscription_language: \n\n  shape: rectangular\n\n  materials_name: paper (fiber product)\n\n  techniques_name: printing (process)\n\n  object_colour: black-and-white (colors)\n\n  physical_appearance: This is a black-and-white clipping. The clipping features a photograph with a short blurb underneath it. The photograph shows three men standing in a row. Behind them is the Cathay building. There are some pen marks across the clipping near the bottom.\n\n  subject_terms_1: world wars resistance movements theatres (buildings)\n\n  subject_terms_2: World War\n 1939-1945 Great Britain. Army. Force 136 Force 136 (Guerilla movement) Clippings (Books\n newspapers\n etc.) Cathay (Organization)\n\n  subject_terms_3: Force 136 (Guerilla movement) Lung\n Chiu Ying 1942-1945 Japanese occupation Cathay Building\n\n  subject_terms_4: \n\n  sgcool_label_text: These photographs\n printed images\n pamphlets and clippings belong to Lung Chui Ying and is part of a larger collection related to the World War II underground resistance movement known as Force 136. The collection of materials was gathered by Tan Chong Tee (1916- 2012)\n who was a key member of this resistance group. The collection consists of original materials belonging to Tan and other members of Force 136 dating from the 1940s to new materials reproduced from memory by Tan Chong Tee\n which date from the mid-1990s to early 2000s. \\r\\n\\r\\nForce 136 was set up in July 1942 as part of the British Special Operations Executive (SOE). It recruited and trained local guerillas to gather intelligence and create an underground spy network to support planned British invasion of Japanese-occupied Malaya.\\r\\n\\r\\nLung Chui Ying was a Hainanese born in Johor and recruited as a Force 136 member to fight against the Japanese in Malaya. \\r\\n\n",
  "createdDate": "20201120223707",
  "version": 0,
  "latest": false,
  "roles": [],
  "metadata": {
    "accession_no_csv": "2017-00156-024",
    "Image": "",
    "object_work_type": "clippings (information artifacts)",
    "title_text": "Lung Chui Ying Collection: Photographs, Printed Images, Pamphlets and Clippings  collected by Lung Chui Ying ????? Lung Chiu Ying Collection: three men in front of Cathay Building",
    "preference": "alternate alternate main",
    "title_language": "",
    "creation_date": "Not indicated",
    "creation_place_original_location": "Singapore",
    "inscriptions": "",
    "inscription_language": "",
    "shape": "rectangular",
    "materials_name": "paper (fiber product)",
    "techniques_name": "printing (process)",
    "object_colour": "black-and-white (colors)",
    "physical_appearance": "This is a black-and-white clipping. The clipping features a photograph with a short blurb underneath it. The photograph shows three men standing in a row. Behind them is the Cathay building. There are some pen marks across the clipping near the bottom.",
    "subject_terms_1": "world wars resistance movements theatres (buildings)",
    "subject_terms_2": "World War, 1939-1945 Great Britain. Army. Force 136 Force 136 (Guerilla movement) Clippings (Books, newspapers, etc.) Cathay (Organization)",
    "subject_terms_3": "Force 136 (Guerilla movement) Lung, Chiu Ying 1942-1945 Japanese occupation Cathay Building",
    "subject_terms_4": "",
    "sgcool_label_text": "These photographs, printed images, pamphlets and clippings belong to Lung Chui Ying and is part of a larger collection related to the World War II underground resistance movement known as Force 136. The collection of materials was gathered by Tan Chong Tee (1916- 2012), who was a key member of this resistance group. The collection consists of original materials belonging to Tan and other members of Force 136 dating from the 1940s to new materials reproduced from memory by Tan Chong Tee, which date from the mid-1990s to early 2000s. \r\n\r\nForce 136 was set up in July 1942 as part of the British Special Operations Executive (SOE). It recruited and trained local guerillas to gather intelligence and create an underground spy network to support planned British invasion of Japanese-occupied Malaya.\r\n\r\nLung Chui Ying was a Hainanese born in Johor and recruited as a Force 136 member to fight against the Japanese in Malaya. \r\n"
  },
  "nlpDate": "20201120223707",
  "connectorId": 0,
  "tags": {}
}