{
  "id": "2017-00136",
  "title": "Tan Chong Tee Collection: Tan Chong Tee Tan Chong Tee Collection: Photograph featuring Tan Chong Tee with note by Colonel Broome",
  "source": "Bumblebee",
  "path": "./Data/json/",
  "content": "\n  accession_no_csv: 2017-00136\n\n  Image: \n\n  object_work_type: photographs studio portraits\n\n  title_text: Tan Chong Tee Collection: Tan Chong Tee Tan Chong Tee Collection: Photograph featuring Tan Chong Tee with note by Colonel Broome\n\n  preference: main alternate\n\n  title_language: \n\n  creation_date: 1946\n\n  creation_place_original_location: Singapore\n\n  inscriptions: \n\n  inscription_language: \n\n  shape: rectangular\n\n  materials_name: paper (fiber product)\n\n  techniques_name: printing (process)\n\n  object_colour: black-and-white (colors)\n\n  physical_appearance: These are two studio portrait photographs of Tan Chong Tee. He is shown dressed in a uniform in both pictures. The uniform features a circular badge on the left shoulder sleeve\n and a rectangular badge on the left collar. The photograph on the left shows him standing on a tiled floor against a plain background\n with his right hand on his hip. The photograph on the right shows him seated\n with only half of his body in the photograph.\n\n  subject_terms_1: resistance movements world wars soldiers\n\n  subject_terms_2: World War\n 1939-1945 Chen\n Chongzhi\n 1916- Great Britain. Army. Force 136 Force 136 (Guerilla movement) Portrait photography Soldiers\n\n  subject_terms_3: 1942-1945 Japanese occupation Tan\n Chong Tee Force 136 (Guerilla movement) Portrait photography\n\n  subject_terms_4: \n\n  sgcool_label_text: This photograph belongs to part of a collection of artefacts related to the World War II underground resistance movement known as Force 136. The collection of materials was gathered by Tan Chong Tee (1916- 2012)\n who was a key member of this resistance group. The collection consists of original materials belonging to Tan and other members of Force 136 dating from the 1940s to new materials reproduced from memory by Tan Chong Tee\n which date from the late 1980s to early 2000s. \\r\\n\\r\\nForce 136 was set up in July 1942 as part of the British Special Operations Executive (SOE). It recruited and trained local guerillas to gather intelligence and create an underground spy network to support planned British invasion of Japanese-occupied Malaya\n",
  "createdDate": "20201201203308",
  "version": 0,
  "latest": false,
  "roles": [],
  "metadata": {
    "accession_no_csv": "2017-00136",
    "Image": "",
    "object_work_type": "photographs studio portraits",
    "title_text": "Tan Chong Tee Collection: Tan Chong Tee Tan Chong Tee Collection: Photograph featuring Tan Chong Tee with note by Colonel Broome",
    "preference": "main alternate",
    "title_language": "",
    "creation_date": "1946",
    "creation_place_original_location": "Singapore",
    "inscriptions": "",
    "inscription_language": "",
    "shape": "rectangular",
    "materials_name": "paper (fiber product)",
    "techniques_name": "printing (process)",
    "object_colour": "black-and-white (colors)",
    "physical_appearance": "These are two studio portrait photographs of Tan Chong Tee. He is shown dressed in a uniform in both pictures. The uniform features a circular badge on the left shoulder sleeve, and a rectangular badge on the left collar. The photograph on the left shows him standing on a tiled floor against a plain background, with his right hand on his hip. The photograph on the right shows him seated, with only half of his body in the photograph.",
    "subject_terms_1": "resistance movements world wars soldiers",
    "subject_terms_2": "World War, 1939-1945 Chen, Chongzhi, 1916- Great Britain. Army. Force 136 Force 136 (Guerilla movement) Portrait photography Soldiers",
    "subject_terms_3": "1942-1945 Japanese occupation Tan, Chong Tee Force 136 (Guerilla movement) Portrait photography",
    "subject_terms_4": "",
    "sgcool_label_text": "This photograph belongs to part of a collection of artefacts related to the World War II underground resistance movement known as Force 136. The collection of materials was gathered by Tan Chong Tee (1916- 2012), who was a key member of this resistance group. The collection consists of original materials belonging to Tan and other members of Force 136 dating from the 1940s to new materials reproduced from memory by Tan Chong Tee, which date from the late 1980s to early 2000s. \r\n\r\nForce 136 was set up in July 1942 as part of the British Special Operations Executive (SOE). It recruited and trained local guerillas to gather intelligence and create an underground spy network to support planned British invasion of Japanese-occupied Malaya"
  },
  "nlpDate": "20201201203308",
  "connectorId": 0,
  "tags": {}
}