{"id":"2017-00157","title":"Letters from Lim Bo Seng to Lee Shao Meng","source":"Bumblebee","path":"./Data/json/","content":"accession_no_csv:2017-00157\nImage:\nobject_work_type:letters (correspondence)\ntitle_text:Letters from Lim Bo Seng to Lee Shao Meng\npreference:main\ntitle_language:\ncreator_2:Lim Bo Seng (?)\ncreator_1:Lim\n Bo Seng\n 1909-1944\ncreator_role:authors\ncreation_date:1943\ncreation_place_original_location:Singapore\ninscriptions:\ninscription_language:\nshape:rectangular\nmaterials_name:paper (fiber product) ink\ntechniques_name:writing (processes)\nobject_colour:black-and-white (colors)\nphysical_appearance:This is a handwritten letter. It is writen in black ink against a plain piece of paper. The date is written on the top-right of the letter\n and it is signed at the bottom-right. There is a photograph identification of a man at the bottom-right of the letter. He is wearing spectacles\n and dressed in a white suit and dark tie. The letter is slightly smudged in places\n with visible crease lines along the folds.\nsubject_terms_1:world wars resistance movements handwriting\nsubject_terms_2:World War\n 1939-1945 Great Britain. Army. Force 136 Force 136 (Guerilla movement) Letters Lim\n Bo Seng\n 1909-1944 Chen\n Chongzhi\n 1916- Writing\nsubject_terms_3:Force 136 (Guerilla movement) 1942-1945 Japanese occupation Letters Lim\n Bo Seng Tan\n Chong Tee Lee\n Shao Meng\nsubject_terms_4:\ncontext_1:World War\n 1939-1945 1942-1945 Japanese Occupation\ncontext_2:world wars occupations (armed conflicts)\ncontext_3:1939-1945 1942-1945\ncontext_4:1939 1942\ncontext_5:1945 1945\ncontext_6:Malaya Singapore\ncontext_7:Great Britain. Army. Force 136\ncontext_8:armed forces\nsgcool_label_text:This letter belongs to part of a collection of artefacts related to the World War II underground resistance movement known as Force 136. The collection of materials was gathered by Tan Chong Tee (1916- 2012)\n who was a key member of this resistance group. The collection consists of original materials belonging to Tan and other members of Force 136 dating from the 1940s to new materials reproduced from memory by Tan Chong Tee\n which date from the mid-1990s to early 2000s. \\r\\n\\r\\nForce 136 was set up in July 1942 as part of the British Special Operations Executive (SOE). It recruited and trained local guerillas to gather intelligence and create an underground spy network to support planned British invasion of Japanese-occupied Malaya.\\r\\n\\r\\nThis letter is written in English by Lim Bo Seng\n the war hero to Miss Lee Shao Meng ???\n wife of Tan Chong Tee. \\r\\n","createdDate":"20201119143406","version":0,"latest":false,"roles":[],"metadata":{"accession_no_csv":"2017-00157","Image":"","object_work_type":"letters (correspondence)","title_text":"Letters from Lim Bo Seng to Lee Shao Meng","preference":"main","title_language":"","creator_2":"Lim Bo Seng (?)","creator_1":"Lim, Bo Seng, 1909-1944","creator_role":"authors","creation_date":"1943","creation_place_original_location":"Singapore","inscriptions":"","inscription_language":"","shape":"rectangular","materials_name":"paper (fiber product) ink","techniques_name":"writing (processes)","object_colour":"black-and-white (colors)","physical_appearance":"This is a handwritten letter. It is writen in black ink against a plain piece of paper. The date is written on the top-right of the letter, and it is signed at the bottom-right. There is a photograph identification of a man at the bottom-right of the letter. He is wearing spectacles, and dressed in a white suit and dark tie. The letter is slightly smudged in places, with visible crease lines along the folds.","subject_terms_1":"world wars resistance movements handwriting","subject_terms_2":"World War, 1939-1945 Great Britain. Army. Force 136 Force 136 (Guerilla movement) Letters Lim, Bo Seng, 1909-1944 Chen, Chongzhi, 1916- Writing","subject_terms_3":"Force 136 (Guerilla movement) 1942-1945 Japanese occupation Letters Lim, Bo Seng Tan, Chong Tee Lee, Shao Meng","subject_terms_4":"","context_1":"World War, 1939-1945 1942-1945 Japanese Occupation","context_2":"world wars occupations (armed conflicts)","context_3":"1939-1945 1942-1945","context_4":"1939 1942","context_5":"1945 1945","context_6":"Malaya Singapore","context_7":"Great Britain. Army. Force 136","context_8":"armed forces","sgcool_label_text":"This letter belongs to part of a collection of artefacts related to the World War II underground resistance movement known as Force 136. The collection of materials was gathered by Tan Chong Tee (1916- 2012), who was a key member of this resistance group. The collection consists of original materials belonging to Tan and other members of Force 136 dating from the 1940s to new materials reproduced from memory by Tan Chong Tee, which date from the mid-1990s to early 2000s. \r\n\r\nForce 136 was set up in July 1942 as part of the British Special Operations Executive (SOE). It recruited and trained local guerillas to gather intelligence and create an underground spy network to support planned British invasion of Japanese-occupied Malaya.\r\n\r\nThis letter is written in English by Lim Bo Seng, the war hero to Miss Lee Shao Meng ???, wife of Tan Chong Tee. \r\n"},"nlpDate":"20201119143406","connectorId":0,"tags":{}}