{"id":"2017-00936-001 and 002 ","title":"Gold buckle with silver belt","source":"Bumblebee","path":"./Data/json/","content":"accession_no_csv:2017-00936-001 and 002 \nImage:\nobject_work_type:belts (costume accessories)\ntitle_text:Gold buckle with silver belt\npreference:main\ntitle_language:\ncreation_date:1950s\ncreation_place_original_location:Singapore\ninscriptions:\ninscription_language:\nshape:irregular\nmaterials_name:gold (metal)  silver (metal) * I put this because the belt is actually silver\ntechniques_name:metalworking  casting (process)\nobject_colour:multicoloured\nphysical_appearance:This is a silver belt fastened with a gold buckle. The buckle has lobed edges\n an escutcheon in the center\n surrounded by birds and foliage in open metal work. The belt is made of links and three rows of florets.\nsubject_terms_1:belt buckles  florets (tools)  coats of arms  foliage (motif)  birds (motif)\nsubject_terms_2:Belts (Clothing)  Escutcheons (Heraldry) Birds in art  Flowers in art Leaves in art\nsubject_terms_3:Decorative arts\nsgcool_label_text:This gold buckle with lobed edges has at its centre an escutcheon flanked by two birds with their wings outstretched as if in flight.  The composition resembles a coat of arms and is seamlessly woven into the background of rich foliage\n all cast in delicate openwork. The shape of the buckle is a variation of the ogive which was popular among the Malays and Peranakan Chinese. Nyonyas often wore buckles with metal belts. The owner wore this buckle with a silver belt\n made up of links and three rows of florets.","createdDate":"20201119143406","version":0,"latest":false,"roles":[],"metadata":{"accession_no_csv":"2017-00936-001 and 002 ","Image":"","object_work_type":"belts (costume accessories)","title_text":"Gold buckle with silver belt","preference":"main","title_language":"","creation_date":"1950s","creation_place_original_location":"Singapore","inscriptions":"","inscription_language":"","shape":"irregular","materials_name":"gold (metal)  silver (metal) * I put this because the belt is actually silver","techniques_name":"metalworking  casting (process)","object_colour":"multicoloured","physical_appearance":"This is a silver belt fastened with a gold buckle. The buckle has lobed edges, an escutcheon in the center, surrounded by birds and foliage in open metal work. The belt is made of links and three rows of florets.","subject_terms_1":"belt buckles  florets (tools)  coats of arms  foliage (motif)  birds (motif)","subject_terms_2":"Belts (Clothing)  Escutcheons (Heraldry) Birds in art  Flowers in art Leaves in art","subject_terms_3":"Decorative arts","sgcool_label_text":"This gold buckle with lobed edges has at its centre an escutcheon flanked by two birds with their wings outstretched as if in flight.  The composition resembles a coat of arms and is seamlessly woven into the background of rich foliage, all cast in delicate openwork. The shape of the buckle is a variation of the ogive which was popular among the Malays and Peranakan Chinese. Nyonyas often wore buckles with metal belts. The owner wore this buckle with a silver belt, made up of links and three rows of florets."},"nlpDate":"20201119143406","connectorId":0,"tags":{}}