{"id":"2017-00918","title":"Photograph of Oei Tiong Ham Oei Tiong Ham","source":"Bumblebee","path":"./Data/json/","content":"accession_no_csv:2017-00918\nImage:\nobject_work_type:black-and-white photographs studio portraits\ntitle_text:Photograph of Oei Tiong Ham Oei Tiong Ham\npreference:alternate main\ntitle_language:\ncreation_date:1920\ncreation_place_original_location:Singapore\ninscriptions:\ninscription_language:\nshape:rectangular\nmaterials_name:paper (fiber product)\ntechniques_name:printing (process) photography (process)\nobject_colour:black-and-white (colors)\nphysical_appearance:This is a black-and-white photograph of a man in a suit. He is seated on a long chair\n with a large paned window behind him. His body is tilted slightly towards the left\n with only his gaze towards the front. His hands are placed together in front of him\n with the right leg slightly forward from his left. There are no inscriptions seen on the photograph.\nsubject_terms_1:photographs businessmen Peranakan\nsubject_terms_2:Photographs Peranakan (Asian people) Businessmen Oei\n Tiong Ham\n 1866-1924\nsubject_terms_3:Portrait photography Oei\n Tiong Ham\nsgcool_label_text:This is a photograph of Oei Tiong Ham\n a wealthy businessman and Majoor (major) of the Chinese community in Semarang.  Seated on a chair\n he is dressed in a suit\n and was reportedly the first Chinese man in Semarang to adopt Western clothing\n given its political significance. Oei Tiong Ham made his fortune in sugar production and opium trading and was known as the “Sugar King” of Indonesia\n He donated land  for the construction of the Tao Nan School building (now  Peranakan Museum) in 1910. The rise in the number of photography studios in the 1850s led to the circulation of nineteenth-century European-styled portraits in the Straits Settlements and Dutch East Indies.","createdDate":"20201018182636","version":0,"latest":false,"roles":[],"metadata":{"accession_no_csv":"2017-00918","Image":"","object_work_type":"black-and-white photographs studio portraits","title_text":"Photograph of Oei Tiong Ham Oei Tiong Ham","preference":"alternate main","title_language":"","creation_date":"1920","creation_place_original_location":"Singapore","inscriptions":"","inscription_language":"","shape":"rectangular","materials_name":"paper (fiber product)","techniques_name":"printing (process) photography (process)","object_colour":"black-and-white (colors)","physical_appearance":"This is a black-and-white photograph of a man in a suit. He is seated on a long chair, with a large paned window behind him. His body is tilted slightly towards the left, with only his gaze towards the front. His hands are placed together in front of him, with the right leg slightly forward from his left. There are no inscriptions seen on the photograph.","subject_terms_1":"photographs businessmen Peranakan","subject_terms_2":"Photographs Peranakan (Asian people) Businessmen Oei, Tiong Ham, 1866-1924","subject_terms_3":"Portrait photography Oei, Tiong Ham","sgcool_label_text":"This is a photograph of Oei Tiong Ham, a wealthy businessman and Majoor (major) of the Chinese community in Semarang.  Seated on a chair, he is dressed in a suit, and was reportedly the first Chinese man in Semarang to adopt Western clothing, given its political significance. Oei Tiong Ham made his fortune in sugar production and opium trading and was known as the “Sugar King” of Indonesia, He donated land  for the construction of the Tao Nan School building (now  Peranakan Museum) in 1910. The rise in the number of photography studios in the 1850s led to the circulation of nineteenth-century European-styled portraits in the Straits Settlements and Dutch East Indies."},"nlpDate":"20201018182636","connectorId":0,"tags":{}}