{"id":"2017-00928","title":"Violin and case","source":"Bumblebee","path":"./Data/json/","content":"accession_no_csv:2017-00928\nImage:\nobject_work_type:violins\ntitle_text:Violin and case\npreference:main\ntitle_language:\ncreation_place_original_location:China\ninscriptions:\ninscription_language:\nshape:irregular\nobject_colour:multicolored\nphysical_appearance:This is a violin with a violin case and accessories. The exterior of the case is black\n with a green inner lining. The case has a handle at the side and a silver lock. On the underside of the case lid\n there are two violin bows. The body of the violin is brown. On the outside of the case\n there is a blue cloth\n a key\n and violin rosins.\nsubject_terms_1:violin cases rosin bows (chordophone components) musical instruments\nsubject_terms_2:Violin Violin cases Gums and resins Violin bows Dondang sayang Musical instruments\nsubject_terms_3:Music Dondang sayang Koh\n Hoon Teck\nsgcool_label_text:The violin and the Malay drum (rebana) are two of the principal musical instruments used in Dondang Sayang\n an exchange of songs\n which made use of the pantun (a Malay poetic form). These instruments belonged to Koh Hoon Teck\n who founded the Gunong Sayang Association in 1910\n one of the first Peranakan theatre associations in Singapore\n which is still active today. Koh excelled at the violin and also mentored prominent singers such as his nephew Gwee Peng Kwee. Koh’s company (founded in 1905)\n Koh and Company\n published five volumes of Malay poems for Dondang Sayang which were compiled by Koh and his father.","createdDate":"20201018182636","version":0,"latest":false,"roles":[],"metadata":{"accession_no_csv":"2017-00928","Image":"","object_work_type":"violins","title_text":"Violin and case","preference":"main","title_language":"","creation_place_original_location":"China","inscriptions":"","inscription_language":"","shape":"irregular","object_colour":"multicolored","physical_appearance":"This is a violin with a violin case and accessories. The exterior of the case is black, with a green inner lining. The case has a handle at the side and a silver lock. On the underside of the case lid, there are two violin bows. The body of the violin is brown. On the outside of the case, there is a blue cloth, a key, and violin rosins.","subject_terms_1":"violin cases rosin bows (chordophone components) musical instruments","subject_terms_2":"Violin Violin cases Gums and resins Violin bows Dondang sayang Musical instruments","subject_terms_3":"Music Dondang sayang Koh, Hoon Teck","sgcool_label_text":"The violin and the Malay drum (rebana) are two of the principal musical instruments used in Dondang Sayang, an exchange of songs, which made use of the pantun (a Malay poetic form). These instruments belonged to Koh Hoon Teck, who founded the Gunong Sayang Association in 1910, one of the first Peranakan theatre associations in Singapore, which is still active today. Koh excelled at the violin and also mentored prominent singers such as his nephew Gwee Peng Kwee. Koh’s company (founded in 1905), Koh and Company, published five volumes of Malay poems for Dondang Sayang which were compiled by Koh and his father."},"nlpDate":"20201018182636","connectorId":0,"tags":{}}