{"id":"2017-00427","title":"Drawn fabric template","source":"Bumblebee","path":"./Data/json/","content":"accession_no_csv:2017-00427\nImage:\nobject_work_type:templates (shaping tools)\ntitle_text:Drawn fabric template\npreference:main\ntitle_language:\ncreation_date:early 20th century\ncreation_place_original_location:Pulau Pinang (Malaysia : State)\ninscriptions:\ninscription_language:\nshape:rectangular\nmaterials_name:canvas (textile) ink\ntechniques_name:drawing (image-making)\nobject_colour:multicolored\nphysical_appearance:This is a drawn fabric template. It consists of a horizontal scrolling floral pattern on a long canvas. Along the central pattern is a repeating motif of a pair of birds flanking a singular lily stalk. The motif is set against a foliate background\n with a row of flowers on either side of the pattern.\nsubject_terms_1:textile art (visual works) birds (motifs) flower (motif) patterns (design elements)\nsubject_terms_2:Textile crafts Textile design Motifs\nsubject_terms_3:Textile art and design Vanishing trade\nsgcool_label_text:Fabric templates were used to guide the embroiderer. Along the central border is a repeating motif of a pair of birds flanking a singular lily stalk\n set against a foliate background. A row of flowers on both sides complete the pattern.\\r\\n\\r\\nThe small holes of double-thread Penelope canvas and other kinds of counted-thread canvases\n made it possible to create out of beads designs which were originally used for silk embroidery. The fabric was cut diagonally so as to align beads in a vertical position.\\r\\n","createdDate":"20201119143406","version":0,"latest":false,"roles":[],"metadata":{"accession_no_csv":"2017-00427","Image":"","object_work_type":"templates (shaping tools)","title_text":"Drawn fabric template","preference":"main","title_language":"","creation_date":"early 20th century","creation_place_original_location":"Pulau Pinang (Malaysia : State)","inscriptions":"","inscription_language":"","shape":"rectangular","materials_name":"canvas (textile) ink","techniques_name":"drawing (image-making)","object_colour":"multicolored","physical_appearance":"This is a drawn fabric template. It consists of a horizontal scrolling floral pattern on a long canvas. Along the central pattern is a repeating motif of a pair of birds flanking a singular lily stalk. The motif is set against a foliate background, with a row of flowers on either side of the pattern.","subject_terms_1":"textile art (visual works) birds (motifs) flower (motif) patterns (design elements)","subject_terms_2":"Textile crafts Textile design Motifs","subject_terms_3":"Textile art and design Vanishing trade","sgcool_label_text":"Fabric templates were used to guide the embroiderer. Along the central border is a repeating motif of a pair of birds flanking a singular lily stalk, set against a foliate background. A row of flowers on both sides complete the pattern.\r\n\r\nThe small holes of double-thread Penelope canvas and other kinds of counted-thread canvases, made it possible to create out of beads designs which were originally used for silk embroidery. The fabric was cut diagonally so as to align beads in a vertical position.\r\n"},"nlpDate":"20201119143406","connectorId":0,"tags":{}}