{"id":"2017-01040-136","title":"\"Personal photograph album titled \"\"Sixteen Months in Singapore\"\"\" Sixteen Months in Singapore: Photograph of Corporal A. Silver at the beach","source":"Bumblebee","path":"./Data/json/","content":"accession_no_csv:2017-01040-136\nImage:\nobject_work_type:black-and-white photographs photographs\ntitle_text:\\Personal photograph album titled \\\\Sixteen Months in Singapore\\\\\\ Sixteen Months in Singapore: Photograph of Corporal A. Silver at the beach\npreference:alternate main\ntitle_language:\ncreation_date:1951-1952\ncreation_place_original_location:Singapore\ninscriptions:\ninscription_language:\nshape:rectangular\nmaterials_name:paper (fiber product)\ntechniques_name:photographic processes\nobject_colour:black-and-white (colors)\nphysical_appearance:This is a black-and-white photograph. It is rectangular in shape and portrait in orientation. It features a woman in a bathing suit\n sitting on a beach towel\n on sand. Her legs are outstretched and she is facing downwards. She is photographed in mid-action\n with her hands towards the left of the photograph. Behind her\n there are several items seen\n including a bag\n several magazines\n and shoes\nsubject_terms_1:snapshots women (female humans) beaches recreation\nsubject_terms_2:Photographs Portrait photography Women Beaches Recreation\nsubject_terms_3:Portrait photography Women\nsubject_terms_4:\nsgcool_label_text:This is a personal photograph album that belonged to a Corporal A. Silver who spent 16 months in Singapore between 1951 and 1952. Silver was presumably a Jewish lady who was stationed in Singapore to serve at the Royal Air Force (RAF) Hospital at Changi. The album contains photographs that document her working and personal life\n including friends she made within the Jewish community in Singapore.","createdDate":"20201018182637","version":0,"latest":false,"roles":[],"metadata":{"accession_no_csv":"2017-01040-136","Image":"","object_work_type":"black-and-white photographs photographs","title_text":"\"Personal photograph album titled \"\"Sixteen Months in Singapore\"\"\" Sixteen Months in Singapore: Photograph of Corporal A. Silver at the beach","preference":"alternate main","title_language":"","creation_date":"1951-1952","creation_place_original_location":"Singapore","inscriptions":"","inscription_language":"","shape":"rectangular","materials_name":"paper (fiber product)","techniques_name":"photographic processes","object_colour":"black-and-white (colors)","physical_appearance":"This is a black-and-white photograph. It is rectangular in shape and portrait in orientation. It features a woman in a bathing suit, sitting on a beach towel, on sand. Her legs are outstretched and she is facing downwards. She is photographed in mid-action, with her hands towards the left of the photograph. Behind her, there are several items seen, including a bag, several magazines, and shoes","subject_terms_1":"snapshots women (female humans) beaches recreation","subject_terms_2":"Photographs Portrait photography Women Beaches Recreation","subject_terms_3":"Portrait photography Women","subject_terms_4":"","sgcool_label_text":"This is a personal photograph album that belonged to a Corporal A. Silver who spent 16 months in Singapore between 1951 and 1952. Silver was presumably a Jewish lady who was stationed in Singapore to serve at the Royal Air Force (RAF) Hospital at Changi. The album contains photographs that document her working and personal life, including friends she made within the Jewish community in Singapore."},"nlpDate":"20201018182637","connectorId":0,"tags":{}}