{
  "id": "2017-00553",
  "title": "The Journey of Panji",
  "source": "Bumblebee",
  "path": "./Data/json/",
  "content": "\n  accession_no_csv: 2017-00553\n\n  Image: \n\n  object_work_type: prints (visual works) installations (visual works)\n\n  title_text: The Journey of Panji\n\n  preference: main\n\n  title_language: \n\n  creator_2: Eddy Susanto\n\n  creator_role: artists (visual artists)\n\n  creation_date: 2016\n\n  creation_place_original_location: Indonesia\n\n  styles_periods_indexing_terms: Contemporary (style of art)\n\n  inscriptions: \n\n  inscription_language: \n\n  shape: irregular\n\n  materials_name: canvas (textile material) wood (plant material) Ink acrylic paint\n\n  techniques_name: installing\n\n  object_colour: multicolored\n\n  physical_appearance: This installation depicts the collection of stories\n the Wangbang Wideya\n written by S.O. Robson\n as a physical artwork. There is a large sculpture of the book on the ground\n with letters spilling out from its sides. Behind the book\n the letters lead up to a screen. On the screen are illustrated images of human figures in various scenes.\n\n  subject_terms_1: folk tales depictions (visual works) alphabets (symbols) symbolism cartography (discipline)\n\n  subject_terms_2: Panji Melayu Robson\n S. O. (Stuart O.)\n 1941- Symbolism Prints Folk tales Installations (Art) Cartography Alphabets\n\n  subject_terms_3: Installation art\n\n  sgcool_label_text: The images in this artwork are taken from reliefs illustrating episodes from the Panji cycle. Their outlines are rendered in scripts\n starting first with Javanese script\n then flowing out into scripts reflecting the various regions and localities that this narrative has travelled to: a calligraphic cartography charting the movement of the Panji cycle throughout Southeast Asia. Even as the work reminds us of Southeast Asia’s shared cultural histories\n the letters spilling out from the compendium of Panji stories suggest the impossibility of ‘containing’ Southeast Asia and the limits of any attempt to unify its histories or to conceive of the region as a singular entity. The Panji cycle is a collection of stories revolving around the legendary Prince Panji\n which originated in Java around the 14th century and spread to what is now modern-day Malaysia\n Cambodia\n Myanmar\n the Philippines and Thailand. It was only in the last century that these stories were gathered into a single volume\n the Wangbang Wideya\n by S.O. Robson.\n",
  "createdDate": "20201201203308",
  "version": 0,
  "latest": false,
  "roles": [],
  "metadata": {
    "accession_no_csv": "2017-00553",
    "Image": "",
    "object_work_type": "prints (visual works) installations (visual works)",
    "title_text": "The Journey of Panji",
    "preference": "main",
    "title_language": "",
    "creator_2": "Eddy Susanto",
    "creator_role": "artists (visual artists)",
    "creation_date": "2016",
    "creation_place_original_location": "Indonesia",
    "styles_periods_indexing_terms": "Contemporary (style of art)",
    "inscriptions": "",
    "inscription_language": "",
    "shape": "irregular",
    "materials_name": "canvas (textile material) wood (plant material) Ink acrylic paint",
    "techniques_name": "installing",
    "object_colour": "multicolored",
    "physical_appearance": "This installation depicts the collection of stories, the Wangbang Wideya, written by S.O. Robson, as a physical artwork. There is a large sculpture of the book on the ground, with letters spilling out from its sides. Behind the book, the letters lead up to a screen. On the screen are illustrated images of human figures in various scenes.",
    "subject_terms_1": "folk tales depictions (visual works) alphabets (symbols) symbolism cartography (discipline)",
    "subject_terms_2": "Panji Melayu Robson, S. O. (Stuart O.), 1941- Symbolism Prints Folk tales Installations (Art) Cartography Alphabets",
    "subject_terms_3": "Installation art",
    "sgcool_label_text": "The images in this artwork are taken from reliefs illustrating episodes from the Panji cycle. Their outlines are rendered in scripts, starting first with Javanese script, then flowing out into scripts reflecting the various regions and localities that this narrative has travelled to: a calligraphic cartography charting the movement of the Panji cycle throughout Southeast Asia. Even as the work reminds us of Southeast Asia’s shared cultural histories, the letters spilling out from the compendium of Panji stories suggest the impossibility of ‘containing’ Southeast Asia and the limits of any attempt to unify its histories or to conceive of the region as a singular entity. The Panji cycle is a collection of stories revolving around the legendary Prince Panji, which originated in Java around the 14th century and spread to what is now modern-day Malaysia, Cambodia, Myanmar, the Philippines and Thailand. It was only in the last century that these stories were gathered into a single volume, the Wangbang Wideya, by S.O. Robson."
  },
  "nlpDate": "20201201203308",
  "connectorId": 0,
  "tags": {}
}