{
  "id": "2017-00145-041",
  "title": "Reflections of Tan Chong Tee: Letters, Notes, and Photographs ???????????????????????????? Reflections of Tan Chong Tee: Photograph of a group of people",
  "source": "Bumblebee",
  "path": "./Data/json/",
  "content": "\n  accession_no_csv: 2017-00145-041\n\n  Image: \n\n  object_work_type: black-and-white photographs photographs\n\n  title_text: Reflections of Tan Chong Tee: Letters\n Notes\n and Photographs ???????????????????????????? Reflections of Tan Chong Tee: Photograph of a group of people\n\n  preference: alternate alternate main\n\n  title_language: \n\n  creation_date: 13-Jan-46\n\n  creation_place_original_location: Singapore\n\n  inscriptions: \n\n  inscription_language: \n\n  shape: Rectangular\n\n  materials_name: paper (fiber product)\n\n  techniques_name: black-and-white photography\n\n  object_colour: black-and-white (colors)\n\n  physical_appearance: This is a group portrait of Mrs Lim together with other armed forces personnel.\n\n  subject_terms_1: resistance movements  guerilla warfare local histories armed forces  funerals  wakes  group portraits  world wars\n\n  subject_terms_2: Force 136 (Guerilla movement) War resistance movements  Guerillas  Local history Photographs  Armed Forces  Great Britain. Army. Force 136 Military funerals  Lim\n Bo Seng\n 1909-1944 Portraits\n Group Chen\n Chongzhi\n 1916-  World War\n 1939-1945\n\n  subject_terms_3: Force 136 (Guerilla movement) Death customs  Lim\n Bo Seng  Gan\n Choo Neo ? Portrait photography  MacRitchie Reservoir  Tan\n Chong Tee war personalities  1942-1945 Japanese Occupation\n\n  context_1: Lim Bo Seng\\u0027s Memorial Service\n\n  context_2: memorial services\n\n  context_3: 13-Jan-46\n\n  context_4: 13-Jan-46\n\n  context_5: 13-Jan-46\n\n  context_6: City Hall (Singapore) MacRitchie Reservoir\n\n  context_7: Great Britain. Army. Force 136\n\n  context_8: planners\n\n  context_20: MacRitchie Reservoir\n Lim Bo Seng\\u0027s tomb\n\n  context_21: MacRitchie Reservoir\n\n  context_22: 13-Jan-46\n\n  context_23: 13-Jan-46\n\n  context_24: 13-Jan-46\n\n  sgcool_label_text: These documents and photographs belong to a larger part of a collection of artefacts related to the World War II underground resistance movement known as Force 136. The collection of materials was gathered by Tan Chong Tee (1916- 2012)\n who was a key member of this resistance group. The collection consists of original materials belonging to Tan and other members of Force 136 dating from the 1940s to new materials reproduced from memory by Tan Chong Tee\n which date from the late 1980s to early 2000s. \\r\\n\\r\\nForce 136 was set up in July 1942 as part of the British Special Operations Executive (SOE). It recruited and trained local guerillas to gather intelligence and create an underground spy network to support planned British invasion of Japanese-occupied Malaya.\\r\\n\n",
  "createdDate": "20201120223707",
  "version": 0,
  "latest": false,
  "roles": [],
  "metadata": {
    "accession_no_csv": "2017-00145-041",
    "Image": "",
    "object_work_type": "black-and-white photographs photographs",
    "title_text": "Reflections of Tan Chong Tee: Letters, Notes, and Photographs ???????????????????????????? Reflections of Tan Chong Tee: Photograph of a group of people",
    "preference": "alternate alternate main",
    "title_language": "",
    "creation_date": "13-Jan-46",
    "creation_place_original_location": "Singapore",
    "inscriptions": "",
    "inscription_language": "",
    "shape": "Rectangular",
    "materials_name": "paper (fiber product)",
    "techniques_name": "black-and-white photography",
    "object_colour": "black-and-white (colors)",
    "physical_appearance": "This is a group portrait of Mrs Lim together with other armed forces personnel.",
    "subject_terms_1": "resistance movements  guerilla warfare local histories armed forces  funerals  wakes  group portraits  world wars",
    "subject_terms_2": "Force 136 (Guerilla movement) War resistance movements  Guerillas  Local history Photographs  Armed Forces  Great Britain. Army. Force 136 Military funerals  Lim, Bo Seng, 1909-1944 Portraits, Group Chen, Chongzhi, 1916-  World War, 1939-1945",
    "subject_terms_3": "Force 136 (Guerilla movement) Death customs  Lim, Bo Seng  Gan, Choo Neo ? Portrait photography  MacRitchie Reservoir  Tan, Chong Tee war personalities  1942-1945 Japanese Occupation",
    "context_1": "Lim Bo Seng\u0027s Memorial Service",
    "context_2": "memorial services",
    "context_3": "13-Jan-46",
    "context_4": "13-Jan-46",
    "context_5": "13-Jan-46",
    "context_6": "City Hall (Singapore) MacRitchie Reservoir",
    "context_7": "Great Britain. Army. Force 136",
    "context_8": "planners",
    "context_20": "MacRitchie Reservoir, Lim Bo Seng\u0027s tomb",
    "context_21": "MacRitchie Reservoir",
    "context_22": "13-Jan-46",
    "context_23": "13-Jan-46",
    "context_24": "13-Jan-46",
    "sgcool_label_text": "These documents and photographs belong to a larger part of a collection of artefacts related to the World War II underground resistance movement known as Force 136. The collection of materials was gathered by Tan Chong Tee (1916- 2012), who was a key member of this resistance group. The collection consists of original materials belonging to Tan and other members of Force 136 dating from the 1940s to new materials reproduced from memory by Tan Chong Tee, which date from the late 1980s to early 2000s. \r\n\r\nForce 136 was set up in July 1942 as part of the British Special Operations Executive (SOE). It recruited and trained local guerillas to gather intelligence and create an underground spy network to support planned British invasion of Japanese-occupied Malaya.\r\n"
  },
  "nlpDate": "20201120223707",
  "connectorId": 0,
  "tags": {}
}