{
  "id": "2017-00610",
  "title": "Tunic",
  "source": "Bumblebee",
  "path": "./Data/json/",
  "content": "\n  accession_no_csv: 2017-00610\n\n  Image: \n\n  object_work_type: tunics\n\n  title_text: Tunic\n\n  preference: main\n\n  title_language: \n\n  creation_date: 20th century\n\n  creation_place_original_location: Kachchh (India)\n\n  inscriptions: \n\n  inscription_language: \n\n  shape: irregular\n\n  materials_name: satin silk (textile)\n\n  techniques_name: sewing (needleworking technique) embroidering\n\n  object_colour: multicolored\n\n  physical_appearance: This is a tunic blouse. It is black\n with a red fabric panel along the shoulders and down the front of the blouse. The blouse features embroided geometric and floral pattern. It is short sleeved with a shallow scalloped collar.\n\n  subject_terms_1: folk costume embroidery (visual works) flower (motif) geometric motifs tops (garments\n general) blouses (main garments)\n\n  subject_terms_2: Ethnic costume Blouses Embroidery Motifs\n\n  subject_terms_3: Indian costumes\n\n  subject_terms_4: \n\n  sgcool_label_text: Exceptional example of an embroidered tunic from the Saiyed Muslim communities of west Kutch.\n",
  "createdDate": "20201120223708",
  "version": 0,
  "latest": false,
  "roles": [],
  "metadata": {
    "accession_no_csv": "2017-00610",
    "Image": "",
    "object_work_type": "tunics",
    "title_text": "Tunic",
    "preference": "main",
    "title_language": "",
    "creation_date": "20th century",
    "creation_place_original_location": "Kachchh (India)",
    "inscriptions": "",
    "inscription_language": "",
    "shape": "irregular",
    "materials_name": "satin silk (textile)",
    "techniques_name": "sewing (needleworking technique) embroidering",
    "object_colour": "multicolored",
    "physical_appearance": "This is a tunic blouse. It is black, with a red fabric panel along the shoulders and down the front of the blouse. The blouse features embroided geometric and floral pattern. It is short sleeved with a shallow scalloped collar.",
    "subject_terms_1": "folk costume embroidery (visual works) flower (motif) geometric motifs tops (garments, general) blouses (main garments)",
    "subject_terms_2": "Ethnic costume Blouses Embroidery Motifs",
    "subject_terms_3": "Indian costumes",
    "subject_terms_4": "",
    "sgcool_label_text": "Exceptional example of an embroidered tunic from the Saiyed Muslim communities of west Kutch."
  },
  "nlpDate": "20201120223708",
  "connectorId": 0,
  "tags": {}
}