{
  "id": "2017-00180",
  "title": "Lim Hong Pei Collection: KMT youth membership certificate  ?????",
  "source": "Bumblebee",
  "path": "./Data/json/",
  "content": "\n  accession_no_csv: 2017-00180\n\n  Image: \n\n  object_work_type: certificates\n\n  title_text: Lim Hong Pei Collection: KMT youth membership certificate  ?????\n\n  preference: alternate alternate\n\n  title_language: \n\n  creation_date: 1941\n\n  creation_place_original_location: Singapore\n\n  inscriptions: \n\n  inscription_language: \n\n  shape: rectangular\n\n  materials_name: paper (fiber product)\n\n  techniques_name: printing (process)\n\n  object_colour: red (color) black (color)\n\n  physical_appearance: This is a certificate of membership for the Kuomintang. The document is printed in black ink on a red piece of card. There is a photograph identification attached to the bottom left of the document\n. A blue stamped is marked over the photograph on its right. There is another printed portrait photograph on the right side of the document\n in an oval\n\n  subject_terms_1: world wars resistance movements documents (object genre) Chinese scripts\n\n  subject_terms_2: World War\n 1939-1945 Great Britain. Army. Force 136 Force 136 (Guerilla movement) Lim\n Hong Pei\n 1922- Certification Zhongguo guo min dang Memberships\n\n  subject_terms_3: Force 136 (Guerilla movement) 1942-1945 Japanese occupation war personalities\n\n  subject_terms_4: \n\n  context_1: World War\n 1939-1945 1942-1945 Japanese Occupation\n\n  context_2: world wars occupations (armed conflicts)\n\n  context_3: 1939-1945 1942-1945\n\n  context_4: 1939 1942\n\n  context_5: 1945 1945\n\n  context_6: Malaya Singapore\n\n  context_7: Great Britain. Army. Force 136\n\n  context_8: armed forces\n\n  sgcool_label_text: This certificate belongs to part of a collection of artefacts related to the World War II underground resistance movement known as Force 136. The collection of materials was gathered by Tan Chong Tee (1916- 2012)\n who was a key member of this resistance group. The collection consists of original materials belonging to Tan and other members of Force 136 dating from the 1940s to new materials reproduced from memory by Tan Chong Tee\n which date from the late 1980s to early 2000s. \\r\\n\\r\\nForce 136 was set up in July 1942 as part of the British Special Operations Executive (SOE). It recruited and trained local guerillas to gather intelligence and create an underground spy network to support planned British invasion of Japanese-occupied Malaya.\n",
  "createdDate": "20201120223707",
  "version": 0,
  "latest": false,
  "roles": [],
  "metadata": {
    "accession_no_csv": "2017-00180",
    "Image": "",
    "object_work_type": "certificates",
    "title_text": "Lim Hong Pei Collection: KMT youth membership certificate  ?????",
    "preference": "alternate alternate",
    "title_language": "",
    "creation_date": "1941",
    "creation_place_original_location": "Singapore",
    "inscriptions": "",
    "inscription_language": "",
    "shape": "rectangular",
    "materials_name": "paper (fiber product)",
    "techniques_name": "printing (process)",
    "object_colour": "red (color) black (color)",
    "physical_appearance": "This is a certificate of membership for the Kuomintang. The document is printed in black ink on a red piece of card. There is a photograph identification attached to the bottom left of the document,. A blue stamped is marked over the photograph on its right. There is another printed portrait photograph on the right side of the document, in an oval",
    "subject_terms_1": "world wars resistance movements documents (object genre) Chinese scripts",
    "subject_terms_2": "World War, 1939-1945 Great Britain. Army. Force 136 Force 136 (Guerilla movement) Lim, Hong Pei, 1922- Certification Zhongguo guo min dang Memberships",
    "subject_terms_3": "Force 136 (Guerilla movement) 1942-1945 Japanese occupation war personalities",
    "subject_terms_4": "",
    "context_1": "World War, 1939-1945 1942-1945 Japanese Occupation",
    "context_2": "world wars occupations (armed conflicts)",
    "context_3": "1939-1945 1942-1945",
    "context_4": "1939 1942",
    "context_5": "1945 1945",
    "context_6": "Malaya Singapore",
    "context_7": "Great Britain. Army. Force 136",
    "context_8": "armed forces",
    "sgcool_label_text": "This certificate belongs to part of a collection of artefacts related to the World War II underground resistance movement known as Force 136. The collection of materials was gathered by Tan Chong Tee (1916- 2012), who was a key member of this resistance group. The collection consists of original materials belonging to Tan and other members of Force 136 dating from the 1940s to new materials reproduced from memory by Tan Chong Tee, which date from the late 1980s to early 2000s. \r\n\r\nForce 136 was set up in July 1942 as part of the British Special Operations Executive (SOE). It recruited and trained local guerillas to gather intelligence and create an underground spy network to support planned British invasion of Japanese-occupied Malaya."
  },
  "nlpDate": "20201120223707",
  "connectorId": 0,
  "tags": {}
}