{
  "id": "2017-01040-124",
  "title": "\"Personal photograph album titled \"\"Sixteen Months in Singapore\"\"\" Sixteen Months in Singapore: Photograph of crowd and vehicles under tentages",
  "source": "Bumblebee",
  "path": "./Data/json/",
  "content": "\n  accession_no_csv: 2017-01040-124\n\n  Image: \n\n  object_work_type: photographs black-and-white photographs\n\n  title_text: \\Personal photograph album titled \\\\Sixteen Months in Singapore\\\\\\ Sixteen Months in Singapore: Photograph of crowd and vehicles under tentages\n\n  preference: main alternate\n\n  title_language: \n\n  creation_date: 1951-1952\n\n  creation_place_original_location: Singapore\n\n  inscriptions: \n\n  inscription_language: \n\n  shape: rectangular\n\n  materials_name: paper (fiber product)\n\n  techniques_name: photographic processes\n\n  object_colour: black-and-white (colors)\n\n  physical_appearance: This is a black-and-white photograph. It is rectangular in shape and landscape in orientation. It features a road stretching from the left to the front-right of the photograph. Along the road\n there are several cars parked. Several tentages are set up. There is a crowd of people seen under the tentages\n amongst the vehicles. There is a section of a banner seen on the left of the photograph. There is a motorcyclist driving down the road in the center. There is a slight fold mark along the vertical centre of the photograph.\n\n  subject_terms_1: automobile racing spectators (event observers) snapshots races (events)\n\n  subject_terms_2: Spectators Racetracks (Automobile racing) Photographs\n\n  subject_terms_3: Photography Auto racing events\n\n  subject_terms_4: \n\n  sgcool_label_text: This is a personal photograph album that belonged to a Corporal A. Silver who spent 16 months in Singapore between 1951 and 1952. Silver was presumably a Jewish lady who was stationed in Singapore to serve at the Royal Air Force (RAF) Hospital at Changi. The album contains photographs that document her working and personal life\n including friends she made within the Jewish community in Singapore.\n",
  "createdDate": "20201201203307",
  "version": 0,
  "latest": false,
  "roles": [],
  "metadata": {
    "accession_no_csv": "2017-01040-124",
    "Image": "",
    "object_work_type": "photographs black-and-white photographs",
    "title_text": "\"Personal photograph album titled \"\"Sixteen Months in Singapore\"\"\" Sixteen Months in Singapore: Photograph of crowd and vehicles under tentages",
    "preference": "main alternate",
    "title_language": "",
    "creation_date": "1951-1952",
    "creation_place_original_location": "Singapore",
    "inscriptions": "",
    "inscription_language": "",
    "shape": "rectangular",
    "materials_name": "paper (fiber product)",
    "techniques_name": "photographic processes",
    "object_colour": "black-and-white (colors)",
    "physical_appearance": "This is a black-and-white photograph. It is rectangular in shape and landscape in orientation. It features a road stretching from the left to the front-right of the photograph. Along the road, there are several cars parked. Several tentages are set up. There is a crowd of people seen under the tentages, amongst the vehicles. There is a section of a banner seen on the left of the photograph. There is a motorcyclist driving down the road in the center. There is a slight fold mark along the vertical centre of the photograph.",
    "subject_terms_1": "automobile racing spectators (event observers) snapshots races (events)",
    "subject_terms_2": "Spectators Racetracks (Automobile racing) Photographs",
    "subject_terms_3": "Photography Auto racing events",
    "subject_terms_4": "",
    "sgcool_label_text": "This is a personal photograph album that belonged to a Corporal A. Silver who spent 16 months in Singapore between 1951 and 1952. Silver was presumably a Jewish lady who was stationed in Singapore to serve at the Royal Air Force (RAF) Hospital at Changi. The album contains photographs that document her working and personal life, including friends she made within the Jewish community in Singapore."
  },
  "nlpDate": "20201201203307",
  "connectorId": 0,
  "tags": {}
}