{"id":"2017-00225-003","title":"Miniatures from The Sunny Orient where Sorrow Smiles and Poverty and Riches – Sin and Sanctity – Beauty and Ugliness all keep company Boats Sailing on Water","source":"Bumblebee","path":"./Data/json/","content":"accession_no_csv:2017-00225-003\nImage:\nobject_work_type:gelatin silver prints  photographic prints  black-and-white prints (photographs)\ntitle_text:Miniatures from The Sunny Orient where Sorrow Smiles and Poverty and Riches – Sin and Sanctity – Beauty and Ugliness all keep company Boats Sailing on Water\npreference:alternate  main\ntitle_language:\ncreator_2:SHEAF\n Egbert Thomas.\ncreator_role:photographers\ncreation_date:1922-1925\ncreation_place_original_location:Asia\ninscriptions:\ninscription_language:\nshape:Rectangular\nmaterials_name:gelatin  baryta paper  silver sulfide\ntechniques_name:gelatin silver process  photographic printing techniques  black-and-white photography\nobject_colour:black-and-white (colours)\nphysical_appearance:This is a scene of a calm water way upon which four wooden boats with their sails fully extended are seen cruising along.\nsubject_terms_1:nature photography  seascapes  travel photography boats  junks (vessels)  bodies of water (natural)\nsubject_terms_2:Prints  Landscape photography  Nature photography Travel photography  Boats and boating  Junks  Bodies of water\nsubject_terms_3:Landscape photography Travel photography Waterways Visual arts\nsubject_terms_4:\nsgcool_label_text:These photographs were taken by Egbert Sheaf\n the Australian Trade Commissioner in Singapore\n several taken before and some of which were most likely taken when he was posted here between 1922-25. Sheaf conscientiously studied South-East Asia\\u0027s ethnography and his scholarship was coupled with a passion for travel and adventure. His photographs cover various aspects of daily and cultural life such as weaving\n the rice agriculture and other rituals of Javanese and Malayan communities\n as explained and illustrated in the portfolios and albums.","createdDate":"20201018182636","version":0,"latest":false,"roles":[],"metadata":{"accession_no_csv":"2017-00225-003","Image":"","object_work_type":"gelatin silver prints  photographic prints  black-and-white prints (photographs)","title_text":"Miniatures from The Sunny Orient where Sorrow Smiles and Poverty and Riches – Sin and Sanctity – Beauty and Ugliness all keep company Boats Sailing on Water","preference":"alternate  main","title_language":"","creator_2":"SHEAF, Egbert Thomas.","creator_role":"photographers","creation_date":"1922-1925","creation_place_original_location":"Asia","inscriptions":"","inscription_language":"","shape":"Rectangular","materials_name":"gelatin  baryta paper  silver sulfide","techniques_name":"gelatin silver process  photographic printing techniques  black-and-white photography","object_colour":"black-and-white (colours)","physical_appearance":"This is a scene of a calm water way upon which four wooden boats with their sails fully extended are seen cruising along.","subject_terms_1":"nature photography  seascapes  travel photography boats  junks (vessels)  bodies of water (natural)","subject_terms_2":"Prints  Landscape photography  Nature photography Travel photography  Boats and boating  Junks  Bodies of water","subject_terms_3":"Landscape photography Travel photography Waterways Visual arts","subject_terms_4":"","sgcool_label_text":"These photographs were taken by Egbert Sheaf, the Australian Trade Commissioner in Singapore, several taken before and some of which were most likely taken when he was posted here between 1922-25. Sheaf conscientiously studied South-East Asia\u0027s ethnography and his scholarship was coupled with a passion for travel and adventure. His photographs cover various aspects of daily and cultural life such as weaving, the rice agriculture and other rituals of Javanese and Malayan communities, as explained and illustrated in the portfolios and albums."},"nlpDate":"20201018182636","connectorId":0,"tags":{}}