{"id":"2017-00555","title":"\"Preparatory drawing for \"\"Asking for Nothingness\"\" \" ?????????????????","source":"Bumblebee","path":"./Data/json/","content":"accession_no_csv:2017-00555\nImage:\nobject_work_type:design development drawings  sketches\ntitle_text:\\Preparatory drawing for \\\\Asking for Nothingness\\\\ \\ ?????????????????\npreference:main\ntitle_language:\ncreator_2:Navin Rawanchaikul\ncreator_1:Rawanchaikul\n Navin\ncreator_role:artists (visual artists)\ncreation_date:1995\ncreation_place_original_location:Thailand\ninscriptions:\ninscription_language:\nshape:Rectangular\nmaterials_name:charcoal (material)  photographic paper pencil (marking material)\ntechniques_name:drawing (image making)  black-and-white photography\nobject_colour:multicoloured\nphysical_appearance:There are four components to this sketch. To the left and right\n are images of a half dressed elderly man\n and an elderly woman respectively. As for the central panel\n it has been segmented into two parts. The top half is an aerial view of the installation\n whilst the bottom half shows the design from the front.\nsubject_terms_1:cultural heritage  elderly  group identity  memory  black-and-white photographs\nsubject_terms_2:Heritage  Older people  Group identity  Collective memory  Black \\u0026 White Pictures\nsubject_terms_3:Drawing  Photography\nsgcool_label_text:Asking for Nothingness is the largest work from Thai artist Navin Rawanchaikul’s series of bottle installations from the 1990s and rounds off a style that marked the artist’s early period of experimentation and social engagement\n which included segues into assemblages and performances with intravenous injection bottles and bottled water. The bottle series started with a performance-installation titled Fon Pan-ya and Dee U-raporn in 1993\n where the artist invited a pair of elderly villagers\n one 72-year-old male and one 64-year-old female\n in rural Chiang Mai to sit within two large vitrines holding two book covers embossed with details such as name\n age and address\n in order to highlight the disappearance of traditional values and modern society’s neglect of the elderly and illiterate.  This gradually morphed into black and white photographs of Thai villagers inserted into old medicine bottles and then displayed in wooden cabinets\n buried into mud-filled wooden troughs or on tiered open-shelf columns – the last being the work There is No Voice (1993) which was also shown at the seminal exhibition “Traditions/Tensions” in New York. Asking for Nothingness expands on the presentation of There is No Voice\n making it into a large-scale immersive room installation where the visitor meanders through the columns confronting or contemplating the myriad faces of the villagers.  Rawanchaikul’s message-in-a-bottle photographic archive of Chiang Mai\\u0027s marginalised aged reaffirms the educational\n historic\n and cultural significance our seniors can imbue\n if we take the time to preserve.","createdDate":"20201018182636","version":0,"latest":false,"roles":[],"metadata":{"accession_no_csv":"2017-00555","Image":"","object_work_type":"design development drawings  sketches","title_text":"\"Preparatory drawing for \"\"Asking for Nothingness\"\" \" ?????????????????","preference":"main","title_language":"","creator_2":"Navin Rawanchaikul","creator_1":"Rawanchaikul, Navin","creator_role":"artists (visual artists)","creation_date":"1995","creation_place_original_location":"Thailand","inscriptions":"","inscription_language":"","shape":"Rectangular","materials_name":"charcoal (material)  photographic paper pencil (marking material)","techniques_name":"drawing (image making)  black-and-white photography","object_colour":"multicoloured","physical_appearance":"There are four components to this sketch. To the left and right, are images of a half dressed elderly man, and an elderly woman respectively. As for the central panel, it has been segmented into two parts. The top half is an aerial view of the installation, whilst the bottom half shows the design from the front.","subject_terms_1":"cultural heritage  elderly  group identity  memory  black-and-white photographs","subject_terms_2":"Heritage  Older people  Group identity  Collective memory  Black \u0026 White Pictures","subject_terms_3":"Drawing  Photography","sgcool_label_text":"Asking for Nothingness is the largest work from Thai artist Navin Rawanchaikul’s series of bottle installations from the 1990s and rounds off a style that marked the artist’s early period of experimentation and social engagement, which included segues into assemblages and performances with intravenous injection bottles and bottled water. The bottle series started with a performance-installation titled Fon Pan-ya and Dee U-raporn in 1993, where the artist invited a pair of elderly villagers, one 72-year-old male and one 64-year-old female, in rural Chiang Mai to sit within two large vitrines holding two book covers embossed with details such as name, age and address, in order to highlight the disappearance of traditional values and modern society’s neglect of the elderly and illiterate.  This gradually morphed into black and white photographs of Thai villagers inserted into old medicine bottles and then displayed in wooden cabinets, buried into mud-filled wooden troughs or on tiered open-shelf columns – the last being the work There is No Voice (1993) which was also shown at the seminal exhibition “Traditions/Tensions” in New York. Asking for Nothingness expands on the presentation of There is No Voice, making it into a large-scale immersive room installation where the visitor meanders through the columns confronting or contemplating the myriad faces of the villagers.  Rawanchaikul’s message-in-a-bottle photographic archive of Chiang Mai\u0027s marginalised aged reaffirms the educational, historic, and cultural significance our seniors can imbue, if we take the time to preserve."},"nlpDate":"20201018182636","connectorId":0,"tags":{}}