{
  "id": "2017-00184-015",
  "title": "Lim Hong Pei Collection: Photographs Lim Hong Pei Collection: three soldiers",
  "source": "Bumblebee",
  "path": "./Data/json/",
  "content": "\n  accession_no_csv: 2017-00184-015\n\n  Image: \n\n  object_work_type: black-and-white photographs\n\n  title_text: Lim Hong Pei Collection: Photographs Lim Hong Pei Collection: three soldiers\n\n  preference: main alternate\n\n  title_language: \n\n  creation_date: 1940s\n\n  creation_place_original_location: Singapore\n\n  inscriptions: \n\n  inscription_language: \n\n  shape: rectangular\n\n  materials_name: paper (fiber product)\n\n  techniques_name: photographic processes\n\n  object_colour: black-and-white (colors)\n\n  physical_appearance: This is a black-and-white portrait photograph of three military soldiers. The man on the left is standing\n the man in the middle is seated\n while the man on the right is resting on the arm rest of the chair. They are all gazing forwards\n and dressed in military uniform with folded sleeves\n headgear\n and boots. They are photographed against a plain wall.\n\n  subject_terms_1: resistance movements world wars soldiers group portraits\n\n  subject_terms_2: Lim\n Hong Pei\n 1922- Portraits\n group World War\n 1939-1945 Great Britain. Army. Force 136 Force 136 (Guerilla movement) Portrait photography Soldiers\n\n  subject_terms_3: 1942-1945 Japanese occupation Force 136 (Guerilla movement) Portrait photography war personalities\n\n  subject_terms_4: \n\n  context_1: World War\n 1939-1945 1942-1945 Japanese Occupation\n\n  context_2: occupations (armed conflicts) world wars\n\n  context_3: 1942-1945 1939-1945\n\n  context_4: 1939 1942\n\n  context_5: 1945\n\n  context_6: Singapore Malaya\n\n  context_7: Great Britain. Army. Force 136\n\n  context_8: armed forces\n\n  sgcool_label_text: These photographs belong to part of a collection of artefacts related to the World War II underground resistance movement known as Force 136. The collection of materials was gathered by Tan Chong Tee (1916- 2012)\n who was a key member of this resistance group. The collection consists of original materials belonging to Tan and other members of Force 136 dating from the 1940s to new materials reproduced from memory by Tan Chong Tee\n which date from the late 1980s to early 2000s. \\r\\n\\r\\nForce 136 was set up in July 1942 as part of the British Special Operations Executive (SOE). It recruited and trained local guerillas to gather intelligence and create an underground spy network to support planned British invasion of Japanese-occupied Malaya.\n",
  "createdDate": "20201201203308",
  "version": 0,
  "latest": false,
  "roles": [],
  "metadata": {
    "accession_no_csv": "2017-00184-015",
    "Image": "",
    "object_work_type": "black-and-white photographs",
    "title_text": "Lim Hong Pei Collection: Photographs Lim Hong Pei Collection: three soldiers",
    "preference": "main alternate",
    "title_language": "",
    "creation_date": "1940s",
    "creation_place_original_location": "Singapore",
    "inscriptions": "",
    "inscription_language": "",
    "shape": "rectangular",
    "materials_name": "paper (fiber product)",
    "techniques_name": "photographic processes",
    "object_colour": "black-and-white (colors)",
    "physical_appearance": "This is a black-and-white portrait photograph of three military soldiers. The man on the left is standing, the man in the middle is seated, while the man on the right is resting on the arm rest of the chair. They are all gazing forwards, and dressed in military uniform with folded sleeves, headgear, and boots. They are photographed against a plain wall.",
    "subject_terms_1": "resistance movements world wars soldiers group portraits",
    "subject_terms_2": "Lim, Hong Pei, 1922- Portraits, group World War, 1939-1945 Great Britain. Army. Force 136 Force 136 (Guerilla movement) Portrait photography Soldiers",
    "subject_terms_3": "1942-1945 Japanese occupation Force 136 (Guerilla movement) Portrait photography war personalities",
    "subject_terms_4": "",
    "context_1": "World War, 1939-1945 1942-1945 Japanese Occupation",
    "context_2": "occupations (armed conflicts) world wars",
    "context_3": "1942-1945 1939-1945",
    "context_4": "1939 1942",
    "context_5": "1945",
    "context_6": "Singapore Malaya",
    "context_7": "Great Britain. Army. Force 136",
    "context_8": "armed forces",
    "sgcool_label_text": "These photographs belong to part of a collection of artefacts related to the World War II underground resistance movement known as Force 136. The collection of materials was gathered by Tan Chong Tee (1916- 2012), who was a key member of this resistance group. The collection consists of original materials belonging to Tan and other members of Force 136 dating from the 1940s to new materials reproduced from memory by Tan Chong Tee, which date from the late 1980s to early 2000s. \r\n\r\nForce 136 was set up in July 1942 as part of the British Special Operations Executive (SOE). It recruited and trained local guerillas to gather intelligence and create an underground spy network to support planned British invasion of Japanese-occupied Malaya."
  },
  "nlpDate": "20201201203308",
  "connectorId": 0,
  "tags": {}
}