{
  "id": "2017-00171-001",
  "title": "Lumut Sites of Force 136 Operations",
  "source": "Bumblebee",
  "path": "./Data/json/",
  "content": "\n  accession_no_csv: 2017-00171-001\n\n  Image: \n\n  object_work_type: photographs\n\n  title_text: Lumut Sites of Force 136 Operations\n\n  preference: alternate main\n\n  title_language: \n\n  creation_date: 1943\n\n  creation_place_original_location: Singapore Lumut (Perak\n Malaysia)\n\n  inscriptions: \n\n  inscription_language: \n\n  shape: rectangular\n\n  materials_name: paper (fiber product)\n\n  techniques_name: photographic processes\n\n  object_colour: multicolored\n\n  physical_appearance: This is a multicolored photograph of a street. There is a row of shophouses\n with several vehicles parked in front of them. There are several shop signs along the building. There is a marked arrow pointing downwards towards a roof at the top\n marked in black ink.\n\n  subject_terms_1: world wars resistance movements\n\n  subject_terms_2: World War\n 1939-1945 Great Britain. Army. Force 136 Force 136 (Guerilla movement) Chen\n Chongzhi\n 1916- Photography Lumut (Perak\n Malaysia)\n\n  subject_terms_3: Force 136 (Guerilla movement) 1942-1945 Japanese occupation Tan\n Chong Tee Photography shophouses war personalities\n\n  subject_terms_4: \n\n  context_1: World War\n 1939-1945 1942-1945 Japanese Occupation\n\n  context_2: world wars occupations (armed conflicts)\n\n  context_3: 1939-1945 1942-1945\n\n  context_4: 1939 1942\n\n  context_5: 1945 1945\n\n  context_6: Malaya Singapore\n\n  context_7: Great Britain. Army. Force 136\n\n  context_8: armed forces\n\n  sgcool_label_text: This is a collation of the sites in which Force 136 operated and belongs to part of a collection of artefacts related to the World War II underground resistance movement known as Force 136. The collection of materials was gathered by Tan Chong Tee (1916- 2012)\n who was a key member of this resistance group. The collection consists of original materials belonging to Tan and other members of Force 136 dating from the 1940s to new materials reproduced from memory by Tan Chong Tee\n which date from the late 1980s to early 2000s. \\r\\n\\r\\nForce 136 was set up in July 1942 as part of the British Special Operations Executive (SOE). It recruited and trained local guerillas to gather intelligence and create an underground spy network to support planned British invasion of Japanese-occupied Malaya.\\r\\n\n",
  "createdDate": "20201120223707",
  "version": 0,
  "latest": false,
  "roles": [],
  "metadata": {
    "accession_no_csv": "2017-00171-001",
    "Image": "",
    "object_work_type": "photographs",
    "title_text": "Lumut Sites of Force 136 Operations",
    "preference": "alternate main",
    "title_language": "",
    "creation_date": "1943",
    "creation_place_original_location": "Singapore Lumut (Perak, Malaysia)",
    "inscriptions": "",
    "inscription_language": "",
    "shape": "rectangular",
    "materials_name": "paper (fiber product)",
    "techniques_name": "photographic processes",
    "object_colour": "multicolored",
    "physical_appearance": "This is a multicolored photograph of a street. There is a row of shophouses, with several vehicles parked in front of them. There are several shop signs along the building. There is a marked arrow pointing downwards towards a roof at the top, marked in black ink.",
    "subject_terms_1": "world wars resistance movements",
    "subject_terms_2": "World War, 1939-1945 Great Britain. Army. Force 136 Force 136 (Guerilla movement) Chen, Chongzhi, 1916- Photography Lumut (Perak, Malaysia)",
    "subject_terms_3": "Force 136 (Guerilla movement) 1942-1945 Japanese occupation Tan, Chong Tee Photography shophouses war personalities",
    "subject_terms_4": "",
    "context_1": "World War, 1939-1945 1942-1945 Japanese Occupation",
    "context_2": "world wars occupations (armed conflicts)",
    "context_3": "1939-1945 1942-1945",
    "context_4": "1939 1942",
    "context_5": "1945 1945",
    "context_6": "Malaya Singapore",
    "context_7": "Great Britain. Army. Force 136",
    "context_8": "armed forces",
    "sgcool_label_text": "This is a collation of the sites in which Force 136 operated and belongs to part of a collection of artefacts related to the World War II underground resistance movement known as Force 136. The collection of materials was gathered by Tan Chong Tee (1916- 2012), who was a key member of this resistance group. The collection consists of original materials belonging to Tan and other members of Force 136 dating from the 1940s to new materials reproduced from memory by Tan Chong Tee, which date from the late 1980s to early 2000s. \r\n\r\nForce 136 was set up in July 1942 as part of the British Special Operations Executive (SOE). It recruited and trained local guerillas to gather intelligence and create an underground spy network to support planned British invasion of Japanese-occupied Malaya.\r\n"
  },
  "nlpDate": "20201120223707",
  "connectorId": 0,
  "tags": {}
}