{"id":"2017-00068","title":"Panel","source":"Bumblebee","path":"./Data/json/","content":"accession_no_csv:2017-00068\nImage:\nobject_work_type:panels (costume components)\ntitle_text:Panel\npreference:main\ntitle_language:\ncreation_date:Early 20th century\ncreation_place_original_location:Straits Settlements\nstyles_periods_indexing_terms:Chinese (culture or style)\ninscriptions:\ninscription_language:\nshape:rectangular\nmaterials_name:cotton (textile) silk (textile)\ntechniques_name:sewing (needleworking technique) embroidering\nobject_colour:multicolored\nphysical_appearance:This is a textile panel. It comprises of three main horizontal decorative sections. The topmost section features stitched Chinese scrolls. The middle section features vases of flowers amidst scrolls and butterflies\n with brown lobed medallions enclosing birds and flowers. The bottom panel feature two horizontal rows of black-bordered sections. Each section alternates flowers\n birds and animal motifs. The edges of the panel is slightly frayed\n especially at the bottom-right.\nsubject_terms_1:embroidery (visual works) birds (motifs) scrolls (motifs) flower (motif) symbolism (artistic concept) Buddhism\nsubject_terms_2:Textiles Embroidery Motifs Symbolism Buddhism\nsubject_terms_3:Textile art and design Buddhism\nsgcool_label_text:This textile panel comprises three main horizontal decorative sections.  Satin-stitched Chinese scrolls occupy the uppermost section.  In the middle section\n vases of flowers\n also one of the eight Buddhist auspicious symbols\n are shown amidst the scrolls and butterflies while birds and flowers are enclosed within brown lobed medallions and black diaper patterns.  At the bottom of the panel are two horizontal rows of black diaper borders.  They feature alternating vase of flowers\n bird and animal motifs.  It is plausible that the stylized motifs represent the phoenix and qilin\n both of which are commonly depicted on nyonya embroidery.  The phoenix is symbolic of martial harmony while the qilin represents fertility and longevity.","createdDate":"20201119143406","version":0,"latest":false,"roles":[],"metadata":{"accession_no_csv":"2017-00068","Image":"","object_work_type":"panels (costume components)","title_text":"Panel","preference":"main","title_language":"","creation_date":"Early 20th century","creation_place_original_location":"Straits Settlements","styles_periods_indexing_terms":"Chinese (culture or style)","inscriptions":"","inscription_language":"","shape":"rectangular","materials_name":"cotton (textile) silk (textile)","techniques_name":"sewing (needleworking technique) embroidering","object_colour":"multicolored","physical_appearance":"This is a textile panel. It comprises of three main horizontal decorative sections. The topmost section features stitched Chinese scrolls. The middle section features vases of flowers amidst scrolls and butterflies, with brown lobed medallions enclosing birds and flowers. The bottom panel feature two horizontal rows of black-bordered sections. Each section alternates flowers, birds and animal motifs. The edges of the panel is slightly frayed, especially at the bottom-right.","subject_terms_1":"embroidery (visual works) birds (motifs) scrolls (motifs) flower (motif) symbolism (artistic concept) Buddhism","subject_terms_2":"Textiles Embroidery Motifs Symbolism Buddhism","subject_terms_3":"Textile art and design Buddhism","sgcool_label_text":"This textile panel comprises three main horizontal decorative sections.  Satin-stitched Chinese scrolls occupy the uppermost section.  In the middle section, vases of flowers, also one of the eight Buddhist auspicious symbols, are shown amidst the scrolls and butterflies while birds and flowers are enclosed within brown lobed medallions and black diaper patterns.  At the bottom of the panel are two horizontal rows of black diaper borders.  They feature alternating vase of flowers, bird and animal motifs.  It is plausible that the stylized motifs represent the phoenix and qilin, both of which are commonly depicted on nyonya embroidery.  The phoenix is symbolic of martial harmony while the qilin represents fertility and longevity."},"nlpDate":"20201119143406","connectorId":0,"tags":{}}