{"id":"2017-00497","title":"Handmade yellow Swiss cotton lace  samples from Sylvia Kho’s collection","source":"Bumblebee","path":"./Data/json/","content":"accession_no_csv:2017-00497\nImage:\nobject_work_type:lace (needlework) textile art (visual works)\ntitle_text:Handmade yellow Swiss cotton lace  samples from Sylvia Kho’s collection\npreference:main\ntitle_language:\ncreator_2:Not specified\ncreation_date:1960s - 1980s\ncreation_place_original_location:Europe  Switzerland\ninscriptions:\ninscription_language:\nshape:Rectangular\nmaterials_name:cotton (textile)\ntechniques_name:lace making\nobject_colour:yellow (colour)\nphysical_appearance:This is a yellow lace sample with leaf motifs.\nsubject_terms_1:plant-derived motif  imports  handmade\nsubject_terms_2:Leaves in art  Lace and lace making  Textile crafts  Imports  Kho\n Sylvia\n 1917- Handmade style?\nsubject_terms_3:Textile art and design\nsgcool_label_text:These lace sample come from the collection of Sylvia Kho who was a prominent bridal couturier in Singapore from the 1950s to 1990s. She designed and custom-made wedding gowns using elaborate laces imported from Europe.  She travelled extensively to France and USA to learn how wedding gowns were designed and made. She also became one of the greatest buyers of wedding gown laces in France. This lace sample would have been offered to her clients who comprised not only of brides but also mothers\n aunts and sisters of the brides. \\r\\nThis particular type of hand-made cotton lace were particularly popular with the mothers of brides.  Made by hand\n such fine quality of lace are no longer produced by millinery houses in Europe.","createdDate":"20201119143406","version":0,"latest":false,"roles":[],"metadata":{"accession_no_csv":"2017-00497","Image":"","object_work_type":"lace (needlework) textile art (visual works)","title_text":"Handmade yellow Swiss cotton lace  samples from Sylvia Kho’s collection","preference":"main","title_language":"","creator_2":"Not specified","creation_date":"1960s - 1980s","creation_place_original_location":"Europe  Switzerland","inscriptions":"","inscription_language":"","shape":"Rectangular","materials_name":"cotton (textile)","techniques_name":"lace making","object_colour":"yellow (colour)","physical_appearance":"This is a yellow lace sample with leaf motifs.","subject_terms_1":"plant-derived motif  imports  handmade","subject_terms_2":"Leaves in art  Lace and lace making  Textile crafts  Imports  Kho, Sylvia, 1917- Handmade style?","subject_terms_3":"Textile art and design","sgcool_label_text":"These lace sample come from the collection of Sylvia Kho who was a prominent bridal couturier in Singapore from the 1950s to 1990s. She designed and custom-made wedding gowns using elaborate laces imported from Europe.  She travelled extensively to France and USA to learn how wedding gowns were designed and made. She also became one of the greatest buyers of wedding gown laces in France. This lace sample would have been offered to her clients who comprised not only of brides but also mothers, aunts and sisters of the brides. \r\nThis particular type of hand-made cotton lace were particularly popular with the mothers of brides.  Made by hand, such fine quality of lace are no longer produced by millinery houses in Europe."},"nlpDate":"20201119143406","connectorId":0,"tags":{}}