{
  "id": "2017-00890",
  "title": "Majie’s mandarin-collar top",
  "source": "Bumblebee",
  "path": "./Data/json/",
  "content": "\n  accession_no_csv: 2017-00890\n\n  Image: \n\n  object_work_type: womenswear folk costume\n\n  title_text: Majie’s mandarin-collar top\n\n  preference: main\n\n  title_language: \n\n  creation_date: Mid-20th century\n\n  creation_place_original_location: Singapore\n\n  styles_periods_indexing_terms: Chinese (culture or style)\n\n  inscriptions: \n\n  inscription_language: \n\n  shape: irregular\n\n  materials_name: cotton (textile)\n\n  techniques_name: sewing (needleworking technique)\n\n  object_colour: blue (color)\n\n  physical_appearance: This is a mandarin-collar top. It is blue in colour. The buttons run from the collar and sideways\n towards the left. The sleeves are mid-length. The hem of the top flares outwards slightly. The fabric features a light vertical striped pattern. There are no tears seen on this garment.\n\n  subject_terms_1: tops (garments\n general) maids (servants) stripes\n\n  subject_terms_2: Ethnic costume Stripes Household employees\n\n  subject_terms_3: Chinese costumes Lu\n Earl Ming-Teh\n\n  subject_terms_4: \n\n  sgcool_label_text: This blue coloured mandarin-collar top with woven stripes belonged to a majie\n a Cantonese female domestic helper. Majie is derived from a Shun Tak term (ma cheh) which means mother and sister. As this group of women had taken a vow never to marry\n the term Majie alludes to their spinsterhood and refers to their work taking care of children. Majies typically wore a samfoo uniform consisting of a white mandarin-collar top and black trousers.\n",
  "createdDate": "20201125084515",
  "version": 0,
  "latest": false,
  "roles": [],
  "metadata": {
    "accession_no_csv": "2017-00890",
    "Image": "",
    "object_work_type": "womenswear folk costume",
    "title_text": "Majie’s mandarin-collar top",
    "preference": "main",
    "title_language": "",
    "creation_date": "Mid-20th century",
    "creation_place_original_location": "Singapore",
    "styles_periods_indexing_terms": "Chinese (culture or style)",
    "inscriptions": "",
    "inscription_language": "",
    "shape": "irregular",
    "materials_name": "cotton (textile)",
    "techniques_name": "sewing (needleworking technique)",
    "object_colour": "blue (color)",
    "physical_appearance": "This is a mandarin-collar top. It is blue in colour. The buttons run from the collar and sideways, towards the left. The sleeves are mid-length. The hem of the top flares outwards slightly. The fabric features a light vertical striped pattern. There are no tears seen on this garment.",
    "subject_terms_1": "tops (garments, general) maids (servants) stripes",
    "subject_terms_2": "Ethnic costume Stripes Household employees",
    "subject_terms_3": "Chinese costumes Lu, Earl Ming-Teh",
    "subject_terms_4": "",
    "sgcool_label_text": "This blue coloured mandarin-collar top with woven stripes belonged to a majie, a Cantonese female domestic helper. Majie is derived from a Shun Tak term (ma cheh) which means mother and sister. As this group of women had taken a vow never to marry, the term Majie alludes to their spinsterhood and refers to their work taking care of children. Majies typically wore a samfoo uniform consisting of a white mandarin-collar top and black trousers."
  },
  "nlpDate": "20201125084515",
  "connectorId": 0,
  "tags": {}
}