{"id":"2017-00067","title":"Panel","source":"Bumblebee","path":"./Data/json/","content":"accession_no_csv:2017-00067\nImage:\nobject_work_type:panels (costume components)\ntitle_text:Panel\npreference:main\ntitle_language:\ncreation_date:Early 20th century\ncreation_place_original_location:Straits Settlements\nstyles_periods_indexing_terms:Chinese (culture or style)\ninscriptions:\ninscription_language:\nshape:rectangular\nmaterials_name:cotton (textile) metal thread glass (material)\ntechniques_name:sewing (needleworking technique)\nobject_colour:multicolored\nphysical_appearance:This is a costume panel. It is long and bronze in colour\n featuring nine medallions in the center. The center medallion features a dragon motif\n while the other medallions feature other symbols such as a whisk\n a fan and a drum.\nsubject_terms_1:dragons folk costume symbolism (artistic concept) Taoism\nsubject_terms_2:Clothing and dress Ethnic costume Symbolism Motifs Taoism Dragons\nsubject_terms_3:Chinese costumes Taoism\nsgcool_label_text:A dragon motif occupies the central lobed medallion\n and is flanked by auspicious Daoist symbols--the fly whisk\n fan\n pair of castanets\n and bamboo drum—similarly enclosed in lobed medallions.  The front- facing dragon was possibly inspired by Ming dynasty imperial court robes\n with the dragon symbolising the emperor’s centrality in the universe.  Pencil outlines of the designs in the cartouches are evident where some beads have fallen off.","createdDate":"20201018182636","version":0,"latest":false,"roles":[],"metadata":{"accession_no_csv":"2017-00067","Image":"","object_work_type":"panels (costume components)","title_text":"Panel","preference":"main","title_language":"","creation_date":"Early 20th century","creation_place_original_location":"Straits Settlements","styles_periods_indexing_terms":"Chinese (culture or style)","inscriptions":"","inscription_language":"","shape":"rectangular","materials_name":"cotton (textile) metal thread glass (material)","techniques_name":"sewing (needleworking technique)","object_colour":"multicolored","physical_appearance":"This is a costume panel. It is long and bronze in colour, featuring nine medallions in the center. The center medallion features a dragon motif, while the other medallions feature other symbols such as a whisk, a fan and a drum.","subject_terms_1":"dragons folk costume symbolism (artistic concept) Taoism","subject_terms_2":"Clothing and dress Ethnic costume Symbolism Motifs Taoism Dragons","subject_terms_3":"Chinese costumes Taoism","sgcool_label_text":"A dragon motif occupies the central lobed medallion, and is flanked by auspicious Daoist symbols--the fly whisk, fan, pair of castanets, and bamboo drum—similarly enclosed in lobed medallions.  The front- facing dragon was possibly inspired by Ming dynasty imperial court robes, with the dragon symbolising the emperor’s centrality in the universe.  Pencil outlines of the designs in the cartouches are evident where some beads have fallen off."},"nlpDate":"20201018182636","connectorId":0,"tags":{}}