{"id":"2017-00302-024","title":"Miscellaneous scraps of paper from P.O.W James Steele Archives (30 pieces) P.O.W. James Steele Archives: Letter of acknowledgement from Colonial Secretary","source":"Bumblebee","path":"./Data/json/","content":"accession_no_csv:2017-00302-024\nImage:\nobject_work_type:letters (correspondence)\ntitle_text:Miscellaneous scraps of paper from P.O.W James Steele Archives (30 pieces) P.O.W. James Steele Archives: Letter of acknowledgement from Colonial Secretary\npreference:alternate main\ntitle_language:\ncreation_date:1941-1945\ncreation_place_original_location:Singapore\ninscriptions:\ninscription_language:\nshape:rectangular\nmaterials_name:paper (fiber product)\ntechniques_name:writing (processes) printing (process)\nobject_colour:multicolored\nphysical_appearance:This is a letter. The letter is printed in black ink on a plain sheet of paper. The letterhead is printed at the top\n with a circular logo of the Colonial Secretary\n Straits Settlement printed at the top. The date is printed at the top-right corner. There is a blue stamp with red inscriptions at the top-right corner. The letter is printed in a small paragraph at the right hand side of the paper. The signature is printed at the bottom-left corner. The document has several tears and folds around the edges especially along the top-right and borrom-left corners.\nsubject_terms_1:world wars prisoners of war documents (object genre) petitions\nsubject_terms_2:World War\n 1939-1945 Prisoners of war Letters Petitions\nsubject_terms_3:war personalities Letters\nsubject_terms_4:\nsgcool_label_text:Loose papers from the James Steele\n P.O.W archive that include a symbolic drawing\n Japanese banana money\n map of camp\n administrative papers from Changi prison pre-dating internment\n list of soldiers of a regiment as well as James Steele’s warrant to  join the army. These papers are part of the archive of James Steele\n Royal Artillery (Field) who served in Malaya from January 1941-February 1942\n when interned as a P.O.W at Changi until his release in October 1945.","createdDate":"20201018182636","version":0,"latest":false,"roles":[],"metadata":{"accession_no_csv":"2017-00302-024","Image":"","object_work_type":"letters (correspondence)","title_text":"Miscellaneous scraps of paper from P.O.W James Steele Archives (30 pieces) P.O.W. James Steele Archives: Letter of acknowledgement from Colonial Secretary","preference":"alternate main","title_language":"","creation_date":"1941-1945","creation_place_original_location":"Singapore","inscriptions":"","inscription_language":"","shape":"rectangular","materials_name":"paper (fiber product)","techniques_name":"writing (processes) printing (process)","object_colour":"multicolored","physical_appearance":"This is a letter. The letter is printed in black ink on a plain sheet of paper. The letterhead is printed at the top, with a circular logo of the Colonial Secretary, Straits Settlement printed at the top. The date is printed at the top-right corner. There is a blue stamp with red inscriptions at the top-right corner. The letter is printed in a small paragraph at the right hand side of the paper. The signature is printed at the bottom-left corner. The document has several tears and folds around the edges especially along the top-right and borrom-left corners.","subject_terms_1":"world wars prisoners of war documents (object genre) petitions","subject_terms_2":"World War, 1939-1945 Prisoners of war Letters Petitions","subject_terms_3":"war personalities Letters","subject_terms_4":"","sgcool_label_text":"Loose papers from the James Steele, P.O.W archive that include a symbolic drawing, Japanese banana money, map of camp, administrative papers from Changi prison pre-dating internment, list of soldiers of a regiment as well as James Steele’s warrant to  join the army. These papers are part of the archive of James Steele, Royal Artillery (Field) who served in Malaya from January 1941-February 1942, when interned as a P.O.W at Changi until his release in October 1945."},"nlpDate":"20201018182636","connectorId":0,"tags":{}}