{"id":"2017-00792-014","title":"Photographs of Dr Joseph M Carrier 1962-1973","source":"Bumblebee","path":"./Data/json/","content":"accession_no_csv:2017-00792-014\nImage:\nobject_work_type:photogravures (prints)\ntitle_text:Photographs of Dr Joseph M Carrier 1962-1973\npreference:main\ntitle_language:\ncreator_2:Danh Vo  Joseph Carrier\ncreator_1:Vo\n Danh\n 1975-  Carrier\n Joseph M.\ncreator_role:Artist (visual artists)  Photographers\ncreation_date:2010\ncreation_place_original_location:Vietnam\ninscriptions:\ninscription_language:\nshape:Rectangular\nmaterials_name:paper (fiber product)\ntechniques_name:photogravure (process)\nobject_colour:black-and-white (colours)\nedition_description:24th edition\nphysical_appearance:This is a portrait of a shirtless man backfacing the viewer. He stands facing the ocean\n whilst leaning against the ledge.\nsubject_terms_1:black-and-white prints (prints on paper)  histories (literature genre)  travel photography\nsubject_terms_2:Black \\u0026 White Pictures  Genre prints  Travel photography  Vietnamese  Carrier\n Joseph M.\nsubject_terms_3:Travel photography  Visual arts\nsgcool_label_text:Born in Vietnam in 1975 and brought up in Denmark\n Danh Vo’s conceptual artworks and installations often draw upon elements of personal lived experience (his own\n the lives of his parents and other family members) to explore broader historical\n social or political themes\n particularly those relating to the history of Vietnam at the close of the twentieth century. The photos were taken by Joseph Carrier\n an American working in Vietnam. Like the objects owned by McNamara and JFK in Danh’s Mother Tongue show\n or Martin Wong’s possessions in IMU UR2\n the acquisition and appropriation of the photos become part of the work. That is\n the history of the object matters. Here\n meaning slides between US involvement in Vietnam\n Carrier’s history and Danh’s own history.","createdDate":"20201119143406","version":0,"latest":false,"roles":[],"metadata":{"accession_no_csv":"2017-00792-014","Image":"","object_work_type":"photogravures (prints)","title_text":"Photographs of Dr Joseph M Carrier 1962-1973","preference":"main","title_language":"","creator_2":"Danh Vo  Joseph Carrier","creator_1":"Vo, Danh, 1975-  Carrier, Joseph M.","creator_role":"Artist (visual artists)  Photographers","creation_date":"2010","creation_place_original_location":"Vietnam","inscriptions":"","inscription_language":"","shape":"Rectangular","materials_name":"paper (fiber product)","techniques_name":"photogravure (process)","object_colour":"black-and-white (colours)","edition_description":"24th edition","physical_appearance":"This is a portrait of a shirtless man backfacing the viewer. He stands facing the ocean, whilst leaning against the ledge.","subject_terms_1":"black-and-white prints (prints on paper)  histories (literature genre)  travel photography","subject_terms_2":"Black \u0026 White Pictures  Genre prints  Travel photography  Vietnamese  Carrier, Joseph M.","subject_terms_3":"Travel photography  Visual arts","sgcool_label_text":"Born in Vietnam in 1975 and brought up in Denmark, Danh Vo’s conceptual artworks and installations often draw upon elements of personal lived experience (his own, the lives of his parents and other family members) to explore broader historical, social or political themes, particularly those relating to the history of Vietnam at the close of the twentieth century. The photos were taken by Joseph Carrier, an American working in Vietnam. Like the objects owned by McNamara and JFK in Danh’s Mother Tongue show, or Martin Wong’s possessions in IMU UR2, the acquisition and appropriation of the photos become part of the work. That is, the history of the object matters. Here, meaning slides between US involvement in Vietnam, Carrier’s history and Danh’s own history."},"nlpDate":"20201119143406","connectorId":0,"tags":{}}