{
  "id": "2017-00956",
  "title": "Rafflesia patma Coloured lithograph of the Rafflesia patma",
  "source": "Bumblebee",
  "path": "./Data/json/",
  "content": "\n  accession_no_csv: 2017-00956\n\n  Image: \n\n  object_work_type: colour lithographs\n\n  title_text: Rafflesia patma Coloured lithograph of the Rafflesia patma\n\n  preference: main alternative\n\n  title_language: \n\n  creator_2: Flore des serres et des Jardins de l\\u0027Europe\n\n  creator_1: Not indicated\n\n  creator_role: publishers\n\n  creation_date: 1862-1865\n\n  creation_place_original_location: Belgium\n\n  inscriptions: \n\n  inscription_language: \n\n  shape: rectangular\n\n  materials_name: printing paper\n\n  techniques_name: printing (process)\n\n  object_colour: multicoloured\n\n  physical_appearance: \\The image shows a lithographic print. It is rectangular in shape and \\\\Rafflesia Patma B1\\\\ is stated at the bottom centre. Above it are four separate images of the same plant species. The bottom two images show the plant in the earliest stage of its life cycle\n\n  subject_terms_1: with its unbloomed flower and a tiny flower emerging respectively. The top two images show the plant in its later life cycles botany\n\n  subject_terms_2: Rafflesiaceae with its flower getting bigger and its interior being visible. \\ Botany\n\n  subject_terms_3: Angiospermae (division) Visual arts\n\n  subject_terms_4: Lithographs\n\n  context_1: Plants\n",
  "createdDate": "20201125084514",
  "version": 0,
  "latest": false,
  "roles": [],
  "metadata": {
    "accession_no_csv": "2017-00956",
    "Image": "",
    "object_work_type": "colour lithographs",
    "title_text": "Rafflesia patma Coloured lithograph of the Rafflesia patma",
    "preference": "main alternative",
    "title_language": "",
    "creator_2": "Flore des serres et des Jardins de l\u0027Europe",
    "creator_1": "Not indicated",
    "creator_role": "publishers",
    "creation_date": "1862-1865",
    "creation_place_original_location": "Belgium",
    "inscriptions": "",
    "inscription_language": "",
    "shape": "rectangular",
    "materials_name": "printing paper",
    "techniques_name": "printing (process)",
    "object_colour": "multicoloured",
    "physical_appearance": "\"The image shows a lithographic print. It is rectangular in shape and \"\"Rafflesia Patma B1\"\" is stated at the bottom centre. Above it are four separate images of the same plant species. The bottom two images show the plant in the earliest stage of its life cycle",
    "subject_terms_1": "with its unbloomed flower and a tiny flower emerging respectively. The top two images show the plant in its later life cycles botany",
    "subject_terms_2": "Rafflesiaceae with its flower getting bigger and its interior being visible. \" Botany",
    "subject_terms_3": "Angiospermae (division) Visual arts",
    "subject_terms_4": "Lithographs",
    "context_1": "Plants"
  },
  "nlpDate": "20201125084514",
  "connectorId": 0,
  "tags": {}
}