{"id":"2017-00494","title":"\"Japanese photography magazine, \"\"Shashin Shuho\"\" (The Week in Photographs) Shashin Shuho Issue No. 206","source":"Bumblebee","path":"./Data/json/","content":"accession_no_csv:2017-00494\nImage:\nobject_work_type:magazines (periodicals)\ntitle_text:\\Japanese photography magazine\n \\\\Shashin Shuho\\\\ (The Week in Photographs) Shashin Shuho Issue No. 206\npreference:Issue No. 206\\ main\ntitle_language:alternate\ncreator_2:\ncreator_1:Cabinet Intelligence Department (Japan)\ncreation_date:Publisher\ncreation_place_original_location:1942 Singapore\nstyles_periods_indexing_terms:Japan\ninscription_language:\nscale_type:\nmaterials_name:rectangular printing paper\ntechniques_name:paper (fiber product)\nobject_colour:printing (process)\nedition_description:grey\nsubject_terms_1:This pictorial journal is grey in colour and it does not look creased. The page on the left has a darker tone of grey as compared to the one on the right. The page spread depicts Japanese military activity in Malaya and Burma. There is an image of a map of Malaya and Singapore with Japanese flags scattered among its territories. There are kanji scripts on the pages.  news photographs invasions\nsubject_terms_2:world wars Japan. Rikugun Malaya Shashin Shuho Periodicals\nsubject_terms_3:World War\n 1939 - 1945 Wars\nsubject_terms_4:1942-1945 Japanese occupation\ncontext_2:World War\n 1939 - 1945\ncontext_3:world wars\ncontext_4:1939 - 1945\ncontext_5:1939\ncontext_6:1945\ncontext_7:Southeast Asia\ncontext_8:Southeast Asia","createdDate":"20201018182636","version":0,"latest":false,"roles":[],"metadata":{"accession_no_csv":"2017-00494","Image":"","object_work_type":"magazines (periodicals)","title_text":"\"Japanese photography magazine, \"\"Shashin Shuho\"\" (The Week in Photographs) Shashin Shuho Issue No. 206","preference":"Issue No. 206\" main","title_language":"alternate","creator_2":"","creator_1":"Cabinet Intelligence Department (Japan)","creation_date":"Publisher","creation_place_original_location":"1942 Singapore","styles_periods_indexing_terms":"Japan","inscription_language":"","scale_type":"","materials_name":"rectangular printing paper","techniques_name":"paper (fiber product)","object_colour":"printing (process)","edition_description":"grey","subject_terms_1":"This pictorial journal is grey in colour and it does not look creased. The page on the left has a darker tone of grey as compared to the one on the right. The page spread depicts Japanese military activity in Malaya and Burma. There is an image of a map of Malaya and Singapore with Japanese flags scattered among its territories. There are kanji scripts on the pages.  news photographs invasions","subject_terms_2":"world wars Japan. Rikugun Malaya Shashin Shuho Periodicals","subject_terms_3":"World War, 1939 - 1945 Wars","subject_terms_4":"1942-1945 Japanese occupation","context_2":"World War, 1939 - 1945","context_3":"world wars","context_4":"1939 - 1945","context_5":"1939","context_6":"1945","context_7":"Southeast Asia","context_8":"Southeast Asia"},"nlpDate":"20201018182636","connectorId":0,"tags":{}}