{
  "id": "2017-00509",
  "title": "Passage to Little India (Billboard Painting)",
  "source": "Bumblebee",
  "path": "./Data/json/",
  "content": "\n  accession_no_csv: 2017-00509\n\n  Image: \n\n  object_work_type: acrylic paintings (visual works)  canvas paining\n\n  title_text: Passage to Little India (Billboard Painting)\n\n  preference: main\n\n  title_language: \n\n  creator_2: Navin Rawanchaikul\n\n  creator_1: Rawanchaikul\n Navin\n\n  creator_role: artists (visual artists)\n\n  creation_date: 2016\n\n  creation_place_original_location: Singapore\n\n  inscriptions: \n\n  inscription_language: \n\n  shape: Rectangular\n\n  materials_name: acrylic paint  canvas board canvas (textile material)\n\n  techniques_name: acrylic painting (technique)\n\n  object_colour: multicoloured\n\n  physical_appearance: \\This is an acrylic painted billboard featuring a collage of the sights and people of Little India. The title\n \\\\A Passage to Little India\\\\ is painted in red and yellow in bold across the top panel.\\\n\n  subject_terms_1: billboard art  communities (inhabited places)  photomontages\n\n  subject_terms_2: Billboards  Little India (Singapore)  Communities  Rawanchaikul\n Navin Local history  Acrylic painting  Photomontage\n\n  subject_terms_3: Little India Conservation Area Little India Sub Zone History  Poster art Acrylic painting\n\n  subject_terms_4: \n\n  sgcool_label_text: \\The large billboard painting covers the history of Little India in Singapore through archival and recent pictures of the community. The compiled images of people and places integrate texts and titles like a movie poster\n providing an introductory note to the visualised narrative of the artist\\u0027s journey through Little India\n past and present\n which is further fleshed out through the two accompanying pieces of \\\\Passage to Little India\\\\.\\\n",
  "createdDate": "20201120223708",
  "version": 0,
  "latest": false,
  "roles": [],
  "metadata": {
    "accession_no_csv": "2017-00509",
    "Image": "",
    "object_work_type": "acrylic paintings (visual works)  canvas paining",
    "title_text": "Passage to Little India (Billboard Painting)",
    "preference": "main",
    "title_language": "",
    "creator_2": "Navin Rawanchaikul",
    "creator_1": "Rawanchaikul, Navin",
    "creator_role": "artists (visual artists)",
    "creation_date": "2016",
    "creation_place_original_location": "Singapore",
    "inscriptions": "",
    "inscription_language": "",
    "shape": "Rectangular",
    "materials_name": "acrylic paint  canvas board canvas (textile material)",
    "techniques_name": "acrylic painting (technique)",
    "object_colour": "multicoloured",
    "physical_appearance": "\"This is an acrylic painted billboard featuring a collage of the sights and people of Little India. The title, \"\"A Passage to Little India\"\" is painted in red and yellow in bold across the top panel.\"",
    "subject_terms_1": "billboard art  communities (inhabited places)  photomontages",
    "subject_terms_2": "Billboards  Little India (Singapore)  Communities  Rawanchaikul, Navin Local history  Acrylic painting  Photomontage",
    "subject_terms_3": "Little India Conservation Area Little India Sub Zone History  Poster art Acrylic painting",
    "subject_terms_4": "",
    "sgcool_label_text": "\"The large billboard painting covers the history of Little India in Singapore through archival and recent pictures of the community. The compiled images of people and places integrate texts and titles like a movie poster, providing an introductory note to the visualised narrative of the artist\u0027s journey through Little India, past and present, which is further fleshed out through the two accompanying pieces of \"\"Passage to Little India\"\".\""
  },
  "nlpDate": "20201120223708",
  "connectorId": 0,
  "tags": {}
}