{"id":"2017-00072","title":"A Sanskrit Lexicon Amarakosa Sanskrit Lexicon","source":"Bumblebee","path":"./Data/json/","content":"accession_no_csv:2017-00072\nImage:\nobject_work_type:lexicons\ntitle_text:A Sanskrit Lexicon Amarakosa Sanskrit Lexicon\npreference:alternate alternate main\ntitle_language:English\ncreation_date:Early 19th century\ncreation_place_original_location:Sri Lanka\ninscriptions:\ninscription_language:\nshape:irregular\nmaterials_name:palm leaf (material)\ntechniques_name:inscribing\nobject_colour:brown (color)\nphysical_appearance:This is a Sanskrit Lexicon. It is compiled on inscribed palm leaf pieces. Each piece is rectangular in shape\n and has two holes in the center. There is a string by the compiled manuscript.\nsubject_terms_1:Sanskrit (language) inscriptions\nsubject_terms_2:Dictionaries Sanskrit language Palm-leaf inscriptions\nsubject_terms_3:\nsubject_terms_4:\nsgcool_label_text:The Amarakosa (“immortal treasure”) is a lexicon of the Sanskrit language\n authored sometime between the 5th and 8th centuries\n and has had over 40 commentaries written to it. This palm-leaf manuscript of the Amarakosa originates from Sri Lanka\n dating to the early 19th century\n indicating the spread of the usage and study of Sanskrit\n and its continued prevalence even in the 19th century.","createdDate":"20201018182636","version":0,"latest":false,"roles":[],"metadata":{"accession_no_csv":"2017-00072","Image":"","object_work_type":"lexicons","title_text":"A Sanskrit Lexicon Amarakosa Sanskrit Lexicon","preference":"alternate alternate main","title_language":"English","creation_date":"Early 19th century","creation_place_original_location":"Sri Lanka","inscriptions":"","inscription_language":"","shape":"irregular","materials_name":"palm leaf (material)","techniques_name":"inscribing","object_colour":"brown (color)","physical_appearance":"This is a Sanskrit Lexicon. It is compiled on inscribed palm leaf pieces. Each piece is rectangular in shape, and has two holes in the center. There is a string by the compiled manuscript.","subject_terms_1":"Sanskrit (language) inscriptions","subject_terms_2":"Dictionaries Sanskrit language Palm-leaf inscriptions","subject_terms_3":"","subject_terms_4":"","sgcool_label_text":"The Amarakosa (“immortal treasure”) is a lexicon of the Sanskrit language, authored sometime between the 5th and 8th centuries, and has had over 40 commentaries written to it. This palm-leaf manuscript of the Amarakosa originates from Sri Lanka, dating to the early 19th century, indicating the spread of the usage and study of Sanskrit, and its continued prevalence even in the 19th century."},"nlpDate":"20201018182636","connectorId":0,"tags":{}}