{
  "id": "2017-00926",
  "title": "Ensign Carbine, Houghton-Butcher",
  "source": "Bumblebee",
  "path": "./Data/json/",
  "content": "\n  accession_no_csv: 2017-00926\n\n  Image: \n\n  object_work_type: folding cameras\n\n  title_text: Ensign Carbine\n Houghton-Butcher\n\n  preference: main\n\n  title_language: \n\n  creator_2: Houghton-Butcher Manufacturing Co. (?)\n\n  creator_role: manufacturers\n\n  creation_date: early 20th century\n\n  creation_place_original_location: England\n\n  inscriptions: \n\n  inscription_language: \n\n  shape: irregular\n\n  materials_name: glass (material) brass (alloy) metal leather\n\n  object_colour: multicolored\n\n  physical_appearance: This is an Ensign folding camera. It has a brown external body\n and opens up horizontally along the side. The lens is folded inwards by black struts. The exterior of the camera is slightly scratched and faded.\n\n  subject_terms_1: vintage (period) photography (discipline) cameras (photographic equipment)\n\n  subject_terms_2: Photography Cameras Vintage Leica camera\n\n  subject_terms_3: Photography\n\n  sgcool_label_text: The Ensign camera was produced by Houghton-Butcher Manufacturing Co. Promoted with the tagline ‘Cameras for the Tropics’\n it was available in Robinsons and Co. as early as 1909. \\r\\n\\r\\nBefore the advent of the portable camera in the late 19th century\n the taking of photographs was limited to the studio. However portable cameras remained affordable only to the rich until the first decades of the 20th century.\n",
  "createdDate": "20201201203308",
  "version": 0,
  "latest": false,
  "roles": [],
  "metadata": {
    "accession_no_csv": "2017-00926",
    "Image": "",
    "object_work_type": "folding cameras",
    "title_text": "Ensign Carbine, Houghton-Butcher",
    "preference": "main",
    "title_language": "",
    "creator_2": "Houghton-Butcher Manufacturing Co. (?)",
    "creator_role": "manufacturers",
    "creation_date": "early 20th century",
    "creation_place_original_location": "England",
    "inscriptions": "",
    "inscription_language": "",
    "shape": "irregular",
    "materials_name": "glass (material) brass (alloy) metal leather",
    "object_colour": "multicolored",
    "physical_appearance": "This is an Ensign folding camera. It has a brown external body, and opens up horizontally along the side. The lens is folded inwards by black struts. The exterior of the camera is slightly scratched and faded.",
    "subject_terms_1": "vintage (period) photography (discipline) cameras (photographic equipment)",
    "subject_terms_2": "Photography Cameras Vintage Leica camera",
    "subject_terms_3": "Photography",
    "sgcool_label_text": "The Ensign camera was produced by Houghton-Butcher Manufacturing Co. Promoted with the tagline ‘Cameras for the Tropics’, it was available in Robinsons and Co. as early as 1909. \r\n\r\nBefore the advent of the portable camera in the late 19th century, the taking of photographs was limited to the studio. However portable cameras remained affordable only to the rich until the first decades of the 20th century."
  },
  "nlpDate": "20201201203308",
  "connectorId": 0,
  "tags": {}
}