{"id":"2017-00126","title":"Tan Chong Tee Collection: Certificate for Overseas Chinese  ?????","source":"Bumblebee","path":"./Data/json/","content":"accession_no_csv:2017-00126\nImage:\nobject_work_type:certificates\ntitle_text:Tan Chong Tee Collection: Certificate for Overseas Chinese  ?????\npreference:main alternate\ntitle_language:\ncreation_date:1942\ncreation_place_original_location:Singapore\ninscriptions:\ninscription_language:\nshape:rectangular\nmaterials_name:paper (fiber product) ink\ntechniques_name:printing (processes)\nobject_colour:multicolored\nphysical_appearance:This is a certificate from the Kuomintang. The cover is dark blue in colour\n with beige prints. In the center of the certificate cover\n there is a geometric symbol of a sun. The title is printed below the sun. There is a border around the edge. The edges of the certificate is worn out\n especially around the sides\n with scratch marks.\nsubject_terms_1:world wars resistance movements documents (object genre) Chinese scripts\nsubject_terms_2:World War\n 1939-1945 Great Britain. Army. Force 136 Force 136 (Guerilla movement) Chen\n Chongzhi\n 1916- Certification Zhongguo guo min dang\nsubject_terms_3:Force 136 (Guerilla movement) Tan\n Chong Tee 1942-1945 Japanese occupation\nsubject_terms_4:\ncontext_1:World War\n 1939-1945 1942-1945 Japanese Occupation\ncontext_2:world wars occupations (armed conflicts)\ncontext_3:1939-1945 1942-1945\ncontext_4:1939 1942\ncontext_5:1945 1945\ncontext_6:Malaya Singapore\ncontext_7:Great Britain. Army. Force 136\ncontext_8:armed forces\nsgcool_label_text:This certificate belongs to part of a collection of artefacts related to the World War II underground resistance movement known as Force 136. The collection of materials was gathered by Tan Chong Tee (1916- 2012)\n who was a key member of this resistance group. The collection consists of original materials belonging to Tan and other members of Force 136 dating from the 1940s to new materials reproduced from memory by Tan Chong Tee\n which date from the late 1980s to early 2000s. \\r\\n\\r\\nForce 136 was set up in July 1942 as part of the British Special Operations Executive (SOE). It recruited and trained local guerillas to gather intelligence and create an underground spy network to support planned British invasion of Japanese-occupied Malaya.","createdDate":"20201018182636","version":0,"latest":false,"roles":[],"metadata":{"accession_no_csv":"2017-00126","Image":"","object_work_type":"certificates","title_text":"Tan Chong Tee Collection: Certificate for Overseas Chinese  ?????","preference":"main alternate","title_language":"","creation_date":"1942","creation_place_original_location":"Singapore","inscriptions":"","inscription_language":"","shape":"rectangular","materials_name":"paper (fiber product) ink","techniques_name":"printing (processes)","object_colour":"multicolored","physical_appearance":"This is a certificate from the Kuomintang. The cover is dark blue in colour, with beige prints. In the center of the certificate cover, there is a geometric symbol of a sun. The title is printed below the sun. There is a border around the edge. The edges of the certificate is worn out, especially around the sides, with scratch marks.","subject_terms_1":"world wars resistance movements documents (object genre) Chinese scripts","subject_terms_2":"World War, 1939-1945 Great Britain. Army. Force 136 Force 136 (Guerilla movement) Chen, Chongzhi, 1916- Certification Zhongguo guo min dang","subject_terms_3":"Force 136 (Guerilla movement) Tan, Chong Tee 1942-1945 Japanese occupation","subject_terms_4":"","context_1":"World War, 1939-1945 1942-1945 Japanese Occupation","context_2":"world wars occupations (armed conflicts)","context_3":"1939-1945 1942-1945","context_4":"1939 1942","context_5":"1945 1945","context_6":"Malaya Singapore","context_7":"Great Britain. Army. Force 136","context_8":"armed forces","sgcool_label_text":"This certificate belongs to part of a collection of artefacts related to the World War II underground resistance movement known as Force 136. The collection of materials was gathered by Tan Chong Tee (1916- 2012), who was a key member of this resistance group. The collection consists of original materials belonging to Tan and other members of Force 136 dating from the 1940s to new materials reproduced from memory by Tan Chong Tee, which date from the late 1980s to early 2000s. \r\n\r\nForce 136 was set up in July 1942 as part of the British Special Operations Executive (SOE). It recruited and trained local guerillas to gather intelligence and create an underground spy network to support planned British invasion of Japanese-occupied Malaya."},"nlpDate":"20201018182636","connectorId":0,"tags":{}}