{
  "id": "2017-00181-002",
  "title": "Lim Hong Pei Collection: Certificate  Lim Hong Pei Collection: Photographs and Certificate",
  "source": "Bumblebee",
  "path": "./Data/json/",
  "content": "\n  accession_no_csv: 2017-00181-002\n\n  Image: \n\n  object_work_type: certificates\n\n  title_text: Lim Hong Pei Collection: Certificate  Lim Hong Pei Collection: Photographs and Certificate\n\n  preference: main alternate\n\n  title_language: \n\n  creation_date: Not indicated\n\n  creation_place_original_location: Singapore\n\n  inscriptions: \n\n  inscription_language: \n\n  shape: rectangular\n\n  materials_name: paper (fiber product)\n\n  techniques_name: printing (process)\n\n  object_colour: multicolored\n\n  physical_appearance: This is a certificate. It consists of two sides when opened by the fold. The template of the certificate is printed in blue. On the top-left side\n there is a photography identification attached within a blue box. The fields of the certificate appears to be empty. The certificate has a rust mark on the top-right\n and is slightly folded along the right edge.\n\n  subject_terms_1: resistance movements identification photographs world wars Kanji (writing system)\n\n  subject_terms_2: Lim\n Hong Pei\n 1922- World War\n 1939-1945 Kanji Great Britain. Army. Force 136 Certification Force 136 (Guerilla movement) Identification photographs\n\n  subject_terms_3: 1942-1945 Japanese occupation Force 136 (Guerilla movement) war personalities\n\n  subject_terms_4: \n\n  context_1: World War\n 1939-1945 1942-1945 Japanese Occupation\n\n  context_2: occupations (armed conflicts) world wars\n\n  context_3: 1942-1945 1939-1945\n\n  context_4: 1939 1942\n\n  context_5: 1945\n\n  context_6: Singapore Malaya\n\n  context_7: Great Britain. Army. Force 136\n\n  context_8: armed forces\n\n  sgcool_label_text: These photograph and certificate belong to part of a collection of artefacts related to the World War II underground resistance movement known as Force 136. The collection of materials was gathered by Tan Chong Tee (1916- 2012)\n who was a key member of this resistance group. The collection consists of original materials belonging to Tan and other members of Force 136 dating from the 1940s to new materials reproduced from memory by Tan Chong Tee\n which date from the late 1980s to early 2000s. \\r\\n\\r\\nForce 136 was set up in July 1942 as part of the British Special Operations Executive (SOE). It recruited and trained local guerillas to gather intelligence and create an underground spy network to support planned British invasion of Japanese-occupied Malaya.\n",
  "createdDate": "20201201203308",
  "version": 0,
  "latest": false,
  "roles": [],
  "metadata": {
    "accession_no_csv": "2017-00181-002",
    "Image": "",
    "object_work_type": "certificates",
    "title_text": "Lim Hong Pei Collection: Certificate  Lim Hong Pei Collection: Photographs and Certificate",
    "preference": "main alternate",
    "title_language": "",
    "creation_date": "Not indicated",
    "creation_place_original_location": "Singapore",
    "inscriptions": "",
    "inscription_language": "",
    "shape": "rectangular",
    "materials_name": "paper (fiber product)",
    "techniques_name": "printing (process)",
    "object_colour": "multicolored",
    "physical_appearance": "This is a certificate. It consists of two sides when opened by the fold. The template of the certificate is printed in blue. On the top-left side, there is a photography identification attached within a blue box. The fields of the certificate appears to be empty. The certificate has a rust mark on the top-right, and is slightly folded along the right edge.",
    "subject_terms_1": "resistance movements identification photographs world wars Kanji (writing system)",
    "subject_terms_2": "Lim, Hong Pei, 1922- World War, 1939-1945 Kanji Great Britain. Army. Force 136 Certification Force 136 (Guerilla movement) Identification photographs",
    "subject_terms_3": "1942-1945 Japanese occupation Force 136 (Guerilla movement) war personalities",
    "subject_terms_4": "",
    "context_1": "World War, 1939-1945 1942-1945 Japanese Occupation",
    "context_2": "occupations (armed conflicts) world wars",
    "context_3": "1942-1945 1939-1945",
    "context_4": "1939 1942",
    "context_5": "1945",
    "context_6": "Singapore Malaya",
    "context_7": "Great Britain. Army. Force 136",
    "context_8": "armed forces",
    "sgcool_label_text": "These photograph and certificate belong to part of a collection of artefacts related to the World War II underground resistance movement known as Force 136. The collection of materials was gathered by Tan Chong Tee (1916- 2012), who was a key member of this resistance group. The collection consists of original materials belonging to Tan and other members of Force 136 dating from the 1940s to new materials reproduced from memory by Tan Chong Tee, which date from the late 1980s to early 2000s. \r\n\r\nForce 136 was set up in July 1942 as part of the British Special Operations Executive (SOE). It recruited and trained local guerillas to gather intelligence and create an underground spy network to support planned British invasion of Japanese-occupied Malaya."
  },
  "nlpDate": "20201201203308",
  "connectorId": 0,
  "tags": {}
}