{
  "id": "2017-00041",
  "title": "Ripple Reflection",
  "source": "Bumblebee",
  "path": "./Data/json/",
  "content": "\n  accession_no_csv: 2017-00041\n\n  Image: \n\n  object_work_type: black-and-white prints (photographs) photographic prints gelatin silver prints\n\n  title_text: Ripple Reflection\n\n  preference: main\n\n  title_language: \n\n  creator_2: Lee\n Lim\n\n  creator_1: Lee\n Lim\n\n  creator_role: photographers\n\n  creation_date: c.1960\n\n  creation_place_original_location: Singapore\n\n  inscriptions: \n\n  inscription_language: \n\n  shape: Rectangular\n\n  materials_name: silver sulfide paper (fibre product) baryta paper gelatin\n\n  techniques_name: gelatin silver process photographic printing techniques black-and-white photography\n\n  object_colour: black-and-white (colours)\n\n  physical_appearance: This print shows the bow of a boat and its ripple reflection in the water. The edges of the print show a degree of discolouration.\n\n  subject_terms_1: reflection (action) Mariners\\u0027 Museum (Newport News\n Va)_ boats bodies of water (natural)\n\n  subject_terms_2: Boats and boating Bodies of water Marine photography Reflections Photography\n Artistic\n\n  subject_terms_3: visual arts Artistic photography\n\n  context_21: No 1 Tiong Bahru Road\n Singapore 3\n\n  sgcool_label_text: Lee Lim was one of the most important modern photographers in Singapore\n influencing a generation of photographers in the pictorial photography circles. Between 1952 and 1979\n Lee took part in more than 100 photographic competitions and won numerous awards and honours. He received the Fellowship of the Royal Photographic Society (UK) in 1959 and the Artist Distinction by the International Federation of Photographic Art (FIAP) in 1977. He was also conferred an honorary fellowship by the Photographic Society of Singapore and won the Cultural Medallion in 1987.\n",
  "createdDate": "20201201203308",
  "version": 0,
  "latest": false,
  "roles": [],
  "metadata": {
    "accession_no_csv": "2017-00041",
    "Image": "",
    "object_work_type": "black-and-white prints (photographs) photographic prints gelatin silver prints",
    "title_text": "Ripple Reflection",
    "preference": "main",
    "title_language": "",
    "creator_2": "Lee, Lim",
    "creator_1": "Lee, Lim",
    "creator_role": "photographers",
    "creation_date": "c.1960",
    "creation_place_original_location": "Singapore",
    "inscriptions": "",
    "inscription_language": "",
    "shape": "Rectangular",
    "materials_name": "silver sulfide paper (fibre product) baryta paper gelatin",
    "techniques_name": "gelatin silver process photographic printing techniques black-and-white photography",
    "object_colour": "black-and-white (colours)",
    "physical_appearance": "This print shows the bow of a boat and its ripple reflection in the water. The edges of the print show a degree of discolouration.",
    "subject_terms_1": "reflection (action) Mariners\u0027 Museum (Newport News, Va)_ boats bodies of water (natural)",
    "subject_terms_2": "Boats and boating Bodies of water Marine photography Reflections Photography, Artistic",
    "subject_terms_3": "visual arts Artistic photography",
    "context_21": "No 1 Tiong Bahru Road, Singapore 3",
    "sgcool_label_text": "Lee Lim was one of the most important modern photographers in Singapore, influencing a generation of photographers in the pictorial photography circles. Between 1952 and 1979, Lee took part in more than 100 photographic competitions and won numerous awards and honours. He received the Fellowship of the Royal Photographic Society (UK) in 1959 and the Artist Distinction by the International Federation of Photographic Art (FIAP) in 1977. He was also conferred an honorary fellowship by the Photographic Society of Singapore and won the Cultural Medallion in 1987."
  },
  "nlpDate": "20201201203308",
  "connectorId": 0,
  "tags": {}
}