{
  "id": "2017-00318",
  "title": "Yong Bamboo and Rock",
  "source": "Bumblebee",
  "path": "./Data/json/",
  "content": "\n  accession_no_csv: 2017-00318\n\n  Image: \n\n  object_work_type: ink wash paintings\n\n  title_text: Yong Bamboo and Rock\n\n  preference: main alternate\n\n  title_language: \n\n  creator_2: Fan\n Chang Tien\n\n  creator_1: Fan\n Changqian\n 1907-1987\n\n  creator_role: artists (visual artists)\n\n  creation_date: 1973\n\n  styles_periods_indexing_terms: Chinese (culture or style) xieyi\n\n  inscriptions: \n\n  inscription_language: \n\n  shape: Rectangular\n\n  materials_name: paper (fiber product) Chinese ink\n\n  techniques_name: dry-brush painting xieyi painting (image-making)\n\n  object_colour: black-and-white (colours)\n\n  physical_appearance: \\This chinese ink painting of a bamboo and a rock has been executed in a one-colour (yi se biao) style. While the leaves of the bamboo were painted with a wet brush\n its stalk and the rock were done with both wet and dry brushes.  In particular\n the outline of the rock was drawn in a \\\\flying white\\\\ technique where pressure has been applied such that the hairs of the brush separate to reveal streaks of white spaces in the stroke itself. Strokes are then added to produce a less defined effect by utilizing a \\\\bands dragged in mud\\\\ technique. \\\n\n  subject_terms_1: Wen ren running script inscriptions bamboo (plant) rock (inorganic material)\n\n  subject_terms_2: rocks Ink painting\n Chinese Inscriptions\n Chinese Chinese language Writing Xing style Bamboo in art\n\n  subject_terms_3: visual arts Chinese ink painting\n\n  sgcool_label_text: \\As one of the most influential pioneer artists in local art scene\n Fan Chang Tien(1907-1987) was significant in shaping the direction for the modern development of ink painting in Singapore. During the 1920s\n Fan studied in Shanghai Xin Hua Art Academy and then Shanghai Changming Academy of Art. He was taught by renowned Shanghai school artists such as Wang Geyi\n Wang Yiting\n Zhu Wenyun and Pan Tianshou. Fan arrived in Singapore in 1956 and began teaching art in Chung Cheng High School and Whampoa Secondary School respectively. Over decades\n the artist nurtured a group of ink painters\n and some of them become the leading figures of modern ink innovation in Singapore such Chua Ek Kay\n Tan Oe Pang and Chen Kezhan. \\r\\n\\r\\nFan is specialised in the \\\\xiey\\\\i style (an expressive and sketchy style of Chinese ink painting) Chinese painting.  This is one of his best works representing the subjects of bamboo and rock. The compositional emphasis on the rock in front and the seasoned brushstrokes convey the strong spirit of a literati mind.   \\\n",
  "createdDate": "20201201203308",
  "version": 0,
  "latest": false,
  "roles": [],
  "metadata": {
    "accession_no_csv": "2017-00318",
    "Image": "",
    "object_work_type": "ink wash paintings",
    "title_text": "Yong Bamboo and Rock",
    "preference": "main alternate",
    "title_language": "",
    "creator_2": "Fan, Chang Tien",
    "creator_1": "Fan, Changqian, 1907-1987",
    "creator_role": "artists (visual artists)",
    "creation_date": "1973",
    "styles_periods_indexing_terms": "Chinese (culture or style) xieyi",
    "inscriptions": "",
    "inscription_language": "",
    "shape": "Rectangular",
    "materials_name": "paper (fiber product) Chinese ink",
    "techniques_name": "dry-brush painting xieyi painting (image-making)",
    "object_colour": "black-and-white (colours)",
    "physical_appearance": "\"This chinese ink painting of a bamboo and a rock has been executed in a one-colour (yi se biao) style. While the leaves of the bamboo were painted with a wet brush, its stalk and the rock were done with both wet and dry brushes.  In particular, the outline of the rock was drawn in a \"\"flying white\"\" technique where pressure has been applied such that the hairs of the brush separate to reveal streaks of white spaces in the stroke itself. Strokes are then added to produce a less defined effect by utilizing a \"\"bands dragged in mud\"\" technique. \"",
    "subject_terms_1": "Wen ren running script inscriptions bamboo (plant) rock (inorganic material)",
    "subject_terms_2": "rocks Ink painting, Chinese Inscriptions, Chinese Chinese language Writing Xing style Bamboo in art",
    "subject_terms_3": "visual arts Chinese ink painting",
    "sgcool_label_text": "\"As one of the most influential pioneer artists in local art scene, Fan Chang Tien(1907-1987) was significant in shaping the direction for the modern development of ink painting in Singapore. During the 1920s, Fan studied in Shanghai Xin Hua Art Academy and then Shanghai Changming Academy of Art. He was taught by renowned Shanghai school artists such as Wang Geyi, Wang Yiting, Zhu Wenyun and Pan Tianshou. Fan arrived in Singapore in 1956 and began teaching art in Chung Cheng High School and Whampoa Secondary School respectively. Over decades, the artist nurtured a group of ink painters, and some of them become the leading figures of modern ink innovation in Singapore such Chua Ek Kay, Tan Oe Pang and Chen Kezhan. \r\n\r\nFan is specialised in the \"\"xiey\"\"i style (an expressive and sketchy style of Chinese ink painting) Chinese painting.  This is one of his best works representing the subjects of bamboo and rock. The compositional emphasis on the rock in front and the seasoned brushstrokes convey the strong spirit of a literati mind.   \""
  },
  "nlpDate": "20201201203308",
  "connectorId": 0,
  "tags": {}
}