{
  "id": "2017-00499",
  "title": "Diploma certificate from the Academy of Beauty Culture, London",
  "source": "Bumblebee",
  "path": "./Data/json/",
  "content": "\n  accession_no_csv: 2017-00499\n\n  Image: \n\n  object_work_type: certificates\n\n  title_text: Diploma certificate from the Academy of Beauty Culture\n London\n\n  preference: main\n\n  title_language: \n\n  creator_2: The Academy of Beauty Culture\n Ltd ?\n\n  creator_role: administrators?\n\n  creation_date: 1954 14-Sep-54\n\n  creation_place_original_location: London (England)\n\n  inscriptions: \n\n  inscription_language: \n\n  shape: Rectangular\n\n  materials_name: paper (fiber product)\n\n  techniques_name: printing (process) writing (processes)\n\n  object_colour: multicoloured\n\n  physical_appearance: This is a diploma certificate issued and endorsed by The Academy of Beauty Culture Ltd certifying that Florence Chong Chit Moy is qualified to practise short wave epilation. The certificate it framed in a black frame.\n\n  subject_terms_1: education beauty certification diplomas\n\n  subject_terms_2: Diplomas Hair Removal Education Certification Beauty schools\n\n  subject_terms_3: Education?\n\n  sgcool_label_text: This diploma was awarded to Mrs Florence Chong (nee Wong Chit Moy) on 14 September 1954 by the Academy of Beauty Culture Ltd at New Bond Street\n London. Mrs Florence Chong was the seventh sister of prominent local bridal designer Mrs Sylvia Kho (nee Wong Sien Moy). She received training in make-up and hairstyling in London and provided her services to brides in Singapore as early as the 1950s.\n",
  "createdDate": "20201201203308",
  "version": 0,
  "latest": false,
  "roles": [],
  "metadata": {
    "accession_no_csv": "2017-00499",
    "Image": "",
    "object_work_type": "certificates",
    "title_text": "Diploma certificate from the Academy of Beauty Culture, London",
    "preference": "main",
    "title_language": "",
    "creator_2": "The Academy of Beauty Culture, Ltd ?",
    "creator_role": "administrators?",
    "creation_date": "1954 14-Sep-54",
    "creation_place_original_location": "London (England)",
    "inscriptions": "",
    "inscription_language": "",
    "shape": "Rectangular",
    "materials_name": "paper (fiber product)",
    "techniques_name": "printing (process) writing (processes)",
    "object_colour": "multicoloured",
    "physical_appearance": "This is a diploma certificate issued and endorsed by The Academy of Beauty Culture Ltd certifying that Florence Chong Chit Moy is qualified to practise short wave epilation. The certificate it framed in a black frame.",
    "subject_terms_1": "education beauty certification diplomas",
    "subject_terms_2": "Diplomas Hair Removal Education Certification Beauty schools",
    "subject_terms_3": "Education?",
    "sgcool_label_text": "This diploma was awarded to Mrs Florence Chong (nee Wong Chit Moy) on 14 September 1954 by the Academy of Beauty Culture Ltd at New Bond Street, London. Mrs Florence Chong was the seventh sister of prominent local bridal designer Mrs Sylvia Kho (nee Wong Sien Moy). She received training in make-up and hairstyling in London and provided her services to brides in Singapore as early as the 1950s."
  },
  "nlpDate": "20201201203308",
  "connectorId": 0,
  "tags": {}
}