{"id":"2017-00224","title":"English-Malay bi-directional Dictionary  BOWREY, Thomas.  A dictionary English and Malayo, Malayo and English. To which is added some short grammar rules and directions for the better observation of the propriety and elegancy of this language.  London, Sam. Bridge for the author, 1701.","source":"Bumblebee","path":"./Data/json/","content":"accession_no_csv:2017-00224\nImage:\nobject_work_type:dictionaries\ntitle_text:English-Malay bi-directional Dictionary  BOWREY\n Thomas.  A dictionary English and Malayo\n Malayo and English. To which is added some short grammar rules and directions for the better observation of the propriety and elegancy of this language.  London\n Sam. Bridge for the author\n 1701.\npreference:main  alternate\ntitle_language:\ncreator_2:Thomas Bowrey\ncreator_1:Bowrey\n Thomas\n approximately 1650-1713\ncreator_role:compiler (people in literature)  shipmasters\ncreation_date:1701\ncreation_place_original_location:London (England)\ninscriptions:\ninscription_language:\nshape:Rectangular\nmaterials_name:paper (fiber product)\ntechniques_name:compiling (additive processes)\nobject_colour:black-and-white (colours)\nedition_description:First edition\nphysical_appearance:This is an English-Malay dictionary. It is hardback\n and the cover is reddish-brown. Noticeably\n the edges of the papers are red.\nsubject_terms_1:Malay (language)  English (language)\nsubject_terms_2:Dictionary  Malay language  English\nsubject_terms_3:\nsubject_terms_4:\nsgcool_label_text:This is a first edition copy of an English-Malay dictionary\n compiled by Thomas Bowrey and published in London in 1701. Bowrey (ca. 1650-1713)\n was an East India Company (EIC) sea captain who spent nineteen years from 1669 sailing about the islands\n seas and coastlines of the Malay Archipelago. He endured many perils during his voyages\n including attacks by pirates\n hidden shipwrecks and local warfare. Bowrey explains in the Preface (p. 6) the reasons for such a publication: ‘I finding so very few English Men that have attained any tollerable knowledge of the Malayo tongue\n so absolutely necessary to trade in those Southern Seas\n and that there is no book of this kind published in English\n to help the attaining of that Language; these considerations\n I say\n has imboldened me to publish the insuing Dictionary…”. That such a dictionary existed so early in the 18th century\n suggests that international trade in the area was significant enough for the English to learn the language of business there\n i.e. Malay.","createdDate":"20201119143406","version":0,"latest":false,"roles":[],"metadata":{"accession_no_csv":"2017-00224","Image":"","object_work_type":"dictionaries","title_text":"English-Malay bi-directional Dictionary  BOWREY, Thomas.  A dictionary English and Malayo, Malayo and English. To which is added some short grammar rules and directions for the better observation of the propriety and elegancy of this language.  London, Sam. Bridge for the author, 1701.","preference":"main  alternate","title_language":"","creator_2":"Thomas Bowrey","creator_1":"Bowrey, Thomas, approximately 1650-1713","creator_role":"compiler (people in literature)  shipmasters","creation_date":"1701","creation_place_original_location":"London (England)","inscriptions":"","inscription_language":"","shape":"Rectangular","materials_name":"paper (fiber product)","techniques_name":"compiling (additive processes)","object_colour":"black-and-white (colours)","edition_description":"First edition","physical_appearance":"This is an English-Malay dictionary. It is hardback, and the cover is reddish-brown. Noticeably, the edges of the papers are red.","subject_terms_1":"Malay (language)  English (language)","subject_terms_2":"Dictionary  Malay language  English","subject_terms_3":"","subject_terms_4":"","sgcool_label_text":"This is a first edition copy of an English-Malay dictionary, compiled by Thomas Bowrey and published in London in 1701. Bowrey (ca. 1650-1713), was an East India Company (EIC) sea captain who spent nineteen years from 1669 sailing about the islands, seas and coastlines of the Malay Archipelago. He endured many perils during his voyages, including attacks by pirates, hidden shipwrecks and local warfare. Bowrey explains in the Preface (p. 6) the reasons for such a publication: ‘I finding so very few English Men that have attained any tollerable knowledge of the Malayo tongue, so absolutely necessary to trade in those Southern Seas, and that there is no book of this kind published in English, to help the attaining of that Language; these considerations, I say, has imboldened me to publish the insuing Dictionary…”. That such a dictionary existed so early in the 18th century, suggests that international trade in the area was significant enough for the English to learn the language of business there, i.e. Malay."},"nlpDate":"20201119143406","connectorId":0,"tags":{}}