{
  "id": "2017-00388",
  "title": "Sarong",
  "source": "Bumblebee",
  "path": "./Data/json/",
  "content": "\n  accession_no_csv: 2017-00388\n\n  Image: \n\n  object_work_type: batik art sarongs\n\n  title_text: Sarong\n\n  preference: main\n\n  title_language: \n\n  creator_2: Jane Hendromartono\n\n  creator_role: textile designers\n\n  creation_date: 1960\n\n  creation_place_original_location: Pekalongan (Indonesia)\n\n  styles_periods_indexing_terms: Peranakan\n\n  inscriptions: \n\n  inscription_language: \n\n  shape: rectangular\n\n  materials_name: cotton (textile)\n\n  techniques_name: batik\n\n  object_colour: multicolored\n\n  physical_appearance: This is a batik sarong. It features a repeated motif of large bouquets of European flowers interspersed with butterflies and birds. The panel at the bottom of the batik sarong is set against a green background decorated with small leaves. The main body of the batik sarong is set against a purple lilac background.\n\n  subject_terms_1: Peranakan birds (motifs) flower (motif) cultural diffusion folk costume\n\n  subject_terms_2: Motifs Ethnic costume Peranakan (Asian people) Culture diffusion Batik\n\n  subject_terms_3: Peranakan costumes Batik\n\n  sgcool_label_text: The buketan design\n comprising large bouquets of European flowers interspersed with butterflies and birds\n is repeated on this sarong.  It is set against a green background on the kepala (or broad vertical panel of the batik)\n with a background patterning of leaves.  The buketan is repeated on the badan (or main design feature of the batik) against a plain lilac ground.  This batik comes from the family collection of Oey Djien Nio (1929-1987)\n the last in three generations of documented batik-makers in Pekalongan.  In her earlier signatures\n she used her husband’s name\n Liem Siok Hien.  But from 1965 onwards\n she used Jane Hendromartono\n combining her husband’s new Indonesian family name\n Hendromartono with Jane\n as people addressed her by.  She developed a personal style distinct from her mother and grandmother\n and experimented with a wide spectrum of colours and exotic combinations of birds\n rock formations and mythical animals.  Jane Hendromartono’s clientele expanded beyond the elite in Indonesia to include Europe\n America and Japan\n especially in the 1980s.  This piece is signed “Jane Hendro Pekalongan ‘60”.\n",
  "createdDate": "20201125084521",
  "version": 0,
  "latest": false,
  "roles": [],
  "metadata": {
    "accession_no_csv": "2017-00388",
    "Image": "",
    "object_work_type": "batik art sarongs",
    "title_text": "Sarong",
    "preference": "main",
    "title_language": "",
    "creator_2": "Jane Hendromartono",
    "creator_role": "textile designers",
    "creation_date": "1960",
    "creation_place_original_location": "Pekalongan (Indonesia)",
    "styles_periods_indexing_terms": "Peranakan",
    "inscriptions": "",
    "inscription_language": "",
    "shape": "rectangular",
    "materials_name": "cotton (textile)",
    "techniques_name": "batik",
    "object_colour": "multicolored",
    "physical_appearance": "This is a batik sarong. It features a repeated motif of large bouquets of European flowers interspersed with butterflies and birds. The panel at the bottom of the batik sarong is set against a green background decorated with small leaves. The main body of the batik sarong is set against a purple lilac background.",
    "subject_terms_1": "Peranakan birds (motifs) flower (motif) cultural diffusion folk costume",
    "subject_terms_2": "Motifs Ethnic costume Peranakan (Asian people) Culture diffusion Batik",
    "subject_terms_3": "Peranakan costumes Batik",
    "sgcool_label_text": "The buketan design, comprising large bouquets of European flowers interspersed with butterflies and birds, is repeated on this sarong.  It is set against a green background on the kepala (or broad vertical panel of the batik), with a background patterning of leaves.  The buketan is repeated on the badan (or main design feature of the batik) against a plain lilac ground.  This batik comes from the family collection of Oey Djien Nio (1929-1987), the last in three generations of documented batik-makers in Pekalongan.  In her earlier signatures, she used her husband’s name, Liem Siok Hien.  But from 1965 onwards, she used Jane Hendromartono, combining her husband’s new Indonesian family name, Hendromartono with Jane, as people addressed her by.  She developed a personal style distinct from her mother and grandmother, and experimented with a wide spectrum of colours and exotic combinations of birds, rock formations and mythical animals.  Jane Hendromartono’s clientele expanded beyond the elite in Indonesia to include Europe, America and Japan, especially in the 1980s.  This piece is signed “Jane Hendro Pekalongan ‘60”."
  },
  "nlpDate": "20201125084521",
  "connectorId": 0,
  "tags": {}
}