{
  "id": "2017-01039-022",
  "title": "Photograph album presented to George Lowe as a souvenir of his visit to Singapore George Lowe album: Photograph of former Clifford Pier",
  "source": "Bumblebee",
  "path": "./Data/json/",
  "content": "\n  accession_no_csv: 2017-01039-022\n\n  Image: \n\n  object_work_type: black-and-white photographs photographs\n\n  title_text: Photograph album presented to George Lowe as a souvenir of his visit to Singapore George Lowe album: Photograph of former Clifford Pier\n\n  preference: alternate main\n\n  title_language: \n\n  creation_date: 1953\n\n  creation_place_original_location: Singapore\n\n  inscriptions: \n\n  inscription_language: \n\n  shape: rectangular\n\n  materials_name: paper (fiber product)\n\n  techniques_name: photographic processes\n\n  object_colour: black-and-white (colors)\n\n  physical_appearance: This is a black-and-white photograph. There is a wide road starting from the bottom of the photograph and extending towards the top-right. There are rows of parked cars along the road. On the left\n there is a waterfront. There is a built structure extending outwards onto the water. There are several small boats near the port. Several larger ships can be seen in the background\n further from the waterfront. There are no inscriptions on the photograph. There are no tears or folds seen.\n\n  subject_terms_1: Photographs souvenirs waterfronts\n\n  subject_terms_2: Photographs Photograph albums Souvenir Lowe\n George\n 1924-2013 Hillary\n Edmund\n 1919-2008 Waterfronts\n\n  subject_terms_3: Photography Clifford Pier\n\n  subject_terms_4: \n\n  sgcool_label_text: George Lowe was a member of the British Expedition that saw Sir Edmund Hillary scale Mount Everest on 29 May 1953. In September that year\n Lowe accompanied Hillary on a visit to Singapore to deliver their first Everest lecture outside of New Zealand at the Odeon Theatre to an audience of 1\n620 schoolchildren. This photograph album\n with the coat of arms of the City of Singapore in gilt on the cover\n was presented to Lowe as a souvenir of his visit.\n",
  "createdDate": "20201120223708",
  "version": 0,
  "latest": false,
  "roles": [],
  "metadata": {
    "accession_no_csv": "2017-01039-022",
    "Image": "",
    "object_work_type": "black-and-white photographs photographs",
    "title_text": "Photograph album presented to George Lowe as a souvenir of his visit to Singapore George Lowe album: Photograph of former Clifford Pier",
    "preference": "alternate main",
    "title_language": "",
    "creation_date": "1953",
    "creation_place_original_location": "Singapore",
    "inscriptions": "",
    "inscription_language": "",
    "shape": "rectangular",
    "materials_name": "paper (fiber product)",
    "techniques_name": "photographic processes",
    "object_colour": "black-and-white (colors)",
    "physical_appearance": "This is a black-and-white photograph. There is a wide road starting from the bottom of the photograph and extending towards the top-right. There are rows of parked cars along the road. On the left, there is a waterfront. There is a built structure extending outwards onto the water. There are several small boats near the port. Several larger ships can be seen in the background, further from the waterfront. There are no inscriptions on the photograph. There are no tears or folds seen.",
    "subject_terms_1": "Photographs souvenirs waterfronts",
    "subject_terms_2": "Photographs Photograph albums Souvenir Lowe, George, 1924-2013 Hillary, Edmund, 1919-2008 Waterfronts",
    "subject_terms_3": "Photography Clifford Pier",
    "subject_terms_4": "",
    "sgcool_label_text": "George Lowe was a member of the British Expedition that saw Sir Edmund Hillary scale Mount Everest on 29 May 1953. In September that year, Lowe accompanied Hillary on a visit to Singapore to deliver their first Everest lecture outside of New Zealand at the Odeon Theatre to an audience of 1,620 schoolchildren. This photograph album, with the coat of arms of the City of Singapore in gilt on the cover, was presented to Lowe as a souvenir of his visit."
  },
  "nlpDate": "20201120223708",
  "connectorId": 0,
  "tags": {}
}