{
  "id": "2017-00244",
  "title": "67 bottles of beads",
  "source": "Bumblebee",
  "path": "./Data/json/",
  "content": "\n  accession_no_csv: 2017-00244\n\n  Image: \n\n  object_work_type: beads (pierced objects)\n\n  title_text: 67 bottles of beads\n\n  preference: main\n\n  title_language: \n\n  creation_date: Not indicated\n\n  creation_place_original_location: Malacca (Malacca\n Malaysia) Singapore\n\n  styles_periods_indexing_terms: Peranakan\n\n  inscriptions: \n\n  inscription_language: \n\n  shape: irregular\n\n  object_colour: multicolored\n\n  physical_appearance: These are bottles containing beads in various shades. The bottles are of varied sizes\n and are placed in a curved row.\n\n  subject_terms_1: Peranakan sewing tools tailors beadwork (visual works)\n\n  subject_terms_2: Beads Peranakan (Asian people) Sewing Equipment and supplies Tailors Clothing trade Bead embroidery\n\n  subject_terms_3: Vanishing trade Textile art and design\n\n  sgcool_label_text: These bottles contain beads in hues of dark blue\n light blue\n green\n red\n and white. Embroiderers would unstring the beads and categorise them by placing them into small bottles for use. The original owner of these items made a living fashioning beaded slippers and dresses\n working from home as she did not have a shop.\n",
  "createdDate": "20201120223707",
  "version": 0,
  "latest": false,
  "roles": [],
  "metadata": {
    "accession_no_csv": "2017-00244",
    "Image": "",
    "object_work_type": "beads (pierced objects)",
    "title_text": "67 bottles of beads",
    "preference": "main",
    "title_language": "",
    "creation_date": "Not indicated",
    "creation_place_original_location": "Malacca (Malacca, Malaysia) Singapore",
    "styles_periods_indexing_terms": "Peranakan",
    "inscriptions": "",
    "inscription_language": "",
    "shape": "irregular",
    "object_colour": "multicolored",
    "physical_appearance": "These are bottles containing beads in various shades. The bottles are of varied sizes, and are placed in a curved row.",
    "subject_terms_1": "Peranakan sewing tools tailors beadwork (visual works)",
    "subject_terms_2": "Beads Peranakan (Asian people) Sewing Equipment and supplies Tailors Clothing trade Bead embroidery",
    "subject_terms_3": "Vanishing trade Textile art and design",
    "sgcool_label_text": "These bottles contain beads in hues of dark blue, light blue, green, red, and white. Embroiderers would unstring the beads and categorise them by placing them into small bottles for use. The original owner of these items made a living fashioning beaded slippers and dresses, working from home as she did not have a shop."
  },
  "nlpDate": "20201120223707",
  "connectorId": 0,
  "tags": {}
}