{"id":"2017-00066","title":"Robe Silk robe","source":"Bumblebee","path":"./Data/json/","content":"accession_no_csv:2017-00066\nImage:\nobject_work_type:robes (main garments)\ntitle_text:Robe Silk robe\npreference:alternate main\ntitle_language:\ncreation_date:Early 20th century\ncreation_place_original_location:Padang (Indonesia)\nstyles_periods_indexing_terms:Chinese (culture or style)\ninscriptions:\ninscription_language:\nshape:irregular\nmaterials_name:silk (textile)\ntechniques_name:sewing (needleworking technique)\nobject_colour:multicolored\nphysical_appearance:This is a silk robe. It has a V-shaped opening. The collar is enclosed by a quatrefoil of scrolling chrysanthemums and hibiscus. The floral motif is repeated on the edges of the sleeves.  Peacocks interspersed amongst flowers are printed along the bottom on the front of the robe.\nsubject_terms_1:tops (garments\n general) flower (motif) birds (motifs) symbolism (artistic concept) folk costume\nsubject_terms_2:Robes Motifs Symbolism Ethnic costume\nsubject_terms_3:Chinese costumes\nsgcool_label_text:This silk robe has a v-shaped opening for the head.  Its collar is enclosed by a quatrefoil of scrolling chrysanthemums and hibiscus motif.  This cloud cover design\n also known as the auspicious ruiyi fungus motif\n resembles 18th century Qing dynasty robe designs.  The floral motif is repeated on the edges of the sleeves.  Peacocks interspersed among flowers are printed on both the front and back of the robe.  The peacock is a symbol of beauty of dignity in Chinese culture.","createdDate":"20201119143406","version":0,"latest":false,"roles":[],"metadata":{"accession_no_csv":"2017-00066","Image":"","object_work_type":"robes (main garments)","title_text":"Robe Silk robe","preference":"alternate main","title_language":"","creation_date":"Early 20th century","creation_place_original_location":"Padang (Indonesia)","styles_periods_indexing_terms":"Chinese (culture or style)","inscriptions":"","inscription_language":"","shape":"irregular","materials_name":"silk (textile)","techniques_name":"sewing (needleworking technique)","object_colour":"multicolored","physical_appearance":"This is a silk robe. It has a V-shaped opening. The collar is enclosed by a quatrefoil of scrolling chrysanthemums and hibiscus. The floral motif is repeated on the edges of the sleeves.  Peacocks interspersed amongst flowers are printed along the bottom on the front of the robe.","subject_terms_1":"tops (garments, general) flower (motif) birds (motifs) symbolism (artistic concept) folk costume","subject_terms_2":"Robes Motifs Symbolism Ethnic costume","subject_terms_3":"Chinese costumes","sgcool_label_text":"This silk robe has a v-shaped opening for the head.  Its collar is enclosed by a quatrefoil of scrolling chrysanthemums and hibiscus motif.  This cloud cover design, also known as the auspicious ruiyi fungus motif, resembles 18th century Qing dynasty robe designs.  The floral motif is repeated on the edges of the sleeves.  Peacocks interspersed among flowers are printed on both the front and back of the robe.  The peacock is a symbol of beauty of dignity in Chinese culture."},"nlpDate":"20201119143406","connectorId":0,"tags":{}}