{
  "id": "2017-00611-003",
  "title": "Waist band of the Bridegroom\u0027s Dress Wagho, choyni Turban cloth of the Bridegroom\u0027s Dress",
  "source": "Bumblebee",
  "path": "./Data/json/",
  "content": "\n  accession_no_csv: 2017-00611-003\n\n  Image: \n\n  object_work_type: textiles (visual works)\n\n  title_text: Waist band of the Bridegroom\\u0027s Dress Wagho\n choyni Turban cloth of the Bridegroom\\u0027s Dress\n\n  preference: alternate alternate main\n\n  title_language: \n\n  creation_date: 20th century\n\n  creation_place_original_location: Kachchh (India)\n\n  inscriptions: \n\n  inscription_language: \n\n  shape: irregular\n\n  materials_name: cotton (textile)\n\n  techniques_name: sewing (needleworking technique) embroidering\n\n  object_colour: multicolored\n\n  physical_appearance: This is a turban cloth\n which is part of a bridegroom\\u0027s clothes. It features vertical multicoloured stripes on the left end of the band. The stripes are made of embroidered thread. The remaining length of the turban cloth is folded up on the left.\n\n  subject_terms_1: folk costume geometric motifs embroidery (visual works) cloth ceremonial costume bridegrooms\n\n  subject_terms_2: Ethnic costume Motifs Embroidery Wedding costume Rabaris Bridegrooms Turbans Textile fabrics\n\n  subject_terms_3: Indian costumes\n\n  subject_terms_4: \n\n  sgcool_label_text: This set of garments - tunic\n trousers and a turban cloth - form a set of bridegroom\\u0027s clothes among the Dhebaria Rabari community of east Kutch. The group features excellent cotton embroidery incorporating mirrorwork embellishments. The fabric of the trousers is handwoven Mashroo silk\n while the turban cloth is made from handspun cotton.\n",
  "createdDate": "20201120223708",
  "version": 0,
  "latest": false,
  "roles": [],
  "metadata": {
    "accession_no_csv": "2017-00611-003",
    "Image": "",
    "object_work_type": "textiles (visual works)",
    "title_text": "Waist band of the Bridegroom\u0027s Dress Wagho, choyni Turban cloth of the Bridegroom\u0027s Dress",
    "preference": "alternate alternate main",
    "title_language": "",
    "creation_date": "20th century",
    "creation_place_original_location": "Kachchh (India)",
    "inscriptions": "",
    "inscription_language": "",
    "shape": "irregular",
    "materials_name": "cotton (textile)",
    "techniques_name": "sewing (needleworking technique) embroidering",
    "object_colour": "multicolored",
    "physical_appearance": "This is a turban cloth, which is part of a bridegroom\u0027s clothes. It features vertical multicoloured stripes on the left end of the band. The stripes are made of embroidered thread. The remaining length of the turban cloth is folded up on the left.",
    "subject_terms_1": "folk costume geometric motifs embroidery (visual works) cloth ceremonial costume bridegrooms",
    "subject_terms_2": "Ethnic costume Motifs Embroidery Wedding costume Rabaris Bridegrooms Turbans Textile fabrics",
    "subject_terms_3": "Indian costumes",
    "subject_terms_4": "",
    "sgcool_label_text": "This set of garments - tunic, trousers and a turban cloth - form a set of bridegroom\u0027s clothes among the Dhebaria Rabari community of east Kutch. The group features excellent cotton embroidery incorporating mirrorwork embellishments. The fabric of the trousers is handwoven Mashroo silk, while the turban cloth is made from handspun cotton."
  },
  "nlpDate": "20201120223708",
  "connectorId": 0,
  "tags": {}
}