{"id":"2017-00612","title":"Patola Sari ????","source":"Bumblebee","path":"./Data/json/","content":"accession_no_csv:2017-00612\nImage:\nobject_work_type:patolas (textiles)\ntitle_text:Patola Sari ????\npreference:main\ntitle_language:Tamil\ncreation_date:20th century\ncreation_place_original_location:Gujarat (India)\ninscriptions:????\ninscription_language:Tamil\nshape:irregular\nmaterials_name:silk (textile)\ntechniques_name:weaving\nobject_colour:multicolored\nphysical_appearance:This is a piece of patola textile. It features a diamond pattern\n intersected with rosettes. It is red\n with multicolored woven designs.\nsubject_terms_1:lozenges flower (motif) saris (garments)\nsubject_terms_2:Textile fabrics Motifs Embroidery Saris\nsubject_terms_3:Textile art and design Indian costumes\nsubject_terms_4:\nsgcool_label_text:A fine example of a Bohra Gajji Bhat weave of Gujarati Patola. The Bohra Gajji is characterised by its diamond pattern\n intersected with rosettes. This weave of patola is associated with the Bohra Muslim communities of Gujarat","createdDate":"20201119143406","version":0,"latest":false,"roles":[],"metadata":{"accession_no_csv":"2017-00612","Image":"","object_work_type":"patolas (textiles)","title_text":"Patola Sari ????","preference":"main","title_language":"Tamil","creation_date":"20th century","creation_place_original_location":"Gujarat (India)","inscriptions":"????","inscription_language":"Tamil","shape":"irregular","materials_name":"silk (textile)","techniques_name":"weaving","object_colour":"multicolored","physical_appearance":"This is a piece of patola textile. It features a diamond pattern, intersected with rosettes. It is red, with multicolored woven designs.","subject_terms_1":"lozenges flower (motif) saris (garments)","subject_terms_2":"Textile fabrics Motifs Embroidery Saris","subject_terms_3":"Textile art and design Indian costumes","subject_terms_4":"","sgcool_label_text":"A fine example of a Bohra Gajji Bhat weave of Gujarati Patola. The Bohra Gajji is characterised by its diamond pattern, intersected with rosettes. This weave of patola is associated with the Bohra Muslim communities of Gujarat"},"nlpDate":"20201119143406","connectorId":0,"tags":{}}