{"id":"2017-00363","title":"Table cloth","source":"Bumblebee","path":"./Data/json/","content":"accession_no_csv:2017-00363\nImage:\nobject_work_type:tablecloths batik art\ntitle_text:Table cloth\npreference:main\ntitle_language:\ncreator_2:Kok Sing Oey\ncreator_role:textile designers\ncreation_date:20th century\ncreation_place_original_location:Pekalongan (Indonesia)\nstyles_periods_indexing_terms:Peranakan\ninscriptions:\ninscription_language:\nshape:square (shape)\nmaterials_name:cotton (textile)\ntechniques_name:batik\nobject_colour:multicolored\nphysical_appearance:This is a batik table cloth. It features a medallion of four hibiscus blooms at the center. The blooms are surrounded by a dense background pattern made of intricate tendrils\n and featuring four butterflies at the cardinal points. Hibiscus blooms and leaves create a square border around the design. The background of the textile is pink. The table cloth is deeply creased.\nsubject_terms_1:Peranakan flower (motif) foliage (motif) cultural diffusion\nsubject_terms_2:Batik Tablecloths Peranakan (Asian people) Motifs Culture diffusion\nsubject_terms_3:Batik\nsgcool_label_text:A medallion of four hibiscus blooms occupies the centre of the batik.  It is surrounded by a dense background pattern of intricately rendered tendrils and four butterflies that mark the cardinal points.  On the outer border of this design\n the hibiscus blooms and leaves form a continuous frame for the overall design.  This batik comes from the family collection of Oey Kok Sing (1896-1966)\n the second in three generations of documented batik-makers in Pekalongan.  Her later batik designs attest to her virtuosity in technique and inventive colour palette.  Her repertoire of tiny isen-isen motifs (filler motifs within the outlines of the key motifs) in particular\n exudes a strong sense of artistic individuality\n possibly informed by modernist designs on European printed cloths.  Her treatment of floral bouquets is also charactertistic of the undulating and curving lines of the Art Noveau style that was introduced in the northern coast of Java by the Europeans.","createdDate":"20201018182636","version":0,"latest":false,"roles":[],"metadata":{"accession_no_csv":"2017-00363","Image":"","object_work_type":"tablecloths batik art","title_text":"Table cloth","preference":"main","title_language":"","creator_2":"Kok Sing Oey","creator_role":"textile designers","creation_date":"20th century","creation_place_original_location":"Pekalongan (Indonesia)","styles_periods_indexing_terms":"Peranakan","inscriptions":"","inscription_language":"","shape":"square (shape)","materials_name":"cotton (textile)","techniques_name":"batik","object_colour":"multicolored","physical_appearance":"This is a batik table cloth. It features a medallion of four hibiscus blooms at the center. The blooms are surrounded by a dense background pattern made of intricate tendrils, and featuring four butterflies at the cardinal points. Hibiscus blooms and leaves create a square border around the design. The background of the textile is pink. The table cloth is deeply creased.","subject_terms_1":"Peranakan flower (motif) foliage (motif) cultural diffusion","subject_terms_2":"Batik Tablecloths Peranakan (Asian people) Motifs Culture diffusion","subject_terms_3":"Batik","sgcool_label_text":"A medallion of four hibiscus blooms occupies the centre of the batik.  It is surrounded by a dense background pattern of intricately rendered tendrils and four butterflies that mark the cardinal points.  On the outer border of this design, the hibiscus blooms and leaves form a continuous frame for the overall design.  This batik comes from the family collection of Oey Kok Sing (1896-1966), the second in three generations of documented batik-makers in Pekalongan.  Her later batik designs attest to her virtuosity in technique and inventive colour palette.  Her repertoire of tiny isen-isen motifs (filler motifs within the outlines of the key motifs) in particular, exudes a strong sense of artistic individuality, possibly informed by modernist designs on European printed cloths.  Her treatment of floral bouquets is also charactertistic of the undulating and curving lines of the Art Noveau style that was introduced in the northern coast of Java by the Europeans."},"nlpDate":"20201018182636","connectorId":0,"tags":{}}