{"id":"2017-00236","title":"Irian Man with Bird of Paradise  Orang Irian dengan Burung Tjenderawasih","source":"Bumblebee","path":"./Data/json/","content":"accession_no_csv:2017-00236\nImage:\nobject_work_type:oil paintings (visual works)  canvas paintings\ntitle_text:Irian Man with Bird of Paradise  Orang Irian dengan Burung Tjenderawasih\npreference:main alternate\ntitle_language:\ncreator_2:Emiria Soenassa\ncreator_role:artists (visual artists)\ncreation_date:1948\ncreation_place_original_location:Indonesia\ninscriptions:\ninscription_language:\nshape:Rectangular\nmaterials_name:oil paint (paint)  canvas board\ntechniques_name:painting (image-making)\nobject_colour:multicoloured\nphysical_appearance:The painting depicts an Irian shaman with a stern\n piercing look. In his arms are several birds; one of which appears to be about to take flight. The colour scheme gravitates towards earthly hues of dark green and brown\n with the exception of the bright red and yellow strokes on the birds. The contrast of hues enhances the mysticism of the piece; especially with respect to the positioning of the foot as an arm on the right of the painting.\nsubject_terms_1:magic  shamans contrast indigenous people  religious characters\nsubject_terms_2:Shamans  Indigenous men  Papua (Indonesia)  Shamanism  Painting\nsubject_terms_3:visual arts  oil painting  Religious life and practices\nsgcool_label_text:As a sole female participant in PERSAGI (Persatuan Ahli Gambar Indonesia or Association of Indonesian Draftsmen) \n Emiria Soenassa is a pioneering modern artist from Indonesia.  An Irian shaman with a mask-like face and piercing gaze is shown embracing the magical birds\n with one of them abou to take flight.  The dreamy imaginative qualities of the work is emphasised through the stark contrast between dark and bright hues and the magical transformation of the man\\u0027s hand to an earthy foot.  As a self-proclaimed princess from the island Sultanate of Tidore\n Emiria advocated for Papuan independence from the Dutch.  Painted one year before the UN Roundtable Conference to discuss the handover of sovereignty over Papuan region from the Dutch to Indonesian government\n this work may be associated with her political inclination.","createdDate":"20201119143406","version":0,"latest":false,"roles":[],"metadata":{"accession_no_csv":"2017-00236","Image":"","object_work_type":"oil paintings (visual works)  canvas paintings","title_text":"Irian Man with Bird of Paradise  Orang Irian dengan Burung Tjenderawasih","preference":"main alternate","title_language":"","creator_2":"Emiria Soenassa","creator_role":"artists (visual artists)","creation_date":"1948","creation_place_original_location":"Indonesia","inscriptions":"","inscription_language":"","shape":"Rectangular","materials_name":"oil paint (paint)  canvas board","techniques_name":"painting (image-making)","object_colour":"multicoloured","physical_appearance":"The painting depicts an Irian shaman with a stern, piercing look. In his arms are several birds; one of which appears to be about to take flight. The colour scheme gravitates towards earthly hues of dark green and brown, with the exception of the bright red and yellow strokes on the birds. The contrast of hues enhances the mysticism of the piece; especially with respect to the positioning of the foot as an arm on the right of the painting.","subject_terms_1":"magic  shamans contrast indigenous people  religious characters","subject_terms_2":"Shamans  Indigenous men  Papua (Indonesia)  Shamanism  Painting","subject_terms_3":"visual arts  oil painting  Religious life and practices","sgcool_label_text":"As a sole female participant in PERSAGI (Persatuan Ahli Gambar Indonesia or Association of Indonesian Draftsmen) , Emiria Soenassa is a pioneering modern artist from Indonesia.  An Irian shaman with a mask-like face and piercing gaze is shown embracing the magical birds, with one of them abou to take flight.  The dreamy imaginative qualities of the work is emphasised through the stark contrast between dark and bright hues and the magical transformation of the man\u0027s hand to an earthy foot.  As a self-proclaimed princess from the island Sultanate of Tidore, Emiria advocated for Papuan independence from the Dutch.  Painted one year before the UN Roundtable Conference to discuss the handover of sovereignty over Papuan region from the Dutch to Indonesian government, this work may be associated with her political inclination."},"nlpDate":"20201119143406","connectorId":0,"tags":{}}