{"id":"2017-00020","title":"Tranquility","source":"Bumblebee","path":"./Data/json/","content":"accession_no_csv:2017-00020\nImage:\nobject_work_type:black-and-white prints (photographs) gelatin silver prints  photographic prints\ntitle_text:Tranquility\npreference:main\ntitle_language:\ncreator_2:Lee\n Lim\ncreator_1:Lee\n Lim\ncreator_role:photographers\ncreation_date:c.1960\ncreation_place_original_location:Not indicated\ninscriptions:\ninscription_language:\nshape:rectangular\nmaterials_name:gelatin  paper (fibre product)  silver sulfide  baryta paper\ntechniques_name:gelatin silver process photographic printing techniques black-and-white photography\nobject_colour:black-and-white (colours)\nphysical_appearance:This is a gelatin silver print and the image captured centers on two single storied houses with sloping roofs; the left larger than the one on the right. Multiple eletric wire poles pepper the area surrounding the houses\n and the skeleton of an open-air bridge can be seen on the right. A full moon hangs high in the sky. Several small but noticeable pin holes can be found along the four corners of the picture. Two of the artist\\u0027s photography studio chops and a 1966 2nd Pictorial Photography Exhibition of Malaya and Singapore chop can be found on the verso.\nsubject_terms_1:cultural landscapes  rural areas  pitched roofs  utility poles  bridges (built works)\nsubject_terms_2:Bridges  Cultural landscapes Photography\n Artistic  Landscapes  Royal Photographic Society of Great Britain\nsubject_terms_3:Artistic photography  visual arts  Bridges\ncontext_1:Presented by The Photographic Society of Johore. Though there is no information on the exact location of this exhibition\n its recent 50th year anniversary (2014/15)exhibition was held at Johor Bahru\\u0027s Sutera Mall.\ncontext_2:exhibitions (events)\ncontext_3:1966\ncontext_4:1966\ncontext_5:1966\ncontext_6:Johor Bahru (Johor\n Malaysia)\ncontext_7:The Photographic society of Johor\ncontext_8:planners\ncontext_20:Address indicated on photography studio\\u0027s chop.\ncontext_21:No 1 Tiong Bahru Road\n Singapore 3\ncontext_22:c.1960\ncontext_23:1955\ncontext_24:1965\nsgcool_label_text:Lee Lim was one of the most important modern photographers in Singapore\n influencing a generation of photographers in the pictorial photography circles. Between 1952 and 1979\n Lee took part in more than 100 photographic competitions and won numerous awards and honours. He received the Fellowship of the Royal Photographic Society (UK) in 1959 and the Artist Distinction by the International Federation of Photographic Art (FIAP) in 1977. He was also conferred an honorary fellowship by the Photographic Society of Singapore and won the Cultural Medallion in 1987.","createdDate":"20201119143406","version":0,"latest":false,"roles":[],"metadata":{"accession_no_csv":"2017-00020","Image":"","object_work_type":"black-and-white prints (photographs) gelatin silver prints  photographic prints","title_text":"Tranquility","preference":"main","title_language":"","creator_2":"Lee, Lim","creator_1":"Lee, Lim","creator_role":"photographers","creation_date":"c.1960","creation_place_original_location":"Not indicated","inscriptions":"","inscription_language":"","shape":"rectangular","materials_name":"gelatin  paper (fibre product)  silver sulfide  baryta paper","techniques_name":"gelatin silver process photographic printing techniques black-and-white photography","object_colour":"black-and-white (colours)","physical_appearance":"This is a gelatin silver print and the image captured centers on two single storied houses with sloping roofs; the left larger than the one on the right. Multiple eletric wire poles pepper the area surrounding the houses, and the skeleton of an open-air bridge can be seen on the right. A full moon hangs high in the sky. Several small but noticeable pin holes can be found along the four corners of the picture. Two of the artist\u0027s photography studio chops and a 1966 2nd Pictorial Photography Exhibition of Malaya and Singapore chop can be found on the verso.","subject_terms_1":"cultural landscapes  rural areas  pitched roofs  utility poles  bridges (built works)","subject_terms_2":"Bridges  Cultural landscapes Photography, Artistic  Landscapes  Royal Photographic Society of Great Britain","subject_terms_3":"Artistic photography  visual arts  Bridges","context_1":"Presented by The Photographic Society of Johore. Though there is no information on the exact location of this exhibition, its recent 50th year anniversary (2014/15)exhibition was held at Johor Bahru\u0027s Sutera Mall.","context_2":"exhibitions (events)","context_3":"1966","context_4":"1966","context_5":"1966","context_6":"Johor Bahru (Johor, Malaysia)","context_7":"The Photographic society of Johor","context_8":"planners","context_20":"Address indicated on photography studio\u0027s chop.","context_21":"No 1 Tiong Bahru Road, Singapore 3","context_22":"c.1960","context_23":"1955","context_24":"1965","sgcool_label_text":"Lee Lim was one of the most important modern photographers in Singapore, influencing a generation of photographers in the pictorial photography circles. Between 1952 and 1979, Lee took part in more than 100 photographic competitions and won numerous awards and honours. He received the Fellowship of the Royal Photographic Society (UK) in 1959 and the Artist Distinction by the International Federation of Photographic Art (FIAP) in 1977. He was also conferred an honorary fellowship by the Photographic Society of Singapore and won the Cultural Medallion in 1987."},"nlpDate":"20201119143406","connectorId":0,"tags":{}}