{"id":"2017-00546","title":"Dollah Jawa","source":"Bumblebee","path":"./Data/json/","content":"accession_no_csv:2017-00546\nImage:\nobject_work_type:projections (visual works) video art\ntitle_text:Dollah Jawa\npreference:main\ntitle_language:\ncreator_2:Faizal Hamdam\ncreator_role:artists (visual artists)\ncreation_date:2016\ncreation_place_original_location:Brunei\ninscriptions:\ninscription_language:\ntechniques_name:videography\nphysical_appearance:There are four image clips taken from a video recording. On the most left\n there is a portrait picture of a man. The second left-most photograph shows a family portrait of a couple and three children. The second right-most photo shows a royal man sitting on a throne chair and accompanied by three others. The right-most photograph shows a group of soldiers in uniform.\nsubject_terms_1:video recordings families (kinship groups) artists\\u0027 films\nsubject_terms_2:Installations (Art) Video recordings Family recordings Malaya History Japanese occupation\n 1942-1945 Video art\nsubject_terms_3:Installation art Films Family history 1942-1945 Japanese occupation\nsgcool_label_text:Faizal Hamdan is a Bruneian artist born in Tutong\n and raised in Bandar Seri Begawan. His practice is centered on the mediums of painting\n sculpture and installation\n and is often concerned with issues of materiality and tactility.  Commissioned for the 2016 Singapore Biennale (“An Atlas of Mirrors”)\n Faizal’s installation\n Dollah Jawa\n proffers the intersection of dual histories\n macro and micro. In the telling of two intertwined tales\n it engages on one hand with the neglected history of forced migration in Southeast Asia during the Second World War\n and\n on the other with the artist’s personal family history\n which was the result of broader developments in the trajectory of the region’s past. Faizal’s grandfather\n who hailed from West Java\n was one of many Javanese who were forcefully expatriated to Brunei by the Japanese Army to serve the imperial troops during the war. He stayed on after the occupation ended\n marrying a local woman and raising a family there. Those convergent historical vectors are materialised here in the form of visual images. Like dimly remembered figures from the past\n or hazy memories of events occluded by dominant historical accounts\n these images are cast as blurry projections on either side of a screen of fabric\n the lack of pictorial definition seeming almost to serve as a metaphor for the erosive work of the passage of time. On one side of the screen\n old photographs featuring Faizal’s grandfather – official portraits\n sepia-tinged family snapshots – suggest familial ties\n with some featuring fragments of scribbled notes on the back. On the other side are archival images from the Japanese Occupation in Brunei\n which occurred from 1941 to 1945: these include\n among others\n the photograph of the arrival of Japanese troops in the sultanate\n the then Sultan Ahmad Tajuddin with members of the occupying forces\n an example of the ‘banana’ currency used during the occupation\n and the Japanese surrender to the Australians at the end of the war.","createdDate":"20201018182636","version":0,"latest":false,"roles":[],"metadata":{"accession_no_csv":"2017-00546","Image":"","object_work_type":"projections (visual works) video art","title_text":"Dollah Jawa","preference":"main","title_language":"","creator_2":"Faizal Hamdam","creator_role":"artists (visual artists)","creation_date":"2016","creation_place_original_location":"Brunei","inscriptions":"","inscription_language":"","techniques_name":"videography","physical_appearance":"There are four image clips taken from a video recording. On the most left, there is a portrait picture of a man. The second left-most photograph shows a family portrait of a couple and three children. The second right-most photo shows a royal man sitting on a throne chair and accompanied by three others. The right-most photograph shows a group of soldiers in uniform.","subject_terms_1":"video recordings families (kinship groups) artists\u0027 films","subject_terms_2":"Installations (Art) Video recordings Family recordings Malaya History Japanese occupation, 1942-1945 Video art","subject_terms_3":"Installation art Films Family history 1942-1945 Japanese occupation","sgcool_label_text":"Faizal Hamdan is a Bruneian artist born in Tutong, and raised in Bandar Seri Begawan. His practice is centered on the mediums of painting, sculpture and installation, and is often concerned with issues of materiality and tactility.  Commissioned for the 2016 Singapore Biennale (“An Atlas of Mirrors”), Faizal’s installation, Dollah Jawa, proffers the intersection of dual histories, macro and micro. In the telling of two intertwined tales, it engages on one hand with the neglected history of forced migration in Southeast Asia during the Second World War, and, on the other with the artist’s personal family history, which was the result of broader developments in the trajectory of the region’s past. Faizal’s grandfather, who hailed from West Java, was one of many Javanese who were forcefully expatriated to Brunei by the Japanese Army to serve the imperial troops during the war. He stayed on after the occupation ended, marrying a local woman and raising a family there. Those convergent historical vectors are materialised here in the form of visual images. Like dimly remembered figures from the past, or hazy memories of events occluded by dominant historical accounts, these images are cast as blurry projections on either side of a screen of fabric, the lack of pictorial definition seeming almost to serve as a metaphor for the erosive work of the passage of time. On one side of the screen, old photographs featuring Faizal’s grandfather – official portraits, sepia-tinged family snapshots – suggest familial ties, with some featuring fragments of scribbled notes on the back. On the other side are archival images from the Japanese Occupation in Brunei, which occurred from 1941 to 1945: these include, among others, the photograph of the arrival of Japanese troops in the sultanate, the then Sultan Ahmad Tajuddin with members of the occupying forces, an example of the ‘banana’ currency used during the occupation, and the Japanese surrender to the Australians at the end of the war."},"nlpDate":"20201018182636","connectorId":0,"tags":{}}