{
  "id": "2017-00172",
  "title": "Materials on Lim Bo Seng",
  "source": "Bumblebee",
  "path": "./Data/json/",
  "content": "\n  accession_no_csv: 2017-00172\n\n  Image: \n\n  object_work_type: biographies (documents)\n\n  title_text: Materials on Lim Bo Seng\n\n  preference: main alternate\n\n  title_language: \n\n  creation_place_original_location: Singapore\n\n  inscriptions: \n\n  inscription_language: \n\n  shape: rectangular\n\n  materials_name: paper (fiber product)\n\n  techniques_name: printing (process) writing (processes)\n\n  object_colour: black-and-white (colors)\n\n  physical_appearance: This is a typed document spanning two and a half pages. It is printed in black ink against a plain paper. The pages have several holes punched into them along the top and left side. They also have tape marks across the page. The edges of the pages are badly torn and folded.\n\n  subject_terms_1: resistance movements documents (object genre) world wars\n\n  subject_terms_2: World War\n 1939-1945 Lim\n Bo Seng\n 1909-1944 Chen\n Chongzhi\n 1916- Biographies Great Britain. Army. Force 136 Force 136 (Guerilla movement)\n\n  subject_terms_3: 1942-1945 Japanese occupation Tan\n Chong Tee Lim\n Bo Seng Force 136 (Guerilla movement) war personalities\n\n  subject_terms_4: \n\n  sgcool_label_text: These materials regarding Lim Bo Seng belongs to part of a collection of artefacts related to the World War II underground resistance movement known as Force 136. The collection of materials was gathered by Tan Chong Tee (1916- 2012)\n who was a key member of this resistance group. The collection consists of original materials belonging to Tan and other members of Force 136 dating from the 1940s to new materials reproduced from memory by Tan Chong Tee\n which date from the late 1980s to early 2000s. \\r\\n\\r\\nForce 136 was set up in July 1942 as part of the British Special Operations Executive (SOE). It recruited and trained local guerillas to gather intelligence and create an underground spy network to support planned British invasion of Japanese-occupied Malaya.\n",
  "createdDate": "20201201203308",
  "version": 0,
  "latest": false,
  "roles": [],
  "metadata": {
    "accession_no_csv": "2017-00172",
    "Image": "",
    "object_work_type": "biographies (documents)",
    "title_text": "Materials on Lim Bo Seng",
    "preference": "main alternate",
    "title_language": "",
    "creation_place_original_location": "Singapore",
    "inscriptions": "",
    "inscription_language": "",
    "shape": "rectangular",
    "materials_name": "paper (fiber product)",
    "techniques_name": "printing (process) writing (processes)",
    "object_colour": "black-and-white (colors)",
    "physical_appearance": "This is a typed document spanning two and a half pages. It is printed in black ink against a plain paper. The pages have several holes punched into them along the top and left side. They also have tape marks across the page. The edges of the pages are badly torn and folded.",
    "subject_terms_1": "resistance movements documents (object genre) world wars",
    "subject_terms_2": "World War, 1939-1945 Lim, Bo Seng, 1909-1944 Chen, Chongzhi, 1916- Biographies Great Britain. Army. Force 136 Force 136 (Guerilla movement)",
    "subject_terms_3": "1942-1945 Japanese occupation Tan, Chong Tee Lim, Bo Seng Force 136 (Guerilla movement) war personalities",
    "subject_terms_4": "",
    "sgcool_label_text": "These materials regarding Lim Bo Seng belongs to part of a collection of artefacts related to the World War II underground resistance movement known as Force 136. The collection of materials was gathered by Tan Chong Tee (1916- 2012), who was a key member of this resistance group. The collection consists of original materials belonging to Tan and other members of Force 136 dating from the 1940s to new materials reproduced from memory by Tan Chong Tee, which date from the late 1980s to early 2000s. \r\n\r\nForce 136 was set up in July 1942 as part of the British Special Operations Executive (SOE). It recruited and trained local guerillas to gather intelligence and create an underground spy network to support planned British invasion of Japanese-occupied Malaya."
  },
  "nlpDate": "20201201203308",
  "connectorId": 0,
  "tags": {}
}