{"id":"2017-00519","title":"Reproduction of a historic photograph of the Muna Island Southeast Sulawesi teak industry from the collection of Mr W. T. Bermuli","source":"Bumblebee","path":"./Data/json/","content":"accession_no_csv:2017-00519\nImage:\nobject_work_type:prints (visual works)  woodcuts (prints)\ntitle_text:Reproduction of a historic photograph of the Muna Island Southeast Sulawesi teak industry from the collection of Mr W. T. Bermuli\npreference:main\ntitle_language:\ncreator_2:Lucy Davis\ncreator_role:artists (visual artists)\ncreation_date:2012\ncreation_place_original_location:Singapore\ninscriptions:\ninscription_language:\nshape:Rectangular\nmaterials_name:paper (fiber product)  charcoal (material)  teak (wood)\ntechniques_name:block printing (relief printing process)\nobject_colour:black-and-white (colours)\nphysical_appearance:This black-and-white print shows a group of men standing amidst foliage. In particular\n three men stand in a row to the left\n whilst the central figure points to the trunk of a tree.\nsubject_terms_1:natural history  ecology  teak (wood)\nsubject_terms_2:Ecology  Sulawesi Selatan (Indonesia)  Lumber trade  Muna Island (Indonesia) Teak\nsubject_terms_3:Visual arts\ncontext_1:Together Again: (wood:cut) Part III Material exhibition at Royal Botanic Gardens\n Edinburgh\ncontext_2:exhibitions (events)\ncontext_3:March - July 2013\ncontext_4:13-Mar\ncontext_5:13-Jul\ncontext_6:Royal Botanic Garden\n Edinburgh\ncontext_7:Lucy Davis and the Migrant Ecologies Project team\ncontext_8:planners\nsgcool_label_text:Artist\n educator and writer Lucy Davis’s interdisciplinary practice is informed by a longstanding interest in animal studies\n natural histories\n science and indigenous knowledge\n materiality and memory in Southeast Asia\n and the evocations of nature in art and visual culture. This work by Lucy Davis is part of the series titled ‘Together Again (Wood:Cut) Part lll: Material’\n the third iteration of the eponymous research project\n which the artist has been developing since 2008. The third iteration is focused on the questions of material\n and is an artistic and part-scientific inquiry into our material world\n and how everyday objects are reflective of the histories\n migratory lives and sources of knowledge across Southeast Asia. Specifically\n this body of work takes a 1950s teak bed as both starting and departure point for artistic\n ecological and social inquiry all in an attempt to trace its historic\n genetic and poetic life. \\r\\n\\r\\nThe project put in motion when\n in 2010\n the Migrant Ecologies Project (founded by Davis) was awarded a Singapore Ministry of Education Tier 1 grant to extract DNA from a selected teak bed\n and to travel to wherever the DNA suggested the timbre originated. This was carried out in collaboration with Double Helix Tracking Technologies\n which used DNA technologies that traced the original location of the rainforest product to Sulawesi. Together with a team of scientists and a photographer\n Davis visited a century year old teak plantation on Muna Island in South Sulawesi where she met with the villagers of Muna. The components that comprise ‘Together Again (Wood:Cut) Part lll: Material’ are a meditation on the experience of visiting Muna\n and of the competing systems of knowledge the team encountered\n between the shamanistic insights of the villagers in Sulawesi and the scientific inquiry of DNA technology. More than a simple forensic ‘search for origins’ of a particular rainforest product\n the project opens on to a world in which the forces of magic has a deep significance to a community largely dependent on wood\n and becomes embroiled in the contestation between what kinds of knowledge are allowed to make claims over the understanding of reality.","createdDate":"20201119143406","version":0,"latest":false,"roles":[],"metadata":{"accession_no_csv":"2017-00519","Image":"","object_work_type":"prints (visual works)  woodcuts (prints)","title_text":"Reproduction of a historic photograph of the Muna Island Southeast Sulawesi teak industry from the collection of Mr W. T. Bermuli","preference":"main","title_language":"","creator_2":"Lucy Davis","creator_role":"artists (visual artists)","creation_date":"2012","creation_place_original_location":"Singapore","inscriptions":"","inscription_language":"","shape":"Rectangular","materials_name":"paper (fiber product)  charcoal (material)  teak (wood)","techniques_name":"block printing (relief printing process)","object_colour":"black-and-white (colours)","physical_appearance":"This black-and-white print shows a group of men standing amidst foliage. In particular, three men stand in a row to the left, whilst the central figure points to the trunk of a tree.","subject_terms_1":"natural history  ecology  teak (wood)","subject_terms_2":"Ecology  Sulawesi Selatan (Indonesia)  Lumber trade  Muna Island (Indonesia) Teak","subject_terms_3":"Visual arts","context_1":"Together Again: (wood:cut) Part III Material exhibition at Royal Botanic Gardens, Edinburgh","context_2":"exhibitions (events)","context_3":"March - July 2013","context_4":"13-Mar","context_5":"13-Jul","context_6":"Royal Botanic Garden, Edinburgh","context_7":"Lucy Davis and the Migrant Ecologies Project team","context_8":"planners","sgcool_label_text":"Artist, educator and writer Lucy Davis’s interdisciplinary practice is informed by a longstanding interest in animal studies, natural histories, science and indigenous knowledge, materiality and memory in Southeast Asia, and the evocations of nature in art and visual culture. This work by Lucy Davis is part of the series titled ‘Together Again (Wood:Cut) Part lll: Material’, the third iteration of the eponymous research project, which the artist has been developing since 2008. The third iteration is focused on the questions of material, and is an artistic and part-scientific inquiry into our material world, and how everyday objects are reflective of the histories, migratory lives and sources of knowledge across Southeast Asia. Specifically, this body of work takes a 1950s teak bed as both starting and departure point for artistic, ecological and social inquiry all in an attempt to trace its historic, genetic and poetic life. \r\n\r\nThe project put in motion when, in 2010, the Migrant Ecologies Project (founded by Davis) was awarded a Singapore Ministry of Education Tier 1 grant to extract DNA from a selected teak bed, and to travel to wherever the DNA suggested the timbre originated. This was carried out in collaboration with Double Helix Tracking Technologies, which used DNA technologies that traced the original location of the rainforest product to Sulawesi. Together with a team of scientists and a photographer, Davis visited a century year old teak plantation on Muna Island in South Sulawesi where she met with the villagers of Muna. The components that comprise ‘Together Again (Wood:Cut) Part lll: Material’ are a meditation on the experience of visiting Muna, and of the competing systems of knowledge the team encountered, between the shamanistic insights of the villagers in Sulawesi and the scientific inquiry of DNA technology. More than a simple forensic ‘search for origins’ of a particular rainforest product, the project opens on to a world in which the forces of magic has a deep significance to a community largely dependent on wood, and becomes embroiled in the contestation between what kinds of knowledge are allowed to make claims over the understanding of reality."},"nlpDate":"20201119143406","connectorId":0,"tags":{}}