{"id":"2017-00951-013","title":"Tanah Impian (Dream Land) TMII (Taman Mini Indonesia Indah)","source":"Bumblebee","path":"./Data/json/","content":"accession_no_csv:2017-00951-013\nImage:\nobject_work_type:screen prints  adaptations (derivative objects)\ntitle_text:Tanah Impian (Dream Land) TMII (Taman Mini Indonesia Indah)\npreference:alternate main\ntitle_language:\ncreator_2:Krack Studio\ncreator_role:artists (visual artists)\ncreation_date:2014\ncreation_place_original_location:Indonesia\nstyles_periods_indexing_terms:Contemporary (style of art)\ninscriptions:\ninscription_language:\nshape:Square\nmaterials_name:paper (fiber product)\ntechniques_name:screen printing\nobject_colour:multicoloured\nedition_description:2-Oct\nphysical_appearance:This is a promotional poster for Taman Mini Indonesia Indah\n a cultural recreation park. The name of the theme bark is formed by a manicured bush that is surrounded by a castle\n a cable car\n a dinosaur figure\n and a museum.\nsubject_terms_1:identity  nationalism  advertisements posters  cultural parks  ways of life  popular culture  appropriation (imagery) redesign\nsubject_terms_2:Indonesia  Serigraphy Art\n Indonesian Nationalism Identity  promotional materials  Posters  Taman Mini Indonesia Indah  Cultural parks  Ways of life Popular culture  Appropriation (Art) Adaptations\nsubject_terms_3:Visual arts  National identity  Heritage and Culture? Places of interest? / Parks and gardens? Tourism posters?  Media and advertising  Popular culture\nsgcool_label_text:Tanah Impian (Dream Land) is a series of prints based on images drawn from Indonesian popular culture\n spanning 100 years. The project was conceived in 2014\n the year of the elections in Indonesia when nationalist rhetoric dominated public consciousness\n Artist collective Krack Studio sifted through a mass of research and archival material\n eventually selecting 24 images that referenced the idea of the Indonesian Dream and / or told an interesting story about changing definitions of the ‘Nation’. Ranging from political posters to advertisements\n comic strips\n movie posters and magazines\n these images\n reconstructed and re-imagined by the artist collective\n chronicle Indonesia’s evolving aspirations\n desires and identity\n as well as how Indonesia has been perceived and imaged for the ‘Western’ gaze.","createdDate":"20201018182636","version":0,"latest":false,"roles":[],"metadata":{"accession_no_csv":"2017-00951-013","Image":"","object_work_type":"screen prints  adaptations (derivative objects)","title_text":"Tanah Impian (Dream Land) TMII (Taman Mini Indonesia Indah)","preference":"alternate main","title_language":"","creator_2":"Krack Studio","creator_role":"artists (visual artists)","creation_date":"2014","creation_place_original_location":"Indonesia","styles_periods_indexing_terms":"Contemporary (style of art)","inscriptions":"","inscription_language":"","shape":"Square","materials_name":"paper (fiber product)","techniques_name":"screen printing","object_colour":"multicoloured","edition_description":"2-Oct","physical_appearance":"This is a promotional poster for Taman Mini Indonesia Indah, a cultural recreation park. The name of the theme bark is formed by a manicured bush that is surrounded by a castle, a cable car, a dinosaur figure, and a museum.","subject_terms_1":"identity  nationalism  advertisements posters  cultural parks  ways of life  popular culture  appropriation (imagery) redesign","subject_terms_2":"Indonesia  Serigraphy Art, Indonesian Nationalism Identity  promotional materials  Posters  Taman Mini Indonesia Indah  Cultural parks  Ways of life Popular culture  Appropriation (Art) Adaptations","subject_terms_3":"Visual arts  National identity  Heritage and Culture? Places of interest? / Parks and gardens? Tourism posters?  Media and advertising  Popular culture","sgcool_label_text":"Tanah Impian (Dream Land) is a series of prints based on images drawn from Indonesian popular culture, spanning 100 years. The project was conceived in 2014, the year of the elections in Indonesia when nationalist rhetoric dominated public consciousness, Artist collective Krack Studio sifted through a mass of research and archival material, eventually selecting 24 images that referenced the idea of the Indonesian Dream and / or told an interesting story about changing definitions of the ‘Nation’. Ranging from political posters to advertisements, comic strips, movie posters and magazines, these images, reconstructed and re-imagined by the artist collective, chronicle Indonesia’s evolving aspirations, desires and identity, as well as how Indonesia has been perceived and imaged for the ‘Western’ gaze."},"nlpDate":"20201018182636","connectorId":0,"tags":{}}