{"id":"2017-01034","title":"A Calladium - Tanglin, Singapore Photograph of man by Caladium plant at Tanglin","source":"Bumblebee","path":"./Data/json/","content":"accession_no_csv:2017-01034\nImage:\nobject_work_type:black-and-white photographs photographs\ntitle_text:A Calladium - Tanglin\n Singapore Photograph of man by Caladium plant at Tanglin\npreference:alternate main\ntitle_language:\ncreator_2:August Sachtler of Sachtler \\u0026 Co.\ncreator_role:photographers\ncreation_date:1860s\ncreation_place_original_location:Singapore\ninscriptions:\ninscription_language:\nshape:rectangular\nmaterials_name:paper (fiber product)\ntechniques_name:photographic processes\nobject_colour:black-and-white (colors)\nphysical_appearance:This is a black-and-white photograph. It features a man\n standing on the left of a large caladium plant. The root of the plant is bordered by a patch of ferns. The man is holding a long object on his left shoulder\n and is dressed in a long sleeved top\n pants\n and wrap cloth around his waist.\nsubject_terms_1:indigenous people folk costume\nsubject_terms_2:Carte de visite photographs Photographs Indigenous people Ethnic costume Tanglin (Singapore) Caladium\nsubject_terms_3:Photography Ethnic costumes Tanglin\nsubject_terms_4:\nsgcool_label_text:\\This carte de visite photograph of a calladium plant at Tanglin was taken by August Sachtler\n a German photographer who started photographing in Singapore in the early 1860s. The studio details inscribed on the back of these cartes de visite read \\\\A. Sachtler in Singapore\\\\","createdDate":"20201119143406","version":0,"latest":false,"roles":[],"metadata":{"accession_no_csv":"2017-01034","Image":"","object_work_type":"black-and-white photographs photographs","title_text":"A Calladium - Tanglin, Singapore Photograph of man by Caladium plant at Tanglin","preference":"alternate main","title_language":"","creator_2":"August Sachtler of Sachtler \u0026 Co.","creator_role":"photographers","creation_date":"1860s","creation_place_original_location":"Singapore","inscriptions":"","inscription_language":"","shape":"rectangular","materials_name":"paper (fiber product)","techniques_name":"photographic processes","object_colour":"black-and-white (colors)","physical_appearance":"This is a black-and-white photograph. It features a man, standing on the left of a large caladium plant. The root of the plant is bordered by a patch of ferns. The man is holding a long object on his left shoulder, and is dressed in a long sleeved top, pants, and wrap cloth around his waist.","subject_terms_1":"indigenous people folk costume","subject_terms_2":"Carte de visite photographs Photographs Indigenous people Ethnic costume Tanglin (Singapore) Caladium","subject_terms_3":"Photography Ethnic costumes Tanglin","subject_terms_4":"","sgcool_label_text":"\"This carte de visite photograph of a calladium plant at Tanglin was taken by August Sachtler, a German photographer who started photographing in Singapore in the early 1860s. The studio details inscribed on the back of these cartes de visite read \"\"A. Sachtler in Singapore\"\""},"nlpDate":"20201119143406","connectorId":0,"tags":{}}