{
  "id": "2017-00371",
  "title": "Sarong",
  "source": "Bumblebee",
  "path": "./Data/json/",
  "content": "\n  accession_no_csv: 2017-00371\n\n  Image: \n\n  object_work_type: sarongs batik art\n\n  title_text: Sarong\n\n  preference: main\n\n  title_language: \n\n  creator_2: Jane Hendromartono\n\n  creator_role: textile designers\n\n  creation_date: 1950-1965\n\n  creation_place_original_location: Pekalongan (Indonesia)\n\n  styles_periods_indexing_terms: Peranakan\n\n  inscriptions: \n\n  inscription_language: \n\n  shape: rectangular\n\n  materials_name: cotton (textile)\n\n  techniques_name: batik\n\n  object_colour: multicolored\n\n  physical_appearance: This is a batik sarong. It features large bunches of orchids interspersed with birds. The motif is set against a dense background patterning on the left side of the batik. On the right\n the floral motif is set against a plain brown background. There is a green dense foliage border along the left and bottom of the right panel. There is a signature at the top-left of the batik sarong.\n\n  subject_terms_1: Peranakan folk costume birds (motifs) foliage (motif) cultural diffusion\n\n  subject_terms_2: Batik Ethnic costume Peranakan (Asian people) Motifs Culture diffusion\n\n  subject_terms_3: Batik Peranakan costumes\n\n  sgcool_label_text: Large bunches of orchids are set against dense background patterning on the broad vertical section of the batik (kepala).  On the “body” or main design feature (badan) of the cloth\n Lily of the Nile blooms were added to the brown background.  Amusing birds in flight bearing envelopes and single blooms enliven the design.  This batik comes from the family collection of Oey Djien Nio (1929-1987)\n the last in three generations of documented batik-makers in Pekalongan.  In her earlier signatures\n she used her husband’s name\n Liem Siok Hien.  But from 1965 onwards\n she used Jane Hendromartono\n combining her husband’s new Indonesian family name\n Hendromartono with Jane\n as people addressed her by.  She developed a personal style distinct from her mother and grandmother\n and experimented with a wide spectrum of colours and exotic combinations of birds\n rock formations and mythical animals.  Jane Hendromartono’s clientele expanded beyond the elite in Indonesia to include Europe\n America and Japan\n especially in the 1980s.  This piece is signed “Liem Siok Hien Pekl”.\n",
  "createdDate": "20201120223708",
  "version": 0,
  "latest": false,
  "roles": [],
  "metadata": {
    "accession_no_csv": "2017-00371",
    "Image": "",
    "object_work_type": "sarongs batik art",
    "title_text": "Sarong",
    "preference": "main",
    "title_language": "",
    "creator_2": "Jane Hendromartono",
    "creator_role": "textile designers",
    "creation_date": "1950-1965",
    "creation_place_original_location": "Pekalongan (Indonesia)",
    "styles_periods_indexing_terms": "Peranakan",
    "inscriptions": "",
    "inscription_language": "",
    "shape": "rectangular",
    "materials_name": "cotton (textile)",
    "techniques_name": "batik",
    "object_colour": "multicolored",
    "physical_appearance": "This is a batik sarong. It features large bunches of orchids interspersed with birds. The motif is set against a dense background patterning on the left side of the batik. On the right, the floral motif is set against a plain brown background. There is a green dense foliage border along the left and bottom of the right panel. There is a signature at the top-left of the batik sarong.",
    "subject_terms_1": "Peranakan folk costume birds (motifs) foliage (motif) cultural diffusion",
    "subject_terms_2": "Batik Ethnic costume Peranakan (Asian people) Motifs Culture diffusion",
    "subject_terms_3": "Batik Peranakan costumes",
    "sgcool_label_text": "Large bunches of orchids are set against dense background patterning on the broad vertical section of the batik (kepala).  On the “body” or main design feature (badan) of the cloth, Lily of the Nile blooms were added to the brown background.  Amusing birds in flight bearing envelopes and single blooms enliven the design.  This batik comes from the family collection of Oey Djien Nio (1929-1987), the last in three generations of documented batik-makers in Pekalongan.  In her earlier signatures, she used her husband’s name, Liem Siok Hien.  But from 1965 onwards, she used Jane Hendromartono, combining her husband’s new Indonesian family name, Hendromartono with Jane, as people addressed her by.  She developed a personal style distinct from her mother and grandmother, and experimented with a wide spectrum of colours and exotic combinations of birds, rock formations and mythical animals.  Jane Hendromartono’s clientele expanded beyond the elite in Indonesia to include Europe, America and Japan, especially in the 1980s.  This piece is signed “Liem Siok Hien Pekl”."
  },
  "nlpDate": "20201120223708",
  "connectorId": 0,
  "tags": {}
}