{
  "id": "2017-00504",
  "title": "Green Batik Dress with Stand-up Collar by Sylvia Kho nee Wong Sien Moy Green Batik Dress with Stand-up Collar",
  "source": "Bumblebee",
  "path": "./Data/json/",
  "content": "\n  accession_no_csv: 2017-00504\n\n  Image: \n\n  object_work_type: dresses (garments)\n\n  title_text: Green Batik Dress with Stand-up Collar by Sylvia Kho nee Wong Sien Moy Green Batik Dress with Stand-up Collar\n\n  preference: main alternate\n\n  title_language: \n\n  creator_2: Sylvia Kho\n\n  creator_1: Kho\n Sylvia\n 1917-\n\n  creator_role: fashion designers\n\n  creation_date: 1980s\n\n  creation_place_original_location: Singapore\n\n  inscriptions: \n\n  inscription_language: \n\n  shape: irregular\n\n  techniques_name: batik sewing (needleworking technique)\n\n  object_colour: green (colour)\n\n  physical_appearance: This is a green batik dress with stand up collar. It has stripped patterns of varying designs across the panel of the dress.\n\n  subject_terms_1: custom-made womenswear\n\n  subject_terms_2: Custom-made clothing Women\\u0027s clothing Kho\n Sylvia\n 1917- Dresses\n\n  subject_terms_3: Fashion design Kho\n Sylvia\n 1917-\n\n  sgcool_label_text: Mrs Sylvia Kho (nee Wong Sien Moy) was a prominent bridal designer in Singapore from the 1950s to 1990s. Beyond wedding gowns\n she also designed dresses for her female relatives. This mother of the bride dress was designed and made by Sylvia Kho for her seventh sister\n Mrs Florence Chong (nee Wong Chit Moy). It was worn by Mrs Florence Chong at her daughter Susan’s wedding in 1984.\n",
  "createdDate": "20201125084519",
  "version": 0,
  "latest": false,
  "roles": [],
  "metadata": {
    "accession_no_csv": "2017-00504",
    "Image": "",
    "object_work_type": "dresses (garments)",
    "title_text": "Green Batik Dress with Stand-up Collar by Sylvia Kho nee Wong Sien Moy Green Batik Dress with Stand-up Collar",
    "preference": "main alternate",
    "title_language": "",
    "creator_2": "Sylvia Kho",
    "creator_1": "Kho, Sylvia, 1917-",
    "creator_role": "fashion designers",
    "creation_date": "1980s",
    "creation_place_original_location": "Singapore",
    "inscriptions": "",
    "inscription_language": "",
    "shape": "irregular",
    "techniques_name": "batik sewing (needleworking technique)",
    "object_colour": "green (colour)",
    "physical_appearance": "This is a green batik dress with stand up collar. It has stripped patterns of varying designs across the panel of the dress.",
    "subject_terms_1": "custom-made womenswear",
    "subject_terms_2": "Custom-made clothing Women\u0027s clothing Kho, Sylvia, 1917- Dresses",
    "subject_terms_3": "Fashion design Kho, Sylvia, 1917-",
    "sgcool_label_text": "Mrs Sylvia Kho (nee Wong Sien Moy) was a prominent bridal designer in Singapore from the 1950s to 1990s. Beyond wedding gowns, she also designed dresses for her female relatives. This mother of the bride dress was designed and made by Sylvia Kho for her seventh sister, Mrs Florence Chong (nee Wong Chit Moy). It was worn by Mrs Florence Chong at her daughter Susan’s wedding in 1984."
  },
  "nlpDate": "20201125084519",
  "connectorId": 0,
  "tags": {}
}