{
  "id": "2017-00289-002",
  "title": "Detailed manuscript plan for a 1944 church service and party organised for 122nd Field Regiment (2 pieces) 1944 Church service and Christmas greeting card",
  "source": "Bumblebee",
  "path": "./Data/json/",
  "content": "\n  accession_no_csv: 2017-00289-002\n\n  Image: \n\n  object_work_type: greeting cards\n\n  title_text: Detailed manuscript plan for a 1944 church service and party organised for 122nd Field Regiment (2 pieces) 1944 Church service and Christmas greeting card\n\n  preference: alternate main\n\n  title_language: \n\n  creation_date: 1941-1945\n\n  creation_place_original_location: Singapore\n\n  inscriptions: \n\n  inscription_language: \n\n  shape: rectangular\n\n  materials_name: paper (fiber product)\n\n  techniques_name: drawing (image-making)\n\n  object_colour: multicolored\n\n  physical_appearance: This is a Christmas greeting card relating to a church service. It is handdrawn and handwritten in multicolored ink. There is a logo drawn at the top-center of the card. On the left\n there is a box describing an order of church services. On the right\n the location and year is written. There are no tears on the card.\n\n  subject_terms_1: world wars prisoners of war documents (object genre) handwriting cards (information artifacts)\n\n  subject_terms_2: World War\n 1939-1945 Prisoners of war Writing Christmas cards\n\n  subject_terms_3: 1942-1945 Japanese occupation Changi Prison\n\n  subject_terms_4: \n\n  context_1: World War\n 1939-1945 1942-1945 Japanese Occupation\n\n  context_2: world wars occupations (armed conflicts)\n\n  context_3: 1939-1945 1942-1945\n\n  context_4: 1939 1942\n\n  context_5: 1945 1945\n\n  context_6: Malaya Singapore\n\n  context_7: Great Britain. Army. Royal Field Artillery\n\n  context_8: armed forces\n\n  sgcool_label_text: This is a detailed manuscript plan for a 1944 church service and party organised for 122nd Field Regiment written on the verso of a typed memo from Singapore Inspector of Prisons (1938)\n with Steele\\u0027s manuscript invitation. This artefact is part of the archive of James Steele\n Royal Artillery (Field) who served in Malaya from January 1941-February 1942\n when interned as a P.O.W at Changi until his release in October 1945.\n",
  "createdDate": "20201120223707",
  "version": 0,
  "latest": false,
  "roles": [],
  "metadata": {
    "accession_no_csv": "2017-00289-002",
    "Image": "",
    "object_work_type": "greeting cards",
    "title_text": "Detailed manuscript plan for a 1944 church service and party organised for 122nd Field Regiment (2 pieces) 1944 Church service and Christmas greeting card",
    "preference": "alternate main",
    "title_language": "",
    "creation_date": "1941-1945",
    "creation_place_original_location": "Singapore",
    "inscriptions": "",
    "inscription_language": "",
    "shape": "rectangular",
    "materials_name": "paper (fiber product)",
    "techniques_name": "drawing (image-making)",
    "object_colour": "multicolored",
    "physical_appearance": "This is a Christmas greeting card relating to a church service. It is handdrawn and handwritten in multicolored ink. There is a logo drawn at the top-center of the card. On the left, there is a box describing an order of church services. On the right, the location and year is written. There are no tears on the card.",
    "subject_terms_1": "world wars prisoners of war documents (object genre) handwriting cards (information artifacts)",
    "subject_terms_2": "World War, 1939-1945 Prisoners of war Writing Christmas cards",
    "subject_terms_3": "1942-1945 Japanese occupation Changi Prison",
    "subject_terms_4": "",
    "context_1": "World War, 1939-1945 1942-1945 Japanese Occupation",
    "context_2": "world wars occupations (armed conflicts)",
    "context_3": "1939-1945 1942-1945",
    "context_4": "1939 1942",
    "context_5": "1945 1945",
    "context_6": "Malaya Singapore",
    "context_7": "Great Britain. Army. Royal Field Artillery",
    "context_8": "armed forces",
    "sgcool_label_text": "This is a detailed manuscript plan for a 1944 church service and party organised for 122nd Field Regiment written on the verso of a typed memo from Singapore Inspector of Prisons (1938), with Steele\u0027s manuscript invitation. This artefact is part of the archive of James Steele, Royal Artillery (Field) who served in Malaya from January 1941-February 1942, when interned as a P.O.W at Changi until his release in October 1945."
  },
  "nlpDate": "20201120223707",
  "connectorId": 0,
  "tags": {}
}