{"id":"2017-00225-019","title":"Miniatures from The Sunny Orient where Sorrow Smiles and Poverty and Riches – Sin and Sanctity – Beauty and Ugliness all keep company Man Standing Along The Walkway","source":"Bumblebee","path":"./Data/json/","content":"accession_no_csv:2017-00225-019\nImage:\nobject_work_type:gelatin silver prints  photographic prints  black-and-white prints (photographs)\ntitle_text:Miniatures from The Sunny Orient where Sorrow Smiles and Poverty and Riches – Sin and Sanctity – Beauty and Ugliness all keep company Man Standing Along The Walkway\npreference:alternate  main\ntitle_language:\ncreator_2:SHEAF\n Egbert Thomas.\ncreator_role:photographers\ncreation_date:1922-1925\ncreation_place_original_location:Asia\ninscriptions:\ninscription_language:\nshape:Rectangular\nmaterials_name:gelatin  baryta paper  silver sulfide\ntechniques_name:gelatin silver process  photographic printing techniques  black-and-white photography\nobject_colour:black-and-white (colours)\nphysical_appearance:This print shows a man standing along the walkway. Behind him stands a tall drum\n and on the wall above the archway is an yin-yang symbol with radiating concentric circles.\nsubject_terms_1:travel photography genre (visual works) drums (membranophones) folk costume Chinese architecture styles\nsubject_terms_2:Genre prints  Travel photography  Drum  Ethnic costume Architecture\n Chinese\nsubject_terms_3:Travel photography Chinese costumes Visual arts\nsubject_terms_4:\nsgcool_label_text:These photographs were taken by Egbert Sheaf\n the Australian Trade Commissioner in Singapore\n several taken before and some of which were most likely taken when he was posted here between 1922-25. Sheaf conscientiously studied South-East Asia\\u0027s ethnography and his scholarship was coupled with a passion for travel and adventure. His photographs cover various aspects of daily and cultural life such as weaving\n the rice agriculture and other rituals of Javanese and Malayan communities\n as explained and illustrated in the portfolios and albums.","createdDate":"20201018182636","version":0,"latest":false,"roles":[],"metadata":{"accession_no_csv":"2017-00225-019","Image":"","object_work_type":"gelatin silver prints  photographic prints  black-and-white prints (photographs)","title_text":"Miniatures from The Sunny Orient where Sorrow Smiles and Poverty and Riches – Sin and Sanctity – Beauty and Ugliness all keep company Man Standing Along The Walkway","preference":"alternate  main","title_language":"","creator_2":"SHEAF, Egbert Thomas.","creator_role":"photographers","creation_date":"1922-1925","creation_place_original_location":"Asia","inscriptions":"","inscription_language":"","shape":"Rectangular","materials_name":"gelatin  baryta paper  silver sulfide","techniques_name":"gelatin silver process  photographic printing techniques  black-and-white photography","object_colour":"black-and-white (colours)","physical_appearance":"This print shows a man standing along the walkway. Behind him stands a tall drum, and on the wall above the archway is an yin-yang symbol with radiating concentric circles.","subject_terms_1":"travel photography genre (visual works) drums (membranophones) folk costume Chinese architecture styles","subject_terms_2":"Genre prints  Travel photography  Drum  Ethnic costume Architecture, Chinese","subject_terms_3":"Travel photography Chinese costumes Visual arts","subject_terms_4":"","sgcool_label_text":"These photographs were taken by Egbert Sheaf, the Australian Trade Commissioner in Singapore, several taken before and some of which were most likely taken when he was posted here between 1922-25. Sheaf conscientiously studied South-East Asia\u0027s ethnography and his scholarship was coupled with a passion for travel and adventure. His photographs cover various aspects of daily and cultural life such as weaving, the rice agriculture and other rituals of Javanese and Malayan communities, as explained and illustrated in the portfolios and albums."},"nlpDate":"20201018182636","connectorId":0,"tags":{}}