{
  "id": "2017-00397",
  "title": "Kain panjang",
  "source": "Bumblebee",
  "path": "./Data/json/",
  "content": "\n  accession_no_csv: 2017-00397\n\n  Image: \n\n  object_work_type: batik art folk costume\n\n  title_text: Kain panjang\n\n  preference: main\n\n  title_language: \n\n  creator_2: Jane Hendromartono\n\n  creator_role: textile designers\n\n  creation_date: 1950-1980s\n\n  creation_place_original_location: Pekalongan (Indonesia)\n\n  styles_periods_indexing_terms: Peranakan\n\n  inscriptions: \n\n  inscription_language: \n\n  shape: rectangular\n\n  materials_name: cotton (textile)\n\n  techniques_name: batik\n\n  object_colour: multicolored\n\n  physical_appearance: This is a batik kain panjang. It is set against a dark teal background. The decoration on this batik kain panjang is limited to only the left and bottom of the batik\n with a small pair of stylised wings at the top right. The flower and plant form motifs feature intricate filler dotted patterns. There is a small signature at the top left of the batik kain panjang.\n\n  subject_terms_1: Peranakan flower (motif) foliage (motif)\n\n  subject_terms_2: Motifs Ethnic costume Peranakan (Asian people) Batik\n\n  subject_terms_3: Peranakan costumes Batik\n\n  sgcool_label_text: The decoration on this teal kain panjang is limited to the sides of the batik.  Nonetheless\n the artist used intricate filler motifs\n such as squares\n circles and stars within each main motif to enhance the overall design of the flowers and plant forms.  This batik comes from the family collection of Oey Djien Nio (1929-1987)\n the last in three generations of documented batik-makers in Pekalongan.  In her earlier signatures\n she used her husband’s name\n Liem Siok Hien.  But from 1965 onwards\n she used Jane Hendromartono\n combining her husband’s new Indonesian family name\n Hendromartono with Jane\n as people addressed her by.  She developed a personal style distinct from her mother and grandmother\n and experimented with a wide spectrum of colours and exotic combinations of birds\n rock formations and mythical animals.  Jane Hendromartono’s clientele expanded beyond the elite in Indonesia to include Europe\n America and Japan\n especially in the 1980s.\n",
  "createdDate": "20201125084520",
  "version": 0,
  "latest": false,
  "roles": [],
  "metadata": {
    "accession_no_csv": "2017-00397",
    "Image": "",
    "object_work_type": "batik art folk costume",
    "title_text": "Kain panjang",
    "preference": "main",
    "title_language": "",
    "creator_2": "Jane Hendromartono",
    "creator_role": "textile designers",
    "creation_date": "1950-1980s",
    "creation_place_original_location": "Pekalongan (Indonesia)",
    "styles_periods_indexing_terms": "Peranakan",
    "inscriptions": "",
    "inscription_language": "",
    "shape": "rectangular",
    "materials_name": "cotton (textile)",
    "techniques_name": "batik",
    "object_colour": "multicolored",
    "physical_appearance": "This is a batik kain panjang. It is set against a dark teal background. The decoration on this batik kain panjang is limited to only the left and bottom of the batik, with a small pair of stylised wings at the top right. The flower and plant form motifs feature intricate filler dotted patterns. There is a small signature at the top left of the batik kain panjang.",
    "subject_terms_1": "Peranakan flower (motif) foliage (motif)",
    "subject_terms_2": "Motifs Ethnic costume Peranakan (Asian people) Batik",
    "subject_terms_3": "Peranakan costumes Batik",
    "sgcool_label_text": "The decoration on this teal kain panjang is limited to the sides of the batik.  Nonetheless, the artist used intricate filler motifs, such as squares, circles and stars within each main motif to enhance the overall design of the flowers and plant forms.  This batik comes from the family collection of Oey Djien Nio (1929-1987), the last in three generations of documented batik-makers in Pekalongan.  In her earlier signatures, she used her husband’s name, Liem Siok Hien.  But from 1965 onwards, she used Jane Hendromartono, combining her husband’s new Indonesian family name, Hendromartono with Jane, as people addressed her by.  She developed a personal style distinct from her mother and grandmother, and experimented with a wide spectrum of colours and exotic combinations of birds, rock formations and mythical animals.  Jane Hendromartono’s clientele expanded beyond the elite in Indonesia to include Europe, America and Japan, especially in the 1980s."
  },
  "nlpDate": "20201125084520",
  "connectorId": 0,
  "tags": {}
}