{"id":"2017-00534-001 to 007","title":"The Mystical Reality Reinvented -- To be Completed","source":"Bumblebee","path":"./Data/json/","content":"accession_no_csv:2017-00534-001 to 007\nImage:\nobject_work_type:installations (visual works)\ntitle_text:The Mystical Reality Reinvented -- To be Completed\npreference:main\ntitle_language:\ncreator_2:Sulaiman Esa\ncreator_1:Sulaiman Hj. Esa\n 1941-\ncreator_role:artists (visual artists)\ncreation_date:2016\ncreation_place_original_location:Malaysia\ninscriptions:\ninscription_language:\nmaterials_name:acrylic paint  canvas (textile material)  wood (plant material)\ntechniques_name:acrylic painting (technique)\nobject_colour:multicoloured\nphysical_appearance:\\This is an installation piece that consists of a painting on an easel\n and a tabletop that has a large and small paint can\n a palette\n and a paint brush. The painting has the words \\\\to be completed\\\\ and it shows the side profile of a man. \\\nsubject_terms_1:group identity  ethnicity  memory\nsubject_terms_2:Redza Piyadasa\n 1939-  group identity  Ethnicity  Collective memory  Installations (Arts)  Art\n Malaysian\nsubject_terms_3:Installation art\nsgcool_label_text:As graduates from the Hornsey College of Art in London (1962-1968)\n Sulaiman and fellow Malaysian art student Redza Piyadasa co-created a seminal artwork-cum-exhibition called “Towards a Mystical Reality: A Documentation of Jointly Initiated Experienced by Redza Piyadasa and Suleiman Esa” (TMR) at the Dewan Bahasa dan Pustaka (Institute of Language and Literature) in Kuala Lumpur from 2-7 August\n 1974.  The exhibition showed an assortment of everyday objects and detritus but each indexing an event. In so doing\n the artists presented a paradigm shift in how art was received and theorised in Malaysia at the time:  art became a means of critical enquiry and discussions about the definitions of art informed their enquiries and creations\n where the art object was secondary to the ideas and experiences provoked by it.\\r\\n  \\r\\nFor the inaugural exhibition of the Southeast Asia Gallery and to complement its archival display of the historic 1974 exhibition of TMR\n the Gallery is commissioning the artist Sulaiman Esa (the surviving half of the duo) to produce a new work titled “A Mystical Reality Reinvented”\n which looks back at TMR but interpreting this from the vantage point of today and also his own practice\\r\\n","createdDate":"20201119143406","version":0,"latest":false,"roles":[],"metadata":{"accession_no_csv":"2017-00534-001 to 007","Image":"","object_work_type":"installations (visual works)","title_text":"The Mystical Reality Reinvented -- To be Completed","preference":"main","title_language":"","creator_2":"Sulaiman Esa","creator_1":"Sulaiman Hj. Esa, 1941-","creator_role":"artists (visual artists)","creation_date":"2016","creation_place_original_location":"Malaysia","inscriptions":"","inscription_language":"","materials_name":"acrylic paint  canvas (textile material)  wood (plant material)","techniques_name":"acrylic painting (technique)","object_colour":"multicoloured","physical_appearance":"\"This is an installation piece that consists of a painting on an easel, and a tabletop that has a large and small paint can, a palette, and a paint brush. The painting has the words \"\"to be completed\"\" and it shows the side profile of a man. \"","subject_terms_1":"group identity  ethnicity  memory","subject_terms_2":"Redza Piyadasa, 1939-  group identity  Ethnicity  Collective memory  Installations (Arts)  Art, Malaysian","subject_terms_3":"Installation art","sgcool_label_text":"As graduates from the Hornsey College of Art in London (1962-1968), Sulaiman and fellow Malaysian art student Redza Piyadasa co-created a seminal artwork-cum-exhibition called “Towards a Mystical Reality: A Documentation of Jointly Initiated Experienced by Redza Piyadasa and Suleiman Esa” (TMR) at the Dewan Bahasa dan Pustaka (Institute of Language and Literature) in Kuala Lumpur from 2-7 August, 1974.  The exhibition showed an assortment of everyday objects and detritus but each indexing an event. In so doing, the artists presented a paradigm shift in how art was received and theorised in Malaysia at the time:  art became a means of critical enquiry and discussions about the definitions of art informed their enquiries and creations, where the art object was secondary to the ideas and experiences provoked by it.\r\n  \r\nFor the inaugural exhibition of the Southeast Asia Gallery and to complement its archival display of the historic 1974 exhibition of TMR, the Gallery is commissioning the artist Sulaiman Esa (the surviving half of the duo) to produce a new work titled “A Mystical Reality Reinvented”, which looks back at TMR but interpreting this from the vantage point of today and also his own practice\r\n"},"nlpDate":"20201119143406","connectorId":0,"tags":{}}