{
  "id": "2017-00039",
  "title": "The Endless Trail",
  "source": "Bumblebee",
  "path": "./Data/json/",
  "content": "\n  accession_no_csv: 2017-00039\n\n  Image: \n\n  object_work_type: black-and-white prints (photographs) photographic prints gelatin silver prints\n\n  title_text: The Endless Trail\n\n  preference: main\n\n  title_language: \n\n  creator_2: Lee\n Lim\n\n  creator_1: Lee\n Lim\n\n  creator_role: photographers\n\n  creation_date: c. 1960\n\n  creation_place_original_location: Singapore\n\n  inscriptions: \n\n  inscription_language: \n\n  shape: Rectangular\n\n  materials_name: silver sulfide paper (fibre product) baryta paper gelatin\n\n  techniques_name: gelatin silver process photographic printing techniques black-and-white photography\n\n  object_colour: black-and-white (colours)\n\n  physical_appearance: This is an image of a man herding a group of cows. The subjects are all backfacing the camera\n and are pictured to be walking away from the photographer. A large fluffy cloud looms in the sky.\n\n  subject_terms_1: cows (mammals) nature photography? clouds rural life\n\n  subject_terms_2: Cattle herders Photography of cows Herding\n\n  subject_terms_3: visual arts Artistic photography\n\n  context_21: No 1 Tiong Bahru Road\n Singapore 3\n\n  sgcool_label_text: Lee Lim was one of the most important modern photographers in Singapore\n influencing a generation of photographers in the pictorial photography circles. Between 1952 and 1979\n Lee took part in more than 100 photographic competitions and won numerous awards and honours. He received the Fellowship of the Royal Photographic Society (UK) in 1959 and the Artist Distinction by the International Federation of Photographic Art (FIAP) in 1977. He was also conferred an honorary fellowship by the Photographic Society of Singapore and won the Cultural Medallion in 1987.\n",
  "createdDate": "20201125084530",
  "version": 0,
  "latest": false,
  "roles": [],
  "metadata": {
    "accession_no_csv": "2017-00039",
    "Image": "",
    "object_work_type": "black-and-white prints (photographs) photographic prints gelatin silver prints",
    "title_text": "The Endless Trail",
    "preference": "main",
    "title_language": "",
    "creator_2": "Lee, Lim",
    "creator_1": "Lee, Lim",
    "creator_role": "photographers",
    "creation_date": "c. 1960",
    "creation_place_original_location": "Singapore",
    "inscriptions": "",
    "inscription_language": "",
    "shape": "Rectangular",
    "materials_name": "silver sulfide paper (fibre product) baryta paper gelatin",
    "techniques_name": "gelatin silver process photographic printing techniques black-and-white photography",
    "object_colour": "black-and-white (colours)",
    "physical_appearance": "This is an image of a man herding a group of cows. The subjects are all backfacing the camera, and are pictured to be walking away from the photographer. A large fluffy cloud looms in the sky.",
    "subject_terms_1": "cows (mammals) nature photography? clouds rural life",
    "subject_terms_2": "Cattle herders Photography of cows Herding",
    "subject_terms_3": "visual arts Artistic photography",
    "context_21": "No 1 Tiong Bahru Road, Singapore 3",
    "sgcool_label_text": "Lee Lim was one of the most important modern photographers in Singapore, influencing a generation of photographers in the pictorial photography circles. Between 1952 and 1979, Lee took part in more than 100 photographic competitions and won numerous awards and honours. He received the Fellowship of the Royal Photographic Society (UK) in 1959 and the Artist Distinction by the International Federation of Photographic Art (FIAP) in 1977. He was also conferred an honorary fellowship by the Photographic Society of Singapore and won the Cultural Medallion in 1987."
  },
  "nlpDate": "20201125084530",
  "connectorId": 0,
  "tags": {}
}