{"id":"2017-00077","title":"The Marco Polo Bridge Incident in 1937 ?????????","source":"Bumblebee","path":"./Data/json/","content":"accession_no_csv:2017-00077\nImage:\nobject_work_type:drawings (visual works)\ntitle_text:The Marco Polo Bridge Incident in 1937 ?????????\npreference:main alternate\ntitle_language:\ncreator_2:Tan Chong Tee\ncreator_1:Chen\n Chongzhi\n 1916-\ncreator_role:artists (visual artists)\ncreation_date:2002\ncreation_place_original_location:Singapore\ninscriptions:\ninscription_language:\nshape:rectangular\nmaterials_name:paper (fiber product) ink colour (pigment)\ntechniques_name:drawing (image-making)\nobject_colour:multicolored\nphysical_appearance:This is a multicoloured drawing depicting the events of the Marco Polo Bridge Incident in 1937. The drawing features several portraits of military leaders in uniform\n blended against marching military groups. There are some inscriptions across the top and by each segment of the drawing.\nsubject_terms_1:world wars depictions (visual works) military officers resistance movements Chinese scripts\nsubject_terms_2:Drawing World War\n 1939-1945 Great Britain. Army. Force 136 Force 136 (Guerilla movement) Chen\n Chongzhi\n 1916- Marco Polo Bridge Incident\n China\n 1937\nsubject_terms_3:Drawing Force 136 (Guerilla movement) Tan\n Chong Tee 1942-1945 Japanese occupation\nsubject_terms_4:\nsgcool_label_text:This drawing belongs to part of a collection of artefacts related to the World War II underground resistance movement known as Force 136. The collection of materials was gathered by Tan Chong Tee (1916- 2012)\n who was a key member of this resistance group. The collection consists of original materials belonging to Tan and other members of Force 136 dating from the 1940s to new materials reproduced from memory by Tan Chong Tee\n which date from mid 1990s to early 2000s. \\r\\n\\r\\nForce 136 was set up in 1942-45 as part of the British Special Operations Executive (SOE). It recruited and trained local guerillas to gather intelligence and create an underground spy network to support planned British invasion of Japanese-occupied Malaya.\\r\\n\\r\\nThis drawing is Tan’s rendition of the Marco Polo Bridge Incident in 1937. \\r\\n","createdDate":"20201119143406","version":0,"latest":false,"roles":[],"metadata":{"accession_no_csv":"2017-00077","Image":"","object_work_type":"drawings (visual works)","title_text":"The Marco Polo Bridge Incident in 1937 ?????????","preference":"main alternate","title_language":"","creator_2":"Tan Chong Tee","creator_1":"Chen, Chongzhi, 1916-","creator_role":"artists (visual artists)","creation_date":"2002","creation_place_original_location":"Singapore","inscriptions":"","inscription_language":"","shape":"rectangular","materials_name":"paper (fiber product) ink colour (pigment)","techniques_name":"drawing (image-making)","object_colour":"multicolored","physical_appearance":"This is a multicoloured drawing depicting the events of the Marco Polo Bridge Incident in 1937. The drawing features several portraits of military leaders in uniform, blended against marching military groups. There are some inscriptions across the top and by each segment of the drawing.","subject_terms_1":"world wars depictions (visual works) military officers resistance movements Chinese scripts","subject_terms_2":"Drawing World War, 1939-1945 Great Britain. Army. Force 136 Force 136 (Guerilla movement) Chen, Chongzhi, 1916- Marco Polo Bridge Incident, China, 1937","subject_terms_3":"Drawing Force 136 (Guerilla movement) Tan, Chong Tee 1942-1945 Japanese occupation","subject_terms_4":"","sgcool_label_text":"This drawing belongs to part of a collection of artefacts related to the World War II underground resistance movement known as Force 136. The collection of materials was gathered by Tan Chong Tee (1916- 2012), who was a key member of this resistance group. The collection consists of original materials belonging to Tan and other members of Force 136 dating from the 1940s to new materials reproduced from memory by Tan Chong Tee, which date from mid 1990s to early 2000s. \r\n\r\nForce 136 was set up in 1942-45 as part of the British Special Operations Executive (SOE). It recruited and trained local guerillas to gather intelligence and create an underground spy network to support planned British invasion of Japanese-occupied Malaya.\r\n\r\nThis drawing is Tan’s rendition of the Marco Polo Bridge Incident in 1937. \r\n"},"nlpDate":"20201119143406","connectorId":0,"tags":{}}