{
  "id": "2017-00950",
  "title": "In Between Spaces",
  "source": "Bumblebee",
  "path": "./Data/json/",
  "content": "\n  accession_no_csv: 2017-00950\n\n  Image: \n\n  object_work_type: installations (visual works)\n\n  title_text: In Between Spaces\n\n  preference: main\n\n  title_language: \n\n  creator_2: Zen Teh\n Sharifah Nasser\n\n  creator_role: artists (visual artists)\n\n  creation_date: 2016\n\n  creation_place_original_location: Singapore\n\n  inscriptions: \n\n  inscription_language: \n\n  shape: rectangular\n\n  materials_name: aluminium (metal) cement\n\n  techniques_name: printing (process) sculpting photography (process)\n\n  object_colour: multicolored\n\n  physical_appearance: This installation depicts a triptych of concrete panels. On each panel\n there are narrow strips of photographic prints set in shallow trenches cut into the surface of the panels. The trench on the top panel is cut vertically\n the second horizontally\n while the third panel only has a short trench on the bottom left corner.\n\n  subject_terms_1: urban development mixed media photographs nature trails urban environments symbolism triptychs\n\n  subject_terms_2: Photography Symbolism Urbanisation Nature Triptychs Installations (Art) Mixed media (Art)\n\n  subject_terms_3: Photography Nature and Environment Installation art\n\n  sgcool_label_text: In Between Spaces is a collaboration between Singaporean artist Zen Teh and product designer\n Sharifah Nasser. Teh (b. 1988) was educated at the School of Art\n Design and Media of NTU\n and has so far been included in numerous group shows locally\n and abroad in Thailand\n Taiwan and China; she enjoyed a solo presentation at 2902 Gallery in their former Waterloo space. Her practice is defined by her interest in the impact of human activity and urban expansion on the natural world\n especially in Southeast Asia\n and often assumes the mediums of photography\n sculpture and installation\n integrating photographic images in three-dimensional forms. The present work consists of a triptych of raw concrete panels\n into which has been set – in shallow trenches cut into the surface of the panels – narrow strips of photographic prints on dibond. The images are of the Green Corridor\n an uninterrupted stretch of natural greenery that runs the entire length of Singapore\n from the old Tanjong Pagar Rail Station in the south to the border of Malaysia in the north; the stretch\n of course\n once marked the extent of the Malaysian KTM line that reached its southern terminus in Singapore. The material configurations of the piece are symbolic and immediately recognizable: the concrete suggests the rapid and large-scale urbanization of the island’s terrain\n and the strips of images of vegetation evokes the corridor itself\n a confined\n circumscribed island of natural flora adrift in a sea of unchecked development – at the expense of the environment.\n",
  "createdDate": "20201201203308",
  "version": 0,
  "latest": false,
  "roles": [],
  "metadata": {
    "accession_no_csv": "2017-00950",
    "Image": "",
    "object_work_type": "installations (visual works)",
    "title_text": "In Between Spaces",
    "preference": "main",
    "title_language": "",
    "creator_2": "Zen Teh, Sharifah Nasser",
    "creator_role": "artists (visual artists)",
    "creation_date": "2016",
    "creation_place_original_location": "Singapore",
    "inscriptions": "",
    "inscription_language": "",
    "shape": "rectangular",
    "materials_name": "aluminium (metal) cement",
    "techniques_name": "printing (process) sculpting photography (process)",
    "object_colour": "multicolored",
    "physical_appearance": "This installation depicts a triptych of concrete panels. On each panel, there are narrow strips of photographic prints set in shallow trenches cut into the surface of the panels. The trench on the top panel is cut vertically, the second horizontally, while the third panel only has a short trench on the bottom left corner.",
    "subject_terms_1": "urban development mixed media photographs nature trails urban environments symbolism triptychs",
    "subject_terms_2": "Photography Symbolism Urbanisation Nature Triptychs Installations (Art) Mixed media (Art)",
    "subject_terms_3": "Photography Nature and Environment Installation art",
    "sgcool_label_text": "In Between Spaces is a collaboration between Singaporean artist Zen Teh and product designer, Sharifah Nasser. Teh (b. 1988) was educated at the School of Art, Design and Media of NTU, and has so far been included in numerous group shows locally, and abroad in Thailand, Taiwan and China; she enjoyed a solo presentation at 2902 Gallery in their former Waterloo space. Her practice is defined by her interest in the impact of human activity and urban expansion on the natural world, especially in Southeast Asia, and often assumes the mediums of photography, sculpture and installation, integrating photographic images in three-dimensional forms. The present work consists of a triptych of raw concrete panels, into which has been set – in shallow trenches cut into the surface of the panels – narrow strips of photographic prints on dibond. The images are of the Green Corridor, an uninterrupted stretch of natural greenery that runs the entire length of Singapore, from the old Tanjong Pagar Rail Station in the south to the border of Malaysia in the north; the stretch, of course, once marked the extent of the Malaysian KTM line that reached its southern terminus in Singapore. The material configurations of the piece are symbolic and immediately recognizable: the concrete suggests the rapid and large-scale urbanization of the island’s terrain, and the strips of images of vegetation evokes the corridor itself, a confined, circumscribed island of natural flora adrift in a sea of unchecked development – at the expense of the environment."
  },
  "nlpDate": "20201201203308",
  "connectorId": 0,
  "tags": {}
}