{"id":"2017-00506","title":"Red Metallic Fiber Dress by Sylvia Kho nee Wong Sien Moy  Red Metallic Fiber Dress","source":"Bumblebee","path":"./Data/json/","content":"accession_no_csv:2017-00506\nImage:\nobject_work_type:dresses (garments)\ntitle_text:Red Metallic Fiber Dress by Sylvia Kho nee Wong Sien Moy  Red Metallic Fiber Dress\npreference:alternate  main\ntitle_language:\ncreator_2:Sylvia Kho\ncreator_1:Kho\n Sylvia\n 1917-\ncreator_role:fashion designers\ncreation_date:1960s\ncreation_place_original_location:Singapore\ninscriptions:\ninscription_language:\nshape:irregular\nmaterials_name:polyester (fiber)\ntechniques_name:sewing (needleworking technique)\nobject_colour:red (colour)\nphysical_appearance:This is a long-sleeved red metallic fiber dress with Chinese buttons that run down the center of the piece.\nsubject_terms_1:custom-made  womenswear  metallic (colour attribute)\nsubject_terms_2:Dresses Custom-made clothing Women\\u0027s clothing Kho\n Sylvia\n 1917-\nsubject_terms_3:Fashion design  Kho\n Sylvia\n 1917-\nsgcool_label_text:Mrs Sylvia Kho (nee Wong Sien Moy) was a prominent bridal designer in Singapore from the 1950s to 1990s. Beyond wedding gowns\n she also designed dresses for her female relatives. This red metallic fiber dress with Chinese knot buttons was designed and made by Sylvia Kho for her seventh sister\n Mrs Florence Chong (nee Wong Chit Moy).","createdDate":"20201018182636","version":0,"latest":false,"roles":[],"metadata":{"accession_no_csv":"2017-00506","Image":"","object_work_type":"dresses (garments)","title_text":"Red Metallic Fiber Dress by Sylvia Kho nee Wong Sien Moy  Red Metallic Fiber Dress","preference":"alternate  main","title_language":"","creator_2":"Sylvia Kho","creator_1":"Kho, Sylvia, 1917-","creator_role":"fashion designers","creation_date":"1960s","creation_place_original_location":"Singapore","inscriptions":"","inscription_language":"","shape":"irregular","materials_name":"polyester (fiber)","techniques_name":"sewing (needleworking technique)","object_colour":"red (colour)","physical_appearance":"This is a long-sleeved red metallic fiber dress with Chinese buttons that run down the center of the piece.","subject_terms_1":"custom-made  womenswear  metallic (colour attribute)","subject_terms_2":"Dresses Custom-made clothing Women\u0027s clothing Kho, Sylvia, 1917-","subject_terms_3":"Fashion design  Kho, Sylvia, 1917-","sgcool_label_text":"Mrs Sylvia Kho (nee Wong Sien Moy) was a prominent bridal designer in Singapore from the 1950s to 1990s. Beyond wedding gowns, she also designed dresses for her female relatives. This red metallic fiber dress with Chinese knot buttons was designed and made by Sylvia Kho for her seventh sister, Mrs Florence Chong (nee Wong Chit Moy)."},"nlpDate":"20201018182636","connectorId":0,"tags":{}}