{"id":"2017-00586","title":"Embroidered set of RAF wings","source":"Bumblebee","path":"./Data/json/","content":"accession_no_csv:2017-00586\nImage:\nobject_work_type:badges\ntitle_text:Embroidered set of RAF wings\npreference:main\ntitle_language:\ncreator_2:George Dudley Binsted (?)\ncreator_role:creators\ncreation_date:1942-1945\ncreation_place_original_location:Singapore\ninscriptions:\ninscription_language:\nscale_type:Not indicated\nshape:irregular\nmaterials_name:thread\ntechniques_name:embroidering\nobject_colour:multicolored\nphysical_appearance:This is an embroidered set of wings symbolising the British Royal Air Force. It is capped by a crown\n and has outstretched wings on either side. The letters \\u0027RAF\\u0027 are embroided in the middle\n with a wreath bordering it. The wings are embroided with two shades of beige thread\n on a black base.\nsubject_terms_1:prisoners of war world wars military officers embroidery (visual works)\nsubject_terms_2:Wings (Insignia) Great Britain\n Royal Air Force Prisoner of war World War\n 1939-1945 Embroidery\nsubject_terms_3:1942-1945 Japanese occupation Great Britain\n Royal Air Force\nsubject_terms_4:\ncontext_1:World War\n 1939-1945 1942-1945 Japanese Occupation\ncontext_2:world wars occupations (armed conflicts)\ncontext_3:1939-1945 1942-1945\ncontext_4:1939 1942\ncontext_5:1945 1945\ncontext_6:Malaya Singapore\ncontext_7:Great Britain. Army. Force 136\ncontext_8:armed forces\nsgcool_label_text:This embroidered set of RAF wings belonged to George Dudley Binsted\n who joined the Royal Air Force (RAF) in 1941 and had flown Spitfires over France before being posted to Java. After the fall of Singapore in February 1942\n Binsted along with four others\n were captured by the Japanese. They were transported by ship to Singapore\n where they spent the next three and a half years as POWs in Changi Prison. While in captivity\n Binsted created this set of RAF wings from scratch\n using scraps of thread he could find in prison.","createdDate":"20201018182636","version":0,"latest":false,"roles":[],"metadata":{"accession_no_csv":"2017-00586","Image":"","object_work_type":"badges","title_text":"Embroidered set of RAF wings","preference":"main","title_language":"","creator_2":"George Dudley Binsted (?)","creator_role":"creators","creation_date":"1942-1945","creation_place_original_location":"Singapore","inscriptions":"","inscription_language":"","scale_type":"Not indicated","shape":"irregular","materials_name":"thread","techniques_name":"embroidering","object_colour":"multicolored","physical_appearance":"This is an embroidered set of wings symbolising the British Royal Air Force. It is capped by a crown, and has outstretched wings on either side. The letters \u0027RAF\u0027 are embroided in the middle, with a wreath bordering it. The wings are embroided with two shades of beige thread, on a black base.","subject_terms_1":"prisoners of war world wars military officers embroidery (visual works)","subject_terms_2":"Wings (Insignia) Great Britain, Royal Air Force Prisoner of war World War, 1939-1945 Embroidery","subject_terms_3":"1942-1945 Japanese occupation Great Britain, Royal Air Force","subject_terms_4":"","context_1":"World War, 1939-1945 1942-1945 Japanese Occupation","context_2":"world wars occupations (armed conflicts)","context_3":"1939-1945 1942-1945","context_4":"1939 1942","context_5":"1945 1945","context_6":"Malaya Singapore","context_7":"Great Britain. Army. Force 136","context_8":"armed forces","sgcool_label_text":"This embroidered set of RAF wings belonged to George Dudley Binsted, who joined the Royal Air Force (RAF) in 1941 and had flown Spitfires over France before being posted to Java. After the fall of Singapore in February 1942, Binsted along with four others, were captured by the Japanese. They were transported by ship to Singapore, where they spent the next three and a half years as POWs in Changi Prison. While in captivity, Binsted created this set of RAF wings from scratch, using scraps of thread he could find in prison."},"nlpDate":"20201018182636","connectorId":0,"tags":{}}