{"id":"2017-00505","title":"Purple Dress with Embroidered Floral Motifs in Gold Threading by Sylvia Kho nee Wong Sien Moy  Purple Dress with Embroidered Floral Motifs in Gold Threading","source":"Bumblebee","path":"./Data/json/","content":"accession_no_csv:2017-00505\nImage:\nobject_work_type:dresses (garments)\ntitle_text:Purple Dress with Embroidered Floral Motifs in Gold Threading by Sylvia Kho nee Wong Sien Moy  Purple Dress with Embroidered Floral Motifs in Gold Threading\npreference:alternate  main\ntitle_language:\ncreator_2:Sylvia Kho\ncreator_1:Kho\n Sylvia\n 1917-\ncreator_role:fashion designers\ncreation_date:1973\ncreation_place_original_location:Singapore\ninscriptions:\ninscription_language:\nshape:irregular\nmaterials_name:tulle (meshed textile)\ntechniques_name:sewing (needleworking technique) embroidering\nobject_colour:multicoloured\nphysical_appearance:This is a collared long-sleeved purple dress with embroidered floral motifs in gold threading.\nsubject_terms_1:custom-made  womenswear  flower (motif)\nsubject_terms_2:Tulle  Dresses Custom-made clothing Women\\u0027s clothing Kho\n Sylvia\n 1917- Flowers in art\nsubject_terms_3:Fashion design  Kho\n Sylvia\n 1917-\nsgcool_label_text:Mrs Sylvia Kho (nee Wong Sien Moy) was a prominent bridal designer in Singapore from the 1950s to 1990s. Beyond wedding gowns\n she also designed dresses for her female relatives.  This mother of the bride dress was designed and made by Sylvia Kho for her seventh sister\n Mrs Florence Chong (nee Wong Chit Moy). It was worn by Mrs Florence Chong at her daughter Colleen’s wedding in July 1973.","createdDate":"20201119143406","version":0,"latest":false,"roles":[],"metadata":{"accession_no_csv":"2017-00505","Image":"","object_work_type":"dresses (garments)","title_text":"Purple Dress with Embroidered Floral Motifs in Gold Threading by Sylvia Kho nee Wong Sien Moy  Purple Dress with Embroidered Floral Motifs in Gold Threading","preference":"alternate  main","title_language":"","creator_2":"Sylvia Kho","creator_1":"Kho, Sylvia, 1917-","creator_role":"fashion designers","creation_date":"1973","creation_place_original_location":"Singapore","inscriptions":"","inscription_language":"","shape":"irregular","materials_name":"tulle (meshed textile)","techniques_name":"sewing (needleworking technique) embroidering","object_colour":"multicoloured","physical_appearance":"This is a collared long-sleeved purple dress with embroidered floral motifs in gold threading.","subject_terms_1":"custom-made  womenswear  flower (motif)","subject_terms_2":"Tulle  Dresses Custom-made clothing Women\u0027s clothing Kho, Sylvia, 1917- Flowers in art","subject_terms_3":"Fashion design  Kho, Sylvia, 1917-","sgcool_label_text":"Mrs Sylvia Kho (nee Wong Sien Moy) was a prominent bridal designer in Singapore from the 1950s to 1990s. Beyond wedding gowns, she also designed dresses for her female relatives.  This mother of the bride dress was designed and made by Sylvia Kho for her seventh sister, Mrs Florence Chong (nee Wong Chit Moy). It was worn by Mrs Florence Chong at her daughter Colleen’s wedding in July 1973."},"nlpDate":"20201119143406","connectorId":0,"tags":{}}