{
  "id": "2017-00938",
  "title": "Painted Chinese Silk Gown For The European Market  Robe a la francaise",
  "source": "Bumblebee",
  "path": "./Data/json/",
  "content": "\n  accession_no_csv: 2017-00938\n\n  Image: \n\n  object_work_type: sacks (dresses)\n\n  title_text: Painted Chinese Silk Gown For The European Market  Robe a la francaise\n\n  preference: main alternate\n\n  title_language: \n\n  creation_date: 1770\n\n  creation_place_original_location: China  Europe\n\n  styles_periods_indexing_terms: European\n\n  inscriptions: \n\n  inscription_language: \n\n  materials_name: silk (textile) paint (coating)\n\n  techniques_name: painting (image-making)  dressmaking\n\n  object_colour: multicoloured\n\n  physical_appearance: This is a silk robe a la francaise with an open front. It is decorated with flowers that were hand-painted.\n\n  subject_terms_1: womenswear flower (motif)  imports  cultural diffusion  hand-painted\n\n  subject_terms_2: Dressmaking  Dresses Women\\u0027s clothing  Silk  Flowers in art  Imports  Culture diffusion\n\n  subject_terms_3: Textile art and design\n\n  subject_terms_4: \n\n  sgcool_label_text: This gown made of imported Chinese hand-painted silk reflects how Europe acquired luxurious Chinese export textiles to be tailored by French dressmakers into fashionable Western silhouettes. This sack-back gown style (robe a la francaise) with open front showing a decorative petticoat\n and fabric at the back arranged in large flat pleats from the shoulder to the floor opening into a full skirt\n was popular in 18th-century Europe. The featured flowers are quite distinctively British\n such as roses\n carnations (pinks) and lilac. \\r\\n\\r\\nChinese export silks and wallpapers were probably hand-painted in the same workshops in Guangzhou\n and appreciated extensively by wealthy Europeans in their dress and home furnishings since the 18th century. In technique and design\n such silk textiles also suggest a Chinese market response to the European fascination in Indian painted cottons.\n",
  "createdDate": "20201120223708",
  "version": 0,
  "latest": false,
  "roles": [],
  "metadata": {
    "accession_no_csv": "2017-00938",
    "Image": "",
    "object_work_type": "sacks (dresses)",
    "title_text": "Painted Chinese Silk Gown For The European Market  Robe a la francaise",
    "preference": "main alternate",
    "title_language": "",
    "creation_date": "1770",
    "creation_place_original_location": "China  Europe",
    "styles_periods_indexing_terms": "European",
    "inscriptions": "",
    "inscription_language": "",
    "materials_name": "silk (textile) paint (coating)",
    "techniques_name": "painting (image-making)  dressmaking",
    "object_colour": "multicoloured",
    "physical_appearance": "This is a silk robe a la francaise with an open front. It is decorated with flowers that were hand-painted.",
    "subject_terms_1": "womenswear flower (motif)  imports  cultural diffusion  hand-painted",
    "subject_terms_2": "Dressmaking  Dresses Women\u0027s clothing  Silk  Flowers in art  Imports  Culture diffusion",
    "subject_terms_3": "Textile art and design",
    "subject_terms_4": "",
    "sgcool_label_text": "This gown made of imported Chinese hand-painted silk reflects how Europe acquired luxurious Chinese export textiles to be tailored by French dressmakers into fashionable Western silhouettes. This sack-back gown style (robe a la francaise) with open front showing a decorative petticoat, and fabric at the back arranged in large flat pleats from the shoulder to the floor opening into a full skirt, was popular in 18th-century Europe. The featured flowers are quite distinctively British, such as roses, carnations (pinks) and lilac. \r\n\r\nChinese export silks and wallpapers were probably hand-painted in the same workshops in Guangzhou, and appreciated extensively by wealthy Europeans in their dress and home furnishings since the 18th century. In technique and design, such silk textiles also suggest a Chinese market response to the European fascination in Indian painted cottons."
  },
  "nlpDate": "20201120223708",
  "connectorId": 0,
  "tags": {}
}