{
  "id": "2017-00802 ",
  "title": "Black slip dress by Benny Ong",
  "source": "Bumblebee",
  "path": "./Data/json/",
  "content": "\n  accession_no_csv: 2017-00802 \n\n  Image: \n\n  object_work_type: dresses (garments)\n\n  title_text: Black slip dress by Benny Ong\n\n  preference: main\n\n  title_language: \n\n  creator_2: Benny Ong\n\n  creator_role: fashion designers\n\n  creation_date: 1978\n\n  creation_place_original_location: Singapore\n\n  inscriptions: \n\n  inscription_language: \n\n  materials_name: organza\n\n  techniques_name: sewing (needleworking technique)\n\n  object_colour: black (colour)\n\n  physical_appearance: This is a black slip dress with a wine red textile in the inner layer. The dress has two spaghetti straps.\n\n  subject_terms_1: womenswear fashion design\n\n  subject_terms_2: Fashion design Selfridges (firm) Dresses London (England)\n\n  subject_terms_3: Fashion design\n\n  sgcool_label_text: This is a black organza waisted slip dress designed by Singapore-born designer Benny Ong. The dress has a label “Design Room\n Selfridges” and was likely stocked in Selfridges\n one of London’s most reputable department stores\n in the 1970s. Ong is one of the pioneer Singapore-born designers known for dressing royalty such as the late Princess Diana and for establishing his brand in London.\n",
  "createdDate": "20201201203308",
  "version": 0,
  "latest": false,
  "roles": [],
  "metadata": {
    "accession_no_csv": "2017-00802 ",
    "Image": "",
    "object_work_type": "dresses (garments)",
    "title_text": "Black slip dress by Benny Ong",
    "preference": "main",
    "title_language": "",
    "creator_2": "Benny Ong",
    "creator_role": "fashion designers",
    "creation_date": "1978",
    "creation_place_original_location": "Singapore",
    "inscriptions": "",
    "inscription_language": "",
    "materials_name": "organza",
    "techniques_name": "sewing (needleworking technique)",
    "object_colour": "black (colour)",
    "physical_appearance": "This is a black slip dress with a wine red textile in the inner layer. The dress has two spaghetti straps.",
    "subject_terms_1": "womenswear fashion design",
    "subject_terms_2": "Fashion design Selfridges (firm) Dresses London (England)",
    "subject_terms_3": "Fashion design",
    "sgcool_label_text": "This is a black organza waisted slip dress designed by Singapore-born designer Benny Ong. The dress has a label “Design Room, Selfridges” and was likely stocked in Selfridges, one of London’s most reputable department stores, in the 1970s. Ong is one of the pioneer Singapore-born designers known for dressing royalty such as the late Princess Diana and for establishing his brand in London."
  },
  "nlpDate": "20201201203308",
  "connectorId": 0,
  "tags": {}
}