{"id":"2017-00420","title":"Altar cloth","source":"Bumblebee","path":"./Data/json/","content":"accession_no_csv:2017-00420\nImage:\nobject_work_type:altar cloths\ntitle_text:Altar cloth\npreference:main\ntitle_language:\ncreator_2:Jane Hendromartono\ncreator_role:textile designers\ncreation_date:1977\ncreation_place_original_location:Pekalongan (Indonesia)\nstyles_periods_indexing_terms:Peranakan\ninscriptions:\ninscription_language:\nshape:rectangular\nmaterials_name:cotton (textile)\ntechniques_name:batik\nobject_colour:multicolored\nphysical_appearance:This is a batik altar cloth. It consists of two panels. The lower panel features a pair of phoenixes and three mythical qilins amidst cloud forms. Surrounding them are emblems such as a scroll and a vase. The top panel features eight figures amongst cloud forms. The panels are bordered by a floral scrolling pattern. There is a signature on the bottom-right of the altar cloth.\nsubject_terms_1:Peranakan phoenixes legendary beings symbolism depictions (visual works) Taoism flower (motif)\nsubject_terms_2:Altar-cloths Batik Peranakan (Asian people) Symbolism Taoism Motifs\nsubject_terms_3:Batik Taoism\nsgcool_label_text:A pair of phoenixes and three mythical qilins are shown on the lower panel of this tok wi or altar cloth.  On the upper panel are eight figures\n possibly depicting semi-divine Daoist Eight Immortals.  Surrouding the qilins and phoenixes on the lower panel are emblems of the Eight Immortals\n symbolising happiness and transmutation.  This batik comes from the family collection of Oey Djien Nio (1929-1987)\n the last in three generations of documented batik-makers in Pekalongan.  In her earlier signatures\n she used her husband’s name\n Liem Siok Hien.  But from 1965 onwards\n she used Jane Hendromartono\n combining her husband’s new Indonesian family name\n Hendromartono with Jane\n as people addressed her by.  She developed a personal style distinct from her mother and grandmother\n and experimented with a wide spectrum of colours and exotic combinations of birds\n rock formations and mythical animals.  Jane Hendromartono’s clientele expanded beyond the elite in Indonesia to include Europe\n America and Japan\n especially in the 1980s.  This piece is signed “Jane Hendromartono ‘77”.","createdDate":"20201119143406","version":0,"latest":false,"roles":[],"metadata":{"accession_no_csv":"2017-00420","Image":"","object_work_type":"altar cloths","title_text":"Altar cloth","preference":"main","title_language":"","creator_2":"Jane Hendromartono","creator_role":"textile designers","creation_date":"1977","creation_place_original_location":"Pekalongan (Indonesia)","styles_periods_indexing_terms":"Peranakan","inscriptions":"","inscription_language":"","shape":"rectangular","materials_name":"cotton (textile)","techniques_name":"batik","object_colour":"multicolored","physical_appearance":"This is a batik altar cloth. It consists of two panels. The lower panel features a pair of phoenixes and three mythical qilins amidst cloud forms. Surrounding them are emblems such as a scroll and a vase. The top panel features eight figures amongst cloud forms. The panels are bordered by a floral scrolling pattern. There is a signature on the bottom-right of the altar cloth.","subject_terms_1":"Peranakan phoenixes legendary beings symbolism depictions (visual works) Taoism flower (motif)","subject_terms_2":"Altar-cloths Batik Peranakan (Asian people) Symbolism Taoism Motifs","subject_terms_3":"Batik Taoism","sgcool_label_text":"A pair of phoenixes and three mythical qilins are shown on the lower panel of this tok wi or altar cloth.  On the upper panel are eight figures, possibly depicting semi-divine Daoist Eight Immortals.  Surrouding the qilins and phoenixes on the lower panel are emblems of the Eight Immortals, symbolising happiness and transmutation.  This batik comes from the family collection of Oey Djien Nio (1929-1987), the last in three generations of documented batik-makers in Pekalongan.  In her earlier signatures, she used her husband’s name, Liem Siok Hien.  But from 1965 onwards, she used Jane Hendromartono, combining her husband’s new Indonesian family name, Hendromartono with Jane, as people addressed her by.  She developed a personal style distinct from her mother and grandmother, and experimented with a wide spectrum of colours and exotic combinations of birds, rock formations and mythical animals.  Jane Hendromartono’s clientele expanded beyond the elite in Indonesia to include Europe, America and Japan, especially in the 1980s.  This piece is signed “Jane Hendromartono ‘77”."},"nlpDate":"20201119143406","connectorId":0,"tags":{}}