{
  "id": "2017-00592",
  "title": "Blouse Yoke",
  "source": "Bumblebee",
  "path": "./Data/json/",
  "content": "\n  accession_no_csv: 2017-00592\n\n  Image: \n\n  object_work_type: womenswear costume components\n\n  title_text: Blouse Yoke\n\n  preference: main\n\n  title_language: English\n\n  creation_date: 20th century\n\n  creation_place_original_location: Multan District (Pakistan)\n\n  inscriptions: \n\n  inscription_language: \n\n  shape: irregular\n\n  materials_name: silk (textile) silver thread cotton (textile)\n\n  techniques_name: sewing (needleworking technique) embroidering\n\n  object_colour: multicolored\n\n  physical_appearance: This is an embroidered yoke. It is red\n with silver and gold embroided geometric patterns. There is a square hole in the middle of the garment. The garment looks slightly frayed around the edges.\n\n  subject_terms_1: geometric motifs tunics embroidery (visual works) folk costume\n\n  subject_terms_2: Tunics Motifs Sindhi (South Asian people) Embroidery Ethnic costume Clothing and dress\n\n  subject_terms_3: Indian costumes\n\n  subject_terms_4: \n\n  sgcool_label_text: A finely embroidered yoke\n that would have been stitched on to a blouse or tunic\n to be worn by a Sindhi woman.\n",
  "createdDate": "20201201203308",
  "version": 0,
  "latest": false,
  "roles": [],
  "metadata": {
    "accession_no_csv": "2017-00592",
    "Image": "",
    "object_work_type": "womenswear costume components",
    "title_text": "Blouse Yoke",
    "preference": "main",
    "title_language": "English",
    "creation_date": "20th century",
    "creation_place_original_location": "Multan District (Pakistan)",
    "inscriptions": "",
    "inscription_language": "",
    "shape": "irregular",
    "materials_name": "silk (textile) silver thread cotton (textile)",
    "techniques_name": "sewing (needleworking technique) embroidering",
    "object_colour": "multicolored",
    "physical_appearance": "This is an embroidered yoke. It is red, with silver and gold embroided geometric patterns. There is a square hole in the middle of the garment. The garment looks slightly frayed around the edges.",
    "subject_terms_1": "geometric motifs tunics embroidery (visual works) folk costume",
    "subject_terms_2": "Tunics Motifs Sindhi (South Asian people) Embroidery Ethnic costume Clothing and dress",
    "subject_terms_3": "Indian costumes",
    "subject_terms_4": "",
    "sgcool_label_text": "A finely embroidered yoke, that would have been stitched on to a blouse or tunic, to be worn by a Sindhi woman."
  },
  "nlpDate": "20201201203308",
  "connectorId": 0,
  "tags": {}
}