{
  "id": "2017-00805",
  "title": "Men’s black gummed silk jacket with four pockets",
  "source": "Bumblebee",
  "path": "./Data/json/",
  "content": "\n  accession_no_csv: 2017-00805\n\n  Image: \n\n  object_work_type: silks (costume by material)  jackets (garments)\n\n  title_text: Men’s black gummed silk jacket with four pockets\n\n  preference: main\n\n  title_language: \n\n  creation_date: 1920s-1930s\n\n  creation_place_original_location: Hong Kong (China)  Hong Kong (China)\n\n  styles_periods_indexing_terms: Chinese (culture or style)\n\n  inscriptions: \n\n  inscription_language: \n\n  shape: T-shaped?\n\n  materials_name: silk (textile)\n\n  techniques_name: sewing (needleworking technique)\n\n  object_colour: brown (colour)  black (colour)\n\n  physical_appearance: This is a black and brown jacket that has two breast pockets and two waist pockets. It has mandarin buttons that run down the center.\n\n  subject_terms_1: folk costume?  menswear\n\n  subject_terms_2: Silk  Ethnic costume Tailoring Waterproof clothing  Jackets  Men\\u0027s clothing\n\n  subject_terms_3: Chinese costumes\n\n  context_20: Bullion Trading Company “Yee Shing”\n\n  context_21: 20 Canal Road in Singapore\n\n  context_22: 1930s\n\n  context_23: 1930\n\n  context_24: 1939\n\n  sgcool_label_text: Black gummed silk (known as xiangyunsha??? or heijiaochou???  in Chinese) was a popular material used in the tailoring of summer clothing in Beijing\n Shanghai and Hong Kong in the 1920s to 1930s. It has a distinctive black shiny surface which is waterproof and a matt brown underside which reveals an underlying weave of varying patterns. It originates in the district of Shunde in Guangdong province and is still being made there today.\\r\\n\\r\\nThis jacket belonged to Mr Kaan Tat Choi\n who was a successful businessman in the bullion business. Mr Kan expanded his business from Hong Kong to Malaya in the 1920s\n acquiring several rubber plantations along the east coast of Malaya. He also opened a bullion trading company called “Yee Shing” at 20 Canal Road in Singapore in the 1930s. \\r\\n\n",
  "createdDate": "20201120223708",
  "version": 0,
  "latest": false,
  "roles": [],
  "metadata": {
    "accession_no_csv": "2017-00805",
    "Image": "",
    "object_work_type": "silks (costume by material)  jackets (garments)",
    "title_text": "Men’s black gummed silk jacket with four pockets",
    "preference": "main",
    "title_language": "",
    "creation_date": "1920s-1930s",
    "creation_place_original_location": "Hong Kong (China)  Hong Kong (China)",
    "styles_periods_indexing_terms": "Chinese (culture or style)",
    "inscriptions": "",
    "inscription_language": "",
    "shape": "T-shaped?",
    "materials_name": "silk (textile)",
    "techniques_name": "sewing (needleworking technique)",
    "object_colour": "brown (colour)  black (colour)",
    "physical_appearance": "This is a black and brown jacket that has two breast pockets and two waist pockets. It has mandarin buttons that run down the center.",
    "subject_terms_1": "folk costume?  menswear",
    "subject_terms_2": "Silk  Ethnic costume Tailoring Waterproof clothing  Jackets  Men\u0027s clothing",
    "subject_terms_3": "Chinese costumes",
    "context_20": "Bullion Trading Company “Yee Shing”",
    "context_21": "20 Canal Road in Singapore",
    "context_22": "1930s",
    "context_23": "1930",
    "context_24": "1939",
    "sgcool_label_text": "Black gummed silk (known as xiangyunsha??? or heijiaochou???  in Chinese) was a popular material used in the tailoring of summer clothing in Beijing, Shanghai and Hong Kong in the 1920s to 1930s. It has a distinctive black shiny surface which is waterproof and a matt brown underside which reveals an underlying weave of varying patterns. It originates in the district of Shunde in Guangdong province and is still being made there today.\r\n\r\nThis jacket belonged to Mr Kaan Tat Choi, who was a successful businessman in the bullion business. Mr Kan expanded his business from Hong Kong to Malaya in the 1920s, acquiring several rubber plantations along the east coast of Malaya. He also opened a bullion trading company called “Yee Shing” at 20 Canal Road in Singapore in the 1930s. \r\n"
  },
  "nlpDate": "20201120223708",
  "connectorId": 0,
  "tags": {}
}