{
  "id": "2017-00594",
  "title": "Embroidered Tunic Chola",
  "source": "Bumblebee",
  "path": "./Data/json/",
  "content": "\n  accession_no_csv: 2017-00594\n\n  Image: \n\n  object_work_type: tunics womenswear\n\n  title_text: Embroidered Tunic Chola\n\n  preference: main alternate\n\n  title_language: English\n\n  creation_date: 20th century\n\n  creation_place_original_location: Multan District (Pakistan)\n\n  inscriptions: \n\n  inscription_language: \n\n  shape: irregular\n\n  materials_name: cotton (textile) silk (textile)\n\n  techniques_name: sewing (needleworking technique) embroidering\n\n  object_colour: multicolored\n\n  physical_appearance: This is an embroidered tunic. It has mid-length sleeves. It is multicolored\n with various coloured panellings and embroidered designs. It has a small square collar.\n\n  subject_terms_1: folk costume geometric motifs embroidery (visual works) tops (garments\n general) blouses (main garments) ceremonial costume\n\n  subject_terms_2: Ethnic costume Tunics Motifs Embroidery Sindhi (South Asian people) Blouses\n\n  subject_terms_3: Indian costumes\n\n  subject_terms_4: \n\n  sgcool_label_text: This is a tunic or chola\n worn traditionally in the Sindh region of Pakistan. The tunic would have been made for a woman\n to be worn for special occasions.\n",
  "createdDate": "20201120223708",
  "version": 0,
  "latest": false,
  "roles": [],
  "metadata": {
    "accession_no_csv": "2017-00594",
    "Image": "",
    "object_work_type": "tunics womenswear",
    "title_text": "Embroidered Tunic Chola",
    "preference": "main alternate",
    "title_language": "English",
    "creation_date": "20th century",
    "creation_place_original_location": "Multan District (Pakistan)",
    "inscriptions": "",
    "inscription_language": "",
    "shape": "irregular",
    "materials_name": "cotton (textile) silk (textile)",
    "techniques_name": "sewing (needleworking technique) embroidering",
    "object_colour": "multicolored",
    "physical_appearance": "This is an embroidered tunic. It has mid-length sleeves. It is multicolored, with various coloured panellings and embroidered designs. It has a small square collar.",
    "subject_terms_1": "folk costume geometric motifs embroidery (visual works) tops (garments, general) blouses (main garments) ceremonial costume",
    "subject_terms_2": "Ethnic costume Tunics Motifs Embroidery Sindhi (South Asian people) Blouses",
    "subject_terms_3": "Indian costumes",
    "subject_terms_4": "",
    "sgcool_label_text": "This is a tunic or chola, worn traditionally in the Sindh region of Pakistan. The tunic would have been made for a woman, to be worn for special occasions."
  },
  "nlpDate": "20201120223708",
  "connectorId": 0,
  "tags": {}
}