{
  "id": "2017-00018",
  "title": "Completing",
  "source": "Bumblebee",
  "path": "./Data/json/",
  "content": "\n  accession_no_csv: 2017-00018\n\n  Image: \n\n  object_work_type: black-and-white prints (photographs) photographic prints gelatin silver prints\n\n  title_text: Completing\n\n  preference: main\n\n  title_language: \n\n  creator_2: Lee\n Lim\n\n  creator_1: Lee\n Lim\n\n  creator_role: photographers\n\n  creation_date: c. 1961\n\n  creation_place_original_location: Not indicated\n\n  inscriptions: \n\n  inscription_language: \n\n  shape: rectangular\n\n  materials_name: silver sulfide paper (fibre product) baryta paper gelatin\n\n  techniques_name: gelatin silver process photographic printing techniques black-and-white photography\n\n  object_colour: black-and-white (colours)\n\n  physical_appearance: \\This is a gelatin silver print and the image captures two men in sun hats sawing a beam atop a roof\\u0027s skeleton frame. On the verso there is a photographer\\u0027s chop and the title \\\\Completing\\\\\n\n  subject_terms_1: constructing construction workers a Fresno sticker sawing\n\n  subject_terms_2: Rooftop construction Royal Photographic Society of Great Britain and an Espana Salon chop. \\ Photography\n Artistic Sawing\n\n  subject_terms_3: Building and Construction construction sites Artistic photography\n\n  subject_terms_4: Construction Workers\n\n  context_1: visual arts\n\n  context_22: Address indicated on photography studio\\u0027s chop.\n\n  context_23: No 1 Tiong Bahru Road\n Singapore 3\n\n  context_24: c. 1961\n\n  sgcool_label_text: 1956\n",
  "createdDate": "20201125084530",
  "version": 0,
  "latest": false,
  "roles": [],
  "metadata": {
    "accession_no_csv": "2017-00018",
    "Image": "",
    "object_work_type": "black-and-white prints (photographs) photographic prints gelatin silver prints",
    "title_text": "Completing",
    "preference": "main",
    "title_language": "",
    "creator_2": "Lee, Lim",
    "creator_1": "Lee, Lim",
    "creator_role": "photographers",
    "creation_date": "c. 1961",
    "creation_place_original_location": "Not indicated",
    "inscriptions": "",
    "inscription_language": "",
    "shape": "rectangular",
    "materials_name": "silver sulfide paper (fibre product) baryta paper gelatin",
    "techniques_name": "gelatin silver process photographic printing techniques black-and-white photography",
    "object_colour": "black-and-white (colours)",
    "physical_appearance": "\"This is a gelatin silver print and the image captures two men in sun hats sawing a beam atop a roof\u0027s skeleton frame. On the verso there is a photographer\u0027s chop and the title \"\"Completing\"\"",
    "subject_terms_1": "constructing construction workers a Fresno sticker sawing",
    "subject_terms_2": "Rooftop construction Royal Photographic Society of Great Britain and an Espana Salon chop. \" Photography, Artistic Sawing",
    "subject_terms_3": "Building and Construction construction sites Artistic photography",
    "subject_terms_4": "Construction Workers",
    "context_1": "visual arts",
    "context_22": "Address indicated on photography studio\u0027s chop.",
    "context_23": "No 1 Tiong Bahru Road, Singapore 3",
    "context_24": "c. 1961",
    "sgcool_label_text": "1956"
  },
  "nlpDate": "20201125084530",
  "connectorId": 0,
  "tags": {}
}