{
  "id": "2017-00946-001 TO 079",
  "title": "Rape and Pillage",
  "source": "Bumblebee",
  "path": "./Data/json/",
  "content": "\n  accession_no_csv: 2017-00946-001 TO 079\n\n  Image: \n\n  object_work_type: installations (visual works)\n\n  title_text: Rape and Pillage\n\n  preference: main\n\n  title_language: \n\n  creator_2: Jakkai Siributr\n\n  creator_1: Siributr\n Jakkai\n 1969-\n\n  creator_role: artists (visual artists)\n\n  creation_date: 2013\n\n  creation_place_original_location: Thailand\n\n  inscriptions: \n\n  inscription_language: \n\n  materials_name: polyester (fiber) textile materials\n\n  techniques_name: sound recordings embroidering\n\n  object_colour: multicoloured\n\n  edition_description: Unique\n\n  physical_appearance: This is an installation work consisting of 39 Thai civil service uniforms\n each with an embroidered portrait of a Thai politician. The uniforms hover above the ground.\n\n  subject_terms_1: uniforms public services (organizations) politicians embroidery (visual works) social issues\n\n  subject_terms_2: Thailand Embroidery Politicians Civil service Installations (Art) Uniforms\n\n  subject_terms_3: Installation art\n\n  sgcool_label_text: Thai artist Jakkai Siributr is best known for his works in the textile medium. Featuring intricate embroidery and needlework\n Jakkai confronts socio-political issues afflicting Thailand through the medium of fabric. In his numerous exploration of the turbulent Thai political scene\n Jakkai hasn’t shied away from vocal critique. Immediately confrontational\n Rape and Pillage features 39 white polyester jacket and trouser uniforms worn by the Thai civil service. Each uniform has been embroidered with the portrait of a Thai politician. Hovering off the ground\n these uniforms strike the viewer as spectral representations of the politicians. Jakkai’s distrust of the state’s political leaders rings clear – the title of the work makes no attempt at concealing any disdain whatsoever. Yet\n the work is also an invitation to viewers to cast their own judgement on these leaders themselves.In a time of political instability\n the textile-based practice of Jakkai Siributr stands as a stark contrast to the state of affairs in the country today. The meticulously-crafted and labour-intensive hand-made pieces\n all slow\n skillful precision and carefully worked stitching\n are in their sobriety and virtuosity in absolute opposition to the ethos of Thai public affairs today: fast\n thoughtless\n and random.\n",
  "createdDate": "20201201203308",
  "version": 0,
  "latest": false,
  "roles": [],
  "metadata": {
    "accession_no_csv": "2017-00946-001 TO 079",
    "Image": "",
    "object_work_type": "installations (visual works)",
    "title_text": "Rape and Pillage",
    "preference": "main",
    "title_language": "",
    "creator_2": "Jakkai Siributr",
    "creator_1": "Siributr, Jakkai, 1969-",
    "creator_role": "artists (visual artists)",
    "creation_date": "2013",
    "creation_place_original_location": "Thailand",
    "inscriptions": "",
    "inscription_language": "",
    "materials_name": "polyester (fiber) textile materials",
    "techniques_name": "sound recordings embroidering",
    "object_colour": "multicoloured",
    "edition_description": "Unique",
    "physical_appearance": "This is an installation work consisting of 39 Thai civil service uniforms, each with an embroidered portrait of a Thai politician. The uniforms hover above the ground.",
    "subject_terms_1": "uniforms public services (organizations) politicians embroidery (visual works) social issues",
    "subject_terms_2": "Thailand Embroidery Politicians Civil service Installations (Art) Uniforms",
    "subject_terms_3": "Installation art",
    "sgcool_label_text": "Thai artist Jakkai Siributr is best known for his works in the textile medium. Featuring intricate embroidery and needlework, Jakkai confronts socio-political issues afflicting Thailand through the medium of fabric. In his numerous exploration of the turbulent Thai political scene, Jakkai hasn’t shied away from vocal critique. Immediately confrontational, Rape and Pillage features 39 white polyester jacket and trouser uniforms worn by the Thai civil service. Each uniform has been embroidered with the portrait of a Thai politician. Hovering off the ground, these uniforms strike the viewer as spectral representations of the politicians. Jakkai’s distrust of the state’s political leaders rings clear – the title of the work makes no attempt at concealing any disdain whatsoever. Yet, the work is also an invitation to viewers to cast their own judgement on these leaders themselves.In a time of political instability, the textile-based practice of Jakkai Siributr stands as a stark contrast to the state of affairs in the country today. The meticulously-crafted and labour-intensive hand-made pieces, all slow, skillful precision and carefully worked stitching, are in their sobriety and virtuosity in absolute opposition to the ethos of Thai public affairs today: fast, thoughtless, and random."
  },
  "nlpDate": "20201201203308",
  "connectorId": 0,
  "tags": {}
}