{
  "id": "2017-00162",
  "title": "Lee Shao Meng Collection: Yunnan University Certificate",
  "source": "Bumblebee",
  "path": "./Data/json/",
  "content": "\n  accession_no_csv: 2017-00162\n\n  Image: \n\n  object_work_type: certificates\n\n  title_text: Lee Shao Meng Collection: Yunnan University Certificate\n\n  preference: main alternate\n\n  title_language: \n\n  creation_date: 1946\n\n  creation_place_original_location: Singapore\n\n  inscriptions: \n\n  inscription_language: \n\n  shape: rectangular\n\n  materials_name: paper (fiber product)\n\n  techniques_name: writing (processes)\n\n  object_colour: multicolored\n\n  physical_appearance: This is a university certificate. It is printed in black ink against a paper with a red printed template. There is a red stamp on the left. The signature is stamped in blue ink on the bottom-left. There are several holes in the document along the top and bottom.\n\n  subject_terms_1: resistance movements documents (object genre) world wars postsecondary education\n\n  subject_terms_2: World War\n 1939-1945 Postsecondary education Great Britain. Army. Force 136 Certification Force 136 (Guerilla movement) Yunnan da xue\n\n  subject_terms_3: 1942-1945 Japanese occupation Force 136 (Guerilla movement) Lee\n Shao Meng\n\n  subject_terms_4: \n\n  sgcool_label_text: This certificate belongs to part of a collection of artefacts related to the World War II underground resistance movement known as Force 136. The collection of materials was gathered by Tan Chong Tee (1916- 2012)\n who was a key member of this resistance group. The collection consists of original materials belonging to Tan and other members of Force 136 dating from the 1940s to new materials reproduced from memory by Tan Chong Tee\n which date from the late 1980s to early 2000s. \\r\\n\\r\\nForce 136 was set up in July 1942 as part of the British Special Operations Executive (SOE). It recruited and trained local guerillas to gather intelligence and create an underground spy network to support planned British invasion of Japanese-occupied Malaya.\\r\\n\\r\\nLee Shao Meng was the wife of Tan Chong Tee and was also involved in the war resistance movement in Malaya against the Japanese.\\r\\n\n",
  "createdDate": "20201125084525",
  "version": 0,
  "latest": false,
  "roles": [],
  "metadata": {
    "accession_no_csv": "2017-00162",
    "Image": "",
    "object_work_type": "certificates",
    "title_text": "Lee Shao Meng Collection: Yunnan University Certificate",
    "preference": "main alternate",
    "title_language": "",
    "creation_date": "1946",
    "creation_place_original_location": "Singapore",
    "inscriptions": "",
    "inscription_language": "",
    "shape": "rectangular",
    "materials_name": "paper (fiber product)",
    "techniques_name": "writing (processes)",
    "object_colour": "multicolored",
    "physical_appearance": "This is a university certificate. It is printed in black ink against a paper with a red printed template. There is a red stamp on the left. The signature is stamped in blue ink on the bottom-left. There are several holes in the document along the top and bottom.",
    "subject_terms_1": "resistance movements documents (object genre) world wars postsecondary education",
    "subject_terms_2": "World War, 1939-1945 Postsecondary education Great Britain. Army. Force 136 Certification Force 136 (Guerilla movement) Yunnan da xue",
    "subject_terms_3": "1942-1945 Japanese occupation Force 136 (Guerilla movement) Lee, Shao Meng",
    "subject_terms_4": "",
    "sgcool_label_text": "This certificate belongs to part of a collection of artefacts related to the World War II underground resistance movement known as Force 136. The collection of materials was gathered by Tan Chong Tee (1916- 2012), who was a key member of this resistance group. The collection consists of original materials belonging to Tan and other members of Force 136 dating from the 1940s to new materials reproduced from memory by Tan Chong Tee, which date from the late 1980s to early 2000s. \r\n\r\nForce 136 was set up in July 1942 as part of the British Special Operations Executive (SOE). It recruited and trained local guerillas to gather intelligence and create an underground spy network to support planned British invasion of Japanese-occupied Malaya.\r\n\r\nLee Shao Meng was the wife of Tan Chong Tee and was also involved in the war resistance movement in Malaya against the Japanese.\r\n"
  },
  "nlpDate": "20201125084525",
  "connectorId": 0,
  "tags": {}
}