{
  "id": "2017-00933",
  "title": "Photograph of Tan Cheng Siang Tan Cheng Siang",
  "source": "Bumblebee",
  "path": "./Data/json/",
  "content": "\n  accession_no_csv: 2017-00933\n\n  Image: \n\n  object_work_type: black-and-white photographs studio portraits\n\n  title_text: Photograph of Tan Cheng Siang Tan Cheng Siang\n\n  preference: main alternate\n\n  title_language: \n\n  creation_date: Early 20th century\n\n  creation_place_original_location: Singapore\n\n  inscriptions: \n\n  inscription_language: \n\n  shape: rectangular\n\n  materials_name: paper (fiber product) wood (plant material)\n\n  techniques_name: photography (process)\n\n  object_colour: black-and-white (color)\n\n  physical_appearance: This is a black-and-white portrait photograph of Tan cheng Siang. He is seated on a chair\n gazing forward towards the viewer. He is wearing a double breasted suit with a bouteonniere and pocket watch\n sitting against a plain backdrop with a panama hat on the left. There is a signature stamp on the bottom-right of the photograph.\n\n  subject_terms_1: businessmen Peranakan photographs\n\n  subject_terms_2: Peranakan (Asian people) Photographs Portrait photography Businessmen\n\n  subject_terms_3: Tan\n Kim Tian Portrait photography Peranakan clans and associations\n\n  sgcool_label_text: Tan Cheng Siang(1885-1977) looks out confidently at the viewer in this studio photograph. Wearing a double breasted suit\n complete with a boutonniere and pocket watch\n he sits before a plain backdrop with a panama hat by his side. The shop mark ‘Koon Sun Photographer\n Singapore’ can be seen on the photograph. Koon Sun Photo Studio was located along South Bridge Road in Singapore’s city centre. It was one of the two photographic studios established by Lee Tat Loon and Lee Tit Loon\n whose son went on to found Lee Brothers Studio. This photograph came from the collection of Botan House\n the ancestral home built by Tan Kim Tian.\n",
  "createdDate": "20201201203308",
  "version": 0,
  "latest": false,
  "roles": [],
  "metadata": {
    "accession_no_csv": "2017-00933",
    "Image": "",
    "object_work_type": "black-and-white photographs studio portraits",
    "title_text": "Photograph of Tan Cheng Siang Tan Cheng Siang",
    "preference": "main alternate",
    "title_language": "",
    "creation_date": "Early 20th century",
    "creation_place_original_location": "Singapore",
    "inscriptions": "",
    "inscription_language": "",
    "shape": "rectangular",
    "materials_name": "paper (fiber product) wood (plant material)",
    "techniques_name": "photography (process)",
    "object_colour": "black-and-white (color)",
    "physical_appearance": "This is a black-and-white portrait photograph of Tan cheng Siang. He is seated on a chair, gazing forward towards the viewer. He is wearing a double breasted suit with a bouteonniere and pocket watch, sitting against a plain backdrop with a panama hat on the left. There is a signature stamp on the bottom-right of the photograph.",
    "subject_terms_1": "businessmen Peranakan photographs",
    "subject_terms_2": "Peranakan (Asian people) Photographs Portrait photography Businessmen",
    "subject_terms_3": "Tan, Kim Tian Portrait photography Peranakan clans and associations",
    "sgcool_label_text": "Tan Cheng Siang(1885-1977) looks out confidently at the viewer in this studio photograph. Wearing a double breasted suit, complete with a boutonniere and pocket watch, he sits before a plain backdrop with a panama hat by his side. The shop mark ‘Koon Sun Photographer, Singapore’ can be seen on the photograph. Koon Sun Photo Studio was located along South Bridge Road in Singapore’s city centre. It was one of the two photographic studios established by Lee Tat Loon and Lee Tit Loon, whose son went on to found Lee Brothers Studio. This photograph came from the collection of Botan House, the ancestral home built by Tan Kim Tian."
  },
  "nlpDate": "20201201203308",
  "connectorId": 0,
  "tags": {}
}