{"id":"2017-00797","title":"Cicadas #2","source":"Bumblebee","path":"./Data/json/","content":"accession_no_csv:2017-00797\nImage:\nobject_work_type:shaped canvases (paintings by form) canvas paintings\ntitle_text:Cicadas #2\npreference:main\ntitle_language:\ncreator_2:Genevieve Chua\ncreator_1:Chua\n Genevieve\ncreator_role:artists (visual artists)\ncreation_date:2016\ncreation_place_original_location:Singapore\ninscriptions:\ninscription_language:\nshape:irregular\nmaterials_name:acrylic paint  canvas (textile material)\ntechniques_name:acrylic painting (technique) screen printing\nobject_colour:multicoloured\nedition_description:unique\nphysical_appearance:This is a shaped canvas painting. There are lines of red that course through the work.\nsubject_terms_1:screen prints  Cicadidae (family) wings (animal components) abstraction\nsubject_terms_2:Shaped canvas  Acrylic painting  Cicadas in art  Wings  Abstraction Art\n Singaporean\nsubject_terms_3:Acrylic painting\ncontext_1:Unnatural History Drawings\ncontext_2:exhibitions (events)\ncontext_3:8-Sep-2016 to 10-Sep-2016\ncontext_4:8-Sep-16\ncontext_5:10-Sep-16\ncontext_6:Singapore\ncontext_7:Artspace@Helutrans\n Singapore\ncontext_8:planners\nsgcool_label_text:Cicadas #2 brings together two interests that have coursed through Genevieve Chua’s practice: nature and the wild\n as well as the intertwining relationship between sound and image. Part of Chua’s ‘Unnatural History Drawings’\n the shaped canvas takes as its starting point\n the extensive collection of natural history drawings that were commissioned by William Farquhar in the early 19th century. With an abiding interest to explore abstraction in painting\n the work also incorporates the ultrasound image as a means to probe the relationship between sound and vision\n and how sensorial experiences can translate across one other. Chua’s use of the ultrasound gestures towards the realm of possibility of what lies beyond the range of human sensory detection\n as made realisable by science and technology. \\r\\n\\r\\nCicada #2 evokes the shape of the insect delicately unfolding its damp wings after its period of dormancy\n a phase and life ‘lived’ buried underground for 17 years for some species of cicadas. Waking as a thunderous force after dormancy\n the cicadas collectively produce a deafening song during the mating season\n only to die shortly after. Sex and impending demise are conjoined in the cicada song\n a sonic cry that finds translation into the visual realm through the ultrasound pattern on the painting’s surface that is rendered based on the cicadas’ mating call. \\r\\n\\r\\nGenevieve Chua (b. 1984\n Singapore) is a visual artist who works primarily through abstraction. Selected solo exhibitions include “Rehearsals for the Wilful” (Manila\n 2016); “Parabola” (Singapore\n 2014); and “Cicadas Cicadas” (Los Angeles\n 2014). She has also participated in the Singapore Biennale (2011)\n and was the Young Artist Award in 2012 conferred by the National Arts Council\n Singapore.\\r\\n","createdDate":"20201119143406","version":0,"latest":false,"roles":[],"metadata":{"accession_no_csv":"2017-00797","Image":"","object_work_type":"shaped canvases (paintings by form) canvas paintings","title_text":"Cicadas #2","preference":"main","title_language":"","creator_2":"Genevieve Chua","creator_1":"Chua, Genevieve","creator_role":"artists (visual artists)","creation_date":"2016","creation_place_original_location":"Singapore","inscriptions":"","inscription_language":"","shape":"irregular","materials_name":"acrylic paint  canvas (textile material)","techniques_name":"acrylic painting (technique) screen printing","object_colour":"multicoloured","edition_description":"unique","physical_appearance":"This is a shaped canvas painting. There are lines of red that course through the work.","subject_terms_1":"screen prints  Cicadidae (family) wings (animal components) abstraction","subject_terms_2":"Shaped canvas  Acrylic painting  Cicadas in art  Wings  Abstraction Art, Singaporean","subject_terms_3":"Acrylic painting","context_1":"Unnatural History Drawings","context_2":"exhibitions (events)","context_3":"8-Sep-2016 to 10-Sep-2016","context_4":"8-Sep-16","context_5":"10-Sep-16","context_6":"Singapore","context_7":"Artspace@Helutrans, Singapore","context_8":"planners","sgcool_label_text":"Cicadas #2 brings together two interests that have coursed through Genevieve Chua’s practice: nature and the wild, as well as the intertwining relationship between sound and image. Part of Chua’s ‘Unnatural History Drawings’, the shaped canvas takes as its starting point, the extensive collection of natural history drawings that were commissioned by William Farquhar in the early 19th century. With an abiding interest to explore abstraction in painting, the work also incorporates the ultrasound image as a means to probe the relationship between sound and vision, and how sensorial experiences can translate across one other. Chua’s use of the ultrasound gestures towards the realm of possibility of what lies beyond the range of human sensory detection, as made realisable by science and technology. \r\n\r\nCicada #2 evokes the shape of the insect delicately unfolding its damp wings after its period of dormancy, a phase and life ‘lived’ buried underground for 17 years for some species of cicadas. Waking as a thunderous force after dormancy, the cicadas collectively produce a deafening song during the mating season, only to die shortly after. Sex and impending demise are conjoined in the cicada song, a sonic cry that finds translation into the visual realm through the ultrasound pattern on the painting’s surface that is rendered based on the cicadas’ mating call. \r\n\r\nGenevieve Chua (b. 1984, Singapore) is a visual artist who works primarily through abstraction. Selected solo exhibitions include “Rehearsals for the Wilful” (Manila, 2016); “Parabola” (Singapore, 2014); and “Cicadas Cicadas” (Los Angeles, 2014). She has also participated in the Singapore Biennale (2011), and was the Young Artist Award in 2012 conferred by the National Arts Council, Singapore.\r\n"},"nlpDate":"20201119143406","connectorId":0,"tags":{}}