{"id":"2017-00160","title":"Lee Shao Meng Collection: Student certificate of Lee Shao Meng ?????","source":"Bumblebee","path":"./Data/json/","content":"accession_no_csv:2017-00160\nImage:\nobject_work_type:certificates\ntitle_text:Lee Shao Meng Collection: Student certificate of Lee Shao Meng ?????\npreference:main alternate\ntitle_language:\ncreation_date:Not indicated\ncreation_place_original_location:Singapore\ninscriptions:\ninscription_language:\nshape:rectangular\nmaterials_name:paper (fiber product)\ntechniques_name:printing (processes)\nobject_colour:multicolored\nphysical_appearance:This is a student identification certificate. The form is printed in black ink\n on a plain piece of paper. The fields are filled in with handwritten inscriptions in black ink. There are several blue and red stamps across the page. There is a photograph of a woman on the top-left of the document.\nsubject_terms_1:world wars resistance movements documents (object genre)\nsubject_terms_2:Certification World War\n 1939-1945 Great Britain. Army. Force 136 Force 136 (Guerilla movement)\nsubject_terms_3:Force 136 (Guerilla movement) 1942-1945 Japanese occupation Lee\n Shao Meng\nsubject_terms_4:\nsgcool_label_text:This certificate belongs to part of a collection of artefacts related to the World War II underground resistance movement known as Force 136. The collection of materials was gathered by Tan Chong Tee (1916- 2012)\n who was a key member of this resistance group. The collection consists of original materials belonging to Tan and other members of Force 136 dating from the 1940s to new materials reproduced from memory by Tan Chong Tee\n which date from the late 1980s to early 2000s. \\r\\n\\r\\nForce 136 was set up in July 1942 as part of the British Special Operations Executive (SOE). It recruited and trained local guerillas to gather intelligence and create an underground spy network to support planned British invasion of Japanese-occupied Malaya.\\r\\n\\r\\nLee Shao Meng was the wife of Tan Chong Tee and was also involved in the war resistance movement in Malaya against the Japanese. \\r\\n","createdDate":"20201018182636","version":0,"latest":false,"roles":[],"metadata":{"accession_no_csv":"2017-00160","Image":"","object_work_type":"certificates","title_text":"Lee Shao Meng Collection: Student certificate of Lee Shao Meng ?????","preference":"main alternate","title_language":"","creation_date":"Not indicated","creation_place_original_location":"Singapore","inscriptions":"","inscription_language":"","shape":"rectangular","materials_name":"paper (fiber product)","techniques_name":"printing (processes)","object_colour":"multicolored","physical_appearance":"This is a student identification certificate. The form is printed in black ink, on a plain piece of paper. The fields are filled in with handwritten inscriptions in black ink. There are several blue and red stamps across the page. There is a photograph of a woman on the top-left of the document.","subject_terms_1":"world wars resistance movements documents (object genre)","subject_terms_2":"Certification World War, 1939-1945 Great Britain. Army. Force 136 Force 136 (Guerilla movement)","subject_terms_3":"Force 136 (Guerilla movement) 1942-1945 Japanese occupation Lee, Shao Meng","subject_terms_4":"","sgcool_label_text":"This certificate belongs to part of a collection of artefacts related to the World War II underground resistance movement known as Force 136. The collection of materials was gathered by Tan Chong Tee (1916- 2012), who was a key member of this resistance group. The collection consists of original materials belonging to Tan and other members of Force 136 dating from the 1940s to new materials reproduced from memory by Tan Chong Tee, which date from the late 1980s to early 2000s. \r\n\r\nForce 136 was set up in July 1942 as part of the British Special Operations Executive (SOE). It recruited and trained local guerillas to gather intelligence and create an underground spy network to support planned British invasion of Japanese-occupied Malaya.\r\n\r\nLee Shao Meng was the wife of Tan Chong Tee and was also involved in the war resistance movement in Malaya against the Japanese. \r\n"},"nlpDate":"20201018182636","connectorId":0,"tags":{}}