{"id":"2017-01035","title":"Portrait of a woman Photograph of woman in long striped dress","source":"Bumblebee","path":"./Data/json/","content":"accession_no_csv:2017-01035\nImage:\nobject_work_type:black-and-white photographs photographs\ntitle_text:Portrait of a woman Photograph of woman in long striped dress\npreference:alternate main\ntitle_language:\ncreator_2:John Thomson\ncreator_1:Thomson\n J. (John)\n 1837-1921\ncreator_role:photographers\ncreation_date:1860s\ncreation_place_original_location:Singapore\ninscriptions:\ninscription_language:\nshape:rectangular\nmaterials_name:paper (fiber product)\ntechniques_name:photographic processes\nobject_colour:black-and-white (colors)\nphysical_appearance:This is a black-and-white portrait photograph of a woman. She is photographed wearing a long\n striped dress\n with accessories on her head\n earrings\n necklaces\n and bracelets. She is standing in the middle of a room\n with a short decorative column on the left\n a vase on the column\n and a furniture with a textile draped over it on the right. There are no inscriptions on the photograph. There are no tears or folds seen.\nsubject_terms_1:studio portraits folk costume\nsubject_terms_2:Carte de visite photographs Portrait photography Ethnic costume\nsubject_terms_3:Portrait photography Ethnic costumes\nsubject_terms_4:\nsgcool_label_text:This carte-de-visite format photograph was taken in the studio of John Thomson\n who arrived in Singapore in 1862 and established a studio at Beach Road on 16 June that year. Thomson would later travel to photograph in Siam and China before embarking on a series on street life in London.","createdDate":"20201018182636","version":0,"latest":false,"roles":[],"metadata":{"accession_no_csv":"2017-01035","Image":"","object_work_type":"black-and-white photographs photographs","title_text":"Portrait of a woman Photograph of woman in long striped dress","preference":"alternate main","title_language":"","creator_2":"John Thomson","creator_1":"Thomson, J. (John), 1837-1921","creator_role":"photographers","creation_date":"1860s","creation_place_original_location":"Singapore","inscriptions":"","inscription_language":"","shape":"rectangular","materials_name":"paper (fiber product)","techniques_name":"photographic processes","object_colour":"black-and-white (colors)","physical_appearance":"This is a black-and-white portrait photograph of a woman. She is photographed wearing a long, striped dress, with accessories on her head, earrings, necklaces, and bracelets. She is standing in the middle of a room, with a short decorative column on the left, a vase on the column, and a furniture with a textile draped over it on the right. There are no inscriptions on the photograph. There are no tears or folds seen.","subject_terms_1":"studio portraits folk costume","subject_terms_2":"Carte de visite photographs Portrait photography Ethnic costume","subject_terms_3":"Portrait photography Ethnic costumes","subject_terms_4":"","sgcool_label_text":"This carte-de-visite format photograph was taken in the studio of John Thomson, who arrived in Singapore in 1862 and established a studio at Beach Road on 16 June that year. Thomson would later travel to photograph in Siam and China before embarking on a series on street life in London."},"nlpDate":"20201018182636","connectorId":0,"tags":{}}