{"id":"2017-00156-026","title":"Lung Chui Ying Collection: Photographs, Printed Images, Pamphlets and Clippings  collected by Lung Chui Ying ????? Lung Chiu Ying Collection: identity card","source":"Bumblebee","path":"./Data/json/","content":"accession_no_csv:2017-00156-026\nImage:\nobject_work_type:identity cards\ntitle_text:Lung Chui Ying Collection: Photographs\n Printed Images\n Pamphlets and Clippings  collected by Lung Chui Ying ????? Lung Chiu Ying Collection: identity card\npreference:alternate alternate main\ntitle_language:\ncreation_date:Not indicated\ncreation_place_original_location:Singapore\ninscriptions:\ninscription_language:\nshape:rectangular\nmaterials_name:paper (fiber product)\ntechniques_name:writing (processes)\nobject_colour:multicolored\nphysical_appearance:This is a handwritten temporary identity card. The text is written witin a red outlined box. The title is written at the top-left corner. The letter is signed at the bottom of the page. The date is stated at the bottom-left of the page. There is a small tear near the bottom-right of the paper.\nsubject_terms_1:world wars resistance movements documents (object genre) handwriting\nsubject_terms_2:World War\n 1939-1945 Great Britain. Army. Force 136 Force 136 (Guerilla movement) Identification cards Writing\nsubject_terms_3:Force 136 (Guerilla movement) Lung\n Chiu Ying 1942-1945 Japanese occupation\nsubject_terms_4:\ncontext_1:World War\n 1939-1945 1942-1945 Japanese Occupation\ncontext_2:world wars occupations (armed conflicts)\ncontext_3:1939-1945 1942-1945\ncontext_4:1939 1942\ncontext_5:1945 1945\ncontext_6:Malaya Singapore\ncontext_7:Great Britain. Army. Force 136\ncontext_8:armed forces\nsgcool_label_text:These photographs\n printed images\n pamphlets and clippings belong to Lung Chui Ying and is part of a larger collection related to the World War II underground resistance movement known as Force 136. The collection of materials was gathered by Tan Chong Tee (1916- 2012)\n who was a key member of this resistance group. The collection consists of original materials belonging to Tan and other members of Force 136 dating from the 1940s to new materials reproduced from memory by Tan Chong Tee\n which date from the mid-1990s to early 2000s. \\r\\n\\r\\nForce 136 was set up in July 1942 as part of the British Special Operations Executive (SOE). It recruited and trained local guerillas to gather intelligence and create an underground spy network to support planned British invasion of Japanese-occupied Malaya.\\r\\n\\r\\nLung Chui Ying was a Hainanese born in Johor and recruited as a Force 136 member to fight against the Japanese in Malaya. \\r\\n","createdDate":"20201018182636","version":0,"latest":false,"roles":[],"metadata":{"accession_no_csv":"2017-00156-026","Image":"","object_work_type":"identity cards","title_text":"Lung Chui Ying Collection: Photographs, Printed Images, Pamphlets and Clippings  collected by Lung Chui Ying ????? Lung Chiu Ying Collection: identity card","preference":"alternate alternate main","title_language":"","creation_date":"Not indicated","creation_place_original_location":"Singapore","inscriptions":"","inscription_language":"","shape":"rectangular","materials_name":"paper (fiber product)","techniques_name":"writing (processes)","object_colour":"multicolored","physical_appearance":"This is a handwritten temporary identity card. The text is written witin a red outlined box. The title is written at the top-left corner. The letter is signed at the bottom of the page. The date is stated at the bottom-left of the page. There is a small tear near the bottom-right of the paper.","subject_terms_1":"world wars resistance movements documents (object genre) handwriting","subject_terms_2":"World War, 1939-1945 Great Britain. Army. Force 136 Force 136 (Guerilla movement) Identification cards Writing","subject_terms_3":"Force 136 (Guerilla movement) Lung, Chiu Ying 1942-1945 Japanese occupation","subject_terms_4":"","context_1":"World War, 1939-1945 1942-1945 Japanese Occupation","context_2":"world wars occupations (armed conflicts)","context_3":"1939-1945 1942-1945","context_4":"1939 1942","context_5":"1945 1945","context_6":"Malaya Singapore","context_7":"Great Britain. Army. Force 136","context_8":"armed forces","sgcool_label_text":"These photographs, printed images, pamphlets and clippings belong to Lung Chui Ying and is part of a larger collection related to the World War II underground resistance movement known as Force 136. The collection of materials was gathered by Tan Chong Tee (1916- 2012), who was a key member of this resistance group. The collection consists of original materials belonging to Tan and other members of Force 136 dating from the 1940s to new materials reproduced from memory by Tan Chong Tee, which date from the mid-1990s to early 2000s. \r\n\r\nForce 136 was set up in July 1942 as part of the British Special Operations Executive (SOE). It recruited and trained local guerillas to gather intelligence and create an underground spy network to support planned British invasion of Japanese-occupied Malaya.\r\n\r\nLung Chui Ying was a Hainanese born in Johor and recruited as a Force 136 member to fight against the Japanese in Malaya. \r\n"},"nlpDate":"20201018182636","connectorId":0,"tags":{}}