{
  "id": "2017-00266",
  "title": "Blue and white dish with qilin motif",
  "source": "Bumblebee",
  "path": "./Data/json/",
  "content": "\n  accession_no_csv: 2017-00266\n\n  Image: \n\n  object_work_type: porcelain (visual works) dishes (object genre) Ceramics (object genre)\n\n  title_text: Blue and white dish with qilin motif\n\n  preference: main\n\n  title_language: \n\n  creation_date: Ming dynasty\n late 15th - early 16th century\n\n  creation_place_original_location: Fujian  Sheng (China) Zhangzhou Shi (China). Tong ji ju\n\n  styles_periods_indexing_terms: Ming (culture\n period\n and styles) Chinese ceramics styles Chinese export (ceramics style)\n\n  inscriptions: \n\n  inscription_language: \n\n  shape: concave\n\n  materials_name: clay blue-and-white (ceramic glaze) ceramic glaze cobalt blue (pigment) porcelain (material)\n\n  techniques_name: freehand drawing (technique) firing (technique) underglazing porcelain painting (image-making) molding (forming) glazing (coating process) throwing (pottery techniques)\n\n  object_colour: multicoloured\n\n  physical_appearance: This is a Ming dynasty Zhangzhou dish.  Depicted in the central medallion is a qilin; a mythical beast in Chinese traditions.  Sketchily rendered\n it is surrounded by circular symbols that resemble classic symbols of wealth and fortune in Chinese tradition.\n\n  subject_terms_1: porcelain paintings (visual works) qilin legendary beings Chinese export porcelain freehand drawings (drawings) symbolism\n\n  subject_terms_2: Porcelain\n Chinese Ming- Qing dynasties\n 1368-1912 China trade porcelain Qilin China painting Mythical beasts Blue and white ware China\n\n  subject_terms_3: visual arts Ceramics Decorative arts\n\n  subject_terms_4: \n\n  sgcool_label_text: The creature depicted in the centre is typically identified as a qilin\n a mythological beast believed to embody attributes such as benevolence\n longevity and the bearing of illustrious offspring. Such dishes with a sketchily-rendered qilin motif have been recovered in large quantities in the Malay Archipelago. The thick potting and quality of glaze and decoration of this dish suggests that it was probably a product of the Zhangzhou kilns in Fujian province. Zhangzhou wares\n which were distinguished by their spontaneous and often exuberant painted decoration\n were a popular type of ceramics made for export during the late Ming dynasty.\n",
  "createdDate": "20201201203308",
  "version": 0,
  "latest": false,
  "roles": [],
  "metadata": {
    "accession_no_csv": "2017-00266",
    "Image": "",
    "object_work_type": "porcelain (visual works) dishes (object genre) Ceramics (object genre)",
    "title_text": "Blue and white dish with qilin motif",
    "preference": "main",
    "title_language": "",
    "creation_date": "Ming dynasty, late 15th - early 16th century",
    "creation_place_original_location": "Fujian  Sheng (China) Zhangzhou Shi (China). Tong ji ju",
    "styles_periods_indexing_terms": "Ming (culture, period, and styles) Chinese ceramics styles Chinese export (ceramics style)",
    "inscriptions": "",
    "inscription_language": "",
    "shape": "concave",
    "materials_name": "clay blue-and-white (ceramic glaze) ceramic glaze cobalt blue (pigment) porcelain (material)",
    "techniques_name": "freehand drawing (technique) firing (technique) underglazing porcelain painting (image-making) molding (forming) glazing (coating process) throwing (pottery techniques)",
    "object_colour": "multicoloured",
    "physical_appearance": "This is a Ming dynasty Zhangzhou dish.  Depicted in the central medallion is a qilin; a mythical beast in Chinese traditions.  Sketchily rendered, it is surrounded by circular symbols that resemble classic symbols of wealth and fortune in Chinese tradition.",
    "subject_terms_1": "porcelain paintings (visual works) qilin legendary beings Chinese export porcelain freehand drawings (drawings) symbolism",
    "subject_terms_2": "Porcelain, Chinese Ming- Qing dynasties, 1368-1912 China trade porcelain Qilin China painting Mythical beasts Blue and white ware China",
    "subject_terms_3": "visual arts Ceramics Decorative arts",
    "subject_terms_4": "",
    "sgcool_label_text": "The creature depicted in the centre is typically identified as a qilin, a mythological beast believed to embody attributes such as benevolence, longevity and the bearing of illustrious offspring. Such dishes with a sketchily-rendered qilin motif have been recovered in large quantities in the Malay Archipelago. The thick potting and quality of glaze and decoration of this dish suggests that it was probably a product of the Zhangzhou kilns in Fujian province. Zhangzhou wares, which were distinguished by their spontaneous and often exuberant painted decoration, were a popular type of ceramics made for export during the late Ming dynasty."
  },
  "nlpDate": "20201201203308",
  "connectorId": 0,
  "tags": {}
}