{"id":"2017-00948","title":"Marriage Certificate of Lim Chong Pang","source":"Bumblebee","path":"./Data/json/","content":"accession_no_csv:2017-00948\nImage:\nobject_work_type:marriage certificates\ntitle_text:Marriage Certificate of Lim Chong Pang\npreference:main\ntitle_language:\ncreation_date:3-Dec-44\ncreation_place_original_location:Singapore\ninscriptions:\ninscription_language:\nshape:Rectangular\nmaterials_name:paper (fiber product)\ntechniques_name:writing (processes)\nphysical_appearance:\\This is Lim Chong Pang\\u0027s marriage certificate. The document contains the names of the witnesses\n the people who introduced the couple to each other\n as well the solemnizer. Above the title of the marriage certificate and between two phoenixes\n is the word “?\\\\ (joy)\nsubject_terms_1:symbolizing the happiness of a matrimonial union. The borders framing the wordings comprise of two Chinese cherubs (one holding a bow and arrow whilst the other carries a horn) legal documents\nsubject_terms_2:lotuses Legal documents\nsubject_terms_3:a peacock Marriage certificates\nsubject_terms_4:butterflies\ncontext_1:birds\ncontext_2:and peonies. The name of the printing company\ncontext_3:????????????\ncontext_4:is found at the bottom center of the document. \\\ncontext_5:marriage (social construct)\ncontext_6:Marriage\ncontext_7:Lim\n Chong Pang","createdDate":"20201018182636","version":0,"latest":false,"roles":[],"metadata":{"accession_no_csv":"2017-00948","Image":"","object_work_type":"marriage certificates","title_text":"Marriage Certificate of Lim Chong Pang","preference":"main","title_language":"","creation_date":"3-Dec-44","creation_place_original_location":"Singapore","inscriptions":"","inscription_language":"","shape":"Rectangular","materials_name":"paper (fiber product)","techniques_name":"writing (processes)","physical_appearance":"\"This is Lim Chong Pang\u0027s marriage certificate. The document contains the names of the witnesses, the people who introduced the couple to each other, as well the solemnizer. Above the title of the marriage certificate and between two phoenixes, is the word “?\"\" (joy)","subject_terms_1":"symbolizing the happiness of a matrimonial union. The borders framing the wordings comprise of two Chinese cherubs (one holding a bow and arrow whilst the other carries a horn) legal documents","subject_terms_2":"lotuses Legal documents","subject_terms_3":"a peacock Marriage certificates","subject_terms_4":"butterflies","context_1":"birds","context_2":"and peonies. The name of the printing company","context_3":"????????????","context_4":"is found at the bottom center of the document. \"","context_5":"marriage (social construct)","context_6":"Marriage","context_7":"Lim, Chong Pang"},"nlpDate":"20201018182636","connectorId":0,"tags":{}}