{
  "id": "2017-00935",
  "title": "Mirror",
  "source": "Bumblebee",
  "path": "./Data/json/",
  "content": "\n  accession_no_csv: 2017-00935\n\n  Image: \n\n  object_work_type: mirrors\n\n  title_text: Mirror\n\n  preference: main\n\n  title_language: \n\n  creation_date: Late 19 - early 20th century\n\n  creation_place_original_location: Singapore\n\n  inscriptions: \n\n  inscription_language: \n\n  shape: irregular\n\n  materials_name: wood (plant material)\n\n  techniques_name: woodcarving\n\n  object_colour: brown (color)\n\n  physical_appearance: This is a mirror. It is framed by wooden beams with engraved incised designs. The top of the mirror is decorated with a balustrade of small spindles. The top of the mirror features carved flowers and vines against a speckled background in a triangular shape. There are small carvings along the left and right side of the mirror frame as well.\n\n  subject_terms_1: Peranakan furniture cultural diffusion carvings (visual works)\n\n  subject_terms_2: Mirrors Culture diffusion Peranakan (Asian people) Furniture\n\n  subject_terms_3: Tan\n Kim Tian Furniture design\n\n  sgcool_label_text: This mirror is framed by beams with incised designs\n including a balustrade formed by finely carved spindles. This is crowned by a gable filled with carvings of flowers and vines against a speckled background. With its features inspired by European architecture\n this mirror is a modest example of Peranakan hybrid tastes. Teak furniture whose designs were inspired by English styles was popular among Peranakans since the late 19th century. This mirror came from the collection of Botan House\n the ancestral home built by Tan Kim Tian in 1883 at the corner of Neil Road and Craig Road (since demolished).\n",
  "createdDate": "20201201203308",
  "version": 0,
  "latest": false,
  "roles": [],
  "metadata": {
    "accession_no_csv": "2017-00935",
    "Image": "",
    "object_work_type": "mirrors",
    "title_text": "Mirror",
    "preference": "main",
    "title_language": "",
    "creation_date": "Late 19 - early 20th century",
    "creation_place_original_location": "Singapore",
    "inscriptions": "",
    "inscription_language": "",
    "shape": "irregular",
    "materials_name": "wood (plant material)",
    "techniques_name": "woodcarving",
    "object_colour": "brown (color)",
    "physical_appearance": "This is a mirror. It is framed by wooden beams with engraved incised designs. The top of the mirror is decorated with a balustrade of small spindles. The top of the mirror features carved flowers and vines against a speckled background in a triangular shape. There are small carvings along the left and right side of the mirror frame as well.",
    "subject_terms_1": "Peranakan furniture cultural diffusion carvings (visual works)",
    "subject_terms_2": "Mirrors Culture diffusion Peranakan (Asian people) Furniture",
    "subject_terms_3": "Tan, Kim Tian Furniture design",
    "sgcool_label_text": "This mirror is framed by beams with incised designs, including a balustrade formed by finely carved spindles. This is crowned by a gable filled with carvings of flowers and vines against a speckled background. With its features inspired by European architecture, this mirror is a modest example of Peranakan hybrid tastes. Teak furniture whose designs were inspired by English styles was popular among Peranakans since the late 19th century. This mirror came from the collection of Botan House, the ancestral home built by Tan Kim Tian in 1883 at the corner of Neil Road and Craig Road (since demolished)."
  },
  "nlpDate": "20201201203308",
  "connectorId": 0,
  "tags": {}
}