{
  "id": "2017-00149",
  "title": "Lung Chui Ying Collection: Maps of Malaya and Sumatra ????? Lung Chiu Ying Collection: Maps of Malaya and Sumatra",
  "source": "Bumblebee",
  "path": "./Data/json/",
  "content": "\n  accession_no_csv: 2017-00149\n\n  Image: \n\n  object_work_type: maps (documents)\n\n  title_text: Lung Chui Ying Collection: Maps of Malaya and Sumatra ????? Lung Chiu Ying Collection: Maps of Malaya and Sumatra\n\n  preference: alternate alternate main\n\n  title_language: \n\n  creation_date: 1943-1945\n\n  creation_place_original_location: Singapore\n\n  inscriptions: \n\n  inscription_language: \n\n  shape: rectangular\n\n  materials_name: paper (fiber product)\n\n  techniques_name: printing (process)\n\n  object_colour: multicolored\n\n  physical_appearance: This is a map featuring Malaya and Sumatra. On the bottom-left of the map\n there is a wider view of the region in a rectangular boxed section. The map utilises shades of brown and orange to indicate altitude. The map is deeply creased along the folds.\n\n  subject_terms_1: world wars resistance movements\n\n  subject_terms_2: World War\n 1939-1945 Great Britain. Army. Force 136 Force 136 (Guerilla movement) Maps Malaya Sumatra (Indonesia)\n\n  subject_terms_3: Force 136 (Guerilla movement) 1942-1945 Japanese occupation Lung\n Chiu Ying\n\n  subject_terms_4: \n\n  context_1: World War\n 1939-1945 1942-1945 Japanese Occupation\n\n  context_2: world wars occupations (armed conflicts)\n\n  context_3: 1939-1945 1942-1945\n\n  context_4: 1939 1942\n\n  context_5: 1945 1945\n\n  context_6: Malaya Singapore\n\n  context_7: Great Britain. Army. Force 136\n\n  context_8: armed forces\n\n  sgcool_label_text: These two map feature Malaya and Sumatra and belongs to Lung Chui Ying. They form part of a collection of artefacts related to the World War II underground resistance movement known as Force 136. The collection of materials was amassed by Tan Chong Tee (1916- 2012)\n who was a key member of this resistance group. The collection consists of original materials belonging to Tan and other members of Force 136 dating from the 1940s to new materials reproduced from memory by Tan Chong Tee\n which date from the mid-1990s to early 2000s. \\r\\n\\r\\nForce 136 was set up in July 1942 as part of the British Special Operations Executive (SOE). It recruited and trained local guerillas to gather intelligence and create an underground spy network to support planned British invasion of Japanese-occupied Malaya.\\r\\n\n",
  "createdDate": "20201120223707",
  "version": 0,
  "latest": false,
  "roles": [],
  "metadata": {
    "accession_no_csv": "2017-00149",
    "Image": "",
    "object_work_type": "maps (documents)",
    "title_text": "Lung Chui Ying Collection: Maps of Malaya and Sumatra ????? Lung Chiu Ying Collection: Maps of Malaya and Sumatra",
    "preference": "alternate alternate main",
    "title_language": "",
    "creation_date": "1943-1945",
    "creation_place_original_location": "Singapore",
    "inscriptions": "",
    "inscription_language": "",
    "shape": "rectangular",
    "materials_name": "paper (fiber product)",
    "techniques_name": "printing (process)",
    "object_colour": "multicolored",
    "physical_appearance": "This is a map featuring Malaya and Sumatra. On the bottom-left of the map, there is a wider view of the region in a rectangular boxed section. The map utilises shades of brown and orange to indicate altitude. The map is deeply creased along the folds.",
    "subject_terms_1": "world wars resistance movements",
    "subject_terms_2": "World War, 1939-1945 Great Britain. Army. Force 136 Force 136 (Guerilla movement) Maps Malaya Sumatra (Indonesia)",
    "subject_terms_3": "Force 136 (Guerilla movement) 1942-1945 Japanese occupation Lung, Chiu Ying",
    "subject_terms_4": "",
    "context_1": "World War, 1939-1945 1942-1945 Japanese Occupation",
    "context_2": "world wars occupations (armed conflicts)",
    "context_3": "1939-1945 1942-1945",
    "context_4": "1939 1942",
    "context_5": "1945 1945",
    "context_6": "Malaya Singapore",
    "context_7": "Great Britain. Army. Force 136",
    "context_8": "armed forces",
    "sgcool_label_text": "These two map feature Malaya and Sumatra and belongs to Lung Chui Ying. They form part of a collection of artefacts related to the World War II underground resistance movement known as Force 136. The collection of materials was amassed by Tan Chong Tee (1916- 2012), who was a key member of this resistance group. The collection consists of original materials belonging to Tan and other members of Force 136 dating from the 1940s to new materials reproduced from memory by Tan Chong Tee, which date from the mid-1990s to early 2000s. \r\n\r\nForce 136 was set up in July 1942 as part of the British Special Operations Executive (SOE). It recruited and trained local guerillas to gather intelligence and create an underground spy network to support planned British invasion of Japanese-occupied Malaya.\r\n"
  },
  "nlpDate": "20201120223707",
  "connectorId": 0,
  "tags": {}
}