{
  "id": "2017-01040-145",
  "title": "\"Personal photograph album titled \"\"Sixteen Months in Singapore\"\"\" Sixteen Months in Singapore: Photograph of natural landscape",
  "source": "Bumblebee",
  "path": "./Data/json/",
  "content": "\n  accession_no_csv: 2017-01040-145\n\n  Image: \n\n  object_work_type: black-and-white photographs photographs\n\n  title_text: \\Personal photograph album titled \\\\Sixteen Months in Singapore\\\\\\ Sixteen Months in Singapore: Photograph of natural landscape\n\n  preference: alternate main\n\n  title_language: \n\n  creation_date: 1951-1952\n\n  creation_place_original_location: Singapore\n\n  inscriptions: \n\n  inscription_language: \n\n  shape: rectangular\n\n  materials_name: paper (fiber product)\n\n  techniques_name: photographic processes\n\n  object_colour: black-and-white (colors)\n\n  physical_appearance: This is a black-and-white photograph. It is rectangular in shape and landscape in orientation. It features a natural landscape\n with an open field in the foreground\n and a forested area in the background. There is a section of a water body on the left of the photograph. There are no individuals seen in the photograph. There are no inscriptions. There are no tears or folds seen.\n\n  subject_terms_1: aerial views landscapes (environment) snapshots\n\n  subject_terms_2: Photographs Landscape photography\n\n  subject_terms_3: Landscape photography\n\n  subject_terms_4: \n\n  sgcool_label_text: This is a personal photograph album that belonged to a Corporal A. Silver who spent 16 months in Singapore between 1951 and 1952. Silver was presumably a Jewish lady who was stationed in Singapore to serve at the Royal Air Force (RAF) Hospital at Changi. The album contains photographs that document her working and personal life\n including friends she made within the Jewish community in Singapore.\n",
  "createdDate": "20201120223708",
  "version": 0,
  "latest": false,
  "roles": [],
  "metadata": {
    "accession_no_csv": "2017-01040-145",
    "Image": "",
    "object_work_type": "black-and-white photographs photographs",
    "title_text": "\"Personal photograph album titled \"\"Sixteen Months in Singapore\"\"\" Sixteen Months in Singapore: Photograph of natural landscape",
    "preference": "alternate main",
    "title_language": "",
    "creation_date": "1951-1952",
    "creation_place_original_location": "Singapore",
    "inscriptions": "",
    "inscription_language": "",
    "shape": "rectangular",
    "materials_name": "paper (fiber product)",
    "techniques_name": "photographic processes",
    "object_colour": "black-and-white (colors)",
    "physical_appearance": "This is a black-and-white photograph. It is rectangular in shape and landscape in orientation. It features a natural landscape, with an open field in the foreground, and a forested area in the background. There is a section of a water body on the left of the photograph. There are no individuals seen in the photograph. There are no inscriptions. There are no tears or folds seen.",
    "subject_terms_1": "aerial views landscapes (environment) snapshots",
    "subject_terms_2": "Photographs Landscape photography",
    "subject_terms_3": "Landscape photography",
    "subject_terms_4": "",
    "sgcool_label_text": "This is a personal photograph album that belonged to a Corporal A. Silver who spent 16 months in Singapore between 1951 and 1952. Silver was presumably a Jewish lady who was stationed in Singapore to serve at the Royal Air Force (RAF) Hospital at Changi. The album contains photographs that document her working and personal life, including friends she made within the Jewish community in Singapore."
  },
  "nlpDate": "20201120223708",
  "connectorId": 0,
  "tags": {}
}