{"id":"2017-00190-001","title":"Chan Phui Kong Collection: Pouch containing Booklets, a Badge and Notes Chan Phui Kong Collection: Military reconnaissance survey form","source":"Bumblebee","path":"./Data/json/","content":"accession_no_csv:2017-00190-001\nImage:\nobject_work_type:surveys (documents)\ntitle_text:Chan Phui Kong Collection: Pouch containing Booklets\n a Badge and Notes Chan Phui Kong Collection: Military reconnaissance survey form\npreference:alternative main\ntitle_language:\ncreation_date:1942\ncreation_place_original_location:Singapore\ninscriptions:\ninscription_language:\nshape:rectangular\nmaterials_name:paper (fiber product)\ntechniques_name:printing (process)\nobject_colour:black-and-white (colors)\nphysical_appearance:This is a form document. The title is printed at the top of the document\n and is underlined. The form has several sections\n each segmented by a horizontal printed line. It is printed in black ink. On the form\n there are written inscriptions in a pencil. The document is slightly torn\n especially along the top.\nsubject_terms_1:world wars resistance movements documents (object genre)\nsubject_terms_2:World War\n 1939-1945 Great Britain. Army. Force 136 Force 136 (Guerilla movement) Chin\n Phui Kong\n 1923- Military reconnaissance\nsubject_terms_3:Force 136 (Guerilla movement) 1942-1945 Japanese occupation Chin\n Phui Kong\n 1923- war personalities\nsubject_terms_4:\ncontext_1:World War\n 1939-1945 1942-1945 Japanese Occupation\ncontext_2:world wars occupations (armed conflicts)\ncontext_3:1939-1945 1942-1945\ncontext_4:1939 1942\ncontext_5:1945 1945\ncontext_6:Malaya Singapore\ncontext_7:Great Britain. Army. Force 136\ncontext_8:armed forces\nsgcool_label_text:This pouch containing booklets\n notes and a badge belongs to part of a collection of artefacts owned by Chan Phui Kong who was involved in the World War II underground resistance movement known as Force 136. Chan’s collection forms part of a larger collection of materials gathered by Tan Chong Tee (1916- 2012)\n who was also a key member of this resistance group. The collection consists of original materials belonging to Tan and other members of Force 136 dating from the 1940s to new materials reproduced from memory by Tan Chong Tee\n which date from the late 1980s to early 2000s. \\r\\n\\r\\nForce 136 was set up in July 1942 as part of the British Special Operations Executive (SOE). It recruited and trained local guerillas to gather intelligence and create an underground spy network to support planned British invasion of Japanese-occupied Malaya.\\r\\n\\r\\nThe notes contain information on the nature of explosives and how to proceed with a guerrilla mission.","createdDate":"20201119143406","version":0,"latest":false,"roles":[],"metadata":{"accession_no_csv":"2017-00190-001","Image":"","object_work_type":"surveys (documents)","title_text":"Chan Phui Kong Collection: Pouch containing Booklets, a Badge and Notes Chan Phui Kong Collection: Military reconnaissance survey form","preference":"alternative main","title_language":"","creation_date":"1942","creation_place_original_location":"Singapore","inscriptions":"","inscription_language":"","shape":"rectangular","materials_name":"paper (fiber product)","techniques_name":"printing (process)","object_colour":"black-and-white (colors)","physical_appearance":"This is a form document. The title is printed at the top of the document, and is underlined. The form has several sections, each segmented by a horizontal printed line. It is printed in black ink. On the form, there are written inscriptions in a pencil. The document is slightly torn, especially along the top.","subject_terms_1":"world wars resistance movements documents (object genre)","subject_terms_2":"World War, 1939-1945 Great Britain. Army. Force 136 Force 136 (Guerilla movement) Chin, Phui Kong, 1923- Military reconnaissance","subject_terms_3":"Force 136 (Guerilla movement) 1942-1945 Japanese occupation Chin, Phui Kong, 1923- war personalities","subject_terms_4":"","context_1":"World War, 1939-1945 1942-1945 Japanese Occupation","context_2":"world wars occupations (armed conflicts)","context_3":"1939-1945 1942-1945","context_4":"1939 1942","context_5":"1945 1945","context_6":"Malaya Singapore","context_7":"Great Britain. Army. Force 136","context_8":"armed forces","sgcool_label_text":"This pouch containing booklets, notes and a badge belongs to part of a collection of artefacts owned by Chan Phui Kong who was involved in the World War II underground resistance movement known as Force 136. Chan’s collection forms part of a larger collection of materials gathered by Tan Chong Tee (1916- 2012), who was also a key member of this resistance group. The collection consists of original materials belonging to Tan and other members of Force 136 dating from the 1940s to new materials reproduced from memory by Tan Chong Tee, which date from the late 1980s to early 2000s. \r\n\r\nForce 136 was set up in July 1942 as part of the British Special Operations Executive (SOE). It recruited and trained local guerillas to gather intelligence and create an underground spy network to support planned British invasion of Japanese-occupied Malaya.\r\n\r\nThe notes contain information on the nature of explosives and how to proceed with a guerrilla mission."},"nlpDate":"20201119143406","connectorId":0,"tags":{}}