{
  "id": "2017-00846",
  "title": "WWII Japanese Map of Southeast Asia and Northern Australia",
  "source": "Bumblebee",
  "path": "./Data/json/",
  "content": "\n  accession_no_csv: 2017-00846\n\n  Image: \n\n  object_work_type: maps (documents)\n\n  title_text: WWII Japanese Map of Southeast Asia and Northern Australia\n\n  preference: main\n\n  title_language: \n\n  creation_date: 1942\n\n  creation_place_original_location: Japan\n\n  inscriptions: \n\n  inscription_language: \n\n  scale_type: 0:500km\n\n  shape: Rectangular\n\n  materials_name: paper (fiber product)\n\n  techniques_name: mapmaking (process)\n\n  object_colour: multicoloured\n\n  physical_appearance: This is a World War II map of Southeast Asia and Northern Australia. It is an overview of the Southern Co-Prosperity Sphere. It was issued by the Japanese Intelligency agency.\n\n  subject_terms_1: cartography (discipline)\n\n  subject_terms_2: World War\n 1939-1945 Maps Southeast Asia Cartography Australia\n Northern Greater East Asia Co-prosperity Sphere\n\n  subject_terms_3: Geographical areas and countries\n\n  sgcool_label_text: This map provides an overview of the Southern Co-Prosperity Sphere\n of northern Australia and Southeast Asia. Issued by the Japanese intelligence agency\n there is also an inset map in the lower left corner that depicts Australia and Southeast Asia in the larger region.\n",
  "createdDate": "20201125084516",
  "version": 0,
  "latest": false,
  "roles": [],
  "metadata": {
    "accession_no_csv": "2017-00846",
    "Image": "",
    "object_work_type": "maps (documents)",
    "title_text": "WWII Japanese Map of Southeast Asia and Northern Australia",
    "preference": "main",
    "title_language": "",
    "creation_date": "1942",
    "creation_place_original_location": "Japan",
    "inscriptions": "",
    "inscription_language": "",
    "scale_type": "0:500km",
    "shape": "Rectangular",
    "materials_name": "paper (fiber product)",
    "techniques_name": "mapmaking (process)",
    "object_colour": "multicoloured",
    "physical_appearance": "This is a World War II map of Southeast Asia and Northern Australia. It is an overview of the Southern Co-Prosperity Sphere. It was issued by the Japanese Intelligency agency.",
    "subject_terms_1": "cartography (discipline)",
    "subject_terms_2": "World War, 1939-1945 Maps Southeast Asia Cartography Australia, Northern Greater East Asia Co-prosperity Sphere",
    "subject_terms_3": "Geographical areas and countries",
    "sgcool_label_text": "This map provides an overview of the Southern Co-Prosperity Sphere, of northern Australia and Southeast Asia. Issued by the Japanese intelligence agency, there is also an inset map in the lower left corner that depicts Australia and Southeast Asia in the larger region."
  },
  "nlpDate": "20201125084516",
  "connectorId": 0,
  "tags": {}
}