{
  "id": "2017-00859",
  "title": "Choose",
  "source": "Bumblebee",
  "path": "./Data/json/",
  "content": "\n  accession_no_csv: 2017-00859\n\n  Image: \n\n  object_work_type: video art\n\n  title_text: Choose\n\n  preference: main\n\n  title_language: \n\n  creator_2: Johnny Manahan\n\n  creator_1: Manahan\n Johnny\n\n  creator_role: artists (visual artists)\n\n  creation_date: 1982\n\n  creation_place_original_location: Philippines\n\n  inscriptions: \n\n  inscription_language: \n\n  materials_name: mixed media\n\n  techniques_name: videography\n\n  object_colour: multicoloured\n\n  edition_description: 1 of 6\n\n  physical_appearance: This is an image of two sony monitors\n where the one on the left shows a video clip. This image of the clip shows an image of a television with a woman in it.\n\n  subject_terms_1: videocasettes  U-Matic  criticism\n\n  subject_terms_2: Video art  Art\n Philippine  Criticism  Videocasettes\n\n  subject_terms_3: Visual arts\n\n  context_1: A Fact Has No Appearance: Art Beyond the Object\n\n  context_2: exhibitions (events)\n\n  context_3: 22-Jan-2016 - 19-Jun-2016\n\n  context_4: 22-Jan-16\n\n  context_5: 19-Jun-16\n\n  context_6: National Gallery Singapore\n\n  context_7: National Gallery Singapore\n\n  context_8: planners curators\n\n  sgcool_label_text: Johnny Manahan’s Choose (1982) is probably the earliest surviving video artwork from the Philippines and the last artwork made Manahan made before completely devoting himself to his work in television. The video is historically and culturally significant for Philippine art and is probably among the earliest video works in Southeast Asia. The video is a self-reflexive commentary on the medium of video and television.\n",
  "createdDate": "20201120223708",
  "version": 0,
  "latest": false,
  "roles": [],
  "metadata": {
    "accession_no_csv": "2017-00859",
    "Image": "",
    "object_work_type": "video art",
    "title_text": "Choose",
    "preference": "main",
    "title_language": "",
    "creator_2": "Johnny Manahan",
    "creator_1": "Manahan, Johnny",
    "creator_role": "artists (visual artists)",
    "creation_date": "1982",
    "creation_place_original_location": "Philippines",
    "inscriptions": "",
    "inscription_language": "",
    "materials_name": "mixed media",
    "techniques_name": "videography",
    "object_colour": "multicoloured",
    "edition_description": "1 of 6",
    "physical_appearance": "This is an image of two sony monitors, where the one on the left shows a video clip. This image of the clip shows an image of a television with a woman in it.",
    "subject_terms_1": "videocasettes  U-Matic  criticism",
    "subject_terms_2": "Video art  Art, Philippine  Criticism  Videocasettes",
    "subject_terms_3": "Visual arts",
    "context_1": "A Fact Has No Appearance: Art Beyond the Object",
    "context_2": "exhibitions (events)",
    "context_3": "22-Jan-2016 - 19-Jun-2016",
    "context_4": "22-Jan-16",
    "context_5": "19-Jun-16",
    "context_6": "National Gallery Singapore",
    "context_7": "National Gallery Singapore",
    "context_8": "planners curators",
    "sgcool_label_text": "Johnny Manahan’s Choose (1982) is probably the earliest surviving video artwork from the Philippines and the last artwork made Manahan made before completely devoting himself to his work in television. The video is historically and culturally significant for Philippine art and is probably among the earliest video works in Southeast Asia. The video is a self-reflexive commentary on the medium of video and television."
  },
  "nlpDate": "20201120223708",
  "connectorId": 0,
  "tags": {}
}