{"id":"2017-01033-003","title":"Series of six carte de visite portraits by August Sachtler Photograph of  Sultan Hamengkubowono VI of Yogyakarta","source":"Bumblebee","path":"./Data/json/","content":"accession_no_csv:2017-01033-003\nImage:\nobject_work_type:black-and-white photographs photographs\ntitle_text:Series of six carte de visite portraits by August Sachtler Photograph of  Sultan Hamengkubowono VI of Yogyakarta\npreference:alternate main\ntitle_language:\ncreator_2:August Sachtler of Sachtler \\u0026 Co.\ncreator_role:photographers\ncreation_date:1860s\ncreation_place_original_location:Singapore\ninscriptions:\ninscription_language:\nshape:rectangular\nmaterials_name:paper (fiber product)\ntechniques_name:photographic processes\nobject_colour:black-and-white (colors)\nphysical_appearance:This is a black-and-white portrait photograph. It features a man\n dressed in elaborately designed attire\n with wrap cloth and hat. He is wearing several accessories around his neck\n and is seated on a raised platform. He is facing forward\n with his hands on his knees. The photograph is quite faded and stained. There are no inscriptions\n tears\n or folds seen.\nsubject_terms_1:indigenous people ways of life folk costume kings (people) portraits\nsubject_terms_2:Carte de visite photographs Portrait photography Indigenous people Lifestyles Ethnic costume Sultans\nsubject_terms_3:Portrait photography Ethnic costumes\nsubject_terms_4:\nsgcool_label_text:\\This is part of a series of small carte de visite format portrait photographs by August Sachtler\n a German photographer who started photographing in Singapore in the early 1860s. The studio details inscribed on the back of these cartes de visite read \\\\A. Sachtler in Singapore\\\\","createdDate":"20201018182636","version":0,"latest":false,"roles":[],"metadata":{"accession_no_csv":"2017-01033-003","Image":"","object_work_type":"black-and-white photographs photographs","title_text":"Series of six carte de visite portraits by August Sachtler Photograph of  Sultan Hamengkubowono VI of Yogyakarta","preference":"alternate main","title_language":"","creator_2":"August Sachtler of Sachtler \u0026 Co.","creator_role":"photographers","creation_date":"1860s","creation_place_original_location":"Singapore","inscriptions":"","inscription_language":"","shape":"rectangular","materials_name":"paper (fiber product)","techniques_name":"photographic processes","object_colour":"black-and-white (colors)","physical_appearance":"This is a black-and-white portrait photograph. It features a man, dressed in elaborately designed attire, with wrap cloth and hat. He is wearing several accessories around his neck, and is seated on a raised platform. He is facing forward, with his hands on his knees. The photograph is quite faded and stained. There are no inscriptions, tears, or folds seen.","subject_terms_1":"indigenous people ways of life folk costume kings (people) portraits","subject_terms_2":"Carte de visite photographs Portrait photography Indigenous people Lifestyles Ethnic costume Sultans","subject_terms_3":"Portrait photography Ethnic costumes","subject_terms_4":"","sgcool_label_text":"\"This is part of a series of small carte de visite format portrait photographs by August Sachtler, a German photographer who started photographing in Singapore in the early 1860s. The studio details inscribed on the back of these cartes de visite read \"\"A. Sachtler in Singapore\"\""},"nlpDate":"20201018182636","connectorId":0,"tags":{}}