{
  "id": "2017-00501",
  "title": "Certificate from Mayfair School of Cosmetic Science and Manufacture",
  "source": "Bumblebee",
  "path": "./Data/json/",
  "content": "\n  accession_no_csv: 2017-00501\n\n  Image: \n\n  object_work_type: certificates\n\n  title_text: Certificate from Mayfair School of Cosmetic Science and Manufacture\n\n  preference: main\n\n  title_language: \n\n  creator_2: Mayfair School of Cosmetic Science and Manufacture ?\n\n  creator_role: administrators?\n\n  creation_date: 1955 6-Feb-55\n\n  creation_place_original_location: London (England)\n\n  inscriptions: \n\n  inscription_language: \n\n  shape: Rectangular\n\n  materials_name: paper (fiber product)\n\n  techniques_name: printing (process) writing (processes)\n\n  object_colour: black-and-white (colours)\n\n  physical_appearance: This is a certificate certifying Mrs Chong\\u0027s completion of a course in Cosmetic Chemistry at Mairfair School of Cosmetic Science and Manufacture. It was signed off by the director and teacher of cosmetic chemistry.\n\n  subject_terms_1: education science (modern discipline) certification\n\n  subject_terms_2: Education certification Science\n\n  subject_terms_3: Education\n\n  sgcool_label_text: This certificate from Mayfair School of Cosmetic Science and Manufacture was awarded to Mrs Florence Chong (nee Wong Chit Moy) on 6 February 1955. Mrs Florence Chong was the seventh sister of prominent local bridal designer Mrs Sylvia Kho (nee Wong Sien Moy). She received training in make-up and hairstyling in London and provided her services to brides in Singapore as early as the 1950s.\n",
  "createdDate": "20201201203308",
  "version": 0,
  "latest": false,
  "roles": [],
  "metadata": {
    "accession_no_csv": "2017-00501",
    "Image": "",
    "object_work_type": "certificates",
    "title_text": "Certificate from Mayfair School of Cosmetic Science and Manufacture",
    "preference": "main",
    "title_language": "",
    "creator_2": "Mayfair School of Cosmetic Science and Manufacture ?",
    "creator_role": "administrators?",
    "creation_date": "1955 6-Feb-55",
    "creation_place_original_location": "London (England)",
    "inscriptions": "",
    "inscription_language": "",
    "shape": "Rectangular",
    "materials_name": "paper (fiber product)",
    "techniques_name": "printing (process) writing (processes)",
    "object_colour": "black-and-white (colours)",
    "physical_appearance": "This is a certificate certifying Mrs Chong\u0027s completion of a course in Cosmetic Chemistry at Mairfair School of Cosmetic Science and Manufacture. It was signed off by the director and teacher of cosmetic chemistry.",
    "subject_terms_1": "education science (modern discipline) certification",
    "subject_terms_2": "Education certification Science",
    "subject_terms_3": "Education",
    "sgcool_label_text": "This certificate from Mayfair School of Cosmetic Science and Manufacture was awarded to Mrs Florence Chong (nee Wong Chit Moy) on 6 February 1955. Mrs Florence Chong was the seventh sister of prominent local bridal designer Mrs Sylvia Kho (nee Wong Sien Moy). She received training in make-up and hairstyling in London and provided her services to brides in Singapore as early as the 1950s."
  },
  "nlpDate": "20201201203308",
  "connectorId": 0,
  "tags": {}
}