{
  "id": "2017-00103",
  "title": "Secret Service at the Foot of Bukit Segari",
  "source": "Bumblebee",
  "path": "./Data/json/",
  "content": "\n  accession_no_csv: 2017-00103\n\n  Image: \n\n  object_work_type: paintings (visual works)\n\n  title_text: Secret Service at the Foot of Bukit Segari\n\n  preference: main alternate\n\n  title_language: \n\n  creator_2: Tan Chong Tee\n\n  creator_1: Chen\n Chongzhi\n 1916-\n\n  creator_role: artists (visual artists)\n\n  creation_date: 2000\n\n  creation_place_original_location: Singapore\n\n  inscriptions: \n\n  inscription_language: \n\n  shape: rectangular\n\n  materials_name: paper (fiber product) gouache (paint)\n\n  techniques_name: painting (image-making)\n\n  object_colour: multicolored\n\n  physical_appearance: This is a landscape painting of the secret service camp at the foot of Bukit Segari. It features a few roofed structures and a clothing line at the bottom right of the painting. The left and foreground of the painting shows a hill with several trees. The camp looks nestled within a forested area. There is a Chinese inscription on the bottom-left of the painting.\n\n  subject_terms_1: depictions (visual works) resistance movements world wars spies (people) army camps\n\n  subject_terms_2: World War\n 1939-1945 Painting Chen\n Chongzhi\n 1916- Great Britain. Army. Force 136 Espionage Force 136 (Guerilla movement) Military training camps Perak (Malaysia)\n\n  subject_terms_3: Painting 1942-1945 Japanese occupation Tan\n Chong Tee Force 136 (Guerilla movement)\n\n  subject_terms_4: \n\n  sgcool_label_text: This drawing belongs to part of a collection of artefacts related to the World War II underground resistance movement known as Force 136. The collection of materials was gathered by Tan Chong Tee (1916- 2012)\n who was a key member of this resistance group. The collection consists of original materials belonging to Tan and other members of Force 136 dating from the 1940s to new materials reproduced from memory by Tan Chong Tee\n which date from mid 1990s to early 2000s. \\r\\n\\r\\nForce 136 was set up in July 1942 as part of the British Special Operations Executive (SOE). It recruited and trained local guerrillas to gather intelligence and create an underground spy network to support planned British invasion of Japanese-occupied Malaya.\\r\\n\\r\\nThis drawing is a later rendition of the secret service camp at the foot of Bukit Segari Camp Ground by Tan Chong Tee. \\r\\n\n",
  "createdDate": "20201125084529",
  "version": 0,
  "latest": false,
  "roles": [],
  "metadata": {
    "accession_no_csv": "2017-00103",
    "Image": "",
    "object_work_type": "paintings (visual works)",
    "title_text": "Secret Service at the Foot of Bukit Segari",
    "preference": "main alternate",
    "title_language": "",
    "creator_2": "Tan Chong Tee",
    "creator_1": "Chen, Chongzhi, 1916-",
    "creator_role": "artists (visual artists)",
    "creation_date": "2000",
    "creation_place_original_location": "Singapore",
    "inscriptions": "",
    "inscription_language": "",
    "shape": "rectangular",
    "materials_name": "paper (fiber product) gouache (paint)",
    "techniques_name": "painting (image-making)",
    "object_colour": "multicolored",
    "physical_appearance": "This is a landscape painting of the secret service camp at the foot of Bukit Segari. It features a few roofed structures and a clothing line at the bottom right of the painting. The left and foreground of the painting shows a hill with several trees. The camp looks nestled within a forested area. There is a Chinese inscription on the bottom-left of the painting.",
    "subject_terms_1": "depictions (visual works) resistance movements world wars spies (people) army camps",
    "subject_terms_2": "World War, 1939-1945 Painting Chen, Chongzhi, 1916- Great Britain. Army. Force 136 Espionage Force 136 (Guerilla movement) Military training camps Perak (Malaysia)",
    "subject_terms_3": "Painting 1942-1945 Japanese occupation Tan, Chong Tee Force 136 (Guerilla movement)",
    "subject_terms_4": "",
    "sgcool_label_text": "This drawing belongs to part of a collection of artefacts related to the World War II underground resistance movement known as Force 136. The collection of materials was gathered by Tan Chong Tee (1916- 2012), who was a key member of this resistance group. The collection consists of original materials belonging to Tan and other members of Force 136 dating from the 1940s to new materials reproduced from memory by Tan Chong Tee, which date from mid 1990s to early 2000s. \r\n\r\nForce 136 was set up in July 1942 as part of the British Special Operations Executive (SOE). It recruited and trained local guerrillas to gather intelligence and create an underground spy network to support planned British invasion of Japanese-occupied Malaya.\r\n\r\nThis drawing is a later rendition of the secret service camp at the foot of Bukit Segari Camp Ground by Tan Chong Tee. \r\n"
  },
  "nlpDate": "20201125084529",
  "connectorId": 0,
  "tags": {}
}