{
  "id": "2017-00373",
  "title": "Kain panjang",
  "source": "Bumblebee",
  "path": "./Data/json/",
  "content": "\n  accession_no_csv: 2017-00373\n\n  Image: \n\n  object_work_type: folk costume batik art\n\n  title_text: Kain panjang\n\n  preference: main\n\n  title_language: \n\n  creator_2: Jane Hendromartono\n\n  creator_role: textile designers\n\n  creation_date: 1950-1980s\n\n  creation_place_original_location: Pekalongan (Indonesia)\n\n  styles_periods_indexing_terms: Peranakan\n\n  inscriptions: \n\n  inscription_language: \n\n  shape: rectangular\n\n  materials_name: cotton (textile)\n\n  techniques_name: batik\n\n  object_colour: multicolored\n\n  physical_appearance: This is a batik kain panjang. It features two different but related designs on each half of the batik. The left side of the batik features flowering branches emerging from wave-like rocks amidst fishes and birds. The right side of the batik features flower blooms against a set of oddly-shaped rice kernels. The right side is also set against a more densely decorated background filled with geometric shapes. There is a signature on the top-left of the batik kain panjang.\n\n  subject_terms_1: Peranakan flower (motif) birds (motifs) cultural diffusion\n\n  subject_terms_2: Batik Ethnic costume Peranakan (Asian people) Motifs Culture diffusion\n\n  subject_terms_3: Batik Peranakan costumes\n\n  sgcool_label_text: This kain panjang is structured in the pagi-sore format\n comprising two different but related designs on each half of the batik.  Flowering branches emerge from wave-like rocks amidst fishes and birds on one half of the cloth.  On the other half\n blooms and lanterns are set against a background of oddly-shaped rice kernels.  This batik comes from the family collection of Oey Djien Nio (1929-1987)\n the last in three generations of documented batik-makers in Pekalongan.  In her earlier signatures\n she used her husband’s name\n Liem Siok Hien.  But from 1965 onwards\n she used Jane Hendromartono\n combining her husband’s new Indonesian family name\n Hendromartono with Jane\n as people addressed her by.  She developed a personal style distinct from her mother and grandmother\n and experimented with a wide spectrum of colours and exotic combinations of birds\n rock formations and mythical animals.  Jane Hendromartono’s clientele expanded beyond the elite in Indonesia to include Europe\n America and Japan\n especially in the 1980s.\n",
  "createdDate": "20201120223708",
  "version": 0,
  "latest": false,
  "roles": [],
  "metadata": {
    "accession_no_csv": "2017-00373",
    "Image": "",
    "object_work_type": "folk costume batik art",
    "title_text": "Kain panjang",
    "preference": "main",
    "title_language": "",
    "creator_2": "Jane Hendromartono",
    "creator_role": "textile designers",
    "creation_date": "1950-1980s",
    "creation_place_original_location": "Pekalongan (Indonesia)",
    "styles_periods_indexing_terms": "Peranakan",
    "inscriptions": "",
    "inscription_language": "",
    "shape": "rectangular",
    "materials_name": "cotton (textile)",
    "techniques_name": "batik",
    "object_colour": "multicolored",
    "physical_appearance": "This is a batik kain panjang. It features two different but related designs on each half of the batik. The left side of the batik features flowering branches emerging from wave-like rocks amidst fishes and birds. The right side of the batik features flower blooms against a set of oddly-shaped rice kernels. The right side is also set against a more densely decorated background filled with geometric shapes. There is a signature on the top-left of the batik kain panjang.",
    "subject_terms_1": "Peranakan flower (motif) birds (motifs) cultural diffusion",
    "subject_terms_2": "Batik Ethnic costume Peranakan (Asian people) Motifs Culture diffusion",
    "subject_terms_3": "Batik Peranakan costumes",
    "sgcool_label_text": "This kain panjang is structured in the pagi-sore format, comprising two different but related designs on each half of the batik.  Flowering branches emerge from wave-like rocks amidst fishes and birds on one half of the cloth.  On the other half, blooms and lanterns are set against a background of oddly-shaped rice kernels.  This batik comes from the family collection of Oey Djien Nio (1929-1987), the last in three generations of documented batik-makers in Pekalongan.  In her earlier signatures, she used her husband’s name, Liem Siok Hien.  But from 1965 onwards, she used Jane Hendromartono, combining her husband’s new Indonesian family name, Hendromartono with Jane, as people addressed her by.  She developed a personal style distinct from her mother and grandmother, and experimented with a wide spectrum of colours and exotic combinations of birds, rock formations and mythical animals.  Jane Hendromartono’s clientele expanded beyond the elite in Indonesia to include Europe, America and Japan, especially in the 1980s."
  },
  "nlpDate": "20201120223708",
  "connectorId": 0,
  "tags": {}
}