{"id":"2017-00132","title":"Tan Chong Tee Collection: Certificate of Incompletion of Studies ?????","source":"Bumblebee","path":"./Data/json/","content":"accession_no_csv:2017-00132\nImage:\nobject_work_type:certificates\ntitle_text:Tan Chong Tee Collection: Certificate of Incompletion of Studies ?????\npreference:main alternate\ntitle_language:\ncreation_date:1940s\ncreation_place_original_location:Singapore\ninscriptions:\ninscription_language:\nshape:rectangular\nmaterials_name:paper (fiber product)\ntechniques_name:printing (process)\nobject_colour:multicolored\nphysical_appearance:This is a document certifying the incompletion of studies. It is printed in orange and blank ink. There is a red stamp on the left of the document\n and a blue inscription underneath it. The certificate has tape marks along the vertical and horizontal center\n nad a taped section on the bottom left. The document is quite torn and folded\n especially along the edges.\nsubject_terms_1:world wars resistance movements documents (object genre) Chinese scripts\nsubject_terms_2:Certification World War\n 1939-1945 Great Britain. Army. Force 136 Force 136 (Guerilla movement) Chen\n Chongzhi\n 1916-\nsubject_terms_3:Force 136 (Guerilla movement) Tan\n Chong Tee 1942-1945 Japanese occupation\nsubject_terms_4:\ncontext_1:World War\n 1939-1945 1942-1945 Japanese Occupation\ncontext_2:world wars occupations (armed conflicts)\ncontext_3:1939-1945 1942-1945\ncontext_4:1939 1942\ncontext_5:1945 1945\ncontext_6:Malaya Singapore\ncontext_7:Great Britain. Army. Force 136\ncontext_8:armed forces\nsgcool_label_text:This certificate belongs to part of a collection of artefacts related to the World War II underground resistance movement known as Force 136. The collection of materials was gathered by Tan Chong Tee (1916- 2012)\n who was a key member of this resistance group. The collection consists of original materials belonging to Tan and other members of Force 136 dating from the 1940s to new materials reproduced from memory by Tan Chong Tee\n which date from the late 1980s to early 2000s. \\r\\n\\r\\nForce 136 was set up in July 1942 as part of the British Special Operations Executive (SOE). It recruited and trained local guerillas to gather intelligence and create an underground spy network to support planned British invasion of Japanese-occupied Malaya.\\r\\n","createdDate":"20201018182636","version":0,"latest":false,"roles":[],"metadata":{"accession_no_csv":"2017-00132","Image":"","object_work_type":"certificates","title_text":"Tan Chong Tee Collection: Certificate of Incompletion of Studies ?????","preference":"main alternate","title_language":"","creation_date":"1940s","creation_place_original_location":"Singapore","inscriptions":"","inscription_language":"","shape":"rectangular","materials_name":"paper (fiber product)","techniques_name":"printing (process)","object_colour":"multicolored","physical_appearance":"This is a document certifying the incompletion of studies. It is printed in orange and blank ink. There is a red stamp on the left of the document, and a blue inscription underneath it. The certificate has tape marks along the vertical and horizontal center, nad a taped section on the bottom left. The document is quite torn and folded, especially along the edges.","subject_terms_1":"world wars resistance movements documents (object genre) Chinese scripts","subject_terms_2":"Certification World War, 1939-1945 Great Britain. Army. Force 136 Force 136 (Guerilla movement) Chen, Chongzhi, 1916-","subject_terms_3":"Force 136 (Guerilla movement) Tan, Chong Tee 1942-1945 Japanese occupation","subject_terms_4":"","context_1":"World War, 1939-1945 1942-1945 Japanese Occupation","context_2":"world wars occupations (armed conflicts)","context_3":"1939-1945 1942-1945","context_4":"1939 1942","context_5":"1945 1945","context_6":"Malaya Singapore","context_7":"Great Britain. Army. Force 136","context_8":"armed forces","sgcool_label_text":"This certificate belongs to part of a collection of artefacts related to the World War II underground resistance movement known as Force 136. The collection of materials was gathered by Tan Chong Tee (1916- 2012), who was a key member of this resistance group. The collection consists of original materials belonging to Tan and other members of Force 136 dating from the 1940s to new materials reproduced from memory by Tan Chong Tee, which date from the late 1980s to early 2000s. \r\n\r\nForce 136 was set up in July 1942 as part of the British Special Operations Executive (SOE). It recruited and trained local guerillas to gather intelligence and create an underground spy network to support planned British invasion of Japanese-occupied Malaya.\r\n"},"nlpDate":"20201018182636","connectorId":0,"tags":{}}