{"id":"2017-00270 (001 to 004)","title":"Blue and white covered boxes","source":"Bumblebee","path":"./Data/json/","content":"accession_no_csv:2017-00270 (001 to 004)\nImage:\nobject_work_type:porcelain (visual works)  Ceramics (object genre)  containers (receptacles)\ntitle_text:Blue and white covered boxes\npreference:main\ntitle_language:\ncreation_date:Late Ming dynasty\n 17th century\ncreation_place_original_location:Fujian Sheng (China)\nstyles_periods_indexing_terms:Chinese ceramics styles  Ming (culture\n period\n and styles)  Chinese export (ceramics style)\ninscriptions:\ninscription_language:\nshape:concave\nmaterials_name:blue-and-white (ceramic glaze) porcelain (material)  cobalt blue (pigment)  clay  ceramic glaze\ntechniques_name:glazing (coating process)  throwing (pottery techniques)  underglazing molding (forming)  firing (technique)  porcelain painting (image-making) freehand drawing (technique)\nobject_colour:multicoloured\nphysical_appearance:This is a pair of Ming blue white covered boxes. The central medallion of each lid is decorated with a large peony blossom\n and its curved rim is covered with cartouches of flowering shrubs. The exterior of its lower base is is also decorated with floral motifs.\nsubject_terms_1:Paeonia (genus)  porcelain paintings (visual works)  symbolism  freehand drawings (drawings)  floral patterns\nsubject_terms_2:Porcelain\n Chinese Ming- Qing dynasties\n 1368-1912 Blue and white ware  China Peonies Flowering shrubs China painting\nsubject_terms_3:visual arts  Decorative arts Ceramics\nsubject_terms_4:\ncontext_1:The dish was exhibited in the Exhibition of Chinese Blue-and-White Ceramics exhibition held at the National Museum of Singapore in April 1978. It is featured as number 156 in the exhibition catalogue. They are featured as number 131 and 132 in the exhibition catalogue.\ncontext_2:exhibitions (events)\ncontext_3:Apr-78\ncontext_4:18-Apr-78\ncontext_5:18-Apr-78\ncontext_6:National Museum of Singapore\ncontext_7:National Museum (Singapore)\ncontext_8:planners curators\nsgcool_label_text:The pair of circular boxes have covers which are decorated with a peony blossom at the centre\n surrounded by flowering shrubs in four bracketed panels. Covered ceramic boxes from China have been found in large quantities in Southeast Asia\n and were most probably used to store incense\n cosmetics or medicines. \\r\\nAlthough the decorative style of arranging designs into panels is generally associated with Kraak porcelain produced at Jingdezhen\n it was also adopted by the Fujian potters at Zhangzhou. The relatively thick bodies\n off-white glaze colour and more spontaneously-rendered decoration\n suggests that the boxes were probably made at the Zhangzhou kilns. Boxes are unusual among extant examples of Zhangzhou wares\n making this pair an important addition to the museum’s collection of Zhangzhou ceramics. \\r\\n","createdDate":"20201119143406","version":0,"latest":false,"roles":[],"metadata":{"accession_no_csv":"2017-00270 (001 to 004)","Image":"","object_work_type":"porcelain (visual works)  Ceramics (object genre)  containers (receptacles)","title_text":"Blue and white covered boxes","preference":"main","title_language":"","creation_date":"Late Ming dynasty, 17th century","creation_place_original_location":"Fujian Sheng (China)","styles_periods_indexing_terms":"Chinese ceramics styles  Ming (culture, period, and styles)  Chinese export (ceramics style)","inscriptions":"","inscription_language":"","shape":"concave","materials_name":"blue-and-white (ceramic glaze) porcelain (material)  cobalt blue (pigment)  clay  ceramic glaze","techniques_name":"glazing (coating process)  throwing (pottery techniques)  underglazing molding (forming)  firing (technique)  porcelain painting (image-making) freehand drawing (technique)","object_colour":"multicoloured","physical_appearance":"This is a pair of Ming blue white covered boxes. The central medallion of each lid is decorated with a large peony blossom, and its curved rim is covered with cartouches of flowering shrubs. The exterior of its lower base is is also decorated with floral motifs.","subject_terms_1":"Paeonia (genus)  porcelain paintings (visual works)  symbolism  freehand drawings (drawings)  floral patterns","subject_terms_2":"Porcelain, Chinese Ming- Qing dynasties, 1368-1912 Blue and white ware  China Peonies Flowering shrubs China painting","subject_terms_3":"visual arts  Decorative arts Ceramics","subject_terms_4":"","context_1":"The dish was exhibited in the Exhibition of Chinese Blue-and-White Ceramics exhibition held at the National Museum of Singapore in April 1978. It is featured as number 156 in the exhibition catalogue. They are featured as number 131 and 132 in the exhibition catalogue.","context_2":"exhibitions (events)","context_3":"Apr-78","context_4":"18-Apr-78","context_5":"18-Apr-78","context_6":"National Museum of Singapore","context_7":"National Museum (Singapore)","context_8":"planners curators","sgcool_label_text":"The pair of circular boxes have covers which are decorated with a peony blossom at the centre, surrounded by flowering shrubs in four bracketed panels. Covered ceramic boxes from China have been found in large quantities in Southeast Asia, and were most probably used to store incense, cosmetics or medicines. \r\nAlthough the decorative style of arranging designs into panels is generally associated with Kraak porcelain produced at Jingdezhen, it was also adopted by the Fujian potters at Zhangzhou. The relatively thick bodies, off-white glaze colour and more spontaneously-rendered decoration, suggests that the boxes were probably made at the Zhangzhou kilns. Boxes are unusual among extant examples of Zhangzhou wares, making this pair an important addition to the museum’s collection of Zhangzhou ceramics. \r\n"},"nlpDate":"20201119143406","connectorId":0,"tags":{}}