{"id":"2017-00837","title":"Candle holder","source":"Bumblebee","path":"./Data/json/","content":"accession_no_csv:2017-00837\nImage:\nobject_work_type:candle holder  porcelain (visual works)\ntitle_text:Candle holder\npreference:main\ntitle_language:\ncreator_2:Hans Tan\ncreator_role:designers\ncreation_date:2012\ncreation_place_original_location:Singapore\nstyles_periods_indexing_terms:Contemporary (style of art)\ninscriptions:\ninscription_language:\nshape:irregular ?\nmaterials_name:porcelain (material)  clay ceramic glaze\ntechniques_name:sandblasting  glazing (coating process)  throwing (pottery techniques)  molding (forming)  firing (technique)\nobject_colour:multicoloured\nphysical_appearance:This is a candle holder decorated with a dotted design. These are multicoloured dots on a white porcelain base. They each capture glimpses / parts of a floral and foliage decorative scheme.\nsubject_terms_1:Peranakan  altar components  religious objects commissions (orders for works)\nsubject_terms_2:Batik  Contemporary art  Geometry in art Reinterpreting history  Porcelain\n Peranakan  Peranakan (Asian people)\nsubject_terms_3:Decorative arts  Religious life and practices\nsgcool_label_text:This candle holder is one of the five porcelain wares from the award-winning “Spotted Nyonya” series by Singaporean designer\n Hans Tan.  This series is a contemporary take on traditional Peranakan porcelain or nyonyaware.  Hans Tan was inspired by batik\n particularly the resist-dyeing technique\n to transform the surface of these wares.  Original glazed portions are preserved in the form of a new dotted pattern while the white porcelain body is revealed after sandblasting away and erasing the original glaze on these pieces.  The combination of green and pink polychrome colours or dots on the original decoration of these pieces are typical of nyonyaware.  Motifs commonly found on nyonyaware would include realistically depicted birds and insects amongst floral sprays.","createdDate":"20201018182636","version":0,"latest":false,"roles":[],"metadata":{"accession_no_csv":"2017-00837","Image":"","object_work_type":"candle holder  porcelain (visual works)","title_text":"Candle holder","preference":"main","title_language":"","creator_2":"Hans Tan","creator_role":"designers","creation_date":"2012","creation_place_original_location":"Singapore","styles_periods_indexing_terms":"Contemporary (style of art)","inscriptions":"","inscription_language":"","shape":"irregular ?","materials_name":"porcelain (material)  clay ceramic glaze","techniques_name":"sandblasting  glazing (coating process)  throwing (pottery techniques)  molding (forming)  firing (technique)","object_colour":"multicoloured","physical_appearance":"This is a candle holder decorated with a dotted design. These are multicoloured dots on a white porcelain base. They each capture glimpses / parts of a floral and foliage decorative scheme.","subject_terms_1":"Peranakan  altar components  religious objects commissions (orders for works)","subject_terms_2":"Batik  Contemporary art  Geometry in art Reinterpreting history  Porcelain, Peranakan  Peranakan (Asian people)","subject_terms_3":"Decorative arts  Religious life and practices","sgcool_label_text":"This candle holder is one of the five porcelain wares from the award-winning “Spotted Nyonya” series by Singaporean designer, Hans Tan.  This series is a contemporary take on traditional Peranakan porcelain or nyonyaware.  Hans Tan was inspired by batik, particularly the resist-dyeing technique, to transform the surface of these wares.  Original glazed portions are preserved in the form of a new dotted pattern while the white porcelain body is revealed after sandblasting away and erasing the original glaze on these pieces.  The combination of green and pink polychrome colours or dots on the original decoration of these pieces are typical of nyonyaware.  Motifs commonly found on nyonyaware would include realistically depicted birds and insects amongst floral sprays."},"nlpDate":"20201018182636","connectorId":0,"tags":{}}