{"id":"2017-00184-010","title":"Lim Hong Pei Collection: Photographs  ????? Lim Hong Pei Collection: group of soldiers","source":"Bumblebee","path":"./Data/json/","content":"accession_no_csv:2017-00184-010\nImage:\nobject_work_type:black-and-white photographs\ntitle_text:Lim Hong Pei Collection: Photographs  ????? Lim Hong Pei Collection: group of soldiers\npreference:alternate alternate main\ntitle_language:\ncreation_date:1940s\ncreation_place_original_location:Singapore\ninscriptions:\ninscription_language:\nshape:rectangular\nmaterials_name:paper (fiber product)\ntechniques_name:photographic processes\nobject_colour:black-and-white (colors)\nphysical_appearance:This is a black-and-white photograph of a group of five men. Three of them are seated while two of them are standing behind them. The man in the center is wearing a darker military uniform. The others are wearing a light collared shirt. The photograph is faded and torn\n especially near the bottom of the photograph.\nsubject_terms_1:world wars resistance movements soldiers group portraits\nsubject_terms_2:World War\n 1939-1945 Great Britain. Army. Force 136 Force 136 (Guerilla movement) Lim\n Hong Pei\n 1922- Portraits\n group Soldiers\nsubject_terms_3:Force 136 (Guerilla movement) 1942-1945 Japanese occupation Photography war personalities\nsubject_terms_4:\ncontext_1:World War\n 1939-1945 1942-1945 Japanese Occupation\ncontext_2:world wars occupations (armed conflicts)\ncontext_3:1939-1945 1942-1945\ncontext_4:1939 1942\ncontext_5:1945 1945\ncontext_6:Malaya Singapore\ncontext_7:Great Britain. Army. Force 136\ncontext_8:armed forces\nsgcool_label_text:These photographs belong to part of a collection of artefacts related to the World War II underground resistance movement known as Force 136. The collection of materials was gathered by Tan Chong Tee (1916- 2012)\n who was a key member of this resistance group. The collection consists of original materials belonging to Tan and other members of Force 136 dating from the 1940s to new materials reproduced from memory by Tan Chong Tee\n which date from the late 1980s to early 2000s. \\r\\n\\r\\nForce 136 was set up in July 1942 as part of the British Special Operations Executive (SOE). It recruited and trained local guerillas to gather intelligence and create an underground spy network to support planned British invasion of Japanese-occupied Malaya.","createdDate":"20201119143406","version":0,"latest":false,"roles":[],"metadata":{"accession_no_csv":"2017-00184-010","Image":"","object_work_type":"black-and-white photographs","title_text":"Lim Hong Pei Collection: Photographs  ????? Lim Hong Pei Collection: group of soldiers","preference":"alternate alternate main","title_language":"","creation_date":"1940s","creation_place_original_location":"Singapore","inscriptions":"","inscription_language":"","shape":"rectangular","materials_name":"paper (fiber product)","techniques_name":"photographic processes","object_colour":"black-and-white (colors)","physical_appearance":"This is a black-and-white photograph of a group of five men. Three of them are seated while two of them are standing behind them. The man in the center is wearing a darker military uniform. The others are wearing a light collared shirt. The photograph is faded and torn, especially near the bottom of the photograph.","subject_terms_1":"world wars resistance movements soldiers group portraits","subject_terms_2":"World War, 1939-1945 Great Britain. Army. Force 136 Force 136 (Guerilla movement) Lim, Hong Pei, 1922- Portraits, group Soldiers","subject_terms_3":"Force 136 (Guerilla movement) 1942-1945 Japanese occupation Photography war personalities","subject_terms_4":"","context_1":"World War, 1939-1945 1942-1945 Japanese Occupation","context_2":"world wars occupations (armed conflicts)","context_3":"1939-1945 1942-1945","context_4":"1939 1942","context_5":"1945 1945","context_6":"Malaya Singapore","context_7":"Great Britain. Army. Force 136","context_8":"armed forces","sgcool_label_text":"These photographs belong to part of a collection of artefacts related to the World War II underground resistance movement known as Force 136. The collection of materials was gathered by Tan Chong Tee (1916- 2012), who was a key member of this resistance group. The collection consists of original materials belonging to Tan and other members of Force 136 dating from the 1940s to new materials reproduced from memory by Tan Chong Tee, which date from the late 1980s to early 2000s. \r\n\r\nForce 136 was set up in July 1942 as part of the British Special Operations Executive (SOE). It recruited and trained local guerillas to gather intelligence and create an underground spy network to support planned British invasion of Japanese-occupied Malaya."},"nlpDate":"20201119143406","connectorId":0,"tags":{}}