{"id":"2017-00302-026","title":"Miscellaneous scraps of paper from P.O.W James Steele Archives (30 pieces) P.O.W. James Steele Archives: Fifty cents Japanese banana money","source":"Bumblebee","path":"./Data/json/","content":"accession_no_csv:2017-00302-026\nImage:\nobject_work_type:currencies (systems of money)\ntitle_text:Miscellaneous scraps of paper from P.O.W James Steele Archives (30 pieces) P.O.W. James Steele Archives: Fifty cents Japanese banana money\npreference:alternate main\ntitle_language:\ncreation_date:1941-1945\ncreation_place_original_location:Singapore\ninscriptions:\ninscription_language:\nshape:rectangular\nmaterials_name:paper (fiber product)\ntechniques_name:printing (process)\nobject_colour:multicolored\nphysical_appearance:This is a fifty cent Japanese government currency. The note is printed in reddish-brown ink. The number \\u002750\\u0027 is printed on the four corners of the note. The words in the center are in capitals. The currency features a large banana tree on the right side. There are some kanji inscriptions along the bottom of the note. The note is quite worn out\n with some tears and folds around the edges.\nsubject_terms_1:world wars prisoners of war occupation currency Kanji (writing system)\nsubject_terms_2:World War\n 1939-1945 Prisoners of war Money Occupation currency\n Japanese Kanji\nsubject_terms_3:war personalities 1942-1945 Japanese occupation\nsubject_terms_4:\ncontext_1:World War\n 1939-1945 1942-1945 Japanese Occupation\ncontext_2:world wars occupations (armed conflicts)\ncontext_3:1939-1945 1942-1945\ncontext_4:1939 1942\ncontext_5:1945 1945\ncontext_6:Malaya Singapore\ncontext_7:Great Britain. Army. Royal Field Artillery\ncontext_8:armed forces\nsgcool_label_text:Loose papers from the James Steele\n P.O.W archive that include a symbolic drawing\n Japanese banana money\n map of camp\n administrative papers from Changi prison pre-dating internment\n list of soldiers of a regiment as well as James Steele’s warrant to  join the army. These papers are part of the archive of James Steele\n Royal Artillery (Field) who served in Malaya from January 1941-February 1942\n when interned as a P.O.W at Changi until his release in October 1945.","createdDate":"20201018182636","version":0,"latest":false,"roles":[],"metadata":{"accession_no_csv":"2017-00302-026","Image":"","object_work_type":"currencies (systems of money)","title_text":"Miscellaneous scraps of paper from P.O.W James Steele Archives (30 pieces) P.O.W. James Steele Archives: Fifty cents Japanese banana money","preference":"alternate main","title_language":"","creation_date":"1941-1945","creation_place_original_location":"Singapore","inscriptions":"","inscription_language":"","shape":"rectangular","materials_name":"paper (fiber product)","techniques_name":"printing (process)","object_colour":"multicolored","physical_appearance":"This is a fifty cent Japanese government currency. The note is printed in reddish-brown ink. The number \u002750\u0027 is printed on the four corners of the note. The words in the center are in capitals. The currency features a large banana tree on the right side. There are some kanji inscriptions along the bottom of the note. The note is quite worn out, with some tears and folds around the edges.","subject_terms_1":"world wars prisoners of war occupation currency Kanji (writing system)","subject_terms_2":"World War, 1939-1945 Prisoners of war Money Occupation currency, Japanese Kanji","subject_terms_3":"war personalities 1942-1945 Japanese occupation","subject_terms_4":"","context_1":"World War, 1939-1945 1942-1945 Japanese Occupation","context_2":"world wars occupations (armed conflicts)","context_3":"1939-1945 1942-1945","context_4":"1939 1942","context_5":"1945 1945","context_6":"Malaya Singapore","context_7":"Great Britain. Army. Royal Field Artillery","context_8":"armed forces","sgcool_label_text":"Loose papers from the James Steele, P.O.W archive that include a symbolic drawing, Japanese banana money, map of camp, administrative papers from Changi prison pre-dating internment, list of soldiers of a regiment as well as James Steele’s warrant to  join the army. These papers are part of the archive of James Steele, Royal Artillery (Field) who served in Malaya from January 1941-February 1942, when interned as a P.O.W at Changi until his release in October 1945."},"nlpDate":"20201018182636","connectorId":0,"tags":{}}