{
  "id": "2017-00425-001 to 007",
  "title": "Friesland Wall Clock",
  "source": "Bumblebee",
  "path": "./Data/json/",
  "content": "\n  accession_no_csv: 2017-00425-001 to 007\n\n  Image: \n\n  object_work_type: wall clocks\n\n  title_text: Friesland Wall Clock\n\n  preference: main\n\n  title_language: \n\n  creation_date: 1790\n\n  creation_place_original_location: Friesland (Netherlands) Netherlands\n\n  styles_periods_indexing_terms: Frisian (culture or style)\n\n  inscriptions: \n\n  inscription_language: \n\n  materials_name: wood (plant material) gilding (material) paint (coating)\n\n  techniques_name: gilding (technique) carving (processes) painting (image-making)\n\n  object_colour: multicoloured\n\n  physical_appearance: This is a wall clock and its body sits on four black rounded studs that rest on a wall bracket. Its overall decorative scheme includes paintings of vines\n flowers\n mermaids\n as well as carved and gilded vases\n cherub heads\n and scrolling vines in open metal work. The clock\\u0027s mechanisms can be seen via the glass panels on either side of the clock.\n\n  subject_terms_1: vine scrolls mermaids putti (motifs) mechanical clocks\n\n  subject_terms_2: Scrolls (Decorative arts) Malacca (Malacca\n Malaysia) Cherubs (Art) Mermaids\n\n  subject_terms_3: Furniture design\n\n  subject_terms_4: \n\n  sgcool_label_text: Elaborately painted and gilded clocks like this\n made in the northern province of Friesland in the Netherlands\n were popular in Dutch colonial port cities. They appear frequently in inventories of the estates of residents of Batavia and Malacca.\\r\\n\\r\\nThe clock body itself sits within a large wall bracket with canopy. Because the wall bracket was thought to resemble a seat for the clock\n the Dutch used the term “stoelklok” (stool clock) for them. \\r\\n\\r\\nThey are also called “Friesian” or “Frisian” clocks\n because of where they were made.\n",
  "createdDate": "20201125084520",
  "version": 0,
  "latest": false,
  "roles": [],
  "metadata": {
    "accession_no_csv": "2017-00425-001 to 007",
    "Image": "",
    "object_work_type": "wall clocks",
    "title_text": "Friesland Wall Clock",
    "preference": "main",
    "title_language": "",
    "creation_date": "1790",
    "creation_place_original_location": "Friesland (Netherlands) Netherlands",
    "styles_periods_indexing_terms": "Frisian (culture or style)",
    "inscriptions": "",
    "inscription_language": "",
    "materials_name": "wood (plant material) gilding (material) paint (coating)",
    "techniques_name": "gilding (technique) carving (processes) painting (image-making)",
    "object_colour": "multicoloured",
    "physical_appearance": "This is a wall clock and its body sits on four black rounded studs that rest on a wall bracket. Its overall decorative scheme includes paintings of vines, flowers, mermaids, as well as carved and gilded vases, cherub heads, and scrolling vines in open metal work. The clock\u0027s mechanisms can be seen via the glass panels on either side of the clock.",
    "subject_terms_1": "vine scrolls mermaids putti (motifs) mechanical clocks",
    "subject_terms_2": "Scrolls (Decorative arts) Malacca (Malacca, Malaysia) Cherubs (Art) Mermaids",
    "subject_terms_3": "Furniture design",
    "subject_terms_4": "",
    "sgcool_label_text": "Elaborately painted and gilded clocks like this, made in the northern province of Friesland in the Netherlands, were popular in Dutch colonial port cities. They appear frequently in inventories of the estates of residents of Batavia and Malacca.\r\n\r\nThe clock body itself sits within a large wall bracket with canopy. Because the wall bracket was thought to resemble a seat for the clock, the Dutch used the term “stoelklok” (stool clock) for them. \r\n\r\nThey are also called “Friesian” or “Frisian” clocks, because of where they were made."
  },
  "nlpDate": "20201125084520",
  "connectorId": 0,
  "tags": {}
}