{
  "id": "2017-00145-003",
  "title": "Reflections of Tan Chong Tee: Letters, Notes, and Photographs Reflections of Tan Chong Tee: Photograph taken at the farewell for Chinese liaison officers",
  "source": "Bumblebee",
  "path": "./Data/json/",
  "content": "\n  accession_no_csv: 2017-00145-003\n\n  Image: \n\n  object_work_type: black-and-white photographs photographs\n\n  title_text: Reflections of Tan Chong Tee: Letters\n Notes\n and Photographs Reflections of Tan Chong Tee: Photograph taken at the farewell for Chinese liaison officers\n\n  preference: alternate  main\n\n  title_language: \n\n  creation_place_original_location: Ipoh (Perak\n Malaysia)\n\n  inscriptions: \n\n  inscription_language: \n\n  shape: Rectangular\n\n  materials_name: paper (fiber product)\n\n  techniques_name: black-and-white photography  printing (process)\n\n  object_colour: black-and-white (colours)\n\n  physical_appearance: This is a commemorative group portrait taken in front of the Selangor Commercial Union. The event captured is a farewell for the liaison officers from China. The Kuomintang party symbol hangs beneath the union\\u0027s signboard.\n\n  subject_terms_1: group portraits  world wars resistance movements  guerilla warfare local histories officers (administrators) military officers  soldiers\n\n  subject_terms_2: Portraits\n Group Zhongguo guo min dang  War resistance movements  Guerillas  Local history Photographs  Farewells Chinese diaspora  Force 136 (Guerilla movement) Public officers  Chen\n Chongzhi\n 1916-  Great Britain. Army. Force 136 Allied Forces. Southeast Asia Command World War\n 1939-1945 Soldiers\n\n  subject_terms_3: Portrait photography  1942-1945 Japanese Occupation  Wars Force 136 (Guerilla movement) Tan\n Chong Tee Government officials  History  war personalities\n\n  context_1: 1942-1945 Japanese Occupation\n\n  context_2: occupations (armed conflicts)\n\n  context_3: 1942-1945\n\n  context_4: 1942\n\n  context_5: 1945\n\n  context_6: Singapore\n\n  context_7: Japan. Rikugun  Imperial Japanese Army\n\n  context_8: colonists\n\n  sgcool_label_text: These documents and photographs belong to a larger part of a collection of artefacts related to the World War II underground resistance movement known as Force 136. The collection of materials was gathered by Tan Chong Tee (1916- 2012)\n who was a key member of this resistance group. The collection consists of original materials belonging to Tan and other members of Force 136 dating from the 1940s to new materials reproduced from memory by Tan Chong Tee\n which date from the late 1980s to early 2000s. \\r\\n\\r\\nForce 136 was set up in July 1942 as part of the British Special Operations Executive (SOE). It recruited and trained local guerillas to gather intelligence and create an underground spy network to support planned British invasion of Japanese-occupied Malaya.\\r\\n\n",
  "createdDate": "20201120223707",
  "version": 0,
  "latest": false,
  "roles": [],
  "metadata": {
    "accession_no_csv": "2017-00145-003",
    "Image": "",
    "object_work_type": "black-and-white photographs photographs",
    "title_text": "Reflections of Tan Chong Tee: Letters, Notes, and Photographs Reflections of Tan Chong Tee: Photograph taken at the farewell for Chinese liaison officers",
    "preference": "alternate  main",
    "title_language": "",
    "creation_place_original_location": "Ipoh (Perak, Malaysia)",
    "inscriptions": "",
    "inscription_language": "",
    "shape": "Rectangular",
    "materials_name": "paper (fiber product)",
    "techniques_name": "black-and-white photography  printing (process)",
    "object_colour": "black-and-white (colours)",
    "physical_appearance": "This is a commemorative group portrait taken in front of the Selangor Commercial Union. The event captured is a farewell for the liaison officers from China. The Kuomintang party symbol hangs beneath the union\u0027s signboard.",
    "subject_terms_1": "group portraits  world wars resistance movements  guerilla warfare local histories officers (administrators) military officers  soldiers",
    "subject_terms_2": "Portraits, Group Zhongguo guo min dang  War resistance movements  Guerillas  Local history Photographs  Farewells Chinese diaspora  Force 136 (Guerilla movement) Public officers  Chen, Chongzhi, 1916-  Great Britain. Army. Force 136 Allied Forces. Southeast Asia Command World War, 1939-1945 Soldiers",
    "subject_terms_3": "Portrait photography  1942-1945 Japanese Occupation  Wars Force 136 (Guerilla movement) Tan, Chong Tee Government officials  History  war personalities",
    "context_1": "1942-1945 Japanese Occupation",
    "context_2": "occupations (armed conflicts)",
    "context_3": "1942-1945",
    "context_4": "1942",
    "context_5": "1945",
    "context_6": "Singapore",
    "context_7": "Japan. Rikugun  Imperial Japanese Army",
    "context_8": "colonists",
    "sgcool_label_text": "These documents and photographs belong to a larger part of a collection of artefacts related to the World War II underground resistance movement known as Force 136. The collection of materials was gathered by Tan Chong Tee (1916- 2012), who was a key member of this resistance group. The collection consists of original materials belonging to Tan and other members of Force 136 dating from the 1940s to new materials reproduced from memory by Tan Chong Tee, which date from the late 1980s to early 2000s. \r\n\r\nForce 136 was set up in July 1942 as part of the British Special Operations Executive (SOE). It recruited and trained local guerillas to gather intelligence and create an underground spy network to support planned British invasion of Japanese-occupied Malaya.\r\n"
  },
  "nlpDate": "20201120223707",
  "connectorId": 0,
  "tags": {}
}