{
  "id": "2017-00242",
  "title": "20 cards of strings of beads",
  "source": "Bumblebee",
  "path": "./Data/json/",
  "content": "\n  accession_no_csv: 2017-00242\n\n  Image: \n\n  object_work_type: beads (pierced objects)\n\n  title_text: 20 cards of strings of beads\n\n  preference: main\n\n  title_language: \n\n  creation_date: Not indicated\n\n  creation_place_original_location: Malacca (Malacca\n Malaysia) Singapore\n\n  styles_periods_indexing_terms: Peranakan\n\n  inscriptions: \n\n  inscription_language: \n\n  shape: irregular\n\n  object_colour: multicolored\n\n  physical_appearance: This is a set of 20 cards each containing strings of seed beads. There are four carrying green beads of various shades\n two with blue beads of various shades\n and the rest bearing beads of various colours.\n\n  subject_terms_1: Peranakan sewing tools tailors beadwork (visual works)\n\n  subject_terms_2: Beads Peranakan (Asian people) Sewing Equipment and supplies Tailors Clothing trade Bead embroidery\n\n  subject_terms_3: Vanishing trade Textile art and design\n\n  sgcool_label_text: Strings of seed beads used in nyonya needlework are hung on these 20 cardboard pieces. The presence of shop marks on the backs of some of the cards is also important in identifying the provenance of these materials. Handwritten labels indicating the sizes of strings of beads also useful show how beads were categorised by size. These beads show the variety of bead types available to embroiderers in Malacca and Singapore. The original owner of these items made a living fashioning beaded slippers and dresses\n working from home as she did not have a shop.\n",
  "createdDate": "20201120223707",
  "version": 0,
  "latest": false,
  "roles": [],
  "metadata": {
    "accession_no_csv": "2017-00242",
    "Image": "",
    "object_work_type": "beads (pierced objects)",
    "title_text": "20 cards of strings of beads",
    "preference": "main",
    "title_language": "",
    "creation_date": "Not indicated",
    "creation_place_original_location": "Malacca (Malacca, Malaysia) Singapore",
    "styles_periods_indexing_terms": "Peranakan",
    "inscriptions": "",
    "inscription_language": "",
    "shape": "irregular",
    "object_colour": "multicolored",
    "physical_appearance": "This is a set of 20 cards each containing strings of seed beads. There are four carrying green beads of various shades, two with blue beads of various shades, and the rest bearing beads of various colours.",
    "subject_terms_1": "Peranakan sewing tools tailors beadwork (visual works)",
    "subject_terms_2": "Beads Peranakan (Asian people) Sewing Equipment and supplies Tailors Clothing trade Bead embroidery",
    "subject_terms_3": "Vanishing trade Textile art and design",
    "sgcool_label_text": "Strings of seed beads used in nyonya needlework are hung on these 20 cardboard pieces. The presence of shop marks on the backs of some of the cards is also important in identifying the provenance of these materials. Handwritten labels indicating the sizes of strings of beads also useful show how beads were categorised by size. These beads show the variety of bead types available to embroiderers in Malacca and Singapore. The original owner of these items made a living fashioning beaded slippers and dresses, working from home as she did not have a shop."
  },
  "nlpDate": "20201120223707",
  "connectorId": 0,
  "tags": {}
}