{"id":"2017-00354","title":"Sarong","source":"Bumblebee","path":"./Data/json/","content":"accession_no_csv:2017-00354\nImage:\nobject_work_type:sarongs batik art\ntitle_text:Sarong\npreference:main\ntitle_language:\ncreator_2:Kok Sing Oey\ncreator_role:textile designers\ncreation_date:Early 20th century\ncreation_place_original_location:Pekalongan (Indonesia)\nstyles_periods_indexing_terms:Peranakan\ninscriptions:\ninscription_language:\nshape:rectangular\nmaterials_name:cotton (textile)\ntechniques_name:batik\nobject_colour:multicolored\nphysical_appearance:This is a batik sarong. It features large bouquets of European flowers interspersed with butterflies and birds. The background is green\n filled with dense fern-like leaves motif. The top of the batik features a scrolling floral pattern with blue background\n while the bottom features the same pattern with a coral background. There is no signature seen on this batik sarong.\nsubject_terms_1:Peranakan folk costume birds (motifs) foliage (motif) cultural diffusion flower (motif)\nsubject_terms_2:Batik Ethnic costume Peranakan (Asian people) Motifs Culture diffusion\nsubject_terms_3:Batik Peranakan costumes\nsgcool_label_text:The buketan design\n comprising large bouquets of European flowers interspersed with butterflies and birds\n is repeated on this sarong.  The kepala (broad vertical panel) of this batik is set on a coral plain background while the badan (main design feature of the batik or ‘body’) is filled with dense fern-like motif.  The bouquet of tulips and orchids are repeated on both the kepala and badan\n with slight variations in the colour combination of the flowers.  This batik comes from the family collection of Oey Kok Sing (1896-1966)\n the second in three generations of documented batik-makers in Pekalongan.  Her later batik designs attest to her virtuosity in technique and inventive colour palette.  Her repertoire of tiny isen-isen motifs (filler motifs within the outlines of the key motifs) in particular\n exudes a strong sense of artistic individuality\n possibly informed by modernist designs on European printed cloths.  Her treatment of floral bouquets is also charactertistic of the undulating and curving lines of the Art Noveau style that was introduced in the northern coast of Java by the Europeans.","createdDate":"20201018182636","version":0,"latest":false,"roles":[],"metadata":{"accession_no_csv":"2017-00354","Image":"","object_work_type":"sarongs batik art","title_text":"Sarong","preference":"main","title_language":"","creator_2":"Kok Sing Oey","creator_role":"textile designers","creation_date":"Early 20th century","creation_place_original_location":"Pekalongan (Indonesia)","styles_periods_indexing_terms":"Peranakan","inscriptions":"","inscription_language":"","shape":"rectangular","materials_name":"cotton (textile)","techniques_name":"batik","object_colour":"multicolored","physical_appearance":"This is a batik sarong. It features large bouquets of European flowers interspersed with butterflies and birds. The background is green, filled with dense fern-like leaves motif. The top of the batik features a scrolling floral pattern with blue background, while the bottom features the same pattern with a coral background. There is no signature seen on this batik sarong.","subject_terms_1":"Peranakan folk costume birds (motifs) foliage (motif) cultural diffusion flower (motif)","subject_terms_2":"Batik Ethnic costume Peranakan (Asian people) Motifs Culture diffusion","subject_terms_3":"Batik Peranakan costumes","sgcool_label_text":"The buketan design, comprising large bouquets of European flowers interspersed with butterflies and birds, is repeated on this sarong.  The kepala (broad vertical panel) of this batik is set on a coral plain background while the badan (main design feature of the batik or ‘body’) is filled with dense fern-like motif.  The bouquet of tulips and orchids are repeated on both the kepala and badan, with slight variations in the colour combination of the flowers.  This batik comes from the family collection of Oey Kok Sing (1896-1966), the second in three generations of documented batik-makers in Pekalongan.  Her later batik designs attest to her virtuosity in technique and inventive colour palette.  Her repertoire of tiny isen-isen motifs (filler motifs within the outlines of the key motifs) in particular, exudes a strong sense of artistic individuality, possibly informed by modernist designs on European printed cloths.  Her treatment of floral bouquets is also charactertistic of the undulating and curving lines of the Art Noveau style that was introduced in the northern coast of Java by the Europeans."},"nlpDate":"20201018182636","connectorId":0,"tags":{}}