{
  "id": "2017-00228",
  "title": "Compilation of bugle calls for the Ceylon Rifle Regiment",
  "source": "Bumblebee",
  "path": "./Data/json/",
  "content": "\n  accession_no_csv: 2017-00228\n\n  Image: \n\n  object_work_type: manuscripts (documents)\n\n  title_text: Compilation of bugle calls for the Ceylon Rifle Regiment\n\n  preference: main\n\n  title_language: \n\n  creator_2: Ensign William Guy\n\n  creator_role: compilers (people in literature)?\n\n  creation_date: 1856\n\n  creation_place_original_location: Ceylon\n\n  inscriptions: \n\n  inscription_language: \n\n  shape: Rectangular\n\n  materials_name: paper (fiber product) ink\n\n  techniques_name: compiling (additive processes) writing (processes)\n\n  object_colour: multicoloured\n\n  physical_appearance: This is a compilation of bugle calls for the Ceylon Rifle Regiment. The cover of the book is brown\n with strips of red along its spine as well as on the top and bottom right corners.\n\n  subject_terms_1: bugles (valveless aerophones) military officers\n\n  subject_terms_2: Ensign William Guy Musical notation Bugle calls East India Company\n\n  subject_terms_3: East India Company\n\n  sgcool_label_text: The Ceylon Rifle Regiment (CRR) was a regular native regiment formed by the British in Ceylon in 1795\n when five independent companies of Malays were transferred from the Dutch to the British East India Company service. This manuscript\n dated 1856\n compiles the bugle calls for 113 military commands\n each with musical notation and explanatory remarks in English\n Malay and Tamil. It was compiled by Ensign William Guy of the CRR\n and was directed to native and non-commissioned officers of the Regiment. The bugle calls were divided into ‘regulation sounds’\n daily barrack sounds’ and ‘miscellaneous sounds’.\n",
  "createdDate": "20201201203308",
  "version": 0,
  "latest": false,
  "roles": [],
  "metadata": {
    "accession_no_csv": "2017-00228",
    "Image": "",
    "object_work_type": "manuscripts (documents)",
    "title_text": "Compilation of bugle calls for the Ceylon Rifle Regiment",
    "preference": "main",
    "title_language": "",
    "creator_2": "Ensign William Guy",
    "creator_role": "compilers (people in literature)?",
    "creation_date": "1856",
    "creation_place_original_location": "Ceylon",
    "inscriptions": "",
    "inscription_language": "",
    "shape": "Rectangular",
    "materials_name": "paper (fiber product) ink",
    "techniques_name": "compiling (additive processes) writing (processes)",
    "object_colour": "multicoloured",
    "physical_appearance": "This is a compilation of bugle calls for the Ceylon Rifle Regiment. The cover of the book is brown, with strips of red along its spine as well as on the top and bottom right corners.",
    "subject_terms_1": "bugles (valveless aerophones) military officers",
    "subject_terms_2": "Ensign William Guy Musical notation Bugle calls East India Company",
    "subject_terms_3": "East India Company",
    "sgcool_label_text": "The Ceylon Rifle Regiment (CRR) was a regular native regiment formed by the British in Ceylon in 1795, when five independent companies of Malays were transferred from the Dutch to the British East India Company service. This manuscript, dated 1856, compiles the bugle calls for 113 military commands, each with musical notation and explanatory remarks in English, Malay and Tamil. It was compiled by Ensign William Guy of the CRR, and was directed to native and non-commissioned officers of the Regiment. The bugle calls were divided into ‘regulation sounds’, daily barrack sounds’ and ‘miscellaneous sounds’."
  },
  "nlpDate": "20201201203308",
  "connectorId": 0,
  "tags": {}
}