{
  "id": "2017-00292",
  "title": "\"A carved wooden \"\"In Memoriam\"\" plaque commemorating \"\"Lt. G.C. Kerr. Killed in Action. Singapore. Feb 10th 1942\"\" and 1 postcard\" Memoriam plague and postcard",
  "source": "Bumblebee",
  "path": "./Data/json/",
  "content": "\n  accession_no_csv: 2017-00292\n\n  Image: \n\n  object_work_type: plaques (flat objects) black-and-white photographs\n\n  title_text: \\A carved wooden \\\\In Memoriam\\\\ plaque commemorating \\\\Lt. G.C. Kerr. Killed in Action. Singapore. Feb 10th 1942\\\\ and 1 postcard\\ Memoriam plague and postcard\n\n  preference: alternate main\n\n  title_language: \n\n  creation_date: 1941-1945\n\n  creation_place_original_location: Singapore\n\n  inscriptions: \n\n  inscription_language: \n\n  shape: rectangular\n\n  materials_name: wood (plant material) paper (fiber product)\n\n  techniques_name: woodcarving printing (processes)\n\n  object_colour: multicolored\n\n  physical_appearance: This is a set of items consisting of a wooden plaque and a postcard with a black-and-white photograph.\n\n  subject_terms_1: world wars commemorative plaques prisoners of war\n\n  subject_terms_2: World War\n 1939-1945 Plaques\n plaquettes Photography Postcards Prisoners of war\n\n  subject_terms_3: 1942-1945 Japanese occupation war personalities\n\n  subject_terms_4: \n\n  context_1: World War\n 1939-1945 1942-1945 Japanese Occupation\n\n  context_2: world wars occupations (armed conflicts)\n\n  context_3: 1939-1945 1942-1945\n\n  context_4: 1939 1942\n\n  context_5: 1945 1945\n\n  context_6: Malaya Singapore\n\n  context_7: Great Britain. Army. Royal Field Artillery\n\n  context_8: armed forces\n\n  sgcool_label_text: \\A carved wooden \\\\In Memoriam\\\\ plaque commemorating Lt. G.C. Kerr who was killed in action in Singapore on Feb 10th 1942. It would have possibly been assembled during internment and speaks to P.O.W efforts to remember their fallen comrades. This artefact is part of the archive of James Steele\n",
  "createdDate": "20201120223707",
  "version": 0,
  "latest": false,
  "roles": [],
  "metadata": {
    "accession_no_csv": "2017-00292",
    "Image": "",
    "object_work_type": "plaques (flat objects) black-and-white photographs",
    "title_text": "\"A carved wooden \"\"In Memoriam\"\" plaque commemorating \"\"Lt. G.C. Kerr. Killed in Action. Singapore. Feb 10th 1942\"\" and 1 postcard\" Memoriam plague and postcard",
    "preference": "alternate main",
    "title_language": "",
    "creation_date": "1941-1945",
    "creation_place_original_location": "Singapore",
    "inscriptions": "",
    "inscription_language": "",
    "shape": "rectangular",
    "materials_name": "wood (plant material) paper (fiber product)",
    "techniques_name": "woodcarving printing (processes)",
    "object_colour": "multicolored",
    "physical_appearance": "This is a set of items consisting of a wooden plaque and a postcard with a black-and-white photograph.",
    "subject_terms_1": "world wars commemorative plaques prisoners of war",
    "subject_terms_2": "World War, 1939-1945 Plaques, plaquettes Photography Postcards Prisoners of war",
    "subject_terms_3": "1942-1945 Japanese occupation war personalities",
    "subject_terms_4": "",
    "context_1": "World War, 1939-1945 1942-1945 Japanese Occupation",
    "context_2": "world wars occupations (armed conflicts)",
    "context_3": "1939-1945 1942-1945",
    "context_4": "1939 1942",
    "context_5": "1945 1945",
    "context_6": "Malaya Singapore",
    "context_7": "Great Britain. Army. Royal Field Artillery",
    "context_8": "armed forces",
    "sgcool_label_text": "\"A carved wooden \"\"In Memoriam\"\" plaque commemorating Lt. G.C. Kerr who was killed in action in Singapore on Feb 10th 1942. It would have possibly been assembled during internment and speaks to P.O.W efforts to remember their fallen comrades. This artefact is part of the archive of James Steele"
  },
  "nlpDate": "20201120223707",
  "connectorId": 0,
  "tags": {}
}