{
  "id": "2017-00294-019",
  "title": "Group of 50 photographs of P.O.W James Steele and regiment when stationed in Malaysia in 1941 (and 2 later photographs of Steele placing a wreath at ceremony of remembrance)  Bowns. Ryder. Heg. Grant. Shipp. Naval Base Singapore 1941",
  "source": "Bumblebee",
  "path": "./Data/json/",
  "content": "\n  accession_no_csv: 2017-00294-019\n\n  Image: \n\n  object_work_type: black-and-white photographs\n\n  title_text: Group of 50 photographs of P.O.W James Steele and regiment when stationed in Malaysia in 1941 (and 2 later photographs of Steele placing a wreath at ceremony of remembrance)  Bowns. Ryder. Heg. Grant. Shipp. Naval Base Singapore 1941\n\n  preference: alternate main\n\n  title_language: \n\n  creation_date: 1941-1945\n\n  creation_place_original_location: Singapore Naval Base\n\n  inscriptions: \n\n  inscription_language: \n\n  shape: rectangular\n\n  materials_name: paper (fiber product)\n\n  techniques_name: photographic processes\n\n  object_colour: black-and-white (colors)\n\n  physical_appearance: This is a black-and-white photograph. It features a group of five soldiers\n dressed in military uinform and headgear\n standing in attention in a line. They are each holding a rifle in their right hand. Behind them on the right\n stands another military officer. In the background of the photograph\n there are several roofed buildings. There are no tears or folds seen on the photograph.\n\n  subject_terms_1: world wars soldiers group portraits\n\n  subject_terms_2: World War\n 1939-1945 Portraits\n Group Photography Soldiers Singapore Naval Base\n\n  subject_terms_3: Photography\n\n  subject_terms_4: \n\n  context_1: World War\n 1939-1945\n\n  context_2: world wars\n\n  context_3: 1939-1945\n\n  context_4: 1939\n\n  context_5: 1945\n\n  context_6: Malaya\n\n  context_7: Great Britain. Army. Royal Field Artillery\n\n  context_8: armed forces\n\n  sgcool_label_text: A variety of portraits of British soldiers that show them at leisure as well as two photographs of James Steele placing a wreath at a remembrance ceremony\n this collection is part of the archive of James Steele\n Royal Artillery (Field) who served in Malaya from January 1941-February 1942\n when interned as a P.O.W at Changi until his release in October 1945.\n",
  "createdDate": "20201120223707",
  "version": 0,
  "latest": false,
  "roles": [],
  "metadata": {
    "accession_no_csv": "2017-00294-019",
    "Image": "",
    "object_work_type": "black-and-white photographs",
    "title_text": "Group of 50 photographs of P.O.W James Steele and regiment when stationed in Malaysia in 1941 (and 2 later photographs of Steele placing a wreath at ceremony of remembrance)  Bowns. Ryder. Heg. Grant. Shipp. Naval Base Singapore 1941",
    "preference": "alternate main",
    "title_language": "",
    "creation_date": "1941-1945",
    "creation_place_original_location": "Singapore Naval Base",
    "inscriptions": "",
    "inscription_language": "",
    "shape": "rectangular",
    "materials_name": "paper (fiber product)",
    "techniques_name": "photographic processes",
    "object_colour": "black-and-white (colors)",
    "physical_appearance": "This is a black-and-white photograph. It features a group of five soldiers, dressed in military uinform and headgear, standing in attention in a line. They are each holding a rifle in their right hand. Behind them on the right, stands another military officer. In the background of the photograph, there are several roofed buildings. There are no tears or folds seen on the photograph.",
    "subject_terms_1": "world wars soldiers group portraits",
    "subject_terms_2": "World War, 1939-1945 Portraits, Group Photography Soldiers Singapore Naval Base",
    "subject_terms_3": "Photography",
    "subject_terms_4": "",
    "context_1": "World War, 1939-1945",
    "context_2": "world wars",
    "context_3": "1939-1945",
    "context_4": "1939",
    "context_5": "1945",
    "context_6": "Malaya",
    "context_7": "Great Britain. Army. Royal Field Artillery",
    "context_8": "armed forces",
    "sgcool_label_text": "A variety of portraits of British soldiers that show them at leisure as well as two photographs of James Steele placing a wreath at a remembrance ceremony, this collection is part of the archive of James Steele, Royal Artillery (Field) who served in Malaya from January 1941-February 1942, when interned as a P.O.W at Changi until his release in October 1945."
  },
  "nlpDate": "20201120223707",
  "connectorId": 0,
  "tags": {}
}