{"id":"2017-00186","title":"Chan Phui Kong Collection: Canvas bag","source":"Bumblebee","path":"./Data/json/","content":"accession_no_csv:2017-00186\nImage:\nobject_work_type:messenger bags\ntitle_text:Chan Phui Kong Collection: Canvas bag\npreference:main\ntitle_language:\ncreation_date:1942\ncreation_place_original_location:Singapore\ninscriptions:\ninscription_language:\nshape:irregular\nmaterials_name:canvas (textile material)\ntechniques_name:sewing (needleworking technique)\nobject_colour:brown (color)\nphysical_appearance:This is a brown canvas bag. It is rectangular in shape\n with a flap across the top and two fastening buckles in front. The bag has a single long strap attached to the sides. It is slightly stained. There are no inscriptions seen on the bag.\nsubject_terms_1:world wars resistance movements bags (generic containers)\nsubject_terms_2:World War\n 1939-1945 Great Britain. Army. Force 136 Force 136 (Guerilla movement) Chin\n Phui Kong\n 1923- Bags\nsubject_terms_3:Force 136 (Guerilla movement) 1942-1945 Japanese occupation Chin\n Phui Kong\n 1923- war personalities\nsubject_terms_4:\ncontext_1:World War\n 1939-1945 1942-1945 Japanese Occupation\ncontext_2:world wars occupations (armed conflicts)\ncontext_3:1939-1945 1942-1945\ncontext_4:1939 1942\ncontext_5:1945 1945\ncontext_6:Malaya Singapore\ncontext_7:Great Britain. Army. Force 136\ncontext_8:armed forces\nsgcool_label_text:This bag belongs to part of a collection of artefacts owned by Chan Phui Kong ???and related to the World War II underground resistance movement known as Force 136. Chan’s collection forms part of a larger collection of materials gathered by Tan Chong Tee (1916- 2012)\n who was a fellow and key member of this resistance group. The collection consists of original materials belonging to Tan and other members of Force 136 dating from the 1940s to new materials reproduced from memory by Tan Chong Tee\n which date from the late 1980s to early 2000s. \\r\\n\\r\\nForce 136 was set up in July 1942 as part of the British Special Operations Executive (SOE). It recruited and trained local guerillas to gather intelligence and create an underground spy network to support planned British invasion of Japanese-occupied Malaya.","createdDate":"20201119143406","version":0,"latest":false,"roles":[],"metadata":{"accession_no_csv":"2017-00186","Image":"","object_work_type":"messenger bags","title_text":"Chan Phui Kong Collection: Canvas bag","preference":"main","title_language":"","creation_date":"1942","creation_place_original_location":"Singapore","inscriptions":"","inscription_language":"","shape":"irregular","materials_name":"canvas (textile material)","techniques_name":"sewing (needleworking technique)","object_colour":"brown (color)","physical_appearance":"This is a brown canvas bag. It is rectangular in shape, with a flap across the top and two fastening buckles in front. The bag has a single long strap attached to the sides. It is slightly stained. There are no inscriptions seen on the bag.","subject_terms_1":"world wars resistance movements bags (generic containers)","subject_terms_2":"World War, 1939-1945 Great Britain. Army. Force 136 Force 136 (Guerilla movement) Chin, Phui Kong, 1923- Bags","subject_terms_3":"Force 136 (Guerilla movement) 1942-1945 Japanese occupation Chin, Phui Kong, 1923- war personalities","subject_terms_4":"","context_1":"World War, 1939-1945 1942-1945 Japanese Occupation","context_2":"world wars occupations (armed conflicts)","context_3":"1939-1945 1942-1945","context_4":"1939 1942","context_5":"1945 1945","context_6":"Malaya Singapore","context_7":"Great Britain. Army. Force 136","context_8":"armed forces","sgcool_label_text":"This bag belongs to part of a collection of artefacts owned by Chan Phui Kong ???and related to the World War II underground resistance movement known as Force 136. Chan’s collection forms part of a larger collection of materials gathered by Tan Chong Tee (1916- 2012), who was a fellow and key member of this resistance group. The collection consists of original materials belonging to Tan and other members of Force 136 dating from the 1940s to new materials reproduced from memory by Tan Chong Tee, which date from the late 1980s to early 2000s. \r\n\r\nForce 136 was set up in July 1942 as part of the British Special Operations Executive (SOE). It recruited and trained local guerillas to gather intelligence and create an underground spy network to support planned British invasion of Japanese-occupied Malaya."},"nlpDate":"20201119143406","connectorId":0,"tags":{}}