{"id":"2017-00110","title":"General Wu (Full Body Portrait) ????","source":"Bumblebee","path":"./Data/json/","content":"accession_no_csv:2017-00110\nImage:\nobject_work_type:portraits paintings (visual works)\ntitle_text:General Wu (Full Body Portrait) ????\npreference:main main\ntitle_language:\ncreator_2:Tan Chong Tee\ncreator_1:Chen\n Chongzhi\n 1916-\ncreator_role:artists (visual artists)\ncreation_date:Not indicated\ncreation_place_original_location:Singapore\ninscriptions:\ninscription_language:\nshape:rectangular\nmaterials_name:paper (fiber product) ink colour (pigment)\ntechniques_name:painting (image-making)\nobject_colour:multicolored\nphysical_appearance:This is a full body multicolored portrait of General Wu Tieh-cheng in his later years. He is portrayed sitting on a red chair\n and holding a walking stick. He is dressed in a white suit with blue tie\n and is wearing glasses with black shoes. He is facing forwards towards the viewer. There is a signature on the left of the portrait. The portrait is presented on a long vertical scroll.\nsubject_terms_1:world wars depictions (visual works) resistance movements military officers scroll paintings Chinese scripts\nsubject_terms_2:Painting Portraits World War\n 1939-1945 Great Britain. Army. Force 136 Force 136 (Guerilla movement) Chen\n Chongzhi\n 1916- Wu\n Tiecheng\n 1888-1953\nsubject_terms_3:Painting Force 136 (Guerilla movement) Tan\n Chong Tee 1942-1945 Japanese occupation war personalities\nsubject_terms_4:\ncontext_1:World War\n 1939-1945 1942-1945 Japanese Occupation\ncontext_2:world wars occupations (armed conflicts)\ncontext_3:1939-1945 1942-1945\ncontext_4:1939 1942\ncontext_5:1945 1945\ncontext_6:Malaya Singapore\ncontext_7:Great Britain. Army. Force 136\ncontext_8:armed forces\nsgcool_label_text:This portrait belongs to part of a collection of artefacts related to the World War II underground resistance movement known as Force 136. The collection of materials was gathered by Tan Chong Tee (1916- 2012)\n who was a key member of this resistance group. The collection consists of original materials belonging to Tan and other members of Force 136 dating from the 1940s to new materials reproduced from memory by Tan Chong Tee\n which date from mid 1990s to early 2000s. \\r\\n\\r\\nForce 136 was set up in July 1942 as part of the British Special Operations Executive (SOE). It recruited and trained local guerrillas to gather intelligence and create an underground spy network to support planned British invasion of Japanese-occupied Malaya.\\r\\n\\r\\nThis portrait depicts general Wu Tieh-cheng in his later years.","createdDate":"20201119143406","version":0,"latest":false,"roles":[],"metadata":{"accession_no_csv":"2017-00110","Image":"","object_work_type":"portraits paintings (visual works)","title_text":"General Wu (Full Body Portrait) ????","preference":"main main","title_language":"","creator_2":"Tan Chong Tee","creator_1":"Chen, Chongzhi, 1916-","creator_role":"artists (visual artists)","creation_date":"Not indicated","creation_place_original_location":"Singapore","inscriptions":"","inscription_language":"","shape":"rectangular","materials_name":"paper (fiber product) ink colour (pigment)","techniques_name":"painting (image-making)","object_colour":"multicolored","physical_appearance":"This is a full body multicolored portrait of General Wu Tieh-cheng in his later years. He is portrayed sitting on a red chair, and holding a walking stick. He is dressed in a white suit with blue tie, and is wearing glasses with black shoes. He is facing forwards towards the viewer. There is a signature on the left of the portrait. The portrait is presented on a long vertical scroll.","subject_terms_1":"world wars depictions (visual works) resistance movements military officers scroll paintings Chinese scripts","subject_terms_2":"Painting Portraits World War, 1939-1945 Great Britain. Army. Force 136 Force 136 (Guerilla movement) Chen, Chongzhi, 1916- Wu, Tiecheng, 1888-1953","subject_terms_3":"Painting Force 136 (Guerilla movement) Tan, Chong Tee 1942-1945 Japanese occupation war personalities","subject_terms_4":"","context_1":"World War, 1939-1945 1942-1945 Japanese Occupation","context_2":"world wars occupations (armed conflicts)","context_3":"1939-1945 1942-1945","context_4":"1939 1942","context_5":"1945 1945","context_6":"Malaya Singapore","context_7":"Great Britain. Army. Force 136","context_8":"armed forces","sgcool_label_text":"This portrait belongs to part of a collection of artefacts related to the World War II underground resistance movement known as Force 136. The collection of materials was gathered by Tan Chong Tee (1916- 2012), who was a key member of this resistance group. The collection consists of original materials belonging to Tan and other members of Force 136 dating from the 1940s to new materials reproduced from memory by Tan Chong Tee, which date from mid 1990s to early 2000s. \r\n\r\nForce 136 was set up in July 1942 as part of the British Special Operations Executive (SOE). It recruited and trained local guerrillas to gather intelligence and create an underground spy network to support planned British invasion of Japanese-occupied Malaya.\r\n\r\nThis portrait depicts general Wu Tieh-cheng in his later years."},"nlpDate":"20201119143406","connectorId":0,"tags":{}}