{"id":"2017-00925","title":"Leica Standard Leica Standard camera and components","source":"Bumblebee","path":"./Data/json/","content":"accession_no_csv:2017-00925\nImage:\nobject_work_type:35mm cameras\ntitle_text:Leica Standard Leica Standard camera and components\npreference:alternate main\ntitle_language:\ncreation_date:1930s\ncreation_place_original_location:Germany\ninscriptions:\ninscription_language:\nshape:irregular\nobject_colour:black (color) silver (color)\nphysical_appearance:This is a Leica camera accompanied by a set of camera equipment. The camera has a black body\n with silver knobs at the top\n and a rotational lens. The camera is accompanied by several parts such as an extra filter and case\n film roll cases\n and a black pouch.\nsubject_terms_1:cameras (photographic equipment) photography (discipline) vintage (period) camera components camera accessories\nsubject_terms_2:Cameras Photography Vintage Leica camera\nsubject_terms_3:Photography\nsgcool_label_text:This Leica camera has a black body and is attached with a rotational nickle-finished Elmar lens. The Leica Standard was available in shops like Singapore Photo Co. which was located at High Street in 1935. \\r\\n\\r\\nBefore the advent of the portable camera in the late 19th century\n the taking of photographs was limited to the studio. However portable cameras remained affordable only to the rich until the first decades of the 20th century.","createdDate":"20201119143406","version":0,"latest":false,"roles":[],"metadata":{"accession_no_csv":"2017-00925","Image":"","object_work_type":"35mm cameras","title_text":"Leica Standard Leica Standard camera and components","preference":"alternate main","title_language":"","creation_date":"1930s","creation_place_original_location":"Germany","inscriptions":"","inscription_language":"","shape":"irregular","object_colour":"black (color) silver (color)","physical_appearance":"This is a Leica camera accompanied by a set of camera equipment. The camera has a black body, with silver knobs at the top, and a rotational lens. The camera is accompanied by several parts such as an extra filter and case, film roll cases, and a black pouch.","subject_terms_1":"cameras (photographic equipment) photography (discipline) vintage (period) camera components camera accessories","subject_terms_2":"Cameras Photography Vintage Leica camera","subject_terms_3":"Photography","sgcool_label_text":"This Leica camera has a black body and is attached with a rotational nickle-finished Elmar lens. The Leica Standard was available in shops like Singapore Photo Co. which was located at High Street in 1935. \r\n\r\nBefore the advent of the portable camera in the late 19th century, the taking of photographs was limited to the studio. However portable cameras remained affordable only to the rich until the first decades of the 20th century."},"nlpDate":"20201119143406","connectorId":0,"tags":{}}