{"id":"2017-01040-123","title":"\"Personal photograph album titled \"\"Sixteen Months in Singapore\"\"\" Sixteen Months in Singapore: Photograph of Corporal A. Silver  holding booklet, camera and handbag","source":"Bumblebee","path":"./Data/json/","content":"accession_no_csv:2017-01040-123\nImage:\nobject_work_type:black-and-white photographs photographs\ntitle_text:\\Personal photograph album titled \\\\Sixteen Months in Singapore\\\\\\ Sixteen Months in Singapore: Photograph of Corporal A. Silver  holding booklet\n camera and handbag\npreference:alternate main\ntitle_language:\ncreation_date:1951-1952\ncreation_place_original_location:Singapore\ninscriptions:\ninscription_language:\nshape:rectangular\nmaterials_name:paper (fiber product)\ntechniques_name:photographic processes\nobject_colour:black-and-white (colors)\nphysical_appearance:This is a black-and-white photograph. It is rectangular in shape and landscape in orientation. It features a woman in a striped dress. She is standing\n and facing towards the left. She is holding a booklet\n a camera and a handbag in her hands. In the background\n there are several others seen standing on a grass patch.\nsubject_terms_1:women (female humans) snapshots\nsubject_terms_2:Photographs Women\nsubject_terms_3:Photography Women\nsubject_terms_4:\nsgcool_label_text:This is a personal photograph album that belonged to a Corporal A. Silver who spent 16 months in Singapore between 1951 and 1952. Silver was presumably a Jewish lady who was stationed in Singapore to serve at the Royal Air Force (RAF) Hospital at Changi. The album contains photographs that document her working and personal life\n including friends she made within the Jewish community in Singapore.","createdDate":"20201119143407","version":0,"latest":false,"roles":[],"metadata":{"accession_no_csv":"2017-01040-123","Image":"","object_work_type":"black-and-white photographs photographs","title_text":"\"Personal photograph album titled \"\"Sixteen Months in Singapore\"\"\" Sixteen Months in Singapore: Photograph of Corporal A. Silver  holding booklet, camera and handbag","preference":"alternate main","title_language":"","creation_date":"1951-1952","creation_place_original_location":"Singapore","inscriptions":"","inscription_language":"","shape":"rectangular","materials_name":"paper (fiber product)","techniques_name":"photographic processes","object_colour":"black-and-white (colors)","physical_appearance":"This is a black-and-white photograph. It is rectangular in shape and landscape in orientation. It features a woman in a striped dress. She is standing, and facing towards the left. She is holding a booklet, a camera and a handbag in her hands. In the background, there are several others seen standing on a grass patch.","subject_terms_1":"women (female humans) snapshots","subject_terms_2":"Photographs Women","subject_terms_3":"Photography Women","subject_terms_4":"","sgcool_label_text":"This is a personal photograph album that belonged to a Corporal A. Silver who spent 16 months in Singapore between 1951 and 1952. Silver was presumably a Jewish lady who was stationed in Singapore to serve at the Royal Air Force (RAF) Hospital at Changi. The album contains photographs that document her working and personal life, including friends she made within the Jewish community in Singapore."},"nlpDate":"20201119143407","connectorId":0,"tags":{}}