{
  "id": "2017-01039-012",
  "title": "Photograph album presented to George Lowe as a souvenir of his visit to Singapore George Lowe album: Photograph of group standing over table",
  "source": "Bumblebee",
  "path": "./Data/json/",
  "content": "\n  accession_no_csv: 2017-01039-012\n\n  Image: \n\n  object_work_type: black-and-white photographs photographs\n\n  title_text: Photograph album presented to George Lowe as a souvenir of his visit to Singapore George Lowe album: Photograph of group standing over table\n\n  preference: alternate main\n\n  title_language: \n\n  creation_date: 1953\n\n  creation_place_original_location: Singapore\n\n  inscriptions: \n\n  inscription_language: \n\n  shape: rectangular\n\n  materials_name: paper (fiber product)\n\n  techniques_name: photographic processes\n\n  object_colour: black-and-white (colors)\n\n  physical_appearance: This is a black-and-white photograph. It features four individuals\n standing over a table. Two men are dressed in a suit\n the man on the right dressed in a shirt\n and the woman dressed in a dress. On the table\n there is an opened frame box. There are no tears or folds seen on the photograph.\n\n  subject_terms_1: Photographs souvenirs\n\n  subject_terms_2: Photographs Photograph albums Souvenir Lowe\n George\n 1924-2013 Hillary\n Edmund\n 1919-2008\n\n  subject_terms_3: Photography City Hall (Singapore)\n\n  subject_terms_4: \n\n  sgcool_label_text: George Lowe was a member of the British Expedition that saw Sir Edmund Hillary scale Mount Everest on 29 May 1953. In September that year\n Lowe accompanied Hillary on a visit to Singapore to deliver their first Everest lecture outside of New Zealand at the Odeon Theatre to an audience of 1\n620 schoolchildren. This photograph album\n with the coat of arms of the City of Singapore in gilt on the cover\n was presented to Lowe as a souvenir of his visit.\n",
  "createdDate": "20201120223708",
  "version": 0,
  "latest": false,
  "roles": [],
  "metadata": {
    "accession_no_csv": "2017-01039-012",
    "Image": "",
    "object_work_type": "black-and-white photographs photographs",
    "title_text": "Photograph album presented to George Lowe as a souvenir of his visit to Singapore George Lowe album: Photograph of group standing over table",
    "preference": "alternate main",
    "title_language": "",
    "creation_date": "1953",
    "creation_place_original_location": "Singapore",
    "inscriptions": "",
    "inscription_language": "",
    "shape": "rectangular",
    "materials_name": "paper (fiber product)",
    "techniques_name": "photographic processes",
    "object_colour": "black-and-white (colors)",
    "physical_appearance": "This is a black-and-white photograph. It features four individuals, standing over a table. Two men are dressed in a suit, the man on the right dressed in a shirt, and the woman dressed in a dress. On the table, there is an opened frame box. There are no tears or folds seen on the photograph.",
    "subject_terms_1": "Photographs souvenirs",
    "subject_terms_2": "Photographs Photograph albums Souvenir Lowe, George, 1924-2013 Hillary, Edmund, 1919-2008",
    "subject_terms_3": "Photography City Hall (Singapore)",
    "subject_terms_4": "",
    "sgcool_label_text": "George Lowe was a member of the British Expedition that saw Sir Edmund Hillary scale Mount Everest on 29 May 1953. In September that year, Lowe accompanied Hillary on a visit to Singapore to deliver their first Everest lecture outside of New Zealand at the Odeon Theatre to an audience of 1,620 schoolchildren. This photograph album, with the coat of arms of the City of Singapore in gilt on the cover, was presented to Lowe as a souvenir of his visit."
  },
  "nlpDate": "20201120223708",
  "connectorId": 0,
  "tags": {}
}