{
  "id": "2017-00653",
  "title": "Cushion cover",
  "source": "Bumblebee",
  "path": "./Data/json/",
  "content": "\n  accession_no_csv: 2017-00653\n\n  Image: \n\n  object_work_type: coverings for soft furnishings\n\n  title_text: Cushion cover\n\n  preference: main\n\n  title_language: \n\n  creation_date: 20th century\n\n  creation_place_original_location: Gujarat (India)\n\n  inscriptions: \n\n  inscription_language: \n\n  shape: square (shape)\n\n  materials_name: glass (material) textile materials\n\n  techniques_name: sewing (needleworking technique) embroidering\n\n  object_colour: multicolored\n\n  physical_appearance: This is a cushion cover. It is square in shape\n with a multicolored geometric scrolling border\n and a cotton weave in the center. The cotton weave features a stylized embroidery of four deities\n with a row of small flowers in the center.\n\n  subject_terms_1: embroidery (visual works) deities depictions (visual works) flower (motif) beadwork (visual works) cushions\n\n  subject_terms_2: Pillowcases Embroidery Motifs Gods Cushions\n\n  subject_terms_3: Textile art and design\n\n  subject_terms_4: \n",
  "createdDate": "20201120223708",
  "version": 0,
  "latest": false,
  "roles": [],
  "metadata": {
    "accession_no_csv": "2017-00653",
    "Image": "",
    "object_work_type": "coverings for soft furnishings",
    "title_text": "Cushion cover",
    "preference": "main",
    "title_language": "",
    "creation_date": "20th century",
    "creation_place_original_location": "Gujarat (India)",
    "inscriptions": "",
    "inscription_language": "",
    "shape": "square (shape)",
    "materials_name": "glass (material) textile materials",
    "techniques_name": "sewing (needleworking technique) embroidering",
    "object_colour": "multicolored",
    "physical_appearance": "This is a cushion cover. It is square in shape, with a multicolored geometric scrolling border, and a cotton weave in the center. The cotton weave features a stylized embroidery of four deities, with a row of small flowers in the center.",
    "subject_terms_1": "embroidery (visual works) deities depictions (visual works) flower (motif) beadwork (visual works) cushions",
    "subject_terms_2": "Pillowcases Embroidery Motifs Gods Cushions",
    "subject_terms_3": "Textile art and design",
    "subject_terms_4": ""
  },
  "nlpDate": "20201120223708",
  "connectorId": 0,
  "tags": {}
}