{
  "id": "2017-00654",
  "title": "Beaded hair ornament",
  "source": "Bumblebee",
  "path": "./Data/json/",
  "content": "\n  accession_no_csv: 2017-00654\n\n  Image: \n\n  object_work_type: hair ornaments\n\n  title_text: Beaded hair ornament\n\n  preference: main\n\n  title_language: \n\n  creation_date: 20th century\n\n  creation_place_original_location: Gujarat (India)\n\n  inscriptions: \n\n  inscription_language: \n\n  shape: irregular\n\n  materials_name: glass (material)\n\n  techniques_name: sewing (needleworking technique)\n\n  object_colour: multicolored\n\n  physical_appearance: This is a beaded hair ornament. It consists of two dangling sections\n each decorated with numerous white beads amongst coloured threads. The two sections are connected to a black woven thread\n that has been bundled at the top.\n\n  subject_terms_1: beadwork (visual works) folk costume\n\n  subject_terms_2: Hair ornaments Ethnic jewelry\n\n  subject_terms_3: Indian costumes\n\n  subject_terms_4: \n",
  "createdDate": "20201201203308",
  "version": 0,
  "latest": false,
  "roles": [],
  "metadata": {
    "accession_no_csv": "2017-00654",
    "Image": "",
    "object_work_type": "hair ornaments",
    "title_text": "Beaded hair ornament",
    "preference": "main",
    "title_language": "",
    "creation_date": "20th century",
    "creation_place_original_location": "Gujarat (India)",
    "inscriptions": "",
    "inscription_language": "",
    "shape": "irregular",
    "materials_name": "glass (material)",
    "techniques_name": "sewing (needleworking technique)",
    "object_colour": "multicolored",
    "physical_appearance": "This is a beaded hair ornament. It consists of two dangling sections, each decorated with numerous white beads amongst coloured threads. The two sections are connected to a black woven thread, that has been bundled at the top.",
    "subject_terms_1": "beadwork (visual works) folk costume",
    "subject_terms_2": "Hair ornaments Ethnic jewelry",
    "subject_terms_3": "Indian costumes",
    "subject_terms_4": ""
  },
  "nlpDate": "20201201203308",
  "connectorId": 0,
  "tags": {}
}