{
  "id": "2017-00085",
  "title": "Enlistment ???",
  "source": "Bumblebee",
  "path": "./Data/json/",
  "content": "\n  accession_no_csv: 2017-00085\n\n  Image: \n\n  object_work_type: oil paintings (visual works)\n\n  title_text: Enlistment ???\n\n  preference: main alternate\n\n  title_language: \n\n  creator_2: Tan Chong Tee\n\n  creator_1: Chen\n Chongzhi\n 1916-\n\n  creator_role: artists (visual artists)\n\n  creation_date: 1942\n\n  creation_place_original_location: Singapore\n\n  inscriptions: \n\n  inscription_language: \n\n  shape: rectangular\n\n  materials_name: canvas (textile material) oil paint (paint)\n\n  techniques_name: painting (image-making)\n\n  object_colour: multicolored\n\n  physical_appearance: This is an oil painting depicting the recruitment and enlistment activities of Chinese recruits for Force 136. In the foreground on the left\n there is a woman carrying a child saying goodbye to a man. The man is carrying something in his left arm and is turned towards the woman and child. There is another man behind him. In the background on the left\n there are three more men walking to the left. There is a signature on the bottom-left of the painting.\n\n  subject_terms_1: world wars depictions (visual works) resistance movements soldiers\n\n  subject_terms_2: Painting World War\n 1939-1945 Great Britain. Army. Force 136 Force 136 (Guerilla movement) Chen\n Chongzhi\n 1916- Recruitment and enlistment Soldiers\n\n  subject_terms_3: Oil painting Force 136 (Guerilla movement) Tan\n Chong Tee 1942-1945 Japanese occupation\n\n  subject_terms_4: \n\n  context_1: World War\n 1939-1945 1942-1945 Japanese Occupation\n\n  context_2: world wars occupations (armed conflicts)\n\n  context_3: 1939-1945 1942-1945\n\n  context_4: 1939 1942\n\n  context_5: 1945 1945\n\n  context_6: Malaya Singapore\n\n  context_7: Great Britain. Army. Force 136\n\n  context_8: armed forces\n\n  sgcool_label_text: This painting belongs to part of a collection of artefacts related to the World War II underground resistance movement known as Force 136. The collection of materials was gathered by Tan Chong Tee (1916-2012)\n who was a key member of this resistance group. The collection consists of original materials belonging to Tan and other members of Force 136 dating from the 1940s to new materials reproduced from memory by Tan Chong Tee\n which date from mid 1990s to early 2000s. \\r\\n\\r\\nForce 136 was set up in 1942-45 as part of the British Special Operations Executive (SOE). It recruited and trained local guerillas to gather intelligence and create an underground spy network to support planned British invasion of Japanese-occupied Malaya.\\r\\n\\r\\nThis painting depicts the enlistment of Chinese recruits for Force 136. \\r\\n\n",
  "createdDate": "20201120223707",
  "version": 0,
  "latest": false,
  "roles": [],
  "metadata": {
    "accession_no_csv": "2017-00085",
    "Image": "",
    "object_work_type": "oil paintings (visual works)",
    "title_text": "Enlistment ???",
    "preference": "main alternate",
    "title_language": "",
    "creator_2": "Tan Chong Tee",
    "creator_1": "Chen, Chongzhi, 1916-",
    "creator_role": "artists (visual artists)",
    "creation_date": "1942",
    "creation_place_original_location": "Singapore",
    "inscriptions": "",
    "inscription_language": "",
    "shape": "rectangular",
    "materials_name": "canvas (textile material) oil paint (paint)",
    "techniques_name": "painting (image-making)",
    "object_colour": "multicolored",
    "physical_appearance": "This is an oil painting depicting the recruitment and enlistment activities of Chinese recruits for Force 136. In the foreground on the left, there is a woman carrying a child saying goodbye to a man. The man is carrying something in his left arm and is turned towards the woman and child. There is another man behind him. In the background on the left, there are three more men walking to the left. There is a signature on the bottom-left of the painting.",
    "subject_terms_1": "world wars depictions (visual works) resistance movements soldiers",
    "subject_terms_2": "Painting World War, 1939-1945 Great Britain. Army. Force 136 Force 136 (Guerilla movement) Chen, Chongzhi, 1916- Recruitment and enlistment Soldiers",
    "subject_terms_3": "Oil painting Force 136 (Guerilla movement) Tan, Chong Tee 1942-1945 Japanese occupation",
    "subject_terms_4": "",
    "context_1": "World War, 1939-1945 1942-1945 Japanese Occupation",
    "context_2": "world wars occupations (armed conflicts)",
    "context_3": "1939-1945 1942-1945",
    "context_4": "1939 1942",
    "context_5": "1945 1945",
    "context_6": "Malaya Singapore",
    "context_7": "Great Britain. Army. Force 136",
    "context_8": "armed forces",
    "sgcool_label_text": "This painting belongs to part of a collection of artefacts related to the World War II underground resistance movement known as Force 136. The collection of materials was gathered by Tan Chong Tee (1916-2012), who was a key member of this resistance group. The collection consists of original materials belonging to Tan and other members of Force 136 dating from the 1940s to new materials reproduced from memory by Tan Chong Tee, which date from mid 1990s to early 2000s. \r\n\r\nForce 136 was set up in 1942-45 as part of the British Special Operations Executive (SOE). It recruited and trained local guerillas to gather intelligence and create an underground spy network to support planned British invasion of Japanese-occupied Malaya.\r\n\r\nThis painting depicts the enlistment of Chinese recruits for Force 136. \r\n"
  },
  "nlpDate": "20201120223707",
  "connectorId": 0,
  "tags": {}
}