{
  "id": "2017-00634",
  "title": "Hanging Chakla",
  "source": "Bumblebee",
  "path": "./Data/json/",
  "content": "\n  accession_no_csv: 2017-00634\n\n  Image: \n\n  object_work_type: hangings (coverings)\n\n  title_text: Hanging Chakla\n\n  preference: main alternate\n\n  title_language: \n\n  creation_date: 20th century\n\n  creation_place_original_location: Gujarat (India)\n\n  inscriptions: \n\n  inscription_language: \n\n  shape: pentagonal\n\n  materials_name: glass (material) cotton (textile)\n\n  techniques_name: sewing (needleworking technique) embroidering\n\n  object_colour: multicolored\n\n  physical_appearance: This is a chakla or a hanging textile. It features a cotton weave with embroidery work. It is pentagonal shape\n with a triangular top and square bottom. The chakla is decorated with stylized flowers\n elephants\n cows\n and the Hindu god Ganesha. There is a sewn-on inscription in the center of the chakla.\n\n  subject_terms_1: beadwork (visual works) depictions (visual works) deities birds (motifs) flower (motif) embroidery (visual works)\n\n  subject_terms_2: Motifs Ganesha (Hindu deity) Embroidery Draperies\n\n  subject_terms_3: Textile art and design\n\n  subject_terms_4: \n",
  "createdDate": "20201125084517",
  "version": 0,
  "latest": false,
  "roles": [],
  "metadata": {
    "accession_no_csv": "2017-00634",
    "Image": "",
    "object_work_type": "hangings (coverings)",
    "title_text": "Hanging Chakla",
    "preference": "main alternate",
    "title_language": "",
    "creation_date": "20th century",
    "creation_place_original_location": "Gujarat (India)",
    "inscriptions": "",
    "inscription_language": "",
    "shape": "pentagonal",
    "materials_name": "glass (material) cotton (textile)",
    "techniques_name": "sewing (needleworking technique) embroidering",
    "object_colour": "multicolored",
    "physical_appearance": "This is a chakla or a hanging textile. It features a cotton weave with embroidery work. It is pentagonal shape, with a triangular top and square bottom. The chakla is decorated with stylized flowers, elephants, cows, and the Hindu god Ganesha. There is a sewn-on inscription in the center of the chakla.",
    "subject_terms_1": "beadwork (visual works) depictions (visual works) deities birds (motifs) flower (motif) embroidery (visual works)",
    "subject_terms_2": "Motifs Ganesha (Hindu deity) Embroidery Draperies",
    "subject_terms_3": "Textile art and design",
    "subject_terms_4": ""
  },
  "nlpDate": "20201125084517",
  "connectorId": 0,
  "tags": {}
}