{
  "id": "2017-00263",
  "title": "Blue and white dish with floral decoration",
  "source": "Bumblebee",
  "path": "./Data/json/",
  "content": "\n  accession_no_csv: 2017-00263\n\n  Image: \n\n  object_work_type: porcelain (visual works)  dishes (object genre)  Ceramics (object genre)\n\n  title_text: Blue and white dish with floral decoration\n\n  preference: main\n\n  title_language: \n\n  creation_date: MIng dynasty\n 16th century\n\n  creation_place_original_location: Zhangzhou Shi (China). Tong ji ju\n\n  styles_periods_indexing_terms: Ming (culture\n period\n and styles)  Chinese ceramics styles  Chinese export (ceramics style)\n\n  inscriptions: \n\n  inscription_language: \n\n  shape: concave\n\n  materials_name: blue-and-white (ceramic glaze) porcelain (material)  cobalt blue (pigment)  clay  ceramic glaze\n\n  techniques_name: glazing (coating process)  throwing (pottery techniques)  underglazing molding (forming)  firing (technique)  porcelain painting (image-making) freehand drawing (technique)\n\n  object_colour: multicoloured\n\n  physical_appearance: This is a Ming dynasty Zhangzhou ware\n evidenced by the grit on the base of the dish. The upper and lower rim of its exterior surface is decorated with simple blue lines\n while its interior decorative scheme is composed of floral motifs and sprays segmented in three concentric bands.\n\n  subject_terms_1: porcelain paintings (visual works)  symbolism  floral patterns  freehand drawings (drawings)  Chinese export porcelain\n\n  subject_terms_2: Porcelain\n Chinese Ming- Qing dynasties\n 1368-1912 Blue and white ware China China trade porcelain  China painting\n\n  subject_terms_3: visual arts  Decorative arts Ceramics\n\n  subject_terms_4: \n\n  sgcool_label_text: This dish is decorated with floral sprays arranged in three concentric bands. The thick potting\n sketchily-rendered decoration and gritty base of this dish indicates that it was produced at the Zhangzhou kilns in Fujian province. Grit often adhered to the foot of Zhangzhou wares as the pieces were placed directly on the coarse sand (spread on the bottom of the saggar) while they were still wet with glaze. Zhangzhou wares\n which are distinguished by their free and vigorous style of painted decoration\n were a popular type of ceramics made for export during the late Ming dynasty.\n",
  "createdDate": "20201120223707",
  "version": 0,
  "latest": false,
  "roles": [],
  "metadata": {
    "accession_no_csv": "2017-00263",
    "Image": "",
    "object_work_type": "porcelain (visual works)  dishes (object genre)  Ceramics (object genre)",
    "title_text": "Blue and white dish with floral decoration",
    "preference": "main",
    "title_language": "",
    "creation_date": "MIng dynasty, 16th century",
    "creation_place_original_location": "Zhangzhou Shi (China). Tong ji ju",
    "styles_periods_indexing_terms": "Ming (culture, period, and styles)  Chinese ceramics styles  Chinese export (ceramics style)",
    "inscriptions": "",
    "inscription_language": "",
    "shape": "concave",
    "materials_name": "blue-and-white (ceramic glaze) porcelain (material)  cobalt blue (pigment)  clay  ceramic glaze",
    "techniques_name": "glazing (coating process)  throwing (pottery techniques)  underglazing molding (forming)  firing (technique)  porcelain painting (image-making) freehand drawing (technique)",
    "object_colour": "multicoloured",
    "physical_appearance": "This is a Ming dynasty Zhangzhou ware, evidenced by the grit on the base of the dish. The upper and lower rim of its exterior surface is decorated with simple blue lines, while its interior decorative scheme is composed of floral motifs and sprays segmented in three concentric bands.",
    "subject_terms_1": "porcelain paintings (visual works)  symbolism  floral patterns  freehand drawings (drawings)  Chinese export porcelain",
    "subject_terms_2": "Porcelain, Chinese Ming- Qing dynasties, 1368-1912 Blue and white ware China China trade porcelain  China painting",
    "subject_terms_3": "visual arts  Decorative arts Ceramics",
    "subject_terms_4": "",
    "sgcool_label_text": "This dish is decorated with floral sprays arranged in three concentric bands. The thick potting, sketchily-rendered decoration and gritty base of this dish indicates that it was produced at the Zhangzhou kilns in Fujian province. Grit often adhered to the foot of Zhangzhou wares as the pieces were placed directly on the coarse sand (spread on the bottom of the saggar) while they were still wet with glaze. Zhangzhou wares, which are distinguished by their free and vigorous style of painted decoration, were a popular type of ceramics made for export during the late Ming dynasty."
  },
  "nlpDate": "20201120223707",
  "connectorId": 0,
  "tags": {}
}