{
  "id": "2017-00302-013",
  "title": "Miscellaneous scraps of paper from P.O.W James Steele Archives (30 pieces) P.O.W. James Steele Archives: A Journalist\u0027s Story of the Torpedoeing in the Malacca Straits",
  "source": "Bumblebee",
  "path": "./Data/json/",
  "content": "\n  accession_no_csv: 2017-00302-013\n\n  Image: \n\n  object_work_type: articles\n\n  title_text: Miscellaneous scraps of paper from P.O.W James Steele Archives (30 pieces) P.O.W. James Steele Archives: A Journalist\\u0027s Story of the Torpedoeing in the Malacca Straits\n\n  preference: alternate main\n\n  title_language: \n\n  creation_date: 1941-1945\n\n  creation_place_original_location: Singapore\n\n  inscriptions: \n\n  inscription_language: \n\n  shape: rectangular\n\n  materials_name: paper (fiber product)\n\n  techniques_name: writing (processes) printing (process)\n\n  object_colour: black-and-white (colors)\n\n  physical_appearance: This is a page from a document that contains an article. It is printed in black ink on a plain sheet of paper. There is a page number at the top-center of the document. The document is slightly folded and torn especially along the right. There are several horizontal fold lines across the document.\n\n  subject_terms_1: world wars prisoners of war journalism torpedoes documents (object genre)\n\n  subject_terms_2: World War\n 1939-1945 Prisoners of war Journalism Torpedoes War stories\n\n  subject_terms_3: war personalities Non-fiction\n\n  subject_terms_4: \n\n  context_1: World War\n 1939-1945 1942-1945 Japanese Occupation\n\n  context_2: world wars occupations (armed conflicts)\n\n  context_3: 1939-1945 1942-1945\n\n  context_4: 1939 1942\n\n  context_5: 1945 1945\n\n  context_6: Malaya Singapore\n\n  context_7: Great Britain. Army. Royal Field Artillery\n\n  context_8: armed forces\n\n  sgcool_label_text: Loose papers from the James Steele\n P.O.W archive that include a symbolic drawing\n Japanese banana money\n map of camp\n administrative papers from Changi prison pre-dating internment\n list of soldiers of a regiment as well as James Steele’s warrant to  join the army. These papers are part of the archive of James Steele\n Royal Artillery (Field) who served in Malaya from January 1941-February 1942\n when interned as a P.O.W at Changi until his release in October 1945.\n",
  "createdDate": "20201120223707",
  "version": 0,
  "latest": false,
  "roles": [],
  "metadata": {
    "accession_no_csv": "2017-00302-013",
    "Image": "",
    "object_work_type": "articles",
    "title_text": "Miscellaneous scraps of paper from P.O.W James Steele Archives (30 pieces) P.O.W. James Steele Archives: A Journalist\u0027s Story of the Torpedoeing in the Malacca Straits",
    "preference": "alternate main",
    "title_language": "",
    "creation_date": "1941-1945",
    "creation_place_original_location": "Singapore",
    "inscriptions": "",
    "inscription_language": "",
    "shape": "rectangular",
    "materials_name": "paper (fiber product)",
    "techniques_name": "writing (processes) printing (process)",
    "object_colour": "black-and-white (colors)",
    "physical_appearance": "This is a page from a document that contains an article. It is printed in black ink on a plain sheet of paper. There is a page number at the top-center of the document. The document is slightly folded and torn especially along the right. There are several horizontal fold lines across the document.",
    "subject_terms_1": "world wars prisoners of war journalism torpedoes documents (object genre)",
    "subject_terms_2": "World War, 1939-1945 Prisoners of war Journalism Torpedoes War stories",
    "subject_terms_3": "war personalities Non-fiction",
    "subject_terms_4": "",
    "context_1": "World War, 1939-1945 1942-1945 Japanese Occupation",
    "context_2": "world wars occupations (armed conflicts)",
    "context_3": "1939-1945 1942-1945",
    "context_4": "1939 1942",
    "context_5": "1945 1945",
    "context_6": "Malaya Singapore",
    "context_7": "Great Britain. Army. Royal Field Artillery",
    "context_8": "armed forces",
    "sgcool_label_text": "Loose papers from the James Steele, P.O.W archive that include a symbolic drawing, Japanese banana money, map of camp, administrative papers from Changi prison pre-dating internment, list of soldiers of a regiment as well as James Steele’s warrant to  join the army. These papers are part of the archive of James Steele, Royal Artillery (Field) who served in Malaya from January 1941-February 1942, when interned as a P.O.W at Changi until his release in October 1945."
  },
  "nlpDate": "20201120223707",
  "connectorId": 0,
  "tags": {}
}