{
  "id": "2017-00922",
  "title": "Vest Pocket, Kodak",
  "source": "Bumblebee",
  "path": "./Data/json/",
  "content": "\n  accession_no_csv: 2017-00922\n\n  Image: \n\n  object_work_type: folding cameras\n\n  title_text: Vest Pocket\n Kodak\n\n  preference: main\n\n  title_language: \n\n  creator_2: Kodak (?)\n\n  creator_1: Eastman Kodak Company\n\n  creator_role: manufacturers\n\n  creation_date: 1915\n\n  creation_place_original_location: United States\n\n  inscriptions: \n\n  inscription_language: \n\n  shape: irregular\n\n  materials_name: glass (material) metal\n\n  object_colour: black (color)\n\n  physical_appearance: This is Kodak Vest Pocket folding camera. The main body is black and rectangular in shape\n with curved sides. Thhe front of the camera extends outwards by a metal strut. There is some inscription around the front lens.\n\n  subject_terms_1: vintage (period) photography (discipline) cameras (photographic equipment)\n\n  subject_terms_2: Photography Cameras Kodak camera Vintage\n\n  subject_terms_3: Photography\n\n  sgcool_label_text: The Vest Pocket was the first of a long series that started in 1912. Portability was its most appealing feature for it measured merely an inch thick when closed. To use it\n the lens and shutter were pulled out and allowed to rest on struts. \\r\\n\\r\\nBefore the advent of the portable camera in the late 19th century\n the taking of photographs was limited to the studio. However portable cameras remained affordable only to the rich until the first decades of the 20th century.\n",
  "createdDate": "20201201203308",
  "version": 0,
  "latest": false,
  "roles": [],
  "metadata": {
    "accession_no_csv": "2017-00922",
    "Image": "",
    "object_work_type": "folding cameras",
    "title_text": "Vest Pocket, Kodak",
    "preference": "main",
    "title_language": "",
    "creator_2": "Kodak (?)",
    "creator_1": "Eastman Kodak Company",
    "creator_role": "manufacturers",
    "creation_date": "1915",
    "creation_place_original_location": "United States",
    "inscriptions": "",
    "inscription_language": "",
    "shape": "irregular",
    "materials_name": "glass (material) metal",
    "object_colour": "black (color)",
    "physical_appearance": "This is Kodak Vest Pocket folding camera. The main body is black and rectangular in shape, with curved sides. Thhe front of the camera extends outwards by a metal strut. There is some inscription around the front lens.",
    "subject_terms_1": "vintage (period) photography (discipline) cameras (photographic equipment)",
    "subject_terms_2": "Photography Cameras Kodak camera Vintage",
    "subject_terms_3": "Photography",
    "sgcool_label_text": "The Vest Pocket was the first of a long series that started in 1912. Portability was its most appealing feature for it measured merely an inch thick when closed. To use it, the lens and shutter were pulled out and allowed to rest on struts. \r\n\r\nBefore the advent of the portable camera in the late 19th century, the taking of photographs was limited to the studio. However portable cameras remained affordable only to the rich until the first decades of the 20th century."
  },
  "nlpDate": "20201201203308",
  "connectorId": 0,
  "tags": {}
}