{
  "id": "2017-00593",
  "title": "Tunic Yoke",
  "source": "Bumblebee",
  "path": "./Data/json/",
  "content": "\n  accession_no_csv: 2017-00593\n\n  Image: \n\n  object_work_type: womenswear costume components\n\n  title_text: Tunic Yoke\n\n  preference: main\n\n  title_language: English\n\n  creation_date: 20th century\n\n  creation_place_original_location: Multan District (Pakistan)\n\n  inscriptions: \n\n  inscription_language: \n\n  shape: irregular\n\n  materials_name: silk (textile) silver thread\n\n  techniques_name: sewing (needleworking technique) embroidering\n\n  object_colour: multicolored\n\n  physical_appearance: This is an embroidered yoke. It is red and yellow\n with silver embroidered geometric patterns. The yellow fabric with silver stitched pattern creates a semicircular collar a the top of the garment. There are no stains seen on the garment.\n\n  subject_terms_1: geometric motifs tunics embroidery (visual works) folk costume\n\n  subject_terms_2: Tunics Motifs Sindhi (South Asian people) Embroidery Ethnic costume Clothing and dress\n\n  subject_terms_3: Indian costumes\n\n  subject_terms_4: \n\n  sgcool_label_text: This is the front of a blouse\n or the yoke of a tunic\n that would be stitched onto a backing. It is a fine example of 20th century zardozi work\n as utilised on clothing in the Sindh region.\n",
  "createdDate": "20201201203308",
  "version": 0,
  "latest": false,
  "roles": [],
  "metadata": {
    "accession_no_csv": "2017-00593",
    "Image": "",
    "object_work_type": "womenswear costume components",
    "title_text": "Tunic Yoke",
    "preference": "main",
    "title_language": "English",
    "creation_date": "20th century",
    "creation_place_original_location": "Multan District (Pakistan)",
    "inscriptions": "",
    "inscription_language": "",
    "shape": "irregular",
    "materials_name": "silk (textile) silver thread",
    "techniques_name": "sewing (needleworking technique) embroidering",
    "object_colour": "multicolored",
    "physical_appearance": "This is an embroidered yoke. It is red and yellow, with silver embroidered geometric patterns. The yellow fabric with silver stitched pattern creates a semicircular collar a the top of the garment. There are no stains seen on the garment.",
    "subject_terms_1": "geometric motifs tunics embroidery (visual works) folk costume",
    "subject_terms_2": "Tunics Motifs Sindhi (South Asian people) Embroidery Ethnic costume Clothing and dress",
    "subject_terms_3": "Indian costumes",
    "subject_terms_4": "",
    "sgcool_label_text": "This is the front of a blouse, or the yoke of a tunic, that would be stitched onto a backing. It is a fine example of 20th century zardozi work, as utilised on clothing in the Sindh region."
  },
  "nlpDate": "20201201203308",
  "connectorId": 0,
  "tags": {}
}