{
  "id": "2017-01033-001",
  "title": "Series of six carte de visite portraits by August Sachtler Photograph of vegetable seller",
  "source": "Bumblebee",
  "path": "./Data/json/",
  "content": "\n  accession_no_csv: 2017-01033-001\n\n  Image: \n\n  object_work_type: black-and-white photographs photographs\n\n  title_text: Series of six carte de visite portraits by August Sachtler Photograph of vegetable seller\n\n  preference: alternate main\n\n  title_language: \n\n  creator_2: August Sachtler of Sachtler \\u0026 Co.\n\n  creator_role: photographers\n\n  creation_date: 1860s\n\n  creation_place_original_location: Singapore\n\n  inscriptions: \n\n  inscription_language: \n\n  shape: rectangular\n\n  materials_name: paper (fiber product)\n\n  techniques_name: photographic processes\n\n  object_colour: black-and-white (colors)\n\n  physical_appearance: This is a black-and-white portrait photograph. It features a vegetable seller. It is a photograph of a man\n wearing a hat\n a white vest\n long shirt\n long pants\n and a wrap cloth around his waist. In front of him are two baskets of vegetables\n tied together with a long stick. The photograph is quite faded and stained. There are no inscriptions\n tears\n or folds seen.\n\n  subject_terms_1: indigenous people ways of life folk costume occupations (livelihoods) portraits\n\n  subject_terms_2: Carte de visite photographs Portrait photography Indigenous people Lifestyles Ethnic costume Occupations\n\n  subject_terms_3: Portrait photography Ethnic costumes\n\n  subject_terms_4: \n\n  sgcool_label_text: \\This is part of a series of small carte de visite format portrait photographs by August Sachtler\n a German photographer who started photographing in Singapore in the early 1860s. The studio details inscribed on the back of these cartes de visite read \\\\A. Sachtler in Singapore\\\\\n",
  "createdDate": "20201120223708",
  "version": 0,
  "latest": false,
  "roles": [],
  "metadata": {
    "accession_no_csv": "2017-01033-001",
    "Image": "",
    "object_work_type": "black-and-white photographs photographs",
    "title_text": "Series of six carte de visite portraits by August Sachtler Photograph of vegetable seller",
    "preference": "alternate main",
    "title_language": "",
    "creator_2": "August Sachtler of Sachtler \u0026 Co.",
    "creator_role": "photographers",
    "creation_date": "1860s",
    "creation_place_original_location": "Singapore",
    "inscriptions": "",
    "inscription_language": "",
    "shape": "rectangular",
    "materials_name": "paper (fiber product)",
    "techniques_name": "photographic processes",
    "object_colour": "black-and-white (colors)",
    "physical_appearance": "This is a black-and-white portrait photograph. It features a vegetable seller. It is a photograph of a man, wearing a hat, a white vest, long shirt, long pants, and a wrap cloth around his waist. In front of him are two baskets of vegetables, tied together with a long stick. The photograph is quite faded and stained. There are no inscriptions, tears, or folds seen.",
    "subject_terms_1": "indigenous people ways of life folk costume occupations (livelihoods) portraits",
    "subject_terms_2": "Carte de visite photographs Portrait photography Indigenous people Lifestyles Ethnic costume Occupations",
    "subject_terms_3": "Portrait photography Ethnic costumes",
    "subject_terms_4": "",
    "sgcool_label_text": "\"This is part of a series of small carte de visite format portrait photographs by August Sachtler, a German photographer who started photographing in Singapore in the early 1860s. The studio details inscribed on the back of these cartes de visite read \"\"A. Sachtler in Singapore\"\""
  },
  "nlpDate": "20201120223708",
  "connectorId": 0,
  "tags": {}
}