{
  "id": "2017-00483-012",
  "title": "Liberte - Merdeka",
  "source": "Bumblebee",
  "path": "./Data/json/",
  "content": "\n  accession_no_csv: 2017-00483-012\n\n  Image: \n\n  object_work_type: linocuts (prints)  artists\\u0027 books (books)\n\n  title_text: Liberte - Merdeka\n\n  preference: main\n\n  title_language: \n\n  creator_2: Popo Iskandar (1927) Srihadi Sudarsono (1932) G. Sidharta Soegijo But Mochtar (1930-1993) Abdul Djalil Pirous (1933) Ahmad Sadali (1924-1987) Mochtar Apin (1923-1994)  Kaboel Soeadi  Affendy Jusuf  Setjadipradja Angkama  Zaini\n\n  creator_1: Iskandar\n Popo Soedarsono\n Srihadi\n 1931- Sidharta\n G. (Gregorius)\n 1932- Pirous\n A. D. (Abdul Djalil)\n 1932-  Sadali\n Ahmad\n 1924-1987 Apin\n Mochtar Suadi\n Kaboel\n 1935- Zaini\n\n  creator_role: artists (visual artists)\n\n  creation_date: 1967\n\n  creation_place_original_location: Bandung (Indonesia)\n\n  styles_periods_indexing_terms: Indonesian (culture or style)\n\n  inscriptions: \n\n  inscription_language: \n\n  shape: Rectangular\n\n  materials_name: paper (fiber product)\n\n  techniques_name: linoleum block printing\n\n  object_colour: black-and-white (colors)\n\n  edition_description: Artist Proof\n\n  physical_appearance: This is a folded page. The page on the left is in French while the right is in Indonesian.\n\n  subject_terms_1: French (language) Indonesian (language)  descriptions (documents)  folio (leaves) poems  poets  freedom  independence\n\n  subject_terms_2: Prints\n Indonesian  French language Indonesian language  Folios  Poets  Poetry  Freedom Independence\n\n  subject_terms_3: Visual arts\n\n  sgcool_label_text: Published in 1967\n Liberte/ Merdeka is a folio of prints produced by artists associated with the Bandung Technological Institute (ITB). This interesting set of prints was essentially the artists’ interpretation of noted Surrealist poet\n Paul Eluard’s poem Liberte. Consisting of the ‘who’s who’ of the ‘Bandung School’ of artists\n this folio of prints can be seen both as an experimental publication in terms of the art-literary collaboration\n and also the promotion of the print-making medium within the Indonesian context.\n",
  "createdDate": "20201120223708",
  "version": 0,
  "latest": false,
  "roles": [],
  "metadata": {
    "accession_no_csv": "2017-00483-012",
    "Image": "",
    "object_work_type": "linocuts (prints)  artists\u0027 books (books)",
    "title_text": "Liberte - Merdeka",
    "preference": "main",
    "title_language": "",
    "creator_2": "Popo Iskandar (1927) Srihadi Sudarsono (1932) G. Sidharta Soegijo But Mochtar (1930-1993) Abdul Djalil Pirous (1933) Ahmad Sadali (1924-1987) Mochtar Apin (1923-1994)  Kaboel Soeadi  Affendy Jusuf  Setjadipradja Angkama  Zaini",
    "creator_1": "Iskandar, Popo Soedarsono, Srihadi, 1931- Sidharta, G. (Gregorius), 1932- Pirous, A. D. (Abdul Djalil), 1932-  Sadali, Ahmad, 1924-1987 Apin, Mochtar Suadi, Kaboel, 1935- Zaini",
    "creator_role": "artists (visual artists)",
    "creation_date": "1967",
    "creation_place_original_location": "Bandung (Indonesia)",
    "styles_periods_indexing_terms": "Indonesian (culture or style)",
    "inscriptions": "",
    "inscription_language": "",
    "shape": "Rectangular",
    "materials_name": "paper (fiber product)",
    "techniques_name": "linoleum block printing",
    "object_colour": "black-and-white (colors)",
    "edition_description": "Artist Proof",
    "physical_appearance": "This is a folded page. The page on the left is in French while the right is in Indonesian.",
    "subject_terms_1": "French (language) Indonesian (language)  descriptions (documents)  folio (leaves) poems  poets  freedom  independence",
    "subject_terms_2": "Prints, Indonesian  French language Indonesian language  Folios  Poets  Poetry  Freedom Independence",
    "subject_terms_3": "Visual arts",
    "sgcool_label_text": "Published in 1967, Liberte/ Merdeka is a folio of prints produced by artists associated with the Bandung Technological Institute (ITB). This interesting set of prints was essentially the artists’ interpretation of noted Surrealist poet, Paul Eluard’s poem Liberte. Consisting of the ‘who’s who’ of the ‘Bandung School’ of artists, this folio of prints can be seen both as an experimental publication in terms of the art-literary collaboration, and also the promotion of the print-making medium within the Indonesian context."
  },
  "nlpDate": "20201120223708",
  "connectorId": 0,
  "tags": {}
}