{
  "id": "2017-00277-001 and 002",
  "title": "Brush-or ink- rest",
  "source": "Bumblebee",
  "path": "./Data/json/",
  "content": "\n  accession_no_csv: 2017-00277-001 and 002\n\n  Image: \n\n  object_work_type: porcelain (visual works) Ceramics (object genre)\n\n  title_text: Brush-or ink- rest\n\n  preference: main\n\n  title_language: \n\n  creation_date: 1644-1911\n\n  creation_place_original_location: China\n\n  styles_periods_indexing_terms: Qing (dynastic styles and periods) Chinese ceramics styles\n\n  inscriptions: \n\n  inscription_language: \n\n  shape: Irregular\n\n  materials_name: clay wood (plant material) ceramic glaze cobalt blue (pigment) porcelain (material)\n\n  techniques_name: firing (technique) underglazing molding (forming) carving (processes) glazing (coating process) throwing (pottery techniques)\n\n  object_colour: monochrome\n\n  physical_appearance: This blue-glazed porcelain elephant has its trunk moulded facing upwards. It rests on a carved wooden stand of the same shape.\n\n  subject_terms_1: Wen ren zoomorphic symbolism\n\n  subject_terms_2: Porcelain\n Chinese Ming- Qing dynasties\n 1368-1912 Monochrome art Brush stands\n\n  subject_terms_3: visual arts Ceramics Decorative arts\n\n  subject_terms_4: \n\n  sgcool_label_text: This blue-glazed porcelain elephant was probably an item made for the scholar’s desk. Apart from serving as a holder to rest a scholar’s brush or inkstick\n this elephant is also a delightful example of a “scholar’s plaything”. The potter has imbued the elephant with life by modelling the animal’s trunk in an upturned and trumpet-like manner. The outline of the animal also takes the form of a double-gourd. The gourd was a popular motif in Chinese art as it was associated with longevity as well as protective and magical properties.\n",
  "createdDate": "20201201203308",
  "version": 0,
  "latest": false,
  "roles": [],
  "metadata": {
    "accession_no_csv": "2017-00277-001 and 002",
    "Image": "",
    "object_work_type": "porcelain (visual works) Ceramics (object genre)",
    "title_text": "Brush-or ink- rest",
    "preference": "main",
    "title_language": "",
    "creation_date": "1644-1911",
    "creation_place_original_location": "China",
    "styles_periods_indexing_terms": "Qing (dynastic styles and periods) Chinese ceramics styles",
    "inscriptions": "",
    "inscription_language": "",
    "shape": "Irregular",
    "materials_name": "clay wood (plant material) ceramic glaze cobalt blue (pigment) porcelain (material)",
    "techniques_name": "firing (technique) underglazing molding (forming) carving (processes) glazing (coating process) throwing (pottery techniques)",
    "object_colour": "monochrome",
    "physical_appearance": "This blue-glazed porcelain elephant has its trunk moulded facing upwards. It rests on a carved wooden stand of the same shape.",
    "subject_terms_1": "Wen ren zoomorphic symbolism",
    "subject_terms_2": "Porcelain, Chinese Ming- Qing dynasties, 1368-1912 Monochrome art Brush stands",
    "subject_terms_3": "visual arts Ceramics Decorative arts",
    "subject_terms_4": "",
    "sgcool_label_text": "This blue-glazed porcelain elephant was probably an item made for the scholar’s desk. Apart from serving as a holder to rest a scholar’s brush or inkstick, this elephant is also a delightful example of a “scholar’s plaything”. The potter has imbued the elephant with life by modelling the animal’s trunk in an upturned and trumpet-like manner. The outline of the animal also takes the form of a double-gourd. The gourd was a popular motif in Chinese art as it was associated with longevity as well as protective and magical properties."
  },
  "nlpDate": "20201201203308",
  "connectorId": 0,
  "tags": {}
}