{
  "id": "2017-00302-030",
  "title": "P.O.W. James Steele Archives: Army acknowledgement form Miscellaneous scraps of paper from P.O.W James Steele Archives (30 pieces)",
  "source": "Bumblebee",
  "path": "./Data/json/",
  "content": "\n  accession_no_csv: 2017-00302-030\n\n  Image: \n\n  object_work_type: forms (documents)\n\n  title_text: P.O.W. James Steele Archives: Army acknowledgement form Miscellaneous scraps of paper from P.O.W James Steele Archives (30 pieces)\n\n  preference: main alternate\n\n  title_language: \n\n  creation_date: 1941-1945\n\n  creation_place_original_location: Singapore\n\n  inscriptions: \n\n  inscription_language: \n\n  shape: rectangular\n\n  materials_name: paper (fiber product)\n\n  techniques_name: printing (process) writing (processes)\n\n  object_colour: multicolored\n\n  physical_appearance: This is an acknowledgement form stating receipt of letter. It is printed in black ink\n with the fields filled in with handwritten inscription in blue ink. There is a registered number at the top left corner. The date is written at the top-right corner. The form is signed at the bottom right corner in black ink\n above a purple stamp. There are no tears or folds seen on this document.\n\n  subject_terms_1: documents (object genre) world wars acknowledgments prisoners of war letters (correspondence)\n\n  subject_terms_2: World War\n 1939-1945 Letters Prisoners of war\n\n  subject_terms_3: Letters war personalities\n\n  subject_terms_4: \n\n  context_1: World War\n 1939-1945 1942-1945 Japanese Occupation\n\n  context_2: occupations (armed conflicts) world wars\n\n  context_3: 1942-1945 1939-1945\n\n  context_4: 1939 1942\n\n  context_5: 1945\n\n  context_6: Singapore Malaya\n\n  context_7: Great Britain. Army. Royal Field Artillery\n\n  context_8: armed forces\n\n  sgcool_label_text: Loose papers from the James Steele\n P.O.W archive that include a symbolic drawing\n Japanese banana money\n map of camp\n administrative papers from Changi prison pre-dating internment\n list of soldiers of a regiment as well as James Steele’s warrant to  join the army. These papers are part of the archive of James Steele\n Royal Artillery (Field) who served in Malaya from January 1941-February 1942\n when interned as a P.O.W at Changi until his release in October 1945.\n",
  "createdDate": "20201201203308",
  "version": 0,
  "latest": false,
  "roles": [],
  "metadata": {
    "accession_no_csv": "2017-00302-030",
    "Image": "",
    "object_work_type": "forms (documents)",
    "title_text": "P.O.W. James Steele Archives: Army acknowledgement form Miscellaneous scraps of paper from P.O.W James Steele Archives (30 pieces)",
    "preference": "main alternate",
    "title_language": "",
    "creation_date": "1941-1945",
    "creation_place_original_location": "Singapore",
    "inscriptions": "",
    "inscription_language": "",
    "shape": "rectangular",
    "materials_name": "paper (fiber product)",
    "techniques_name": "printing (process) writing (processes)",
    "object_colour": "multicolored",
    "physical_appearance": "This is an acknowledgement form stating receipt of letter. It is printed in black ink, with the fields filled in with handwritten inscription in blue ink. There is a registered number at the top left corner. The date is written at the top-right corner. The form is signed at the bottom right corner in black ink, above a purple stamp. There are no tears or folds seen on this document.",
    "subject_terms_1": "documents (object genre) world wars acknowledgments prisoners of war letters (correspondence)",
    "subject_terms_2": "World War, 1939-1945 Letters Prisoners of war",
    "subject_terms_3": "Letters war personalities",
    "subject_terms_4": "",
    "context_1": "World War, 1939-1945 1942-1945 Japanese Occupation",
    "context_2": "occupations (armed conflicts) world wars",
    "context_3": "1942-1945 1939-1945",
    "context_4": "1939 1942",
    "context_5": "1945",
    "context_6": "Singapore Malaya",
    "context_7": "Great Britain. Army. Royal Field Artillery",
    "context_8": "armed forces",
    "sgcool_label_text": "Loose papers from the James Steele, P.O.W archive that include a symbolic drawing, Japanese banana money, map of camp, administrative papers from Changi prison pre-dating internment, list of soldiers of a regiment as well as James Steele’s warrant to  join the army. These papers are part of the archive of James Steele, Royal Artillery (Field) who served in Malaya from January 1941-February 1942, when interned as a P.O.W at Changi until his release in October 1945."
  },
  "nlpDate": "20201201203308",
  "connectorId": 0,
  "tags": {}
}