{"id":"2017-00286","title":"\"Pencil drawing of \"\"The Little House The Little House, Changi Prison Camp","source":"Bumblebee","path":"./Data/json/","content":"accession_no_csv:2017-00286\nImage:\nobject_work_type:drawings (visual works)\ntitle_text:\\Pencil drawing of \\\\The Little House The Little House\n Changi Prison Camp\npreference:Changi Prison Camp”\\ main\ntitle_language:alternate\ncreator_2:\ncreator_1:LBDR McMahon\ncreation_date:illustrators\ncreation_place_original_location:1942\nstyles_periods_indexing_terms:Singapore\ninscription_language:\nscale_type:\nmaterials_name:rectangular\ntechniques_name:paper (fiber product)\nobject_colour:drawing (image-making)\nedition_description:white-and-black (colors)\nsubject_terms_1:This is a pencil drawing featuring a small living space. In the drawing\n there are two tables\n one on the left and one in the center-right. The right table has two stands sitting on top of it on either end. The walls of the space seems to be made of wood panels. The title is written on the bottom-right\n above the signature and date. The edges of the paper are quite torn and folded\n especially on the right corners. The right edge of the drawing is stained and dotted. prisoners of war prison camps\nsubject_terms_2:world wars Prisoners of war Drawing Prisoner-of-war camps\nsubject_terms_3:World War\n 1939-1945 Changi Prison Drawing\nsubject_terms_4:1942-1945 Japanese occupation\ncontext_1:1942-1945 Japanese Occupation\ncontext_2:World War\n 1939-1945 occupations (armed conflicts)\ncontext_3:world wars 1942-1945\ncontext_4:1939-1945 1942\ncontext_5:1939 1945\ncontext_6:1945 Singapore\ncontext_7:Malaya\ncontext_8:Great Britain. Army. Royal Field Artillery\ncontext_9:armed forces","createdDate":"20201119143406","version":0,"latest":false,"roles":[],"metadata":{"accession_no_csv":"2017-00286","Image":"","object_work_type":"drawings (visual works)","title_text":"\"Pencil drawing of \"\"The Little House The Little House, Changi Prison Camp","preference":"Changi Prison Camp”\" main","title_language":"alternate","creator_2":"","creator_1":"LBDR McMahon","creation_date":"illustrators","creation_place_original_location":"1942","styles_periods_indexing_terms":"Singapore","inscription_language":"","scale_type":"","materials_name":"rectangular","techniques_name":"paper (fiber product)","object_colour":"drawing (image-making)","edition_description":"white-and-black (colors)","subject_terms_1":"This is a pencil drawing featuring a small living space. In the drawing, there are two tables, one on the left and one in the center-right. The right table has two stands sitting on top of it on either end. The walls of the space seems to be made of wood panels. The title is written on the bottom-right, above the signature and date. The edges of the paper are quite torn and folded, especially on the right corners. The right edge of the drawing is stained and dotted. prisoners of war prison camps","subject_terms_2":"world wars Prisoners of war Drawing Prisoner-of-war camps","subject_terms_3":"World War, 1939-1945 Changi Prison Drawing","subject_terms_4":"1942-1945 Japanese occupation","context_1":"1942-1945 Japanese Occupation","context_2":"World War, 1939-1945 occupations (armed conflicts)","context_3":"world wars 1942-1945","context_4":"1939-1945 1942","context_5":"1939 1945","context_6":"1945 Singapore","context_7":"Malaya","context_8":"Great Britain. Army. Royal Field Artillery","context_9":"armed forces"},"nlpDate":"20201119143406","connectorId":0,"tags":{}}