{
  "id": "2017-00001",
  "title": "Running Stream",
  "source": "Bumblebee",
  "path": "./Data/json/",
  "content": "\n  accession_no_csv: 2017-00001\n\n  Image: \n\n  object_work_type: ink wash paintings\n\n  title_text: Running Stream\n\n  preference: main\n\n  title_language: \n\n  creator_2: Wu Guanzhong (1919-2010)\n\n  creator_1: Wu\n Guanzhong\n\n  creator_role: artists (visual artists)\n\n  creation_date: 1988\n\n  creation_place_original_location: China\n\n  styles_periods_indexing_terms: Chinese (culture or style)\n\n  inscriptions: \n\n  inscription_language: \n\n  scale_type: N.A\n\n  shape: rectangular\n\n  materials_name: coloured ink Chinese ink paper (fibre product)\n\n  techniques_name: painting (image-making)\n\n  object_colour: multicoloured\n\n  edition_description: N.A\n\n  physical_appearance: This image is a landscape painting that depicts a running stream that cuts across the composition. Several tall trees line this stream. There are two seals; one on the top right hand corner\n whilst the other is on the bottom left. Accompanying the latter\n is the artist\\u0027s signature\n followed by the year of creation\n and lastly a description of the painting in Chinese.\n\n  subject_terms_1: streams landscapes (representations)\n\n  subject_terms_2: Ink painting\n Chinese Rivers Landscapes\n\n  subject_terms_3: visual arts Chinese ink painting Chinese landscape painting\n\n  sgcool_label_text: Wu Guanzhong (1919 - 2010) is one of the most significant artists of 20th century China. He belonged to a generation of Chinese painters who went to France to study art in the 1940s. His distinctive style integrates Western and Chinese art traditions\n setting a new direction for modern Chinese art. Running Stream us a representative work of Wu\\u0027s from the 1980s. Wu painted bold black strokes for the trees\n quick washes for the running stream and included his iconic dots of colours for flowers and plants. From his inscription\n it is also indicated that this was a scene from the bottom of the Jade Dragon Mountain\n a subject that Wu revisits often in his artistic practice.\n",
  "createdDate": "20201201203308",
  "version": 0,
  "latest": false,
  "roles": [],
  "metadata": {
    "accession_no_csv": "2017-00001",
    "Image": "",
    "object_work_type": "ink wash paintings",
    "title_text": "Running Stream",
    "preference": "main",
    "title_language": "",
    "creator_2": "Wu Guanzhong (1919-2010)",
    "creator_1": "Wu, Guanzhong",
    "creator_role": "artists (visual artists)",
    "creation_date": "1988",
    "creation_place_original_location": "China",
    "styles_periods_indexing_terms": "Chinese (culture or style)",
    "inscriptions": "",
    "inscription_language": "",
    "scale_type": "N.A",
    "shape": "rectangular",
    "materials_name": "coloured ink Chinese ink paper (fibre product)",
    "techniques_name": "painting (image-making)",
    "object_colour": "multicoloured",
    "edition_description": "N.A",
    "physical_appearance": "This image is a landscape painting that depicts a running stream that cuts across the composition. Several tall trees line this stream. There are two seals; one on the top right hand corner, whilst the other is on the bottom left. Accompanying the latter, is the artist\u0027s signature, followed by the year of creation, and lastly a description of the painting in Chinese.",
    "subject_terms_1": "streams landscapes (representations)",
    "subject_terms_2": "Ink painting, Chinese Rivers Landscapes",
    "subject_terms_3": "visual arts Chinese ink painting Chinese landscape painting",
    "sgcool_label_text": "Wu Guanzhong (1919 - 2010) is one of the most significant artists of 20th century China. He belonged to a generation of Chinese painters who went to France to study art in the 1940s. His distinctive style integrates Western and Chinese art traditions, setting a new direction for modern Chinese art. Running Stream us a representative work of Wu\u0027s from the 1980s. Wu painted bold black strokes for the trees, quick washes for the running stream and included his iconic dots of colours for flowers and plants. From his inscription, it is also indicated that this was a scene from the bottom of the Jade Dragon Mountain, a subject that Wu revisits often in his artistic practice."
  },
  "nlpDate": "20201201203308",
  "connectorId": 0,
  "tags": {}
}