{
  "id": "2017-00539\r\n\r\n",
  "title": "Ancestor figure Hampatong",
  "source": "Bumblebee",
  "path": "./Data/json/",
  "content": "\n  accession_no_csv: 2017-00539\\r\\n\\r\\n\n\n  Image: \n\n  object_work_type: fetish figures\n\n  title_text: Ancestor figure Hampatong\n\n  preference: main alternate\n\n  title_language: \n\n  creation_date: 19th century or earlier\n\n  creation_place_original_location: Kalimantan Barat (Indonesia)\n\n  inscriptions: \n\n  inscription_language: \n\n  shape: irregular?\n\n  materials_name: wood (plant material)\n\n  techniques_name: carving (processes)\n\n  object_colour: brown (colour)\n\n  physical_appearance: This is a figural sculpture raised on a stump. The figure stands with his/her leg apart\n and arms around the hips. The body is darkened brown\n while the shoulder and head of the figure is of a lighter brown.\n\n  subject_terms_1: magic ancestor worship\n\n  subject_terms_2: Dayak (Indonesian people) Ancestor worship Art\n Dayak Fetishes (Ceremonial objects) Protection magic Sculpture Figurative art\n\n  subject_terms_3: Religious life and practices Sculpture\n\n  subject_terms_4: \n",
  "createdDate": "20201125084518",
  "version": 0,
  "latest": false,
  "roles": [],
  "metadata": {
    "accession_no_csv": "2017-00539\r\n\r\n",
    "Image": "",
    "object_work_type": "fetish figures",
    "title_text": "Ancestor figure Hampatong",
    "preference": "main alternate",
    "title_language": "",
    "creation_date": "19th century or earlier",
    "creation_place_original_location": "Kalimantan Barat (Indonesia)",
    "inscriptions": "",
    "inscription_language": "",
    "shape": "irregular?",
    "materials_name": "wood (plant material)",
    "techniques_name": "carving (processes)",
    "object_colour": "brown (colour)",
    "physical_appearance": "This is a figural sculpture raised on a stump. The figure stands with his/her leg apart, and arms around the hips. The body is darkened brown, while the shoulder and head of the figure is of a lighter brown.",
    "subject_terms_1": "magic ancestor worship",
    "subject_terms_2": "Dayak (Indonesian people) Ancestor worship Art, Dayak Fetishes (Ceremonial objects) Protection magic Sculpture Figurative art",
    "subject_terms_3": "Religious life and practices Sculpture",
    "subject_terms_4": ""
  },
  "nlpDate": "20201125084518",
  "connectorId": 0,
  "tags": {}
}