{
  "id": "2017-00812",
  "title": "Origin",
  "source": "Bumblebee",
  "path": "./Data/json/",
  "content": "\n  accession_no_csv: 2017-00812\n\n  Image: \n\n  object_work_type: ink wash paintings\n\n  title_text: Origin\n\n  preference: main\n\n  title_language: \n\n  creator_2: Shengtao Zhuang\n\n  creator_1: Zhuang\n Shengtao\n 1944-\n\n  creator_role: artists (visual artists)\n\n  creation_date: Undated\n\n  creation_place_original_location: Singapore China\n\n  styles_periods_indexing_terms: Chinese (culture or style)\n\n  inscriptions: \n\n  inscription_language: \n\n  shape: Rectangular\n\n  materials_name: paper (fiber product) Chinese ink\n\n  techniques_name: painting (image-making)\n\n  object_colour: black-and-white (colour)\n\n  physical_appearance: This is a Chinese calligraphic ink work. It is composed of thick\n vigorous and swift brush strokes that cover the entire paper. It is framed by a brown frame. The artist\\u0027s seal can be found at the top left corner.\n\n  subject_terms_1: negative space\n\n  subject_terms_2: Ink painting\n Chinese Emptiness\n\n  subject_terms_3: visual arts Chinese ink painting\n\n  sgcool_label_text: Zhuang Shengtao  (b. 1944\n Guandong province\n China) is a noted Chinese ink and calligraphy artist who has been affiliated with contemporary Chinese ink development in Singapore. Currently residing in Suzhou China\n he had a history of studying and exhibiting in Singapore. He studied art at the Nanyang Academy of Fine Arts\n Singapore and was tutored by the Singapore ink master Shi Xiang Tuo. A Nanyang University graduate\n he pursued further studies at the University of Nice\n France and the Monterey Institute of International Studies\n California USA in the 1980s. He also studied printmaking at the Cornish College of Arts\n Seattle in 1988 and obtained his Masters of Fine Art at the University of Washington in 1990.\\r\\nThis monumental ink work exemplifies Zhuang’s distillation of calligraphic and ink brush work and the aesthetic sensibilities of American Expressionism. In particular\n Zhuang found affinity with the practice of Jackson Pollock\n whose works he encountered directly and closely at the museums with his move to the USA in 1987. Through this interface\n Zhuang explored compositions that were bolder in scale and more complex in composition – producing depth and nuances in tonal values.  \\r\\n \\r\\nThe vigour and improvisational quality of Zhuang’s brushwork belies the discipline and compositional decisions determining the balance between ink and void. The notion of ‘Origin’ also captures the theme of Zhuang’s artistic preoccupations in probing both Chinese and western canons of art-making. Trained and mentored by Shi Xiang Tuo\n Zhuang had risen to attention through his calligraphy and the principles of the calligraphic brush work have permeated his ink paintings. \\r\\n\n",
  "createdDate": "20201201203308",
  "version": 0,
  "latest": false,
  "roles": [],
  "metadata": {
    "accession_no_csv": "2017-00812",
    "Image": "",
    "object_work_type": "ink wash paintings",
    "title_text": "Origin",
    "preference": "main",
    "title_language": "",
    "creator_2": "Shengtao Zhuang",
    "creator_1": "Zhuang, Shengtao, 1944-",
    "creator_role": "artists (visual artists)",
    "creation_date": "Undated",
    "creation_place_original_location": "Singapore China",
    "styles_periods_indexing_terms": "Chinese (culture or style)",
    "inscriptions": "",
    "inscription_language": "",
    "shape": "Rectangular",
    "materials_name": "paper (fiber product) Chinese ink",
    "techniques_name": "painting (image-making)",
    "object_colour": "black-and-white (colour)",
    "physical_appearance": "This is a Chinese calligraphic ink work. It is composed of thick, vigorous and swift brush strokes that cover the entire paper. It is framed by a brown frame. The artist\u0027s seal can be found at the top left corner.",
    "subject_terms_1": "negative space",
    "subject_terms_2": "Ink painting, Chinese Emptiness",
    "subject_terms_3": "visual arts Chinese ink painting",
    "sgcool_label_text": "Zhuang Shengtao  (b. 1944, Guandong province, China) is a noted Chinese ink and calligraphy artist who has been affiliated with contemporary Chinese ink development in Singapore. Currently residing in Suzhou China, he had a history of studying and exhibiting in Singapore. He studied art at the Nanyang Academy of Fine Arts, Singapore and was tutored by the Singapore ink master Shi Xiang Tuo. A Nanyang University graduate, he pursued further studies at the University of Nice, France and the Monterey Institute of International Studies, California USA in the 1980s. He also studied printmaking at the Cornish College of Arts, Seattle in 1988 and obtained his Masters of Fine Art at the University of Washington in 1990.\r\nThis monumental ink work exemplifies Zhuang’s distillation of calligraphic and ink brush work and the aesthetic sensibilities of American Expressionism. In particular, Zhuang found affinity with the practice of Jackson Pollock, whose works he encountered directly and closely at the museums with his move to the USA in 1987. Through this interface, Zhuang explored compositions that were bolder in scale and more complex in composition – producing depth and nuances in tonal values.  \r\n \r\nThe vigour and improvisational quality of Zhuang’s brushwork belies the discipline and compositional decisions determining the balance between ink and void. The notion of ‘Origin’ also captures the theme of Zhuang’s artistic preoccupations in probing both Chinese and western canons of art-making. Trained and mentored by Shi Xiang Tuo, Zhuang had risen to attention through his calligraphy and the principles of the calligraphic brush work have permeated his ink paintings. \r\n"
  },
  "nlpDate": "20201201203308",
  "connectorId": 0,
  "tags": {}
}