{"id":"2017-00115","title":"Lim Bo Seng in his final days of imprisonment ???????","source":"Bumblebee","path":"./Data/json/","content":"accession_no_csv:2017-00115\nImage:\nobject_work_type:paintings (visual works)\ntitle_text:Lim Bo Seng in his final days of imprisonment ???????\npreference:main alternate\ntitle_language:\ncreator_2:Tan Chong Tee\ncreator_1:Chen\n Chongzhi\n 1916-\ncreator_role:artists (visual artists)\ncreation_date:2002\ncreation_place_original_location:Singapore\ninscriptions:\ninscription_language:\nshape:rectangular\nmaterials_name:paper (fiber product) ink colour (pigment)\ntechniques_name:painting (image-making)\nobject_colour:multicolored\nphysical_appearance:This is a painting featuring the artist\\u0027s depiction of Lim Bo Seng\\u0027s trials in his final days of imprisonment. The painting features two portraits of Lim Bo Seng\\u0027s face\n with some scenes of him being tortured in the prisoners-of-war camp at the bottom-left. There are some inscriptions at the top of the painting as well as at the bottom-right.\nsubject_terms_1:world wars depictions (visual works) resistance movements torturing scroll paintings prisoners of war Chinese scripts\nsubject_terms_2:Painting World War\n 1939-1945 Great Britain. Army. Force 136 Force 136 (Guerilla movement) Chen\n Chongzhi\n 1916- Torture Prisoners of war Lim\n Bo Seng\n 1909-1944\nsubject_terms_3:Painting Force 136 (Guerilla movement) Tan\n Chong Tee 1942-1945 Japanese occupation Lim\n Bo Seng\nsubject_terms_4:\nsgcool_label_text:This painting belongs to part of a collection of artefacts related to the World War II underground resistance movement known as Force 136. The collection of materials was gathered by Tan Chong Tee (1916- 2012)\n who was a key member of this resistance group. The collection consists of original materials belonging to Tan and other members of Force 136 dating from the 1940s to new materials reproduced from memory by Tan Chong Tee\n which date from mid 1990s to early 2000s.\\r\\n\\r\\nForce 136 was set up in July 1942 as part of the British Special Operations Executive (SOE). It recruited and trained local guerrillas to gather intelligence and create an underground spy network to support planned British invasion of Japanese-occupied Malaya. \\r\\n\\r\\nThis painting is painted from the memory of Tan Chong Tee and depicts the trials underwent by war hero\n Lim Bo Seng.","createdDate":"20201119143406","version":0,"latest":false,"roles":[],"metadata":{"accession_no_csv":"2017-00115","Image":"","object_work_type":"paintings (visual works)","title_text":"Lim Bo Seng in his final days of imprisonment ???????","preference":"main alternate","title_language":"","creator_2":"Tan Chong Tee","creator_1":"Chen, Chongzhi, 1916-","creator_role":"artists (visual artists)","creation_date":"2002","creation_place_original_location":"Singapore","inscriptions":"","inscription_language":"","shape":"rectangular","materials_name":"paper (fiber product) ink colour (pigment)","techniques_name":"painting (image-making)","object_colour":"multicolored","physical_appearance":"This is a painting featuring the artist\u0027s depiction of Lim Bo Seng\u0027s trials in his final days of imprisonment. The painting features two portraits of Lim Bo Seng\u0027s face, with some scenes of him being tortured in the prisoners-of-war camp at the bottom-left. There are some inscriptions at the top of the painting as well as at the bottom-right.","subject_terms_1":"world wars depictions (visual works) resistance movements torturing scroll paintings prisoners of war Chinese scripts","subject_terms_2":"Painting World War, 1939-1945 Great Britain. Army. Force 136 Force 136 (Guerilla movement) Chen, Chongzhi, 1916- Torture Prisoners of war Lim, Bo Seng, 1909-1944","subject_terms_3":"Painting Force 136 (Guerilla movement) Tan, Chong Tee 1942-1945 Japanese occupation Lim, Bo Seng","subject_terms_4":"","sgcool_label_text":"This painting belongs to part of a collection of artefacts related to the World War II underground resistance movement known as Force 136. The collection of materials was gathered by Tan Chong Tee (1916- 2012), who was a key member of this resistance group. The collection consists of original materials belonging to Tan and other members of Force 136 dating from the 1940s to new materials reproduced from memory by Tan Chong Tee, which date from mid 1990s to early 2000s.\r\n\r\nForce 136 was set up in July 1942 as part of the British Special Operations Executive (SOE). It recruited and trained local guerrillas to gather intelligence and create an underground spy network to support planned British invasion of Japanese-occupied Malaya. \r\n\r\nThis painting is painted from the memory of Tan Chong Tee and depicts the trials underwent by war hero, Lim Bo Seng."},"nlpDate":"20201119143406","connectorId":0,"tags":{}}