{"id":"2017-00026","title":"Unknown","source":"Bumblebee","path":"./Data/json/","content":"accession_no_csv:2017-00026\nImage:\nobject_work_type:colour prints (photographs)  photographic prints\ntitle_text:Unknown\npreference:main\ntitle_language:\ncreator_2:Koon\n Sang Ho\ncreator_role:photographers\ncreation_date:c.1960\ncreation_place_original_location:Singapore\ninscriptions:\ninscription_language:\nshape:rectangular\nmaterials_name:photographic paper\ntechniques_name:photographic printing techniques colour photography\nobject_colour:multicoloured\nphysical_appearance:This is a coloured print and the image captures a bustling open air roadside market place. Vendors spread out their items on a piece of cloth on the ground and sit behind them so as to meet the gaze of the buyer. Electric cords are seen hanging across buildings. On the verso there are two labels; one being the photographer\\u0027s studio label (with its address) and the other by The Song Heng Association Singapore \\u0026 Overseas Hainanese Artists Art Exhibition 2010.\nsubject_terms_1:marketplaces roadsides flea markets street vendors  colour photography  genre (visual works)\nsubject_terms_2:Marketplaces Street vendors  Photography\n Artistic  Genre prints\nsubject_terms_3:visual arts  Artistic photography\ncontext_1:An exhibition was held to commemorate 70 years of establishment\ncontext_2:exhibitions (events)\ncontext_3:30th January to 28th February 2010\ncontext_4:30th January 2010\ncontext_5:28th February 2010\ncontext_6:National Library (Singapore)\ncontext_7:The Song Heng Association\ncontext_8:planners\ncontext_20:Address found on the photography studio\\u0027s label (verso)\ncontext_21:82 Macpherson Lane #09-23\n Singapore 360082  Sungei Road Flea Market  11 Purvis Street\n Singapore 188590\ncontext_22:c.1960\ncontext_23:1955\ncontext_24:1965\nsgcool_label_text:Ho Koon Sang was a member of the Photographic Society of Singapore and an Associate of the Royal Photographic Society in London. This is a very early and unique print shot on colour film.","createdDate":"20201018182636","version":0,"latest":false,"roles":[],"metadata":{"accession_no_csv":"2017-00026","Image":"","object_work_type":"colour prints (photographs)  photographic prints","title_text":"Unknown","preference":"main","title_language":"","creator_2":"Koon, Sang Ho","creator_role":"photographers","creation_date":"c.1960","creation_place_original_location":"Singapore","inscriptions":"","inscription_language":"","shape":"rectangular","materials_name":"photographic paper","techniques_name":"photographic printing techniques colour photography","object_colour":"multicoloured","physical_appearance":"This is a coloured print and the image captures a bustling open air roadside market place. Vendors spread out their items on a piece of cloth on the ground and sit behind them so as to meet the gaze of the buyer. Electric cords are seen hanging across buildings. On the verso there are two labels; one being the photographer\u0027s studio label (with its address) and the other by The Song Heng Association Singapore \u0026 Overseas Hainanese Artists Art Exhibition 2010.","subject_terms_1":"marketplaces roadsides flea markets street vendors  colour photography  genre (visual works)","subject_terms_2":"Marketplaces Street vendors  Photography, Artistic  Genre prints","subject_terms_3":"visual arts  Artistic photography","context_1":"An exhibition was held to commemorate 70 years of establishment","context_2":"exhibitions (events)","context_3":"30th January to 28th February 2010","context_4":"30th January 2010","context_5":"28th February 2010","context_6":"National Library (Singapore)","context_7":"The Song Heng Association","context_8":"planners","context_20":"Address found on the photography studio\u0027s label (verso)","context_21":"82 Macpherson Lane #09-23, Singapore 360082  Sungei Road Flea Market  11 Purvis Street, Singapore 188590","context_22":"c.1960","context_23":"1955","context_24":"1965","sgcool_label_text":"Ho Koon Sang was a member of the Photographic Society of Singapore and an Associate of the Royal Photographic Society in London. This is a very early and unique print shot on colour film."},"nlpDate":"20201018182636","connectorId":0,"tags":{}}