{"id":"2017-00811","title":"Men’s maroon short jacket with fur lining","source":"Bumblebee","path":"./Data/json/","content":"accession_no_csv:2017-00811\nImage:\nobject_work_type:silks (costume by material)  jackets (garments)\ntitle_text:Men’s maroon short jacket with fur lining\npreference:main\ntitle_language:\ncreation_date:1920s-1930s\ncreation_place_original_location:Hong Kong (China)  Hong Kong (China)\nstyles_periods_indexing_terms:Chinese (culture or style)\ninscriptions:\ninscription_language:\nshape:T-shaped?\nmaterials_name:silk (textile)  fur (hair material)\ntechniques_name:sewing (needleworking technique)\nobject_colour:maroon (colour)\nphysical_appearance:This is a maroon short jacket that buttons to the proper right of the garment. It has a fur lining in the inner side of the jacket.\nsubject_terms_1:casual wear  folk costume menswear winter clothing\nsubject_terms_2:Jackets Ethnic costume Silk  Men\\u0027s clothing  Fur\nsubject_terms_3:Chinese costumes\ncontext_20:Bullion Trading Company “Yee Shing”\ncontext_21:20 Canal Road in Singapore\ncontext_22:1930s\ncontext_23:1930\ncontext_24:1939\nsgcool_label_text:This short jacket is known as a ‘magua’ ?? and was worn over a long robe (‘changshan’ or ‘changpao’) in the early 20th century in China and Hong Kong. This fur-lined jacket would have been used during the winter season. \\r\\n\\r\\nIt belonged to Mr Kaan Tat Choi\n who was a successful businessman in the bullion business. Mr Kaan expanded his business from Hong Kong to Malaya in the 1920s\n acquiring several rubber plantations along the east coast of Malaya. He also opened a bullion trading company called “Yee Shing” at 20 Canal Road in Singapore in the 1930s\\r\\n","createdDate":"20201119143406","version":0,"latest":false,"roles":[],"metadata":{"accession_no_csv":"2017-00811","Image":"","object_work_type":"silks (costume by material)  jackets (garments)","title_text":"Men’s maroon short jacket with fur lining","preference":"main","title_language":"","creation_date":"1920s-1930s","creation_place_original_location":"Hong Kong (China)  Hong Kong (China)","styles_periods_indexing_terms":"Chinese (culture or style)","inscriptions":"","inscription_language":"","shape":"T-shaped?","materials_name":"silk (textile)  fur (hair material)","techniques_name":"sewing (needleworking technique)","object_colour":"maroon (colour)","physical_appearance":"This is a maroon short jacket that buttons to the proper right of the garment. It has a fur lining in the inner side of the jacket.","subject_terms_1":"casual wear  folk costume menswear winter clothing","subject_terms_2":"Jackets Ethnic costume Silk  Men\u0027s clothing  Fur","subject_terms_3":"Chinese costumes","context_20":"Bullion Trading Company “Yee Shing”","context_21":"20 Canal Road in Singapore","context_22":"1930s","context_23":"1930","context_24":"1939","sgcool_label_text":"This short jacket is known as a ‘magua’ ?? and was worn over a long robe (‘changshan’ or ‘changpao’) in the early 20th century in China and Hong Kong. This fur-lined jacket would have been used during the winter season. \r\n\r\nIt belonged to Mr Kaan Tat Choi, who was a successful businessman in the bullion business. Mr Kaan expanded his business from Hong Kong to Malaya in the 1920s, acquiring several rubber plantations along the east coast of Malaya. He also opened a bullion trading company called “Yee Shing” at 20 Canal Road in Singapore in the 1930s\r\n"},"nlpDate":"20201119143406","connectorId":0,"tags":{}}