{"id":"2017-00650","title":"Cushion cover","source":"Bumblebee","path":"./Data/json/","content":"accession_no_csv:2017-00650\nImage:\nobject_work_type:coverings for soft furnishings\ntitle_text:Cushion cover\npreference:main\ntitle_language:\ncreation_date:Not indicated\ncreation_place_original_location:Gujarat (India)\ninscriptions:\ninscription_language:\nshape:square (shape)\nmaterials_name:glass (material) textile materials\ntechniques_name:sewing (needleworking technique) embroidering\nobject_colour:multicolored\nphysical_appearance:This is a cushion cover. It has an orange underside\n with a square cotton embroidery featured in the front. The cover is decorated with stylized embroidery of figures and animals such as horses and birds\n surrounding a large tree in the center. The design is bordered by a repeated tree pattern.\nsubject_terms_1:embroidery (visual works) foliage (motif) flower (motif) birds (motifs) beadwork (visual works) cushions\nsubject_terms_2:Pillowcases Embroidery Motifs Cushions\nsubject_terms_3:Textile art and design\nsubject_terms_4:","createdDate":"20201018182636","version":0,"latest":false,"roles":[],"metadata":{"accession_no_csv":"2017-00650","Image":"","object_work_type":"coverings for soft furnishings","title_text":"Cushion cover","preference":"main","title_language":"","creation_date":"Not indicated","creation_place_original_location":"Gujarat (India)","inscriptions":"","inscription_language":"","shape":"square (shape)","materials_name":"glass (material) textile materials","techniques_name":"sewing (needleworking technique) embroidering","object_colour":"multicolored","physical_appearance":"This is a cushion cover. It has an orange underside, with a square cotton embroidery featured in the front. The cover is decorated with stylized embroidery of figures and animals such as horses and birds, surrounding a large tree in the center. The design is bordered by a repeated tree pattern.","subject_terms_1":"embroidery (visual works) foliage (motif) flower (motif) birds (motifs) beadwork (visual works) cushions","subject_terms_2":"Pillowcases Embroidery Motifs Cushions","subject_terms_3":"Textile art and design","subject_terms_4":""},"nlpDate":"20201018182636","connectorId":0,"tags":{}}