{"id":"2017-00359","title":"Kain panjang","source":"Bumblebee","path":"./Data/json/","content":"accession_no_csv:2017-00359\nImage:\nobject_work_type:folk costume batik art\ntitle_text:Kain panjang\npreference:main\ntitle_language:\ncreator_2:Kok Sing Oey\ncreator_role:textile designers\ncreation_date:1941\ncreation_place_original_location:Pekalongan (Indonesia)\nstyles_periods_indexing_terms:Peranakan\ninscriptions:\ninscription_language:\nshape:rectangular\nmaterials_name:cotton (textile)\ntechniques_name:batik\nobject_colour:multicolored\nphysical_appearance:This is a batik kain panjang. It is blue\n with lighter blue and white designs. The kain panjang features large bouquets interspersed with birds and butterflies. On the left side of the batik\n the bouquet motifs are set against a dense patterned background\n with repeated floral blooms. The right side of the batik features a more sparse design\n with the bouquets set against a plain blue background.\nsubject_terms_1:Peranakan flower (motif) birds (motifs) cultural diffusion\nsubject_terms_2:Batik Ethnic costume Peranakan (Asian people) Motifs Culture diffusion\nsubject_terms_3:Batik Peranakan costumes\nsubject_terms_4:Kain panjang\nsgcool_label_text:This batik is structured in the pagi-sore format\n comprising two different but related designs on each half of the kain panjang.  One side comprises large bouquets of carnations interspersed with butterflies and birds.  This buketan design is also applied to the other side although the large rose bouquets are surrounded by densely packed background patterns.  This batik comes from the family collection of Oey Kok Sing (1896-1966)\n the second in three generations of documented batik-makers in Pekalongan.  Her later batik designs attest to her virtuosity in technique and inventive colour palette.  Her repertoire of tiny isen-isen motifs (filler motifs within the outlines of the key motifs) in particular\n exudes a strong sense of artistic individuality\n possibly informed by modernist designs on European printed cloths.  Her treatment of floral bouquets is also charactertistic of the undulating and curving lines of the Art Noveau style that was introduced in the northern coast of Java by the Europeans.","createdDate":"20201018182636","version":0,"latest":false,"roles":[],"metadata":{"accession_no_csv":"2017-00359","Image":"","object_work_type":"folk costume batik art","title_text":"Kain panjang","preference":"main","title_language":"","creator_2":"Kok Sing Oey","creator_role":"textile designers","creation_date":"1941","creation_place_original_location":"Pekalongan (Indonesia)","styles_periods_indexing_terms":"Peranakan","inscriptions":"","inscription_language":"","shape":"rectangular","materials_name":"cotton (textile)","techniques_name":"batik","object_colour":"multicolored","physical_appearance":"This is a batik kain panjang. It is blue, with lighter blue and white designs. The kain panjang features large bouquets interspersed with birds and butterflies. On the left side of the batik, the bouquet motifs are set against a dense patterned background, with repeated floral blooms. The right side of the batik features a more sparse design, with the bouquets set against a plain blue background.","subject_terms_1":"Peranakan flower (motif) birds (motifs) cultural diffusion","subject_terms_2":"Batik Ethnic costume Peranakan (Asian people) Motifs Culture diffusion","subject_terms_3":"Batik Peranakan costumes","subject_terms_4":"Kain panjang","sgcool_label_text":"This batik is structured in the pagi-sore format, comprising two different but related designs on each half of the kain panjang.  One side comprises large bouquets of carnations interspersed with butterflies and birds.  This buketan design is also applied to the other side although the large rose bouquets are surrounded by densely packed background patterns.  This batik comes from the family collection of Oey Kok Sing (1896-1966), the second in three generations of documented batik-makers in Pekalongan.  Her later batik designs attest to her virtuosity in technique and inventive colour palette.  Her repertoire of tiny isen-isen motifs (filler motifs within the outlines of the key motifs) in particular, exudes a strong sense of artistic individuality, possibly informed by modernist designs on European printed cloths.  Her treatment of floral bouquets is also charactertistic of the undulating and curving lines of the Art Noveau style that was introduced in the northern coast of Java by the Europeans."},"nlpDate":"20201018182636","connectorId":0,"tags":{}}