{
  "id": "2017-00258",
  "title": "The Goddess emanates from the essence of all the gods",
  "source": "Bumblebee",
  "path": "./Data/json/",
  "content": "\n  accession_no_csv: 2017-00258\n\n  Image: \n\n  object_work_type: watercolours (paintings)\n\n  title_text: The Goddess emanates from the essence of all the gods\n\n  preference: main\n\n  title_language: \n\n  creation_place_original_location: Himachal Pradesh (India)\n\n  styles_periods_indexing_terms: Indian (South Asian)\n\n  inscriptions: \n\n  inscription_language: \n\n  shape: rectangular\n\n  materials_name: paper (fibre product) watercolour paper watercolour (paint)\n\n  techniques_name: watercolour painting (technique)\n\n  object_colour: multicoloured\n\n  physical_appearance: This watercolour painting depicts a scene from the Devi Mahatmya (Glory of the Goddess). Surrounding the central goddess figure are various gods. They are adorned with crowns and are of different skin colours. Swift strokes of differing thickness emanate from the circle of gods towards the central figure\n contributing to the culmination of her bodily form.\n\n  subject_terms_1: religious art religious texts religious symbolism deities religious visual works religious characters religious concepts\n\n  subject_terms_2: Puranas. Markandeyapurana. Devimahatmya Indra (Hindu deity) Hindu goddesses Religious art Hindu symbolism Hindu gods Gods\n\n  subject_terms_3: visual arts Hinduism Religious life and practices watercolour painting\n\n  subject_terms_4: \n\n  sgcool_label_text: The painting depicts a scene from the Devi Mahatmya (Glory of the Goddess)\n written between fifth and sixth century as part of the Markandeya Purana. The text indicates that all goddesses are in fact different aspects of one\n ultimate goddess. She is said to have emerged from the combined energy of all the gods. \\r\\n\\r\\nThe story states that Indra and the other gods had been expelled from their heaven by the buffalo-headed demon Mahishasura\n and they appealed to Vishnu and Shiva for help. The anger of all the gods is channelled into pure energy that unites into a female form\n thus creating the Great Goddess. She goes on to kill the buffalo demon Mahishasura\n and the gods are restored to Indra’s heaven. \\r\\n\\r\\nThe main Hindu gods are recognisable\n ash-white Shiva\n Indra covered in eyes\n and blue Vishnu on the left\n with four-headed Brahma on the right. The blank background indicates that the event happens outside of space and time. \\r\\n\n",
  "createdDate": "20201125084523",
  "version": 0,
  "latest": false,
  "roles": [],
  "metadata": {
    "accession_no_csv": "2017-00258",
    "Image": "",
    "object_work_type": "watercolours (paintings)",
    "title_text": "The Goddess emanates from the essence of all the gods",
    "preference": "main",
    "title_language": "",
    "creation_place_original_location": "Himachal Pradesh (India)",
    "styles_periods_indexing_terms": "Indian (South Asian)",
    "inscriptions": "",
    "inscription_language": "",
    "shape": "rectangular",
    "materials_name": "paper (fibre product) watercolour paper watercolour (paint)",
    "techniques_name": "watercolour painting (technique)",
    "object_colour": "multicoloured",
    "physical_appearance": "This watercolour painting depicts a scene from the Devi Mahatmya (Glory of the Goddess). Surrounding the central goddess figure are various gods. They are adorned with crowns and are of different skin colours. Swift strokes of differing thickness emanate from the circle of gods towards the central figure, contributing to the culmination of her bodily form.",
    "subject_terms_1": "religious art religious texts religious symbolism deities religious visual works religious characters religious concepts",
    "subject_terms_2": "Puranas. Markandeyapurana. Devimahatmya Indra (Hindu deity) Hindu goddesses Religious art Hindu symbolism Hindu gods Gods",
    "subject_terms_3": "visual arts Hinduism Religious life and practices watercolour painting",
    "subject_terms_4": "",
    "sgcool_label_text": "The painting depicts a scene from the Devi Mahatmya (Glory of the Goddess), written between fifth and sixth century as part of the Markandeya Purana. The text indicates that all goddesses are in fact different aspects of one, ultimate goddess. She is said to have emerged from the combined energy of all the gods. \r\n\r\nThe story states that Indra and the other gods had been expelled from their heaven by the buffalo-headed demon Mahishasura, and they appealed to Vishnu and Shiva for help. The anger of all the gods is channelled into pure energy that unites into a female form, thus creating the Great Goddess. She goes on to kill the buffalo demon Mahishasura, and the gods are restored to Indra’s heaven. \r\n\r\nThe main Hindu gods are recognisable, ash-white Shiva, Indra covered in eyes, and blue Vishnu on the left, with four-headed Brahma on the right. The blank background indicates that the event happens outside of space and time. \r\n"
  },
  "nlpDate": "20201125084523",
  "connectorId": 0,
  "tags": {}
}