{"id":"2017-00031","title":"Toothache","source":"Bumblebee","path":"./Data/json/","content":"accession_no_csv:2017-00031\nImage:\nobject_work_type:black-and-white prints (photographs) gelatin silver prints  photographic prints\ntitle_text:Toothache\npreference:main\ntitle_language:\ncreator_2:Koon\n Sang Ho\ncreator_role:photographers\ncreation_date:c.1956\ncreation_place_original_location:Singapore\ninscriptions:\ninscription_language:\nshape:rectangular\nmaterials_name:gelatin  paper (fibre product)  silver sulfide  baryta paper\ntechniques_name:gelatin silver process photographic printing techniques black-and-white photography\nobject_colour:black-and-white (colours)\nphysical_appearance:This print is a pictorial of a young boy who is pointing to a tooth with his left pinky. He looks afar in a distance; attention turned away from the viewer. There is some discolouration on the four corners of the print\n and the backing on which it is mounted on has brown spots as well. On the bottom right corner there is an RPS Associate 1957 embossed\n and on the verso\n the photographer\\u0027s chop as well as the title of the work are found.\nsubject_terms_1:teeth (animal components)  children (people by age group)\nsubject_terms_2:Photography\n Artistic  Portrait photography  Children\nsubject_terms_3:visual arts  Artistic photography Children\ncontext_21:40 Holloway  Lane\n Singapore 7\ncontext_22:c.1956\ncontext_23:1951\ncontext_24:1961\nsgcool_label_text:Ho Koon Sang was a member of the Photographic Society of Singapore and an Associate of the Royal Photographic Society in London. This photograph was part of a set of 12 prints sent to the Royal Photographic Society in 1956.","createdDate":"20201018182636","version":0,"latest":false,"roles":[],"metadata":{"accession_no_csv":"2017-00031","Image":"","object_work_type":"black-and-white prints (photographs) gelatin silver prints  photographic prints","title_text":"Toothache","preference":"main","title_language":"","creator_2":"Koon, Sang Ho","creator_role":"photographers","creation_date":"c.1956","creation_place_original_location":"Singapore","inscriptions":"","inscription_language":"","shape":"rectangular","materials_name":"gelatin  paper (fibre product)  silver sulfide  baryta paper","techniques_name":"gelatin silver process photographic printing techniques black-and-white photography","object_colour":"black-and-white (colours)","physical_appearance":"This print is a pictorial of a young boy who is pointing to a tooth with his left pinky. He looks afar in a distance; attention turned away from the viewer. There is some discolouration on the four corners of the print, and the backing on which it is mounted on has brown spots as well. On the bottom right corner there is an RPS Associate 1957 embossed, and on the verso, the photographer\u0027s chop as well as the title of the work are found.","subject_terms_1":"teeth (animal components)  children (people by age group)","subject_terms_2":"Photography, Artistic  Portrait photography  Children","subject_terms_3":"visual arts  Artistic photography Children","context_21":"40 Holloway  Lane, Singapore 7","context_22":"c.1956","context_23":"1951","context_24":"1961","sgcool_label_text":"Ho Koon Sang was a member of the Photographic Society of Singapore and an Associate of the Royal Photographic Society in London. This photograph was part of a set of 12 prints sent to the Royal Photographic Society in 1956."},"nlpDate":"20201018182636","connectorId":0,"tags":{}}