{
  "id": "2017-00073-001 and 002 ",
  "title": "Bridal tunic",
  "source": "Bumblebee",
  "path": "./Data/json/",
  "content": "\n  accession_no_csv: 2017-00073-001 and 002 \n\n  Image: \n\n  object_work_type: wedding clothes tunics\n\n  title_text: Bridal tunic\n\n  preference: main\n\n  title_language: \n\n  creation_date: Early 20th century\n\n  creation_place_original_location: Indonesia\n\n  inscriptions: \n\n  inscription_language: \n\n  materials_name: silk (textile) gold thread\n\n  techniques_name: embroidering\n\n  object_colour: multicoloured\n\n  physical_appearance: This is a red tunic with elaborate embroidery done with gold thread. It is T-shaped\n and has broad\n straight sleeves. Central to the tunic is a large red lotus motif surrounded by phoenixes and peonies. It is paired with a skirt which has a frontal and back panel joined together at the waist; each panel has either a dragon or a phoenix motif that is framed by floral borders.\n\n  subject_terms_1: phoenixes weddings (ceremonies) Peranakan plant-derived motifs dragons lotus (motif)\n\n  subject_terms_2: Lotus in art Peranakan (Asian people) Wedding costume Floral decorations\n\n  subject_terms_3: Religious life and practices\n\n  sgcool_label_text: This skirt is made up of two pieces\n a frontal panel and a back panel joined together at the waist.  Each panel comprises either an auspicious dragon or phoenix motif.  Framed by brightly coloured floral borders\n the dragon and phoenix are worked in gold thread couchings.  The front-facing coiled dragon motif was possibly inspired by Ming dynasty imperial court robes\n with the dragon symbolising the emperor’s centrality in the universe.  Dragons are seldom seen in Peranakan embroidery\n whereas the phoenix\n signifying loyalty and good fortune\n is more common.  Here\n the dragon represents the yang or male principle while the phoenix represents the complementary yin or female principle. The bride wore this skirt together with a tunic as part of her twelve-day Peranakan wedding.\n",
  "createdDate": "20201125084529",
  "version": 0,
  "latest": false,
  "roles": [],
  "metadata": {
    "accession_no_csv": "2017-00073-001 and 002 ",
    "Image": "",
    "object_work_type": "wedding clothes tunics",
    "title_text": "Bridal tunic",
    "preference": "main",
    "title_language": "",
    "creation_date": "Early 20th century",
    "creation_place_original_location": "Indonesia",
    "inscriptions": "",
    "inscription_language": "",
    "materials_name": "silk (textile) gold thread",
    "techniques_name": "embroidering",
    "object_colour": "multicoloured",
    "physical_appearance": "This is a red tunic with elaborate embroidery done with gold thread. It is T-shaped, and has broad, straight sleeves. Central to the tunic is a large red lotus motif surrounded by phoenixes and peonies. It is paired with a skirt which has a frontal and back panel joined together at the waist; each panel has either a dragon or a phoenix motif that is framed by floral borders.",
    "subject_terms_1": "phoenixes weddings (ceremonies) Peranakan plant-derived motifs dragons lotus (motif)",
    "subject_terms_2": "Lotus in art Peranakan (Asian people) Wedding costume Floral decorations",
    "subject_terms_3": "Religious life and practices",
    "sgcool_label_text": "This skirt is made up of two pieces, a frontal panel and a back panel joined together at the waist.  Each panel comprises either an auspicious dragon or phoenix motif.  Framed by brightly coloured floral borders, the dragon and phoenix are worked in gold thread couchings.  The front-facing coiled dragon motif was possibly inspired by Ming dynasty imperial court robes, with the dragon symbolising the emperor’s centrality in the universe.  Dragons are seldom seen in Peranakan embroidery, whereas the phoenix, signifying loyalty and good fortune, is more common.  Here, the dragon represents the yang or male principle while the phoenix represents the complementary yin or female principle. The bride wore this skirt together with a tunic as part of her twelve-day Peranakan wedding."
  },
  "nlpDate": "20201125084529",
  "connectorId": 0,
  "tags": {}
}