{"id":"2017-00664\r\n\r\n","title":"Print from Journal Des Voyages on the various native types of Singapore","source":"Bumblebee","path":"./Data/json/","content":"accession_no_csv:2017-00664\\r\\n\\r\\n\nImage:\nobject_work_type:colour prints (prints)  lithographs\ntitle_text:Print from Journal Des Voyages on the various native types of Singapore\npreference:main\ntitle_language:\ncreator_2:Not specified\ncreator_1:Allers\n Christian Wilhelm\n 1857-1915\ncreator_role:artists (visual artists)\ncreation_date:29-Sep-13\ncreation_place_original_location:Paris (France)\ninscriptions:\ninscription_language:\nshape:Rectangular\nmaterials_name:paper (fibre product)  lithographic ink\ntechniques_name:hand colouring  printing techniques\nobject_colour:multicoloured\nedition_description:First\nphysical_appearance:\\This is a page from the magazine \\\\Journal des Voyages\\\\ (as seen in the heading). Its title is \\\\Ethnographie d\\u0027Extreme-Orient Les Tyoes de Singapour.\\\\ There are coloured images of men and children in turbans running diagonally across the page; dividing the text into two sections. \\\nsubject_terms_1:Orientalism  ethnicity  cultural pluralism travel sketches  weeklies (publications)\nsubject_terms_2:Lithography Publications Periodicals Publishing Cultural pluralism Orientalism  Singapore  East Asia  Prints  Allers\n Christian Wilhelm\n 1857-1915\nsubject_terms_3:Periodicals  Visual arts\nsgcool_label_text:\\This is a page taken from the Parisian weekly magazine Journal des Voyages. It contains writeups on the \\\\Ethnography of the Far East\\\\ and \\\\The Types of Singapore\\\\","createdDate":"20201018182636","version":0,"latest":false,"roles":[],"metadata":{"accession_no_csv":"2017-00664\r\n\r\n","Image":"","object_work_type":"colour prints (prints)  lithographs","title_text":"Print from Journal Des Voyages on the various native types of Singapore","preference":"main","title_language":"","creator_2":"Not specified","creator_1":"Allers, Christian Wilhelm, 1857-1915","creator_role":"artists (visual artists)","creation_date":"29-Sep-13","creation_place_original_location":"Paris (France)","inscriptions":"","inscription_language":"","shape":"Rectangular","materials_name":"paper (fibre product)  lithographic ink","techniques_name":"hand colouring  printing techniques","object_colour":"multicoloured","edition_description":"First","physical_appearance":"\"This is a page from the magazine \"\"Journal des Voyages\"\" (as seen in the heading). Its title is \"\"Ethnographie d\u0027Extreme-Orient Les Tyoes de Singapour.\"\" There are coloured images of men and children in turbans running diagonally across the page; dividing the text into two sections. \"","subject_terms_1":"Orientalism  ethnicity  cultural pluralism travel sketches  weeklies (publications)","subject_terms_2":"Lithography Publications Periodicals Publishing Cultural pluralism Orientalism  Singapore  East Asia  Prints  Allers, Christian Wilhelm, 1857-1915","subject_terms_3":"Periodicals  Visual arts","sgcool_label_text":"\"This is a page taken from the Parisian weekly magazine Journal des Voyages. It contains writeups on the \"\"Ethnography of the Far East\"\" and \"\"The Types of Singapore\"\""},"nlpDate":"20201018182636","connectorId":0,"tags":{}}