{"id":"2017-00860 ","title":"Bride-to-be","source":"Bumblebee","path":"./Data/json/","content":"accession_no_csv:2017-00860 \nImage:\nobject_work_type:woodcuts (prints)\ntitle_text:Bride-to-be\npreference:main\ntitle_language:\ncreator_2:See Cheen Tee\ncreator_1:See\n Cheen Tee\n 1928-1996\ncreator_role:Artist (visual artists)\ncreation_date:1966\ncreation_place_original_location:Singapore\ninscriptions:\ninscription_language:\nshape:Rectangular\nmaterials_name:wood (plant material)  coloured ink  paper (fiber product)\ntechniques_name:woodcut (process)\nobject_colour:multicoloured\nedition_description:8th edition\nphysical_appearance:This is a coloured woodcut print depicting an elderly lady combing the hair of a younger lady who\n in this image\n is squatting. She holds a mirror in her right hand\n and has three bangles on her left hand. A basket with yellow and red flowers and a used scissor lie in the foreground.\nsubject_terms_1:combs (grooming tools) hand mirrors  weddings (ceremonies)  flower (motif)  cultural ceremonies  hairstyling\nsubject_terms_2:Cats in art  Combs Flowers in art  Wedding  wood-engraving  Hairdressing\nsubject_terms_3:visual arts\nsgcool_label_text:See Cheen Tee (1928 - 1996) was born in Terengganu\n Malaysia. He came to Singapore in 1947 to pursue a formal Chinese education and completed his secondary education at the Catholic High School in 1948. He then joined NAFA in 1950 and was taught by the pioneer artists which include Cheong Soo Pieng\n Chen Wen Hsi\n Chen Chong Swee and Lim Hak Tai.\\r\\n\\r\\nSee Cheen Tee was adept at various mediums which include oil painting\n watercolour\n and sculpture but he was most known for his woodcuts. He started producing black-and-white woodcuts in the mid-1950s where his depictions of the social realities of life in Malaya back then\n were amongst the finest he produced. Subsequently he started producing coloured woodblock prints from the mid-1960s. The latter were generally more decorative but his draftsmanship and illustrations continued to be of the highest quality\n if not\n more refined.","createdDate":"20201119143406","version":0,"latest":false,"roles":[],"metadata":{"accession_no_csv":"2017-00860 ","Image":"","object_work_type":"woodcuts (prints)","title_text":"Bride-to-be","preference":"main","title_language":"","creator_2":"See Cheen Tee","creator_1":"See, Cheen Tee, 1928-1996","creator_role":"Artist (visual artists)","creation_date":"1966","creation_place_original_location":"Singapore","inscriptions":"","inscription_language":"","shape":"Rectangular","materials_name":"wood (plant material)  coloured ink  paper (fiber product)","techniques_name":"woodcut (process)","object_colour":"multicoloured","edition_description":"8th edition","physical_appearance":"This is a coloured woodcut print depicting an elderly lady combing the hair of a younger lady who, in this image, is squatting. She holds a mirror in her right hand, and has three bangles on her left hand. A basket with yellow and red flowers and a used scissor lie in the foreground.","subject_terms_1":"combs (grooming tools) hand mirrors  weddings (ceremonies)  flower (motif)  cultural ceremonies  hairstyling","subject_terms_2":"Cats in art  Combs Flowers in art  Wedding  wood-engraving  Hairdressing","subject_terms_3":"visual arts","sgcool_label_text":"See Cheen Tee (1928 - 1996) was born in Terengganu, Malaysia. He came to Singapore in 1947 to pursue a formal Chinese education and completed his secondary education at the Catholic High School in 1948. He then joined NAFA in 1950 and was taught by the pioneer artists which include Cheong Soo Pieng, Chen Wen Hsi, Chen Chong Swee and Lim Hak Tai.\r\n\r\nSee Cheen Tee was adept at various mediums which include oil painting, watercolour, and sculpture but he was most known for his woodcuts. He started producing black-and-white woodcuts in the mid-1950s where his depictions of the social realities of life in Malaya back then, were amongst the finest he produced. Subsequently he started producing coloured woodblock prints from the mid-1960s. The latter were generally more decorative but his draftsmanship and illustrations continued to be of the highest quality, if not, more refined."},"nlpDate":"20201119143406","connectorId":0,"tags":{}}