{
  "id": "2017-00030",
  "title": "Unity is Strength",
  "source": "Bumblebee",
  "path": "./Data/json/",
  "content": "\n  accession_no_csv: 2017-00030\n\n  Image: \n\n  object_work_type: black-and-white prints (photographs) gelatin silver prints  photographic prints\n\n  title_text: Unity is Strength\n\n  preference: main\n\n  title_language: \n\n  creator_2: Koon\n Sang Ho\n\n  creator_role: photographers\n\n  creation_date: c.1956\n\n  creation_place_original_location: Singapore\n\n  inscriptions: \n\n  inscription_language: \n\n  shape: rectangular\n\n  materials_name: gelatin  paper (fibre product)  silver sulfide  baryta paper\n\n  techniques_name: gelatin silver process photographic printing techniques black-and-white photography\n\n  object_colour: black-and-white (colours)\n\n  physical_appearance: This print depicts a group of five men reeling in a fishing net on a sandy seashore. The print shows signs of discolouration as yellow hues can be seen in patches and along the edges of the print. The backing on which it is mounted on has yellow-brown spots as well.  In the bottom right corner\n there is an RPS Associate 1957 symbol embossed. On the verso\n there is the artist\\u0027s photography studio chop\n the number\n and title of the work.\n\n  subject_terms_1: fishing seashores fishermen (people) rural communities\n\n  subject_terms_2: Photography\n Artistic  Rural  Fishing Seashore\n\n  subject_terms_3: visual arts  Artistic photography\n\n  context_21: 40 Holloway  Lane\n Singapore 7\n\n  context_22: c.1956\n\n  context_23: 1951\n\n  context_24: 1961\n\n  sgcool_label_text: Ho Koon Sang was a member of the Photographic Society of Singapore and an Associate of the Royal Photographic Society in London. This photograph was part of a set of 12 prints sent to the Royal Photographic Society in 1956.\n",
  "createdDate": "20201120223707",
  "version": 0,
  "latest": false,
  "roles": [],
  "metadata": {
    "accession_no_csv": "2017-00030",
    "Image": "",
    "object_work_type": "black-and-white prints (photographs) gelatin silver prints  photographic prints",
    "title_text": "Unity is Strength",
    "preference": "main",
    "title_language": "",
    "creator_2": "Koon, Sang Ho",
    "creator_role": "photographers",
    "creation_date": "c.1956",
    "creation_place_original_location": "Singapore",
    "inscriptions": "",
    "inscription_language": "",
    "shape": "rectangular",
    "materials_name": "gelatin  paper (fibre product)  silver sulfide  baryta paper",
    "techniques_name": "gelatin silver process photographic printing techniques black-and-white photography",
    "object_colour": "black-and-white (colours)",
    "physical_appearance": "This print depicts a group of five men reeling in a fishing net on a sandy seashore. The print shows signs of discolouration as yellow hues can be seen in patches and along the edges of the print. The backing on which it is mounted on has yellow-brown spots as well.  In the bottom right corner, there is an RPS Associate 1957 symbol embossed. On the verso, there is the artist\u0027s photography studio chop, the number, and title of the work.",
    "subject_terms_1": "fishing seashores fishermen (people) rural communities",
    "subject_terms_2": "Photography, Artistic  Rural  Fishing Seashore",
    "subject_terms_3": "visual arts  Artistic photography",
    "context_21": "40 Holloway  Lane, Singapore 7",
    "context_22": "c.1956",
    "context_23": "1951",
    "context_24": "1961",
    "sgcool_label_text": "Ho Koon Sang was a member of the Photographic Society of Singapore and an Associate of the Royal Photographic Society in London. This photograph was part of a set of 12 prints sent to the Royal Photographic Society in 1956."
  },
  "nlpDate": "20201120223707",
  "connectorId": 0,
  "tags": {}
}