{
  "id": "2017-00051",
  "title": "A Chart of the West Coast of Sumatra A Chart of the West Coast of Sumatra",
  "source": "Bumblebee",
  "path": "./Data/json/",
  "content": "\n  accession_no_csv: 2017-00051\n\n  Image: \n\n  object_work_type: aquatints (prints) marine charts navigation charts nautical charts\n\n  title_text: A Chart of the West Coast of Sumatra A Chart of the West Coast of Sumatra\n\n  preference: main main\n\n  title_language: \n\n  creator_2: Captain Joseph Huddart Laurie \\u0026 Whittle Captain Joseph Huddart\n\n  creator_1: Huddart\n Joseph\n 1741 - 1816 Laurie \\u0026 Whittle Huddart\n Joseph\n 1741-1816\n\n  creator_role: hydrographers publishers hydrographers\n\n  creation_date: 1790s 1790s\n\n  creation_place_original_location: London (England) London (England)\n\n  styles_periods_indexing_terms: NA NA\n\n  inscriptions: \n\n  inscription_language: \n\n  scale_type: 1 : 1 Nautical Mile 1 : 5 Nautical Miles NA\n\n  shape: rectangular Rectangular\n\n  materials_name: paper (fiber product) paper (fiber product)\n\n  techniques_name: aquatint (printing process) copper engraving (printing process)\n\n  object_colour: white (colour) black-and-white (colours)\n\n  edition_description: NA NA\n\n  physical_appearance: \\This marine chart is rectangular in shape and its perimeter is marked by a black line. The chart is divided into three sections\n with one part occupying the left half while the right side is halved into two smaller areas. There are two different sets of scales used in this map\n with 1 : 5 Nautical miles being used for the larger section and 1 : 1 Nautical mile for both the smaller sections. The title\n \\\\A Chart of the West Coast of Sumatra\\\\ This is a chart of the West coast of Sumatra.  It also has a plan of Poolo Bay\n and that of Rat Island. These have been charted by Joseph Huddart.\n\n  subject_terms_1: and its sub-title islands (landforms) bays (bodies of water) maps (documents) coastlines  hydrography\n\n  subject_terms_2: \\\\From Old Bencoolen to Buffaloe Point containing the Road of Bencoolen and Poolo Bay\\\\ prints East India Company Nautical charts Colonization Sumatra (Indonesia) Bengkulu (Indonesia) Islands Coasts East India Company  Laurie \\u0026 Whittle  Nautical charts Hydrography  Coasts Sumatra (Indonesia)\n\n  subject_terms_3: are stated on the upper left hand side of the chart. The words \\\\By Joseph Huddart\\\\ are displayed in all three sections of the chart. The title of the top section at the right hand side of the chart states \\\\Plan of Rat Island\\\\. The title of the bottom section at the right hand side of the chart states \\\\Plan of Poolo Bay\\\\. At the bottom of the chart East India Company\n\n  subject_terms_4: it states \\\\London. Printed for Rob Sayer \\u0026 Jn. Bennett NA\n\n  context_1: Map \\u0026 Sea Chart sellers. N°. 53 Fleet Street as the Act directs. 20 April 1778. There are longitudes present in all the sections of the chart.\\ NA\n\n  context_2: colonial settlements NA\n\n  context_3: Aquatint NA\n\n  context_4: East India Company NA\n\n  context_5: NA NA\n\n  context_6: NA NA\n\n  context_7: NA NA\n\n  context_8: NA NA\n\n  context_9: NA NA\n\n  context_10: NA NA\n\n  context_11: NA NA\n\n  context_12: NA NA\n\n  context_13: NA NA\n\n  context_14: NA NA\n\n  context_15: NA NA\n\n  context_16: NA NA\n\n  context_17: NA NA\n\n  context_18: NA NA\n\n  context_19: NA NA\n\n  context_20: NA NA\n\n  context_21: NA NA\n\n  context_22: NA NA\n\n  context_23: NA NA\n\n  context_24: NA NA\n\n  sgcool_label_text: NA This chart of the southwestern coast of Sumatra was published by Laurie \\u0026 Whittle\n a commercial publisher of sea charts in the late eighteenth and early nineteeth centuries. Depicting the British East India Company (EIC) harbour of Bencoolen\n the chart was based on the navigational work of Captain Joseph Huddart\n hydrographer for the EIC.\n",
  "createdDate": "20201120223707",
  "version": 0,
  "latest": false,
  "roles": [],
  "metadata": {
    "accession_no_csv": "2017-00051",
    "Image": "",
    "object_work_type": "aquatints (prints) marine charts navigation charts nautical charts",
    "title_text": "A Chart of the West Coast of Sumatra A Chart of the West Coast of Sumatra",
    "preference": "main main",
    "title_language": "",
    "creator_2": "Captain Joseph Huddart Laurie \u0026 Whittle Captain Joseph Huddart",
    "creator_1": "Huddart, Joseph, 1741 - 1816 Laurie \u0026 Whittle Huddart, Joseph, 1741-1816",
    "creator_role": "hydrographers publishers hydrographers",
    "creation_date": "1790s 1790s",
    "creation_place_original_location": "London (England) London (England)",
    "styles_periods_indexing_terms": "NA NA",
    "inscriptions": "",
    "inscription_language": "",
    "scale_type": "1 : 1 Nautical Mile 1 : 5 Nautical Miles NA",
    "shape": "rectangular Rectangular",
    "materials_name": "paper (fiber product) paper (fiber product)",
    "techniques_name": "aquatint (printing process) copper engraving (printing process)",
    "object_colour": "white (colour) black-and-white (colours)",
    "edition_description": "NA NA",
    "physical_appearance": "\"This marine chart is rectangular in shape and its perimeter is marked by a black line. The chart is divided into three sections, with one part occupying the left half while the right side is halved into two smaller areas. There are two different sets of scales used in this map, with 1 : 5 Nautical miles being used for the larger section and 1 : 1 Nautical mile for both the smaller sections. The title, \"\"A Chart of the West Coast of Sumatra\"\" This is a chart of the West coast of Sumatra.  It also has a plan of Poolo Bay, and that of Rat Island. These have been charted by Joseph Huddart.",
    "subject_terms_1": "and its sub-title islands (landforms) bays (bodies of water) maps (documents) coastlines  hydrography",
    "subject_terms_2": "\"\"From Old Bencoolen to Buffaloe Point containing the Road of Bencoolen and Poolo Bay\"\" prints East India Company Nautical charts Colonization Sumatra (Indonesia) Bengkulu (Indonesia) Islands Coasts East India Company  Laurie \u0026 Whittle  Nautical charts Hydrography  Coasts Sumatra (Indonesia)",
    "subject_terms_3": "are stated on the upper left hand side of the chart. The words \"\"By Joseph Huddart\"\" are displayed in all three sections of the chart. The title of the top section at the right hand side of the chart states \"\"Plan of Rat Island\"\". The title of the bottom section at the right hand side of the chart states \"\"Plan of Poolo Bay\"\". At the bottom of the chart East India Company",
    "subject_terms_4": "it states \"\"London. Printed for Rob Sayer \u0026 Jn. Bennett NA",
    "context_1": "Map \u0026 Sea Chart sellers. N°. 53 Fleet Street as the Act directs. 20 April 1778. There are longitudes present in all the sections of the chart.\" NA",
    "context_2": "colonial settlements NA",
    "context_3": "Aquatint NA",
    "context_4": "East India Company NA",
    "context_5": "NA NA",
    "context_6": "NA NA",
    "context_7": "NA NA",
    "context_8": "NA NA",
    "context_9": "NA NA",
    "context_10": "NA NA",
    "context_11": "NA NA",
    "context_12": "NA NA",
    "context_13": "NA NA",
    "context_14": "NA NA",
    "context_15": "NA NA",
    "context_16": "NA NA",
    "context_17": "NA NA",
    "context_18": "NA NA",
    "context_19": "NA NA",
    "context_20": "NA NA",
    "context_21": "NA NA",
    "context_22": "NA NA",
    "context_23": "NA NA",
    "context_24": "NA NA",
    "sgcool_label_text": "NA This chart of the southwestern coast of Sumatra was published by Laurie \u0026 Whittle, a commercial publisher of sea charts in the late eighteenth and early nineteeth centuries. Depicting the British East India Company (EIC) harbour of Bencoolen, the chart was based on the navigational work of Captain Joseph Huddart, hydrographer for the EIC."
  },
  "nlpDate": "20201120223707",
  "connectorId": 0,
  "tags": {}
}