{
  "id": "2017-00620",
  "title": "Malay Brass Rose Water Sprinkler",
  "source": "Bumblebee",
  "path": "./Data/json/",
  "content": "\n  accession_no_csv: 2017-00620\n\n  Image: \n\n  object_work_type: sprinkler flasks\n\n  title_text: Malay Brass Rose Water Sprinkler\n\n  preference: main\n\n  title_language: \n\n  creation_date: 18th century\n\n  creation_place_original_location: Malay Peninsula\n\n  inscriptions: \n\n  inscription_language: \n\n  shape: irregular\n\n  materials_name: brass (alloy)\n\n  techniques_name: forging (metal forming) engraving (action)\n\n  object_colour: bronze (color)\n\n  physical_appearance: This is a brass sprinkler flask. It has a tall\n slender neck with a wide foot and body. The base\n body and nozzle are decorated with concentric rings. The neck does not have any carved rings. There are some minor scratches on the sprinkler\n especially on the neck. There are no inscriptions or decorative motifs seen.\n\n  subject_terms_1: ceremonial objects brasswork (visual works) customs (social concepts)\n\n  subject_terms_2: Brasswork Ceremonial objects Manners and customs\n\n  subject_terms_3: Malay decorative arts\n\n  subject_terms_4: \n",
  "createdDate": "20201201203308",
  "version": 0,
  "latest": false,
  "roles": [],
  "metadata": {
    "accession_no_csv": "2017-00620",
    "Image": "",
    "object_work_type": "sprinkler flasks",
    "title_text": "Malay Brass Rose Water Sprinkler",
    "preference": "main",
    "title_language": "",
    "creation_date": "18th century",
    "creation_place_original_location": "Malay Peninsula",
    "inscriptions": "",
    "inscription_language": "",
    "shape": "irregular",
    "materials_name": "brass (alloy)",
    "techniques_name": "forging (metal forming) engraving (action)",
    "object_colour": "bronze (color)",
    "physical_appearance": "This is a brass sprinkler flask. It has a tall, slender neck with a wide foot and body. The base, body and nozzle are decorated with concentric rings. The neck does not have any carved rings. There are some minor scratches on the sprinkler, especially on the neck. There are no inscriptions or decorative motifs seen.",
    "subject_terms_1": "ceremonial objects brasswork (visual works) customs (social concepts)",
    "subject_terms_2": "Brasswork Ceremonial objects Manners and customs",
    "subject_terms_3": "Malay decorative arts",
    "subject_terms_4": ""
  },
  "nlpDate": "20201201203308",
  "connectorId": 0,
  "tags": {}
}