{
  "id": "2017-00896",
  "title": "Majie’s trousers with light blue waistband",
  "source": "Bumblebee",
  "path": "./Data/json/",
  "content": "\n  accession_no_csv: 2017-00896\n\n  Image: \n\n  object_work_type: womenswear folk costume\n\n  title_text: Majie’s trousers with light blue waistband\n\n  preference: main\n\n  title_language: \n\n  creation_date: Mid-20th century\n\n  creation_place_original_location: Singapore\n\n  styles_periods_indexing_terms: Chinese (culture or style)\n\n  inscriptions: \n\n  inscription_language: \n\n  shape: irregular\n\n  materials_name: silk (textile)\n\n  techniques_name: sewing (needleworking technique)\n\n  object_colour: multicolored\n\n  physical_appearance: This is a pair of trousers. It is black in colour\n with repeated floral motifs embossed onto the fabric. It features a printed light blue waistband. The trousers are mid-length.\n\n  subject_terms_1: maids (servants) trousers flower (motif)\n\n  subject_terms_2: Motifs Ethnic costume Pants Household employees\n\n  subject_terms_3: Chinese costumes Lu\n Earl Ming-Teh\n\n  subject_terms_4: \n\n  sgcool_label_text: This pair of trousers belonged to a majie\n a Cantonese female domestic helper. The trousers are wide and loose-fitting\n with a printed cotton light blue waistband to secure the garment.\\r\\n\\r\\nMajie is derived from a Shun Tak term (ma cheh) which means mother and sister. As this group of women had taken a vow never to marry\n the term Majie alludes to their spinsterhood and refers to their work taking care of children. Majies took a vow of celibacy and sought to reflect the same purity and modesty in plain outfits. They typically wore a samfoo uniform consisting of a white mandarin-collar top and black trousers.\n",
  "createdDate": "20201125084515",
  "version": 0,
  "latest": false,
  "roles": [],
  "metadata": {
    "accession_no_csv": "2017-00896",
    "Image": "",
    "object_work_type": "womenswear folk costume",
    "title_text": "Majie’s trousers with light blue waistband",
    "preference": "main",
    "title_language": "",
    "creation_date": "Mid-20th century",
    "creation_place_original_location": "Singapore",
    "styles_periods_indexing_terms": "Chinese (culture or style)",
    "inscriptions": "",
    "inscription_language": "",
    "shape": "irregular",
    "materials_name": "silk (textile)",
    "techniques_name": "sewing (needleworking technique)",
    "object_colour": "multicolored",
    "physical_appearance": "This is a pair of trousers. It is black in colour, with repeated floral motifs embossed onto the fabric. It features a printed light blue waistband. The trousers are mid-length.",
    "subject_terms_1": "maids (servants) trousers flower (motif)",
    "subject_terms_2": "Motifs Ethnic costume Pants Household employees",
    "subject_terms_3": "Chinese costumes Lu, Earl Ming-Teh",
    "subject_terms_4": "",
    "sgcool_label_text": "This pair of trousers belonged to a majie, a Cantonese female domestic helper. The trousers are wide and loose-fitting, with a printed cotton light blue waistband to secure the garment.\r\n\r\nMajie is derived from a Shun Tak term (ma cheh) which means mother and sister. As this group of women had taken a vow never to marry, the term Majie alludes to their spinsterhood and refers to their work taking care of children. Majies took a vow of celibacy and sought to reflect the same purity and modesty in plain outfits. They typically wore a samfoo uniform consisting of a white mandarin-collar top and black trousers."
  },
  "nlpDate": "20201125084515",
  "connectorId": 0,
  "tags": {}
}