{
  "id": "2017-00600",
  "title": "Trousers",
  "source": "Bumblebee",
  "path": "./Data/json/",
  "content": "\n  accession_no_csv: 2017-00600\n\n  Image: \n\n  object_work_type: trousers\n\n  title_text: Trousers\n\n  preference: main\n\n  title_language: English\n\n  creation_date: 20th century\n\n  creation_place_original_location: Kachchh (India)\n\n  inscriptions: \n\n  inscription_language: \n\n  shape: irregular\n\n  materials_name: silk (textile)\n\n  techniques_name: sewing (needleworking technique)\n\n  object_colour: multicolored\n\n  physical_appearance: This is a pair of trousers. It is vertically striped red\n yellow and black\n with two strips of green in the middle. The trouserts are mid-length.\n\n  subject_terms_1: folk costume stripes\n\n  subject_terms_2: Ethnic costume Pants Stripes Dhangar (South Asian people)\n\n  subject_terms_3: Indian costumes\n\n  subject_terms_4: \n\n  sgcool_label_text: Trousers made from handwoven Mashroo silk\n belonging to the Ahir community of eastern Kutch.\n",
  "createdDate": "20201125084517",
  "version": 0,
  "latest": false,
  "roles": [],
  "metadata": {
    "accession_no_csv": "2017-00600",
    "Image": "",
    "object_work_type": "trousers",
    "title_text": "Trousers",
    "preference": "main",
    "title_language": "English",
    "creation_date": "20th century",
    "creation_place_original_location": "Kachchh (India)",
    "inscriptions": "",
    "inscription_language": "",
    "shape": "irregular",
    "materials_name": "silk (textile)",
    "techniques_name": "sewing (needleworking technique)",
    "object_colour": "multicolored",
    "physical_appearance": "This is a pair of trousers. It is vertically striped red, yellow and black, with two strips of green in the middle. The trouserts are mid-length.",
    "subject_terms_1": "folk costume stripes",
    "subject_terms_2": "Ethnic costume Pants Stripes Dhangar (South Asian people)",
    "subject_terms_3": "Indian costumes",
    "subject_terms_4": "",
    "sgcool_label_text": "Trousers made from handwoven Mashroo silk, belonging to the Ahir community of eastern Kutch."
  },
  "nlpDate": "20201125084517",
  "connectorId": 0,
  "tags": {}
}