{
  "id": "2017-00481-001 to 0026",
  "title": "Linoleographs- Baharoedin \u0026 Mochtar Apin",
  "source": "Bumblebee",
  "path": "./Data/json/",
  "content": "\n  accession_no_csv: 2017-00481-001 to 0026\n\n  Image: \n\n  object_work_type: artists\\u0027 books (books) linocuts (prints)\n\n  title_text: Linoleographs- Baharoedin \\u0026 Mochtar Apin\n\n  preference: main\n\n  title_language: \n\n  creator_2: Mochtar Apin Baharudin?\n\n  creator_1: Apin\n Mochtar\n\n  creator_role: artists (visual artists)\n\n  creation_date: 1946\n\n  creation_place_original_location: Bandung (Indonesia)\n\n  styles_periods_indexing_terms: Indonesian (culture or style)\n\n  inscriptions: \n\n  inscription_language: \n\n  shape: Rectangular\n\n  materials_name: paper (fiber product)\n\n  techniques_name: linoleum block printing\n\n  object_colour: black-and-white (colors)\n\n  physical_appearance: \\This is a folio of linoleographs. The cover is labelled \\\\Linoleographs\n\n  subject_terms_1: Baharoedin propaganda identity\n\n  subject_terms_2: Prints\n Indonesian Mochatar Apin 1946\\\\ \\ Propaganda Independence Artists\\u0027 books\n\n  subject_terms_3: National Identity independence\n\n  subject_terms_4: Merdeka\n\n  context_1: visual arts\n\n  context_3: First anniversary of Indonesia\\u0027s Declaration of Independence\n\n  context_4: national holidays\n\n  context_5: 17-Aug-46\n\n  context_6: 17-Aug-46\n\n  context_7: 17-Aug-46\n\n  context_8: Indonesia\n\n  context_9: Indonesian Government ?\n\n  context_10: commissioners (people who order works)\n",
  "createdDate": "20201125084520",
  "version": 0,
  "latest": false,
  "roles": [],
  "metadata": {
    "accession_no_csv": "2017-00481-001 to 0026",
    "Image": "",
    "object_work_type": "artists\u0027 books (books) linocuts (prints)",
    "title_text": "Linoleographs- Baharoedin \u0026 Mochtar Apin",
    "preference": "main",
    "title_language": "",
    "creator_2": "Mochtar Apin Baharudin?",
    "creator_1": "Apin, Mochtar",
    "creator_role": "artists (visual artists)",
    "creation_date": "1946",
    "creation_place_original_location": "Bandung (Indonesia)",
    "styles_periods_indexing_terms": "Indonesian (culture or style)",
    "inscriptions": "",
    "inscription_language": "",
    "shape": "Rectangular",
    "materials_name": "paper (fiber product)",
    "techniques_name": "linoleum block printing",
    "object_colour": "black-and-white (colors)",
    "physical_appearance": "\"This is a folio of linoleographs. The cover is labelled \"\"Linoleographs",
    "subject_terms_1": "Baharoedin propaganda identity",
    "subject_terms_2": "Prints, Indonesian Mochatar Apin 1946\"\" \" Propaganda Independence Artists\u0027 books",
    "subject_terms_3": "National Identity independence",
    "subject_terms_4": "Merdeka",
    "context_1": "visual arts",
    "context_3": "First anniversary of Indonesia\u0027s Declaration of Independence",
    "context_4": "national holidays",
    "context_5": "17-Aug-46",
    "context_6": "17-Aug-46",
    "context_7": "17-Aug-46",
    "context_8": "Indonesia",
    "context_9": "Indonesian Government ?",
    "context_10": "commissioners (people who order works)"
  },
  "nlpDate": "20201125084520",
  "connectorId": 0,
  "tags": {}
}