{"id":"2017-00094","title":"Ten Mighty Warriors of the Anti-Japanese Pioneer Commando ??????? ?????","source":"Bumblebee","path":"./Data/json/","content":"accession_no_csv:2017-00094\nImage:\nobject_work_type:paintings (visual works)\ntitle_text:Ten Mighty Warriors of the Anti-Japanese Pioneer Commando ??????? ?????\npreference:main alternate\ntitle_language:\ncreator_2:Tan Chong Tee\ncreator_1:Chen\n Chongzhi\n 1916-\ncreator_role:artists (visual artists)\ncreation_date:1996\ncreation_place_original_location:Singapore\ninscriptions:\ninscription_language:\nshape:rectangular\nmaterials_name:canvas (textile material) oil paint (paint)\ntechniques_name:painting (image-making)\nobject_colour:multicolored\nphysical_appearance:This is a painting of the artist\\u0027s depiction of the Ten Mighty Warriors of the Anti-Japanese Pioneer Commando. Eleven portraits are blended together against a background of scenes of the war. The right side of the painting shows dark scenes of destruction. In the middle\n there is a half-body portrait of a man in a white shirt and glasses. The bottom-left of the painting shows the ocean with two ships.\nsubject_terms_1:world wars depictions (visual works) resistance movements military officers portraits\nsubject_terms_2:Drawing Portraits World War\n 1939-1945 Great Britain. Army. Force 136 Force 136 (Guerilla movement) Chen\n Chongzhi\n 1916-\nsubject_terms_3:Drawing Force 136 (Guerilla movement) Tan\n Chong Tee 1942-1945 Japanese occupation war personalities\nsubject_terms_4:\nsgcool_label_text:This painting belongs to part of a collection of artefacts related to the World War II underground resistance movement known as Force 136. The collection of materials was gathered by Tan Chong Tee (1916-2012)\n who was a key member of this resistance group. The collection consists of original materials belonging to Tan and other members of Force 136 dating from the 1940s to new materials reproduced from memory by Tan Chong Tee\n which date from mid 1990s to early 2000s.\\r\\n\\r\\nForce 136 was set up in 1942-45 as part of the British Special Operations Executive (SOE). It recruited and trained local guerillas to gather intelligence and create an underground spy network to support planned British invasion of Japanese-occupied Malaya. \\r\\n\\r\\nThis painting is a rendition of the Ten Mighty Warriors of the Anti-Japanese Pioneer Commando by Tan Chong Tee.","createdDate":"20201119143406","version":0,"latest":false,"roles":[],"metadata":{"accession_no_csv":"2017-00094","Image":"","object_work_type":"paintings (visual works)","title_text":"Ten Mighty Warriors of the Anti-Japanese Pioneer Commando ??????? ?????","preference":"main alternate","title_language":"","creator_2":"Tan Chong Tee","creator_1":"Chen, Chongzhi, 1916-","creator_role":"artists (visual artists)","creation_date":"1996","creation_place_original_location":"Singapore","inscriptions":"","inscription_language":"","shape":"rectangular","materials_name":"canvas (textile material) oil paint (paint)","techniques_name":"painting (image-making)","object_colour":"multicolored","physical_appearance":"This is a painting of the artist\u0027s depiction of the Ten Mighty Warriors of the Anti-Japanese Pioneer Commando. Eleven portraits are blended together against a background of scenes of the war. The right side of the painting shows dark scenes of destruction. In the middle, there is a half-body portrait of a man in a white shirt and glasses. The bottom-left of the painting shows the ocean with two ships.","subject_terms_1":"world wars depictions (visual works) resistance movements military officers portraits","subject_terms_2":"Drawing Portraits World War, 1939-1945 Great Britain. Army. Force 136 Force 136 (Guerilla movement) Chen, Chongzhi, 1916-","subject_terms_3":"Drawing Force 136 (Guerilla movement) Tan, Chong Tee 1942-1945 Japanese occupation war personalities","subject_terms_4":"","sgcool_label_text":"This painting belongs to part of a collection of artefacts related to the World War II underground resistance movement known as Force 136. The collection of materials was gathered by Tan Chong Tee (1916-2012), who was a key member of this resistance group. The collection consists of original materials belonging to Tan and other members of Force 136 dating from the 1940s to new materials reproduced from memory by Tan Chong Tee, which date from mid 1990s to early 2000s.\r\n\r\nForce 136 was set up in 1942-45 as part of the British Special Operations Executive (SOE). It recruited and trained local guerillas to gather intelligence and create an underground spy network to support planned British invasion of Japanese-occupied Malaya. \r\n\r\nThis painting is a rendition of the Ten Mighty Warriors of the Anti-Japanese Pioneer Commando by Tan Chong Tee."},"nlpDate":"20201119143406","connectorId":0,"tags":{}}