{
  "id": "2017-00611-001",
  "title": "Robe of the Bridegroom\u0027s Dress Wagho, choyni",
  "source": "Bumblebee",
  "path": "./Data/json/",
  "content": "\n  accession_no_csv: 2017-00611-001\n\n  Image: \n\n  object_work_type: robes (main garments) menswear\n\n  title_text: Robe of the Bridegroom\\u0027s Dress Wagho\n choyni\n\n  preference: main alternate\n\n  title_language: \n\n  creation_date: 20th century\n\n  creation_place_original_location: Kachchh (India)\n\n  inscriptions: \n\n  inscription_language: \n\n  shape: irregular\n\n  materials_name: silk (textile) cotton (textile)\n\n  techniques_name: sewing (needleworking technique) embroidering\n\n  object_colour: multicolored\n\n  physical_appearance: This is a bridegroom\\u0027s robe or tunic. It has long sleeves\n flared hem\n and opens down the front. The top and bottom section of the garment features a dense\n multicoloured embroidery of repeated geometric patterns.\n\n  subject_terms_1: geometric motifs ceremonial costume bridegrooms embroidery (visual works) folk costume\n\n  subject_terms_2: Tunics Motifs Ethnic costume Embroidery Rabaris Wedding costume Robes Bridegrooms\n\n  subject_terms_3: Indian costumes\n\n  subject_terms_4: \n\n  sgcool_label_text: This set of garments - tunic\n trousers and a turban cloth - form a set of bridegroom\\u0027s clothes among the Dhebaria Rabari community of east Kutch. The group features excellent cotton embroidery incorporating mirrorwork embellishments. The fabric of the trousers is handwoven Mashroo silk\n while the turban cloth is made from handspun cotton.\n",
  "createdDate": "20201201203308",
  "version": 0,
  "latest": false,
  "roles": [],
  "metadata": {
    "accession_no_csv": "2017-00611-001",
    "Image": "",
    "object_work_type": "robes (main garments) menswear",
    "title_text": "Robe of the Bridegroom\u0027s Dress Wagho, choyni",
    "preference": "main alternate",
    "title_language": "",
    "creation_date": "20th century",
    "creation_place_original_location": "Kachchh (India)",
    "inscriptions": "",
    "inscription_language": "",
    "shape": "irregular",
    "materials_name": "silk (textile) cotton (textile)",
    "techniques_name": "sewing (needleworking technique) embroidering",
    "object_colour": "multicolored",
    "physical_appearance": "This is a bridegroom\u0027s robe or tunic. It has long sleeves, flared hem, and opens down the front. The top and bottom section of the garment features a dense, multicoloured embroidery of repeated geometric patterns.",
    "subject_terms_1": "geometric motifs ceremonial costume bridegrooms embroidery (visual works) folk costume",
    "subject_terms_2": "Tunics Motifs Ethnic costume Embroidery Rabaris Wedding costume Robes Bridegrooms",
    "subject_terms_3": "Indian costumes",
    "subject_terms_4": "",
    "sgcool_label_text": "This set of garments - tunic, trousers and a turban cloth - form a set of bridegroom\u0027s clothes among the Dhebaria Rabari community of east Kutch. The group features excellent cotton embroidery incorporating mirrorwork embellishments. The fabric of the trousers is handwoven Mashroo silk, while the turban cloth is made from handspun cotton."
  },
  "nlpDate": "20201201203308",
  "connectorId": 0,
  "tags": {}
}