{"id":"2017-00233","title":"Untitled","source":"Bumblebee","path":"./Data/json/","content":"accession_no_csv:2017-00233\nImage:\nobject_work_type:oil paintings (visual works)\ntitle_text:Untitled\npreference:main\ntitle_language:\ncreator_2:Patrick Ng\ncreator_role:artists (visual artists)\ncreation_date:c. mid to late 1950s\ncreation_place_original_location:Malaysia\ninscriptions:\ninscription_language:\nshape:Rectangular\nmaterials_name:oil paint (paint)\ntechniques_name:painting (image-making)\nobject_colour:multicoloured\nphysical_appearance:This oil painting depicts a serene scene of a rural community set amidst lush greenery. Tall trees with dense foliage occupy more than half of the composition\n while the back center piece features a bamboo house with a high attap-roof. Emphasis is paid to the hut as it is framed under the arch of a rainbow that cuts across the sky. Filled with fluffy white clouds\n the sky features a lone star that can be seen on the top right corner. To the hut\\u0027s right\n one notices another hut in a distance.\nsubject_terms_1:identity  landscapes (representations)  rural areas  thatched roofs rural life  rural houses\nsubject_terms_2:Identity  Rural  National identity  Cross/cultures Painting\nsubject_terms_3:visual arts  oil painting\nsgcool_label_text:Born in 1932\n Patrick Ng received his early education at Oxford English School in Singapore and his secondary education at St John\\u0027s Institution and Victoria Institution (VI) in Kuala Lumpur. As a mentee of Peter Harris\n Ng was one of the earliest members of the Wednesday Art Group\n founded in 1952 and was secretary to the group who met at the Selangor Education Department office. Ng left for London under a British Council-administered scholarship known as the Sino-British fellow trust\n now defunct\n to study at the Hammersmith College of Art and Building (later Chelsea College of Art) from 1964-66. He continued his studies at Southlands Teacher Training College (majoring in fine art and textiles) from 1966-68. In his work\n Ng incorporates a range of local Malaysian iconography and his distinctive style has positioned him as one of the most highly acclaimed artists in the history of modern Malaysian art.  \\r\\n\\r\\nUpon comparing his painting styles across other works\n this proposed work was likely to have been painted around the time of Ng’s most well-known painting Spirit of earth\n water and air (1958/59)\n which is gazetted in the Malaysian National Heritage Register List and listed by Redza Piyadasa as one of the masterpieces in the collection of the National Art Gallery Malaysia. Spirit was used as front cover image for SAM’s catalogue Modernity and Beyond (1996). Ng’s Self-Portrait from 1958 is also rendered with similar motifs and in a similar colour scheme.  The proposed painting also looks to be a probable precursor to both those paintings\n where Ng is working out the landscape composition and patterns from natural elements before the inclusion of human figures.\\r\\n","createdDate":"20201119143406","version":0,"latest":false,"roles":[],"metadata":{"accession_no_csv":"2017-00233","Image":"","object_work_type":"oil paintings (visual works)","title_text":"Untitled","preference":"main","title_language":"","creator_2":"Patrick Ng","creator_role":"artists (visual artists)","creation_date":"c. mid to late 1950s","creation_place_original_location":"Malaysia","inscriptions":"","inscription_language":"","shape":"Rectangular","materials_name":"oil paint (paint)","techniques_name":"painting (image-making)","object_colour":"multicoloured","physical_appearance":"This oil painting depicts a serene scene of a rural community set amidst lush greenery. Tall trees with dense foliage occupy more than half of the composition, while the back center piece features a bamboo house with a high attap-roof. Emphasis is paid to the hut as it is framed under the arch of a rainbow that cuts across the sky. Filled with fluffy white clouds, the sky features a lone star that can be seen on the top right corner. To the hut\u0027s right, one notices another hut in a distance.","subject_terms_1":"identity  landscapes (representations)  rural areas  thatched roofs rural life  rural houses","subject_terms_2":"Identity  Rural  National identity  Cross/cultures Painting","subject_terms_3":"visual arts  oil painting","sgcool_label_text":"Born in 1932, Patrick Ng received his early education at Oxford English School in Singapore and his secondary education at St John\u0027s Institution and Victoria Institution (VI) in Kuala Lumpur. As a mentee of Peter Harris, Ng was one of the earliest members of the Wednesday Art Group, founded in 1952 and was secretary to the group who met at the Selangor Education Department office. Ng left for London under a British Council-administered scholarship known as the Sino-British fellow trust, now defunct, to study at the Hammersmith College of Art and Building (later Chelsea College of Art) from 1964-66. He continued his studies at Southlands Teacher Training College (majoring in fine art and textiles) from 1966-68. In his work, Ng incorporates a range of local Malaysian iconography and his distinctive style has positioned him as one of the most highly acclaimed artists in the history of modern Malaysian art.  \r\n\r\nUpon comparing his painting styles across other works, this proposed work was likely to have been painted around the time of Ng’s most well-known painting Spirit of earth, water and air (1958/59), which is gazetted in the Malaysian National Heritage Register List and listed by Redza Piyadasa as one of the masterpieces in the collection of the National Art Gallery Malaysia. Spirit was used as front cover image for SAM’s catalogue Modernity and Beyond (1996). Ng’s Self-Portrait from 1958 is also rendered with similar motifs and in a similar colour scheme.  The proposed painting also looks to be a probable precursor to both those paintings, where Ng is working out the landscape composition and patterns from natural elements before the inclusion of human figures.\r\n"},"nlpDate":"20201119143406","connectorId":0,"tags":{}}