{
  "id": "2017-00081",
  "title": "Chiang Kai-Sheik Surveying the War Zone  ???????",
  "source": "Bumblebee",
  "path": "./Data/json/",
  "content": "\n  accession_no_csv: 2017-00081\n\n  Image: \n\n  object_work_type: drawings (visual works)\n\n  title_text: Chiang Kai-Sheik Surveying the War Zone  ???????\n\n  preference: main alternate\n\n  title_language: \n\n  creator_2: Tan Chong Tee\n\n  creator_1: Chen\n Chongzhi\n 1916-\n\n  creator_role: artists (visual artists)\n\n  creation_date: Not indicated\n\n  creation_place_original_location: Singapore\n\n  inscriptions: \n\n  inscription_language: \n\n  shape: rectangular\n\n  materials_name: paper (fiber product) ink\n\n  techniques_name: drawing (image-making)\n\n  object_colour: black-and-white (colors)\n\n  physical_appearance: This is a black-and-white drawing. It depicts a group of military men in uniforms\n with a tank in the background. The man in the center is shown to be inspecting the area. The scene seems to be depicted within a mountainous area.\n\n  subject_terms_1: world wars depictions (visual works) resistance movements armed forces military officers soldiers Chinese scripts\n\n  subject_terms_2: Drawing World War\n 1939-1945 Great Britain. Army. Force 136 Force 136 (Guerilla movement) Chen\n Chongzhi\n 1916- Chiang\n Kai-shek\n 1887-1975 Soldiers\n\n  subject_terms_3: Drawing War personalities Force 136 (Guerilla movement) Tan\n Chong Tee 1942-1945 Japanese occupation\n\n  subject_terms_4: \n\n  context_5: NAN\n\n  context_6: AN\n\n  sgcool_label_text: This drawing belongs to part of a collection of artefacts related to the World War II underground resistance movement known as Force 136. The collection of materials was gathered by Tan Chong Tee (1916-2012)\n who was a key member of this resistance group. The collection consists of original materials belonging to Tan and other members of Force 136 dating from the 1940s to new materials reproduced from memory by Tan Chong Tee\n which date from mid 1990s to early 2000s. \\r\\n\\r\\nForce 136 was set up in 1942-45 as part of the British Special Operations Executive (SOE). It recruited and trained local guerillas to gather intelligence and create an underground spy network to support planned British invasion of Japanese-occupied Malaya.\\r\\n\\r\\nThis drawing is Tan’s rendition of Chiang Kai-Sheik surveying the War Zone. \\r\\n\n",
  "createdDate": "20201120223707",
  "version": 0,
  "latest": false,
  "roles": [],
  "metadata": {
    "accession_no_csv": "2017-00081",
    "Image": "",
    "object_work_type": "drawings (visual works)",
    "title_text": "Chiang Kai-Sheik Surveying the War Zone  ???????",
    "preference": "main alternate",
    "title_language": "",
    "creator_2": "Tan Chong Tee",
    "creator_1": "Chen, Chongzhi, 1916-",
    "creator_role": "artists (visual artists)",
    "creation_date": "Not indicated",
    "creation_place_original_location": "Singapore",
    "inscriptions": "",
    "inscription_language": "",
    "shape": "rectangular",
    "materials_name": "paper (fiber product) ink",
    "techniques_name": "drawing (image-making)",
    "object_colour": "black-and-white (colors)",
    "physical_appearance": "This is a black-and-white drawing. It depicts a group of military men in uniforms, with a tank in the background. The man in the center is shown to be inspecting the area. The scene seems to be depicted within a mountainous area.",
    "subject_terms_1": "world wars depictions (visual works) resistance movements armed forces military officers soldiers Chinese scripts",
    "subject_terms_2": "Drawing World War, 1939-1945 Great Britain. Army. Force 136 Force 136 (Guerilla movement) Chen, Chongzhi, 1916- Chiang, Kai-shek, 1887-1975 Soldiers",
    "subject_terms_3": "Drawing War personalities Force 136 (Guerilla movement) Tan, Chong Tee 1942-1945 Japanese occupation",
    "subject_terms_4": "",
    "context_5": "NAN",
    "context_6": "AN",
    "sgcool_label_text": "This drawing belongs to part of a collection of artefacts related to the World War II underground resistance movement known as Force 136. The collection of materials was gathered by Tan Chong Tee (1916-2012), who was a key member of this resistance group. The collection consists of original materials belonging to Tan and other members of Force 136 dating from the 1940s to new materials reproduced from memory by Tan Chong Tee, which date from mid 1990s to early 2000s. \r\n\r\nForce 136 was set up in 1942-45 as part of the British Special Operations Executive (SOE). It recruited and trained local guerillas to gather intelligence and create an underground spy network to support planned British invasion of Japanese-occupied Malaya.\r\n\r\nThis drawing is Tan’s rendition of Chiang Kai-Sheik surveying the War Zone. \r\n"
  },
  "nlpDate": "20201120223707",
  "connectorId": 0,
  "tags": {}
}