{"id":"2017-00803","title":"Men’s single-breasted, black light wool long jacket","source":"Bumblebee","path":"./Data/json/","content":"accession_no_csv:2017-00803\nImage:\nobject_work_type:jackets (garments)\ntitle_text:Men’s single-breasted\n black light wool long jacket\npreference:main\ntitle_language:\ncreation_date:1920s\ncreation_place_original_location:Hong Kong (China)  Hong Kong (China)\nstyles_periods_indexing_terms:Chinese (culture or style)\ninscriptions:\ninscription_language:\nshape:T-shaped?\nmaterials_name:wool (textile)\ntechniques_name:sewing (needleworking technique)\nobject_colour:black (colour)\nphysical_appearance:This is a single-breasted\n black light wool long jacket. It is collared\n has a slit at the bottom\n and has a singular button that holds the front together.\nsubject_terms_1:full evening dress?  fashion design  menswear\nsubject_terms_2:Jackets  Wool  Fashion design  Men\\u0027s clothing\nsubject_terms_3:Fashion design\ncontext_20:Bullion Trading Company “Yee Shing”\ncontext_21:20 Canal Road in Singapore\ncontext_22:1930s\ncontext_23:1930\ncontext_24:1939\nsgcool_label_text:The long jacket was considered the appropriate formal wear for men during the early Republican period in China and Hong Kong. There was an interest in Western fashion after the collapse of the Qing dynasty. This Western style long jacket belonged to Mr Kaan Tat Choi\n who was a successful businessman in the bullion business in Hong Kong. Mr Kaan expanded his business to Malaya in the 1920s\n acquiring several rubber plantations along the east coast of Malaya. He also opened a bullion trading company called “Yee Shing” at 20 Canal Road in Singapore in the 1930s.","createdDate":"20201018182636","version":0,"latest":false,"roles":[],"metadata":{"accession_no_csv":"2017-00803","Image":"","object_work_type":"jackets (garments)","title_text":"Men’s single-breasted, black light wool long jacket","preference":"main","title_language":"","creation_date":"1920s","creation_place_original_location":"Hong Kong (China)  Hong Kong (China)","styles_periods_indexing_terms":"Chinese (culture or style)","inscriptions":"","inscription_language":"","shape":"T-shaped?","materials_name":"wool (textile)","techniques_name":"sewing (needleworking technique)","object_colour":"black (colour)","physical_appearance":"This is a single-breasted, black light wool long jacket. It is collared, has a slit at the bottom, and has a singular button that holds the front together.","subject_terms_1":"full evening dress?  fashion design  menswear","subject_terms_2":"Jackets  Wool  Fashion design  Men\u0027s clothing","subject_terms_3":"Fashion design","context_20":"Bullion Trading Company “Yee Shing”","context_21":"20 Canal Road in Singapore","context_22":"1930s","context_23":"1930","context_24":"1939","sgcool_label_text":"The long jacket was considered the appropriate formal wear for men during the early Republican period in China and Hong Kong. There was an interest in Western fashion after the collapse of the Qing dynasty. This Western style long jacket belonged to Mr Kaan Tat Choi, who was a successful businessman in the bullion business in Hong Kong. Mr Kaan expanded his business to Malaya in the 1920s, acquiring several rubber plantations along the east coast of Malaya. He also opened a bullion trading company called “Yee Shing” at 20 Canal Road in Singapore in the 1930s."},"nlpDate":"20201018182636","connectorId":0,"tags":{}}