{
  "id": "2017-00243",
  "title": "Packet of strings of beads",
  "source": "Bumblebee",
  "path": "./Data/json/",
  "content": "\n  accession_no_csv: 2017-00243\n\n  Image: \n\n  object_work_type: beads (pierced objects)\n\n  title_text: Packet of strings of beads\n\n  preference: main\n\n  title_language: \n\n  creation_date: Not indicated\n\n  creation_place_original_location: Malacca (Malacca\n Malaysia) Singapore\n\n  styles_periods_indexing_terms: Peranakan\n\n  inscriptions: \n\n  inscription_language: \n\n  shape: irregular\n\n  object_colour: multicolored\n\n  physical_appearance: This is a packet containing strings of seed beads in various shades. The beads of the same colour are strung along a white string\n forming bundles. The strings of beads are placed in a brown packet.\n\n  subject_terms_1: Peranakan sewing tools tailors beadwork (visual works)\n\n  subject_terms_2: Beads Peranakan (Asian people) Sewing Equipment and supplies Tailors Clothing trade Bead embroidery\n\n  subject_terms_3: Vanishing trade Textile art and design\n\n  sgcool_label_text: This packet contains strings of seed beads in various shades. Seed beads are hallmarks of Peranakan needlework and were traditionally referred to as manek potong (cut beads) regardless of the types of beads at hand. These examples show the variety of beads available to embroiderers working in Malacca and Singapore.\\r\\n\\r\\nThe original owner of these items made a living fashioning beaded slippers and dresses\n\n",
  "createdDate": "20201120223707",
  "version": 0,
  "latest": false,
  "roles": [],
  "metadata": {
    "accession_no_csv": "2017-00243",
    "Image": "",
    "object_work_type": "beads (pierced objects)",
    "title_text": "Packet of strings of beads",
    "preference": "main",
    "title_language": "",
    "creation_date": "Not indicated",
    "creation_place_original_location": "Malacca (Malacca, Malaysia) Singapore",
    "styles_periods_indexing_terms": "Peranakan",
    "inscriptions": "",
    "inscription_language": "",
    "shape": "irregular",
    "object_colour": "multicolored",
    "physical_appearance": "This is a packet containing strings of seed beads in various shades. The beads of the same colour are strung along a white string, forming bundles. The strings of beads are placed in a brown packet.",
    "subject_terms_1": "Peranakan sewing tools tailors beadwork (visual works)",
    "subject_terms_2": "Beads Peranakan (Asian people) Sewing Equipment and supplies Tailors Clothing trade Bead embroidery",
    "subject_terms_3": "Vanishing trade Textile art and design",
    "sgcool_label_text": "This packet contains strings of seed beads in various shades. Seed beads are hallmarks of Peranakan needlework and were traditionally referred to as manek potong (cut beads) regardless of the types of beads at hand. These examples show the variety of beads available to embroiderers working in Malacca and Singapore.\r\n\r\nThe original owner of these items made a living fashioning beaded slippers and dresses,"
  },
  "nlpDate": "20201120223707",
  "connectorId": 0,
  "tags": {}
}