{
  "id": "2017-00549",
  "title": "History",
  "source": "Bumblebee",
  "path": "./Data/json/",
  "content": "\n  accession_no_csv: 2017-00549\n\n  Image: \n\n  object_work_type: textile art (visual works)\n\n  title_text: History\n\n  preference: main\n\n  title_language: \n\n  creator_2: Phasao Lao\n\n  creator_1: Not indicated\n\n  creator_role: textile artists\n\n  creation_date: 2013 - 2015\n\n  creation_place_original_location: Laos\n\n  styles_periods_indexing_terms: Hmong (culture or style)\n\n  inscriptions: \n\n  inscription_language: \n\n  shape: rectangular\n\n  materials_name: cloth coloured ink cotton (textile)\n\n  techniques_name: appliqué (technique) drawing (image-making) embroidering\n\n  object_colour: multicoloured\n\n  edition_description: Unique\n\n  physical_appearance: The images present a series of five rectangular textile artworks\n placed side by side. They are mounted on a wall. All of the artworks have a similar border comprising of a black motif with red dots in the triangular\n heart\n and clubbed shape designs. The background of the artworks are yellow in colour. Each artwork depicts the outlines of two people standing side by side. They are holding hands and facing the viewer. All of them are barefoot. They are represented with ethnic costumes and headgears. Lao script has been embroidered on all five of the textile artworks.\n\n  subject_terms_1: depictions (visual works) ethnic groups motifs symbolism (artistic concept) folk costume genealogies (histories)\n\n  subject_terms_2: Motifs Embroidery\n Hmong Hmong (Asian people) Ethnic costume Symbolism Appliqué Family histories\n\n  subject_terms_3: Ethnic costume Textile art and design Genealogy\n\n  subject_terms_4: \n\n  sgcool_label_text: Phasao Lao’s History series is a rudimentary chronicle of his Hmong clan and its familial provenance. Each panel includes a black border of motifs that symbolise ‘spirits’\n and an outline of different ancestors or leaders in red\n the colour of strength and courage. But whereas oral and pictorial histories are more commonplace in Hmong culture\n Lao has embroidered Lao script onto the fabric\n placing significance on the posterity of both his artwork and his Hmong clan.\n",
  "createdDate": "20201125084518",
  "version": 0,
  "latest": false,
  "roles": [],
  "metadata": {
    "accession_no_csv": "2017-00549",
    "Image": "",
    "object_work_type": "textile art (visual works)",
    "title_text": "History",
    "preference": "main",
    "title_language": "",
    "creator_2": "Phasao Lao",
    "creator_1": "Not indicated",
    "creator_role": "textile artists",
    "creation_date": "2013 - 2015",
    "creation_place_original_location": "Laos",
    "styles_periods_indexing_terms": "Hmong (culture or style)",
    "inscriptions": "",
    "inscription_language": "",
    "shape": "rectangular",
    "materials_name": "cloth coloured ink cotton (textile)",
    "techniques_name": "appliqué (technique) drawing (image-making) embroidering",
    "object_colour": "multicoloured",
    "edition_description": "Unique",
    "physical_appearance": "The images present a series of five rectangular textile artworks, placed side by side. They are mounted on a wall. All of the artworks have a similar border comprising of a black motif with red dots in the triangular, heart, and clubbed shape designs. The background of the artworks are yellow in colour. Each artwork depicts the outlines of two people standing side by side. They are holding hands and facing the viewer. All of them are barefoot. They are represented with ethnic costumes and headgears. Lao script has been embroidered on all five of the textile artworks.",
    "subject_terms_1": "depictions (visual works) ethnic groups motifs symbolism (artistic concept) folk costume genealogies (histories)",
    "subject_terms_2": "Motifs Embroidery, Hmong Hmong (Asian people) Ethnic costume Symbolism Appliqué Family histories",
    "subject_terms_3": "Ethnic costume Textile art and design Genealogy",
    "subject_terms_4": "",
    "sgcool_label_text": "Phasao Lao’s History series is a rudimentary chronicle of his Hmong clan and its familial provenance. Each panel includes a black border of motifs that symbolise ‘spirits’, and an outline of different ancestors or leaders in red, the colour of strength and courage. But whereas oral and pictorial histories are more commonplace in Hmong culture, Lao has embroidered Lao script onto the fabric, placing significance on the posterity of both his artwork and his Hmong clan."
  },
  "nlpDate": "20201125084518",
  "connectorId": 0,
  "tags": {}
}