{"id":"2017-00192-009","title":"Chan Phui Kong Collection: Japanese Flag, Parachute Cloth, Photographs, Maps, Documents and Scarfs  Chan Phui Kong Collection: Street view","source":"Bumblebee","path":"./Data/json/","content":"accession_no_csv:2017-00192-009\nImage:\nobject_work_type:black-and-white photographs\ntitle_text:Chan Phui Kong Collection: Japanese Flag\n Parachute Cloth\n Photographs\n Maps\n Documents and Scarfs  Chan Phui Kong Collection: Street view\npreference:alternate main\ntitle_language:\ncreation_date:1942-2000\ncreation_place_original_location:Singapore\ninscriptions:\ninscription_language:\nshape:rectangular\nmaterials_name:paper (fiber product)\ntechniques_name:photographic processes\nobject_colour:black-and-white (colors)\nphysical_appearance:This is a black-and-white photograph. It features a view of the street\n with buildings on either side. The street is occupied by large crowds walking down the sides. In the middle of the street\n there is a row of vehicles. The photograph is quite faded\n especially at the corners.\nsubject_terms_1:world wars resistance movements streets\nsubject_terms_2:World War\n 1939-1945 Great Britain. Army. Force 136 Force 136 (Guerilla movement) Chin\n Phui Kong\n 1923- Photography Streets Crowds\nsubject_terms_3:Force 136 (Guerilla movement) 1942-1945 Japanese occupation Chin\n Phui Kong\n 1923- Photography war personalities\nsubject_terms_4:\nsgcool_label_text:These materials belong to Chan Phui Kong and consist of items which he used in guerrilla warfare as a member of the World War II underground resistance movement known as Force 136.  They form part of a larger collection of materials gathered by Tan Chong Tee (1916- 2012)\n who was a key member of this resistance group. The collection consists of original materials belonging to Tan and other members of Force 136 dating from the 1940s to new materials reproduced from memory by Tan Chong Tee\n which date from the late 1980s to early 2000s.\\r\\n\\r\\nForce 136 was set up in July 1942 as part of the British Special Operations Executive (SOE). It recruited and trained local guerillas to gather intelligence and create an underground spy network to support planned British invasion of Japanese-occupied Malaya.","createdDate":"20201119143406","version":0,"latest":false,"roles":[],"metadata":{"accession_no_csv":"2017-00192-009","Image":"","object_work_type":"black-and-white photographs","title_text":"Chan Phui Kong Collection: Japanese Flag, Parachute Cloth, Photographs, Maps, Documents and Scarfs  Chan Phui Kong Collection: Street view","preference":"alternate main","title_language":"","creation_date":"1942-2000","creation_place_original_location":"Singapore","inscriptions":"","inscription_language":"","shape":"rectangular","materials_name":"paper (fiber product)","techniques_name":"photographic processes","object_colour":"black-and-white (colors)","physical_appearance":"This is a black-and-white photograph. It features a view of the street, with buildings on either side. The street is occupied by large crowds walking down the sides. In the middle of the street, there is a row of vehicles. The photograph is quite faded, especially at the corners.","subject_terms_1":"world wars resistance movements streets","subject_terms_2":"World War, 1939-1945 Great Britain. Army. Force 136 Force 136 (Guerilla movement) Chin, Phui Kong, 1923- Photography Streets Crowds","subject_terms_3":"Force 136 (Guerilla movement) 1942-1945 Japanese occupation Chin, Phui Kong, 1923- Photography war personalities","subject_terms_4":"","sgcool_label_text":"These materials belong to Chan Phui Kong and consist of items which he used in guerrilla warfare as a member of the World War II underground resistance movement known as Force 136.  They form part of a larger collection of materials gathered by Tan Chong Tee (1916- 2012), who was a key member of this resistance group. The collection consists of original materials belonging to Tan and other members of Force 136 dating from the 1940s to new materials reproduced from memory by Tan Chong Tee, which date from the late 1980s to early 2000s.\r\n\r\nForce 136 was set up in July 1942 as part of the British Special Operations Executive (SOE). It recruited and trained local guerillas to gather intelligence and create an underground spy network to support planned British invasion of Japanese-occupied Malaya."},"nlpDate":"20201119143406","connectorId":0,"tags":{}}