{
  "id": "2017-00951-020",
  "title": "Tanah Impian (Dream Land) Graha Garuda",
  "source": "Bumblebee",
  "path": "./Data/json/",
  "content": "\n  accession_no_csv: 2017-00951-020\n\n  Image: \n\n  object_work_type: screen prints  adaptations (derivative objects)\n\n  title_text: Tanah Impian (Dream Land) Graha Garuda\n\n  preference: alternate main\n\n  title_language: \n\n  creator_2: Krack Studio\n\n  creator_role: artists (visual artists)\n\n  creation_date: 2014\n\n  creation_place_original_location: Indonesia\n\n  styles_periods_indexing_terms: Contemporary (style of art)\n\n  inscriptions: \n\n  inscription_language: \n\n  shape: Rectangular\n\n  materials_name: paper (fiber product)\n\n  techniques_name: screen printing\n\n  object_colour: multicoloured\n\n  edition_description: 2-Oct\n\n  physical_appearance: This print is a promotional poster for Graha Garuda Tiara; a hotel and convention centre. The hotel is shaped as a garuda\n and has the Indonesia coat of arms.\n\n  subject_terms_1: identity  nationalism  advertisements posters  hotels (public accomodations)  convention centers\n\n  subject_terms_2: Indonesia  Serigraphy Art\n Indonesian Nationalism Identity  promotional materials  Posters  Pancasila  Hotels  Convention facilities\n\n  subject_terms_3: Visual arts  National identity  Poster art  Commercial buildings  Media and advertising  Popular culture\n\n  context_20: Graha Garuda Tiara\n\n  context_21: Jalan Siliwangi\n Gunung Putri Desa Cileungsi Kidul\n Cileungsi Bogor 16820\n\n  context_22: 1995-2014?\n\n  context_23: 1995\n\n  context_24: 2014? According to Belarminus\n Robertus. (2015\n April 16). The Mystery of Garuda Park Harto that now flattens with the land. Retrieved January 26\n 2018\n from http://megapolitan.kompas.com/read/2015/04/16/18350961/Misteri.Garuda.Park.Harto.yang.Kini Rata.dengan.Tanah\n the building was demolished in 2014.\n\n  sgcool_label_text: Tanah Impian (Dream Land) is a series of prints based on images drawn from Indonesian popular culture\n spanning 100 years. The project was conceived in 2014\n the year of the elections in Indonesia when nationalist rhetoric dominated public consciousness\n Artist collective Krack Studio sifted through a mass of research and archival material\n eventually selecting 24 images that referenced the idea of the Indonesian Dream and / or told an interesting story about changing definitions of the ‘Nation’. Ranging from political posters to advertisements\n comic strips\n movie posters and magazines\n these images\n reconstructed and re-imagined by the artist collective\n chronicle Indonesia’s evolving aspirations\n desires and identity\n as well as how Indonesia has been perceived and imaged for the ‘Western’ gaze.\n",
  "createdDate": "20201120223708",
  "version": 0,
  "latest": false,
  "roles": [],
  "metadata": {
    "accession_no_csv": "2017-00951-020",
    "Image": "",
    "object_work_type": "screen prints  adaptations (derivative objects)",
    "title_text": "Tanah Impian (Dream Land) Graha Garuda",
    "preference": "alternate main",
    "title_language": "",
    "creator_2": "Krack Studio",
    "creator_role": "artists (visual artists)",
    "creation_date": "2014",
    "creation_place_original_location": "Indonesia",
    "styles_periods_indexing_terms": "Contemporary (style of art)",
    "inscriptions": "",
    "inscription_language": "",
    "shape": "Rectangular",
    "materials_name": "paper (fiber product)",
    "techniques_name": "screen printing",
    "object_colour": "multicoloured",
    "edition_description": "2-Oct",
    "physical_appearance": "This print is a promotional poster for Graha Garuda Tiara; a hotel and convention centre. The hotel is shaped as a garuda, and has the Indonesia coat of arms.",
    "subject_terms_1": "identity  nationalism  advertisements posters  hotels (public accomodations)  convention centers",
    "subject_terms_2": "Indonesia  Serigraphy Art, Indonesian Nationalism Identity  promotional materials  Posters  Pancasila  Hotels  Convention facilities",
    "subject_terms_3": "Visual arts  National identity  Poster art  Commercial buildings  Media and advertising  Popular culture",
    "context_20": "Graha Garuda Tiara",
    "context_21": "Jalan Siliwangi, Gunung Putri Desa Cileungsi Kidul, Cileungsi Bogor 16820",
    "context_22": "1995-2014?",
    "context_23": "1995",
    "context_24": "2014? According to Belarminus, Robertus. (2015, April 16). The Mystery of Garuda Park Harto that now flattens with the land. Retrieved January 26, 2018, from http://megapolitan.kompas.com/read/2015/04/16/18350961/Misteri.Garuda.Park.Harto.yang.Kini Rata.dengan.Tanah, the building was demolished in 2014.",
    "sgcool_label_text": "Tanah Impian (Dream Land) is a series of prints based on images drawn from Indonesian popular culture, spanning 100 years. The project was conceived in 2014, the year of the elections in Indonesia when nationalist rhetoric dominated public consciousness, Artist collective Krack Studio sifted through a mass of research and archival material, eventually selecting 24 images that referenced the idea of the Indonesian Dream and / or told an interesting story about changing definitions of the ‘Nation’. Ranging from political posters to advertisements, comic strips, movie posters and magazines, these images, reconstructed and re-imagined by the artist collective, chronicle Indonesia’s evolving aspirations, desires and identity, as well as how Indonesia has been perceived and imaged for the ‘Western’ gaze."
  },
  "nlpDate": "20201120223708",
  "connectorId": 0,
  "tags": {}
}