{"id":"2017-00889","title":"Majie’s mandarin-collar top","source":"Bumblebee","path":"./Data/json/","content":"accession_no_csv:2017-00889\nImage:\nobject_work_type:folk costume womenswear\ntitle_text:Majie’s mandarin-collar top\npreference:main\ntitle_language:\ncreation_date:Mid-20th century\ncreation_place_original_location:Singapore\nstyles_periods_indexing_terms:Chinese (culture or style)\ninscriptions:\ninscription_language:\nshape:irregular\nmaterials_name:cotton (textile)\ntechniques_name:sewing (needleworking technique)\nobject_colour:white (color)\nphysical_appearance:This is a mandarin-collar top. It is white in colour. The buttons run from the collar and sideways\n towards the left. The sleeves are mid-length. The hem of the top flares outwards slightly. The fabric features subtle repeated pineapple motifs. There are no tears seen on this garment.\nsubject_terms_1:tops (garments\n general) maids (servants) pineapple (motif)\nsubject_terms_2:Ethnic costume Household employees Motifs\nsubject_terms_3:Chinese costumes Lu\n Earl Ming-Teh\nsubject_terms_4:\nsgcool_label_text:This cream coloured mandarin-collar top with pineapple motifs belonged to a majie\n a Cantonese female domestic helper. Majie is derived from a Shun Tak term (ma cheh) which means mother and sister. As this group of women had taken a vow never to marry\n the term Majie alludes to their spinsterhood and refers to their work taking care of children. Majies typically wore a samfoo uniform consisting of a white mandarin-collar top and black trousers.","createdDate":"20201119143406","version":0,"latest":false,"roles":[],"metadata":{"accession_no_csv":"2017-00889","Image":"","object_work_type":"folk costume womenswear","title_text":"Majie’s mandarin-collar top","preference":"main","title_language":"","creation_date":"Mid-20th century","creation_place_original_location":"Singapore","styles_periods_indexing_terms":"Chinese (culture or style)","inscriptions":"","inscription_language":"","shape":"irregular","materials_name":"cotton (textile)","techniques_name":"sewing (needleworking technique)","object_colour":"white (color)","physical_appearance":"This is a mandarin-collar top. It is white in colour. The buttons run from the collar and sideways, towards the left. The sleeves are mid-length. The hem of the top flares outwards slightly. The fabric features subtle repeated pineapple motifs. There are no tears seen on this garment.","subject_terms_1":"tops (garments, general) maids (servants) pineapple (motif)","subject_terms_2":"Ethnic costume Household employees Motifs","subject_terms_3":"Chinese costumes Lu, Earl Ming-Teh","subject_terms_4":"","sgcool_label_text":"This cream coloured mandarin-collar top with pineapple motifs belonged to a majie, a Cantonese female domestic helper. Majie is derived from a Shun Tak term (ma cheh) which means mother and sister. As this group of women had taken a vow never to marry, the term Majie alludes to their spinsterhood and refers to their work taking care of children. Majies typically wore a samfoo uniform consisting of a white mandarin-collar top and black trousers."},"nlpDate":"20201119143406","connectorId":0,"tags":{}}