{
  "id": "2017-00389",
  "title": "Kain panjang",
  "source": "Bumblebee",
  "path": "./Data/json/",
  "content": "\n  accession_no_csv: 2017-00389\n\n  Image: \n\n  object_work_type: folk costume batik art\n\n  title_text: Kain panjang\n\n  preference: main\n\n  title_language: \n\n  creator_2: Jane Hendromartono\n\n  creator_role: textile designers\n\n  creation_date: 1950-1965\n\n  creation_place_original_location: Pekalongan (Indonesia)\n\n  styles_periods_indexing_terms: Peranakan\n\n  inscriptions: \n\n  inscription_language: \n\n  shape: rectangular\n\n  materials_name: cotton (textile)\n\n  techniques_name: batik\n\n  object_colour: multicolored\n\n  physical_appearance: This is a batik kain panjang. It features two different but similar designs on each half of the kain panjang. The left side of the kain panjang features bunches of peony blooms interspersed with birds. The right side of the kain panjang features bunches of orchids and roses interspersed with butterflies. There is a signature at the top-left of the batik kain panjang.\n\n  subject_terms_1: Peranakan flower (motif) birds (motifs)\n\n  subject_terms_2: Batik Ethnic costume Peranakan (Asian people) Motifs\n\n  subject_terms_3: Batik Peranakan costumes\n\n  sgcool_label_text: This batik is structured in the pagi-sore format\n comprising two different but related designs on each half of the kain panjang.  On both halves\n the buketan design\n comprising large bouquets of European flowers interspersed with butterflies and birds\n is depicted.  Two different varieties of flowers and background filler motifs are used on each half.  This batik comes from the family collection of Oey Djien Nio (1929-1987)\n the last in three generations of documented batik-makers in Pekalongan.  In her earlier signatures\n she used her husband’s name\n Liem Siok Hien.  But from 1965 onwards\n she used Jane Hendromartono\n combining her husband’s new Indonesian family name\n Hendromartono with Jane\n as people addressed her by.  She developed a personal style distinct from her mother and grandmother\n and experimented with a wide spectrum of colours and exotic combinations of birds\n rock formations and mythical animals.  Jane Hendromartono’s clientele expanded beyond the elite in Indonesia to include Europe\n America and Japan\n especially in the 1980s.  This piece is signed “Batik Kesenian Liem Siok Hien Kudus”.\n",
  "createdDate": "20201120223708",
  "version": 0,
  "latest": false,
  "roles": [],
  "metadata": {
    "accession_no_csv": "2017-00389",
    "Image": "",
    "object_work_type": "folk costume batik art",
    "title_text": "Kain panjang",
    "preference": "main",
    "title_language": "",
    "creator_2": "Jane Hendromartono",
    "creator_role": "textile designers",
    "creation_date": "1950-1965",
    "creation_place_original_location": "Pekalongan (Indonesia)",
    "styles_periods_indexing_terms": "Peranakan",
    "inscriptions": "",
    "inscription_language": "",
    "shape": "rectangular",
    "materials_name": "cotton (textile)",
    "techniques_name": "batik",
    "object_colour": "multicolored",
    "physical_appearance": "This is a batik kain panjang. It features two different but similar designs on each half of the kain panjang. The left side of the kain panjang features bunches of peony blooms interspersed with birds. The right side of the kain panjang features bunches of orchids and roses interspersed with butterflies. There is a signature at the top-left of the batik kain panjang.",
    "subject_terms_1": "Peranakan flower (motif) birds (motifs)",
    "subject_terms_2": "Batik Ethnic costume Peranakan (Asian people) Motifs",
    "subject_terms_3": "Batik Peranakan costumes",
    "sgcool_label_text": "This batik is structured in the pagi-sore format, comprising two different but related designs on each half of the kain panjang.  On both halves, the buketan design, comprising large bouquets of European flowers interspersed with butterflies and birds, is depicted.  Two different varieties of flowers and background filler motifs are used on each half.  This batik comes from the family collection of Oey Djien Nio (1929-1987), the last in three generations of documented batik-makers in Pekalongan.  In her earlier signatures, she used her husband’s name, Liem Siok Hien.  But from 1965 onwards, she used Jane Hendromartono, combining her husband’s new Indonesian family name, Hendromartono with Jane, as people addressed her by.  She developed a personal style distinct from her mother and grandmother, and experimented with a wide spectrum of colours and exotic combinations of birds, rock formations and mythical animals.  Jane Hendromartono’s clientele expanded beyond the elite in Indonesia to include Europe, America and Japan, especially in the 1980s.  This piece is signed “Batik Kesenian Liem Siok Hien Kudus”."
  },
  "nlpDate": "20201120223708",
  "connectorId": 0,
  "tags": {}
}