{"id":"2017-00302-025","title":"Miscellaneous scraps of paper from P.O.W James Steele Archives (30 pieces) P.O.W. James Steele Archives: List of Plan Numbers","source":"Bumblebee","path":"./Data/json/","content":"accession_no_csv:2017-00302-025\nImage:\nobject_work_type:keys (texts)\ntitle_text:Miscellaneous scraps of paper from P.O.W James Steele Archives (30 pieces) P.O.W. James Steele Archives: List of Plan Numbers\npreference:alternate main\ntitle_language:\ncreation_date:1941-1945\ncreation_place_original_location:Singapore\ninscriptions:\ninscription_language:\nshape:rectangular\nmaterials_name:paper (fiber product)\ntechniques_name:printing (process)\nobject_colour:multicolored\nphysical_appearance:This is a list of plans and their corresponding numbers. It is printed in blue ink on a plain sheet of paper. The title is printed at the top\n and underlined. There are several handwritten inscriptions in black and blue ink at the bottom of the list. The document is quite folded and torn especially on the top-right and bottom-right corners. There is a small rusty stain at the top-center of the document.\nsubject_terms_1:world wars prisoners of war documents (object genre) plans (maps)\nsubject_terms_2:World War\n 1939-1945 Prisoners of war Lists Floor plans\nsubject_terms_3:war personalities\nsubject_terms_4:\nsgcool_label_text:Loose papers from the James Steele\n P.O.W archive that include a symbolic drawing\n Japanese banana money\n map of camp\n administrative papers from Changi prison pre-dating internment\n list of soldiers of a regiment as well as James Steele’s warrant to  join the army. These papers are part of the archive of James Steele\n Royal Artillery (Field) who served in Malaya from January 1941-February 1942\n when interned as a P.O.W at Changi until his release in October 1945.","createdDate":"20201018182636","version":0,"latest":false,"roles":[],"metadata":{"accession_no_csv":"2017-00302-025","Image":"","object_work_type":"keys (texts)","title_text":"Miscellaneous scraps of paper from P.O.W James Steele Archives (30 pieces) P.O.W. James Steele Archives: List of Plan Numbers","preference":"alternate main","title_language":"","creation_date":"1941-1945","creation_place_original_location":"Singapore","inscriptions":"","inscription_language":"","shape":"rectangular","materials_name":"paper (fiber product)","techniques_name":"printing (process)","object_colour":"multicolored","physical_appearance":"This is a list of plans and their corresponding numbers. It is printed in blue ink on a plain sheet of paper. The title is printed at the top, and underlined. There are several handwritten inscriptions in black and blue ink at the bottom of the list. The document is quite folded and torn especially on the top-right and bottom-right corners. There is a small rusty stain at the top-center of the document.","subject_terms_1":"world wars prisoners of war documents (object genre) plans (maps)","subject_terms_2":"World War, 1939-1945 Prisoners of war Lists Floor plans","subject_terms_3":"war personalities","subject_terms_4":"","sgcool_label_text":"Loose papers from the James Steele, P.O.W archive that include a symbolic drawing, Japanese banana money, map of camp, administrative papers from Changi prison pre-dating internment, list of soldiers of a regiment as well as James Steele’s warrant to  join the army. These papers are part of the archive of James Steele, Royal Artillery (Field) who served in Malaya from January 1941-February 1942, when interned as a P.O.W at Changi until his release in October 1945."},"nlpDate":"20201018182636","connectorId":0,"tags":{}}