{
  "id": "2017-00129",
  "title": "Tan Chong Tee Collection: Japanese Trophies note",
  "source": "Bumblebee",
  "path": "./Data/json/",
  "content": "\n  accession_no_csv: 2017-00129\n\n  Image: \n\n  object_work_type: forms (documents)\n\n  title_text: Tan Chong Tee Collection: Japanese Trophies note\n\n  preference: main alternate\n\n  title_language: \n\n  creation_date: 1945\n\n  creation_place_original_location: Singapore\n\n  inscriptions: \n\n  inscription_language: \n\n  shape: rectangular\n\n  materials_name: paper (fiber product)\n\n  techniques_name: printing (process) laminating\n\n  object_colour: black-and-white (colors)\n\n  physical_appearance: This is a note titled \\u0027Japanese Trophies\\u0027. It is laminated. The note is printed in black ink\n with the name\n unit\n date and signature handwritten in black ink. There is a faded stamp on the signature at the bottom-left of the note.\n\n  subject_terms_1: resistance movements documents (object genre) world wars swords\n\n  subject_terms_2: World War\n 1939-1945 Chen\n Chongzhi\n 1916- Great Britain. Army. Force 136 Force 136 (Guerilla movement) Swords\n\n  subject_terms_3: 1942-1945 Japanese occupation Tan\n Chong Tee Force 136 (Guerilla movement)\n\n  subject_terms_4: \n\n  context_1: World War\n 1939-1945 1942-1945 Japanese Occupation\n\n  context_2: occupations (armed conflicts) world wars\n\n  context_3: 1942-1945 1939-1945\n\n  context_4: 1939 1942\n\n  context_5: 1945\n\n  context_6: Singapore Malaya\n\n  context_7: Great Britain. Army. Force 136\n\n  context_8: armed forces\n\n  sgcool_label_text: This note belongs to part of a collection of artefacts related to the World War II underground resistance movement known as Force 136. The collection of materials was gathered by Tan Chong Tee (1916- 2012)\n who was a key member of this resistance group. The collection consists of original materials belonging to Tan and other members of Force 136 dating from the 1940s to new materials reproduced from memory by Tan Chong Tee\n which date from the late 1980s to early 2000s. \\r\\n\\r\\nForce 136 was set up in July 1942 as part of the British Special Operations Executive (SOE). It recruited and trained local guerillas to gather intelligence and create an underground spy network to support planned British invasion of Japanese-occupied Malaya.\n",
  "createdDate": "20201201203308",
  "version": 0,
  "latest": false,
  "roles": [],
  "metadata": {
    "accession_no_csv": "2017-00129",
    "Image": "",
    "object_work_type": "forms (documents)",
    "title_text": "Tan Chong Tee Collection: Japanese Trophies note",
    "preference": "main alternate",
    "title_language": "",
    "creation_date": "1945",
    "creation_place_original_location": "Singapore",
    "inscriptions": "",
    "inscription_language": "",
    "shape": "rectangular",
    "materials_name": "paper (fiber product)",
    "techniques_name": "printing (process) laminating",
    "object_colour": "black-and-white (colors)",
    "physical_appearance": "This is a note titled \u0027Japanese Trophies\u0027. It is laminated. The note is printed in black ink, with the name, unit, date and signature handwritten in black ink. There is a faded stamp on the signature at the bottom-left of the note.",
    "subject_terms_1": "resistance movements documents (object genre) world wars swords",
    "subject_terms_2": "World War, 1939-1945 Chen, Chongzhi, 1916- Great Britain. Army. Force 136 Force 136 (Guerilla movement) Swords",
    "subject_terms_3": "1942-1945 Japanese occupation Tan, Chong Tee Force 136 (Guerilla movement)",
    "subject_terms_4": "",
    "context_1": "World War, 1939-1945 1942-1945 Japanese Occupation",
    "context_2": "occupations (armed conflicts) world wars",
    "context_3": "1942-1945 1939-1945",
    "context_4": "1939 1942",
    "context_5": "1945",
    "context_6": "Singapore Malaya",
    "context_7": "Great Britain. Army. Force 136",
    "context_8": "armed forces",
    "sgcool_label_text": "This note belongs to part of a collection of artefacts related to the World War II underground resistance movement known as Force 136. The collection of materials was gathered by Tan Chong Tee (1916- 2012), who was a key member of this resistance group. The collection consists of original materials belonging to Tan and other members of Force 136 dating from the 1940s to new materials reproduced from memory by Tan Chong Tee, which date from the late 1980s to early 2000s. \r\n\r\nForce 136 was set up in July 1942 as part of the British Special Operations Executive (SOE). It recruited and trained local guerillas to gather intelligence and create an underground spy network to support planned British invasion of Japanese-occupied Malaya."
  },
  "nlpDate": "20201201203308",
  "connectorId": 0,
  "tags": {}
}