{"id":"2017-00183-001","title":"Lim Hong Pei Collection: Reproductions of certificates \u0026 letters  ????? Lim Hong Pei Collection: Reproduction of certificate of Mention in Despatches","source":"Bumblebee","path":"./Data/json/","content":"accession_no_csv:2017-00183-001\nImage:\nobject_work_type:certificates\ntitle_text:Lim Hong Pei Collection: Reproductions of certificates \\u0026 letters  ????? Lim Hong Pei Collection: Reproduction of certificate of Mention in Despatches\npreference:alternate alternate main\ntitle_language:\ncreation_date:Not indicated\ncreation_place_original_location:Singapore\ninscriptions:\ninscription_language:\nshape:rectangular\nmaterials_name:paper (fiber product)\ntechniques_name:printing (process)\nobject_colour:black-and-white (colors)\nphysical_appearance:This is a black-and-white reproduction of a certificate. There is a logo printed at the top-center of the document. The name of the recipient is printed in the center. There is a signature at the bottom-right of the document. There are no tears or folds seen on the document.\nsubject_terms_1:world wars resistance movements documents (object genre) photocopies\nsubject_terms_2:World War\n 1939-1945 Great Britain. Army. Force 136 Force 136 (Guerilla movement) Certification Facsimiles Lim\n Hong Pei\n 1922-\nsubject_terms_3:Force 136 (Guerilla movement) 1942-1945 Japanese occupation war personalities\nsubject_terms_4:\nsgcool_label_text:These reproductions belong to part of a collection of artefacts related to the World War II underground resistance movement known as Force 136. The collection of materials was gathered by Tan Chong Tee (1916- 2012)\n who was a key member of this resistance group. The collection consists of original materials belonging to Tan and other members of Force 136 dating from the 1940s to new materials reproduced from memory by Tan Chong Tee\n which date from the late 1980s to early 2000s. \\r\\n\\r\\nForce 136 was set up in July 1942 as part of the British Special Operations Executive (SOE). It recruited and trained local guerillas to gather intelligence and create an underground spy network to support planned British invasion of Japanese-occupied Malaya.\\r\\n","createdDate":"20201018182636","version":0,"latest":false,"roles":[],"metadata":{"accession_no_csv":"2017-00183-001","Image":"","object_work_type":"certificates","title_text":"Lim Hong Pei Collection: Reproductions of certificates \u0026 letters  ????? Lim Hong Pei Collection: Reproduction of certificate of Mention in Despatches","preference":"alternate alternate main","title_language":"","creation_date":"Not indicated","creation_place_original_location":"Singapore","inscriptions":"","inscription_language":"","shape":"rectangular","materials_name":"paper (fiber product)","techniques_name":"printing (process)","object_colour":"black-and-white (colors)","physical_appearance":"This is a black-and-white reproduction of a certificate. There is a logo printed at the top-center of the document. The name of the recipient is printed in the center. There is a signature at the bottom-right of the document. There are no tears or folds seen on the document.","subject_terms_1":"world wars resistance movements documents (object genre) photocopies","subject_terms_2":"World War, 1939-1945 Great Britain. Army. Force 136 Force 136 (Guerilla movement) Certification Facsimiles Lim, Hong Pei, 1922-","subject_terms_3":"Force 136 (Guerilla movement) 1942-1945 Japanese occupation war personalities","subject_terms_4":"","sgcool_label_text":"These reproductions belong to part of a collection of artefacts related to the World War II underground resistance movement known as Force 136. The collection of materials was gathered by Tan Chong Tee (1916- 2012), who was a key member of this resistance group. The collection consists of original materials belonging to Tan and other members of Force 136 dating from the 1940s to new materials reproduced from memory by Tan Chong Tee, which date from the late 1980s to early 2000s. \r\n\r\nForce 136 was set up in July 1942 as part of the British Special Operations Executive (SOE). It recruited and trained local guerillas to gather intelligence and create an underground spy network to support planned British invasion of Japanese-occupied Malaya.\r\n"},"nlpDate":"20201018182636","connectorId":0,"tags":{}}