{"id":"2017-00050","title":"The Loss by Fire of the H.E.I. Steamer Madagascar The Loss by Fire of the H.E.I. Steamer Madagascar","source":"Bumblebee","path":"./Data/json/","content":"accession_no_csv:2017-00050\nImage:\nobject_work_type:aquatints (prints) engravings (prints) paperwork (visual works)  aquatints\ntitle_text:The Loss by Fire of the H.E.I. Steamer Madagascar The Loss by Fire of the H.E.I. Steamer Madagascar\npreference:main main\ntitle_language:\ncreator_2:William Huggins Edward Duncan William Huggins Edward Duncan  James Minns Dicey\ncreator_1:Huggins\n William John\n 1781 - 1845 Duncan\n Edward\n 1804 - 1882 Huggins\n William John\n 1781-1845? Duncan\n Edward\n 1804-1882 NA\ncreator_role:marine artists engravers (printmakers) artists (visual artists) engravers (printmakers) captains (military officers)\ncreation_date:1843 1843\ncreation_place_original_location:London (England) London (England)\nstyles_periods_indexing_terms:NA NA\ninscriptions:\ninscription_language:\nscale_type:NA NA\nshape:rectangular Rectangular\nmaterials_name:paper (fiber product) paper (fiber product)\ntechniques_name:aquatint (printing process) aquatint (printing process)\nobject_colour:multicoloured multicoloured\nedition_description:NA NA\nphysical_appearance:This artwork depicts a steamer being damaged by fire in stormy weather in the ocean. There is a wooden frame and it has a white border with a brown perimeter in between. At the bottom of the artwork\n its title is displayed in capital letters. Under its title\n there are three rows of paragraphs that dedicate this artwork to H.E. Vice Admiral Sir William Parker. The colours on the aquatint do not look smudged.  A paddle-wheel steamer is set ablaze in the middle of a tumultuous ocean. Several boats can be seen riding the waves around the steamer.\nsubject_terms_1:marines (visual works) steamships fire damage storms paddle steamers  disasters expeditions (journeys)  fire (physical concept) typhoons\nsubject_terms_2:Aquatint Engraving East India Company Steamboats prints Storms Paddle steamers  Typhoons  Expedition Fires Aquatint Huggins\n William John\n 1781-1845? Duncan\n Edward\n 1804-1882 East India Company  Storms  Engraving\nsubject_terms_3:Visual arts East India Company Visual Arts  East India Company\nsubject_terms_4:NA NA\ncontext_1:NA NA\ncontext_2:NA NA\ncontext_3:NA NA\ncontext_4:NA NA\ncontext_5:NA NA\ncontext_6:NA NA\ncontext_7:NA NA\ncontext_8:NA NA\ncontext_9:NA NA\ncontext_10:NA NA\ncontext_11:NA NA\ncontext_12:NA NA\ncontext_13:NA NA\ncontext_14:NA NA\ncontext_15:NA NA\ncontext_16:NA NA\ncontext_17:NA NA\ncontext_18:NA NA\ncontext_19:NA NA\ncontext_20:NA It was here that the Madagascar\n a paddle-wheel steamer\n was lost to a raging fire.\ncontext_21:NA Entrance of the Formosa Channel\ncontext_22:NA 1841\ncontext_23:NA 1841\ncontext_24:NA 1841\nsgcool_label_text:This print depicts the loss by fire of the Madagascar\n a paddle-wheel steamer\n with severa otherl boats seen in the midst of the storm. The steamer was caught in a typhoon at the entrance of the Formosa Channel when it was part of the British expedition to China in 1841. This aquatint was engraved by Edward Duncan\n after a painting by marine artist William Huggins\n who based his work on a sketch by the ship\\u0027s captain James Minns Dicey. This print depicts the loss by fire of the Madagascar\n a paddle-wheel steamer\n with several other boats seen in the midst of the storm. The steamer was caught in a typhoon at the entrance of the Formosa Channel when it was part of the British expedition to China in 1841. This aquatint was engraved by Edward Duncan\n after a painting by marine artist William Huggins\n who based his work on a sketch by the ship\\u0027s captain James Minns Dicey.","createdDate":"20201119143406","version":0,"latest":false,"roles":[],"metadata":{"accession_no_csv":"2017-00050","Image":"","object_work_type":"aquatints (prints) engravings (prints) paperwork (visual works)  aquatints","title_text":"The Loss by Fire of the H.E.I. Steamer Madagascar The Loss by Fire of the H.E.I. Steamer Madagascar","preference":"main main","title_language":"","creator_2":"William Huggins Edward Duncan William Huggins Edward Duncan  James Minns Dicey","creator_1":"Huggins, William John, 1781 - 1845 Duncan, Edward, 1804 - 1882 Huggins, William John, 1781-1845? Duncan, Edward, 1804-1882 NA","creator_role":"marine artists engravers (printmakers) artists (visual artists) engravers (printmakers) captains (military officers)","creation_date":"1843 1843","creation_place_original_location":"London (England) London (England)","styles_periods_indexing_terms":"NA NA","inscriptions":"","inscription_language":"","scale_type":"NA NA","shape":"rectangular Rectangular","materials_name":"paper (fiber product) paper (fiber product)","techniques_name":"aquatint (printing process) aquatint (printing process)","object_colour":"multicoloured multicoloured","edition_description":"NA NA","physical_appearance":"This artwork depicts a steamer being damaged by fire in stormy weather in the ocean. There is a wooden frame and it has a white border with a brown perimeter in between. At the bottom of the artwork, its title is displayed in capital letters. Under its title, there are three rows of paragraphs that dedicate this artwork to H.E. Vice Admiral Sir William Parker. The colours on the aquatint do not look smudged.  A paddle-wheel steamer is set ablaze in the middle of a tumultuous ocean. Several boats can be seen riding the waves around the steamer.","subject_terms_1":"marines (visual works) steamships fire damage storms paddle steamers  disasters expeditions (journeys)  fire (physical concept) typhoons","subject_terms_2":"Aquatint Engraving East India Company Steamboats prints Storms Paddle steamers  Typhoons  Expedition Fires Aquatint Huggins, William John, 1781-1845? Duncan, Edward, 1804-1882 East India Company  Storms  Engraving","subject_terms_3":"Visual arts East India Company Visual Arts  East India Company","subject_terms_4":"NA NA","context_1":"NA NA","context_2":"NA NA","context_3":"NA NA","context_4":"NA NA","context_5":"NA NA","context_6":"NA NA","context_7":"NA NA","context_8":"NA NA","context_9":"NA NA","context_10":"NA NA","context_11":"NA NA","context_12":"NA NA","context_13":"NA NA","context_14":"NA NA","context_15":"NA NA","context_16":"NA NA","context_17":"NA NA","context_18":"NA NA","context_19":"NA NA","context_20":"NA It was here that the Madagascar, a paddle-wheel steamer, was lost to a raging fire.","context_21":"NA Entrance of the Formosa Channel","context_22":"NA 1841","context_23":"NA 1841","context_24":"NA 1841","sgcool_label_text":"This print depicts the loss by fire of the Madagascar, a paddle-wheel steamer, with severa otherl boats seen in the midst of the storm. The steamer was caught in a typhoon at the entrance of the Formosa Channel when it was part of the British expedition to China in 1841. This aquatint was engraved by Edward Duncan, after a painting by marine artist William Huggins, who based his work on a sketch by the ship\u0027s captain James Minns Dicey. This print depicts the loss by fire of the Madagascar, a paddle-wheel steamer, with several other boats seen in the midst of the storm. The steamer was caught in a typhoon at the entrance of the Formosa Channel when it was part of the British expedition to China in 1841. This aquatint was engraved by Edward Duncan, after a painting by marine artist William Huggins, who based his work on a sketch by the ship\u0027s captain James Minns Dicey."},"nlpDate":"20201119143406","connectorId":0,"tags":{}}