{
  "id": "2017-00536",
  "title": "Figure of an immortal",
  "source": "Bumblebee",
  "path": "./Data/json/",
  "content": "\n  accession_no_csv: 2017-00536\n\n  Image: \n\n  object_work_type: sculpture (visual works) metalwork (visual works)\n\n  title_text: Figure of an immortal\n\n  preference: main\n\n  title_language: \n\n  creation_date: 16th or 17th century\n\n  creation_place_original_location: China\n\n  styles_periods_indexing_terms: Ming (culture\n period\n and styles)\n\n  inscriptions: \n\n  inscription_language: \n\n  materials_name: bronze (metal)\n\n  techniques_name: casting (process)\n\n  object_colour: bronze (colour)\n\n  physical_appearance: This is a sculpture of a man dressed in robes that cling to his body but flow with weight to his ankles. He stands atop a rock set amidst waves. He has his arms folded into his sleeves\n and he dons a scholar\\u0027s cap. His head tilts downwards to the left. A double gourd is seen to be fastened to his waist. Noticibly\n there are small holes in the face of the figure.\n\n  subject_terms_1: Taoism deities gourd\n\n  subject_terms_2: Taoism Deities Gourds Ba Xian (Taoist mythology) Lü\n Dongbin\n 798-\n\n  subject_terms_3: Taoism visual arts\n\n  subject_terms_4: \n\n  sgcool_label_text: This sculpture represents the continued interest and tradition in the production of bronzes in China\n which had begun in the Shang dynasty (ca. 1600–1050 BCE). The figure exudes a sense of vitality through the billowing robes and the fluttering ribbons trailing from his cap. A double-gourd hangs from a cord fastened around the figure’s waist\n which suggests that he is probably an immortal. The gourd was associated with longevity as well as protective and magical properties in Chinese culture. The figure may be Lü Dongbin\n a Tang dynasty (618–907) poet and scholar who came to be venerated as one of the Eight Immortals in Daoism. Lü is regarded as the most influential of the Eight Immortals and is also revered as the Patriarch of the Daoist Quanzhen  (‘Complete Perfection’) Sect.\n",
  "createdDate": "20201201203308",
  "version": 0,
  "latest": false,
  "roles": [],
  "metadata": {
    "accession_no_csv": "2017-00536",
    "Image": "",
    "object_work_type": "sculpture (visual works) metalwork (visual works)",
    "title_text": "Figure of an immortal",
    "preference": "main",
    "title_language": "",
    "creation_date": "16th or 17th century",
    "creation_place_original_location": "China",
    "styles_periods_indexing_terms": "Ming (culture, period, and styles)",
    "inscriptions": "",
    "inscription_language": "",
    "materials_name": "bronze (metal)",
    "techniques_name": "casting (process)",
    "object_colour": "bronze (colour)",
    "physical_appearance": "This is a sculpture of a man dressed in robes that cling to his body but flow with weight to his ankles. He stands atop a rock set amidst waves. He has his arms folded into his sleeves, and he dons a scholar\u0027s cap. His head tilts downwards to the left. A double gourd is seen to be fastened to his waist. Noticibly, there are small holes in the face of the figure.",
    "subject_terms_1": "Taoism deities gourd",
    "subject_terms_2": "Taoism Deities Gourds Ba Xian (Taoist mythology) Lü, Dongbin, 798-",
    "subject_terms_3": "Taoism visual arts",
    "subject_terms_4": "",
    "sgcool_label_text": "This sculpture represents the continued interest and tradition in the production of bronzes in China, which had begun in the Shang dynasty (ca. 1600–1050 BCE). The figure exudes a sense of vitality through the billowing robes and the fluttering ribbons trailing from his cap. A double-gourd hangs from a cord fastened around the figure’s waist, which suggests that he is probably an immortal. The gourd was associated with longevity as well as protective and magical properties in Chinese culture. The figure may be Lü Dongbin, a Tang dynasty (618–907) poet and scholar who came to be venerated as one of the Eight Immortals in Daoism. Lü is regarded as the most influential of the Eight Immortals and is also revered as the Patriarch of the Daoist Quanzhen  (‘Complete Perfection’) Sect."
  },
  "nlpDate": "20201201203308",
  "connectorId": 0,
  "tags": {}
}