{"id":"2017-00934","title":"Portrait of Tan Kim Tian Tan Kim Tian","source":"Bumblebee","path":"./Data/json/","content":"accession_no_csv:2017-00934\nImage:\nobject_work_type:drawings (visual works) portraits\ntitle_text:Portrait of Tan Kim Tian Tan Kim Tian\npreference:alternate main\ntitle_language:\ncreator_2:Ong Kwee Huang (?)\ncreator_role:artists (visual artists)\ncreation_date:19th century\ncreation_place_original_location:Singapore\ninscriptions:\ninscription_language:\nshape:rectangular\nmaterials_name:paper (fiber product) wood (plant material)\ntechniques_name:drawing (image-making)\nobject_colour:multicolored\nphysical_appearance:This is a drawn portrait of Tan Kim Tian. He is depicted seated. There is an ornate table on the let\n with a vase of flowers on it. He is dressed in a black jacket over a blue silk robe\n and is holding a fan in his right hand. The face of the fan depicts a Chinese landscape painting. The drawing is largely creased and faded on some areas.\nsubject_terms_1:Peranakan businessmen folk costume\nsubject_terms_2:Portraits Peranakan (Asian people) Businessmen Ethnic costume Drawing\nsubject_terms_3:Drawing Tan\n Kim Tian Peranakan clans and associations\nsgcool_label_text:In this portrait\n Tan Kim Tian (1832-1882) is depicted seated by an ornate table\n accompanied by objects that point to his learning\n taste and wealth. Dressed in a black jacket (magua) over a blue silk robe (changpao)\n he holds a fan\n on which a Chinese landscape painting is visible. The portrait is signed\n ‘Drawn by Ong Kwee Huang\n Coleman Street No. 22\n Singapore\n AD 1887.’ Together with his son Tan Beng Wan\n Tan Kim Tian founded Tan Kim Tian and Son Steamship Company in 1871\n which was one of the first in Singapore to buy and build ships. He was also the first president of the Tan clan temple. Botan House was built by Tan Kim Tian in 1883 at the corner of Neil Road and Craig Road (since demolished).","createdDate":"20201119143406","version":0,"latest":false,"roles":[],"metadata":{"accession_no_csv":"2017-00934","Image":"","object_work_type":"drawings (visual works) portraits","title_text":"Portrait of Tan Kim Tian Tan Kim Tian","preference":"alternate main","title_language":"","creator_2":"Ong Kwee Huang (?)","creator_role":"artists (visual artists)","creation_date":"19th century","creation_place_original_location":"Singapore","inscriptions":"","inscription_language":"","shape":"rectangular","materials_name":"paper (fiber product) wood (plant material)","techniques_name":"drawing (image-making)","object_colour":"multicolored","physical_appearance":"This is a drawn portrait of Tan Kim Tian. He is depicted seated. There is an ornate table on the let, with a vase of flowers on it. He is dressed in a black jacket over a blue silk robe, and is holding a fan in his right hand. The face of the fan depicts a Chinese landscape painting. The drawing is largely creased and faded on some areas.","subject_terms_1":"Peranakan businessmen folk costume","subject_terms_2":"Portraits Peranakan (Asian people) Businessmen Ethnic costume Drawing","subject_terms_3":"Drawing Tan, Kim Tian Peranakan clans and associations","sgcool_label_text":"In this portrait, Tan Kim Tian (1832-1882) is depicted seated by an ornate table, accompanied by objects that point to his learning, taste and wealth. Dressed in a black jacket (magua) over a blue silk robe (changpao), he holds a fan, on which a Chinese landscape painting is visible. The portrait is signed, ‘Drawn by Ong Kwee Huang, Coleman Street No. 22, Singapore, AD 1887.’ Together with his son Tan Beng Wan, Tan Kim Tian founded Tan Kim Tian and Son Steamship Company in 1871, which was one of the first in Singapore to buy and build ships. He was also the first president of the Tan clan temple. Botan House was built by Tan Kim Tian in 1883 at the corner of Neil Road and Craig Road (since demolished)."},"nlpDate":"20201119143406","connectorId":0,"tags":{}}