{"id":"2017-00851-001 TO 005","title":"Untitled","source":"Bumblebee","path":"./Data/json/","content":"accession_no_csv:2017-00851-001 TO 005\nImage:\nobject_work_type:sculpture (visual works)\ntitle_text:Untitled\npreference:main\ntitle_language:\ncreator_2:Dusadee Huntrakul\ncreator_role:artists (visual artists)\ncreation_date:2015\ncreation_place_original_location:Thailand\nstyles_periods_indexing_terms:Contemporary (style of art)\ninscriptions:\ninscription_language:\nshape:Rectangular\nmaterials_name:porcelain (material)  graphite (mineral)  clay\ntechniques_name:installing  sculpting\nobject_colour:multicoloured\nedition_description:Unique\nphysical_appearance:This sculpture is composed of  cylindrical rods that have been moulded\n a porcelain rope that hangs off it\n two eggs\n and a wave-like sculptural motif.\nsubject_terms_1:fear memory  waves (natural events)  symbolism (artistic concept)\nsubject_terms_2:Sculpture  Loss (Psychology)  Fear Memories  Waves  Symbolism  Art\n Thai\nsubject_terms_3:Visual arts  Sculpure\nsgcool_label_text:Untitled incorporates numerous elements characteristic of Dusadee Huntrakul’s ceramic practice. While appearing unassuming\n the sculpture’s curved contortions highlight the artist’s technical finesse with the medium. The porcelain rope seemingly defiant to the attraction of gravity lends the work a certain élan vital\n and the work exudes an energy seemingly further amplified by two small egg-shaped pieces that rest upon the sculpture. What these “eggs” are are open to interpretation\n and placement as well – and draw comparisons to a primordial cosmic egg\n or when placed side-by-side\n testicles as well. The wave motif present in other works from Dusadee also makes an appearance here. Now\n in conjunction with the spheres\n the waves seem to suggest the primordial nature of water\n and it as a life force in itself.","createdDate":"20201119143406","version":0,"latest":false,"roles":[],"metadata":{"accession_no_csv":"2017-00851-001 TO 005","Image":"","object_work_type":"sculpture (visual works)","title_text":"Untitled","preference":"main","title_language":"","creator_2":"Dusadee Huntrakul","creator_role":"artists (visual artists)","creation_date":"2015","creation_place_original_location":"Thailand","styles_periods_indexing_terms":"Contemporary (style of art)","inscriptions":"","inscription_language":"","shape":"Rectangular","materials_name":"porcelain (material)  graphite (mineral)  clay","techniques_name":"installing  sculpting","object_colour":"multicoloured","edition_description":"Unique","physical_appearance":"This sculpture is composed of  cylindrical rods that have been moulded, a porcelain rope that hangs off it, two eggs, and a wave-like sculptural motif.","subject_terms_1":"fear memory  waves (natural events)  symbolism (artistic concept)","subject_terms_2":"Sculpture  Loss (Psychology)  Fear Memories  Waves  Symbolism  Art, Thai","subject_terms_3":"Visual arts  Sculpure","sgcool_label_text":"Untitled incorporates numerous elements characteristic of Dusadee Huntrakul’s ceramic practice. While appearing unassuming, the sculpture’s curved contortions highlight the artist’s technical finesse with the medium. The porcelain rope seemingly defiant to the attraction of gravity lends the work a certain élan vital, and the work exudes an energy seemingly further amplified by two small egg-shaped pieces that rest upon the sculpture. What these “eggs” are are open to interpretation, and placement as well – and draw comparisons to a primordial cosmic egg, or when placed side-by-side, testicles as well. The wave motif present in other works from Dusadee also makes an appearance here. Now, in conjunction with the spheres, the waves seem to suggest the primordial nature of water, and it as a life force in itself."},"nlpDate":"20201119143406","connectorId":0,"tags":{}}