{"id":"2017-00148","title":"Lung Chui Ying Collection: Scarf of Force 136  ????? Lung Chiu Ying Collection: Scarf of Force 136","source":"Bumblebee","path":"./Data/json/","content":"accession_no_csv:2017-00148\nImage:\nobject_work_type:scarves (costume accessories)\ntitle_text:Lung Chui Ying Collection: Scarf of Force 136  ????? Lung Chiu Ying Collection: Scarf of Force 136\npreference:alternate alternate main\ntitle_language:\ncreation_date:Not indicated\ncreation_place_original_location:Singapore\ninscriptions:\ninscription_language:\nshape:irregular\nmaterials_name:cloth\ntechniques_name:sewing (needleworking technique) embroidering\nobject_colour:multicolored\nphysical_appearance:This is a scarf of Force 136. It has a white base\n with fraying ends. Embroidered on the scarf is a portrait image of a man in a collared uniform in blue. There are initials on the bottom-right of the man\\u0027s portrait. On the underside of the scarf\n there is a embroidered image of a coast\n with a name\n date and place embroidered underneath it. The scarf is slightly stained.\nsubject_terms_1:world wars resistance movements embroidery (visual works) portraits\nsubject_terms_2:World War\n 1939-1945 Great Britain. Army. Force 136 Force 136 (Guerilla movement) Scarves Embroidery Portraits\nsubject_terms_3:Force 136 (Guerilla movement) 1942-1945 Japanese occupation Lung\n Chiu Ying\nsubject_terms_4:\ncontext_1:World War\n 1939-1945 1942-1945 Japanese Occupation\ncontext_2:world wars occupations (armed conflicts)\ncontext_3:1939-1945 1942-1945\ncontext_4:1939 1942\ncontext_5:1945 1945\ncontext_6:Malaya Singapore\ncontext_7:Great Britain. Army. Force 136\ncontext_8:armed forces\nsgcool_label_text:This scarf belongs to Lung Chui Ying and forms part of a larger collection of artefacts related to the World War II underground resistance movement known as Force 136. The collection of materials was amassed by Tan Chong Tee (1916- 2012)\n who was a key member of this resistance group. The collection consists of original materials belonging to Tan and other members of Force 136 dating from the 1940s to new materials reproduced from memory by Tan Chong Tee\n which date from the mid-1990s to early 2000s. \\r\\n\\r\\nForce 136 was set up in July 1942 as part of the British Special Operations Executive (SOE). It recruited and trained local guerillas to gather intelligence and create an underground spy network to support planned British invasion of Japanese-occupied Malaya.\\r\\n\\r\\nLung Chui Ying was a Hainanese born in Johor and recruited as a Force 136 member to fight against the Japanese in Malaya.","createdDate":"20201119143406","version":0,"latest":false,"roles":[],"metadata":{"accession_no_csv":"2017-00148","Image":"","object_work_type":"scarves (costume accessories)","title_text":"Lung Chui Ying Collection: Scarf of Force 136  ????? Lung Chiu Ying Collection: Scarf of Force 136","preference":"alternate alternate main","title_language":"","creation_date":"Not indicated","creation_place_original_location":"Singapore","inscriptions":"","inscription_language":"","shape":"irregular","materials_name":"cloth","techniques_name":"sewing (needleworking technique) embroidering","object_colour":"multicolored","physical_appearance":"This is a scarf of Force 136. It has a white base, with fraying ends. Embroidered on the scarf is a portrait image of a man in a collared uniform in blue. There are initials on the bottom-right of the man\u0027s portrait. On the underside of the scarf, there is a embroidered image of a coast, with a name, date and place embroidered underneath it. The scarf is slightly stained.","subject_terms_1":"world wars resistance movements embroidery (visual works) portraits","subject_terms_2":"World War, 1939-1945 Great Britain. Army. Force 136 Force 136 (Guerilla movement) Scarves Embroidery Portraits","subject_terms_3":"Force 136 (Guerilla movement) 1942-1945 Japanese occupation Lung, Chiu Ying","subject_terms_4":"","context_1":"World War, 1939-1945 1942-1945 Japanese Occupation","context_2":"world wars occupations (armed conflicts)","context_3":"1939-1945 1942-1945","context_4":"1939 1942","context_5":"1945 1945","context_6":"Malaya Singapore","context_7":"Great Britain. Army. Force 136","context_8":"armed forces","sgcool_label_text":"This scarf belongs to Lung Chui Ying and forms part of a larger collection of artefacts related to the World War II underground resistance movement known as Force 136. The collection of materials was amassed by Tan Chong Tee (1916- 2012), who was a key member of this resistance group. The collection consists of original materials belonging to Tan and other members of Force 136 dating from the 1940s to new materials reproduced from memory by Tan Chong Tee, which date from the mid-1990s to early 2000s. \r\n\r\nForce 136 was set up in July 1942 as part of the British Special Operations Executive (SOE). It recruited and trained local guerillas to gather intelligence and create an underground spy network to support planned British invasion of Japanese-occupied Malaya.\r\n\r\nLung Chui Ying was a Hainanese born in Johor and recruited as a Force 136 member to fight against the Japanese in Malaya."},"nlpDate":"20201119143406","connectorId":0,"tags":{}}