{"id":"2017-00487","title":"Damien, I’m Famished (After Damien Hirst)","source":"Bumblebee","path":"./Data/json/","content":"accession_no_csv:2017-00487\nImage:\nobject_work_type:installations (visual works)\ntitle_text:Damien\n I’m Famished (After Damien Hirst)\npreference:main\ntitle_language:\ncreator_2:Krit Ngamsom\ncreator_1:Not indicated\ncreator_role:sculptors\ncreation_date:2016\ncreation_place_original_location:Thailand\nstyles_periods_indexing_terms:Contemporary (style of art)\ninscriptions:\ninscription_language:\nshape:irregular\nmaterials_name:steel (alloy) acrylic (plastic) polyester (resin)\ntechniques_name:forming (physical activity) sculpting\nobject_colour:multicoloured\nedition_description:3 of 3\nphysical_appearance:The installation art is set in a space that has blue walls and floors\n albeit of different hues. To the left\n a shark with its head and teeth exposed protrudes from a transparent tank. The shark is positioned\n with its gaping mouth\n in the direction of a school of fish. The fish have orange tips on their caudal fins and they are all of different sizes. They are made to look like they are swimming\n with the help of vertical rods that extend from the ground.\nsubject_terms_1:sculpture (visual works) adaptations (derivative objects) Selachii (order) fish (animals) symbolism (artistic concept)\nsubject_terms_2:Kinetic sculpture Installations (Art) Art Adaptations Sharks Fishes Symbolism\nsubject_terms_3:Installation Art Sculpture\nsubject_terms_4:\nsgcool_label_text:Krit Ngamsom’s kinetic sculptures are tongue-in-cheek references to iconic artworks that have changed definitions and assumptions about art. Damien\n I’m Famished is a playful reinterpretation of Damien Hirst’s iconic work\n The Physical Impossibility of Death in the Mind of Someone Living. Featuring the shark bursting from its tank to go after a tasty snack of fish\n Ngamsom’s reinterpretation of the work draws its inspiration from notions of Thai-ness – and in this case\n the Buddhist practice of Life Release.","createdDate":"20201018182636","version":0,"latest":false,"roles":[],"metadata":{"accession_no_csv":"2017-00487","Image":"","object_work_type":"installations (visual works)","title_text":"Damien, I’m Famished (After Damien Hirst)","preference":"main","title_language":"","creator_2":"Krit Ngamsom","creator_1":"Not indicated","creator_role":"sculptors","creation_date":"2016","creation_place_original_location":"Thailand","styles_periods_indexing_terms":"Contemporary (style of art)","inscriptions":"","inscription_language":"","shape":"irregular","materials_name":"steel (alloy) acrylic (plastic) polyester (resin)","techniques_name":"forming (physical activity) sculpting","object_colour":"multicoloured","edition_description":"3 of 3","physical_appearance":"The installation art is set in a space that has blue walls and floors, albeit of different hues. To the left, a shark with its head and teeth exposed protrudes from a transparent tank. The shark is positioned, with its gaping mouth, in the direction of a school of fish. The fish have orange tips on their caudal fins and they are all of different sizes. They are made to look like they are swimming, with the help of vertical rods that extend from the ground.","subject_terms_1":"sculpture (visual works) adaptations (derivative objects) Selachii (order) fish (animals) symbolism (artistic concept)","subject_terms_2":"Kinetic sculpture Installations (Art) Art Adaptations Sharks Fishes Symbolism","subject_terms_3":"Installation Art Sculpture","subject_terms_4":"","sgcool_label_text":"Krit Ngamsom’s kinetic sculptures are tongue-in-cheek references to iconic artworks that have changed definitions and assumptions about art. Damien, I’m Famished is a playful reinterpretation of Damien Hirst’s iconic work, The Physical Impossibility of Death in the Mind of Someone Living. Featuring the shark bursting from its tank to go after a tasty snack of fish, Ngamsom’s reinterpretation of the work draws its inspiration from notions of Thai-ness – and in this case, the Buddhist practice of Life Release."},"nlpDate":"20201018182636","connectorId":0,"tags":{}}