{
  "id": "2017-00657",
  "title": "Pillow cover",
  "source": "Bumblebee",
  "path": "./Data/json/",
  "content": "\n  accession_no_csv: 2017-00657\n\n  Image: \n\n  object_work_type: pillowcases\n\n  title_text: Pillow cover\n\n  preference: main\n\n  title_language: \n\n  creation_date: 20th century\n\n  creation_place_original_location: Gujarat (India)\n\n  inscriptions: \n\n  inscription_language: \n\n  shape: rectangular\n\n  materials_name: glass (material)\n\n  techniques_name: sewing (needleworking technique)\n\n  object_colour: multicolored\n\n  physical_appearance: This is a beaded pillow cover. It is rectangular in shape. It is decorated with colourful scrolling geometric patterns\n and stylized depictions of figures\n animals\n trees\n and flowers in the center panels. The entire pillow cover is made of beaded embroidery work.\n\n  subject_terms_1: beadwork (visual works) birds (motifs) flower (motif) embroidery (visual works)\n\n  subject_terms_2: Motifs Embroidery Pillowcases\n\n  subject_terms_3: Textile art and design\n\n  subject_terms_4: \n",
  "createdDate": "20201201203308",
  "version": 0,
  "latest": false,
  "roles": [],
  "metadata": {
    "accession_no_csv": "2017-00657",
    "Image": "",
    "object_work_type": "pillowcases",
    "title_text": "Pillow cover",
    "preference": "main",
    "title_language": "",
    "creation_date": "20th century",
    "creation_place_original_location": "Gujarat (India)",
    "inscriptions": "",
    "inscription_language": "",
    "shape": "rectangular",
    "materials_name": "glass (material)",
    "techniques_name": "sewing (needleworking technique)",
    "object_colour": "multicolored",
    "physical_appearance": "This is a beaded pillow cover. It is rectangular in shape. It is decorated with colourful scrolling geometric patterns, and stylized depictions of figures, animals, trees, and flowers in the center panels. The entire pillow cover is made of beaded embroidery work.",
    "subject_terms_1": "beadwork (visual works) birds (motifs) flower (motif) embroidery (visual works)",
    "subject_terms_2": "Motifs Embroidery Pillowcases",
    "subject_terms_3": "Textile art and design",
    "subject_terms_4": ""
  },
  "nlpDate": "20201201203308",
  "connectorId": 0,
  "tags": {}
}