{
  "id": "2017-00181-001",
  "title": "Lim Hong Pei Collection: Photographs and Certificate ????? Lim Hong Pei Collection: Parachute Troops",
  "source": "Bumblebee",
  "path": "./Data/json/",
  "content": "\n  accession_no_csv: 2017-00181-001\n\n  Image: \n\n  object_work_type: black-and-white photographs\n\n  title_text: Lim Hong Pei Collection: Photographs and Certificate ????? Lim Hong Pei Collection: Parachute Troops\n\n  preference: alternate alternate main\n\n  title_language: \n\n  creation_date: Not indicated\n\n  creation_place_original_location: Singapore\n\n  inscriptions: \n\n  inscription_language: \n\n  shape: rectangular\n\n  materials_name: paper (fiber product)\n\n  techniques_name: photographic processes printing (process)\n\n  object_colour: black-and-white (colors)\n\n  physical_appearance: This is a black-and-white photograph of parachute troops. The photograph features two parachutes\n both on the left side\n against a cloudy sky. There are no inscriptions\n tears or folds seen on the photograph.\n\n  subject_terms_1: world wars resistance movements parachutes (life-saving equipment)\n\n  subject_terms_2: World War\n 1939-1945 Great Britain. Army. Force 136 Force 136 (Guerilla movement) Lim\n Hong Pei\n 1922- Photography Parachutes\n\n  subject_terms_3: Force 136 (Guerilla movement) 1942-1945 Japanese occupation Photography war personalities\n\n  subject_terms_4: \n\n  context_1: World War\n 1939-1945 1942-1945 Japanese Occupation\n\n  context_2: world wars occupations (armed conflicts)\n\n  context_3: 1939-1945 1942-1945\n\n  context_4: 1939 1942\n\n  context_5: 1945 1945\n\n  context_6: Malaya Singapore\n\n  context_7: Great Britain. Army. Force 136\n\n  context_8: armed forces\n\n  sgcool_label_text: These photograph and certificate belong to part of a collection of artefacts related to the World War II underground resistance movement known as Force 136. The collection of materials was gathered by Tan Chong Tee (1916- 2012)\n who was a key member of this resistance group. The collection consists of original materials belonging to Tan and other members of Force 136 dating from the 1940s to new materials reproduced from memory by Tan Chong Tee\n which date from the late 1980s to early 2000s. \\r\\n\\r\\nForce 136 was set up in July 1942 as part of the British Special Operations Executive (SOE). It recruited and trained local guerillas to gather intelligence and create an underground spy network to support planned British invasion of Japanese-occupied Malaya.\n",
  "createdDate": "20201120223707",
  "version": 0,
  "latest": false,
  "roles": [],
  "metadata": {
    "accession_no_csv": "2017-00181-001",
    "Image": "",
    "object_work_type": "black-and-white photographs",
    "title_text": "Lim Hong Pei Collection: Photographs and Certificate ????? Lim Hong Pei Collection: Parachute Troops",
    "preference": "alternate alternate main",
    "title_language": "",
    "creation_date": "Not indicated",
    "creation_place_original_location": "Singapore",
    "inscriptions": "",
    "inscription_language": "",
    "shape": "rectangular",
    "materials_name": "paper (fiber product)",
    "techniques_name": "photographic processes printing (process)",
    "object_colour": "black-and-white (colors)",
    "physical_appearance": "This is a black-and-white photograph of parachute troops. The photograph features two parachutes, both on the left side, against a cloudy sky. There are no inscriptions, tears or folds seen on the photograph.",
    "subject_terms_1": "world wars resistance movements parachutes (life-saving equipment)",
    "subject_terms_2": "World War, 1939-1945 Great Britain. Army. Force 136 Force 136 (Guerilla movement) Lim, Hong Pei, 1922- Photography Parachutes",
    "subject_terms_3": "Force 136 (Guerilla movement) 1942-1945 Japanese occupation Photography war personalities",
    "subject_terms_4": "",
    "context_1": "World War, 1939-1945 1942-1945 Japanese Occupation",
    "context_2": "world wars occupations (armed conflicts)",
    "context_3": "1939-1945 1942-1945",
    "context_4": "1939 1942",
    "context_5": "1945 1945",
    "context_6": "Malaya Singapore",
    "context_7": "Great Britain. Army. Force 136",
    "context_8": "armed forces",
    "sgcool_label_text": "These photograph and certificate belong to part of a collection of artefacts related to the World War II underground resistance movement known as Force 136. The collection of materials was gathered by Tan Chong Tee (1916- 2012), who was a key member of this resistance group. The collection consists of original materials belonging to Tan and other members of Force 136 dating from the 1940s to new materials reproduced from memory by Tan Chong Tee, which date from the late 1980s to early 2000s. \r\n\r\nForce 136 was set up in July 1942 as part of the British Special Operations Executive (SOE). It recruited and trained local guerillas to gather intelligence and create an underground spy network to support planned British invasion of Japanese-occupied Malaya."
  },
  "nlpDate": "20201120223707",
  "connectorId": 0,
  "tags": {}
}