{"id":"2017-00153-002","title":"Lung Chui Ying Collection: Passport of Lung Chui Ying including a Registration of Foreigners Rules Form  ????? Lung Chiu Ying Collection: Registration of Foreigners Rules Form","source":"Bumblebee","path":"./Data/json/","content":"accession_no_csv:2017-00153-002\nImage:\nobject_work_type:registrations (licenses) certificates\ntitle_text:Lung Chui Ying Collection: Passport of Lung Chui Ying including a Registration of Foreigners Rules Form  ????? Lung Chiu Ying Collection: Registration of Foreigners Rules Form\npreference:alternate alternate main\ntitle_language:\ncreation_date:1938\ncreation_place_original_location:Singapore Kolkata (India)\ninscriptions:\ninscription_language:\nshape:rectangular\nmaterials_name:paper (fiber product) ink\ntechniques_name:printing (process)\nobject_colour:multicolored\nphysical_appearance:This is a Registration of Foreigners Rules form. The form is printed on a long piece of white paper\n with black ink. The fields are filled with handwritten inscriptions in black ink. There is a circular stamp at the bottom of the form\n by the date and signature. The signature is signed in blue ink. The left edge of the form is slightly uneven.\nsubject_terms_1:world wars resistance movements documents (object genre) travel documents\nsubject_terms_2:World War\n 1939-1945 Great Britain. Army. Force 136 Force 136 (Guerilla movement) Certification Recording and registration\nsubject_terms_3:Force 136 (Guerilla movement) 1942-1945 Japanese occupation Lung\n Chiu Ying\nsubject_terms_4:\nsgcool_label_text:This passport and form belongs to Lung Chui Ying and is part of a larger collection of artefacts related to the World War II underground resistance movement known as Force 136. The collection of materials was gathered by Tan Chong Tee (1916- 2012)\n who was a key member of this resistance group. The collection consists of original materials belonging to Tan and other members of Force 136 dating from the 1940s to new materials reproduced from memory by Tan Chong Tee\n which date from the mid-1990s to early 2000s. \\r\\n\\r\\nForce 136 was set up in July 1942 as part of the British Special Operations Executive (SOE). It recruited and trained local guerillas to gather intelligence and create an underground spy network to support planned British invasion of Japanese-occupied Malaya.","createdDate":"20201119143406","version":0,"latest":false,"roles":[],"metadata":{"accession_no_csv":"2017-00153-002","Image":"","object_work_type":"registrations (licenses) certificates","title_text":"Lung Chui Ying Collection: Passport of Lung Chui Ying including a Registration of Foreigners Rules Form  ????? Lung Chiu Ying Collection: Registration of Foreigners Rules Form","preference":"alternate alternate main","title_language":"","creation_date":"1938","creation_place_original_location":"Singapore Kolkata (India)","inscriptions":"","inscription_language":"","shape":"rectangular","materials_name":"paper (fiber product) ink","techniques_name":"printing (process)","object_colour":"multicolored","physical_appearance":"This is a Registration of Foreigners Rules form. The form is printed on a long piece of white paper, with black ink. The fields are filled with handwritten inscriptions in black ink. There is a circular stamp at the bottom of the form, by the date and signature. The signature is signed in blue ink. The left edge of the form is slightly uneven.","subject_terms_1":"world wars resistance movements documents (object genre) travel documents","subject_terms_2":"World War, 1939-1945 Great Britain. Army. Force 136 Force 136 (Guerilla movement) Certification Recording and registration","subject_terms_3":"Force 136 (Guerilla movement) 1942-1945 Japanese occupation Lung, Chiu Ying","subject_terms_4":"","sgcool_label_text":"This passport and form belongs to Lung Chui Ying and is part of a larger collection of artefacts related to the World War II underground resistance movement known as Force 136. The collection of materials was gathered by Tan Chong Tee (1916- 2012), who was a key member of this resistance group. The collection consists of original materials belonging to Tan and other members of Force 136 dating from the 1940s to new materials reproduced from memory by Tan Chong Tee, which date from the mid-1990s to early 2000s. \r\n\r\nForce 136 was set up in July 1942 as part of the British Special Operations Executive (SOE). It recruited and trained local guerillas to gather intelligence and create an underground spy network to support planned British invasion of Japanese-occupied Malaya."},"nlpDate":"20201119143406","connectorId":0,"tags":{}}