{"id":"2017-00302-005","title":"Miscellaneous scraps of paper from P.O.W James Steele Archives (30 pieces) P.O.W. James Steele Archives: Report on the Malayan Campaign","source":"Bumblebee","path":"./Data/json/","content":"accession_no_csv:2017-00302-005\nImage:\nobject_work_type:reports\ntitle_text:Miscellaneous scraps of paper from P.O.W James Steele Archives (30 pieces) P.O.W. James Steele Archives: Report on the Malayan Campaign\npreference:alternate main\ntitle_language:\ncreator_2:Lt. Gen. Sir Lewis Heath (?)\ncreator_role:authors\ncreation_date:1941-1945\ncreation_place_original_location:Singapore\ninscriptions:\ninscription_language:\nshape:rectangular\nmaterials_name:paper (fiber product)\ntechniques_name:writing (processes) printing (process)\nobject_colour:white (color) blue (color)\nphysical_appearance:This is a page from a document reporting on The Malayan Campaign. The page number is printed at the top of the document in red ink. The report is printed in blue ink. The edges of the page is badly torn and folded\n especially on the right. There are two holes in the middle of the page.\nsubject_terms_1:world wars prisoners of war documents (object genre) military campaigns\nsubject_terms_2:World War\n 1939-1945 Prisoners of war Military campaigns\nsubject_terms_3:war personalities Non-fiction Malayan Campaign\n British Malaya\n 1941-1942\nsubject_terms_4:\ncontext_1:World War\n 1939-1945 Malayan Campaign\n British Malaya\n 1941-1942\ncontext_2:world wars military campaigns\ncontext_3:1939-1945 1941-1942\ncontext_4:1939 1941\ncontext_5:1945 1942\ncontext_6:Malaya Malaya\ncontext_7:Great Britain. Army. Royal Field Artillery Allied Forces\ncontext_8:armed forces armed forces\nsgcool_label_text:Loose papers from the James Steele\n P.O.W archive that include a symbolic drawing\n Japanese banana money\n map of camp\n administrative papers from Changi prison pre-dating internment\n list of soldiers of a regiment as well as James Steele’s warrant to  join the army. These papers are part of the archive of James Steele\n Royal Artillery (Field) who served in Malaya from January 1941-February 1942\n when interned as a P.O.W at Changi until his release in October 1945.","createdDate":"20201119143406","version":0,"latest":false,"roles":[],"metadata":{"accession_no_csv":"2017-00302-005","Image":"","object_work_type":"reports","title_text":"Miscellaneous scraps of paper from P.O.W James Steele Archives (30 pieces) P.O.W. James Steele Archives: Report on the Malayan Campaign","preference":"alternate main","title_language":"","creator_2":"Lt. Gen. Sir Lewis Heath (?)","creator_role":"authors","creation_date":"1941-1945","creation_place_original_location":"Singapore","inscriptions":"","inscription_language":"","shape":"rectangular","materials_name":"paper (fiber product)","techniques_name":"writing (processes) printing (process)","object_colour":"white (color) blue (color)","physical_appearance":"This is a page from a document reporting on The Malayan Campaign. The page number is printed at the top of the document in red ink. The report is printed in blue ink. The edges of the page is badly torn and folded, especially on the right. There are two holes in the middle of the page.","subject_terms_1":"world wars prisoners of war documents (object genre) military campaigns","subject_terms_2":"World War, 1939-1945 Prisoners of war Military campaigns","subject_terms_3":"war personalities Non-fiction Malayan Campaign, British Malaya, 1941-1942","subject_terms_4":"","context_1":"World War, 1939-1945 Malayan Campaign, British Malaya, 1941-1942","context_2":"world wars military campaigns","context_3":"1939-1945 1941-1942","context_4":"1939 1941","context_5":"1945 1942","context_6":"Malaya Malaya","context_7":"Great Britain. Army. Royal Field Artillery Allied Forces","context_8":"armed forces armed forces","sgcool_label_text":"Loose papers from the James Steele, P.O.W archive that include a symbolic drawing, Japanese banana money, map of camp, administrative papers from Changi prison pre-dating internment, list of soldiers of a regiment as well as James Steele’s warrant to  join the army. These papers are part of the archive of James Steele, Royal Artillery (Field) who served in Malaya from January 1941-February 1942, when interned as a P.O.W at Changi until his release in October 1945."},"nlpDate":"20201119143406","connectorId":0,"tags":{}}