{
  "id": "2017-00605",
  "title": "Turban cloth",
  "source": "Bumblebee",
  "path": "./Data/json/",
  "content": "\n  accession_no_csv: 2017-00605\n\n  Image: \n\n  object_work_type: textiles (visual works)\n\n  title_text: Turban cloth\n\n  preference: main\n\n  title_language: English\n\n  creation_date: 20th century\n\n  creation_place_original_location: Rajasthan (India)\n\n  inscriptions: \n\n  inscription_language: \n\n  shape: rectangular\n\n  materials_name: brocade (textile) wire silver (metal)\n\n  techniques_name: sewing (needleworking technique) brocading embroidering\n\n  object_colour: multicolored\n\n  physical_appearance: This is a long piece of cloth\n used as a turban. It is gold in colour\n with brocading. The ends of the cloth feature a geometric design made of silver sequins and embroidered thread. The ends are slightly frayed. The ends of the turban cloth is laid out on the right\n while the rest of the length of the fabric is collected on the right.\n\n  subject_terms_1: brocade (textile) embroidery (visual works) turbans cloth\n\n  subject_terms_2: Textile fabrics Brocade Embroidery Turbans\n\n  subject_terms_3: Textile art and design Indian costumes\n\n  subject_terms_4: \n\n  sgcool_label_text: This length of fine brocade\n embellished with embroidery and silver sequins\n is a turban cloth. It would have been used by aristocracy or royalty in Rajasthan\n",
  "createdDate": "20201120223708",
  "version": 0,
  "latest": false,
  "roles": [],
  "metadata": {
    "accession_no_csv": "2017-00605",
    "Image": "",
    "object_work_type": "textiles (visual works)",
    "title_text": "Turban cloth",
    "preference": "main",
    "title_language": "English",
    "creation_date": "20th century",
    "creation_place_original_location": "Rajasthan (India)",
    "inscriptions": "",
    "inscription_language": "",
    "shape": "rectangular",
    "materials_name": "brocade (textile) wire silver (metal)",
    "techniques_name": "sewing (needleworking technique) brocading embroidering",
    "object_colour": "multicolored",
    "physical_appearance": "This is a long piece of cloth, used as a turban. It is gold in colour, with brocading. The ends of the cloth feature a geometric design made of silver sequins and embroidered thread. The ends are slightly frayed. The ends of the turban cloth is laid out on the right, while the rest of the length of the fabric is collected on the right.",
    "subject_terms_1": "brocade (textile) embroidery (visual works) turbans cloth",
    "subject_terms_2": "Textile fabrics Brocade Embroidery Turbans",
    "subject_terms_3": "Textile art and design Indian costumes",
    "subject_terms_4": "",
    "sgcool_label_text": "This length of fine brocade, embellished with embroidery and silver sequins, is a turban cloth. It would have been used by aristocracy or royalty in Rajasthan"
  },
  "nlpDate": "20201120223708",
  "connectorId": 0,
  "tags": {}
}