{
  "id": "2017-00301",
  "title": "Prayer in hand-written calligraphy from P.O.W archive",
  "source": "Bumblebee",
  "path": "./Data/json/",
  "content": "\n  accession_no_csv: 2017-00301\n\n  Image: \n\n  object_work_type: calligraphy (visual works)\n\n  title_text: Prayer in hand-written calligraphy from P.O.W archive\n\n  preference: main\n\n  title_language: \n\n  creation_date: 1941-1945\n\n  creation_place_original_location: Singapore\n\n  inscriptions: \n\n  inscription_language: \n\n  shape: rectangular\n\n  materials_name: paper (fiber product)\n\n  techniques_name: writing (process)\n\n  object_colour: multicolored\n\n  physical_appearance: This is a handwritten calligraphy consisting of a prayer written on a piece of black sheet of paper. The title is printed at the top in reddish ink. The first and last line of the prayer is written in black ink. The rest of the prayer is written in reddish ink. There is a blue border around the prayer. The sheet of paper has several tears and holes in it\n especially along the left\n and top sides.\n\n  subject_terms_1: world wars prisoners of war prayers (document genre)\n\n  subject_terms_2: World War\n 1939-1945 Prisoners of war Calligraphy Prayers\n\n  subject_terms_3: war personalities Calligraphy\n\n  subject_terms_4: \n\n  context_1: World War\n 1939-1945\n\n  context_2: world wars\n\n  context_3: 1939-1945\n\n  context_4: 1939\n\n  context_5: 1945\n\n  context_6: Malaya\n\n  context_7: Great Britain. Army. Royal Field Artillery\n\n  context_8: armed forces\n\n  sgcool_label_text: This artefact is part of the archive of James Steele\n Royal Artillery (Field) who served in Malaya from January 1941-February 1942\n when interned as a P.O.W at Changi until his release in October 1945.\n",
  "createdDate": "20201120223707",
  "version": 0,
  "latest": false,
  "roles": [],
  "metadata": {
    "accession_no_csv": "2017-00301",
    "Image": "",
    "object_work_type": "calligraphy (visual works)",
    "title_text": "Prayer in hand-written calligraphy from P.O.W archive",
    "preference": "main",
    "title_language": "",
    "creation_date": "1941-1945",
    "creation_place_original_location": "Singapore",
    "inscriptions": "",
    "inscription_language": "",
    "shape": "rectangular",
    "materials_name": "paper (fiber product)",
    "techniques_name": "writing (process)",
    "object_colour": "multicolored",
    "physical_appearance": "This is a handwritten calligraphy consisting of a prayer written on a piece of black sheet of paper. The title is printed at the top in reddish ink. The first and last line of the prayer is written in black ink. The rest of the prayer is written in reddish ink. There is a blue border around the prayer. The sheet of paper has several tears and holes in it, especially along the left, and top sides.",
    "subject_terms_1": "world wars prisoners of war prayers (document genre)",
    "subject_terms_2": "World War, 1939-1945 Prisoners of war Calligraphy Prayers",
    "subject_terms_3": "war personalities Calligraphy",
    "subject_terms_4": "",
    "context_1": "World War, 1939-1945",
    "context_2": "world wars",
    "context_3": "1939-1945",
    "context_4": "1939",
    "context_5": "1945",
    "context_6": "Malaya",
    "context_7": "Great Britain. Army. Royal Field Artillery",
    "context_8": "armed forces",
    "sgcool_label_text": "This artefact is part of the archive of James Steele, Royal Artillery (Field) who served in Malaya from January 1941-February 1942, when interned as a P.O.W at Changi until his release in October 1945."
  },
  "nlpDate": "20201120223707",
  "connectorId": 0,
  "tags": {}
}