{
  "id": "2017-00145-111",
  "title": "Reflections of Tan Chong Tee: Memoir Reflections of Tan Chong Tee: Letters, Notes, and Photographs",
  "source": "Bumblebee",
  "path": "./Data/json/",
  "content": "\n  accession_no_csv: 2017-00145-111\n\n  Image: \n\n  object_work_type: document (object genre) memoirs\n\n  title_text: Reflections of Tan Chong Tee: Memoir Reflections of Tan Chong Tee: Letters\n Notes\n and Photographs\n\n  preference: main alternate\n\n  title_language: \n\n  creator_2: Tan Chong Tee\n\n  creator_1: Tan\n Chong Tee Chen\n Chongzhi\n 1916-\n\n  creator_role: authors\n\n  creation_place_original_location: Singapore\n\n  inscriptions: \n\n  inscription_language: \n\n  shape: Rectangular\n\n  materials_name: paper (fiber product)\n\n  techniques_name: handwriting\n\n  object_colour: multicoloured\n\n  physical_appearance: \\The text\n written in Chinese in blue ink\n is marked 26 on the top left corner. The subheading \\\\Pangkor has been compromised\\\\ is underlined in yellow. Numerous cancellations and insertions were added in a darker shade of blue ink. The paper is torn where the hole puncture holes are. \\\n\n  subject_terms_1: resistance movements local histories world wars Chinese scripts arrests (legal events) armed forces prisoners of war guerilla warfare\n\n  subject_terms_2: World War\n 1939-1945 Chen\n Chongzhi\n 1916- Armed Forces Guerillas Great Britain. Army. Force 136 Local history Chinese characters Force 136 (Guerilla movement) Prisoners of war War resistance movements Arrest Writing\n\n  subject_terms_3: History Tan\n Chong Tee Lee\n Han Kong 1942-1945 Japanese Occupation Force 136 (Guerilla movement) war personalities\n\n  sgcool_label_text: These documents and photographs belong to a larger part of a collection of artefacts related to the World War II underground resistance movement known as Force 136. The collection of materials was gathered by Tan Chong Tee (1916- 2012)\n who was a key member of this resistance group. The collection consists of original materials belonging to Tan and other members of Force 136 dating from the 1940s to new materials reproduced from memory by Tan Chong Tee\n which date from the late 1980s to early 2000s. \\r\\n\\r\\nForce 136 was set up in July 1942 as part of the British Special Operations Executive (SOE). It recruited and trained local guerillas to gather intelligence and create an underground spy network to support planned British invasion of Japanese-occupied Malaya.\\r\\n\n",
  "createdDate": "20201201203308",
  "version": 0,
  "latest": false,
  "roles": [],
  "metadata": {
    "accession_no_csv": "2017-00145-111",
    "Image": "",
    "object_work_type": "document (object genre) memoirs",
    "title_text": "Reflections of Tan Chong Tee: Memoir Reflections of Tan Chong Tee: Letters, Notes, and Photographs",
    "preference": "main alternate",
    "title_language": "",
    "creator_2": "Tan Chong Tee",
    "creator_1": "Tan, Chong Tee Chen, Chongzhi, 1916-",
    "creator_role": "authors",
    "creation_place_original_location": "Singapore",
    "inscriptions": "",
    "inscription_language": "",
    "shape": "Rectangular",
    "materials_name": "paper (fiber product)",
    "techniques_name": "handwriting",
    "object_colour": "multicoloured",
    "physical_appearance": "\"The text, written in Chinese in blue ink, is marked 26 on the top left corner. The subheading \"\"Pangkor has been compromised\"\" is underlined in yellow. Numerous cancellations and insertions were added in a darker shade of blue ink. The paper is torn where the hole puncture holes are. \"",
    "subject_terms_1": "resistance movements local histories world wars Chinese scripts arrests (legal events) armed forces prisoners of war guerilla warfare",
    "subject_terms_2": "World War, 1939-1945 Chen, Chongzhi, 1916- Armed Forces Guerillas Great Britain. Army. Force 136 Local history Chinese characters Force 136 (Guerilla movement) Prisoners of war War resistance movements Arrest Writing",
    "subject_terms_3": "History Tan, Chong Tee Lee, Han Kong 1942-1945 Japanese Occupation Force 136 (Guerilla movement) war personalities",
    "sgcool_label_text": "These documents and photographs belong to a larger part of a collection of artefacts related to the World War II underground resistance movement known as Force 136. The collection of materials was gathered by Tan Chong Tee (1916- 2012), who was a key member of this resistance group. The collection consists of original materials belonging to Tan and other members of Force 136 dating from the 1940s to new materials reproduced from memory by Tan Chong Tee, which date from the late 1980s to early 2000s. \r\n\r\nForce 136 was set up in July 1942 as part of the British Special Operations Executive (SOE). It recruited and trained local guerillas to gather intelligence and create an underground spy network to support planned British invasion of Japanese-occupied Malaya.\r\n"
  },
  "nlpDate": "20201201203308",
  "connectorId": 0,
  "tags": {}
}