{
  "id": "2017-00394",
  "title": "Kain panjang",
  "source": "Bumblebee",
  "path": "./Data/json/",
  "content": "\n  accession_no_csv: 2017-00394\n\n  Image: \n\n  object_work_type: batik art folk costume\n\n  title_text: Kain panjang\n\n  preference: main\n\n  title_language: \n\n  creator_2: Jane Hendromartono\n\n  creator_role: textile designers\n\n  creation_date: 1965-1980s\n\n  creation_place_original_location: Pekalongan (Indonesia)\n\n  styles_periods_indexing_terms: Peranakan\n\n  inscriptions: \n\n  inscription_language: \n\n  shape: rectangular\n\n  materials_name: cotton (textile)\n\n  techniques_name: batik\n\n  object_colour: multicolored\n\n  physical_appearance: This is a batik kain panjang. The main body of the kain panjang features stylised winged animals and birds amongst potted plants. On the left of the kain panjang\n there is a vertical panel decorated with opposing triangles. Between the rows of triangles\n there is a vertical row of diamonds\n each enclosing birds and flowers. There is a signature on the top left of the batik kain panjang.\n\n  subject_terms_1: depictions (visual works) legendary beings Peranakan lozenges foliage (motif)\n\n  subject_terms_2: Motifs Ethnic costume Peranakan (Asian people) Batik\n\n  subject_terms_3: Peranakan costumes Batik\n\n  sgcool_label_text: The main design field (or badan) of this batik is decorated winged animals and fowls amidst potted plants.  On broad vertical panel (kepala)\n rows of opposing triangles\n known as tumpal\n are shown.  Square and upright diamonds appear between these rows\n each enclosing birds and flowers.  This batik comes from the family collection of Oey Djien Nio (1929-1987)\n the last in three generations of documented batik-makers in Pekalongan.  In her earlier signatures\n she used her husband’s name\n Liem Siok Hien.  But from 1965 onwards\n she used Jane Hendromartono\n combining her husband’s new Indonesian family name\n Hendromartono with Jane\n as people addressed her by.  She developed a personal style distinct from her mother and grandmother\n and experimented with a wide spectrum of colours and exotic combinations of birds\n rock formations and mythical animals.  Jane Hendromartono’s clientele expanded beyond the elite in Indonesia to include Europe\n America and Japan\n especially in the 1980s.  This piece is signed “Hendromartono’s Batik Art” Unique Pekalongan 100% Tulis”.\n",
  "createdDate": "20201201203308",
  "version": 0,
  "latest": false,
  "roles": [],
  "metadata": {
    "accession_no_csv": "2017-00394",
    "Image": "",
    "object_work_type": "batik art folk costume",
    "title_text": "Kain panjang",
    "preference": "main",
    "title_language": "",
    "creator_2": "Jane Hendromartono",
    "creator_role": "textile designers",
    "creation_date": "1965-1980s",
    "creation_place_original_location": "Pekalongan (Indonesia)",
    "styles_periods_indexing_terms": "Peranakan",
    "inscriptions": "",
    "inscription_language": "",
    "shape": "rectangular",
    "materials_name": "cotton (textile)",
    "techniques_name": "batik",
    "object_colour": "multicolored",
    "physical_appearance": "This is a batik kain panjang. The main body of the kain panjang features stylised winged animals and birds amongst potted plants. On the left of the kain panjang, there is a vertical panel decorated with opposing triangles. Between the rows of triangles, there is a vertical row of diamonds, each enclosing birds and flowers. There is a signature on the top left of the batik kain panjang.",
    "subject_terms_1": "depictions (visual works) legendary beings Peranakan lozenges foliage (motif)",
    "subject_terms_2": "Motifs Ethnic costume Peranakan (Asian people) Batik",
    "subject_terms_3": "Peranakan costumes Batik",
    "sgcool_label_text": "The main design field (or badan) of this batik is decorated winged animals and fowls amidst potted plants.  On broad vertical panel (kepala), rows of opposing triangles, known as tumpal, are shown.  Square and upright diamonds appear between these rows, each enclosing birds and flowers.  This batik comes from the family collection of Oey Djien Nio (1929-1987), the last in three generations of documented batik-makers in Pekalongan.  In her earlier signatures, she used her husband’s name, Liem Siok Hien.  But from 1965 onwards, she used Jane Hendromartono, combining her husband’s new Indonesian family name, Hendromartono with Jane, as people addressed her by.  She developed a personal style distinct from her mother and grandmother, and experimented with a wide spectrum of colours and exotic combinations of birds, rock formations and mythical animals.  Jane Hendromartono’s clientele expanded beyond the elite in Indonesia to include Europe, America and Japan, especially in the 1980s.  This piece is signed “Hendromartono’s Batik Art” Unique Pekalongan 100% Tulis”."
  },
  "nlpDate": "20201201203308",
  "connectorId": 0,
  "tags": {}
}