{
  "id": "2017-00269",
  "title": "Blue and white censer",
  "source": "Bumblebee",
  "path": "./Data/json/",
  "content": "\n  accession_no_csv: 2017-00269\n\n  Image: \n\n  object_work_type: porcelain (visual works) censers Ceramics (object genre)\n\n  title_text: Blue and white censer\n\n  preference: main\n\n  title_language: \n\n  creation_date: 17th or 18th century\n\n  creation_place_original_location: China\n\n  styles_periods_indexing_terms: Qing (dynastic styles and periods) Chinese ceramics styles\n\n  inscriptions: \n\n  inscription_language: \n\n  shape: concave\n\n  materials_name: clay blue-and-white (ceramic glaze) ceramic glaze cobalt blue (pigment) porcelain (material)\n\n  techniques_name: freehand drawing (technique) firing (technique) underglazing porcelain painting (image-making) molding (forming) glazing (coating process) throwing (pottery techniques)\n\n  object_colour: multicoloured\n\n  physical_appearance: This is a Qing blue white censer whose form replicates that of a bronze gui censer. Painted around its neck is a panel of stylized motifs that visually echo taotie masks often found on ancient Chinese bronzes. The decoration around its body consists of ruyi-heads and ring handles.\n\n  subject_terms_1: porcelain paintings (visual works) zoomorphic ring handles freehand drawings (drawings) symbolism\n\n  subject_terms_2: Porcelain\n Chinese Ming- Qing dynasties\n 1368-1912 China painting Ru yi (Scepters) Blue and white ware China\n\n  subject_terms_3: visual arts Religious life and practices Ceramics Decorative arts\n\n  subject_terms_4: \n\n  sgcool_label_text: This vessel which takes the form of a bronze gui censer is painted with a band of stylised decoration around the neck\n and ruyi-heads and ring handles on the body. The decoration around the neck makes reference to taotie masks and other motifs used on ancient Chinese bronzes. The nod to antiquity highlights the prevalence of archaism as a key theme in the production of Chinese porcelain during the Qing dynasty (1644–1911).\n",
  "createdDate": "20201201203308",
  "version": 0,
  "latest": false,
  "roles": [],
  "metadata": {
    "accession_no_csv": "2017-00269",
    "Image": "",
    "object_work_type": "porcelain (visual works) censers Ceramics (object genre)",
    "title_text": "Blue and white censer",
    "preference": "main",
    "title_language": "",
    "creation_date": "17th or 18th century",
    "creation_place_original_location": "China",
    "styles_periods_indexing_terms": "Qing (dynastic styles and periods) Chinese ceramics styles",
    "inscriptions": "",
    "inscription_language": "",
    "shape": "concave",
    "materials_name": "clay blue-and-white (ceramic glaze) ceramic glaze cobalt blue (pigment) porcelain (material)",
    "techniques_name": "freehand drawing (technique) firing (technique) underglazing porcelain painting (image-making) molding (forming) glazing (coating process) throwing (pottery techniques)",
    "object_colour": "multicoloured",
    "physical_appearance": "This is a Qing blue white censer whose form replicates that of a bronze gui censer. Painted around its neck is a panel of stylized motifs that visually echo taotie masks often found on ancient Chinese bronzes. The decoration around its body consists of ruyi-heads and ring handles.",
    "subject_terms_1": "porcelain paintings (visual works) zoomorphic ring handles freehand drawings (drawings) symbolism",
    "subject_terms_2": "Porcelain, Chinese Ming- Qing dynasties, 1368-1912 China painting Ru yi (Scepters) Blue and white ware China",
    "subject_terms_3": "visual arts Religious life and practices Ceramics Decorative arts",
    "subject_terms_4": "",
    "sgcool_label_text": "This vessel which takes the form of a bronze gui censer is painted with a band of stylised decoration around the neck, and ruyi-heads and ring handles on the body. The decoration around the neck makes reference to taotie masks and other motifs used on ancient Chinese bronzes. The nod to antiquity highlights the prevalence of archaism as a key theme in the production of Chinese porcelain during the Qing dynasty (1644–1911)."
  },
  "nlpDate": "20201201203308",
  "connectorId": 0,
  "tags": {}
}