{"id":"2017-00302-011","title":"Miscellaneous scraps of paper from P.O.W James Steele Archives (30 pieces) P.O.W. James Steele Archives: Portrait photograph","source":"Bumblebee","path":"./Data/json/","content":"accession_no_csv:2017-00302-011\nImage:\nobject_work_type:black-and-white photographs\ntitle_text:Miscellaneous scraps of paper from P.O.W James Steele Archives (30 pieces) P.O.W. James Steele Archives: Portrait photograph\npreference:alternate main\ntitle_language:\ncreation_date:1941-1945\ncreation_place_original_location:Singapore\ninscriptions:\ninscription_language:\nshape:rectangular\nmaterials_name:paper (fiber product)\ntechniques_name:photographic processes\nobject_colour:black-and-white (colors)\nphysical_appearance:This is a portrait photograph. It features a man\n dressed in a shirt\n pants and tie\n sitting in a foldable lounge chair on a grassy land. Behind him\n there is a fence\n with a tall field of grass behind it. There are several small rooftops seen in the background. The man is smoking a cigarette. There are no inscriptions on the photograph.\nsubject_terms_1:world wars prisoners of war documents (object genre) portraits\nsubject_terms_2:World War\n 1939-1945 Prisoners of war Portrait photography\nsubject_terms_3:war personalities Portrait photography\nsubject_terms_4:\ncontext_1:World War\n 1939-1945\ncontext_2:world wars\ncontext_3:1939-1945\ncontext_4:1939\ncontext_5:1945\ncontext_6:Malaya\ncontext_7:Great Britain. Army. Royal Field Artillery\ncontext_8:armed forces\nsgcool_label_text:Loose papers from the James Steele\n P.O.W archive that include a symbolic drawing\n Japanese banana money\n map of camp\n administrative papers from Changi prison pre-dating internment\n list of soldiers of a regiment as well as James Steele’s warrant to  join the army. These papers are part of the archive of James Steele\n Royal Artillery (Field) who served in Malaya from January 1941-February 1942\n when interned as a P.O.W at Changi until his release in October 1945.","createdDate":"20201119143406","version":0,"latest":false,"roles":[],"metadata":{"accession_no_csv":"2017-00302-011","Image":"","object_work_type":"black-and-white photographs","title_text":"Miscellaneous scraps of paper from P.O.W James Steele Archives (30 pieces) P.O.W. James Steele Archives: Portrait photograph","preference":"alternate main","title_language":"","creation_date":"1941-1945","creation_place_original_location":"Singapore","inscriptions":"","inscription_language":"","shape":"rectangular","materials_name":"paper (fiber product)","techniques_name":"photographic processes","object_colour":"black-and-white (colors)","physical_appearance":"This is a portrait photograph. It features a man, dressed in a shirt, pants and tie, sitting in a foldable lounge chair on a grassy land. Behind him, there is a fence, with a tall field of grass behind it. There are several small rooftops seen in the background. The man is smoking a cigarette. There are no inscriptions on the photograph.","subject_terms_1":"world wars prisoners of war documents (object genre) portraits","subject_terms_2":"World War, 1939-1945 Prisoners of war Portrait photography","subject_terms_3":"war personalities Portrait photography","subject_terms_4":"","context_1":"World War, 1939-1945","context_2":"world wars","context_3":"1939-1945","context_4":"1939","context_5":"1945","context_6":"Malaya","context_7":"Great Britain. Army. Royal Field Artillery","context_8":"armed forces","sgcool_label_text":"Loose papers from the James Steele, P.O.W archive that include a symbolic drawing, Japanese banana money, map of camp, administrative papers from Changi prison pre-dating internment, list of soldiers of a regiment as well as James Steele’s warrant to  join the army. These papers are part of the archive of James Steele, Royal Artillery (Field) who served in Malaya from January 1941-February 1942, when interned as a P.O.W at Changi until his release in October 1945."},"nlpDate":"20201119143406","connectorId":0,"tags":{}}