{
  "id": "2017-00145-018",
  "title": "Reflections of Tan Chong Tee: Photograph of Lim Bo Seng Reflections of Tan Chong Tee: Letters, Notes, and Photographs",
  "source": "Bumblebee",
  "path": "./Data/json/",
  "content": "\n  accession_no_csv: 2017-00145-018\n\n  Image: \n\n  object_work_type: photographs black-and-white photographs\n\n  title_text: Reflections of Tan Chong Tee: Photograph of Lim Bo Seng Reflections of Tan Chong Tee: Letters\n Notes\n and Photographs\n\n  preference: main alternate\n\n  title_language: \n\n  creation_place_original_location: Singapore\n\n  inscriptions: \n\n  inscription_language: \n\n  shape: Rectangular\n\n  materials_name: paper (fiber product)\n\n  techniques_name: black-and-white photography\n\n  object_colour: black-and-white (colors)\n\n  physical_appearance: \\This is a black and white photograph of Lim Bo Seng. A dark yellow line cuts across the center of the photograph. At the bottom right corner is Mrs Lim\\u0027s signature \\\\Gan Choo Neo\\\\. \\\n\n  subject_terms_1: resistance movements local histories world wars armed forces portraits guerilla warfare\n\n  subject_terms_2: World War\n 1939-1945 Lim\n Bo Seng\n 1909-1944 Portraits Chen\n Chongzhi\n 1916- Armed Forces Guerillas Photographs Great Britain. Army. Force 136 Local history Force 136 (Guerilla movement) War resistance movements\n\n  subject_terms_3: History Tan\n Chong Tee Lim\n Bo Seng 1942-1945 Japanese Occupation Force 136 (Guerilla movement) war personalities Portrait photography\n\n  context_1: Lim Bo Seng\\u0027s Memorial Service\n\n  context_2: memorial services\n\n  context_3: 13-Jan-46\n\n  context_4: 13-Jan-46\n\n  context_5: 13-Jan-46\n\n  context_6: MacRitchie Reservoir City Hall (Singapore)\n\n  context_7: Great Britain. Army. Force 136\n\n  context_8: planners\n\n  sgcool_label_text: These documents and photographs belong to a larger part of a collection of artefacts related to the World War II underground resistance movement known as Force 136. The collection of materials was gathered by Tan Chong Tee (1916- 2012)\n who was a key member of this resistance group. The collection consists of original materials belonging to Tan and other members of Force 136 dating from the 1940s to new materials reproduced from memory by Tan Chong Tee\n which date from the late 1980s to early 2000s. \\r\\n\\r\\nForce 136 was set up in July 1942 as part of the British Special Operations Executive (SOE). It recruited and trained local guerillas to gather intelligence and create an underground spy network to support planned British invasion of Japanese-occupied Malaya.\\r\\n\n",
  "createdDate": "20201125084528",
  "version": 0,
  "latest": false,
  "roles": [],
  "metadata": {
    "accession_no_csv": "2017-00145-018",
    "Image": "",
    "object_work_type": "photographs black-and-white photographs",
    "title_text": "Reflections of Tan Chong Tee: Photograph of Lim Bo Seng Reflections of Tan Chong Tee: Letters, Notes, and Photographs",
    "preference": "main alternate",
    "title_language": "",
    "creation_place_original_location": "Singapore",
    "inscriptions": "",
    "inscription_language": "",
    "shape": "Rectangular",
    "materials_name": "paper (fiber product)",
    "techniques_name": "black-and-white photography",
    "object_colour": "black-and-white (colors)",
    "physical_appearance": "\"This is a black and white photograph of Lim Bo Seng. A dark yellow line cuts across the center of the photograph. At the bottom right corner is Mrs Lim\u0027s signature \"\"Gan Choo Neo\"\". \"",
    "subject_terms_1": "resistance movements local histories world wars armed forces portraits guerilla warfare",
    "subject_terms_2": "World War, 1939-1945 Lim, Bo Seng, 1909-1944 Portraits Chen, Chongzhi, 1916- Armed Forces Guerillas Photographs Great Britain. Army. Force 136 Local history Force 136 (Guerilla movement) War resistance movements",
    "subject_terms_3": "History Tan, Chong Tee Lim, Bo Seng 1942-1945 Japanese Occupation Force 136 (Guerilla movement) war personalities Portrait photography",
    "context_1": "Lim Bo Seng\u0027s Memorial Service",
    "context_2": "memorial services",
    "context_3": "13-Jan-46",
    "context_4": "13-Jan-46",
    "context_5": "13-Jan-46",
    "context_6": "MacRitchie Reservoir City Hall (Singapore)",
    "context_7": "Great Britain. Army. Force 136",
    "context_8": "planners",
    "sgcool_label_text": "These documents and photographs belong to a larger part of a collection of artefacts related to the World War II underground resistance movement known as Force 136. The collection of materials was gathered by Tan Chong Tee (1916- 2012), who was a key member of this resistance group. The collection consists of original materials belonging to Tan and other members of Force 136 dating from the 1940s to new materials reproduced from memory by Tan Chong Tee, which date from the late 1980s to early 2000s. \r\n\r\nForce 136 was set up in July 1942 as part of the British Special Operations Executive (SOE). It recruited and trained local guerillas to gather intelligence and create an underground spy network to support planned British invasion of Japanese-occupied Malaya.\r\n"
  },
  "nlpDate": "20201125084528",
  "connectorId": 0,
  "tags": {}
}