{
  "id": "2017-00182",
  "title": "Lim Hong Pei Collection: Reproduction of a discharge document",
  "source": "Bumblebee",
  "path": "./Data/json/",
  "content": "\n  accession_no_csv: 2017-00182\n\n  Image: \n\n  object_work_type: documents (object genre)\n\n  title_text: Lim Hong Pei Collection: Reproduction of a discharge document\n\n  preference: main alternate\n\n  title_language: \n\n  creation_date: Not indicated\n\n  creation_place_original_location: Singapore\n\n  inscriptions: \n\n  inscription_language: \n\n  shape: rectangular\n\n  materials_name: paper (fiber product)\n\n  techniques_name: printing (process)\n\n  object_colour: black-and-white (colors)\n\n  physical_appearance: This is a reproduced document certifying honourable discharge from Force 136. The title is printed at the top-center of the document. Below it\n there is a signature on the left\n with a identification photograph on the right. There is a Force 136 stamp marked against the photograph. The date and signature is marked at the bottom of the document\n with several added handwritten inscriptions. The document is slightly folded around the corners.\n\n  subject_terms_1: resistance movements reproduction (copying) world wars discharges\n\n  subject_terms_2: Lim\n Hong Pei\n 1922- World War\n 1939-1945 Great Britain. Army. Force 136 Military discharge Facsimiles Force 136 (Guerilla movement)\n\n  subject_terms_3: 1942-1945 Japanese occupation Force 136 (Guerilla movement) war personalities\n\n  subject_terms_4: \n\n  sgcool_label_text: This reproduction belongs to part of a collection of artefacts related to the World War II underground resistance movement known as Force 136. The collection of materials was gathered by Tan Chong Tee (1916- 2012)\n who was a key member of this resistance group. The collection consists of original materials belonging to Tan and other members of Force 136 dating from the 1940s to new materials reproduced from memory by Tan Chong Tee\n which date from the late 1980s to early 2000s. \\r\\n\\r\\nForce 136 was set up in July 1942 as part of the British Special Operations Executive (SOE). It recruited and trained local guerrillas to gather intelligence and create an underground spy network to support planned British invasion of Japanese-occupied Malaya.\n",
  "createdDate": "20201201203308",
  "version": 0,
  "latest": false,
  "roles": [],
  "metadata": {
    "accession_no_csv": "2017-00182",
    "Image": "",
    "object_work_type": "documents (object genre)",
    "title_text": "Lim Hong Pei Collection: Reproduction of a discharge document",
    "preference": "main alternate",
    "title_language": "",
    "creation_date": "Not indicated",
    "creation_place_original_location": "Singapore",
    "inscriptions": "",
    "inscription_language": "",
    "shape": "rectangular",
    "materials_name": "paper (fiber product)",
    "techniques_name": "printing (process)",
    "object_colour": "black-and-white (colors)",
    "physical_appearance": "This is a reproduced document certifying honourable discharge from Force 136. The title is printed at the top-center of the document. Below it, there is a signature on the left, with a identification photograph on the right. There is a Force 136 stamp marked against the photograph. The date and signature is marked at the bottom of the document, with several added handwritten inscriptions. The document is slightly folded around the corners.",
    "subject_terms_1": "resistance movements reproduction (copying) world wars discharges",
    "subject_terms_2": "Lim, Hong Pei, 1922- World War, 1939-1945 Great Britain. Army. Force 136 Military discharge Facsimiles Force 136 (Guerilla movement)",
    "subject_terms_3": "1942-1945 Japanese occupation Force 136 (Guerilla movement) war personalities",
    "subject_terms_4": "",
    "sgcool_label_text": "This reproduction belongs to part of a collection of artefacts related to the World War II underground resistance movement known as Force 136. The collection of materials was gathered by Tan Chong Tee (1916- 2012), who was a key member of this resistance group. The collection consists of original materials belonging to Tan and other members of Force 136 dating from the 1940s to new materials reproduced from memory by Tan Chong Tee, which date from the late 1980s to early 2000s. \r\n\r\nForce 136 was set up in July 1942 as part of the British Special Operations Executive (SOE). It recruited and trained local guerrillas to gather intelligence and create an underground spy network to support planned British invasion of Japanese-occupied Malaya."
  },
  "nlpDate": "20201201203308",
  "connectorId": 0,
  "tags": {}
}