{
  "id": "2017-00937",
  "title": "Gold buckle and belt",
  "source": "Bumblebee",
  "path": "./Data/json/",
  "content": "\n  accession_no_csv: 2017-00937\n\n  Image: \n\n  object_work_type: belts (costume accessories)\n\n  title_text: Gold buckle and belt\n\n  preference: main\n\n  title_language: \n\n  creation_date: 1950s\n\n  creation_place_original_location: Singapore\n\n  inscriptions: \n\n  inscription_language: \n\n  shape: irregular\n\n  materials_name: gold (metal)\n\n  techniques_name: casting (process) chasing (metalworking)\n\n  object_colour: gold (colour)\n\n  physical_appearance: This is a gold belt with a gold buckle. The overall decorative scheme is an interplay of stylised ribbons where some strands have been chased to give an added texture to the item.\n\n  subject_terms_1: stylization belt buckles\n\n  subject_terms_2: Palembang (Indonesia) Straits Settlements Belts (Clothing)\n\n  subject_terms_3: Decorative arts\n\n  sgcool_label_text: The buckle of the gold belt features a dynamic interplay of stylised ribbons\n some of which are lightly chased to give the effect of depth and texture. This Art Deco pattern is repeated in the smaller plaques of pierced gold. Several markings can be found on the back : Dun jing ( or pound gold)\n \n \n and ‘HP’. While belts with multiple panels were popular in the Straits Settlements at the beginning of the 20th century\n the style could be traced to the courts of Palembang.\n",
  "createdDate": "20201125084515",
  "version": 0,
  "latest": false,
  "roles": [],
  "metadata": {
    "accession_no_csv": "2017-00937",
    "Image": "",
    "object_work_type": "belts (costume accessories)",
    "title_text": "Gold buckle and belt",
    "preference": "main",
    "title_language": "",
    "creation_date": "1950s",
    "creation_place_original_location": "Singapore",
    "inscriptions": "",
    "inscription_language": "",
    "shape": "irregular",
    "materials_name": "gold (metal)",
    "techniques_name": "casting (process) chasing (metalworking)",
    "object_colour": "gold (colour)",
    "physical_appearance": "This is a gold belt with a gold buckle. The overall decorative scheme is an interplay of stylised ribbons where some strands have been chased to give an added texture to the item.",
    "subject_terms_1": "stylization belt buckles",
    "subject_terms_2": "Palembang (Indonesia) Straits Settlements Belts (Clothing)",
    "subject_terms_3": "Decorative arts",
    "sgcool_label_text": "The buckle of the gold belt features a dynamic interplay of stylised ribbons, some of which are lightly chased to give the effect of depth and texture. This Art Deco pattern is repeated in the smaller plaques of pierced gold. Several markings can be found on the back : Dun jing ( or pound gold), , , and ‘HP’. While belts with multiple panels were popular in the Straits Settlements at the beginning of the 20th century, the style could be traced to the courts of Palembang."
  },
  "nlpDate": "20201125084515",
  "connectorId": 0,
  "tags": {}
}