{
  "id": "2017-00171-003",
  "title": "Lumut Sites of Force 136 Operations",
  "source": "Bumblebee",
  "path": "./Data/json/",
  "content": "\n  accession_no_csv: 2017-00171-003\n\n  Image: \n\n  object_work_type: photographs\n\n  title_text: Lumut Sites of Force 136 Operations\n\n  preference: main alternate\n\n  title_language: \n\n  creation_date: 1943\n\n  creation_place_original_location: Lumut (Perak\n Malaysia) Singapore\n\n  inscriptions: \n\n  inscription_language: \n\n  shape: rectangular\n\n  materials_name: paper (fiber product)\n\n  techniques_name: photographic processes\n\n  object_colour: multicolored\n\n  physical_appearance: This is a multicolored photograph of a street. There are two rows of shophouses on the right and left of the photograph. The street in the middle of the shops are lined with parked vehicles\n with one vehicle seen on the road. There is a cropped image of a woman on the bottom left of the photograph. There is a marked arrow pointing downwards towards a roof at the top\n marked in black ink.\n\n  subject_terms_1: resistance movements world wars\n\n  subject_terms_2: World War\n 1939-1945 Photography Chen\n Chongzhi\n 1916- Great Britain. Army. Force 136 Force 136 (Guerilla movement)\n\n  subject_terms_3: 1942-1945 Japanese occupation Photography Tan\n Chong Tee shophouses Force 136 (Guerilla movement) war personalities\n\n  subject_terms_4: \n\n  context_1: World War\n 1939-1945 1942-1945 Japanese Occupation\n\n  context_2: occupations (armed conflicts) world wars\n\n  context_3: 1942-1945 1939-1945\n\n  context_4: 1939 1942\n\n  context_5: 1945\n\n  context_6: Singapore Malaya\n\n  context_7: Great Britain. Army. Force 136\n\n  context_8: armed forces\n\n  sgcool_label_text: This is a collation of the sites in which Force 136 operated and belongs to part of a collection of artefacts related to the World War II underground resistance movement known as Force 136. The collection of materials was gathered by Tan Chong Tee (1916- 2012)\n who was a key member of this resistance group. The collection consists of original materials belonging to Tan and other members of Force 136 dating from the 1940s to new materials reproduced from memory by Tan Chong Tee\n which date from the late 1980s to early 2000s. \\r\\n\\r\\nForce 136 was set up in July 1942 as part of the British Special Operations Executive (SOE). It recruited and trained local guerillas to gather intelligence and create an underground spy network to support planned British invasion of Japanese-occupied Malaya.\\r\\n\n",
  "createdDate": "20201125084525",
  "version": 0,
  "latest": false,
  "roles": [],
  "metadata": {
    "accession_no_csv": "2017-00171-003",
    "Image": "",
    "object_work_type": "photographs",
    "title_text": "Lumut Sites of Force 136 Operations",
    "preference": "main alternate",
    "title_language": "",
    "creation_date": "1943",
    "creation_place_original_location": "Lumut (Perak, Malaysia) Singapore",
    "inscriptions": "",
    "inscription_language": "",
    "shape": "rectangular",
    "materials_name": "paper (fiber product)",
    "techniques_name": "photographic processes",
    "object_colour": "multicolored",
    "physical_appearance": "This is a multicolored photograph of a street. There are two rows of shophouses on the right and left of the photograph. The street in the middle of the shops are lined with parked vehicles, with one vehicle seen on the road. There is a cropped image of a woman on the bottom left of the photograph. There is a marked arrow pointing downwards towards a roof at the top, marked in black ink.",
    "subject_terms_1": "resistance movements world wars",
    "subject_terms_2": "World War, 1939-1945 Photography Chen, Chongzhi, 1916- Great Britain. Army. Force 136 Force 136 (Guerilla movement)",
    "subject_terms_3": "1942-1945 Japanese occupation Photography Tan, Chong Tee shophouses Force 136 (Guerilla movement) war personalities",
    "subject_terms_4": "",
    "context_1": "World War, 1939-1945 1942-1945 Japanese Occupation",
    "context_2": "occupations (armed conflicts) world wars",
    "context_3": "1942-1945 1939-1945",
    "context_4": "1939 1942",
    "context_5": "1945",
    "context_6": "Singapore Malaya",
    "context_7": "Great Britain. Army. Force 136",
    "context_8": "armed forces",
    "sgcool_label_text": "This is a collation of the sites in which Force 136 operated and belongs to part of a collection of artefacts related to the World War II underground resistance movement known as Force 136. The collection of materials was gathered by Tan Chong Tee (1916- 2012), who was a key member of this resistance group. The collection consists of original materials belonging to Tan and other members of Force 136 dating from the 1940s to new materials reproduced from memory by Tan Chong Tee, which date from the late 1980s to early 2000s. \r\n\r\nForce 136 was set up in July 1942 as part of the British Special Operations Executive (SOE). It recruited and trained local guerillas to gather intelligence and create an underground spy network to support planned British invasion of Japanese-occupied Malaya.\r\n"
  },
  "nlpDate": "20201125084525",
  "connectorId": 0,
  "tags": {}
}