{"id":"2017-00156-009","title":"Lung Chui Ying Collection: Photographs, Printed Images, Pamphlets and Clippings  collected by Lung Chui Ying ????? Lung Chiu Ying Collection: Letter of Service","source":"Bumblebee","path":"./Data/json/","content":"accession_no_csv:2017-00156-009\nImage:\nobject_work_type:documents (object genre)\ntitle_text:Lung Chui Ying Collection: Photographs\n Printed Images\n Pamphlets and Clippings  collected by Lung Chui Ying ????? Lung Chiu Ying Collection: Letter of Service\npreference:alternate alternate main\ntitle_language:\ncreation_date:Not indicated\ncreation_place_original_location:Singapore\ninscriptions:\ninscription_language:\nshape:rectangular\nmaterials_name:paper (fiber product)\ntechniques_name:printing (process)\nobject_colour:black-and-white (colors)\nphysical_appearance:This is a letter certifying service for Loong Sow Ying. It is printed in blue ink against a plain slip of paper. On the top right side there is a photograph identification of a man in a uniform. There is a Force 136 stamp in blue ink on the right side of the photograph. The document is dated at the bottom\n alongside a signature inscribed in faded black ink.\nsubject_terms_1:world wars resistance movements certification\nsubject_terms_2:World War\n 1939-1945 Great Britain. Army. Force 136 Force 136 (Guerilla movement) Letters Certification\nsubject_terms_3:Force 136 (Guerilla movement) Lung\n Chiu Ying 1942-1945 Japanese occupation Letters\nsubject_terms_4:\ncontext_1:World War\n 1939-1945 1942-1945 Japanese Occupation\ncontext_2:world wars occupations (armed conflicts)\ncontext_3:1939-1945 1942-1945\ncontext_4:1939 1942\ncontext_5:1945 1945\ncontext_6:Malaya Singapore\ncontext_7:Great Britain. Army. Force 136\ncontext_8:armed forces\nsgcool_label_text:These photographs\n printed images\n pamphlets and clippings belong to Lung Chui Ying and is part of a larger collection related to the World War II underground resistance movement known as Force 136. The collection of materials was gathered by Tan Chong Tee (1916- 2012)\n who was a key member of this resistance group. The collection consists of original materials belonging to Tan and other members of Force 136 dating from the 1940s to new materials reproduced from memory by Tan Chong Tee\n which date from the mid-1990s to early 2000s. \\r\\n\\r\\nForce 136 was set up in July 1942 as part of the British Special Operations Executive (SOE). It recruited and trained local guerillas to gather intelligence and create an underground spy network to support planned British invasion of Japanese-occupied Malaya.\\r\\n\\r\\nLung Chui Ying was a Hainanese born in Johor and recruited as a Force 136 member to fight against the Japanese in Malaya. \\r\\n","createdDate":"20201018182636","version":0,"latest":false,"roles":[],"metadata":{"accession_no_csv":"2017-00156-009","Image":"","object_work_type":"documents (object genre)","title_text":"Lung Chui Ying Collection: Photographs, Printed Images, Pamphlets and Clippings  collected by Lung Chui Ying ????? Lung Chiu Ying Collection: Letter of Service","preference":"alternate alternate main","title_language":"","creation_date":"Not indicated","creation_place_original_location":"Singapore","inscriptions":"","inscription_language":"","shape":"rectangular","materials_name":"paper (fiber product)","techniques_name":"printing (process)","object_colour":"black-and-white (colors)","physical_appearance":"This is a letter certifying service for Loong Sow Ying. It is printed in blue ink against a plain slip of paper. On the top right side there is a photograph identification of a man in a uniform. There is a Force 136 stamp in blue ink on the right side of the photograph. The document is dated at the bottom, alongside a signature inscribed in faded black ink.","subject_terms_1":"world wars resistance movements certification","subject_terms_2":"World War, 1939-1945 Great Britain. Army. Force 136 Force 136 (Guerilla movement) Letters Certification","subject_terms_3":"Force 136 (Guerilla movement) Lung, Chiu Ying 1942-1945 Japanese occupation Letters","subject_terms_4":"","context_1":"World War, 1939-1945 1942-1945 Japanese Occupation","context_2":"world wars occupations (armed conflicts)","context_3":"1939-1945 1942-1945","context_4":"1939 1942","context_5":"1945 1945","context_6":"Malaya Singapore","context_7":"Great Britain. Army. Force 136","context_8":"armed forces","sgcool_label_text":"These photographs, printed images, pamphlets and clippings belong to Lung Chui Ying and is part of a larger collection related to the World War II underground resistance movement known as Force 136. The collection of materials was gathered by Tan Chong Tee (1916- 2012), who was a key member of this resistance group. The collection consists of original materials belonging to Tan and other members of Force 136 dating from the 1940s to new materials reproduced from memory by Tan Chong Tee, which date from the mid-1990s to early 2000s. \r\n\r\nForce 136 was set up in July 1942 as part of the British Special Operations Executive (SOE). It recruited and trained local guerillas to gather intelligence and create an underground spy network to support planned British invasion of Japanese-occupied Malaya.\r\n\r\nLung Chui Ying was a Hainanese born in Johor and recruited as a Force 136 member to fight against the Japanese in Malaya. \r\n"},"nlpDate":"20201018182636","connectorId":0,"tags":{}}