{
  "id": "2017-00631",
  "title": "Doorway hanging Toran",
  "source": "Bumblebee",
  "path": "./Data/json/",
  "content": "\n  accession_no_csv: 2017-00631\n\n  Image: \n\n  object_work_type: hangings (coverings)\n\n  title_text: Doorway hanging Toran\n\n  preference: main alternate\n\n  title_language: \n\n  creation_date: 20th century\n\n  creation_place_original_location: Gujarat (India)\n\n  inscriptions: \n\n  inscription_language: \n\n  shape: irregular\n\n  materials_name: glass (material) cotton (textile)\n\n  techniques_name: sewing (needleworking technique) embroidering\n\n  object_colour: multicolored\n\n  physical_appearance: This is a toran or a doorway hanging. It features a cotton weave with embroidery work. The toran is decorated with stylized depictions of birds\n animals\n foliage\n and deities. There is a sewn-on inscription on the center-right of the hanging. The shape of the toran is irregular\n with a rectangular top and nine dangling panels along the bottom.\n\n  subject_terms_1: embroidery (visual works) flower (motif) birds (motifs) deities depictions (visual works) swastikas beadwork (visual works)\n\n  subject_terms_2: Draperies Embroidery Motifs Gods\n\n  subject_terms_3: Textile art and design\n\n  subject_terms_4: \n",
  "createdDate": "20201120223708",
  "version": 0,
  "latest": false,
  "roles": [],
  "metadata": {
    "accession_no_csv": "2017-00631",
    "Image": "",
    "object_work_type": "hangings (coverings)",
    "title_text": "Doorway hanging Toran",
    "preference": "main alternate",
    "title_language": "",
    "creation_date": "20th century",
    "creation_place_original_location": "Gujarat (India)",
    "inscriptions": "",
    "inscription_language": "",
    "shape": "irregular",
    "materials_name": "glass (material) cotton (textile)",
    "techniques_name": "sewing (needleworking technique) embroidering",
    "object_colour": "multicolored",
    "physical_appearance": "This is a toran or a doorway hanging. It features a cotton weave with embroidery work. The toran is decorated with stylized depictions of birds, animals, foliage, and deities. There is a sewn-on inscription on the center-right of the hanging. The shape of the toran is irregular, with a rectangular top and nine dangling panels along the bottom.",
    "subject_terms_1": "embroidery (visual works) flower (motif) birds (motifs) deities depictions (visual works) swastikas beadwork (visual works)",
    "subject_terms_2": "Draperies Embroidery Motifs Gods",
    "subject_terms_3": "Textile art and design",
    "subject_terms_4": ""
  },
  "nlpDate": "20201120223708",
  "connectorId": 0,
  "tags": {}
}