{"id":"2017-00554-001 to 154","title":"Asking for Nothingness","source":"Bumblebee","path":"./Data/json/","content":"accession_no_csv:2017-00554-001 to 154\nImage:\nobject_work_type:installations (visual works)\ntitle_text:Asking for Nothingness\npreference:main\ntitle_language:\ncreator_2:Navin Rawanchaikul\ncreator_1:Rawanchaikul\n Navin\ncreator_role:artists (visual artists)\ncreation_date:1995-1997\ncreation_place_original_location:Thailand\ninscriptions:\ninscription_language:\nmaterials_name:glass (material)  cork (bark)  wood (plant material)  photographic paper\ntechniques_name:installing\nobject_colour:multicoloured\nphysical_appearance:This is an installation comprising of multiple wooden open-shelf columns with glass bottles that have been filled with black and white photographs. The height of the columns tower over the average person\n and the arrangement allows for the visitor to walk into and around the installation.\nsubject_terms_1:cultural heritage  elderly  group identity  memory\nsubject_terms_2:Heritage  Older people  Group identity  Collective memory  Installations (Arts)\nsubject_terms_3:Installation art\nsgcool_label_text:Asking for Nothingness is the largest work from Thai artist Navin Rawanchaikul’s series of bottle installations from the 1990s and rounds off a style that marked the artist’s early period of experimentation and social engagement\n which included segues into assemblages and performances with intravenous injection bottles and bottled water. The bottle series started with a performance-installation titled Fon Pan-ya and Dee U-raporn in 1993\n where the artist invited a pair of elderly villagers\n one 72-year-old male and one 64-year-old female\n in rural Chiang Mai to sit within two large vitrines holding two book covers embossed with details such as name\n age and address\n in order to highlight the disappearance of traditional values and modern society’s neglect of the elderly and illiterate.  This gradually morphed into black and white photographs of Thai villagers inserted into old medicine bottles and then displayed in wooden cabinets\n buried into mud-filled wooden troughs or on tiered open-shelf columns – the last being the work There is No Voice (1993) which was also shown at the seminal exhibition “Traditions/Tensions” in New York. Asking for Nothingness expands on the presentation of There is No Voice\n making it into a large-scale immersive room installation where the visitor meanders through the columns confronting or contemplating the myriad faces of the villagers.  Rawanchaikul’s message-in-a-bottle photographic archive of Chiang Mai\\u0027s marginalised aged reaffirms the educational\n historic\n and cultural significance our seniors can imbue\n if we take the time to preserve.","createdDate":"20201018182636","version":0,"latest":false,"roles":[],"metadata":{"accession_no_csv":"2017-00554-001 to 154","Image":"","object_work_type":"installations (visual works)","title_text":"Asking for Nothingness","preference":"main","title_language":"","creator_2":"Navin Rawanchaikul","creator_1":"Rawanchaikul, Navin","creator_role":"artists (visual artists)","creation_date":"1995-1997","creation_place_original_location":"Thailand","inscriptions":"","inscription_language":"","materials_name":"glass (material)  cork (bark)  wood (plant material)  photographic paper","techniques_name":"installing","object_colour":"multicoloured","physical_appearance":"This is an installation comprising of multiple wooden open-shelf columns with glass bottles that have been filled with black and white photographs. The height of the columns tower over the average person, and the arrangement allows for the visitor to walk into and around the installation.","subject_terms_1":"cultural heritage  elderly  group identity  memory","subject_terms_2":"Heritage  Older people  Group identity  Collective memory  Installations (Arts)","subject_terms_3":"Installation art","sgcool_label_text":"Asking for Nothingness is the largest work from Thai artist Navin Rawanchaikul’s series of bottle installations from the 1990s and rounds off a style that marked the artist’s early period of experimentation and social engagement, which included segues into assemblages and performances with intravenous injection bottles and bottled water. The bottle series started with a performance-installation titled Fon Pan-ya and Dee U-raporn in 1993, where the artist invited a pair of elderly villagers, one 72-year-old male and one 64-year-old female, in rural Chiang Mai to sit within two large vitrines holding two book covers embossed with details such as name, age and address, in order to highlight the disappearance of traditional values and modern society’s neglect of the elderly and illiterate.  This gradually morphed into black and white photographs of Thai villagers inserted into old medicine bottles and then displayed in wooden cabinets, buried into mud-filled wooden troughs or on tiered open-shelf columns – the last being the work There is No Voice (1993) which was also shown at the seminal exhibition “Traditions/Tensions” in New York. Asking for Nothingness expands on the presentation of There is No Voice, making it into a large-scale immersive room installation where the visitor meanders through the columns confronting or contemplating the myriad faces of the villagers.  Rawanchaikul’s message-in-a-bottle photographic archive of Chiang Mai\u0027s marginalised aged reaffirms the educational, historic, and cultural significance our seniors can imbue, if we take the time to preserve."},"nlpDate":"20201018182636","connectorId":0,"tags":{}}