{
  "id": "2017-00192-005",
  "title": "Chan Phui Kong Collection: Japanese Flag, Parachute Cloth, Photographs, Maps, Documents and Scarfs  Chan Phui Kong Collection: Military men on hilltop",
  "source": "Bumblebee",
  "path": "./Data/json/",
  "content": "\n  accession_no_csv: 2017-00192-005\n\n  Image: \n\n  object_work_type: black-and-white photographs\n\n  title_text: Chan Phui Kong Collection: Japanese Flag\n Parachute Cloth\n Photographs\n Maps\n Documents and Scarfs  Chan Phui Kong Collection: Military men on hilltop\n\n  preference: alternate main\n\n  title_language: \n\n  creation_date: 1942-2000\n\n  creation_place_original_location: Singapore\n\n  inscriptions: \n\n  inscription_language: \n\n  shape: rectangular\n\n  materials_name: paper (fiber product)\n\n  techniques_name: photographic processes\n\n  object_colour: black-and-white (colors)\n\n  physical_appearance: This is a black-and-white photograph. It features a group of men standing on a hilltop.  A man on the foreground on the left side is shirtless and in shorts. The others are dressed in military uniform\n with berets. They are all facing towards the left. In the background of the photograph\n there are several other men on the right. In the distance\n there are several hilltops. There are no tears or folds seen on the photograph.\n\n  subject_terms_1: world wars resistance movements soldiers\n\n  subject_terms_2: World War\n 1939-1945 Great Britain. Army. Force 136 Force 136 (Guerilla movement) Chin\n Phui Kong\n 1923- Photography Soldiers\n\n  subject_terms_3: Force 136 (Guerilla movement) 1942-1945 Japanese occupation Chin\n Phui Kong\n 1923- Photography war personalities\n\n  subject_terms_4: \n\n  context_1: World War\n 1939-1945 1942-1945 Japanese Occupation\n\n  context_2: world wars occupations (armed conflicts)\n\n  context_3: 1939-1945 1942-1945\n\n  context_4: 1939 1942\n\n  context_5: 1945 1945\n\n  context_6: Malaya Singapore\n\n  context_7: Great Britain. Army. Force 136\n\n  context_8: armed forces\n\n  sgcool_label_text: These materials belong to Chan Phui Kong and consist of items which he used in guerrilla warfare as a member of the World War II underground resistance movement known as Force 136.  They form part of a larger collection of materials gathered by Tan Chong Tee (1916- 2012)\n who was a key member of this resistance group. The collection consists of original materials belonging to Tan and other members of Force 136 dating from the 1940s to new materials reproduced from memory by Tan Chong Tee\n which date from the late 1980s to early 2000s.\\r\\n\\r\\nForce 136 was set up in July 1942 as part of the British Special Operations Executive (SOE). It recruited and trained local guerillas to gather intelligence and create an underground spy network to support planned British invasion of Japanese-occupied Malaya.\n",
  "createdDate": "20201120223707",
  "version": 0,
  "latest": false,
  "roles": [],
  "metadata": {
    "accession_no_csv": "2017-00192-005",
    "Image": "",
    "object_work_type": "black-and-white photographs",
    "title_text": "Chan Phui Kong Collection: Japanese Flag, Parachute Cloth, Photographs, Maps, Documents and Scarfs  Chan Phui Kong Collection: Military men on hilltop",
    "preference": "alternate main",
    "title_language": "",
    "creation_date": "1942-2000",
    "creation_place_original_location": "Singapore",
    "inscriptions": "",
    "inscription_language": "",
    "shape": "rectangular",
    "materials_name": "paper (fiber product)",
    "techniques_name": "photographic processes",
    "object_colour": "black-and-white (colors)",
    "physical_appearance": "This is a black-and-white photograph. It features a group of men standing on a hilltop.  A man on the foreground on the left side is shirtless and in shorts. The others are dressed in military uniform, with berets. They are all facing towards the left. In the background of the photograph, there are several other men on the right. In the distance, there are several hilltops. There are no tears or folds seen on the photograph.",
    "subject_terms_1": "world wars resistance movements soldiers",
    "subject_terms_2": "World War, 1939-1945 Great Britain. Army. Force 136 Force 136 (Guerilla movement) Chin, Phui Kong, 1923- Photography Soldiers",
    "subject_terms_3": "Force 136 (Guerilla movement) 1942-1945 Japanese occupation Chin, Phui Kong, 1923- Photography war personalities",
    "subject_terms_4": "",
    "context_1": "World War, 1939-1945 1942-1945 Japanese Occupation",
    "context_2": "world wars occupations (armed conflicts)",
    "context_3": "1939-1945 1942-1945",
    "context_4": "1939 1942",
    "context_5": "1945 1945",
    "context_6": "Malaya Singapore",
    "context_7": "Great Britain. Army. Force 136",
    "context_8": "armed forces",
    "sgcool_label_text": "These materials belong to Chan Phui Kong and consist of items which he used in guerrilla warfare as a member of the World War II underground resistance movement known as Force 136.  They form part of a larger collection of materials gathered by Tan Chong Tee (1916- 2012), who was a key member of this resistance group. The collection consists of original materials belonging to Tan and other members of Force 136 dating from the 1940s to new materials reproduced from memory by Tan Chong Tee, which date from the late 1980s to early 2000s.\r\n\r\nForce 136 was set up in July 1942 as part of the British Special Operations Executive (SOE). It recruited and trained local guerillas to gather intelligence and create an underground spy network to support planned British invasion of Japanese-occupied Malaya."
  },
  "nlpDate": "20201120223707",
  "connectorId": 0,
  "tags": {}
}