{
  "id": "2017-00288",
  "title": "Pencil diagrams for the Sime Road P.O.W. camp war graves (2 pieces) Sime Road P.O.W. camp war graves",
  "source": "Bumblebee",
  "path": "./Data/json/",
  "content": "\n  accession_no_csv: 2017-00288\n\n  Image: \n\n  object_work_type: drawings (visual works) diagrams\n\n  title_text: Pencil diagrams for the Sime Road P.O.W. camp war graves (2 pieces) Sime Road P.O.W. camp war graves\n\n  preference: main alternate\n\n  title_language: \n\n  creation_date: 1941-1945\n\n  creation_place_original_location: Singapore\n\n  inscriptions: \n\n  inscription_language: \n\n  shape: rectangular\n\n  materials_name: paper (fiber product)\n\n  techniques_name: drawing (image-making)\n\n  object_colour: black-and-white (colors)\n\n  physical_appearance: This is a drawn pencil diagram. It is drawn on two pieces of paper that were originally blank naval message forms. The top page shows a rough sketch of a building with an outside pathway linking across a garden at the bottom. The second page is split into two vertical sections\n each showing a different burial ground in a different camp.\n\n  subject_terms_1: site plans documents (object genre) world wars prisoners of war handwriting burial sites\n\n  subject_terms_2: Cemetries World War\n 1939-1945 Prisoners of war Writing\n\n  subject_terms_3: Changi Prison 1942-1945 Japanese occupation\n\n  subject_terms_4: \n\n  context_1: World War\n 1939-1945 1942-1945 Japanese Occupation\n\n  context_2: occupations (armed conflicts) world wars\n\n  context_3: 1942-1945 1939-1945\n\n  context_4: 1939 1942\n\n  context_5: 1945\n\n  context_6: Singapore Malaya\n\n  context_7: Great Britain. Army. Royal Field Artillery\n\n  context_8: armed forces\n\n  sgcool_label_text: Once the Malaya Command Battle Headquarters\n the fall of Singapore in 1942 saw the Sime Road Camp being converted into temporary quarters for POWs working within the vicinity\n as well as a staging post for prisoners who were sent up-country to work on the infamous ‘death railway’\n the Thailand-Burma railway. Life at the Sime Road Camp was deplorable - characterised by hunger\n disease and death. This artefact which speaks to life at Sime Road camp is part of the archive of James Steele\n Royal Artillery (Field) who served in Malaya from January 1941-February 1942\n when interned as a P.O.W at Changi until his release in October 1945.\n",
  "createdDate": "20201125084523",
  "version": 0,
  "latest": false,
  "roles": [],
  "metadata": {
    "accession_no_csv": "2017-00288",
    "Image": "",
    "object_work_type": "drawings (visual works) diagrams",
    "title_text": "Pencil diagrams for the Sime Road P.O.W. camp war graves (2 pieces) Sime Road P.O.W. camp war graves",
    "preference": "main alternate",
    "title_language": "",
    "creation_date": "1941-1945",
    "creation_place_original_location": "Singapore",
    "inscriptions": "",
    "inscription_language": "",
    "shape": "rectangular",
    "materials_name": "paper (fiber product)",
    "techniques_name": "drawing (image-making)",
    "object_colour": "black-and-white (colors)",
    "physical_appearance": "This is a drawn pencil diagram. It is drawn on two pieces of paper that were originally blank naval message forms. The top page shows a rough sketch of a building with an outside pathway linking across a garden at the bottom. The second page is split into two vertical sections, each showing a different burial ground in a different camp.",
    "subject_terms_1": "site plans documents (object genre) world wars prisoners of war handwriting burial sites",
    "subject_terms_2": "Cemetries World War, 1939-1945 Prisoners of war Writing",
    "subject_terms_3": "Changi Prison 1942-1945 Japanese occupation",
    "subject_terms_4": "",
    "context_1": "World War, 1939-1945 1942-1945 Japanese Occupation",
    "context_2": "occupations (armed conflicts) world wars",
    "context_3": "1942-1945 1939-1945",
    "context_4": "1939 1942",
    "context_5": "1945",
    "context_6": "Singapore Malaya",
    "context_7": "Great Britain. Army. Royal Field Artillery",
    "context_8": "armed forces",
    "sgcool_label_text": "Once the Malaya Command Battle Headquarters, the fall of Singapore in 1942 saw the Sime Road Camp being converted into temporary quarters for POWs working within the vicinity, as well as a staging post for prisoners who were sent up-country to work on the infamous ‘death railway’, the Thailand-Burma railway. Life at the Sime Road Camp was deplorable - characterised by hunger, disease and death. This artefact which speaks to life at Sime Road camp is part of the archive of James Steele, Royal Artillery (Field) who served in Malaya from January 1941-February 1942, when interned as a P.O.W at Changi until his release in October 1945."
  },
  "nlpDate": "20201125084523",
  "connectorId": 0,
  "tags": {}
}