{
  "id": "2017-00558 and 2017-00559",
  "title": "2 \u0027Cap Mohor\u0027 (Business or brand seals)",
  "source": "Bumblebee",
  "path": "./Data/json/",
  "content": "\n  accession_no_csv: 2017-00558 and 2017-00559\n\n  Image: \n\n  object_work_type: seals (artifacts)\n\n  title_text: 2 \\u0027Cap Mohor\\u0027 (Business or brand seals)\n\n  preference: main\n\n  title_language: \n\n  creation_date: 19th-20th century\n\n  creation_place_original_location: Straits Settlements\n\n  inscriptions: \n\n  inscription_language: \n\n  shape: octagonal ? circular (shape)\n\n  materials_name: stone (worked rock) metal\n\n  techniques_name: inscribing\n\n  object_colour: black (colour)\n\n  physical_appearance: \\This is a set of seals. One is circular inscribed with a stylised \\\\J\\\\ while the other is octagonal with a Jawi inscription. \\\n\n  subject_terms_1: stamping (marking)  merchants  business (commercial function)\n\n  subject_terms_2: Stamp seals  Jawi alphabet  Business  Merchants  Straits Settlements\n\n  subject_terms_3: Decorative arts\n\n  subject_terms_4: \n\n  sgcool_label_text: Not indicated\n",
  "createdDate": "20201120223708",
  "version": 0,
  "latest": false,
  "roles": [],
  "metadata": {
    "accession_no_csv": "2017-00558 and 2017-00559",
    "Image": "",
    "object_work_type": "seals (artifacts)",
    "title_text": "2 \u0027Cap Mohor\u0027 (Business or brand seals)",
    "preference": "main",
    "title_language": "",
    "creation_date": "19th-20th century",
    "creation_place_original_location": "Straits Settlements",
    "inscriptions": "",
    "inscription_language": "",
    "shape": "octagonal ? circular (shape)",
    "materials_name": "stone (worked rock) metal",
    "techniques_name": "inscribing",
    "object_colour": "black (colour)",
    "physical_appearance": "\"This is a set of seals. One is circular inscribed with a stylised \"\"J\"\" while the other is octagonal with a Jawi inscription. \"",
    "subject_terms_1": "stamping (marking)  merchants  business (commercial function)",
    "subject_terms_2": "Stamp seals  Jawi alphabet  Business  Merchants  Straits Settlements",
    "subject_terms_3": "Decorative arts",
    "subject_terms_4": "",
    "sgcool_label_text": "Not indicated"
  },
  "nlpDate": "20201120223708",
  "connectorId": 0,
  "tags": {}
}