{
  "id": "2017-00152",
  "title": "Lung Chui Ying Collection: Certificate of Registration for Overseas Chinese  belonging to Lung Chui Ying ????? Lung Chiu Ying Collection: Certificate of Registration for Overseas Chinese  belonging to Lung Chui Ying",
  "source": "Bumblebee",
  "path": "./Data/json/",
  "content": "\n  accession_no_csv: 2017-00152\n\n  Image: \n\n  object_work_type: certificates\n\n  title_text: Lung Chui Ying Collection: Certificate of Registration for Overseas Chinese  belonging to Lung Chui Ying ????? Lung Chiu Ying Collection: Certificate of Registration for Overseas Chinese  belonging to Lung Chui Ying\n\n  preference: alternate alternate main\n\n  title_language: \n\n  creation_date: 1937\n\n  creation_place_original_location: Singapore\n\n  inscriptions: \n\n  inscription_language: \n\n  shape: rectangular\n\n  materials_name: paper (fiber product)\n\n  techniques_name: printing (process)\n\n  object_colour: multicolored\n\n  physical_appearance: This is a certificate of registration. The cover is black\n and looks textured. In the center\n the title for \\u0027Certificate of Registration for Overseas Chinese\\u0027 is printed vertically in Chinese. Above it\n there is an emblem of a sun within a circle. The emblem and the title are slightly faded.\n\n  subject_terms_1: world wars resistance movements documents (object genre) Chinese scripts\n\n  subject_terms_2: World War\n 1939-1945 Great Britain. Army. Force 136 Force 136 (Guerilla movement) Certification\n\n  subject_terms_3: Force 136 (Guerilla movement) 1942-1945 Japanese occupation Lung\n Chiu Ying\n\n  subject_terms_4: \n\n  sgcool_label_text: This Certificate of Registration belongs to Lung Chui Ying and is part of a larger collection of artefacts related to the World War II underground resistance movement known as Force 136. The collection of materials was gathered by Tan Chong Tee (1916- 2012)\n who was a key member of this resistance group. The collection consists of original materials belonging to Tan and other members of Force 136 dating from the 1940s to new materials reproduced from memory by Tan Chong Tee\n which date from the mid-1990s to early 2000s. \\r\\n\\r\\nForce 136 was set up in July 1942 as part of the British Special Operations Executive (SOE). It recruited and trained local guerillas to gather intelligence and create an underground spy network to support planned British invasion of Japanese-occupied Malaya.\n",
  "createdDate": "20201120223707",
  "version": 0,
  "latest": false,
  "roles": [],
  "metadata": {
    "accession_no_csv": "2017-00152",
    "Image": "",
    "object_work_type": "certificates",
    "title_text": "Lung Chui Ying Collection: Certificate of Registration for Overseas Chinese  belonging to Lung Chui Ying ????? Lung Chiu Ying Collection: Certificate of Registration for Overseas Chinese  belonging to Lung Chui Ying",
    "preference": "alternate alternate main",
    "title_language": "",
    "creation_date": "1937",
    "creation_place_original_location": "Singapore",
    "inscriptions": "",
    "inscription_language": "",
    "shape": "rectangular",
    "materials_name": "paper (fiber product)",
    "techniques_name": "printing (process)",
    "object_colour": "multicolored",
    "physical_appearance": "This is a certificate of registration. The cover is black, and looks textured. In the center, the title for \u0027Certificate of Registration for Overseas Chinese\u0027 is printed vertically in Chinese. Above it, there is an emblem of a sun within a circle. The emblem and the title are slightly faded.",
    "subject_terms_1": "world wars resistance movements documents (object genre) Chinese scripts",
    "subject_terms_2": "World War, 1939-1945 Great Britain. Army. Force 136 Force 136 (Guerilla movement) Certification",
    "subject_terms_3": "Force 136 (Guerilla movement) 1942-1945 Japanese occupation Lung, Chiu Ying",
    "subject_terms_4": "",
    "sgcool_label_text": "This Certificate of Registration belongs to Lung Chui Ying and is part of a larger collection of artefacts related to the World War II underground resistance movement known as Force 136. The collection of materials was gathered by Tan Chong Tee (1916- 2012), who was a key member of this resistance group. The collection consists of original materials belonging to Tan and other members of Force 136 dating from the 1940s to new materials reproduced from memory by Tan Chong Tee, which date from the mid-1990s to early 2000s. \r\n\r\nForce 136 was set up in July 1942 as part of the British Special Operations Executive (SOE). It recruited and trained local guerillas to gather intelligence and create an underground spy network to support planned British invasion of Japanese-occupied Malaya."
  },
  "nlpDate": "20201120223707",
  "connectorId": 0,
  "tags": {}
}