{
  "id": "2017-00541",
  "title": "Ossuary figure",
  "source": "Bumblebee",
  "path": "./Data/json/",
  "content": "\n  accession_no_csv: 2017-00541\n\n  Image: \n\n  object_work_type: figurines  fetishes\n\n  title_text: Ossuary figure\n\n  preference: main\n\n  title_language: \n\n  creation_date: 19th century or earlier\n\n  creation_place_original_location: Mahakam River Delta (Indonesia)\n\n  inscriptions: \n\n  inscription_language: \n\n  shape: irregular\n\n  materials_name: wood (plant material)\n\n  techniques_name: carving (processes)\n\n  object_colour: brown (colour)\n\n  physical_appearance: This is a carved ossuary figure in a squatting position. Its palms are facing up and elbow resting on its kneecaps. The eye sockets are hollow and its teeth are bared.\n\n  subject_terms_1: indigenous people  magic  ancestor worship  ossuaries (funerary containers) sculpture\n\n  subject_terms_2: Fetishes (Ceremonial objects) Wood-carved figurines  Ossuaries  Ancestor worship  Protection magic  Figurative art Sculpture\n\n  subject_terms_3: Religious life and practices  Sculpture\n\n  subject_terms_4: \n\n  sgcool_label_text: This figure would have originally adorned the end of a bone box or ossuary used to carefully store the remains of revered ancestors. It was found hidden deep inside a cave.  It is probably meant to represent an ancestor\n a protecting spirit intended to frighten away thieves and evil spirits alike.  Ancestor figures carved in the form of a squatting man are found all over island Southeast Asia and are a common theme in the art of the Austronesian people.\n",
  "createdDate": "20201120223708",
  "version": 0,
  "latest": false,
  "roles": [],
  "metadata": {
    "accession_no_csv": "2017-00541",
    "Image": "",
    "object_work_type": "figurines  fetishes",
    "title_text": "Ossuary figure",
    "preference": "main",
    "title_language": "",
    "creation_date": "19th century or earlier",
    "creation_place_original_location": "Mahakam River Delta (Indonesia)",
    "inscriptions": "",
    "inscription_language": "",
    "shape": "irregular",
    "materials_name": "wood (plant material)",
    "techniques_name": "carving (processes)",
    "object_colour": "brown (colour)",
    "physical_appearance": "This is a carved ossuary figure in a squatting position. Its palms are facing up and elbow resting on its kneecaps. The eye sockets are hollow and its teeth are bared.",
    "subject_terms_1": "indigenous people  magic  ancestor worship  ossuaries (funerary containers) sculpture",
    "subject_terms_2": "Fetishes (Ceremonial objects) Wood-carved figurines  Ossuaries  Ancestor worship  Protection magic  Figurative art Sculpture",
    "subject_terms_3": "Religious life and practices  Sculpture",
    "subject_terms_4": "",
    "sgcool_label_text": "This figure would have originally adorned the end of a bone box or ossuary used to carefully store the remains of revered ancestors. It was found hidden deep inside a cave.  It is probably meant to represent an ancestor, a protecting spirit intended to frighten away thieves and evil spirits alike.  Ancestor figures carved in the form of a squatting man are found all over island Southeast Asia and are a common theme in the art of the Austronesian people."
  },
  "nlpDate": "20201120223708",
  "connectorId": 0,
  "tags": {}
}