{"id":"2017-00230","title":"The Matriarch of Negros","source":"Bumblebee","path":"./Data/json/","content":"accession_no_csv:2017-00230\nImage:\nobject_work_type:collages (visual works)  fabric art (visual works)\ntitle_text:The Matriarch of Negros\npreference:main\ntitle_language:\ncreator_2:Norberto Roldan\ncreator_1:Roldan\n Norberto\ncreator_role:artists (visual artists)\ncreation_date:1989\ncreation_place_original_location:Philippines\ninscriptions:\ninscription_language:\nshape:Rectangular\nmaterials_name:cloth  bamboo (material)\ntechniques_name:stitching (generic process)  embroidering  screen printing  weaving  beading (process)\nobject_colour:multicoloured\nphysical_appearance:\\This is an assemblage consisting of baby amulet beeds\n silk screen images of familiries and embroidery. The base fabric is that of traditional Visayan \\\\patadyong\\\\. The central image has a green tint\nsubject_terms_1:and is framed in a square shaped embroidery. Two other silk screen images of individuals can be found on the top right and left corners. \\ memory  group identity  collective biographies biography (genre)  ethnicity\nsubject_terms_2:material culture (genre)  Visayan Islands (Philippines) Group identity Ethnicity Collective memory  Biography\nsubject_terms_3:Material culture Mixed media artists\nsubject_terms_4:visual arts","createdDate":"20201119143406","version":0,"latest":false,"roles":[],"metadata":{"accession_no_csv":"2017-00230","Image":"","object_work_type":"collages (visual works)  fabric art (visual works)","title_text":"The Matriarch of Negros","preference":"main","title_language":"","creator_2":"Norberto Roldan","creator_1":"Roldan, Norberto","creator_role":"artists (visual artists)","creation_date":"1989","creation_place_original_location":"Philippines","inscriptions":"","inscription_language":"","shape":"Rectangular","materials_name":"cloth  bamboo (material)","techniques_name":"stitching (generic process)  embroidering  screen printing  weaving  beading (process)","object_colour":"multicoloured","physical_appearance":"\"This is an assemblage consisting of baby amulet beeds, silk screen images of familiries and embroidery. The base fabric is that of traditional Visayan \"\"patadyong\"\". The central image has a green tint","subject_terms_1":"and is framed in a square shaped embroidery. Two other silk screen images of individuals can be found on the top right and left corners. \" memory  group identity  collective biographies biography (genre)  ethnicity","subject_terms_2":"material culture (genre)  Visayan Islands (Philippines) Group identity Ethnicity Collective memory  Biography","subject_terms_3":"Material culture Mixed media artists","subject_terms_4":"visual arts"},"nlpDate":"20201119143406","connectorId":0,"tags":{}}