{"id":"2017-00131","title":"Tan Chong Tee Collection: Certificate of registration of a teacher  ?????","source":"Bumblebee","path":"./Data/json/","content":"accession_no_csv:2017-00131\nImage:\nobject_work_type:registrations (licences)\ntitle_text:Tan Chong Tee Collection: Certificate of registration of a teacher  ?????\npreference:main alternate\ntitle_language:\ncreation_date:1933\ncreation_place_original_location:Singapore\ninscriptions:\ninscription_language:\nshape:rectangular\nmaterials_name:paper (fiber product)\ntechniques_name:printing (process)\nobject_colour:multicolored\nphysical_appearance:This is a document certifying the registration of a teacher. The title is printed at the top-center of the document. The document is printed in black ink\n with blue stamps\n and black handwritten inscriptions. The document is slightly folded and torn\n especially along the bottom and edges.\nsubject_terms_1:world wars resistance movements documents (object genre) teachers\nsubject_terms_2:Certification World War\n 1939-1945 Great Britain. Army. Force 136 Force 136 (Guerilla movement) Chen\n Chongzhi\n 1916- Teachers\nsubject_terms_3:Force 136 (Guerilla movement) Tan\n Chong Tee 1942-1945 Japanese occupation\nsubject_terms_4:\nsgcool_label_text:This certificate belongs to part of a collection of artefacts related to the World War II underground resistance movement known as Force 136. The collection of materials was gathered by Tan Chong Tee (1916- 2012)\n who was a key member of this resistance group. The collection consists of original materials belonging to Tan and other members of Force 136 dating from the 1940s to new materials reproduced from memory by Tan Chong Tee\n which date from the late 1980s to early 2000s. \\r\\n\\r\\nForce 136 was set up in July 1942 as part of the British Special Operations Executive (SOE). It recruited and trained local guerillas to gather intelligence and create an underground spy network to support planned British invasion of Japanese-occupied Malaya.","createdDate":"20201119143406","version":0,"latest":false,"roles":[],"metadata":{"accession_no_csv":"2017-00131","Image":"","object_work_type":"registrations (licences)","title_text":"Tan Chong Tee Collection: Certificate of registration of a teacher  ?????","preference":"main alternate","title_language":"","creation_date":"1933","creation_place_original_location":"Singapore","inscriptions":"","inscription_language":"","shape":"rectangular","materials_name":"paper (fiber product)","techniques_name":"printing (process)","object_colour":"multicolored","physical_appearance":"This is a document certifying the registration of a teacher. The title is printed at the top-center of the document. The document is printed in black ink, with blue stamps, and black handwritten inscriptions. The document is slightly folded and torn, especially along the bottom and edges.","subject_terms_1":"world wars resistance movements documents (object genre) teachers","subject_terms_2":"Certification World War, 1939-1945 Great Britain. Army. Force 136 Force 136 (Guerilla movement) Chen, Chongzhi, 1916- Teachers","subject_terms_3":"Force 136 (Guerilla movement) Tan, Chong Tee 1942-1945 Japanese occupation","subject_terms_4":"","sgcool_label_text":"This certificate belongs to part of a collection of artefacts related to the World War II underground resistance movement known as Force 136. The collection of materials was gathered by Tan Chong Tee (1916- 2012), who was a key member of this resistance group. The collection consists of original materials belonging to Tan and other members of Force 136 dating from the 1940s to new materials reproduced from memory by Tan Chong Tee, which date from the late 1980s to early 2000s. \r\n\r\nForce 136 was set up in July 1942 as part of the British Special Operations Executive (SOE). It recruited and trained local guerillas to gather intelligence and create an underground spy network to support planned British invasion of Japanese-occupied Malaya."},"nlpDate":"20201119143406","connectorId":0,"tags":{}}