{
  "id": "2017-00810 ",
  "title": "Men’s black silk satin short jacket with a woven pattern of medallions set against an overall cloud pattern",
  "source": "Bumblebee",
  "path": "./Data/json/",
  "content": "\n  accession_no_csv: 2017-00810 \n\n  Image: \n\n  object_work_type: silks (costume by material) jackets (garments)\n\n  title_text: Men’s black silk satin short jacket with a woven pattern of medallions set against an overall cloud pattern\n\n  preference: main\n\n  title_language: \n\n  creation_date: 1920s-1930s\n\n  creation_place_original_location: Hong Kong (China)\n\n  styles_periods_indexing_terms: Chinese (culture or style)\n\n  inscriptions: \n\n  inscription_language: \n\n  shape: T-shaped?\n\n  materials_name: silk (textile)\n\n  techniques_name: sewing (needleworking technique)\n\n  object_colour: black (colour)\n\n  physical_appearance: This is a black silk satin short jacket that buttons down the middle. It is decorated with a woven pattern of medallions set amidst an elaborate cloud pattern.\n\n  subject_terms_1: menswear medallions (ornament areas) cloud scrolls / cloud bands? folk costume casual wear\n\n  subject_terms_2: Silk Clouds in art Ethnic costume Men\\u0027s clothing Medallions (Decorative arts) Jackets\n\n  subject_terms_3: Chinese costumes\n\n  context_20: Bullion Trading Company “Yee Shing”\n\n  context_21: 20 Canal Road in Singapore\n\n  context_22: 1930s\n\n  context_23: 1930\n\n  context_24: 1939\n\n  sgcool_label_text: This short jacket is known as a ‘magua’  and was worn over a long robe (‘changshan’ or ‘changpao’) in the early 20th century in China and Hong Kong. It was the standard informal garment worn by men during the early Republican period.\\r\\n\\r\\nThis silk satin jacket would have been worn by Mr Kaan Tat Choi’s son. Mr Kaan was a successful businessman in the bullion business. He expanded his business from Hong Kong to Malaya in the 1920s\n acquiring several rubber plantations along the east coast of Malaya. Mr Kaan also opened a bullion trading company called “Yee Shing” at 20 Canal Road in Singapore in the 1930s. \\r\\n\n",
  "createdDate": "20201201203308",
  "version": 0,
  "latest": false,
  "roles": [],
  "metadata": {
    "accession_no_csv": "2017-00810 ",
    "Image": "",
    "object_work_type": "silks (costume by material) jackets (garments)",
    "title_text": "Men’s black silk satin short jacket with a woven pattern of medallions set against an overall cloud pattern",
    "preference": "main",
    "title_language": "",
    "creation_date": "1920s-1930s",
    "creation_place_original_location": "Hong Kong (China)",
    "styles_periods_indexing_terms": "Chinese (culture or style)",
    "inscriptions": "",
    "inscription_language": "",
    "shape": "T-shaped?",
    "materials_name": "silk (textile)",
    "techniques_name": "sewing (needleworking technique)",
    "object_colour": "black (colour)",
    "physical_appearance": "This is a black silk satin short jacket that buttons down the middle. It is decorated with a woven pattern of medallions set amidst an elaborate cloud pattern.",
    "subject_terms_1": "menswear medallions (ornament areas) cloud scrolls / cloud bands? folk costume casual wear",
    "subject_terms_2": "Silk Clouds in art Ethnic costume Men\u0027s clothing Medallions (Decorative arts) Jackets",
    "subject_terms_3": "Chinese costumes",
    "context_20": "Bullion Trading Company “Yee Shing”",
    "context_21": "20 Canal Road in Singapore",
    "context_22": "1930s",
    "context_23": "1930",
    "context_24": "1939",
    "sgcool_label_text": "This short jacket is known as a ‘magua’  and was worn over a long robe (‘changshan’ or ‘changpao’) in the early 20th century in China and Hong Kong. It was the standard informal garment worn by men during the early Republican period.\r\n\r\nThis silk satin jacket would have been worn by Mr Kaan Tat Choi’s son. Mr Kaan was a successful businessman in the bullion business. He expanded his business from Hong Kong to Malaya in the 1920s, acquiring several rubber plantations along the east coast of Malaya. Mr Kaan also opened a bullion trading company called “Yee Shing” at 20 Canal Road in Singapore in the 1930s. \r\n"
  },
  "nlpDate": "20201201203308",
  "connectorId": 0,
  "tags": {}
}