{"id":"2017-00481-008","title":"Linoleographs- Baharoedin \u0026 Mochtar Apin","source":"Bumblebee","path":"./Data/json/","content":"accession_no_csv:2017-00481-008\nImage:\nobject_work_type:artists\\u0027 books (books)\ntitle_text:Linoleographs- Baharoedin \\u0026 Mochtar Apin\npreference:main\ntitle_language:\ncreator_2:Mochtar Apin\ncreator_1:Apin\n Mochtar\ncreator_role:artists (visual artists)\ncreation_date:1946\ncreation_place_original_location:Bandung (Indonesia)\nstyles_periods_indexing_terms:Indonesian (culture or style)\ninscriptions:\ninscription_language:\nshape:Rectangular\nmaterials_name:paper (fiber product)\ntechniques_name:linoleum block printing\nobject_colour:black-and-white (colors)\nphysical_appearance:This is an index page of the contents of the folder in three languages; Bahasa Indonesia\n French\n and English\nsubject_terms_1:indexes (reference sources)\nsubject_terms_2:Indexes\nsubject_terms_3:visual arts\ncontext_1:First anniversary of Indonesia\\u0027s Declaration of Independence\ncontext_2:national holidays\ncontext_3:17-Aug-46\ncontext_4:17-Aug-46\ncontext_5:17-Aug-46\ncontext_6:Indonesia\ncontext_7:Indonesian Government ?\ncontext_8:commissioners (people who order works)\nsgcool_label_text:This folio of 19 prints is a historically significant body of work relating to Indonesia’s Declaration of Independence in 1945. Commissioned by the Indonesia Bureau of Youth Affairs to celebrate the first anniversary of Indonesia’s independence\n Baharoedin was informed that the government was interested in producing some propaganda materials. Consisting of 10 prints by Baharoedin and 9 prints by Apin\n the works depict various images associated with the nation’s struggle towards Independence. 36 of these folios were then printed and distributed to various countries who had recognized Indonesia’s independence during that period.","createdDate":"20201018182636","version":0,"latest":false,"roles":[],"metadata":{"accession_no_csv":"2017-00481-008","Image":"","object_work_type":"artists\u0027 books (books)","title_text":"Linoleographs- Baharoedin \u0026 Mochtar Apin","preference":"main","title_language":"","creator_2":"Mochtar Apin","creator_1":"Apin, Mochtar","creator_role":"artists (visual artists)","creation_date":"1946","creation_place_original_location":"Bandung (Indonesia)","styles_periods_indexing_terms":"Indonesian (culture or style)","inscriptions":"","inscription_language":"","shape":"Rectangular","materials_name":"paper (fiber product)","techniques_name":"linoleum block printing","object_colour":"black-and-white (colors)","physical_appearance":"This is an index page of the contents of the folder in three languages; Bahasa Indonesia, French, and English","subject_terms_1":"indexes (reference sources)","subject_terms_2":"Indexes","subject_terms_3":"visual arts","context_1":"First anniversary of Indonesia\u0027s Declaration of Independence","context_2":"national holidays","context_3":"17-Aug-46","context_4":"17-Aug-46","context_5":"17-Aug-46","context_6":"Indonesia","context_7":"Indonesian Government ?","context_8":"commissioners (people who order works)","sgcool_label_text":"This folio of 19 prints is a historically significant body of work relating to Indonesia’s Declaration of Independence in 1945. Commissioned by the Indonesia Bureau of Youth Affairs to celebrate the first anniversary of Indonesia’s independence, Baharoedin was informed that the government was interested in producing some propaganda materials. Consisting of 10 prints by Baharoedin and 9 prints by Apin, the works depict various images associated with the nation’s struggle towards Independence. 36 of these folios were then printed and distributed to various countries who had recognized Indonesia’s independence during that period."},"nlpDate":"20201018182636","connectorId":0,"tags":{}}