{
  "id": "2017-00191",
  "title": "Chan Phui Kong Collection: Banner",
  "source": "Bumblebee",
  "path": "./Data/json/",
  "content": "\n  accession_no_csv: 2017-00191\n\n  Image: \n\n  object_work_type: banners\n\n  title_text: Chan Phui Kong Collection: Banner\n\n  preference: main\n\n  title_language: \n\n  creation_date: 1940s\n\n  creation_place_original_location: Singapore\n\n  inscriptions: \n\n  inscription_language: \n\n  shape: irregular\n\n  materials_name: silk (textile) linen (material)\n\n  techniques_name: sewing (needleworking technique)\n\n  object_colour: multicolored\n\n  physical_appearance: This is a banner. It has a flat square top\n and hangs downwards\n with an angular shape at the bottom. The bottom hem is lined with loose threads. The banner features a large logo in the center\n topped with the shape of a bird with outstretched wings. Below the bird\n there are several lines of Chinese scripts.\n\n  subject_terms_1: resistance movements world wars Chinese scripts birds (motifs)\n\n  subject_terms_2: World War\n 1939-1945 Motifs Chin\n Phui Kong\n 1923- Great Britain. Army. Force 136 Banners Force 136 (Guerilla movement)\n\n  subject_terms_3: 1942-1945 Japanese occupation Chin\n Phui Kong\n 1923- Textile art and design Force 136 (Guerilla movement) war personalities\n\n  subject_terms_4: \n\n  context_1: World War\n 1939-1945 1942-1945 Japanese Occupation\n\n  context_2: occupations (armed conflicts) world wars\n\n  context_3: 1942-1945 1939-1945\n\n  context_4: 1939 1942\n\n  context_5: 1945\n\n  context_6: Singapore Malaya\n\n  context_7: Great Britain. Army. Force 136\n\n  context_8: armed forces\n\n  sgcool_label_text: This banner belongs to part of a collection of artefacts owned by Chan Phui Kong who was involved in the World War II underground resistance movement known as Force 136.  Chan’s collection forms part of a larger collection of materials gathered by Tan Chong Tee (1916- 2012)\n who was a key member of this resistance group. The collection consists of original materials belonging to Tan and other members of Force 136 dating from the 1940s to new materials reproduced from memory by Tan Chong Tee\n which date from the late 1980s to early 2000s. \\r\\n\\r\\nForce 136 was set up in July 1942 as part of the British Special Operations Executive (SOE). It recruited and trained local guerillas to gather intelligence and create an underground spy network to support planned British invasion of Japanese-occupied Malaya.\\r\\n\n",
  "createdDate": "20201125084524",
  "version": 0,
  "latest": false,
  "roles": [],
  "metadata": {
    "accession_no_csv": "2017-00191",
    "Image": "",
    "object_work_type": "banners",
    "title_text": "Chan Phui Kong Collection: Banner",
    "preference": "main",
    "title_language": "",
    "creation_date": "1940s",
    "creation_place_original_location": "Singapore",
    "inscriptions": "",
    "inscription_language": "",
    "shape": "irregular",
    "materials_name": "silk (textile) linen (material)",
    "techniques_name": "sewing (needleworking technique)",
    "object_colour": "multicolored",
    "physical_appearance": "This is a banner. It has a flat square top, and hangs downwards, with an angular shape at the bottom. The bottom hem is lined with loose threads. The banner features a large logo in the center, topped with the shape of a bird with outstretched wings. Below the bird, there are several lines of Chinese scripts.",
    "subject_terms_1": "resistance movements world wars Chinese scripts birds (motifs)",
    "subject_terms_2": "World War, 1939-1945 Motifs Chin, Phui Kong, 1923- Great Britain. Army. Force 136 Banners Force 136 (Guerilla movement)",
    "subject_terms_3": "1942-1945 Japanese occupation Chin, Phui Kong, 1923- Textile art and design Force 136 (Guerilla movement) war personalities",
    "subject_terms_4": "",
    "context_1": "World War, 1939-1945 1942-1945 Japanese Occupation",
    "context_2": "occupations (armed conflicts) world wars",
    "context_3": "1942-1945 1939-1945",
    "context_4": "1939 1942",
    "context_5": "1945",
    "context_6": "Singapore Malaya",
    "context_7": "Great Britain. Army. Force 136",
    "context_8": "armed forces",
    "sgcool_label_text": "This banner belongs to part of a collection of artefacts owned by Chan Phui Kong who was involved in the World War II underground resistance movement known as Force 136.  Chan’s collection forms part of a larger collection of materials gathered by Tan Chong Tee (1916- 2012), who was a key member of this resistance group. The collection consists of original materials belonging to Tan and other members of Force 136 dating from the 1940s to new materials reproduced from memory by Tan Chong Tee, which date from the late 1980s to early 2000s. \r\n\r\nForce 136 was set up in July 1942 as part of the British Special Operations Executive (SOE). It recruited and trained local guerillas to gather intelligence and create an underground spy network to support planned British invasion of Japanese-occupied Malaya.\r\n"
  },
  "nlpDate": "20201125084524",
  "connectorId": 0,
  "tags": {}
}