{"id":"2017-00166","title":"Report on Demobilisation of Force 136","source":"Bumblebee","path":"./Data/json/","content":"accession_no_csv:2017-00166\nImage:\nobject_work_type:reports\ntitle_text:Report on Demobilisation of Force 136\npreference:main\ntitle_language:\ncreation_date:1945\ncreation_place_original_location:Singapore\ninscriptions:\ninscription_language:\nshape:rectangular\nmaterials_name:paper (fiber product)\ntechniques_name:writing (processes)\nobject_colour:black-and-white (colors)\nphysical_appearance:This is a report on demobilisation of Force 136. It consists of six pages\n written in vertical columns. There are several holes on the document\n especially on the first page on the right.\nsubject_terms_1:world wars resistance movements documents (object genre) handwriting Chinese scripts\nsubject_terms_2:World War\n 1939-1945 Great Britain. Army. Force 136 Force 136 (Guerilla movement) Demobilization Chen\n Chongzhi\n 1916- Writing\nsubject_terms_3:Force 136 (Guerilla movement) 1942-1945 Japanese occupation Tan\n Chong Tee\nsubject_terms_4:\ncontext_1:World War\n 1939-1945 1942-1945 Japanese Occupation\ncontext_2:world wars occupations (armed conflicts)\ncontext_3:1939-1945 1942-1945\ncontext_4:1939 1942\ncontext_5:1945 1945\ncontext_6:Malaya Singapore\ncontext_7:Great Britain. Army. Force 136\ncontext_8:armed forces\nsgcool_label_text:This report belongs to part of a collection of artefacts related to the World War II underground resistance movement known as Force 136. The collection of materials was gathered by Tan Chong Tee (1916- 2012)\n who was a key member of this resistance group. The collection consists of original materials belonging to Tan and other members of Force 136 dating from the 1940s to new materials reproduced from memory by Tan Chong Tee\n which date from the mid-1990s to early 2000s. \\r\\n\\r\\nForce 136 was set up in July 1942 as part of the British Special Operations Executive (SOE). It recruited and trained local guerillas to gather intelligence and create an underground spy network to support planned British invasion of Japanese-occupied Malaya.\\r\\n\\r\\nThis report outlines the work revolving the demobilisation of Force 136 at the end of the war. \\r\\n","createdDate":"20201119143406","version":0,"latest":false,"roles":[],"metadata":{"accession_no_csv":"2017-00166","Image":"","object_work_type":"reports","title_text":"Report on Demobilisation of Force 136","preference":"main","title_language":"","creation_date":"1945","creation_place_original_location":"Singapore","inscriptions":"","inscription_language":"","shape":"rectangular","materials_name":"paper (fiber product)","techniques_name":"writing (processes)","object_colour":"black-and-white (colors)","physical_appearance":"This is a report on demobilisation of Force 136. It consists of six pages, written in vertical columns. There are several holes on the document, especially on the first page on the right.","subject_terms_1":"world wars resistance movements documents (object genre) handwriting Chinese scripts","subject_terms_2":"World War, 1939-1945 Great Britain. Army. Force 136 Force 136 (Guerilla movement) Demobilization Chen, Chongzhi, 1916- Writing","subject_terms_3":"Force 136 (Guerilla movement) 1942-1945 Japanese occupation Tan, Chong Tee","subject_terms_4":"","context_1":"World War, 1939-1945 1942-1945 Japanese Occupation","context_2":"world wars occupations (armed conflicts)","context_3":"1939-1945 1942-1945","context_4":"1939 1942","context_5":"1945 1945","context_6":"Malaya Singapore","context_7":"Great Britain. Army. Force 136","context_8":"armed forces","sgcool_label_text":"This report belongs to part of a collection of artefacts related to the World War II underground resistance movement known as Force 136. The collection of materials was gathered by Tan Chong Tee (1916- 2012), who was a key member of this resistance group. The collection consists of original materials belonging to Tan and other members of Force 136 dating from the 1940s to new materials reproduced from memory by Tan Chong Tee, which date from the mid-1990s to early 2000s. \r\n\r\nForce 136 was set up in July 1942 as part of the British Special Operations Executive (SOE). It recruited and trained local guerillas to gather intelligence and create an underground spy network to support planned British invasion of Japanese-occupied Malaya.\r\n\r\nThis report outlines the work revolving the demobilisation of Force 136 at the end of the war. \r\n"},"nlpDate":"20201119143406","connectorId":0,"tags":{}}