{"id":"2017-00108","title":"Plan of the Batu Gajah Prison ?????","source":"Bumblebee","path":"./Data/json/","content":"accession_no_csv:2017-00108\nImage:\nobject_work_type:paintings (visual works)\ntitle_text:Plan of the Batu Gajah Prison ?????\npreference:main alternate\ntitle_language:\ncreator_2:Tan Chong Tee\ncreator_1:Chen\n Chongzhi\n 1916-\ncreator_role:artists (visual artists)\ncreation_date:1995\ncreation_place_original_location:Singapore\ninscriptions:\ninscription_language:\nshape:rectangular\nmaterials_name:paper (fiber product) ink watercolour (paint)\ntechniques_name:painting (image-making)\nobject_colour:multicolored\nphysical_appearance:This is a watercolour painting of the artist\\u0027s memory of the Batu Gajah Prison. It features a three-storey building in the background. There is a raised Japanese flag in the middle. On the foreground\n there are several roofed structures on the grounds of the prison. There is a row of drawn arrows from a third-floor window to the bottom of the prison grounds. There is a written caption below the painting. The painting is signed and dated at the bottom-left.\nsubject_terms_1:world wars depictions (visual works) resistance movements prisons (institutions) prisons (buildings) Chinese scripts\nsubject_terms_2:Painting World War\n 1939-1945 Great Britain. Army. Force 136 Force 136 (Guerilla movement) Chen\n Chongzhi\n 1916- Prisoner-of-war camps Batu Gajah (Perak\n Malaysia)\nsubject_terms_3:Watercolour painting Force 136 (Guerilla movement) Tan\n Chong Tee 1942-1945 Japanese occupation\nsubject_terms_4:\nsgcool_label_text:This drawing belongs to part of a collection of artefacts related to the World War II underground resistance movement known as Force 136. The collection of materials was gathered by Tan Chong Tee (1916- 2012)\n who was a key member of this resistance group. The collection consists of original materials belonging to Tan and other members of Force 136 dating from the 1940s to new materials reproduced from memory by Tan Chong Tee\n which date from mid 1990s to early 2000s. \\r\\n\\r\\nForce 136 was set up in July 1942 as part of the British Special Operations Executive (SOE). It recruited and trained local guerrillas to gather intelligence and create an underground spy network to support planned British invasion of Japanese-occupied Malaya.\\r\\n\\r\\nThis drawing is painted from the memory of Tan Chong Tee and depicts the plan of the Batu Gajah prison where he and Lim Bo Seng were imprisoned from 1944 to 1945.","createdDate":"20201018182636","version":0,"latest":false,"roles":[],"metadata":{"accession_no_csv":"2017-00108","Image":"","object_work_type":"paintings (visual works)","title_text":"Plan of the Batu Gajah Prison ?????","preference":"main alternate","title_language":"","creator_2":"Tan Chong Tee","creator_1":"Chen, Chongzhi, 1916-","creator_role":"artists (visual artists)","creation_date":"1995","creation_place_original_location":"Singapore","inscriptions":"","inscription_language":"","shape":"rectangular","materials_name":"paper (fiber product) ink watercolour (paint)","techniques_name":"painting (image-making)","object_colour":"multicolored","physical_appearance":"This is a watercolour painting of the artist\u0027s memory of the Batu Gajah Prison. It features a three-storey building in the background. There is a raised Japanese flag in the middle. On the foreground, there are several roofed structures on the grounds of the prison. There is a row of drawn arrows from a third-floor window to the bottom of the prison grounds. There is a written caption below the painting. The painting is signed and dated at the bottom-left.","subject_terms_1":"world wars depictions (visual works) resistance movements prisons (institutions) prisons (buildings) Chinese scripts","subject_terms_2":"Painting World War, 1939-1945 Great Britain. Army. Force 136 Force 136 (Guerilla movement) Chen, Chongzhi, 1916- Prisoner-of-war camps Batu Gajah (Perak, Malaysia)","subject_terms_3":"Watercolour painting Force 136 (Guerilla movement) Tan, Chong Tee 1942-1945 Japanese occupation","subject_terms_4":"","sgcool_label_text":"This drawing belongs to part of a collection of artefacts related to the World War II underground resistance movement known as Force 136. The collection of materials was gathered by Tan Chong Tee (1916- 2012), who was a key member of this resistance group. The collection consists of original materials belonging to Tan and other members of Force 136 dating from the 1940s to new materials reproduced from memory by Tan Chong Tee, which date from mid 1990s to early 2000s. \r\n\r\nForce 136 was set up in July 1942 as part of the British Special Operations Executive (SOE). It recruited and trained local guerrillas to gather intelligence and create an underground spy network to support planned British invasion of Japanese-occupied Malaya.\r\n\r\nThis drawing is painted from the memory of Tan Chong Tee and depicts the plan of the Batu Gajah prison where he and Lim Bo Seng were imprisoned from 1944 to 1945."},"nlpDate":"20201018182636","connectorId":0,"tags":{}}