{
  "id": "2017-00038",
  "title": "Malaya\u0027s Income",
  "source": "Bumblebee",
  "path": "./Data/json/",
  "content": "\n  accession_no_csv: 2017-00038\n\n  Image: \n\n  object_work_type: black-and-white prints (photographs) photographic prints gelatin silver prints\n\n  title_text: Malaya\\u0027s Income\n\n  preference: main\n\n  title_language: \n\n  creator_2: Koon\n Sang Ho\n\n  creator_role: photographers\n\n  creation_date: c.1956\n\n  creation_place_original_location: Singapore\n\n  inscriptions: \n\n  inscription_language: \n\n  shape: Square\n\n  materials_name: silver sulfide paper (fibre product) baryta paper gelatin\n\n  techniques_name: gelatin silver process photographic printing techniques black-and-white photography\n\n  object_colour: black-and-white (colours)\n\n  physical_appearance: This image focuses on a woman clad in a floral attire hollowing coconuts. She has her head wrapped in a cloth garb. Dominating the composition are coconuts that have been halved. Set in the background are fencing structures fashioned out of chopped bamboo.\n\n  subject_terms_1: husk (plant material) coconut (fruit) bamboo (material) rural life fences (site elements) rural areas rural communities\n\n  subject_terms_2: Bamboo fences Coconut Rural Photography\n Artistic\n\n  subject_terms_3: visual arts Potrait photography Artistic photography\n\n  sgcool_label_text: Ho Koon Sang was a member of the Photographic Society of Singapore and an Associate of the Royal Photographic Society in London. This photograph was part of a set of 12 prints sent to the Royal Photographic Society in 1956.\n",
  "createdDate": "20201125084530",
  "version": 0,
  "latest": false,
  "roles": [],
  "metadata": {
    "accession_no_csv": "2017-00038",
    "Image": "",
    "object_work_type": "black-and-white prints (photographs) photographic prints gelatin silver prints",
    "title_text": "Malaya\u0027s Income",
    "preference": "main",
    "title_language": "",
    "creator_2": "Koon, Sang Ho",
    "creator_role": "photographers",
    "creation_date": "c.1956",
    "creation_place_original_location": "Singapore",
    "inscriptions": "",
    "inscription_language": "",
    "shape": "Square",
    "materials_name": "silver sulfide paper (fibre product) baryta paper gelatin",
    "techniques_name": "gelatin silver process photographic printing techniques black-and-white photography",
    "object_colour": "black-and-white (colours)",
    "physical_appearance": "This image focuses on a woman clad in a floral attire hollowing coconuts. She has her head wrapped in a cloth garb. Dominating the composition are coconuts that have been halved. Set in the background are fencing structures fashioned out of chopped bamboo.",
    "subject_terms_1": "husk (plant material) coconut (fruit) bamboo (material) rural life fences (site elements) rural areas rural communities",
    "subject_terms_2": "Bamboo fences Coconut Rural Photography, Artistic",
    "subject_terms_3": "visual arts Potrait photography Artistic photography",
    "sgcool_label_text": "Ho Koon Sang was a member of the Photographic Society of Singapore and an Associate of the Royal Photographic Society in London. This photograph was part of a set of 12 prints sent to the Royal Photographic Society in 1956."
  },
  "nlpDate": "20201125084530",
  "connectorId": 0,
  "tags": {}
}