{"id":"2017-00819","title":"Untitled","source":"Bumblebee","path":"./Data/json/","content":"accession_no_csv:2017-00819\nImage:\nobject_work_type:ink wash paintings\ntitle_text:Untitled\npreference:main\ntitle_language:\ncreator_2:Keen Wong\ncreator_1:Wong\n Keen\n 1942-\ncreator_role:painters (artists)  artists (visual artists)\ncreation_date:1965\ncreation_place_original_location:Singapore\nstyles_periods_indexing_terms:Chinese (culture or style)\ninscriptions:\ninscription_language:\nshape:Rectangular\nmaterials_name:paper (fiber product)  Chinese ink\ntechniques_name:painting (image-making)\nobject_colour:multicoloured\nphysical_appearance:This is a Chinese ink painting done in a hanging scroll format. An amorphous form of two colour hues occupy the top half of the scroll\n while the bottom half has two singular diagonal strokes in opposing directions; one red and the other in black ink.\nsubject_terms_1:xieyi  abstraction\nsubject_terms_2:Art\n Abstract  Ink painting\n Chinese\nsubject_terms_3:Chinese ink painting\nsgcool_label_text:Wong Keen (b. 1942) is regarded as a leading painter whose practice is often framed as the outcome of distilling and re-enervating eastern and western art genres. His oil paintings are marked by gestural and expressive brushwork\n reinforcing affiliations with American abstract expressionism that shaped his formative years in New York; his paint handling also acknowledges debt to his grounding and fervor for calligraphy and Chinese ink particularly of the xieyi school.  \\r\\n\\r\\nWhile this work was produced during Wong’s student years\n it is important to note that Wong was actively exhibiting and excelling during these ‘school years’. He was the recipient of the Ford Foundation tuition scholarship just a year earlier\n in 1964; and the year this work was made was the year he won the Edward G. McDowell Travelling Scholarship – marking the first for a Singaporean recipient. The latter scholarship allowed Wong to travel to Europe and London.  \\r\\n Wong had been tutored by Liu Kang and mentored intensively by Chen Wen Hsi. He participated in local exhibitions from 1956\n with a solo exhibition at the National Library in 1961 before leaving for the USA\n enrolling at the Art Students League of New York (1961-65) and later St Martin’s School of Art London (entered in 1966). He excelled in school and actively exhibited\n receiving the Ford Foundation tuition grant in 1964 and the Edward G. McDowell Travelling Scholarship the following year that enabled him to tour Europe and the UK. He took on art related jobs including as an art instructor and art director in New York and continued to paint - winning the Consul-Gen of Japan Award in 1967\n In the late 1970s he established a frame shop Keen’s Gallery and eventually an art gallery for emerging artists. He returned to art professionally and began to exhibit in Singapore.","createdDate":"20201119143406","version":0,"latest":false,"roles":[],"metadata":{"accession_no_csv":"2017-00819","Image":"","object_work_type":"ink wash paintings","title_text":"Untitled","preference":"main","title_language":"","creator_2":"Keen Wong","creator_1":"Wong, Keen, 1942-","creator_role":"painters (artists)  artists (visual artists)","creation_date":"1965","creation_place_original_location":"Singapore","styles_periods_indexing_terms":"Chinese (culture or style)","inscriptions":"","inscription_language":"","shape":"Rectangular","materials_name":"paper (fiber product)  Chinese ink","techniques_name":"painting (image-making)","object_colour":"multicoloured","physical_appearance":"This is a Chinese ink painting done in a hanging scroll format. An amorphous form of two colour hues occupy the top half of the scroll, while the bottom half has two singular diagonal strokes in opposing directions; one red and the other in black ink.","subject_terms_1":"xieyi  abstraction","subject_terms_2":"Art, Abstract  Ink painting, Chinese","subject_terms_3":"Chinese ink painting","sgcool_label_text":"Wong Keen (b. 1942) is regarded as a leading painter whose practice is often framed as the outcome of distilling and re-enervating eastern and western art genres. His oil paintings are marked by gestural and expressive brushwork, reinforcing affiliations with American abstract expressionism that shaped his formative years in New York; his paint handling also acknowledges debt to his grounding and fervor for calligraphy and Chinese ink particularly of the xieyi school.  \r\n\r\nWhile this work was produced during Wong’s student years, it is important to note that Wong was actively exhibiting and excelling during these ‘school years’. He was the recipient of the Ford Foundation tuition scholarship just a year earlier, in 1964; and the year this work was made was the year he won the Edward G. McDowell Travelling Scholarship – marking the first for a Singaporean recipient. The latter scholarship allowed Wong to travel to Europe and London.  \r\n Wong had been tutored by Liu Kang and mentored intensively by Chen Wen Hsi. He participated in local exhibitions from 1956, with a solo exhibition at the National Library in 1961 before leaving for the USA, enrolling at the Art Students League of New York (1961-65) and later St Martin’s School of Art London (entered in 1966). He excelled in school and actively exhibited, receiving the Ford Foundation tuition grant in 1964 and the Edward G. McDowell Travelling Scholarship the following year that enabled him to tour Europe and the UK. He took on art related jobs including as an art instructor and art director in New York and continued to paint - winning the Consul-Gen of Japan Award in 1967, In the late 1970s he established a frame shop Keen’s Gallery and eventually an art gallery for emerging artists. He returned to art professionally and began to exhibit in Singapore."},"nlpDate":"20201119143406","connectorId":0,"tags":{}}