{
  "id": "2017-00496",
  "title": "Handmade white lace trimming from Sylvia Kho’s collection",
  "source": "Bumblebee",
  "path": "./Data/json/",
  "content": "\n  accession_no_csv: 2017-00496\n\n  Image: \n\n  object_work_type: lace (needlework) textile art (visual works)\n\n  title_text: Handmade white lace trimming from Sylvia Kho’s collection\n\n  preference: main\n\n  title_language: \n\n  creator_2: Not specified\n\n  creation_date: 1960s - 1980s\n\n  creation_place_original_location: Europe\n\n  inscriptions: \n\n  inscription_language: \n\n  shape: irregular\n\n  materials_name: cotton (textile)\n\n  techniques_name: lace making\n\n  object_colour: white (colour)\n\n  physical_appearance: This is a lace trimming with leaf motifs. It has saw tooth edges.\n\n  subject_terms_1: plant-derived motif imports handmade\n\n  subject_terms_2: Textile crafts Imports Kho\n Sylvia\n 1917- Handmade style? Lace and lace making Leaves in art\n\n  subject_terms_3: Textile art and design\n\n  sgcool_label_text: This handmade lace trimming is from the collection of Sylvia Kho who was a prominent bridal couturier in Singapore from the 1950s to 1990s. She designed and custom-made wedding gowns using elaborate laces imported from Europe.  She travelled extensively to France and USA to learn how wedding gowns were designed and made. She also became one of the greatest buyers of wedding gown lace in France. This lace trimming would have been used on details of the gowns such as on the sleeves or the collar.\n",
  "createdDate": "20201201203308",
  "version": 0,
  "latest": false,
  "roles": [],
  "metadata": {
    "accession_no_csv": "2017-00496",
    "Image": "",
    "object_work_type": "lace (needlework) textile art (visual works)",
    "title_text": "Handmade white lace trimming from Sylvia Kho’s collection",
    "preference": "main",
    "title_language": "",
    "creator_2": "Not specified",
    "creation_date": "1960s - 1980s",
    "creation_place_original_location": "Europe",
    "inscriptions": "",
    "inscription_language": "",
    "shape": "irregular",
    "materials_name": "cotton (textile)",
    "techniques_name": "lace making",
    "object_colour": "white (colour)",
    "physical_appearance": "This is a lace trimming with leaf motifs. It has saw tooth edges.",
    "subject_terms_1": "plant-derived motif imports handmade",
    "subject_terms_2": "Textile crafts Imports Kho, Sylvia, 1917- Handmade style? Lace and lace making Leaves in art",
    "subject_terms_3": "Textile art and design",
    "sgcool_label_text": "This handmade lace trimming is from the collection of Sylvia Kho who was a prominent bridal couturier in Singapore from the 1950s to 1990s. She designed and custom-made wedding gowns using elaborate laces imported from Europe.  She travelled extensively to France and USA to learn how wedding gowns were designed and made. She also became one of the greatest buyers of wedding gown lace in France. This lace trimming would have been used on details of the gowns such as on the sleeves or the collar."
  },
  "nlpDate": "20201201203308",
  "connectorId": 0,
  "tags": {}
}