{"id":"2017-00335","title":"Kain panjang","source":"Bumblebee","path":"./Data/json/","content":"accession_no_csv:2017-00335\nImage:\nobject_work_type:folk costume batik art\ntitle_text:Kain panjang\npreference:main\ntitle_language:\ncreator_2:Soen King Oey\ncreator_role:textile designers\ncreation_date:Late 19th-early 20th century\ncreation_place_original_location:Pekalongan (Indonesia)\nstyles_periods_indexing_terms:Peranakan\ninscriptions:\ninscription_language:\nshape:rectangular\nmaterials_name:cotton (textile)\ntechniques_name:batik\nobject_colour:multicolored\nphysical_appearance:This is a batik kain panjang. The design features elongated triangles at both ends of the kain panjang\n against a dark background with small flower blooms. The middle section of the kain panjang is decorated with Chinese motifs such as bats and qilins\n and Javanese elements such as garuda wings and tail feathers.\nsubject_terms_1:Peranakan flower (motif) birds (motifs) foliage (motif) cultural diffusion symbolism (artistic concept)\nsubject_terms_2:Batik Ethnic costume Peranakan (Asian people) Motifs Culture diffusion Symbolism\nsubject_terms_3:Batik Peranakan costumes\nsgcool_label_text:The main design field (badan) is set against a cream ground\n decorated with auspicious Chinese symbols such as the bat (homonym of fortune) and qilin.  Javanese elements\n such as the sawat motif\n are attached to plant forms on this piece.   The sawat design\n consisting of a pair of garuda wings and tail feathers\n was exclusively reserved for the Javanese courts.  A row of opposing triangles known as tumpal\n appear on the vertical band (kepala) on one end of this piece.  This batik comes from the family collection of Oey Soen King (1861-1942)\n the first in three generations of documented batik-makers in Pekalongan.  Her batiks feature the classic layout typical of her time\n and are embellished with Chinese traditional motifs.  These motifs include lotus flowers\n centipedes and cloud motifs\n which are rendered sensitively and imaginatively.  The combination of natural red and blue dyes on a cream ground is also characteristic of batiks made during this period in the north coast of Java\n before the invention and widespread popularity of chemical dyes in batik sarongs by the late 19th century.  Oey Soen King’s pieces were all unsigned as signatures were not yet fashionable.","createdDate":"20201119143406","version":0,"latest":false,"roles":[],"metadata":{"accession_no_csv":"2017-00335","Image":"","object_work_type":"folk costume batik art","title_text":"Kain panjang","preference":"main","title_language":"","creator_2":"Soen King Oey","creator_role":"textile designers","creation_date":"Late 19th-early 20th century","creation_place_original_location":"Pekalongan (Indonesia)","styles_periods_indexing_terms":"Peranakan","inscriptions":"","inscription_language":"","shape":"rectangular","materials_name":"cotton (textile)","techniques_name":"batik","object_colour":"multicolored","physical_appearance":"This is a batik kain panjang. The design features elongated triangles at both ends of the kain panjang, against a dark background with small flower blooms. The middle section of the kain panjang is decorated with Chinese motifs such as bats and qilins, and Javanese elements such as garuda wings and tail feathers.","subject_terms_1":"Peranakan flower (motif) birds (motifs) foliage (motif) cultural diffusion symbolism (artistic concept)","subject_terms_2":"Batik Ethnic costume Peranakan (Asian people) Motifs Culture diffusion Symbolism","subject_terms_3":"Batik Peranakan costumes","sgcool_label_text":"The main design field (badan) is set against a cream ground, decorated with auspicious Chinese symbols such as the bat (homonym of fortune) and qilin.  Javanese elements, such as the sawat motif, are attached to plant forms on this piece.   The sawat design, consisting of a pair of garuda wings and tail feathers, was exclusively reserved for the Javanese courts.  A row of opposing triangles known as tumpal, appear on the vertical band (kepala) on one end of this piece.  This batik comes from the family collection of Oey Soen King (1861-1942), the first in three generations of documented batik-makers in Pekalongan.  Her batiks feature the classic layout typical of her time, and are embellished with Chinese traditional motifs.  These motifs include lotus flowers, centipedes and cloud motifs, which are rendered sensitively and imaginatively.  The combination of natural red and blue dyes on a cream ground is also characteristic of batiks made during this period in the north coast of Java, before the invention and widespread popularity of chemical dyes in batik sarongs by the late 19th century.  Oey Soen King’s pieces were all unsigned as signatures were not yet fashionable."},"nlpDate":"20201119143406","connectorId":0,"tags":{}}