{
  "id": "2017-00927",
  "title": "Olympus Trip 35",
  "source": "Bumblebee",
  "path": "./Data/json/",
  "content": "\n  accession_no_csv: 2017-00927\n\n  Image: \n\n  object_work_type: 35mm cameras\n\n  title_text: Olympus Trip 35\n\n  preference: main\n\n  title_language: \n\n  creator_2: Olympus Corporation (?)\n\n  creator_1: Orinpasu Kabushiki Kaisha\n\n  creator_role: manufacturers\n\n  creation_date: 1965\n\n  creation_place_original_location: Japan\n\n  inscriptions: \n\n  inscription_language: \n\n  shape: irregular\n\n  object_colour: multicolored\n\n  physical_appearance: This is an Olympus 35mm automatic camera. It has a black and silver body. It has a viewer on the right side\n with a rotational camera lens in front. The lens cover is black and has the brand name \\u0027Olympus\\u0027 inscribed on it. The camera model \\u0027Olympus Trip 35\\u0027 is inscribed on the top left of the camera. There is a strap attached to the back.\n\n  subject_terms_1: vintage (period) photography (discipline) cameras (photographic equipment)\n\n  subject_terms_2: Photography Cameras Vintage Olympus camera\n\n  subject_terms_3: Photography\n\n  sgcool_label_text: The Olympus Trip 35 was advertised in Singapore in 1970 as the only 35mm automatic camera. Marketed features included simplified focusing and fully automatic exposures. \\r\\n\\r\\nBefore the advent of the portable camera in the late 19th century\n the taking of photographs was limited to the studio. However portable cameras remained affordable only to the rich until the first decades of the 20th century.\n",
  "createdDate": "20201201203308",
  "version": 0,
  "latest": false,
  "roles": [],
  "metadata": {
    "accession_no_csv": "2017-00927",
    "Image": "",
    "object_work_type": "35mm cameras",
    "title_text": "Olympus Trip 35",
    "preference": "main",
    "title_language": "",
    "creator_2": "Olympus Corporation (?)",
    "creator_1": "Orinpasu Kabushiki Kaisha",
    "creator_role": "manufacturers",
    "creation_date": "1965",
    "creation_place_original_location": "Japan",
    "inscriptions": "",
    "inscription_language": "",
    "shape": "irregular",
    "object_colour": "multicolored",
    "physical_appearance": "This is an Olympus 35mm automatic camera. It has a black and silver body. It has a viewer on the right side, with a rotational camera lens in front. The lens cover is black and has the brand name \u0027Olympus\u0027 inscribed on it. The camera model \u0027Olympus Trip 35\u0027 is inscribed on the top left of the camera. There is a strap attached to the back.",
    "subject_terms_1": "vintage (period) photography (discipline) cameras (photographic equipment)",
    "subject_terms_2": "Photography Cameras Vintage Olympus camera",
    "subject_terms_3": "Photography",
    "sgcool_label_text": "The Olympus Trip 35 was advertised in Singapore in 1970 as the only 35mm automatic camera. Marketed features included simplified focusing and fully automatic exposures. \r\n\r\nBefore the advent of the portable camera in the late 19th century, the taking of photographs was limited to the studio. However portable cameras remained affordable only to the rich until the first decades of the 20th century."
  },
  "nlpDate": "20201201203308",
  "connectorId": 0,
  "tags": {}
}