{
  "id": "2017-00951-007",
  "title": "Kekoeatan Asia Tanah Impian (Dream Land)",
  "source": "Bumblebee",
  "path": "./Data/json/",
  "content": "\n  accession_no_csv: 2017-00951-007\n\n  Image: \n\n  object_work_type: screen prints adaptations (derivative objects)\n\n  title_text: Kekoeatan Asia Tanah Impian (Dream Land)\n\n  preference: main alternate\n\n  title_language: \n\n  creator_2: Krack Studio\n\n  creator_role: artists (visual artists)\n\n  creation_date: 2014\n\n  creation_place_original_location: Indonesia\n\n  styles_periods_indexing_terms: Contemporary (style of art)\n\n  inscriptions: \n\n  inscription_language: \n\n  shape: Rectangular\n\n  materials_name: paper (fiber product)\n\n  techniques_name: screen printing\n\n  object_colour: multicoloured\n\n  edition_description: 2-Oct\n\n  physical_appearance: This print shows a large scissors cutting the chains linking the flag of Nationalist China\n Britain\n and the United states.\n\n  subject_terms_1: ways of life appropriation (imagery) propaganda identity political posters popular culture redesign nationalism\n\n  subject_terms_2: Anti-imperialist movements Serigraphy Art\n Indonesian Asia United States Popular culture Appropriation (Art) Identity United Kingdom Nationalism Adaptations Political posters Ways of life Propaganda China\n\n  subject_terms_3: Popular culture Poster art National identity Visual arts\n\n  sgcool_label_text: Tanah Impian (Dream Land) is a series of prints based on images drawn from Indonesian popular culture\n spanning 100 years. The project was conceived in 2014\n the year of the elections in Indonesia when nationalist rhetoric dominated public consciousness\n Artist collective Krack Studio sifted through a mass of research and archival material\n eventually selecting 24 images that referenced the idea of the Indonesian Dream and / or told an interesting story about changing definitions of the ‘Nation’. Ranging from political posters to advertisements\n comic strips\n movie posters and magazines\n these images\n reconstructed and re-imagined by the artist collective\n chronicle Indonesia’s evolving aspirations\n desires and identity\n as well as how Indonesia has been perceived and imaged for the ‘Western’ gaze.\n",
  "createdDate": "20201201203308",
  "version": 0,
  "latest": false,
  "roles": [],
  "metadata": {
    "accession_no_csv": "2017-00951-007",
    "Image": "",
    "object_work_type": "screen prints adaptations (derivative objects)",
    "title_text": "Kekoeatan Asia Tanah Impian (Dream Land)",
    "preference": "main alternate",
    "title_language": "",
    "creator_2": "Krack Studio",
    "creator_role": "artists (visual artists)",
    "creation_date": "2014",
    "creation_place_original_location": "Indonesia",
    "styles_periods_indexing_terms": "Contemporary (style of art)",
    "inscriptions": "",
    "inscription_language": "",
    "shape": "Rectangular",
    "materials_name": "paper (fiber product)",
    "techniques_name": "screen printing",
    "object_colour": "multicoloured",
    "edition_description": "2-Oct",
    "physical_appearance": "This print shows a large scissors cutting the chains linking the flag of Nationalist China, Britain, and the United states.",
    "subject_terms_1": "ways of life appropriation (imagery) propaganda identity political posters popular culture redesign nationalism",
    "subject_terms_2": "Anti-imperialist movements Serigraphy Art, Indonesian Asia United States Popular culture Appropriation (Art) Identity United Kingdom Nationalism Adaptations Political posters Ways of life Propaganda China",
    "subject_terms_3": "Popular culture Poster art National identity Visual arts",
    "sgcool_label_text": "Tanah Impian (Dream Land) is a series of prints based on images drawn from Indonesian popular culture, spanning 100 years. The project was conceived in 2014, the year of the elections in Indonesia when nationalist rhetoric dominated public consciousness, Artist collective Krack Studio sifted through a mass of research and archival material, eventually selecting 24 images that referenced the idea of the Indonesian Dream and / or told an interesting story about changing definitions of the ‘Nation’. Ranging from political posters to advertisements, comic strips, movie posters and magazines, these images, reconstructed and re-imagined by the artist collective, chronicle Indonesia’s evolving aspirations, desires and identity, as well as how Indonesia has been perceived and imaged for the ‘Western’ gaze."
  },
  "nlpDate": "20201201203308",
  "connectorId": 0,
  "tags": {}
}