{"id":"2017-00385","title":"Kain panjang","source":"Bumblebee","path":"./Data/json/","content":"accession_no_csv:2017-00385\nImage:\nobject_work_type:folk costume batik art\ntitle_text:Kain panjang\npreference:main\ntitle_language:\ncreator_2:Jane Hendromartono\ncreator_role:textile designers\ncreation_date:1967\ncreation_place_original_location:Pekalongan (Indonesia)\nstyles_periods_indexing_terms:Peranakan\ninscriptions:\ninscription_language:\nshape:rectangular\nmaterials_name:cotton (textile)\ntechniques_name:batik\nobject_colour:multicolored\nphysical_appearance:This is a batik kain panjang. It features a large bouquet of flowers on the right\n against a brown background and decorated with a variety of little animals such as birds\n foshes\n and sea creatures. The panel is outlined with a border of various flower blooms. The main body of the kain panjang is also decorated with various flower blooms\n set against a green background. There is a signature on the bottom-right of the batik kain panjang.\nsubject_terms_1:Peranakan flower (motif) birds (motifs)\nsubject_terms_2:Batik Ethnic costume Peranakan (Asian people) Motifs\nsubject_terms_3:Batik Peranakan costumes\nsgcool_label_text:The buketan motif or a large bouquet of flowers is depicted on the brown kepala or broad vertical panel of the batik.  It is decorated with vignettes of amusing animals such as a standing elephant and a hare staring at plants.  On the badan or main design field\n a variety of floral blooms embellish the green background.  This batik comes from the family collection of Oey Djien Nio (1929-1987)\n the last in three generations of documented batik-makers in Pekalongan.  In her earlier signatures\n she used her husband’s name\n Liem Siok Hien.  But from 1965 onwards\n she used Jane Hendromartono\n combining her husband’s new Indonesian family name\n Hendromartono with Jane\n as people addressed her by.  She developed a personal style distinct from her mother and grandmother\n and experimented with a wide spectrum of colours and exotic combinations of birds\n rock formations and mythical animals.  Jane Hendromartono’s clientele expanded beyond the elite in Indonesia to include Europe\n America and Japan\n especially in the 1980s.  This piece is signed “Jane Hendro Pekalongan ‘67”.","createdDate":"20201119143406","version":0,"latest":false,"roles":[],"metadata":{"accession_no_csv":"2017-00385","Image":"","object_work_type":"folk costume batik art","title_text":"Kain panjang","preference":"main","title_language":"","creator_2":"Jane Hendromartono","creator_role":"textile designers","creation_date":"1967","creation_place_original_location":"Pekalongan (Indonesia)","styles_periods_indexing_terms":"Peranakan","inscriptions":"","inscription_language":"","shape":"rectangular","materials_name":"cotton (textile)","techniques_name":"batik","object_colour":"multicolored","physical_appearance":"This is a batik kain panjang. It features a large bouquet of flowers on the right, against a brown background and decorated with a variety of little animals such as birds, foshes, and sea creatures. The panel is outlined with a border of various flower blooms. The main body of the kain panjang is also decorated with various flower blooms, set against a green background. There is a signature on the bottom-right of the batik kain panjang.","subject_terms_1":"Peranakan flower (motif) birds (motifs)","subject_terms_2":"Batik Ethnic costume Peranakan (Asian people) Motifs","subject_terms_3":"Batik Peranakan costumes","sgcool_label_text":"The buketan motif or a large bouquet of flowers is depicted on the brown kepala or broad vertical panel of the batik.  It is decorated with vignettes of amusing animals such as a standing elephant and a hare staring at plants.  On the badan or main design field, a variety of floral blooms embellish the green background.  This batik comes from the family collection of Oey Djien Nio (1929-1987), the last in three generations of documented batik-makers in Pekalongan.  In her earlier signatures, she used her husband’s name, Liem Siok Hien.  But from 1965 onwards, she used Jane Hendromartono, combining her husband’s new Indonesian family name, Hendromartono with Jane, as people addressed her by.  She developed a personal style distinct from her mother and grandmother, and experimented with a wide spectrum of colours and exotic combinations of birds, rock formations and mythical animals.  Jane Hendromartono’s clientele expanded beyond the elite in Indonesia to include Europe, America and Japan, especially in the 1980s.  This piece is signed “Jane Hendro Pekalongan ‘67”."},"nlpDate":"20201119143406","connectorId":0,"tags":{}}