{
  "id": "2017-00585",
  "title": "1941 RAF map of the Malay Peninsular",
  "source": "Bumblebee",
  "path": "./Data/json/",
  "content": "\n  accession_no_csv: 2017-00585\n\n  Image: \n\n  object_work_type: maps (documents)\n\n  title_text: 1941 RAF map of the Malay Peninsular\n\n  preference: main\n\n  title_language: \n\n  creator_2: George Dudley Binsted (?)\n\n  creator_role: creators\n\n  creation_date: 1941\n\n  creation_place_original_location: Singapore Malaya\n\n  inscriptions: \n\n  inscription_language: \n\n  scale_type: Not indicated\n\n  shape: rectangular\n\n  materials_name: paper (fiber product) ink\n\n  techniques_name: drawing (image-making) printing (processes)\n\n  object_colour: multicolored\n\n  physical_appearance: This is an annotated map of the Malay Peninsular. The map is printed in multiple colours including black\n beige and red. There are several penned annotations\n marking out places and interest\n written in blue ink. The map is quite worn\n with the fold lines stained and the edges creased and slightly torn.\n\n  subject_terms_1: world wars prisoners of war military officers\n\n  subject_terms_2: World War\n 1939-1945 Great Britain\n Royal Air Force Maps Malay Peninsula Prisoner of war\n\n  subject_terms_3: 1942-1945 Japanese occupation Great Britain\n Royal Air Force\n\n  subject_terms_4: \n\n  context_1: World War\n 1939-1945 1942-1945 Japanese Occupation\n\n  context_2: occupations (armed conflicts) world wars\n\n  context_3: 1942-1945 1939-1945\n\n  context_4: 1939 1942\n\n  context_5: 1945\n\n  context_6: Singapore Malaya\n\n  context_7: Great Britain. Army. Force 136\n\n  context_8: armed forces\n\n  sgcool_label_text: This map belonged to George Dudley Binsted\n a former Changi POW. This map of the Malay Peninsular was issued by the Royal Air Force (RAF)\n which Binsted had kept throughout his years of captivity and after. The map contains hand markings\n which were believed to be the escape route he had planned. Binsted joined the Royal Air Force in 1941 and had flown Spitfires over France before being posted to Java. After the fall of Singapore in February 1942\n Binsted along with four others\n were captured by the Japanese. They were transported by ship to Singapore\n where they spent the next three and a half years as POWs in Changi Prison.\n",
  "createdDate": "20201125084518",
  "version": 0,
  "latest": false,
  "roles": [],
  "metadata": {
    "accession_no_csv": "2017-00585",
    "Image": "",
    "object_work_type": "maps (documents)",
    "title_text": "1941 RAF map of the Malay Peninsular",
    "preference": "main",
    "title_language": "",
    "creator_2": "George Dudley Binsted (?)",
    "creator_role": "creators",
    "creation_date": "1941",
    "creation_place_original_location": "Singapore Malaya",
    "inscriptions": "",
    "inscription_language": "",
    "scale_type": "Not indicated",
    "shape": "rectangular",
    "materials_name": "paper (fiber product) ink",
    "techniques_name": "drawing (image-making) printing (processes)",
    "object_colour": "multicolored",
    "physical_appearance": "This is an annotated map of the Malay Peninsular. The map is printed in multiple colours including black, beige and red. There are several penned annotations, marking out places and interest, written in blue ink. The map is quite worn, with the fold lines stained and the edges creased and slightly torn.",
    "subject_terms_1": "world wars prisoners of war military officers",
    "subject_terms_2": "World War, 1939-1945 Great Britain, Royal Air Force Maps Malay Peninsula Prisoner of war",
    "subject_terms_3": "1942-1945 Japanese occupation Great Britain, Royal Air Force",
    "subject_terms_4": "",
    "context_1": "World War, 1939-1945 1942-1945 Japanese Occupation",
    "context_2": "occupations (armed conflicts) world wars",
    "context_3": "1942-1945 1939-1945",
    "context_4": "1939 1942",
    "context_5": "1945",
    "context_6": "Singapore Malaya",
    "context_7": "Great Britain. Army. Force 136",
    "context_8": "armed forces",
    "sgcool_label_text": "This map belonged to George Dudley Binsted, a former Changi POW. This map of the Malay Peninsular was issued by the Royal Air Force (RAF), which Binsted had kept throughout his years of captivity and after. The map contains hand markings, which were believed to be the escape route he had planned. Binsted joined the Royal Air Force in 1941 and had flown Spitfires over France before being posted to Java. After the fall of Singapore in February 1942, Binsted along with four others, were captured by the Japanese. They were transported by ship to Singapore, where they spent the next three and a half years as POWs in Changi Prison."
  },
  "nlpDate": "20201125084518",
  "connectorId": 0,
  "tags": {}
}