{
  "id": "2017-00381",
  "title": "Kain panjang",
  "source": "Bumblebee",
  "path": "./Data/json/",
  "content": "\n  accession_no_csv: 2017-00381\n\n  Image: \n\n  object_work_type: batik art folk costume\n\n  title_text: Kain panjang\n\n  preference: main\n\n  title_language: \n\n  creator_2: Jane Hendromartono\n\n  creator_role: textile designers\n\n  creation_date: 1965-1980s\n\n  creation_place_original_location: Pekalongan (Indonesia)\n\n  styles_periods_indexing_terms: Peranakan\n\n  inscriptions: \n\n  inscription_language: \n\n  shape: rectangular\n\n  materials_name: cotton (textile)\n\n  techniques_name: batik\n\n  object_colour: multicolored\n\n  physical_appearance: This is a batik kain panjang\n It features a bouquet of flowers set against a cream panel filled with dense scrolls on the left. The panel is bordered by a scrolling floral bloom pattern. The main body of the kain panjang is set against a blue ground\n decorated with phoenixes and a variety of tendril patterns. There is a signature at the top-left of the batik kain panjang.\n\n  subject_terms_1: phoenixes Peranakan flower (motif) scrolls (motifs) foliage (motif)\n\n  subject_terms_2: Motifs Ethnic costume Peranakan (Asian people) Batik\n\n  subject_terms_3: Peranakan costumes Batik\n\n  sgcool_label_text: The buketan motif (or a large bouquet of flowers) is set against a background of dense cream swirls on the kepala (broad vertical panel of the batik).  On the badan (or main design field)\n phoenixes are depicted amidst foilage and trefoil background patterns on a blue ground.  This batik comes from the family collection of Oey Djien Nio (1929-1987)\n the last in three generations of documented batik-makers in Pekalongan.  In her earlier signatures\n she used her husband’s name\n Liem Siok Hien.  But from 1965 onwards\n she used Jane Hendromartono\n combining her husband’s new Indonesian family name\n Hendromartono with Jane\n as people addressed her by.  She developed a personal style distinct from her mother and grandmother\n and experimented with a wide spectrum of colours and exotic combinations of birds\n rock formations and mythical animals.  Jane Hendromartono’s clientele expanded beyond the elite in Indonesia to include Europe\n America and Japan\n especially in the 1980s.  This piece is signed “Hendromartono Batik Art” Unique Pekalongan\n 100% Tulis”.\n",
  "createdDate": "20201125084521",
  "version": 0,
  "latest": false,
  "roles": [],
  "metadata": {
    "accession_no_csv": "2017-00381",
    "Image": "",
    "object_work_type": "batik art folk costume",
    "title_text": "Kain panjang",
    "preference": "main",
    "title_language": "",
    "creator_2": "Jane Hendromartono",
    "creator_role": "textile designers",
    "creation_date": "1965-1980s",
    "creation_place_original_location": "Pekalongan (Indonesia)",
    "styles_periods_indexing_terms": "Peranakan",
    "inscriptions": "",
    "inscription_language": "",
    "shape": "rectangular",
    "materials_name": "cotton (textile)",
    "techniques_name": "batik",
    "object_colour": "multicolored",
    "physical_appearance": "This is a batik kain panjang, It features a bouquet of flowers set against a cream panel filled with dense scrolls on the left. The panel is bordered by a scrolling floral bloom pattern. The main body of the kain panjang is set against a blue ground, decorated with phoenixes and a variety of tendril patterns. There is a signature at the top-left of the batik kain panjang.",
    "subject_terms_1": "phoenixes Peranakan flower (motif) scrolls (motifs) foliage (motif)",
    "subject_terms_2": "Motifs Ethnic costume Peranakan (Asian people) Batik",
    "subject_terms_3": "Peranakan costumes Batik",
    "sgcool_label_text": "The buketan motif (or a large bouquet of flowers) is set against a background of dense cream swirls on the kepala (broad vertical panel of the batik).  On the badan (or main design field), phoenixes are depicted amidst foilage and trefoil background patterns on a blue ground.  This batik comes from the family collection of Oey Djien Nio (1929-1987), the last in three generations of documented batik-makers in Pekalongan.  In her earlier signatures, she used her husband’s name, Liem Siok Hien.  But from 1965 onwards, she used Jane Hendromartono, combining her husband’s new Indonesian family name, Hendromartono with Jane, as people addressed her by.  She developed a personal style distinct from her mother and grandmother, and experimented with a wide spectrum of colours and exotic combinations of birds, rock formations and mythical animals.  Jane Hendromartono’s clientele expanded beyond the elite in Indonesia to include Europe, America and Japan, especially in the 1980s.  This piece is signed “Hendromartono Batik Art” Unique Pekalongan, 100% Tulis”."
  },
  "nlpDate": "20201125084521",
  "connectorId": 0,
  "tags": {}
}