{
  "id": "2017-00169",
  "title": "Malayan People’s Anti-Japanese Army (MPAJA)’s Memo on  Resistance to the Japanese",
  "source": "Bumblebee",
  "path": "./Data/json/",
  "content": "\n  accession_no_csv: 2017-00169\n\n  Image: \n\n  object_work_type: memorandums\n\n  title_text: Malayan People’s Anti-Japanese Army (MPAJA)’s Memo on  Resistance to the Japanese\n\n  preference: main\n\n  title_language: \n\n  creator_2: Malayan People\\u0027s Anti-Japanese Army (?)\n\n  creator_1: Malayan People\\u0027s Anti-Japanese Army\n\n  creator_role: armies\n\n  creation_date: 1943\n\n  creation_place_original_location: Singapore\n\n  inscriptions: \n\n  inscription_language: \n\n  shape: rectangular\n\n  materials_name: paper (fiber product) ink\n\n  techniques_name: writing (processes)\n\n  object_colour: black-and-white (colors)\n\n  physical_appearance: This is a memorandum note. It is handwritten in black ink on a blank piece of paper. The text is written in Chinese\n in vertical lines. There are two holes punched at the top center of the document. The top-right corner of the document is torn.\n\n  subject_terms_1: resistance movements documents (object genre) world wars Chinese scripts handwriting\n\n  subject_terms_2: World War\n 1939-1945 Chen\n Chongzhi\n 1916- Great Britain. Army. Force 136 Memorandums Force 136 (Guerilla movement) Writing\n\n  subject_terms_3: 1942-1945 Japanese occupation Tan\n Chong Tee Force 136 (Guerilla movement) war personalities Malayan People\\u0027s Anti-Japanese Army\n\n  subject_terms_4: \n\n  context_1: World War\n 1939-1945 1942-1945 Japanese Occupation\n\n  context_2: occupations (armed conflicts) world wars\n\n  context_3: 1942-1945 1939-1945\n\n  context_4: 1939 1942\n\n  context_5: 1945\n\n  context_6: Singapore Malaya\n\n  context_7: Great Britain. Army. Force 136\n\n  context_8: armed forces\n",
  "createdDate": "20201201203308",
  "version": 0,
  "latest": false,
  "roles": [],
  "metadata": {
    "accession_no_csv": "2017-00169",
    "Image": "",
    "object_work_type": "memorandums",
    "title_text": "Malayan People’s Anti-Japanese Army (MPAJA)’s Memo on  Resistance to the Japanese",
    "preference": "main",
    "title_language": "",
    "creator_2": "Malayan People\u0027s Anti-Japanese Army (?)",
    "creator_1": "Malayan People\u0027s Anti-Japanese Army",
    "creator_role": "armies",
    "creation_date": "1943",
    "creation_place_original_location": "Singapore",
    "inscriptions": "",
    "inscription_language": "",
    "shape": "rectangular",
    "materials_name": "paper (fiber product) ink",
    "techniques_name": "writing (processes)",
    "object_colour": "black-and-white (colors)",
    "physical_appearance": "This is a memorandum note. It is handwritten in black ink on a blank piece of paper. The text is written in Chinese, in vertical lines. There are two holes punched at the top center of the document. The top-right corner of the document is torn.",
    "subject_terms_1": "resistance movements documents (object genre) world wars Chinese scripts handwriting",
    "subject_terms_2": "World War, 1939-1945 Chen, Chongzhi, 1916- Great Britain. Army. Force 136 Memorandums Force 136 (Guerilla movement) Writing",
    "subject_terms_3": "1942-1945 Japanese occupation Tan, Chong Tee Force 136 (Guerilla movement) war personalities Malayan People\u0027s Anti-Japanese Army",
    "subject_terms_4": "",
    "context_1": "World War, 1939-1945 1942-1945 Japanese Occupation",
    "context_2": "occupations (armed conflicts) world wars",
    "context_3": "1942-1945 1939-1945",
    "context_4": "1939 1942",
    "context_5": "1945",
    "context_6": "Singapore Malaya",
    "context_7": "Great Britain. Army. Force 136",
    "context_8": "armed forces"
  },
  "nlpDate": "20201201203308",
  "connectorId": 0,
  "tags": {}
}