{"id":"2017-00628","title":"Doorway Hanging  Toran","source":"Bumblebee","path":"./Data/json/","content":"accession_no_csv:2017-00628\nImage:\nobject_work_type:hangings (coverings)\ntitle_text:Doorway Hanging  Toran\npreference:main alternate\ntitle_language:English\ncreation_date:20th century\ncreation_place_original_location:Gujarat (India)\ninscriptions:\ninscription_language:\nshape:irregular\nmaterials_name:glass (material) cotton (textile)\ntechniques_name:sewing (needleworking technique) embroidering\nobject_colour:multicolored\nphysical_appearance:This is a toran or a doorway hanging. It features a cotton weave with embroidery and mirror work. The piece is decorated with stylized depictions of peacocks\n flowers\n and deities. There are ten small mirror pieces attached to the textile. In the center\n there is a sewn-on inscription. The shape of the toran is irregular\n with a square top and seven dangling panels along the bottom.\nsubject_terms_1:embroidery (visual works) flower (motif) birds (motifs) deities depictions (visual works) beadwork (visual works)\nsubject_terms_2:Draperies Embroidery Motifs Gods\nsubject_terms_3:Textile art and design\nsubject_terms_4:","createdDate":"20201119143406","version":0,"latest":false,"roles":[],"metadata":{"accession_no_csv":"2017-00628","Image":"","object_work_type":"hangings (coverings)","title_text":"Doorway Hanging  Toran","preference":"main alternate","title_language":"English","creation_date":"20th century","creation_place_original_location":"Gujarat (India)","inscriptions":"","inscription_language":"","shape":"irregular","materials_name":"glass (material) cotton (textile)","techniques_name":"sewing (needleworking technique) embroidering","object_colour":"multicolored","physical_appearance":"This is a toran or a doorway hanging. It features a cotton weave with embroidery and mirror work. The piece is decorated with stylized depictions of peacocks, flowers, and deities. There are ten small mirror pieces attached to the textile. In the center, there is a sewn-on inscription. The shape of the toran is irregular, with a square top and seven dangling panels along the bottom.","subject_terms_1":"embroidery (visual works) flower (motif) birds (motifs) deities depictions (visual works) beadwork (visual works)","subject_terms_2":"Draperies Embroidery Motifs Gods","subject_terms_3":"Textile art and design","subject_terms_4":""},"nlpDate":"20201119143406","connectorId":0,"tags":{}}