{
  "id": "2017-00917",
  "title": "Koh and Co.’s Post Card Exchange Register",
  "source": "Bumblebee",
  "path": "./Data/json/",
  "content": "\n  accession_no_csv: 2017-00917\n\n  Image: \n\n  object_work_type: magazines (periodicals)\n\n  title_text: Koh and Co.’s Post Card Exchange Register\n\n  preference: main\n\n  title_language: \n\n  creator_2: Koh and Company (?)\n\n  creator_role: publishers\n\n  creation_date: 1909\n\n  creation_place_original_location: Singapore\n\n  inscriptions: \n\n  inscription_language: \n\n  shape: rectangular\n\n  materials_name: paper (fiber product)\n\n  techniques_name: printing (process)\n\n  object_colour: black-and-white (colors)\n\n  physical_appearance: \\This is the front page of the publication \\\\Koh \\u0026 Co\\u0027s Post Card Exchange Register\\\\. It is printed in black-and-white. The title is printed at the top of the page\n\n  subject_terms_1: collecting cards postage stamps temples (buildings) with a subtitle and date printed underneath it. There are two photographs featured on the page. The larger photograph depicts a Chinese temple along Telok Ayer Street. The price of the publication is printed along the bottom.\\ postcards\n\n  subject_terms_2: Hobbies Temples Peranakan (Asian people) Stamp collecting collectors Postcards Collectibles\n\n  subject_terms_3: Periodicals Telok Ayer Street Koh\n Hoon Teck Peranakan clans and associations Hobbies\n\n  subject_terms_4: periodicals\n",
  "createdDate": "20201201203308",
  "version": 0,
  "latest": false,
  "roles": [],
  "metadata": {
    "accession_no_csv": "2017-00917",
    "Image": "",
    "object_work_type": "magazines (periodicals)",
    "title_text": "Koh and Co.’s Post Card Exchange Register",
    "preference": "main",
    "title_language": "",
    "creator_2": "Koh and Company (?)",
    "creator_role": "publishers",
    "creation_date": "1909",
    "creation_place_original_location": "Singapore",
    "inscriptions": "",
    "inscription_language": "",
    "shape": "rectangular",
    "materials_name": "paper (fiber product)",
    "techniques_name": "printing (process)",
    "object_colour": "black-and-white (colors)",
    "physical_appearance": "\"This is the front page of the publication \"\"Koh \u0026 Co\u0027s Post Card Exchange Register\"\". It is printed in black-and-white. The title is printed at the top of the page",
    "subject_terms_1": "collecting cards postage stamps temples (buildings) with a subtitle and date printed underneath it. There are two photographs featured on the page. The larger photograph depicts a Chinese temple along Telok Ayer Street. The price of the publication is printed along the bottom.\" postcards",
    "subject_terms_2": "Hobbies Temples Peranakan (Asian people) Stamp collecting collectors Postcards Collectibles",
    "subject_terms_3": "Periodicals Telok Ayer Street Koh, Hoon Teck Peranakan clans and associations Hobbies",
    "subject_terms_4": "periodicals"
  },
  "nlpDate": "20201201203308",
  "connectorId": 0,
  "tags": {}
}