{"id":"2017-00930\r\n2017-00931","title":"Photograph of Tan Beng Wan in gold-coloured frame Tan Beng Wan","source":"Bumblebee","path":"./Data/json/","content":"accession_no_csv:2017-00930\\r\\n2017-00931\nImage:\nobject_work_type:black-and-white photographs studio portraits\ntitle_text:Photograph of Tan Beng Wan in gold-coloured frame Tan Beng Wan\npreference:alternate main\ntitle_language:\ncreation_date:Late 19th century\ncreation_place_original_location:Singapore\ninscriptions:\ninscription_language:\nshape:rectangular\nmaterials_name:paper (fiber product) wood (plant material)\ntechniques_name:photography (process)\nobject_colour:black-and-white (color)\nphysical_appearance:These are two identical black-and-white photographs. They are a portrait photograph of Tan Beng Wan\n wearing traditional Han Chinese dress of a jacket and long robe. He is leaning against a draped balustrade\n with his right hand resting on the structure\n and his left hand on his hip.\nsubject_terms_1:Peranakan businessmen Han (Chinese\n culture\n style\n period) folk costume photographs\nsubject_terms_2:Portrait photography Peranakan (Asian people) Businessmen Ethnic costume Photographs\nsubject_terms_3:Portrait photography Tan\n Kim Tian Peranakan clans and associations\nsgcool_label_text:This photograph shows Tan Beng Wan (1851-1891) wearing traditional Han Chinese dress of a jacket (magua) and long robe (changpao). He poses in what is likely to be a photographic studio\n leaning against a draped balustrade. Tan Beng Wan was the eldest son of Tan Kim Tian\n with whom he founded Tan Kim Tian and Son Steamship Company in 1871. The firm was one of the first in Singapore to buy and build ships. He also served as Municipal Commissioner from 1888 until his death. This photograph came from the collection of Botan House\n the ancestral home built by Tan Kim Tian.","createdDate":"20201119143406","version":0,"latest":false,"roles":[],"metadata":{"accession_no_csv":"2017-00930\r\n2017-00931","Image":"","object_work_type":"black-and-white photographs studio portraits","title_text":"Photograph of Tan Beng Wan in gold-coloured frame Tan Beng Wan","preference":"alternate main","title_language":"","creation_date":"Late 19th century","creation_place_original_location":"Singapore","inscriptions":"","inscription_language":"","shape":"rectangular","materials_name":"paper (fiber product) wood (plant material)","techniques_name":"photography (process)","object_colour":"black-and-white (color)","physical_appearance":"These are two identical black-and-white photographs. They are a portrait photograph of Tan Beng Wan, wearing traditional Han Chinese dress of a jacket and long robe. He is leaning against a draped balustrade, with his right hand resting on the structure, and his left hand on his hip.","subject_terms_1":"Peranakan businessmen Han (Chinese, culture, style, period) folk costume photographs","subject_terms_2":"Portrait photography Peranakan (Asian people) Businessmen Ethnic costume Photographs","subject_terms_3":"Portrait photography Tan, Kim Tian Peranakan clans and associations","sgcool_label_text":"This photograph shows Tan Beng Wan (1851-1891) wearing traditional Han Chinese dress of a jacket (magua) and long robe (changpao). He poses in what is likely to be a photographic studio, leaning against a draped balustrade. Tan Beng Wan was the eldest son of Tan Kim Tian, with whom he founded Tan Kim Tian and Son Steamship Company in 1871. The firm was one of the first in Singapore to buy and build ships. He also served as Municipal Commissioner from 1888 until his death. This photograph came from the collection of Botan House, the ancestral home built by Tan Kim Tian."},"nlpDate":"20201119143406","connectorId":0,"tags":{}}