{"id":"2017-00320-001 and 002","title":"Lanna Buddha Head","source":"Bumblebee","path":"./Data/json/","content":"accession_no_csv:2017-00320-001 and 002\nImage:\nobject_work_type:Buddhas (visual works)\ntitle_text:Lanna Buddha Head\npreference:main\ntitle_language:\ncreation_date:Early 16th century\ncreation_place_original_location:Thailand\n Northern  Lanna (Kingdom)\nstyles_periods_indexing_terms:Northern Thai\ninscriptions:\ninscription_language:\nmaterials_name:bronze (metal)\ntechniques_name:lost-wax process casting (process)\nobject_colour:bronze (colour)\nphysical_appearance:This is a bronze Buddha head. He is depicted with highly arched brows that meet at the bridge of his nose\n downcast eyes\n a tall nose\n relatively thin lips that curve slightly upwards at its edges\n a defined chin\n and long ear lobes. He also sports an ushnisha\n snail-shell coils as hair\n and has three lines on his neck; lakshanas that define him as a mahapurusha (Great Being). He is missing his top finial.\nsubject_terms_1:buddhas (people) attributes (symbols)  nirvana  religious art religious visual works religious symbolism\nsubject_terms_2:Buddha Nirvana  Introspection Religious art\nsubject_terms_3:Buddhism\nsubject_terms_4:\nsgcool_label_text:This Buddha\n when it was complete\n would have looked down serenely upon those who worshipped it. It was produced in Lan Na (northern Thailand)\n a major bronze-casting centre. Its prominent cranial bump (ushnisha) was originally topped by a flame finial (now missing) similar to those on the two Sukhothai Buddha images on display in this gallery. \\r\\n\\r\\nAs with Sukhothai\n Lan Na was heavily influenced by Sri Lankan Buddhism. Styles flowed between the various kingdoms\n and Buddha images from Lan Na and Sukhothai share many similarities. Influence also moved by less peaceful means: in the 15th century\n Sawankhalok captured by Tiloka\n the Lan Na king\n who then repulsed a number of attempts by Sukhothai to regain the city. \\r\\n","createdDate":"20201018182636","version":0,"latest":false,"roles":[],"metadata":{"accession_no_csv":"2017-00320-001 and 002","Image":"","object_work_type":"Buddhas (visual works)","title_text":"Lanna Buddha Head","preference":"main","title_language":"","creation_date":"Early 16th century","creation_place_original_location":"Thailand, Northern  Lanna (Kingdom)","styles_periods_indexing_terms":"Northern Thai","inscriptions":"","inscription_language":"","materials_name":"bronze (metal)","techniques_name":"lost-wax process casting (process)","object_colour":"bronze (colour)","physical_appearance":"This is a bronze Buddha head. He is depicted with highly arched brows that meet at the bridge of his nose, downcast eyes, a tall nose, relatively thin lips that curve slightly upwards at its edges, a defined chin, and long ear lobes. He also sports an ushnisha, snail-shell coils as hair, and has three lines on his neck; lakshanas that define him as a mahapurusha (Great Being). He is missing his top finial.","subject_terms_1":"buddhas (people) attributes (symbols)  nirvana  religious art religious visual works religious symbolism","subject_terms_2":"Buddha Nirvana  Introspection Religious art","subject_terms_3":"Buddhism","subject_terms_4":"","sgcool_label_text":"This Buddha, when it was complete, would have looked down serenely upon those who worshipped it. It was produced in Lan Na (northern Thailand), a major bronze-casting centre. Its prominent cranial bump (ushnisha) was originally topped by a flame finial (now missing) similar to those on the two Sukhothai Buddha images on display in this gallery. \r\n\r\nAs with Sukhothai, Lan Na was heavily influenced by Sri Lankan Buddhism. Styles flowed between the various kingdoms, and Buddha images from Lan Na and Sukhothai share many similarities. Influence also moved by less peaceful means: in the 15th century, Sawankhalok captured by Tiloka, the Lan Na king, who then repulsed a number of attempts by Sukhothai to regain the city. \r\n"},"nlpDate":"20201018182636","connectorId":0,"tags":{}}