{
  "id": "2017-00145-134",
  "title": "Reflections of Tan Chong Tee: Memoir Reflections of Tan Chong Tee: Letters, Notes, and Photographs",
  "source": "Bumblebee",
  "path": "./Data/json/",
  "content": "\n  accession_no_csv: 2017-00145-134\n\n  Image: \n\n  object_work_type: document (object genre) memoirs\n\n  title_text: Reflections of Tan Chong Tee: Memoir Reflections of Tan Chong Tee: Letters\n Notes\n and Photographs\n\n  preference: main alternate\n\n  title_language: \n\n  creator_2: Tan Chong Tee\n\n  creator_1: Tan\n Chong Tee Chen\n Chongzhi\n 1916-\n\n  creator_role: authors\n\n  creation_place_original_location: Singapore\n\n  inscriptions: \n\n  inscription_language: \n\n  shape: Rectangular\n\n  materials_name: paper (fiber product)\n\n  techniques_name: handwriting\n\n  object_colour: multicoloured\n\n  physical_appearance: This text documents the author\\u0027s desire to leak the information regarding Lim\\u0027s death and their transfer to the police lockup in Tapah. The document is composed of text written on a piece of Chinese foolscap which has a another piece of writing pasted on it. The words are written in two shades of blue ink and red ink. It has numerous corrections\n and is marked 32 (/ second part.5) on the top left corner. The paper is folded inwards on both the left and right length. There is a tick on the bottom right corner.\n\n  subject_terms_1: beheadings resistance movements local histories world wars Chinese scripts armed forces prisoners of war guerilla warfare\n\n  subject_terms_2: World War\n 1939-1945 Lim\n Bo Seng\n 1909-1944 Chen\n Chongzhi\n 1916- Armed Forces Guerillas Great Britain. Army. Force 136 Beheading Local history Chinese characters Force 136 (Guerilla movement) Prisoners of war War resistance movements Writing\n\n  subject_terms_3: History Tan\n Chong Tee kempeitai Lim\n Bo Seng 1942-1945 Japanese Occupation Force 136 (Guerilla movement) war personalities\n\n  context_2: \n\n  sgcool_label_text: These documents and photographs belong to a larger part of a collection of artefacts related to the World War II underground resistance movement known as Force 136. The collection of materials was gathered by Tan Chong Tee (1916- 2012)\n who was a key member of this resistance group. The collection consists of original materials belonging to Tan and other members of Force 136 dating from the 1940s to new materials reproduced from memory by Tan Chong Tee\n which date from the late 1980s to early 2000s. \\r\\n\\r\\nForce 136 was set up in July 1942 as part of the British Special Operations Executive (SOE). It recruited and trained local guerillas to gather intelligence and create an underground spy network to support planned British invasion of Japanese-occupied Malaya.\\r\\n\n",
  "createdDate": "20201125084526",
  "version": 0,
  "latest": false,
  "roles": [],
  "metadata": {
    "accession_no_csv": "2017-00145-134",
    "Image": "",
    "object_work_type": "document (object genre) memoirs",
    "title_text": "Reflections of Tan Chong Tee: Memoir Reflections of Tan Chong Tee: Letters, Notes, and Photographs",
    "preference": "main alternate",
    "title_language": "",
    "creator_2": "Tan Chong Tee",
    "creator_1": "Tan, Chong Tee Chen, Chongzhi, 1916-",
    "creator_role": "authors",
    "creation_place_original_location": "Singapore",
    "inscriptions": "",
    "inscription_language": "",
    "shape": "Rectangular",
    "materials_name": "paper (fiber product)",
    "techniques_name": "handwriting",
    "object_colour": "multicoloured",
    "physical_appearance": "This text documents the author\u0027s desire to leak the information regarding Lim\u0027s death and their transfer to the police lockup in Tapah. The document is composed of text written on a piece of Chinese foolscap which has a another piece of writing pasted on it. The words are written in two shades of blue ink and red ink. It has numerous corrections, and is marked 32 (/ second part.5) on the top left corner. The paper is folded inwards on both the left and right length. There is a tick on the bottom right corner.",
    "subject_terms_1": "beheadings resistance movements local histories world wars Chinese scripts armed forces prisoners of war guerilla warfare",
    "subject_terms_2": "World War, 1939-1945 Lim, Bo Seng, 1909-1944 Chen, Chongzhi, 1916- Armed Forces Guerillas Great Britain. Army. Force 136 Beheading Local history Chinese characters Force 136 (Guerilla movement) Prisoners of war War resistance movements Writing",
    "subject_terms_3": "History Tan, Chong Tee kempeitai Lim, Bo Seng 1942-1945 Japanese Occupation Force 136 (Guerilla movement) war personalities",
    "context_2": "",
    "sgcool_label_text": "These documents and photographs belong to a larger part of a collection of artefacts related to the World War II underground resistance movement known as Force 136. The collection of materials was gathered by Tan Chong Tee (1916- 2012), who was a key member of this resistance group. The collection consists of original materials belonging to Tan and other members of Force 136 dating from the 1940s to new materials reproduced from memory by Tan Chong Tee, which date from the late 1980s to early 2000s. \r\n\r\nForce 136 was set up in July 1942 as part of the British Special Operations Executive (SOE). It recruited and trained local guerillas to gather intelligence and create an underground spy network to support planned British invasion of Japanese-occupied Malaya.\r\n"
  },
  "nlpDate": "20201125084526",
  "connectorId": 0,
  "tags": {}
}