{
  "id": "2017-00303",
  "title": "New Year Greeting Card to  P.O.W",
  "source": "Bumblebee",
  "path": "./Data/json/",
  "content": "\n  accession_no_csv: 2017-00303\n\n  Image: \n\n  object_work_type: New Year cards\n\n  title_text: New Year Greeting Card to  P.O.W\n\n  preference: main\n\n  title_language: \n\n  creation_date: 1945\n\n  creation_place_original_location: Singapore\n\n  inscriptions: \n\n  inscription_language: \n\n  shape: rectangular\n\n  materials_name: paper (fiber product)\n\n  techniques_name: drawing (image-making)\n\n  object_colour: multicolored\n\n  physical_appearance: This is a greeting card. The card is brown in colour. The words \\u0027Xmas Greetings 1944\\u0027 is written in light white ink. There is a decorative line across the bottom of the card in orange ink. The card has a white and black string attached to the left of the card. There are no tears or folds seen.\n\n  subject_terms_1: world wars Christmas cards prisoners of war\n\n  subject_terms_2: World War\n 1939-1945 New Year cards Christmas cards Prisoners of war\n\n  subject_terms_3: Changi Prison 1942-1945 Japanese Occupation war personalities\n\n  subject_terms_4: \n\n  context_1: World War\n 1939-1945 1942-1945 Japanese Occupation\n\n  context_2: occupations (armed conflicts) world wars\n\n  context_3: 1942-1945 1939-1945\n\n  context_4: 1939 1942\n\n  context_5: 1945\n\n  context_6: Singapore Malaya\n\n  context_7: Great Britain. Army. Royal Field Artillery\n\n  context_8: armed forces\n\n  sgcool_label_text: A card with a new year wish from one P.O.W to another\n it is inscribed with the wish “returned from active service”. The card is part of the archive of James Steele\n Royal Artillery (Field) who served in Malaya from January 1941-February 1942\n when interned as a P.O.W at Changi until his release in October 1945\n",
  "createdDate": "20201201203308",
  "version": 0,
  "latest": false,
  "roles": [],
  "metadata": {
    "accession_no_csv": "2017-00303",
    "Image": "",
    "object_work_type": "New Year cards",
    "title_text": "New Year Greeting Card to  P.O.W",
    "preference": "main",
    "title_language": "",
    "creation_date": "1945",
    "creation_place_original_location": "Singapore",
    "inscriptions": "",
    "inscription_language": "",
    "shape": "rectangular",
    "materials_name": "paper (fiber product)",
    "techniques_name": "drawing (image-making)",
    "object_colour": "multicolored",
    "physical_appearance": "This is a greeting card. The card is brown in colour. The words \u0027Xmas Greetings 1944\u0027 is written in light white ink. There is a decorative line across the bottom of the card in orange ink. The card has a white and black string attached to the left of the card. There are no tears or folds seen.",
    "subject_terms_1": "world wars Christmas cards prisoners of war",
    "subject_terms_2": "World War, 1939-1945 New Year cards Christmas cards Prisoners of war",
    "subject_terms_3": "Changi Prison 1942-1945 Japanese Occupation war personalities",
    "subject_terms_4": "",
    "context_1": "World War, 1939-1945 1942-1945 Japanese Occupation",
    "context_2": "occupations (armed conflicts) world wars",
    "context_3": "1942-1945 1939-1945",
    "context_4": "1939 1942",
    "context_5": "1945",
    "context_6": "Singapore Malaya",
    "context_7": "Great Britain. Army. Royal Field Artillery",
    "context_8": "armed forces",
    "sgcool_label_text": "A card with a new year wish from one P.O.W to another, it is inscribed with the wish “returned from active service”. The card is part of the archive of James Steele, Royal Artillery (Field) who served in Malaya from January 1941-February 1942, when interned as a P.O.W at Changi until his release in October 1945"
  },
  "nlpDate": "20201201203308",
  "connectorId": 0,
  "tags": {}
}