{
  "id": "2017-00547",
  "title": "The Wait Without Waiting",
  "source": "Bumblebee",
  "path": "./Data/json/",
  "content": "\n  accession_no_csv: 2017-00547\n\n  Image: \n\n  object_work_type: video art\n\n  title_text: The Wait Without Waiting\n\n  preference: main\n\n  title_language: \n\n  creator_2: Kai Qun Chun\n\n  creator_role: artists (visual artists)\n\n  creation_date: 2015\n\n  creation_place_original_location: Singapore\n\n  inscriptions: \n\n  inscription_language: \n\n  techniques_name: videography\n\n  physical_appearance: There are two image clips taken from a video recording. In both clips\n there is a still image of a road with a petrol kiosk in the background on the left. The image on the right has a yellow taxi on the road. The image on the right shows a small white lorry on the road. There are no people seen in either images.\n\n  subject_terms_1: streets taxicabs waiting video recordings\n\n  subject_terms_2: Video recordings Streets Taxicabs Waiting (Philosophy) Video Art\n\n  subject_terms_3: Films Streets and Places\n\n  sgcool_label_text: Compositionally\n The Wait without Waiting calls to mind the works Nighthawks (1942) and Twentysix Gasoline Stations (1963) and Standard Station\n Amarillo Texas (1964) by American Realist painters\n Edward Hopper and Ed Ruscha respectively. Sensationally too\n The Wait draws the viewer to reflect on notions of identity\n isolation and loneliness\n echoing the impressions presented in Hopper and Ruscha’s renowned works. Stylistically\n The Wait’s painterly quality arises out of the various ‘lines’ that cross the screen: the harsh horizontal and vertical lines marked out by the petrol station’s stationary silhouette along with the ‘green’ and ‘red’ taxis that brush past the screen work together to create a dynamic landscape that evokes both a sense of ‘stability’ and ‘instability’ that hangs in a fine balance. Through carefully crafted edits\n that result in one footage presenting only available taxis and the other featuring only unavailable taxis\n The Wait plays on the familiar emotions of satisfaction and frustration witnessed by individuals who attempt to hail taxis; “I edited the video separating the available and unavailable taxis\n thereby also removing the actual waiting time of six hours. Then I stitched them all together into two separate channels\n the taxis emerging continuously\n seamlessly without wait\n” explained the artist.\n",
  "createdDate": "20201120223708",
  "version": 0,
  "latest": false,
  "roles": [],
  "metadata": {
    "accession_no_csv": "2017-00547",
    "Image": "",
    "object_work_type": "video art",
    "title_text": "The Wait Without Waiting",
    "preference": "main",
    "title_language": "",
    "creator_2": "Kai Qun Chun",
    "creator_role": "artists (visual artists)",
    "creation_date": "2015",
    "creation_place_original_location": "Singapore",
    "inscriptions": "",
    "inscription_language": "",
    "techniques_name": "videography",
    "physical_appearance": "There are two image clips taken from a video recording. In both clips, there is a still image of a road with a petrol kiosk in the background on the left. The image on the right has a yellow taxi on the road. The image on the right shows a small white lorry on the road. There are no people seen in either images.",
    "subject_terms_1": "streets taxicabs waiting video recordings",
    "subject_terms_2": "Video recordings Streets Taxicabs Waiting (Philosophy) Video Art",
    "subject_terms_3": "Films Streets and Places",
    "sgcool_label_text": "Compositionally, The Wait without Waiting calls to mind the works Nighthawks (1942) and Twentysix Gasoline Stations (1963) and Standard Station, Amarillo Texas (1964) by American Realist painters, Edward Hopper and Ed Ruscha respectively. Sensationally too, The Wait draws the viewer to reflect on notions of identity, isolation and loneliness, echoing the impressions presented in Hopper and Ruscha’s renowned works. Stylistically, The Wait’s painterly quality arises out of the various ‘lines’ that cross the screen: the harsh horizontal and vertical lines marked out by the petrol station’s stationary silhouette along with the ‘green’ and ‘red’ taxis that brush past the screen work together to create a dynamic landscape that evokes both a sense of ‘stability’ and ‘instability’ that hangs in a fine balance. Through carefully crafted edits, that result in one footage presenting only available taxis and the other featuring only unavailable taxis, The Wait plays on the familiar emotions of satisfaction and frustration witnessed by individuals who attempt to hail taxis; “I edited the video separating the available and unavailable taxis, thereby also removing the actual waiting time of six hours. Then I stitched them all together into two separate channels, the taxis emerging continuously, seamlessly without wait,” explained the artist."
  },
  "nlpDate": "20201120223708",
  "connectorId": 0,
  "tags": {}
}