{"id":"2017-00294-045","title":"Group of 50 photographs of P.O.W James Steele and regiment when stationed in Malaysia in 1941 (and 2 later photographs of Steele placing a wreath at ceremony of remembrance)  Dr Grant, Mersing 1941","source":"Bumblebee","path":"./Data/json/","content":"accession_no_csv:2017-00294-045\nImage:\nobject_work_type:black-and-white photographs\ntitle_text:Group of 50 photographs of P.O.W James Steele and regiment when stationed in Malaysia in 1941 (and 2 later photographs of Steele placing a wreath at ceremony of remembrance)  Dr Grant\n Mersing 1941\npreference:alternate main\ntitle_language:\ncreation_date:1941-1945\ncreation_place_original_location:Singapore Johor Bahru (Johor\n Malaysia)\ninscriptions:\ninscription_language:\nshape:rectangular\nmaterials_name:paper (fiber product)\ntechniques_name:photographic processes\nobject_colour:black-and-white (colors)\nphysical_appearance:This is a black-and-white photograph. It features a man standing in the middle of a sandy\n uneven beach. He is dressed only in shorts\n and is holding a coconut in his right hand. The sea can be seen in the background. The edges of the photograph are uneven. There are no tears and folds seen on the photograph.\nsubject_terms_1:world wars soldiers beaches\nsubject_terms_2:World War\n 1939-1945 Soldiers Photography Beaches\nsubject_terms_3:war personalities Photography\nsubject_terms_4:\ncontext_1:World War\n 1939-1945\ncontext_2:world wars\ncontext_3:1939-1945\ncontext_4:1939\ncontext_5:1945\ncontext_6:Malaya\ncontext_7:Great Britain. Army. Royal Field Artillery\ncontext_8:armed forces\nsgcool_label_text:A variety of portraits of British soldiers that show them at leisure as well as two photographs of James Steele placing a wreath at a remembrance ceremony\n this collection is part of the archive of James Steele\n Royal Artillery (Field) who served in Malaya from January 1941-February 1942\n when interned as a P.O.W at Changi until his release in October 1945.","createdDate":"20201018182636","version":0,"latest":false,"roles":[],"metadata":{"accession_no_csv":"2017-00294-045","Image":"","object_work_type":"black-and-white photographs","title_text":"Group of 50 photographs of P.O.W James Steele and regiment when stationed in Malaysia in 1941 (and 2 later photographs of Steele placing a wreath at ceremony of remembrance)  Dr Grant, Mersing 1941","preference":"alternate main","title_language":"","creation_date":"1941-1945","creation_place_original_location":"Singapore Johor Bahru (Johor, Malaysia)","inscriptions":"","inscription_language":"","shape":"rectangular","materials_name":"paper (fiber product)","techniques_name":"photographic processes","object_colour":"black-and-white (colors)","physical_appearance":"This is a black-and-white photograph. It features a man standing in the middle of a sandy, uneven beach. He is dressed only in shorts, and is holding a coconut in his right hand. The sea can be seen in the background. The edges of the photograph are uneven. There are no tears and folds seen on the photograph.","subject_terms_1":"world wars soldiers beaches","subject_terms_2":"World War, 1939-1945 Soldiers Photography Beaches","subject_terms_3":"war personalities Photography","subject_terms_4":"","context_1":"World War, 1939-1945","context_2":"world wars","context_3":"1939-1945","context_4":"1939","context_5":"1945","context_6":"Malaya","context_7":"Great Britain. Army. Royal Field Artillery","context_8":"armed forces","sgcool_label_text":"A variety of portraits of British soldiers that show them at leisure as well as two photographs of James Steele placing a wreath at a remembrance ceremony, this collection is part of the archive of James Steele, Royal Artillery (Field) who served in Malaya from January 1941-February 1942, when interned as a P.O.W at Changi until his release in October 1945."},"nlpDate":"20201018182636","connectorId":0,"tags":{}}