{"id":"2017-00635","title":"Doorway hanging Chakla","source":"Bumblebee","path":"./Data/json/","content":"accession_no_csv:2017-00635\nImage:\nobject_work_type:hangings (coverings)\ntitle_text:Doorway hanging Chakla\npreference:main alternate\ntitle_language:\ncreation_date:20th century\ncreation_place_original_location:Gujarat (India)\ninscriptions:\ninscription_language:\nshape:pentagonal\nmaterials_name:glass (material) cotton (textile)\ntechniques_name:sewing (needleworking technique) embroidering\nobject_colour:multicolored\nphysical_appearance:This is a chakla or a hanging textile. It features a cotton weave with embroidery work. The chakla is decorated with stylized foliage\n animals\n and three deity figures. The chakla is in the shape of a five-sided figure\n with a higher triangular top and square bottom.\nsubject_terms_1:embroidery (visual works) foliage (motif) birds (motifs) deities depictions (visual works) beadwork (visual works)\nsubject_terms_2:Draperies Embroidery Motifs Gods\nsubject_terms_3:Textile art and design\nsubject_terms_4:","createdDate":"20201119143406","version":0,"latest":false,"roles":[],"metadata":{"accession_no_csv":"2017-00635","Image":"","object_work_type":"hangings (coverings)","title_text":"Doorway hanging Chakla","preference":"main alternate","title_language":"","creation_date":"20th century","creation_place_original_location":"Gujarat (India)","inscriptions":"","inscription_language":"","shape":"pentagonal","materials_name":"glass (material) cotton (textile)","techniques_name":"sewing (needleworking technique) embroidering","object_colour":"multicolored","physical_appearance":"This is a chakla or a hanging textile. It features a cotton weave with embroidery work. The chakla is decorated with stylized foliage, animals, and three deity figures. The chakla is in the shape of a five-sided figure, with a higher triangular top and square bottom.","subject_terms_1":"embroidery (visual works) foliage (motif) birds (motifs) deities depictions (visual works) beadwork (visual works)","subject_terms_2":"Draperies Embroidery Motifs Gods","subject_terms_3":"Textile art and design","subject_terms_4":""},"nlpDate":"20201119143406","connectorId":0,"tags":{}}