{"id":"2017-00226","title":"The Greater East Asia Co-Prosperity Sphere by Utsunomiya Ken","source":"Bumblebee","path":"./Data/json/","content":"accession_no_csv:2017-00226\nImage:\nobject_work_type:books\ntitle_text:The Greater East Asia Co-Prosperity Sphere by Utsunomiya Ken\npreference:main\ntitle_language:\ncreator_2:Utsunomiya Ken  Nihon Rekishi Kenky?kai\ncreator_role:editors (people who revise)  publishers\ncreation_date:1942\ncreation_place_original_location:Japan\ninscriptions:\ninscription_language:\nshape:Rectangular\nmaterials_name:paper (fiber product)\ntechniques_name:bookbinding (process)  photography (process)\nobject_colour:black-and-white (colours)\nedition_description:First\nphysical_appearance:On the cover of the book\n the title\n substitle\n and publisher\\u0027s name can be found. It is also underlined in blue.  Along the right edge of the book are white strings that reveal how the book has been bound. Beneath the title is an illustration of palm trees and aeroplanes in flight.\nsubject_terms_1:propaganda world wars colonialism\nsubject_terms_2:Southeast Asia  Photographic surveying  Propaganda\n Japanese  Colonies  World War\n 1939-1945 Books Greater East Asia Co-prosperity Sphere  Utsunomiya Ken  Nihon Rekishi Kenky?kai\nsubject_terms_3:Wars\nsgcool_label_text:Published in 1942\n this book is an extensive photographic survey of the regions of Southeast Asia under Japanese colonial rule during the Pacific War\n including the Philippines\n French Indochina\n Thailand\n Burma\n Malaya\n Borneo and Singapore. It was edited by Utsunomiya Ken\n and published by Nihon Rekishi Kenky?kai (Japanese History Research Group). As a propagandistic publication\n it intended to promote the concept of ‘brotherhood’ amongst Southeast Asian people under the Japanese Empire.","createdDate":"20201119143406","version":0,"latest":false,"roles":[],"metadata":{"accession_no_csv":"2017-00226","Image":"","object_work_type":"books","title_text":"The Greater East Asia Co-Prosperity Sphere by Utsunomiya Ken","preference":"main","title_language":"","creator_2":"Utsunomiya Ken  Nihon Rekishi Kenky?kai","creator_role":"editors (people who revise)  publishers","creation_date":"1942","creation_place_original_location":"Japan","inscriptions":"","inscription_language":"","shape":"Rectangular","materials_name":"paper (fiber product)","techniques_name":"bookbinding (process)  photography (process)","object_colour":"black-and-white (colours)","edition_description":"First","physical_appearance":"On the cover of the book, the title, substitle, and publisher\u0027s name can be found. It is also underlined in blue.  Along the right edge of the book are white strings that reveal how the book has been bound. Beneath the title is an illustration of palm trees and aeroplanes in flight.","subject_terms_1":"propaganda world wars colonialism","subject_terms_2":"Southeast Asia  Photographic surveying  Propaganda, Japanese  Colonies  World War, 1939-1945 Books Greater East Asia Co-prosperity Sphere  Utsunomiya Ken  Nihon Rekishi Kenky?kai","subject_terms_3":"Wars","sgcool_label_text":"Published in 1942, this book is an extensive photographic survey of the regions of Southeast Asia under Japanese colonial rule during the Pacific War, including the Philippines, French Indochina, Thailand, Burma, Malaya, Borneo and Singapore. It was edited by Utsunomiya Ken, and published by Nihon Rekishi Kenky?kai (Japanese History Research Group). As a propagandistic publication, it intended to promote the concept of ‘brotherhood’ amongst Southeast Asian people under the Japanese Empire."},"nlpDate":"20201119143406","connectorId":0,"tags":{}}