{"id":"2018-00034","title":"Henry. Keppel’s, A visit to the Indian Archipelago, in H.M. ship Maeander, with portions of the private journal of Sir James Brooke, K.C.R.","source":"Bumblebee","path":"./Data/json/","content":"accession_no_csv:2018-00034\nImage:\nobject_work_type:hardcover books illustrated books rare books\ntitle_text:Henry. Keppel’s\n A visit to the Indian Archipelago\n in H.M. ship Maeander\n with portions of the private journal of Sir James Brooke\n K.C.R.\npreference:main\ntitle_language:\ncreator_2:Captain. The Honorary Henry Keppel\n R.N.  Oswald W. Brierly London: Richard Bentley\n New Burlington Street Day \\u0026 Son\n Lithographers to the Queen J \\u0026 C Walker James Brooke\ncreator_1:Keppel\n Henry\n Sir\n 1809-1904 Brierly\n Oswald Walters\n Sir\n 1817-1894 Richard Bentley (Firm) Day \\u0026 Son J \\u0026 C Walker (Firm) James\n Rajah of Sarawak\n 1803-1868\ncreator_role:authors illustrators publishers lithographers engravers (printmakers) contributors\ncreation_date:1853\ncreation_place_original_location:Greater London (metropolitan area) Southeast Asia\nstyles_periods_indexing_terms:Not indicated\ninscriptions:\ninscription_language:\nscale_type:Not indicated\nshape:rectangular\nmaterials_name:paper (fiber product) printing paper\ntechniques_name:colour printing bookbinding (process) book cloth (textile material) illustration (process)\nobject_colour:grey (colour) monochrome\nedition_description:First Edition\nphysical_appearance:\\The book is hardcover and its front cover and spine are black in colour. The book is open and the contents of two pages are displayed. The title\n contributor\n author\n illustrator\n and publisher are displayed on the page on the right hand side of the book. There is an image of a mountain with a body of water and some small boats on the left page. \\\\Santabong Entrance\\\\ is stated at the bottom of the image. \\\\O.W. Brierly\\\\\nsubject_terms_1:\\\\G. Hawkins\\\\ expeditions (journeys) archipelagoes colonial settlements mountains frigates\nsubject_terms_2:and \\\\Day \\u0026 Son Illustrated books Voyages and travels Colonies Mountains Frigates\nsubject_terms_3:Lithographers to the Queen\\\\ are stated at the bottom as well. \\ Keppel\n Henry\n Sir Colonial administrators Military transportation\nsubject_terms_4:travel literature\ncontext_1:Travel writing\ncontext_2:Non-fiction\ncontext_3:Malay Archipelago (islands)","createdDate":"20201018182637","version":0,"latest":false,"roles":[],"metadata":{"accession_no_csv":"2018-00034","Image":"","object_work_type":"hardcover books illustrated books rare books","title_text":"Henry. Keppel’s, A visit to the Indian Archipelago, in H.M. ship Maeander, with portions of the private journal of Sir James Brooke, K.C.R.","preference":"main","title_language":"","creator_2":"Captain. The Honorary Henry Keppel, R.N.  Oswald W. Brierly London: Richard Bentley, New Burlington Street Day \u0026 Son, Lithographers to the Queen J \u0026 C Walker James Brooke","creator_1":"Keppel, Henry, Sir, 1809-1904 Brierly, Oswald Walters, Sir, 1817-1894 Richard Bentley (Firm) Day \u0026 Son J \u0026 C Walker (Firm) James, Rajah of Sarawak, 1803-1868","creator_role":"authors illustrators publishers lithographers engravers (printmakers) contributors","creation_date":"1853","creation_place_original_location":"Greater London (metropolitan area) Southeast Asia","styles_periods_indexing_terms":"Not indicated","inscriptions":"","inscription_language":"","scale_type":"Not indicated","shape":"rectangular","materials_name":"paper (fiber product) printing paper","techniques_name":"colour printing bookbinding (process) book cloth (textile material) illustration (process)","object_colour":"grey (colour) monochrome","edition_description":"First Edition","physical_appearance":"\"The book is hardcover and its front cover and spine are black in colour. The book is open and the contents of two pages are displayed. The title, contributor, author, illustrator, and publisher are displayed on the page on the right hand side of the book. There is an image of a mountain with a body of water and some small boats on the left page. \"\"Santabong Entrance\"\" is stated at the bottom of the image. \"\"O.W. Brierly\"\"","subject_terms_1":"\"\"G. Hawkins\"\" expeditions (journeys) archipelagoes colonial settlements mountains frigates","subject_terms_2":"and \"\"Day \u0026 Son Illustrated books Voyages and travels Colonies Mountains Frigates","subject_terms_3":"Lithographers to the Queen\"\" are stated at the bottom as well. \" Keppel, Henry, Sir Colonial administrators Military transportation","subject_terms_4":"travel literature","context_1":"Travel writing","context_2":"Non-fiction","context_3":"Malay Archipelago (islands)"},"nlpDate":"20201018182637","connectorId":0,"tags":{}}