{"id":"2018-00162","title":"Photograph of three seated Indo Eurasian women and a standing woman","source":"Bumblebee","path":"./Data/json/","content":"accession_no_csv:2018-00162\nImage:\nobject_work_type:black-and-white photographs photographs\ntitle_text:Photograph of three seated Indo Eurasian women and a standing woman\npreference:main\ntitle_language:\ncreator_2:Not indicated\ncreator_1:Not indicated\ncreation_date:Late 19th century\ncreation_place_original_location:Indonesia (nation)\ninscriptions:\ninscription_language:\nshape:rectangular\nmaterials_name:paper (fiber product)\ntechniques_name:printing (process) photographic processes\nobject_colour:grey monochrome\nphysical_appearance:The image shows a black-and-white photograph. It is rectangular and it features four ladies. Three of them are sitting down and looking towards the direction where the photograph was captured. A cabin takes up the background of the photograph. A lady can be seen standing in the porch of the cabin.\nsubject_terms_1:group portraits women (female humans) Peranakan folk costume cabins (houses)\nsubject_terms_2:Black-and-white photography Portrait photography Portraits\n Group Women Log cabins Eurasians Ethnic costume\nsubject_terms_3:Portrait photography Women Peranakan costumes\nsgcool_label_text:This photograph shows three Indo Eurasian women in sarong kebayas seated at a table in front of  Cabine de Planteurs de Cacao van Houten\n with a woman standing behind. \\r\\n\\r\\nWith continuous improvement of camera technology\n it became possible to take photographs outside a studio in the first decades of the 20th century. Many middle-class families collected photographs in albums as a way of documenting family life\n or documentasi keluarga.","createdDate":"20201018182637","version":0,"latest":false,"roles":[],"metadata":{"accession_no_csv":"2018-00162","Image":"","object_work_type":"black-and-white photographs photographs","title_text":"Photograph of three seated Indo Eurasian women and a standing woman","preference":"main","title_language":"","creator_2":"Not indicated","creator_1":"Not indicated","creation_date":"Late 19th century","creation_place_original_location":"Indonesia (nation)","inscriptions":"","inscription_language":"","shape":"rectangular","materials_name":"paper (fiber product)","techniques_name":"printing (process) photographic processes","object_colour":"grey monochrome","physical_appearance":"The image shows a black-and-white photograph. It is rectangular and it features four ladies. Three of them are sitting down and looking towards the direction where the photograph was captured. A cabin takes up the background of the photograph. A lady can be seen standing in the porch of the cabin.","subject_terms_1":"group portraits women (female humans) Peranakan folk costume cabins (houses)","subject_terms_2":"Black-and-white photography Portrait photography Portraits, Group Women Log cabins Eurasians Ethnic costume","subject_terms_3":"Portrait photography Women Peranakan costumes","sgcool_label_text":"This photograph shows three Indo Eurasian women in sarong kebayas seated at a table in front of  Cabine de Planteurs de Cacao van Houten, with a woman standing behind. \r\n\r\nWith continuous improvement of camera technology, it became possible to take photographs outside a studio in the first decades of the 20th century. Many middle-class families collected photographs in albums as a way of documenting family life, or documentasi keluarga."},"nlpDate":"20201018182637","connectorId":0,"tags":{}}