{
  "id": "2018-00127",
  "title": "Photograph of John Mather",
  "source": "Bumblebee",
  "path": "./Data/json/",
  "content": "\n  accession_no_csv: 2018-00127\n\n  Image: \n\n  object_work_type: cartes-de-visite (card photographs)\n\n  title_text: Photograph of John Mather\n\n  preference: main\n\n  title_language: \n\n  creator_2: Tien Seng\n\n  creator_1: Not indicated\n\n  creator_role: photography studios (organizations)\n\n  creation_date: 1890s-1900s\n\n  creation_place_original_location: Singapore (nation)\n\n  inscriptions: \n\n  inscription_language: \n\n  shape: rectangular\n\n  materials_name: paper (fiber product)\n\n  techniques_name: printing (process) photographic processes\n\n  object_colour: grey monochrome\n\n  physical_appearance: The image shows a black-and-white photograph. It is rectangular and it features a man standing up. He is looking towards the direction where the photograph was captured. He is wearing a long sleeved shirt and pants. His right hand is placed on top of a table.\n\n  subject_terms_1: black-and-white photographs studio portraits men (male humans)\n\n  subject_terms_2: Black-and-white photography Portrait photography Men\n\n  subject_terms_3: Portrait photography\n\n  sgcool_label_text: This carte de visite shows John Mather standing before a painted backdrop. The shopmark ‘Tien Seng. Photographer\n Singapore’ is printed on the lower edge of the carte. \\r\\n\\r\\nTien Seng was a photography studio located at North Bridge Road in Singapore. Studios were already established across the Strait Settlements and the Dutch East Indies by the 1840s and became increasingly prevalent in the 1850s. During the 1920s\n Chinese-owned studios dominated the studio photography trade in Southeast Asia.\n",
  "createdDate": "20201120223708",
  "version": 0,
  "latest": false,
  "roles": [],
  "metadata": {
    "accession_no_csv": "2018-00127",
    "Image": "",
    "object_work_type": "cartes-de-visite (card photographs)",
    "title_text": "Photograph of John Mather",
    "preference": "main",
    "title_language": "",
    "creator_2": "Tien Seng",
    "creator_1": "Not indicated",
    "creator_role": "photography studios (organizations)",
    "creation_date": "1890s-1900s",
    "creation_place_original_location": "Singapore (nation)",
    "inscriptions": "",
    "inscription_language": "",
    "shape": "rectangular",
    "materials_name": "paper (fiber product)",
    "techniques_name": "printing (process) photographic processes",
    "object_colour": "grey monochrome",
    "physical_appearance": "The image shows a black-and-white photograph. It is rectangular and it features a man standing up. He is looking towards the direction where the photograph was captured. He is wearing a long sleeved shirt and pants. His right hand is placed on top of a table.",
    "subject_terms_1": "black-and-white photographs studio portraits men (male humans)",
    "subject_terms_2": "Black-and-white photography Portrait photography Men",
    "subject_terms_3": "Portrait photography",
    "sgcool_label_text": "This carte de visite shows John Mather standing before a painted backdrop. The shopmark ‘Tien Seng. Photographer, Singapore’ is printed on the lower edge of the carte. \r\n\r\nTien Seng was a photography studio located at North Bridge Road in Singapore. Studios were already established across the Strait Settlements and the Dutch East Indies by the 1840s and became increasingly prevalent in the 1850s. During the 1920s, Chinese-owned studios dominated the studio photography trade in Southeast Asia."
  },
  "nlpDate": "20201120223708",
  "connectorId": 0,
  "tags": {}
}