{
  "id": "2018-00021",
  "title": "Photochrom of Battery Road",
  "source": "Bumblebee",
  "path": "./Data/json/",
  "content": "\n  accession_no_csv: 2018-00021\n\n  Image: \n\n  object_work_type: photochroms\n\n  title_text: Photochrom of Battery Road\n\n  preference: main\n\n  title_language: \n\n  creator_2: Not indicated\n\n  creator_1: Not indicated\n\n  creation_date: Late 19th – early 20th century\n\n  creation_place_original_location: Singapore (nation)\n\n  inscriptions: \n\n  inscription_language: \n\n  shape: rectangular\n\n  materials_name: paper (fiber product)\n\n  techniques_name: printing (process) photographic processes\n\n  object_colour: multicoloured\n\n  physical_appearance: \\The image shows a colour photograph. To the left at the foreground\n \\\\The Dispensary\\\\ is stated on the building. Pedestrians\n\n  subject_terms_1: rickshaws dispensaries (health facilities) mercantile buildings roads street scenes\n\n  subject_terms_2: Buildings Roads and horse drawn carriages can be seen on the road. Numerous multi storey roofed buildings can be seen Prints Dispensaries Singapore\n\n  subject_terms_3: Health facilities which stretch on beyond the background. \\\\20207. P. Z. – Singapore. Battery Road\\\\ is stated at the bottom right hand side. \\ Battery Road\n\n  subject_terms_4: photographic prints\n\n  context_1: Colour photography\n\n  context_2: Photography\n",
  "createdDate": "20201125084512",
  "version": 0,
  "latest": false,
  "roles": [],
  "metadata": {
    "accession_no_csv": "2018-00021",
    "Image": "",
    "object_work_type": "photochroms",
    "title_text": "Photochrom of Battery Road",
    "preference": "main",
    "title_language": "",
    "creator_2": "Not indicated",
    "creator_1": "Not indicated",
    "creation_date": "Late 19th – early 20th century",
    "creation_place_original_location": "Singapore (nation)",
    "inscriptions": "",
    "inscription_language": "",
    "shape": "rectangular",
    "materials_name": "paper (fiber product)",
    "techniques_name": "printing (process) photographic processes",
    "object_colour": "multicoloured",
    "physical_appearance": "\"The image shows a colour photograph. To the left at the foreground, \"\"The Dispensary\"\" is stated on the building. Pedestrians",
    "subject_terms_1": "rickshaws dispensaries (health facilities) mercantile buildings roads street scenes",
    "subject_terms_2": "Buildings Roads and horse drawn carriages can be seen on the road. Numerous multi storey roofed buildings can be seen Prints Dispensaries Singapore",
    "subject_terms_3": "Health facilities which stretch on beyond the background. \"\"20207. P. Z. – Singapore. Battery Road\"\" is stated at the bottom right hand side. \" Battery Road",
    "subject_terms_4": "photographic prints",
    "context_1": "Colour photography",
    "context_2": "Photography"
  },
  "nlpDate": "20201125084512",
  "connectorId": 0,
  "tags": {}
}