{"id":"2018-00414","title":"Set of seven Sherwani buttons","source":"Bumblebee","path":"./Data/json/","content":"accession_no_csv:2018-00414\nImage:\nobject_work_type:buttons (fasteners)\ntitle_text:Set of seven Sherwani buttons\npreference:main\ntitle_language:\ncreator_2:Not indicated\ncreator_1:Not indicated\ncreation_date:19th century\ncreation_place_original_location:Jaipur (inhabited place)\nstyles_periods_indexing_terms:Deccani\ninscriptions:\ninscription_language:\nshape:circular (shape)\nmaterials_name:gold (metal) enamel (fused coating) diamond (mineral)\ntechniques_name:jewellery making enamelling layering forming (physical activity)\nobject_colour:gold (colour)\nphysical_appearance:The image shows a set of seven buttons. All of them have the identical design and they are circular in shape. They are gold in colour and arranged side by side in a tubular brown box. Each button has a floral design on its surface. Gemstones are embedded in the indentations caused by the floral designs. These gemstones are silver in colour.\nsubject_terms_1:goldwork (visual works) jewellery ornaments (object genre) flower (motif) worn costume accessories\nsubject_terms_2:Buttons Gold jewellery Goldwork Motifs Dress accessories\nsubject_terms_3:Jewellery Indian decorative arts\nsgcool_label_text:This set of buttons are mounted in gold and set with flat-cut diamonds on a blue ground. The reverse sides are enamelled with polychrome floral designs. Blue buds with green leaves support several five-petalled\n red flowers. \\r\\n\\r\\nThe buttons were intended to be attached to front of a sherwani\n a knee length coat commonly worn in India in the late 1800s. A western adaptation\n the sherwani became associated with the image of an elite and educated Indian man. Decorated sherwanis would have gem-studded buttons like these attached to them.","createdDate":"20201018182637","version":0,"latest":false,"roles":[],"metadata":{"accession_no_csv":"2018-00414","Image":"","object_work_type":"buttons (fasteners)","title_text":"Set of seven Sherwani buttons","preference":"main","title_language":"","creator_2":"Not indicated","creator_1":"Not indicated","creation_date":"19th century","creation_place_original_location":"Jaipur (inhabited place)","styles_periods_indexing_terms":"Deccani","inscriptions":"","inscription_language":"","shape":"circular (shape)","materials_name":"gold (metal) enamel (fused coating) diamond (mineral)","techniques_name":"jewellery making enamelling layering forming (physical activity)","object_colour":"gold (colour)","physical_appearance":"The image shows a set of seven buttons. All of them have the identical design and they are circular in shape. They are gold in colour and arranged side by side in a tubular brown box. Each button has a floral design on its surface. Gemstones are embedded in the indentations caused by the floral designs. These gemstones are silver in colour.","subject_terms_1":"goldwork (visual works) jewellery ornaments (object genre) flower (motif) worn costume accessories","subject_terms_2":"Buttons Gold jewellery Goldwork Motifs Dress accessories","subject_terms_3":"Jewellery Indian decorative arts","sgcool_label_text":"This set of buttons are mounted in gold and set with flat-cut diamonds on a blue ground. The reverse sides are enamelled with polychrome floral designs. Blue buds with green leaves support several five-petalled, red flowers. \r\n\r\nThe buttons were intended to be attached to front of a sherwani, a knee length coat commonly worn in India in the late 1800s. A western adaptation, the sherwani became associated with the image of an elite and educated Indian man. Decorated sherwanis would have gem-studded buttons like these attached to them."},"nlpDate":"20201018182637","connectorId":0,"tags":{}}