{"id":"2018-00052-002","title":"Z: Artists\u0027 Proof Z","source":"Bumblebee","path":"./Data/json/","content":"accession_no_csv:2018-00052-002\nImage:\nobject_work_type:artists\\u0027 proofs proofs (prints by function)\ntitle_text:Z: Artists\\u0027 Proof Z\npreference:main alternate\ntitle_language:\ncreator_2:Tan Lip Seng\ncreator_1:Tan\n Lip Seng\n 1942- Tan\n Lip Seng\ncreator_role:photographers\ncreation_date:1970\ncreation_place_original_location:Singapore (nation)\nstyles_periods_indexing_terms:Not indicated\ninscriptions:\ninscription_language:\nscale_type:Not indicated\nshape:rectangular\nmaterials_name:metallic paper\ntechniques_name:printing (process) montage (image-making technique)\nobject_colour:multicoloured\nedition_description:1 of 3\nphysical_appearance:The image shows an artist\\u0027s proof. It is rectangular in shape. The proof is encased within a black frame.The background of the photograph shows the structure of a flight of stairs in a zig-zag orientation. The flight of stairs has red railings. A construction worker is depicted to be ascending the flight of stairs. He adorns a yellow helmet and carries a red pail.\nsubject_terms_1:construction workers industrial structures flights (stair components) universities (institutions)\nsubject_terms_2:Proofs (Printing) Construction workers Industrial buildings Stairs National University of Singapore\nsubject_terms_3:Photography National University of Singapore\nsgcool_label_text:This photograph was taken at National University Singapore by Singaporean photographer Tan Lip Seng. Tan is arguably the most important photographer in the region developing colour derivative and photo montage techniques. His works in the 1960s were a result of various experiments meticulously combining multiple colour transparencies into one to achieve the desired montage within one frame.\\r\\n\\r\\nTan Lip Seng also spent 42 years as a medical photographer at the National University of Singapore.","createdDate":"20201119143407","version":0,"latest":false,"roles":[],"metadata":{"accession_no_csv":"2018-00052-002","Image":"","object_work_type":"artists\u0027 proofs proofs (prints by function)","title_text":"Z: Artists\u0027 Proof Z","preference":"main alternate","title_language":"","creator_2":"Tan Lip Seng","creator_1":"Tan, Lip Seng, 1942- Tan, Lip Seng","creator_role":"photographers","creation_date":"1970","creation_place_original_location":"Singapore (nation)","styles_periods_indexing_terms":"Not indicated","inscriptions":"","inscription_language":"","scale_type":"Not indicated","shape":"rectangular","materials_name":"metallic paper","techniques_name":"printing (process) montage (image-making technique)","object_colour":"multicoloured","edition_description":"1 of 3","physical_appearance":"The image shows an artist\u0027s proof. It is rectangular in shape. The proof is encased within a black frame.The background of the photograph shows the structure of a flight of stairs in a zig-zag orientation. The flight of stairs has red railings. A construction worker is depicted to be ascending the flight of stairs. He adorns a yellow helmet and carries a red pail.","subject_terms_1":"construction workers industrial structures flights (stair components) universities (institutions)","subject_terms_2":"Proofs (Printing) Construction workers Industrial buildings Stairs National University of Singapore","subject_terms_3":"Photography National University of Singapore","sgcool_label_text":"This photograph was taken at National University Singapore by Singaporean photographer Tan Lip Seng. Tan is arguably the most important photographer in the region developing colour derivative and photo montage techniques. His works in the 1960s were a result of various experiments meticulously combining multiple colour transparencies into one to achieve the desired montage within one frame.\r\n\r\nTan Lip Seng also spent 42 years as a medical photographer at the National University of Singapore."},"nlpDate":"20201119143407","connectorId":0,"tags":{}}