{"id":"2018-00467","title":"Untitled (Singapore River Bank)","source":"Bumblebee","path":"./Data/json/","content":"accession_no_csv:2018-00467\nImage:\nobject_work_type:drawings (visual works)\ntitle_text:Untitled (Singapore River Bank)\npreference:main\ntitle_language:\ncreator_2:Choon Ghee Tan\ncreator_1:Tan\n Choon Ghee\n 1930- Tan\n Choon Ghee\ncreator_role:artists (visual artists)\ncreation_date:1964\ncreation_place_original_location:Pulau Pinang (state) Singapore (nation)\nstyles_periods_indexing_terms:Not indicated\ninscriptions:\ninscription_language:\nscale_type:Not indicated\nshape:rectangular\nmaterials_name:rice paper (paper) ink\ntechniques_name:creating (artistic activity) drawing (image-making)\nobject_colour:black (colour)\nphysical_appearance:\\The image shows a drawing. It is rectangular in shape. The lines drawn are all black in colour. There are numerous human figures depicted in the painting. The background shows a several layers of roofed buildings. A bridge can be seen at the right hand side of the drawing. The foreground shows a sheltered area. A table can be seen and several items are placed on it. The title\n signature\n and year\n \\\\S\\u0027pore River Bank\nsubject_terms_1:Tan. 1963\\\\ is stated at the bottom right hand side.\\ rivers figures (representation)\nsubject_terms_2:buildings (structures) Buildings Singapore River (Singapore)\nsubject_terms_3:Drawings Buildings Singapore River\nsubject_terms_4:Drawing Singapore (nation)\ncontext_1:Singapore River (river)","createdDate":"20201119143407","version":0,"latest":false,"roles":[],"metadata":{"accession_no_csv":"2018-00467","Image":"","object_work_type":"drawings (visual works)","title_text":"Untitled (Singapore River Bank)","preference":"main","title_language":"","creator_2":"Choon Ghee Tan","creator_1":"Tan, Choon Ghee, 1930- Tan, Choon Ghee","creator_role":"artists (visual artists)","creation_date":"1964","creation_place_original_location":"Pulau Pinang (state) Singapore (nation)","styles_periods_indexing_terms":"Not indicated","inscriptions":"","inscription_language":"","scale_type":"Not indicated","shape":"rectangular","materials_name":"rice paper (paper) ink","techniques_name":"creating (artistic activity) drawing (image-making)","object_colour":"black (colour)","physical_appearance":"\"The image shows a drawing. It is rectangular in shape. The lines drawn are all black in colour. There are numerous human figures depicted in the painting. The background shows a several layers of roofed buildings. A bridge can be seen at the right hand side of the drawing. The foreground shows a sheltered area. A table can be seen and several items are placed on it. The title, signature, and year, \"\"S\u0027pore River Bank","subject_terms_1":"Tan. 1963\"\" is stated at the bottom right hand side.\" rivers figures (representation)","subject_terms_2":"buildings (structures) Buildings Singapore River (Singapore)","subject_terms_3":"Drawings Buildings Singapore River","subject_terms_4":"Drawing Singapore (nation)","context_1":"Singapore River (river)"},"nlpDate":"20201119143407","connectorId":0,"tags":{}}