{"id":"2018-00045","title":"Children of the Sun","source":"Bumblebee","path":"./Data/json/","content":"accession_no_csv:2018-00045\nImage:\nobject_work_type:paintings (visual works) oil paintings (visual works)\ntitle_text:Children of the Sun\npreference:main\ntitle_language:\ncreator_2:Sui Ho Khoo\ncreator_1:Khoo\n Sui Hoe\n 1939-\ncreator_role:painters (artists)\ncreation_date:1965\ncreation_place_original_location:Malaysia (nation)\nstyles_periods_indexing_terms:figurative art\ninscriptions:\ninscription_language:\nshape:square (shape)\nmaterials_name:canvas (textile material) oil paint (paint)\ntechniques_name:painting (image-making)\nobject_colour:multicolored\nphysical_appearance:This is a large multicolored painting. It is in the shape of a square. It depicts seven figurative figures in various positions\n using bright colours and defined shapes. There is a bright\n circular shape at the top-center of the painting\n with yellow and white wavey lines portruding from it. In from of the circular shape\n there is a figure painted in shades of green\n with an arm stretched upwards. At the bottom of the painting\n one figure is resting on an open stylised plant with outstretched leaves. There are no signatures seen.\nsubject_terms_1:commissions (orders for works) natural element motifs figurative art\nsubject_terms_2:Painting Oil on canvas Figurative art Art commissions\nsubject_terms_3:Khoo\n Sui Hoe Oil painting Lim\n Chong Keat Singapore Conference Hall\nsubject_terms_4:\ncontext_1:Opening of the Singapore Conference Hall\ncontext_2:openings (events)\ncontext_3:15/10/65\ncontext_4:15/10/65\ncontext_5:15/10/65\ncontext_6:Singapore Conference Hall\ncontext_7:National Trades Union Congress\ncontext_8:trade unions\nsgcool_label_text:Children of the Sun is one of the few works undertaken by the artist on such a monumental scale. It could be considered an early work\n but is deeply intertwined with the artists’ interest in the figurative form. The history of the painting intertwines deeply with the national development of Singapore. The Children of the Sun was first commissioned for the opening of the Singapore Conference Hall (currently a National Monument). The painting was then kept on display in the lounge of the conference hall. Painted in 1965 at Datuk Seri Lim’s Pasir Panjang seaside cottage\n the Children of the Sun was the first major large painting by Khoo Sui Hoe. \\r\\n","createdDate":"20201119143407","version":0,"latest":false,"roles":[],"metadata":{"accession_no_csv":"2018-00045","Image":"","object_work_type":"paintings (visual works) oil paintings (visual works)","title_text":"Children of the Sun","preference":"main","title_language":"","creator_2":"Sui Ho Khoo","creator_1":"Khoo, Sui Hoe, 1939-","creator_role":"painters (artists)","creation_date":"1965","creation_place_original_location":"Malaysia (nation)","styles_periods_indexing_terms":"figurative art","inscriptions":"","inscription_language":"","shape":"square (shape)","materials_name":"canvas (textile material) oil paint (paint)","techniques_name":"painting (image-making)","object_colour":"multicolored","physical_appearance":"This is a large multicolored painting. It is in the shape of a square. It depicts seven figurative figures in various positions, using bright colours and defined shapes. There is a bright, circular shape at the top-center of the painting, with yellow and white wavey lines portruding from it. In from of the circular shape, there is a figure painted in shades of green, with an arm stretched upwards. At the bottom of the painting, one figure is resting on an open stylised plant with outstretched leaves. There are no signatures seen.","subject_terms_1":"commissions (orders for works) natural element motifs figurative art","subject_terms_2":"Painting Oil on canvas Figurative art Art commissions","subject_terms_3":"Khoo, Sui Hoe Oil painting Lim, Chong Keat Singapore Conference Hall","subject_terms_4":"","context_1":"Opening of the Singapore Conference Hall","context_2":"openings (events)","context_3":"15/10/65","context_4":"15/10/65","context_5":"15/10/65","context_6":"Singapore Conference Hall","context_7":"National Trades Union Congress","context_8":"trade unions","sgcool_label_text":"Children of the Sun is one of the few works undertaken by the artist on such a monumental scale. It could be considered an early work, but is deeply intertwined with the artists’ interest in the figurative form. The history of the painting intertwines deeply with the national development of Singapore. The Children of the Sun was first commissioned for the opening of the Singapore Conference Hall (currently a National Monument). The painting was then kept on display in the lounge of the conference hall. Painted in 1965 at Datuk Seri Lim’s Pasir Panjang seaside cottage, the Children of the Sun was the first major large painting by Khoo Sui Hoe. \r\n"},"nlpDate":"20201119143407","connectorId":0,"tags":{}}