{
  "id": "2018-00046-001",
  "title": "Three Workers: Original Artwork Three Workers",
  "source": "Bumblebee",
  "path": "./Data/json/",
  "content": "\n  accession_no_csv: 2018-00046-001\n\n  Image: \n\n  object_work_type: digital prints prints (visual works)\n\n  title_text: Three Workers: Original Artwork Three Workers\n\n  preference: main alternate\n\n  title_language: \n\n  creator_2: Tan Lip Seng\n\n  creator_1: Tan\n Lip Seng\n 1942- Tan\n Lip Seng\n\n  creator_role: photographers\n\n  creation_date: 1965\n\n  creation_place_original_location: Singapore (nation)\n\n  styles_periods_indexing_terms: Not indicated\n\n  inscriptions: \n\n  inscription_language: \n\n  scale_type: Not indicated\n\n  shape: rectangular\n\n  materials_name: photographic paper\n\n  techniques_name: photographic processes montage (image-making technique)\n\n  object_colour: multicoloured\n\n  edition_description: 1 of 3\n\n  physical_appearance: The image shows a digital print. It is rectangular in shape. The backs of three women are facing the direction in which the print was captured. All of them are wearing headscarfs and shoes. The background of the print shows a building. The first level of the building contains running rectangular patterns along its wall. There are numerous cracks along the concrete\n above the base of the building. The ground in which the three women are walking on contains numerous stones. It is also uneven.\n\n  subject_terms_1: workers women (female humans)\n\n  subject_terms_2: Employees Women Colour prints Digitally printed materials\n\n  subject_terms_3: Women Photography\n\n  sgcool_label_text: This photograph was taken by Singaporean photographer Tan Lip Seng. Tan is arguably the most important photographer in the region developing colour derivative and photo montage techniques. His works in the 1960s were a result of various experiments meticulously combining multiple colour transparencies into one to achieve the desired montage within one frame.\\r\\n\\r\\nTan spent 42 years as a medical photographer at the National University of Singapore. Many of his works have won numerous awards internationally and show a strong graphic and stylistic sensibility.\n",
  "createdDate": "20201120223708",
  "version": 0,
  "latest": false,
  "roles": [],
  "metadata": {
    "accession_no_csv": "2018-00046-001",
    "Image": "",
    "object_work_type": "digital prints prints (visual works)",
    "title_text": "Three Workers: Original Artwork Three Workers",
    "preference": "main alternate",
    "title_language": "",
    "creator_2": "Tan Lip Seng",
    "creator_1": "Tan, Lip Seng, 1942- Tan, Lip Seng",
    "creator_role": "photographers",
    "creation_date": "1965",
    "creation_place_original_location": "Singapore (nation)",
    "styles_periods_indexing_terms": "Not indicated",
    "inscriptions": "",
    "inscription_language": "",
    "scale_type": "Not indicated",
    "shape": "rectangular",
    "materials_name": "photographic paper",
    "techniques_name": "photographic processes montage (image-making technique)",
    "object_colour": "multicoloured",
    "edition_description": "1 of 3",
    "physical_appearance": "The image shows a digital print. It is rectangular in shape. The backs of three women are facing the direction in which the print was captured. All of them are wearing headscarfs and shoes. The background of the print shows a building. The first level of the building contains running rectangular patterns along its wall. There are numerous cracks along the concrete, above the base of the building. The ground in which the three women are walking on contains numerous stones. It is also uneven.",
    "subject_terms_1": "workers women (female humans)",
    "subject_terms_2": "Employees Women Colour prints Digitally printed materials",
    "subject_terms_3": "Women Photography",
    "sgcool_label_text": "This photograph was taken by Singaporean photographer Tan Lip Seng. Tan is arguably the most important photographer in the region developing colour derivative and photo montage techniques. His works in the 1960s were a result of various experiments meticulously combining multiple colour transparencies into one to achieve the desired montage within one frame.\r\n\r\nTan spent 42 years as a medical photographer at the National University of Singapore. Many of his works have won numerous awards internationally and show a strong graphic and stylistic sensibility."
  },
  "nlpDate": "20201120223708",
  "connectorId": 0,
  "tags": {}
}