{"id":"2018-00175","title":"Photograph of Lee Chin Koon","source":"Bumblebee","path":"./Data/json/","content":"accession_no_csv:2018-00175\nImage:\nobject_work_type:black-and-white photographs photographs\ntitle_text:Photograph of Lee Chin Koon\npreference:main\ntitle_language:\ncreator_2:Not indicated\ncreator_1:Not indicated\ncreation_date:1998\ncreation_place_original_location:Singapore (nation)\ninscriptions:\ninscription_language:\nshape:rectangular\nmaterials_name:paper (fiber product)\ntechniques_name:printing (process) photographic processes\nobject_colour:grey monochrome\nphysical_appearance:The image shows a black-and-white photograph. It is rectangular and it features an elderly man. He is sitting down and looking towards the direction where the photograph was captured. He adorns a long-sleeved shirt that has flowery patterns all over.\nsubject_terms_1:portraits men (male humans) lawyers\nsubject_terms_2:Black-and-white photography Portrait photography Men Lawyers\nsubject_terms_3:Portrait photography Lee\n Chin Koon Lawyers\nsgcool_label_text:This photograph shows Lee Chin Koon (1903-1997)\n father of Lee Kuan Yew (1923-2015) who was the first Prime Minster of Singapore. Born in Indonesia\n he was the attorney to the Sugar King Oei Tiong Ham\n and the first honorary secretary of the Chinese Swimming Club.","createdDate":"20201018182637","version":0,"latest":false,"roles":[],"metadata":{"accession_no_csv":"2018-00175","Image":"","object_work_type":"black-and-white photographs photographs","title_text":"Photograph of Lee Chin Koon","preference":"main","title_language":"","creator_2":"Not indicated","creator_1":"Not indicated","creation_date":"1998","creation_place_original_location":"Singapore (nation)","inscriptions":"","inscription_language":"","shape":"rectangular","materials_name":"paper (fiber product)","techniques_name":"printing (process) photographic processes","object_colour":"grey monochrome","physical_appearance":"The image shows a black-and-white photograph. It is rectangular and it features an elderly man. He is sitting down and looking towards the direction where the photograph was captured. He adorns a long-sleeved shirt that has flowery patterns all over.","subject_terms_1":"portraits men (male humans) lawyers","subject_terms_2":"Black-and-white photography Portrait photography Men Lawyers","subject_terms_3":"Portrait photography Lee, Chin Koon Lawyers","sgcool_label_text":"This photograph shows Lee Chin Koon (1903-1997), father of Lee Kuan Yew (1923-2015) who was the first Prime Minster of Singapore. Born in Indonesia, he was the attorney to the Sugar King Oei Tiong Ham, and the first honorary secretary of the Chinese Swimming Club."},"nlpDate":"20201018182637","connectorId":0,"tags":{}}