{"id":"2018-00051","title":"Iron and Steel","source":"Bumblebee","path":"./Data/json/","content":"accession_no_csv:2018-00051\nImage:\nobject_work_type:digital prints artists\\u0027 proofs colour slides\ntitle_text:Iron and Steel\npreference:main\ntitle_language:\ncreator_2:Tan Lip Seng\ncreator_1:Tan\n Lip Seng\n 1942- Tan\n Lip Seng\ncreator_role:photographers\ncreation_date:1970\ncreation_place_original_location:Singapore (nation)\nstyles_periods_indexing_terms:Not indicated\ninscriptions:\ninscription_language:\nscale_type:Not indicated\nshape:rectangular\nmaterials_name:photographic paper metallic paper photographic film (photographic materials)\ntechniques_name:photographic processes montage (image-making technique) printing (process)\nobject_colour:multicoloured\nedition_description:1 of 3\nphysical_appearance:\\The image shows a digital print\n an artist\\u0027s proof\n and a slide. They are rectangular in shape. The background of the digital print and artist\\u0027s proof are black and red in colour. The background of the digital print and artist\\u0027s proof show the metal structure of a building\n which is red in colour. At the left hand side of the digital print and artist\\u0027s proof\n a construction worker can be seen sitting atop a metal beam. He is wearing a blue helmet and is using a hammer on the bolts in the steel structure.  The image at the bottom shows a slide. It is in colour. It is held in place by a frame. On the borders of the frame\n \\\\Iron and Steel\\\\ is stated at the top for the image at the bottom. \\\\Tan Lip Seng\nsubject_terms_1:A.R.P.S. AFIAP working construction (assembling) prints (visual works) proofs (prints by function) industrial structures slides (photographs)\nsubject_terms_2:96A Tiong Bahru Road. Singapore 3 Building Digitally printed materials Slides (photography) Colour prints Industrial buildings Proofs (Printing)\nsubject_terms_3:PSA Galaxy Award\\\\ is stated at the bottom for the image at the bottom.\\ Industrial buildings\nsubject_terms_4:construction workers\ncontext_1:Construction workers\ncontext_2:Photography","createdDate":"20201018182637","version":0,"latest":false,"roles":[],"metadata":{"accession_no_csv":"2018-00051","Image":"","object_work_type":"digital prints artists\u0027 proofs colour slides","title_text":"Iron and Steel","preference":"main","title_language":"","creator_2":"Tan Lip Seng","creator_1":"Tan, Lip Seng, 1942- Tan, Lip Seng","creator_role":"photographers","creation_date":"1970","creation_place_original_location":"Singapore (nation)","styles_periods_indexing_terms":"Not indicated","inscriptions":"","inscription_language":"","scale_type":"Not indicated","shape":"rectangular","materials_name":"photographic paper metallic paper photographic film (photographic materials)","techniques_name":"photographic processes montage (image-making technique) printing (process)","object_colour":"multicoloured","edition_description":"1 of 3","physical_appearance":"\"The image shows a digital print, an artist\u0027s proof, and a slide. They are rectangular in shape. The background of the digital print and artist\u0027s proof are black and red in colour. The background of the digital print and artist\u0027s proof show the metal structure of a building, which is red in colour. At the left hand side of the digital print and artist\u0027s proof, a construction worker can be seen sitting atop a metal beam. He is wearing a blue helmet and is using a hammer on the bolts in the steel structure.  The image at the bottom shows a slide. It is in colour. It is held in place by a frame. On the borders of the frame, \"\"Iron and Steel\"\" is stated at the top for the image at the bottom. \"\"Tan Lip Seng","subject_terms_1":"A.R.P.S. AFIAP working construction (assembling) prints (visual works) proofs (prints by function) industrial structures slides (photographs)","subject_terms_2":"96A Tiong Bahru Road. Singapore 3 Building Digitally printed materials Slides (photography) Colour prints Industrial buildings Proofs (Printing)","subject_terms_3":"PSA Galaxy Award\"\" is stated at the bottom for the image at the bottom.\" Industrial buildings","subject_terms_4":"construction workers","context_1":"Construction workers","context_2":"Photography"},"nlpDate":"20201018182637","connectorId":0,"tags":{}}