{"id":"2018-00153","title":"Photograph of a group of Anglo-Chinese School students","source":"Bumblebee","path":"./Data/json/","content":"accession_no_csv:2018-00153\nImage:\nobject_work_type:black-and-white photographs photographs\ntitle_text:Photograph of a group of Anglo-Chinese School students\npreference:main\ntitle_language:\ncreator_2:Not indicated\ncreator_1:Not indicated\ncreation_date:1910\ncreation_place_original_location:Singapore (nation) Malaysia (nation)\ninscriptions:\ninscription_language:\nshape:rectangular\nmaterials_name:paper (fiber product)\ntechniques_name:printing (process) photographic processes\nobject_colour:grey monochrome\nphysical_appearance:The image shows a black-and-white photograph. It is rectangular and it features a group of people. Most of them are sitting down on chairs\n with some on the ground. Mnay of them are wearing hats. The background of the photograph shows the woods.\nsubject_terms_1:group portraits students\nsubject_terms_2:Black-and-white photography Portrait photography Portraits\n Group Students Schools\nsubject_terms_3:Portrait photography Youth Anglo-Chinese School\nsgcool_label_text:This photograph shows a group of Anglo-Chinese School students posing before a bamboo grove.\\r\\n\\r\\nThe Anglo-Chinese School was a Methodist school founded in 1886 by Bishop William Fitzjames Oldham.\\r\\n\\r\\nWith continuous improvement of camera technology\n it became possible to take photographs outside a studio in the first decades of the 20th century. Many middle-class families collected photographs in albums as a way of documenting family life\n or documentasi keluarga.","createdDate":"20201018182637","version":0,"latest":false,"roles":[],"metadata":{"accession_no_csv":"2018-00153","Image":"","object_work_type":"black-and-white photographs photographs","title_text":"Photograph of a group of Anglo-Chinese School students","preference":"main","title_language":"","creator_2":"Not indicated","creator_1":"Not indicated","creation_date":"1910","creation_place_original_location":"Singapore (nation) Malaysia (nation)","inscriptions":"","inscription_language":"","shape":"rectangular","materials_name":"paper (fiber product)","techniques_name":"printing (process) photographic processes","object_colour":"grey monochrome","physical_appearance":"The image shows a black-and-white photograph. It is rectangular and it features a group of people. Most of them are sitting down on chairs, with some on the ground. Mnay of them are wearing hats. The background of the photograph shows the woods.","subject_terms_1":"group portraits students","subject_terms_2":"Black-and-white photography Portrait photography Portraits, Group Students Schools","subject_terms_3":"Portrait photography Youth Anglo-Chinese School","sgcool_label_text":"This photograph shows a group of Anglo-Chinese School students posing before a bamboo grove.\r\n\r\nThe Anglo-Chinese School was a Methodist school founded in 1886 by Bishop William Fitzjames Oldham.\r\n\r\nWith continuous improvement of camera technology, it became possible to take photographs outside a studio in the first decades of the 20th century. Many middle-class families collected photographs in albums as a way of documenting family life, or documentasi keluarga."},"nlpDate":"20201018182637","connectorId":0,"tags":{}}