{
  "id": "2018-00156",
  "title": "Photograph of the Vosmarr family",
  "source": "Bumblebee",
  "path": "./Data/json/",
  "content": "\n  accession_no_csv: 2018-00156\n\n  Image: \n\n  object_work_type: photographs black-and-white photographs\n\n  title_text: Photograph of the Vosmarr family\n\n  preference: main\n\n  title_language: \n\n  creator_2: Not indicated\n\n  creator_1: Not indicated\n\n  creation_date: 1925\n\n  creation_place_original_location: Jakarta (inhabited place)\n\n  inscriptions: \n\n  inscription_language: \n\n  shape: rectangular\n\n  materials_name: paper (fiber product)\n\n  techniques_name: printing (process) photographic processes\n\n  object_colour: grey monochrome\n\n  physical_appearance: The image shows a black-and-white photograph. It is rectangular and it features a group of people. They are sitting down on chairs in the interior of a building. Resolution of phootgraph is not high enough to identify more details.\n\n  subject_terms_1: families (kinship groups) teas (meals)\n\n  subject_terms_2: Afternoon teas Families Black-and-white photography\n\n  subject_terms_3: Photography\n\n  sgcool_label_text: This photograph shows the Vosmarr family having tea on the veranda.\\r\\n\\r\\nWith continuous improvement of camera technology\n it became possible to take photographs outside a studio in the first decades of the 20th century. Many middle-class families collected photographs in ff as a way of documenting family life\n or documentasi keluarga.\n",
  "createdDate": "20201201203307",
  "version": 0,
  "latest": false,
  "roles": [],
  "metadata": {
    "accession_no_csv": "2018-00156",
    "Image": "",
    "object_work_type": "photographs black-and-white photographs",
    "title_text": "Photograph of the Vosmarr family",
    "preference": "main",
    "title_language": "",
    "creator_2": "Not indicated",
    "creator_1": "Not indicated",
    "creation_date": "1925",
    "creation_place_original_location": "Jakarta (inhabited place)",
    "inscriptions": "",
    "inscription_language": "",
    "shape": "rectangular",
    "materials_name": "paper (fiber product)",
    "techniques_name": "printing (process) photographic processes",
    "object_colour": "grey monochrome",
    "physical_appearance": "The image shows a black-and-white photograph. It is rectangular and it features a group of people. They are sitting down on chairs in the interior of a building. Resolution of phootgraph is not high enough to identify more details.",
    "subject_terms_1": "families (kinship groups) teas (meals)",
    "subject_terms_2": "Afternoon teas Families Black-and-white photography",
    "subject_terms_3": "Photography",
    "sgcool_label_text": "This photograph shows the Vosmarr family having tea on the veranda.\r\n\r\nWith continuous improvement of camera technology, it became possible to take photographs outside a studio in the first decades of the 20th century. Many middle-class families collected photographs in ff as a way of documenting family life, or documentasi keluarga."
  },
  "nlpDate": "20201201203307",
  "connectorId": 0,
  "tags": {}
}