{"id":"2018-00157","title":"Photograph of a colonial bungalow with family and servants","source":"Bumblebee","path":"./Data/json/","content":"accession_no_csv:2018-00157\nImage:\nobject_work_type:black-and-white photographs photographs\ntitle_text:Photograph of a colonial bungalow with family and servants\npreference:main\ntitle_language:\ncreator_2:Not indicated\ncreator_1:Not indicated\ncreation_date:Late 19th centiury\ncreation_place_original_location:Indonesia (nation)\ninscriptions:\ninscription_language:\nshape:rectangular\nmaterials_name:paper (fiber product)\ntechniques_name:printing (process) photographic processes\nobject_colour:grey monochrome\nphysical_appearance:The image shows a black-and-white photograph. It is rectangular and it features an image of a bungalow. It is situated in the background of the photograph. There are trees in front and to the sides of the bungalow. There are groups of people standing in front of the bungalow.\nsubject_terms_1:families (kinship groups) servants bungalows\nsubject_terms_2:Black-and-white photography Families Household employees Bungalows Architecture\n Colonial\nsubject_terms_3:Photography Colonial architecture\nsgcool_label_text:This photograph is a long shot of a colonial bungalow with the family and servants posing before it.\\r\\n\\r\\nWith continuous improvement of camera technology\n it became possible to take photographs outside a studio in the first decades of the 20th century. Many middle-class families collected photographs in albums as a way of documenting family life\n or documentasi keluarga.","createdDate":"20201119143407","version":0,"latest":false,"roles":[],"metadata":{"accession_no_csv":"2018-00157","Image":"","object_work_type":"black-and-white photographs photographs","title_text":"Photograph of a colonial bungalow with family and servants","preference":"main","title_language":"","creator_2":"Not indicated","creator_1":"Not indicated","creation_date":"Late 19th centiury","creation_place_original_location":"Indonesia (nation)","inscriptions":"","inscription_language":"","shape":"rectangular","materials_name":"paper (fiber product)","techniques_name":"printing (process) photographic processes","object_colour":"grey monochrome","physical_appearance":"The image shows a black-and-white photograph. It is rectangular and it features an image of a bungalow. It is situated in the background of the photograph. There are trees in front and to the sides of the bungalow. There are groups of people standing in front of the bungalow.","subject_terms_1":"families (kinship groups) servants bungalows","subject_terms_2":"Black-and-white photography Families Household employees Bungalows Architecture, Colonial","subject_terms_3":"Photography Colonial architecture","sgcool_label_text":"This photograph is a long shot of a colonial bungalow with the family and servants posing before it.\r\n\r\nWith continuous improvement of camera technology, it became possible to take photographs outside a studio in the first decades of the 20th century. Many middle-class families collected photographs in albums as a way of documenting family life, or documentasi keluarga."},"nlpDate":"20201119143407","connectorId":0,"tags":{}}