{"id":"2018-00140","title":"Studio portrait of a seated baba","source":"Bumblebee","path":"./Data/json/","content":"accession_no_csv:2018-00140\nImage:\nobject_work_type:black-and-white photographs photographs\ntitle_text:Studio portrait of a seated baba\npreference:main\ntitle_language:\ncreator_2:Not indicated\ncreator_1:Not indicated\ncreation_date:1870s\ncreation_place_original_location:Singapore (nation)\ninscriptions:\ninscription_language:\nshape:rectangular\nmaterials_name:paper (fiber product)\ntechniques_name:printing (process) photographic processes\nobject_colour:grey monochrome\nphysical_appearance:The image shows a black-and-white photograph. It is rectangular and it features a man. He is seated beside a table and resting his arms on the supports of the chair. He is dresssed in his ethnic costume and is looking towards the direction in which the photograph was captured.\nsubject_terms_1:studio portraits men (male humans) Peranakan folk costume\nsubject_terms_2:Black-and-white photography Portrait photography Men Ethnic costume Peranakan (Asian people)\nsubject_terms_3:Portrait photography Peranakan costumes\nsgcool_label_text:This studio portrait shows a baba seated beside a table\n his arms resting on the arms of the chair. \\r\\n\\r\\nStudios were already established across the Strait Settlements and the Dutch East Indies by the 1840s and became increasingly prevalent in the 1850s. During the 1920s\n Chinese-owned studios dominated the studio photography trade in Southeast Asia.","createdDate":"20201018182637","version":0,"latest":false,"roles":[],"metadata":{"accession_no_csv":"2018-00140","Image":"","object_work_type":"black-and-white photographs photographs","title_text":"Studio portrait of a seated baba","preference":"main","title_language":"","creator_2":"Not indicated","creator_1":"Not indicated","creation_date":"1870s","creation_place_original_location":"Singapore (nation)","inscriptions":"","inscription_language":"","shape":"rectangular","materials_name":"paper (fiber product)","techniques_name":"printing (process) photographic processes","object_colour":"grey monochrome","physical_appearance":"The image shows a black-and-white photograph. It is rectangular and it features a man. He is seated beside a table and resting his arms on the supports of the chair. He is dresssed in his ethnic costume and is looking towards the direction in which the photograph was captured.","subject_terms_1":"studio portraits men (male humans) Peranakan folk costume","subject_terms_2":"Black-and-white photography Portrait photography Men Ethnic costume Peranakan (Asian people)","subject_terms_3":"Portrait photography Peranakan costumes","sgcool_label_text":"This studio portrait shows a baba seated beside a table, his arms resting on the arms of the chair. \r\n\r\nStudios were already established across the Strait Settlements and the Dutch East Indies by the 1840s and became increasingly prevalent in the 1850s. During the 1920s, Chinese-owned studios dominated the studio photography trade in Southeast Asia."},"nlpDate":"20201018182637","connectorId":0,"tags":{}}