{
  "id": "2018-00202",
  "title": "Officials of the Peranakan Association",
  "source": "Bumblebee",
  "path": "./Data/json/",
  "content": "\n  accession_no_csv: 2018-00202\n\n  Image: \n\n  object_work_type: photographs black-and-white photographs\n\n  title_text: Officials of the Peranakan Association\n\n  preference: main\n\n  title_language: \n\n  creator_2: David Studio Singapore\n\n  creator_1: Not indicated\n\n  creator_role: photography studios (organizations)\n\n  creation_date: 1973 - 1974\n\n  creation_place_original_location: Singapore (nation)\n\n  inscriptions: \n\n  inscription_language: \n\n  shape: rectangular\n\n  materials_name: paper (fiber product)\n\n  techniques_name: printing (process) photographic processes\n\n  object_colour: grey monochrome\n\n  physical_appearance: \\The image shows a black-and-white photograph. It is rectangular and it features a group of people. The ones in the front are sitting down while the others are standing behind. All of them are facing the direction in which the photograph was captured. \\\\Officials of the Perawakan Association\n\n  subject_terms_1: studio portraits 1973 - 1974\\\\ is stated at the top. \\\\David Studio Singapore\\\\ is stated at the bottom right hand side in red. The names of the people in the photograph are stated at the bottom. All of the men are wearing suits and ties. There is only one lady in the picture associations members\n\n  subject_terms_2: sitting at the front row towards the left hand side of the photograph.\\ Peranakan (Asian people) Lee\n Kip Lin Portraits\n Group Peranakan Association\n Singapore Black-and-white photography\n\n  subject_terms_3: Lee\n Kip Lin Peranakan Association\n Singapore group portraits\n\n  subject_terms_4: Portrait photography\n\n  context_1: Portrait photography\n",
  "createdDate": "20201125084507",
  "version": 0,
  "latest": false,
  "roles": [],
  "metadata": {
    "accession_no_csv": "2018-00202",
    "Image": "",
    "object_work_type": "photographs black-and-white photographs",
    "title_text": "Officials of the Peranakan Association",
    "preference": "main",
    "title_language": "",
    "creator_2": "David Studio Singapore",
    "creator_1": "Not indicated",
    "creator_role": "photography studios (organizations)",
    "creation_date": "1973 - 1974",
    "creation_place_original_location": "Singapore (nation)",
    "inscriptions": "",
    "inscription_language": "",
    "shape": "rectangular",
    "materials_name": "paper (fiber product)",
    "techniques_name": "printing (process) photographic processes",
    "object_colour": "grey monochrome",
    "physical_appearance": "\"The image shows a black-and-white photograph. It is rectangular and it features a group of people. The ones in the front are sitting down while the others are standing behind. All of them are facing the direction in which the photograph was captured. \"\"Officials of the Perawakan Association",
    "subject_terms_1": "studio portraits 1973 - 1974\"\" is stated at the top. \"\"David Studio Singapore\"\" is stated at the bottom right hand side in red. The names of the people in the photograph are stated at the bottom. All of the men are wearing suits and ties. There is only one lady in the picture associations members",
    "subject_terms_2": "sitting at the front row towards the left hand side of the photograph.\" Peranakan (Asian people) Lee, Kip Lin Portraits, Group Peranakan Association, Singapore Black-and-white photography",
    "subject_terms_3": "Lee, Kip Lin Peranakan Association, Singapore group portraits",
    "subject_terms_4": "Portrait photography",
    "context_1": "Portrait photography"
  },
  "nlpDate": "20201125084507",
  "connectorId": 0,
  "tags": {}
}