{"id":"2018-00051-002","title":"Iron and Steel: Artists\u0027 Proof Iron and Steel","source":"Bumblebee","path":"./Data/json/","content":"accession_no_csv:2018-00051-002\nImage:\nobject_work_type:artists\\u0027 proofs proofs (prints by function)\ntitle_text:Iron and Steel: Artists\\u0027 Proof Iron and Steel\npreference:main alternate\ntitle_language:\ncreator_2:Tan Lip Seng\ncreator_1:Tan\n Lip Seng\n 1942- Tan\n Lip Seng\ncreator_role:photographers\ncreation_date:1970\ncreation_place_original_location:Singapore (nation)\nstyles_periods_indexing_terms:Not indicated\ninscriptions:\ninscription_language:\nscale_type:Not indicated\nshape:rectangular\nmaterials_name:metallic paper\ntechniques_name:printing (process) montage (image-making technique)\nobject_colour:multicoloured\nedition_description:1 of 3\nphysical_appearance:The image shows an artist\\u0027s proof. It is rectangular in shape. The proof is encased within a black frame.It features the metal structure of a building\n which is red in colour. A construction worker can be seen sitting atop a metal beam. He is wearing a blue helmet and is using a hammer on the bolts in the steel structure.\nsubject_terms_1:construction workers working construction (assembling) industrial structures\nsubject_terms_2:Proofs (Printing) Construction workers Building Industrial buildings Work\nsubject_terms_3:Photography Industrial buildings\nsgcool_label_text:This photograph was taken by Singaporean photographer Tan Lip Seng. His works in the 1960s were a result of various experiments meticulously combining multiple colour transparencies into one to achieve the desired montage within one frame.\\r\\n\\r\\nTan Lip Seng started his career as a medical photographer at the National University of Singapore. He is famous worldwide for his innovative colour derivative photo montage technique as well as his travel photography.\\r\\n","createdDate":"20201119143407","version":0,"latest":false,"roles":[],"metadata":{"accession_no_csv":"2018-00051-002","Image":"","object_work_type":"artists\u0027 proofs proofs (prints by function)","title_text":"Iron and Steel: Artists\u0027 Proof Iron and Steel","preference":"main alternate","title_language":"","creator_2":"Tan Lip Seng","creator_1":"Tan, Lip Seng, 1942- Tan, Lip Seng","creator_role":"photographers","creation_date":"1970","creation_place_original_location":"Singapore (nation)","styles_periods_indexing_terms":"Not indicated","inscriptions":"","inscription_language":"","scale_type":"Not indicated","shape":"rectangular","materials_name":"metallic paper","techniques_name":"printing (process) montage (image-making technique)","object_colour":"multicoloured","edition_description":"1 of 3","physical_appearance":"The image shows an artist\u0027s proof. It is rectangular in shape. The proof is encased within a black frame.It features the metal structure of a building, which is red in colour. A construction worker can be seen sitting atop a metal beam. He is wearing a blue helmet and is using a hammer on the bolts in the steel structure.","subject_terms_1":"construction workers working construction (assembling) industrial structures","subject_terms_2":"Proofs (Printing) Construction workers Building Industrial buildings Work","subject_terms_3":"Photography Industrial buildings","sgcool_label_text":"This photograph was taken by Singaporean photographer Tan Lip Seng. His works in the 1960s were a result of various experiments meticulously combining multiple colour transparencies into one to achieve the desired montage within one frame.\r\n\r\nTan Lip Seng started his career as a medical photographer at the National University of Singapore. He is famous worldwide for his innovative colour derivative photo montage technique as well as his travel photography.\r\n"},"nlpDate":"20201119143407","connectorId":0,"tags":{}}