{"id":"2018-00155","title":"Photograph of Charlotte Adelheid Vosmarr with a dog","source":"Bumblebee","path":"./Data/json/","content":"accession_no_csv:2018-00155\nImage:\nobject_work_type:black-and-white photographs photographs\ntitle_text:Photograph of Charlotte Adelheid Vosmarr with a dog\npreference:main\ntitle_language:\ncreator_2:Not indicated\ncreator_1:Not indicated\ncreation_date:1930\ncreation_place_original_location:Indonesia (nation)\ninscriptions:\ninscription_language:\nshape:rectangular\nmaterials_name:paper (fiber product)\ntechniques_name:printing (process) photographic processes\nobject_colour:grey monochrome\nphysical_appearance:The image shows a black-and-white photograph. It is rectangular and it features a woman and a dog. The woman has placed the dog on her laps and is holding it. The dog is looking towards the direction where the photograph was captured\n while the lady is looking at the dog. The lady wears a dress with a headdress.\nsubject_terms_1:women (female humans) Caris (genus) studio portraits\nsubject_terms_2:Black-and-white photography Women Dogs Portrait photography\nsubject_terms_3:Portrait photography Women\nsgcool_label_text:This photograph shows Charlotte Adelheid Vosmarr with a dog on her lap.\\r\\n\\r\\nWith continuous improvement of camera technology\n it became possible to take photographs outside a studio in the first decades of the 20th century. Many middle-class families collected photographs in albums as a way of documenting family life\n or documentasi keluarga.","createdDate":"20201018182637","version":0,"latest":false,"roles":[],"metadata":{"accession_no_csv":"2018-00155","Image":"","object_work_type":"black-and-white photographs photographs","title_text":"Photograph of Charlotte Adelheid Vosmarr with a dog","preference":"main","title_language":"","creator_2":"Not indicated","creator_1":"Not indicated","creation_date":"1930","creation_place_original_location":"Indonesia (nation)","inscriptions":"","inscription_language":"","shape":"rectangular","materials_name":"paper (fiber product)","techniques_name":"printing (process) photographic processes","object_colour":"grey monochrome","physical_appearance":"The image shows a black-and-white photograph. It is rectangular and it features a woman and a dog. The woman has placed the dog on her laps and is holding it. The dog is looking towards the direction where the photograph was captured, while the lady is looking at the dog. The lady wears a dress with a headdress.","subject_terms_1":"women (female humans) Caris (genus) studio portraits","subject_terms_2":"Black-and-white photography Women Dogs Portrait photography","subject_terms_3":"Portrait photography Women","sgcool_label_text":"This photograph shows Charlotte Adelheid Vosmarr with a dog on her lap.\r\n\r\nWith continuous improvement of camera technology, it became possible to take photographs outside a studio in the first decades of the 20th century. Many middle-class families collected photographs in albums as a way of documenting family life, or documentasi keluarga."},"nlpDate":"20201018182637","connectorId":0,"tags":{}}