{
  "id": "2018-00464",
  "title": "Elizabeth Walk, Singapore",
  "source": "Bumblebee",
  "path": "./Data/json/",
  "content": "\n  accession_no_csv: 2018-00464\n\n  Image: \n\n  object_work_type: drawings (visual works)\n\n  title_text: Elizabeth Walk\n Singapore\n\n  preference: main\n\n  title_language: \n\n  creator_2: Choon Ghee Tan\n\n  creator_1: Tan\n Choon Ghee\n 1930- Tan\n Choon Ghee\n\n  creator_role: artists (visual artists)\n\n  creation_date: 1963\n\n  creation_place_original_location: Pulau Pinang (state) Singapore (nation)\n\n  styles_periods_indexing_terms: Not indicated\n\n  inscriptions: \n\n  inscription_language: \n\n  scale_type: Not indicated\n\n  shape: rectangular\n\n  materials_name: paper (fiber product) ink\n\n  techniques_name: drawing (image-making) creating (artistic activity)\n\n  object_colour: black (colour)\n\n  physical_appearance: \\The image shows a painting. It is rectangular in shape. It depicts a seated figure on a stool. The seated figure is wearing a shirt and shorts\n as well as headgear. There is a table beside the seated figue\n and there are objects placed on top of it. The title\n signature\n and year\n \\\\Elizabeth Walk\n\n  subject_terms_1: seated figures Tan. 1963\\\\ is stated at the bottom right hand side. There are two vertical lines of Chinese characters\n\n  subject_terms_2: Drawings Singapore above the signature and year.  \\\n\n  subject_terms_3: Drawing Visual arts workers\n\n  subject_terms_4: Employees\n\n  context_1: Queen Elizabeth Walk\n\n  context_2: Singapore (nation)\n",
  "createdDate": "20201201203307",
  "version": 0,
  "latest": false,
  "roles": [],
  "metadata": {
    "accession_no_csv": "2018-00464",
    "Image": "",
    "object_work_type": "drawings (visual works)",
    "title_text": "Elizabeth Walk, Singapore",
    "preference": "main",
    "title_language": "",
    "creator_2": "Choon Ghee Tan",
    "creator_1": "Tan, Choon Ghee, 1930- Tan, Choon Ghee",
    "creator_role": "artists (visual artists)",
    "creation_date": "1963",
    "creation_place_original_location": "Pulau Pinang (state) Singapore (nation)",
    "styles_periods_indexing_terms": "Not indicated",
    "inscriptions": "",
    "inscription_language": "",
    "scale_type": "Not indicated",
    "shape": "rectangular",
    "materials_name": "paper (fiber product) ink",
    "techniques_name": "drawing (image-making) creating (artistic activity)",
    "object_colour": "black (colour)",
    "physical_appearance": "\"The image shows a painting. It is rectangular in shape. It depicts a seated figure on a stool. The seated figure is wearing a shirt and shorts, as well as headgear. There is a table beside the seated figue, and there are objects placed on top of it. The title, signature, and year, \"\"Elizabeth Walk",
    "subject_terms_1": "seated figures Tan. 1963\"\" is stated at the bottom right hand side. There are two vertical lines of Chinese characters",
    "subject_terms_2": "Drawings Singapore above the signature and year.  \"",
    "subject_terms_3": "Drawing Visual arts workers",
    "subject_terms_4": "Employees",
    "context_1": "Queen Elizabeth Walk",
    "context_2": "Singapore (nation)"
  },
  "nlpDate": "20201201203307",
  "connectorId": 0,
  "tags": {}
}