{
  "id": "2018-00062",
  "title": "Visscher\u0027s Map of Southeast Asia published by Pieter Schenk",
  "source": "Bumblebee",
  "path": "./Data/json/",
  "content": "\n  accession_no_csv: 2018-00062\n\n  Image: \n\n  object_work_type: maps (documents) pictorial maps\n\n  title_text: Visscher\\u0027s Map of Southeast Asia published by Pieter Schenk\n\n  preference: main\n\n  title_language: \n\n  creator_2: Nicolas Visscher I Pieter Schenk Jr\n\n  creator_1: not indicated\n\n  creator_role: publishers cartographers\n\n  creation_date: Early 18th century\n\n  creation_place_original_location: not indicated\n\n  styles_periods_indexing_terms: not indicated\n\n  inscriptions: \n\n  inscription_language: \n\n  scale_type: The scale of the map is in miles.\n\n  shape: rectangular\n\n  materials_name: paper (fiber product)\n\n  techniques_name: papermaking copper engraving (printing process) hand coloring\n\n  object_colour: multicoloured\n\n  physical_appearance: This is a multicoloured map of Southeast Asia\n created by Nicolas Visscher I and published by Pieter Schenk Jr. There are many words at the top of the map\n highlighting the names of places in Southeast Asia where the Dutch East India Company (VOC) extended their control over trade activities. The bottom of the map has lines of text that represent the title and scale of the map.\n\n  subject_terms_1: coastlines trade (general function) cartouches (ornament) cartography (discipline)\n\n  subject_terms_2: Australia Pictorial maps India Spice trade Southeast Asia East Indies Nederlandsche Oost-Indische Compagnie Coasts Cartography Cartouches\n Ornamental (Decorative arts)\n\n  subject_terms_4: Australia (nation) India (nation) East Indies (general region) Southeast Asia (general region)\n\n  sgcool_label_text: This map of Southeast Asia by Nicolas Visscher was printed in the early 18th century by Pieter Schenk. It depicts the sphere of influence of the Dutch East India Company\n spanning from India to the northern coastline of Australia. The focus\n however\n is that of the East Indies around which the spice trade was centred.\n",
  "createdDate": "20201201203307",
  "version": 0,
  "latest": false,
  "roles": [],
  "metadata": {
    "accession_no_csv": "2018-00062",
    "Image": "",
    "object_work_type": "maps (documents) pictorial maps",
    "title_text": "Visscher\u0027s Map of Southeast Asia published by Pieter Schenk",
    "preference": "main",
    "title_language": "",
    "creator_2": "Nicolas Visscher I Pieter Schenk Jr",
    "creator_1": "not indicated",
    "creator_role": "publishers cartographers",
    "creation_date": "Early 18th century",
    "creation_place_original_location": "not indicated",
    "styles_periods_indexing_terms": "not indicated",
    "inscriptions": "",
    "inscription_language": "",
    "scale_type": "The scale of the map is in miles.",
    "shape": "rectangular",
    "materials_name": "paper (fiber product)",
    "techniques_name": "papermaking copper engraving (printing process) hand coloring",
    "object_colour": "multicoloured",
    "physical_appearance": "This is a multicoloured map of Southeast Asia, created by Nicolas Visscher I and published by Pieter Schenk Jr. There are many words at the top of the map, highlighting the names of places in Southeast Asia where the Dutch East India Company (VOC) extended their control over trade activities. The bottom of the map has lines of text that represent the title and scale of the map.",
    "subject_terms_1": "coastlines trade (general function) cartouches (ornament) cartography (discipline)",
    "subject_terms_2": "Australia Pictorial maps India Spice trade Southeast Asia East Indies Nederlandsche Oost-Indische Compagnie Coasts Cartography Cartouches, Ornamental (Decorative arts)",
    "subject_terms_4": "Australia (nation) India (nation) East Indies (general region) Southeast Asia (general region)",
    "sgcool_label_text": "This map of Southeast Asia by Nicolas Visscher was printed in the early 18th century by Pieter Schenk. It depicts the sphere of influence of the Dutch East India Company, spanning from India to the northern coastline of Australia. The focus, however, is that of the East Indies around which the spice trade was centred."
  },
  "nlpDate": "20201201203307",
  "connectorId": 0,
  "tags": {}
}