{
  "id": "2018-00468",
  "title": "Kallang Basin Singapore",
  "source": "Bumblebee",
  "path": "./Data/json/",
  "content": "\n  accession_no_csv: 2018-00468\n\n  Image: \n\n  object_work_type: drawings (visual works)\n\n  title_text: Kallang Basin Singapore\n\n  preference: main\n\n  title_language: \n\n  creator_2: Choon Ghee Tan\n\n  creator_1: Tan\n Choon Ghee\n 1930- Tan\n Choon Ghee\n\n  creator_role: artists (visual artists)\n\n  creation_date: 1964\n\n  creation_place_original_location: Pulau Pinang (state) Singapore (nation)\n\n  styles_periods_indexing_terms: Not indicated\n\n  inscriptions: \n\n  inscription_language: \n\n  scale_type: Not indicated\n\n  shape: rectangular\n\n  materials_name: paper (fiber product) ink\n\n  techniques_name: drawing (image-making) creating (artistic activity)\n\n  object_colour: grey (colour)\n\n  physical_appearance: \\The image shows a painting. It is rectangular in shape. The lines drawn are all black in colour. Numerous boats can be seen atop the body of water\n with several masts and poles appearing in the background of the painting. The title\n signature\n and year\n \\\\Kallang Basin S\\u0027pore\n\n  subject_terms_1: basins (landforms) Tan. 1964\\\\ is stated at the bottom right hand side. \\ boats\n\n  subject_terms_2: Boats and boating Bodies of water bodies of water (natural) Kallang Basin (Singapore)\n\n  subject_terms_3: Drawings Visual arts Water catchment areas\n\n  subject_terms_4: Drawing\n\n  context_1: Singapore (nation)\n",
  "createdDate": "20201201203307",
  "version": 0,
  "latest": false,
  "roles": [],
  "metadata": {
    "accession_no_csv": "2018-00468",
    "Image": "",
    "object_work_type": "drawings (visual works)",
    "title_text": "Kallang Basin Singapore",
    "preference": "main",
    "title_language": "",
    "creator_2": "Choon Ghee Tan",
    "creator_1": "Tan, Choon Ghee, 1930- Tan, Choon Ghee",
    "creator_role": "artists (visual artists)",
    "creation_date": "1964",
    "creation_place_original_location": "Pulau Pinang (state) Singapore (nation)",
    "styles_periods_indexing_terms": "Not indicated",
    "inscriptions": "",
    "inscription_language": "",
    "scale_type": "Not indicated",
    "shape": "rectangular",
    "materials_name": "paper (fiber product) ink",
    "techniques_name": "drawing (image-making) creating (artistic activity)",
    "object_colour": "grey (colour)",
    "physical_appearance": "\"The image shows a painting. It is rectangular in shape. The lines drawn are all black in colour. Numerous boats can be seen atop the body of water, with several masts and poles appearing in the background of the painting. The title, signature, and year, \"\"Kallang Basin S\u0027pore",
    "subject_terms_1": "basins (landforms) Tan. 1964\"\" is stated at the bottom right hand side. \" boats",
    "subject_terms_2": "Boats and boating Bodies of water bodies of water (natural) Kallang Basin (Singapore)",
    "subject_terms_3": "Drawings Visual arts Water catchment areas",
    "subject_terms_4": "Drawing",
    "context_1": "Singapore (nation)"
  },
  "nlpDate": "20201201203307",
  "connectorId": 0,
  "tags": {}
}