{"id":"2018-00053-002","title":"The Frame: Artists\u0027 Proof The Frame","source":"Bumblebee","path":"./Data/json/","content":"accession_no_csv:2018-00053-002\nImage:\nobject_work_type:artists\\u0027 proofs proofs (prints by function)\ntitle_text:The Frame: Artists\\u0027 Proof The Frame\npreference:main alternate\ntitle_language:\ncreator_2:Tan Lip Seng\ncreator_1:Tan\n Lip Seng\n 1942- Tan\n Lip Seng\ncreator_role:photographers\ncreation_date:1974\ncreation_place_original_location:Singapore (nation)\nstyles_periods_indexing_terms:Not indicated\ninscriptions:\ninscription_language:\nscale_type:Not indicated\nshape:rectangular\nmaterials_name:metallic paper\ntechniques_name:printing (process) montage (image-making technique)\nobject_colour:multicoloured\nedition_description:1 of 3\nphysical_appearance:The image shows an artist\\u0027s proof. It is rectangular in shape. The background of the artist\\u0027s proof is blue in colour. It depicts two ladies and a horse. One of the lady is sitting on a horse with her helmet on\n while the other lady stands beside them with her helmet in her hands. The rest of the photograph is fragmented into rectangles\n as a result of horizontal and vertical black lines aligning to form a mesh pattern.\nsubject_terms_1:Equus caballus (species) women (female humans) polo clubs (built complexes)\nsubject_terms_2:Proofs (Printing) Polo ponies Women Polo\nsubject_terms_3:Women Singapore Polo Club Photography\nsgcool_label_text:The Frame (1974) is an example of one of Tan Lip Seng\\u0027s many experiments with colour photography. This photograph was taken at the Singapore Polo Club (next to the old Police Academy along) and the silhouetted frame in the foreground of the photograph was produced from laying a wire mesh over the transparency slide. \\r\\n\\r\\nTan spent 42 years as a medical photographer at the National University of Singapore. Many of his works have won numerous awards internationally and show a strong graphic and stylistic sensibility. Tan is also the first Singaporean to be awarded a fellowship by the Royal Photographic Society of the United Kingdom in 1970. Conferred the Cultural Medallion in 1985\n Tan recently published a retrospective of his works\n ‘Light \\u0026 Shadow: Tan Lip Seng’s 50 Years of Photography’ in 2009.","createdDate":"20201018182637","version":0,"latest":false,"roles":[],"metadata":{"accession_no_csv":"2018-00053-002","Image":"","object_work_type":"artists\u0027 proofs proofs (prints by function)","title_text":"The Frame: Artists\u0027 Proof The Frame","preference":"main alternate","title_language":"","creator_2":"Tan Lip Seng","creator_1":"Tan, Lip Seng, 1942- Tan, Lip Seng","creator_role":"photographers","creation_date":"1974","creation_place_original_location":"Singapore (nation)","styles_periods_indexing_terms":"Not indicated","inscriptions":"","inscription_language":"","scale_type":"Not indicated","shape":"rectangular","materials_name":"metallic paper","techniques_name":"printing (process) montage (image-making technique)","object_colour":"multicoloured","edition_description":"1 of 3","physical_appearance":"The image shows an artist\u0027s proof. It is rectangular in shape. The background of the artist\u0027s proof is blue in colour. It depicts two ladies and a horse. One of the lady is sitting on a horse with her helmet on, while the other lady stands beside them with her helmet in her hands. The rest of the photograph is fragmented into rectangles, as a result of horizontal and vertical black lines aligning to form a mesh pattern.","subject_terms_1":"Equus caballus (species) women (female humans) polo clubs (built complexes)","subject_terms_2":"Proofs (Printing) Polo ponies Women Polo","subject_terms_3":"Women Singapore Polo Club Photography","sgcool_label_text":"The Frame (1974) is an example of one of Tan Lip Seng\u0027s many experiments with colour photography. This photograph was taken at the Singapore Polo Club (next to the old Police Academy along) and the silhouetted frame in the foreground of the photograph was produced from laying a wire mesh over the transparency slide. \r\n\r\nTan spent 42 years as a medical photographer at the National University of Singapore. Many of his works have won numerous awards internationally and show a strong graphic and stylistic sensibility. Tan is also the first Singaporean to be awarded a fellowship by the Royal Photographic Society of the United Kingdom in 1970. Conferred the Cultural Medallion in 1985, Tan recently published a retrospective of his works, ‘Light \u0026 Shadow: Tan Lip Seng’s 50 Years of Photography’ in 2009."},"nlpDate":"20201018182637","connectorId":0,"tags":{}}