{
  "id": "2018-00415",
  "title": "Not titled (Pulau Saigon with a view of Supreme Court)",
  "source": "Bumblebee",
  "path": "./Data/json/",
  "content": "\n  accession_no_csv: 2018-00415\n\n  Image: \n\n  object_work_type: watercolours (paintings)\n\n  title_text: Not titled (Pulau Saigon with a view of Supreme Court)\n\n  preference: main\n\n  title_language: \n\n  creator_2: Cheng Hoe Lim (1912 - 1979)\n\n  creator_1: Lim\n Cheng Hoe Lin\n Qinghe\n 1912-1979\n\n  creator_role: watercolourists\n\n  creation_date: 1971\n\n  creation_place_original_location: Singapore (nation)\n\n  styles_periods_indexing_terms: Not indicated\n\n  inscriptions: \n\n  inscription_language: \n\n  scale_type: Not indicated\n\n  shape: rectangular\n\n  materials_name: paper (fiber product) gouache (paint)\n\n  techniques_name: gouache (technique) watercolour painting (technique)\n\n  object_colour: multicoloured\n\n  physical_appearance: The image shows a watercolour painting. The painting depicts a view of the Singpaore river in the foreground. There are several boats on the river. There is a bridge joining the river banks\n where houses and high-rise flats occupy. In the background of the painting\n the cupola of the former Supreme court is visible.\n\n  subject_terms_1: islands (landforms) national monuments bridges (built works) rivers courthouses boats\n\n  subject_terms_2: Singapore River (Singapore) Boats and boating National monuments Appellate courts Saigon Island (Singapore) Bridges Watercolour painting\n\n  subject_terms_3: Pulau Saigon National monuments Watercolour Painting Pulau Saigon Bridge Visual arts Former Supreme Court (Singapore) Singapore River\n\n  subject_terms_4: Singapore River (river)\n\n  sgcool_label_text: Lim Cheng Hoe is attributed as a pioneering artists who specialized in the medium of watercolour. He was a founding member of Singapore Watercolour Society since its inauguration in 1969.\\r\\n\\r\\nLim Cheng Hoe regarded himself as a self-taught artist as his only exposure to art education was when he received art instruction from Richard Walker as a student at Raflles Institution. Nonetheless\n he was respected by his peers and juniors for his mastery of the watercolour medium. Notable artists such as Ong Kim Seng and Gog Sing Hooi highly regarded him as their mentor.\\r\\n\\r\\nWhile he exhibited in shows organised and/or facilitated by the Singapore Art Society\n YMCA Art Club and Singapore Watercolour society\n Lim never had a solo exhibition during his lifetime. His first solo exhibition was presented by the Singapore Watercolour Society in 1980 following his demise in 1979.\\r\\n\\r\\nHis paintings can be found in the collections of the National Heritage Board\n Monetary Authority of Singapore\n Balai Seni Visual Negara and other private organisations and individuals.\n",
  "createdDate": "20201125084507",
  "version": 0,
  "latest": false,
  "roles": [],
  "metadata": {
    "accession_no_csv": "2018-00415",
    "Image": "",
    "object_work_type": "watercolours (paintings)",
    "title_text": "Not titled (Pulau Saigon with a view of Supreme Court)",
    "preference": "main",
    "title_language": "",
    "creator_2": "Cheng Hoe Lim (1912 - 1979)",
    "creator_1": "Lim, Cheng Hoe Lin, Qinghe, 1912-1979",
    "creator_role": "watercolourists",
    "creation_date": "1971",
    "creation_place_original_location": "Singapore (nation)",
    "styles_periods_indexing_terms": "Not indicated",
    "inscriptions": "",
    "inscription_language": "",
    "scale_type": "Not indicated",
    "shape": "rectangular",
    "materials_name": "paper (fiber product) gouache (paint)",
    "techniques_name": "gouache (technique) watercolour painting (technique)",
    "object_colour": "multicoloured",
    "physical_appearance": "The image shows a watercolour painting. The painting depicts a view of the Singpaore river in the foreground. There are several boats on the river. There is a bridge joining the river banks, where houses and high-rise flats occupy. In the background of the painting, the cupola of the former Supreme court is visible.",
    "subject_terms_1": "islands (landforms) national monuments bridges (built works) rivers courthouses boats",
    "subject_terms_2": "Singapore River (Singapore) Boats and boating National monuments Appellate courts Saigon Island (Singapore) Bridges Watercolour painting",
    "subject_terms_3": "Pulau Saigon National monuments Watercolour Painting Pulau Saigon Bridge Visual arts Former Supreme Court (Singapore) Singapore River",
    "subject_terms_4": "Singapore River (river)",
    "sgcool_label_text": "Lim Cheng Hoe is attributed as a pioneering artists who specialized in the medium of watercolour. He was a founding member of Singapore Watercolour Society since its inauguration in 1969.\r\n\r\nLim Cheng Hoe regarded himself as a self-taught artist as his only exposure to art education was when he received art instruction from Richard Walker as a student at Raflles Institution. Nonetheless, he was respected by his peers and juniors for his mastery of the watercolour medium. Notable artists such as Ong Kim Seng and Gog Sing Hooi highly regarded him as their mentor.\r\n\r\nWhile he exhibited in shows organised and/or facilitated by the Singapore Art Society, YMCA Art Club and Singapore Watercolour society, Lim never had a solo exhibition during his lifetime. His first solo exhibition was presented by the Singapore Watercolour Society in 1980 following his demise in 1979.\r\n\r\nHis paintings can be found in the collections of the National Heritage Board, Monetary Authority of Singapore, Balai Seni Visual Negara and other private organisations and individuals."
  },
  "nlpDate": "20201125084507",
  "connectorId": 0,
  "tags": {}
}