{"id":"2018-00027","title":"Cover of Drawing Book of Han Hong Yoe Drawing Book of Han Hong Yoe","source":"Bumblebee","path":"./Data/json/","content":"accession_no_csv:2018-00027\nImage:\nobject_work_type:hardcover books\ntitle_text:Cover of Drawing Book of Han Hong Yoe Drawing Book of Han Hong Yoe\npreference:main alternate\ntitle_language:\ncreator_2:Han Hong Yoe\ncreator_1:Not indicated\ncreator_role:authors\ncreation_date:early 20th century\ncreation_place_original_location:Malang (inhabited place)\ninscriptions:\ninscription_language:\nshape:rectangular\nmaterials_name:printing paper book cloth (textile material)\ntechniques_name:colour printing bookbinding (process) illustration (process)\nobject_colour:multicoloured\nphysical_appearance:\\The image shows the front cover of a hardcover book. It has a blue background with a grey spine. At the top centre of the front cover\n \\\\Copy-Boek\\\\ is stated. The front cover looks slightly worn out and scratched\nsubject_terms_1:and some of the pages look to be torn apart from its spine. \\ drawings (visual wotks) flower (motif)\nsubject_terms_2:illustrated books Drawings Motifs\nsubject_terms_3:Drawing books\nsubject_terms_4:Drawing","createdDate":"20201018182637","version":0,"latest":false,"roles":[],"metadata":{"accession_no_csv":"2018-00027","Image":"","object_work_type":"hardcover books","title_text":"Cover of Drawing Book of Han Hong Yoe Drawing Book of Han Hong Yoe","preference":"main alternate","title_language":"","creator_2":"Han Hong Yoe","creator_1":"Not indicated","creator_role":"authors","creation_date":"early 20th century","creation_place_original_location":"Malang (inhabited place)","inscriptions":"","inscription_language":"","shape":"rectangular","materials_name":"printing paper book cloth (textile material)","techniques_name":"colour printing bookbinding (process) illustration (process)","object_colour":"multicoloured","physical_appearance":"\"The image shows the front cover of a hardcover book. It has a blue background with a grey spine. At the top centre of the front cover, \"\"Copy-Boek\"\" is stated. The front cover looks slightly worn out and scratched","subject_terms_1":"and some of the pages look to be torn apart from its spine. \" drawings (visual wotks) flower (motif)","subject_terms_2":"illustrated books Drawings Motifs","subject_terms_3":"Drawing books","subject_terms_4":"Drawing"},"nlpDate":"20201018182637","connectorId":0,"tags":{}}