{"id":"2018-00475","title":"Rotterdam","source":"Bumblebee","path":"./Data/json/","content":"accession_no_csv:2018-00475\nImage:\nobject_work_type:watercolours (paintings) paintings (visual works)\ntitle_text:Rotterdam\npreference:main\ntitle_language:\ncreator_2:Choon Ghee Tan\ncreator_1:Tan\n Choon Ghee\n 1930- Tan\n Choon Ghee\ncreator_role:artists (visual artists)\ncreation_date:1960\ncreation_place_original_location:Singapore (nation) Pulau Pinang (state)\nstyles_periods_indexing_terms:Not indicated\ninscriptions:\ninscription_language:\nscale_type:Not indicated\nshape:rectangular\nmaterials_name:paper (fiber product) watercolour (paint)\ntechniques_name:watercolour painting (technique) creating (artistic activity)\nobject_colour:multicoloured\nphysical_appearance:\\The image shows a painting. It is rectangular in shape. The foreground of the painting shows a body of water. Boats can be seen on the body of water. The background shows the skyline of a series of buildings by the body of water. The buildings in the centre of the painting have spires of different lengths and the one of the buildings to the left has a triangular roof. The location\n signature and year\n \\\\Choon Ngee. 1960\nsubject_terms_1:Venice\\\\ boats cityscapes (representations) rivers\nsubject_terms_2:is stated at the bottom right hand side. \\ rivers Buildings Boats and boating Rotterdam (Netherlands) Cultural landscapes\nsubject_terms_3:buildings (structures) Visual arts Waterways Buildings\nsubject_terms_4:Watercolour painting\ncontext_1:Watercolour Painting\ncontext_2:Rotterdam (inhabited place)","createdDate":"20201018182637","version":0,"latest":false,"roles":[],"metadata":{"accession_no_csv":"2018-00475","Image":"","object_work_type":"watercolours (paintings) paintings (visual works)","title_text":"Rotterdam","preference":"main","title_language":"","creator_2":"Choon Ghee Tan","creator_1":"Tan, Choon Ghee, 1930- Tan, Choon Ghee","creator_role":"artists (visual artists)","creation_date":"1960","creation_place_original_location":"Singapore (nation) Pulau Pinang (state)","styles_periods_indexing_terms":"Not indicated","inscriptions":"","inscription_language":"","scale_type":"Not indicated","shape":"rectangular","materials_name":"paper (fiber product) watercolour (paint)","techniques_name":"watercolour painting (technique) creating (artistic activity)","object_colour":"multicoloured","physical_appearance":"\"The image shows a painting. It is rectangular in shape. The foreground of the painting shows a body of water. Boats can be seen on the body of water. The background shows the skyline of a series of buildings by the body of water. The buildings in the centre of the painting have spires of different lengths and the one of the buildings to the left has a triangular roof. The location, signature and year, \"\"Choon Ngee. 1960","subject_terms_1":"Venice\"\" boats cityscapes (representations) rivers","subject_terms_2":"is stated at the bottom right hand side. \" rivers Buildings Boats and boating Rotterdam (Netherlands) Cultural landscapes","subject_terms_3":"buildings (structures) Visual arts Waterways Buildings","subject_terms_4":"Watercolour painting","context_1":"Watercolour Painting","context_2":"Rotterdam (inhabited place)"},"nlpDate":"20201018182637","connectorId":0,"tags":{}}