{"id":"2018-00466","title":"Untitled (Singapore, 1963)","source":"Bumblebee","path":"./Data/json/","content":"accession_no_csv:2018-00466\nImage:\nobject_work_type:drawings (visual works)\ntitle_text:Untitled (Singapore\n 1963)\npreference:main\ntitle_language:\ncreator_2:Choon Ghee Tan\ncreator_1:Tan\n Choon Ghee\n 1930- Tan\n Choon Ghee\ncreator_role:artists (visual artists)\ncreation_date:1963\ncreation_place_original_location:Pulau Pinang (state) Singapore (nation)\nstyles_periods_indexing_terms:Not indicated\ninscriptions:\ninscription_language:\nscale_type:Not indicated\nshape:rectangular\nmaterials_name:paper (fiber product) ink\ntechniques_name:creating (artistic activity) drawing (image-making)\nobject_colour:black (colour)\nphysical_appearance:The image shows a drawing. It is rectangular in shape. The lines drawn are all black in colour. There is a group of seated figures in the background. There are sitting around a table\n under a shelter. At the foreground outside the shelter\n a figure stands and looks towards the seated group of people. There are numerous items on the table between the standing figure and the seated people. Several pails can be seen on the ground as well.\nsubject_terms_1:seated figures figures (representation)\nsubject_terms_2:Drawings Singapore\nsubject_terms_3:Drawing\nsubject_terms_4:Singapore (nation)\nsgcool_label_text:Tan Choon Ghee was born in Penang in 1930. He travelled to Singapore in the late 1940s to enrol at the Nanyang Academy of Fine Arts (NAFA)\n graduating in 1951. He went on to further his studies at the Slade School of Fine Art in London from 1957-1959. He was subsequently awarded a scholarship from the German government to study art in Germany. During this time\n he travelled extensively in Europe before returning to Penang to settle in 1969.\\r\\n\\r\\nTan is noted as being influenced by fellow Penang-based artist Kuo Ju Ping (1908-1966)\n who had graduated from NAFA earlier in 1940\n as well as other masters of his favoured medium of watercolour\n such as Yong Mun Sen (1896-1962) and Abdullah Ariff (1904-1962).\\r\\n\\r\\nAs a key second generation artist working primarily in the medium of watercolour\n Tan is known for his deft application of ink and colour on paper. During his frequest visits to Singapore\n he was drawn towards depicting the bustling activity of the Singapore port and the workmen and everyday characters that populated his scenes.","createdDate":"20201119143407","version":0,"latest":false,"roles":[],"metadata":{"accession_no_csv":"2018-00466","Image":"","object_work_type":"drawings (visual works)","title_text":"Untitled (Singapore, 1963)","preference":"main","title_language":"","creator_2":"Choon Ghee Tan","creator_1":"Tan, Choon Ghee, 1930- Tan, Choon Ghee","creator_role":"artists (visual artists)","creation_date":"1963","creation_place_original_location":"Pulau Pinang (state) Singapore (nation)","styles_periods_indexing_terms":"Not indicated","inscriptions":"","inscription_language":"","scale_type":"Not indicated","shape":"rectangular","materials_name":"paper (fiber product) ink","techniques_name":"creating (artistic activity) drawing (image-making)","object_colour":"black (colour)","physical_appearance":"The image shows a drawing. It is rectangular in shape. The lines drawn are all black in colour. There is a group of seated figures in the background. There are sitting around a table, under a shelter. At the foreground outside the shelter, a figure stands and looks towards the seated group of people. There are numerous items on the table between the standing figure and the seated people. Several pails can be seen on the ground as well.","subject_terms_1":"seated figures figures (representation)","subject_terms_2":"Drawings Singapore","subject_terms_3":"Drawing","subject_terms_4":"Singapore (nation)","sgcool_label_text":"Tan Choon Ghee was born in Penang in 1930. He travelled to Singapore in the late 1940s to enrol at the Nanyang Academy of Fine Arts (NAFA), graduating in 1951. He went on to further his studies at the Slade School of Fine Art in London from 1957-1959. He was subsequently awarded a scholarship from the German government to study art in Germany. During this time, he travelled extensively in Europe before returning to Penang to settle in 1969.\r\n\r\nTan is noted as being influenced by fellow Penang-based artist Kuo Ju Ping (1908-1966), who had graduated from NAFA earlier in 1940, as well as other masters of his favoured medium of watercolour, such as Yong Mun Sen (1896-1962) and Abdullah Ariff (1904-1962).\r\n\r\nAs a key second generation artist working primarily in the medium of watercolour, Tan is known for his deft application of ink and colour on paper. During his frequest visits to Singapore, he was drawn towards depicting the bustling activity of the Singapore port and the workmen and everyday characters that populated his scenes."},"nlpDate":"20201119143407","connectorId":0,"tags":{}}