{"id":"2018-00118","title":"Studio portrait of a nyonya and a girl","source":"Bumblebee","path":"./Data/json/","content":"accession_no_csv:2018-00118\nImage:\nobject_work_type:black-and-white photographs photographs\ntitle_text:Studio portrait of a nyonya and a girl\npreference:main\ntitle_language:\ncreator_2:G.R. Lambert \\u0026 Company\ncreator_1:G.R. Lambert \\u0026 Co.\ncreator_role:photography studios (organizations)\ncreation_date:1870s\ncreation_place_original_location:Singapore (nation)\ninscriptions:\ninscription_language:\nshape:rectangular\nmaterials_name:paper (fiber product)\ntechniques_name:printing (process) photographic processes\nobject_colour:grey monochrome\nphysical_appearance:The image shows a black-and-white photograph. It is rectangular and it features a lady and  female child. The lady is sitting down while the child is standing to her right. Both of them are wearing their ethnic costumes. The lady is sitting beside a pillar\n which is at the left hand side of the photograph.\nsubject_terms_1:studio portraits double portraits women (female humans) Peranakan folk costume children (people by age group)\nsubject_terms_2:Black-and-white photography Portrait photography Women Ethnic costume Peranakan (Asian people) Children\nsubject_terms_3:Portrait photography Women Peranakan costumes Children\nsgcool_label_text:This studio photograph shows a nyonya and a girl with a table between them. This photograph was probably taken by G.R. Lambert and Co.\\r\\n\\r\\nG.R. Lambert and Co was a leading and the most enduring of the European photography studios in Singapore. The studio was established in 1867 by Gustave Richard Lambert\n who was originally from Dresden\n Germany. Popular among the elites\n the firm was often chosen as the official photographers for important state events in Singapore. In 1861 it was appointed as the official photographer of the King of Siam and the Sultan of Johore.","createdDate":"20201018182637","version":0,"latest":false,"roles":[],"metadata":{"accession_no_csv":"2018-00118","Image":"","object_work_type":"black-and-white photographs photographs","title_text":"Studio portrait of a nyonya and a girl","preference":"main","title_language":"","creator_2":"G.R. Lambert \u0026 Company","creator_1":"G.R. Lambert \u0026 Co.","creator_role":"photography studios (organizations)","creation_date":"1870s","creation_place_original_location":"Singapore (nation)","inscriptions":"","inscription_language":"","shape":"rectangular","materials_name":"paper (fiber product)","techniques_name":"printing (process) photographic processes","object_colour":"grey monochrome","physical_appearance":"The image shows a black-and-white photograph. It is rectangular and it features a lady and  female child. The lady is sitting down while the child is standing to her right. Both of them are wearing their ethnic costumes. The lady is sitting beside a pillar, which is at the left hand side of the photograph.","subject_terms_1":"studio portraits double portraits women (female humans) Peranakan folk costume children (people by age group)","subject_terms_2":"Black-and-white photography Portrait photography Women Ethnic costume Peranakan (Asian people) Children","subject_terms_3":"Portrait photography Women Peranakan costumes Children","sgcool_label_text":"This studio photograph shows a nyonya and a girl with a table between them. This photograph was probably taken by G.R. Lambert and Co.\r\n\r\nG.R. Lambert and Co was a leading and the most enduring of the European photography studios in Singapore. The studio was established in 1867 by Gustave Richard Lambert, who was originally from Dresden, Germany. Popular among the elites, the firm was often chosen as the official photographers for important state events in Singapore. In 1861 it was appointed as the official photographer of the King of Siam and the Sultan of Johore."},"nlpDate":"20201018182637","connectorId":0,"tags":{}}