{
  "id": "2018-00196-068",
  "title": "Booklet of film negatives Booklet of film negatives: Negative of a statue of Guanyin",
  "source": "Bumblebee",
  "path": "./Data/json/",
  "content": "\n  accession_no_csv: 2018-00196-068\n\n  Image: \n\n  object_work_type: negatives (photographs)\n\n  title_text: Booklet of film negatives Booklet of film negatives: Negative of a statue of Guanyin\n\n  preference: alternate\n\n  title_language: \n\n  creator_2: Not indicated\n\n  creator_1: Not indicated\n\n  creation_date: 1950s\n\n  creation_place_original_location: Singapore (nation)\n\n  inscriptions: \n\n  inscription_language: \n\n  shape: rectangular\n\n  materials_name: paper (fiber product)\n\n  techniques_name: printing (process)\n\n  object_colour: grey monochrome\n\n  physical_appearance: \n\n  subject_terms_1: statues Buddhism bodhisattvas\n\n  subject_terms_2: Avalokite?vara (Buddhist deity) Statues\n\n  subject_terms_3: Photography Buddhism\n\n  sgcool_label_text: This booklet contains film negatives. \\r\\n\n",
  "createdDate": "20201125084507",
  "version": 0,
  "latest": false,
  "roles": [],
  "metadata": {
    "accession_no_csv": "2018-00196-068",
    "Image": "",
    "object_work_type": "negatives (photographs)",
    "title_text": "Booklet of film negatives Booklet of film negatives: Negative of a statue of Guanyin",
    "preference": "alternate",
    "title_language": "",
    "creator_2": "Not indicated",
    "creator_1": "Not indicated",
    "creation_date": "1950s",
    "creation_place_original_location": "Singapore (nation)",
    "inscriptions": "",
    "inscription_language": "",
    "shape": "rectangular",
    "materials_name": "paper (fiber product)",
    "techniques_name": "printing (process)",
    "object_colour": "grey monochrome",
    "physical_appearance": "",
    "subject_terms_1": "statues Buddhism bodhisattvas",
    "subject_terms_2": "Avalokite?vara (Buddhist deity) Statues",
    "subject_terms_3": "Photography Buddhism",
    "sgcool_label_text": "This booklet contains film negatives. \r\n"
  },
  "nlpDate": "20201125084507",
  "connectorId": 0,
  "tags": {}
}