{"id":"2018-00158","title":"Photograph of a group of Europeans in the verandah of a colonial house A group of Europeans in the verandah of a colonial house","source":"Bumblebee","path":"./Data/json/","content":"accession_no_csv:2018-00158\nImage:\nobject_work_type:black-and-white photographs photographs\ntitle_text:Photograph of a group of Europeans in the verandah of a colonial house A group of Europeans in the verandah of a colonial house\npreference:main alternate\ntitle_language:\ncreator_2:Not indicated\ncreator_1:Not indicated\ncreation_date:Late 19th centiury / early 1900s\ncreation_place_original_location:Java (island)\ninscriptions:\ninscription_language:\nshape:rectangular\nmaterials_name:paper (fiber product)\ntechniques_name:printing (process) photographic processes\nobject_colour:grey monochrome\nphysical_appearance:The image shows a black-and-white photograph. It is rectangular and it features an image of a bungalow.  It is situated in the background of the photograph. There are groups of people standing in the verandah of the bungalow and sitting on its front steps.\nsubject_terms_1:families (kinship groups) servants bungalows\nsubject_terms_2:Black-and-white photography Families Household employees Bungalows Architecture\n Colonial Europeans\nsubject_terms_3:Photography Colonial architecture\nsgcool_label_text:This photograph shows a colonial bungalow with family and servants posing on the veranda.The European men are dressed in white cotton drill jackets known as ‘jas tutup’ (“closed coat”) and matching trousers\n or white shirts paired with batik trousers.\\r\\n\\r\\nWith continuous improvement of camera technology\n it became possible to take photographs outside a studio in the first decades of the 20th century. Many middle-class families collected photographs in albums as a way of documenting family life\n or documentasi keluarga.","createdDate":"20201119143407","version":0,"latest":false,"roles":[],"metadata":{"accession_no_csv":"2018-00158","Image":"","object_work_type":"black-and-white photographs photographs","title_text":"Photograph of a group of Europeans in the verandah of a colonial house A group of Europeans in the verandah of a colonial house","preference":"main alternate","title_language":"","creator_2":"Not indicated","creator_1":"Not indicated","creation_date":"Late 19th centiury / early 1900s","creation_place_original_location":"Java (island)","inscriptions":"","inscription_language":"","shape":"rectangular","materials_name":"paper (fiber product)","techniques_name":"printing (process) photographic processes","object_colour":"grey monochrome","physical_appearance":"The image shows a black-and-white photograph. It is rectangular and it features an image of a bungalow.  It is situated in the background of the photograph. There are groups of people standing in the verandah of the bungalow and sitting on its front steps.","subject_terms_1":"families (kinship groups) servants bungalows","subject_terms_2":"Black-and-white photography Families Household employees Bungalows Architecture, Colonial Europeans","subject_terms_3":"Photography Colonial architecture","sgcool_label_text":"This photograph shows a colonial bungalow with family and servants posing on the veranda.The European men are dressed in white cotton drill jackets known as ‘jas tutup’ (“closed coat”) and matching trousers, or white shirts paired with batik trousers.\r\n\r\nWith continuous improvement of camera technology, it became possible to take photographs outside a studio in the first decades of the 20th century. Many middle-class families collected photographs in albums as a way of documenting family life, or documentasi keluarga."},"nlpDate":"20201119143407","connectorId":0,"tags":{}}