{"id":"2018-00147","title":"Photograph of four nyonyas and four children","source":"Bumblebee","path":"./Data/json/","content":"accession_no_csv:2018-00147\nImage:\nobject_work_type:black-and-white photographs photographs\ntitle_text:Photograph of four nyonyas and four children\npreference:main\ntitle_language:\ncreator_2:Not indicated\ncreator_1:Not indicated\ncreation_date:1870s-1890s\ncreation_place_original_location:Straits Settlement (former territory/colony/dependent state)\ninscriptions:\ninscription_language:\nshape:rectangular\nmaterials_name:paper (fiber product)\ntechniques_name:printing (process) photographic processes\nobject_colour:grey monochrome\nphysical_appearance:The image shows a black-and-white photograph. It is rectangular and it features four ladies and four children. Six of them are standing up and two of them are sitting down. All of them are looking towards the direction where the photograph was captured. They are dressed in theri ethnic costumes and some of them adorn headdresses. A lady in the centre who is sitting down is holding onto a child who is sitting on her lap.\nsubject_terms_1:studio portraits women (female humans) Peranakan folk costume group portraits children (people by age group)\nsubject_terms_2:Black-and-white photography Portrait photography Portraits\n Group Ethnic costume Peranakan (Asian people) Women Children\nsubject_terms_3:Portrait photography Women Peranakan costumes Children\nsgcool_label_text:This studio photograph shows a group of four nyonyas and four children posing before a painted backdrop of a Chinese landscape. \\r\\n\\r\\nStudios were already established across the Strait Settlements and the Dutch East Indies by the 1840s and became increasingly prevalent in the 1850s. During the 1920s\n Chinese-owned studios dominated the studio photography trade in Southeast Asia.","createdDate":"20201119143407","version":0,"latest":false,"roles":[],"metadata":{"accession_no_csv":"2018-00147","Image":"","object_work_type":"black-and-white photographs photographs","title_text":"Photograph of four nyonyas and four children","preference":"main","title_language":"","creator_2":"Not indicated","creator_1":"Not indicated","creation_date":"1870s-1890s","creation_place_original_location":"Straits Settlement (former territory/colony/dependent state)","inscriptions":"","inscription_language":"","shape":"rectangular","materials_name":"paper (fiber product)","techniques_name":"printing (process) photographic processes","object_colour":"grey monochrome","physical_appearance":"The image shows a black-and-white photograph. It is rectangular and it features four ladies and four children. Six of them are standing up and two of them are sitting down. All of them are looking towards the direction where the photograph was captured. They are dressed in theri ethnic costumes and some of them adorn headdresses. A lady in the centre who is sitting down is holding onto a child who is sitting on her lap.","subject_terms_1":"studio portraits women (female humans) Peranakan folk costume group portraits children (people by age group)","subject_terms_2":"Black-and-white photography Portrait photography Portraits, Group Ethnic costume Peranakan (Asian people) Women Children","subject_terms_3":"Portrait photography Women Peranakan costumes Children","sgcool_label_text":"This studio photograph shows a group of four nyonyas and four children posing before a painted backdrop of a Chinese landscape. \r\n\r\nStudios were already established across the Strait Settlements and the Dutch East Indies by the 1840s and became increasingly prevalent in the 1850s. During the 1920s, Chinese-owned studios dominated the studio photography trade in Southeast Asia."},"nlpDate":"20201119143407","connectorId":0,"tags":{}}