{
  "id": "2018-00047",
  "title": "Under Construction",
  "source": "Bumblebee",
  "path": "./Data/json/",
  "content": "\n  accession_no_csv: 2018-00047\n\n  Image: \n\n  object_work_type: digital prints artists\\u0027 proofs colour slides\n\n  title_text: Under Construction\n\n  preference: main\n\n  title_language: \n\n  creator_2: Tan Lip Seng\n\n  creator_1: Tan\n Lip Seng\n 1942- Tan\n Lip Seng\n\n  creator_role: photographers\n\n  creation_date: 1970\n\n  creation_place_original_location: Singapore (nation)\n\n  styles_periods_indexing_terms: Not indicated\n\n  inscriptions: \n\n  inscription_language: \n\n  scale_type: Not indicated\n\n  shape: rectangular\n\n  materials_name: photographic paper metallic paper photographic film (photographic materials)\n\n  techniques_name: printing (process) montage (image-making technique) photographic processes\n\n  object_colour: multicoloured\n\n  edition_description: 1 of 3\n\n  physical_appearance: \\The image shows a digital print\n an artist\\u0027s proof\n and a slide. They are rectangular in shape. The background of the digital print and artist\\u0027s proof are black in colour. They feature two construction workers at work. Both of them are wearing yellow helmets and gloves. They are standing at the top of a building structure\n and bending forwards with a wood plank in their hands. The image at the bottom shows a slide. It is in colour. It is held in place by a frame. On the borders of the frame\n \\\\Under Construction\\\\ is stated at the top for the image at the bottom. \\\\Tan Lip Seng\n\n  subject_terms_1: working prints (visual works) proofs (prints by function) A.R.P.S. AFIAP construction (assembling) slides (photographs)\n\n  subject_terms_2: Colour prints Slides (photography) Building Proofs (Printing) 96A Tiong Bahru Road. Singapore 3\\\\ is stated at the bottom for the image at the bottom. \\ Digitally printed materials Work\n\n  subject_terms_3: construction workers\n\n  subject_terms_4: Construction workers\n\n  context_1: Photography\n",
  "createdDate": "20201125084511",
  "version": 0,
  "latest": false,
  "roles": [],
  "metadata": {
    "accession_no_csv": "2018-00047",
    "Image": "",
    "object_work_type": "digital prints artists\u0027 proofs colour slides",
    "title_text": "Under Construction",
    "preference": "main",
    "title_language": "",
    "creator_2": "Tan Lip Seng",
    "creator_1": "Tan, Lip Seng, 1942- Tan, Lip Seng",
    "creator_role": "photographers",
    "creation_date": "1970",
    "creation_place_original_location": "Singapore (nation)",
    "styles_periods_indexing_terms": "Not indicated",
    "inscriptions": "",
    "inscription_language": "",
    "scale_type": "Not indicated",
    "shape": "rectangular",
    "materials_name": "photographic paper metallic paper photographic film (photographic materials)",
    "techniques_name": "printing (process) montage (image-making technique) photographic processes",
    "object_colour": "multicoloured",
    "edition_description": "1 of 3",
    "physical_appearance": "\"The image shows a digital print, an artist\u0027s proof, and a slide. They are rectangular in shape. The background of the digital print and artist\u0027s proof are black in colour. They feature two construction workers at work. Both of them are wearing yellow helmets and gloves. They are standing at the top of a building structure, and bending forwards with a wood plank in their hands. The image at the bottom shows a slide. It is in colour. It is held in place by a frame. On the borders of the frame, \"\"Under Construction\"\" is stated at the top for the image at the bottom. \"\"Tan Lip Seng",
    "subject_terms_1": "working prints (visual works) proofs (prints by function) A.R.P.S. AFIAP construction (assembling) slides (photographs)",
    "subject_terms_2": "Colour prints Slides (photography) Building Proofs (Printing) 96A Tiong Bahru Road. Singapore 3\"\" is stated at the bottom for the image at the bottom. \" Digitally printed materials Work",
    "subject_terms_3": "construction workers",
    "subject_terms_4": "Construction workers",
    "context_1": "Photography"
  },
  "nlpDate": "20201125084511",
  "connectorId": 0,
  "tags": {}
}