{
  "id": "2018-00137",
  "title": "Studio portrait of seated nyonya with two children",
  "source": "Bumblebee",
  "path": "./Data/json/",
  "content": "\n  accession_no_csv: 2018-00137\n\n  Image: \n\n  object_work_type: black-and-white photographs photographs\n\n  title_text: Studio portrait of seated nyonya with two children\n\n  preference: main\n\n  title_language: \n\n  creator_2: Not indicated\n\n  creator_1: Not indicated\n\n  creation_date: 1870s\n\n  creation_place_original_location: Singapore (nation)\n\n  inscriptions: \n\n  inscription_language: \n\n  shape: rectangular\n\n  materials_name: paper (fiber product)\n\n  techniques_name: printing (process) photographic processes\n\n  object_colour: grey monochrome\n\n  physical_appearance: The image shows a black-and-white photograph. It is rectangular and it features a lady and two children. The lady sits in the middle while the two children stand on either side. All of them are wearing their ethnic costumes\n and the children have their headdresses on but not the lady. The child on the right has a tasselled headdress.\n\n  subject_terms_1: studio portraits women (female humans) Peranakan folk costume children (people by age group)\n\n  subject_terms_2: Black-and-white photography Portrait photography Women Ethnic costume Peranakan (Asian people) Children\n\n  subject_terms_3: Portrait photography Women Peranakan costumes Children\n\n  sgcool_label_text: This studio portrait shows a seated nyonya in a baju panjang flanked by two boys wearing headdresses. \\r\\n\\r\\nStudios were already established across the Strait Settlements and the Dutch East Indies by the 1840s and became increasingly prevalent in the 1850s. During the 1920s\n Chinese-owned studios dominated the studio photography trade in Southeast Asia.\n",
  "createdDate": "20201120223708",
  "version": 0,
  "latest": false,
  "roles": [],
  "metadata": {
    "accession_no_csv": "2018-00137",
    "Image": "",
    "object_work_type": "black-and-white photographs photographs",
    "title_text": "Studio portrait of seated nyonya with two children",
    "preference": "main",
    "title_language": "",
    "creator_2": "Not indicated",
    "creator_1": "Not indicated",
    "creation_date": "1870s",
    "creation_place_original_location": "Singapore (nation)",
    "inscriptions": "",
    "inscription_language": "",
    "shape": "rectangular",
    "materials_name": "paper (fiber product)",
    "techniques_name": "printing (process) photographic processes",
    "object_colour": "grey monochrome",
    "physical_appearance": "The image shows a black-and-white photograph. It is rectangular and it features a lady and two children. The lady sits in the middle while the two children stand on either side. All of them are wearing their ethnic costumes, and the children have their headdresses on but not the lady. The child on the right has a tasselled headdress.",
    "subject_terms_1": "studio portraits women (female humans) Peranakan folk costume children (people by age group)",
    "subject_terms_2": "Black-and-white photography Portrait photography Women Ethnic costume Peranakan (Asian people) Children",
    "subject_terms_3": "Portrait photography Women Peranakan costumes Children",
    "sgcool_label_text": "This studio portrait shows a seated nyonya in a baju panjang flanked by two boys wearing headdresses. \r\n\r\nStudios were already established across the Strait Settlements and the Dutch East Indies by the 1840s and became increasingly prevalent in the 1850s. During the 1920s, Chinese-owned studios dominated the studio photography trade in Southeast Asia."
  },
  "nlpDate": "20201120223708",
  "connectorId": 0,
  "tags": {}
}