{
  "id": "2018-00406",
  "title": "Pumpkin ???",
  "source": "Bumblebee",
  "path": "./Data/json/",
  "content": "\n  accession_no_csv: 2018-00406\n\n  Image: \n\n  object_work_type: finger paintings (visual works)\n\n  title_text: Pumpkin ???\n\n  preference: main main\n\n  title_language: \n\n  creator_2: Tsai Yen Wu (1911 - 2001)\n\n  creator_1: Wu\n Zaiyan\n 1911-2001\n\n  creator_role: painters (artist)\n\n  creation_date: 1964\n\n  creation_place_original_location: Singapore (nation) Malay Peninsula\n\n  styles_periods_indexing_terms: Chinese (culture or style)\n\n  inscriptions: \n\n  inscription_language: \n\n  scale_type: Not indicated\n\n  shape: rectangular\n\n  materials_name: Chinese ink paint (coating) paper (fiber product)\n\n  techniques_name: creating (artistic activity) finger painting (technique)\n\n  object_colour: multicoloured\n\n  physical_appearance: The images show a painting. The image on the right contains a close-up of the painting in question\n while the image on the left hand side shows the same painting\n with its frames and white border visible. Images of pumpkins\n with leaves and thin branches\n are depicted in the painting. There are two vertical lines of Chinese characters on the left hand side of the painting.\n\n  subject_terms_1: symbolism (artistic concept) squash (gourd)\n\n  subject_terms_2: Paintings Symbolism Motifs Squashes\n\n  subject_terms_3: Painting Visual Arts\n\n  sgcool_label_text: Pumpkin is an exemplary work by Wu Tsai Yen that demonstrates his skilled execution and mastery of the finger-painting technique\n which traces its practice to the Tang Dynasty. At the same time\n this particular painting acts as a record of a visit Wu had. Shown in the inscription\n on a day during the start of the winter season in 1964\n Jiong Xi brought along some refined objects\n most likely antiques or curiosities of some sort\n during his meeting with Wu. It was an enjoyable time. \\r\\n\\r\\nWhile it is not known to us who Jiong Xi might be\n the choice of material and motif of this painting emblems the precious moment of friendship and in the changing season. The orange colour of the pumpkin and its swaying leaves gives off a translucent gleamy effect on the paper\n which carries specks of white\n silver\n and gold.\n",
  "createdDate": "20201120223709",
  "version": 0,
  "latest": false,
  "roles": [],
  "metadata": {
    "accession_no_csv": "2018-00406",
    "Image": "",
    "object_work_type": "finger paintings (visual works)",
    "title_text": "Pumpkin ???",
    "preference": "main main",
    "title_language": "",
    "creator_2": "Tsai Yen Wu (1911 - 2001)",
    "creator_1": "Wu, Zaiyan, 1911-2001",
    "creator_role": "painters (artist)",
    "creation_date": "1964",
    "creation_place_original_location": "Singapore (nation) Malay Peninsula",
    "styles_periods_indexing_terms": "Chinese (culture or style)",
    "inscriptions": "",
    "inscription_language": "",
    "scale_type": "Not indicated",
    "shape": "rectangular",
    "materials_name": "Chinese ink paint (coating) paper (fiber product)",
    "techniques_name": "creating (artistic activity) finger painting (technique)",
    "object_colour": "multicoloured",
    "physical_appearance": "The images show a painting. The image on the right contains a close-up of the painting in question, while the image on the left hand side shows the same painting, with its frames and white border visible. Images of pumpkins, with leaves and thin branches, are depicted in the painting. There are two vertical lines of Chinese characters on the left hand side of the painting.",
    "subject_terms_1": "symbolism (artistic concept) squash (gourd)",
    "subject_terms_2": "Paintings Symbolism Motifs Squashes",
    "subject_terms_3": "Painting Visual Arts",
    "sgcool_label_text": "Pumpkin is an exemplary work by Wu Tsai Yen that demonstrates his skilled execution and mastery of the finger-painting technique, which traces its practice to the Tang Dynasty. At the same time, this particular painting acts as a record of a visit Wu had. Shown in the inscription, on a day during the start of the winter season in 1964, Jiong Xi brought along some refined objects, most likely antiques or curiosities of some sort, during his meeting with Wu. It was an enjoyable time. \r\n\r\nWhile it is not known to us who Jiong Xi might be, the choice of material and motif of this painting emblems the precious moment of friendship and in the changing season. The orange colour of the pumpkin and its swaying leaves gives off a translucent gleamy effect on the paper, which carries specks of white, silver, and gold."
  },
  "nlpDate": "20201120223709",
  "connectorId": 0,
  "tags": {}
}