{
  "id": "2018-00015",
  "title": "Invisible Force",
  "source": "Bumblebee",
  "path": "./Data/json/",
  "content": "\n  accession_no_csv: 2018-00015\n\n  Image: \n\n  object_work_type: installations (visual works)\n\n  title_text: Invisible Force\n\n  preference: main\n\n  title_language: \n\n  creator_2: Ni Youyu\n\n  creator_1: Not indicated\n\n  creator_role: creators\n\n  creation_date: 2015\n\n  creation_place_original_location: China (nation)\n\n  styles_periods_indexing_terms: Not indicated\n\n  inscriptions: \n\n  inscription_language: \n\n  scale_type: Not indicated\n\n  shape: rectangular\n\n  materials_name: photographic paper steel (alloy) magnets mixed media\n\n  techniques_name: creating (artistic activity) photographic processes metalworking forming (physical activity)\n\n  object_colour: multicoloured\n\n  edition_description: Unique\n\n  physical_appearance: The image shows an installation. It is rectangular in shape. The background of the installation is black in colour. There are numerous bright specks scattered throughout the entire installation. The installation resembles stars in a dark sky.\n\n  subject_terms_1: sky stars (extraterrestial bodies) celestial space (astronomical concept) force (mechanical concept) mixed media works\n\n  subject_terms_2: Installations (Art) Constellations Stars Force and energy Derivative works\n\n  subject_terms_3: Installations (Art)\n\n  sgcool_label_text: Invisible Force reproduces part of the starry sky as photographed by NASA\n strictly in accordance with the location and the size of the stars\n by using nearly 30\n000 industrial magnets that weigh almost two tonnes. Through the use of magnets\n the work ingeniously represents the invisible gravitational forces between the celestial bodies.\n",
  "createdDate": "20201120223708",
  "version": 0,
  "latest": false,
  "roles": [],
  "metadata": {
    "accession_no_csv": "2018-00015",
    "Image": "",
    "object_work_type": "installations (visual works)",
    "title_text": "Invisible Force",
    "preference": "main",
    "title_language": "",
    "creator_2": "Ni Youyu",
    "creator_1": "Not indicated",
    "creator_role": "creators",
    "creation_date": "2015",
    "creation_place_original_location": "China (nation)",
    "styles_periods_indexing_terms": "Not indicated",
    "inscriptions": "",
    "inscription_language": "",
    "scale_type": "Not indicated",
    "shape": "rectangular",
    "materials_name": "photographic paper steel (alloy) magnets mixed media",
    "techniques_name": "creating (artistic activity) photographic processes metalworking forming (physical activity)",
    "object_colour": "multicoloured",
    "edition_description": "Unique",
    "physical_appearance": "The image shows an installation. It is rectangular in shape. The background of the installation is black in colour. There are numerous bright specks scattered throughout the entire installation. The installation resembles stars in a dark sky.",
    "subject_terms_1": "sky stars (extraterrestial bodies) celestial space (astronomical concept) force (mechanical concept) mixed media works",
    "subject_terms_2": "Installations (Art) Constellations Stars Force and energy Derivative works",
    "subject_terms_3": "Installations (Art)",
    "sgcool_label_text": "Invisible Force reproduces part of the starry sky as photographed by NASA, strictly in accordance with the location and the size of the stars, by using nearly 30,000 industrial magnets that weigh almost two tonnes. Through the use of magnets, the work ingeniously represents the invisible gravitational forces between the celestial bodies."
  },
  "nlpDate": "20201120223708",
  "connectorId": 0,
  "tags": {}
}