{"id":"2018-00633","title":"Tanjung Rhu Singapore","source":"Bumblebee","path":"./Data/json/","content":"accession_no_csv:2018-00633\nImage:\nobject_work_type:watercolours (paintings)\ntitle_text:Tanjung Rhu Singapore\npreference:main\ntitle_language:\ncreator_2:Idris Mohd Ali\ncreator_1:Idris Mohd Ali\n 1944- Idris Mohamed Ali\ncreator_role:painters (artist)\ncreation_date:1963\ncreation_place_original_location:Singapore (inhabited place)\nstyles_periods_indexing_terms:Not indicated\ninscriptions:\ninscription_language:\nscale_type:Not indicated\nshape:rectangular\nmaterials_name:paper (fiber product) gouache (paint) watercolour (paint)\ntechniques_name:watercolour painting (technique) gouache (technique)\nobject_colour:multicoloured\nphysical_appearance:The image shows a watercolour painting. The painting depicts several boats that are coloured brown\n on water. Each boat has a long mast extending from its centre. There are a couple of men on the decks of the boats. The outlines of birds can be discerned near the top of the painting\n beneath the sky. The name of the painting\n and the name of the artist are stated at the bottom right hand side of the painting. But the inscriptions are not clear enough to discern the exact wordings.\nsubject_terms_1:capes (landforms)  boats\nsubject_terms_2:Watercolour painting Capes (Coasts) Singapore Boats and boating\nsubject_terms_3:Watercolour Painting Visual arts Tanjong Rhu Heritage and Culture\nsgcool_label_text:Known for his watercolour landscapes and street scenes\n Idris Mohamed Ali’s works reveal a strong understanding of colour\n depth and realism. His paintings of old Singapore are especially important as they serve as a visual documentation of our national heritage. \\r\\nStarted painting at 10 and not being able to afford formal art training\n Idris learnt from books\n observation\n practice and a brief tutelage under pioneer Malay artist\n S. Mahdar. In 1962\n at the age of 18\n this self-taught artist had his first group exhibition at the Singapore Victoria Memoral Hall.\\r\\n","createdDate":"20201119143407","version":0,"latest":false,"roles":[],"metadata":{"accession_no_csv":"2018-00633","Image":"","object_work_type":"watercolours (paintings)","title_text":"Tanjung Rhu Singapore","preference":"main","title_language":"","creator_2":"Idris Mohd Ali","creator_1":"Idris Mohd Ali, 1944- Idris Mohamed Ali","creator_role":"painters (artist)","creation_date":"1963","creation_place_original_location":"Singapore (inhabited place)","styles_periods_indexing_terms":"Not indicated","inscriptions":"","inscription_language":"","scale_type":"Not indicated","shape":"rectangular","materials_name":"paper (fiber product) gouache (paint) watercolour (paint)","techniques_name":"watercolour painting (technique) gouache (technique)","object_colour":"multicoloured","physical_appearance":"The image shows a watercolour painting. The painting depicts several boats that are coloured brown, on water. Each boat has a long mast extending from its centre. There are a couple of men on the decks of the boats. The outlines of birds can be discerned near the top of the painting, beneath the sky. The name of the painting, and the name of the artist are stated at the bottom right hand side of the painting. But the inscriptions are not clear enough to discern the exact wordings.","subject_terms_1":"capes (landforms)  boats","subject_terms_2":"Watercolour painting Capes (Coasts) Singapore Boats and boating","subject_terms_3":"Watercolour Painting Visual arts Tanjong Rhu Heritage and Culture","sgcool_label_text":"Known for his watercolour landscapes and street scenes, Idris Mohamed Ali’s works reveal a strong understanding of colour, depth and realism. His paintings of old Singapore are especially important as they serve as a visual documentation of our national heritage. \r\nStarted painting at 10 and not being able to afford formal art training, Idris learnt from books, observation, practice and a brief tutelage under pioneer Malay artist, S. Mahdar. In 1962, at the age of 18, this self-taught artist had his first group exhibition at the Singapore Victoria Memoral Hall.\r\n"},"nlpDate":"20201119143407","connectorId":0,"tags":{}}