{
  "id": "2018-00052",
  "title": "Z",
  "source": "Bumblebee",
  "path": "./Data/json/",
  "content": "\n  accession_no_csv: 2018-00052\n\n  Image: \n\n  object_work_type: digital prints artists\\u0027 proofs colour slides\n\n  title_text: Z\n\n  preference: main\n\n  title_language: \n\n  creator_2: Tan Lip Seng\n\n  creator_1: Tan\n Lip Seng\n 1942- Tan\n Lip Seng\n\n  creator_role: photographers\n\n  creation_date: 1970\n\n  creation_place_original_location: Singapore (nation)\n\n  styles_periods_indexing_terms: Not indicated\n\n  inscriptions: \n\n  inscription_language: \n\n  scale_type: Not indicated\n\n  shape: rectangular\n\n  materials_name: photographic paper metallic paper photographic film (photographic materials)\n\n  techniques_name: printing (process) montage (image-making technique) photographic processes\n\n  object_colour: multicoloured\n\n  edition_description: 1 of 3\n\n  physical_appearance: \\The image shows a digital print\n an artist\\u0027s proof\n and a slide. They are rectangular in shape. The background of the digital print and artist\\u0027s proof are blue in colour. The background of the photograph shows the structure of a flight of stairs in a zig-zag orientation. The flight of stairs has red railings. A construction worker is depicted to be ascending the flight of stairs. He adorns a yellow helmet and carries a red pail. The image at the bottom shows a slide. It is in colour. It is held in place by a frame. On the borders of the frame\n \\\\Z No. 1\\\\ is stated at the top for the image at the bottom \\\\Tan Lip Seng\n\n  subject_terms_1: prints (visual works) proofs (prints by function) A.R.P.S. EFIAP flights (stair components) universities (institutions) industrial structures slides (photographs)\n\n  subject_terms_2: Colour prints Slides (photography) Industrial buildings National University of Singapore Proofs (Printing) Digitally printed materials Stairs 19 Oxley Road #03-02. 19 Begonia Terrace\\\\ is stated at the bottom for the image at the bottom. \\\n\n  subject_terms_3: construction workers National University of Singapore\n\n  subject_terms_4: Construction workers\n\n  context_1: Photography\n",
  "createdDate": "20201125084511",
  "version": 0,
  "latest": false,
  "roles": [],
  "metadata": {
    "accession_no_csv": "2018-00052",
    "Image": "",
    "object_work_type": "digital prints artists\u0027 proofs colour slides",
    "title_text": "Z",
    "preference": "main",
    "title_language": "",
    "creator_2": "Tan Lip Seng",
    "creator_1": "Tan, Lip Seng, 1942- Tan, Lip Seng",
    "creator_role": "photographers",
    "creation_date": "1970",
    "creation_place_original_location": "Singapore (nation)",
    "styles_periods_indexing_terms": "Not indicated",
    "inscriptions": "",
    "inscription_language": "",
    "scale_type": "Not indicated",
    "shape": "rectangular",
    "materials_name": "photographic paper metallic paper photographic film (photographic materials)",
    "techniques_name": "printing (process) montage (image-making technique) photographic processes",
    "object_colour": "multicoloured",
    "edition_description": "1 of 3",
    "physical_appearance": "\"The image shows a digital print, an artist\u0027s proof, and a slide. They are rectangular in shape. The background of the digital print and artist\u0027s proof are blue in colour. The background of the photograph shows the structure of a flight of stairs in a zig-zag orientation. The flight of stairs has red railings. A construction worker is depicted to be ascending the flight of stairs. He adorns a yellow helmet and carries a red pail. The image at the bottom shows a slide. It is in colour. It is held in place by a frame. On the borders of the frame, \"\"Z No. 1\"\" is stated at the top for the image at the bottom \"\"Tan Lip Seng",
    "subject_terms_1": "prints (visual works) proofs (prints by function) A.R.P.S. EFIAP flights (stair components) universities (institutions) industrial structures slides (photographs)",
    "subject_terms_2": "Colour prints Slides (photography) Industrial buildings National University of Singapore Proofs (Printing) Digitally printed materials Stairs 19 Oxley Road #03-02. 19 Begonia Terrace\"\" is stated at the bottom for the image at the bottom. \"",
    "subject_terms_3": "construction workers National University of Singapore",
    "subject_terms_4": "Construction workers",
    "context_1": "Photography"
  },
  "nlpDate": "20201125084511",
  "connectorId": 0,
  "tags": {}
}