{"id":"2018-00039","title":"Detailed instructions and information for VOC officers arriving in Batavia and the Cape,watermarked with an equestrian portrait of Willem IV, Prince of Orange Nassau\r\n1748","source":"Bumblebee","path":"./Data/json/","content":"accession_no_csv:2018-00039\nImage:\nobject_work_type:administrative records records (documents)\ntitle_text:Detailed instructions and information for VOC officers arriving in Batavia and the Cape\nwatermarked with an equestrian portrait of Willem IV\n Prince of Orange Nassau\\r\\n1748\npreference:main\ntitle_language:\ncreator_2:not indicated\ncreator_1:not indicated\ncreation_date:1748\ncreation_place_original_location:Jakarta (inhabited place)\\r\\n\nstyles_periods_indexing_terms:not indicated\ninscriptions:\ninscription_language:\nshape:rectangular\nmaterials_name:paper (fiber product)\ntechniques_name:papermaking handwriting\nobject_colour:brown (colour) white (colour)\nphysical_appearance:This is a handwritten manuscript\n in Dutch containing detailed instructions and information for VOC officers arriving in Batavia and the Cape.\nsubject_terms_1:written word Dutch Colonial watermarks manuscripts (documents) stadtholders\nsubject_terms_2:administration Watermarks Orange-Nassau\n House of Stadholders Nederlandsche Oost-Indische Compagnie Manuscripts Netherlands\nsubject_terms_4:Netherlands (nation)\nsgcool_label_text:The handwritten document illustrates at a very fundamental level the colonial practice of administration of the Dutch VOC. The manuscript in Dutch reveals various aspects including \\r\\nprotocols\n procedures\n finances and administrative paperwork for VOC officers arriving in Batavia and the Cape of Good Hope. Among other instructions to be found is information on the cost of purchasing a black slave boy in Batavia and the expense of his upkeep.","createdDate":"20201018182637","version":0,"latest":false,"roles":[],"metadata":{"accession_no_csv":"2018-00039","Image":"","object_work_type":"administrative records records (documents)","title_text":"Detailed instructions and information for VOC officers arriving in Batavia and the Cape,watermarked with an equestrian portrait of Willem IV, Prince of Orange Nassau\r\n1748","preference":"main","title_language":"","creator_2":"not indicated","creator_1":"not indicated","creation_date":"1748","creation_place_original_location":"Jakarta (inhabited place)\r\n","styles_periods_indexing_terms":"not indicated","inscriptions":"","inscription_language":"","shape":"rectangular","materials_name":"paper (fiber product)","techniques_name":"papermaking handwriting","object_colour":"brown (colour) white (colour)","physical_appearance":"This is a handwritten manuscript, in Dutch containing detailed instructions and information for VOC officers arriving in Batavia and the Cape.","subject_terms_1":"written word Dutch Colonial watermarks manuscripts (documents) stadtholders","subject_terms_2":"administration Watermarks Orange-Nassau, House of Stadholders Nederlandsche Oost-Indische Compagnie Manuscripts Netherlands","subject_terms_4":"Netherlands (nation)","sgcool_label_text":"The handwritten document illustrates at a very fundamental level the colonial practice of administration of the Dutch VOC. The manuscript in Dutch reveals various aspects including \r\nprotocols, procedures, finances and administrative paperwork for VOC officers arriving in Batavia and the Cape of Good Hope. Among other instructions to be found is information on the cost of purchasing a black slave boy in Batavia and the expense of his upkeep."},"nlpDate":"20201018182637","connectorId":0,"tags":{}}