{
  "id": "2018-00142",
  "title": "Photograph of Chinese cemetery on a hillside",
  "source": "Bumblebee",
  "path": "./Data/json/",
  "content": "\n  accession_no_csv: 2018-00142\n\n  Image: \n\n  object_work_type: black-and-white photographs photographs\n\n  title_text: Photograph of Chinese cemetery on a hillside\n\n  preference: main\n\n  title_language: \n\n  creator_2: Not indicated\n\n  creator_1: Not indicated\n\n  creation_date: March 1878\n\n  creation_place_original_location: Pulau Pinang (state)\n\n  inscriptions: \n\n  inscription_language: \n\n  shape: rectangular\n\n  materials_name: paper (fiber product)\n\n  techniques_name: printing (process) photographic processes\n\n  object_colour: grey monochrome\n\n  physical_appearance: The image shows a black-and-white photograph. It is rectangular and it features a cemetery. The ground is uneven and it elevates from the foreground of the photograph. There are trees in the background. Tombstones with their mounds can be seen all over the ground.\n\n  subject_terms_1: cemeteries Chinese (culture or style) hills\n\n  subject_terms_2: Black-and-white photography Cemeteries Mountains\n\n  subject_terms_3: Photography Cemeteries Hills\n\n  sgcool_label_text: This photograph shows a view of Chinese cemetery on a hillside\n",
  "createdDate": "20201120223708",
  "version": 0,
  "latest": false,
  "roles": [],
  "metadata": {
    "accession_no_csv": "2018-00142",
    "Image": "",
    "object_work_type": "black-and-white photographs photographs",
    "title_text": "Photograph of Chinese cemetery on a hillside",
    "preference": "main",
    "title_language": "",
    "creator_2": "Not indicated",
    "creator_1": "Not indicated",
    "creation_date": "March 1878",
    "creation_place_original_location": "Pulau Pinang (state)",
    "inscriptions": "",
    "inscription_language": "",
    "shape": "rectangular",
    "materials_name": "paper (fiber product)",
    "techniques_name": "printing (process) photographic processes",
    "object_colour": "grey monochrome",
    "physical_appearance": "The image shows a black-and-white photograph. It is rectangular and it features a cemetery. The ground is uneven and it elevates from the foreground of the photograph. There are trees in the background. Tombstones with their mounds can be seen all over the ground.",
    "subject_terms_1": "cemeteries Chinese (culture or style) hills",
    "subject_terms_2": "Black-and-white photography Cemeteries Mountains",
    "subject_terms_3": "Photography Cemeteries Hills",
    "sgcool_label_text": "This photograph shows a view of Chinese cemetery on a hillside"
  },
  "nlpDate": "20201120223708",
  "connectorId": 0,
  "tags": {}
}