{"id":"2018-00023","title":"Portrait of a woman and child","source":"Bumblebee","path":"./Data/json/","content":"accession_no_csv:2018-00023\nImage:\nobject_work_type:colour photographs photographs\ntitle_text:Portrait of a woman and child\npreference:main\ntitle_language:\ncreator_2:The Eastern Studio Singapore\ncreator_1:Not indicated\ncreation_date:1920-1942\ncreation_place_original_location:Singapore (nation)\ninscriptions:\ninscription_language:\nshape:rectangular\nmaterials_name:paper (fiber product)\ntechniques_name:printing (process) photographic processes hand colouring\nobject_colour:multicoloured\nphysical_appearance:The image shows a rectangular colour photograph.  There is an inner and outer border. The surrounding frame is dark brown in colour. A woman and an infant are present in the portrait. Both of them are looking towards the direction where the photograph was captured. The woman holds the infant in her arms and lap. She is sitting on a chair with curved handles.\nsubject_terms_1:studio portraits double portraits women (female humans) infants\nsubject_terms_2:Colour photography Portrait photography Women Infants\nsubject_terms_3:Portrait photography Women Children\nsgcool_label_text:This hand-coloured photograph shows a women with a baby on her lap. Inscribed on the photograph is the studio mark ‘The Eastern Studio Singapore’. \\r\\n\\r\\nEastern Studio was set up by the early 1920s by Lee King Yan\n who was also the founder of Lee Brothers Studio. A well-respected photographer in Singapore\n newspapers lauded him as ‘one of the pioneers of photography’ in Singapore and the ‘Colony’s Grand Old Man of Photography’ at the time of his passing.\\r\\n","createdDate":"20201018182637","version":0,"latest":false,"roles":[],"metadata":{"accession_no_csv":"2018-00023","Image":"","object_work_type":"colour photographs photographs","title_text":"Portrait of a woman and child","preference":"main","title_language":"","creator_2":"The Eastern Studio Singapore","creator_1":"Not indicated","creation_date":"1920-1942","creation_place_original_location":"Singapore (nation)","inscriptions":"","inscription_language":"","shape":"rectangular","materials_name":"paper (fiber product)","techniques_name":"printing (process) photographic processes hand colouring","object_colour":"multicoloured","physical_appearance":"The image shows a rectangular colour photograph.  There is an inner and outer border. The surrounding frame is dark brown in colour. A woman and an infant are present in the portrait. Both of them are looking towards the direction where the photograph was captured. The woman holds the infant in her arms and lap. She is sitting on a chair with curved handles.","subject_terms_1":"studio portraits double portraits women (female humans) infants","subject_terms_2":"Colour photography Portrait photography Women Infants","subject_terms_3":"Portrait photography Women Children","sgcool_label_text":"This hand-coloured photograph shows a women with a baby on her lap. Inscribed on the photograph is the studio mark ‘The Eastern Studio Singapore’. \r\n\r\nEastern Studio was set up by the early 1920s by Lee King Yan, who was also the founder of Lee Brothers Studio. A well-respected photographer in Singapore, newspapers lauded him as ‘one of the pioneers of photography’ in Singapore and the ‘Colony’s Grand Old Man of Photography’ at the time of his passing.\r\n"},"nlpDate":"20201018182637","connectorId":0,"tags":{}}