{"id":"2018-00112","title":"Studio portrait of a boy with neck cape","source":"Bumblebee","path":"./Data/json/","content":"accession_no_csv:2018-00112\nImage:\nobject_work_type:black-and-white photographs photographs\ntitle_text:Studio portrait of a boy with neck cape\npreference:main\ntitle_language:\ncreator_2:G.R. Lambert \\u0026 Company\ncreator_1:G.R. Lambert \\u0026 Co.\ncreator_role:photography studios (organizations)\ncreation_date:1890s-1900s\ncreation_place_original_location:Singapore (nation)\ninscriptions:\ninscription_language:\nshape:rectangular\nmaterials_name:paper (fiber product)\ntechniques_name:printing (process) photographic processes\nobject_colour:grey monochrome\nphysical_appearance:The image shows a black-and-white photograph. It is rectangular and it features a young boy. He is looking towards the direction where the photograph was captured. He is dressed up in his ethnic costume\n which comes with headwear. He is also standing on a carpet\n and in front of an armchair.\nsubject_terms_1:studio portraits children (people by age group) Peranakan folk costume\nsubject_terms_2:Black-and-white photography Portrait photography Children Ethnic costume Peranakan (Asian people)\nsubject_terms_3:Portrait photography Children Peranakan costumes\nsgcool_label_text:This studio portrait shows a boy with a fringed neck cape. The photograph is stamped with the studio mark ‘GR Lambert \\u0026 Co Singapore’.\\r\\n\\r\\nG.R. Lambert and Co was a leading and the most enduring of the European photography studios in Singapore. The studio was established in 1867 by Gustave Richard Lambert\n who was originally from Dresden\n Germany. Popular among the elites\n the firm was often chosen as the official photographers for important state events in Singapore. In 1861 it was appointed as the official photographer of the King of Siam and the Sultan of Johore.","createdDate":"20201119143407","version":0,"latest":false,"roles":[],"metadata":{"accession_no_csv":"2018-00112","Image":"","object_work_type":"black-and-white photographs photographs","title_text":"Studio portrait of a boy with neck cape","preference":"main","title_language":"","creator_2":"G.R. Lambert \u0026 Company","creator_1":"G.R. Lambert \u0026 Co.","creator_role":"photography studios (organizations)","creation_date":"1890s-1900s","creation_place_original_location":"Singapore (nation)","inscriptions":"","inscription_language":"","shape":"rectangular","materials_name":"paper (fiber product)","techniques_name":"printing (process) photographic processes","object_colour":"grey monochrome","physical_appearance":"The image shows a black-and-white photograph. It is rectangular and it features a young boy. He is looking towards the direction where the photograph was captured. He is dressed up in his ethnic costume, which comes with headwear. He is also standing on a carpet, and in front of an armchair.","subject_terms_1":"studio portraits children (people by age group) Peranakan folk costume","subject_terms_2":"Black-and-white photography Portrait photography Children Ethnic costume Peranakan (Asian people)","subject_terms_3":"Portrait photography Children Peranakan costumes","sgcool_label_text":"This studio portrait shows a boy with a fringed neck cape. The photograph is stamped with the studio mark ‘GR Lambert \u0026 Co Singapore’.\r\n\r\nG.R. Lambert and Co was a leading and the most enduring of the European photography studios in Singapore. The studio was established in 1867 by Gustave Richard Lambert, who was originally from Dresden, Germany. Popular among the elites, the firm was often chosen as the official photographers for important state events in Singapore. In 1861 it was appointed as the official photographer of the King of Siam and the Sultan of Johore."},"nlpDate":"20201119143407","connectorId":0,"tags":{}}