{
  "id": "2018-00163",
  "title": "Photograph of two Indo Eurasian women with a piano",
  "source": "Bumblebee",
  "path": "./Data/json/",
  "content": "\n  accession_no_csv: 2018-00163\n\n  Image: \n\n  object_work_type: black-and-white photographs photographs\n\n  title_text: Photograph of two Indo Eurasian women with a piano\n\n  preference: main\n\n  title_language: \n\n  creator_2: Not indicated\n\n  creator_1: Not indicated\n\n  creation_date: Late 19th century\n\n  creation_place_original_location: Indonesia (nation)\n\n  inscriptions: \n\n  inscription_language: \n\n  shape: rectangular\n\n  materials_name: paper (fiber product)\n\n  techniques_name: printing (process) photographic processes\n\n  object_colour: grey monochrome\n\n  physical_appearance: The image shows a black-and-white photograph. It is rectangular and it features two ladies. One of them is sitting down while the other is standing up. Both of them are looking towards the direction where the photograph was captured. They are wearing their ethnic costumes as well. There is a piano at the background. Both ladies are resting their hands and elbows respectively on a table that is covered with a cloth in the middle of the photograph.\n\n  subject_terms_1: double portraits women (female humans) Peranakan folk costume\n\n  subject_terms_2: Black-and-white photography Portrait photography Women Eurasians Ethnic costume\n\n  subject_terms_3: Portrait photography Women Peranakan costumes\n\n  sgcool_label_text: The photograph shows two Indo Eurasian woman (probably a mother and daughter) posing with a piano in the background. The younger woman wears a fashionable kebaya of the late 19th century.\\r\\n\\r\\nWith continuous improvement of camera technology\n it became possible to take photographs outside a studio in the first decades of the 20th century. Many middle-class families collected photographs in albums as a way of documenting family life\n or documentasi keluarga.\n",
  "createdDate": "20201120223708",
  "version": 0,
  "latest": false,
  "roles": [],
  "metadata": {
    "accession_no_csv": "2018-00163",
    "Image": "",
    "object_work_type": "black-and-white photographs photographs",
    "title_text": "Photograph of two Indo Eurasian women with a piano",
    "preference": "main",
    "title_language": "",
    "creator_2": "Not indicated",
    "creator_1": "Not indicated",
    "creation_date": "Late 19th century",
    "creation_place_original_location": "Indonesia (nation)",
    "inscriptions": "",
    "inscription_language": "",
    "shape": "rectangular",
    "materials_name": "paper (fiber product)",
    "techniques_name": "printing (process) photographic processes",
    "object_colour": "grey monochrome",
    "physical_appearance": "The image shows a black-and-white photograph. It is rectangular and it features two ladies. One of them is sitting down while the other is standing up. Both of them are looking towards the direction where the photograph was captured. They are wearing their ethnic costumes as well. There is a piano at the background. Both ladies are resting their hands and elbows respectively on a table that is covered with a cloth in the middle of the photograph.",
    "subject_terms_1": "double portraits women (female humans) Peranakan folk costume",
    "subject_terms_2": "Black-and-white photography Portrait photography Women Eurasians Ethnic costume",
    "subject_terms_3": "Portrait photography Women Peranakan costumes",
    "sgcool_label_text": "The photograph shows two Indo Eurasian woman (probably a mother and daughter) posing with a piano in the background. The younger woman wears a fashionable kebaya of the late 19th century.\r\n\r\nWith continuous improvement of camera technology, it became possible to take photographs outside a studio in the first decades of the 20th century. Many middle-class families collected photographs in albums as a way of documenting family life, or documentasi keluarga."
  },
  "nlpDate": "20201120223708",
  "connectorId": 0,
  "tags": {}
}