{"id":"2018-00166","title":"Photograph of two Indo Eurasian and a child on a patio","source":"Bumblebee","path":"./Data/json/","content":"accession_no_csv:2018-00166\nImage:\nobject_work_type:black-and-white photographs photographs\ntitle_text:Photograph of two Indo Eurasian and a child on a patio\npreference:main\ntitle_language:\ncreator_2:Not indicated\ncreator_1:Not indicated\ncreation_date:Late 19th century\ncreation_place_original_location:Indonesia (nation)\ninscriptions:\ninscription_language:\nshape:rectangular\nmaterials_name:paper (fiber product)\ntechniques_name:printing (process) photographic processes\nobject_colour:grey monochrome\nphysical_appearance:The image shows a black-and-white photograph. It is rectangular and it features two ladies and a child. All of them are looking towards the direction where the photograph was captured. The ladies are dressed in their ethnic costumes. There are large potted plants in the background.\nsubject_terms_1:group portraits Peranakan folk costume women (female humans) children (people by age group)\nsubject_terms_2:Black-and-white photography Portrait photography Portraits\n Group Eurasians Ethnic costume Women Children\nsubject_terms_3:Portrait photography Peranakan costumes Women Children\nsgcool_label_text:This photograph shows two Indo Eurasian women in sarong kebayas and a child on the patio. \\r\\n\\r\\nWith continuous improvement of camera technology\n it became possible to take photographs outside a studio in the first decades of the 20th century. Many middle-class families collected photographs in albums as a way of documenting family life\n or documentasi keluarga.","createdDate":"20201018182637","version":0,"latest":false,"roles":[],"metadata":{"accession_no_csv":"2018-00166","Image":"","object_work_type":"black-and-white photographs photographs","title_text":"Photograph of two Indo Eurasian and a child on a patio","preference":"main","title_language":"","creator_2":"Not indicated","creator_1":"Not indicated","creation_date":"Late 19th century","creation_place_original_location":"Indonesia (nation)","inscriptions":"","inscription_language":"","shape":"rectangular","materials_name":"paper (fiber product)","techniques_name":"printing (process) photographic processes","object_colour":"grey monochrome","physical_appearance":"The image shows a black-and-white photograph. It is rectangular and it features two ladies and a child. All of them are looking towards the direction where the photograph was captured. The ladies are dressed in their ethnic costumes. There are large potted plants in the background.","subject_terms_1":"group portraits Peranakan folk costume women (female humans) children (people by age group)","subject_terms_2":"Black-and-white photography Portrait photography Portraits, Group Eurasians Ethnic costume Women Children","subject_terms_3":"Portrait photography Peranakan costumes Women Children","sgcool_label_text":"This photograph shows two Indo Eurasian women in sarong kebayas and a child on the patio. \r\n\r\nWith continuous improvement of camera technology, it became possible to take photographs outside a studio in the first decades of the 20th century. Many middle-class families collected photographs in albums as a way of documenting family life, or documentasi keluarga."},"nlpDate":"20201018182637","connectorId":0,"tags":{}}