{
  "id": "2018-00735",
  "title": "Large ewer and salver",
  "source": "Bumblebee",
  "path": "./Data/json/",
  "content": "\n  accession_no_csv: 2018-00735\n\n  Image: \n\n  object_work_type: salvers ewers (vessels)\n\n  title_text: Large ewer and salver\n\n  preference: main\n\n  title_language: \n\n  creator_2: Not indicated\n\n  creation_date: c. 1600 (?)\n\n  creation_place_original_location: Hyderabad (inhabited place) Bijapur (inhabited place)\n\n  styles_periods_indexing_terms: Deccani Golconda\n\n  inscriptions: \n\n  inscription_language: \n\n  shape: irregular\n\n  materials_name: copper alloy\n\n  techniques_name: metalworking engraving (action)\n\n  object_colour: copper (colour)\n\n  physical_appearance: This is a set comprising of a large ewer and its accompanying salver. The ewer is of a globular form\n sitting on a foot\n with a thin neck rising towards a wide spout with straight edges. The slaver has raised edges. Both the ewer and the salver has engravings throughout the body\n with a detailed foliate ground comprising of mythical beasts and animal motifs. There is an inscriptive band on the neck and rim of the ewer.\n\n  subject_terms_1: khamsa inscriptions Qur\\u0027ans birds (motifs) scrolls (motifs)\n\n  subject_terms_2: Motifs Islamic inscriptions Ewers Salvers\n\n  subject_terms_3: Decorative arts\n\n  subject_terms_4: \n\n  sgcool_label_text: Exquisite metalwork represents one of the more significant artistic traditions of the Muslim sultanates along the Deccan plateau in southern India\n that emerged at the end of the 15th century. Owing to either descent from Persian adncestors or belief in the Shi’i faith\n the Deccani courts showed an affinity with Persian artistic traditions and influences. The animal decorations on both the ewer and the salver allude to this Persian reference with the inclusion of mythical beasts such as senmurv\n yali and dragons\n with other animals such as elephants and hares. These motifs are set against a detailed foliate ground on the ewer. A hamsa\n an aquatic bird with symbolic meaning derived from the Hindu tradition\n is depicted on the centre of the salverr. The presence of Hindu and Persian elements reaffirms the association with the Deccani sultanates while the inscription bands in Arabic script bear verses from the Quran\n surat al-Baqarah (Chapter 2: ‘The Heifer’) found mainly on the neck and rims of the ewer underscore the Muslim context.\n",
  "createdDate": "20201201203307",
  "version": 0,
  "latest": false,
  "roles": [],
  "metadata": {
    "accession_no_csv": "2018-00735",
    "Image": "",
    "object_work_type": "salvers ewers (vessels)",
    "title_text": "Large ewer and salver",
    "preference": "main",
    "title_language": "",
    "creator_2": "Not indicated",
    "creation_date": "c. 1600 (?)",
    "creation_place_original_location": "Hyderabad (inhabited place) Bijapur (inhabited place)",
    "styles_periods_indexing_terms": "Deccani Golconda",
    "inscriptions": "",
    "inscription_language": "",
    "shape": "irregular",
    "materials_name": "copper alloy",
    "techniques_name": "metalworking engraving (action)",
    "object_colour": "copper (colour)",
    "physical_appearance": "This is a set comprising of a large ewer and its accompanying salver. The ewer is of a globular form, sitting on a foot, with a thin neck rising towards a wide spout with straight edges. The slaver has raised edges. Both the ewer and the salver has engravings throughout the body, with a detailed foliate ground comprising of mythical beasts and animal motifs. There is an inscriptive band on the neck and rim of the ewer.",
    "subject_terms_1": "khamsa inscriptions Qur\u0027ans birds (motifs) scrolls (motifs)",
    "subject_terms_2": "Motifs Islamic inscriptions Ewers Salvers",
    "subject_terms_3": "Decorative arts",
    "subject_terms_4": "",
    "sgcool_label_text": "Exquisite metalwork represents one of the more significant artistic traditions of the Muslim sultanates along the Deccan plateau in southern India, that emerged at the end of the 15th century. Owing to either descent from Persian adncestors or belief in the Shi’i faith, the Deccani courts showed an affinity with Persian artistic traditions and influences. The animal decorations on both the ewer and the salver allude to this Persian reference with the inclusion of mythical beasts such as senmurv, yali and dragons, with other animals such as elephants and hares. These motifs are set against a detailed foliate ground on the ewer. A hamsa, an aquatic bird with symbolic meaning derived from the Hindu tradition, is depicted on the centre of the salverr. The presence of Hindu and Persian elements reaffirms the association with the Deccani sultanates while the inscription bands in Arabic script bear verses from the Quran, surat al-Baqarah (Chapter 2: ‘The Heifer’) found mainly on the neck and rims of the ewer underscore the Muslim context."
  },
  "nlpDate": "20201201203307",
  "connectorId": 0,
  "tags": {}
}