{
  "id": "2018-00411",
  "title": "\"Dutch Colonial \"\"Five-Foot\"\" Chest\"",
  "source": "Bumblebee",
  "path": "./Data/json/",
  "content": "\n  accession_no_csv: 2018-00411\n\n  Image: \n\n  object_work_type: case furniture chests (case furniture)\n\n  title_text: \\Dutch Colonial \\\\Five-Foot\\\\ Chest\\\n\n  preference: main\n\n  title_language: \n\n  creation_date: 18th century\n\n  creation_place_original_location: Dutch East Indies (former territory/colony/dependent state)\n\n  styles_periods_indexing_terms: Dutch Colonial\n\n  inscriptions: \n\n  inscription_language: \n\n  shape: rectangular cuboid\n\n  materials_name: teak (wood) brass (alloy)\n\n  techniques_name: woodworking metalworking brass smithing furniture making\n\n  object_colour: multicoloured\n\n  physical_appearance: This teak chest is brown in colour. It has embroidered brass fittings in the colour gold\n along the sides and below the lid of the chest. There are 3 bolt like structures\n gold in colour\n on the top left corner and bottom  centre of the lid of the chest. The chest includes 2 pieces of furniture  with knob-like legs\n another plank of wood furniture and a key with a clover-like head.\n\n  subject_terms_1: storage furniture\n\n  subject_terms_2: Furniture\n Dutch Colonial Nederlandsche Oost-Indische Compagnie Chests\n\n  sgcool_label_text: \\This is an 18th century Dutch colonial teak chest with brass fittings\n with later mounted bun feet for use as furniture. Such chests were used by Dutch East India Company (VOC) officials for their travels. However\n the dimensions and number of chests carried per official was regulated\n with the Governor General permitted to take 18 chests of this \\\\five foot\\\\ size until 1791 when the permitted sizes were reduced.\\\n",
  "createdDate": "20201201203307",
  "version": 0,
  "latest": false,
  "roles": [],
  "metadata": {
    "accession_no_csv": "2018-00411",
    "Image": "",
    "object_work_type": "case furniture chests (case furniture)",
    "title_text": "\"Dutch Colonial \"\"Five-Foot\"\" Chest\"",
    "preference": "main",
    "title_language": "",
    "creation_date": "18th century",
    "creation_place_original_location": "Dutch East Indies (former territory/colony/dependent state)",
    "styles_periods_indexing_terms": "Dutch Colonial",
    "inscriptions": "",
    "inscription_language": "",
    "shape": "rectangular cuboid",
    "materials_name": "teak (wood) brass (alloy)",
    "techniques_name": "woodworking metalworking brass smithing furniture making",
    "object_colour": "multicoloured",
    "physical_appearance": "This teak chest is brown in colour. It has embroidered brass fittings in the colour gold, along the sides and below the lid of the chest. There are 3 bolt like structures, gold in colour, on the top left corner and bottom  centre of the lid of the chest. The chest includes 2 pieces of furniture  with knob-like legs, another plank of wood furniture and a key with a clover-like head.",
    "subject_terms_1": "storage furniture",
    "subject_terms_2": "Furniture, Dutch Colonial Nederlandsche Oost-Indische Compagnie Chests",
    "sgcool_label_text": "\"This is an 18th century Dutch colonial teak chest with brass fittings, with later mounted bun feet for use as furniture. Such chests were used by Dutch East India Company (VOC) officials for their travels. However, the dimensions and number of chests carried per official was regulated, with the Governor General permitted to take 18 chests of this \"\"five foot\"\" size until 1791 when the permitted sizes were reduced.\""
  },
  "nlpDate": "20201201203307",
  "connectorId": 0,
  "tags": {}
}