{"id":"2018-00200","title":"Photograph of Mrs Lee Choon Guan","source":"Bumblebee","path":"./Data/json/","content":"accession_no_csv:2018-00200\nImage:\nobject_work_type:colour photographs photographs\ntitle_text:Photograph of Mrs Lee Choon Guan\npreference:main\ntitle_language:\ncreator_2:Not indicated\ncreator_1:Not indicated\ncreation_date:1978\ncreation_place_original_location:Singapore (nation)\ninscriptions:\ninscription_language:\nshape:rectangular\nmaterials_name:paper (fiber product)\ntechniques_name:printing (process) photographic processes\nobject_colour:multicoloured\nphysical_appearance:\\The image shows a colour photograph. It features an elderly lady sitting on a striped couch. She is bespectacled and looking towards the direction where the photograph is captured. A cake has been placed in front of her. The numeral \\u0027100\\u0027 is positioned on top of the cake. \\\\To the Grand Dame of Singapore\\\\ is stated on the bottom tier of the cake.\\\nsubject_terms_1:portraits women (female humans) birthdays\nsubject_terms_2:Portrait photography Women Centenarians Birthdays\nsubject_terms_3:Portrait photography Women\nsgcool_label_text:This photograph shows Mrs Lee Choon Guan at her 100th birthday celebrations.","createdDate":"20201119143407","version":0,"latest":false,"roles":[],"metadata":{"accession_no_csv":"2018-00200","Image":"","object_work_type":"colour photographs photographs","title_text":"Photograph of Mrs Lee Choon Guan","preference":"main","title_language":"","creator_2":"Not indicated","creator_1":"Not indicated","creation_date":"1978","creation_place_original_location":"Singapore (nation)","inscriptions":"","inscription_language":"","shape":"rectangular","materials_name":"paper (fiber product)","techniques_name":"printing (process) photographic processes","object_colour":"multicoloured","physical_appearance":"\"The image shows a colour photograph. It features an elderly lady sitting on a striped couch. She is bespectacled and looking towards the direction where the photograph is captured. A cake has been placed in front of her. The numeral \u0027100\u0027 is positioned on top of the cake. \"\"To the Grand Dame of Singapore\"\" is stated on the bottom tier of the cake.\"","subject_terms_1":"portraits women (female humans) birthdays","subject_terms_2":"Portrait photography Women Centenarians Birthdays","subject_terms_3":"Portrait photography Women","sgcool_label_text":"This photograph shows Mrs Lee Choon Guan at her 100th birthday celebrations."},"nlpDate":"20201119143407","connectorId":0,"tags":{}}