{
  "id": "2018-00191",
  "title": "Photograph of a young nyonya in a green kebaya",
  "source": "Bumblebee",
  "path": "./Data/json/",
  "content": "\n  accession_no_csv: 2018-00191\n\n  Image: \n\n  object_work_type: chromogenic colour prints photographs\n\n  title_text: Photograph of a young nyonya in a green kebaya\n\n  preference: main\n\n  title_language: \n\n  creator_2: Not indicated\n\n  creator_1: Not indicated\n\n  creation_date: 2000\n\n  creation_place_original_location: Singapore (nation)\n\n  inscriptions: \n\n  inscription_language: \n\n  shape: rectangular\n\n  materials_name: paper (fiber product)\n\n  techniques_name: printing (process) photographic processes\n\n  object_colour: multicoloured\n\n  physical_appearance: The image shows a colour photograph. It features a lady. She is standing up and posing sideways\n looking towards the direction where the photograph was captured. She is wearing her ethnic costume\n with a turquoise top and a brown lower garment with flowery designs. There are also red garlands tied around her hair. The background of the photograph shows greenery and trees.\n\n  subject_terms_1: portraits women (female humans) folk costume Peranakan\n\n  subject_terms_2: Portrait photography Women Peranakan (Asian people) Ethnic costume Colour photography\n\n  subject_terms_3: Portrait photography Women Peranakan costumes\n\n  sgcool_label_text: This Chromogenic print on Kodak paper shows a young nyonya in a green kebaya.\n",
  "createdDate": "20201120223708",
  "version": 0,
  "latest": false,
  "roles": [],
  "metadata": {
    "accession_no_csv": "2018-00191",
    "Image": "",
    "object_work_type": "chromogenic colour prints photographs",
    "title_text": "Photograph of a young nyonya in a green kebaya",
    "preference": "main",
    "title_language": "",
    "creator_2": "Not indicated",
    "creator_1": "Not indicated",
    "creation_date": "2000",
    "creation_place_original_location": "Singapore (nation)",
    "inscriptions": "",
    "inscription_language": "",
    "shape": "rectangular",
    "materials_name": "paper (fiber product)",
    "techniques_name": "printing (process) photographic processes",
    "object_colour": "multicoloured",
    "physical_appearance": "The image shows a colour photograph. It features a lady. She is standing up and posing sideways, looking towards the direction where the photograph was captured. She is wearing her ethnic costume, with a turquoise top and a brown lower garment with flowery designs. There are also red garlands tied around her hair. The background of the photograph shows greenery and trees.",
    "subject_terms_1": "portraits women (female humans) folk costume Peranakan",
    "subject_terms_2": "Portrait photography Women Peranakan (Asian people) Ethnic costume Colour photography",
    "subject_terms_3": "Portrait photography Women Peranakan costumes",
    "sgcool_label_text": "This Chromogenic print on Kodak paper shows a young nyonya in a green kebaya."
  },
  "nlpDate": "20201120223708",
  "connectorId": 0,
  "tags": {}
}