{
  "id": "2018-00125",
  "title": "Photograph of two Peranakan children",
  "source": "Bumblebee",
  "path": "./Data/json/",
  "content": "\n  accession_no_csv: 2018-00125\n\n  Image: \n\n  object_work_type: cartes-de-visite (card photographs)\n\n  title_text: Photograph of two Peranakan children\n\n  preference: main\n\n  title_language: \n\n  creator_2: Pun Lun Photography Studio at High Street\n\n  creator_1: Not indicated\n\n  creator_role: photography studios (organizations)\n\n  creation_date: 1890s-1900s\n\n  creation_place_original_location: Singapore (nation)\n\n  inscriptions: \n\n  inscription_language: \n\n  shape: rectangular\n\n  materials_name: paper (fiber product)\n\n  techniques_name: printing (process) photographic processes\n\n  object_colour: grey monochrome\n\n  physical_appearance: The image shows a black-and-white photograph. It is rectangular and it features two children. Both of them standing up and looking towards the direction where the photograph was captured. They are dressed in their ethnic costumes. The background of the photograph features a backdrop of buildings and trees.\n\n  subject_terms_1: Peranakan black-and-white photographs double portraits studio portraits children (people by age group) folk costume\n\n  subject_terms_2: Ethnic costume Children Peranakan (Asian people) Portrait photography Black-and-white photography\n\n  subject_terms_3: Children Portrait photography Peranakan costumes\n\n  sgcool_label_text: This carte de visite shows a  studio photograph of two children posing with a porcelain drum stool\n before a painted backdrop of a landscape with houses. This photograph was probably taken by Pun Lun photography studio at High Street in Singapore. \\r\\n\\r\\nPun Lun (1864 – c.1900) was a Chinese photographer\n with a successful studio in Hong Kong and branches in Foochow (Fuzhou)\n Saigon and Singapore.\\r\\n\\r\\nStudios were already established across the Strait Settlements and the Dutch East Indies by the 1840s and became increasingly prevalent in the 1850s. During the 1920s\n Chinese-owned studios dominated the studio photography trade in Southeast Asia.\n",
  "createdDate": "20201201203307",
  "version": 0,
  "latest": false,
  "roles": [],
  "metadata": {
    "accession_no_csv": "2018-00125",
    "Image": "",
    "object_work_type": "cartes-de-visite (card photographs)",
    "title_text": "Photograph of two Peranakan children",
    "preference": "main",
    "title_language": "",
    "creator_2": "Pun Lun Photography Studio at High Street",
    "creator_1": "Not indicated",
    "creator_role": "photography studios (organizations)",
    "creation_date": "1890s-1900s",
    "creation_place_original_location": "Singapore (nation)",
    "inscriptions": "",
    "inscription_language": "",
    "shape": "rectangular",
    "materials_name": "paper (fiber product)",
    "techniques_name": "printing (process) photographic processes",
    "object_colour": "grey monochrome",
    "physical_appearance": "The image shows a black-and-white photograph. It is rectangular and it features two children. Both of them standing up and looking towards the direction where the photograph was captured. They are dressed in their ethnic costumes. The background of the photograph features a backdrop of buildings and trees.",
    "subject_terms_1": "Peranakan black-and-white photographs double portraits studio portraits children (people by age group) folk costume",
    "subject_terms_2": "Ethnic costume Children Peranakan (Asian people) Portrait photography Black-and-white photography",
    "subject_terms_3": "Children Portrait photography Peranakan costumes",
    "sgcool_label_text": "This carte de visite shows a  studio photograph of two children posing with a porcelain drum stool, before a painted backdrop of a landscape with houses. This photograph was probably taken by Pun Lun photography studio at High Street in Singapore. \r\n\r\nPun Lun (1864 – c.1900) was a Chinese photographer, with a successful studio in Hong Kong and branches in Foochow (Fuzhou), Saigon and Singapore.\r\n\r\nStudios were already established across the Strait Settlements and the Dutch East Indies by the 1840s and became increasingly prevalent in the 1850s. During the 1920s, Chinese-owned studios dominated the studio photography trade in Southeast Asia."
  },
  "nlpDate": "20201201203307",
  "connectorId": 0,
  "tags": {}
}