{"id":"2018-00145","title":"Photograph of a young boy","source":"Bumblebee","path":"./Data/json/","content":"accession_no_csv:2018-00145\nImage:\nobject_work_type:black-and-white photographs photographs\ntitle_text:Photograph of a young boy\npreference:main\ntitle_language:\ncreator_2:Not indicated\ncreator_1:Not indicated\ncreation_date:1860s\ncreation_place_original_location:Java (island)\ninscriptions:\ninscription_language:\nshape:rectangular\nmaterials_name:paper (fiber product)\ntechniques_name:printing (process) photographic processes\nobject_colour:grey monochrome\nphysical_appearance:The image shows a black-and-white photograph. It is rectangular and it features a young boy. He is sitting on a chair and holding onto the edge of a table. He has a headdress on as well and is looking towards the direction where the photograph was captured.\nsubject_terms_1:portraits children (people by age group)\nsubject_terms_2:Black-and-white photography Portrait photography Children\nsubject_terms_3:Portrait photography Children\nsgcool_label_text:This photograph shows a young boy holding onto the table beside him.","createdDate":"20201119143407","version":0,"latest":false,"roles":[],"metadata":{"accession_no_csv":"2018-00145","Image":"","object_work_type":"black-and-white photographs photographs","title_text":"Photograph of a young boy","preference":"main","title_language":"","creator_2":"Not indicated","creator_1":"Not indicated","creation_date":"1860s","creation_place_original_location":"Java (island)","inscriptions":"","inscription_language":"","shape":"rectangular","materials_name":"paper (fiber product)","techniques_name":"printing (process) photographic processes","object_colour":"grey monochrome","physical_appearance":"The image shows a black-and-white photograph. It is rectangular and it features a young boy. He is sitting on a chair and holding onto the edge of a table. He has a headdress on as well and is looking towards the direction where the photograph was captured.","subject_terms_1":"portraits children (people by age group)","subject_terms_2":"Black-and-white photography Portrait photography Children","subject_terms_3":"Portrait photography Children","sgcool_label_text":"This photograph shows a young boy holding onto the table beside him."},"nlpDate":"20201119143407","connectorId":0,"tags":{}}