{
  "id": "2018-00026",
  "title": "How to make a Good Photo: a book for the amateur photographer",
  "source": "Bumblebee",
  "path": "./Data/json/",
  "content": "\n  accession_no_csv: 2018-00026\n\n  Image: \n\n  object_work_type: paperbacks\n\n  title_text: How to make a Good Photo: a book for the amateur photographer\n\n  preference: main\n\n  title_language: \n\n  creator_2: Eastman Kodak Company\n\n  creator_1: Eastman Kodak Company\n\n  creator_role: publishers\n\n  creation_date: 1920s\n\n  creation_place_original_location: Jakarta (inhabited place)\n\n  inscriptions: \n\n  inscription_language: \n\n  shape: rectangular\n\n  materials_name: printing paper book cloth (textile material)\n\n  techniques_name: colour printing bookbinding (process)\n\n  object_colour: multicoloured\n\n  physical_appearance: The image shows a paperback. It has a grey background. The title and publisher are printed in black\n in the Dutch language. There is a rectangular line in orange that serves to form a margin\n between the words and the sides of the page. The font size of the titles vary as well\n with some words being bigger than others.\n\n  subject_terms_1: photography (discipline) amateurs instructional materials\n\n  subject_terms_2: Paperbacks Photography Instructional and educational works\n\n  sgcool_label_text: Written in Dutch\n ‘How to make a Good Photo: a book for the amateur photographer’ was published by the Eastman Kodak Company in Batavia. \\r\\n\\r\\nThe Eastman Kodak Company was established in 1892\n and succeeded the company George Eastman first founded when he started producing dry plates for sale in Rochester\n New York in 1880. The introduction of the Kodak camera in 1888 marked a milestone in the history of photography for it made photography accessible and affordable to millions of amateurs who were not professionally trained. \\r\\n\n",
  "createdDate": "20201120223708",
  "version": 0,
  "latest": false,
  "roles": [],
  "metadata": {
    "accession_no_csv": "2018-00026",
    "Image": "",
    "object_work_type": "paperbacks",
    "title_text": "How to make a Good Photo: a book for the amateur photographer",
    "preference": "main",
    "title_language": "",
    "creator_2": "Eastman Kodak Company",
    "creator_1": "Eastman Kodak Company",
    "creator_role": "publishers",
    "creation_date": "1920s",
    "creation_place_original_location": "Jakarta (inhabited place)",
    "inscriptions": "",
    "inscription_language": "",
    "shape": "rectangular",
    "materials_name": "printing paper book cloth (textile material)",
    "techniques_name": "colour printing bookbinding (process)",
    "object_colour": "multicoloured",
    "physical_appearance": "The image shows a paperback. It has a grey background. The title and publisher are printed in black, in the Dutch language. There is a rectangular line in orange that serves to form a margin, between the words and the sides of the page. The font size of the titles vary as well, with some words being bigger than others.",
    "subject_terms_1": "photography (discipline) amateurs instructional materials",
    "subject_terms_2": "Paperbacks Photography Instructional and educational works",
    "sgcool_label_text": "Written in Dutch, ‘How to make a Good Photo: a book for the amateur photographer’ was published by the Eastman Kodak Company in Batavia. \r\n\r\nThe Eastman Kodak Company was established in 1892, and succeeded the company George Eastman first founded when he started producing dry plates for sale in Rochester, New York in 1880. The introduction of the Kodak camera in 1888 marked a milestone in the history of photography for it made photography accessible and affordable to millions of amateurs who were not professionally trained. \r\n"
  },
  "nlpDate": "20201120223708",
  "connectorId": 0,
  "tags": {}
}