{
  "id": "2018-00196-031",
  "title": "Booklet of film negatives Booklet of film negatives: Negative of thirteen people",
  "source": "Bumblebee",
  "path": "./Data/json/",
  "content": "\n  accession_no_csv: 2018-00196-031\n\n  Image: \n\n  object_work_type: negatives (photographs)\n\n  title_text: Booklet of film negatives Booklet of film negatives: Negative of thirteen people\n\n  preference: main alternate\n\n  title_language: \n\n  creator_2: Not indicated\n\n  creator_1: Not indicated\n\n  creation_date: 1950s\n\n  creation_place_original_location: Singapore (nation)\n\n  inscriptions: \n\n  inscription_language: \n\n  shape: rectangular\n\n  materials_name: Not indicated\n\n  techniques_name: Not indicated\n\n  object_colour: grey monochrome\n\n  physical_appearance: \n\n  subject_terms_1: group portraits\n\n  subject_terms_2: Portraits\n Group Portrait photography\n\n  subject_terms_3: Portrait photography\n\n  sgcool_label_text: This booklet contains film negatives. \\r\\n\n",
  "createdDate": "20201125084508",
  "version": 0,
  "latest": false,
  "roles": [],
  "metadata": {
    "accession_no_csv": "2018-00196-031",
    "Image": "",
    "object_work_type": "negatives (photographs)",
    "title_text": "Booklet of film negatives Booklet of film negatives: Negative of thirteen people",
    "preference": "main alternate",
    "title_language": "",
    "creator_2": "Not indicated",
    "creator_1": "Not indicated",
    "creation_date": "1950s",
    "creation_place_original_location": "Singapore (nation)",
    "inscriptions": "",
    "inscription_language": "",
    "shape": "rectangular",
    "materials_name": "Not indicated",
    "techniques_name": "Not indicated",
    "object_colour": "grey monochrome",
    "physical_appearance": "",
    "subject_terms_1": "group portraits",
    "subject_terms_2": "Portraits, Group Portrait photography",
    "subject_terms_3": "Portrait photography",
    "sgcool_label_text": "This booklet contains film negatives. \r\n"
  },
  "nlpDate": "20201125084508",
  "connectorId": 0,
  "tags": {}
}