{"id":"2018-00154","title":"Photograph of a road with carts pulled by oxen","source":"Bumblebee","path":"./Data/json/","content":"accession_no_csv:2018-00154\nImage:\nobject_work_type:black-and-white photographs photographs\ntitle_text:Photograph of a road with carts pulled by oxen\npreference:main\ntitle_language:\ncreator_2:Not indicated\ncreator_1:Not indicated\ncreation_date:Late 19th centiury\ncreation_place_original_location:Singapore (nation)\ninscriptions:\ninscription_language:\nshape:rectangular\nmaterials_name:paper (fiber product)\ntechniques_name:printing (process) photographic processes\nobject_colour:grey monochrome\nphysical_appearance:\\The image shows a black-and-white photograph. It is rectangular and it features an image of a road. Carts pulled by oxen can seen going in opposite directions on the road. To the right hand side of the photograph\n there are a three peopl walking on the edge of the road. \\\\Singapore\\\\ is displayed at the top. \\\\Char à Buffles \\u0026 Malaises’\\\\ is displayed at the bottom. \\\nsubject_terms_1:oxen carts roads\nsubject_terms_2:Black-and-white photography Carriages and carts Oxen Roads\nsubject_terms_3:Photography\nsgcool_label_text:This photograph shows carts being pulled by oxen along a road. It is inscribed with ‘Singapore. Char à Buffles \\u0026 Malaises’.","createdDate":"20201018182637","version":0,"latest":false,"roles":[],"metadata":{"accession_no_csv":"2018-00154","Image":"","object_work_type":"black-and-white photographs photographs","title_text":"Photograph of a road with carts pulled by oxen","preference":"main","title_language":"","creator_2":"Not indicated","creator_1":"Not indicated","creation_date":"Late 19th centiury","creation_place_original_location":"Singapore (nation)","inscriptions":"","inscription_language":"","shape":"rectangular","materials_name":"paper (fiber product)","techniques_name":"printing (process) photographic processes","object_colour":"grey monochrome","physical_appearance":"\"The image shows a black-and-white photograph. It is rectangular and it features an image of a road. Carts pulled by oxen can seen going in opposite directions on the road. To the right hand side of the photograph, there are a three peopl walking on the edge of the road. \"\"Singapore\"\" is displayed at the top. \"\"Char à Buffles \u0026 Malaises’\"\" is displayed at the bottom. \"","subject_terms_1":"oxen carts roads","subject_terms_2":"Black-and-white photography Carriages and carts Oxen Roads","subject_terms_3":"Photography","sgcool_label_text":"This photograph shows carts being pulled by oxen along a road. It is inscribed with ‘Singapore. Char à Buffles \u0026 Malaises’."},"nlpDate":"20201018182637","connectorId":0,"tags":{}}