{"id":"2018-00054-001","title":"The Painter: Original Artwork The Painter","source":"Bumblebee","path":"./Data/json/","content":"accession_no_csv:2018-00054-001\nImage:\nobject_work_type:digital prints prints (visual works)\ntitle_text:The Painter: Original Artwork The Painter\npreference:main alternate\ntitle_language:\ncreator_2:Tan Lip Seng\ncreator_1:Tan\n Lip Seng\n 1942- Tan\n Lip Seng\ncreator_role:photographers\ncreation_date:1971\ncreation_place_original_location:Singapore (nation)\nstyles_periods_indexing_terms:Not indicated\ninscriptions:\ninscription_language:\nscale_type:Not indicated\nshape:rectangular\nmaterials_name:photographic paper\ntechniques_name:photographic processes montage (image-making technique)\nobject_colour:multicoloured\nedition_description:1 of 3\nphysical_appearance:The image shows a digital print. It is rectangular in shape. The background of the digital print is black in colour. It depicts  a man who is bending forwards. In his hands is a thin stick that has a roller brush attached to it at one end. He is applying paint to the surface of a wall. The painter is wearing a yellow helmet and his face is not captured in the images.\nsubject_terms_1:painters (tradespeople) proofs (prints by function) prints (visual works) slides (photographs)\nsubject_terms_2:Digitally printed materials Painters Slides (photography) Digitally printed materials Proofs (Printing) Colour prints\nsubject_terms_3:Photography\nsgcool_label_text:This photograph was taken by Singaporean photographer Tan Lip Seng. Tan is arguably the most important photographer in the region developing colour derivative and photo montage techniques. His works in the 1960s were a result of various experiments meticulously combining multiple colour transparencies into one to achieve the desired montage within one frame.\\r\\n\\r\\nTan spent 42 years as a medical photographer at the National University of Singapore. Many of his works have won numerous awards internationally and show a strong graphic and stylistic sensibility. Tan is also the first Singaporean to be awarded a fellowship by the Royal Photographic Society of the United Kingdom in 1970. Conferred the Cultural Medallion in 1985\n Tan recently published a retrospective of his works\n ‘Light \\u0026 Shadow: Tan Lip Seng’s 50 Years of Photography’ in 2009.","createdDate":"20201018182637","version":0,"latest":false,"roles":[],"metadata":{"accession_no_csv":"2018-00054-001","Image":"","object_work_type":"digital prints prints (visual works)","title_text":"The Painter: Original Artwork The Painter","preference":"main alternate","title_language":"","creator_2":"Tan Lip Seng","creator_1":"Tan, Lip Seng, 1942- Tan, Lip Seng","creator_role":"photographers","creation_date":"1971","creation_place_original_location":"Singapore (nation)","styles_periods_indexing_terms":"Not indicated","inscriptions":"","inscription_language":"","scale_type":"Not indicated","shape":"rectangular","materials_name":"photographic paper","techniques_name":"photographic processes montage (image-making technique)","object_colour":"multicoloured","edition_description":"1 of 3","physical_appearance":"The image shows a digital print. It is rectangular in shape. The background of the digital print is black in colour. It depicts  a man who is bending forwards. In his hands is a thin stick that has a roller brush attached to it at one end. He is applying paint to the surface of a wall. The painter is wearing a yellow helmet and his face is not captured in the images.","subject_terms_1":"painters (tradespeople) proofs (prints by function) prints (visual works) slides (photographs)","subject_terms_2":"Digitally printed materials Painters Slides (photography) Digitally printed materials Proofs (Printing) Colour prints","subject_terms_3":"Photography","sgcool_label_text":"This photograph was taken by Singaporean photographer Tan Lip Seng. Tan is arguably the most important photographer in the region developing colour derivative and photo montage techniques. His works in the 1960s were a result of various experiments meticulously combining multiple colour transparencies into one to achieve the desired montage within one frame.\r\n\r\nTan spent 42 years as a medical photographer at the National University of Singapore. Many of his works have won numerous awards internationally and show a strong graphic and stylistic sensibility. Tan is also the first Singaporean to be awarded a fellowship by the Royal Photographic Society of the United Kingdom in 1970. Conferred the Cultural Medallion in 1985, Tan recently published a retrospective of his works, ‘Light \u0026 Shadow: Tan Lip Seng’s 50 Years of Photography’ in 2009."},"nlpDate":"20201018182637","connectorId":0,"tags":{}}