{
  "id": "2018-00048-001",
  "title": "Two Workers Two Workers: Original Artwork",
  "source": "Bumblebee",
  "path": "./Data/json/",
  "content": "\n  accession_no_csv: 2018-00048-001\n\n  Image: \n\n  object_work_type: prints (visual works) digital prints\n\n  title_text: Two Workers Two Workers: Original Artwork\n\n  preference: main alternate\n\n  title_language: \n\n  creator_2: Tan Lip Seng\n\n  creator_1: Tan\n Lip Seng\n 1942- Tan\n Lip Seng\n\n  creator_role: photographers\n\n  creation_date: 1968\n\n  creation_place_original_location: Singapore (nation)\n\n  styles_periods_indexing_terms: Not indicated\n\n  inscriptions: \n\n  inscription_language: \n\n  scale_type: Not indicated\n\n  shape: rectangular\n\n  materials_name: photographic paper\n\n  techniques_name: montage (image-making technique) photographic processes\n\n  object_colour: multicoloured\n\n  edition_description: 1 of 3\n\n  physical_appearance: The image shows a digital print. It is rectangular in shape. It features the backs of two workers\n which are facing the direction in which the photograph was captured. Their heads are covered with red headgear\n and they are carrying blue pails. Patches of grass can be seen on the ground.\n\n  subject_terms_1: workers\n\n  subject_terms_2: Colour prints Employees Digitally printed materials\n\n  subject_terms_3: Photography\n\n  sgcool_label_text: This photograph was taken by Singaporean photographer Tan Lip Seng. Tan is arguably the most important photographer in the region developing colour derivative and photo montage techniques. His works in the 1960s were a result of various experiments meticulously combining multiple colour transparencies into one to achieve the desired montage within one frame.\\r\\n\\r\\nTan spent 42 years as a medical photographer at the National University of Singapore. Many of his works have won numerous awards internationally and show a strong graphic and stylistic sensibility. Tan is also the first Singaporean to be awarded a fellowship by the Royal Photographic Society of the United Kingdom in 1970. Conferred the Cultural Medallion in 1985\n Tan recently published a retrospective of his works\n ‘Light \\u0026 Shadow: Tan Lip Seng’s 50 Years of Photography’ in 2009.\n",
  "createdDate": "20201201203307",
  "version": 0,
  "latest": false,
  "roles": [],
  "metadata": {
    "accession_no_csv": "2018-00048-001",
    "Image": "",
    "object_work_type": "prints (visual works) digital prints",
    "title_text": "Two Workers Two Workers: Original Artwork",
    "preference": "main alternate",
    "title_language": "",
    "creator_2": "Tan Lip Seng",
    "creator_1": "Tan, Lip Seng, 1942- Tan, Lip Seng",
    "creator_role": "photographers",
    "creation_date": "1968",
    "creation_place_original_location": "Singapore (nation)",
    "styles_periods_indexing_terms": "Not indicated",
    "inscriptions": "",
    "inscription_language": "",
    "scale_type": "Not indicated",
    "shape": "rectangular",
    "materials_name": "photographic paper",
    "techniques_name": "montage (image-making technique) photographic processes",
    "object_colour": "multicoloured",
    "edition_description": "1 of 3",
    "physical_appearance": "The image shows a digital print. It is rectangular in shape. It features the backs of two workers, which are facing the direction in which the photograph was captured. Their heads are covered with red headgear, and they are carrying blue pails. Patches of grass can be seen on the ground.",
    "subject_terms_1": "workers",
    "subject_terms_2": "Colour prints Employees Digitally printed materials",
    "subject_terms_3": "Photography",
    "sgcool_label_text": "This photograph was taken by Singaporean photographer Tan Lip Seng. Tan is arguably the most important photographer in the region developing colour derivative and photo montage techniques. His works in the 1960s were a result of various experiments meticulously combining multiple colour transparencies into one to achieve the desired montage within one frame.\r\n\r\nTan spent 42 years as a medical photographer at the National University of Singapore. Many of his works have won numerous awards internationally and show a strong graphic and stylistic sensibility. Tan is also the first Singaporean to be awarded a fellowship by the Royal Photographic Society of the United Kingdom in 1970. Conferred the Cultural Medallion in 1985, Tan recently published a retrospective of his works, ‘Light \u0026 Shadow: Tan Lip Seng’s 50 Years of Photography’ in 2009."
  },
  "nlpDate": "20201201203307",
  "connectorId": 0,
  "tags": {}
}