{"id":"2018-00473","title":"Venice, Piazza San Marco Venice, Plaza San Marco","source":"Bumblebee","path":"./Data/json/","content":"accession_no_csv:2018-00473\nImage:\nobject_work_type:drawings (visual works)\ntitle_text:Venice\n Piazza San Marco Venice\n Plaza San Marco\npreference:main alternate\ntitle_language:\ncreator_2:Choon Ghee Tan\ncreator_1:Tan\n Choon Ghee\n 1930- Tan\n Choon Ghee\ncreator_role:artists (visual artists)\ncreation_date:1958\ncreation_place_original_location:Singapore (nation) Pulau Pinang (state)\nstyles_periods_indexing_terms:Not indicated\ninscriptions:\ninscription_language:\nscale_type:Not indicated\nshape:rectangular\nmaterials_name:paper (fiber product) ink\ntechniques_name:creating (artistic activity) drawing (image-making)\nobject_colour:black (colour)\nphysical_appearance:\\The image shows a drawing. It is rectangular in shape.. The foreground shows a large building with several domes. All of the domes have spires attached above them. To the right of the drawing\n there is a tall rectangular building and a couple of roofed buildings as well. The foreground of the drawing shows a crowd of people. Most of the people in the drawing have their backs towards the viewer\n and are facing the buildings. The location\n signature and year\n \\\\Tan. 1958\nsubject_terms_1:Venice cathedrals (buildings) street scenes buildings (structures)\nsubject_terms_2:Piazza San Marco\\\\ is stated at the left hand side.  \\ Piazza San Marco (Venice\n Italy) Basilica di San Marco (Venice\n Italy) Buildings\nsubject_terms_3:squares (open spaces) Churches Buildings\nsubject_terms_4:Drawings\ncontext_1:Drawing\ncontext_2:Sestière di San Marco (sestiere)","createdDate":"20201018182637","version":0,"latest":false,"roles":[],"metadata":{"accession_no_csv":"2018-00473","Image":"","object_work_type":"drawings (visual works)","title_text":"Venice, Piazza San Marco Venice, Plaza San Marco","preference":"main alternate","title_language":"","creator_2":"Choon Ghee Tan","creator_1":"Tan, Choon Ghee, 1930- Tan, Choon Ghee","creator_role":"artists (visual artists)","creation_date":"1958","creation_place_original_location":"Singapore (nation) Pulau Pinang (state)","styles_periods_indexing_terms":"Not indicated","inscriptions":"","inscription_language":"","scale_type":"Not indicated","shape":"rectangular","materials_name":"paper (fiber product) ink","techniques_name":"creating (artistic activity) drawing (image-making)","object_colour":"black (colour)","physical_appearance":"\"The image shows a drawing. It is rectangular in shape.. The foreground shows a large building with several domes. All of the domes have spires attached above them. To the right of the drawing, there is a tall rectangular building and a couple of roofed buildings as well. The foreground of the drawing shows a crowd of people. Most of the people in the drawing have their backs towards the viewer, and are facing the buildings. The location, signature and year, \"\"Tan. 1958","subject_terms_1":"Venice cathedrals (buildings) street scenes buildings (structures)","subject_terms_2":"Piazza San Marco\"\" is stated at the left hand side.  \" Piazza San Marco (Venice, Italy) Basilica di San Marco (Venice, Italy) Buildings","subject_terms_3":"squares (open spaces) Churches Buildings","subject_terms_4":"Drawings","context_1":"Drawing","context_2":"Sestière di San Marco (sestiere)"},"nlpDate":"20201018182637","connectorId":0,"tags":{}}