{"id":"2018-00413","title":"Bazuband (armband)","source":"Bumblebee","path":"./Data/json/","content":"accession_no_csv:2018-00413\nImage:\nobject_work_type:armbands\ntitle_text:Bazuband (armband)\npreference:main\ntitle_language:\ncreator_2:Not indicated\ncreator_1:Not indicated\ncreation_date:19th century\ncreation_place_original_location:Jaipur (inhabited place)\nstyles_periods_indexing_terms:Mughal styles\ninscriptions:\ninscription_language:\nshape:tubular\nmaterials_name:gold (metal) sapphire (mineral) enamel (fused coating)\ntechniques_name:jewellery making enamelling layering\nobject_colour:multicoloured\nphysical_appearance:The image shows an armband. It is tubular in shape and floral designs in the form of gems line the surface of the ornament. The gems come in two forms of colour\n namely white and blue. There are also some red gems at both ends of the jewellery. The perimeter of the armband is embellished with white gems in the shape of circular beads.\nsubject_terms_1:goldwork (visual works) jewellery ornaments (object genre) allover patterns foliage (motif) flower (motif)\nsubject_terms_2:Armbands Gold jewellery Goldwork Motifs\nsubject_terms_3:Jewellery Indian decorative arts\nsgcool_label_text:The bazuband\n the Persian name for an upper armband\n is a classic form of Mughal jewellery worn by both men and women. Mounted in gold\n this bazuband is set with white sapphires and enamelled on the reverse with polychrome floral designs. \\r\\n\\r\\nThe gems are set on a blue ground in the kundan technique. The kundan-set is one of the oldest forms of jewel-making in India and involves layering narrow strips of gold (kundan) to form a solid wedge around the gemstone. Mughal jewellery was often a unique combination of kundan-set gems and enamelling. Traditional mughal jewellery is still made in this manner today. \\r\\n","createdDate":"20201018182637","version":0,"latest":false,"roles":[],"metadata":{"accession_no_csv":"2018-00413","Image":"","object_work_type":"armbands","title_text":"Bazuband (armband)","preference":"main","title_language":"","creator_2":"Not indicated","creator_1":"Not indicated","creation_date":"19th century","creation_place_original_location":"Jaipur (inhabited place)","styles_periods_indexing_terms":"Mughal styles","inscriptions":"","inscription_language":"","shape":"tubular","materials_name":"gold (metal) sapphire (mineral) enamel (fused coating)","techniques_name":"jewellery making enamelling layering","object_colour":"multicoloured","physical_appearance":"The image shows an armband. It is tubular in shape and floral designs in the form of gems line the surface of the ornament. The gems come in two forms of colour, namely white and blue. There are also some red gems at both ends of the jewellery. The perimeter of the armband is embellished with white gems in the shape of circular beads.","subject_terms_1":"goldwork (visual works) jewellery ornaments (object genre) allover patterns foliage (motif) flower (motif)","subject_terms_2":"Armbands Gold jewellery Goldwork Motifs","subject_terms_3":"Jewellery Indian decorative arts","sgcool_label_text":"The bazuband, the Persian name for an upper armband, is a classic form of Mughal jewellery worn by both men and women. Mounted in gold, this bazuband is set with white sapphires and enamelled on the reverse with polychrome floral designs. \r\n\r\nThe gems are set on a blue ground in the kundan technique. The kundan-set is one of the oldest forms of jewel-making in India and involves layering narrow strips of gold (kundan) to form a solid wedge around the gemstone. Mughal jewellery was often a unique combination of kundan-set gems and enamelling. Traditional mughal jewellery is still made in this manner today. \r\n"},"nlpDate":"20201018182637","connectorId":0,"tags":{}}