{"id":"2018-00171","title":"Passport of Tan Tik Sioc","source":"Bumblebee","path":"./Data/json/","content":"accession_no_csv:2018-00171\nImage:\nobject_work_type:passports\ntitle_text:Passport of Tan Tik Sioc\npreference:main\ntitle_language:\ncreator_2:Consulate of the Repbulic of China at Surabaya\ncreator_1:Not indicated\ncreator_role:creators\ncreation_date:1910s\ncreation_place_original_location:Java (island)\ninscriptions:\ninscription_language:\nshape:rectangular\nmaterials_name:paper (fiber product)\ntechniques_name:printing (process)\nobject_colour:multicoloured\nphysical_appearance:\\The image shows a passport document. It is rectangular in shape and at the upper right hand side of the certificate\n a black-and-white passport sized photograph of a man is present. \\\\Passport\\\\ is stated at the top centre\nsubject_terms_1:below a logo. \\\\11 Jul 1927\\\\ is stated at the bottom left hand side citizenship papers\nsubject_terms_2:together with a signature and a stamp. \\\\Consulate of the Repbulic of China Surabaya\\\\ is stamped at the bottom and top right. \\ Passports Diplomatic and consular service China\nsubject_terms_3:passport photographs\nsubject_terms_4:Identification photographs","createdDate":"20201018182637","version":0,"latest":false,"roles":[],"metadata":{"accession_no_csv":"2018-00171","Image":"","object_work_type":"passports","title_text":"Passport of Tan Tik Sioc","preference":"main","title_language":"","creator_2":"Consulate of the Repbulic of China at Surabaya","creator_1":"Not indicated","creator_role":"creators","creation_date":"1910s","creation_place_original_location":"Java (island)","inscriptions":"","inscription_language":"","shape":"rectangular","materials_name":"paper (fiber product)","techniques_name":"printing (process)","object_colour":"multicoloured","physical_appearance":"\"The image shows a passport document. It is rectangular in shape and at the upper right hand side of the certificate, a black-and-white passport sized photograph of a man is present. \"\"Passport\"\" is stated at the top centre","subject_terms_1":"below a logo. \"\"11 Jul 1927\"\" is stated at the bottom left hand side citizenship papers","subject_terms_2":"together with a signature and a stamp. \"\"Consulate of the Repbulic of China Surabaya\"\" is stamped at the bottom and top right. \" Passports Diplomatic and consular service China","subject_terms_3":"passport photographs","subject_terms_4":"Identification photographs"},"nlpDate":"20201018182637","connectorId":0,"tags":{}}