{
  "id": "2018-00136",
  "title": "Studio portrait of a seated nyonya and a girl",
  "source": "Bumblebee",
  "path": "./Data/json/",
  "content": "\n  accession_no_csv: 2018-00136\n\n  Image: \n\n  object_work_type: photographs black-and-white photographs\n\n  title_text: Studio portrait of a seated nyonya and a girl\n\n  preference: main\n\n  title_language: \n\n  creator_2: J. B. Jasper\n\n  creator_1: Not indicated\n\n  creator_role: photography studios (organizations)\n\n  creation_date: 1860s\n\n  creation_place_original_location: Surabaya (inhabited place)\n\n  inscriptions: \n\n  inscription_language: \n\n  shape: rectangular\n\n  materials_name: paper (fiber product)\n\n  techniques_name: printing (process) photographic processes\n\n  object_colour: grey monochrome\n\n  physical_appearance: The image shows a black-and-white photograph. It is rectangular and it features a lady and  female child. The lady is sitting down while the child is standing to her left. Both of them are wearing their ethnic costumes and have their hairs tied back. The girl adorns a necklace as well.\n\n  subject_terms_1: women (female humans) Peranakan double portraits studio portraits children (people by age group) folk costume\n\n  subject_terms_2: Ethnic costume Peranakan (Asian people) Children Portrait photography Black-and-white photography Women\n\n  subject_terms_3: Children Portrait photography Peranakan costumes Women\n\n  sgcool_label_text: This studio portrait shows a seated nyonya and a girl wearing a necklace. The studio mark of J. B. Jasper is stamped on the back of the photograph. \\r\\n\\r\\nStudios were already established across the Strait Settlements and the Dutch East Indies by the 1840s and became increasingly prevalent in the 1850s. During the 1920s\n Chinese-owned studios dominated the studio photography trade in Southeast Asia.\n",
  "createdDate": "20201201203307",
  "version": 0,
  "latest": false,
  "roles": [],
  "metadata": {
    "accession_no_csv": "2018-00136",
    "Image": "",
    "object_work_type": "photographs black-and-white photographs",
    "title_text": "Studio portrait of a seated nyonya and a girl",
    "preference": "main",
    "title_language": "",
    "creator_2": "J. B. Jasper",
    "creator_1": "Not indicated",
    "creator_role": "photography studios (organizations)",
    "creation_date": "1860s",
    "creation_place_original_location": "Surabaya (inhabited place)",
    "inscriptions": "",
    "inscription_language": "",
    "shape": "rectangular",
    "materials_name": "paper (fiber product)",
    "techniques_name": "printing (process) photographic processes",
    "object_colour": "grey monochrome",
    "physical_appearance": "The image shows a black-and-white photograph. It is rectangular and it features a lady and  female child. The lady is sitting down while the child is standing to her left. Both of them are wearing their ethnic costumes and have their hairs tied back. The girl adorns a necklace as well.",
    "subject_terms_1": "women (female humans) Peranakan double portraits studio portraits children (people by age group) folk costume",
    "subject_terms_2": "Ethnic costume Peranakan (Asian people) Children Portrait photography Black-and-white photography Women",
    "subject_terms_3": "Children Portrait photography Peranakan costumes Women",
    "sgcool_label_text": "This studio portrait shows a seated nyonya and a girl wearing a necklace. The studio mark of J. B. Jasper is stamped on the back of the photograph. \r\n\r\nStudios were already established across the Strait Settlements and the Dutch East Indies by the 1840s and became increasingly prevalent in the 1850s. During the 1920s, Chinese-owned studios dominated the studio photography trade in Southeast Asia."
  },
  "nlpDate": "20201201203307",
  "connectorId": 0,
  "tags": {}
}