{"id":"2018-00032","title":"Photograph of Sunbeam Musical Party Sunbeam Musical Party","source":"Bumblebee","path":"./Data/json/","content":"accession_no_csv:2018-00032\nImage:\nobject_work_type:black-and-white photographs photographs\ntitle_text:Photograph of Sunbeam Musical Party Sunbeam Musical Party\npreference:main alternate\ntitle_language:\ncreator_2:Not indicated\ncreator_1:Not indicated\ncreation_date:1932\ncreation_place_original_location:Singapore (nation)\ninscriptions:\ninscription_language:\nshape:rectangular\nmaterials_name:paper (fiber product)\ntechniques_name:printing (process) photographic processes\nobject_colour:grey monochrome\nphysical_appearance:\\The image shows a black-and-white photograph. It is rectangular and it features  group of musicians. All of them are adults except for two children. The adults in the front row are sitting down while the people in the back row stand. All of the adults are holding a musical instrument\n such as a violins\n banjos\n and guitars etc. There is a drum present at the centre as well. The background features a single storey roofed building and several tall trees. \\\\Sunbeam Musical Party\nsubject_terms_1:Exempted 1931\\\\ is stated at the top. \\\\First Anniversary Celebration ensembles (musical groups) music (performing arts) anniversaries celebrations\nsubject_terms_2:1932\\\\ is stated at the bottom. Names of members are stated on the left and right side.  \\ Portraits\n Group Portrait photography Musical groups Anniversaries\nsubject_terms_3:group portraits Musicians Musical groups\nsubject_terms_4:Black-and-white photography\ncontext_1:Portrait photography","createdDate":"20201119143407","version":0,"latest":false,"roles":[],"metadata":{"accession_no_csv":"2018-00032","Image":"","object_work_type":"black-and-white photographs photographs","title_text":"Photograph of Sunbeam Musical Party Sunbeam Musical Party","preference":"main alternate","title_language":"","creator_2":"Not indicated","creator_1":"Not indicated","creation_date":"1932","creation_place_original_location":"Singapore (nation)","inscriptions":"","inscription_language":"","shape":"rectangular","materials_name":"paper (fiber product)","techniques_name":"printing (process) photographic processes","object_colour":"grey monochrome","physical_appearance":"\"The image shows a black-and-white photograph. It is rectangular and it features  group of musicians. All of them are adults except for two children. The adults in the front row are sitting down while the people in the back row stand. All of the adults are holding a musical instrument, such as a violins, banjos, and guitars etc. There is a drum present at the centre as well. The background features a single storey roofed building and several tall trees. \"\"Sunbeam Musical Party","subject_terms_1":"Exempted 1931\"\" is stated at the top. \"\"First Anniversary Celebration ensembles (musical groups) music (performing arts) anniversaries celebrations","subject_terms_2":"1932\"\" is stated at the bottom. Names of members are stated on the left and right side.  \" Portraits, Group Portrait photography Musical groups Anniversaries","subject_terms_3":"group portraits Musicians Musical groups","subject_terms_4":"Black-and-white photography","context_1":"Portrait photography"},"nlpDate":"20201119143407","connectorId":0,"tags":{}}