{"id":"2018-00016","title":"Dust (Singapore Galaxy)","source":"Bumblebee","path":"./Data/json/","content":"accession_no_csv:2018-00016\nImage:\nobject_work_type:installations (visual works)\ntitle_text:Dust (Singapore Galaxy)\npreference:main\ntitle_language:\ncreator_2:Ni Youyu\ncreator_1:Not indicated\ncreator_role:artists (visual artists)\ncreation_date:2016\ncreation_place_original_location:China (nation)\nstyles_periods_indexing_terms:Not indicated\ninscriptions:\ninscription_language:\nshape:rectangular\nmaterials_name:chalk glue mixed media\ntechniques_name:forming (physical activity) creating (artistic activity)\nobject_colour:multicoloured\nphysical_appearance:This installation is created in a landscape fashion. This work is composed on a black and grey background where white dots are interspaced throughout the entire piece of art.\nsubject_terms_1:sky stars (extraterrestial bodies) space (astronomical concept) galaxies mixed media works symbolism (artistic concept)\nsubject_terms_2:Sky Stars Installations (Art) Galaxies Derivative works Outer space Symbolism\nsubject_terms_3:Installation art\nsubject_terms_4:Singapore (nation)\nsgcool_label_text:Dust (Singapore Galaxy) is based on a photograph of the night sky around Singapore. The seemingly random scattering of chalk dust is in fact a precise placement charting stellar distributions as depicted in the original astronomical photograph. In Chinese\n the characters for ‘dust’ also refer to those who are socially underprivileged\n and carry the additional meanings of the ordinary and mundane. Here\n dust is vested with solemnity and divinity in its transformation into the limitless universe\n mapping the infinitesimal traces of human existence onto the infinite.","createdDate":"20201119143407","version":0,"latest":false,"roles":[],"metadata":{"accession_no_csv":"2018-00016","Image":"","object_work_type":"installations (visual works)","title_text":"Dust (Singapore Galaxy)","preference":"main","title_language":"","creator_2":"Ni Youyu","creator_1":"Not indicated","creator_role":"artists (visual artists)","creation_date":"2016","creation_place_original_location":"China (nation)","styles_periods_indexing_terms":"Not indicated","inscriptions":"","inscription_language":"","shape":"rectangular","materials_name":"chalk glue mixed media","techniques_name":"forming (physical activity) creating (artistic activity)","object_colour":"multicoloured","physical_appearance":"This installation is created in a landscape fashion. This work is composed on a black and grey background where white dots are interspaced throughout the entire piece of art.","subject_terms_1":"sky stars (extraterrestial bodies) space (astronomical concept) galaxies mixed media works symbolism (artistic concept)","subject_terms_2":"Sky Stars Installations (Art) Galaxies Derivative works Outer space Symbolism","subject_terms_3":"Installation art","subject_terms_4":"Singapore (nation)","sgcool_label_text":"Dust (Singapore Galaxy) is based on a photograph of the night sky around Singapore. The seemingly random scattering of chalk dust is in fact a precise placement charting stellar distributions as depicted in the original astronomical photograph. In Chinese, the characters for ‘dust’ also refer to those who are socially underprivileged, and carry the additional meanings of the ordinary and mundane. Here, dust is vested with solemnity and divinity in its transformation into the limitless universe, mapping the infinitesimal traces of human existence onto the infinite."},"nlpDate":"20201119143407","connectorId":0,"tags":{}}