{"id":"2018-00126","title":"Photograph of John Mather","source":"Bumblebee","path":"./Data/json/","content":"accession_no_csv:2018-00126\nImage:\nobject_work_type:cartes-de-visite (card photographs)\ntitle_text:Photograph of John Mather\npreference:main\ntitle_language:\ncreator_2:Quan Seng Studio\ncreator_1:Not indicated\ncreator_role:photography studios (organizations)\ncreation_date:1890s-1900s\ncreation_place_original_location:Singapore (nation)\ninscriptions:\ninscription_language:\nshape:rectangular\nmaterials_name:paper (fiber product)\ntechniques_name:printing (process) photographic processes\nobject_colour:grey monochrome\nphysical_appearance:The image shows a black-and-white photograph. It is rectangular and it features a man sitting down. His legs are crossed and he is looking towards the direction where the photograph was captured. He is holding a cane in his left hand and his hat is placed on the ground to the right of the photograph. There is a flower vase on a rised platform to his left as well.\nsubject_terms_1:black-and-white photographs studio portraits men (male humans)\nsubject_terms_2:Black-and-white photography Portrait photography Men\nsubject_terms_3:Portrait photography\nsgcool_label_text:This carte de visite shows John Mather seated on a mother-of-pearl chair with a cane and his hat at his feet. The studio mark ‘Quan Seng’ is printed on the back of the carte. \\r\\n\\r\\nStudios were already established across the Strait Settlements and the Dutch East Indies by the 1840s and became increasingly prevalent in the 1850s. During the 1920s\n Chinese-owned studios dominated the studio photography trade in Southeast Asia.","createdDate":"20201018182637","version":0,"latest":false,"roles":[],"metadata":{"accession_no_csv":"2018-00126","Image":"","object_work_type":"cartes-de-visite (card photographs)","title_text":"Photograph of John Mather","preference":"main","title_language":"","creator_2":"Quan Seng Studio","creator_1":"Not indicated","creator_role":"photography studios (organizations)","creation_date":"1890s-1900s","creation_place_original_location":"Singapore (nation)","inscriptions":"","inscription_language":"","shape":"rectangular","materials_name":"paper (fiber product)","techniques_name":"printing (process) photographic processes","object_colour":"grey monochrome","physical_appearance":"The image shows a black-and-white photograph. It is rectangular and it features a man sitting down. His legs are crossed and he is looking towards the direction where the photograph was captured. He is holding a cane in his left hand and his hat is placed on the ground to the right of the photograph. There is a flower vase on a rised platform to his left as well.","subject_terms_1":"black-and-white photographs studio portraits men (male humans)","subject_terms_2":"Black-and-white photography Portrait photography Men","subject_terms_3":"Portrait photography","sgcool_label_text":"This carte de visite shows John Mather seated on a mother-of-pearl chair with a cane and his hat at his feet. The studio mark ‘Quan Seng’ is printed on the back of the carte. \r\n\r\nStudios were already established across the Strait Settlements and the Dutch East Indies by the 1840s and became increasingly prevalent in the 1850s. During the 1920s, Chinese-owned studios dominated the studio photography trade in Southeast Asia."},"nlpDate":"20201018182637","connectorId":0,"tags":{}}