{
  "id": "2018-00122",
  "title": "Album leaf with four photographs including Cheang Hong Lim Album leaf with five photographs including Cheang Hong Lim",
  "source": "Bumblebee",
  "path": "./Data/json/",
  "content": "\n  accession_no_csv: 2018-00122\n\n  Image: \n\n  object_work_type: black-and-white photographs photograph albums photographs\n\n  title_text: Album leaf with four photographs including Cheang Hong Lim Album leaf with five photographs including Cheang Hong Lim\n\n  preference: main alternate\n\n  title_language: \n\n  creator_2: G.R. Lambert \\u0026 Company\n\n  creator_1: G.R. Lambert \\u0026 Co.\n\n  creator_role: photography studios (organizations)\n\n  creation_date: 1890s-1900s\n\n  creation_place_original_location: Singapore (nation)\n\n  inscriptions: \n\n  inscription_language: \n\n  shape: rectangular\n\n  materials_name: paper (fiber product)\n\n  techniques_name: printing (process) photographic processes\n\n  object_colour: grey monochrome\n\n  physical_appearance: The image shows four black-and-white photographs. They are rectangular and two of them have landscape orientations while the other two are of portrait orientations. The image at the top left hand side features a horse drawn carriage. The image at the top right hand side features a group of people who are sitting down. The image at the bottom left hand side features three people\n of which two are sitting down on the ground while the other is standing in the middle. The image at the bottom right hand side features a man dressed in his ethnic costume\n with headwear.\n\n  subject_terms_1: studio portraits group portraits Peranakan folk costume businessmen carriages (vehicles)\n\n  subject_terms_2: Black-and-white photography Portrait photography Portraits\n Group Peranakan (Asian people) Ethnic costume Businessmen Carriages and carts\n\n  subject_terms_3: Portrait photography Businesspeople Peranakan costumes Cheang\n Hong Lim\n\n  sgcool_label_text: This album leaf contains five photographs\n including one from around 1905 of Peranakan businessman and philanthropist Cheang Hong Lim\n dressed in the robes of a Qing Chinese official. The photograph on the verso  shows a view of the Buddhist temple of Borobudur in Central Java\n Indonesia. ‘Gallery View Boeroe Boeder by Neeijela’ is inscribed on the lower edge of the leaf. These photographs were probably taken by G.R. Lambert and Co.\\r\\n\\r\\nG.R. Lambert and Co was a leading and the most enduring of the European photography studios in Singapore. The studio was established in 1867 by Gustave Richard Lambert\n who was originally from Dresden\n Germany. Popular among the elites\n the firm was often chosen as the official photographers for important state events in Singapore. In 1861 it was appointed as the official photographer of the King of Siam and the Sultan of Johore.\n",
  "createdDate": "20201120223708",
  "version": 0,
  "latest": false,
  "roles": [],
  "metadata": {
    "accession_no_csv": "2018-00122",
    "Image": "",
    "object_work_type": "black-and-white photographs photograph albums photographs",
    "title_text": "Album leaf with four photographs including Cheang Hong Lim Album leaf with five photographs including Cheang Hong Lim",
    "preference": "main alternate",
    "title_language": "",
    "creator_2": "G.R. Lambert \u0026 Company",
    "creator_1": "G.R. Lambert \u0026 Co.",
    "creator_role": "photography studios (organizations)",
    "creation_date": "1890s-1900s",
    "creation_place_original_location": "Singapore (nation)",
    "inscriptions": "",
    "inscription_language": "",
    "shape": "rectangular",
    "materials_name": "paper (fiber product)",
    "techniques_name": "printing (process) photographic processes",
    "object_colour": "grey monochrome",
    "physical_appearance": "The image shows four black-and-white photographs. They are rectangular and two of them have landscape orientations while the other two are of portrait orientations. The image at the top left hand side features a horse drawn carriage. The image at the top right hand side features a group of people who are sitting down. The image at the bottom left hand side features three people, of which two are sitting down on the ground while the other is standing in the middle. The image at the bottom right hand side features a man dressed in his ethnic costume, with headwear.",
    "subject_terms_1": "studio portraits group portraits Peranakan folk costume businessmen carriages (vehicles)",
    "subject_terms_2": "Black-and-white photography Portrait photography Portraits, Group Peranakan (Asian people) Ethnic costume Businessmen Carriages and carts",
    "subject_terms_3": "Portrait photography Businesspeople Peranakan costumes Cheang, Hong Lim",
    "sgcool_label_text": "This album leaf contains five photographs, including one from around 1905 of Peranakan businessman and philanthropist Cheang Hong Lim, dressed in the robes of a Qing Chinese official. The photograph on the verso  shows a view of the Buddhist temple of Borobudur in Central Java, Indonesia. ‘Gallery View Boeroe Boeder by Neeijela’ is inscribed on the lower edge of the leaf. These photographs were probably taken by G.R. Lambert and Co.\r\n\r\nG.R. Lambert and Co was a leading and the most enduring of the European photography studios in Singapore. The studio was established in 1867 by Gustave Richard Lambert, who was originally from Dresden, Germany. Popular among the elites, the firm was often chosen as the official photographers for important state events in Singapore. In 1861 it was appointed as the official photographer of the King of Siam and the Sultan of Johore."
  },
  "nlpDate": "20201120223708",
  "connectorId": 0,
  "tags": {}
}