{
  "id": "2018-00031",
  "title": "The Oleh Oleh Party Photograph of The Oleh Oleh Party",
  "source": "Bumblebee",
  "path": "./Data/json/",
  "content": "\n  accession_no_csv: 2018-00031\n\n  Image: \n\n  object_work_type: photographs black-and-white photographs\n\n  title_text: The Oleh Oleh Party Photograph of The Oleh Oleh Party\n\n  preference: main alternate\n\n  title_language: \n\n  creator_2: Not indicated\n\n  creator_1: Not indicated\n\n  creation_date: 1933\n\n  creation_place_original_location: Singapore (nation)\n\n  inscriptions: \n\n  inscription_language: \n\n  shape: rectangular\n\n  materials_name: paper (fiber product)\n\n  techniques_name: printing (process) photographic processes\n\n  object_colour: grey monochrome\n\n  physical_appearance: \\The image shows a black-and-white photograph. It is rectangular and it features a group of people standing and sitting down on a stage platform. Both men and women are present. The stage backdrop features flowery designs and an arched hallway with square pillars. \\\\Moonlight Opera\\\\ is stated at the top of the stage. \\\\The Oleh Oleh Party of Singapore: 14\n\n  subject_terms_1: opera companies Peranakan performing artists cultural groups theaters (institutions) stages (performance spaces) cultural heritage 15 \\u0026 16 April 1933\\\\ is written at the bottom. \\\n\n  subject_terms_2: Opera companies Peranakan (Asian people) Portraits\n Group Entertainers Portrait photography group portraits Theatres\n\n  subject_terms_3: Theatre Cultural development Peranakan clans and associations Black-and-white photography\n\n  subject_terms_4: Portrait photography\n",
  "createdDate": "20201201203307",
  "version": 0,
  "latest": false,
  "roles": [],
  "metadata": {
    "accession_no_csv": "2018-00031",
    "Image": "",
    "object_work_type": "photographs black-and-white photographs",
    "title_text": "The Oleh Oleh Party Photograph of The Oleh Oleh Party",
    "preference": "main alternate",
    "title_language": "",
    "creator_2": "Not indicated",
    "creator_1": "Not indicated",
    "creation_date": "1933",
    "creation_place_original_location": "Singapore (nation)",
    "inscriptions": "",
    "inscription_language": "",
    "shape": "rectangular",
    "materials_name": "paper (fiber product)",
    "techniques_name": "printing (process) photographic processes",
    "object_colour": "grey monochrome",
    "physical_appearance": "\"The image shows a black-and-white photograph. It is rectangular and it features a group of people standing and sitting down on a stage platform. Both men and women are present. The stage backdrop features flowery designs and an arched hallway with square pillars. \"\"Moonlight Opera\"\" is stated at the top of the stage. \"\"The Oleh Oleh Party of Singapore: 14",
    "subject_terms_1": "opera companies Peranakan performing artists cultural groups theaters (institutions) stages (performance spaces) cultural heritage 15 \u0026 16 April 1933\"\" is written at the bottom. \"",
    "subject_terms_2": "Opera companies Peranakan (Asian people) Portraits, Group Entertainers Portrait photography group portraits Theatres",
    "subject_terms_3": "Theatre Cultural development Peranakan clans and associations Black-and-white photography",
    "subject_terms_4": "Portrait photography"
  },
  "nlpDate": "20201201203307",
  "connectorId": 0,
  "tags": {}
}