{"id":"2018-00479","title":"Untitled (Accommodation in London)","source":"Bumblebee","path":"./Data/json/","content":"accession_no_csv:2018-00479\nImage:\nobject_work_type:drawings (visual works)\ntitle_text:Untitled (Accommodation in London)\npreference:main\ntitle_language:\ncreator_2:Choon Ghee Tan\ncreator_1:Tan\n Choon Ghee\n 1930- Tan\n Choon Ghee\ncreator_role:artists (visual artists)\ncreation_date:1960\ncreation_place_original_location:Singapore (nation) Pulau Pinang (state)\nstyles_periods_indexing_terms:Not indicated\ninscriptions:\ninscription_language:\nscale_type:Not indicated\nshape:rectangular\nmaterials_name:paper (fiber product) ink\ntechniques_name:creating (artistic activity) drawing (image-making)\nobject_colour:black (colour)\nphysical_appearance:The image shows a drawing. The lines drawn are all black in colour. The drawing depicts the interior of an accomodation. An open book can be discerned to be lying on a bed. To the left\n a suitcase is placed adjacent to a cupboard. There is a sink\n a table with a lamp on it\n and some cabinets. Shoes and some bottles can be seen on the floor. The background of the drawing depicts a window with curtains.\nsubject_terms_1:dwellings\nsubject_terms_2:Drawings London (England) Dwellings\nsubject_terms_3:Drawing Visual arts\nsubject_terms_4:London (inhabited place)\nsgcool_label_text:Tan Choon Ghee was born in Penang in 1930. He travelled to Singapore in the late 1940s to enrol at the Nanyang Academy of Fine Arts (NAFA)\n graduating in 1951. He went on to further his studies at the Slade School of Fine Art in London from 1957-1959. He was subsequently awarded a scholarship from the German government to study art in Germany. During this time\n he travelled extensively in Europe before returning to Penang to settle in 1969.\\r\\n\\r\\nTan is noted as being influenced by fellow Penang-based artist Kuo Ju Ping (1908-1966)\n who had graduated from NAFA earlier in 1940\n as well as other masters of his favoured medium of watercolour\n such as Yong Mun Sen (1896-1962) and Abdullah Ariff (1904-1962).\\r\\n\\r\\nAs a key second generation artist working primarily in the medium of watercolour\n Tan is known for his deft application of ink and colour on paper. He painted a large number of works during his time spent in Europe\n where he was continually drawn to the lively waterways of Europe such as in Venice\n Rotterdam\n and London.","createdDate":"20201018182637","version":0,"latest":false,"roles":[],"metadata":{"accession_no_csv":"2018-00479","Image":"","object_work_type":"drawings (visual works)","title_text":"Untitled (Accommodation in London)","preference":"main","title_language":"","creator_2":"Choon Ghee Tan","creator_1":"Tan, Choon Ghee, 1930- Tan, Choon Ghee","creator_role":"artists (visual artists)","creation_date":"1960","creation_place_original_location":"Singapore (nation) Pulau Pinang (state)","styles_periods_indexing_terms":"Not indicated","inscriptions":"","inscription_language":"","scale_type":"Not indicated","shape":"rectangular","materials_name":"paper (fiber product) ink","techniques_name":"creating (artistic activity) drawing (image-making)","object_colour":"black (colour)","physical_appearance":"The image shows a drawing. The lines drawn are all black in colour. The drawing depicts the interior of an accomodation. An open book can be discerned to be lying on a bed. To the left, a suitcase is placed adjacent to a cupboard. There is a sink, a table with a lamp on it, and some cabinets. Shoes and some bottles can be seen on the floor. The background of the drawing depicts a window with curtains.","subject_terms_1":"dwellings","subject_terms_2":"Drawings London (England) Dwellings","subject_terms_3":"Drawing Visual arts","subject_terms_4":"London (inhabited place)","sgcool_label_text":"Tan Choon Ghee was born in Penang in 1930. He travelled to Singapore in the late 1940s to enrol at the Nanyang Academy of Fine Arts (NAFA), graduating in 1951. He went on to further his studies at the Slade School of Fine Art in London from 1957-1959. He was subsequently awarded a scholarship from the German government to study art in Germany. During this time, he travelled extensively in Europe before returning to Penang to settle in 1969.\r\n\r\nTan is noted as being influenced by fellow Penang-based artist Kuo Ju Ping (1908-1966), who had graduated from NAFA earlier in 1940, as well as other masters of his favoured medium of watercolour, such as Yong Mun Sen (1896-1962) and Abdullah Ariff (1904-1962).\r\n\r\nAs a key second generation artist working primarily in the medium of watercolour, Tan is known for his deft application of ink and colour on paper. He painted a large number of works during his time spent in Europe, where he was continually drawn to the lively waterways of Europe such as in Venice, Rotterdam, and London."},"nlpDate":"20201018182637","connectorId":0,"tags":{}}