{"id":"2018-00150","title":"Photograph of four seated nyonyas","source":"Bumblebee","path":"./Data/json/","content":"accession_no_csv:2018-00150\nImage:\nobject_work_type:black-and-white photographs photographs\ntitle_text:Photograph of four seated nyonyas\npreference:main\ntitle_language:\ncreator_2:Not indicated\ncreator_1:Not indicated\ncreation_date:1860s-1870s\ncreation_place_original_location:Pulau Pinang (state)\ninscriptions:\ninscription_language:\nshape:rectangular\nmaterials_name:paper (fiber product)\ntechniques_name:printing (process) photographic processes\nobject_colour:grey monochrome\nphysical_appearance:The image shows a black-and-white photograph. It is rectangular and it features four women . All of them are sitting down and they are looking towards the direction in which the photograph was taken. A balustrade is situated behind them. They are all dressed in their ethnic costumes as well.\nsubject_terms_1:group portraits women (female humans) Peranakan folk costume\nsubject_terms_2:Black-and-white photography Portrait photography Portraits\n Group Ethnic costume Peranakan (Asian people) Women\nsubject_terms_3:Portrait photography Women Peranakan costumes\nsgcool_label_text:This photograph shows four nyonyas seated before a balustrade.\\r\\n\\r\\nStudios were already established across the Strait Settlements and the Dutch East Indies by the 1840s and became increasingly prevalent in the 1850s. During the 1920s\n Chinese-owned studios dominated the studio photography trade in Southeast Asia.","createdDate":"20201018182637","version":0,"latest":false,"roles":[],"metadata":{"accession_no_csv":"2018-00150","Image":"","object_work_type":"black-and-white photographs photographs","title_text":"Photograph of four seated nyonyas","preference":"main","title_language":"","creator_2":"Not indicated","creator_1":"Not indicated","creation_date":"1860s-1870s","creation_place_original_location":"Pulau Pinang (state)","inscriptions":"","inscription_language":"","shape":"rectangular","materials_name":"paper (fiber product)","techniques_name":"printing (process) photographic processes","object_colour":"grey monochrome","physical_appearance":"The image shows a black-and-white photograph. It is rectangular and it features four women . All of them are sitting down and they are looking towards the direction in which the photograph was taken. A balustrade is situated behind them. They are all dressed in their ethnic costumes as well.","subject_terms_1":"group portraits women (female humans) Peranakan folk costume","subject_terms_2":"Black-and-white photography Portrait photography Portraits, Group Ethnic costume Peranakan (Asian people) Women","subject_terms_3":"Portrait photography Women Peranakan costumes","sgcool_label_text":"This photograph shows four nyonyas seated before a balustrade.\r\n\r\nStudios were already established across the Strait Settlements and the Dutch East Indies by the 1840s and became increasingly prevalent in the 1850s. During the 1920s, Chinese-owned studios dominated the studio photography trade in Southeast Asia."},"nlpDate":"20201018182637","connectorId":0,"tags":{}}