{"id":"2018-00055-001","title":"Tough Job: Original Artwork Tough Job","source":"Bumblebee","path":"./Data/json/","content":"accession_no_csv:2018-00055-001\nImage:\nobject_work_type:digital prints prints (visual works)\ntitle_text:Tough Job: Original Artwork Tough Job\npreference:main alternate\ntitle_language:\ncreator_2:Tan Lip Seng\ncreator_1:Tan\n Lip Seng\n 1942- Tan\n Lip Seng\ncreator_role:photographers\ncreation_date:1968\ncreation_place_original_location:Singapore (nation)\nstyles_periods_indexing_terms:Not indicated\ninscriptions:\ninscription_language:\nscale_type:Not indicated\nshape:rectangular\nmaterials_name:photographic paper\ntechniques_name:photographic processes montage (image-making technique)\nobject_colour:multicoloured\nedition_description:1 of 3\nphysical_appearance:The image shows a digital print. It is rectangular in shape. The background of the digital print is purple in colour. It depicts a worker standing at the top of a wooden ramp. The worker is wearing a pink shirt and adorns a brown hat. Two pails are suspended from a shoulder yoke that is being carried by the worker.The background of the images depict the cloudless blue sky as well.\nsubject_terms_1:working workers\nsubject_terms_2:Digitally printed materials Colour prints Employees Work\nsubject_terms_3:Photography\nsgcool_label_text:This photograph by Singaporean photographer Tan Lip Seng was submitted to the Royal Photographic Society (UK) for his Fellowship application. This work is one of the examples of Tan\\u0027s innovative colour technique\n in which he creates a high contrast backdrop in order to bring out details of his subject matter. \\r\\n\\r\\nTan Lip Seng started his career as a medical photographer at the National University of Singapore. He was the first Singaporean to be awarded a fellowship by the Royal Photographic Society of the United Kingdom in 1970.","createdDate":"20201119143407","version":0,"latest":false,"roles":[],"metadata":{"accession_no_csv":"2018-00055-001","Image":"","object_work_type":"digital prints prints (visual works)","title_text":"Tough Job: Original Artwork Tough Job","preference":"main alternate","title_language":"","creator_2":"Tan Lip Seng","creator_1":"Tan, Lip Seng, 1942- Tan, Lip Seng","creator_role":"photographers","creation_date":"1968","creation_place_original_location":"Singapore (nation)","styles_periods_indexing_terms":"Not indicated","inscriptions":"","inscription_language":"","scale_type":"Not indicated","shape":"rectangular","materials_name":"photographic paper","techniques_name":"photographic processes montage (image-making technique)","object_colour":"multicoloured","edition_description":"1 of 3","physical_appearance":"The image shows a digital print. It is rectangular in shape. The background of the digital print is purple in colour. It depicts a worker standing at the top of a wooden ramp. The worker is wearing a pink shirt and adorns a brown hat. Two pails are suspended from a shoulder yoke that is being carried by the worker.The background of the images depict the cloudless blue sky as well.","subject_terms_1":"working workers","subject_terms_2":"Digitally printed materials Colour prints Employees Work","subject_terms_3":"Photography","sgcool_label_text":"This photograph by Singaporean photographer Tan Lip Seng was submitted to the Royal Photographic Society (UK) for his Fellowship application. This work is one of the examples of Tan\u0027s innovative colour technique, in which he creates a high contrast backdrop in order to bring out details of his subject matter. \r\n\r\nTan Lip Seng started his career as a medical photographer at the National University of Singapore. He was the first Singaporean to be awarded a fellowship by the Royal Photographic Society of the United Kingdom in 1970."},"nlpDate":"20201119143407","connectorId":0,"tags":{}}