{
  "id": "2018-00047-002",
  "title": "Under Construction: Artists\u0027 Proof Under Construction",
  "source": "Bumblebee",
  "path": "./Data/json/",
  "content": "\n  accession_no_csv: 2018-00047-002\n\n  Image: \n\n  object_work_type: proofs (prints by function) artists\\u0027 proofs\n\n  title_text: Under Construction: Artists\\u0027 Proof Under Construction\n\n  preference: main alternate\n\n  title_language: \n\n  creator_2: Tan Lip Seng\n\n  creator_1: Tan\n Lip Seng\n 1942- Tan\n Lip Seng\n\n  creator_role: photographers\n\n  creation_date: 1970\n\n  creation_place_original_location: Singapore (nation)\n\n  styles_periods_indexing_terms: Not indicated\n\n  inscriptions: \n\n  inscription_language: \n\n  scale_type: Not indicated\n\n  shape: rectangular\n\n  materials_name: metallic paper\n\n  techniques_name: printing (process) montage (image-making technique)\n\n  object_colour: multicoloured\n\n  edition_description: 1 of 3\n\n  physical_appearance: The image shows an artist\\u0027s proof. It is rectangular in shape. The proof is encased within a black frame. It features two construction workers at work. Both of them are wearing yellow helmets and gloves. They are standing at the top of a building structure\n and bending forwards with a wood plank in their hands.\n\n  subject_terms_1: construction workers working construction (assembling)\n\n  subject_terms_2: Construction workers Building Proofs (Printing) Work\n\n  subject_terms_3: Photography\n\n  sgcool_label_text: This photograph was taken by Singaporean photographer Tan Lip Seng. Tan is arguably the most important photographer in the region developing colour derivative and photo montage techniques. His works in the 1960s were a result of various experiments meticulously combining multiple colour transparencies into one to achieve the desired montage within one frame.\\r\\n\\r\\nTan spent 42 years as a medical photographer at the National University of Singapore. Many of his works have won numerous awards internationally and show a strong graphic and stylistic sensibility. Tan is also the first Singaporean to be awarded a fellowship by the Royal Photographic Society of the United Kingdom in 1970. Conferred the Cultural Medallion in 1985\n Tan recently published a retrospective of his works\n ‘Light \\u0026 Shadow: Tan Lip Seng’s 50 Years of Photography’ in 2009.\n",
  "createdDate": "20201125084511",
  "version": 0,
  "latest": false,
  "roles": [],
  "metadata": {
    "accession_no_csv": "2018-00047-002",
    "Image": "",
    "object_work_type": "proofs (prints by function) artists\u0027 proofs",
    "title_text": "Under Construction: Artists\u0027 Proof Under Construction",
    "preference": "main alternate",
    "title_language": "",
    "creator_2": "Tan Lip Seng",
    "creator_1": "Tan, Lip Seng, 1942- Tan, Lip Seng",
    "creator_role": "photographers",
    "creation_date": "1970",
    "creation_place_original_location": "Singapore (nation)",
    "styles_periods_indexing_terms": "Not indicated",
    "inscriptions": "",
    "inscription_language": "",
    "scale_type": "Not indicated",
    "shape": "rectangular",
    "materials_name": "metallic paper",
    "techniques_name": "printing (process) montage (image-making technique)",
    "object_colour": "multicoloured",
    "edition_description": "1 of 3",
    "physical_appearance": "The image shows an artist\u0027s proof. It is rectangular in shape. The proof is encased within a black frame. It features two construction workers at work. Both of them are wearing yellow helmets and gloves. They are standing at the top of a building structure, and bending forwards with a wood plank in their hands.",
    "subject_terms_1": "construction workers working construction (assembling)",
    "subject_terms_2": "Construction workers Building Proofs (Printing) Work",
    "subject_terms_3": "Photography",
    "sgcool_label_text": "This photograph was taken by Singaporean photographer Tan Lip Seng. Tan is arguably the most important photographer in the region developing colour derivative and photo montage techniques. His works in the 1960s were a result of various experiments meticulously combining multiple colour transparencies into one to achieve the desired montage within one frame.\r\n\r\nTan spent 42 years as a medical photographer at the National University of Singapore. Many of his works have won numerous awards internationally and show a strong graphic and stylistic sensibility. Tan is also the first Singaporean to be awarded a fellowship by the Royal Photographic Society of the United Kingdom in 1970. Conferred the Cultural Medallion in 1985, Tan recently published a retrospective of his works, ‘Light \u0026 Shadow: Tan Lip Seng’s 50 Years of Photography’ in 2009."
  },
  "nlpDate": "20201125084511",
  "connectorId": 0,
  "tags": {}
}