{"id":"2018-00634","title":"Kampong Pasir Panjang","source":"Bumblebee","path":"./Data/json/","content":"accession_no_csv:2018-00634\nImage:\nobject_work_type:paintings (visual works) watercolors (paintings)\ntitle_text:Kampong Pasir Panjang\npreference:main\ntitle_language:\ncreator_2:Idris Mohd Ali\ncreator_1:Idris Mohamed Ali\ncreator_role:painters (artists)\ncreation_date:1965\ncreation_place_original_location:Singapore (nation)\ninscriptions:\ninscription_language:\nshape:rectangular\nmaterials_name:watercolor (paint) gouache (paint) paper (fiber product)\ntechniques_name:watercolour painting (technique)\nobject_colour:multicolored\nphysical_appearance:This is a watercolour painting. It is landscape in orientation. It features a scene of Kampong Pasir Panjang. There is a roofed house on stilts in the center of the painting. It is surrounded by trees and vegetation. On the left\n there is a rough silhoutte of a person at the front of the house. There is a signature in black on the bottom left\n with a year indicated.\nsubject_terms_1:dwellings rural areas  stilts houses\nsubject_terms_2:Watercolor painting Singapore Landscapes\nsubject_terms_3:Pasir Panjang Idris Mohamed Ali Visual arts Heritage and Culture\nsubject_terms_4:Singapore (nation) Pasir Panjang (inhabited place)\nsgcool_label_text:Known for his watercolour landscapes and street scenes\n Idris Mohamed Ali’s works reveal a strong understanding of colour\n depth and realism. His paintings of old Singapore are especially important as they serve as a visual documentation of our national heritage. \\r\\nStarted painting at 10 and not being able to afford formal art training\n Idris learnt from books\n observation\n practice and a brief tutelage under pioneer Malay artist\n S. Mahdar. In 1962\n at the age of 18\n this self-taught artist had his first group exhibition at the Singapore Victoria Memoral Hall.\\r\\n\\r\\n","createdDate":"20201119143407","version":0,"latest":false,"roles":[],"metadata":{"accession_no_csv":"2018-00634","Image":"","object_work_type":"paintings (visual works) watercolors (paintings)","title_text":"Kampong Pasir Panjang","preference":"main","title_language":"","creator_2":"Idris Mohd Ali","creator_1":"Idris Mohamed Ali","creator_role":"painters (artists)","creation_date":"1965","creation_place_original_location":"Singapore (nation)","inscriptions":"","inscription_language":"","shape":"rectangular","materials_name":"watercolor (paint) gouache (paint) paper (fiber product)","techniques_name":"watercolour painting (technique)","object_colour":"multicolored","physical_appearance":"This is a watercolour painting. It is landscape in orientation. It features a scene of Kampong Pasir Panjang. There is a roofed house on stilts in the center of the painting. It is surrounded by trees and vegetation. On the left, there is a rough silhoutte of a person at the front of the house. There is a signature in black on the bottom left, with a year indicated.","subject_terms_1":"dwellings rural areas  stilts houses","subject_terms_2":"Watercolor painting Singapore Landscapes","subject_terms_3":"Pasir Panjang Idris Mohamed Ali Visual arts Heritage and Culture","subject_terms_4":"Singapore (nation) Pasir Panjang (inhabited place)","sgcool_label_text":"Known for his watercolour landscapes and street scenes, Idris Mohamed Ali’s works reveal a strong understanding of colour, depth and realism. His paintings of old Singapore are especially important as they serve as a visual documentation of our national heritage. \r\nStarted painting at 10 and not being able to afford formal art training, Idris learnt from books, observation, practice and a brief tutelage under pioneer Malay artist, S. Mahdar. In 1962, at the age of 18, this self-taught artist had his first group exhibition at the Singapore Victoria Memoral Hall.\r\n\r\n"},"nlpDate":"20201119143407","connectorId":0,"tags":{}}