{
  "id": "2018-00174",
  "title": "Photograph of Alice and Agnes Tan",
  "source": "Bumblebee",
  "path": "./Data/json/",
  "content": "\n  accession_no_csv: 2018-00174\n\n  Image: \n\n  object_work_type: photographs black-and-white photographs\n\n  title_text: Photograph of Alice and Agnes Tan\n\n  preference: main\n\n  title_language: \n\n  creator_2: Not indicated\n\n  creator_1: Not indicated\n\n  creation_date: 1998\n\n  creation_place_original_location: Singapore (nation)\n\n  inscriptions: \n\n  inscription_language: \n\n  shape: rectangular\n\n  materials_name: paper (fiber product)\n\n  techniques_name: printing (process) photographic processes\n\n  object_colour: grey monochrome\n\n  physical_appearance: The image shows a black-and-white photograph. It is rectangular and it features two ladies. Both of them are looking towards the direction where the photograph was captured. They have their arms around one another. They are standing on a carpeted floor. The background of the photograph shows the interior of a house. Chairs\n table\n and a wall clock can be seen.\n\n  subject_terms_1: women (female humans) Peranakan double portraits folk costume\n\n  subject_terms_2: Ethnic costume Peranakan (Asian people) Portrait photography Black-and-white photography Women\n\n  subject_terms_3: Portrait photography Peranakan costumes Women\n\n  sgcool_label_text: This photograph shows Alice and Agnes Tan\n daughters of prominent Malayan Peranakan politician and businessman  Tun Dato\\u0027 Sir Tan Cheng Lock\n posing inside a house.\n",
  "createdDate": "20201201203307",
  "version": 0,
  "latest": false,
  "roles": [],
  "metadata": {
    "accession_no_csv": "2018-00174",
    "Image": "",
    "object_work_type": "photographs black-and-white photographs",
    "title_text": "Photograph of Alice and Agnes Tan",
    "preference": "main",
    "title_language": "",
    "creator_2": "Not indicated",
    "creator_1": "Not indicated",
    "creation_date": "1998",
    "creation_place_original_location": "Singapore (nation)",
    "inscriptions": "",
    "inscription_language": "",
    "shape": "rectangular",
    "materials_name": "paper (fiber product)",
    "techniques_name": "printing (process) photographic processes",
    "object_colour": "grey monochrome",
    "physical_appearance": "The image shows a black-and-white photograph. It is rectangular and it features two ladies. Both of them are looking towards the direction where the photograph was captured. They have their arms around one another. They are standing on a carpeted floor. The background of the photograph shows the interior of a house. Chairs, table, and a wall clock can be seen.",
    "subject_terms_1": "women (female humans) Peranakan double portraits folk costume",
    "subject_terms_2": "Ethnic costume Peranakan (Asian people) Portrait photography Black-and-white photography Women",
    "subject_terms_3": "Portrait photography Peranakan costumes Women",
    "sgcool_label_text": "This photograph shows Alice and Agnes Tan, daughters of prominent Malayan Peranakan politician and businessman  Tun Dato\u0027 Sir Tan Cheng Lock, posing inside a house."
  },
  "nlpDate": "20201201203307",
  "connectorId": 0,
  "tags": {}
}