{"id":"2018-00046-002","title":"Three Workers: Artists\u0027 Proof Three Workers","source":"Bumblebee","path":"./Data/json/","content":"accession_no_csv:2018-00046-002\nImage:\nobject_work_type:artists\\u0027 proofs proofs (prints by function)\ntitle_text:Three Workers: Artists\\u0027 Proof Three Workers\npreference:main alternate\ntitle_language:\ncreator_2:Tan Lip Seng\ncreator_1:Tan\n Lip Seng\n 1942- Tan\n Lip Seng\ncreator_role:photographers\ncreation_date:1965\ncreation_place_original_location:Singapore (nation)\nstyles_periods_indexing_terms:Not indicated\ninscriptions:\ninscription_language:\nscale_type:Not indicated\nshape:rectangular\nmaterials_name:metallic paper\ntechniques_name:printing (process) montage (image-making technique)\nobject_colour:multicoloured\nedition_description:1 of 3\nphysical_appearance:The image shows an artist\\u0027s proof. It is rectangular in shape. The proof is encased within a black frame. The backs of three women are facing the direction in which the artist\\u0027s proof was captured. All of them are wearing headscarfs and shoes. The background of the artist\\u0027s proof shows a building. The first level of the building contains running rectangular patterns along its wall. There are numerous cracks along the concrete\n above the base of the building. The ground in which the three women are walking on contains numerous stones. It is also uneven.\nsubject_terms_1:workers women (female humans)\nsubject_terms_2:Employees Women Proofs (Printing)\nsubject_terms_3:Women Photography\nsgcool_label_text:This photograph was taken by Singaporean photographer Tan Lip Seng. Tan is arguably the most important photographer in the region developing colour derivative and photo montage techniques. His works in the 1960s were a result of various experiments meticulously combining multiple colour transparencies into one to achieve the desired montage within one frame.\\r\\n\\r\\nTan spent 42 years as a medical photographer at the National University of Singapore. Many of his works have won numerous awards internationally and show a strong graphic and stylistic sensibility.","createdDate":"20201018182637","version":0,"latest":false,"roles":[],"metadata":{"accession_no_csv":"2018-00046-002","Image":"","object_work_type":"artists\u0027 proofs proofs (prints by function)","title_text":"Three Workers: Artists\u0027 Proof Three Workers","preference":"main alternate","title_language":"","creator_2":"Tan Lip Seng","creator_1":"Tan, Lip Seng, 1942- Tan, Lip Seng","creator_role":"photographers","creation_date":"1965","creation_place_original_location":"Singapore (nation)","styles_periods_indexing_terms":"Not indicated","inscriptions":"","inscription_language":"","scale_type":"Not indicated","shape":"rectangular","materials_name":"metallic paper","techniques_name":"printing (process) montage (image-making technique)","object_colour":"multicoloured","edition_description":"1 of 3","physical_appearance":"The image shows an artist\u0027s proof. It is rectangular in shape. The proof is encased within a black frame. The backs of three women are facing the direction in which the artist\u0027s proof was captured. All of them are wearing headscarfs and shoes. The background of the artist\u0027s proof shows a building. The first level of the building contains running rectangular patterns along its wall. There are numerous cracks along the concrete, above the base of the building. The ground in which the three women are walking on contains numerous stones. It is also uneven.","subject_terms_1":"workers women (female humans)","subject_terms_2":"Employees Women Proofs (Printing)","subject_terms_3":"Women Photography","sgcool_label_text":"This photograph was taken by Singaporean photographer Tan Lip Seng. Tan is arguably the most important photographer in the region developing colour derivative and photo montage techniques. His works in the 1960s were a result of various experiments meticulously combining multiple colour transparencies into one to achieve the desired montage within one frame.\r\n\r\nTan spent 42 years as a medical photographer at the National University of Singapore. Many of his works have won numerous awards internationally and show a strong graphic and stylistic sensibility."},"nlpDate":"20201018182637","connectorId":0,"tags":{}}