{"id":"2018-00600","title":"Type 0 Civilization","source":"Bumblebee","path":"./Data/json/","content":"accession_no_csv:2018-00600\nImage:\nobject_work_type:paintings (visual works)\ntitle_text:Type 0 Civilization\npreference:main\ntitle_language:\ncreator_2:Ruben Pang\ncreator_1:Pang\n Ruben\ncreator_role:artists (visual artists)\ncreation_date:2016-2017\ncreation_place_original_location:Singapore (nation)\ninscriptions:\ninscription_language:\nshape:rectangular\nmaterials_name:oil paint (paint) alkyd paint varnish aluminium alloy\ntechniques_name:painting (image-making)\nobject_colour:multicoloured\nedition_description:Unique\nphysical_appearance:This is a painting. It is portrait in orientation. The painting is an abstract piece\n featuring multicoloured\n strong brushstrokes. There are no signatures seen on the painting.\nsubject_terms_1:abstract (general art genre) symbolism (artistic concept) energy\nsubject_terms_2:Rubens\n Peter Paul\n 1577-1640 Symbolism Humanity Apocalypse in art Energy\nsubject_terms_3:Painting\nsgcool_label_text:Working with the medium of painting for more than a decade now\n Ruben Pang is a young Singaporean artist who has gained significant recognition for his abstract works. Paintings from Pang possess an almost musical quality – through his brushstrokes and erasure of the paint that has been applied\n the colours presented upon his wood\n canvas\n or aluminum panels reflect the musical qualities of counterpoint and harmony\n even as he delves into themes of apocalypse and chaos. \\r\\n\\r\\nType 0 Civilisation is a work inspired from Pang’s travels to Europe where he encountered works of western masters\n such as\n John Martin\n Gerhard Richter\n and Peter Paul Rubens.  Especially drawn to apocalyptic scenes\n Type 0 Civilisation is Ruben Pang’s re-capturing of Peter Paul Rubens’ iconic work\n The Fall of The Damned. Executing the work intuitively\n Pang sought to extract the essence of the work from classical painterly principles of light and shadow. Contrasting the deliberate and planned methodologies utilized by Rubens\n Type 0 Civilisation\n like numerous of Pang’s other works was executed in a style that can be best described as a stream of consciousness. With no pre-determined goal in mind\n Pang’s brushstrokes are led by intuition\n reflex\n and accident. \\r\\n\\r\\nThe work’s title references the expanded Kardashev scale\n a system of measuring a civilization’s technical advancement based on its ability to harness and store energy. The original Kardashev scale ranges Type I\n Type II\n and Type III\n each corresponding to planetary\n stellar\n and galactic civilisations; the expanded scale’s inclusion of a Type 0 references our planet’s current state of advancement. In this regard\n one may perhaps draw a mirroring between the Archangel Michael’s casting of the fallen angels from the heavens and humanity’s current desire for technological advancement – where the unfettered thirst for power are paths leading to potential ruin. \\r\\n","createdDate":"20201018182637","version":0,"latest":false,"roles":[],"metadata":{"accession_no_csv":"2018-00600","Image":"","object_work_type":"paintings (visual works)","title_text":"Type 0 Civilization","preference":"main","title_language":"","creator_2":"Ruben Pang","creator_1":"Pang, Ruben","creator_role":"artists (visual artists)","creation_date":"2016-2017","creation_place_original_location":"Singapore (nation)","inscriptions":"","inscription_language":"","shape":"rectangular","materials_name":"oil paint (paint) alkyd paint varnish aluminium alloy","techniques_name":"painting (image-making)","object_colour":"multicoloured","edition_description":"Unique","physical_appearance":"This is a painting. It is portrait in orientation. The painting is an abstract piece, featuring multicoloured, strong brushstrokes. There are no signatures seen on the painting.","subject_terms_1":"abstract (general art genre) symbolism (artistic concept) energy","subject_terms_2":"Rubens, Peter Paul, 1577-1640 Symbolism Humanity Apocalypse in art Energy","subject_terms_3":"Painting","sgcool_label_text":"Working with the medium of painting for more than a decade now, Ruben Pang is a young Singaporean artist who has gained significant recognition for his abstract works. Paintings from Pang possess an almost musical quality – through his brushstrokes and erasure of the paint that has been applied, the colours presented upon his wood, canvas, or aluminum panels reflect the musical qualities of counterpoint and harmony, even as he delves into themes of apocalypse and chaos. \r\n\r\nType 0 Civilisation is a work inspired from Pang’s travels to Europe where he encountered works of western masters, such as, John Martin, Gerhard Richter, and Peter Paul Rubens.  Especially drawn to apocalyptic scenes, Type 0 Civilisation is Ruben Pang’s re-capturing of Peter Paul Rubens’ iconic work, The Fall of The Damned. Executing the work intuitively, Pang sought to extract the essence of the work from classical painterly principles of light and shadow. Contrasting the deliberate and planned methodologies utilized by Rubens, Type 0 Civilisation, like numerous of Pang’s other works was executed in a style that can be best described as a stream of consciousness. With no pre-determined goal in mind, Pang’s brushstrokes are led by intuition, reflex, and accident. \r\n\r\nThe work’s title references the expanded Kardashev scale, a system of measuring a civilization’s technical advancement based on its ability to harness and store energy. The original Kardashev scale ranges Type I, Type II, and Type III, each corresponding to planetary, stellar, and galactic civilisations; the expanded scale’s inclusion of a Type 0 references our planet’s current state of advancement. In this regard, one may perhaps draw a mirroring between the Archangel Michael’s casting of the fallen angels from the heavens and humanity’s current desire for technological advancement – where the unfettered thirst for power are paths leading to potential ruin. \r\n"},"nlpDate":"20201018182637","connectorId":0,"tags":{}}