{"id":"2018-00027-001","title":"Drawing Book of Han Hong Yoe","source":"Bumblebee","path":"./Data/json/","content":"accession_no_csv:2018-00027-001\nImage:\nobject_work_type:hardcover books\ntitle_text:Drawing Book of Han Hong Yoe\npreference:main\ntitle_language:\ncreator_2:Han Hong Yoe\ncreator_1:Not indicated\ncreator_role:authors\ncreation_date:early 20th century\ncreation_place_original_location:Malang (inhabited place)\ninscriptions:\ninscription_language:\nshape:rectangular\nmaterials_name:printing paper book cloth (textile material)\ntechniques_name:colour printing bookbinding (process) illustration (process)\nobject_colour:multicoloured\nphysical_appearance:\\The image shows the front two pages of a hardcover book. The page on the left contains a picture of a man.. On the page to the left\n there are numerous colourful drawings of flowers. Above the picture of the man\n there are scrolls with Chinese characters and Dutch words on them. \\\\Han Hong Yoe\\\\ is stated at the bottom on the page to the left in a scroll as well. The page on the right features a drawing of a man and a body of text.\\\nsubject_terms_1:illustrated books drawings (visual wotks) flower (motif)\nsubject_terms_2:Drawing books Drawings Motifs\nsubject_terms_3:Drawing\nsgcool_label_text:The book contains various tracings and painted illustrations. Its first page is filled with colourful flowers around a photograph of a man\n probably the author. Flowing scrolls are inscribed with ‘Schilder Boeken’ (painting books) and ‘Van heer – Han Hong Yoe’. \\r\\n\\r\\nIn Indonesia\n photography studios were established by the Chinese as early as the last decade of the 19th century. Many of these were established by recent immigrants from China and came to rival the European-owned studios which dominated the market. \\r\\n","createdDate":"20201018182637","version":0,"latest":false,"roles":[],"metadata":{"accession_no_csv":"2018-00027-001","Image":"","object_work_type":"hardcover books","title_text":"Drawing Book of Han Hong Yoe","preference":"main","title_language":"","creator_2":"Han Hong Yoe","creator_1":"Not indicated","creator_role":"authors","creation_date":"early 20th century","creation_place_original_location":"Malang (inhabited place)","inscriptions":"","inscription_language":"","shape":"rectangular","materials_name":"printing paper book cloth (textile material)","techniques_name":"colour printing bookbinding (process) illustration (process)","object_colour":"multicoloured","physical_appearance":"\"The image shows the front two pages of a hardcover book. The page on the left contains a picture of a man.. On the page to the left, there are numerous colourful drawings of flowers. Above the picture of the man, there are scrolls with Chinese characters and Dutch words on them. \"\"Han Hong Yoe\"\" is stated at the bottom on the page to the left in a scroll as well. The page on the right features a drawing of a man and a body of text.\"","subject_terms_1":"illustrated books drawings (visual wotks) flower (motif)","subject_terms_2":"Drawing books Drawings Motifs","subject_terms_3":"Drawing","sgcool_label_text":"The book contains various tracings and painted illustrations. Its first page is filled with colourful flowers around a photograph of a man, probably the author. Flowing scrolls are inscribed with ‘Schilder Boeken’ (painting books) and ‘Van heer – Han Hong Yoe’. \r\n\r\nIn Indonesia, photography studios were established by the Chinese as early as the last decade of the 19th century. Many of these were established by recent immigrants from China and came to rival the European-owned studios which dominated the market. \r\n"},"nlpDate":"20201018182637","connectorId":0,"tags":{}}