{
  "id": "2018-00048-003",
  "title": "Two Workers Two Workers: Original Transparency Slide",
  "source": "Bumblebee",
  "path": "./Data/json/",
  "content": "\n  accession_no_csv: 2018-00048-003\n\n  Image: \n\n  object_work_type: colour slides slides (photographs)\n\n  title_text: Two Workers Two Workers: Original Transparency Slide\n\n  preference: main alternate\n\n  title_language: \n\n  creator_2: Tan Lip Seng\n\n  creator_1: Tan\n Lip Seng\n 1942- Tan\n Lip Seng\n\n  creator_role: photographers\n\n  creation_date: 1968\n\n  creation_place_original_location: Singapore (nation)\n\n  styles_periods_indexing_terms: Not indicated\n\n  inscriptions: \n\n  inscription_language: \n\n  scale_type: Not indicated\n\n  shape: rectangular\n\n  materials_name: photographic film (photographic materials)\n\n  techniques_name: photographic processes\n\n  object_colour: multicoloured\n\n  edition_description: 1 of 3\n\n  physical_appearance: \\The image on the right shows a slide. It is in colour. It is held in place by a frame. On the borders of the frame\n \\\\Under Construction\\\\ is stated at the top for the image at the bottom. On the borders of the frame\n\n  subject_terms_1: \\\\Two Workers\\\\ is stated at the bottom for the image at the bottom. \\\\Tan Lip Seng\n\n  subject_terms_2: A.R.P.S. AFIAP Employees\n\n  subject_terms_3: 96A Tiong Bahru Road. Singapore 3\\\\ is stated at the bottom for the image at the bottom. \\\n\n  subject_terms_4: workers\n\n  context_1: Slides (photography)\n\n  context_2: Photography\n",
  "createdDate": "20201201203307",
  "version": 0,
  "latest": false,
  "roles": [],
  "metadata": {
    "accession_no_csv": "2018-00048-003",
    "Image": "",
    "object_work_type": "colour slides slides (photographs)",
    "title_text": "Two Workers Two Workers: Original Transparency Slide",
    "preference": "main alternate",
    "title_language": "",
    "creator_2": "Tan Lip Seng",
    "creator_1": "Tan, Lip Seng, 1942- Tan, Lip Seng",
    "creator_role": "photographers",
    "creation_date": "1968",
    "creation_place_original_location": "Singapore (nation)",
    "styles_periods_indexing_terms": "Not indicated",
    "inscriptions": "",
    "inscription_language": "",
    "scale_type": "Not indicated",
    "shape": "rectangular",
    "materials_name": "photographic film (photographic materials)",
    "techniques_name": "photographic processes",
    "object_colour": "multicoloured",
    "edition_description": "1 of 3",
    "physical_appearance": "\"The image on the right shows a slide. It is in colour. It is held in place by a frame. On the borders of the frame, \"\"Under Construction\"\" is stated at the top for the image at the bottom. On the borders of the frame",
    "subject_terms_1": "\"\"Two Workers\"\" is stated at the bottom for the image at the bottom. \"\"Tan Lip Seng",
    "subject_terms_2": "A.R.P.S. AFIAP Employees",
    "subject_terms_3": "96A Tiong Bahru Road. Singapore 3\"\" is stated at the bottom for the image at the bottom. \"",
    "subject_terms_4": "workers",
    "context_1": "Slides (photography)",
    "context_2": "Photography"
  },
  "nlpDate": "20201201203307",
  "connectorId": 0,
  "tags": {}
}