{
  "id": "2018-00161",
  "title": "Carte de Visite of an Indies lady in morning house dress",
  "source": "Bumblebee",
  "path": "./Data/json/",
  "content": "\n  accession_no_csv: 2018-00161\n\n  Image: \n\n  object_work_type: photographs black-and-white photographs\n\n  title_text: Carte de Visite of an Indies lady in morning house dress\n\n  preference: main\n\n  title_language: \n\n  creator_2: Not indicated\n\n  creator_1: Not indicated\n\n  creation_date: Late 19th century\n\n  creation_place_original_location: Indonesia (nation)\n\n  inscriptions: \n\n  inscription_language: \n\n  shape: rectangular\n\n  materials_name: paper (fiber product)\n\n  techniques_name: printing (process) photographic processes\n\n  object_colour: grey monochrome\n\n  physical_appearance: The image shows a black-and-white photograph. It is rectangular and it features a lady. She is sitting down on  a chair with high back support and looking towards the direction where the photograph was captured. She is wearing a blouse and a long skirt. There are potted plants at the right hand side of the photograph.\n\n  subject_terms_1: women (female humans) black-and-white photographs housedresses studio portraits\n\n  subject_terms_2: Dresses Portrait photography Black-and-white photography Women\n\n  subject_terms_3: Portrait photography Women\n\n  sgcool_label_text: This carte de visite shows an Indies lady (a European or Eurasian woman) in Indies house dress. It is inscribed “Indische Dame in Morgen-gesp. Haus Kleide” on the border. \\r\\n\\r\\nStudios were already established across the Strait Settlements and the Dutch East Indies by the 1840s and became increasingly prevalent in the 1850s. During the 1920s\n Chinese-owned studios dominated the studio photography trade in Southeast Asia.\n",
  "createdDate": "20201125084510",
  "version": 0,
  "latest": false,
  "roles": [],
  "metadata": {
    "accession_no_csv": "2018-00161",
    "Image": "",
    "object_work_type": "photographs black-and-white photographs",
    "title_text": "Carte de Visite of an Indies lady in morning house dress",
    "preference": "main",
    "title_language": "",
    "creator_2": "Not indicated",
    "creator_1": "Not indicated",
    "creation_date": "Late 19th century",
    "creation_place_original_location": "Indonesia (nation)",
    "inscriptions": "",
    "inscription_language": "",
    "shape": "rectangular",
    "materials_name": "paper (fiber product)",
    "techniques_name": "printing (process) photographic processes",
    "object_colour": "grey monochrome",
    "physical_appearance": "The image shows a black-and-white photograph. It is rectangular and it features a lady. She is sitting down on  a chair with high back support and looking towards the direction where the photograph was captured. She is wearing a blouse and a long skirt. There are potted plants at the right hand side of the photograph.",
    "subject_terms_1": "women (female humans) black-and-white photographs housedresses studio portraits",
    "subject_terms_2": "Dresses Portrait photography Black-and-white photography Women",
    "subject_terms_3": "Portrait photography Women",
    "sgcool_label_text": "This carte de visite shows an Indies lady (a European or Eurasian woman) in Indies house dress. It is inscribed “Indische Dame in Morgen-gesp. Haus Kleide” on the border. \r\n\r\nStudios were already established across the Strait Settlements and the Dutch East Indies by the 1840s and became increasingly prevalent in the 1850s. During the 1920s, Chinese-owned studios dominated the studio photography trade in Southeast Asia."
  },
  "nlpDate": "20201125084510",
  "connectorId": 0,
  "tags": {}
}