{"id":"2018-00119","title":"Photograph of a Chinese grave guarded by four lion statues","source":"Bumblebee","path":"./Data/json/","content":"accession_no_csv:2018-00119\nImage:\nobject_work_type:black-and-white photographs photographs\ntitle_text:Photograph of a Chinese grave guarded by four lion statues\npreference:main\ntitle_language:\ncreator_2:G.R. Lambert \\u0026 Company\ncreator_1:G.R. Lambert \\u0026 Co.\ncreator_role:photography studios (organizations)\ncreation_date:1900\ncreation_place_original_location:Singapore (nation)\ninscriptions:\ninscription_language:\nshape:rectangular\nmaterials_name:paper (fiber product)\ntechniques_name:printing (process) photographic processes\nobject_colour:grey monochrome\nphysical_appearance:The image shows a black-and-white photograph. It is rectangular and it features a grave in the foreground. There are steps leading up to the raised stone platform where the tombstone is placed. There are two lion statues each\n on both sides of the tombstone. The background features a field with greenery. Tall trees can also be seen.\nsubject_terms_1:tombs statues\nsubject_terms_2:Black-and-white photography Tombs Statues\nsubject_terms_3:Photography Tombs\nsgcool_label_text:This photograph shows a Chinese grave guarded by four large lion statues. ‘4/2 Chinese Grave’ is inscribed on the photograph. This photograph was probably taken by G.R. Lambert and Co.\\r\\n\\r\\nG.R. Lambert and Co was a leading and the most enduring of the European photography studios in Singapore. The studio was established in 1867 by Gustave Richard Lambert\n who was originally from Dresden\n Germany. Popular among the elites\n the firm was often chosen as the official photographers for important state events in Singapore. In 1861 it was appointed as the official photographer of the King of Siam and the Sultan of Johore.","createdDate":"20201018182637","version":0,"latest":false,"roles":[],"metadata":{"accession_no_csv":"2018-00119","Image":"","object_work_type":"black-and-white photographs photographs","title_text":"Photograph of a Chinese grave guarded by four lion statues","preference":"main","title_language":"","creator_2":"G.R. Lambert \u0026 Company","creator_1":"G.R. Lambert \u0026 Co.","creator_role":"photography studios (organizations)","creation_date":"1900","creation_place_original_location":"Singapore (nation)","inscriptions":"","inscription_language":"","shape":"rectangular","materials_name":"paper (fiber product)","techniques_name":"printing (process) photographic processes","object_colour":"grey monochrome","physical_appearance":"The image shows a black-and-white photograph. It is rectangular and it features a grave in the foreground. There are steps leading up to the raised stone platform where the tombstone is placed. There are two lion statues each, on both sides of the tombstone. The background features a field with greenery. Tall trees can also be seen.","subject_terms_1":"tombs statues","subject_terms_2":"Black-and-white photography Tombs Statues","subject_terms_3":"Photography Tombs","sgcool_label_text":"This photograph shows a Chinese grave guarded by four large lion statues. ‘4/2 Chinese Grave’ is inscribed on the photograph. This photograph was probably taken by G.R. Lambert and Co.\r\n\r\nG.R. Lambert and Co was a leading and the most enduring of the European photography studios in Singapore. The studio was established in 1867 by Gustave Richard Lambert, who was originally from Dresden, Germany. Popular among the elites, the firm was often chosen as the official photographers for important state events in Singapore. In 1861 it was appointed as the official photographer of the King of Siam and the Sultan of Johore."},"nlpDate":"20201018182637","connectorId":0,"tags":{}}