{"id":"2018-00151","title":"Photograph of two nyonyas and three children","source":"Bumblebee","path":"./Data/json/","content":"accession_no_csv:2018-00151\nImage:\nobject_work_type:black-and-white photographs photographs\ntitle_text:Photograph of two nyonyas and three children\npreference:main\ntitle_language:\ncreator_2:Not indicated\ncreator_1:Not indicated\ncreation_date:1870s-1890s\ncreation_place_original_location:Straits Settlement (former territory/colony/dependent state)\ninscriptions:\ninscription_language:\nshape:rectangular\nmaterials_name:paper (fiber product)\ntechniques_name:printing (process) photographic processes\nobject_colour:grey monochrome\nphysical_appearance:The image shows a black-and-white photograph. It is rectangular and it features two ladies and three children. The two women are sitting down while the three children are standing up\n one on either side of the adults and the third in the middle. All of them are looking towards the direction in which the photograph was captured. They are all dressed in their ethnic costumes. The boy on the left hand side has his headdress on.\nsubject_terms_1:group portraits Peranakan folk costume women (female humans) children (people by age group)\nsubject_terms_2:Black-and-white photography Portrait photography Portraits\n Group Ethnic costume Peranakan (Asian people) Women Children\nsubject_terms_3:Portrait photography Peranakan costumes Chinese costumes Women Children\nsgcool_label_text:This photograph shows two nyonyas seated between three children. The two young girls wear machine-printed baju panjangs\n while the boy is dressed in Chinese robes.\\r\\n\\r\\nStudios were already established across the Strait Settlements and the Dutch East Indies by the 1840s and became increasingly prevalent in the 1850s. During the 1920s\n Chinese-owned studios dominated the studio photography trade in Southeast Asia.","createdDate":"20201018182637","version":0,"latest":false,"roles":[],"metadata":{"accession_no_csv":"2018-00151","Image":"","object_work_type":"black-and-white photographs photographs","title_text":"Photograph of two nyonyas and three children","preference":"main","title_language":"","creator_2":"Not indicated","creator_1":"Not indicated","creation_date":"1870s-1890s","creation_place_original_location":"Straits Settlement (former territory/colony/dependent state)","inscriptions":"","inscription_language":"","shape":"rectangular","materials_name":"paper (fiber product)","techniques_name":"printing (process) photographic processes","object_colour":"grey monochrome","physical_appearance":"The image shows a black-and-white photograph. It is rectangular and it features two ladies and three children. The two women are sitting down while the three children are standing up, one on either side of the adults and the third in the middle. All of them are looking towards the direction in which the photograph was captured. They are all dressed in their ethnic costumes. The boy on the left hand side has his headdress on.","subject_terms_1":"group portraits Peranakan folk costume women (female humans) children (people by age group)","subject_terms_2":"Black-and-white photography Portrait photography Portraits, Group Ethnic costume Peranakan (Asian people) Women Children","subject_terms_3":"Portrait photography Peranakan costumes Chinese costumes Women Children","sgcool_label_text":"This photograph shows two nyonyas seated between three children. The two young girls wear machine-printed baju panjangs, while the boy is dressed in Chinese robes.\r\n\r\nStudios were already established across the Strait Settlements and the Dutch East Indies by the 1840s and became increasingly prevalent in the 1850s. During the 1920s, Chinese-owned studios dominated the studio photography trade in Southeast Asia."},"nlpDate":"20201018182637","connectorId":0,"tags":{}}