{"id":"2018-00474","title":"Venice","source":"Bumblebee","path":"./Data/json/","content":"accession_no_csv:2018-00474\nImage:\nobject_work_type:watercolours (paintings) paintings (visual works)\ntitle_text:Venice\npreference:main\ntitle_language:\ncreator_2:Choon Ghee Tan\ncreator_1:Tan\n Choon Ghee\n 1930- Tan\n Choon Ghee\ncreator_role:artists (visual artists)\ncreation_date:1960\ncreation_place_original_location:Singapore (nation) Pulau Pinang (state)\nstyles_periods_indexing_terms:Not indicated\ninscriptions:\ninscription_language:\nscale_type:Not indicated\nshape:rectangular\nmaterials_name:paper (fiber product) watercolour (paint)\ntechniques_name:watercolour painting (technique) creating (artistic activity)\nobject_colour:multicoloured\nphysical_appearance:The image shows a painting. It is rectangular in shape. The background of the painting shows a large building. It has dome shaped windows as well as balustrades on all of its levels. Several other buildings can be seen further in the background of the painting. At the foreground\n there is a waterway and people can be seen atop the boats. Some of them are sitting down while others are rowing the boats.\nsubject_terms_1:waterways buildings (structures) boats\nsubject_terms_2:Watercolour painting Venice (Italy) Waterways Buildings Boats and boating\nsubject_terms_3:Watercolour Painting Visual arts Waterways Buildings\nsubject_terms_4:Venice (inhabited place)\nsgcool_label_text:Tan Choon Ghee was born in Penang in 1930. He travelled to Singapore in the late 1940s to enrol at the Nanyang Academy of Fine Arts (NAFA)\n graduating in 1951. He went on to further his studies at the Slade School of Fine Art in London from 1957-1959. He was subsequently awarded a scholarship from the German government to study art in Germany. During this time\n he travelled extensively in Europe before returning to Penang to settle in 1969.\\r\\n\\r\\nTan is noted as being influenced by fellow Penang-based artist Kuo Ju Ping (1908-1966)\n who had graduated from NAFA earlier in 1940\n and masters of his favoured medium of watercolour\n such as Yong Mun Sen (1896-1962) and Abdullah Ariff (1904-1962).\\r\\n\\r\\nAs a key second generation artist working primarily in the medium of watercolour\n Tan is known for his deft application of watercolour and ink on paper. He painted a large number of works during his time spent in Europe\n and was particularly inspired by the distinctive architectural features of Venice set against its iconic waterways that Tan would seek to capture repeatedly in his art.","createdDate":"20201018182637","version":0,"latest":false,"roles":[],"metadata":{"accession_no_csv":"2018-00474","Image":"","object_work_type":"watercolours (paintings) paintings (visual works)","title_text":"Venice","preference":"main","title_language":"","creator_2":"Choon Ghee Tan","creator_1":"Tan, Choon Ghee, 1930- Tan, Choon Ghee","creator_role":"artists (visual artists)","creation_date":"1960","creation_place_original_location":"Singapore (nation) Pulau Pinang (state)","styles_periods_indexing_terms":"Not indicated","inscriptions":"","inscription_language":"","scale_type":"Not indicated","shape":"rectangular","materials_name":"paper (fiber product) watercolour (paint)","techniques_name":"watercolour painting (technique) creating (artistic activity)","object_colour":"multicoloured","physical_appearance":"The image shows a painting. It is rectangular in shape. The background of the painting shows a large building. It has dome shaped windows as well as balustrades on all of its levels. Several other buildings can be seen further in the background of the painting. At the foreground, there is a waterway and people can be seen atop the boats. Some of them are sitting down while others are rowing the boats.","subject_terms_1":"waterways buildings (structures) boats","subject_terms_2":"Watercolour painting Venice (Italy) Waterways Buildings Boats and boating","subject_terms_3":"Watercolour Painting Visual arts Waterways Buildings","subject_terms_4":"Venice (inhabited place)","sgcool_label_text":"Tan Choon Ghee was born in Penang in 1930. He travelled to Singapore in the late 1940s to enrol at the Nanyang Academy of Fine Arts (NAFA), graduating in 1951. He went on to further his studies at the Slade School of Fine Art in London from 1957-1959. He was subsequently awarded a scholarship from the German government to study art in Germany. During this time, he travelled extensively in Europe before returning to Penang to settle in 1969.\r\n\r\nTan is noted as being influenced by fellow Penang-based artist Kuo Ju Ping (1908-1966), who had graduated from NAFA earlier in 1940, and masters of his favoured medium of watercolour, such as Yong Mun Sen (1896-1962) and Abdullah Ariff (1904-1962).\r\n\r\nAs a key second generation artist working primarily in the medium of watercolour, Tan is known for his deft application of watercolour and ink on paper. He painted a large number of works during his time spent in Europe, and was particularly inspired by the distinctive architectural features of Venice set against its iconic waterways that Tan would seek to capture repeatedly in his art."},"nlpDate":"20201018182637","connectorId":0,"tags":{}}