{
  "id": "2018-00063",
  "title": "Matthaus Seutter\u0027s Flag Chart of the Seafaring Nations printed by Tobias Lotter",
  "source": "Bumblebee",
  "path": "./Data/json/",
  "content": "\n  accession_no_csv: 2018-00063\n\n  Image: \n\n  object_work_type: charts (graphic documents) graphic document genres\n\n  title_text: Matthaus Seutter\\u0027s Flag Chart of the Seafaring Nations printed by Tobias Lotter\n\n  preference: main\n\n  title_language: \n\n  creator_2: Georg Matthaus Seutter Tobias Lotter\n\n  creator_1: not indicated\n\n  creator_role: creators publishers\n\n  creation_date: c1760\n\n  creation_place_original_location: not indicated\n\n  styles_periods_indexing_terms: not indicated\n\n  inscriptions: \n\n  inscription_language: \n\n  shape: rectangular\n\n  materials_name: paper (fiber product)\n\n  techniques_name: papermaking copper engraving (printing process) hand coloring\n\n  object_colour: multicoloured\n\n  physical_appearance: This is a multicoloured flag chart of the seafaring nations created by Matthaus Seutter and printed by Tobias Lotter. The title of the chart can be seen in two lines of text in German at the top of the chart. A single line of text also appears on top of each of the 139 flags represented in the chart. There is also one line of text centralised at the bottom of the chart\n beneath all the flags.\n\n  subject_terms_1: flags identifying artefacts\n\n  subject_terms_2: Flags Identification\n\n  sgcool_label_text: This 18th century flag chart illustrates the flags of 139 seafaring nations. It was published by Tobias Lotter\n based on the work of his father-in-law Georg Matthaus Seutter.\n",
  "createdDate": "20201120223708",
  "version": 0,
  "latest": false,
  "roles": [],
  "metadata": {
    "accession_no_csv": "2018-00063",
    "Image": "",
    "object_work_type": "charts (graphic documents) graphic document genres",
    "title_text": "Matthaus Seutter\u0027s Flag Chart of the Seafaring Nations printed by Tobias Lotter",
    "preference": "main",
    "title_language": "",
    "creator_2": "Georg Matthaus Seutter Tobias Lotter",
    "creator_1": "not indicated",
    "creator_role": "creators publishers",
    "creation_date": "c1760",
    "creation_place_original_location": "not indicated",
    "styles_periods_indexing_terms": "not indicated",
    "inscriptions": "",
    "inscription_language": "",
    "shape": "rectangular",
    "materials_name": "paper (fiber product)",
    "techniques_name": "papermaking copper engraving (printing process) hand coloring",
    "object_colour": "multicoloured",
    "physical_appearance": "This is a multicoloured flag chart of the seafaring nations created by Matthaus Seutter and printed by Tobias Lotter. The title of the chart can be seen in two lines of text in German at the top of the chart. A single line of text also appears on top of each of the 139 flags represented in the chart. There is also one line of text centralised at the bottom of the chart, beneath all the flags.",
    "subject_terms_1": "flags identifying artefacts",
    "subject_terms_2": "Flags Identification",
    "sgcool_label_text": "This 18th century flag chart illustrates the flags of 139 seafaring nations. It was published by Tobias Lotter, based on the work of his father-in-law Georg Matthaus Seutter."
  },
  "nlpDate": "20201120223708",
  "connectorId": 0,
  "tags": {}
}