{
  "id": "2018-00030",
  "title": "Photograph of Tiong Hwa Hway Kwan Student Band",
  "source": "Bumblebee",
  "path": "./Data/json/",
  "content": "\n  accession_no_csv: 2018-00030\n\n  Image: \n\n  object_work_type: black-and-white photographs photographs\n\n  title_text: Photograph of Tiong Hwa Hway Kwan Student Band\n\n  preference: main\n\n  title_language: \n\n  creator_2: Not indicated\n\n  creator_1: Not indicated\n\n  creation_date: 1915-1920\n\n  creation_place_original_location: Surabaya (inhabited place)\n\n  inscriptions: \n\n  inscription_language: \n\n  shape: rectangular\n\n  materials_name: paper (fiber product)\n\n  techniques_name: printing (process) photographic processes\n\n  object_colour: grey monochrome\n\n  physical_appearance: The image shows a black-and-white photograph. It is rectangular and it features a group of male students in uniforms. All of them have headgear on and some of them are wearing shorts with long socks. A number of musical instruments can be seen\n such as the trombone\n trumpet\n and drums. ‘Soerabaja’ and ‘Blass Muziek’ are stated on the banner to the left . The background of the phootgraph shows drapings on the walls as well as leaf drapings.\n\n  subject_terms_1: group portraits bands (ensembles) music (performing arts) students\n\n  subject_terms_2: Black-and-white photography Portraits\n Group Portrait photography Bands (Music) Students\n\n  subject_terms_3: Portrait photography Bands Musicians\n\n  sgcool_label_text: This photograph shows a group of young men from the Tiong Hwa Hway Kwan Student Band. They are each holding an instrument and dressed in uniform. Standing partially outside the frame is a fringed banner\n with the words ‘Soerabaja’ and ‘Blass Muziek’ (wind music) visible. \\r\\n\\r\\nThe Tiong Hwa Hwe Koan was founded in 1900 by a group of Chinese businessmen and journalists and aimed to promote the customs and language among the Indies Chinese. The first Tiong Hwa Hwe Koan Chinese school was established a year later.\n",
  "createdDate": "20201120223708",
  "version": 0,
  "latest": false,
  "roles": [],
  "metadata": {
    "accession_no_csv": "2018-00030",
    "Image": "",
    "object_work_type": "black-and-white photographs photographs",
    "title_text": "Photograph of Tiong Hwa Hway Kwan Student Band",
    "preference": "main",
    "title_language": "",
    "creator_2": "Not indicated",
    "creator_1": "Not indicated",
    "creation_date": "1915-1920",
    "creation_place_original_location": "Surabaya (inhabited place)",
    "inscriptions": "",
    "inscription_language": "",
    "shape": "rectangular",
    "materials_name": "paper (fiber product)",
    "techniques_name": "printing (process) photographic processes",
    "object_colour": "grey monochrome",
    "physical_appearance": "The image shows a black-and-white photograph. It is rectangular and it features a group of male students in uniforms. All of them have headgear on and some of them are wearing shorts with long socks. A number of musical instruments can be seen, such as the trombone, trumpet, and drums. ‘Soerabaja’ and ‘Blass Muziek’ are stated on the banner to the left . The background of the phootgraph shows drapings on the walls as well as leaf drapings.",
    "subject_terms_1": "group portraits bands (ensembles) music (performing arts) students",
    "subject_terms_2": "Black-and-white photography Portraits, Group Portrait photography Bands (Music) Students",
    "subject_terms_3": "Portrait photography Bands Musicians",
    "sgcool_label_text": "This photograph shows a group of young men from the Tiong Hwa Hway Kwan Student Band. They are each holding an instrument and dressed in uniform. Standing partially outside the frame is a fringed banner, with the words ‘Soerabaja’ and ‘Blass Muziek’ (wind music) visible. \r\n\r\nThe Tiong Hwa Hwe Koan was founded in 1900 by a group of Chinese businessmen and journalists and aimed to promote the customs and language among the Indies Chinese. The first Tiong Hwa Hwe Koan Chinese school was established a year later."
  },
  "nlpDate": "20201120223708",
  "connectorId": 0,
  "tags": {}
}