{"id":"2018-00120","title":"Album leaf with three photographs of Malay, Peranakan and Javanese women Album leaf with six photographs of Malay, Peranakan and Javanese women","source":"Bumblebee","path":"./Data/json/","content":"accession_no_csv:2018-00120\nImage:\nobject_work_type:black-and-white photographs photograph albums photographs\ntitle_text:Album leaf with three photographs of Malay\n Peranakan and Javanese women Album leaf with six photographs of Malay\n Peranakan and Javanese women\npreference:main alternate\ntitle_language:\ncreator_2:G.R. Lambert \\u0026 Company\ncreator_1:G.R. Lambert \\u0026 Co.\ncreator_role:photography studios (organizations)\ncreation_date:1890s-1900s\ncreation_place_original_location:Singapore (nation)\ninscriptions:\ninscription_language:\nshape:rectangular\nmaterials_name:paper (fiber product)\ntechniques_name:printing (process) photographic processes\nobject_colour:grey monochrome\nphysical_appearance:The image shows three black-and-white photographs. They are rectangular and two of them have landscape orientations while the other on the right is of a potrait orientation. All of the images feature people. The photograph at the top and the one at the right hand side feature just a single individual lady. Both the ladies are wearing their ethnic costumes. The photograph at the bottom left hand side shows a group of people.Most of them are sitting down while a few are standing up.\nsubject_terms_1:studio portraits women (female humans) Peranakan folk costume Javanese (culture or style) group portraits\nsubject_terms_2:Black-and-white photography Portrait photography Ethnic costume Peranakan (Asian people) Women\n Javanese Women\n Malay Portraits\n Group\nsubject_terms_3:Portrait photography Women Peranakan costumes Malay costumes\nsgcool_label_text:This album leaf contains six photographs showing women from the Malay\n Peranakan and Javanese communities\n each accompanied by inscriptions which identify them. These photographs were probably taken by G.R. Lambert and Co.\\r\\n\\r\\nG.R. Lambert and Co was a leading and the most enduring of the European photography studios in Singapore. The studio was established in 1867 by Gustave Richard Lambert\n who was originally from Dresden\n Germany. Popular among the elites\n the firm was often chosen as the official photographers for important state events in Singapore. In 1861 it was appointed as the official photographer of the King of Siam and the Sultan of Johore.","createdDate":"20201018182637","version":0,"latest":false,"roles":[],"metadata":{"accession_no_csv":"2018-00120","Image":"","object_work_type":"black-and-white photographs photograph albums photographs","title_text":"Album leaf with three photographs of Malay, Peranakan and Javanese women Album leaf with six photographs of Malay, Peranakan and Javanese women","preference":"main alternate","title_language":"","creator_2":"G.R. Lambert \u0026 Company","creator_1":"G.R. Lambert \u0026 Co.","creator_role":"photography studios (organizations)","creation_date":"1890s-1900s","creation_place_original_location":"Singapore (nation)","inscriptions":"","inscription_language":"","shape":"rectangular","materials_name":"paper (fiber product)","techniques_name":"printing (process) photographic processes","object_colour":"grey monochrome","physical_appearance":"The image shows three black-and-white photographs. They are rectangular and two of them have landscape orientations while the other on the right is of a potrait orientation. All of the images feature people. The photograph at the top and the one at the right hand side feature just a single individual lady. Both the ladies are wearing their ethnic costumes. The photograph at the bottom left hand side shows a group of people.Most of them are sitting down while a few are standing up.","subject_terms_1":"studio portraits women (female humans) Peranakan folk costume Javanese (culture or style) group portraits","subject_terms_2":"Black-and-white photography Portrait photography Ethnic costume Peranakan (Asian people) Women, Javanese Women, Malay Portraits, Group","subject_terms_3":"Portrait photography Women Peranakan costumes Malay costumes","sgcool_label_text":"This album leaf contains six photographs showing women from the Malay, Peranakan and Javanese communities, each accompanied by inscriptions which identify them. These photographs were probably taken by G.R. Lambert and Co.\r\n\r\nG.R. Lambert and Co was a leading and the most enduring of the European photography studios in Singapore. The studio was established in 1867 by Gustave Richard Lambert, who was originally from Dresden, Germany. Popular among the elites, the firm was often chosen as the official photographers for important state events in Singapore. In 1861 it was appointed as the official photographer of the King of Siam and the Sultan of Johore."},"nlpDate":"20201018182637","connectorId":0,"tags":{}}