{"id":"2018-00469","title":"Clifford Pier, Singapore","source":"Bumblebee","path":"./Data/json/","content":"accession_no_csv:2018-00469\nImage:\nobject_work_type:watercolours (paintings) paintings (visual works)\ntitle_text:Clifford Pier\n Singapore\npreference:main\ntitle_language:\ncreator_2:Choon Ghee Tan\ncreator_1:Tan\n Choon Ghee\n 1930- Tan\n Choon Ghee\ncreator_role:artists (visual artists)\ncreation_date:1964\ncreation_place_original_location:Pulau Pinang (state) Singapore (nation)\nstyles_periods_indexing_terms:Not indicated\ninscriptions:\ninscription_language:\nscale_type:Not indicated\nshape:rectangular\nmaterials_name:ink rice paper (paper) watercolour (paint)\ntechniques_name:creating (artistic activity) watercolour painting (technique)\nobject_colour:multicoloured\nphysical_appearance:\\The image shows a painting. It is rectangular in shape. The painting depicts a figure sitting on a bench. The figure seems to be male and is reading\n with his bags to his side. His shoes are to his side and his red socks are visible. The outlines of boats can be seen at the background of the painting\n beyond the railing. The signature and year\n \\\\Tan. 1964\\\\ is stated at the bottom right hand side. There is a vertical line of Chinese characters\nsubject_terms_1:from the extreme top left hand side. \\ figures (representation)\nsubject_terms_2:piers (marine landings) Piers\nsubject_terms_3:Watercolour painting Visual arts Clifford Pier\nsubject_terms_4:Watercolour Painting\ncontext_1:Singapore (nation)","createdDate":"20201018182637","version":0,"latest":false,"roles":[],"metadata":{"accession_no_csv":"2018-00469","Image":"","object_work_type":"watercolours (paintings) paintings (visual works)","title_text":"Clifford Pier, Singapore","preference":"main","title_language":"","creator_2":"Choon Ghee Tan","creator_1":"Tan, Choon Ghee, 1930- Tan, Choon Ghee","creator_role":"artists (visual artists)","creation_date":"1964","creation_place_original_location":"Pulau Pinang (state) Singapore (nation)","styles_periods_indexing_terms":"Not indicated","inscriptions":"","inscription_language":"","scale_type":"Not indicated","shape":"rectangular","materials_name":"ink rice paper (paper) watercolour (paint)","techniques_name":"creating (artistic activity) watercolour painting (technique)","object_colour":"multicoloured","physical_appearance":"\"The image shows a painting. It is rectangular in shape. The painting depicts a figure sitting on a bench. The figure seems to be male and is reading, with his bags to his side. His shoes are to his side and his red socks are visible. The outlines of boats can be seen at the background of the painting, beyond the railing. The signature and year, \"\"Tan. 1964\"\" is stated at the bottom right hand side. There is a vertical line of Chinese characters","subject_terms_1":"from the extreme top left hand side. \" figures (representation)","subject_terms_2":"piers (marine landings) Piers","subject_terms_3":"Watercolour painting Visual arts Clifford Pier","subject_terms_4":"Watercolour Painting","context_1":"Singapore (nation)"},"nlpDate":"20201018182637","connectorId":0,"tags":{}}