{"id":"2018-00189","title":"Photograph of a group at a dining table","source":"Bumblebee","path":"./Data/json/","content":"accession_no_csv:2018-00189\nImage:\nobject_work_type:colour photographs photographs\ntitle_text:Photograph of a group at a dining table\npreference:main\ntitle_language:\ncreator_2:Not indicated\ncreator_1:Not indicated\ncreation_date:1965\ncreation_place_original_location:Singapore (nation)\ninscriptions:\ninscription_language:\nshape:rectangular\nmaterials_name:paper (fiber product)\ntechniques_name:printing (process) photographic processes\nobject_colour:multicoloured\nphysical_appearance:The image shows a colour photograph. It depicts a group of people. They are sitting around a dining table. The table is covered with a checkered tablecloth. There are beverages on the table. The men are dressed in suits and ties while the women are wearing sleeveless dresses. They are looking and speaking to one another. Other groups of people can be discerned in the background.\nsubject_terms_1:adults dining beverages\nsubject_terms_2:Colour photography Dinners and dining Beverages\nsubject_terms_3:Photography\nsgcool_label_text:This Polacolor photograph shows a group seated at a dining table.","createdDate":"20201119143407","version":0,"latest":false,"roles":[],"metadata":{"accession_no_csv":"2018-00189","Image":"","object_work_type":"colour photographs photographs","title_text":"Photograph of a group at a dining table","preference":"main","title_language":"","creator_2":"Not indicated","creator_1":"Not indicated","creation_date":"1965","creation_place_original_location":"Singapore (nation)","inscriptions":"","inscription_language":"","shape":"rectangular","materials_name":"paper (fiber product)","techniques_name":"printing (process) photographic processes","object_colour":"multicoloured","physical_appearance":"The image shows a colour photograph. It depicts a group of people. They are sitting around a dining table. The table is covered with a checkered tablecloth. There are beverages on the table. The men are dressed in suits and ties while the women are wearing sleeveless dresses. They are looking and speaking to one another. Other groups of people can be discerned in the background.","subject_terms_1":"adults dining beverages","subject_terms_2":"Colour photography Dinners and dining Beverages","subject_terms_3":"Photography","sgcool_label_text":"This Polacolor photograph shows a group seated at a dining table."},"nlpDate":"20201119143407","connectorId":0,"tags":{}}