{"id":"2018-00198","title":"Identity certificate of Lee Tong Wee","source":"Bumblebee","path":"./Data/json/","content":"accession_no_csv:2018-00198\nImage:\nobject_work_type:identity cards\ntitle_text:Identity certificate of Lee Tong Wee\npreference:main\ntitle_language:\ncreator_2:Not indicated\ncreator_1:Not indicated\ncreation_date:1942\ncreation_place_original_location:Singapore (nation)\ninscriptions:\ninscription_language:\nshape:rectangular\nmaterials_name:paper (fiber product)\ntechniques_name:printing (process)\nobject_colour:multicoloured\nphysical_appearance:\\The image shows a rectangular card. A passport sized photograph of a Chinese man is displayed at the bottom right hand side of the card. There are Chinese characters all over and the numeral \\\\5416\\\\ is stated at the bottom left hand side. There are red stamps at the bottom and the left hand side of the card as well.\\\nsubject_terms_1:identification photographs\nsubject_terms_2:Identification photographs Identification cards\nsgcool_label_text:This Singapore identity certificate issued in 1942 in Chinese includes a passport photograph of Lee Tong Wee.","createdDate":"20201119143407","version":0,"latest":false,"roles":[],"metadata":{"accession_no_csv":"2018-00198","Image":"","object_work_type":"identity cards","title_text":"Identity certificate of Lee Tong Wee","preference":"main","title_language":"","creator_2":"Not indicated","creator_1":"Not indicated","creation_date":"1942","creation_place_original_location":"Singapore (nation)","inscriptions":"","inscription_language":"","shape":"rectangular","materials_name":"paper (fiber product)","techniques_name":"printing (process)","object_colour":"multicoloured","physical_appearance":"\"The image shows a rectangular card. A passport sized photograph of a Chinese man is displayed at the bottom right hand side of the card. There are Chinese characters all over and the numeral \"\"5416\"\" is stated at the bottom left hand side. There are red stamps at the bottom and the left hand side of the card as well.\"","subject_terms_1":"identification photographs","subject_terms_2":"Identification photographs Identification cards","sgcool_label_text":"This Singapore identity certificate issued in 1942 in Chinese includes a passport photograph of Lee Tong Wee."},"nlpDate":"20201119143407","connectorId":0,"tags":{}}