{
  "id": "2018-00182",
  "title": "Album leaf with nine photographs",
  "source": "Bumblebee",
  "path": "./Data/json/",
  "content": "\n  accession_no_csv: 2018-00182\n\n  Image: \n\n  object_work_type: photographs black-and-white photographs photograph albums\n\n  title_text: Album leaf with nine photographs\n\n  preference: main\n\n  title_language: \n\n  creator_2: Not indicated\n\n  creator_1: Not indicated\n\n  creation_date: 1910s-1920s\n\n  creation_place_original_location: Java (island)\n\n  inscriptions: \n\n  inscription_language: \n\n  shape: rectangular\n\n  materials_name: paper (fiber product)\n\n  techniques_name: printing (process) photographic processes\n\n  object_colour: grey monochrome\n\n  physical_appearance: The image shows nine black-and-white photographs. All of them are rectangular and seven of them are in landscape orientation while the other two are in portrait orientation. The photograph at the bottom right shows a person dressed in formal attire and holding a magician\\u0027s hat and wand. Another photograph at the left hand side shows a woman reading and in the interior of a building. The settings of the other photographs are in this same room as well. An individual wearing a suit and tie\n with a hat\n is present in most of these photographs.\n\n  subject_terms_1: costumes (character dress) women (female humans) conversation pieces (portraits) studio portraits reading (activity) folk costume\n\n  subject_terms_2: Ethnic costume Portraits\n Group Reading Portrait photography Black-and-white photography Women Costumes and clothes\n\n  subject_terms_3: Portrait photography Ethnic costumes Women\n\n  sgcool_label_text: Pasted on the same album page\n these nine photographs show various recurring figures in two rooms. \\r\\n\\r\\nWith continuous improvement of camera technology\n it became possible to take photographs outside a studio in the first decades of the 20th century. Many middle-class families collected photographs in albums as a way of documenting family life\n or documentasi keluarga.\n",
  "createdDate": "20201201203307",
  "version": 0,
  "latest": false,
  "roles": [],
  "metadata": {
    "accession_no_csv": "2018-00182",
    "Image": "",
    "object_work_type": "photographs black-and-white photographs photograph albums",
    "title_text": "Album leaf with nine photographs",
    "preference": "main",
    "title_language": "",
    "creator_2": "Not indicated",
    "creator_1": "Not indicated",
    "creation_date": "1910s-1920s",
    "creation_place_original_location": "Java (island)",
    "inscriptions": "",
    "inscription_language": "",
    "shape": "rectangular",
    "materials_name": "paper (fiber product)",
    "techniques_name": "printing (process) photographic processes",
    "object_colour": "grey monochrome",
    "physical_appearance": "The image shows nine black-and-white photographs. All of them are rectangular and seven of them are in landscape orientation while the other two are in portrait orientation. The photograph at the bottom right shows a person dressed in formal attire and holding a magician\u0027s hat and wand. Another photograph at the left hand side shows a woman reading and in the interior of a building. The settings of the other photographs are in this same room as well. An individual wearing a suit and tie, with a hat, is present in most of these photographs.",
    "subject_terms_1": "costumes (character dress) women (female humans) conversation pieces (portraits) studio portraits reading (activity) folk costume",
    "subject_terms_2": "Ethnic costume Portraits, Group Reading Portrait photography Black-and-white photography Women Costumes and clothes",
    "subject_terms_3": "Portrait photography Ethnic costumes Women",
    "sgcool_label_text": "Pasted on the same album page, these nine photographs show various recurring figures in two rooms. \r\n\r\nWith continuous improvement of camera technology, it became possible to take photographs outside a studio in the first decades of the 20th century. Many middle-class families collected photographs in albums as a way of documenting family life, or documentasi keluarga."
  },
  "nlpDate": "20201201203307",
  "connectorId": 0,
  "tags": {}
}