{
  "id": "2018-00046-003",
  "title": "Three Workers: Original Transparency Slide Three Workers",
  "source": "Bumblebee",
  "path": "./Data/json/",
  "content": "\n  accession_no_csv: 2018-00046-003\n\n  Image: \n\n  object_work_type: black-and-white slides slides (photographs)\n\n  title_text: Three Workers: Original Transparency Slide Three Workers\n\n  preference: main alternate\n\n  title_language: \n\n  creator_2: Tan Lip Seng\n\n  creator_1: Tan\n Lip Seng\n 1942- Tan\n Lip Seng\n\n  creator_role: photographers\n\n  creation_date: 1965\n\n  creation_place_original_location: Singapore (nation)\n\n  styles_periods_indexing_terms: Not indicated\n\n  inscriptions: \n\n  inscription_language: \n\n  scale_type: Not indicated\n\n  shape: rectangular\n\n  materials_name: photographic film (photographic materials)\n\n  techniques_name: photographic processes\n\n  object_colour: multicoloured\n\n  edition_description: 1 of 3\n\n  physical_appearance: \\The image on the right shows a slide. It is black-and-white in colour. It is held in place by a frame. On the borders of the frame\n \\\\Three Worker\\\\ is stated at the top and \\\\Tan Lip Seng\n\n  subject_terms_1: women (female humans) A.R.P.S.\n\n  subject_terms_2: Employees 353 Pasir Panjang Road Women\n\n  subject_terms_3: Photography Singapore\n\n  subject_terms_4: 5\\\\ is stated at the bottom.\\\n\n  context_1: workers\n\n  context_2: Slides (photography)\n\n  context_3: Women\n",
  "createdDate": "20201201203307",
  "version": 0,
  "latest": false,
  "roles": [],
  "metadata": {
    "accession_no_csv": "2018-00046-003",
    "Image": "",
    "object_work_type": "black-and-white slides slides (photographs)",
    "title_text": "Three Workers: Original Transparency Slide Three Workers",
    "preference": "main alternate",
    "title_language": "",
    "creator_2": "Tan Lip Seng",
    "creator_1": "Tan, Lip Seng, 1942- Tan, Lip Seng",
    "creator_role": "photographers",
    "creation_date": "1965",
    "creation_place_original_location": "Singapore (nation)",
    "styles_periods_indexing_terms": "Not indicated",
    "inscriptions": "",
    "inscription_language": "",
    "scale_type": "Not indicated",
    "shape": "rectangular",
    "materials_name": "photographic film (photographic materials)",
    "techniques_name": "photographic processes",
    "object_colour": "multicoloured",
    "edition_description": "1 of 3",
    "physical_appearance": "\"The image on the right shows a slide. It is black-and-white in colour. It is held in place by a frame. On the borders of the frame, \"\"Three Worker\"\" is stated at the top and \"\"Tan Lip Seng",
    "subject_terms_1": "women (female humans) A.R.P.S.",
    "subject_terms_2": "Employees 353 Pasir Panjang Road Women",
    "subject_terms_3": "Photography Singapore",
    "subject_terms_4": "5\"\" is stated at the bottom.\"",
    "context_1": "workers",
    "context_2": "Slides (photography)",
    "context_3": "Women"
  },
  "nlpDate": "20201201203307",
  "connectorId": 0,
  "tags": {}
}