{
  "id": "2018-00134",
  "title": "Photograph of Gho Boen Keil",
  "source": "Bumblebee",
  "path": "./Data/json/",
  "content": "\n  accession_no_csv: 2018-00134\n\n  Image: \n\n  object_work_type: cartes-de-visite (card photographs)\n\n  title_text: Photograph of Gho Boen Keil\n\n  preference: main\n\n  title_language: \n\n  creator_2: J. B. Jasper\n\n  creator_1: Not indicated\n\n  creator_role: photography studios (organizations)\n\n  creation_date: October 1869\n\n  creation_place_original_location: Surabaya (inhabited place)\n\n  inscriptions: \n\n  inscription_language: \n\n  shape: rectangular\n\n  materials_name: paper (fiber product)\n\n  techniques_name: printing (process) photographic processes\n\n  object_colour: grey monochrome\n\n  physical_appearance: The image shows a black-and-white photograph. It is rectangular and it features a man. Only his head and upper torso are captured in the photograph. He has very short hair and he is wearing a collared outfit.\n\n  subject_terms_1: black-and-white photographs studio portraits men (male humans)\n\n  subject_terms_2: Black-and-white photography Portrait photography Men\n\n  subject_terms_3: Portrait photography\n\n  sgcool_label_text: This carte de visite shows a portrait of Gho Boen Keil. The studio mark of J. B. Jasper is stamped on the back of the carte. \\r\\n\\r\\nStudios were already established across the Strait Settlements and the Dutch East Indies by the 1840s and became increasingly prevalent in the 1850s. During the 1920s\n Chinese-owned studios dominated the studio photography trade in Southeast Asia.\n",
  "createdDate": "20201120223708",
  "version": 0,
  "latest": false,
  "roles": [],
  "metadata": {
    "accession_no_csv": "2018-00134",
    "Image": "",
    "object_work_type": "cartes-de-visite (card photographs)",
    "title_text": "Photograph of Gho Boen Keil",
    "preference": "main",
    "title_language": "",
    "creator_2": "J. B. Jasper",
    "creator_1": "Not indicated",
    "creator_role": "photography studios (organizations)",
    "creation_date": "October 1869",
    "creation_place_original_location": "Surabaya (inhabited place)",
    "inscriptions": "",
    "inscription_language": "",
    "shape": "rectangular",
    "materials_name": "paper (fiber product)",
    "techniques_name": "printing (process) photographic processes",
    "object_colour": "grey monochrome",
    "physical_appearance": "The image shows a black-and-white photograph. It is rectangular and it features a man. Only his head and upper torso are captured in the photograph. He has very short hair and he is wearing a collared outfit.",
    "subject_terms_1": "black-and-white photographs studio portraits men (male humans)",
    "subject_terms_2": "Black-and-white photography Portrait photography Men",
    "subject_terms_3": "Portrait photography",
    "sgcool_label_text": "This carte de visite shows a portrait of Gho Boen Keil. The studio mark of J. B. Jasper is stamped on the back of the carte. \r\n\r\nStudios were already established across the Strait Settlements and the Dutch East Indies by the 1840s and became increasingly prevalent in the 1850s. During the 1920s, Chinese-owned studios dominated the studio photography trade in Southeast Asia."
  },
  "nlpDate": "20201120223708",
  "connectorId": 0,
  "tags": {}
}