{"id":"2018-00047-003","title":"Under Construction: Original Transparency Slide Under Construction","source":"Bumblebee","path":"./Data/json/","content":"accession_no_csv:2018-00047-003\nImage:\nobject_work_type:slides (photographs) colour slides\ntitle_text:Under Construction: Original Transparency Slide Under Construction\npreference:main alternate\ntitle_language:\ncreator_2:Tan Lip Seng\ncreator_1:Tan\n Lip Seng\n 1942- Tan\n Lip Seng\ncreator_role:photographers\ncreation_date:1970\ncreation_place_original_location:Singapore (nation)\nstyles_periods_indexing_terms:Not indicated\ninscriptions:\ninscription_language:\nscale_type:Not indicated\nshape:rectangular\nmaterials_name:photographic film (photographic materials)\ntechniques_name:photographic processes\nobject_colour:multicoloured\nedition_description:1 of 3\nphysical_appearance:\\The image on the right shows a slide. It is in colour. It is held in place by a frame. On the borders of the frame\n \\\\Under Construction\\\\ is stated at the top for the image at the bottom. \\\\Tan Lip Seng\nsubject_terms_1:A.R.P.S. AFIAP working construction (assembling)\nsubject_terms_2:96A Tiong Bahru Road. Singapore 3\\\\ is stated at the bottom for the image at the bottom. \\ Construction workers Building Work\nsubject_terms_3:construction workers\nsubject_terms_4:Slides (photography)\ncontext_1:Photography","createdDate":"20201018182637","version":0,"latest":false,"roles":[],"metadata":{"accession_no_csv":"2018-00047-003","Image":"","object_work_type":"slides (photographs) colour slides","title_text":"Under Construction: Original Transparency Slide Under Construction","preference":"main alternate","title_language":"","creator_2":"Tan Lip Seng","creator_1":"Tan, Lip Seng, 1942- Tan, Lip Seng","creator_role":"photographers","creation_date":"1970","creation_place_original_location":"Singapore (nation)","styles_periods_indexing_terms":"Not indicated","inscriptions":"","inscription_language":"","scale_type":"Not indicated","shape":"rectangular","materials_name":"photographic film (photographic materials)","techniques_name":"photographic processes","object_colour":"multicoloured","edition_description":"1 of 3","physical_appearance":"\"The image on the right shows a slide. It is in colour. It is held in place by a frame. On the borders of the frame, \"\"Under Construction\"\" is stated at the top for the image at the bottom. \"\"Tan Lip Seng","subject_terms_1":"A.R.P.S. AFIAP working construction (assembling)","subject_terms_2":"96A Tiong Bahru Road. Singapore 3\"\" is stated at the bottom for the image at the bottom. \" Construction workers Building Work","subject_terms_3":"construction workers","subject_terms_4":"Slides (photography)","context_1":"Photography"},"nlpDate":"20201018182637","connectorId":0,"tags":{}}