{"id":"2018-00177","title":"Photograph of three men","source":"Bumblebee","path":"./Data/json/","content":"accession_no_csv:2018-00177\nImage:\nobject_work_type:black-and-white photographs photographs\ntitle_text:Photograph of three men\npreference:main\ntitle_language:\ncreator_2:Not indicated\ncreator_1:Not indicated\ncreation_date:1920s-1930s\ncreation_place_original_location:Java (island)\ninscriptions:\ninscription_language:\nshape:rectangular\nmaterials_name:paper (fiber product)\ntechniques_name:printing (process) photographic processes\nobject_colour:grey monochrome\nphysical_appearance:The image shows a black-and-white photograph. It is rectangular and it features three men. They are all sitting down around a table. Two of them are drinking from a teacup\n while the third is reading a document. Both of the men are looking at him as he reads. There is a potted plant on the ground to the left hand side of the photograph. The background shows plants around the walls.\nsubject_terms_1:group portraits men (male humans) studio portraits\nsubject_terms_2:Black-and-white photography Portrait photography Portraits\n Group Men\nsubject_terms_3:Portrait photography\nsgcool_label_text:This photograph shows three men in an informal setting \\r\\n\\r\\nStudios were already established across the Strait Settlements and the Dutch East Indies by the 1840s and became increasingly prevalent in the 1850s. During the 1920s\n Chinese-owned studios dominated the studio photography trade in Southeast Asia.","createdDate":"20201018182637","version":0,"latest":false,"roles":[],"metadata":{"accession_no_csv":"2018-00177","Image":"","object_work_type":"black-and-white photographs photographs","title_text":"Photograph of three men","preference":"main","title_language":"","creator_2":"Not indicated","creator_1":"Not indicated","creation_date":"1920s-1930s","creation_place_original_location":"Java (island)","inscriptions":"","inscription_language":"","shape":"rectangular","materials_name":"paper (fiber product)","techniques_name":"printing (process) photographic processes","object_colour":"grey monochrome","physical_appearance":"The image shows a black-and-white photograph. It is rectangular and it features three men. They are all sitting down around a table. Two of them are drinking from a teacup, while the third is reading a document. Both of the men are looking at him as he reads. There is a potted plant on the ground to the left hand side of the photograph. The background shows plants around the walls.","subject_terms_1":"group portraits men (male humans) studio portraits","subject_terms_2":"Black-and-white photography Portrait photography Portraits, Group Men","subject_terms_3":"Portrait photography","sgcool_label_text":"This photograph shows three men in an informal setting \r\n\r\nStudios were already established across the Strait Settlements and the Dutch East Indies by the 1840s and became increasingly prevalent in the 1850s. During the 1920s, Chinese-owned studios dominated the studio photography trade in Southeast Asia."},"nlpDate":"20201018182637","connectorId":0,"tags":{}}