{
  "id": "2018-00152",
  "title": "Photograph of a seated Chinese man",
  "source": "Bumblebee",
  "path": "./Data/json/",
  "content": "\n  accession_no_csv: 2018-00152\n\n  Image: \n\n  object_work_type: photographs black-and-white photographs\n\n  title_text: Photograph of a seated Chinese man\n\n  preference: main\n\n  title_language: \n\n  creator_2: Not indicated\n\n  creator_1: Not indicated\n\n  creation_date: 1860s-1870s\n\n  creation_place_original_location: Pulau Pinang (state)\n\n  inscriptions: \n\n  inscription_language: \n\n  shape: rectangular\n\n  materials_name: paper (fiber product)\n\n  techniques_name: printing (process) photographic processes\n\n  object_colour: grey monochrome\n\n  physical_appearance: The image shows a black-and-white photograph. It is rectangular and it features a man. He is sitting down. Resolution of phootgraph is not high enough to identify more details\n\n  subject_terms_1: men (male humans) black-and-white photographs portraits folk costume\n\n  subject_terms_2: Ethnic costume Portrait photography Men Black-and-white photography\n\n  subject_terms_3: Chinese costumes Portrait photography\n\n  sgcool_label_text: This photograph shows a seated man in Chinese robes and a hat.\\r\\n\\r\\nStudios were already established across the Strait Settlements and the Dutch East Indies by the 1840s and became increasingly prevalent in the 1850s. During the 1920s\n Chinese-owned studios dominated the studio photography trade in Southeast Asia.\n",
  "createdDate": "20201201203307",
  "version": 0,
  "latest": false,
  "roles": [],
  "metadata": {
    "accession_no_csv": "2018-00152",
    "Image": "",
    "object_work_type": "photographs black-and-white photographs",
    "title_text": "Photograph of a seated Chinese man",
    "preference": "main",
    "title_language": "",
    "creator_2": "Not indicated",
    "creator_1": "Not indicated",
    "creation_date": "1860s-1870s",
    "creation_place_original_location": "Pulau Pinang (state)",
    "inscriptions": "",
    "inscription_language": "",
    "shape": "rectangular",
    "materials_name": "paper (fiber product)",
    "techniques_name": "printing (process) photographic processes",
    "object_colour": "grey monochrome",
    "physical_appearance": "The image shows a black-and-white photograph. It is rectangular and it features a man. He is sitting down. Resolution of phootgraph is not high enough to identify more details",
    "subject_terms_1": "men (male humans) black-and-white photographs portraits folk costume",
    "subject_terms_2": "Ethnic costume Portrait photography Men Black-and-white photography",
    "subject_terms_3": "Chinese costumes Portrait photography",
    "sgcool_label_text": "This photograph shows a seated man in Chinese robes and a hat.\r\n\r\nStudios were already established across the Strait Settlements and the Dutch East Indies by the 1840s and became increasingly prevalent in the 1850s. During the 1920s, Chinese-owned studios dominated the studio photography trade in Southeast Asia."
  },
  "nlpDate": "20201201203307",
  "connectorId": 0,
  "tags": {}
}