{
  "id": "2018-00113",
  "title": "Studio portrait of  two nyonya",
  "source": "Bumblebee",
  "path": "./Data/json/",
  "content": "\n  accession_no_csv: 2018-00113\n\n  Image: \n\n  object_work_type: black-and-white photographs photographs\n\n  title_text: Studio portrait of  two nyonya\n\n  preference: main\n\n  title_language: \n\n  creator_2: G.R. Lambert \\u0026 Company\n\n  creator_1: G.R. Lambert \\u0026 Co.\n\n  creator_role: photography studios (organizations)\n\n  creation_date: 1870s\n\n  creation_place_original_location: Singapore (nation)\n\n  inscriptions: \n\n  inscription_language: \n\n  shape: rectangular\n\n  materials_name: paper (fiber product)\n\n  techniques_name: printing (process) photographic processes\n\n  object_colour: grey monochrome\n\n  physical_appearance: The image shows a black-and-white photograph. It is rectangular and it features two ladies. Both of them are sitting down and looking towards the direction where the photograph was captured. They are both wearing their ethnic costumes and holding one another\\u0027s hands.\n\n  subject_terms_1: studio portraits double portraits women (female humans) Peranakan folk costume\n\n  subject_terms_2: Black-and-white photography Portrait photography Women Ethnic costume Peranakan (Asian people)\n\n  subject_terms_3: Portrait photography Women Peranakan costumes\n\n  sgcool_label_text: This studio portrait shows a seated nyonya tenderly holding the hands of her companion.  This photograph was probably taken by G.R. Lambert and Co.\\r\\n\\r\\nG.R. Lambert and Co was a leading and the most enduring of the European photography studios in Singapore. The studio was established in 1867 by Gustave Richard Lambert\n who was originally from Dresden\n Germany. Popular among the elites\n the firm was often chosen as the official photographers for important state events in Singapore. In 1861 it was appointed as the official photographer of the King of Siam and the Sultan of Johore.\n",
  "createdDate": "20201120223708",
  "version": 0,
  "latest": false,
  "roles": [],
  "metadata": {
    "accession_no_csv": "2018-00113",
    "Image": "",
    "object_work_type": "black-and-white photographs photographs",
    "title_text": "Studio portrait of  two nyonya",
    "preference": "main",
    "title_language": "",
    "creator_2": "G.R. Lambert \u0026 Company",
    "creator_1": "G.R. Lambert \u0026 Co.",
    "creator_role": "photography studios (organizations)",
    "creation_date": "1870s",
    "creation_place_original_location": "Singapore (nation)",
    "inscriptions": "",
    "inscription_language": "",
    "shape": "rectangular",
    "materials_name": "paper (fiber product)",
    "techniques_name": "printing (process) photographic processes",
    "object_colour": "grey monochrome",
    "physical_appearance": "The image shows a black-and-white photograph. It is rectangular and it features two ladies. Both of them are sitting down and looking towards the direction where the photograph was captured. They are both wearing their ethnic costumes and holding one another\u0027s hands.",
    "subject_terms_1": "studio portraits double portraits women (female humans) Peranakan folk costume",
    "subject_terms_2": "Black-and-white photography Portrait photography Women Ethnic costume Peranakan (Asian people)",
    "subject_terms_3": "Portrait photography Women Peranakan costumes",
    "sgcool_label_text": "This studio portrait shows a seated nyonya tenderly holding the hands of her companion.  This photograph was probably taken by G.R. Lambert and Co.\r\n\r\nG.R. Lambert and Co was a leading and the most enduring of the European photography studios in Singapore. The studio was established in 1867 by Gustave Richard Lambert, who was originally from Dresden, Germany. Popular among the elites, the firm was often chosen as the official photographers for important state events in Singapore. In 1861 it was appointed as the official photographer of the King of Siam and the Sultan of Johore."
  },
  "nlpDate": "20201120223708",
  "connectorId": 0,
  "tags": {}
}