{"id":"2018-00124","title":"Photograph of two Chinese men and a child in courtyard","source":"Bumblebee","path":"./Data/json/","content":"accession_no_csv:2018-00124\nImage:\nobject_work_type:black-and-white photographs photographs\ntitle_text:Photograph of two Chinese men and a child in courtyard\npreference:main\ntitle_language:\ncreator_2:G.R. Lambert \\u0026 Company\ncreator_1:G.R. Lambert \\u0026 Co.\ncreator_role:photography studios (organizations)\ncreation_date:1900s\ncreation_place_original_location:Straits Settlement (former territory/colony/dependent state)\ninscriptions:\ninscription_language:\nshape:rectangular\nmaterials_name:paper (fiber product)\ntechniques_name:printing (process) photographic processes\nobject_colour:grey monochrome\nphysical_appearance:The image shows a black-and-white photograph. It is rectangular and it features a child and two men. All of them are wearing their ethnic costumes and they are standing up. Both of the adults have headwear on but not the child. The men on the right is holding onto the beaded necklace that is worn around his neck. There are flower pots on a stand behind them and the background suggests that this photograph was taken in the interior of a building.\nsubject_terms_1:studio portraits group portraits children (people by age group) men (male humans) folk costume\nsubject_terms_2:Black-and-white photography Portrait photography Portraits\n Group Children Men Ethnic costume\nsubject_terms_3:Portrait photography Children Chinese costumes\nsgcool_label_text:This photograph shows two men and a child in Chinese robes standing in a courtyard. Although the photographer is not known\n it may be taken by G.R. Lambert and Co.\\r\\n\\r\\nG.R. Lambert and Co was a leading and the most enduring of the European photography studios in Singapore. The studio was established in 1867 by Gustave Richard Lambert\n who was originally from Dresden\n Germany. Popular among the elites\n the firm was often chosen as the official photographers for important state events in Singapore. In 1861 it was appointed as the official photographer of the King of Siam and the Sultan of Johore.","createdDate":"20201119143407","version":0,"latest":false,"roles":[],"metadata":{"accession_no_csv":"2018-00124","Image":"","object_work_type":"black-and-white photographs photographs","title_text":"Photograph of two Chinese men and a child in courtyard","preference":"main","title_language":"","creator_2":"G.R. Lambert \u0026 Company","creator_1":"G.R. Lambert \u0026 Co.","creator_role":"photography studios (organizations)","creation_date":"1900s","creation_place_original_location":"Straits Settlement (former territory/colony/dependent state)","inscriptions":"","inscription_language":"","shape":"rectangular","materials_name":"paper (fiber product)","techniques_name":"printing (process) photographic processes","object_colour":"grey monochrome","physical_appearance":"The image shows a black-and-white photograph. It is rectangular and it features a child and two men. All of them are wearing their ethnic costumes and they are standing up. Both of the adults have headwear on but not the child. The men on the right is holding onto the beaded necklace that is worn around his neck. There are flower pots on a stand behind them and the background suggests that this photograph was taken in the interior of a building.","subject_terms_1":"studio portraits group portraits children (people by age group) men (male humans) folk costume","subject_terms_2":"Black-and-white photography Portrait photography Portraits, Group Children Men Ethnic costume","subject_terms_3":"Portrait photography Children Chinese costumes","sgcool_label_text":"This photograph shows two men and a child in Chinese robes standing in a courtyard. Although the photographer is not known, it may be taken by G.R. Lambert and Co.\r\n\r\nG.R. Lambert and Co was a leading and the most enduring of the European photography studios in Singapore. The studio was established in 1867 by Gustave Richard Lambert, who was originally from Dresden, Germany. Popular among the elites, the firm was often chosen as the official photographers for important state events in Singapore. In 1861 it was appointed as the official photographer of the King of Siam and the Sultan of Johore."},"nlpDate":"20201119143407","connectorId":0,"tags":{}}